Workbook

Sheet ReadMe
A1: NMIM v0.1 - National Mitigation Investment Model (simplified)
A3: What it is | B3: A simplified national model of net zero mitigation investment for 186 countries, annual 2024-2050, built to CPAT norms. For each country it projects baseline (current trends) and net zero energy use, power capacity, investment by sector, emissions, fuel bills and air pollution, and the incremental cost of the net zero path under three lenses: (a) market WACC, (b) World Bank 6%, (c) 6% with local co-benefits.
A4: How to use | B4: Choose a country on Settings!C4. Mitigation recalculates in live formulas (CPAT layout: K = 2021 ... N = 2024 base year ... AN = 2050). Dashboard summarises it. Inputs holds every parameter (MTInputs column structure; edit column G). Results_All holds every country from the Python engine; Check compares the two.
A5: Method | B5: See NMIM_Method_v0_1.md. Baseline end use follows CPAT's activity equation with CPAT income-group elasticities and prices fixed in real terms; net zero applies sector transformations (EV sales, heat electrification, industrial abatement, fossil-free power by group target year); power capacity is a stock model with lives and learning; incremental cost sums capital charges on incremental capital in service.
A6: Consistency | B6: Codes and data follow CPAT (IMF CPAT 2024 panel; mit.<indicator>.<fuel>.<sector>.<scenario>). CBAM goods process CO2 comes from the CBAM Policy Tool's Country data. Market WACC is the v1.1 investment-needs workbook's (observed, Damodaran or IHLEG default).
A7: Colours | B7: Title 00B050; section 92D050; inputs EBF1DE (blue text); codes DCE6F1; base year DDD9C4; results to review FFF2CC.
A8: Caveats | B8: Simplified: no price response, no power optimisation, car-equivalent vehicles, assumed transformation dates; several formulas exceed the 100-character norm (to be split). Parameters marked † are assumptions.
A9: Version log | B9: v0.1 | 2026-10-20 | First build: 186 countries, 11 end-use rows, power stock model, three lenses; workbook = Python on key rows (Check).

Sheet Dashboard
A1: NMIM - Dashboard (selected country)
B3: Country | C3: =Settings!C5 -> India
B5: USD bn a year unless stated
B6: Item | C6: 2025 | D6: 2030 | E6: 2035 | F6: 2040 | G6: 2045 | H6: 2050
B7: GDP (2024 USD bn) | C7: =Mitigation!O48 -> 4047.3128 | D7: =Mitigation!T48 -> 5447.8957 | E7: =Mitigation!Y48 -> 7032.4428 | F7: =Mitigation!AD48 -> 8702.5287 | G7: =Mitigation!AI48 -> 10587.957 | H7: =Mitigation!AN48 -> 12881.868
B8: Investment, baseline | C8: =Mitigation!O175 -> 55.163825 | D8: =Mitigation!T175 -> 59.584452 | E8: =Mitigation!Y175 -> 64.932813 | F8: =Mitigation!AD175 -> 67.544939 | G8: =Mitigation!AI175 -> 74.827393 | H8: =Mitigation!AN175 -> 81.977408
B9: Investment, net zero | C9: =Mitigation!O176 -> 129.90375 | D9: =Mitigation!T176 -> 204.62834 | E9: =Mitigation!Y176 -> 264.97791 | F9: =Mitigation!AD176 -> 348.08479 | G9: =Mitigation!AI176 -> 424.36646 | H9: =Mitigation!AN176 -> 379.82866
B10: Incremental investment | C10: =Mitigation!O177 -> 74.739925 | D10: =Mitigation!T177 -> 145.04389 | E10: =Mitigation!Y177 -> 200.0451 | F10: =Mitigation!AD177 -> 280.53985 | G10: =Mitigation!AI177 -> 349.53907 | H10: =Mitigation!AN177 -> 297.85125
B11: of which power generation | C11: =Mitigation!O168 -> 18.65461 | D11: =Mitigation!T168 -> 32.535282 | E11: =Mitigation!Y168 -> 46.566278 | F11: =Mitigation!AD168 -> 69.617682 | G11: =Mitigation!AI168 -> 92.131926 | H11: =Mitigation!AN168 -> 56.534699
B12: grids and storage | C12: =Mitigation!O169 -> 11.192766 | D12: =Mitigation!T169 -> 29.031039 | E12: =Mitigation!Y169 -> 53.511516 | F12: =Mitigation!AD169 -> 88.770272 | G12: =Mitigation!AI169 -> 111.79951 | H12: =Mitigation!AN169 -> 70.134948
B13: transport | C13: =Mitigation!O170 -> 3.7497381 | D13: =Mitigation!T170 -> 8.4593634 | E13: =Mitigation!Y170 -> 4.7247974 | F13: =Mitigation!AD170 -> 7.5971458 | G13: =Mitigation!AI170 -> 8.1955559 | H13: =Mitigation!AN170 -> 8.8419213
B14: buildings | C14: =Mitigation!O171 -> 9.929822 | D14: =Mitigation!T171 -> 12.129447 | E14: =Mitigation!Y171 -> 14.001797 | F14: =Mitigation!AD171 -> 15.33712 | G14: =Mitigation!AI171 -> 17.201719 | H14: =Mitigation!AN171 -> 19.262357
B15: industry | C15: =Mitigation!O172 -> 27.177721 | D15: =Mitigation!T172 -> 38.677152 | E15: =Mitigation!Y172 -> 46.355438 | F15: =Mitigation!AD172 -> 53.6587 | G15: =Mitigation!AI172 -> 63.977764 | H15: =Mitigation!AN172 -> 76.171067
B16: non-CO2 and land use | C16: =Mitigation!O173 -> 2.7150504 | D16: =Mitigation!T173 -> 16.290302 | E16: =Mitigation!Y173 -> 20.362878 | F16: =Mitigation!AD173 -> 24.435454 | G16: =Mitigation!AI173 -> 28.508029 | H16: =Mitigation!AN173 -> 32.580605
B17: Incremental cost (a) market WACC | C17: =Mitigation!O189 -> 7.7886863 | D17: =Mitigation!T189 -> 51.365079 | E17: =Mitigation!Y189 -> 84.644907 | F17: =Mitigation!AD189 -> 122.81545 | G17: =Mitigation!AI189 -> 178.32856 | H17: =Mitigation!AN189 -> 228.57678
B18: Incremental cost (b) World Bank 6% | C18: =Mitigation!O190 -> 5.8042118 | D18: =Mitigation!T190 -> 35.049096 | E18: =Mitigation!Y190 -> 47.640483 | F18: =Mitigation!AD190 -> 56.630097 | G18: =Mitigation!AI190 -> 73.817306 | H18: =Mitigation!AN190 -> 94.234214
B19: Incremental cost (c) 6% + local co-benefits | C19: =Mitigation!O191 -> 1.773167 | D19: =Mitigation!T191 -> 1.8927626 | E19: =Mitigation!Y191 -> -30.534165 | F19: =Mitigation!AD191 -> -83.281604 | G19: =Mitigation!AI191 -> -141.05509 | H19: =Mitigation!AN191 -> -179.92678
B20: GHG, baseline (MtCO2e) | C20: =Mitigation!O158 -> 4236.5833 | D20: =Mitigation!T158 -> 4680.0616 | E20: =Mitigation!Y158 -> 4990.3881 | F20: =Mitigation!AD158 -> 5220.0356 | G20: =Mitigation!AI158 -> 5410.8813 | H20: =Mitigation!AN158 -> 5596.8304
B21: GHG, net zero (MtCO2e) | C21: =Mitigation!O164 -> 4126.1949 | D21: =Mitigation!T164 -> 3882.6482 | E21: =Mitigation!Y164 -> 3456.1848 | F21: =Mitigation!AD164 -> 2659.7537 | G21: =Mitigation!AI164 -> 1509.3795 | H21: =Mitigation!AN164 -> 1010.2699

Sheet Settings
A1: NMIM - Settings
B4: Country (ISO3) | C4: IND
B5: Country name | C5: =INDEX(Data!$B:$B,MATCH($C$4,Data!$A:$A,0)) -> India
B6: Data row | C6: =MATCH($C$4,Data!$A:$A,0) -> 79
B8: Choose a country in C4 (ISO3 code from the Data sheet). Every formula on Mitigation recalculates for it.

Sheet Inputs
A1: NMIM - Inputs (MTInputs column structure)
A2: Parameters; calculations read column F by name (defined names p_<NameOfParameter>)
B7: Parameters | C7: unit | D7: MT values | E7: Dashboard values | F7: Used for calculation | G7: Defaults | H7: NameOfParameter | I7: Source | J7: Fit
B8: Long-run real GDP growth, low income | C8: % a year | F8: =G8 -> 4.5 | G8: 4.5 | H8: g_lr_lic | I8: Assumption, SSP2-like convergence. † | J8: P
B9: Long-run real GDP growth, lower middle income | C9: % a year | F9: =G9 -> 4 | G9: 4 | H9: g_lr_lmic | I9: Assumption. † | J9: P
B10: Long-run real GDP growth, upper middle income | C10: % a year | F10: =G10 -> 3 | G10: 3 | H10: g_lr_umic | I10: Assumption. † | J10: P
B11: Long-run real GDP growth, high income | C11: % a year | F11: =G11 -> 1.5 | G11: 1.5 | H11: g_lr_hic | I11: Assumption. † | J11: P
B12: Year growth reaches its long-run rate | C12: year | F12: =G12 -> 2040 | G12: 2040 | H12: g_conv_year | I12: Assumption | J12: M
B13: Pass-through of local price level to capital cost | C13: elasticity | F13: =G13 -> 0.5 | G13: 0.5 | H13: phi | I13: As v1.1 workbook. † | J13: P
B14: Fossil-free power, advanced economies | C14: year | F14: =G14 -> 2035 | G14: 2035 | H14: pow_T_ae | I14: IEA Net Zero by 2050 (2021): AE power net zero 2035 | J14: M
B15: Fossil-free power, China | C15: year | F15: =G15 -> 2040 | G15: 2040 | H15: pow_T_chn | I15: IEA NZE: global power net zero 2040 | J15: M
B16: Fossil-free power, other EMDCs | C16: year | F16: =G16 -> 2045 | G16: 2045 | H16: pow_T_emdc | I16: Assumption: five years after the global NZE date. † | J16: P
B17: 100% EV car sales, advanced economies | C17: year | F17: =G17 -> 2035 | G17: 2035 | H17: ev_T_ae | I17: IEA NZE: no new ICE car sales from 2035 | J17: M
B18: 100% EV car sales, China | C18: year | F18: =G18 -> 2035 | G18: 2035 | H18: ev_T_chn | I18: IEA NZE | J18: M
B19: 100% EV car sales, other EMDCs | C19: year | F19: =G19 -> 2040 | G19: 2040 | H19: ev_T_emdc | I19: Assumption: five years later. † | J19: P
... B85: Asset life, grids and storage | C85: years | F85: =G85 -> 40 | G85: 40 | H85: life_grid | I85: Method note | J85: M

Sheet MODULES->

Sheet Mitigation
B1: Fuel | C1: Sector | D1: Description | E1: Unit | F1: Source | G1: Input Code | H1: Output Code | I1: Note | J1: Helper | K1: 2021 | L1: 2022 | M1: 2023 | N1: 2024 | O1: 2025 | P1: 2026 | Q1: 2027 | R1: 2028 | S1: 2029 | T1: 2030 | U1: 2031 | V1: 2032 | W1: 2033 | X1: 2034 | Y1: 2035 | Z1: 2036 | AA1: 2037 | AB1: 2038 | AC1: 2039 | AD1: 2040 | AE1: 2041 | AF1: 2042 | AG1: 2043 | AH1: 2044 | AI1: 2045 | AJ1: 2046 | AK1: 2047 | AL1: 2048 | AM1: 2049 | AN1: 2050
A2: NMIM v0.1 - National Mitigation Investment Model (selected country: see Settings)
A3: 1. Country scalars (column J)
D4: Data row of the selected country | H4: mit.sc.row | J4: =Settings!$C$6 -> 79
D5: IHLEG group (1 AE, 2 China, 3 EMDC) | E5: code | F5: Data / Inputs | G5: grp | H5: mit.sc.grp | J5: =INDEX(Data!$CO:$CO,$J$4) -> 3
D6: CPAT income group (1 LIC, 2 LMIC, 3 UMIC, 4 HIC) | E6: code | F6: Data / Inputs | G6: inc | H6: mit.sc.inc | J6: =INDEX(Data!$CP:$CP,$J$4) -> 2
D7: GDP 2024 | E7: USD bn | F7: Data / Inputs | G7: gdp24 | H7: mit.sc.gdp24 | J7: =INDEX(Data!$CD:$CD,$J$4) -> 3760.814
D8: Real GDP growth 2025 (WEO) | E8: % | F8: Data / Inputs | G8: g25 | H8: mit.sc.g25 | J8: =INDEX(Data!$CB:$CB,$J$4) -> 7.618
D9: Real GDP growth 2026 (WEO) | E9: % | F9: Data / Inputs | G9: g26 | H9: mit.sc.g26 | J9: =INDEX(Data!$CC:$CC,$J$4) -> 6.478
D10: Long-run real GDP growth | E10: % | F10: Data / Inputs | G10: CHOOSE(inc,{g_lr_lic},{g_lr_lmic},{g_lr_umic},{g_lr_hic}) | H10: mit.sc.glr | J10: =CHOOSE($J$6,p_g_lr_lic,p_g_lr_lmic,p_g_lr_umic,p_g_lr_hic) -> 4
D11: Local price factor on capital (price level^phi) | E11: x | F11: Data / Inputs | G11: plevel^{phi} | H11: mit.sc.pf | J11: =INDEX(Data!$DB:$DB,$J$4)^p_phi -> 0.49109414
D12: Market WACC (v1.1: observed, Damodaran or IHLEG default) | E12: rate | F12: Data / Inputs | G12: wacc | H12: mit.sc.wacc | J12: =INDEX(Data!$DO:$DO,$J$4) -> 0.095
D13: Fossil-free power year | E13: year | F13: Data / Inputs | G13: CHOOSE(grp,{pow_T_ae},{pow_T_chn},{pow_T_emdc}) | H13: mit.sc.pow_T | J13: =CHOOSE($J$5,p_pow_T_ae,p_pow_T_chn,p_pow_T_emdc) -> 2045
D14: 100% EV sales year | E14: year | F14: Data / Inputs | G14: CHOOSE(grp,{ev_T_ae},{ev_T_chn},{ev_T_emdc}) | H14: mit.sc.ev_T | J14: =CHOOSE($J$5,p_ev_T_ae,p_ev_T_chn,p_ev_T_emdc) -> 2040
D15: Fossil heating replaced by | E15: year | F15: Data / Inputs | G15: CHOOSE(grp,{bld_T_ae},{bld_T_chn},{bld_T_emdc}) | H15: mit.sc.bld_T | J15: =CHOOSE($J$5,p_bld_T_ae,p_bld_T_chn,p_bld_T_emdc) -> 2050
D16: Industrial fossil use abated by 2050 | E16: share | F16: Data / Inputs | G16: CHOOSE(grp,{ind_a_ae},{ind_a_chn},{ind_a_emdc}) | H16: mit.sc.ind_a | J16: =CHOOSE($J$5,p_ind_a_ae,p_ind_a_chn,p_ind_a_emdc) -> 0.8
D17: EV sales share 2024 | E17: share | F17: Data / Inputs | G17: CHOOSE(grp,{ev0_ae},{ev0_chn},{ev0_emdc}) | H17: mit.sc.ev0 | J17: =CHOOSE($J$5,p_ev0_ae,p_ev0_chn,p_ev0_emdc) -> 0.03
D18: Baseline EV sales share 2035 | E18: share | F18: Data / Inputs | G18: CHOOSE(grp,{evb35_ae},{evb35_chn},{evb35_emdc}) | H18: mit.sc.evb35 | J18: =CHOOSE($J$5,p_evb35_ae,p_evb35_chn,p_evb35_emdc) -> 0.15
D19: EV stock share 2024 | E19: share | F19: Data / Inputs | G19: ev0*{sig0_ratio} | H19: mit.sc.sig0 | J19: =$J$17*p_sig0_ratio -> 0.0099
D20: Generation / end-use electricity, 2024 | E20: ratio | F20: Data / Inputs | G20: MIN(1.4,MAX(0.9,gen_tot/MAX(0.001,dem_twh24))) | H20: mit.sc.gcr | J20: =MIN(1.4,MAX(0.9,INDEX(Data!$CK:$CK,$J$4)/MAX(0.001,INDEX(Data!$BZ:$BZ,$J$4)))) -> 1.2804244
D21: Fossil share of generation 2024 | E21: share | F21: Data / Inputs | G21: MIN(1,gen_fos/MAX(0.001,gen_tot)) | H21: mit.sc.f0 | J21: =MIN(1,INDEX(Data!$CG:$CG,$J$4)/MAX(0.001,INDEX(Data!$CK:$CK,$J$4))) -> 0.73346945
D22: Baseline fall in fossil share | E22: share/yr | F22: Data / Inputs | G22: MIN({fos_trend_cap},MAX(0,fos_trend))/100 | H22: mit.sc.ftrend | J22: =MIN(p_fos_trend_cap,MAX(0,INDEX(Data!$CA:$CA,$J$4)))/100 -> 0.013011805
D23: Clean firm generation (hydro, nuclear, bio, other) | E23: TWh | F23: Data / Inputs | G23: gen_cfirm | H23: mit.sc.cfirm | J23: =INDEX(Data!$CE:$CE,$J$4) -> 254.84
D24: Coal share of fossil generation | E24: share | F24: Data / Inputs | G24: IF(gen_fos>0,gen_coa/gen_fos,0) | H24: mit.sc.sh_coa | J24: =IF(INDEX(Data!$CG:$CG,$J$4)>0,INDEX(Data!$CF:$CF,$J$4)/INDEX(Data!$CG:$CG,$J$4),0) -> 0.96552244
D25: Gas share of fossil generation | E25: share | F25: Data / Inputs | G25: IF(gen_fos>0,gen_nga/gen_fos,0) | H25: mit.sc.sh_nga | J25: =IF(INDEX(Data!$CG:$CG,$J$4)>0,INDEX(Data!$CH:$CH,$J$4)/INDEX(Data!$CG:$CG,$J$4),0) -> 0.031792191
D26: Oil share of fossil generation | E26: share | F26: Data / Inputs | G26: IF(gen_fos>0,gen_oil/gen_fos,1) | H26: mit.sc.sh_oil | J26: =IF(INDEX(Data!$CG:$CG,$J$4)>0,INDEX(Data!$CI:$CI,$J$4)/INDEX(Data!$CG:$CG,$J$4),1) -> 0.0026853726
D27: Coal heat rate, calibrated to CPAT power fuel use | E27: GJ/MWh | F27: Data / Inputs | G27: IF(gen_coa>0.1,MIN(14,MAX(7,con_coa_pow/gen_coa)),{hr_coa}) | H27: mit.sc.hr_coa | J27: =IF(INDEX(Data!$CF:$CF,$J$4)>0.1,MIN(14,MAX(7,INDEX(Data!$AJ:$AJ,$J$4)/INDEX(Data!$CF:$CF,$J$4))),p_hr_coa) -> 7.1451378
D28: Gas heat rate, calibrated to CPAT power fuel use | E28: GJ/MWh | F28: Data / Inputs | G28: IF(gen_nga>0.1,MIN(12,MAX(5.5,con_nga_pow/gen_nga)),{hr_nga} | H28: mit.sc.hr_nga | J28: =IF(INDEX(Data!$CH:$CH,$J$4)>0.1,MIN(12,MAX(5.5,INDEX(Data!$BQ:$BQ,$J$4)/INDEX(Data!$CH:$CH,$J$4))),p_hr_nga) -> 12
D29: Solar capacity factor | E29: share | F29: Data / Inputs | G29: IF(cap_sol>0.05,MIN(0.3,MAX(0.1,gen_sol/(cap_sol*8.76))),{cf | H29: mit.sc.cf_sol | J29: =IF(INDEX(Data!$AA:$AA,$J$4)>0.05,MIN(0.3,MAX(0.1,INDEX(Data!$CJ:$CJ,$J$4)/(INDEX(Data!$AA:$AA,$J$4)*8.76))),p_cf_sol) -> 0.16511651
D30: Wind capacity factor | E30: share | F30: Data / Inputs | G30: IF(cap_wnd>0.05,MIN(0.5,MAX(0.15,gen_wnd/(cap_wnd*8.76))),{c | H30: mit.sc.cf_wnd | J30: =IF(INDEX(Data!$AB:$AB,$J$4)>0.05,MIN(0.5,MAX(0.15,INDEX(Data!$CL:$CL,$J$4)/(INDEX(Data!$AB:$AB,$J$4)*8.76))),p_cf_wnd) -> 0.2177557
D31: Fossil capacity factor | E31: share | F31: Data / Inputs | G31: IF(cap_fos>0.05,MIN(0.8,MAX(0.2,gen_fos/(cap_fos*8.76))),{cf | H31: mit.sc.cf_fos | J31: =IF(INDEX(Data!$Z:$Z,$J$4)>0.05,MIN(0.8,MAX(0.2,INDEX(Data!$CG:$CG,$J$4)/(INDEX(Data!$Z:$Z,$J$4)*8.76))),p_cf_fos) -> 0.58764994
D32: Non-CO2 and other process GHG 2024 | E32: MtCO2e | F32: Data / Inputs | G32: MAX(0,ghg_exc-co2_24-cbam_proc24) | H32: mit.sc.nc24 | J32: =MAX(0,INDEX(Data!$CM:$CM,$J$4)-INDEX(Data!$AE:$AE,$J$4)-INDEX(Data!$AD:$AD,$J$4)) -> 1086.0202
D33: Net land-use source 2024 | E33: MtCO2e | F33: Data / Inputs | G33: MAX(0,ghg_inc-ghg_exc) | H33: mit.sc.lu24 | J33: =MAX(0,INDEX(Data!$CN:$CN,$J$4)-INDEX(Data!$CM:$CM,$J$4)) -> 0
D34: CBAM-goods process CO2 2024 | E34: MtCO2 | F34: Data / Inputs | G34: cbam_proc24 | H34: mit.sc.cbam24 | J34: =INDEX(Data!$AD:$AD,$J$4) -> 200.81683
D35: CBAM-goods output growth to 2030 | E35: % | F35: Data / Inputs | G35: cbam_g | H35: mit.sc.cbam_g | J35: =INDEX(Data!$AC:$AC,$J$4) -> 6.5
D36: CRF at market WACC, grids | E36: x | F36: Data / Inputs | G36: wacc/(1-(1+wacc)^-{life_grid}) | H36: mit.sc.crf_a_grid | J36: =$J$12/(1-(1+$J$12)^-p_life_grid) -> 0.097587188
D37: CRF at market WACC, generation | E37: x | F37: Data / Inputs | G37: wacc/(1-(1+wacc)^-{life_vre}) | H37: mit.sc.crf_a_vre | J37: =$J$12/(1-(1+$J$12)^-p_life_vre) -> 0.10595939
D38: CRF at market WACC, vehicles | E38: x | F38: Data / Inputs | G38: wacc/(1-(1+wacc)^-{veh_life}) | H38: mit.sc.crf_a_veh | J38: =$J$12/(1-(1+$J$12)^-p_veh_life) -> 0.14318771
D39: CRF at market WACC, buildings | E39: x | F39: Data / Inputs | G39: wacc/(1-(1+wacc)^-{life_bld}) | H39: mit.sc.crf_a_bld | J39: =$J$12/(1-(1+$J$12)^-p_life_bld) -> 0.10595939
D40: CRF at market WACC, industry | E40: x | F40: Data / Inputs | G40: wacc/(1-(1+wacc)^-{life_ind}) | H40: mit.sc.crf_a_ind | J40: =$J$12/(1-(1+$J$12)^-p_life_ind) -> 0.10595939
D41: CRF at 6%, grids | E41: x | F41: Data / Inputs | G41: {r_wb}/(1-(1+{r_wb})^-{life_grid}) | H41: mit.sc.crf_b_grid | J41: =p_r_wb/(1-(1+p_r_wb)^-p_life_grid) -> 0.066461536
D42: CRF at 6%, generation | E42: x | F42: Data / Inputs | G42: {r_wb}/(1-(1+{r_wb})^-{life_vre}) | H42: mit.sc.crf_b_vre | J42: =p_r_wb/(1-(1+p_r_wb)^-p_life_vre) -> 0.078226718
D43: CRF at 6%, vehicles | E43: x | F43: Data / Inputs | G43: {r_wb}/(1-(1+{r_wb})^-{veh_life}) | H43: mit.sc.crf_b_veh | J43: =p_r_wb/(1-(1+p_r_wb)^-p_veh_life) -> 0.11927703
D44: CRF at 6%, buildings | E44: x | F44: Data / Inputs | G44: {r_wb}/(1-(1+{r_wb})^-{life_bld}) | H44: mit.sc.crf_b_bld | J44: =p_r_wb/(1-(1+p_r_wb)^-p_life_bld) -> 0.078226718
D45: CRF at 6%, industry | E45: x | F45: Data / Inputs | G45: {r_wb}/(1-(1+{r_wb})^-{life_ind}) | H45: mit.sc.crf_b_ind | J45: =p_r_wb/(1-(1+p_r_wb)^-p_life_ind) -> 0.078226718
A46: 2. Macro
A47: 2 | D47: Real GDP growth | E47: % | F47: Model | H47: mit.gdp.gr | N47: =0 -> 0 | O47: =IF(O$1=2025,$J$8,IF(O$1=2026,$J$9,IF(O$1<p_g_conv_year,$J$9+($J$10-$J$9)*(O$1-2026)/(p_g_conv_year-2026),$J$10))) -> 7.618 | P47: =IF(P$1=2025,$J$8,IF(P$1=2026,$J$9,IF(P$1<p_g_conv_year,$J$9+($J$10-$J$9)*(P$1-2026)/(p_g_conv_year-2026),$J$10))) -> 6.478 | Q47: =IF(Q$1=2025,$J$8,IF(Q$1=2026,$J$9,IF(Q$1<p_g_conv_year,$J$9+($J$10-$J$9)*(Q$1-2026)/(p_g_conv_year-2026),$J$10))) -> 6.301 | R47: =IF(R$1=2025,$J$8,IF(R$1=2026,$J$9,IF(R$1<p_g_conv_year,$J$9+($J$10-$J$9)*(R$1-2026)/(p_g_conv_year-2026),$J$10))) -> 6.124 | S47: =IF(S$1=2025,$J$8,IF(S$1=2026,$J$9,IF(S$1<p_g_conv_year,$J$9+($J$10-$J$9)*(S$1-2026)/(p_g_conv_year-2026),$J$10))) -> 5.947 | T47: =IF(T$1=2025,$J$8,IF(T$1=2026,$J$9,IF(T$1<p_g_conv_year,$J$9+($J$10-$J$9)*(T$1-2026)/(p_g_conv_year-2026),$J$10))) -> 5.77 | U47: =IF(U$1=2025,$J$8,IF(U$1=2026,$J$9,IF(U$1<p_g_conv_year,$J$9+($J$10-$J$9)*(U$1-2026)/(p_g_conv_year-2026),$J$10))) -> 5.593 | V47: =IF(V$1=2025,$J$8,IF(V$1=2026,$J$9,IF(V$1<p_g_conv_year,$J$9+($J$10-$J$9)*(V$1-2026)/(p_g_conv_year-2026),$J$10))) -> 5.416 | ... AN47: =IF(AN$1=2025,$J$8,IF(AN$1=2026,$J$9,IF(AN$1<p_g_conv_year,$J$9+($J$10-$J$9)*(AN$1-2026)/(p_g_conv_year-2026),$J$10))) -> 4
A48: 2 | D48: Real GDP (2024 prices) | E48: USD bn | F48: Model | H48: mit.gdp.lvl | N48: =$J$7 -> 3760.814 | O48: =N48*(1+O47/100) -> 4047.3128 | P48: =O48*(1+P47/100) -> 4309.4977 | Q48: =P48*(1+Q47/100) -> 4581.0392 | R48: =Q48*(1+R47/100) -> 4861.582 | S48: =R48*(1+S47/100) -> 5150.7003 | T48: =S48*(1+T47/100) -> 5447.8957 | U48: =T48*(1+U47/100) -> 5752.5965 | V48: =U48*(1+V47/100) -> 6064.1572 | ... AN48: =AM48*(1+AN47/100) -> 12881.868
A49: 3. Activity (baseline end use, CPAT equation, prices fixed real)
A50: 3 | B50: gso | C50: rod | D50: Energy service demand (ICE-equivalent fuel) | E50: PJ | F50: CPAT data | H50: mit.act.gso.rod | K50: =INDEX(Data!$BB:$BB,$J$4) -> 1324.0301 | L50: =INDEX(Data!$BC:$BC,$J$4) -> 1570.0503 | M50: =INDEX(Data!$BD:$BD,$J$4) -> 1647.4245 | N50: =INDEX(Data!$BA:$BA,$J$4)/(1-$J$19) -> 1818.5923 | O50: =N50*(1+O47/100)^INDEX(Data!$CV:$CV,$J$4)/(1+INDEX(Data!$H:$H,$J$4)) -> 1895.542 | P50: =O50*(1+P47/100)^INDEX(Data!$CV:$CV,$J$4)/(1+INDEX(Data!$H:$H,$J$4)) -> 1961.0739 | Q50: =P50*(1+Q47/100)^INDEX(Data!$CV:$CV,$J$4)/(1+INDEX(Data!$H:$H,$J$4)) -> 2026.5099 | R50: =Q50*(1+R47/100)^INDEX(Data!$CV:$CV,$J$4)/(1+INDEX(Data!$H:$H,$J$4)) -> 2091.6879 | S50: =R50*(1+S47/100)^INDEX(Data!$CV:$CV,$J$4)/(1+INDEX(Data!$H:$H,$J$4)) -> 2156.441 | T50: =S50*(1+T47/100)^INDEX(Data!$CV:$CV,$J$4)/(1+INDEX(Data!$H:$H,$J$4)) -> 2220.598 | U50: =T50*(1+U47/100)^INDEX(Data!$CV:$CV,$J$4)/(1+INDEX(Data!$H:$H,$J$4)) -> 2283.9846 | V50: =U50*(1+V47/100)^INDEX(Data!$CV:$CV,$J$4)/(1+INDEX(Data!$H:$H,$J$4)) -> 2346.4233 | ... AN50: =AM50*(1+AN47/100)^INDEX(Data!$CV:$CV,$J$4)/(1+INDEX(Data!$H:$H,$J$4)) -> 3324.0498
A51: 3 | B51: die | C51: rod | D51: Energy service demand (ICE-equivalent fuel) | E51: PJ | F51: CPAT data | H51: mit.act.die.rod | K51: =INDEX(Data!$AP:$AP,$J$4) -> 2375.9535 | L51: =INDEX(Data!$AQ:$AQ,$J$4) -> 2581.9483 | M51: =INDEX(Data!$AR:$AR,$J$4) -> 2830.0398 | N51: =INDEX(Data!$AO:$AO,$J$4)/(1-$J$19) -> 3072.8118 | O51: =N51*(1+O47/100)^INDEX(Data!$CS:$CS,$J$4)/(1+INDEX(Data!$E:$E,$J$4)) -> 3179.4027 | P51: =O51*(1+P47/100)^INDEX(Data!$CS:$CS,$J$4)/(1+INDEX(Data!$E:$E,$J$4)) -> 3268.7379 | Q51: =P51*(1+Q47/100)^INDEX(Data!$CS:$CS,$J$4)/(1+INDEX(Data!$E:$E,$J$4)) -> 3357.2303 | R51: =Q51*(1+R47/100)^INDEX(Data!$CS:$CS,$J$4)/(1+INDEX(Data!$E:$E,$J$4)) -> 3444.6724 | S51: =R51*(1+S47/100)^INDEX(Data!$CS:$CS,$J$4)/(1+INDEX(Data!$E:$E,$J$4)) -> 3530.8539 | T51: =S51*(1+T47/100)^INDEX(Data!$CS:$CS,$J$4)/(1+INDEX(Data!$E:$E,$J$4)) -> 3615.5625 | U51: =T51*(1+U47/100)^INDEX(Data!$CS:$CS,$J$4)/(1+INDEX(Data!$E:$E,$J$4)) -> 3698.5848 | V51: =U51*(1+V47/100)^INDEX(Data!$CS:$CS,$J$4)/(1+INDEX(Data!$E:$E,$J$4)) -> 3779.7069 | ... AN51: =AM51*(1+AN47/100)^INDEX(Data!$CS:$CS,$J$4)/(1+INDEX(Data!$E:$E,$J$4)) -> 4965.9054
A52: 3 | B52: coa | C52: res | D52: Energy service demand | E52: PJ | F52: CPAT data | H52: mit.act.coa.res | K52: =INDEX(Data!$AL:$AL,$J$4) -> 342.16795 | L52: =INDEX(Data!$AM:$AM,$J$4) -> 371.83386 | M52: =INDEX(Data!$AN:$AN,$J$4) -> 407.56224 | N52: =INDEX(Data!$AK:$AK,$J$4) -> 430.48427 | O52: =N52*(1+O47/100)^INDEX(Data!$CR:$CR,$J$4)/(1+INDEX(Data!$D:$D,$J$4)) -> 437.88161 | P52: =O52*(1+P47/100)^INDEX(Data!$CR:$CR,$J$4)/(1+INDEX(Data!$D:$D,$J$4)) -> 443.98532 | Q52: =P52*(1+Q47/100)^INDEX(Data!$CR:$CR,$J$4)/(1+INDEX(Data!$D:$D,$J$4)) -> 449.94948 | R52: =Q52*(1+R47/100)^INDEX(Data!$CR:$CR,$J$4)/(1+INDEX(Data!$D:$D,$J$4)) -> 455.76584 | S52: =R52*(1+S47/100)^INDEX(Data!$CR:$CR,$J$4)/(1+INDEX(Data!$D:$D,$J$4)) -> 461.42626 | T52: =S52*(1+T47/100)^INDEX(Data!$CR:$CR,$J$4)/(1+INDEX(Data!$D:$D,$J$4)) -> 466.92271 | U52: =T52*(1+U47/100)^INDEX(Data!$CR:$CR,$J$4)/(1+INDEX(Data!$D:$D,$J$4)) -> 472.24729 | V52: =U52*(1+V47/100)^INDEX(Data!$CR:$CR,$J$4)/(1+INDEX(Data!$D:$D,$J$4)) -> 477.39226 | ... AN52: =AM52*(1+AN47/100)^INDEX(Data!$CR:$CR,$J$4)/(1+INDEX(Data!$D:$D,$J$4)) -> 547.07741
A53: 3 | B53: nga | C53: res | D53: Energy service demand | E53: PJ | F53: CPAT data | H53: mit.act.nga.res | K53: =INDEX(Data!$BS:$BS,$J$4) -> 181.39739 | L53: =INDEX(Data!$BT:$BT,$J$4) -> 197.12451 | M53: =INDEX(Data!$BU:$BU,$J$4) -> 216.06561 | N53: =INDEX(Data!$BR:$BR,$J$4) -> 241.48572 | O53: =N53*(1+O47/100)^INDEX(Data!$CZ:$CZ,$J$4)/(1+INDEX(Data!$L:$L,$J$4)) -> 244.41934 | P53: =O53*(1+P47/100)^INDEX(Data!$CZ:$CZ,$J$4)/(1+INDEX(Data!$L:$L,$J$4)) -> 246.59948 | Q53: =P53*(1+Q47/100)^INDEX(Data!$CZ:$CZ,$J$4)/(1+INDEX(Data!$L:$L,$J$4)) -> 248.67492 | R53: =Q53*(1+R47/100)^INDEX(Data!$CZ:$CZ,$J$4)/(1+INDEX(Data!$L:$L,$J$4)) -> 250.64249 | S53: =R53*(1+S47/100)^INDEX(Data!$CZ:$CZ,$J$4)/(1+INDEX(Data!$L:$L,$J$4)) -> 252.49915 | T53: =S53*(1+T47/100)^INDEX(Data!$CZ:$CZ,$J$4)/(1+INDEX(Data!$L:$L,$J$4)) -> 254.242 | U53: =T53*(1+U47/100)^INDEX(Data!$CZ:$CZ,$J$4)/(1+INDEX(Data!$L:$L,$J$4)) -> 255.86829 | V53: =U53*(1+V47/100)^INDEX(Data!$CZ:$CZ,$J$4)/(1+INDEX(Data!$L:$L,$J$4)) -> 257.37541 | ... AN53: =AM53*(1+AN47/100)^INDEX(Data!$CZ:$CZ,$J$4)/(1+INDEX(Data!$L:$L,$J$4)) -> 269.73968
A54: 3 | B54: lpg | C54: res | D54: Energy service demand | E54: PJ | F54: CPAT data | H54: mit.act.lpg.res | K54: =INDEX(Data!$BJ:$BJ,$J$4) -> 1267.8005 | L54: =INDEX(Data!$BK:$BK,$J$4) -> 1377.7186 | M54: =INDEX(Data!$BL:$BL,$J$4) -> 1510.0994 | N54: =INDEX(Data!$BI:$BI,$J$4) -> 1626.2883 | O54: =N54*(1+O47/100)^INDEX(Data!$CX:$CX,$J$4)/(1+INDEX(Data!$J:$J,$J$4)) -> 1678.7033 | P54: =O54*(1+P47/100)^INDEX(Data!$CX:$CX,$J$4)/(1+INDEX(Data!$J:$J,$J$4)) -> 1723.6053 | Q54: =P54*(1+Q47/100)^INDEX(Data!$CX:$CX,$J$4)/(1+INDEX(Data!$J:$J,$J$4)) -> 1768.2369 | R54: =Q54*(1+R47/100)^INDEX(Data!$CX:$CX,$J$4)/(1+INDEX(Data!$J:$J,$J$4)) -> 1812.5132 | S54: =R54*(1+S47/100)^INDEX(Data!$CX:$CX,$J$4)/(1+INDEX(Data!$J:$J,$J$4)) -> 1856.3483 | T54: =S54*(1+T47/100)^INDEX(Data!$CX:$CX,$J$4)/(1+INDEX(Data!$J:$J,$J$4)) -> 1899.6546 | U54: =T54*(1+U47/100)^INDEX(Data!$CX:$CX,$J$4)/(1+INDEX(Data!$J:$J,$J$4)) -> 1942.344 | V54: =U54*(1+V47/100)^INDEX(Data!$CX:$CX,$J$4)/(1+INDEX(Data!$J:$J,$J$4)) -> 1984.3275 | ... AN54: =AM54*(1+AN47/100)^INDEX(Data!$CX:$CX,$J$4)/(1+INDEX(Data!$J:$J,$J$4)) -> 2643.7991
A55: 3 | B55: ker | C55: res | D55: Energy service demand | E55: PJ | F55: CPAT data | H55: mit.act.ker.res | K55: =INDEX(Data!$BF:$BF,$J$4) -> 191.47533 | L55: =INDEX(Data!$BG:$BG,$J$4) -> 208.07621 | M55: =INDEX(Data!$BH:$BH,$J$4) -> 228.06962 | N55: =INDEX(Data!$BE:$BE,$J$4) -> 259.21443 | O55: =N55*(1+O47/100)^INDEX(Data!$CW:$CW,$J$4)/(1+INDEX(Data!$I:$I,$J$4)) -> 267.56886 | P55: =O55*(1+P47/100)^INDEX(Data!$CW:$CW,$J$4)/(1+INDEX(Data!$I:$I,$J$4)) -> 274.7258 | Q55: =P55*(1+Q47/100)^INDEX(Data!$CW:$CW,$J$4)/(1+INDEX(Data!$I:$I,$J$4)) -> 281.83963 | R55: =Q55*(1+R47/100)^INDEX(Data!$CW:$CW,$J$4)/(1+INDEX(Data!$I:$I,$J$4)) -> 288.89685 | S55: =R55*(1+S47/100)^INDEX(Data!$CW:$CW,$J$4)/(1+INDEX(Data!$I:$I,$J$4)) -> 295.88372 | T55: =S55*(1+T47/100)^INDEX(Data!$CW:$CW,$J$4)/(1+INDEX(Data!$I:$I,$J$4)) -> 302.78633 | U55: =T55*(1+U47/100)^INDEX(Data!$CW:$CW,$J$4)/(1+INDEX(Data!$I:$I,$J$4)) -> 309.5906 | V55: =U55*(1+V47/100)^INDEX(Data!$CW:$CW,$J$4)/(1+INDEX(Data!$I:$I,$J$4)) -> 316.28236 | ... AN55: =AM55*(1+AN47/100)^INDEX(Data!$CW:$CW,$J$4)/(1+INDEX(Data!$I:$I,$J$4)) -> 421.39567
A56: 3 | B56: ecy | C56: res | D56: Energy service demand | E56: PJ | F56: CPAT data | H56: mit.act.ecy.res | K56: =INDEX(Data!$AX:$AX,$J$4) -> 1223.208 | L56: =INDEX(Data!$AY:$AY,$J$4) -> 1464.3057 | M56: =INDEX(Data!$AZ:$AZ,$J$4) -> 1545.2887 | N56: =INDEX(Data!$AW:$AW,$J$4) -> 1506.9058 | O56: =N56*(1+O47/100)^INDEX(Data!$CU:$CU,$J$4)/(1+INDEX(Data!$G:$G,$J$4)) -> 1590.1129 | P56: =O56*(1+P47/100)^INDEX(Data!$CU:$CU,$J$4)/(1+INDEX(Data!$G:$G,$J$4)) -> 1663.6801 | Q56: =P56*(1+Q47/100)^INDEX(Data!$CU:$CU,$J$4)/(1+INDEX(Data!$G:$G,$J$4)) -> 1738.3356 | R56: =Q56*(1+R47/100)^INDEX(Data!$CU:$CU,$J$4)/(1+INDEX(Data!$G:$G,$J$4)) -> 1813.9214 | S56: =R56*(1+S47/100)^INDEX(Data!$CU:$CU,$J$4)/(1+INDEX(Data!$G:$G,$J$4)) -> 1890.2678 | T56: =S56*(1+T47/100)^INDEX(Data!$CU:$CU,$J$4)/(1+INDEX(Data!$G:$G,$J$4)) -> 1967.1943 | U56: =T56*(1+U47/100)^INDEX(Data!$CU:$CU,$J$4)/(1+INDEX(Data!$G:$G,$J$4)) -> 2044.5103 | V56: =U56*(1+V47/100)^INDEX(Data!$CU:$CU,$J$4)/(1+INDEX(Data!$G:$G,$J$4)) -> 2122.0151 | ... AN56: =AM56*(1+AN47/100)^INDEX(Data!$CU:$CU,$J$4)/(1+INDEX(Data!$G:$G,$J$4)) -> 3544.2642
A57: 3 | B57: coa | C57: ind | D57: Energy service demand | E57: PJ | F57: CPAT data | H57: mit.act.coa.ind | K57: =INDEX(Data!$AG:$AG,$J$4) -> 4258.2718 | L57: =INDEX(Data!$AH:$AH,$J$4) -> 4627.4632 | M57: =INDEX(Data!$AI:$AI,$J$4) -> 5072.1021 | N57: =INDEX(Data!$AF:$AF,$J$4) -> 5318.8273 | O57: =N57*(1+O47/100)^INDEX(Data!$CQ:$CQ,$J$4)/(1+INDEX(Data!$C:$C,$J$4)) -> 5490.2521 | P57: =O57*(1+P47/100)^INDEX(Data!$CQ:$CQ,$J$4)/(1+INDEX(Data!$C:$C,$J$4)) -> 5637.1056 | Q57: =P57*(1+Q47/100)^INDEX(Data!$CQ:$CQ,$J$4)/(1+INDEX(Data!$C:$C,$J$4)) -> 5783.0744 | R57: =Q57*(1+R47/100)^INDEX(Data!$CQ:$CQ,$J$4)/(1+INDEX(Data!$C:$C,$J$4)) -> 5927.8817 | S57: =R57*(1+S47/100)^INDEX(Data!$CQ:$CQ,$J$4)/(1+INDEX(Data!$C:$C,$J$4)) -> 6071.2455 | T57: =S57*(1+T47/100)^INDEX(Data!$CQ:$CQ,$J$4)/(1+INDEX(Data!$C:$C,$J$4)) -> 6212.8803 | U57: =T57*(1+U47/100)^INDEX(Data!$CQ:$CQ,$J$4)/(1+INDEX(Data!$C:$C,$J$4)) -> 6352.4973 | V57: =U57*(1+V47/100)^INDEX(Data!$CQ:$CQ,$J$4)/(1+INDEX(Data!$C:$C,$J$4)) -> 6489.8057 | ... AN57: =AM57*(1+AN47/100)^INDEX(Data!$CQ:$CQ,$J$4)/(1+INDEX(Data!$C:$C,$J$4)) -> 8646.6282
A58: 3 | B58: nga | C58: ind | D58: Energy service demand | E58: PJ | F58: CPAT data | H58: mit.act.nga.ind | K58: =INDEX(Data!$BN:$BN,$J$4) -> 1025.3036 | L58: =INDEX(Data!$BO:$BO,$J$4) -> 1114.1972 | M58: =INDEX(Data!$BP:$BP,$J$4) -> 1221.2571 | N58: =INDEX(Data!$BM:$BM,$J$4) -> 1369.8988 | O58: =N58*(1+O47/100)^INDEX(Data!$CY:$CY,$J$4)/(1+INDEX(Data!$K:$K,$J$4)) -> 1459.6611 | P58: =O58*(1+P47/100)^INDEX(Data!$CY:$CY,$J$4)/(1+INDEX(Data!$K:$K,$J$4)) -> 1538.8296 | Q58: =P58*(1+Q47/100)^INDEX(Data!$CY:$CY,$J$4)/(1+INDEX(Data!$K:$K,$J$4)) -> 1619.5953 | R58: =Q58*(1+R47/100)^INDEX(Data!$CY:$CY,$J$4)/(1+INDEX(Data!$K:$K,$J$4)) -> 1701.7617 | S58: =R58*(1+S47/100)^INDEX(Data!$CY:$CY,$J$4)/(1+INDEX(Data!$K:$K,$J$4)) -> 1785.1144 | T58: =S58*(1+T47/100)^INDEX(Data!$CY:$CY,$J$4)/(1+INDEX(Data!$K:$K,$J$4)) -> 1869.4213 | U58: =T58*(1+U47/100)^INDEX(Data!$CY:$CY,$J$4)/(1+INDEX(Data!$K:$K,$J$4)) -> 1954.4336 | V58: =U58*(1+V47/100)^INDEX(Data!$CY:$CY,$J$4)/(1+INDEX(Data!$K:$K,$J$4)) -> 2039.8869 | ... AN58: =AM58*(1+AN47/100)^INDEX(Data!$CY:$CY,$J$4)/(1+INDEX(Data!$K:$K,$J$4)) -> 3622.6783
A59: 3 | B59: oil | C59: ind | D59: Energy service demand | E59: PJ | F59: CPAT data | H59: mit.act.oil.ind | K59: =INDEX(Data!$BW:$BW,$J$4) -> 2683.3239 | L59: =INDEX(Data!$BX:$BX,$J$4) -> 2844.0456 | M59: =INDEX(Data!$BY:$BY,$J$4) -> 3118.7831 | N59: =INDEX(Data!$BV:$BV,$J$4) -> 3560.8332 | O59: =N59*(1+O47/100)^INDEX(Data!$DA:$DA,$J$4)/(1+INDEX(Data!$M:$M,$J$4)) -> 3757.4526 | P59: =O59*(1+P47/100)^INDEX(Data!$DA:$DA,$J$4)/(1+INDEX(Data!$M:$M,$J$4)) -> 3931.2924 | Q59: =P59*(1+Q47/100)^INDEX(Data!$DA:$DA,$J$4)/(1+INDEX(Data!$M:$M,$J$4)) -> 4107.7043 | R59: =Q59*(1+R47/100)^INDEX(Data!$DA:$DA,$J$4)/(1+INDEX(Data!$M:$M,$J$4)) -> 4286.3141 | S59: =R59*(1+S47/100)^INDEX(Data!$DA:$DA,$J$4)/(1+INDEX(Data!$M:$M,$J$4)) -> 4466.7214 | T59: =S59*(1+T47/100)^INDEX(Data!$DA:$DA,$J$4)/(1+INDEX(Data!$M:$M,$J$4)) -> 4648.4997 | U59: =T59*(1+U47/100)^INDEX(Data!$DA:$DA,$J$4)/(1+INDEX(Data!$M:$M,$J$4)) -> 4831.1981 | V59: =U59*(1+V47/100)^INDEX(Data!$DA:$DA,$J$4)/(1+INDEX(Data!$M:$M,$J$4)) -> 5014.3427 | ... AN59: =AM59*(1+AN47/100)^INDEX(Data!$DA:$DA,$J$4)/(1+INDEX(Data!$M:$M,$J$4)) -> 8375.1314
A60: 3 | B60: ecy | C60: ind | D60: Energy service demand | E60: PJ | F60: CPAT data | H60: mit.act.ecy.ind | K60: =INDEX(Data!$AT:$AT,$J$4) -> 3501.3898 | L60: =INDEX(Data!$AU:$AU,$J$4) -> 4213.6072 | M60: =INDEX(Data!$AV:$AV,$J$4) -> 4451.8464 | N60: =INDEX(Data!$AS:$AS,$J$4) -> 4345.6537 | O60: =N60*(1+O47/100)^INDEX(Data!$CT:$CT,$J$4)/(1+INDEX(Data!$F:$F,$J$4)) -> 4585.6086 | P60: =O60*(1+P47/100)^INDEX(Data!$CT:$CT,$J$4)/(1+INDEX(Data!$F:$F,$J$4)) -> 4797.7634 | Q60: =P60*(1+Q47/100)^INDEX(Data!$CT:$CT,$J$4)/(1+INDEX(Data!$F:$F,$J$4)) -> 5013.0571 | R60: =Q60*(1+R47/100)^INDEX(Data!$CT:$CT,$J$4)/(1+INDEX(Data!$F:$F,$J$4)) -> 5231.0332 | S60: =R60*(1+S47/100)^INDEX(Data!$CT:$CT,$J$4)/(1+INDEX(Data!$F:$F,$J$4)) -> 5451.2029 | T60: =S60*(1+T47/100)^INDEX(Data!$CT:$CT,$J$4)/(1+INDEX(Data!$F:$F,$J$4)) -> 5673.0458 | U60: =T60*(1+U47/100)^INDEX(Data!$CT:$CT,$J$4)/(1+INDEX(Data!$F:$F,$J$4)) -> 5896.0116 | V60: =U60*(1+V47/100)^INDEX(Data!$CT:$CT,$J$4)/(1+INDEX(Data!$F:$F,$J$4)) -> 6119.5219 | ... AN60: =AM60*(1+AN47/100)^INDEX(Data!$CT:$CT,$J$4)/(1+INDEX(Data!$F:$F,$J$4)) -> 10221.04
A61: 4. Road transport
A62: 4 | C62: rod | D62: Vehicle stock (car-equivalent) | E62: million | F62: Model | H62: mit.veh.stock | N62: =(N50+N51)/p_veh_gj -> 127.04946 | O62: =(O50+O51)/p_veh_gj -> 131.81675 | P62: =(P50+P51)/p_veh_gj -> 135.83927 | Q62: =(Q50+Q51)/p_veh_gj -> 139.83741 | R62: =(R50+R51)/p_veh_gj -> 143.80157 | S62: =(S50+S51)/p_veh_gj -> 147.72194 | T62: =(T50+T51)/p_veh_gj -> 151.58859 | U62: =(U50+U51)/p_veh_gj -> 155.39141 | ... AN62: =(AN50+AN51)/p_veh_gj -> 215.32351
A63: 4 | C63: rod | D63: Vehicle sales | E63: million | F63: Model | H63: mit.veh.sales | N63: =N62/p_veh_life -> 10.587455 | O63: =O62/p_veh_life+MAX(0,O62-N62) -> 15.752017 | P63: =P62/p_veh_life+MAX(0,P62-O62) -> 15.34246 | Q63: =Q62/p_veh_life+MAX(0,Q62-P62) -> 15.651258 | R63: =R62/p_veh_life+MAX(0,R62-Q62) -> 15.947623 | S63: =S62/p_veh_life+MAX(0,S62-R62) -> 16.230541 | T63: =T62/p_veh_life+MAX(0,T62-S62) -> 16.499024 | U63: =U62/p_veh_life+MAX(0,U62-T62) -> 16.752111 | V63: =V62/p_veh_life+MAX(0,V62-U62) -> 16.988876 | ... AN63: =AN62/p_veh_life+MAX(0,AN62-AM62) -> 21.181805
A64: 4 | C64: rod | D64: EV premium incl. nothing for charging | E64: USD/vehicle | F64: Model | H64: mit.ev.prem | N64: =p_ev_prem24 -> 10000 | O64: =MAX(0,p_ev_prem24*(1-(O$1-2024)/(p_ev_parity-2024))) -> 8750 | P64: =MAX(0,p_ev_prem24*(1-(P$1-2024)/(p_ev_parity-2024))) -> 7500 | Q64: =MAX(0,p_ev_prem24*(1-(Q$1-2024)/(p_ev_parity-2024))) -> 6250 | R64: =MAX(0,p_ev_prem24*(1-(R$1-2024)/(p_ev_parity-2024))) -> 5000 | S64: =MAX(0,p_ev_prem24*(1-(S$1-2024)/(p_ev_parity-2024))) -> 3750 | T64: =MAX(0,p_ev_prem24*(1-(T$1-2024)/(p_ev_parity-2024))) -> 2500 | U64: =MAX(0,p_ev_prem24*(1-(U$1-2024)/(p_ev_parity-2024))) -> 1250 | V64: =MAX(0,p_ev_prem24*(1-(V$1-2024)/(p_ev_parity-2024))) -> 0 | ... AN64: =MAX(0,p_ev_prem24*(1-(AN$1-2024)/(p_ev_parity-2024))) -> 0
A65: 4 | B65: ecy | C65: rod | D65: EV share of sales | E65: share | F65: Model | H65: mit.ev.shs.1 | N65: =$J$17 -> 0.03 | O65: =IF(O$1>=2035,$J$18,$J$17+($J$18-$J$17)*(O$1-2024)/11) -> 0.040909091 | P65: =IF(P$1>=2035,$J$18,$J$17+($J$18-$J$17)*(P$1-2024)/11) -> 0.051818182 | Q65: =IF(Q$1>=2035,$J$18,$J$17+($J$18-$J$17)*(Q$1-2024)/11) -> 0.062727273 | R65: =IF(R$1>=2035,$J$18,$J$17+($J$18-$J$17)*(R$1-2024)/11) -> 0.073636364 | S65: =IF(S$1>=2035,$J$18,$J$17+($J$18-$J$17)*(S$1-2024)/11) -> 0.084545455 | T65: =IF(T$1>=2035,$J$18,$J$17+($J$18-$J$17)*(T$1-2024)/11) -> 0.095454545 | U65: =IF(U$1>=2035,$J$18,$J$17+($J$18-$J$17)*(U$1-2024)/11) -> 0.10636364 | V65: =IF(V$1>=2035,$J$18,$J$17+($J$18-$J$17)*(V$1-2024)/11) -> 0.11727273 | ... AN65: =IF(AN$1>=2035,$J$18,$J$17+($J$18-$J$17)*(AN$1-2024)/11) -> 0.15
A66: 4 | B66: ecy | C66: rod | D66: EV share of stock | E66: share | F66: Model | H66: mit.ev.stk.1 | N66: =$J$19 -> 0.0099 | O66: =N66*(1-1/p_veh_life)+O65/p_veh_life -> 0.012484091 | P66: =O66*(1-1/p_veh_life)+P65/p_veh_life -> 0.015761932 | Q66: =P66*(1-1/p_veh_life)+Q65/p_veh_life -> 0.01967571 | R66: =Q66*(1-1/p_veh_life)+R65/p_veh_life -> 0.024172431 | S66: =R66*(1-1/p_veh_life)+S65/p_veh_life -> 0.029203517 | T66: =S66*(1-1/p_veh_life)+T65/p_veh_life -> 0.034724436 | U66: =T66*(1-1/p_veh_life)+U65/p_veh_life -> 0.040694369 | V66: =U66*(1-1/p_veh_life)+V65/p_veh_life -> 0.047075899 | ... AN66: =AM66*(1-1/p_veh_life)+AN65/p_veh_life -> 0.12786556
A67: 4 | B67: gso | C67: rod | D67: Fossil fuel use | E67: PJ | F67: Model | H67: mit.con.gso.rod.1 | N67: =N50*(1-N66) -> 1800.5882 | O67: =O50*(1-O66) -> 1871.8779 | P67: =P50*(1-P66) -> 1930.1636 | Q67: =Q50*(1-Q66) -> 1986.6369 | R67: =R50*(1-R66) -> 2041.1267 | S67: =S50*(1-S66) -> 2093.4653 | T67: =T50*(1-T66) -> 2143.489 | U67: =U50*(1-U66) -> 2191.0393 | ... AN67: =AN50*(1-AN66) -> 2899.0183
A68: 4 | B68: die | C68: rod | D68: Fossil fuel use | E68: PJ | F68: Model | H68: mit.con.die.rod.1 | N68: =N51*(1-N66) -> 3042.391 | O68: =O51*(1-O66) -> 3139.7108 | P68: =P51*(1-P66) -> 3217.2163 | Q68: =Q51*(1-Q66) -> 3291.1744 | R68: =R51*(1-R66) -> 3361.4063 | S68: =S51*(1-S66) -> 3427.7406 | T68: =T51*(1-T66) -> 3490.0142 | U68: =U51*(1-U66) -> 3548.0732 | ... AN68: =AN51*(1-AN66) -> 4330.9372
A69: 4 | B69: ecy | C69: rod | D69: EV electricity | E69: PJ | F69: Model | H69: mit.con.ecy.ev.1 | N69: =(N50+N51)*N66*p_ev_ratio -> 12.106225 | O69: =(O50+O51)*O66*p_ev_ratio -> 15.839018 | P69: =(P50+P51)*P66*p_ev_ratio -> 20.607984 | Q69: =(Q50+Q51)*Q66*p_ev_ratio -> 26.482228 | R69: =(R50+R51)*R66*p_ev_ratio -> 33.456822 | S69: =(S50+S51)*S66*p_ev_ratio -> 41.522253 | T69: =(T50+T51)*T66*p_ev_ratio -> 50.664346 | U69: =(U50+U51)*U66*p_ev_ratio -> 60.864222 | ... AN69: =(AN50+AN51)*AN66*p_ev_ratio -> 264.99994
A70: 4 | C70: rod | D70: Investment: EV premium and chargers | E70: USD bn | F70: Model | H70: mit.inv.trn.1 | N70: =0 -> 0 | O70: =O63*O65*(O64+p_charger)*$J$11/1000 -> 3.0854988 | P70: =P63*P65*(P64+p_charger)*$J$11/1000 -> 3.3186454 | Q70: =Q63*Q65*(Q64+p_charger)*$J$11/1000 -> 3.4954928 | R70: =R63*R65*(R64+p_charger)*$J$11/1000 -> 3.4602246 | S70: =S63*S65*(S64+p_charger)*$J$11/1000 -> 3.2009701 | T70: =T63*T65*(T64+p_charger)*$J$11/1000 -> 2.7069963 | U70: =U63*U65*(U64+p_charger)*$J$11/1000 -> 1.968838 | V70: =V63*V65*(V64+p_charger)*$J$11/1000 -> 0.97842248 | ... AN70: =AN63*AN65*(AN64+p_charger)*$J$11/1000 -> 1.560339
A71: 4 | C71: rod | D71: EV maintenance saving (negative cost) | E71: USD bn | F71: Model | H71: mit.om.trn.1 | N71: =-N66*N62*p_veh_km*p_ev_maint/1000 -> -0.22640213 | O71: =-O66*O62*p_veh_km*p_ev_maint/1000 -> -0.2962102 | P71: =-P66*P62*p_veh_km*p_ev_maint/1000 -> -0.38539607 | Q71: =-Q66*Q62*p_veh_km*p_ev_maint/1000 -> -0.49525205 | R71: =-R66*R62*p_veh_km*p_ev_maint/1000 -> -0.62568603 | S71: =-S66*S62*p_veh_km*p_ev_maint/1000 -> -0.77652005 | T71: =-T66*T62*p_veh_km*p_ev_maint/1000 -> -0.94748906 | U71: =-U66*U62*p_veh_km*p_ev_maint/1000 -> -1.13824 | ... AN71: =-AN66*AN62*p_veh_km*p_ev_maint/1000 -> -4.955843
A72: 4 | B72: ecy | C72: rod | D72: EV share of sales | E72: share | F72: Model | H72: mit.ev.shs.2 | N72: =$J$17 -> 0.03 | O72: =MIN(1,$J$17+(1-$J$17)*(O$1-2024)/($J$14-2024)) -> 0.090625 | P72: =MIN(1,$J$17+(1-$J$17)*(P$1-2024)/($J$14-2024)) -> 0.15125 | Q72: =MIN(1,$J$17+(1-$J$17)*(Q$1-2024)/($J$14-2024)) -> 0.211875 | R72: =MIN(1,$J$17+(1-$J$17)*(R$1-2024)/($J$14-2024)) -> 0.2725 | S72: =MIN(1,$J$17+(1-$J$17)*(S$1-2024)/($J$14-2024)) -> 0.333125 | T72: =MIN(1,$J$17+(1-$J$17)*(T$1-2024)/($J$14-2024)) -> 0.39375 | U72: =MIN(1,$J$17+(1-$J$17)*(U$1-2024)/($J$14-2024)) -> 0.454375 | V72: =MIN(1,$J$17+(1-$J$17)*(V$1-2024)/($J$14-2024)) -> 0.515 | ... AN72: =MIN(1,$J$17+(1-$J$17)*(AN$1-2024)/($J$14-2024)) -> 1
A73: 4 | B73: ecy | C73: rod | D73: EV share of stock | E73: share | F73: Model | H73: mit.ev.stk.2 | N73: =$J$19 -> 0.0099 | O73: =N73*(1-1/p_veh_life)+O72/p_veh_life -> 0.016627083 | P73: =O73*(1-1/p_veh_life)+P72/p_veh_life -> 0.02784566 | Q73: =P73*(1-1/p_veh_life)+Q72/p_veh_life -> 0.043181438 | R73: =Q73*(1-1/p_veh_life)+R72/p_veh_life -> 0.062291318 | S73: =R73*(1-1/p_veh_life)+S72/p_veh_life -> 0.084860792 | T73: =S73*(1-1/p_veh_life)+T72/p_veh_life -> 0.11060156 | U73: =T73*(1-1/p_veh_life)+U72/p_veh_life -> 0.13924935 | V73: =U73*(1-1/p_veh_life)+V72/p_veh_life -> 0.1705619 | ... AN73: =AM73*(1-1/p_veh_life)+AN72/p_veh_life -> 0.78797999
A74: 4 | B74: gso | C74: rod | D74: Fossil fuel use | E74: PJ | F74: Model | H74: mit.con.gso.rod.2 | N74: =N50*(1-N73) -> 1800.5882 | O74: =O50*(1-O73) -> 1864.0247 | P74: =P50*(1-P73) -> 1906.4665 | Q74: =Q50*(1-Q73) -> 1939.0023 | R74: =R50*(1-R73) -> 1961.3939 | S74: =S50*(1-S73) -> 1973.4437 | T74: =T50*(1-T73) -> 1974.9964 | U74: =U50*(1-U73) -> 1965.9412 | ... AN74: =AN50*(1-AN73) -> 704.76509
A75: 4 | B75: die | C75: rod | D75: Fossil fuel use | E75: PJ | F75: Model | H75: mit.con.die.rod.2 | N75: =N51*(1-N73) -> 3042.391 | O75: =O51*(1-O73) -> 3126.5385 | P75: =P51*(1-P73) -> 3177.7177 | Q75: =Q51*(1-Q73) -> 3212.2603 | R75: =R51*(1-R73) -> 3230.0992 | S75: =S51*(1-S73) -> 3231.2229 | T75: =T51*(1-T73) -> 3215.6757 | U75: =U51*(1-U73) -> 3183.5593 | ... AN75: =AN51*(1-AN73) -> 1052.8713
A76: 4 | B76: ecy | C76: rod | D76: EV electricity | E76: PJ | F76: Model | H76: mit.con.ecy.ev.2 | N76: =(N50+N51)*N73*p_ev_ratio -> 12.106225 | O76: =(O50+O51)*O73*p_ev_ratio -> 21.095382 | P76: =(P50+P51)*P73*p_ev_ratio -> 36.40689 | Q76: =(Q50+Q51)*Q73*p_ev_ratio -> 58.119411 | R76: =(R50+R51)*R73*p_ev_ratio -> 86.216795 | S76: =(S50+S51)*S73*p_ev_ratio -> 120.65709 | T76: =(T50+T51)*T73*p_ev_ratio -> 161.37211 | U76: =(U50+U51)*U73*p_ev_ratio -> 208.26722 | ... AN76: =(AN50+AN51)*AN73*p_ev_ratio -> 1633.0797
A77: 4 | C77: rod | D77: Investment: EV premium and chargers | E77: USD bn | F77: Model | H77: mit.inv.trn.2 | N77: =0 -> 0 | O77: =O63*O72*(O64+p_charger)*$J$11/1000 -> 6.8352369 | P77: =P63*P72*(P64+p_charger)*$J$11/1000 -> 9.6866602 | Q77: =Q63*Q72*(Q64+p_charger)*$J$11/1000 -> 11.806787 | R77: =R63*R72*(R64+p_charger)*$J$11/1000 -> 12.804967 | S77: =S63*S72*(S64+p_charger)*$J$11/1000 -> 12.612425 | T77: =T63*T72*(T64+p_charger)*$J$11/1000 -> 11.16636 | U77: =U63*U72*(U64+p_charger)*$J$11/1000 -> 8.4106824 | V77: =V63*V72*(V64+p_charger)*$J$11/1000 -> 4.2967158 | ... AN77: =AN63*AN72*(AN64+p_charger)*$J$11/1000 -> 10.40226
A78: 4 | C78: rod | D78: EV maintenance saving (negative cost) | E78: USD bn | F78: Model | H78: mit.om.trn.2 | N78: =-N73*N62*p_veh_km*p_ev_maint/1000 -> -0.22640213 | O78: =-O73*O62*p_veh_km*p_ev_maint/1000 -> -0.39451104 | P78: =-P73*P62*p_veh_km*p_ev_maint/1000 -> -0.68085612 | Q78: =-Q73*Q62*p_veh_km*p_ev_maint/1000 -> -1.0869085 | R78: =-R73*R62*p_veh_km*p_ev_maint/1000 -> -1.612366 | S78: =-S73*S62*p_veh_km*p_ev_maint/1000 -> -2.2564442 | T78: =-T73*T62*p_veh_km*p_ev_maint/1000 -> -3.0178681 | U78: =-U73*U62*p_veh_km*p_ev_maint/1000 -> -3.8948675 | ... AN78: =-AN73*AN62*p_veh_km*p_ev_maint/1000 -> -30.540711
A79: 5. Buildings
A80: 5 | C80: res | D80: Share of fossil heat replaced (net zero) | E80: share | F80: Model | H80: mit.bld.h.2 | N80: =0 -> 0 | O80: =MIN(1,(O$1-2024)/($J$15-2024)) -> 0.038461538 | P80: =MIN(1,(P$1-2024)/($J$15-2024)) -> 0.076923077 | Q80: =MIN(1,(Q$1-2024)/($J$15-2024)) -> 0.11538462 | R80: =MIN(1,(R$1-2024)/($J$15-2024)) -> 0.15384615 | S80: =MIN(1,(S$1-2024)/($J$15-2024)) -> 0.19230769 | T80: =MIN(1,(T$1-2024)/($J$15-2024)) -> 0.23076923 | U80: =MIN(1,(U$1-2024)/($J$15-2024)) -> 0.26923077 | V80: =MIN(1,(V$1-2024)/($J$15-2024)) -> 0.30769231 | ... AN80: =MIN(1,(AN$1-2024)/($J$15-2024)) -> 1
A81: 5 | B81: coa | C81: res | D81: Fossil fuel use | E81: PJ | F81: Model | H81: mit.con.coa.res.1 | N81: =N52 -> 430.48427 | O81: =O52 -> 437.88161 | P81: =P52 -> 443.98532 | Q81: =Q52 -> 449.94948 | R81: =R52 -> 455.76584 | S81: =S52 -> 461.42626 | T81: =T52 -> 466.92271 | U81: =U52 -> 472.24729 | ... AN81: =AN52 -> 547.07741
A82: 5 | B82: nga | C82: res | D82: Fossil fuel use | E82: PJ | F82: Model | H82: mit.con.nga.res.1 | N82: =N53 -> 241.48572 | O82: =O53 -> 244.41934 | P82: =P53 -> 246.59948 | Q82: =Q53 -> 248.67492 | R82: =R53 -> 250.64249 | S82: =S53 -> 252.49915 | T82: =T53 -> 254.242 | U82: =U53 -> 255.86829 | ... AN82: =AN53 -> 269.73968
A83: 5 | B83: lpg | C83: res | D83: Fossil fuel use | E83: PJ | F83: Model | H83: mit.con.lpg.res.1 | N83: =N54 -> 1626.2883 | O83: =O54 -> 1678.7033 | P83: =P54 -> 1723.6053 | Q83: =Q54 -> 1768.2369 | R83: =R54 -> 1812.5132 | S83: =S54 -> 1856.3483 | T83: =T54 -> 1899.6546 | U83: =U54 -> 1942.344 | ... AN83: =AN54 -> 2643.7991
A84: 5 | B84: ker | C84: res | D84: Fossil fuel use | E84: PJ | F84: Model | H84: mit.con.ker.res.1 | N84: =N55 -> 259.21443 | O84: =O55 -> 267.56886 | P84: =P55 -> 274.7258 | Q84: =Q55 -> 281.83963 | R84: =R55 -> 288.89685 | S84: =S55 -> 295.88372 | T84: =T55 -> 302.78633 | U84: =U55 -> 309.5906 | ... AN84: =AN55 -> 421.39567
A85: 5 | B85: coa | C85: res | D85: Fossil fuel use | E85: PJ | F85: Model | H85: mit.con.coa.res.2 | N85: =N52 -> 430.48427 | O85: =O52*(1-O80) -> 421.04001 | P85: =P52*(1-P80) -> 409.8326 | Q85: =Q52*(1-Q80) -> 398.03223 | R85: =R52*(1-R80) -> 385.64802 | S85: =S52*(1-S80) -> 372.69044 | T85: =T52*(1-T80) -> 359.17132 | U85: =U52*(1-U80) -> 345.10379 | V85: =V52*(1-V80) -> 330.50233 | ... AN85: =AN52*(1-AN80) -> 0
A86: 5 | B86: nga | C86: res | D86: Fossil fuel use | E86: PJ | F86: Model | H86: mit.con.nga.res.2 | N86: =N53 -> 241.48572 | O86: =O53*(1-O80) -> 235.01859 | P86: =P53*(1-P80) -> 227.63029 | Q86: =Q53*(1-Q80) -> 219.98166 | R86: =R53*(1-R80) -> 212.08211 | S86: =S53*(1-S80) -> 203.94162 | T86: =T53*(1-T80) -> 195.57077 | U86: =U53*(1-U80) -> 186.98067 | V86: =V53*(1-V80) -> 178.18298 | ... AN86: =AN53*(1-AN80) -> 0
A87: 5 | B87: lpg | C87: res | D87: Fossil fuel use | E87: PJ | F87: Model | H87: mit.con.lpg.res.2 | N87: =N54 -> 1626.2883 | O87: =O54*(1-O80) -> 1614.1378 | P87: =P54*(1-P80) -> 1591.0203 | Q87: =Q54*(1-Q80) -> 1564.2095 | R87: =R54*(1-R80) -> 1533.665 | S87: =S54*(1-S80) -> 1499.3582 | T87: =T54*(1-T80) -> 1461.2728 | U87: =U54*(1-U80) -> 1419.4052 | V87: =V54*(1-V80) -> 1373.7652 | ... AN87: =AN54*(1-AN80) -> 0
A88: 5 | B88: ker | C88: res | D88: Fossil fuel use | E88: PJ | F88: Model | H88: mit.con.ker.res.2 | N88: =N55 -> 259.21443 | O88: =O55*(1-O80) -> 257.27775 | P88: =P55*(1-P80) -> 253.59305 | Q88: =Q55*(1-Q80) -> 249.31967 | R88: =R55*(1-R80) -> 244.45118 | S88: =S55*(1-S80) -> 238.98301 | T88: =T55*(1-T80) -> 232.91256 | U88: =U55*(1-U80) -> 226.23929 | V88: =V55*(1-V80) -> 218.96471 | ... AN88: =AN55*(1-AN80) -> 0
A89: 5 | C89: res | D89: Fossil heat fuel displaced | E89: PJ | F89: Model | H89: mit.bld.disp.2 | N89: =0 -> 0 | O89: =(O52+O53+O54+O55)*O80 -> 101.09897 | P89: =(P52+P53+P54+P55)*P80 -> 206.83969 | Q89: =(Q52+Q53+Q54+Q55)*Q80 -> 317.1578 | R89: =(R52+R53+R54+R55)*R80 -> 431.97206 | S89: =(S52+S53+S54+S55)*S80 -> 551.18411 | T89: =(T52+T53+T54+T55)*T80 -> 674.67823 | U89: =(U52+U53+U54+U55)*U80 -> 802.3212 | V89: =(V52+V53+V54+V55)*V80 -> 933.96232 | ... AN89: =(AN52+AN53+AN54+AN55)*AN80 -> 3882.0118
A90: 5 | B90: ecy | C90: res | D90: Heat pump electricity | E90: PJ | F90: Model | H90: mit.con.ecy.hp.2 | N90: =0 -> 0 | O90: =O89*p_hp_ratio -> 33.362659 | P90: =P89*p_hp_ratio -> 68.257096 | Q90: =Q89*p_hp_ratio -> 104.66207 | R90: =R89*p_hp_ratio -> 142.55078 | S90: =S89*p_hp_ratio -> 181.89076 | T90: =T89*p_hp_ratio -> 222.64381 | U90: =U89*p_hp_ratio -> 264.766 | V90: =V89*p_hp_ratio -> 308.20757 | ... AN90: =AN89*p_hp_ratio -> 1281.0639
A91: 5 | C91: res | D91: Investment: heat pumps and efficiency | E91: USD bn | F91: Model | H91: mit.inv.bld.2 | N91: =0 -> 0 | O91: =p_k_bld*MAX(0,O89-N89)*$J$11/1000 -> 9.929822 | P91: =p_k_bld*MAX(0,P89-O89)*$J$11/1000 -> 10.38573 | Q91: =p_k_bld*MAX(0,Q89-P89)*$J$11/1000 -> 10.835315 | R91: =p_k_bld*MAX(0,R89-Q89)*$J$11/1000 -> 11.276923 | S91: =p_k_bld*MAX(0,S89-R89)*$J$11/1000 -> 11.708868 | T91: =p_k_bld*MAX(0,T89-S89)*$J$11/1000 -> 12.129447 | U91: =p_k_bld*MAX(0,U89-T89)*$J$11/1000 -> 12.536943 | V91: =p_k_bld*MAX(0,V89-U89)*$J$11/1000 -> 12.929636 | ... AN91: =p_k_bld*MAX(0,AN89-AM89)*$J$11/1000 -> 19.262357
A92: 6. Industry
A93: 6 | C93: ind | D93: Share of industrial fossil use abated (net zero) | E93: share | F93: Model | H93: mit.ind.a.2 | N93: =0 -> 0 | O93: =$J$16*(O$1-2024)/26 -> 0.030769231 | P93: =$J$16*(P$1-2024)/26 -> 0.061538462 | Q93: =$J$16*(Q$1-2024)/26 -> 0.092307692 | R93: =$J$16*(R$1-2024)/26 -> 0.12307692 | S93: =$J$16*(S$1-2024)/26 -> 0.15384615 | T93: =$J$16*(T$1-2024)/26 -> 0.18461538 | U93: =$J$16*(U$1-2024)/26 -> 0.21538462 | V93: =$J$16*(V$1-2024)/26 -> 0.24615385 | ... AN93: =$J$16*(AN$1-2024)/26 -> 0.8
A94: 6 | B94: coa | C94: ind | D94: Fossil fuel use | E94: PJ | F94: Model | H94: mit.con.coa.ind.1 | N94: =N57 -> 5318.8273 | O94: =O57 -> 5490.2521 | P94: =P57 -> 5637.1056 | Q94: =Q57 -> 5783.0744 | R94: =R57 -> 5927.8817 | S94: =S57 -> 6071.2455 | T94: =T57 -> 6212.8803 | U94: =U57 -> 6352.4973 | ... AN94: =AN57 -> 8646.6282
A95: 6 | B95: nga | C95: ind | D95: Fossil fuel use | E95: PJ | F95: Model | H95: mit.con.nga.ind.1 | N95: =N58 -> 1369.8988 | O95: =O58 -> 1459.6611 | P95: =P58 -> 1538.8296 | Q95: =Q58 -> 1619.5953 | R95: =R58 -> 1701.7617 | S95: =S58 -> 1785.1144 | T95: =T58 -> 1869.4213 | U95: =U58 -> 1954.4336 | ... AN95: =AN58 -> 3622.6783
A96: 6 | B96: oil | C96: ind | D96: Fossil fuel use | E96: PJ | F96: Model | H96: mit.con.oil.ind.1 | N96: =N59 -> 3560.8332 | O96: =O59 -> 3757.4526 | P96: =P59 -> 3931.2924 | Q96: =Q59 -> 4107.7043 | R96: =R59 -> 4286.3141 | S96: =S59 -> 4466.7214 | T96: =T59 -> 4648.4997 | U96: =U59 -> 4831.1981 | ... AN96: =AN59 -> 8375.1314
A97: 6 | B97: coa | C97: ind | D97: Fossil fuel use | E97: PJ | F97: Model | H97: mit.con.coa.ind.2 | N97: =N57 -> 5318.8273 | O97: =O57*(1-O93) -> 5321.3213 | P97: =P57*(1-P93) -> 5290.2068 | Q97: =Q57*(1-Q93) -> 5249.2522 | R97: =R57*(1-R93) -> 5198.2962 | S97: =S57*(1-S93) -> 5137.2078 | T97: =T57*(1-T93) -> 5065.887 | U97: =U57*(1-U93) -> 4984.2671 | V97: =V57*(1-V93) -> 4892.3151 | ... AN97: =AN57*(1-AN93) -> 1729.3256
A98: 6 | B98: nga | C98: ind | D98: Fossil fuel use | E98: PJ | F98: Model | H98: mit.con.nga.ind.2 | N98: =N58 -> 1369.8988 | O98: =O58*(1-O93) -> 1414.7484 | P98: =P58*(1-P93) -> 1444.1324 | Q98: =Q58*(1-Q93) -> 1470.0942 | R98: =R58*(1-R93) -> 1492.3141 | S98: =S58*(1-S93) -> 1510.4814 | T98: =T58*(1-T93) -> 1524.2973 | U98: =U58*(1-U93) -> 1533.4787 | V98: =V58*(1-V93) -> 1537.7609 | ... AN98: =AN58*(1-AN93) -> 724.53566
A99: 6 | B99: oil | C99: ind | D99: Fossil fuel use | E99: PJ | F99: Model | H99: mit.con.oil.ind.2 | N99: =N59 -> 3560.8332 | O99: =O59*(1-O93) -> 3641.8386 | P99: =P59*(1-P93) -> 3689.3668 | Q99: =Q59*(1-Q93) -> 3728.5316 | R99: =R59*(1-R93) -> 3758.7678 | S99: =S59*(1-S93) -> 3779.5335 | T99: =T59*(1-T93) -> 3790.3151 | U99: =U59*(1-U93) -> 3790.6324 | V99: =V59*(1-V93) -> 3780.043 | ... AN99: =AN59*(1-AN93) -> 1675.0263
A100: 6 | C100: ind | D100: Industrial fossil use abated | E100: PJ | F100: Model | H100: mit.ind.abt.2 | N100: =0 -> 0 | O100: =(O57+O58+O59)*O93 -> 329.45741 | P100: =(P57+P58+P59)*P93 -> 683.5217 | Q100: =(Q57+Q58+Q59)*Q93 -> 1062.4961 | R100: =(R57+R58+R59)*R93 -> 1466.5794 | S100: =(S57+S58+S59)*S93 -> 1895.8587 | T100: =(T57+T58+T59)*T93 -> 2350.3018 | U100: =(U57+U58+U59)*U93 -> 2829.7509 | V100: =(V57+V58+V59)*V93 -> 3333.9164 | ... AN100: =(AN57+AN58+AN59)*AN93 -> 16515.55
...

Sheet Results_All
A1: Results for all countries (Python engine, values), USD bn and MtCO2e
A2: Incremental cost is the annual cost in that year of all incremental capital in service (capital charge) plus the change in O&M, less fuel savings (less air pollution avoided in lens c). Positive = net cost. PV = present value 2025-2050 at the lens rate.
A4: ISO3 | B4: Country | C4: Group | D4: Market WACC | E4: GDP 2030 | F4: Investment 2030, baseline | G4: Investment 2030, net zero | H4: Incremental investment 2030 | I4: Incr. cost 2030 (a) market | J4: Incr. cost 2030 (b) 6% | K4: Incr. cost 2030 (c) 6% + co-ben. | L4: GHG 2030 baseline | M4: GHG 2030 net zero | N4: GHG 2050 net zero | O4: Cumulative investment 2025-50, net zero | P4: Cumulative incremental 2025-50 | Q4: PV incr. cost (a) | R4: PV incr. cost (b) | S4: PV incr. cost (c) | T4: Cumulative abatement 2025-50 | U4: Energy CO2 2024, model | V4: Energy CO2 2024, CPAT
A5: USA | B5: United States | C5: AE | D5: 0.057 | E5: 33367.503 | F5: 206.5445 | G5: 780.2792 | H5: 573.7347 | I5: 96.7671 | J5: 102.7929 | K5: 70.8357 | L5: 6790.3026 | M5: 5077.4784 | N5: 982.2613 | O5: 17326.688 | P5: 12880.514 | Q5: 1746.394 | R5: 1821.3497 | S5: 1086.8989 | T5: 86412.44 | U5: 4997.031 | V5: 5445.106
A6: CHN | B6: China | C6: China | D6: 0.0389 | E6: 24439.123 | F6: 589.0175 | G6: 1410.615 | H6: 821.5975 | I6: 152.4876 | J6: 206.8429 | K6: -104.7182 | L6: 16649.529 | M6: 13657.93 | N6: 1962.2461 | O6: 43707.719 | P6: 26520.332 | Q6: 5220.0989 | R6: 5417.0399 | S6: -2977.9423 | T6: 184240.95 | U6: 10506.051 | V6: 13206.767
A7: IND | B7: India | C7: EMDC | D7: 0.095 | E7: 5447.8957 | F7: 59.5845 | G7: 204.6283 | H7: 145.0439 | I7: 51.3651 | J7: 35.0491 | K7: 1.8928 | L7: 4680.0616 | M7: 3882.6482 | N7: 1010.2699 | O7: 7564.2486 | P7: 5824.1169 | Q7: 680.4675 | R7: 557.3367 | S7: -555.4278 | T7: 57586.006 | U7: 2415.9374 | V7: 2845.008
A8: DEU | B8: Germany | C8: AE | D8: 0.0232 | E8: 4908.6727 | F8: 33.3628 | G8: 116.4181 | H8: 83.0553 | I8: -5.7167 | J8: 5.1837 | K8: 0.8202 | L8: 688.0652 | M8: 545.8375 | N8: 86.3555 | O8: 2653.6563 | P8: 1827.4695 | Q8: -261.7686 | R8: 95.8305 | S8: -18.5959 | T8: 7355.6659 | U8: 594.9479 | V8: 658.368
A9: JPN | B9: Japan | C9: AE | D9: 0.055 | E9: 4419.0183 | F9: 29.6594 | G9: 145.7058 | H9: 116.0463 | I9: -2.4332 | J9: -0.2849 | K9: -12.7031 | L9: 1228.4346 | M9: 925.189 | N9: 120.7745 | O9: 3306.7086 | P9: 2474.1672 | Q9: 28.367 | R9: 74.3744 | S9: -197.8789 | T9: 14756.347 | U9: 1121.5329 | V9: 1205.177
A10: GBR | B10: United Kingdom | C10: AE | D10: 0.0359 | E10: 3915.292 | F10: 17.4733 | G10: 69.8587 | H10: 52.3854 | I10: -4.7805 | J10: -0.0883 | K10: -2.4179 | L10: 424.7509 | M10: 337.5557 | N10: 63.5164 | O10: 1599.0139 | P10: 1184.014 | Q10: -177.4841 | R10: -17.7496 | S10: -72.1397 | T10: 4524.0143 | U10: 343.3351 | V10: 370.094
A11: FRA | B11: France | C11: AE | D11: 0.033 | E11: 3344.7754 | F11: 11.6931 | G11: 46.8084 | H11: 35.1154 | I11: -0.7779 | J11: 2.7653 | K11: 0.9473 | L11: 391.7834 | M11: 310.0166 | N11: 72.1852 | O11: 1223.2008 | P11: 914.7157 | Q11: -80.9002 | R11: 29.2257 | S11: -15.0187 | T11: 4218.4369 | U11: 279.3269 | V11: 322.969
A12: CAN | B12: Canada | C12: AE | D12: 0.055 | E12: 2488.1419 | F12: 13.6025 | G12: 83.6594 | H12: 70.0569 | I12: 14.1255 | J12: 15.4926 | K12: 14.4429 | L12: 690.5561 | M12: 531.3236 | N12: 107.9266 | O12: 2069.9892 | P12: 1763.9372 | Q12: 302.1613 | R12: 313.9716 | S12: 288.5377 | T12: 8558.7018 | U12: 539.5996 | V12: 554.217
A13: BRA | B13: Brazil | C13: EMDC | D13: 0.0978 | E13: 2476.5515 | F13: 12.525 | G13: 74.2068 | H13: 61.6818 | I13: 36.68 | J13: 32.3176 | K13: 29.41 | L13: 1785.1893 | M13: 1043.0369 | N13: 442.9016 | O13: 2272.2008 | P13: 1900.8246 | Q13: 271.9456 | R13: 286.2362 | S13: 189.706 | T13: 24611.556 | U13: 411.7179 | V13: 505.632
A14: ITA | B14: Italy | C14: AE | D14: 0.0438 | E14: 2475.7888 | F14: 12.2613 | G14: 54.4289 | H14: 42.1676 | I14: -4.3887 | J14: -1.9035 | K14: -5.161 | L14: 419.3619 | M14: 328.2704 | N14: 63.4136 | O14: 1253.9111 | P14: 921.2433 | Q14: -131.039 | R14: -47.513 | S14: -125.8911 | T14: 4561.9678 | U14: 315.8296 | V14: 363.035
A15: RUS | B15: Russian Federation | C15: EMDC | D15: 0.105 | E15: 2361.9368 | F15: 11.5155 | G15: 129.5189 | H15: 118.0034 | I15: 60.0054 | J15: 38.6279 | K15: 17.4818 | L15: 2477.3478 | M15: 2079.0048 | N15: 447.818 | O15: 4928.2513 | P15: 4525.7167 | Q15: 815.6703 | R15: 894.9837 | S15: 135.465 | T15: 30837.071 | U15: 1740.9558 | V15: 1982.113
A16: KOR | B16: Korea, Rep. | C16: AE | D16: 0.055 | E16: 2072.0525 | F16: 17.0764 | G16: 87.2027 | H16: 70.1263 | I16: 2.8344 | J16: 4.0867 | K16: -2.2581 | L16: 818.0975 | M16: 598.6343 | N16: 84.6938 | O16: 2024.1677 | P16: 1617.4028 | Q16: 96.2606 | R16: 119.2885 | S16: -25.8957 | T16: 11124.191 | U16: 634.328 | V16: 732.861
... A190: NRU | B190: Naoero | C190: EMDC | D190: 0.105 | E190: 0.192 | F190: 0.0024 | G190: 0.0142 | H190: 0.0117 | I190: 0.0061 | J190: 0.0039 | K190: 0.0039 | L190: 0.1354 | M190: 0.1303 | N190: 0.0289 | O190: 0.513 | P190: 0.4462 | Q190: 0.0661 | R190: 0.0512 | S190: 0.0512 | T190: 1.2898 | U190: 0.1323 | V190: 0.101

Sheet Check
A1: Check: workbook (live formulas) vs Python engine, selected country
A2: Differences should be 0 to rounding. Max abs difference in B3.
A3: Max abs diff | B3: =MAX(MAX(L6:P21),-MIN(L6:P21)) -> 4.8166003e-06
A5: Code | B5: WB 2024 | C5: WB 2025 | D5: WB 2030 | E5: WB 2040 | F5: WB 2050 | G5: Py 2024 | H5: Py 2025 | I5: Py 2030 | J5: Py 2040 | K5: Py 2050 | L5: Diff 2024 | M5: Diff 2025 | N5: Diff 2030 | O5: Diff 2040 | P5: Diff 2050
A6: mit.gdp.lvl | B6: =Mitigation!N48 -> 3760.814 | C6: =Mitigation!O48 -> 4047.3128 | D6: =Mitigation!T48 -> 5447.8957 | E6: =Mitigation!AD48 -> 8702.5287 | F6: =Mitigation!AN48 -> 12881.868 | G6: =INDEX(PyKey!D$3:D$2978,MATCH(Settings!$C$4&"|mit.gdp.lvl",PyKey!$A$3:$A$2978,0)) -> 3760.814 | H6: =INDEX(PyKey!E$3:E$2978,MATCH(Settings!$C$4&"|mit.gdp.lvl",PyKey!$A$3:$A$2978,0)) -> 4047.3128 | I6: =INDEX(PyKey!F$3:F$2978,MATCH(Settings!$C$4&"|mit.gdp.lvl",PyKey!$A$3:$A$2978,0)) -> 5447.8957 | J6: =INDEX(PyKey!G$3:G$2978,MATCH(Settings!$C$4&"|mit.gdp.lvl",PyKey!$A$3:$A$2978,0)) -> 8702.5287 | K6: =INDEX(PyKey!H$3:H$2978,MATCH(Settings!$C$4&"|mit.gdp.lvl",PyKey!$A$3:$A$2978,0)) -> 12881.868 | L6: =B6-G6 -> 0 | M6: =C6-H6 -> -4.8000038e-07 | N6: =D6-I6 -> 3.8922099e-07 | O6: =E6-J6 -> -4.6624882e-07 | P6: =F6-K6 -> 4.8166003e-06
A7: mit.act.ecy.res | B7: =Mitigation!N56 -> 1506.9058 | C7: =Mitigation!O56 -> 1590.1129 | D7: =Mitigation!T56 -> 1967.1943 | E7: =Mitigation!AD56 -> 2722.1998 | F7: =Mitigation!AN56 -> 3544.2642 | G7: =INDEX(PyKey!D$3:D$2978,MATCH(Settings!$C$4&"|mit.act.ecy.res",PyKey!$A$3:$A$2978,0)) -> 1506.9058 | H7: =INDEX(PyKey!E$3:E$2978,MATCH(Settings!$C$4&"|mit.act.ecy.res",PyKey!$A$3:$A$2978,0)) -> 1590.1129 | I7: =INDEX(PyKey!F$3:F$2978,MATCH(Settings!$C$4&"|mit.act.ecy.res",PyKey!$A$3:$A$2978,0)) -> 1967.1943 | J7: =INDEX(PyKey!G$3:G$2978,MATCH(Settings!$C$4&"|mit.act.ecy.res",PyKey!$A$3:$A$2978,0)) -> 2722.1998 | K7: =INDEX(PyKey!H$3:H$2978,MATCH(Settings!$C$4&"|mit.act.ecy.res",PyKey!$A$3:$A$2978,0)) -> 3544.2642 | L7: =B7-G7 -> 2.8457498e-07 | M7: =C7-H7 -> -7.2533794e-08 | N7: =D7-I7 -> -7.0940132e-08 | O7: =E7-J7 -> -2.3389885e-07 | P7: =F7-K7 -> -3.865398e-07
A8: mit.gen.tot.2 | B8: =Mitigation!N131 -> 2085.9059 | C8: =Mitigation!O131 -> 2272.1555 | D8: =Mitigation!T131 -> 3255.266 | E8: =Mitigation!AD131 -> 5716.3554 | F8: =Mitigation!AN131 -> 8752.0254 | G8: =INDEX(PyKey!D$3:D$2978,MATCH(Settings!$C$4&"|mit.gen.tot.2",PyKey!$A$3:$A$2978,0)) -> 2085.9059 | H8: =INDEX(PyKey!E$3:E$2978,MATCH(Settings!$C$4&"|mit.gen.tot.2",PyKey!$A$3:$A$2978,0)) -> 2272.1555 | I8: =INDEX(PyKey!F$3:F$2978,MATCH(Settings!$C$4&"|mit.gen.tot.2",PyKey!$A$3:$A$2978,0)) -> 3255.266 | J8: =INDEX(PyKey!G$3:G$2978,MATCH(Settings!$C$4&"|mit.gen.tot.2",PyKey!$A$3:$A$2978,0)) -> 5716.3554 | K8: =INDEX(PyKey!H$3:H$2978,MATCH(Settings!$C$4&"|mit.gen.tot.2",PyKey!$A$3:$A$2978,0)) -> 8752.0254 | L8: =B8-G8 -> -1.7075081e-07 | M8: =C8-H8 -> -2.3196981e-07 | N8: =D8-I8 -> 4.534345e-07 | O8: =E8-J8 -> -2.1659071e-07 | P8: =F8-K8 -> 2.3222674e-07
A9: mit.gen.fos.1 | B9: =Mitigation!N112 -> 1529.9482 | C9: =Mitigation!O112 -> 1586.5729 | D9: =Mitigation!T112 -> 1792.8105 | E9: =Mitigation!AD112 -> 2007.5883 | F9: =Mitigation!AN112 -> 1971.9426 | G9: =INDEX(PyKey!D$3:D$2978,MATCH(Settings!$C$4&"|mit.gen.fos.1",PyKey!$A$3:$A$2978,0)) -> 1529.9482 | H9: =INDEX(PyKey!E$3:E$2978,MATCH(Settings!$C$4&"|mit.gen.fos.1",PyKey!$A$3:$A$2978,0)) -> 1586.5729 | I9: =INDEX(PyKey!F$3:F$2978,MATCH(Settings!$C$4&"|mit.gen.fos.1",PyKey!$A$3:$A$2978,0)) -> 1792.8105 | J9: =INDEX(PyKey!G$3:G$2978,MATCH(Settings!$C$4&"|mit.gen.fos.1",PyKey!$A$3:$A$2978,0)) -> 2007.5883 | K9: =INDEX(PyKey!H$3:H$2978,MATCH(Settings!$C$4&"|mit.gen.fos.1",PyKey!$A$3:$A$2978,0)) -> 1971.9426 | L9: =B9-G9 -> -1.7358343e-07 | M9: =C9-H9 -> 1.1414295e-07 | N9: =D9-I9 -> -1.7673801e-07 | O9: =E9-J9 -> 1.9352547e-07 | P9: =F9-K9 -> -3.2568414e-07
A10: mit.inv.gen.2 | B10: =Mitigation!N144 -> 0 | C10: =Mitigation!O144 -> 51.203564 | D10: =Mitigation!T144 -> 67.427458 | E10: =Mitigation!AD144 -> 107.82792 | F10: =Mitigation!AN144 -> 100.47504 | G10: =INDEX(PyKey!D$3:D$2978,MATCH(Settings!$C$4&"|mit.inv.gen.2",PyKey!$A$3:$A$2978,0)) -> 0 | H10: =INDEX(PyKey!E$3:E$2978,MATCH(Settings!$C$4&"|mit.inv.gen.2",PyKey!$A$3:$A$2978,0)) -> 51.203564 | I10: =INDEX(PyKey!F$3:F$2978,MATCH(Settings!$C$4&"|mit.inv.gen.2",PyKey!$A$3:$A$2978,0)) -> 67.427458 | J10: =INDEX(PyKey!G$3:G$2978,MATCH(Settings!$C$4&"|mit.inv.gen.2",PyKey!$A$3:$A$2978,0)) -> 107.82792 | K10: =INDEX(PyKey!H$3:H$2978,MATCH(Settings!$C$4&"|mit.inv.gen.2",PyKey!$A$3:$A$2978,0)) -> 100.47504 | L10: =B10-G10 -> 0 | M10: =C10-H10 -> 3.8494363e-10 | N10: =D10-I10 -> 4.8210325e-09 | O10: =E10-J10 -> -1.5406428e-08 | P10: =F10-K10 -> -4.2780329e-08
A11: mit.inv.grid.2 | B11: =Mitigation!N146 -> 0 | C11: =Mitigation!O146 -> 30.722138 | D11: =Mitigation!T146 -> 51.01632 | E11: =Mitigation!AD146 -> 116.7643 | F11: =Mitigation!AN146 -> 106.61167 | G11: =INDEX(PyKey!D$3:D$2978,MATCH(Settings!$C$4&"|mit.inv.grid.2",PyKey!$A$3:$A$2978,0)) -> 0 | H11: =INDEX(PyKey!E$3:E$2978,MATCH(Settings!$C$4&"|mit.inv.grid.2",PyKey!$A$3:$A$2978,0)) -> 30.722138 | I11: =INDEX(PyKey!F$3:F$2978,MATCH(Settings!$C$4&"|mit.inv.grid.2",PyKey!$A$3:$A$2978,0)) -> 51.01632 | J11: =INDEX(PyKey!G$3:G$2978,MATCH(Settings!$C$4&"|mit.inv.grid.2",PyKey!$A$3:$A$2978,0)) -> 116.7643 | K11: =INDEX(PyKey!H$3:H$2978,MATCH(Settings!$C$4&"|mit.inv.grid.2",PyKey!$A$3:$A$2978,0)) -> 106.61167 | L11: =B11-G11 -> 0 | M11: =C11-H11 -> 4.2309658e-09 | N11: =D11-I11 -> 4.5747512e-09 | O11: =E11-J11 -> -3.5245904e-08 | P11: =F11-K11 -> -3.7555253e-08
A12: mit.inv.trn.2 | B12: =Mitigation!N77 -> 0 | C12: =Mitigation!O77 -> 6.8352369 | D12: =Mitigation!T77 -> 11.16636 | E12: =Mitigation!AD77 -> 8.9378186 | F12: =Mitigation!AN77 -> 10.40226 | G12: =INDEX(PyKey!D$3:D$2978,MATCH(Settings!$C$4&"|mit.inv.trn.2",PyKey!$A$3:$A$2978,0)) -> 0 | H12: =INDEX(PyKey!E$3:E$2978,MATCH(Settings!$C$4&"|mit.inv.trn.2",PyKey!$A$3:$A$2978,0)) -> 6.8352369 | I12: =INDEX(PyKey!F$3:F$2978,MATCH(Settings!$C$4&"|mit.inv.trn.2",PyKey!$A$3:$A$2978,0)) -> 11.16636 | J12: =INDEX(PyKey!G$3:G$2978,MATCH(Settings!$C$4&"|mit.inv.trn.2",PyKey!$A$3:$A$2978,0)) -> 8.9378186 | K12: =INDEX(PyKey!H$3:H$2978,MATCH(Settings!$C$4&"|mit.inv.trn.2",PyKey!$A$3:$A$2978,0)) -> 10.40226 | L12: =B12-G12 -> 0 | M12: =C12-H12 -> -2.742242e-10 | N12: =D12-I12 -> -4.0719712e-09 | O12: =E12-J12 -> -4.8619775e-10 | P12: =F12-K12 -> 4.9639794e-09
A13: mit.inv.bld.2 | B13: =Mitigation!N91 -> 0 | C13: =Mitigation!O91 -> 9.929822 | D13: =Mitigation!T91 -> 12.129447 | E13: =Mitigation!AD91 -> 15.33712 | F13: =Mitigation!AN91 -> 19.262357 | G13: =INDEX(PyKey!D$3:D$2978,MATCH(Settings!$C$4&"|mit.inv.bld.2",PyKey!$A$3:$A$2978,0)) -> 0 | H13: =INDEX(PyKey!E$3:E$2978,MATCH(Settings!$C$4&"|mit.inv.bld.2",PyKey!$A$3:$A$2978,0)) -> 9.929822 | I13: =INDEX(PyKey!F$3:F$2978,MATCH(Settings!$C$4&"|mit.inv.bld.2",PyKey!$A$3:$A$2978,0)) -> 12.129447 | J13: =INDEX(PyKey!G$3:G$2978,MATCH(Settings!$C$4&"|mit.inv.bld.2",PyKey!$A$3:$A$2978,0)) -> 15.33712 | K13: =INDEX(PyKey!H$3:H$2978,MATCH(Settings!$C$4&"|mit.inv.bld.2",PyKey!$A$3:$A$2978,0)) -> 19.262357 | L13: =B13-G13 -> 0 | M13: =C13-H13 -> 2.6413005e-10 | N13: =D13-I13 -> 1.2151862e-09 | O13: =E13-J13 -> 9.4622266e-10 | P13: =F13-K13 -> 2.1494913e-09
A14: mit.inv.ind.2 | B14: =Mitigation!N104 -> 0 | C14: =Mitigation!O104 -> 27.177721 | D14: =Mitigation!T104 -> 38.677152 | E14: =Mitigation!AD104 -> 53.6587 | F14: =Mitigation!AN104 -> 76.171067 | G14: =INDEX(PyKey!D$3:D$2978,MATCH(Settings!$C$4&"|mit.inv.ind.2",PyKey!$A$3:$A$2978,0)) -> 0 | H14: =INDEX(PyKey!E$3:E$2978,MATCH(Settings!$C$4&"|mit.inv.ind.2",PyKey!$A$3:$A$2978,0)) -> 27.177721 | I14: =INDEX(PyKey!F$3:F$2978,MATCH(Settings!$C$4&"|mit.inv.ind.2",PyKey!$A$3:$A$2978,0)) -> 38.677152 | J14: =INDEX(PyKey!G$3:G$2978,MATCH(Settings!$C$4&"|mit.inv.ind.2",PyKey!$A$3:$A$2978,0)) -> 53.6587 | K14: =INDEX(PyKey!H$3:H$2978,MATCH(Settings!$C$4&"|mit.inv.ind.2",PyKey!$A$3:$A$2978,0)) -> 76.171067 | L14: =B14-G14 -> 0 | M14: =C14-H14 -> -1.4722197e-09 | N14: =D14-I14 -> -6.9624662e-10 | O14: =E14-J14 -> 1.2199095e-09 | P14: =F14-K14 -> -2.7706903e-09
A15: mit.inv.tot.1 | B15: =Mitigation!N175 -> 0 | C15: =Mitigation!O175 -> 55.163825 | D15: =Mitigation!T175 -> 59.584452 | E15: =Mitigation!AD175 -> 67.544939 | F15: =Mitigation!AN175 -> 81.977408 | G15: =INDEX(PyKey!D$3:D$2978,MATCH(Settings!$C$4&"|mit.inv.tot.1",PyKey!$A$3:$A$2978,0)) -> 0 | H15: =INDEX(PyKey!E$3:E$2978,MATCH(Settings!$C$4&"|mit.inv.tot.1",PyKey!$A$3:$A$2978,0)) -> 55.163825 | I15: =INDEX(PyKey!F$3:F$2978,MATCH(Settings!$C$4&"|mit.inv.tot.1",PyKey!$A$3:$A$2978,0)) -> 59.584452 | J15: =INDEX(PyKey!G$3:G$2978,MATCH(Settings!$C$4&"|mit.inv.tot.1",PyKey!$A$3:$A$2978,0)) -> 67.544939 | K15: =INDEX(PyKey!H$3:H$2978,MATCH(Settings!$C$4&"|mit.inv.tot.1",PyKey!$A$3:$A$2978,0)) -> 81.977408 | L15: =B15-G15 -> 0 | M15: =C15-H15 -> 2.6058373e-09 | N15: =D15-I15 -> 4.6806861e-09 | O15: =E15-J15 -> 3.8724579e-09 | P15: =F15-K15 -> -3.2489993e-09
A16: mit.inv.tot.2 | B16: =Mitigation!N176 -> 0 | C16: =Mitigation!O176 -> 129.90375 | D16: =Mitigation!T176 -> 204.62834 | E16: =Mitigation!AD176 -> 348.08479 | F16: =Mitigation!AN176 -> 379.82866 | G16: =INDEX(PyKey!D$3:D$2978,MATCH(Settings!$C$4&"|mit.inv.tot.2",PyKey!$A$3:$A$2978,0)) -> 0 | H16: =INDEX(PyKey!E$3:E$2978,MATCH(Settings!$C$4&"|mit.inv.tot.2",PyKey!$A$3:$A$2978,0)) -> 129.90375 | I16: =INDEX(PyKey!F$3:F$2978,MATCH(Settings!$C$4&"|mit.inv.tot.2",PyKey!$A$3:$A$2978,0)) -> 204.62834 | J16: =INDEX(PyKey!G$3:G$2978,MATCH(Settings!$C$4&"|mit.inv.tot.2",PyKey!$A$3:$A$2978,0)) -> 348.08479 | K16: =INDEX(PyKey!H$3:H$2978,MATCH(Settings!$C$4&"|mit.inv.tot.2",PyKey!$A$3:$A$2978,0)) -> 379.82866 | L16: =B16-G16 -> 0 | M16: =C16-H16 -> -3.4190862e-08 | N16: =D16-I16 -> 1.38958e-08 | O16: =E16-J16 -> -4.6309367e-08 | P16: =F16-K16 -> 1.5280307e-08
A17: mit.ghg.tot.1 | B17: =Mitigation!N158 -> 4131.845 | C17: =Mitigation!O158 -> 4236.5833 | D17: =Mitigation!T158 -> 4680.0616 | E17: =Mitigation!AD158 -> 5220.0356 | F17: =Mitigation!AN158 -> 5596.8304 | G17: =INDEX(PyKey!D$3:D$2978,MATCH(Settings!$C$4&"|mit.ghg.tot.1",PyKey!$A$3:$A$2978,0)) -> 4131.845 | H17: =INDEX(PyKey!E$3:E$2978,MATCH(Settings!$C$4&"|mit.ghg.tot.1",PyKey!$A$3:$A$2978,0)) -> 4236.5833 | I17: =INDEX(PyKey!F$3:F$2978,MATCH(Settings!$C$4&"|mit.ghg.tot.1",PyKey!$A$3:$A$2978,0)) -> 4680.0616 | J17: =INDEX(PyKey!G$3:G$2978,MATCH(Settings!$C$4&"|mit.ghg.tot.1",PyKey!$A$3:$A$2978,0)) -> 5220.0356 | K17: =INDEX(PyKey!H$3:H$2978,MATCH(Settings!$C$4&"|mit.ghg.tot.1",PyKey!$A$3:$A$2978,0)) -> 5596.8304 | L17: =B17-G17 -> 0 | M17: =C17-H17 -> -2.9272815e-07 | N17: =D17-I17 -> 8.1154212e-09 | O17: =E17-J17 -> -4.2883858e-07 | P17: =F17-K17 -> -1.3550653e-07
A18: mit.ghg.tot.2 | B18: =Mitigation!N164 -> 4131.845 | C18: =Mitigation!O164 -> 4126.1949 | D18: =Mitigation!T164 -> 3882.6482 | E18: =Mitigation!AD164 -> 2659.7537 | F18: =Mitigation!AN164 -> 1010.2699 | G18: =INDEX(PyKey!D$3:D$2978,MATCH(Settings!$C$4&"|mit.ghg.tot.2",PyKey!$A$3:$A$2978,0)) -> 4131.845 | H18: =INDEX(PyKey!E$3:E$2978,MATCH(Settings!$C$4&"|mit.ghg.tot.2",PyKey!$A$3:$A$2978,0)) -> 4126.1949 | I18: =INDEX(PyKey!F$3:F$2978,MATCH(Settings!$C$4&"|mit.ghg.tot.2",PyKey!$A$3:$A$2978,0)) -> 3882.6482 | J18: =INDEX(PyKey!G$3:G$2978,MATCH(Settings!$C$4&"|mit.ghg.tot.2",PyKey!$A$3:$A$2978,0)) -> 2659.7537 | K18: =INDEX(PyKey!H$3:H$2978,MATCH(Settings!$C$4&"|mit.ghg.tot.2",PyKey!$A$3:$A$2978,0)) -> 1010.2699 | L18: =B18-G18 -> 0 | M18: =C18-H18 -> 2.921297e-09 | N18: =D18-I18 -> -3.2592197e-08 | O18: =E18-J18 -> 4.7242293e-07 | P18: =F18-K18 -> 1.6593742e-07
A19: mit.ic.a | B19: =Mitigation!N189 -> 0 | C19: =Mitigation!O189 -> 7.7886863 | D19: =Mitigation!T189 -> 51.365079 | E19: =Mitigation!AD189 -> 122.81545 | F19: =Mitigation!AN189 -> 228.57678 | G19: =INDEX(PyKey!D$3:D$2978,MATCH(Settings!$C$4&"|mit.ic.a",PyKey!$A$3:$A$2978,0)) -> 0 | H19: =INDEX(PyKey!E$3:E$2978,MATCH(Settings!$C$4&"|mit.ic.a",PyKey!$A$3:$A$2978,0)) -> 7.7886863 | I19: =INDEX(PyKey!F$3:F$2978,MATCH(Settings!$C$4&"|mit.ic.a",PyKey!$A$3:$A$2978,0)) -> 51.365079 | J19: =INDEX(PyKey!G$3:G$2978,MATCH(Settings!$C$4&"|mit.ic.a",PyKey!$A$3:$A$2978,0)) -> 122.81545 | K19: =INDEX(PyKey!H$3:H$2978,MATCH(Settings!$C$4&"|mit.ic.a",PyKey!$A$3:$A$2978,0)) -> 228.57678 | L19: =B19-G19 -> 0 | M19: =C19-H19 -> 3.0166003e-10 | N19: =D19-I19 -> 3.9421053e-09 | O19: =E19-J19 -> 2.5681487e-08 | P19: =F19-K19 -> 3.5159928e-09
A20: mit.ic.b | B20: =Mitigation!N190 -> 0 | C20: =Mitigation!O190 -> 5.8042118 | D20: =Mitigation!T190 -> 35.049096 | E20: =Mitigation!AD190 -> 56.630097 | F20: =Mitigation!AN190 -> 94.234214 | G20: =INDEX(PyKey!D$3:D$2978,MATCH(Settings!$C$4&"|mit.ic.b",PyKey!$A$3:$A$2978,0)) -> 0 | H20: =INDEX(PyKey!E$3:E$2978,MATCH(Settings!$C$4&"|mit.ic.b",PyKey!$A$3:$A$2978,0)) -> 5.8042118 | I20: =INDEX(PyKey!F$3:F$2978,MATCH(Settings!$C$4&"|mit.ic.b",PyKey!$A$3:$A$2978,0)) -> 35.049096 | J20: =INDEX(PyKey!G$3:G$2978,MATCH(Settings!$C$4&"|mit.ic.b",PyKey!$A$3:$A$2978,0)) -> 56.630097 | K20: =INDEX(PyKey!H$3:H$2978,MATCH(Settings!$C$4&"|mit.ic.b",PyKey!$A$3:$A$2978,0)) -> 94.234214 | L20: =B20-G20 -> 0 | M20: =C20-H20 -> 2.2917757e-10 | N20: =D20-I20 -> -3.6484025e-09 | O20: =E20-J20 -> -1.7814656e-09 | P20: =F20-K20 -> 6.0624927e-10
A21: mit.ic.c | B21: =Mitigation!N191 -> 0 | C21: =Mitigation!O191 -> 1.773167 | D21: =Mitigation!T191 -> 1.8927626 | E21: =Mitigation!AD191 -> -83.281604 | F21: =Mitigation!AN191 -> -179.92678 | G21: =INDEX(PyKey!D$3:D$2978,MATCH(Settings!$C$4&"|mit.ic.c",PyKey!$A$3:$A$2978,0)) -> 0 | H21: =INDEX(PyKey!E$3:E$2978,MATCH(Settings!$C$4&"|mit.ic.c",PyKey!$A$3:$A$2978,0)) -> 1.773167 | I21: =INDEX(PyKey!F$3:F$2978,MATCH(Settings!$C$4&"|mit.ic.c",PyKey!$A$3:$A$2978,0)) -> 1.8927626 | J21: =INDEX(PyKey!G$3:G$2978,MATCH(Settings!$C$4&"|mit.ic.c",PyKey!$A$3:$A$2978,0)) -> -83.281604 | K21: =INDEX(PyKey!H$3:H$2978,MATCH(Settings!$C$4&"|mit.ic.c",PyKey!$A$3:$A$2978,0)) -> -179.92678 | L21: =B21-G21 -> 0 | M21: =C21-H21 -> 4.4979931e-10 | N21: =D21-I21 -> 3.7891934e-10 | O21: =E21-J21 -> -8.8887475e-10 | P21: =F21-K21 -> -4.0010548e-08

Sheet DATA->

Sheet Data
A1: Data: one row per country (CPAT 2024 panel, Ember, WEO, CBAM tool, v1.1 WACC). Built by extract_data_v0_1.py.
A3: countrycode | B3: name | C3: aei_coa_ind | D3: aei_coa_res | E3: aei_die_rod | F3: aei_ecy_ind | G3: aei_ecy_res | H3: aei_gso_rod | I3: aei_ker_res | J3: aei_lpg_res | K3: aei_nga_ind | L3: aei_nga_res | M3: aei_oil_ind | N3: ap_coa_ind | O3: ap_coa_pow | P3: ap_coa_res | Q3: ap_die_rod | R3: ap_gso_rod | S3: ap_ker_res | T3: ap_lpg_res | U3: ap_nga_ind | V3: ap_nga_pow | W3: ap_nga_res | X3: ap_oil_ind | Y3: ap_oil_pow | Z3: cap_fos | AA3: cap_sol | AB3: cap_wnd | AC3: cbam_g | AD3: cbam_proc24 | AE3: co2_24 | AF3: con_coa_ind | AG3: con_coa_ind_2021 | AH3: con_coa_ind_2022 | AI3: con_coa_ind_2023 | AJ3: con_coa_pow | AK3: con_coa_res | AL3: con_coa_res_2021 | AM3: con_coa_res_2022 | AN3: con_coa_res_2023 | AO3: con_die_rod | AP3: con_die_rod_2021 | AQ3: con_die_rod_2022 | AR3: con_die_rod_2023 | AS3: con_ecy_ind | AT3: con_ecy_ind_2021 | AU3: con_ecy_ind_2022 | AV3: con_ecy_ind_2023 | AW3: con_ecy_res | AX3: con_ecy_res_2021 | AY3: con_ecy_res_2022 | AZ3: con_ecy_res_2023 | BA3: con_gso_rod | BB3: con_gso_rod_2021 | BC3: con_gso_rod_2022 | BD3: con_gso_rod_2023 | BE3: con_ker_res | BF3: con_ker_res_2021 | BG3: con_ker_res_2022 | BH3: con_ker_res_2023 | BI3: con_lpg_res | BJ3: con_lpg_res_2021 | BK3: con_lpg_res_2022 | BL3: con_lpg_res_2023 | BM3: con_nga_ind | BN3: con_nga_ind_2021 | BO3: con_nga_ind_2022 | BP3: con_nga_ind_2023 | BQ3: con_nga_pow | BR3: con_nga_res | BS3: con_nga_res_2021 | BT3: con_nga_res_2022 | BU3: con_nga_res_2023 | BV3: con_oil_ind | BW3: con_oil_ind_2021 | BX3: con_oil_ind_2022 | BY3: con_oil_ind_2023 | BZ3: dem_twh24 | CA3: fos_trend | CB3: g25 | CC3: g26 | CD3: gdp24 | CE3: gen_cfirm | CF3: gen_coa | CG3: gen_fos | CH3: gen_nga | CI3: gen_oil | CJ3: gen_sol | CK3: gen_tot | CL3: gen_wnd | CM3: ghg_exc | CN3: ghg_inc | CO3: grp | CP3: inc | CQ3: inc_coa_ind | CR3: inc_coa_res | CS3: inc_die_rod | CT3: inc_ecy_ind | CU3: inc_ecy_res | CV3: inc_gso_rod | CW3: inc_ker_res | CX3: inc_lpg_res | CY3: inc_nga_ind | CZ3: inc_nga_res | DA3: inc_oil_ind | DB3: plevel | DC3: sp_coa_ind | DD3: sp_coa_pow | DE3: sp_coa_res | DF3: sp_die_rod | DG3: sp_gso_rod | DH3: sp_ker_res | DI3: sp_lpg_res | DJ3: sp_nga_ind | DK3: sp_nga_pow | DL3: sp_nga_res | DM3: sp_oil_ind | DN3: sp_oil_pow | DO3: wacc
A4: ABW | B4: Aruba | C4: 0.005 | D4: 0.005 | E4: 0.01 | F4: 0.005 | G4: 0.005 | H4: 0.01 | I4: 0.005 | J4: 0.005 | K4: 0.01 | L4: 0.01 | M4: 0.005 | N4: 0 | O4: 0 | P4: 0 | Q4: 0 | R4: 0 | S4: 0 | T4: 0 | U4: 0 | V4: 0 | W4: 0 | X4: 0 | Y4: 0 | Z4: 0.24 | AA4: 0.01 | AB4: 0.03 | AC4: 0 | AD4: 0 | AE4: 0.429 | AF4: 0 | AG4: 0 | AH4: 0 | AI4: 0 | AJ4: 0 | AK4: 0 | AL4: 0 | AM4: 0 | AN4: 0 | AO4: 0.6726517 | AP4: 0.64640713 | AQ4: 0.64640713 | AR4: 0.64640713 | AS4: 1.7736358 | AT4: 1.5855804 | AU4: 1.7436998 | AV4: 1.8023056 | AW4: 1.3329033 | AX4: 1.231542 | AY4: 1.3104061 | AZ4: 1.3544489 | BA4: 3.185888 | BB4: 2.9833029 | BC4: 3.155658 | BD4: 3.0682705 | BE4: 0 | BF4: 0 | BG4: 0 | BH4: 0 | BI4: 0.3839034 | BJ4: 0.37032924 | BK4: 0.37032924 | BL4: 0.37032924 | BM4: 0 | BN4: 0 | BO4: 0 | BP4: 0 | BQ4: 0 | BR4: 0 | BS4: 0 | BT4: 0 | BU4: 0 | BV4: 11.162686 | BW4: 11.588358 | BX4: 11.50107 | BY4: 11.282727 | BZ4: 0.86292754 | CA4: 0 | CB4: 5.608 | CC4: 2.25 | CD4: 4.285 | CE4: 0 | CF4: 0 | CG4: 0.83 | CH4: 0 | CI4: 0.83 | CJ4: 0.03 | CK4: 1 | CL4: 0.14 | CM4: 0.47 | CN4: 0.47 | CO4: 3 | CP4: 4 | CQ4: 0.5 | CR4: 0.3 | CS4: 0.6 | CT4: 0.8 | CU4: 0.8 | CV4: 0.7 | CW4: 0.5 | CX4: 0.5 | CY4: 1 | CZ4: 0.3 | DA4: 0.8 | DB4: 0.76805879 | DC4: 7.124 | DD4: 5.575 | DE4: 12.375895 | DF4: 17.653885 | DG4: 21.924613 | DH4: 15.046824 | DI4: 20.972208 | DJ4: 8.176 | DK4: 6.853 | DL4: 16.35977 | DM4: 13.497473 | DN4: 13.497473 | DO4: 0.105
A5: AFG | B5: Afghanistan | C5: 0.005 | D5: 0.005 | E5: 0.01 | F5: 0.005 | G5: 0.005 | H5: 0.01 | I5: 0.005 | J5: 0.005 | K5: 0.01 | L5: 0.01 | M5: 0.005 | N5: 0.725007 | O5: 0.004124 | P5: 1.988039 | Q5: 0.60171298 | R5: 0.16906045 | S5: 0.26149155 | T5: 0.087122852 | U5: 0.043622 | V5: 0.002521 | W5: 0.010402 | X5: 0.86813036 | Y5: 0.86813036 | Z5: 0.28 | AA5: 0.06 | AB5: 0 | AC5: 0 | AD5: 0 | AE5: 5.893 | AF5: 37.262738 | AG5: 34.328411 | AH5: 34.671695 | AI5: 34.671695 | AJ5: 1.3876284 | AK5: 0 | AL5: 0 | AM5: 0 | AN5: 0 | AO5: 23.103497 | AP5: 22.030559 | AQ5: 22.250865 | AR5: 22.250865 | AS5: 8.0369065 | AT5: 8.3715066 | AU5: 8.0795415 | AV5: 8.0522437 | AW5: 11.885731 | AX5: 12.328619 | AY5: 11.948784 | AZ5: 11.908413 | BA5: 42.414237 | BB5: 43.222909 | BC5: 39.192842 | BD5: 41.36386 | BE5: 2.6071822 | BF5: 2.5860416 | BG5: 2.611902 | BH5: 2.611902 | BI5: 28.421359 | BJ5: 27.42355 | BK5: 27.697785 | BL5: 27.697785 | BM5: 2.87982 | BN5: 2.8664897 | BO5: 2.8951546 | BP5: 2.8951546 | BQ5: 0 | BR5: 0 | BS5: 0 | BT5: 0 | BU5: 0 | BV5: 1.5519122 | BW5: 3.2424263 | BX5: 1.5152981 | BY5: 1.5153562 | BZ5: 5.534066 | CA5: -0.28905406 | CB5: 3.004 | CC5: 3 | CD5: 17.817 | CE5: 0.75 | CF5: 0.03 | CG5: 0.13 | CH5: 0 | CI5: 0.1 | CJ5: 0.11 | CK5: 0.99 | CL5: 0 | CM5: 29.715 | CN5: 29.862 | CO5: 3 | CP5: 1 | CQ5: 0.5 | CR5: 0.3 | CS5: 0.6 | CT5: 0.8 | CU5: 0.8 | CV5: 0.7 | CW5: 0.5 | CX5: 0.5 | CY5: 1 | CZ5: 0.3 | DA5: 0.8 | DB5: 0.18682367 | DC5: 7.124 | DD5: 4.833 | DE5: 12.5961 | DF5: 20.300446 | DG5: 22.648152 | DH5: 18.999265 | DI5: 21.687694 | DJ5: 6.449 | DK5: 5.125 | DL5: 15.829 | DM5: 14.11517 | DN5: 14.11517 | DO5: 0.105
A6: AGO | B6: Angola | C6: 0.005 | D6: 0.005 | E6: 0.01 | F6: 0.005 | G6: 0.005 | H6: 0.01 | I6: 0.005 | J6: 0.005 | K6: 0.01 | L6: 0.01 | M6: 0.005 | N6: 0.282221 | O6: 0.199568 | P6: 7.193399 | Q6: 2.8222674 | R6: 0.64461446 | S6: 0.58446845 | T6: 0.20706224 | U6: 0.012474 | V6: 0.011921 | W6: 0.017842 | X6: 0.57020957 | Y6: 0.57020957 | Z6: 2.36 | AA6: 0.36 | AB6: 0 | AC6: 0 | AD6: 0 | AE6: 19.873 | AF6: 0 | AG6: 0 | AH6: 0 | AI6: 0 | AJ6: 0 | AK6: 0 | AL6: 0 | AM6: 0 | AN6: 0 | AO6: 52.323103 | AP6: 55.365612 | AQ6: 50.933371 | AR6: 51.442704 | AS6: 18.011454 | AT6: 16.010001 | AU6: 16.164924 | AV6: 14.516393 | AW6: 35.336891 | AX6: 31.410215 | AY6: 31.714162 | AZ6: 28.479888 | BA6: 41.411322 | BB6: 34.262694 | BC6: 49.721231 | BD6: 39.983814 | BE6: 0 | BF6: 0 | BG6: 0 | BH6: 0 | BI6: 81.853958 | BJ6: 80.336927 | BK6: 73.905631 | BL6: 74.644687 | BM6: 25.887409 | BN6: 27.197357 | BO6: 25.020098 | BP6: 25.270299 | BQ6: 37.694277 | BR6: 0 | BS6: 0 | BT6: 0 | BU6: 0 | BV6: 41.162827 | BW6: 82.166654 | BX6: 60.161164 | BY6: 39.401542 | BZ6: 14.818985 | CA6: -0.57639221 | CB6: 3.13 | CC6: 2.294 | CD6: 119.574 | CE6: 11.05 | CF6: 0 | CG6: 4.1 | CH6: 1.4 | CI6: 2.7 | CJ6: 0.44 | CK6: 15.59 | CL6: 0 | CM6: 70.933 | CN6: 113.459 | CO6: 3 | CP6: 2 | CQ6: 0.5 | CR6: 0.3 | CS6: 0.6 | CT6: 0.8 | CU6: 0.8 | CV6: 0.7 | CW6: 0.5 | CX6: 0.5 | CY6: 1 | CZ6: 0.3 | DA6: 0.8 | DB6: 0.31475622 | DC6: 7.124 | DD6: 5.575 | DE6: 13.90002 | DF6: 20.889101 | DG6: 23.371435 | DH6: 15.656115 | DI6: 22.525485 | DJ6: 6.696 | DK6: 6.034 | DL6: 12.16038 | DM6: 13.494746 | DN6: 13.494746 | DO6: 0.105
A7: ALB | B7: Albania | C7: 0.005 | D7: 0.005 | E7: 0.01 | F7: 0.005 | G7: 0.005 | H7: 0.01 | I7: 0.005 | J7: 0.005 | K7: 0.01 | L7: 0.01 | M7: 0.005 | N7: 0.854677 | O7: 0.895432 | P7: 66.69538 | Q7: 12.628385 | R7: 1.3628068 | S7: 4.1329228 | T7: 4.7884985 | U7: 0.552136 | V7: 0.090351 | W7: 0.198232 | X7: 8.9926945 | Y7: 8.9926945 | Z7: 0 | AA7: 0 | AB7: 0 | AC7: 3.2 | AD7: 0 | AE7: 4.479 | AF7: 9.9748785 | AG7: 9.3703515 | AH7: 9.7264248 | AI7: 9.3568207 | AJ7: 0 | AK7: 0.14880412 | AL7: 0.13665297 | AM7: 0.14184578 | AN7: 0.13645564 | AO7: 20.596581 | AP7: 20.443194 | AQ7: 21.220036 | AR7: 20.413674 | AS7: 12.745462 | AT7: 11.379739 | AU7: 12.274368 | AV7: 12.929552 | AW7: 14.030846 | AX7: 12.616742 | AY7: 13.51241 | AZ7: 14.233809 | BA7: 3.1098948 | BB7: 3.0867562 | BC7: 3.1704411 | BD7: 3.082299 | BE7: 0 | BF7: 0 | BG7: 0 | BH7: 0 | BI7: 5.425202 | BJ7: 5.1191744 | BK7: 5.313703 | BL7: 5.1117823 | BM7: 1.6153267 | BN7: 1.5822001 | BO7: 1.6423237 | BP7: 1.5799154 | BQ7: 0 | BR7: 0.27693795 | BS7: 0.27125859 | BT7: 0.28156641 | BU7: 0.27086689 | BV7: 12.710964 | BW7: 12.276594 | BX7: 12.737206 | BY7: 12.258867 | BZ7: 7.4378632 | CA7: 0 | CB7: 3.705 | CC7: 3.409 | CD7: 27.084 | CE7: 6.707 | CF7: 0 | CG7: 0 | CH7: 0 | CI7: 0 | CJ7: 0.404 | CK7: 7.111 | CL7: 0 | CM7: 8.074 | CN7: 7.828 | CO7: 3 | CP7: 3 | CQ7: 0.5 | CR7: 0.3 | CS7: 0.6 | CT7: 0.8 | CU7: 0.8 | CV7: 0.7 | CW7: 0.5 | CX7: 0.5 | CY7: 1 | CZ7: 0.3 | DA7: 0.8 | DB7: 0.45608245 | DC7: 5.333 | DD7: 3.252 | DE7: 9.9468 | DF7: 21.594018 | DG7: 23.934779 | DH7: 15.656115 | DI7: 22.265009 | DJ7: 6.853 | DK7: 6.191 | DL7: 12.9876 | DM7: 13.494746 | DN7: 13.494746 | DO7: 0.105
A8: ARE | B8: United Arab Emirates | C8: 0.005 | D8: 0.005 | E8: 0.01 | F8: 0.005 | G8: 0.005 | H8: 0.01 | I8: 0.005 | J8: 0.005 | K8: 0.01 | L8: 0.01 | M8: 0.005 | N8: 4.186571 | O8: 1.405832 | P8: 10.854225 | Q8: 6.4463004 | R8: 1.4539713 | S8: 1.9410933 | T8: 2.636533 | U8: 0.238403 | V8: 0.22187 | W8: 0.020982 | X8: 5.6690649 | Y8: 5.6690649 | Z8: 41.7 | AA8: 6.5 | AB8: 0.11 | AC8: 3 | AD8: 4.2625469 | AE8: 230.363 | AF8: 96.938444 | AG8: 86.409858 | AH8: 87.273957 | AI8: 89.698233 | AJ8: 5.3875039 | AK8: 0 | AL8: 0 | AM8: 0 | AN8: 0 | AO8: 143.66293 | AP8: 131.30045 | AQ8: 132.61345 | AR8: 136.29716 | AS8: 393.28241 | AT8: 330.53553 | AU8: 357.79146 | AV8: 382.69435 | AW8: 180.25171 | AX8: 154.58869 | AY8: 163.98527 | AZ8: 175.39892 | BA8: 366.23614 | BB8: 322.84879 | BC8: 349.82194 | BD8: 347.1227 | BE8: 0 | BF8: 0 | BG8: 0 | BH8: 0 | BI8: 9.93201 | BJ8: 9.1724673 | BK8: 9.2641919 | BL8: 9.5215306 | BM8: 1201.582 | BN8: 1057.5446 | BO8: 1068.1201 | BP8: 1097.7901 | BQ8: 1240.1624 | BR8: 0 | BS8: 0 | BT8: 0 | BU8: 0 | BV8: 104.19137 | BW8: 105.49164 | BX8: 97.992603 | BY8: 100.71815 | BZ8: 159.31503 | CA8: 6.820554 | CB8: 5.804 | CC8: 3.143 | CD8: 552.325 | CE8: 40.84 | CF8: 0 | CG8: 121.01 | CH8: 121.01 | CI8: 0 | CJ8: 15.21 | CK8: 177.26 | CL8: 0.2 | CM8: 313.523 | CN8: 313.523 | CO8: 3 | CP8: 4 | CQ8: 0.5 | CR8: 0.3 | CS8: 0.6 | CT8: 0.8 | CU8: 0.8 | CV8: 0.7 | CW8: 0.5 | CX8: 0.5 | CY8: 1 | CZ8: 0.3 | DA8: 0.8 | DB8: 0.63361676 | DC8: 7.124 | DD8: 5.575 | DE8: 12.80265 | DF8: 20.150722 | DG8: 21.618691 | DH8: 17.272059 | DI8: 20.40463 | DJ8: 6.831 | DK8: 5.975 | DL8: 12.5643 | DM8: 14.11517 | DN8: 14.11517 | DO8: 0.0535
A9: ARG | B9: Argentina | C9: 0.005 | D9: 0.005 | E9: 0.01 | F9: 0.005 | G9: 0.005 | H9: 0.01 | I9: 0.005 | J9: 0.005 | K9: 0.01 | L9: 0.01 | M9: 0.005 | N9: 3.013924 | O9: 1.427653 | P9: 49.865627 | Q9: 16.495317 | R9: 2.5698504 | S9: 1.939133 | T9: 1.6714709 | U9: 0.096787 | V9: 0.090456 | W9: 0.07618 | X9: 7.3222096 | Y9: 7.3222096 | Z9: 28.04 | AA9: 2.59 | AB9: 4.5 | AC9: 3.6 | AD9: 0.20358314 | AE9: 169.164 | AF9: 21.679507 | AG9: 20.019167 | AH9: 20.739857 | AI9: 20.470239 | AJ9: 66.214919 | AK9: 0 | AL9: 0 | AM9: 0 | AN9: 0 | AO9: 284.36721 | AP9: 296.81962 | AQ9: 307.50512 | AR9: 303.50756 | AS9: 282.98121 | AT9: 292.07607 | AU9: 346.24293 | AV9: 280.94466 | AW9: 162.24679 | AX9: 172.65843 | AY9: 198.53345 | AZ9: 161.06134 | BA9: 224.38993 | BB9: 233.17949 | BC9: 275.96728 | BD9: 254.842 | BE9: 8.6041301 | BF9: 9.5794964 | BG9: 9.9243583 | BH9: 9.7953417 | BI9: 51.22736 | BJ9: 56.513731 | BK9: 58.548225 | BL9: 57.787099 | BM9: 477.05652 | BN9: 474.62498 | BO9: 491.71148 | BP9: 485.31923 | BQ9: 548.04669 | BR9: 419.69659 | BS9: 424.62073 | BT9: 439.90708 | BU9: 434.18828 | BV9: 250.88375 | BW9: 355.80849 | BX9: 260.51761 | BY9: 258.29935 | BZ9: 123.67444 | CA9: 2.4839869 | CB9: 4.367 | CC9: 3.5 | CD9: 637.234 | CE9: 39.96 | CF9: 1.34 | CG9: 89.41 | CH9: 82.15 | CI9: 5.92 | CJ9: 5.14 | CK9: 153.13 | CL9: 18.62 | CM9: 370.869 | CN9: 404.174 | CO9: 3 | CP9: 4 | CQ9: 0.5 | CR9: 0.3 | CS9: 0.6 | CT9: 0.8 | CU9: 0.8 | CV9: 0.7 | CW9: 0.5 | CX9: 0.5 | CY9: 1 | CZ9: 0.3 | DA9: 0.8 | DB9: 0.45758351 | DC9: 7.084 | DD9: 5.538 | DE9: 14.66641 | DF9: 18.677931 | DG9: 26.158616 | DH9: 18.206657 | DI9: 23.87845 | DJ9: 8.851 | DK9: 8.117 | DL9: 16.04097 | DM9: 13.494746 | DN9: 13.494746 | DO9: 0.12688
A10: ARM | B10: Armenia | C10: 0.005 | D10: 0.005 | E10: 0.01 | F10: 0.005 | G10: 0.005 | H10: 0.01 | I10: 0.005 | J10: 0.005 | K10: 0.01 | L10: 0.01 | M10: 0.005 | N10: 0 | O10: 0 | P10: 110.46447 | Q10: 35.945064 | R10: 10.869426 | S10: 0 | T10: 0 | U10: 0 | V10: 0 | W10: 0.233965 | X10: 0 | Y10: 0 | Z10: 1.83 | AA10: 0.71 | AB10: 0 | AC10: 0 | AD10: 0 | AE10: 6.321 | AF10: 0 | AG10: 0 | AH10: 0 | AI10: 0 | AJ10: 0 | AK10: 0.43815234 | AL10: 0.47745849 | AM10: 0.42347644 | AN10: 0.41594797 | AO10: 6.2995877 | AP10: 7.0043308 | AQ10: 6.2124126 | AR10: 6.1019697 | AS10: 14.697592 | AT10: 15.268401 | AU10: 14.877927 | AV10: 14.566524 | AW10: 7.2559988 | AX10: 7.5654387 | AY10: 7.3529105 | AZ10: 7.1941531 | BA10: 8.3253067 | BB10: 8.8320255 | BC10: 9.8408222 | BD10: 8.6234374 | BE10: 0 | BF10: 0 | BG10: 0 | BH10: 0 | BI10: 0.015448541 | BJ10: 0.01629676 | BK10: 0.014454228 | BL10: 0.014197264 | BM10: 27.872303 | BN10: 31.001194 | BO10: 27.496161 | BP10: 27.00734 | BQ10: 27.288838 | BR10: 30.732598 | BS10: 34.167951 | BT10: 30.304881 | BU10: 29.766128 | BV10: 4.610282 | BW10: 4.9286383 | BX10: 4.3840409 | BY10: 4.2995413 | BZ10: 6.0982196 | CA10: 0.29072771 | CB10: 7.162 | CC10: 5.3 | CD10: 25.955 | CE10: 4.58 | CF10: 0 | CG10: 3.31 | CH10: 3.31 | CI10: 0 | CJ10: 0.73 | CK10: 8.62 | CL10: 0 | CM10: 9.564 | CN10: 9.609 | CO10: 3 | CP10: 3 | CQ10: 0.5 | CR10: 0.3 | CS10: 0.6 | CT10: 0.8 | CU10: 0.8 | CV10: 0.7 | CW10: 0.5 | CX10: 0.5 | CY10: 1 | CZ10: 0.3 | DA10: 0.8 | DB10: 0.37443917 | DC10: 7.123 | DD10: 4.35 | DE10: 13.1604 | DF10: 22.591653 | DG10: 24.818429 | DH10: 15.656115 | DI10: 19.917929 | DJ10: 3.922 | DK10: 2.599 | DL10: 14.2368 | DM10: 13.494746 | DN10: 13.494746 | DO10: 0.105
A11: ATG | B11: Antigua and Barbuda | C11: 0.005 | D11: 0.005 | E11: 0.01 | F11: 0.005 | G11: 0.005 | H11: 0.01 | I11: 0.005 | J11: 0.005 | K11: 0.01 | L11: 0.01 | M11: 0.005 | N11: 0 | O11: 0 | P11: 0 | Q11: 0 | R11: 0 | S11: 0 | T11: 0 | U11: 0 | V11: 0 | W11: 0 | X11: 0 | Y11: 0 | Z11: 0 | AA11: 0.02 | AB11: 0 | AC11: 0 | AD11: 0 | AE11: 0.265 | AF11: 0 | AG11: 0 | AH11: 0 | AI11: 0 | AJ11: 0 | AK11: 0 | AL11: 0 | AM11: 0 | AN11: 0 | AO11: 1.1188831 | AP11: 1.0971911 | AQ11: 1.0971911 | AR11: 1.0971911 | AS11: 0.79426344 | AT11: 0.72071998 | AU11: 0.75737729 | AV11: 0.77527325 | AW11: 0.40605478 | AX11: 0.37368001 | AY11: 0.38719731 | AZ11: 0.39634634 | BA11: 2.5765006 | BB11: 2.5245264 | BC11: 2.5245264 | BD11: 2.5245264 | BE11: 0 | BF11: 0 | BG11: 0 | BH11: 0 | BI11: 0.14565821 | BJ11: 0.14225196 | BK11: 0.14225196 | BL11: 0.14225196 | BM11: 0 | BN11: 0 | BO11: 0 | BP11: 0 | BQ11: 0 | BR11: 0 | BS11: 0 | BT11: 0 | BU11: 0 | BV11: 8.7579207 | BW11: 8.9060002 | BX11: 8.8004983 | BY11: 8.6980354 | BZ11: 0.33342173 | CA11: 0.7979408 | CB11: 3.039 | CC11: 2.593 | CD11: 2.162 | CE11: 0 | CF11: 0 | CG11: 0.34 | CH11: 0 | CI11: 0.34 | CJ11: 0.03 | CK11: 0.37 | CL11: 0 | CM11: 0.348 | CN11: 0.348 | CO11: 3 | CP11: 4 | CQ11: 0.5 | CR11: 0.3 | CS11: 0.6 | CT11: 0.8 | CU11: 0.8 | CV11: 0.7 | CW11: 0.5 | CX11: 0.5 | CY11: 1 | CZ11: 0.3 | DA11: 0.8 | DB11: 0.69139751 | DC11: 7.124 | DD11: 5.575 | DE11: 14.02195 | DF11: 18.15336 | DG11: 24.677907 | DH11: 15.046824 | DI11: 23.296092 | DJ11: 12.771 | DK11: 11.447 | DL11: 23.8188 | DM11: 13.833596 | DN11: 13.833596 | DO11: 0.105
A12: AUS | B12: Australia | C12: 0.005 | D12: 0.005 | E12: 0.01 | F12: 0.005 | G12: 0.005 | H12: 0.01 | I12: 0.005 | J12: 0.005 | K12: 0.01 | L12: 0.01 | M12: 0.005 | N12: 1.190358 | O12: 1.043582 | P12: 69.0966 | Q12: 5.1478488 | R12: 0.61624708 | S12: 1.7170863 | T12: 0.96513967 | U12: 0.08416 | V12: 0.125549 | W12: 0.070985 | X12: 2.9574088 | Y12: 2.9574088 | Z12: 49.98 | AA12: 41.07 | AB12: 16.35 | AC12: 2 | AD12: 2.4366232 | AE12: 386.813 | AF12: 133.10116 | AG12: 142.25672 | AH12: 160.48854 | AI12: 171.37883 | AJ12: 191.87821 | AK12: 5.339981 | AL12: 5.7206635 | AM12: 6.4538314 | AN12: 6.89177 | AO12: 795.29654 | AP12: 633.55801 | AQ12: 714.75566 | AR12: 763.25693 | AS12: 683.43298 | AT12: 542.86558 | AU12: 625.31001 | AV12: 693.63125 | AW12: 295.9883 | AX12: 236.088 | AY12: 270.7995 | AZ12: 300.42873 | BA12: 636.10535 | BB12: 626.69484 | BC12: 471.61596 | BD12: 616.6296 | BE12: 0 | BF12: 0 | BG12: 0 | BH12: 0 | BI12: 18.966258 | BJ12: 15.176565 | BK12: 17.121615 | BL12: 18.283438 | BM12: 732.51329 | BN12: 638.66891 | BO12: 720.52158 | BP12: 769.41411 | BQ12: 1294.2956 | BR12: 264.40532 | BS12: 221.98472 | BT12: 250.43458 | BU12: 267.42835 | BV12: 1292.4161 | BW12: 663.18269 | BX12: 1076.7206 | BY12: 1216.1481 | BZ12: 272.06147 | CA12: 2.2221613 | CB12: 1.971 | CC12: 2.009 | CD12: 1799.418 | CE12: 15.25 | CF12: 122.31 | CG12: 175.72 | CH12: 47.05 | CI12: 6.36 | CJ12: 56.42 | CK12: 286.68 | CL12: 39.29 | CM12: 517.295 | CN12: 464.132 | CO12: 1 | CP12: 4 | CQ12: 0.5 | CR12: 0.3 | CS12: 0.6 | CT12: 0.8 | CU12: 0.8 | CV12: 0.7 | CW12: 0.5 | CX12: 0.5 | CY12: 1 | CZ12: 0.3 | DA12: 0.8 | DB12: 0.9433473 | DC12: 3.54 | DD12: 2.199 | DE12: 6.0962 | DF12: 20.015208 | DG12: 22.570113 | DH12: 17.272059 | DI12: 20.676084 | DJ12: 9.928 | DK12: 8.604 | DL12: 19.657 | DM12: 14.11517 | DN12: 14.11517 | DO12: 0.0502
A13: AUT | B13: Austria | C13: 0.005 | D13: 0.005 | E13: 0.01 | F13: 0.005 | G13: 0.005 | H13: 0.01 | I13: 0.005 | J13: 0.005 | K13: 0.01 | L13: 0.01 | M13: 0.005 | N13: 2.58947 | O13: 0.002993 | P13: 70.933532 | Q13: 3.8884907 | R13: 0.92957511 | S13: 9.3154411 | T13: 14.158356 | U13: 0.444925 | V13: 0.084597 | W13: 0.189354 | X13: 4.3931055 | Y13: 4.3931055 | Z13: 5.53 | AA13: 10.3 | AB13: 4.29 | AC13: 0 | AD13: 0 | AE13: 64.767 | AF13: 30.659459 | AG13: 35.65929 | AH13: 34.720482 | AI13: 34.546879 | AJ13: 21.973551 | AK13: 0.56760499 | AL13: 0.61290565 | AM13: 0.59676959 | AN13: 0.59378574 | AO13: 242.12657 | AP13: 245.4685 | AQ13: 239.00601 | AR13: 237.81098 | AS13: 150.83903 | AT13: 155.26115 | AU13: 151.80397 | AV13: 159.05403 | AW13: 74.620741 | AX13: 76.770421 | AY13: 75.058206 | AZ13: 78.718035 | BA13: 61.987544 | BB13: 62.663003 | BC13: 65.247809 | BD13: 60.708202 | BE13: 0 | BF13: 0 | BG13: 0 | BH13: 0 | BI13: 1.4977283 | BJ13: 1.3521004 | BK13: 1.3165035 | BL13: 1.3099209 | BM13: 147.38072 | BN13: 126.4956 | BO13: 123.16533 | BP13: 122.5495 | BQ13: 45.448626 | BR13: 111.32428 | BS13: 99.013277 | BT13: 96.406539 | BU13: 95.924506 | BV13: 90.741135 | BW13: 101.80683 | BX13: 87.086631 | BY13: 86.629987 | BZ13: 62.627715 | CA13: 1.7776756 | CB13: 0.616 | CC13: 0.682 | CD13: 534.63 | CE13: 42.59 | CF13: 0 | CG13: 12.07 | CH13: 8.8 | CI13: 3.27 | CJ13: 10.29 | CK13: 73.26 | CL13: 8.31 | CM13: 76.658 | CN13: 66.129 | CO13: 1 | CP13: 4 | CQ13: 0.5 | CR13: 0.3 | CS13: 0.6 | CT13: 0.8 | CU13: 0.8 | CV13: 0.7 | CW13: 0.5 | CX13: 0.5 | CY13: 1 | CZ13: 0.3 | DA13: 0.8 | DB13: 0.79456705 | DC13: 19.923 | DD13: 12.129 | DE13: 13.1628 | DF13: 22.892711 | DG13: 24.837588 | DH13: 15.656115 | DI13: 21.258713 | DJ13: 15.793 | DK13: 15.793 | DL13: 35.6736 | DM13: 13.494746 | DN13: 13.494746 | DO13: 0.0611
A14: AZE | B14: Azerbaijan | C14: 0.005 | D14: 0.005 | E14: 0.01 | F14: 0.005 | G14: 0.005 | H14: 0.01 | I14: 0.005 | J14: 0.005 | K14: 0.01 | L14: 0.01 | M14: 0.005 | N14: 0.502491 | O14: 0 | P14: 154.22811 | Q14: 15.019953 | R14: 4.4558238 | S14: 0 | T14: 0 | U14: 0.498989 | V14: 0 | W14: 0.475882 | X14: 19.478961 | Y14: 19.478961 | Z14: 7.14 | AA14: 0.28 | AB14: 0.06 | AC14: 2.4 | AD14: 0 | AE14: 36.957 | AF14: 0 | AG14: 0 | AH14: 0 | AI14: 0 | AJ14: 0 | AK14: 0 | AL14: 0 | AM14: 0 | AN14: 0 | AO14: 37.18601 | AP14: 40.814572 | AQ14: 40.916609 | AR14: 40.302859 | AS14: 50.072952 | AT14: 48.333244 | AU14: 44.77389 | AV14: 48.315361 | AW14: 26.462479 | AX14: 25.057081 | AY14: 23.657416 | AZ14: 25.535217 | BA14: 60.014661 | BB14: 61.78799 | BC14: 67.943534 | BD14: 61.013323 | BE14: 0 | BF14: 0 | BG14: 0 | BH14: 0 | BI14: 0.4547157 | BJ14: 0.38918396 | BK14: 0.39015692 | BL14: 0.38430457 | BM14: 46.780823 | BN14: 45.338045 | BO14: 45.45139 | BP14: 44.769619 | BQ14: 223.39477 | BR14: 160.06272 | BS14: 158.06997 | BT14: 158.46515 | BU14: 156.08817 | BV14: 35.146201 | BW14: 42.267488 | BX14: 39.513881 | BY14: 37.525411 | BZ14: 21.259842 | CA14: 1.0506312 | CB14: 1.4 | CC14: 2.217 | CD14: 74.426 | CE14: 2.63 | CF14: 0 | CG14: 24.74 | CH14: 24.64 | CI14: 0.1 | CJ14: 0 | CK14: 27.34 | CL14: 0.09 | CM14: 70.588 | CN14: 68.695 | CO14: 3 | CP14: 3 | CQ14: 0.5 | CR14: 0.3 | CS14: 0.6 | CT14: 0.8 | CU14: 0.8 | CV14: 0.7 | CW14: 0.5 | CX14: 0.5 | CY14: 1 | CZ14: 0.3 | DA14: 0.8 | DB14: 0.29009199 | DC14: 7.124 | DD14: 4.351 | DE14: 12.94342 | DF14: 21.12023 | DG14: 24.416767 | DH14: 15.656115 | DI14: 21.01193 | DJ14: 5.56 | DK14: 4.794 | DL14: 11.98054 | DM14: 13.494746 | DN14: 13.494746 | DO14: 0.0914
A15: BDI | B15: Burundi | C15: 0.005 | D15: 0.005 | E15: 0.01 | F15: 0.005 | G15: 0.005 | H15: 0.01 | I15: 0.005 | J15: 0.005 | K15: 0.01 | L15: 0.01 | M15: 0.005 | N15: 0.000803 | O15: 0.018305 | P15: 0.160135 | Q15: 0.14245805 | R15: 0.02942544 | S15: 0.025484234 | T15: 0.0066719192 | U15: 2.6e-05 | V15: 3.9e-05 | W15: 0.000166 | X15: 0.00058131722 | Y15: 0.00058131722 | Z15: 0.05 | AA15: 0.01 | AB15: 0 | AC15: 0 | AD15: 0 | AE15: 0.926 | AF15: 0.33424861 | AG15: 0.3065039 | AH15: 0.31603958 | AI15: 0.30761186 | AJ15: 0 | AK15: 0.13001254 | AL15: 0.12476162 | AM15: 0.12864309 | AN15: 0.12521261 | AO15: 4.0858194 | AP15: 3.98425 | AQ15: 4.1082045 | AR15: 3.9986524 | AS15: 0.68631028 | AT15: 0.55089914 | AU15: 0.5911875 | AV15: 0.6085641 | AW15: 0.63196983 | AX15: 0.50949169 | AY15: 0.54437865 | AZ15: 0.56037941 | BA15: 4.9692873 | BB15: 4.911011 | BC15: 5.0847649 | BD15: 4.9389567 | BE15: 8.6712558e-05 | BF15: 8.5895e-05 | BG15: 8.8567289e-05 | BH15: 8.6205495e-05 | BI15: 9.6844116e-05 | BJ15: 9.218e-05 | BK15: 9.5047822e-05 | BL15: 9.2513214e-05 | BM15: 0 | BN15: 0 | BO15: 0 | BP15: 0 | BQ15: 0 | BR15: 0 | BS15: 0 | BT15: 0 | BU15: 0 | BV15: 1.3103423 | BW15: 1.3392922 | BX15: 1.3040643 | BY15: 1.2673099 | BZ15: 0.36618892 | CA15: 2.093145 | CB15: 3.904 | CC15: 3.819 | CD15: 4.838 | CE15: 0.37 | CF15: 0 | CG15: 0.12 | CH15: 0 | CI15: 0.12 | CJ15: 0 | CK15: 0.49 | CL15: 0 | CM15: 7.661 | CN15: 10.53 | CO15: 3 | CP15: 1 | CQ15: 0.5 | CR15: 0.3 | CS15: 0.6 | CT15: 0.8 | CU15: 0.8 | CV15: 0.7 | CW15: 0.5 | CX15: 0.5 | CY15: 1 | CZ15: 0.3 | DA15: 0.8 | DB15: 0.35935527 | DC15: 7.124 | DD15: 5.575 | DE15: 14.38774 | DF15: 23.675225 | DG15: 24.430265 | DH15: 18.474215 | DI15: 23.481277 | DJ15: 12.794 | DK15: 11.471 | DL15: 24.46848 | DM15: 13.494746 | DN15: 13.494746 | DO15: 0.105
... A189: ZWE | B189: Zimbabwe | C189: 0.005 | D189: 0.005 | E189: 0.01 | F189: 0.005 | G189: 0.005 | H189: 0.01 | I189: 0.005 | J189: 0.005 | K189: 0.01 | L189: 0.01 | M189: 0.005 | N189: 0.00447 | O189: 0.195791 | P189: 0.428912 | Q189: 0.03311419 | R189: 0.0063769419 | S189: 0.024557053 | T189: 0.0081459479 | U189: 0.000194 | V189: 4.4e-05 | W189: 0.001004 | X189: 0.0087306009 | Y189: 0.0087306009 | Z189: 1.68 | AA189: 0.1 | AB189: 0 | AC189: 3 | AD189: 0 | AE189: 9.654 | AF189: 10.660507 | AG189: 10.615238 | AH189: 10.976156 | AI189: 10.471253 | AJ189: 43.407831 | AK189: 5.0368661 | AL189: 5.0105152 | AM189: 5.1808727 | AN189: 4.9425526 | AO189: 11.75872 | AP189: 12.043912 | AQ189: 12.453405 | AR189: 11.880548 | AS189: 25.291965 | AT189: 20.80292 | AU189: 22.138708 | AV189: 24.127047 | AW189: 11.020982 | AX189: 9.0724397 | AY189: 9.6469496 | AZ189: 10.513369 | BA189: 8.9108605 | BB189: 8.0534818 | BC189: 11.116722 | BD189: 9.1788625 | BE189: 2.3400702 | BF189: 2.2879515 | BG189: 2.3657418 | BH189: 2.2569177 | BI189: 2.8095945 | BJ189: 2.6882202 | BK189: 2.7796197 | BL189: 2.6517572 | BM189: 0 | BN189: 0 | BO189: 0 | BP189: 0 | BQ189: 0 | BR189: 0 | BS189: 0 | BT189: 0 | BU189: 0 | BV189: 25.704508 | BW189: 26.157899 | BX189: 29.348961 | BY189: 26.821839 | BZ189: 10.08693 | CA189: -4.5322585 | CB189: 7.54 | CC189: 4.972 | CD189: 49.154 | CE189: 5.82 | CF189: 4.4 | CG189: 4.4 | CH189: 0 | CI189: 0 | CJ189: 0.04 | CK189: 10.26 | CL189: 0 | CM189: 30.23 | CN189: 113.046 | CO189: 3 | CP189: 1 | CQ189: 0.5 | CR189: 0.3 | CS189: 0.6 | CT189: 0.8 | CU189: 0.8 | CV189: 0.7 | CW189: 0.5 | CX189: 0.5 | CY189: 1 | CZ189: 0.3 | DA189: 0.8 | DB189: 0.39214654 | DC189: 3.374 | DD189: 2.051 | DE189: 6.138345 | DF189: 20.528224 | DG189: 22.348436 | DH189: 17.528199 | DI189: 22.784798 | DJ189: 12.782 | DK189: 11.458 | DL189: 23.72898 | DM189: 14.368824 | DN189: 14.368824 | DO189: 0.105

Sheet PyKey
A1: Python results for the key rows (values; Check sheet reads these)
A2: key | B2: iso | C2: code | D2: 2024 | E2: 2025 | F2: 2030 | G2: 2040 | H2: 2050
A3: ABW|mit.gdp.lvl | B3: ABW | C3: mit.gdp.lvl | D3: 4.285 | E3: 4.5253028 | F3: 5.0313793 | G3: 5.9792286 | H3: 6.9391389
A4: AFG|mit.gdp.lvl | B4: AFG | C4: mit.gdp.lvl | D4: 17.817 | E4: 18.352223 | F4: 21.497373 | G4: 31.874649 | H4: 49.500355
A5: AGO|mit.gdp.lvl | B5: AGO | C5: mit.gdp.lvl | D5: 119.574 | E5: 123.31667 | F5: 139.77737 | G5: 196.23928 | H5: 290.48207
A6: ALB|mit.gdp.lvl | B6: ALB | C6: mit.gdp.lvl | D6: 27.084 | E6: 28.087462 | F6: 33.118964 | G6: 45.080336 | H6: 60.584201
A7: ARE|mit.gdp.lvl | B7: ARE | C7: mit.gdp.lvl | D7: 552.325 | E7: 584.38194 | F7: 674.44367 | G7: 824.36639 | H7: 956.71085
A8: ARG|mit.gdp.lvl | B8: ARG | C8: mit.gdp.lvl | D8: 637.234 | E8: 665.06201 | F8: 779.03512 | G8: 962.94617 | H8: 1117.5383
A9: ARM|mit.gdp.lvl | B9: ARM | C9: mit.gdp.lvl | D9: 25.955 | E9: 27.813897 | F9: 35.449659 | G9: 51.168144 | H9: 68.765707
A10: ATG|mit.gdp.lvl | B10: ATG | C10: mit.gdp.lvl | D10: 2.162 | E10: 2.2277032 | F10: 2.5126806 | G10: 3.0185157 | H10: 3.5031107
A11: AUS|mit.gdp.lvl | B11: AUS | C11: mit.gdp.lvl | D11: 1799.418 | E11: 1834.8845 | F11: 2019.5401 | G11: 2381.8003 | H11: 2764.1765
A12: AUT|mit.gdp.lvl | B12: AUT | C12: mit.gdp.lvl | D12: 534.63 | E12: 537.92332 | F12: 559.75462 | G12: 632.9763 | H12: 734.59484
A13: AZE|mit.gdp.lvl | B13: AZE | C13: mit.gdp.lvl | D13: 74.426 | E13: 75.467964 | F13: 84.674493 | G13: 111.04389 | H13: 149.2337
... A2978: ZWE|mit.ic.c | B2978: ZWE | C2978: mit.ic.c | D2978: 0 | E2978: 0.74665912 | F2978: 4.4655633 | G2978: 4.5303426 | H2978: 4.6091946
