Workbook

Sheet README
B1: Mitigation (Net Zero) Investment Needs Model v1.1
B4: What it does
B5: Estimates, for every economy with IMF WEO GDP (195 economies) and seven mitigation sectors, the 2030 total and incremental investment need and its incremental cost under three lenses: (a) market cost of capital, (b) the World Bank rate (6%), and (c) the World Bank rate with local co-benefits. All cells recalculate from the Inputs sheet.
B7: Method (equation numbers follow the SISEPUEDE method note)
B8: 1. Totals. Group pools for 2030 (advanced economies, China, other EMDCs) come from IHLEG (2024) and IEA-IFC (2023); clean energy is split into sectors with the IEA-IFC shares; AFOLU uses IHLEG and UNEP (Inputs, Sector_Params).
B9: 2. Allocation (eq. 1/3, Tier 3 of the note). Each group-sector pool is shared across its countries in proportion to w = [beta x physical-driver share + (1 - beta) x PPP GDP share] x price level^phi. Drivers come from IMF CPAT 2024: electricity demand (power, grids), road fuel (transport), building and industrial energy use, fossil supply (fuels), non-CO2 GHG plus net LULUCF source (AFOLU). Countries without CPAT data use GDP only.
B10: 3. Incremental investment (eq. 2): dI = I x incremental share (AE/China 0.38 from McKinsey 2022; EMDC 0.24 from CCDR vs IHLEG).
B11: 4. Capital charge (eq. 4): A = dI x CRF(r, n), CRF = r / (1 - (1 + r)^-n), asset life n by sector.
B12: 5. Cost of capital (eq. 5). Lens (a) uses a country WACC: the average of observed RE WACC (IRENA 2021, converted to nominal; Steffen et al. 2025) where available; else a Damodaran-based WACC, D/V(rf + default spread)(1 - tax) + E/V(rf + beta x ERP + lambda x CRP), shifted to the observed level; else the IHLEG group rate (AE 5.5%, China 6%, EMDC 10.5%). The high case adds the group gap to 7% / 8% / 15%. Lens (b)/(c) use 6% (or IBRD ~5.2% by switch).
B13: 6. Savings, co-benefits and abatement (eq. 6-7), v1.1. Power generation and transport use engineering parameters: renewable output per dollar displaces the country's fossil generation mix (Ember) at CPAT 2024 fuel supply costs and air-pollution costs, with heat rates and IPCC 2006 CO2 factors; EVs replace gasoline cars (fuel, power and maintenance per vehicle over the purchase premium). Grids carry no benefits of their own (switch p_grid_credit). Low-emission fuels and AFOLU are costed per tonne (USD 100/t and 50/t). Buildings and industry keep the calibrated b = 0.133 and c = 0.129 (SISEPUEDE LAC) scaled by CPAT country indices relative to the investment-weighted world average.
B14: 7. Incremental cost: (a) = CRF(WACC) x dI - savings; (b) = CRF(6%) x dI - savings; (c) = (b) - local co-benefits. Memo lines add avoided emissions (a x dI) at the World Bank shadow price of carbon. Positive = net cost.
B15: 8. PIMA. PIMA-adjusted investment = I x [(1 - public share) + public share / (1 - efficiency gap)]. The gap is mapped from the PEFA PI-11 score where available, otherwise the IMF (2015) income-group gap; the reform switch closes two-thirds of it.
... B32: - Build: python InvestmentNeeds/build/build_investment_model.py (reads only repo files).

Sheet Results_Summary
A1: Mitigation (net zero) investment needs and incremental cost, 2030
A2: USD bn a year, 2023 prices. Flows are annual over the asset life of one year's 2030 investment (as in the method note, Tables 6-7). Incremental cost > 0 is a net cost; < 0 a net saving.
A4: Item | B4: AE | C4: China | D4: EMDC | E4: World
A5: Total investment need, I | B5: =SUMIFS(Calc!$J$5:$J$1369,Calc!$B$5:$B$1369,"AE") -> 2385.9844 | C5: =SUMIFS(Calc!$J$5:$J$1369,Calc!$B$5:$B$1369,"China") -> 863.01562 | D5: =SUMIFS(Calc!$J$5:$J$1369,Calc!$B$5:$B$1369,"EMDC") -> 1950 | E5: =SUM(B5:D5) -> 5199
A6: Incremental investment need, dI | B6: =SUMIFS(Calc!$L$5:$L$1369,Calc!$B$5:$B$1369,"AE") -> 906.67406 | C6: =SUMIFS(Calc!$L$5:$L$1369,Calc!$B$5:$B$1369,"China") -> 327.94594 | D6: =SUMIFS(Calc!$L$5:$L$1369,Calc!$B$5:$B$1369,"EMDC") -> 468 | E6: =SUM(B6:D6) -> 1702.62
A7: Savings on dI (fuel and operating) | B7: =SUMIFS(Calc!$W$5:$W$1369,Calc!$B$5:$B$1369,"AE") -> 59.028123 | C7: =SUMIFS(Calc!$W$5:$W$1369,Calc!$B$5:$B$1369,"China") -> 17.58997 | D7: =SUMIFS(Calc!$W$5:$W$1369,Calc!$B$5:$B$1369,"EMDC") -> 24.509441 | E7: =SUM(B7:D7) -> 101.12753
A8: Local co-benefits on dI | B8: =SUMIFS(Calc!$X$5:$X$1369,Calc!$B$5:$B$1369,"AE") -> 17.36481 | C8: =SUMIFS(Calc!$X$5:$X$1369,Calc!$B$5:$B$1369,"China") -> 36.459082 | D8: =SUMIFS(Calc!$X$5:$X$1369,Calc!$B$5:$B$1369,"EMDC") -> 26.573732 | E8: =SUM(B8:D8) -> 80.397624
A9: Capital charge on dI, lens (a) market | B9: =SUMIFS(Calc!$Z$5:$Z$1369,Calc!$B$5:$B$1369,"AE") -> 68.386404 | C9: =SUMIFS(Calc!$Z$5:$Z$1369,Calc!$B$5:$B$1369,"China") -> 21.957883 | D9: =SUMIFS(Calc!$Z$5:$Z$1369,Calc!$B$5:$B$1369,"EMDC") -> 50.45736 | E9: =SUM(B9:D9) -> 140.80165
A10: Capital charge on dI, lens (b) WB rate | B10: =SUMIFS(Calc!$AB$5:$AB$1369,Calc!$B$5:$B$1369,"AE") -> 74.412002 | C10: =SUMIFS(Calc!$AB$5:$AB$1369,Calc!$B$5:$B$1369,"China") -> 26.914979 | D10: =SUMIFS(Calc!$AB$5:$AB$1369,Calc!$B$5:$B$1369,"EMDC") -> 37.673327 | E10: =SUM(B10:D10) -> 139.00031
A11: INCREMENTAL COST (a) market cost of capital | B11: =SUMIFS(Calc!$AC$5:$AC$1369,Calc!$B$5:$B$1369,"AE") -> 9.3582809 | C11: =SUMIFS(Calc!$AC$5:$AC$1369,Calc!$B$5:$B$1369,"China") -> 4.3679123 | D11: =SUMIFS(Calc!$AC$5:$AC$1369,Calc!$B$5:$B$1369,"EMDC") -> 25.947919 | E11: =SUM(B11:D11) -> 39.674113
A12: INCREMENTAL COST (a) market, high case | B12: =SUMIFS(Calc!$AD$5:$AD$1369,Calc!$B$5:$B$1369,"AE") -> 19.454822 | C12: =SUMIFS(Calc!$AD$5:$AD$1369,Calc!$B$5:$B$1369,"China") -> 9.0549635 | D12: =SUMIFS(Calc!$AD$5:$AD$1369,Calc!$B$5:$B$1369,"EMDC") -> 44.366442 | E12: =SUM(B12:D12) -> 72.876228
A13: INCREMENTAL COST (b) World Bank rate | B13: =SUMIFS(Calc!$AE$5:$AE$1369,Calc!$B$5:$B$1369,"AE") -> 15.383879 | C13: =SUMIFS(Calc!$AE$5:$AE$1369,Calc!$B$5:$B$1369,"China") -> 9.3250089 | D13: =SUMIFS(Calc!$AE$5:$AE$1369,Calc!$B$5:$B$1369,"EMDC") -> 13.163886 | E13: =SUM(B13:D13) -> 37.872774
A14: INCREMENTAL COST (c) WB rate + local co-benefits | B14: =SUMIFS(Calc!$AF$5:$AF$1369,Calc!$B$5:$B$1369,"AE") -> -1.9809314 | C14: =SUMIFS(Calc!$AF$5:$AF$1369,Calc!$B$5:$B$1369,"China") -> -27.134073 | D14: =SUMIFS(Calc!$AF$5:$AF$1369,Calc!$B$5:$B$1369,"EMDC") -> -13.409846 | E14: =SUM(B14:D14) -> -42.52485
A15: memo: (c) + avoided carbon at SPC low | B15: =SUMIFS(Calc!$AG$5:$AG$1369,Calc!$B$5:$B$1369,"AE") -> -21.672504 | C15: =SUMIFS(Calc!$AG$5:$AG$1369,Calc!$B$5:$B$1369,"China") -> -37.199122 | D15: =SUMIFS(Calc!$AG$5:$AG$1369,Calc!$B$5:$B$1369,"EMDC") -> -29.707535 | E15: =SUM(B15:D15) -> -88.579161
A16: memo: (c) + avoided carbon at SPC high | B16: =SUMIFS(Calc!$AH$5:$AH$1369,Calc!$B$5:$B$1369,"AE") -> -41.364077 | C16: =SUMIFS(Calc!$AH$5:$AH$1369,Calc!$B$5:$B$1369,"China") -> -47.264171 | D16: =SUMIFS(Calc!$AH$5:$AH$1369,Calc!$B$5:$B$1369,"EMDC") -> -46.005224 | E16: =SUM(B16:D16) -> -134.63347
A17: Abatement from dI (MtCO2e/yr) | B17: =SUMIFS(Calc!$Y$5:$Y$1369,Calc!$B$5:$B$1369,"AE") -> 393.83146 | C17: =SUMIFS(Calc!$Y$5:$Y$1369,Calc!$B$5:$B$1369,"China") -> 201.30098 | D17: =SUMIFS(Calc!$Y$5:$Y$1369,Calc!$B$5:$B$1369,"EMDC") -> 325.95378 | E17: =SUM(B17:D17) -> 921.08623
A18: Cost-of-capital penalty on I, (a) less (b) | B18: =SUMIFS(Calc!$AM$5:$AM$1369,Calc!$B$5:$B$1369,"AE") -> -15.856837 | C18: =SUMIFS(Calc!$AM$5:$AM$1369,Calc!$B$5:$B$1369,"China") -> -13.044991 | D18: =SUMIFS(Calc!$AM$5:$AM$1369,Calc!$B$5:$B$1369,"EMDC") -> 53.266804 | E18: =SUM(B18:D18) -> 24.364976
A19: PIMA-adjusted total investment | B19: =SUMIFS(Calc!$AN$5:$AN$1369,Calc!$B$5:$B$1369,"AE") -> 2492.9423 | C19: =SUMIFS(Calc!$AN$5:$AN$1369,Calc!$B$5:$B$1369,"China") -> 1022.6144 | D19: =SUMIFS(Calc!$AN$5:$AN$1369,Calc!$B$5:$B$1369,"EMDC") -> 2261.7339 | E19: =SUM(B19:D19) -> 5777.2906
A20: PIMA-adjusted incremental investment | B20: =SUMIFS(Calc!$AO$5:$AO$1369,Calc!$B$5:$B$1369,"AE") -> 947.31807 | C20: =SUMIFS(Calc!$AO$5:$AO$1369,Calc!$B$5:$B$1369,"China") -> 388.59347 | D20: =SUMIFS(Calc!$AO$5:$AO$1369,Calc!$B$5:$B$1369,"EMDC") -> 542.81614 | E20: =SUM(B20:D20) -> 1878.7277
A21: GDP 2030 (USD bn, 2024 prices) | B21: =SUMIFS(Country_Data!$BV$5:$BV$199,Country_Data!$E$5:$E$199,"AE") -> 72737.664 | C21: =SUMIFS(Country_Data!$BV$5:$BV$199,Country_Data!$E$5:$E$199,"China") -> 24676.851 | D21: =SUMIFS(Country_Data!$BV$5:$BV$199,Country_Data!$E$5:$E$199,"EMDC") -> 33458.578 | E21: =SUM(B21:D21) -> 130873.09
A22: I, % of GDP | B22: =B5/B21 -> 0.032802598 | C22: =C5/C21 -> 0.034972681 | D22: =D5/D21 -> 0.058281018 | E22: =E5/E21 -> 0.039725507
A23: dI, % of GDP | B23: =B6/B21 -> 0.012464987 | C23: =C6/C21 -> 0.013289619 | D23: =D6/D21 -> 0.013987444 | E23: =E6/E21 -> 0.013009702
A24: Incremental cost (a), % of GDP | B24: =B11/B21 -> 0.00012865798 | C24: =C11/C21 -> 0.00017700445 | D24: =D11/D21 -> 0.00077552367 | E24: =E11/E21 -> 0.0003031495
A25: Incremental cost (b), % of GDP | B25: =B13/B21 -> 0.00021149812 | C25: =C13/C21 -> 0.00037788489 | D25: =D13/D21 -> 0.00039343831 | E25: =E13/E21 -> 0.00028938549
A26: Incremental cost (c), % of GDP | B26: =B14/B21 -> -2.7233916e-05 | C26: =C14/C21 -> -0.001099576 | D26: =D14/D21 -> -0.00040078946 | E26: =E14/E21 -> -0.00032493195
A27: Financial benefit-cost ratio on dI, lens (a) | B27: =B7/B9 -> 0.86315583 | C27: =C7/C9 -> 0.80107771 | D27: =D7/D9 -> 0.4857456 | E27: =E7/E9 -> 0.71822693
A28: Financial benefit-cost ratio on dI, lens (b) | B28: =B7/B10 -> 0.79326078 | C28: =C7/C10 -> 0.65353832 | D28: =D7/D10 -> 0.65057808 | E28: =E7/E10 -> 0.7275346
A29: Economic benefit-cost ratio on dI, lens (c) | B29: =(B7+B8)/B10 -> 1.0266211 | C29: =(C7+C8)/C10 -> 2.0081402 | D29: =(D7+D8)/D10 -> 1.3559507 | E29: =(E7+E8)/E10 -> 1.3059335
A30: Countries in group | B30: =COUNTIF(Country_Data!$E$5:$E$199,"AE") -> 41 | C30: =COUNTIF(Country_Data!$E$5:$E$199,"China") -> 1 | D30: =COUNTIF(Country_Data!$E$5:$E$199,"EMDC") -> 153 | E30: =SUM(B30:D30) -> 195
A32: Total-investment lens (method note Tables 6-7 framing: b and c applied to total I)
A33: Item | B33: AE | C33: China | D33: EMDC | E33: World
A34: Capital charge on I, (a) | B34: =SUMIFS(Calc!$AI$5:$AI$1369,Calc!$B$5:$B$1369,"AE") -> 179.96422 | C34: =SUMIFS(Calc!$AI$5:$AI$1369,Calc!$B$5:$B$1369,"China") -> 57.783902 | D34: =SUMIFS(Calc!$AI$5:$AI$1369,Calc!$B$5:$B$1369,"EMDC") -> 210.239 | E34: =SUM(B34:D34) -> 447.98712
A35: Capital charge on I, (b) | B35: =SUMIFS(Calc!$AJ$5:$AJ$1369,Calc!$B$5:$B$1369,"AE") -> 195.82106 | C35: =SUMIFS(Calc!$AJ$5:$AJ$1369,Calc!$B$5:$B$1369,"China") -> 70.828893 | D35: =SUMIFS(Calc!$AJ$5:$AJ$1369,Calc!$B$5:$B$1369,"EMDC") -> 156.9722 | E35: =SUM(B35:D35) -> 423.62214
A36: Financial savings on I | B36: =SUMIFS(Calc!$AK$5:$AK$1369,Calc!$B$5:$B$1369,"AE") -> 155.33717 | C36: =SUMIFS(Calc!$AK$5:$AK$1369,Calc!$B$5:$B$1369,"China") -> 46.289396 | D36: =SUMIFS(Calc!$AK$5:$AK$1369,Calc!$B$5:$B$1369,"EMDC") -> 102.12267 | E36: =SUM(B36:D36) -> 303.74923
A37: Co-benefits on I | B37: =SUMIFS(Calc!$AL$5:$AL$1369,Calc!$B$5:$B$1369,"AE") -> 45.696869 | C37: =SUMIFS(Calc!$AL$5:$AL$1369,Calc!$B$5:$B$1369,"China") -> 95.944952 | D37: =SUMIFS(Calc!$AL$5:$AL$1369,Calc!$B$5:$B$1369,"EMDC") -> 110.72388 | E37: =SUM(B37:D37) -> 252.3657
A38: Net financial benefit, (a) | B38: =B36-B34 -> -24.627055 | C38: =C36-C34 -> -11.494506 | D38: =D36-D34 -> -108.11633 | E38: =E36-E34 -> -144.23789
A39: Net financial benefit, (b) | B39: =B36-B35 -> -40.483892 | C39: =C36-C35 -> -24.539497 | D39: =D36-D35 -> -54.849527 | E39: =E36-E35 -> -119.87292
A40: Net benefit with co-benefits, (c) | B40: =B36-B35+B37 -> 5.2129774 | C40: =C36-C35+C37 -> 71.405454 | D40: =D36-D35+D37 -> 55.874357 | E40: =E36-E35+E37 -> 132.49279
A42: Investment by sector and group (USD bn/yr)
A43: Sector | B43: I: AE | C43: I: China | D43: I: EMDC | E43: I: World | F43: dI: World | G43: Incr. cost (a) | H43: Incr. cost (b) | I43: Incr. cost (c)
A44: Power generation (low-emission) | B44: =SUMIFS(Calc!$J$5:$J$1369,Calc!$B$5:$B$1369,"AE",Calc!$C$5:$C$1369,"GEN") -> 822.5 | C44: =SUMIFS(Calc!$J$5:$J$1369,Calc!$B$5:$B$1369,"China",Calc!$C$5:$C$1369,"GEN") -> 297.5 | D44: =SUMIFS(Calc!$J$5:$J$1369,Calc!$B$5:$B$1369,"EMDC",Calc!$C$5:$C$1369,"GEN") -> 560 | E44: =SUM(B44:D44) -> 1680 | F44: =SUMIFS(Calc!$L$5:$L$1369,Calc!$C$5:$C$1369,"GEN") -> 560 | G44: =SUMIFS(Calc!$AC$5:$AC$1369,Calc!$C$5:$C$1369,"GEN") -> 12.690646 | H44: =SUMIFS(Calc!$AE$5:$AE$1369,Calc!$C$5:$C$1369,"GEN") -> 12.883419 | I44: =SUMIFS(Calc!$AF$5:$AF$1369,Calc!$C$5:$C$1369,"GEN") -> -9.9253832
A45: Grids and storage | B45: =SUMIFS(Calc!$J$5:$J$1369,Calc!$B$5:$B$1369,"AE",Calc!$C$5:$C$1369,"GRID") -> 564 | C45: =SUMIFS(Calc!$J$5:$J$1369,Calc!$B$5:$B$1369,"China",Calc!$C$5:$C$1369,"GRID") -> 204 | D45: =SUMIFS(Calc!$J$5:$J$1369,Calc!$B$5:$B$1369,"EMDC",Calc!$C$5:$C$1369,"GRID") -> 384 | E45: =SUM(B45:D45) -> 1152 | F45: =SUMIFS(Calc!$L$5:$L$1369,Calc!$C$5:$C$1369,"GRID") -> 384 | G45: =SUMIFS(Calc!$AC$5:$AC$1369,Calc!$C$5:$C$1369,"GRID") -> 25.368987 | H45: =SUMIFS(Calc!$AE$5:$AE$1369,Calc!$C$5:$C$1369,"GRID") -> 25.52123 | I45: =SUMIFS(Calc!$AF$5:$AF$1369,Calc!$C$5:$C$1369,"GRID") -> 25.52123
A46: Transport (EVs, charging, transit) | B46: =SUMIFS(Calc!$J$5:$J$1369,Calc!$B$5:$B$1369,"AE",Calc!$C$5:$C$1369,"TRN") -> 348.975 | C46: =SUMIFS(Calc!$J$5:$J$1369,Calc!$B$5:$B$1369,"China",Calc!$C$5:$C$1369,"TRN") -> 126.225 | D46: =SUMIFS(Calc!$J$5:$J$1369,Calc!$B$5:$B$1369,"EMDC",Calc!$C$5:$C$1369,"TRN") -> 237.6 | E46: =SUM(B46:D46) -> 712.8 | F46: =SUMIFS(Calc!$L$5:$L$1369,Calc!$C$5:$C$1369,"TRN") -> 237.6 | G46: =SUMIFS(Calc!$AC$5:$AC$1369,Calc!$C$5:$C$1369,"TRN") -> -2.4392558 | H46: =SUMIFS(Calc!$AE$5:$AE$1369,Calc!$C$5:$C$1369,"TRN") -> -2.3297431 | I46: =SUMIFS(Calc!$AF$5:$AF$1369,Calc!$C$5:$C$1369,"TRN") -> -7.9000777
A47: Buildings (efficiency, heat pumps) | B47: =SUMIFS(Calc!$J$5:$J$1369,Calc!$B$5:$B$1369,"AE",Calc!$C$5:$C$1369,"BLD") -> 271.425 | C47: =SUMIFS(Calc!$J$5:$J$1369,Calc!$B$5:$B$1369,"China",Calc!$C$5:$C$1369,"BLD") -> 98.175 | D47: =SUMIFS(Calc!$J$5:$J$1369,Calc!$B$5:$B$1369,"EMDC",Calc!$C$5:$C$1369,"BLD") -> 184.8 | E47: =SUM(B47:D47) -> 554.4 | F47: =SUMIFS(Calc!$L$5:$L$1369,Calc!$C$5:$C$1369,"BLD") -> 184.8 | G47: =SUMIFS(Calc!$AC$5:$AC$1369,Calc!$C$5:$C$1369,"BLD") -> -10.832109 | H47: =SUMIFS(Calc!$AE$5:$AE$1369,Calc!$C$5:$C$1369,"BLD") -> -10.825114 | I47: =SUMIFS(Calc!$AF$5:$AF$1369,Calc!$C$5:$C$1369,"BLD") -> -35.529131
A48: Industry (efficiency, electrification, CCS) | B48: =SUMIFS(Calc!$J$5:$J$1369,Calc!$B$5:$B$1369,"AE",Calc!$C$5:$C$1369,"IND") -> 155.1 | C48: =SUMIFS(Calc!$J$5:$J$1369,Calc!$B$5:$B$1369,"China",Calc!$C$5:$C$1369,"IND") -> 56.1 | D48: =SUMIFS(Calc!$J$5:$J$1369,Calc!$B$5:$B$1369,"EMDC",Calc!$C$5:$C$1369,"IND") -> 105.6 | E48: =SUM(B48:D48) -> 316.8 | F48: =SUMIFS(Calc!$L$5:$L$1369,Calc!$C$5:$C$1369,"IND") -> 105.6 | G48: =SUMIFS(Calc!$AC$5:$AC$1369,Calc!$C$5:$C$1369,"IND") -> -6.019919 | H48: =SUMIFS(Calc!$AE$5:$AE$1369,Calc!$C$5:$C$1369,"IND") -> -5.9918723 | I48: =SUMIFS(Calc!$AF$5:$AF$1369,Calc!$C$5:$C$1369,"IND") -> -20.068362
A49: Low-emission fuels and fuel supply | B49: =SUMIFS(Calc!$J$5:$J$1369,Calc!$B$5:$B$1369,"AE",Calc!$C$5:$C$1369,"FUEL") -> 188 | C49: =SUMIFS(Calc!$J$5:$J$1369,Calc!$B$5:$B$1369,"China",Calc!$C$5:$C$1369,"FUEL") -> 68 | D49: =SUMIFS(Calc!$J$5:$J$1369,Calc!$B$5:$B$1369,"EMDC",Calc!$C$5:$C$1369,"FUEL") -> 128 | E49: =SUM(B49:D49) -> 384 | F49: =SUMIFS(Calc!$L$5:$L$1369,Calc!$C$5:$C$1369,"FUEL") -> 128 | G49: =SUMIFS(Calc!$AC$5:$AC$1369,Calc!$C$5:$C$1369,"FUEL") -> 11.135948 | H49: =SUMIFS(Calc!$AE$5:$AE$1369,Calc!$C$5:$C$1369,"FUEL") -> 11.159623 | I49: =SUMIFS(Calc!$AF$5:$AF$1369,Calc!$C$5:$C$1369,"FUEL") -> 11.159623
A50: AFOLU and nature | B50: =SUMIFS(Calc!$J$5:$J$1369,Calc!$B$5:$B$1369,"AE",Calc!$C$5:$C$1369,"AFOLU") -> 35.984375 | C50: =SUMIFS(Calc!$J$5:$J$1369,Calc!$B$5:$B$1369,"China",Calc!$C$5:$C$1369,"AFOLU") -> 13.015625 | D50: =SUMIFS(Calc!$J$5:$J$1369,Calc!$B$5:$B$1369,"EMDC",Calc!$C$5:$C$1369,"AFOLU") -> 350 | E50: =SUM(B50:D50) -> 399 | F50: =SUMIFS(Calc!$L$5:$L$1369,Calc!$C$5:$C$1369,"AFOLU") -> 102.62 | G50: =SUMIFS(Calc!$AC$5:$AC$1369,Calc!$C$5:$C$1369,"AFOLU") -> 9.7698156 | H50: =SUMIFS(Calc!$AE$5:$AE$1369,Calc!$C$5:$C$1369,"AFOLU") -> 7.4552313 | I50: =SUMIFS(Calc!$AF$5:$AF$1369,Calc!$C$5:$C$1369,"AFOLU") -> -5.7827487
A51: Total | B51: =SUM(B44:B50) -> 2385.9844 | C51: =SUM(C44:C50) -> 863.01562 | D51: =SUM(D44:D50) -> 1950 | E51: =SUM(E44:E50) -> 5199 | F51: =SUM(F44:F50) -> 1702.62 | G51: =SUM(G44:G50) -> 39.674113 | H51: =SUM(H44:H50) -> 37.872774 | I51: =SUM(I44:I50) -> -42.52485

Sheet Results_Country
A1: Results by country: mitigation investment needs and incremental cost, 2030 (USD bn/yr, 2023 prices)
A2: Incremental cost = annual capital charge on incremental investment less fuel and operating savings (less local co-benefits in lens c), over the asset life of one year's investment. Positive = net cost. Sorted by 2024 GDP.
A4: ISO3 | B4: Country | C4: Group | D4: WB income | E4: GDP 2030 (USD bn) | F4: Total investment I | G4: I, % GDP | H4: Incremental investment dI | I4: dI, % GDP | J4: Market WACC (a) | K4: WACC source | L4: Savings on dI | M4: Local co-benefits on dI | N4: Incr. cost (a) market | O4: Incr. cost (a) market high | P4: Incr. cost (b) WB rate | Q4: Incr. cost (c) WB + local co-ben. | R4: (a) % GDP | S4: (b) % GDP | T4: (c) % GDP | U4: memo: (c) + carbon, SPC low | V4: memo: (c) + carbon, SPC high | W4: Abatement (MtCO2e/yr) | X4: Incr. cost per t (a) USD/t | Y4: Incr. cost per t (b) USD/t | Z4: Incr. cost per t (c) USD/t | AA4: CoC penalty on I (a-b) | AB4: PIMA-adjusted I | AC4: PIM efficiency gap | AD4: PEFA PI-11 (1-4) | AE4: Capex execution (%) | AF4: Official-private spread (pp) | AG4: Gross debt (% GDP)
A5: =Country_Data!A5 -> USA | B5: =Country_Data!B5 -> United States | C5: =Country_Data!E5 -> AE | D5: =Country_Data!D5 -> High income | E5: =Country_Data!BV5 -> 33560.153 | F5: =SUMIFS(Calc!$J$5:$J$1369,Calc!$A$5:$A$1369,A5) -> 1069.0936 | G5: =IFERROR(F5/E5,"") -> 0.031856041 | H5: =SUMIFS(Calc!$L$5:$L$1369,Calc!$A$5:$A$1369,A5) -> 406.25558 | I5: =IFERROR(H5/E5,"") -> 0.012105296 | J5: =Country_Data!DW5 -> 0.05705 | K5: =Country_Data!DV5 -> Observed (IRENA/Steffen) | L5: =SUMIFS(Calc!$W$5:$W$1369,Calc!$A$5:$A$1369,A5) -> 18.307599 | M5: =SUMIFS(Calc!$X$5:$X$1369,Calc!$A$5:$A$1369,A5) -> 7.1875018 | N5: =SUMIFS(Calc!$AC$5:$AC$1369,Calc!$A$5:$A$1369,A5) -> 14.325479 | O5: =SUMIFS(Calc!$AD$5:$AD$1369,Calc!$A$5:$A$1369,A5) -> 18.967904 | P5: =SUMIFS(Calc!$AE$5:$AE$1369,Calc!$A$5:$A$1369,A5) -> 15.217629 | Q5: =SUMIFS(Calc!$AF$5:$AF$1369,Calc!$A$5:$A$1369,A5) -> 8.0301275 | R5: =IFERROR(N5/E5,"") -> 0.00042685977 | S5: =IFERROR(P5/E5,"") -> 0.00045344338 | T5: =IFERROR(Q5/E5,"") -> 0.00023927565 | U5: =SUMIFS(Calc!$AG$5:$AG$1369,Calc!$A$5:$A$1369,A5) -> -1.4683876 | V5: =SUMIFS(Calc!$AH$5:$AH$1369,Calc!$A$5:$A$1369,A5) -> -10.966903 | W5: =SUMIFS(Calc!$Y$5:$Y$1369,Calc!$A$5:$A$1369,A5) -> 189.9703 | X5: =IFERROR(N5/W5*1000,"") -> 75.409047 | Y5: =IFERROR(P5/W5*1000,"") -> 80.105306 | Z5: =IFERROR(Q5/W5*1000,"") -> 42.270436 | AA5: =SUMIFS(Calc!$AM$5:$AM$1369,Calc!$A$5:$A$1369,A5) -> -2.3477628 | AB5: =SUMIFS(Calc!$AN$5:$AN$1369,Calc!$A$5:$A$1369,A5) -> 1117.0185 | AC5: =Country_Data!DY5 -> 0.13 | AD5: =IF(Country_Data!BD5="","",Country_Data!BD5) | AE5: =IF(Country_Data!BC5="","",Country_Data!BC5) | AF5: =IF(Country_Data!BL5="","",Country_Data!BL5) | AG5: =IF(Country_Data!BA5="","",Country_Data!BA5) -> 122.27
A6: =Country_Data!A6 -> CHN | B6: =Country_Data!B6 -> China | C6: =Country_Data!E6 -> China | D6: =Country_Data!D6 -> Upper middle income | E6: =Country_Data!BV6 -> 24676.851 | F6: =SUMIFS(Calc!$J$5:$J$1369,Calc!$A$5:$A$1369,A6) -> 863.01562 | G6: =IFERROR(F6/E6,"") -> 0.034972681 | H6: =SUMIFS(Calc!$L$5:$L$1369,Calc!$A$5:$A$1369,A6) -> 327.94594 | I6: =IFERROR(H6/E6,"") -> 0.013289619 | J6: =Country_Data!DW6 -> 0.0389 | K6: =Country_Data!DV6 -> Observed (IRENA/Steffen) | L6: =SUMIFS(Calc!$W$5:$W$1369,Calc!$A$5:$A$1369,A6) -> 17.58997 | M6: =SUMIFS(Calc!$X$5:$X$1369,Calc!$A$5:$A$1369,A6) -> 36.459082 | N6: =SUMIFS(Calc!$AC$5:$AC$1369,Calc!$A$5:$A$1369,A6) -> 4.3679123 | O6: =SUMIFS(Calc!$AD$5:$AD$1369,Calc!$A$5:$A$1369,A6) -> 9.0549635 | P6: =SUMIFS(Calc!$AE$5:$AE$1369,Calc!$A$5:$A$1369,A6) -> 9.3250089 | Q6: =SUMIFS(Calc!$AF$5:$AF$1369,Calc!$A$5:$A$1369,A6) -> -27.134073 | R6: =IFERROR(N6/E6,"") -> 0.00017700445 | S6: =IFERROR(P6/E6,"") -> 0.00037788489 | T6: =IFERROR(Q6/E6,"") -> -0.001099576 | U6: =SUMIFS(Calc!$AG$5:$AG$1369,Calc!$A$5:$A$1369,A6) -> -37.199122 | V6: =SUMIFS(Calc!$AH$5:$AH$1369,Calc!$A$5:$A$1369,A6) -> -47.264171 | W6: =SUMIFS(Calc!$Y$5:$Y$1369,Calc!$A$5:$A$1369,A6) -> 201.30098 | X6: =IFERROR(N6/W6*1000,"") -> 21.698415 | Y6: =IFERROR(P6/W6*1000,"") -> 46.323712 | Z6: =IFERROR(Q6/W6*1000,"") -> -134.79354 | AA6: =SUMIFS(Calc!$AM$5:$AM$1369,Calc!$A$5:$A$1369,A6) -> -13.044991 | AB6: =SUMIFS(Calc!$AN$5:$AN$1369,Calc!$A$5:$A$1369,A6) -> 1022.6144 | AC6: =Country_Data!DY6 -> 0.27 | AD6: =IF(Country_Data!BD6="","",Country_Data!BD6) | AE6: =IF(Country_Data!BC6="","",Country_Data!BC6) | AF6: =IF(Country_Data!BL6="","",Country_Data!BL6) -> 0.656 | AG6: =IF(Country_Data!BA6="","",Country_Data!BA6) -> 90.421
A7: =Country_Data!A7 -> DEU | B7: =Country_Data!B7 -> Germany | C7: =Country_Data!E7 -> AE | D7: =Country_Data!D7 -> High income | E7: =Country_Data!BV7 -> 4884.0892 | F7: =SUMIFS(Calc!$J$5:$J$1369,Calc!$A$5:$A$1369,A7) -> 152.2747 | G7: =IFERROR(F7/E7,"") -> 0.031177707 | H7: =SUMIFS(Calc!$L$5:$L$1369,Calc!$A$5:$A$1369,A7) -> 57.864388 | I7: =IFERROR(H7/E7,"") -> 0.011847529 | J7: =Country_Data!DW7 -> 0.0232 | K7: =Country_Data!DV7 -> Observed (IRENA/Steffen) | L7: =SUMIFS(Calc!$W$5:$W$1369,Calc!$A$5:$A$1369,A7) -> 4.3058879 | M7: =SUMIFS(Calc!$X$5:$X$1369,Calc!$A$5:$A$1369,A7) -> 1.4337864 | N7: =SUMIFS(Calc!$AC$5:$AC$1369,Calc!$A$5:$A$1369,A7) -> -1.0147741 | O7: =SUMIFS(Calc!$AD$5:$AD$1369,Calc!$A$5:$A$1369,A7) -> -0.45142451 | P7: =SUMIFS(Calc!$AE$5:$AE$1369,Calc!$A$5:$A$1369,A7) -> 0.45012401 | Q7: =SUMIFS(Calc!$AF$5:$AF$1369,Calc!$A$5:$A$1369,A7) -> -0.98366234 | R7: =IFERROR(N7/E7,"") -> -0.00020777141 | S7: =IFERROR(P7/E7,"") -> 9.2161301e-05 | T7: =IFERROR(Q7/E7,"") -> -0.00020140139 | U7: =SUMIFS(Calc!$AG$5:$AG$1369,Calc!$A$5:$A$1369,A7) -> -2.2521772 | V7: =SUMIFS(Calc!$AH$5:$AH$1369,Calc!$A$5:$A$1369,A7) -> -3.520692 | W7: =SUMIFS(Calc!$Y$5:$Y$1369,Calc!$A$5:$A$1369,A7) -> 25.370297 | X7: =IFERROR(N7/W7*1000,"") -> -39.998512 | Y7: =IFERROR(P7/W7*1000,"") -> 17.742166 | Z7: =IFERROR(Q7/W7*1000,"") -> -38.772204 | AA7: =SUMIFS(Calc!$AM$5:$AM$1369,Calc!$A$5:$A$1369,A7) -> -3.8549951 | AB7: =SUMIFS(Calc!$AN$5:$AN$1369,Calc!$A$5:$A$1369,A7) -> 159.10081 | AC7: =Country_Data!DY7 -> 0.13 | AD7: =IF(Country_Data!BD7="","",Country_Data!BD7) | AE7: =IF(Country_Data!BC7="","",Country_Data!BC7) | AF7: =IF(Country_Data!BL7="","",Country_Data!BL7) | AG7: =IF(Country_Data!BA7="","",Country_Data!BA7) -> 62.227
A8: =Country_Data!A8 -> JPN | B8: =Country_Data!B8 -> Japan | C8: =Country_Data!E8 -> AE | D8: =Country_Data!D8 -> High income | E8: =Country_Data!BV8 -> 4394.6303 | F8: =SUMIFS(Calc!$J$5:$J$1369,Calc!$A$5:$A$1369,A8) -> 190.59034 | G8: =IFERROR(F8/E8,"") -> 0.043368914 | H8: =SUMIFS(Calc!$L$5:$L$1369,Calc!$A$5:$A$1369,A8) -> 72.424331 | I8: =IFERROR(H8/E8,"") -> 0.016480187 | J8: =Country_Data!DW8 -> 0.055 | K8: =Country_Data!DV8 -> Group default (IHLEG) | L8: =SUMIFS(Calc!$W$5:$W$1369,Calc!$A$5:$A$1369,A8) -> 7.1954829 | M8: =SUMIFS(Calc!$X$5:$X$1369,Calc!$A$5:$A$1369,A8) -> 2.2674151 | N8: =SUMIFS(Calc!$AC$5:$AC$1369,Calc!$A$5:$A$1369,A8) -> -1.6293628 | O8: =SUMIFS(Calc!$AD$5:$AD$1369,Calc!$A$5:$A$1369,A8) -> -0.8016585 | P8: =SUMIFS(Calc!$AE$5:$AE$1369,Calc!$A$5:$A$1369,A8) -> -1.3588844 | Q8: =SUMIFS(Calc!$AF$5:$AF$1369,Calc!$A$5:$A$1369,A8) -> -3.6262995 | R8: =IFERROR(N8/E8,"") -> -0.00037076219 | S8: =IFERROR(P8/E8,"") -> -0.00030921472 | T8: =IFERROR(Q8/E8,"") -> -0.00082516599 | U8: =SUMIFS(Calc!$AG$5:$AG$1369,Calc!$A$5:$A$1369,A8) -> -5.6819736 | V8: =SUMIFS(Calc!$AH$5:$AH$1369,Calc!$A$5:$A$1369,A8) -> -7.7376478 | W8: =SUMIFS(Calc!$Y$5:$Y$1369,Calc!$A$5:$A$1369,A8) -> 41.113483 | X8: =IFERROR(N8/W8*1000,"") -> -39.630862 | Y8: =IFERROR(P8/W8*1000,"") -> -33.052038 | Z8: =IFERROR(Q8/W8*1000,"") -> -88.202196 | AA8: =SUMIFS(Calc!$AM$5:$AM$1369,Calc!$A$5:$A$1369,A8) -> -0.71178515 | AB8: =SUMIFS(Calc!$AN$5:$AN$1369,Calc!$A$5:$A$1369,A8) -> 199.13405 | AC8: =Country_Data!DY8 -> 0.13 | AD8: =IF(Country_Data!BD8="","",Country_Data!BD8) | AE8: =IF(Country_Data!BC8="","",Country_Data!BC8) | AF8: =IF(Country_Data!BL8="","",Country_Data!BL8) | AG8: =IF(Country_Data!BA8="","",Country_Data!BA8) -> 214.487
A9: =Country_Data!A9 -> IND | B9: =Country_Data!B9 -> India | C9: =Country_Data!E9 -> EMDC | D9: =Country_Data!D9 -> Lower middle income | E9: =Country_Data!BV9 -> 5539.4443 | F9: =SUMIFS(Calc!$J$5:$J$1369,Calc!$A$5:$A$1369,A9) -> 291.81555 | G9: =IFERROR(F9/E9,"") -> 0.052679572 | H9: =SUMIFS(Calc!$L$5:$L$1369,Calc!$A$5:$A$1369,A9) -> 70.035732 | I9: =IFERROR(H9/E9,"") -> 0.012643097 | J9: =Country_Data!DW9 -> 0.095 | K9: =Country_Data!DV9 -> Observed (IRENA/Steffen) | L9: =SUMIFS(Calc!$W$5:$W$1369,Calc!$A$5:$A$1369,A9) -> 2.462509 | M9: =SUMIFS(Calc!$X$5:$X$1369,Calc!$A$5:$A$1369,A9) -> 3.8924392 | N9: =SUMIFS(Calc!$AC$5:$AC$1369,Calc!$A$5:$A$1369,A9) -> 5.1234387 | O9: =SUMIFS(Calc!$AD$5:$AD$1369,Calc!$A$5:$A$1369,A9) -> 7.9047084 | P9: =SUMIFS(Calc!$AE$5:$AE$1369,Calc!$A$5:$A$1369,A9) -> 3.1546627 | Q9: =SUMIFS(Calc!$AF$5:$AF$1369,Calc!$A$5:$A$1369,A9) -> -0.73777652 | R9: =IFERROR(N9/E9,"") -> 0.00092490121 | S9: =IFERROR(P9/E9,"") -> 0.00056949082 | T9: =IFERROR(Q9/E9,"") -> -0.00013318602 | U9: =SUMIFS(Calc!$AG$5:$AG$1369,Calc!$A$5:$A$1369,A9) -> -3.6543384 | V9: =SUMIFS(Calc!$AH$5:$AH$1369,Calc!$A$5:$A$1369,A9) -> -6.5709003 | W9: =SUMIFS(Calc!$Y$5:$Y$1369,Calc!$A$5:$A$1369,A9) -> 58.331238 | X9: =IFERROR(N9/W9*1000,"") -> 87.833533 | Y9: =IFERROR(P9/W9*1000,"") -> 54.081874 | Z9: =IFERROR(Q9/W9*1000,"") -> -12.648052 | AA9: =SUMIFS(Calc!$AM$5:$AM$1369,Calc!$A$5:$A$1369,A9) -> 8.2032335 | AB9: =SUMIFS(Calc!$AN$5:$AN$1369,Calc!$A$5:$A$1369,A9) -> 334.98826 | AC9: =Country_Data!DY9 -> 0.27 | AD9: =IF(Country_Data!BD9="","",Country_Data!BD9) | AE9: =IF(Country_Data!BC9="","",Country_Data!BC9) -> 106.972 | AF9: =IF(Country_Data!BL9="","",Country_Data!BL9) -> 0.904 | AG9: =IF(Country_Data!BA9="","",Country_Data!BA9) -> 84.782
A10: =Country_Data!A10 -> GBR | B10: =Country_Data!B10 -> United Kingdom | C10: =Country_Data!E10 -> AE | D10: =Country_Data!D10 -> High income | E10: =Country_Data!BV10 -> 3895.8501 | F10: =SUMIFS(Calc!$J$5:$J$1369,Calc!$A$5:$A$1369,A10) -> 104.58983 | G10: =IFERROR(F10/E10,"") -> 0.026846471 | H10: =SUMIFS(Calc!$L$5:$L$1369,Calc!$A$5:$A$1369,A10) -> 39.744135 | I10: =IFERROR(H10/E10,"") -> 0.010201659 | J10: =Country_Data!DW10 -> 0.03587 | K10: =Country_Data!DV10 -> Observed (IRENA/Steffen) | L10: =SUMIFS(Calc!$W$5:$W$1369,Calc!$A$5:$A$1369,A10) -> 4.9009147 | M10: =SUMIFS(Calc!$X$5:$X$1369,Calc!$A$5:$A$1369,A10) -> 0.62999901 | N10: =SUMIFS(Calc!$AC$5:$AC$1369,Calc!$A$5:$A$1369,A10) -> -2.3067663 | O10: =SUMIFS(Calc!$AD$5:$AD$1369,Calc!$A$5:$A$1369,A10) -> -1.8926891 | P10: =SUMIFS(Calc!$AE$5:$AE$1369,Calc!$A$5:$A$1369,A10) -> -1.6261561 | Q10: =SUMIFS(Calc!$AF$5:$AF$1369,Calc!$A$5:$A$1369,A10) -> -2.2561552 | R10: =IFERROR(N10/E10,"") -> -0.0005921086 | S10: =IFERROR(P10/E10,"") -> -0.00041740727 | T10: =IFERROR(Q10/E10,"") -> -0.00057911755 | U10: =SUMIFS(Calc!$AG$5:$AG$1369,Calc!$A$5:$A$1369,A10) -> -2.964141 | V10: =SUMIFS(Calc!$AH$5:$AH$1369,Calc!$A$5:$A$1369,A10) -> -3.6721269 | W10: =SUMIFS(Calc!$Y$5:$Y$1369,Calc!$A$5:$A$1369,A10) -> 14.159717 | X10: =IFERROR(N10/W10*1000,"") -> -162.91048 | Y10: =IFERROR(P10/W10*1000,"") -> -114.84383 | Z10: =IFERROR(Q10/W10*1000,"") -> -159.33617 | AA10: =SUMIFS(Calc!$AM$5:$AM$1369,Calc!$A$5:$A$1369,A10) -> -1.7910795 | AB10: =SUMIFS(Calc!$AN$5:$AN$1369,Calc!$A$5:$A$1369,A10) -> 109.27834 | AC10: =Country_Data!DY10 -> 0.13 | AD10: =IF(Country_Data!BD10="","",Country_Data!BD10) | AE10: =IF(Country_Data!BC10="","",Country_Data!BC10) | AF10: =IF(Country_Data!BL10="","",Country_Data!BL10) | AG10: =IF(Country_Data!BA10="","",Country_Data!BA10) -> 99.901
A11: =Country_Data!A11 -> FRA | B11: =Country_Data!B11 -> France | C11: =Country_Data!E11 -> AE | D11: =Country_Data!D11 -> High income | E11: =Country_Data!BV11 -> 3329.6125 | F11: =SUMIFS(Calc!$J$5:$J$1369,Calc!$A$5:$A$1369,A11) -> 106.42816 | G11: =IFERROR(F11/E11,"") -> 0.031964127 | H11: =SUMIFS(Calc!$L$5:$L$1369,Calc!$A$5:$A$1369,A11) -> 40.4427 | I11: =IFERROR(H11/E11,"") -> 0.012146368 | J11: =Country_Data!DW11 -> 0.03297 | K11: =Country_Data!DV11 -> Observed (IRENA/Steffen) | L11: =SUMIFS(Calc!$W$5:$W$1369,Calc!$A$5:$A$1369,A11) -> 2.1907408 | M11: =SUMIFS(Calc!$X$5:$X$1369,Calc!$A$5:$A$1369,A11) -> 0.36940981 | N11: =SUMIFS(Calc!$AC$5:$AC$1369,Calc!$A$5:$A$1369,A11) -> 0.3466431 | O11: =SUMIFS(Calc!$AD$5:$AD$1369,Calc!$A$5:$A$1369,A11) -> 0.76313705 | P11: =SUMIFS(Calc!$AE$5:$AE$1369,Calc!$A$5:$A$1369,A11) -> 1.1195525 | Q11: =SUMIFS(Calc!$AF$5:$AF$1369,Calc!$A$5:$A$1369,A11) -> 0.75014268 | R11: =IFERROR(N11/E11,"") -> 0.00010410914 | S11: =IFERROR(P11/E11,"") -> 0.00033624108 | T11: =IFERROR(Q11/E11,"") -> 0.00022529429 | U11: =SUMIFS(Calc!$AG$5:$AG$1369,Calc!$A$5:$A$1369,A11) -> 0.26352499 | V11: =SUMIFS(Calc!$AH$5:$AH$1369,Calc!$A$5:$A$1369,A11) -> -0.22309271 | W11: =SUMIFS(Calc!$Y$5:$Y$1369,Calc!$A$5:$A$1369,A11) -> 9.732354 | X11: =IFERROR(N11/W11*1000,"") -> 35.617601 | Y11: =IFERROR(P11/W11*1000,"") -> 115.03409 | Z11: =IFERROR(Q11/W11*1000,"") -> 77.077209 | AA11: =SUMIFS(Calc!$AM$5:$AM$1369,Calc!$A$5:$A$1369,A11) -> -2.0339721 | AB11: =SUMIFS(Calc!$AN$5:$AN$1369,Calc!$A$5:$A$1369,A11) -> 111.19908 | AC11: =Country_Data!DY11 -> 0.13 | AD11: =IF(Country_Data!BD11="","",Country_Data!BD11) | AE11: =IF(Country_Data!BC11="","",Country_Data!BC11) | AF11: =IF(Country_Data!BL11="","",Country_Data!BL11) | AG11: =IF(Country_Data!BA11="","",Country_Data!BA11) -> 113.171
A12: =Country_Data!A12 -> ITA | B12: =Country_Data!B12 -> Italy | C12: =Country_Data!E12 -> AE | D12: =Country_Data!D12 -> High income | E12: =Country_Data!BV12 -> 2458.6433 | F12: =SUMIFS(Calc!$J$5:$J$1369,Calc!$A$5:$A$1369,A12) -> 81.737972 | G12: =IFERROR(F12/E12,"") -> 0.033245152 | H12: =SUMIFS(Calc!$L$5:$L$1369,Calc!$A$5:$A$1369,A12) -> 31.060429 | I12: =IFERROR(H12/E12,"") -> 0.012633158 | J12: =Country_Data!DW12 -> 0.0438 | K12: =Country_Data!DV12 -> Observed (IRENA/Steffen) | L12: =SUMIFS(Calc!$W$5:$W$1369,Calc!$A$5:$A$1369,A12) -> 3.2611012 | M12: =SUMIFS(Calc!$X$5:$X$1369,Calc!$A$5:$A$1369,A12) -> 0.73380338 | N12: =SUMIFS(Calc!$AC$5:$AC$1369,Calc!$A$5:$A$1369,A12) -> -1.0757859 | O12: =SUMIFS(Calc!$AD$5:$AD$1369,Calc!$A$5:$A$1369,A12) -> -0.73928262 | P12: =SUMIFS(Calc!$AE$5:$AE$1369,Calc!$A$5:$A$1369,A12) -> -0.71140553 | Q12: =SUMIFS(Calc!$AF$5:$AF$1369,Calc!$A$5:$A$1369,A12) -> -1.4452089 | R12: =IFERROR(N12/E12,"") -> -0.00043755267 | S12: =IFERROR(P12/E12,"") -> -0.00028934881 | T12: =IFERROR(Q12/E12,"") -> -0.00058780747 | U12: =SUMIFS(Calc!$AG$5:$AG$1369,Calc!$A$5:$A$1369,A12) -> -2.0647334 | V12: =SUMIFS(Calc!$AH$5:$AH$1369,Calc!$A$5:$A$1369,A12) -> -2.6842578 | W12: =SUMIFS(Calc!$Y$5:$Y$1369,Calc!$A$5:$A$1369,A12) -> 12.390489 | X12: =IFERROR(N12/W12*1000,"") -> -86.823526 | Y12: =IFERROR(P12/W12*1000,"") -> -57.415452 | Z12: =IFERROR(Q12/W12*1000,"") -> -116.63857 | AA12: =SUMIFS(Calc!$AM$5:$AM$1369,Calc!$A$5:$A$1369,A12) -> -0.95889583 | AB12: =SUMIFS(Calc!$AN$5:$AN$1369,Calc!$A$5:$A$1369,A12) -> 85.402088 | AC12: =Country_Data!DY12 -> 0.13 | AD12: =IF(Country_Data!BD12="","",Country_Data!BD12) | AE12: =IF(Country_Data!BC12="","",Country_Data!BC12) | AF12: =IF(Country_Data!BL12="","",Country_Data!BL12) | AG12: =IF(Country_Data!BA12="","",Country_Data!BA12) -> 134.735
A13: =Country_Data!A13 -> CAN | B13: =Country_Data!B13 -> Canada | C13: =Country_Data!E13 -> AE | D13: =Country_Data!D13 -> High income | E13: =Country_Data!BV13 -> 2488.1419 | F13: =SUMIFS(Calc!$J$5:$J$1369,Calc!$A$5:$A$1369,A13) -> 108.78607 | G13: =IFERROR(F13/E13,"") -> 0.043721809 | H13: =SUMIFS(Calc!$L$5:$L$1369,Calc!$A$5:$A$1369,A13) -> 41.338705 | I13: =IFERROR(H13/E13,"") -> 0.016614287 | J13: =Country_Data!DW13 -> 0.055 | K13: =Country_Data!DV13 -> Group default (IHLEG) | L13: =SUMIFS(Calc!$W$5:$W$1369,Calc!$A$5:$A$1369,A13) -> 2.1379202 | M13: =SUMIFS(Calc!$X$5:$X$1369,Calc!$A$5:$A$1369,A13) -> 0.39020643 | N13: =SUMIFS(Calc!$AC$5:$AC$1369,Calc!$A$5:$A$1369,A13) -> 1.0876127 | O13: =SUMIFS(Calc!$AD$5:$AD$1369,Calc!$A$5:$A$1369,A13) -> 1.5575851 | P13: =SUMIFS(Calc!$AE$5:$AE$1369,Calc!$A$5:$A$1369,A13) -> 1.2412154 | Q13: =SUMIFS(Calc!$AF$5:$AF$1369,Calc!$A$5:$A$1369,A13) -> 0.85100898 | R13: =IFERROR(N13/E13,"") -> 0.00043711842 | S13: =IFERROR(P13/E13,"") -> 0.00049885233 | T13: =IFERROR(Q13/E13,"") -> 0.0003420259 | U13: =SUMIFS(Calc!$AG$5:$AG$1369,Calc!$A$5:$A$1369,A13) -> 0.19572601 | V13: =SUMIFS(Calc!$AH$5:$AH$1369,Calc!$A$5:$A$1369,A13) -> -0.45955695 | W13: =SUMIFS(Calc!$Y$5:$Y$1369,Calc!$A$5:$A$1369,A13) -> 13.105659 | X13: =IFERROR(N13/W13*1000,"") -> 82.988016 | Y13: =IFERROR(P13/W13*1000,"") -> 94.708353 | Z13: =IFERROR(Q13/W13*1000,"") -> 64.934465 | AA13: =SUMIFS(Calc!$AM$5:$AM$1369,Calc!$A$5:$A$1369,A13) -> -0.40421773 | AB13: =SUMIFS(Calc!$AN$5:$AN$1369,Calc!$A$5:$A$1369,A13) -> 113.66268 | AC13: =Country_Data!DY13 -> 0.13 | AD13: =IF(Country_Data!BD13="","",Country_Data!BD13) | AE13: =IF(Country_Data!BC13="","",Country_Data!BC13) | AF13: =IF(Country_Data!BL13="","",Country_Data!BL13) | AG13: =IF(Country_Data!BA13="","",Country_Data!BA13) -> 110.019
A14: =Country_Data!A14 -> RUS | B14: =Country_Data!B14 -> Russian Federation | C14: =Country_Data!E14 -> EMDC | D14: =Country_Data!D14 -> High income | E14: =Country_Data!BV14 -> 2330.355 | F14: =SUMIFS(Calc!$J$5:$J$1369,Calc!$A$5:$A$1369,A14) -> 177.39905 | G14: =IFERROR(F14/E14,"") -> 0.076125334 | H14: =SUMIFS(Calc!$L$5:$L$1369,Calc!$A$5:$A$1369,A14) -> 42.575773 | I14: =IFERROR(H14/E14,"") -> 0.01827008 | J14: =Country_Data!DW14 -> 0.105 | K14: =Country_Data!DV14 -> Group default (IHLEG) | L14: =SUMIFS(Calc!$W$5:$W$1369,Calc!$A$5:$A$1369,A14) -> 1.3273054 | M14: =SUMIFS(Calc!$X$5:$X$1369,Calc!$A$5:$A$1369,A14) -> 3.8170708 | N14: =SUMIFS(Calc!$AC$5:$AC$1369,Calc!$A$5:$A$1369,A14) -> 3.6517176 | O14: =SUMIFS(Calc!$AD$5:$AD$1369,Calc!$A$5:$A$1369,A14) -> 5.366839 | P14: =SUMIFS(Calc!$AE$5:$AE$1369,Calc!$A$5:$A$1369,A14) -> 2.095114 | Q14: =SUMIFS(Calc!$AF$5:$AF$1369,Calc!$A$5:$A$1369,A14) -> -1.7219568 | R14: =IFERROR(N14/E14,"") -> 0.001567022 | S14: =IFERROR(P14/E14,"") -> 0.00089905359 | T14: =IFERROR(Q14/E14,"") -> -0.00073892465 | U14: =SUMIFS(Calc!$AG$5:$AG$1369,Calc!$A$5:$A$1369,A14) -> -2.9996619 | V14: =SUMIFS(Calc!$AH$5:$AH$1369,Calc!$A$5:$A$1369,A14) -> -4.2773671 | W14: =SUMIFS(Calc!$Y$5:$Y$1369,Calc!$A$5:$A$1369,A14) -> 25.554103 | X14: =IFERROR(N14/W14*1000,"") -> 142.90142 | Y14: =IFERROR(P14/W14*1000,"") -> 81.987382 | Z14: =IFERROR(Q14/W14*1000,"") -> -67.384746 | AA14: =SUMIFS(Calc!$AM$5:$AM$1369,Calc!$A$5:$A$1369,A14) -> 6.485848 | AB14: =SUMIFS(Calc!$AN$5:$AN$1369,Calc!$A$5:$A$1369,A14) -> 203.64439 | AC14: =Country_Data!DY14 -> 0.27 | AD14: =IF(Country_Data!BD14="","",Country_Data!BD14) | AE14: =IF(Country_Data!BC14="","",Country_Data!BC14) | AF14: =IF(Country_Data!BL14="","",Country_Data!BL14) | AG14: =IF(Country_Data!BA14="","",Country_Data!BA14) -> 14.758
A15: =Country_Data!A15 -> BRA | B15: =Country_Data!B15 -> Brazil | C15: =Country_Data!E15 -> EMDC | D15: =Country_Data!D15 -> Upper middle income | E15: =Country_Data!BV15 -> 2457.7421 | F15: =SUMIFS(Calc!$J$5:$J$1369,Calc!$A$5:$A$1369,A15) -> 139.4253 | G15: =IFERROR(F15/E15,"") -> 0.05672902 | H15: =SUMIFS(Calc!$L$5:$L$1369,Calc!$A$5:$A$1369,A15) -> 33.462072 | I15: =IFERROR(H15/E15,"") -> 0.013614965 | J15: =Country_Data!DW15 -> 0.097755 | K15: =Country_Data!DV15 -> Observed (IRENA/Steffen) | L15: =SUMIFS(Calc!$W$5:$W$1369,Calc!$A$5:$A$1369,A15) -> 1.3933363 | M15: =SUMIFS(Calc!$X$5:$X$1369,Calc!$A$5:$A$1369,A15) -> 1.4264195 | N15: =SUMIFS(Calc!$AC$5:$AC$1369,Calc!$A$5:$A$1369,A15) -> 2.3092408 | O15: =SUMIFS(Calc!$AD$5:$AD$1369,Calc!$A$5:$A$1369,A15) -> 3.6459412 | P15: =SUMIFS(Calc!$AE$5:$AE$1369,Calc!$A$5:$A$1369,A15) -> 1.2890906 | Q15: =SUMIFS(Calc!$AF$5:$AF$1369,Calc!$A$5:$A$1369,A15) -> -0.13732882 | R15: =IFERROR(N15/E15,"") -> 0.00093957818 | S15: =IFERROR(P15/E15,"") -> 0.00052450201 | T15: =IFERROR(Q15/E15,"") -> -5.5876009e-05 | U15: =SUMIFS(Calc!$AG$5:$AG$1369,Calc!$A$5:$A$1369,A15) -> -1.0301501 | V15: =SUMIFS(Calc!$AH$5:$AH$1369,Calc!$A$5:$A$1369,A15) -> -1.9229714 | W15: =SUMIFS(Calc!$Y$5:$Y$1369,Calc!$A$5:$A$1369,A15) -> 17.856426 | X15: =IFERROR(N15/W15*1000,"") -> 129.32268 | Y15: =IFERROR(P15/W15*1000,"") -> 72.191974 | Z15: =IFERROR(Q15/W15*1000,"") -> -7.6907225 | AA15: =SUMIFS(Calc!$AM$5:$AM$1369,Calc!$A$5:$A$1369,A15) -> 4.2506257 | AB15: =SUMIFS(Calc!$AN$5:$AN$1369,Calc!$A$5:$A$1369,A15) -> 160.0526 | AC15: =Country_Data!DY15 -> 0.27 | AD15: =IF(Country_Data!BD15="","",Country_Data!BD15) | AE15: =IF(Country_Data!BC15="","",Country_Data!BC15) -> 87.319 | AF15: =IF(Country_Data!BL15="","",Country_Data!BL15) -> 1.341 | AG15: =IF(Country_Data!BA15="","",Country_Data!BA15) -> 87.028
A16: =Country_Data!A16 -> KOR | B16: =Country_Data!B16 -> Korea, Rep. | C16: =Country_Data!E16 -> AE | D16: =Country_Data!D16 -> High income | E16: =Country_Data!BV16 -> 2077.3209 | F16: =SUMIFS(Calc!$J$5:$J$1369,Calc!$A$5:$A$1369,A16) -> 96.990799 | G16: =IFERROR(F16/E16,"") -> 0.046690329 | H16: =SUMIFS(Calc!$L$5:$L$1369,Calc!$A$5:$A$1369,A16) -> 36.856503 | I16: =IFERROR(H16/E16,"") -> 0.017742325 | J16: =Country_Data!DW16 -> 0.055 | K16: =Country_Data!DV16 -> Group default (IHLEG) | L16: =SUMIFS(Calc!$W$5:$W$1369,Calc!$A$5:$A$1369,A16) -> 2.627822 | M16: =SUMIFS(Calc!$X$5:$X$1369,Calc!$A$5:$A$1369,A16) -> 0.89458407 | N16: =SUMIFS(Calc!$AC$5:$AC$1369,Calc!$A$5:$A$1369,A16) -> 0.20323947 | O16: =SUMIFS(Calc!$AD$5:$AD$1369,Calc!$A$5:$A$1369,A16) -> 0.62452295 | P16: =SUMIFS(Calc!$AE$5:$AE$1369,Calc!$A$5:$A$1369,A16) -> 0.34090632 | Q16: =SUMIFS(Calc!$AF$5:$AF$1369,Calc!$A$5:$A$1369,A16) -> -0.55367775 | R16: =IFERROR(N16/E16,"") -> 9.7837297e-05 | S16: =IFERROR(P16/E16,"") -> 0.00016410864 | T16: =IFERROR(Q16/E16,"") -> -0.00026653452 | U16: =SUMIFS(Calc!$AG$5:$AG$1369,Calc!$A$5:$A$1369,A16) -> -1.5445228 | V16: =SUMIFS(Calc!$AH$5:$AH$1369,Calc!$A$5:$A$1369,A16) -> -2.5353678 | W16: =SUMIFS(Calc!$Y$5:$Y$1369,Calc!$A$5:$A$1369,A16) -> 19.8169 | X16: =IFERROR(N16/W16*1000,"") -> 10.255866 | Y16: =IFERROR(P16/W16*1000,"") -> 17.202808 | Z16: =IFERROR(Q16/W16*1000,"") -> -27.939675 | AA16: =SUMIFS(Calc!$AM$5:$AM$1369,Calc!$A$5:$A$1369,A16) -> -0.36228121 | AB16: =SUMIFS(Calc!$AN$5:$AN$1369,Calc!$A$5:$A$1369,A16) -> 101.33866 | AC16: =Country_Data!DY16 -> 0.13 | AD16: =IF(Country_Data!BD16="","",Country_Data!BD16) | AE16: =IF(Country_Data!BC16="","",Country_Data!BC16) | AF16: =IF(Country_Data!BL16="","",Country_Data!BL16) | AG16: =IF(Country_Data!BA16="","",Country_Data!BA16) -> 49.701
... A199: =Country_Data!A199 -> TUV | B199: =Country_Data!B199 -> Tuvalu | C199: =Country_Data!E199 -> EMDC | D199: =Country_Data!D199 -> Upper middle income | E199: =Country_Data!BV199 -> 0.064843686 | F199: =SUMIFS(Calc!$J$5:$J$1369,Calc!$A$5:$A$1369,A199) -> 0.0023782306 | G199: =IFERROR(F199/E199,"") -> 0.036676363 | H199: =SUMIFS(Calc!$L$5:$L$1369,Calc!$A$5:$A$1369,A199) -> 0.00057077534 | I199: =IFERROR(H199/E199,"") -> 0.0088023272 | J199: =Country_Data!DW199 -> 0.105 | K199: =Country_Data!DV199 -> Group default (IHLEG) | L199: =SUMIFS(Calc!$W$5:$W$1369,Calc!$A$5:$A$1369,A199) -> 4.2387135e-05 | M199: =SUMIFS(Calc!$X$5:$X$1369,Calc!$A$5:$A$1369,A199) -> 5.4287106e-05 | N199: =SUMIFS(Calc!$AC$5:$AC$1369,Calc!$A$5:$A$1369,A199) -> 2.4449162e-05 | O199: =SUMIFS(Calc!$AD$5:$AD$1369,Calc!$A$5:$A$1369,A199) -> 4.7457831e-05 | P199: =SUMIFS(Calc!$AE$5:$AE$1369,Calc!$A$5:$A$1369,A199) -> 3.555517e-06 | Q199: =SUMIFS(Calc!$AF$5:$AF$1369,Calc!$A$5:$A$1369,A199) -> -5.0731589e-05 | R199: =IFERROR(N199/E199,"") -> 0.00037704769 | S199: =IFERROR(P199/E199,"") -> 5.4832124e-05 | T199: =IFERROR(Q199/E199,"") -> -0.00078236745 | U199: =SUMIFS(Calc!$AG$5:$AG$1369,Calc!$A$5:$A$1369,A199) -> -6.5366522e-05 | V199: =SUMIFS(Calc!$AH$5:$AH$1369,Calc!$A$5:$A$1369,A199) -> -8.0001454e-05 | W199: =SUMIFS(Calc!$Y$5:$Y$1369,Calc!$A$5:$A$1369,A199) -> 0.00029269865 | X199: =IFERROR(N199/W199*1000,"") -> 83.530149 | Y199: =IFERROR(P199/W199*1000,"") -> 12.147364 | Z199: =IFERROR(Q199/W199*1000,"") -> -173.32362 | AA199: =SUMIFS(Calc!$AM$5:$AM$1369,Calc!$A$5:$A$1369,A199) -> 8.7056853e-05 | AB199: =SUMIFS(Calc!$AN$5:$AN$1369,Calc!$A$5:$A$1369,A199) -> 0.0030124254 | AC199: =Country_Data!DY199 -> 0.4 | AD199: =IF(Country_Data!BD199="","",Country_Data!BD199) -> 1 | AE199: =IF(Country_Data!BC199="","",Country_Data!BC199) -> 170.025 | AF199: =IF(Country_Data!BL199="","",Country_Data!BL199) | AG199: =IF(Country_Data!BA199="","",Country_Data!BA199) -> 6.957

Sheet Sensitivity
A1: Sensitivity: incremental cost, 2030 (USD bn a year), one input changed at a time
A2: STATIC VALUES written by build/run_sensitivity.py from the inputs as they stood when it ran. Re-run the script after changing inputs. Positive = net cost; negative = net saving.
A4: Case | B4: Inputs changed | C4: World (a) market | D4: World (b) WB 6% | E4: World (c) WB + co-ben. | F4: EMDC (a) | G4: EMDC (b) | H4: EMDC (c) | I4: World dI | J4: Abatement (Mt/yr) | K4: World (b) USD/t
A5: Base case (v1.1 defaults) | B5: - | C5: 39.674113 | D5: 37.872774 | E5: -42.52485 | F5: 25.947919 | G5: 13.163886 | H5: -13.409846 | I5: 1702.62 | J5: 921.08623 | K5: 41.117512
A6: v1.0 calibrated benefits for power and transport | B6: p_eng=0 | C6: -7.0604189 | D6: -8.8617573 | E6: -166.39864 | F6: 20.135048 | G6: 7.3510146 | H6: -38.928999 | I6: 1702.62 | J6: 641.50086 | K6: -13.8141
A7: Grids credited with generation benefits | B7: p_grid_credit=1 | C7: 18.469397 | D7: 16.668059 | E7: -79.369886 | F7: 20.492838 | G7: 7.7088053 | H7: -22.079149 | I7: 1702.62 | J7: 1250.1296 | K7: 13.333065
A8: EV premium USD 2,500 | B8: p_ev_prem=2500 | C8: 9.4695796 | D8: 7.6682412 | E8: -77.943356 | F8: 17.55033 | G8: 4.7662969 | H8: -23.086418 | I8: 1702.62 | J8: 998.85261 | K8: 7.6770497
A9: EV premium USD 10,000 | B9: p_ev_prem=10000 | C9: 54.776379 | D9: 52.975041 | E9: -24.815597 | F9: 30.146714 | G9: 17.362681 | H9: -8.5715593 | I9: 1702.62 | J9: 882.20303 | K9: 60.048581
A10: Renewable capex -25% | B10: p_capex_pv=570, p_capex_wind=870 | C10: 26.96732 | D10: 25.165982 | E10: -62.556289 | F10: 22.742376 | G10: 9.9583435 | H10: -18.133958 | I10: 1702.62 | J10: 1080.1468 | K10: 23.298667
A11: Renewable capex +25% | B11: p_capex_pv=950, p_capex_wind=1450 | C11: 47.298188 | D11: 45.49685 | E11: -30.505986 | F11: 27.871245 | G11: 15.087212 | H11: -10.575378 | I11: 1702.62 | J11: 825.64987 | K11: 55.10429
A12: Calibrated savings b -50% (buildings, industry) | B12: p_b=0.0665 | C12: 60.218143 | D12: 58.416805 | E12: -21.980819 | F12: 30.189684 | G12: 17.405651 | H12: -9.1680807 | I12: 1702.62 | J12: 921.08623 | K12: 63.421647
A13: Calibrated savings b +50% (buildings, industry) | B13: p_b=0.1995 | C13: 19.130082 | D13: 17.328743 | E13: -63.068881 | F13: 21.706155 | G13: 8.9221215 | H13: -17.65161 | I13: 1702.62 | J13: 921.08623 | K13: 18.813378
A14: Co-benefits c -50% (buildings, industry, AFOLU) | B14: p_c=0.0645 | C14: 39.674113 | D14: 37.872774 | E14: -15.919995 | F14: 25.947919 | G14: 13.163886 | H14: -3.0403253 | I14: 1702.62 | J14: 921.08623 | K14: 41.117512
A15: EMDC default WACC 15% | B15: p_r_emdc=0.15 | C15: 44.31363 | D15: 37.872774 | E15: -42.52485 | F15: 30.587436 | G15: 13.163886 | H15: -13.409846 | I15: 1702.62 | J15: 921.08623 | K15: 41.117512
A16: Rates compared in real terms | B16: p_basis=1 | C16: 14.478466 | D16: 37.872774 | E16: -42.52485 | F16: 17.808683 | G16: 13.163886 | H16: -13.409846 | I16: 1702.62 | J16: 921.08623 | K16: 41.117512
... A19: Incremental shares halved | B19: p_inc_ae=0.19, p_inc_chn=0.19, p_inc_emdc=0.12 | C19: 19.837056 | D19: 18.936387 | E19: -21.262425 | F19: 12.97396 | G19: 6.5819432 | H19: -6.7049228 | I19: 851.31 | J19: 460.54311 | K19: 41.117512

Sheet Inputs
A1: Inputs and scenario levers
A2: Blue = hard-coded input. Yellow fill = key assumption to review. † = not verified against the primary source, or an author's assumption. All money in USD billion, 2023 prices (IHLEG basis), unless stated.
A4: Key (named cell) | B4: Parameter | C4: Value | D4: Unit | E4: Source / note | F4: Fit
A5: Investment pools, 2030 (mitigation only)
A6: p_ce_world | B6: Clean energy investment need, world, 2030 | C6: 4800 | D6: USD bn/yr | E6: IHLEG 3 (Bhattacharya et al. 2024), clean energy from IEA; method note Table 4 | F6: G
A7: p_ce_emdc | B7: Clean energy, EMDCs other than China | C7: 1600 | D7: USD bn/yr | E7: IHLEG 3 (2024): EMDCs ex-China clean energy USD 1.6 tn; method note Table 4 | F7: G
A8: p_ce_chn | B8: Clean energy, China | C8: 850 | D8: USD bn/yr | E8: Derived: IEA-IFC (2023) EMDE 2.2-2.8 tn less EMDE ex-China 1.4-1.9 tn (midpoints 2.5 - 1.65). † | F8: M
A9: p_ce_ae | B9: Clean energy, advanced economies (residual) | C9: =p_ce_world-p_ce_emdc-p_ce_chn -> 2350 | D9: USD bn/yr | E9: Residual of the three lines above | F9: M
A10: p_nat_emdc | B10: Nature and agriculture (AFOLU), EMDCs ex-China | C10: 350 | D10: USD bn/yr | E10: IHLEG 3 (2024): nature and agriculture USD 0.3-0.4 tn, midpoint. Includes some non-mitigation nature spending. † | F10: M
A11: p_nbs_world | B11: Nature-based solutions, world, 2030 | C11: 399 | D11: USD bn/yr | E11: UNEP State of Finance for Nature (2021): NbS flows USD 133 bn/yr must triple by 2030 (133 x 3) | F11: M
A12: p_nat_ae | B12: AFOLU, advanced economies | C12: =MAX(0,p_nbs_world-p_nat_emdc)*p_ce_ae/(p_ce_ae+p_ce_chn) -> 35.984375 | D12: USD bn/yr | E12: World NbS less EMDC, split AE/China pro rata to clean energy. † | F12: P
A13: p_nat_chn | B13: AFOLU, China | C13: =MAX(0,p_nbs_world-p_nat_emdc)*p_ce_chn/(p_ce_ae+p_ce_chn) -> 13.015625 | D13: USD bn/yr | E13: As above. † | F13: P
A14: Sector split of clean energy (applied to every group; edit per group on Sector_Params)
A15: p_sh_gen | B15: Low-emission power generation | C15: 0.35 | D15: share | E15: IEA-IFC (2023), EMDEs early 2030s: 'just over a third' to low-emission generation | F15: M
A16: p_sh_grid | B16: Grids and storage | C16: 0.24 | D16: share | E16: IEA-IFC (2023): 'just under a quarter' | F16: M
A17: p_sh_end | B17: Efficiency and end use | C17: 0.33 | D17: share | E17: IEA-IFC (2023): 'another third' | F17: M
A18: p_sh_fuel | B18: Low-emission fuels and fuel supply | C18: 0.08 | D18: share | E18: IEA-IFC (2023): 'around 8%' | F18: M
A19: p_spl_trn | B19: of end use: transport | C19: 0.45 | D19: share of end use | E19: Author's assumption: EVs and charging are the largest end-use item. † | F19: P
A20: p_spl_bld | B20: of end use: buildings | C20: 0.35 | D20: share of end use | E20: Author's assumption. † | F20: P
A21: p_spl_ind | B21: of end use: industry | C21: =1-p_spl_trn-p_spl_bld -> 0.2 | D21: share of end use | E21: Residual | F21: P
A22: Total vs incremental
A23: p_inc_ae | B23: Incremental share of total, advanced economies | C23: 0.38 | D23: share | E23: McKinsey (2022): +USD 3.5 tn over today on USD 9.2 tn gross (3.5/9.2). Method note Table 5 | F23: M
A24: p_inc_chn | B24: Incremental share of total, China | C24: 0.38 | D24: share | E24: As AE (McKinsey global ratio). † | F24: M
A25: p_inc_emdc | B25: Incremental share of total, EMDCs | C25: 0.24 | D25: share | E25: CCDR synthesis USD 574 bn/yr incremental vs IHLEG USD 2.4 tn total (about a quarter). Method note Table 5 | F25: M
A26: Cost of capital (lens a: market)
A27: p_r_ae | B27: Market WACC, advanced economies (default) | C27: 0.055 | D27: rate | E27: IEA via IHLEG (2024): solar WACC 5-6% in AEs. Used where no country estimate exists | F27: M
A28: p_r_chn | B28: Market WACC, China (default) | C28: 0.06 | D28: rate | E28: Method note: assumed close to AEs. † | F28: M
A29: p_r_emdc | B29: Market WACC, EMDCs (default) | C29: 0.105 | D29: rate | E29: IEA via IHLEG (2024): 9-12% in EMDCs, midpoint | F29: M
A30: p_rh_ae | B30: High case WACC, advanced economies | C30: 0.07 | D30: rate | E30: Method note lens (a) high case | F30: M
A31: p_rh_chn | B31: High case WACC, China | C31: 0.08 | D31: rate | E31: Method note lens (a) high case | F31: M
A32: p_rh_emdc | B32: High case WACC, EMDCs | C32: 0.15 | D32: rate | E32: Method note lens (a) high case | F32: M
A33: p_use_obs | B33: Use observed country WACC (IRENA / Steffen)? 1=yes | C33: 1 | D33: switch | E33: Dashboard Finance 1 block. Average of the available observations
A34: p_use_dam | B34: Use Damodaran-based WACC where no observation? 1=yes | C34: 1 | D34: switch | E34: Fills coverage gaps from the Damodaran sheet (equation 5)
A35: p_calib | B35: Calibrate Damodaran WACC to observed level? 1=yes | C35: 1 | D35: switch | E35: Shifts the structural estimate by the mean gap to observed WACC over countries with both
A36: p_basis | B36: Rate basis: 0 = nominal (as published), 1 = real | C36: 0 | D36: switch | E36: IHLEG, IEA, Steffen and the 6% WB rate are compared as published in the method note (0). Set 1 to deflate market rates to real terms with the inflation input
A37: p_infl | B37: Inflation for real/nominal conversion (USD) | C37: 0.02 | D37: rate | E37: Assumption: long-run USD inflation. Also converts IRENA real WACC to nominal. † | F37: M
A38: Damodaran WACC build (equation 5) - used only where Damodaran data are present
A39: p_rf | B39: Risk-free rate (US 10-year Treasury) | C39: 0.042 | D39: rate | E39: Placeholder: approximate 2025-26 level. Update to the date of the Damodaran file. † | F39: M
A40: p_erp | B40: Mature-market equity risk premium | C40: 0.042 | D40: rate | E40: Damodaran, July 2026 update (4.20%), as reported by BVWire 22 Jul 2026. Check against ctryprem.xlsx | F40: M
A41: p_dv | B41: Debt share D/V, renewable projects | C41: 0.7 | D41: share | E41: Steffen et al. (2025) database, median 'Leverage (debt share)', all observations | F41: G
A42: p_beta | B42: Equity beta on mature ERP | C42: 1 | D42: x | E42: Assumption: average-risk project equity | F42: M
A43: p_lambda | B43: Exposure to country risk premium (lambda) | C43: 1 | D43: x | E43: Damodaran default: full exposure to CRP | F43: M
A44: p_tax_def | B44: Corporate tax rate where Damodaran gives none | C44: 0.25 | D44: rate | E44: Assumption. † | F44: M
A45: p_shift | B45: Calibration shift applied to Damodaran WACC (computed) | C45: =IF(AND(p_calib=1,p_n_overlap>0),SUM(Country_Data!$DP$5:$DP$199)/p_n_overlap-SUM(Country_Data!$DQ$5:$DQ$199)/p_n_overlap,0) -> 0 | D45: rate | E45: Mean(observed) less mean(Damodaran) over countries with both; 0 if switch off or no overlap
A46: Lens (b) and (c): World Bank rate, savings and co-benefits
A47: p_r_wb | B47: World Bank social discount rate | C47: 0.06 | D47: rate | E47: Fay et al. (2016), World Bank guidance note; Beyond the Gap and IMF GFSR use 6% | F47: G
A48: p_r_ibrd | B48: IBRD lending rate (memo) | C48: 0.052 | D48: rate | E48: Kharas & Rivard (2022): effective IBRD 10-year flexible loan ~5.2% | F48: M
A49: p_use_ibrd | B49: Use IBRD lending rate instead of 6% in lens (b)/(c)? 1=yes | C49: 0 | D49: switch | E49: Alternative reading of 'World Bank cost of capital'
A50: p_b | B50: Financial savings per USD of capital (b) | C50: 0.133 | D50: per yr | E50: Calibrated on SISEPUEDE LAC: BCR 1.70 at 6% x CRF 0.078. Method note Table 3 | F50: M
A51: p_wb_idx | B51: Weight on country fuel-cost index for b (0-1) | C51: 1 | D51: weight | E51: 1 = scale b by country fossil supply cost per tCO2 (CPAT) relative to world; 0 = uniform b
A52: p_c | B52: Local co-benefits per USD of capital (c) | C52: 0.129 | D52: per yr | E52: Calibrated on SISEPUEDE LAC: co-benefits 1.65 x cost at 6%. Method note Table 3 | F52: M
A53: p_wc_idx | B53: Weight on country co-benefit index for c (0-1) | C53: 1 | D53: weight | E53: 1 = scale c by country local externality cost per tCO2 (CPAT) relative to world; 0 = uniform c
A54: p_road | B54: Include road externalities in co-benefit index? 1=yes | C54: 0 | D54: switch | E54: 0 = local air pollution only. 1 adds congestion, accidents and road damage (SISEPUEDE counts them; EVs alone do not cut them)
A55: p_idx_min | B55: Index floor | C55: 0.25 | D55: x | E55: Guards small economies with tiny CO2 denominators
A56: p_idx_max | B56: Index cap | C56: 4 | D56: x | E56: As above
A57: p_a | B57: Abatement per USD 1,000 of capital (a) | C57: 0.35 | D57: tCO2e/yr | E57: Author's calculation, ~37 Gt over ~USD 110 tn (IEA NZE). Method note Table 3. † | F57: P
A58: p_spc_lo | B58: Shadow price of carbon 2030, low | C58: 50 | D58: USD/tCO2e | E58: World Bank (2017, 2024) | F58: G
A59: p_spc_hi | B59: Shadow price of carbon 2030, high | C59: 100 | D59: USD/tCO2e | E59: World Bank (2017, 2024) | F59: G
A60: Sector benefit methods (v1.1): engineering for power and transport, cost per tonne for fuels and AFOLU
A61: p_eng | B61: Use engineering savings for power and transport? 1=yes | C61: 1 | D61: switch | E61: 1 = derive b, c, a from country fuel mix, prices and externalities (CPAT, Ember). 0 = v1.0 calibrated ratios
A62: p_grid_credit | B62: Share of power-generation benefits credited to grids | C62: 0 | D62: weight | E62: 0 = grids are enabling capital with no savings of their own (conservative). 1 = same per-$ benefits as generation
A63: p_capex_pv | B63: Utility solar PV capital cost | C63: 760 | D63: USD/kW | E63: IRENA (2024) Renewable Power Generation Costs in 2023, global weighted average (method note Table C). † | F63: G
A64: p_capex_wind | B64: Onshore wind capital cost | C64: 1160 | D64: USD/kW | E64: IRENA (2024), as above. † | F64: G
A65: p_sh_pv | B65: Solar share of new generation investment | C65: 0.5 | D65: share | E65: Author's assumption. † | F65: M
A66: p_cf_pv | B66: Solar PV capacity factor | C66: 0.17 | D66: share | E66: Engineering norm, global average (IRENA range 0.15-0.18). † | F66: M
A67: p_cf_wind | B67: Onshore wind capacity factor | C67: 0.35 | D67: share | E67: Engineering norm, global average (IRENA range 0.3-0.4). † | F67: M
A68: p_om_re | B68: Renewable O&M, share of capital a year | C68: 0.015 | D68: share | E68: Engineering norm (~USD 10-20/kW-yr). † | F68: M
A69: p_hr_coal | B69: Heat rate, coal power | C69: 10 | D69: GJ/MWh | E69: Engineering norm, ~36% efficiency. † | F69: M
A70: p_hr_gas | B70: Heat rate, gas power | C70: 7.5 | D70: GJ/MWh | E70: Engineering norm, fleet ~48% efficiency. † | F70: M
A71: p_hr_oil | B71: Heat rate, oil power | C71: 10.5 | D71: GJ/MWh | E71: Engineering norm, ~34% efficiency. † | F71: M
A72: p_ef_coal | B72: CO2 factor, coal | C72: 0.0946 | D72: tCO2/GJ | E72: IPCC 2006 Guidelines Vol. 2 Table 2.2, other bituminous coal | F72: G
A73: p_ef_gas | B73: CO2 factor, natural gas | C73: 0.0561 | D73: tCO2/GJ | E73: IPCC 2006, Table 2.2 | F73: G
A74: p_ef_oil | B74: CO2 factor, residual fuel oil | C74: 0.0774 | D74: tCO2/GJ | E74: IPCC 2006, Table 2.2 | F74: G
... A84: p_cpt_afolu | B84: Abatement cost, AFOLU | C84: 50 | D84: USD/tCO2e | E84: IPCC AR6 WGIII SPM C.9.1: AFOLU potential 8-14 Gt/yr below USD 100/t, 30-50% of it below USD 20/t. 50 is an assumed average. † | F84: P
A85: Allocation of group totals to countries (equation 1 / 3)
A86: p_beta_alloc | B86: Weight on physical driver vs GDP (PPP) | C86: 0.5 | D86: weight | E86: Author's assumption: half current physical activity (replacement), half economic size (growth). † | F86: P
A87: p_phi | B87: Pass-through of local price level to capital cost | C87: 0.5 | D87: elasticity | E87: Author's assumption: about half of clean-energy capex is traded equipment. 0 = none, 1 = full. † | F87: P
A88: PIMA: public investment efficiency
A89: p_ps_ae | B89: Public share of investment, AEs | C89: 0.3 | D89: share | E89: Author's assumption. † | F89: P
A90: p_ps_chn | B90: Public share of investment, China | C90: 0.5 | D90: share | E90: Author's assumption (SOE-led). † | F90: P
A91: p_ps_emdc | B91: Public share of investment, EMDCs | C91: 0.4 | D91: share | E91: IEA-IFC (2023): about 60% of EMDE clean energy investment must be private | F91: M
A92: p_gap_ae | B92: Efficiency gap, advanced economies | C92: 0.13 | D92: share | E92: IMF (2015) Making Public Investment More Efficient | F92: G
A93: p_gap_em | B93: Efficiency gap, emerging markets | C93: 0.27 | D93: share | E93: IMF (2015) | F93: G
A94: p_gap_lic | B94: Efficiency gap, low-income developing | C94: 0.4 | D94: share | E94: IMF (2015) | F94: G
A95: p_use_pefa | B95: Use PEFA PI-11 score where available? 1=yes | C95: 1 | D95: switch | E95: Linear map: score 1 -> LIC gap, score 4 -> AE gap (author's mapping †)
A96: p_reform | B96: PIMA reform scenario? 1=yes | C96: 0 | D96: switch | E96: IMF (2015): stronger PIM institutions can close up to two-thirds of the gap
A97: p_reform_close | B97: Share of gap closed by reform | C97: 0.66666667 | D97: share | E97: IMF (2015) | F97: M
A99: Switch cells take 0 or 1. Rates and shares are stored as fractions (0.06 = 6%).
A102: Computed world benchmarks
A103: p_fc_world | B103: World fuel bill per tCO2 (investment-weighted) | C103: =SUM(Country_Data!$ED$5:$ED$199)/SUM(Country_Data!$EF$5:$EF$199) -> 161.00734 | D103: USD/t
A104: p_cb_world | B104: World local co-benefit per tCO2 (investment-weighted) | C104: =SUM(Country_Data!$EE$5:$EE$199)/SUM(Country_Data!$EF$5:$EF$199) -> 52.590795 | D104: USD/t
A105: p_n_overlap | B105: Countries with both observed and Damodaran WACC | C105: =SUM(Country_Data!$DO$5:$DO$199) -> 0 | D105: count

Sheet Sector_Params
A1: Sector parameters and 2030 investment pools by group (USD bn/yr)
A2: Blue cells are editable. Incremental shares default to the group values on Inputs; overwrite a cell to set a sector-specific share. Technology premium is added to the country market WACC in lens (a) only.
A4: Code | B4: Sector | C4: Share of clean energy | D4: Asset life (yrs) | E4: Tech premium (lens a) | F4: Incr. share AE | G4: Incr. share China | H4: Incr. share EMDC | I4: Savings multiplier (b) | J4: Co-benefit multiplier (c) | K4: Benefit method (v1.1) | L4: Allocation driver | M4: Life source
A5: GEN | B5: Power generation (low-emission) | C5: =p_sh_gen -> 0.35 | D5: 25 | E5: 0 | F5: =p_inc_ae -> 0.38 | G5: =p_inc_chn -> 0.38 | H5: =p_inc_emdc -> 0.24 | I5: 1 | J5: 1 | K5: Engineering: displaced fossil power (Ember mix x heat rates x CPAT fuel cost, air pollution; IPCC CO2 factors) | L5: Electricity demand (TWh) | M5: Method note: 25 yrs (solar 25-30, wind 25)
A6: GRID | B6: Grids and storage | C6: =p_sh_grid -> 0.24 | D6: 40 | E6: 0 | F6: =p_inc_ae -> 0.38 | G6: =p_inc_chn -> 0.38 | H6: =p_inc_emdc -> 0.24 | I6: 1 | J6: 1 | K6: Enabling: no own benefits; p_grid_credit x generation benefits | L6: Electricity demand (TWh) | M6: Method note: grids 40 yrs (storage 15 - blended up)
A7: TRN | B7: Transport (EVs, charging, transit) | C7: =p_sh_end*p_spl_trn -> 0.1485 | D7: 12 | E7: 0 | F7: =p_inc_ae -> 0.38 | G7: =p_inc_chn -> 0.38 | H7: =p_inc_emdc -> 0.24 | I7: 1 | J7: 1 | K7: Engineering: EV vs gasoline car per vehicle (CPAT fuel and power prices, gasoline air pollution) | L7: Road fuel energy (EJ) | M7: Method note: vehicles 12 yrs
A8: BLD | B8: Buildings (efficiency, heat pumps) | C8: =p_sh_end*p_spl_bld -> 0.1155 | D8: 25 | E8: 0 | F8: =p_inc_ae -> 0.38 | G8: =p_inc_chn -> 0.38 | H8: =p_inc_emdc -> 0.24 | I8: 1 | J8: 1 | K8: Calibrated: SISEPUEDE b and c x CPAT country index; a = p_a | L8: Building energy use (EJ) | M8: Method note: 20-30 yrs
A9: IND | B9: Industry (efficiency, electrification, CCS) | C9: =p_sh_end*p_spl_ind -> 0.066 | D9: 25 | E9: 0 | F9: =p_inc_ae -> 0.38 | G9: =p_inc_chn -> 0.38 | H9: =p_inc_emdc -> 0.24 | I9: 1 | J9: 1 | K9: Calibrated: SISEPUEDE b and c x CPAT country index; a = p_a | L9: Industrial energy use (EJ) | M9: Method note: CCS 25 yrs
A10: FUEL | B10: Low-emission fuels and fuel supply | C10: =p_sh_fuel -> 0.08 | D10: 20 | E10: 0 | F10: =p_inc_ae -> 0.38 | G10: =p_inc_chn -> 0.38 | H10: =p_inc_emdc -> 0.24 | I10: 1 | J10: 1 | K10: Cost per tonne: no savings or co-benefits; a = 1000 x CRF(6%) / p_cpt_fuel | L10: Fossil energy supply (EJ) | M10: Assumption †
A11: AFOLU | B11: AFOLU and nature | C11: n.a. | D11: 30 | E11: 0 | F11: =p_inc_ae -> 0.38 | G11: =p_inc_chn -> 0.38 | H11: =p_inc_emdc -> 0.24 | I11: 1 | J11: 1 | K11: Cost per tonne: no savings; c = p_c (ecosystem co-benefits); a = 1000 x CRF(6%) / p_cpt_afolu | L11: Non-CO2 GHG + net LULUCF source (MtCO2e) | M11: Assumption †
B12: Total (energy sectors) | C12: =SUM(C5:C10) -> 1
A14: Investment pools, 2030 (USD bn/yr, total investment)
A15: Code | B15: Sector | C15: AE | D15: China | E15: EMDC | F15: World
A16: GEN | B16: Power generation (low-emission) | C16: =p_ce_ae*C5 -> 822.5 | D16: =p_ce_chn*C5 -> 297.5 | E16: =p_ce_emdc*C5 -> 560 | F16: =SUM(C16:E16) -> 1680
A17: GRID | B17: Grids and storage | C17: =p_ce_ae*C6 -> 564 | D17: =p_ce_chn*C6 -> 204 | E17: =p_ce_emdc*C6 -> 384 | F17: =SUM(C17:E17) -> 1152
A18: TRN | B18: Transport (EVs, charging, transit) | C18: =p_ce_ae*C7 -> 348.975 | D18: =p_ce_chn*C7 -> 126.225 | E18: =p_ce_emdc*C7 -> 237.6 | F18: =SUM(C18:E18) -> 712.8
A19: BLD | B19: Buildings (efficiency, heat pumps) | C19: =p_ce_ae*C8 -> 271.425 | D19: =p_ce_chn*C8 -> 98.175 | E19: =p_ce_emdc*C8 -> 184.8 | F19: =SUM(C19:E19) -> 554.4
A20: IND | B20: Industry (efficiency, electrification, CCS) | C20: =p_ce_ae*C9 -> 155.1 | D20: =p_ce_chn*C9 -> 56.1 | E20: =p_ce_emdc*C9 -> 105.6 | F20: =SUM(C20:E20) -> 316.8
A21: FUEL | B21: Low-emission fuels and fuel supply | C21: =p_ce_ae*C10 -> 188 | D21: =p_ce_chn*C10 -> 68 | E21: =p_ce_emdc*C10 -> 128 | F21: =SUM(C21:E21) -> 384
A22: AFOLU | B22: AFOLU and nature | C22: =p_nat_ae -> 35.984375 | D22: =p_nat_chn -> 13.015625 | E22: =p_nat_emdc -> 350 | F22: =SUM(C22:E22) -> 399
B23: Total | C23: =SUM(C16:C22) -> 2385.9844 | D23: =SUM(D16:D22) -> 863.01562 | E23: =SUM(E16:E22) -> 1950 | F23: =SUM(F16:F22) -> 5199

Sheet Country_Data
A1: Country data (inputs from the dashboard panel, CPAT and WEO) and country parameters (formulas)
A2: Blue = data loaded by the build script; black = formulas. Blank = not available (nothing imputed). Rates as fractions.
A3: iso | B3: name | C3: region | D3: income | E3: group | F3: gdp24 | G3: ppp24 | H3: g25 | I3: g26 | J3: mit.pop.mn | K3: mit.co2.tot.1 | L3: mit.ghg.tot.exc.1 | M3: mit.ghg.tot.inc.1 | N3: mit.con.ecy.ind.1 | O3: mit.con.ecy.res.1 | P3: mit.con.ecy.other.1 | Q3: mit.con.nga.ind.1 | R3: mit.con.nga.res.1 | S3: mit.con.nga.pow.1 | T3: mit.con.nga.other.1 | U3: mit.con.coa.ind.1 | V3: mit.con.coa.res.1 | W3: mit.con.coa.pow.1 | X3: mit.con.coa.other.1 | Y3: mit.con.gso.all.1 | Z3: mit.con.die.all.1 | AA3: mit.con.lpg.all.1 | AB3: mit.con.ker.all.1 | AC3: mit.con.oop.all.1 | AD3: mit.sup.cost.gso.all.1 | AE3: mit.sup.cost.die.all.1 | AF3: mit.sup.cost.lpg.all.1 | AG3: mit.sup.cost.ker.all.1 | AH3: mit.sup.cost.oop.all.1 | AI3: mit.sup.cost.coa.ind.1 | AJ3: mit.sup.cost.coa.res.1 | AK3: mit.sup.cost.coa.pow.1 | AL3: mit.sup.cost.coa.other.1 | AM3: mit.sup.cost.nga.ind.1 | AN3: mit.sup.cost.nga.res.1 | AO3: mit.sup.cost.nga.pow.1 | AP3: mit.sup.cost.nga.other.1 | AQ3: mit.airpol.con.all.all.1 | AR3: mit.con.con.all.all.1 | AS3: mit.roda.con.all.all.1 | AT3: mit.rodd.con.all.all.1 | AU3: mit.ecy.renshare.1 | AV3: mit.sup.cost.ecy.res.1 | AW3: mit.airpol.cost.coa.pow.1 | AX3: mit.airpol.cost.nga.pow.1 | AY3: mit.airpol.cost.oop.1 | AZ3: mit.airpol.cost.gso.all.1 | BA3: gross_debt_pct_gdp | BB3: interest_to_revenue_pct | BC3: capex_execution_rate_pct | BD3: pefa_pi11_pim_score | BE3: pefa_pi122_asset_monitoring | BF3: climate_pfm_diagnostic_on_record | BG3: wacc_solar_real_aftertax_pct | BH3: wacc_steffen_nominal_aftertax_pct | BI3: wacc_steffen_nominal_aftertax_pct__year | BJ3: wacc_n_sources | BK3: wacc_iea_observatory_available | BL3: ids_official_private_rate_spread_pp | BM3: ids_private_creditor_rate_pct | BN3: ids_avg_maturity_years | BO3: mitigation_finance_received_pct_gdp | BP3: ppi_commitments_pct_gdp | BQ3: em_year | BR3: em_Total generation | BS3: em_Coal | BT3: em_Gas | BU3: em_Other fossil | BV3: gdp30 | BW3: ppp_use | BX3: plevel | BY3: has_cpat | BZ3: elec | CA3: d_trn | CB3: d_bld | CC3: d_ind | CD3: d_fuel | CE3: d_afolu | CF3: fuelexp | CG3: co2_pos | CH3: fc_t | CI3: lext | CJ3: cb_t | CK3: idx_b | CL3: idx_c | CM3: b_c | CN3: c_c | CO3: fos_sh | CP3: fos_tot | CQ3: sh_coal | CR3: sh_gas | CS3: sh_oil | CT3: re_kwh | CU3: gen_ok | CV3: fuel_mwh | CW3: co2_mwh | CX3: ap_mwh | CY3: grid_ef | CZ3: b_gen | DA3: c_gen | DB3: a_gen | DC3: trn_ok | DD3: ev_sav | DE3: b_trn | DF3: c_trn | DG3: a_trn | DH3: dam_ds | DI3: dam_crp | DJ3: dam_tax | DK3: w_irena | DL3: w_stef | DM3: w_obs | DN3: w_dam | DO3: ovl | DP3: ovl_obs | DQ3: ovl_dam | DR3: w_damc | DS3: w_grp | DT3: w_grph | DU3: w_sel_n | DV3: w_src | DW3: r_a | DX3: r_ah | DY3: pim_gap | DZ3: pim_src | EA3: pub_sh | EB3: pim_mult | EC3: inv_tot | ED3: fc_wI | EE3: cb_wI | EF3: w_I
A4: ISO3 | B4: Country | C4: WB region | D4: WB income group | E4: IHLEG group (AE / China / EMDC) | F4: GDP 2024 (USD bn), WEO | G4: GDP 2024 (PPP int$ bn), WEO | H4: Real growth 2025 (%), WEO | I4: Real growth 2026 (%), WEO | J4: Population (mn), CPAT 2024 | K4: CO2, energy (Mt), CPAT 2024 | L4: GHG excl. LULUCF (MtCO2e), CPAT 2024 | M4: GHG incl. LULUCF (MtCO2e), CPAT 2024 | N4: Electricity, industry (TWh), CPAT 2024 | O4: Electricity, residential (TWh), CPAT 2024 | P4: Electricity, other (TWh), CPAT 2024 | Q4: Gas, industry (EJ), CPAT 2024 | R4: Gas, residential (EJ), CPAT 2024 | S4: Gas, power (EJ), CPAT 2024 | T4: Gas, other (EJ), CPAT 2024 | U4: Coal, industry (EJ), CPAT 2024 | V4: Coal, residential (EJ), CPAT 2024 | W4: Coal, power (EJ), CPAT 2024 | X4: Coal, other (EJ), CPAT 2024 | Y4: Gasoline (bn litres), CPAT 2024 | Z4: Diesel (bn litres), CPAT 2024 | AA4: LPG (bn litres), CPAT 2024 | AB4: Kerosene (bn litres), CPAT 2024 | AC4: Other oil products (bn litres), CPAT 2024 | AD4: Supply cost gasoline ($/l), CPAT 2024 | AE4: Supply cost diesel ($/l), CPAT 2024 | AF4: Supply cost LPG ($/l), CPAT 2024 | AG4: Supply cost kerosene ($/l), CPAT 2024 | AH4: Supply cost other oil ($/l), CPAT 2024 | AI4: Supply cost coal, industry ($/GJ), CPAT 2024 | AJ4: Supply cost coal, residential ($/GJ), CPAT 2024 | AK4: Supply cost coal, power ($/GJ), CPAT 2024 | AL4: Supply cost coal, other ($/GJ), CPAT 2024 | AM4: Supply cost gas, industry ($/GJ), CPAT 2024 | AN4: Supply cost gas, residential ($/GJ), CPAT 2024 | AO4: Supply cost gas, power ($/GJ), CPAT 2024 | AP4: Supply cost gas, other ($/GJ), CPAT 2024 | AQ4: Local air pollution cost (US$ bn), CPAT 2024 | AR4: Congestion cost (US$ bn), CPAT 2024 | AS4: Road accident cost (US$ bn), CPAT 2024 | AT4: Road damage cost (US$ bn), CPAT 2024 | AU4: Renewable share of electricity (CPAT), CPAT 2024 | AV4: Supply cost electricity, residential ($/kWh), CPAT 2024 | AW4: Air pollution cost coal, power ($/GJ), CPAT 2024 | AX4: Air pollution cost gas, power ($/GJ), CPAT 2024 | AY4: Air pollution cost other oil ($/l), CPAT 2024 | AZ4: Air pollution cost gasoline ($/l), CPAT 2024 | BA4: Gross debt, gen. govt (% GDP) [dashboard: Fiscal] | BB4: Interest-to-revenue (%) [dashboard: Fiscal] | BC4: Capex execution rate (%) [dashboard: PIMA] | BD4: PEFA PI-11 PIM score (1-4) [dashboard: PIMA] | BE4: PEFA PI-12.2 asset monitoring (1-4) [dashboard: PIMA] | BF4: Climate-PFM diagnostic on record (0/1) [dashboard: PIMA] | BG4: WACC solar, real after-tax (%), IRENA 2021 [dashboard: CoC] | BH4: WACC nominal after-tax (%), Steffen et al. [dashboard: CoC] | BI4: Steffen observation year [dashboard: CoC] | BJ4: WACC evidence strength (0-3) [dashboard: CoC] | BK4: IEA CoC Observatory (0/1) [dashboard: CoC] | BL4: Official-private rate spread (pp), IDS [dashboard: CoC] | BM4: Private creditor rate (%), IDS [dashboard: CoC] | BN4: Avg maturity new commitments (yrs), IDS [dashboard: CoC] | BO4: Mitigation finance received (% GDP), OECD [dashboard: Finance] | BP4: PPI commitments (% GDP) [dashboard: Finance] | BQ4: Ember year | BR4: Generation, total (TWh), Ember | BS4: Coal (TWh), Ember | BT4: Gas (TWh), Ember | BU4: Other fossil (TWh), Ember | BV4: GDP 2030 (USD bn, 2024 prices) | BW4: GDP PPP used for weights | BX4: Price level (GDP USD / GDP PPP) | BY4: CPAT data? (1/0) | BZ4: Electricity demand (TWh) | CA4: Road fuel energy (EJ) | CB4: Building energy use (EJ) | CC4: Industrial energy use (EJ) | CD4: Fossil energy supply (EJ) | CE4: Non-CO2 GHG + net LULUCF source (MtCO2e) | CF4: Fossil fuel bill at supply cost (USD bn) | CG4: CO2 used in index (Mt) | CH4: Fuel bill per tCO2 (USD/t) | CI4: Local externality cost (USD bn) | CJ4: Local co-benefit per tCO2 (USD/t) | CK4: Fuel-cost index (world = 1) | CL4: Co-benefit index (world = 1) | CM4: Savings ratio b (per yr) | CN4: Co-benefit ratio c (per yr) | CO4: Fossil share of generation, Ember | CP4: helper: fossil generation (TWh) | CQ4: Coal share of fossil generation | CR4: Gas share of fossil generation | CS4: Oil/other share of fossil generation | CT4: RE output per USD 1,000 (kWh/yr) | CU4: Engineering power data complete? (1/0) | CV4: Fuel cost of displaced fossil power (USD/MWh) | CW4: CO2 of displaced fossil power (t/MWh) | CX4: Air pollution of displaced fossil power (USD/MWh) | CY4: Average grid CO2 (t/MWh) | CZ4: b power: fuel saved per $ less RE O&M | DA4: c power: air pollution avoided per $ | DB4: a power: tCO2/yr per $1,000 | DC4: Engineering transport data complete? (1/0) | DD4: EV saving per vehicle (USD/yr) | DE4: b transport: saving per $ of premium | DF4: c transport: air pollution avoided per $ | DG4: a transport: tCO2/yr per $1,000 | DH4: Damodaran default spread | DI4: Damodaran country risk premium | DJ4: Damodaran corporate tax | DK4: IRENA WACC, nominal | DL4: Steffen WACC, nominal | DM4: Observed WACC (avg of available), nominal | DN4: Damodaran WACC (eq. 5), nominal | DO4: Overlap obs & Damodaran (1/0) | DP4: helper: obs if overlap | DQ4: helper: Damodaran if overlap | DR4: Damodaran WACC, calibrated | DS4: Group default WACC | DT4: Group high-case WACC | DU4: Market WACC selected, nominal | DV4: WACC source | DW4: Lens (a) rate, central | DX4: Lens (a) rate, high | DY4: PIM efficiency gap | DZ4: PIM gap source | EA4: Public share of investment | EB4: PIMA multiplier on investment | EC4: Total investment I (from Results_Country) | ED4: helper: fuel bill per t x I | EE4: helper: co-benefit per t x I | EF4: helper: I where CPAT data
A5: USA | B5: United States | C5: North America | D5: High income | E5: AE | F5: 29298.025 | G5: 29298.025 | H5: 2.117 | I5: 2.324 | J5: 345.42657 | K5: 5445.106 | L5: 6817.344 | M5: 6080.938 | N5: 2439.4512 | O5: 1639.0866 | P5: 146.60976 | Q5: 10.268996 | R5: 10.308221 | S5: 13.159987 | T5: 0.060960446 | U5: 0.57988998 | V5: 0.14075479 | W5: 8.5999238 | X5: 0 | Y5: 482.72417 | Z5: 245.05623 | AA5: 14.212704 | AB5: 62.002549 | AC5: 36.430289 | AD5: 0.801113 | AE5: 0.65939 | AF5: 0.550196 | AG5: 0.703138 | AH5: 0.41922847 | AI5: 2.845 | AJ5: 6.01126 | AK5: 1.746 | AL5: 1.8787875 | AM5: 8.52 | AN5: 12.69448 | AO5: 2.492 | AP5: 7.4441272 | AQ5: 117.01565 | AR5: 469.28343 | AS5: 61.376444 | AT5: 38.964382 | AU5: 0.28314663 | AV5: 0.190364 | AW5: 1.467504 | AX5: 1.182382 | AY5: 0.1834809 | AZ5: 0.038074 | BA5: 122.27 | BB5: 11.67 | BF5: 0 | BH5: 5.705 | BI5: 2020 | BJ5: 1 | BQ5: 2025 | BR5: 4519.79 | BS5: 737.15 | BT5: 1807.34 | BU5: 31.72 | BV5: =F5*(1+N(H5)/100)*(1+N(I5)/100)^5 -> 33560.153 | BW5: =IF(N(G5)>0,G5,F5) -> 29298.025 | BX5: =F5/BW5 -> 1 | BY5: =IF(ISNUMBER(K5),1,0) -> 1 | BZ5: =IF(BY5=0,"",N(N5)+N(O5)+N(P5)) -> 4225.1475 | CA5: =IF(BY5=0,"",(N(Y5)*34.2+N(Z5)*38.6)/1000) -> 25.968337 | CB5: =IF(BY5=0,"",N(O5)*0.0036+N(R5)+N(V5)+(N(AA5)*25.3+N(AB5)*37)/1000) -> 19.003363 | CC5: =IF(BY5=0,"",N(N5)*0.0036+N(Q5)+N(U5)+N(T5)+N(X5)+N(AC5)*38/1000) -> 21.076222 | CD5: =IF(BY5=0,"",N(Q5)+N(R5)+N(S5)+N(T5)+N(U5)+N(V5)+N(W5)+N(X5)+(N(Y5)*34.2+N(Z5)*38.6+N(AA5)*25.3+N(AB5)*37+N(AC5)*38)/1000) -> 73.125097 | CE5: =IF(BY5=0,"",MAX(0,N(L5)-N(K5))+MAX(0,N(M5)-N(L5))) -> 1372.238 | CF5: =IF(BY5=0,"",N(Y5)*N(AD5)+N(Z5)*N(AE5)+N(AA5)*N(AF5)+N(AB5)*N(AG5)+N(AC5)*N(AH5)+N(U5)*N(AI5)+N(V5)*N(AJ5)+N(W5)*N(AK5)+N(X5)*N(AL5)+N(Q5)*N(AM5)+N(R5)*N(AN5)+N(S5)*N(AO5)+N(T5)*N(AP5)) -> 884.10218 | CG5: =IF(AND(BY5=1,N(K5)>0),K5,0) -> 5445.106 | CH5: =IF(CG5>0,CF5*1000/CG5,"") -> 162.36639 | CI5: =IF(BY5=0,"",N(AQ5)+p_road*(N(AR5)+N(AS5)+N(AT5))) -> 117.01565 | CJ5: =IF(CG5>0,CI5*1000/CG5,"") -> 21.490059 | CK5: =IF(CH5="",1,MIN(p_idx_max,MAX(p_idx_min,CH5/p_fc_world))) -> 1.0084409 | CL5: =IF(CJ5="",1,MIN(p_idx_max,MAX(p_idx_min,CJ5/p_cb_world))) -> 0.40862777 | CM5: =p_b*(1-p_wb_idx+p_wb_idx*CK5) -> 0.13412263 | CN5: =p_c*(1-p_wc_idx+p_wc_idx*CL5) -> 0.052712982 | CO5: =IF(N(BR5)>0,(N(BS5)+N(BT5)+N(BU5))/BR5,"") -> 0.56998445 | CP5: =N(BS5)+N(BT5)+N(BU5) -> 2576.21 | CQ5: =IF(CP5>0,N(BS5)/CP5,"") -> 0.28613739 | CR5: =IF(CP5>0,N(BT5)/CP5,"") -> 0.70154995 | CS5: =IF(CP5>0,N(BU5)/CP5,"") -> 0.012312661 | CT5: =1000*(p_sh_pv*p_cf_pv/p_capex_pv+(1-p_sh_pv)*p_cf_wind/p_capex_wind)*8760 -> 2301.2886 | CU5: =IF(AND(ISNUMBER(CO5),ISNUMBER(CQ5),BY5=1),1,0) -> 1 | CV5: =IF(CU5=0,"",CQ5*p_hr_coal*N(AK5)+CR5*p_hr_gas*N(AO5)+CS5*p_hr_oil*N(AH5)/p_gj_l_oil) -> 19.512049 | CW5: =IF(CU5=0,"",CQ5*p_hr_coal*p_ef_coal+CR5*p_hr_gas*p_ef_gas+CS5*p_hr_oil*p_ef_oil) -> 0.57586961 | CX5: =IF(CU5=0,"",CQ5*p_hr_coal*N(AW5)+CR5*p_hr_gas*N(AX5)+CS5*p_hr_oil*N(AY5)/p_gj_l_oil) -> 11.03486 | CY5: =IF(CU5=0,"",CO5*CW5) -> 0.32823672 | CZ5: =IF(CU5=0,"",CT5*CO5*CV5/1000/1000-p_om_re) -> 0.010593929 | DA5: =IF(CU5=0,"",CT5*CO5*CX5/1000/1000) -> 0.014474412 | DB5: =IF(CU5=0,"",CT5*CO5*CW5/1000) -> 0.75536741 | DC5: =IF(AND(CU5=1,ISNUMBER(AD5),ISNUMBER(AV5)),1,0) -> 1 | DD5: =IF(DC5=0,"",p_ev_km*p_ice_l/100*AD5-p_ev_km*p_ev_kwh*AV5+p_ev_km*p_ev_maint) -> 567.26932 | DE5: =IF(DC5=0,"",DD5/p_ev_prem) -> 0.11345387 | DF5: =IF(DC5=0,"",p_ev_km*p_ice_l/100*N(AZ5)/p_ev_prem) -> 0.00856665 | DG5: =IF(DC5=0,"",1000/p_ev_prem*(p_ev_km*p_ice_l/100*p_gj_l_gso*p_ef_gso-p_ev_km*p_ev_kwh/1000*CY5)) -> 0.35601567 | DH5: =IFERROR(IF(INDEX(Damodaran!$D:$D,MATCH(A5,Damodaran!$A:$A,0))="","",INDEX(Damodaran!$D:$D,MATCH(A5,Damodaran!$A:$A,0))),"") | DI5: =IFERROR(IF(INDEX(Damodaran!$E:$E,MATCH(A5,Damodaran!$A:$A,0))="","",INDEX(Damodaran!$E:$E,MATCH(A5,Damodaran!$A:$A,0))),"") | DJ5: =IFERROR(IF(INDEX(Damodaran!$G:$G,MATCH(A5,Damodaran!$A:$A,0))="","",INDEX(Damodaran!$G:$G,MATCH(A5,Damodaran!$A:$A,0))),"") | DK5: =IF(ISNUMBER(BG5),(1+BG5/100)*(1+p_infl)-1,"") | DL5: =IF(ISNUMBER(BH5),BH5/100,"") -> 0.05705 | DM5: =IF(COUNT(DK5,DL5)=0,"",AVERAGE(DK5,DL5)) -> 0.05705 | DN5: =IF(OR(DH5="",DI5=""),"",p_dv*(p_rf+DH5)*(1-IF(DJ5="",p_tax_def,DJ5))+(1-p_dv)*(p_rf+p_beta*p_erp+p_lambda*DI5)) | DO5: =IF(AND(ISNUMBER(DM5),ISNUMBER(DN5)),1,0) -> 0 | DP5: =IF(DO5=1,DM5,0) -> 0 | DQ5: =IF(DO5=1,DN5,0) -> 0 | DR5: =IF(DN5="","",DN5+p_shift) | DS5: =IF(E5="AE",p_r_ae,IF(E5="China",p_r_chn,p_r_emdc)) -> 0.055 | DT5: =IF(E5="AE",p_rh_ae,IF(E5="China",p_rh_chn,p_rh_emdc)) -> 0.07 | DU5: =IF(AND(p_use_obs=1,ISNUMBER(DM5)),DM5,IF(AND(p_use_dam=1,ISNUMBER(DR5)),DR5,DS5)) -> 0.05705 | DV5: =IF(AND(p_use_obs=1,ISNUMBER(DM5)),"Observed (IRENA/Steffen)",IF(AND(p_use_dam=1,ISNUMBER(DR5)),"Damodaran (eq. 5)","Group default (IHLEG)")) -> Observed (IRENA/Steffen) | DW5: =IF(p_basis=1,(1+DU5)/(1+p_infl)-1,DU5) -> 0.05705 | DX5: =DW5+(DT5-DS5) -> 0.07205 | DY5: =IF(AND(p_use_pefa=1,ISNUMBER(BD5)),p_gap_lic-(BD5-1)/3*(p_gap_lic-p_gap_ae),IF(E5="AE",p_gap_ae,IF(D5="Low income",p_gap_lic,p_gap_em)))*(1-p_reform*p_reform_close) -> 0.13 | DZ5: =IF(AND(p_use_pefa=1,ISNUMBER(BD5)),"PEFA PI-11","Income-group default (IMF 2015)") -> Income-group default (IMF 2015) | EA5: =IF(E5="AE",p_ps_ae,IF(E5="China",p_ps_chn,p_ps_emdc)) -> 0.3 | EB5: =(1-EA5)+EA5/(1-DY5) -> 1.0448276 | EC5: =Results_Country!F5 -> 1069.0936 | ED5: =IF(CH5="",0,CH5*EC5) -> 173584.87 | EE5: =IF(CJ5="",0,CJ5*EC5) -> 22974.885 | EF5: =IF(CH5="",0,EC5) -> 1069.0936
A6: CHN | B6: China | C6: East Asia & Pacific | D6: Upper middle income | E6: China | F6: 18945.112 | G6: 38209.549 | H6: 4.959 | I6: 4.413 | J6: 1419.3213 | K6: 13206.767 | L6: 16257.103 | M6: 15609.747 | N6: 6415.8632 | O6: 1531.5154 | P6: 1101.2597 | Q6: 6.7171519 | R6: 3.25633 | S6: 1.1050468 | T6: 1.2383012 | U6: 21.195376 | V6: 2.6260901 | W6: 57.938198 | X6: 0.54846469 | Y6: 208.09895 | Z6: 203.26701 | AA6: 116.98398 | AB6: 44.219572 | AC6: 142.65651 | AD6: 0.794906 | AE6: 0.736181 | AF6: 0.596575 | AG6: 0.653034 | AH6: 0.5433453 | AI6: 7.656 | AJ6: 2.21593 | AK6: 4.109 | AL6: 4.9677196 | AM6: 13.283 | AN6: 18.25741 | AO6: 13.283 | AP6: 14.745136 | AQ6: 1790.2659 | AR6: 49.374988 | AS6: 35.508207 | AT6: 33.990616 | AU6: 0.47897378 | AV6: 0.074173 | AW6: 9.186285 | AX6: 3.78587 | AY6: 0.79761846 | AZ6: 0.240084 | BA6: 90.421 | BB6: 3.693 | BF6: 1 | BG6: 2.5 | BH6: 3.23 | BI6: 2020 | BJ6: 2 | BL6: 0.656 | BM6: 5.003 | BN6: 12.477 | BO6: 0.01 | BP6: 0.137 | BQ6: 2025 | BR6: 10578.05 | BS6: 5772.37 | BT6: 317.89 | BU6: 88.71 | BV6: =F6*(1+N(H6)/100)*(1+N(I6)/100)^5 -> 24676.851 | BW6: =IF(N(G6)>0,G6,F6) -> 38209.549 | BX6: =F6/BW6 -> 0.4958214 | BY6: =IF(ISNUMBER(K6),1,0) -> 1 | BZ6: =IF(BY6=0,"",N(N6)+N(O6)+N(P6)) -> 9048.6382 | CA6: =IF(BY6=0,"",(N(Y6)*34.2+N(Z6)*38.6)/1000) -> 14.963091 | CB6: =IF(BY6=0,"",N(O6)*0.0036+N(R6)+N(V6)+(N(AA6)*25.3+N(AB6)*37)/1000) -> 15.991694 | CC6: =IF(BY6=0,"",N(N6)*0.0036+N(Q6)+N(U6)+N(T6)+N(X6)+N(AC6)*38/1000) -> 58.217349 | CD6: =IF(BY6=0,"",N(Q6)+N(R6)+N(S6)+N(T6)+N(U6)+N(V6)+N(W6)+N(X6)+(N(Y6)*34.2+N(Z6)*38.6+N(AA6)*25.3+N(AB6)*37+N(AC6)*38)/1000) -> 119.60482 | CE6: =IF(BY6=0,"",MAX(0,N(L6)-N(K6))+MAX(0,N(M6)-N(L6))) -> 3050.336 | CF6: =IF(BY6=0,"",N(Y6)*N(AD6)+N(Z6)*N(AE6)+N(AA6)*N(AF6)+N(AB6)*N(AG6)+N(AC6)*N(AH6)+N(U6)*N(AI6)+N(V6)*N(AJ6)+N(W6)*N(AK6)+N(X6)*N(AL6)+N(Q6)*N(AM6)+N(R6)*N(AN6)+N(S6)*N(AO6)+N(T6)*N(AP6)) -> 1081.7358 | CG6: =IF(AND(BY6=1,N(K6)>0),K6,0) -> 13206.767 | CH6: =IF(CG6>0,CF6*1000/CG6,"") -> 81.907692 | CI6: =IF(BY6=0,"",N(AQ6)+p_road*(N(AR6)+N(AS6)+N(AT6))) -> 1790.2659 | CJ6: =IF(CG6>0,CI6*1000/CG6,"") -> 135.55671 | CK6: =IF(CH6="",1,MIN(p_idx_max,MAX(p_idx_min,CH6/p_fc_world))) -> 0.50872022 | CL6: =IF(CJ6="",1,MIN(p_idx_max,MAX(p_idx_min,CJ6/p_cb_world))) -> 2.5775749 | CM6: =p_b*(1-p_wb_idx+p_wb_idx*CK6) -> 0.06765979 | CN6: =p_c*(1-p_wc_idx+p_wc_idx*CL6) -> 0.33250717 | CO6: =IF(N(BR6)>0,(N(BS6)+N(BT6)+N(BU6))/BR6,"") -> 0.58413129 | CP6: =N(BS6)+N(BT6)+N(BU6) -> 6178.97 | CQ6: =IF(CP6>0,N(BS6)/CP6,"") -> 0.93419615 | CR6: =IF(CP6>0,N(BT6)/CP6,"") -> 0.051447086 | CS6: =IF(CP6>0,N(BU6)/CP6,"") -> 0.014356762 | CT6: =1000*(p_sh_pv*p_cf_pv/p_capex_pv+(1-p_sh_pv)*p_cf_wind/p_capex_wind)*8760 -> 2301.2886 | CU6: =IF(AND(ISNUMBER(CO6),ISNUMBER(CQ6),BY6=1),1,0) -> 1 | CV6: =IF(CU6=0,"",CQ6*p_hr_coal*N(AK6)+CR6*p_hr_gas*N(AO6)+CS6*p_hr_oil*N(AH6)/p_gj_l_oil) -> 45.633354 | CW6: =IF(CU6=0,"",CQ6*p_hr_coal*p_ef_coal+CR6*p_hr_gas*p_ef_gas+CS6*p_hr_oil*p_ef_oil) -> 0.91706366 | CX6: =IF(CU6=0,"",CQ6*p_hr_coal*N(AW6)+CR6*p_hr_gas*N(AX6)+CS6*p_hr_oil*N(AY6)/p_gj_l_oil) -> 90.39368 | CY6: =IF(CU6=0,"",CO6*CW6) -> 0.53568558 | CZ6: =IF(CU6=0,"",CT6*CO6*CV6/1000/1000-p_om_re) -> 0.046342848 | DA6: =IF(CU6=0,"",CT6*CO6*CX6/1000/1000) -> 0.12151213 | DB6: =IF(CU6=0,"",CT6*CO6*CW6/1000) -> 1.2327671 | DC6: =IF(AND(CU6=1,ISNUMBER(AD6),ISNUMBER(AV6)),1,0) -> 1 | DD6: =IF(DC6=0,"",p_ev_km*p_ice_l/100*AD6-p_ev_km*p_ev_kwh*AV6+p_ev_km*p_ev_maint) -> 874.00215 | DE6: =IF(DC6=0,"",DD6/p_ev_prem) -> 0.17480043 | DF6: =IF(DC6=0,"",p_ev_km*p_ice_l/100*N(AZ6)/p_ev_prem) -> 0.0540189 | DG6: =IF(DC6=0,"",1000/p_ev_prem*(p_ev_km*p_ice_l/100*p_gj_l_gso*p_ef_gso-p_ev_km*p_ev_kwh/1000*CY6)) -> 0.24399329 | DH6: =IFERROR(IF(INDEX(Damodaran!$D:$D,MATCH(A6,Damodaran!$A:$A,0))="","",INDEX(Damodaran!$D:$D,MATCH(A6,Damodaran!$A:$A,0))),"") | DI6: =IFERROR(IF(INDEX(Damodaran!$E:$E,MATCH(A6,Damodaran!$A:$A,0))="","",INDEX(Damodaran!$E:$E,MATCH(A6,Damodaran!$A:$A,0))),"") | DJ6: =IFERROR(IF(INDEX(Damodaran!$G:$G,MATCH(A6,Damodaran!$A:$A,0))="","",INDEX(Damodaran!$G:$G,MATCH(A6,Damodaran!$A:$A,0))),"") | DK6: =IF(ISNUMBER(BG6),(1+BG6/100)*(1+p_infl)-1,"") -> 0.0455 | DL6: =IF(ISNUMBER(BH6),BH6/100,"") -> 0.0323 | DM6: =IF(COUNT(DK6,DL6)=0,"",AVERAGE(DK6,DL6)) -> 0.0389 | DN6: =IF(OR(DH6="",DI6=""),"",p_dv*(p_rf+DH6)*(1-IF(DJ6="",p_tax_def,DJ6))+(1-p_dv)*(p_rf+p_beta*p_erp+p_lambda*DI6)) | DO6: =IF(AND(ISNUMBER(DM6),ISNUMBER(DN6)),1,0) -> 0 | DP6: =IF(DO6=1,DM6,0) -> 0 | DQ6: =IF(DO6=1,DN6,0) -> 0 | DR6: =IF(DN6="","",DN6+p_shift) | DS6: =IF(E6="AE",p_r_ae,IF(E6="China",p_r_chn,p_r_emdc)) -> 0.06 | DT6: =IF(E6="AE",p_rh_ae,IF(E6="China",p_rh_chn,p_rh_emdc)) -> 0.08 | DU6: =IF(AND(p_use_obs=1,ISNUMBER(DM6)),DM6,IF(AND(p_use_dam=1,ISNUMBER(DR6)),DR6,DS6)) -> 0.0389 | DV6: =IF(AND(p_use_obs=1,ISNUMBER(DM6)),"Observed (IRENA/Steffen)",IF(AND(p_use_dam=1,ISNUMBER(DR6)),"Damodaran (eq. 5)","Group default (IHLEG)")) -> Observed (IRENA/Steffen) | DW6: =IF(p_basis=1,(1+DU6)/(1+p_infl)-1,DU6) -> 0.0389 | DX6: =DW6+(DT6-DS6) -> 0.0589 | DY6: =IF(AND(p_use_pefa=1,ISNUMBER(BD6)),p_gap_lic-(BD6-1)/3*(p_gap_lic-p_gap_ae),IF(E6="AE",p_gap_ae,IF(D6="Low income",p_gap_lic,p_gap_em)))*(1-p_reform*p_reform_close) -> 0.27 | DZ6: =IF(AND(p_use_pefa=1,ISNUMBER(BD6)),"PEFA PI-11","Income-group default (IMF 2015)") -> Income-group default (IMF 2015) | EA6: =IF(E6="AE",p_ps_ae,IF(E6="China",p_ps_chn,p_ps_emdc)) -> 0.5 | EB6: =(1-EA6)+EA6/(1-DY6) -> 1.1849315 | EC6: =Results_Country!F6 -> 863.01562 | ED6: =IF(CH6="",0,CH6*EC6) -> 70687.618 | EE6: =IF(CJ6="",0,CJ6*EC6) -> 116987.56 | EF6: =IF(CH6="",0,EC6) -> 863.01562
A7: DEU | B7: Germany | C7: Europe & Central Asia | D7: High income | E7: AE | F7: 4684.182 | G7: 5996.196 | H7: 0.24 | I7: 0.791 | J7: 84.552242 | K7: 658.368 | L7: 742.151 | M7: 744.658 | N7: 380.56795 | O7: 140.70402 | P7: 12.014505 | Q7: 1.1130533 | R7: 1.9281264 | S7: 0.60282306 | T7: 0.0080273508 | U7: 0.30423141 | V7: 0.023087535 | W7: 0.60344764 | X7: 0 | Y7: 22.456814 | Z7: 58.553961 | AA7: 3.2365836 | AB7: 0.3352232 | AC7: 16.101396 | AD7: 0.856088 | AE7: 0.831054 | AF7: 0.559265 | AG7: 0.70329 | AH7: 0.51946289 | AI7: 6.908 | AJ7: 12.20107 | AK7: 7.042 | AL7: 7.1261706 | AM7: 17.078 | AN7: 30.69843 | AO7: 17.078 | AP7: 24.284885 | AQ7: 21.482424 | AR7: 7.0823331 | AS7: 1.0573126 | AT7: 4.4195969 | AU7: 0.63595124 | AV7: 0.344945 | AW7: 1.654682 | AX7: 0.833046 | AY7: 0.095961881 | AZ7: 0.115105 | BA7: 62.227 | BB7: 1.73 | BF7: 0 | BH7: 2.32 | BI7: 2020 | BJ7: 1 | BQ7: 2025 | BR7: 499.89 | BS7: 103.15 | BT7: 82.67 | BU7: 18.91 | BV7: =F7*(1+N(H7)/100)*(1+N(I7)/100)^5 -> 4884.0892 | BW7: =IF(N(G7)>0,G7,F7) -> 5996.196 | BX7: =F7/BW7 -> 0.78119228 | BY7: =IF(ISNUMBER(K7),1,0) -> 1 | BZ7: =IF(BY7=0,"",N(N7)+N(O7)+N(P7)) -> 533.28647 | CA7: =IF(BY7=0,"",(N(Y7)*34.2+N(Z7)*38.6)/1000) -> 3.0282059 | CB7: =IF(BY7=0,"",N(O7)*0.0036+N(R7)+N(V7)+(N(AA7)*25.3+N(AB7)*37)/1000) -> 2.5520372 | CC7: =IF(BY7=0,"",N(N7)*0.0036+N(Q7)+N(U7)+N(T7)+N(X7)+N(AC7)*38/1000) -> 3.4072098 | CD7: =IF(BY7=0,"",N(Q7)+N(R7)+N(S7)+N(T7)+N(U7)+N(V7)+N(W7)+N(X7)+(N(Y7)*34.2+N(Z7)*38.6+N(AA7)*25.3+N(AB7)*37+N(AC7)*38)/1000) -> 8.3171446 | CE7: =IF(BY7=0,"",MAX(0,N(L7)-N(K7))+MAX(0,N(M7)-N(L7))) -> 86.29 | CF7: =IF(BY7=0,"",N(Y7)*N(AD7)+N(Z7)*N(AE7)+N(AA7)*N(AF7)+N(AB7)*N(AG7)+N(AC7)*N(AH7)+N(U7)*N(AI7)+N(V7)*N(AJ7)+N(W7)*N(AK7)+N(X7)*N(AL7)+N(Q7)*N(AM7)+N(R7)*N(AN7)+N(S7)*N(AO7)+N(T7)*N(AP7)) -> 173.61839 | CG7: =IF(AND(BY7=1,N(K7)>0),K7,0) -> 658.368 | CH7: =IF(CG7>0,CF7*1000/CG7,"") -> 263.71025 | CI7: =IF(BY7=0,"",N(AQ7)+p_road*(N(AR7)+N(AS7)+N(AT7))) -> 21.482424 | CJ7: =IF(CG7>0,CI7*1000/CG7,"") -> 32.629812 | CK7: =IF(CH7="",1,MIN(p_idx_max,MAX(p_idx_min,CH7/p_fc_world))) -> 1.6378772 | CL7: =IF(CJ7="",1,MIN(p_idx_max,MAX(p_idx_min,CJ7/p_cb_world))) -> 0.62044721 | CM7: =p_b*(1-p_wb_idx+p_wb_idx*CK7) -> 0.21783766 | CN7: =p_c*(1-p_wc_idx+p_wc_idx*CL7) -> 0.080037691 | CO7: =IF(N(BR7)>0,(N(BS7)+N(BT7)+N(BU7))/BR7,"") -> 0.4095501 | CP7: =N(BS7)+N(BT7)+N(BU7) -> 204.73 | CQ7: =IF(CP7>0,N(BS7)/CP7,"") -> 0.50383432 | CR7: =IF(CP7>0,N(BT7)/CP7,"") -> 0.40380013 | CS7: =IF(CP7>0,N(BU7)/CP7,"") -> 0.092365555 | CT7: =1000*(p_sh_pv*p_cf_pv/p_capex_pv+(1-p_sh_pv)*p_cf_wind/p_capex_wind)*8760 -> 2301.2886 | CU7: =IF(AND(ISNUMBER(CO7),ISNUMBER(CQ7),BY7=1),1,0) -> 1 | CV7: =IF(CU7=0,"",CQ7*p_hr_coal*N(AK7)+CR7*p_hr_gas*N(AO7)+CS7*p_hr_oil*N(AH7)/p_gj_l_oil) -> 100.25244 | CW7: =IF(CU7=0,"",CQ7*p_hr_coal*p_ef_coal+CR7*p_hr_gas*p_ef_gas+CS7*p_hr_oil*p_ef_oil) -> 0.72159165 | CX7: =IF(CU7=0,"",CQ7*p_hr_coal*N(AW7)+CR7*p_hr_gas*N(AX7)+CS7*p_hr_oil*N(AY7)/p_gj_l_oil) -> 13.270812 | CY7: =IF(CU7=0,"",CO7*CW7) -> 0.29552794 | CZ7: =IF(CU7=0,"",CT7*CO7*CV7/1000/1000-p_om_re) -> 0.079487216 | DA7: =IF(CU7=0,"",CT7*CO7*CX7/1000/1000) -> 0.012507647 | DB7: =IF(CU7=0,"",CT7*CO7*CW7/1000) -> 0.68009506 | DC7: =IF(AND(CU7=1,ISNUMBER(AD7),ISNUMBER(AV7)),1,0) -> 1 | DD7: =IF(DC7=0,"",p_ev_km*p_ice_l/100*AD7-p_ev_km*p_ev_kwh*AV7+p_ev_km*p_ev_maint) -> 211.7475 | DE7: =IF(DC7=0,"",DD7/p_ev_prem) -> 0.0423495 | DF7: =IF(DC7=0,"",p_ev_km*p_ice_l/100*N(AZ7)/p_ev_prem) -> 0.025898625 | DG7: =IF(DC7=0,"",1000/p_ev_prem*(p_ev_km*p_ice_l/100*p_gj_l_gso*p_ef_gso-p_ev_km*p_ev_kwh/1000*CY7)) -> 0.37367842 | DH7: =IFERROR(IF(INDEX(Damodaran!$D:$D,MATCH(A7,Damodaran!$A:$A,0))="","",INDEX(Damodaran!$D:$D,MATCH(A7,Damodaran!$A:$A,0))),"") | DI7: =IFERROR(IF(INDEX(Damodaran!$E:$E,MATCH(A7,Damodaran!$A:$A,0))="","",INDEX(Damodaran!$E:$E,MATCH(A7,Damodaran!$A:$A,0))),"") | DJ7: =IFERROR(IF(INDEX(Damodaran!$G:$G,MATCH(A7,Damodaran!$A:$A,0))="","",INDEX(Damodaran!$G:$G,MATCH(A7,Damodaran!$A:$A,0))),"") | DK7: =IF(ISNUMBER(BG7),(1+BG7/100)*(1+p_infl)-1,"") | DL7: =IF(ISNUMBER(BH7),BH7/100,"") -> 0.0232 | DM7: =IF(COUNT(DK7,DL7)=0,"",AVERAGE(DK7,DL7)) -> 0.0232 | DN7: =IF(OR(DH7="",DI7=""),"",p_dv*(p_rf+DH7)*(1-IF(DJ7="",p_tax_def,DJ7))+(1-p_dv)*(p_rf+p_beta*p_erp+p_lambda*DI7)) | DO7: =IF(AND(ISNUMBER(DM7),ISNUMBER(DN7)),1,0) -> 0 | DP7: =IF(DO7=1,DM7,0) -> 0 | DQ7: =IF(DO7=1,DN7,0) -> 0 | DR7: =IF(DN7="","",DN7+p_shift) | DS7: =IF(E7="AE",p_r_ae,IF(E7="China",p_r_chn,p_r_emdc)) -> 0.055 | DT7: =IF(E7="AE",p_rh_ae,IF(E7="China",p_rh_chn,p_rh_emdc)) -> 0.07 | DU7: =IF(AND(p_use_obs=1,ISNUMBER(DM7)),DM7,IF(AND(p_use_dam=1,ISNUMBER(DR7)),DR7,DS7)) -> 0.0232 | DV7: =IF(AND(p_use_obs=1,ISNUMBER(DM7)),"Observed (IRENA/Steffen)",IF(AND(p_use_dam=1,ISNUMBER(DR7)),"Damodaran (eq. 5)","Group default (IHLEG)")) -> Observed (IRENA/Steffen) | DW7: =IF(p_basis=1,(1+DU7)/(1+p_infl)-1,DU7) -> 0.0232 | DX7: =DW7+(DT7-DS7) -> 0.0382 | DY7: =IF(AND(p_use_pefa=1,ISNUMBER(BD7)),p_gap_lic-(BD7-1)/3*(p_gap_lic-p_gap_ae),IF(E7="AE",p_gap_ae,IF(D7="Low income",p_gap_lic,p_gap_em)))*(1-p_reform*p_reform_close) -> 0.13 | DZ7: =IF(AND(p_use_pefa=1,ISNUMBER(BD7)),"PEFA PI-11","Income-group default (IMF 2015)") -> Income-group default (IMF 2015) | EA7: =IF(E7="AE",p_ps_ae,IF(E7="China",p_ps_chn,p_ps_emdc)) -> 0.3 | EB7: =(1-EA7)+EA7/(1-DY7) -> 1.0448276 | EC7: =Results_Country!F7 -> 152.2747 | ED7: =IF(CH7="",0,CH7*EC7) -> 40156.401 | EE7: =IF(CJ7="",0,CJ7*EC7) -> 4968.695 | EF7: =IF(CH7="",0,EC7) -> 152.2747
A8: JPN | B8: Japan | C8: East Asia & Pacific | D8: High income | E8: AE | F8: 4190.008 | G8: 6735.801 | H8: 1.193 | I8: 0.719 | J8: 123.75304 | K8: 1205.177 | L8: 1316.091 | M8: 1263.984 | N8: 801.31601 | O8: 301.49074 | P8: 19.281774 | Q8: 0.47574463 | R8: 0.90047219 | S8: 1.0770566 | T8: 0.00092139303 | U8: 0.97928717 | V8: 0.0072385758 | W8: 3.2495725 | X8: 1.7134652e-05 | Y8: 44.651636 | Z8: 43.623053 | AA8: 14.335988 | AB8: 16.833812 | AC8: 70.9526 | AD8: 0.792 | AE8: 0.754814 | AF8: 0.537673 | AG8: 0.68874 | AH8: 0.5433453 | AI8: 7.404 | AJ8: 14.7983 | AK8: 7.372 | AL8: 7.3920876 | AM8: 20.553 | AN8: 24.3694 | AO8: 20.53 | AP8: 21.943709 | AQ8: 57.538415 | AR8: 33.629406 | AS8: 4.1083299 | AT8: 5.2908301 | AU8: 0.38617748 | AV8: 0.18271 | AW8: 1.653466 | AX8: 0.979454 | AY8: 0.15777528 | AZ8: 0.083558 | BA8: 214.487 | BB8: 0.325 | BF8: 0 | BQ8: 2025 | BR8: 1029.97 | BS8: 330.12 | BT8: 337.64 | BU8: 25.39 | BV8: =F8*(1+N(H8)/100)*(1+N(I8)/100)^5 -> 4394.6303 | BW8: =IF(N(G8)>0,G8,F8) -> 6735.801 | BX8: =F8/BW8 -> 0.62205044 | BY8: =IF(ISNUMBER(K8),1,0) -> 1 | BZ8: =IF(BY8=0,"",N(N8)+N(O8)+N(P8)) -> 1122.0885 | CA8: =IF(BY8=0,"",(N(Y8)*34.2+N(Z8)*38.6)/1000) -> 3.2109358 | CB8: =IF(BY8=0,"",N(O8)*0.0036+N(R8)+N(V8)+(N(AA8)*25.3+N(AB8)*37)/1000) -> 2.978629 | CC8: =IF(BY8=0,"",N(N8)*0.0036+N(Q8)+N(U8)+N(T8)+N(X8)+N(AC8)*38/1000) -> 7.0369067 | CD8: =IF(BY8=0,"",N(Q8)+N(R8)+N(S8)+N(T8)+N(U8)+N(V8)+N(W8)+N(X8)+(N(Y8)*34.2+N(Z8)*38.6+N(AA8)*25.3+N(AB8)*37+N(AC8)*38)/1000) -> 13.582996 | CE8: =IF(BY8=0,"",MAX(0,N(L8)-N(K8))+MAX(0,N(M8)-N(L8))) -> 110.914 | CF8: =IF(BY8=0,"",N(Y8)*N(AD8)+N(Z8)*N(AE8)+N(AA8)*N(AF8)+N(AB8)*N(AG8)+N(AC8)*N(AH8)+N(U8)*N(AI8)+N(V8)*N(AJ8)+N(W8)*N(AK8)+N(X8)*N(AL8)+N(Q8)*N(AM8)+N(R8)*N(AN8)+N(S8)*N(AO8)+N(T8)*N(AP8)) -> 211.31322 | CG8: =IF(AND(BY8=1,N(K8)>0),K8,0) -> 1205.177 | CH8: =IF(CG8>0,CF8*1000/CG8,"") -> 175.33791 | CI8: =IF(BY8=0,"",N(AQ8)+p_road*(N(AR8)+N(AS8)+N(AT8))) -> 57.538415 | CJ8: =IF(CG8>0,CI8*1000/CG8,"") -> 47.742709 | CK8: =IF(CH8="",1,MIN(p_idx_max,MAX(p_idx_min,CH8/p_fc_world))) -> 1.0890057 | CL8: =IF(CJ8="",1,MIN(p_idx_max,MAX(p_idx_min,CJ8/p_cb_world))) -> 0.90781494 | CM8: =p_b*(1-p_wb_idx+p_wb_idx*CK8) -> 0.14483775 | CN8: =p_c*(1-p_wc_idx+p_wc_idx*CL8) -> 0.11710813 | CO8: =IF(N(BR8)>0,(N(BS8)+N(BT8)+N(BU8))/BR8,"") -> 0.67298077 | CP8: =N(BS8)+N(BT8)+N(BU8) -> 693.15 | CQ8: =IF(CP8>0,N(BS8)/CP8,"") -> 0.47626055 | CR8: =IF(CP8>0,N(BT8)/CP8,"") -> 0.48710957 | CS8: =IF(CP8>0,N(BU8)/CP8,"") -> 0.036629878 | CT8: =1000*(p_sh_pv*p_cf_pv/p_capex_pv+(1-p_sh_pv)*p_cf_wind/p_capex_wind)*8760 -> 2301.2886 | CU8: =IF(AND(ISNUMBER(CO8),ISNUMBER(CQ8),BY8=1),1,0) -> 1 | CV8: =IF(CU8=0,"",CQ8*p_hr_coal*N(AK8)+CR8*p_hr_gas*N(AO8)+CS8*p_hr_oil*N(AH8)/p_gj_l_oil) -> 115.52656 | CW8: =IF(CU8=0,"",CQ8*p_hr_coal*p_ef_coal+CR8*p_hr_gas*p_ef_gas+CS8*p_hr_oil*p_ef_oil) -> 0.68526293 | CX8: =IF(CU8=0,"",CQ8*p_hr_coal*N(AW8)+CR8*p_hr_gas*N(AX8)+CS8*p_hr_oil*N(AY8)/p_gj_l_oil) -> 13.025153 | CY8: =IF(CU8=0,"",CO8*CW8) -> 0.46116877 | CZ8: =IF(CU8=0,"",CT8*CO8*CV8/1000/1000-p_om_re) -> 0.16391864 | DA8: =IF(CU8=0,"",CT8*CO8*CX8/1000/1000) -> 0.020172354 | DB8: =IF(CU8=0,"",CT8*CO8*CW8/1000) -> 1.0612824 | DC8: =IF(AND(CU8=1,ISNUMBER(AD8),ISNUMBER(AV8)),1,0) -> 1 | DD8: =IF(DC8=0,"",p_ev_km*p_ice_l/100*AD8-p_ev_km*p_ev_kwh*AV8+p_ev_km*p_ev_maint) -> 577.683 | DE8: =IF(DC8=0,"",DD8/p_ev_prem) -> 0.1155366 | DF8: =IF(DC8=0,"",p_ev_km*p_ice_l/100*N(AZ8)/p_ev_prem) -> 0.01880055 | DG8: =IF(DC8=0,"",1000/p_ev_prem*(p_ev_km*p_ice_l/100*p_gj_l_gso*p_ef_gso-p_ev_km*p_ev_kwh/1000*CY8)) -> 0.28423236 | DH8: =IFERROR(IF(INDEX(Damodaran!$D:$D,MATCH(A8,Damodaran!$A:$A,0))="","",INDEX(Damodaran!$D:$D,MATCH(A8,Damodaran!$A:$A,0))),"") | DI8: =IFERROR(IF(INDEX(Damodaran!$E:$E,MATCH(A8,Damodaran!$A:$A,0))="","",INDEX(Damodaran!$E:$E,MATCH(A8,Damodaran!$A:$A,0))),"") | DJ8: =IFERROR(IF(INDEX(Damodaran!$G:$G,MATCH(A8,Damodaran!$A:$A,0))="","",INDEX(Damodaran!$G:$G,MATCH(A8,Damodaran!$A:$A,0))),"") | DK8: =IF(ISNUMBER(BG8),(1+BG8/100)*(1+p_infl)-1,"") | DL8: =IF(ISNUMBER(BH8),BH8/100,"") | DM8: =IF(COUNT(DK8,DL8)=0,"",AVERAGE(DK8,DL8)) | DN8: =IF(OR(DH8="",DI8=""),"",p_dv*(p_rf+DH8)*(1-IF(DJ8="",p_tax_def,DJ8))+(1-p_dv)*(p_rf+p_beta*p_erp+p_lambda*DI8)) | DO8: =IF(AND(ISNUMBER(DM8),ISNUMBER(DN8)),1,0) -> 0 | DP8: =IF(DO8=1,DM8,0) -> 0 | DQ8: =IF(DO8=1,DN8,0) -> 0 | DR8: =IF(DN8="","",DN8+p_shift) | DS8: =IF(E8="AE",p_r_ae,IF(E8="China",p_r_chn,p_r_emdc)) -> 0.055 | DT8: =IF(E8="AE",p_rh_ae,IF(E8="China",p_rh_chn,p_rh_emdc)) -> 0.07 | DU8: =IF(AND(p_use_obs=1,ISNUMBER(DM8)),DM8,IF(AND(p_use_dam=1,ISNUMBER(DR8)),DR8,DS8)) -> 0.055 | DV8: =IF(AND(p_use_obs=1,ISNUMBER(DM8)),"Observed (IRENA/Steffen)",IF(AND(p_use_dam=1,ISNUMBER(DR8)),"Damodaran (eq. 5)","Group default (IHLEG)")) -> Group default (IHLEG) | DW8: =IF(p_basis=1,(1+DU8)/(1+p_infl)-1,DU8) -> 0.055 | DX8: =DW8+(DT8-DS8) -> 0.07 | DY8: =IF(AND(p_use_pefa=1,ISNUMBER(BD8)),p_gap_lic-(BD8-1)/3*(p_gap_lic-p_gap_ae),IF(E8="AE",p_gap_ae,IF(D8="Low income",p_gap_lic,p_gap_em)))*(1-p_reform*p_reform_close) -> 0.13 | DZ8: =IF(AND(p_use_pefa=1,ISNUMBER(BD8)),"PEFA PI-11","Income-group default (IMF 2015)") -> Income-group default (IMF 2015) | EA8: =IF(E8="AE",p_ps_ae,IF(E8="China",p_ps_chn,p_ps_emdc)) -> 0.3 | EB8: =(1-EA8)+EA8/(1-DY8) -> 1.0448276 | EC8: =Results_Country!F8 -> 190.59034 | ED8: =IF(CH8="",0,CH8*EC8) -> 33417.712 | EE8: =IF(CJ8="",0,CJ8*EC8) -> 9099.2994 | EF8: =IF(CH8="",0,EC8) -> 190.59034
A9: IND | B9: India | C9: South Asia | D9: Lower middle income | E9: EMDC | F9: 3760.814 | G9: 15593.814 | H9: 7.618 | I9: 6.478 | J9: 1450.9358 | K9: 2845.008 | L9: 4131.845 | M9: 4096.604 | N9: 1086.9847 | O9: 418.58493 | P9: 120.14134 | Q9: 1.1753929 | R9: 0.24148572 | S9: 2.4651982 | T9: 0.19450589 | U9: 5.1925877 | V9: 0.43048427 | W9: 10.533005 | X9: 0.12623964 | Y9: 51.489894 | Z9: 110.40621 | AA9: 70.07475 | AB9: 7.94006 | AC9: 58.837484 | AD9: 0.70564 | AE9: 0.569088 | AF9: 0.474114 | AG9: 0.331677 | AH9: 0.3856912 | AI9: 4.396 | AJ9: 8.01574 | AK9: 2.629 | AL9: 3.340448 | AM9: 9.792 | AN9: 18.51656 | AO9: 8.809 | AP9: 9.7104887 | AQ9: 151.40286 | AR9: 3.8332319 | AS9: 25.298578 | AT9: 11.683349 | AU9: 0.34500237 | AV9: 0.1239 | AW9: 2.749538 | AX9: 0.386554 | AY9: 0.5030703 | AZ9: 0.111705 | BA9: 84.782 | BB9: 22.859 | BC9: 106.972 | BF9: 0 | BH9: 9.5 | BI9: 2022 | BJ9: 1 | BL9: 0.904 | BM9: 4.463 | BN9: 14.5 | BO9: 0.219 | BP9: 0.197 | BQ9: 2025 | BR9: 2081.6 | BS9: 1474.15 | BT9: 48.54 | BU9: 4.1 | BV9: =F9*(1+N(H9)/100)*(1+N(I9)/100)^5 -> 5539.4443 | BW9: =IF(N(G9)>0,G9,F9) -> 15593.814 | BX9: =F9/BW9 -> 0.24117346 | BY9: =IF(ISNUMBER(K9),1,0) -> 1 | BZ9: =IF(BY9=0,"",N(N9)+N(O9)+N(P9)) -> 1625.711 | CA9: =IF(BY9=0,"",(N(Y9)*34.2+N(Z9)*38.6)/1000) -> 6.022634 | CB9: =IF(BY9=0,"",N(O9)*0.0036+N(R9)+N(V9)+(N(AA9)*25.3+N(AB9)*37)/1000) -> 4.2455492 | CC9: =IF(BY9=0,"",N(N9)*0.0036+N(Q9)+N(U9)+N(T9)+N(X9)+N(AC9)*38/1000) -> 12.837695 | CD9: =IF(BY9=0,"",N(Q9)+N(R9)+N(S9)+N(T9)+N(U9)+N(V9)+N(W9)+N(X9)+(N(Y9)*34.2+N(Z9)*38.6+N(AA9)*25.3+N(AB9)*37+N(AC9)*38)/1000) -> 30.684031 | CE9: =IF(BY9=0,"",MAX(0,N(L9)-N(K9))+MAX(0,N(M9)-N(L9))) -> 1286.837 | CF9: =IF(BY9=0,"",N(Y9)*N(AD9)+N(Z9)*N(AE9)+N(AA9)*N(AF9)+N(AB9)*N(AG9)+N(AC9)*N(AH9)+N(U9)*N(AI9)+N(V9)*N(AJ9)+N(W9)*N(AK9)+N(X9)*N(AL9)+N(Q9)*N(AM9)+N(R9)*N(AN9)+N(S9)*N(AO9)+N(T9)*N(AP9)) -> 251.69008 | CG9: =IF(AND(BY9=1,N(K9)>0),K9,0) -> 2845.008 | CH9: =IF(CG9>0,CF9*1000/CG9,"") -> 88.467265 | CI9: =IF(BY9=0,"",N(AQ9)+p_road*(N(AR9)+N(AS9)+N(AT9))) -> 151.40286 | CJ9: =IF(CG9>0,CI9*1000/CG9,"") -> 53.217024 | CK9: =IF(CH9="",1,MIN(p_idx_max,MAX(p_idx_min,CH9/p_fc_world))) -> 0.54946105 | CL9: =IF(CJ9="",1,MIN(p_idx_max,MAX(p_idx_min,CJ9/p_cb_world))) -> 1.0119076 | CM9: =p_b*(1-p_wb_idx+p_wb_idx*CK9) -> 0.07307832 | CN9: =p_c*(1-p_wc_idx+p_wc_idx*CL9) -> 0.13053608 | CO9: =IF(N(BR9)>0,(N(BS9)+N(BT9)+N(BU9))/BR9,"") -> 0.73346945 | CP9: =N(BS9)+N(BT9)+N(BU9) -> 1526.79 | CQ9: =IF(CP9>0,N(BS9)/CP9,"") -> 0.96552244 | CR9: =IF(CP9>0,N(BT9)/CP9,"") -> 0.031792191 | CS9: =IF(CP9>0,N(BU9)/CP9,"") -> 0.0026853726 | CT9: =1000*(p_sh_pv*p_cf_pv/p_capex_pv+(1-p_sh_pv)*p_cf_wind/p_capex_wind)*8760 -> 2301.2886 | CU9: =IF(AND(ISNUMBER(CO9),ISNUMBER(CQ9),BY9=1),1,0) -> 1 | CV9: =IF(CU9=0,"",CQ9*p_hr_coal*N(AK9)+CR9*p_hr_gas*N(AO9)+CS9*p_hr_oil*N(AH9)/p_gj_l_oil) -> 27.765754 | CW9: =IF(CU9=0,"",CQ9*p_hr_coal*p_ef_coal+CR9*p_hr_gas*p_ef_gas+CS9*p_hr_oil*p_ef_oil) -> 0.92894319 | CX9: =IF(CU9=0,"",CQ9*p_hr_coal*N(AW9)+CR9*p_hr_gas*N(AX9)+CS9*p_hr_oil*N(AY9)/p_gj_l_oil) -> 27.007058 | CY9: =IF(CU9=0,"",CO9*CW9) -> 0.68135145 | CZ9: =IF(CU9=0,"",CT9*CO9*CV9/1000/1000-p_om_re) -> 0.031866506 | DA9: =IF(CU9=0,"",CT9*CO9*CX9/1000/1000) -> 0.045585884 | DB9: =IF(CU9=0,"",CT9*CO9*CW9/1000) -> 1.5679863 | DC9: =IF(AND(CU9=1,ISNUMBER(AD9),ISNUMBER(AV9)),1,0) -> 1 | DD9: =IF(DC9=0,"",p_ev_km*p_ice_l/100*AD9-p_ev_km*p_ev_kwh*AV9+p_ev_km*p_ev_maint) -> 639.315 | DE9: =IF(DC9=0,"",DD9/p_ev_prem) -> 0.127863 | DF9: =IF(DC9=0,"",p_ev_km*p_ice_l/100*N(AZ9)/p_ev_prem) -> 0.025133625 | DG9: =IF(DC9=0,"",1000/p_ev_prem*(p_ev_km*p_ice_l/100*p_gj_l_gso*p_ef_gso-p_ev_km*p_ev_kwh/1000*CY9)) -> 0.16533372 | DH9: =IFERROR(IF(INDEX(Damodaran!$D:$D,MATCH(A9,Damodaran!$A:$A,0))="","",INDEX(Damodaran!$D:$D,MATCH(A9,Damodaran!$A:$A,0))),"") | DI9: =IFERROR(IF(INDEX(Damodaran!$E:$E,MATCH(A9,Damodaran!$A:$A,0))="","",INDEX(Damodaran!$E:$E,MATCH(A9,Damodaran!$A:$A,0))),"") | DJ9: =IFERROR(IF(INDEX(Damodaran!$G:$G,MATCH(A9,Damodaran!$A:$A,0))="","",INDEX(Damodaran!$G:$G,MATCH(A9,Damodaran!$A:$A,0))),"") | DK9: =IF(ISNUMBER(BG9),(1+BG9/100)*(1+p_infl)-1,"") | DL9: =IF(ISNUMBER(BH9),BH9/100,"") -> 0.095 | DM9: =IF(COUNT(DK9,DL9)=0,"",AVERAGE(DK9,DL9)) -> 0.095 | DN9: =IF(OR(DH9="",DI9=""),"",p_dv*(p_rf+DH9)*(1-IF(DJ9="",p_tax_def,DJ9))+(1-p_dv)*(p_rf+p_beta*p_erp+p_lambda*DI9)) | DO9: =IF(AND(ISNUMBER(DM9),ISNUMBER(DN9)),1,0) -> 0 | DP9: =IF(DO9=1,DM9,0) -> 0 | DQ9: =IF(DO9=1,DN9,0) -> 0 | DR9: =IF(DN9="","",DN9+p_shift) | DS9: =IF(E9="AE",p_r_ae,IF(E9="China",p_r_chn,p_r_emdc)) -> 0.105 | DT9: =IF(E9="AE",p_rh_ae,IF(E9="China",p_rh_chn,p_rh_emdc)) -> 0.15 | DU9: =IF(AND(p_use_obs=1,ISNUMBER(DM9)),DM9,IF(AND(p_use_dam=1,ISNUMBER(DR9)),DR9,DS9)) -> 0.095 | DV9: =IF(AND(p_use_obs=1,ISNUMBER(DM9)),"Observed (IRENA/Steffen)",IF(AND(p_use_dam=1,ISNUMBER(DR9)),"Damodaran (eq. 5)","Group default (IHLEG)")) -> Observed (IRENA/Steffen) | DW9: =IF(p_basis=1,(1+DU9)/(1+p_infl)-1,DU9) -> 0.095 | DX9: =DW9+(DT9-DS9) -> 0.14 | DY9: =IF(AND(p_use_pefa=1,ISNUMBER(BD9)),p_gap_lic-(BD9-1)/3*(p_gap_lic-p_gap_ae),IF(E9="AE",p_gap_ae,IF(D9="Low income",p_gap_lic,p_gap_em)))*(1-p_reform*p_reform_close) -> 0.27 | DZ9: =IF(AND(p_use_pefa=1,ISNUMBER(BD9)),"PEFA PI-11","Income-group default (IMF 2015)") -> Income-group default (IMF 2015) | EA9: =IF(E9="AE",p_ps_ae,IF(E9="China",p_ps_chn,p_ps_emdc)) -> 0.4 | EB9: =(1-EA9)+EA9/(1-DY9) -> 1.1479452 | EC9: =Results_Country!F9 -> 291.81555 | ED9: =IF(CH9="",0,CH9*EC9) -> 25816.124 | EE9: =IF(CJ9="",0,CJ9*EC9) -> 15529.555 | EF9: =IF(CH9="",0,EC9) -> 291.81555
A10: GBR | B10: United Kingdom | C10: Europe & Central Asia | D10: High income | E10: AE | F10: 3695.355 | G10: 4369.68 | H10: 1.323 | I10: 0.797 | J10: 69.138192 | K10: 370.094 | L10: 454.233 | M10: 450.982 | N10: 158.55894 | O10: 98.997761 | P10: 6.77678 | Q10: 0.61607739 | R10: 1.544851 | S10: 0.5780137 | T10: 0.19301728 | U10: 0.076630585 | V10: 0.022422742 | W10: 0.045718057 | X10: 0.00066681687 | Y10: 14.475101 | Z10: 33.435722 | AA10: 1.9914151 | AB10: 4.5874982 | AC10: 4.3165463 | AD10: 0.8688 | AE10: 0.844368 | AF10: 0.534979 | AG10: 0.654577 | AH10: 0.51946289 | AI10: 14.313 | AJ10: 37.428 | AK10: 13.133 | AL10: 17.520501 | AM10: 19.634 | AN10: 32.5296 | AO10: 32.277 | AP10: 29.575652 | AQ10: 6.4243476 | AR10: 0.16040927 | AS10: 0.021520338 | AT10: 0 | AU10: 0.52006084 | AV10: 0.37416 | AW10: 1.867267 | AX10: 0.95413 | AY10: 0.24720599 | AZ10: 0.037778 | BA10: 99.901 | BB10: 5.403 | BF10: 0 | BH10: 3.587 | BI10: 2020 | BJ10: 1 | BQ10: 2025 | BR10: 292.41 | BS10: 0.33 | BT10: 90.91 | BU10: 12.77 | BV10: =F10*(1+N(H10)/100)*(1+N(I10)/100)^5 -> 3895.8501 | BW10: =IF(N(G10)>0,G10,F10) -> 4369.68 | BX10: =F10/BW10 -> 0.84568092 | BY10: =IF(ISNUMBER(K10),1,0) -> 1 | BZ10: =IF(BY10=0,"",N(N10)+N(O10)+N(P10)) -> 264.33348 | CA10: =IF(BY10=0,"",(N(Y10)*34.2+N(Z10)*38.6)/1000) -> 1.7856673 | CB10: =IF(BY10=0,"",N(O10)*0.0036+N(R10)+N(V10)+(N(AA10)*25.3+N(AB10)*37)/1000) -> 2.1437859 | CC10: =IF(BY10=0,"",N(N10)*0.0036+N(Q10)+N(U10)+N(T10)+N(X10)+N(AC10)*38/1000) -> 1.621233 | CD10: =IF(BY10=0,"",N(Q10)+N(R10)+N(S10)+N(T10)+N(U10)+N(V10)+N(W10)+N(X10)+(N(Y10)*34.2+N(Z10)*38.6+N(AA10)*25.3+N(AB10)*37+N(AC10)*38)/1000) -> 5.2472139 | CE10: =IF(BY10=0,"",MAX(0,N(L10)-N(K10))+MAX(0,N(M10)-N(L10))) -> 84.139 | CF10: =IF(BY10=0,"",N(Y10)*N(AD10)+N(Z10)*N(AE10)+N(AA10)*N(AF10)+N(AB10)*N(AG10)+N(AC10)*N(AH10)+N(U10)*N(AI10)+N(V10)*N(AJ10)+N(W10)*N(AK10)+N(X10)*N(AL10)+N(Q10)*N(AM10)+N(R10)*N(AN10)+N(S10)*N(AO10)+N(T10)*N(AP10)) -> 136.3813 | CG10: =IF(AND(BY10=1,N(K10)>0),K10,0) -> 370.094 | CH10: =IF(CG10>0,CF10*1000/CG10,"") -> 368.50449 | CI10: =IF(BY10=0,"",N(AQ10)+p_road*(N(AR10)+N(AS10)+N(AT10))) -> 6.4243476 | CJ10: =IF(CG10>0,CI10*1000/CG10,"") -> 17.358691 | CK10: =IF(CH10="",1,MIN(p_idx_max,MAX(p_idx_min,CH10/p_fc_world))) -> 2.2887434 | CL10: =IF(CJ10="",1,MIN(p_idx_max,MAX(p_idx_min,CJ10/p_cb_world))) -> 0.33007091 | CM10: =p_b*(1-p_wb_idx+p_wb_idx*CK10) -> 0.30440287 | CN10: =p_c*(1-p_wc_idx+p_wc_idx*CL10) -> 0.042579147 | CO10: =IF(N(BR10)>0,(N(BS10)+N(BT10)+N(BU10))/BR10,"") -> 0.35569919 | CP10: =N(BS10)+N(BT10)+N(BU10) -> 104.01 | CQ10: =IF(CP10>0,N(BS10)/CP10,"") -> 0.0031727718 | CR10: =IF(CP10>0,N(BT10)/CP10,"") -> 0.87405057 | CS10: =IF(CP10>0,N(BU10)/CP10,"") -> 0.12277666 | CT10: =1000*(p_sh_pv*p_cf_pv/p_capex_pv+(1-p_sh_pv)*p_cf_wind/p_capex_wind)*8760 -> 2301.2886 | CU10: =IF(AND(ISNUMBER(CO10),ISNUMBER(CQ10),BY10=1),1,0) -> 1 | CV10: =IF(CU10=0,"",CQ10*p_hr_coal*N(AK10)+CR10*p_hr_gas*N(AO10)+CS10*p_hr_oil*N(AH10)/p_gj_l_oil) -> 229.35357 | CW10: =IF(CU10=0,"",CQ10*p_hr_coal*p_ef_coal+CR10*p_hr_gas*p_ef_gas+CS10*p_hr_oil*p_ef_oil) -> 0.47053881 | CX10: =IF(CU10=0,"",CQ10*p_hr_coal*N(AW10)+CR10*p_hr_gas*N(AX10)+CS10*p_hr_oil*N(AY10)/p_gj_l_oil) -> 14.570063 | CY10: =IF(CU10=0,"",CO10*CW10) -> 0.16737027 | CZ10: =IF(CU10=0,"",CT10*CO10*CV10/1000/1000-p_om_re) -> 0.17274115 | DA10: =IF(CU10=0,"",CT10*CO10*CX10/1000/1000) -> 0.011926565 | DB10: =IF(CU10=0,"",CT10*CO10*CW10/1000) -> 0.3851673 | DC10: =IF(AND(CU10=1,ISNUMBER(AD10),ISNUMBER(AV10)),1,0) -> 1 | DD10: =IF(DC10=0,"",p_ev_km*p_ice_l/100*AD10-p_ev_km*p_ev_kwh*AV10+p_ev_km*p_ev_maint) -> 147.168 | DE10: =IF(DC10=0,"",DD10/p_ev_prem) -> 0.0294336 | DF10: =IF(DC10=0,"",p_ev_km*p_ice_l/100*N(AZ10)/p_ev_prem) -> 0.00850005 | DG10: =IF(DC10=0,"",1000/p_ev_prem*(p_ev_km*p_ice_l/100*p_gj_l_gso*p_ef_gso-p_ev_km*p_ev_kwh/1000*CY10)) -> 0.44288355 | DH10: =IFERROR(IF(INDEX(Damodaran!$D:$D,MATCH(A10,Damodaran!$A:$A,0))="","",INDEX(Damodaran!$D:$D,MATCH(A10,Damodaran!$A:$A,0))),"") | DI10: =IFERROR(IF(INDEX(Damodaran!$E:$E,MATCH(A10,Damodaran!$A:$A,0))="","",INDEX(Damodaran!$E:$E,MATCH(A10,Damodaran!$A:$A,0))),"") | DJ10: =IFERROR(IF(INDEX(Damodaran!$G:$G,MATCH(A10,Damodaran!$A:$A,0))="","",INDEX(Damodaran!$G:$G,MATCH(A10,Damodaran!$A:$A,0))),"") | DK10: =IF(ISNUMBER(BG10),(1+BG10/100)*(1+p_infl)-1,"") | DL10: =IF(ISNUMBER(BH10),BH10/100,"") -> 0.03587 | DM10: =IF(COUNT(DK10,DL10)=0,"",AVERAGE(DK10,DL10)) -> 0.03587 | DN10: =IF(OR(DH10="",DI10=""),"",p_dv*(p_rf+DH10)*(1-IF(DJ10="",p_tax_def,DJ10))+(1-p_dv)*(p_rf+p_beta*p_erp+p_lambda*DI10)) | DO10: =IF(AND(ISNUMBER(DM10),ISNUMBER(DN10)),1,0) -> 0 | DP10: =IF(DO10=1,DM10,0) -> 0 | DQ10: =IF(DO10=1,DN10,0) -> 0 | DR10: =IF(DN10="","",DN10+p_shift) | DS10: =IF(E10="AE",p_r_ae,IF(E10="China",p_r_chn,p_r_emdc)) -> 0.055 | DT10: =IF(E10="AE",p_rh_ae,IF(E10="China",p_rh_chn,p_rh_emdc)) -> 0.07 | DU10: =IF(AND(p_use_obs=1,ISNUMBER(DM10)),DM10,IF(AND(p_use_dam=1,ISNUMBER(DR10)),DR10,DS10)) -> 0.03587 | DV10: =IF(AND(p_use_obs=1,ISNUMBER(DM10)),"Observed (IRENA/Steffen)",IF(AND(p_use_dam=1,ISNUMBER(DR10)),"Damodaran (eq. 5)","Group default (IHLEG)")) -> Observed (IRENA/Steffen) | DW10: =IF(p_basis=1,(1+DU10)/(1+p_infl)-1,DU10) -> 0.03587 | DX10: =DW10+(DT10-DS10) -> 0.05087 | DY10: =IF(AND(p_use_pefa=1,ISNUMBER(BD10)),p_gap_lic-(BD10-1)/3*(p_gap_lic-p_gap_ae),IF(E10="AE",p_gap_ae,IF(D10="Low income",p_gap_lic,p_gap_em)))*(1-p_reform*p_reform_close) -> 0.13 | DZ10: =IF(AND(p_use_pefa=1,ISNUMBER(BD10)),"PEFA PI-11","Income-group default (IMF 2015)") -> Income-group default (IMF 2015) | EA10: =IF(E10="AE",p_ps_ae,IF(E10="China",p_ps_chn,p_ps_emdc)) -> 0.3 | EB10: =(1-EA10)+EA10/(1-DY10) -> 1.0448276 | EC10: =Results_Country!F10 -> 104.58983 | ED10: =IF(CH10="",0,CH10*EC10) -> 38541.822 | EE10: =IF(CJ10="",0,CJ10*EC10) -> 1815.5426 | EF10: =IF(CH10="",0,EC10) -> 104.58983
A11: FRA | B11: France | C11: Europe & Central Asia | D11: High income | E11: AE | F11: 3161.042 | G11: 4396.548 | H11: 0.928 | I11: 0.858 | J11: 66.54853 | K11: 322.969 | L11: 423.894 | M11: 405.322 | N11: 250.17552 | O11: 167.91433 | P11: 10.211677 | Q11: 0.44254701 | R11: 0.91065351 | S11: 0.10173912 | T11: 0.011510992 | U11: 0.17085464 | V11: 0.014263628 | W11: 0.079535257 | X11: 0 | Y11: 10.436445 | Z11: 45.182923 | AA11: 3.2137513 | AB11: 1.6959795 | AC11: 2.2031152 | AD11: 0.862416 | AE11: 0.835659 | AF11: 0.559218 | AG11: 0.7092 | AH11: 0.51946289 | AI11: 15.063 | AJ11: 18.8268 | AK11: 18.133 | AL11: 16.188467 | AM11: 17.329 | AN11: 30.9912 | AO11: 17.329 | AP11: 25.880235 | AQ11: 2.1683202 | AR11: 4.2998076 | AS11: 0.63389444 | AT11: 0.66057443 | AU11: 0.31483385 | AV11: 0.26712 | AW11: 2.240789 | AX11: 0.120672 | AY11: 0.19641642 | AZ11: 0.024442 | BA11: 113.171 | BB11: 3.499 | BF11: 0 | BH11: 3.297 | BI11: 2020 | BJ11: 1 | BQ11: 2025 | BR11: 570.14 | BS11: 1.74 | BT11: 17.25 | BU11: 10.36 | BV11: =F11*(1+N(H11)/100)*(1+N(I11)/100)^5 -> 3329.6125 | BW11: =IF(N(G11)>0,G11,F11) -> 4396.548 | BX11: =F11/BW11 -> 0.71898271 | BY11: =IF(ISNUMBER(K11),1,0) -> 1 | BZ11: =IF(BY11=0,"",N(N11)+N(O11)+N(P11)) -> 428.30152 | CA11: =IF(BY11=0,"",(N(Y11)*34.2+N(Z11)*38.6)/1000) -> 2.1009873 | CB11: =IF(BY11=0,"",N(O11)*0.0036+N(R11)+N(V11)+(N(AA11)*25.3+N(AB11)*37)/1000) -> 1.6734679 | CC11: =IF(BY11=0,"",N(N11)*0.0036+N(Q11)+N(U11)+N(T11)+N(X11)+N(AC11)*38/1000) -> 1.6092629 | CD11: =IF(BY11=0,"",N(Q11)+N(R11)+N(S11)+N(T11)+N(U11)+N(V11)+N(W11)+N(X11)+(N(Y11)*34.2+N(Z11)*38.6+N(AA11)*25.3+N(AB11)*37+N(AC11)*38)/1000) -> 4.059869 | CE11: =IF(BY11=0,"",MAX(0,N(L11)-N(K11))+MAX(0,N(M11)-N(L11))) -> 100.925 | CF11: =IF(BY11=0,"",N(Y11)*N(AD11)+N(Z11)*N(AE11)+N(AA11)*N(AF11)+N(AB11)*N(AG11)+N(AC11)*N(AH11)+N(U11)*N(AI11)+N(V11)*N(AJ11)+N(W11)*N(AK11)+N(X11)*N(AL11)+N(Q11)*N(AM11)+N(R11)*N(AN11)+N(S11)*N(AO11)+N(T11)*N(AP11)) -> 93.138908 | CG11: =IF(AND(BY11=1,N(K11)>0),K11,0) -> 322.969 | CH11: =IF(CG11>0,CF11*1000/CG11,"") -> 288.38343 | CI11: =IF(BY11=0,"",N(AQ11)+p_road*(N(AR11)+N(AS11)+N(AT11))) -> 2.1683202 | CJ11: =IF(CG11>0,CI11*1000/CG11,"") -> 6.7137099 | CK11: =IF(CH11="",1,MIN(p_idx_max,MAX(p_idx_min,CH11/p_fc_world))) -> 1.7911197 | CL11: =IF(CJ11="",1,MIN(p_idx_max,MAX(p_idx_min,CJ11/p_cb_world))) -> 0.25 | CM11: =p_b*(1-p_wb_idx+p_wb_idx*CK11) -> 0.23821892 | CN11: =p_c*(1-p_wc_idx+p_wc_idx*CL11) -> 0.03225 | CO11: =IF(N(BR11)>0,(N(BS11)+N(BT11)+N(BU11))/BR11,"") -> 0.051478584 | CP11: =N(BS11)+N(BT11)+N(BU11) -> 29.35 | CQ11: =IF(CP11>0,N(BS11)/CP11,"") -> 0.059284497 | CR11: =IF(CP11>0,N(BT11)/CP11,"") -> 0.58773424 | CS11: =IF(CP11>0,N(BU11)/CP11,"") -> 0.35298126 | CT11: =1000*(p_sh_pv*p_cf_pv/p_capex_pv+(1-p_sh_pv)*p_cf_wind/p_capex_wind)*8760 -> 2301.2886 | CU11: =IF(AND(ISNUMBER(CO11),ISNUMBER(CQ11),BY11=1),1,0) -> 1 | CV11: =IF(CU11=0,"",CQ11*p_hr_coal*N(AK11)+CR11*p_hr_gas*N(AO11)+CS11*p_hr_oil*N(AH11)/p_gj_l_oil) -> 137.01431 | CW11: =IF(CU11=0,"",CQ11*p_hr_coal*p_ef_coal+CR11*p_hr_gas*p_ef_gas+CS11*p_hr_oil*p_ef_oil) -> 0.59024019 | CX11: =IF(CU11=0,"",CQ11*p_hr_coal*N(AW11)+CR11*p_hr_gas*N(AX11)+CS11*p_hr_oil*N(AY11)/p_gj_l_oil) -> 20.719919 | CY11: =IF(CU11=0,"",CO11*CW11) -> 0.030384729 | CZ11: =IF(CU11=0,"",CT11*CO11*CV11/1000/1000-p_om_re) -> 0.0012316848 | DA11: =IF(CU11=0,"",CT11*CO11*CX11/1000/1000) -> 0.0024546282 | DB11: =IF(CU11=0,"",CT11*CO11*CW11/1000) -> 0.06992403 | DC11: =IF(AND(CU11=1,ISNUMBER(AD11),ISNUMBER(AV11)),1,0) -> 1 | DD11: =IF(DC11=0,"",p_ev_km*p_ice_l/100*AD11-p_ev_km*p_ev_kwh*AV11+p_ev_km*p_ev_maint) -> 428.994 | DE11: =IF(DC11=0,"",DD11/p_ev_prem) -> 0.0857988 | DF11: =IF(DC11=0,"",p_ev_km*p_ice_l/100*N(AZ11)/p_ev_prem) -> 0.00549945 | DG11: =IF(DC11=0,"",1000/p_ev_prem*(p_ev_km*p_ice_l/100*p_gj_l_gso*p_ef_gso-p_ev_km*p_ev_kwh/1000*CY11)) -> 0.51685575 | DH11: =IFERROR(IF(INDEX(Damodaran!$D:$D,MATCH(A11,Damodaran!$A:$A,0))="","",INDEX(Damodaran!$D:$D,MATCH(A11,Damodaran!$A:$A,0))),"") | DI11: =IFERROR(IF(INDEX(Damodaran!$E:$E,MATCH(A11,Damodaran!$A:$A,0))="","",INDEX(Damodaran!$E:$E,MATCH(A11,Damodaran!$A:$A,0))),"") | DJ11: =IFERROR(IF(INDEX(Damodaran!$G:$G,MATCH(A11,Damodaran!$A:$A,0))="","",INDEX(Damodaran!$G:$G,MATCH(A11,Damodaran!$A:$A,0))),"") | DK11: =IF(ISNUMBER(BG11),(1+BG11/100)*(1+p_infl)-1,"") | DL11: =IF(ISNUMBER(BH11),BH11/100,"") -> 0.03297 | DM11: =IF(COUNT(DK11,DL11)=0,"",AVERAGE(DK11,DL11)) -> 0.03297 | DN11: =IF(OR(DH11="",DI11=""),"",p_dv*(p_rf+DH11)*(1-IF(DJ11="",p_tax_def,DJ11))+(1-p_dv)*(p_rf+p_beta*p_erp+p_lambda*DI11)) | DO11: =IF(AND(ISNUMBER(DM11),ISNUMBER(DN11)),1,0) -> 0 | DP11: =IF(DO11=1,DM11,0) -> 0 | DQ11: =IF(DO11=1,DN11,0) -> 0 | DR11: =IF(DN11="","",DN11+p_shift) | DS11: =IF(E11="AE",p_r_ae,IF(E11="China",p_r_chn,p_r_emdc)) -> 0.055 | DT11: =IF(E11="AE",p_rh_ae,IF(E11="China",p_rh_chn,p_rh_emdc)) -> 0.07 | DU11: =IF(AND(p_use_obs=1,ISNUMBER(DM11)),DM11,IF(AND(p_use_dam=1,ISNUMBER(DR11)),DR11,DS11)) -> 0.03297 | DV11: =IF(AND(p_use_obs=1,ISNUMBER(DM11)),"Observed (IRENA/Steffen)",IF(AND(p_use_dam=1,ISNUMBER(DR11)),"Damodaran (eq. 5)","Group default (IHLEG)")) -> Observed (IRENA/Steffen) | DW11: =IF(p_basis=1,(1+DU11)/(1+p_infl)-1,DU11) -> 0.03297 | DX11: =DW11+(DT11-DS11) -> 0.04797 | DY11: =IF(AND(p_use_pefa=1,ISNUMBER(BD11)),p_gap_lic-(BD11-1)/3*(p_gap_lic-p_gap_ae),IF(E11="AE",p_gap_ae,IF(D11="Low income",p_gap_lic,p_gap_em)))*(1-p_reform*p_reform_close) -> 0.13 | DZ11: =IF(AND(p_use_pefa=1,ISNUMBER(BD11)),"PEFA PI-11","Income-group default (IMF 2015)") -> Income-group default (IMF 2015) | EA11: =IF(E11="AE",p_ps_ae,IF(E11="China",p_ps_chn,p_ps_emdc)) -> 0.3 | EB11: =(1-EA11)+EA11/(1-DY11) -> 1.0448276 | EC11: =Results_Country!F11 -> 106.42816 | ED11: =IF(CH11="",0,CH11*EC11) -> 30692.117 | EE11: =IF(CJ11="",0,CJ11*EC11) -> 714.52778 | EF11: =IF(CH11="",0,EC11) -> 106.42816
A12: ITA | B12: Italy | C12: Europe & Central Asia | D12: High income | E12: AE | F12: 2382.718 | G12: 3621.731 | H12: 0.54 | I12: 0.521 | J12: 59.342867 | K12: 363.035 | L12: 447.538 | M12: 420.033 | N12: 213.61648 | O12: 66.269969 | P12: 8.4038798 | Q12: 0.69419561 | R12: 1.1952985 | S12: 0.75673072 | T12: 0.03793074 | U12: 0.049249903 | V12: 0 | W12: 0.27245165 | X12: 0 | Y12: 10.263926 | Z12: 32.318626 | AA12: 6.3067059 | AB12: 0.59085187 | AC12: 7.1239353 | AD12: 0.882842 | AE12: 0.83926 | AF12: 0.550196 | AG12: 0.65601 | AH12: 0.51946289 | AI12: 7.119 | AJ12: 14.5851 | AK12: 5.342 | AL12: 5.6140443 | AM12: 15.923 | AN12: 34.78342 | AO12: 15.923 | AP12: 24.442243 | AQ12: 11.871101 | AR12: 2.0895449 | AS12: 0.71187964 | AT12: 1.5498152 | AU12: 0.53175766 | AV12: 0.256054 | AW12: 2.919646 | AX12: 0.66781 | AY12: 0.22774112 | AZ12: 0.085076 | BA12: 134.735 | BB12: 7.677 | BF12: 0 | BH12: 4.38 | BI12: 2020 | BJ12: 1 | BQ12: 2025 | BR12: 264.94 | BS12: 3.58 | BT12: 125.53 | BU12: 6.72 | BV12: =F12*(1+N(H12)/100)*(1+N(I12)/100)^5 -> 2458.6433 | BW12: =IF(N(G12)>0,G12,F12) -> 3621.731 | BX12: =F12/BW12 -> 0.6578948 | BY12: =IF(ISNUMBER(K12),1,0) -> 1 | BZ12: =IF(BY12=0,"",N(N12)+N(O12)+N(P12)) -> 288.29033 | CA12: =IF(BY12=0,"",(N(Y12)*34.2+N(Z12)*38.6)/1000) -> 1.5985252 | CB12: =IF(BY12=0,"",N(O12)*0.0036+N(R12)+N(V12)+(N(AA12)*25.3+N(AB12)*37)/1000) -> 1.6152916 | CC12: =IF(BY12=0,"",N(N12)*0.0036+N(Q12)+N(U12)+N(T12)+N(X12)+N(AC12)*38/1000) -> 1.8211051 | CD12: =IF(BY12=0,"",N(Q12)+N(R12)+N(S12)+N(T12)+N(U12)+N(V12)+N(W12)+N(X12)+(N(Y12)*34.2+N(Z12)*38.6+N(AA12)*25.3+N(AB12)*37+N(AC12)*38)/1000) -> 5.0565131 | CE12: =IF(BY12=0,"",MAX(0,N(L12)-N(K12))+MAX(0,N(M12)-N(L12))) -> 84.503 | CF12: =IF(BY12=0,"",N(Y12)*N(AD12)+N(Z12)*N(AE12)+N(AA12)*N(AF12)+N(AB12)*N(AG12)+N(AC12)*N(AH12)+N(U12)*N(AI12)+N(V12)*N(AJ12)+N(W12)*N(AK12)+N(X12)*N(AL12)+N(Q12)*N(AM12)+N(R12)*N(AN12)+N(S12)*N(AO12)+N(T12)*N(AP12)) -> 111.15613 | CG12: =IF(AND(BY12=1,N(K12)>0),K12,0) -> 363.035 | CH12: =IF(CG12>0,CF12*1000/CG12,"") -> 306.18572 | CI12: =IF(BY12=0,"",N(AQ12)+p_road*(N(AR12)+N(AS12)+N(AT12))) -> 11.871101 | CJ12: =IF(CG12>0,CI12*1000/CG12,"") -> 32.699605 | CK12: =IF(CH12="",1,MIN(p_idx_max,MAX(p_idx_min,CH12/p_fc_world))) -> 1.9016879 | CL12: =IF(CJ12="",1,MIN(p_idx_max,MAX(p_idx_min,CJ12/p_cb_world))) -> 0.6217743 | CM12: =p_b*(1-p_wb_idx+p_wb_idx*CK12) -> 0.25292449 | CN12: =p_c*(1-p_wc_idx+p_wc_idx*CL12) -> 0.080208885 | CO12: =IF(N(BR12)>0,(N(BS12)+N(BT12)+N(BU12))/BR12,"") -> 0.51268212 | CP12: =N(BS12)+N(BT12)+N(BU12) -> 135.83 | CQ12: =IF(CP12>0,N(BS12)/CP12,"") -> 0.026356475 | CR12: =IF(CP12>0,N(BT12)/CP12,"") -> 0.92416992 | CS12: =IF(CP12>0,N(BU12)/CP12,"") -> 0.049473607 | CT12: =1000*(p_sh_pv*p_cf_pv/p_capex_pv+(1-p_sh_pv)*p_cf_wind/p_capex_wind)*8760 -> 2301.2886 | CU12: =IF(AND(ISNUMBER(CO12),ISNUMBER(CQ12),BY12=1),1,0) -> 1 | CV12: =IF(CU12=0,"",CQ12*p_hr_coal*N(AK12)+CR12*p_hr_gas*N(AO12)+CS12*p_hr_oil*N(AH12)/p_gj_l_oil) -> 118.7655 | CW12: =IF(CU12=0,"",CQ12*p_hr_coal*p_ef_coal+CR12*p_hr_gas*p_ef_gas+CS12*p_hr_oil*p_ef_oil) -> 0.45398492 | CX12: =IF(CU12=0,"",CQ12*p_hr_coal*N(AW12)+CR12*p_hr_gas*N(AX12)+CS12*p_hr_oil*N(AY12)/p_gj_l_oil) -> 8.4631952 | CY12: =IF(CU12=0,"",CO12*CW12) -> 0.23274995 | CZ12: =IF(CU12=0,"",CT12*CO12*CV12/1000/1000-p_om_re) -> 0.12512304 | DA12: =IF(CU12=0,"",CT12*CO12*CX12/1000/1000) -> 0.0099851273 | DB12: =IF(CU12=0,"",CT12*CO12*CW12/1000) -> 0.5356248 | DC12: =IF(AND(CU12=1,ISNUMBER(AD12),ISNUMBER(AV12)),1,0) -> 1 | DD12: =IF(DC12=0,"",p_ev_km*p_ice_l/100*AD12-p_ev_km*p_ev_kwh*AV12+p_ev_km*p_ev_maint) -> 481.85145 | DE12: =IF(DC12=0,"",DD12/p_ev_prem) -> 0.09637029 | DF12: =IF(DC12=0,"",p_ev_km*p_ice_l/100*N(AZ12)/p_ev_prem) -> 0.0191421 | DG12: =IF(DC12=0,"",1000/p_ev_prem*(p_ev_km*p_ice_l/100*p_gj_l_gso*p_ef_gso-p_ev_km*p_ev_kwh/1000*CY12)) -> 0.40757853 | DH12: =IFERROR(IF(INDEX(Damodaran!$D:$D,MATCH(A12,Damodaran!$A:$A,0))="","",INDEX(Damodaran!$D:$D,MATCH(A12,Damodaran!$A:$A,0))),"") | DI12: =IFERROR(IF(INDEX(Damodaran!$E:$E,MATCH(A12,Damodaran!$A:$A,0))="","",INDEX(Damodaran!$E:$E,MATCH(A12,Damodaran!$A:$A,0))),"") | DJ12: =IFERROR(IF(INDEX(Damodaran!$G:$G,MATCH(A12,Damodaran!$A:$A,0))="","",INDEX(Damodaran!$G:$G,MATCH(A12,Damodaran!$A:$A,0))),"") | DK12: =IF(ISNUMBER(BG12),(1+BG12/100)*(1+p_infl)-1,"") | DL12: =IF(ISNUMBER(BH12),BH12/100,"") -> 0.0438 | DM12: =IF(COUNT(DK12,DL12)=0,"",AVERAGE(DK12,DL12)) -> 0.0438 | DN12: =IF(OR(DH12="",DI12=""),"",p_dv*(p_rf+DH12)*(1-IF(DJ12="",p_tax_def,DJ12))+(1-p_dv)*(p_rf+p_beta*p_erp+p_lambda*DI12)) | DO12: =IF(AND(ISNUMBER(DM12),ISNUMBER(DN12)),1,0) -> 0 | DP12: =IF(DO12=1,DM12,0) -> 0 | DQ12: =IF(DO12=1,DN12,0) -> 0 | DR12: =IF(DN12="","",DN12+p_shift) | DS12: =IF(E12="AE",p_r_ae,IF(E12="China",p_r_chn,p_r_emdc)) -> 0.055 | DT12: =IF(E12="AE",p_rh_ae,IF(E12="China",p_rh_chn,p_rh_emdc)) -> 0.07 | DU12: =IF(AND(p_use_obs=1,ISNUMBER(DM12)),DM12,IF(AND(p_use_dam=1,ISNUMBER(DR12)),DR12,DS12)) -> 0.0438 | DV12: =IF(AND(p_use_obs=1,ISNUMBER(DM12)),"Observed (IRENA/Steffen)",IF(AND(p_use_dam=1,ISNUMBER(DR12)),"Damodaran (eq. 5)","Group default (IHLEG)")) -> Observed (IRENA/Steffen) | DW12: =IF(p_basis=1,(1+DU12)/(1+p_infl)-1,DU12) -> 0.0438 | DX12: =DW12+(DT12-DS12) -> 0.0588 | DY12: =IF(AND(p_use_pefa=1,ISNUMBER(BD12)),p_gap_lic-(BD12-1)/3*(p_gap_lic-p_gap_ae),IF(E12="AE",p_gap_ae,IF(D12="Low income",p_gap_lic,p_gap_em)))*(1-p_reform*p_reform_close) -> 0.13 | DZ12: =IF(AND(p_use_pefa=1,ISNUMBER(BD12)),"PEFA PI-11","Income-group default (IMF 2015)") -> Income-group default (IMF 2015) | EA12: =IF(E12="AE",p_ps_ae,IF(E12="China",p_ps_chn,p_ps_emdc)) -> 0.3 | EB12: =(1-EA12)+EA12/(1-DY12) -> 1.0448276 | EC12: =Results_Country!F12 -> 81.737972 | ED12: =IF(CH12="",0,CH12*EC12) -> 25027 | EE12: =IF(CJ12="",0,CJ12*EC12) -> 2672.7994 | EF12: =IF(CH12="",0,EC12) -> 81.737972
A13: CAN | B13: Canada | C13: North America | D13: High income | E13: AE | F13: 2270.076 | G13: 2664.499 | H13: 1.743 | I13: 1.5 | J13: 39.74243 | K13: 554.217 | L13: 692.775 | M13: 674.974 | N13: 361.00577 | O13: 183.85597 | P13: 1.3475757 | Q13: 2.4781693 | R13: 1.3905666 | S13: 0.69045723 | T13: 0.004498239 | U13: 0.085562753 | V13: 0.00054807211 | W13: 0.12823314 | X13: 0 | Y13: 40.858403 | Z13: 33.12605 | AA13: 3.2528522 | AB13: 2.5343506 | AC13: 14.97459 | AD13: 0.791261 | AE13: 0.656437 | AF13: 0.539014 | AG13: 0.571502 | AH13: 0.51946289 | AI13: 5.678 | AJ13: 9.8679 | AK13: 4.055 | AL13: 4.7177396 | AM13: 5.223 | AN13: 8.75175 | AO13: 5.223 | AP13: 6.2992786 | AQ13: 0.70812725 | AR13: 8.70352 | AS13: 0.78918323 | AT13: 0.42018768 | AU13: 0.74209333 | AV13: 0.113295 | AW13: 1.047297 | AX13: 0.169866 | AY13: 0.080510682 | AZ13: 0.018358 | BA13: 110.019 | BB13: 0.014 | BF13: 0 | BQ13: 2025 | BR13: 652.43 | BS13: 26.05 | BT13: 116.61 | BU13: 7.61 | BV13: =F13*(1+N(H13)/100)*(1+N(I13)/100)^5 -> 2488.1419 | BW13: =IF(N(G13)>0,G13,F13) -> 2664.499 | BX13: =F13/BW13 -> 0.85197105 | BY13: =IF(ISNUMBER(K13),1,0) -> 1 | BZ13: =IF(BY13=0,"",N(N13)+N(O13)+N(P13)) -> 546.20931 | CA13: =IF(BY13=0,"",(N(Y13)*34.2+N(Z13)*38.6)/1000) -> 2.6760229 | CB13: =IF(BY13=0,"",N(O13)*0.0036+N(R13)+N(V13)+(N(AA13)*25.3+N(AB13)*37)/1000) -> 2.2290643 | CC13: =IF(BY13=0,"",N(N13)*0.0036+N(Q13)+N(U13)+N(T13)+N(X13)+N(AC13)*38/1000) -> 4.4368854 | CD13: =IF(BY13=0,"",N(Q13)+N(R13)+N(S13)+N(T13)+N(U13)+N(V13)+N(W13)+N(X13)+(N(Y13)*34.2+N(Z13)*38.6+N(AA13)*25.3+N(AB13)*37+N(AC13)*38)/1000) -> 8.1991608 | CE13: =IF(BY13=0,"",MAX(0,N(L13)-N(K13))+MAX(0,N(M13)-N(L13))) -> 138.558 | CF13: =IF(BY13=0,"",N(Y13)*N(AD13)+N(Z13)*N(AE13)+N(AA13)*N(AF13)+N(AB13)*N(AG13)+N(AC13)*N(AH13)+N(U13)*N(AI13)+N(V13)*N(AJ13)+N(W13)*N(AK13)+N(X13)*N(AL13)+N(Q13)*N(AM13)+N(R13)*N(AN13)+N(S13)*N(AO13)+N(T13)*N(AP13)) -> 94.814471 | CG13: =IF(AND(BY13=1,N(K13)>0),K13,0) -> 554.217 | CH13: =IF(CG13>0,CF13*1000/CG13,"") -> 171.07824 | CI13: =IF(BY13=0,"",N(AQ13)+p_road*(N(AR13)+N(AS13)+N(AT13))) -> 0.70812725 | CJ13: =IF(CG13>0,CI13*1000/CG13,"") -> 1.2777075 | CK13: =IF(CH13="",1,MIN(p_idx_max,MAX(p_idx_min,CH13/p_fc_world))) -> 1.0625493 | CL13: =IF(CJ13="",1,MIN(p_idx_max,MAX(p_idx_min,CJ13/p_cb_world))) -> 0.25 | CM13: =p_b*(1-p_wb_idx+p_wb_idx*CK13) -> 0.14131906 | CN13: =p_c*(1-p_wc_idx+p_wc_idx*CL13) -> 0.03225 | CO13: =IF(N(BR13)>0,(N(BS13)+N(BT13)+N(BU13))/BR13,"") -> 0.23032356 | CP13: =N(BS13)+N(BT13)+N(BU13) -> 150.27 | CQ13: =IF(CP13>0,N(BS13)/CP13,"") -> 0.17335463 | CR13: =IF(CP13>0,N(BT13)/CP13,"") -> 0.77600319 | CS13: =IF(CP13>0,N(BU13)/CP13,"") -> 0.050642177 | CT13: =1000*(p_sh_pv*p_cf_pv/p_capex_pv+(1-p_sh_pv)*p_cf_wind/p_capex_wind)*8760 -> 2301.2886 | CU13: =IF(AND(ISNUMBER(CO13),ISNUMBER(CQ13),BY13=1),1,0) -> 1 | CV13: =IF(CU13=0,"",CQ13*p_hr_coal*N(AK13)+CR13*p_hr_gas*N(AO13)+CS13*p_hr_oil*N(AH13)/p_gj_l_oil) -> 44.583492 | CW13: =IF(CU13=0,"",CQ13*p_hr_coal*p_ef_coal+CR13*p_hr_gas*p_ef_gas+CS13*p_hr_oil*p_ef_oil) -> 0.53165372 | CX13: =IF(CU13=0,"",CQ13*p_hr_coal*N(AW13)+CR13*p_hr_gas*N(AX13)+CS13*p_hr_oil*N(AY13)/p_gj_l_oil) -> 3.9132548 | CY13: =IF(CU13=0,"",CO13*CW13) -> 0.12245238 | CZ13: =IF(CU13=0,"",CT13*CO13*CV13/1000/1000-p_om_re) -> 0.0086310773 | DA13: =IF(CU13=0,"",CT13*CO13*CX13/1000/1000) -> 0.0020741854 | DB13: =IF(CU13=0,"",CT13*CO13*CW13/1000) -> 0.28179826 | DC13: =IF(AND(CU13=1,ISNUMBER(AD13),ISNUMBER(AV13)),1,0) -> 1 | DD13: =IF(DC13=0,"",p_ev_km*p_ice_l/100*AD13-p_ev_km*p_ev_kwh*AV13+p_ev_km*p_ev_maint) -> 764.27212 | DE13: =IF(DC13=0,"",DD13/p_ev_prem) -> 0.15285442 | DF13: =IF(DC13=0,"",p_ev_km*p_ice_l/100*N(AZ13)/p_ev_prem) -> 0.00413055 | DG13: =IF(DC13=0,"",1000/p_ev_prem*(p_ev_km*p_ice_l/100*p_gj_l_gso*p_ef_gso-p_ev_km*p_ev_kwh/1000*CY13)) -> 0.46713922 | DH13: =IFERROR(IF(INDEX(Damodaran!$D:$D,MATCH(A13,Damodaran!$A:$A,0))="","",INDEX(Damodaran!$D:$D,MATCH(A13,Damodaran!$A:$A,0))),"") | DI13: =IFERROR(IF(INDEX(Damodaran!$E:$E,MATCH(A13,Damodaran!$A:$A,0))="","",INDEX(Damodaran!$E:$E,MATCH(A13,Damodaran!$A:$A,0))),"") | DJ13: =IFERROR(IF(INDEX(Damodaran!$G:$G,MATCH(A13,Damodaran!$A:$A,0))="","",INDEX(Damodaran!$G:$G,MATCH(A13,Damodaran!$A:$A,0))),"") | DK13: =IF(ISNUMBER(BG13),(1+BG13/100)*(1+p_infl)-1,"") | DL13: =IF(ISNUMBER(BH13),BH13/100,"") | DM13: =IF(COUNT(DK13,DL13)=0,"",AVERAGE(DK13,DL13)) | DN13: =IF(OR(DH13="",DI13=""),"",p_dv*(p_rf+DH13)*(1-IF(DJ13="",p_tax_def,DJ13))+(1-p_dv)*(p_rf+p_beta*p_erp+p_lambda*DI13)) | DO13: =IF(AND(ISNUMBER(DM13),ISNUMBER(DN13)),1,0) -> 0 | DP13: =IF(DO13=1,DM13,0) -> 0 | DQ13: =IF(DO13=1,DN13,0) -> 0 | DR13: =IF(DN13="","",DN13+p_shift) | DS13: =IF(E13="AE",p_r_ae,IF(E13="China",p_r_chn,p_r_emdc)) -> 0.055 | DT13: =IF(E13="AE",p_rh_ae,IF(E13="China",p_rh_chn,p_rh_emdc)) -> 0.07 | DU13: =IF(AND(p_use_obs=1,ISNUMBER(DM13)),DM13,IF(AND(p_use_dam=1,ISNUMBER(DR13)),DR13,DS13)) -> 0.055 | DV13: =IF(AND(p_use_obs=1,ISNUMBER(DM13)),"Observed (IRENA/Steffen)",IF(AND(p_use_dam=1,ISNUMBER(DR13)),"Damodaran (eq. 5)","Group default (IHLEG)")) -> Group default (IHLEG) | DW13: =IF(p_basis=1,(1+DU13)/(1+p_infl)-1,DU13) -> 0.055 | DX13: =DW13+(DT13-DS13) -> 0.07 | DY13: =IF(AND(p_use_pefa=1,ISNUMBER(BD13)),p_gap_lic-(BD13-1)/3*(p_gap_lic-p_gap_ae),IF(E13="AE",p_gap_ae,IF(D13="Low income",p_gap_lic,p_gap_em)))*(1-p_reform*p_reform_close) -> 0.13 | DZ13: =IF(AND(p_use_pefa=1,ISNUMBER(BD13)),"PEFA PI-11","Income-group default (IMF 2015)") -> Income-group default (IMF 2015) | EA13: =IF(E13="AE",p_ps_ae,IF(E13="China",p_ps_chn,p_ps_emdc)) -> 0.3 | EB13: =(1-EA13)+EA13/(1-DY13) -> 1.0448276 | EC13: =Results_Country!F13 -> 108.78607 | ED13: =IF(CH13="",0,CH13*EC13) -> 18610.929 | EE13: =IF(CJ13="",0,CJ13*EC13) -> 138.99678 | EF13: =IF(CH13="",0,EC13) -> 108.78607
A14: RUS | B14: Russian Federation | C14: Europe & Central Asia | D14: High income | E14: EMDC | F14: 2185.848 | G14: 6968.614 | H14: 0.981 | I14: 1.091 | J14: 144.82042 | K14: 1982.113 | L14: 2446.295 | M14: 1907.973 | N14: 662.08196 | O14: 203.20399 | P14: 68.516159 | Q14: 5.7651347 | R14: 3.2312642 | S14: 6.8294025 | T14: 0.024039572 | U14: 2.3028463 | V14: 0.12755457 | W14: 3.853555 | X14: 0 | Y14: 48.677689 | Z14: 48.238173 | AA14: 27.125199 | AB14: 7.4977358 | AC14: 6.913723 | AD14: 0.659127 | AE14: 0.686362 | AF14: 0.512933 | AG14: 0.781 | AH14: 0.4256768 | AI14: 4.347 | AJ14: 3.1116 | AK14: 1.376 | AL14: 2.4999958 | AM14: 2.456 | AN14: 7.7652 | AO14: 2.456 | AP14: 3.5400164 | AQ14: 195.17796 | AR14: 21.230975 | AS14: 14.272179 | AT14: 6.4707108 | AU14: 0.26728612 | AV14: 0.0948 | AW14: 13.272426 | AX14: 1.406916 | AY14: 0.40822491 | AZ14: 0.282325 | BA14: 14.758 | BB14: 0.285 | BF14: 0 | BP14: 0.015 | BQ14: 2025 | BR14: 1192.78 | BS14: 219.52 | BT14: 533.17 | BU14: 14.47 | BV14: =F14*(1+N(H14)/100)*(1+N(I14)/100)^5 -> 2330.355 | BW14: =IF(N(G14)>0,G14,F14) -> 6968.614 | BX14: =F14/BW14 -> 0.31367041 | BY14: =IF(ISNUMBER(K14),1,0) -> 1 | BZ14: =IF(BY14=0,"",N(N14)+N(O14)+N(P14)) -> 933.80212 | CA14: =IF(BY14=0,"",(N(Y14)*34.2+N(Z14)*38.6)/1000) -> 3.5267704 | CB14: =IF(BY14=0,"",N(O14)*0.0036+N(R14)+N(V14)+(N(AA14)*25.3+N(AB14)*37)/1000) -> 5.0540369 | CC14: =IF(BY14=0,"",N(N14)*0.0036+N(Q14)+N(U14)+N(T14)+N(X14)+N(AC14)*38/1000) -> 10.738237 | CD14: =IF(BY14=0,"",N(Q14)+N(R14)+N(S14)+N(T14)+N(U14)+N(V14)+N(W14)+N(X14)+(N(Y14)*34.2+N(Z14)*38.6+N(AA14)*25.3+N(AB14)*37+N(AC14)*38)/1000) -> 26.886972 | CE14: =IF(BY14=0,"",MAX(0,N(L14)-N(K14))+MAX(0,N(M14)-N(L14))) -> 464.182 | CF14: =IF(BY14=0,"",N(Y14)*N(AD14)+N(Z14)*N(AE14)+N(AA14)*N(AF14)+N(AB14)*N(AG14)+N(AC14)*N(AH14)+N(U14)*N(AI14)+N(V14)*N(AJ14)+N(W14)*N(AK14)+N(X14)*N(AL14)+N(Q14)*N(AM14)+N(R14)*N(AN14)+N(S14)*N(AO14)+N(T14)*N(AP14)) -> 159.72434 | CG14: =IF(AND(BY14=1,N(K14)>0),K14,0) -> 1982.113 | CH14: =IF(CG14>0,CF14*1000/CG14,"") -> 80.582863 | CI14: =IF(BY14=0,"",N(AQ14)+p_road*(N(AR14)+N(AS14)+N(AT14))) -> 195.17796 | CJ14: =IF(CG14>0,CI14*1000/CG14,"") -> 98.469642 | CK14: =IF(CH14="",1,MIN(p_idx_max,MAX(p_idx_min,CH14/p_fc_world))) -> 0.50049185 | CL14: =IF(CJ14="",1,MIN(p_idx_max,MAX(p_idx_min,CJ14/p_cb_world))) -> 1.8723741 | CM14: =p_b*(1-p_wb_idx+p_wb_idx*CK14) -> 0.066565415 | CN14: =p_c*(1-p_wc_idx+p_wc_idx*CL14) -> 0.24153626 | CO14: =IF(N(BR14)>0,(N(BS14)+N(BT14)+N(BU14))/BR14,"") -> 0.64316974 | CP14: =N(BS14)+N(BT14)+N(BU14) -> 767.16 | CQ14: =IF(CP14>0,N(BS14)/CP14,"") -> 0.28614631 | CR14: =IF(CP14>0,N(BT14)/CP14,"") -> 0.69499192 | CS14: =IF(CP14>0,N(BU14)/CP14,"") -> 0.018861776 | CT14: =1000*(p_sh_pv*p_cf_pv/p_capex_pv+(1-p_sh_pv)*p_cf_wind/p_capex_wind)*8760 -> 2301.2886 | CU14: =IF(AND(ISNUMBER(CO14),ISNUMBER(CQ14),BY14=1),1,0) -> 1 | CV14: =IF(CU14=0,"",CQ14*p_hr_coal*N(AK14)+CR14*p_hr_gas*N(AO14)+CS14*p_hr_oil*N(AH14)/p_gj_l_oil) -> 18.923184 | CW14: =IF(CU14=0,"",CQ14*p_hr_coal*p_ef_coal+CR14*p_hr_gas*p_ef_gas+CS14*p_hr_oil*p_ef_oil) -> 0.57844122 | CX14: =IF(CU14=0,"",CQ14*p_hr_coal*N(AW14)+CR14*p_hr_gas*N(AX14)+CS14*p_hr_oil*N(AY14)/p_gj_l_oil) -> 47.406539 | CY14: =IF(CU14=0,"",CO14*CW14) -> 0.37203589 | CZ14: =IF(CU14=0,"",CT14*CO14*CV14/1000/1000-p_om_re) -> 0.013008568 | DA14: =IF(CU14=0,"",CT14*CO14*CX14/1000/1000) -> 0.070167327 | DB14: =IF(CU14=0,"",CT14*CO14*CW14/1000) -> 0.85616194 | DC14: =IF(AND(CU14=1,ISNUMBER(AD14),ISNUMBER(AV14)),1,0) -> 1 | DD14: =IF(DC14=0,"",p_ev_km*p_ice_l/100*AD14-p_ev_km*p_ev_kwh*AV14+p_ev_km*p_ev_maint) -> 665.55787 | DE14: =IF(DC14=0,"",DD14/p_ev_prem) -> 0.13311158 | DF14: =IF(DC14=0,"",p_ev_km*p_ice_l/100*N(AZ14)/p_ev_prem) -> 0.063523125 | DG14: =IF(DC14=0,"",1000/p_ev_prem*(p_ev_km*p_ice_l/100*p_gj_l_gso*p_ef_gso-p_ev_km*p_ev_kwh/1000*CY14)) -> 0.33236412 | DH14: =IFERROR(IF(INDEX(Damodaran!$D:$D,MATCH(A14,Damodaran!$A:$A,0))="","",INDEX(Damodaran!$D:$D,MATCH(A14,Damodaran!$A:$A,0))),"") | DI14: =IFERROR(IF(INDEX(Damodaran!$E:$E,MATCH(A14,Damodaran!$A:$A,0))="","",INDEX(Damodaran!$E:$E,MATCH(A14,Damodaran!$A:$A,0))),"") | DJ14: =IFERROR(IF(INDEX(Damodaran!$G:$G,MATCH(A14,Damodaran!$A:$A,0))="","",INDEX(Damodaran!$G:$G,MATCH(A14,Damodaran!$A:$A,0))),"") | DK14: =IF(ISNUMBER(BG14),(1+BG14/100)*(1+p_infl)-1,"") | DL14: =IF(ISNUMBER(BH14),BH14/100,"") | DM14: =IF(COUNT(DK14,DL14)=0,"",AVERAGE(DK14,DL14)) | DN14: =IF(OR(DH14="",DI14=""),"",p_dv*(p_rf+DH14)*(1-IF(DJ14="",p_tax_def,DJ14))+(1-p_dv)*(p_rf+p_beta*p_erp+p_lambda*DI14)) | DO14: =IF(AND(ISNUMBER(DM14),ISNUMBER(DN14)),1,0) -> 0 | DP14: =IF(DO14=1,DM14,0) -> 0 | DQ14: =IF(DO14=1,DN14,0) -> 0 | DR14: =IF(DN14="","",DN14+p_shift) | DS14: =IF(E14="AE",p_r_ae,IF(E14="China",p_r_chn,p_r_emdc)) -> 0.105 | DT14: =IF(E14="AE",p_rh_ae,IF(E14="China",p_rh_chn,p_rh_emdc)) -> 0.15 | DU14: =IF(AND(p_use_obs=1,ISNUMBER(DM14)),DM14,IF(AND(p_use_dam=1,ISNUMBER(DR14)),DR14,DS14)) -> 0.105 | DV14: =IF(AND(p_use_obs=1,ISNUMBER(DM14)),"Observed (IRENA/Steffen)",IF(AND(p_use_dam=1,ISNUMBER(DR14)),"Damodaran (eq. 5)","Group default (IHLEG)")) -> Group default (IHLEG) | DW14: =IF(p_basis=1,(1+DU14)/(1+p_infl)-1,DU14) -> 0.105 | DX14: =DW14+(DT14-DS14) -> 0.15 | DY14: =IF(AND(p_use_pefa=1,ISNUMBER(BD14)),p_gap_lic-(BD14-1)/3*(p_gap_lic-p_gap_ae),IF(E14="AE",p_gap_ae,IF(D14="Low income",p_gap_lic,p_gap_em)))*(1-p_reform*p_reform_close) -> 0.27 | DZ14: =IF(AND(p_use_pefa=1,ISNUMBER(BD14)),"PEFA PI-11","Income-group default (IMF 2015)") -> Income-group default (IMF 2015) | EA14: =IF(E14="AE",p_ps_ae,IF(E14="China",p_ps_chn,p_ps_emdc)) -> 0.4 | EB14: =(1-EA14)+EA14/(1-DY14) -> 1.1479452 | EC14: =Results_Country!F14 -> 177.39905 | ED14: =IF(CH14="",0,CH14*EC14) -> 14295.324 | EE14: =IF(CJ14="",0,CJ14*EC14) -> 17468.421 | EF14: =IF(CH14="",0,EC14) -> 177.39905
A15: BRA | B15: Brazil | C15: Latin America & Caribbean | D15: Upper middle income | E15: EMDC | F15: 2185.822 | G15: 4742.6 | H15: 2.286 | I15: 1.911 | J15: 211.99857 | K15: 505.632 | L15: 1357.434 | M15: 1767.337 | N15: 375.78038 | O15: 149.00536 | P15: 2.0031885 | Q15: 0.57141255 | R15: 0.066238601 | S15: 0.15651863 | T15: 0.081242038 | U15: 0.37001748 | V15: 0.0010197106 | W15: 0.53470008 | X15: 0 | Y15: 25.344537 | Z15: 50.956676 | AA15: 13.494108 | AB15: 2.6414171 | AC15: 17.919337 | AD15: 0.88452 | AE15: 0.669963 | AF15: 0.605352 | AG15: 0.628336 | AH15: 0.51946289 | AI15: 6.222 | AJ15: 12.95424 | AK15: 6.222 | AL15: 6.2295794 | AM15: 17.367 | AN15: 53.76852 | AO15: 17.661 | AP15: 20.461052 | AQ15: 18.303298 | AR15: 4.6164704 | AS15: 1.6907218 | AT15: 8.1834573 | AU15: 0.82939074 | AV15: 0.1638 | AW15: 2.065699 | AX15: 0.228896 | AY15: 0.15514501 | AZ15: 0.024261 | BA15: 87.028 | BB15: 15.121 | BC15: 87.319 | BF15: 0 | BG15: 6.3 | BH15: 11.125 | BI15: 2022 | BJ15: 3 | BK15: 1 | BL15: 1.341 | BM15: 7.018 | BN15: 14.23 | BO15: 0.132 | BP15: 0.529 | BQ15: 2025 | BR15: 752.17 | BS15: 17.19 | BT15: 54.85 | BU15: 12.65 | BV15: =F15*(1+N(H15)/100)*(1+N(I15)/100)^5 -> 2457.7421 | BW15: =IF(N(G15)>0,G15,F15) -> 4742.6 | BX15: =F15/BW15 -> 0.46089107 | BY15: =IF(ISNUMBER(K15),1,0) -> 1 | BZ15: =IF(BY15=0,"",N(N15)+N(O15)+N(P15)) -> 526.78893 | CA15: =IF(BY15=0,"",(N(Y15)*34.2+N(Z15)*38.6)/1000) -> 2.8337109 | CB15: =IF(BY15=0,"",N(O15)*0.0036+N(R15)+N(V15)+(N(AA15)*25.3+N(AB15)*37)/1000) -> 1.042811 | CC15: =IF(BY15=0,"",N(N15)*0.0036+N(Q15)+N(U15)+N(T15)+N(X15)+N(AC15)*38/1000) -> 3.0564162 | CD15: =IF(BY15=0,"",N(Q15)+N(R15)+N(S15)+N(T15)+N(U15)+N(V15)+N(W15)+N(X15)+(N(Y15)*34.2+N(Z15)*38.6+N(AA15)*25.3+N(AB15)*37+N(AC15)*38)/1000) -> 5.7349281 | CE15: =IF(BY15=0,"",MAX(0,N(L15)-N(K15))+MAX(0,N(M15)-N(L15))) -> 1261.705 | CF15: =IF(BY15=0,"",N(Y15)*N(AD15)+N(Z15)*N(AE15)+N(AA15)*N(AF15)+N(AB15)*N(AG15)+N(AC15)*N(AH15)+N(U15)*N(AI15)+N(V15)*N(AJ15)+N(W15)*N(AK15)+N(X15)*N(AL15)+N(Q15)*N(AM15)+N(R15)*N(AN15)+N(S15)*N(AO15)+N(T15)*N(AP15)) -> 99.24786 | CG15: =IF(AND(BY15=1,N(K15)>0),K15,0) -> 505.632 | CH15: =IF(CG15>0,CF15*1000/CG15,"") -> 196.28477 | CI15: =IF(BY15=0,"",N(AQ15)+p_road*(N(AR15)+N(AS15)+N(AT15))) -> 18.303298 | CJ15: =IF(CG15>0,CI15*1000/CG15,"") -> 36.198852 | CK15: =IF(CH15="",1,MIN(p_idx_max,MAX(p_idx_min,CH15/p_fc_world))) -> 1.2191044 | CL15: =IF(CJ15="",1,MIN(p_idx_max,MAX(p_idx_min,CJ15/p_cb_world))) -> 0.68831156 | CM15: =p_b*(1-p_wb_idx+p_wb_idx*CK15) -> 0.16214089 | CN15: =p_c*(1-p_wc_idx+p_wc_idx*CL15) -> 0.088792191 | CO15: =IF(N(BR15)>0,(N(BS15)+N(BT15)+N(BU15))/BR15,"") -> 0.11259423 | CP15: =N(BS15)+N(BT15)+N(BU15) -> 84.69 | CQ15: =IF(CP15>0,N(BS15)/CP15,"") -> 0.20297556 | CR15: =IF(CP15>0,N(BT15)/CP15,"") -> 0.64765616 | CS15: =IF(CP15>0,N(BU15)/CP15,"") -> 0.14936828 | CT15: =1000*(p_sh_pv*p_cf_pv/p_capex_pv+(1-p_sh_pv)*p_cf_wind/p_capex_wind)*8760 -> 2301.2886 | CU15: =IF(AND(ISNUMBER(CO15),ISNUMBER(CQ15),BY15=1),1,0) -> 1 | CV15: =IF(CU15=0,"",CQ15*p_hr_coal*N(AK15)+CR15*p_hr_gas*N(AO15)+CS15*p_hr_oil*N(AH15)/p_gj_l_oil) -> 119.52249 | CW15: =IF(CU15=0,"",CQ15*p_hr_coal*p_ef_coal+CR15*p_hr_gas*p_ef_gas+CS15*p_hr_oil*p_ef_oil) -> 0.58590781 | CX15: =IF(CU15=0,"",CQ15*p_hr_coal*N(AW15)+CR15*p_hr_gas*N(AX15)+CS15*p_hr_oil*N(AY15)/p_gj_l_oil) -> 11.608447 | CY15: =IF(CU15=0,"",CO15*CW15) -> 0.065969837 | CZ15: =IF(CU15=0,"",CT15*CO15*CV15/1000/1000-p_om_re) -> 0.015969689 | DA15: =IF(CU15=0,"",CT15*CO15*CX15/1000/1000) -> 0.0030078857 | DB15: =IF(CU15=0,"",CT15*CO15*CW15/1000) -> 0.15181563 | DC15: =IF(AND(CU15=1,ISNUMBER(AD15),ISNUMBER(AV15)),1,0) -> 1 | DD15: =IF(DC15=0,"",p_ev_km*p_ice_l/100*AD15-p_ev_km*p_ev_kwh*AV15+p_ev_km*p_ev_maint) -> 732.825 | DE15: =IF(DC15=0,"",DD15/p_ev_prem) -> 0.146565 | DF15: =IF(DC15=0,"",p_ev_km*p_ice_l/100*N(AZ15)/p_ev_prem) -> 0.005458725 | DG15: =IF(DC15=0,"",1000/p_ev_prem*(p_ev_km*p_ice_l/100*p_gj_l_gso*p_ef_gso-p_ev_km*p_ev_kwh/1000*CY15)) -> 0.49763979 | DH15: =IFERROR(IF(INDEX(Damodaran!$D:$D,MATCH(A15,Damodaran!$A:$A,0))="","",INDEX(Damodaran!$D:$D,MATCH(A15,Damodaran!$A:$A,0))),"") | DI15: =IFERROR(IF(INDEX(Damodaran!$E:$E,MATCH(A15,Damodaran!$A:$A,0))="","",INDEX(Damodaran!$E:$E,MATCH(A15,Damodaran!$A:$A,0))),"") | DJ15: =IFERROR(IF(INDEX(Damodaran!$G:$G,MATCH(A15,Damodaran!$A:$A,0))="","",INDEX(Damodaran!$G:$G,MATCH(A15,Damodaran!$A:$A,0))),"") | DK15: =IF(ISNUMBER(BG15),(1+BG15/100)*(1+p_infl)-1,"") -> 0.08426 | DL15: =IF(ISNUMBER(BH15),BH15/100,"") -> 0.11125 | DM15: =IF(COUNT(DK15,DL15)=0,"",AVERAGE(DK15,DL15)) -> 0.097755 | DN15: =IF(OR(DH15="",DI15=""),"",p_dv*(p_rf+DH15)*(1-IF(DJ15="",p_tax_def,DJ15))+(1-p_dv)*(p_rf+p_beta*p_erp+p_lambda*DI15)) | DO15: =IF(AND(ISNUMBER(DM15),ISNUMBER(DN15)),1,0) -> 0 | DP15: =IF(DO15=1,DM15,0) -> 0 | DQ15: =IF(DO15=1,DN15,0) -> 0 | DR15: =IF(DN15="","",DN15+p_shift) | DS15: =IF(E15="AE",p_r_ae,IF(E15="China",p_r_chn,p_r_emdc)) -> 0.105 | DT15: =IF(E15="AE",p_rh_ae,IF(E15="China",p_rh_chn,p_rh_emdc)) -> 0.15 | DU15: =IF(AND(p_use_obs=1,ISNUMBER(DM15)),DM15,IF(AND(p_use_dam=1,ISNUMBER(DR15)),DR15,DS15)) -> 0.097755 | DV15: =IF(AND(p_use_obs=1,ISNUMBER(DM15)),"Observed (IRENA/Steffen)",IF(AND(p_use_dam=1,ISNUMBER(DR15)),"Damodaran (eq. 5)","Group default (IHLEG)")) -> Observed (IRENA/Steffen) | DW15: =IF(p_basis=1,(1+DU15)/(1+p_infl)-1,DU15) -> 0.097755 | DX15: =DW15+(DT15-DS15) -> 0.142755 | DY15: =IF(AND(p_use_pefa=1,ISNUMBER(BD15)),p_gap_lic-(BD15-1)/3*(p_gap_lic-p_gap_ae),IF(E15="AE",p_gap_ae,IF(D15="Low income",p_gap_lic,p_gap_em)))*(1-p_reform*p_reform_close) -> 0.27 | DZ15: =IF(AND(p_use_pefa=1,ISNUMBER(BD15)),"PEFA PI-11","Income-group default (IMF 2015)") -> Income-group default (IMF 2015) | EA15: =IF(E15="AE",p_ps_ae,IF(E15="China",p_ps_chn,p_ps_emdc)) -> 0.4 | EB15: =(1-EA15)+EA15/(1-DY15) -> 1.1479452 | EC15: =Results_Country!F15 -> 139.4253 | ED15: =IF(CH15="",0,CH15*EC15) -> 27367.062 | EE15: =IF(CJ15="",0,CJ15*EC15) -> 5047.0357 | EF15: =IF(CH15="",0,EC15) -> 139.4253
A16: KOR | B16: Korea, Rep. | C16: East Asia & Pacific | D16: High income | E16: AE | F16: 1875.388 | G16: 3254.39 | H16: 1.007 | I16: 1.862 | J16: 51.71759 | K16: 732.861 | L16: 825.612 | M16: 779.825 | N16: 541.27577 | O16: 87.389232 | P16: 4.3078858 | Q16: 0.49387268 | R16: 0.72808293 | S16: 0.77597217 | T16: 0.04810011 | U16: 0.63202843 | V16: 0.0095767123 | W16: 2.0500898 | X16: 0 | Y16: 18.354445 | Z16: 31.925628 | AA16: 12.260091 | AB16: 5.5475671 | AC16: 25.089899 | AD16: 0.792 | AE16: 0.762374 | AF16: 0.516312 | AG16: 0.698576 | AH16: 0.54430327 | AI16: 4.883 | AJ16: 9.9803 | AK16: 3.912 | AL16: 4.1615877 | AM16: 16.804 | AN16: 22.9779 | AO16: 14.959 | AP16: 18.33731 | AQ16: 26.805615 | AR16: 12.420219 | AS16: 3.2309895 | AT16: 5.3563007 | AU16: 0.31742371 | AV16: 0.1221 | AW16: 1.902455 | AX16: 0.339071 | AY16: 0.24565022 | AZ16: 0.048364 | BA16: 49.701 | BB16: 0.372 | BF16: 0 | BQ16: 2025 | BR16: 624.66 | BS16: 194.53 | BT16: 174.58 | BU16: 5.95 | BV16: =F16*(1+N(H16)/100)*(1+N(I16)/100)^5 -> 2077.3209 | BW16: =IF(N(G16)>0,G16,F16) -> 3254.39 | BX16: =F16/BW16 -> 0.57626406 | BY16: =IF(ISNUMBER(K16),1,0) -> 1 | BZ16: =IF(BY16=0,"",N(N16)+N(O16)+N(P16)) -> 632.97289 | CA16: =IF(BY16=0,"",(N(Y16)*34.2+N(Z16)*38.6)/1000) -> 1.8600513 | CB16: =IF(BY16=0,"",N(O16)*0.0036+N(R16)+N(V16)+(N(AA16)*25.3+N(AB16)*37)/1000) -> 1.5677012 | CC16: =IF(BY16=0,"",N(N16)*0.0036+N(Q16)+N(U16)+N(T16)+N(X16)+N(AC16)*38/1000) -> 4.0760102 | CD16: =IF(BY16=0,"",N(Q16)+N(R16)+N(S16)+N(T16)+N(U16)+N(V16)+N(W16)+N(X16)+(N(Y16)*34.2+N(Z16)*38.6+N(AA16)*25.3+N(AB16)*37+N(AC16)*38)/1000) -> 8.0666306 | CE16: =IF(BY16=0,"",MAX(0,N(L16)-N(K16))+MAX(0,N(M16)-N(L16))) -> 92.751 | CF16: =IF(BY16=0,"",N(Y16)*N(AD16)+N(Z16)*N(AE16)+N(AA16)*N(AF16)+N(AB16)*N(AG16)+N(AC16)*N(AH16)+N(U16)*N(AI16)+N(V16)*N(AJ16)+N(W16)*N(AK16)+N(X16)*N(AL16)+N(Q16)*N(AM16)+N(R16)*N(AN16)+N(S16)*N(AO16)+N(T16)*N(AP16)) -> 111.45831 | CG16: =IF(AND(BY16=1,N(K16)>0),K16,0) -> 732.861 | CH16: =IF(CG16>0,CF16*1000/CG16,"") -> 152.08656 | CI16: =IF(BY16=0,"",N(AQ16)+p_road*(N(AR16)+N(AS16)+N(AT16))) -> 26.805615 | CJ16: =IF(CG16>0,CI16*1000/CG16,"") -> 36.57667 | CK16: =IF(CH16="",1,MIN(p_idx_max,MAX(p_idx_min,CH16/p_fc_world))) -> 0.9445939 | CL16: =IF(CJ16="",1,MIN(p_idx_max,MAX(p_idx_min,CJ16/p_cb_world))) -> 0.69549568 | CM16: =p_b*(1-p_wb_idx+p_wb_idx*CK16) -> 0.12563099 | CN16: =p_c*(1-p_wc_idx+p_wc_idx*CL16) -> 0.089718942 | CO16: =IF(N(BR16)>0,(N(BS16)+N(BT16)+N(BU16))/BR16,"") -> 0.60042263 | CP16: =N(BS16)+N(BT16)+N(BU16) -> 375.06 | CQ16: =IF(CP16>0,N(BS16)/CP16,"") -> 0.51866368 | CR16: =IF(CP16>0,N(BT16)/CP16,"") -> 0.46547219 | CS16: =IF(CP16>0,N(BU16)/CP16,"") -> 0.015864128 | CT16: =1000*(p_sh_pv*p_cf_pv/p_capex_pv+(1-p_sh_pv)*p_cf_wind/p_capex_wind)*8760 -> 2301.2886 | CU16: =IF(AND(ISNUMBER(CO16),ISNUMBER(CQ16),BY16=1),1,0) -> 1 | CV16: =IF(CU16=0,"",CQ16*p_hr_coal*N(AK16)+CR16*p_hr_gas*N(AO16)+CS16*p_hr_oil*N(AH16)/p_gj_l_oil) -> 74.861483 | CW16: =IF(CU16=0,"",CQ16*p_hr_coal*p_ef_coal+CR16*p_hr_gas*p_ef_gas+CS16*p_hr_oil*p_ef_oil) -> 0.69939604 | CX16: =IF(CU16=0,"",CQ16*p_hr_coal*N(AW16)+CR16*p_hr_gas*N(AX16)+CS16*p_hr_oil*N(AY16)/p_gj_l_oil) -> 12.111126 | CY16: =IF(CU16=0,"",CO16*CW16) -> 0.41993321 | CZ16: =IF(CU16=0,"",CT16*CO16*CV16/1000/1000-p_om_re) -> 0.088439535 | DA16: =IF(CU16=0,"",CT16*CO16*CX16/1000/1000) -> 0.016734497 | DB16: =IF(CU16=0,"",CT16*CO16*CW16/1000) -> 0.9663875 | DC16: =IF(AND(CU16=1,ISNUMBER(AD16),ISNUMBER(AV16)),1,0) -> 1 | DD16: =IF(DC16=0,"",p_ev_km*p_ice_l/100*AD16-p_ev_km*p_ev_kwh*AV16+p_ev_km*p_ev_maint) -> 741.33 | DE16: =IF(DC16=0,"",DD16/p_ev_prem) -> 0.148266 | DF16: =IF(DC16=0,"",p_ev_km*p_ice_l/100*N(AZ16)/p_ev_prem) -> 0.0108819 | DG16: =IF(DC16=0,"",1000/p_ev_prem*(p_ev_km*p_ice_l/100*p_gj_l_gso*p_ef_gso-p_ev_km*p_ev_kwh/1000*CY16)) -> 0.30649957 | DH16: =IFERROR(IF(INDEX(Damodaran!$D:$D,MATCH(A16,Damodaran!$A:$A,0))="","",INDEX(Damodaran!$D:$D,MATCH(A16,Damodaran!$A:$A,0))),"") | DI16: =IFERROR(IF(INDEX(Damodaran!$E:$E,MATCH(A16,Damodaran!$A:$A,0))="","",INDEX(Damodaran!$E:$E,MATCH(A16,Damodaran!$A:$A,0))),"") | DJ16: =IFERROR(IF(INDEX(Damodaran!$G:$G,MATCH(A16,Damodaran!$A:$A,0))="","",INDEX(Damodaran!$G:$G,MATCH(A16,Damodaran!$A:$A,0))),"") | DK16: =IF(ISNUMBER(BG16),(1+BG16/100)*(1+p_infl)-1,"") | DL16: =IF(ISNUMBER(BH16),BH16/100,"") | DM16: =IF(COUNT(DK16,DL16)=0,"",AVERAGE(DK16,DL16)) | DN16: =IF(OR(DH16="",DI16=""),"",p_dv*(p_rf+DH16)*(1-IF(DJ16="",p_tax_def,DJ16))+(1-p_dv)*(p_rf+p_beta*p_erp+p_lambda*DI16)) | DO16: =IF(AND(ISNUMBER(DM16),ISNUMBER(DN16)),1,0) -> 0 | DP16: =IF(DO16=1,DM16,0) -> 0 | DQ16: =IF(DO16=1,DN16,0) -> 0 | DR16: =IF(DN16="","",DN16+p_shift) | DS16: =IF(E16="AE",p_r_ae,IF(E16="China",p_r_chn,p_r_emdc)) -> 0.055 | DT16: =IF(E16="AE",p_rh_ae,IF(E16="China",p_rh_chn,p_rh_emdc)) -> 0.07 | DU16: =IF(AND(p_use_obs=1,ISNUMBER(DM16)),DM16,IF(AND(p_use_dam=1,ISNUMBER(DR16)),DR16,DS16)) -> 0.055 | DV16: =IF(AND(p_use_obs=1,ISNUMBER(DM16)),"Observed (IRENA/Steffen)",IF(AND(p_use_dam=1,ISNUMBER(DR16)),"Damodaran (eq. 5)","Group default (IHLEG)")) -> Group default (IHLEG) | DW16: =IF(p_basis=1,(1+DU16)/(1+p_infl)-1,DU16) -> 0.055 | DX16: =DW16+(DT16-DS16) -> 0.07 | DY16: =IF(AND(p_use_pefa=1,ISNUMBER(BD16)),p_gap_lic-(BD16-1)/3*(p_gap_lic-p_gap_ae),IF(E16="AE",p_gap_ae,IF(D16="Low income",p_gap_lic,p_gap_em)))*(1-p_reform*p_reform_close) -> 0.13 | DZ16: =IF(AND(p_use_pefa=1,ISNUMBER(BD16)),"PEFA PI-11","Income-group default (IMF 2015)") -> Income-group default (IMF 2015) | EA16: =IF(E16="AE",p_ps_ae,IF(E16="China",p_ps_chn,p_ps_emdc)) -> 0.3 | EB16: =(1-EA16)+EA16/(1-DY16) -> 1.0448276 | EC16: =Results_Country!F16 -> 96.990799 | ED16: =IF(CH16="",0,CH16*EC16) -> 14750.996 | EE16: =IF(CJ16="",0,CJ16*EC16) -> 3547.6005 | EF16: =IF(CH16="",0,EC16) -> 96.990799
A17: MEX | B17: Mexico | C17: Latin America & Caribbean | D17: Upper middle income | E17: EMDC | F17: 1830.489 | G17: 3312.004 | H17: 0.562 | I17: 1.639 | J17: 130.86101 | K17: 582.567 | L17: 944.503 | M17: 959.826 | N17: 207.67939 | O17: 71.066146 | P17: 23.190464 | Q17: 1.3493924 | R17: 0.079389349 | S17: 0.7946363 | T17: 0.0022984319 | U17: 0.071417111 | V17: 0 | W17: 1.9457092 | X17: 0 | Y17: 35.995392 | Z17: 12.036161 | AA17: 18.86484 | AB17: 0.018126997 | AC17: 10.205514 | AD17: 0.87696 | AE17: 0.671485 | AF17: 0.584542 | AG17: 0.568 | AH17: 0.51946289 | AI17: 3.06 | AJ17: 11.38076 | AK17: 2.863 | AL17: 2.8699749 | AM17: 3.757 | AN17: 12.13244 | AO17: 4.758 | AP17: 4.4138048 | AQ17: 18.068075 | AR17: 5.5544317 | AS17: 0.75635076 | AT17: 0.98743398 | AU17: 0.25349593 | AV17: 0.129966 | AW17: 2.160589 | AX17: 0.147458 | AY17: 0.38133129 | AZ17: 0.204213 | BA17: 59.135 | BB17: 23.809 | BC17: 109.686 | BF17: 0 | BH17: 11 | BI17: 2022 | BJ17: 1 | BL17: 0.419 | BM17: 6.072 | BN17: 9.755 | BO17: 0.041 | BP17: 0.073 | BQ17: 2025 | BR17: 356.97 | BS17: 10.88 | BT17: 219.92 | BU17: 33.58 | BV17: =F17*(1+N(H17)/100)*(1+N(I17)/100)^5 -> 1996.6546 | BW17: =IF(N(G17)>0,G17,F17) -> 3312.004 | BX17: =F17/BW17 -> 0.55268321 | BY17: =IF(ISNUMBER(K17),1,0) -> 1 | BZ17: =IF(BY17=0,"",N(N17)+N(O17)+N(P17)) -> 301.936 | CA17: =IF(BY17=0,"",(N(Y17)*34.2+N(Z17)*38.6)/1000) -> 1.6956382 | CB17: =IF(BY17=0,"",N(O17)*0.0036+N(R17)+N(V17)+(N(AA17)*25.3+N(AB17)*37)/1000) -> 0.81317862 | CC17: =IF(BY17=0,"",N(N17)*0.0036+N(Q17)+N(U17)+N(T17)+N(X17)+N(AC17)*38/1000) -> 2.5585633 | CD17: =IF(BY17=0,"",N(Q17)+N(R17)+N(S17)+N(T17)+N(U17)+N(V17)+N(W17)+N(X17)+(N(Y17)*34.2+N(Z17)*38.6+N(AA17)*25.3+N(AB17)*37+N(AC17)*38)/1000) -> 6.8042417 | CE17: =IF(BY17=0,"",MAX(0,N(L17)-N(K17))+MAX(0,N(M17)-N(L17))) -> 377.259 | CF17: =IF(BY17=0,"",N(Y17)*N(AD17)+N(Z17)*N(AE17)+N(AA17)*N(AF17)+N(AB17)*N(AG17)+N(AC17)*N(AH17)+N(U17)*N(AI17)+N(V17)*N(AJ17)+N(W17)*N(AK17)+N(X17)*N(AL17)+N(Q17)*N(AM17)+N(R17)*N(AN17)+N(S17)*N(AO17)+N(T17)*N(AP17)) -> 71.600574 | CG17: =IF(AND(BY17=1,N(K17)>0),K17,0) -> 582.567 | CH17: =IF(CG17>0,CF17*1000/CG17,"") -> 122.9053 | CI17: =IF(BY17=0,"",N(AQ17)+p_road*(N(AR17)+N(AS17)+N(AT17))) -> 18.068075 | CJ17: =IF(CG17>0,CI17*1000/CG17,"") -> 31.014588 | CK17: =IF(CH17="",1,MIN(p_idx_max,MAX(p_idx_min,CH17/p_fc_world))) -> 0.76335215 | CL17: =IF(CJ17="",1,MIN(p_idx_max,MAX(p_idx_min,CJ17/p_cb_world))) -> 0.58973416 | CM17: =p_b*(1-p_wb_idx+p_wb_idx*CK17) -> 0.10152584 | CN17: =p_c*(1-p_wc_idx+p_wc_idx*CL17) -> 0.076075706 | CO17: =IF(N(BR17)>0,(N(BS17)+N(BT17)+N(BU17))/BR17,"") -> 0.74062246 | CP17: =N(BS17)+N(BT17)+N(BU17) -> 264.38 | CQ17: =IF(CP17>0,N(BS17)/CP17,"") -> 0.041152886 | CR17: =IF(CP17>0,N(BT17)/CP17,"") -> 0.83183297 | CS17: =IF(CP17>0,N(BU17)/CP17,"") -> 0.12701415 | CT17: =1000*(p_sh_pv*p_cf_pv/p_capex_pv+(1-p_sh_pv)*p_cf_wind/p_capex_wind)*8760 -> 2301.2886 | CU17: =IF(AND(ISNUMBER(CO17),ISNUMBER(CQ17),BY17=1),1,0) -> 1 | CV17: =IF(CU17=0,"",CQ17*p_hr_coal*N(AK17)+CR17*p_hr_gas*N(AO17)+CS17*p_hr_oil*N(AH17)/p_gj_l_oil) -> 48.809859 | CW17: =IF(CU17=0,"",CQ17*p_hr_coal*p_ef_coal+CR17*p_hr_gas*p_ef_gas+CS17*p_hr_oil*p_ef_oil) -> 0.49214875 | CX17: =IF(CU17=0,"",CQ17*p_hr_coal*N(AW17)+CR17*p_hr_gas*N(AX17)+CS17*p_hr_oil*N(AY17)/p_gj_l_oil) -> 14.984277 | CY17: =IF(CU17=0,"",CO17*CW17) -> 0.36449642 | CZ17: =IF(CU17=0,"",CT17*CO17*CV17/1000/1000-p_om_re) -> 0.06819084 | DA17: =IF(CU17=0,"",CT17*CO17*CX17/1000/1000) -> 0.025538992 | DB17: =IF(CU17=0,"",CT17*CO17*CW17/1000) -> 0.83881144 | DC17: =IF(AND(CU17=1,ISNUMBER(AD17),ISNUMBER(AV17)),1,0) -> 1 | DD17: =IF(DC17=0,"",p_ev_km*p_ice_l/100*AD17-p_ev_km*p_ev_kwh*AV17+p_ev_km*p_ev_maint) -> 815.6718 | DE17: =IF(DC17=0,"",DD17/p_ev_prem) -> 0.16313436 | DF17: =IF(DC17=0,"",p_ev_km*p_ice_l/100*N(AZ17)/p_ev_prem) -> 0.045947925 | DG17: =IF(DC17=0,"",1000/p_ev_prem*(p_ev_km*p_ice_l/100*p_gj_l_gso*p_ef_gso-p_ev_km*p_ev_kwh/1000*CY17)) -> 0.33643543 | DH17: =IFERROR(IF(INDEX(Damodaran!$D:$D,MATCH(A17,Damodaran!$A:$A,0))="","",INDEX(Damodaran!$D:$D,MATCH(A17,Damodaran!$A:$A,0))),"") | DI17: =IFERROR(IF(INDEX(Damodaran!$E:$E,MATCH(A17,Damodaran!$A:$A,0))="","",INDEX(Damodaran!$E:$E,MATCH(A17,Damodaran!$A:$A,0))),"") | DJ17: =IFERROR(IF(INDEX(Damodaran!$G:$G,MATCH(A17,Damodaran!$A:$A,0))="","",INDEX(Damodaran!$G:$G,MATCH(A17,Damodaran!$A:$A,0))),"") | DK17: =IF(ISNUMBER(BG17),(1+BG17/100)*(1+p_infl)-1,"") | DL17: =IF(ISNUMBER(BH17),BH17/100,"") -> 0.11 | DM17: =IF(COUNT(DK17,DL17)=0,"",AVERAGE(DK17,DL17)) -> 0.11 | DN17: =IF(OR(DH17="",DI17=""),"",p_dv*(p_rf+DH17)*(1-IF(DJ17="",p_tax_def,DJ17))+(1-p_dv)*(p_rf+p_beta*p_erp+p_lambda*DI17)) | DO17: =IF(AND(ISNUMBER(DM17),ISNUMBER(DN17)),1,0) -> 0 | DP17: =IF(DO17=1,DM17,0) -> 0 | DQ17: =IF(DO17=1,DN17,0) -> 0 | DR17: =IF(DN17="","",DN17+p_shift) | DS17: =IF(E17="AE",p_r_ae,IF(E17="China",p_r_chn,p_r_emdc)) -> 0.105 | DT17: =IF(E17="AE",p_rh_ae,IF(E17="China",p_rh_chn,p_rh_emdc)) -> 0.15 | DU17: =IF(AND(p_use_obs=1,ISNUMBER(DM17)),DM17,IF(AND(p_use_dam=1,ISNUMBER(DR17)),DR17,DS17)) -> 0.11 | DV17: =IF(AND(p_use_obs=1,ISNUMBER(DM17)),"Observed (IRENA/Steffen)",IF(AND(p_use_dam=1,ISNUMBER(DR17)),"Damodaran (eq. 5)","Group default (IHLEG)")) -> Observed (IRENA/Steffen) | DW17: =IF(p_basis=1,(1+DU17)/(1+p_infl)-1,DU17) -> 0.11 | DX17: =DW17+(DT17-DS17) -> 0.155 | DY17: =IF(AND(p_use_pefa=1,ISNUMBER(BD17)),p_gap_lic-(BD17-1)/3*(p_gap_lic-p_gap_ae),IF(E17="AE",p_gap_ae,IF(D17="Low income",p_gap_lic,p_gap_em)))*(1-p_reform*p_reform_close) -> 0.27 | DZ17: =IF(AND(p_use_pefa=1,ISNUMBER(BD17)),"PEFA PI-11","Income-group default (IMF 2015)") -> Income-group default (IMF 2015) | EA17: =IF(E17="AE",p_ps_ae,IF(E17="China",p_ps_chn,p_ps_emdc)) -> 0.4 | EB17: =(1-EA17)+EA17/(1-DY17) -> 1.1479452 | EC17: =Results_Country!F17 -> 93.834102 | ED17: =IF(CH17="",0,CH17*EC17) -> 11532.709 | EE17: =IF(CJ17="",0,CJ17*EC17) -> 2910.226 | EF17: =IF(CH17="",0,EC17) -> 93.834102
A18: AUS | B18: Australia | C18: East Asia & Pacific | D18: High income | E18: AE | F18: 1799.418 | G18: 1907.482 | H18: 1.971 | I18: 2.009 | J18: 26.713205 | K18: 386.813 | L18: 517.295 | M18: 464.132 | N18: 182.01573 | O18: 82.218972 | P18: 7.8267599 | Q18: 0.72923223 | R18: 0.26440532 | S18: 1.2942956 | T18: 0.0032810543 | U18: 0.13310116 | V18: 0.005339981 | W18: 0.19187821 | X18: 0 | Y18: 18.473401 | Z18: 36.998787 | AA18: 1.6296991 | AB18: 2.1811201 | AC18: 15.393412 | AD18: 0.789271 | AE18: 0.746471 | AF18: 0.533023 | AG18: 0.652 | AH18: 0.5433453 | AI18: 3.54 | AJ18: 6.0962 | AK18: 2.199 | AL18: 2.8023544 | AM18: 9.928 | AN18: 19.657 | AO18: 8.604 | AP18: 10.30334 | AQ18: 5.46739 | AR18: 8.3596844 | AS18: 1.0655333 | AT18: 1.9060672 | AU18: 0.39611376 | AV18: 0.190794 | AW18: 1.043582 | AX18: 0.125549 | AY18: 0.11384164 | AZ18: 0.02155 | BA18: 50.611 | BB18: 2.416 | BF18: 0 | BH18: 5.02 | BI18: 2020 | BJ18: 1 | BQ18: 2025 | BR18: 286.68 | BS18: 122.31 | BT18: 47.05 | BU18: 6.36 | BV18: =F18*(1+N(H18)/100)*(1+N(I18)/100)^5 -> 2026.7547 | BW18: =IF(N(G18)>0,G18,F18) -> 1907.482 | BX18: =F18/BW18 -> 0.9433473 | BY18: =IF(ISNUMBER(K18),1,0) -> 1 | BZ18: =IF(BY18=0,"",N(N18)+N(O18)+N(P18)) -> 272.06147 | CA18: =IF(BY18=0,"",(N(Y18)*34.2+N(Z18)*38.6)/1000) -> 2.0599435 | CB18: =IF(BY18=0,"",N(O18)*0.0036+N(R18)+N(V18)+(N(AA18)*25.3+N(AB18)*37)/1000) -> 0.68766643 | CC18: =IF(BY18=0,"",N(N18)*0.0036+N(Q18)+N(U18)+N(T18)+N(X18)+N(AC18)*38/1000) -> 2.1058207 | CD18: =IF(BY18=0,"",N(Q18)+N(R18)+N(S18)+N(T18)+N(U18)+N(V18)+N(W18)+N(X18)+(N(Y18)*34.2+N(Z18)*38.6+N(AA18)*25.3+N(AB18)*37+N(AC18)*38)/1000) -> 5.3883595 | CE18: =IF(BY18=0,"",MAX(0,N(L18)-N(K18))+MAX(0,N(M18)-N(L18))) -> 130.482 | CF18: =IF(BY18=0,"",N(Y18)*N(AD18)+N(Z18)*N(AE18)+N(AA18)*N(AF18)+N(AB18)*N(AG18)+N(AC18)*N(AH18)+N(U18)*N(AI18)+N(V18)*N(AJ18)+N(W18)*N(AK18)+N(X18)*N(AL18)+N(Q18)*N(AM18)+N(R18)*N(AN18)+N(S18)*N(AO18)+N(T18)*N(AP18)) -> 77.386566 | CG18: =IF(AND(BY18=1,N(K18)>0),K18,0) -> 386.813 | CH18: =IF(CG18>0,CF18*1000/CG18,"") -> 200.06196 | CI18: =IF(BY18=0,"",N(AQ18)+p_road*(N(AR18)+N(AS18)+N(AT18))) -> 5.46739 | CJ18: =IF(CG18>0,CI18*1000/CG18,"") -> 14.134453 | CK18: =IF(CH18="",1,MIN(p_idx_max,MAX(p_idx_min,CH18/p_fc_world))) -> 1.2425642 | CL18: =IF(CJ18="",1,MIN(p_idx_max,MAX(p_idx_min,CJ18/p_cb_world))) -> 0.26876286 | CM18: =p_b*(1-p_wb_idx+p_wb_idx*CK18) -> 0.16526104 | CN18: =p_c*(1-p_wc_idx+p_wc_idx*CL18) -> 0.034670409 | CO18: =IF(N(BR18)>0,(N(BS18)+N(BT18)+N(BU18))/BR18,"") -> 0.61294823 | CP18: =N(BS18)+N(BT18)+N(BU18) -> 175.72 | CQ18: =IF(CP18>0,N(BS18)/CP18,"") -> 0.69605053 | CR18: =IF(CP18>0,N(BT18)/CP18,"") -> 0.26775552 | CS18: =IF(CP18>0,N(BU18)/CP18,"") -> 0.036193945 | CT18: =1000*(p_sh_pv*p_cf_pv/p_capex_pv+(1-p_sh_pv)*p_cf_wind/p_capex_wind)*8760 -> 2301.2886 | CU18: =IF(AND(ISNUMBER(CO18),ISNUMBER(CQ18),BY18=1),1,0) -> 1 | CV18: =IF(CU18=0,"",CQ18*p_hr_coal*N(AK18)+CR18*p_hr_gas*N(AO18)+CS18*p_hr_oil*N(AH18)/p_gj_l_oil) -> 37.933923 | CW18: =IF(CU18=0,"",CQ18*p_hr_coal*p_ef_coal+CR18*p_hr_gas*p_ef_gas+CS18*p_hr_oil*p_ef_oil) -> 0.80053676 | CX18: =IF(CU18=0,"",CQ18*p_hr_coal*N(AW18)+CR18*p_hr_gas*N(AX18)+CS18*p_hr_oil*N(AY18)/p_gj_l_oil) -> 8.6368096 | CY18: =IF(CU18=0,"",CO18*CW18) -> 0.49068759 | CZ18: =IF(CU18=0,"",CT18*CO18*CV18/1000/1000-p_om_re) -> 0.038508483 | DA18: =IF(CU18=0,"",CT18*CO18*CX18/1000/1000) -> 0.012182831 | DB18: =IF(CU18=0,"",CT18*CO18*CW18/1000) -> 1.1292138 | DC18: =IF(AND(CU18=1,ISNUMBER(AD18),ISNUMBER(AV18)),1,0) -> 1 | DD18: =IF(DC18=0,"",p_ev_km*p_ice_l/100*AD18-p_ev_km*p_ev_kwh*AV18+p_ev_km*p_ev_maint) -> 552.78607 | DE18: =IF(DC18=0,"",DD18/p_ev_prem) -> 0.11055722 | DF18: =IF(DC18=0,"",p_ev_km*p_ice_l/100*N(AZ18)/p_ev_prem) -> 0.00484875 | DG18: =IF(DC18=0,"",1000/p_ev_prem*(p_ev_km*p_ice_l/100*p_gj_l_gso*p_ef_gso-p_ev_km*p_ev_kwh/1000*CY18)) -> 0.2682922 | DH18: =IFERROR(IF(INDEX(Damodaran!$D:$D,MATCH(A18,Damodaran!$A:$A,0))="","",INDEX(Damodaran!$D:$D,MATCH(A18,Damodaran!$A:$A,0))),"") | DI18: =IFERROR(IF(INDEX(Damodaran!$E:$E,MATCH(A18,Damodaran!$A:$A,0))="","",INDEX(Damodaran!$E:$E,MATCH(A18,Damodaran!$A:$A,0))),"") | DJ18: =IFERROR(IF(INDEX(Damodaran!$G:$G,MATCH(A18,Damodaran!$A:$A,0))="","",INDEX(Damodaran!$G:$G,MATCH(A18,Damodaran!$A:$A,0))),"") | DK18: =IF(ISNUMBER(BG18),(1+BG18/100)*(1+p_infl)-1,"") | DL18: =IF(ISNUMBER(BH18),BH18/100,"") -> 0.0502 | DM18: =IF(COUNT(DK18,DL18)=0,"",AVERAGE(DK18,DL18)) -> 0.0502 | DN18: =IF(OR(DH18="",DI18=""),"",p_dv*(p_rf+DH18)*(1-IF(DJ18="",p_tax_def,DJ18))+(1-p_dv)*(p_rf+p_beta*p_erp+p_lambda*DI18)) | DO18: =IF(AND(ISNUMBER(DM18),ISNUMBER(DN18)),1,0) -> 0 | DP18: =IF(DO18=1,DM18,0) -> 0 | DQ18: =IF(DO18=1,DN18,0) -> 0 | DR18: =IF(DN18="","",DN18+p_shift) | DS18: =IF(E18="AE",p_r_ae,IF(E18="China",p_r_chn,p_r_emdc)) -> 0.055 | DT18: =IF(E18="AE",p_rh_ae,IF(E18="China",p_rh_chn,p_rh_emdc)) -> 0.07 | DU18: =IF(AND(p_use_obs=1,ISNUMBER(DM18)),DM18,IF(AND(p_use_dam=1,ISNUMBER(DR18)),DR18,DS18)) -> 0.0502 | DV18: =IF(AND(p_use_obs=1,ISNUMBER(DM18)),"Observed (IRENA/Steffen)",IF(AND(p_use_dam=1,ISNUMBER(DR18)),"Damodaran (eq. 5)","Group default (IHLEG)")) -> Observed (IRENA/Steffen) | DW18: =IF(p_basis=1,(1+DU18)/(1+p_infl)-1,DU18) -> 0.0502 | DX18: =DW18+(DT18-DS18) -> 0.0652 | DY18: =IF(AND(p_use_pefa=1,ISNUMBER(BD18)),p_gap_lic-(BD18-1)/3*(p_gap_lic-p_gap_ae),IF(E18="AE",p_gap_ae,IF(D18="Low income",p_gap_lic,p_gap_em)))*(1-p_reform*p_reform_close) -> 0.13 | DZ18: =IF(AND(p_use_pefa=1,ISNUMBER(BD18)),"PEFA PI-11","Income-group default (IMF 2015)") -> Income-group default (IMF 2015) | EA18: =IF(E18="AE",p_ps_ae,IF(E18="China",p_ps_chn,p_ps_emdc)) -> 0.3 | EB18: =(1-EA18)+EA18/(1-DY18) -> 1.0448276 | EC18: =Results_Country!F18 -> 68.49999 | ED18: =IF(CH18="",0,CH18*EC18) -> 13704.242 | EE18: =IF(CJ18="",0,CJ18*EC18) -> 968.20986 | EF18: =IF(CH18="",0,EC18) -> 68.49999
A19: ESP | B19: Spain | C19: Europe & Central Asia | D19: High income | E19: AE | F19: 1725.152 | G19: 2683.325 | H19: 2.766 | I19: 2.09 | J19: 47.910526 | K19: 279.606 | L19: 339.165 | M19: 294.259 | N19: 184.05088 | O19: 90.075937 | P19: 4.6629309 | Q19: 0.63548615 | R19: 0.40125116 | S19: 0.24684976 | T19: 0.013093321 | U19: 0.042329528 | V19: 0.0033713913 | W19: 0.25424711 | X19: 0.0040504327 | Y19: 7.4427899 | Z19: 35.256853 | AA19: 2.3261606 | AB19: 2.1781565 | AC19: 9.1332137 | AD19: 0.873591 | AE19: 0.846329 | AF19: 0.588428 | AG19: 0.617007 | AH19: 0.51950827 | AI19: 10.26 | AJ19: 16.59273 | AK19: 7.095 | AL19: 7.6484076 | AM19: 13.578 | AN19: 24.7929 | AO19: 13.578 | AP19: 17.083794 | AQ19: 2.5087601 | AR19: 0.74909734 | AS19: 0.20787657 | AT19: 0.80661421 | AU19: 0.63193848 | AV19: 0.210842 | AW19: 1.14944 | AX19: 1.123725 | AY19: 0.17636891 | AZ19: 0.022455 | BA19: 101.648 | BB19: 4.288 | BF19: 0 | BH19: 5.125 | BI19: 2020 | BJ19: 1 | BQ19: 2025 | BR19: 287.92 | BS19: 0.92 | BT19: 62.06 | BU19: 10.03 | BV19: =F19*(1+N(H19)/100)*(1+N(I19)/100)^5 -> 1966.0422 | BW19: =IF(N(G19)>0,G19,F19) -> 2683.325 | BX19: =F19/BW19 -> 0.64291579 | BY19: =IF(ISNUMBER(K19),1,0) -> 1 | BZ19: =IF(BY19=0,"",N(N19)+N(O19)+N(P19)) -> 278.78975 | CA19: =IF(BY19=0,"",(N(Y19)*34.2+N(Z19)*38.6)/1000) -> 1.6154579 | CB19: =IF(BY19=0,"",N(O19)*0.0036+N(R19)+N(V19)+(N(AA19)*25.3+N(AB19)*37)/1000) -> 0.86833958 | CC19: =IF(BY19=0,"",N(N19)*0.0036+N(Q19)+N(U19)+N(T19)+N(X19)+N(AC19)*38/1000) -> 1.7046047 | CD19: =IF(BY19=0,"",N(Q19)+N(R19)+N(S19)+N(T19)+N(U19)+N(V19)+N(W19)+N(X19)+(N(Y19)*34.2+N(Z19)*38.6+N(AA19)*25.3+N(AB19)*37+N(AC19)*38)/1000) -> 3.7026426 | CE19: =IF(BY19=0,"",MAX(0,N(L19)-N(K19))+MAX(0,N(M19)-N(L19))) -> 59.559 | CF19: =IF(BY19=0,"",N(Y19)*N(AD19)+N(Z19)*N(AE19)+N(AA19)*N(AF19)+N(AB19)*N(AG19)+N(AC19)*N(AH19)+N(U19)*N(AI19)+N(V19)*N(AJ19)+N(W19)*N(AK19)+N(X19)*N(AL19)+N(Q19)*N(AM19)+N(R19)*N(AN19)+N(S19)*N(AO19)+N(T19)*N(AP19)) -> 68.275672 | CG19: =IF(AND(BY19=1,N(K19)>0),K19,0) -> 279.606 | CH19: =IF(CG19>0,CF19*1000/CG19,"") -> 244.18529 | CI19: =IF(BY19=0,"",N(AQ19)+p_road*(N(AR19)+N(AS19)+N(AT19))) -> 2.5087601 | CJ19: =IF(CG19>0,CI19*1000/CG19,"") -> 8.9724832 | CK19: =IF(CH19="",1,MIN(p_idx_max,MAX(p_idx_min,CH19/p_fc_world))) -> 1.5166096 | CL19: =IF(CJ19="",1,MIN(p_idx_max,MAX(p_idx_min,CJ19/p_cb_world))) -> 0.25 | CM19: =p_b*(1-p_wb_idx+p_wb_idx*CK19) -> 0.20170908 | CN19: =p_c*(1-p_wc_idx+p_wc_idx*CL19) -> 0.03225 | CO19: =IF(N(BR19)>0,(N(BS19)+N(BT19)+N(BU19))/BR19,"") -> 0.25357738 | CP19: =N(BS19)+N(BT19)+N(BU19) -> 73.01 | CQ19: =IF(CP19>0,N(BS19)/CP19,"") -> 0.012601014 | CR19: =IF(CP19>0,N(BT19)/CP19,"") -> 0.85002055 | CS19: =IF(CP19>0,N(BU19)/CP19,"") -> 0.13737844 | CT19: =1000*(p_sh_pv*p_cf_pv/p_capex_pv+(1-p_sh_pv)*p_cf_wind/p_capex_wind)*8760 -> 2301.2886 | CU19: =IF(AND(ISNUMBER(CO19),ISNUMBER(CQ19),BY19=1),1,0) -> 1 | CV19: =IF(CU19=0,"",CQ19*p_hr_coal*N(AK19)+CR19*p_hr_gas*N(AO19)+CS19*p_hr_oil*N(AH19)/p_gj_l_oil) -> 106.8698 | CW19: =IF(CU19=0,"",CQ19*p_hr_coal*p_ef_coal+CR19*p_hr_gas*p_ef_gas+CS19*p_hr_oil*p_ef_oil) -> 0.48121416 | CX19: =IF(CU19=0,"",CQ19*p_hr_coal*N(AW19)+CR19*p_hr_gas*N(AX19)+CS19*p_hr_oil*N(AY19)/p_gj_l_oil) -> 13.899629 | CY19: =IF(CU19=0,"",CO19*CW19) -> 0.12202503 | CZ19: =IF(CU19=0,"",CT19*CO19*CV19/1000/1000-p_om_re) -> 0.047364375 | DA19: =IF(CU19=0,"",CT19*CO19*CX19/1000/1000) -> 0.0081111943 | DB19: =IF(CU19=0,"",CT19*CO19*CW19/1000) -> 0.2808148 | DC19: =IF(AND(CU19=1,ISNUMBER(AD19),ISNUMBER(AV19)),1,0) -> 1 | DD19: =IF(DC19=0,"",p_ev_km*p_ice_l/100*AD19-p_ev_km*p_ev_kwh*AV19+p_ev_km*p_ev_maint) -> 593.51648 | DE19: =IF(DC19=0,"",DD19/p_ev_prem) -> 0.1187033 | DF19: =IF(DC19=0,"",p_ev_km*p_ice_l/100*N(AZ19)/p_ev_prem) -> 0.005052375 | DG19: =IF(DC19=0,"",1000/p_ev_prem*(p_ev_km*p_ice_l/100*p_gj_l_gso*p_ef_gso-p_ev_km*p_ev_kwh/1000*CY19)) -> 0.46736998 | DH19: =IFERROR(IF(INDEX(Damodaran!$D:$D,MATCH(A19,Damodaran!$A:$A,0))="","",INDEX(Damodaran!$D:$D,MATCH(A19,Damodaran!$A:$A,0))),"") | DI19: =IFERROR(IF(INDEX(Damodaran!$E:$E,MATCH(A19,Damodaran!$A:$A,0))="","",INDEX(Damodaran!$E:$E,MATCH(A19,Damodaran!$A:$A,0))),"") | DJ19: =IFERROR(IF(INDEX(Damodaran!$G:$G,MATCH(A19,Damodaran!$A:$A,0))="","",INDEX(Damodaran!$G:$G,MATCH(A19,Damodaran!$A:$A,0))),"") | DK19: =IF(ISNUMBER(BG19),(1+BG19/100)*(1+p_infl)-1,"") | DL19: =IF(ISNUMBER(BH19),BH19/100,"") -> 0.05125 | DM19: =IF(COUNT(DK19,DL19)=0,"",AVERAGE(DK19,DL19)) -> 0.05125 | DN19: =IF(OR(DH19="",DI19=""),"",p_dv*(p_rf+DH19)*(1-IF(DJ19="",p_tax_def,DJ19))+(1-p_dv)*(p_rf+p_beta*p_erp+p_lambda*DI19)) | DO19: =IF(AND(ISNUMBER(DM19),ISNUMBER(DN19)),1,0) -> 0 | DP19: =IF(DO19=1,DM19,0) -> 0 | DQ19: =IF(DO19=1,DN19,0) -> 0 | DR19: =IF(DN19="","",DN19+p_shift) | DS19: =IF(E19="AE",p_r_ae,IF(E19="China",p_r_chn,p_r_emdc)) -> 0.055 | DT19: =IF(E19="AE",p_rh_ae,IF(E19="China",p_rh_chn,p_rh_emdc)) -> 0.07 | DU19: =IF(AND(p_use_obs=1,ISNUMBER(DM19)),DM19,IF(AND(p_use_dam=1,ISNUMBER(DR19)),DR19,DS19)) -> 0.05125 | DV19: =IF(AND(p_use_obs=1,ISNUMBER(DM19)),"Observed (IRENA/Steffen)",IF(AND(p_use_dam=1,ISNUMBER(DR19)),"Damodaran (eq. 5)","Group default (IHLEG)")) -> Observed (IRENA/Steffen) | DW19: =IF(p_basis=1,(1+DU19)/(1+p_infl)-1,DU19) -> 0.05125 | DX19: =DW19+(DT19-DS19) -> 0.06625 | DY19: =IF(AND(p_use_pefa=1,ISNUMBER(BD19)),p_gap_lic-(BD19-1)/3*(p_gap_lic-p_gap_ae),IF(E19="AE",p_gap_ae,IF(D19="Low income",p_gap_lic,p_gap_em)))*(1-p_reform*p_reform_close) -> 0.13 | DZ19: =IF(AND(p_use_pefa=1,ISNUMBER(BD19)),"PEFA PI-11","Income-group default (IMF 2015)") -> Income-group default (IMF 2015) | EA19: =IF(E19="AE",p_ps_ae,IF(E19="China",p_ps_chn,p_ps_emdc)) -> 0.3 | EB19: =(1-EA19)+EA19/(1-DY19) -> 1.0448276 | EC19: =Results_Country!F19 -> 64.582759 | ED19: =IF(CH19="",0,CH19*EC19) -> 15770.16 | EE19: =IF(CJ19="",0,CJ19*EC19) -> 579.46772 | EF19: =IF(CH19="",0,EC19) -> 64.582759
A20: IDN | B20: Indonesia | C20: East Asia & Pacific | D20: Upper middle income | E20: EMDC | F20: 1396.302 | G20: 4669.746 | H20: 5.108 | I20: 4.95 | J20: 283.48793 | K20: 700.991 | L20: 1240.011 | M20: 1416.823 | N20: 228.98287 | O20: 158.29003 | P20: 0.46182845 | Q20: 0.92127111 | R20: 0.0071044102 | S20: 1.2650888 | T20: 0.00096338604 | U20: 1.0688894 | V20: 0 | W20: 1.3054847 | X20: 0 | Y20: 40.743582 | Z20: 26.91587 | AA20: 17.726459 | AB20: 2.498567 | AC20: 25.087505 | AD20: 0.7992 | AE20: 0.753712 | AF20: 0.563848 | AG20: 0.713422 | AH20: 0.5433453 | AI20: 2.98 | AJ20: 3.29781 | AK20: 2.672 | AL20: 2.8106546 | AM20: 5.433 | AN20: 10.43844 | AO20: 4.771 | AP20: 5.0674011 | AQ20: 43.892216 | AR20: 2.6379727 | AS20: 19.389408 | AT20: 5.1722853 | AU20: 0.28032819 | AV20: 0.08325 | AW20: 2.926068 | AX20: 0.555308 | AY20: 0.17394422 | AZ20: 0.065259 | BA20: 40.165 | BB20: 15.127 | BD20: 1.5 | BE20: 2 | BF20: 1 | BG20: 6 | BH20: 8.25 | BI20: 2022 | BJ20: 3 | BK20: 1 | BL20: 2.413 | BM20: 5.644 | BN20: 21.175 | BO20: 0.186 | BP20: 0.132 | BQ20: 2024 | BR20: 371.54 | BS20: 228.43 | BT20: 68.78 | BU20: 7.12 | BV20: =F20*(1+N(H20)/100)*(1+N(I20)/100)^5 -> 1868.6473 | BW20: =IF(N(G20)>0,G20,F20) -> 4669.746 | BX20: =F20/BW20 -> 0.29901027 | BY20: =IF(ISNUMBER(K20),1,0) -> 1 | BZ20: =IF(BY20=0,"",N(N20)+N(O20)+N(P20)) -> 387.73473 | CA20: =IF(BY20=0,"",(N(Y20)*34.2+N(Z20)*38.6)/1000) -> 2.4323831 | CB20: =IF(BY20=0,"",N(O20)*0.0036+N(R20)+N(V20)+(N(AA20)*25.3+N(AB20)*37)/1000) -> 1.1178749 | CC20: =IF(BY20=0,"",N(N20)*0.0036+N(Q20)+N(U20)+N(T20)+N(X20)+N(AC20)*38/1000) -> 3.7687874 | CD20: =IF(BY20=0,"",N(Q20)+N(R20)+N(S20)+N(T20)+N(U20)+N(V20)+N(W20)+N(X20)+(N(Y20)*34.2+N(Z20)*38.6+N(AA20)*25.3+N(AB20)*37+N(AC20)*38)/1000) -> 8.4954366 | CE20: =IF(BY20=0,"",MAX(0,N(L20)-N(K20))+MAX(0,N(M20)-N(L20))) -> 715.832 | CF20: =IF(BY20=0,"",N(Y20)*N(AD20)+N(Z20)*N(AE20)+N(AA20)*N(AF20)+N(AB20)*N(AG20)+N(AC20)*N(AH20)+N(U20)*N(AI20)+N(V20)*N(AJ20)+N(W20)*N(AK20)+N(X20)*N(AL20)+N(Q20)*N(AM20)+N(R20)*N(AN20)+N(S20)*N(AO20)+N(T20)*N(AP20)) -> 96.051416 | CG20: =IF(AND(BY20=1,N(K20)>0),K20,0) -> 700.991 | CH20: =IF(CG20>0,CF20*1000/CG20,"") -> 137.02232 | CI20: =IF(BY20=0,"",N(AQ20)+p_road*(N(AR20)+N(AS20)+N(AT20))) -> 43.892216 | CJ20: =IF(CG20>0,CI20*1000/CG20,"") -> 62.614521 | CK20: =IF(CH20="",1,MIN(p_idx_max,MAX(p_idx_min,CH20/p_fc_world))) -> 0.85103151 | CL20: =IF(CJ20="",1,MIN(p_idx_max,MAX(p_idx_min,CJ20/p_cb_world))) -> 1.1905985 | CM20: =p_b*(1-p_wb_idx+p_wb_idx*CK20) -> 0.11318719 | CN20: =p_c*(1-p_wc_idx+p_wc_idx*CL20) -> 0.15358721 | CO20: =IF(N(BR20)>0,(N(BS20)+N(BT20)+N(BU20))/BR20,"") -> 0.81910427 | CP20: =N(BS20)+N(BT20)+N(BU20) -> 304.33 | CQ20: =IF(CP20>0,N(BS20)/CP20,"") -> 0.75059968 | CR20: =IF(CP20>0,N(BT20)/CP20,"") -> 0.22600467 | CS20: =IF(CP20>0,N(BU20)/CP20,"") -> 0.023395656 | CT20: =1000*(p_sh_pv*p_cf_pv/p_capex_pv+(1-p_sh_pv)*p_cf_wind/p_capex_wind)*8760 -> 2301.2886 | CU20: =IF(AND(ISNUMBER(CO20),ISNUMBER(CQ20),BY20=1),1,0) -> 1 | CV20: =IF(CU20=0,"",CQ20*p_hr_coal*N(AK20)+CR20*p_hr_gas*N(AO20)+CS20*p_hr_oil*N(AH20)/p_gj_l_oil) -> 31.600941 | CW20: =IF(CU20=0,"",CQ20*p_hr_coal*p_ef_coal+CR20*p_hr_gas*p_ef_gas+CS20*p_hr_oil*p_ef_oil) -> 0.82417241 | CX20: =IF(CU20=0,"",CQ20*p_hr_coal*N(AW20)+CR20*p_hr_gas*N(AX20)+CS20*p_hr_oil*N(AY20)/p_gj_l_oil) -> 24.011322 | CY20: =IF(CU20=0,"",CO20*CW20) -> 0.67508314 | CZ20: =IF(CU20=0,"",CT20*CO20*CV20/1000/1000-p_om_re) -> 0.044567625 | DA20: =IF(CU20=0,"",CT20*CO20*CX20/1000/1000) -> 0.04526123 | DB20: =IF(CU20=0,"",CT20*CO20*CW20/1000) -> 1.5535611 | DC20: =IF(AND(CU20=1,ISNUMBER(AD20),ISNUMBER(AV20)),1,0) -> 1 | DD20: =IF(DC20=0,"",p_ev_km*p_ice_l/100*AD20-p_ev_km*p_ev_kwh*AV20+p_ev_km*p_ev_maint) -> 854.325 | DE20: =IF(DC20=0,"",DD20/p_ev_prem) -> 0.170865 | DF20: =IF(DC20=0,"",p_ev_km*p_ice_l/100*N(AZ20)/p_ev_prem) -> 0.014683275 | DG20: =IF(DC20=0,"",1000/p_ev_prem*(p_ev_km*p_ice_l/100*p_gj_l_gso*p_ef_gso-p_ev_km*p_ev_kwh/1000*CY20)) -> 0.16871861 | DH20: =IFERROR(IF(INDEX(Damodaran!$D:$D,MATCH(A20,Damodaran!$A:$A,0))="","",INDEX(Damodaran!$D:$D,MATCH(A20,Damodaran!$A:$A,0))),"") | DI20: =IFERROR(IF(INDEX(Damodaran!$E:$E,MATCH(A20,Damodaran!$A:$A,0))="","",INDEX(Damodaran!$E:$E,MATCH(A20,Damodaran!$A:$A,0))),"") | DJ20: =IFERROR(IF(INDEX(Damodaran!$G:$G,MATCH(A20,Damodaran!$A:$A,0))="","",INDEX(Damodaran!$G:$G,MATCH(A20,Damodaran!$A:$A,0))),"") | DK20: =IF(ISNUMBER(BG20),(1+BG20/100)*(1+p_infl)-1,"") -> 0.0812 | DL20: =IF(ISNUMBER(BH20),BH20/100,"") -> 0.0825 | DM20: =IF(COUNT(DK20,DL20)=0,"",AVERAGE(DK20,DL20)) -> 0.08185 | DN20: =IF(OR(DH20="",DI20=""),"",p_dv*(p_rf+DH20)*(1-IF(DJ20="",p_tax_def,DJ20))+(1-p_dv)*(p_rf+p_beta*p_erp+p_lambda*DI20)) | DO20: =IF(AND(ISNUMBER(DM20),ISNUMBER(DN20)),1,0) -> 0 | DP20: =IF(DO20=1,DM20,0) -> 0 | DQ20: =IF(DO20=1,DN20,0) -> 0 | DR20: =IF(DN20="","",DN20+p_shift) | DS20: =IF(E20="AE",p_r_ae,IF(E20="China",p_r_chn,p_r_emdc)) -> 0.105 | DT20: =IF(E20="AE",p_rh_ae,IF(E20="China",p_rh_chn,p_rh_emdc)) -> 0.15 | DU20: =IF(AND(p_use_obs=1,ISNUMBER(DM20)),DM20,IF(AND(p_use_dam=1,ISNUMBER(DR20)),DR20,DS20)) -> 0.08185 | DV20: =IF(AND(p_use_obs=1,ISNUMBER(DM20)),"Observed (IRENA/Steffen)",IF(AND(p_use_dam=1,ISNUMBER(DR20)),"Damodaran (eq. 5)","Group default (IHLEG)")) -> Observed (IRENA/Steffen) | DW20: =IF(p_basis=1,(1+DU20)/(1+p_infl)-1,DU20) -> 0.08185 | DX20: =DW20+(DT20-DS20) -> 0.12685 | DY20: =IF(AND(p_use_pefa=1,ISNUMBER(BD20)),p_gap_lic-(BD20-1)/3*(p_gap_lic-p_gap_ae),IF(E20="AE",p_gap_ae,IF(D20="Low income",p_gap_lic,p_gap_em)))*(1-p_reform*p_reform_close) -> 0.355 | DZ20: =IF(AND(p_use_pefa=1,ISNUMBER(BD20)),"PEFA PI-11","Income-group default (IMF 2015)") -> PEFA PI-11 | EA20: =IF(E20="AE",p_ps_ae,IF(E20="China",p_ps_chn,p_ps_emdc)) -> 0.4 | EB20: =(1-EA20)+EA20/(1-DY20) -> 1.220155 | EC20: =Results_Country!F20 -> 97.634582 | ED20: =IF(CH20="",0,CH20*EC20) -> 13378.117 | EE20: =IF(CJ20="",0,CJ20*EC20) -> 6113.3426 | EF20: =IF(CH20="",0,EC20) -> 97.634582
A21: TUR | B21: Türkiye | C21: Europe & Central Asia | D21: Upper middle income | E21: EMDC | F21: 1358.251 | G21: 3553.197 | H21: 3.605 | I21: 3.366 | J21: 87.473805 | K21: 573.016 | L21: 693.478 | M21: 644.249 | N21: 345.36129 | O21: 95.153213 | P21: 1.984729 | Q21: 0.73298535 | R21: 1.0981476 | S21: 0.72913105 | T21: 0.0035377489 | U21: 0.40523997 | V21: 0.2557627 | W21: 1.536352 | X21: 0 | Y21: 4.1462027 | Z21: 33.670356 | AA21: 7.6648044 | AB21: 1.2945358 | AC21: 5.8163135 | AD21: 0.854296 | AE21: 0.809288 | AF21: 0.522073 | AG21: 0.69738 | AH21: 0.51946289 | AI21: 3.313 | AJ21: 5.31708 | AK21: 1.025 | AL21: 1.9465367 | AM21: 9.197 | AN21: 11.26664 | AO21: 9.197 | AP21: 10.084709 | AQ21: 63.941056 | AR21: 1.6329746 | AS21: 3.847428 | AT21: 5.4304704 | AU21: 0.53799943 | AV21: 0.056876 | AW21: 2.734772 | AX21: 0.557641 | AY21: 0.82843677 | AZ21: 0.036891 | BA21: 23.6 | BB21: 6.939 | BF21: 0 | BG21: 7.5 | BH21: 7.19 | BI21: 2020 | BJ21: 2 | BL21: 1.517 | BM21: 6.215 | BN21: 8.302 | BO21: 0.47 | BP21: 0.091 | BQ21: 2025 | BR21: 353.86 | BS21: 121.4 | BT21: 78.36 | BU21: 1.03 | BV21: =F21*(1+N(H21)/100)*(1+N(I21)/100)^5 -> 1660.5398 | BW21: =IF(N(G21)>0,G21,F21) -> 3553.197 | BX21: =F21/BW21 -> 0.38226166 | BY21: =IF(ISNUMBER(K21),1,0) -> 1 | BZ21: =IF(BY21=0,"",N(N21)+N(O21)+N(P21)) -> 442.49923 | CA21: =IF(BY21=0,"",(N(Y21)*34.2+N(Z21)*38.6)/1000) -> 1.4414759 | CB21: =IF(BY21=0,"",N(O21)*0.0036+N(R21)+N(V21)+(N(AA21)*25.3+N(AB21)*37)/1000) -> 1.9382792 | CC21: =IF(BY21=0,"",N(N21)*0.0036+N(Q21)+N(U21)+N(T21)+N(X21)+N(AC21)*38/1000) -> 2.6060836 | CD21: =IF(BY21=0,"",N(Q21)+N(R21)+N(S21)+N(T21)+N(U21)+N(V21)+N(W21)+N(X21)+(N(Y21)*34.2+N(Z21)*38.6+N(AA21)*25.3+N(AB21)*37+N(AC21)*38)/1000) -> 6.6654695 | CE21: =IF(BY21=0,"",MAX(0,N(L21)-N(K21))+MAX(0,N(M21)-N(L21))) -> 120.462 | CF21: =IF(BY21=0,"",N(Y21)*N(AD21)+N(Z21)*N(AE21)+N(AA21)*N(AF21)+N(AB21)*N(AG21)+N(AC21)*N(AH21)+N(U21)*N(AI21)+N(V21)*N(AJ21)+N(W21)*N(AK21)+N(X21)*N(AL21)+N(Q21)*N(AM21)+N(R21)*N(AN21)+N(S21)*N(AO21)+N(T21)*N(AP21)) -> 68.849256 | CG21: =IF(AND(BY21=1,N(K21)>0),K21,0) -> 573.016 | CH21: =IF(CG21>0,CF21*1000/CG21,"") -> 120.15241 | CI21: =IF(BY21=0,"",N(AQ21)+p_road*(N(AR21)+N(AS21)+N(AT21))) -> 63.941056 | CJ21: =IF(CG21>0,CI21*1000/CG21,"") -> 111.58686 | CK21: =IF(CH21="",1,MIN(p_idx_max,MAX(p_idx_min,CH21/p_fc_world))) -> 0.74625424 | CL21: =IF(CJ21="",1,MIN(p_idx_max,MAX(p_idx_min,CJ21/p_cb_world))) -> 2.1217945 | CM21: =p_b*(1-p_wb_idx+p_wb_idx*CK21) -> 0.099251814 | CN21: =p_c*(1-p_wc_idx+p_wc_idx*CL21) -> 0.27371149 | CO21: =IF(N(BR21)>0,(N(BS21)+N(BT21)+N(BU21))/BR21,"") -> 0.5674278 | CP21: =N(BS21)+N(BT21)+N(BU21) -> 200.79 | CQ21: =IF(CP21>0,N(BS21)/CP21,"") -> 0.60461178 | CR21: =IF(CP21>0,N(BT21)/CP21,"") -> 0.39025848 | CS21: =IF(CP21>0,N(BU21)/CP21,"") -> 0.0051297375 | CT21: =1000*(p_sh_pv*p_cf_pv/p_capex_pv+(1-p_sh_pv)*p_cf_wind/p_capex_wind)*8760 -> 2301.2886 | CU21: =IF(AND(ISNUMBER(CO21),ISNUMBER(CQ21),BY21=1),1,0) -> 1 | CV21: =IF(CU21=0,"",CQ21*p_hr_coal*N(AK21)+CR21*p_hr_gas*N(AO21)+CS21*p_hr_oil*N(AH21)/p_gj_l_oil) -> 33.841181 | CW21: =IF(CU21=0,"",CQ21*p_hr_coal*p_ef_coal+CR21*p_hr_gas*p_ef_gas+CS21*p_hr_oil*p_ef_oil) -> 0.74033294 | CX21: =IF(CU21=0,"",CQ21*p_hr_coal*N(AW21)+CR21*p_hr_gas*N(AX21)+CS21*p_hr_oil*N(AY21)/p_gj_l_oil) -> 19.322931 | CY21: =IF(CU21=0,"",CO21*CW21) -> 0.42008549 | CZ21: =IF(CU21=0,"",CT21*CO21*CV21/1000/1000-p_om_re) -> 0.029190325 | DA21: =IF(CU21=0,"",CT21*CO21*CX21/1000/1000) -> 0.025232175 | DB21: =IF(CU21=0,"",CT21*CO21*CW21/1000) -> 0.96673793 | DC21: =IF(AND(CU21=1,ISNUMBER(AD21),ISNUMBER(AV21)),1,0) -> 1 | DD21: =IF(DC21=0,"",p_ev_km*p_ice_l/100*AD21-p_ev_km*p_ev_kwh*AV21+p_ev_km*p_ev_maint) -> 987.5178 | DE21: =IF(DC21=0,"",DD21/p_ev_prem) -> 0.19750356 | DF21: =IF(DC21=0,"",p_ev_km*p_ice_l/100*N(AZ21)/p_ev_prem) -> 0.008300475 | DG21: =IF(DC21=0,"",1000/p_ev_prem*(p_ev_km*p_ice_l/100*p_gj_l_gso*p_ef_gso-p_ev_km*p_ev_kwh/1000*CY21)) -> 0.30641734 | DH21: =IFERROR(IF(INDEX(Damodaran!$D:$D,MATCH(A21,Damodaran!$A:$A,0))="","",INDEX(Damodaran!$D:$D,MATCH(A21,Damodaran!$A:$A,0))),"") | DI21: =IFERROR(IF(INDEX(Damodaran!$E:$E,MATCH(A21,Damodaran!$A:$A,0))="","",INDEX(Damodaran!$E:$E,MATCH(A21,Damodaran!$A:$A,0))),"") | DJ21: =IFERROR(IF(INDEX(Damodaran!$G:$G,MATCH(A21,Damodaran!$A:$A,0))="","",INDEX(Damodaran!$G:$G,MATCH(A21,Damodaran!$A:$A,0))),"") | DK21: =IF(ISNUMBER(BG21),(1+BG21/100)*(1+p_infl)-1,"") -> 0.0965 | DL21: =IF(ISNUMBER(BH21),BH21/100,"") -> 0.0719 | DM21: =IF(COUNT(DK21,DL21)=0,"",AVERAGE(DK21,DL21)) -> 0.0842 | DN21: =IF(OR(DH21="",DI21=""),"",p_dv*(p_rf+DH21)*(1-IF(DJ21="",p_tax_def,DJ21))+(1-p_dv)*(p_rf+p_beta*p_erp+p_lambda*DI21)) | DO21: =IF(AND(ISNUMBER(DM21),ISNUMBER(DN21)),1,0) -> 0 | DP21: =IF(DO21=1,DM21,0) -> 0 | DQ21: =IF(DO21=1,DN21,0) -> 0 | DR21: =IF(DN21="","",DN21+p_shift) | DS21: =IF(E21="AE",p_r_ae,IF(E21="China",p_r_chn,p_r_emdc)) -> 0.105 | DT21: =IF(E21="AE",p_rh_ae,IF(E21="China",p_rh_chn,p_rh_emdc)) -> 0.15 | DU21: =IF(AND(p_use_obs=1,ISNUMBER(DM21)),DM21,IF(AND(p_use_dam=1,ISNUMBER(DR21)),DR21,DS21)) -> 0.0842 | DV21: =IF(AND(p_use_obs=1,ISNUMBER(DM21)),"Observed (IRENA/Steffen)",IF(AND(p_use_dam=1,ISNUMBER(DR21)),"Damodaran (eq. 5)","Group default (IHLEG)")) -> Observed (IRENA/Steffen) | DW21: =IF(p_basis=1,(1+DU21)/(1+p_infl)-1,DU21) -> 0.0842 | DX21: =DW21+(DT21-DS21) -> 0.1292 | DY21: =IF(AND(p_use_pefa=1,ISNUMBER(BD21)),p_gap_lic-(BD21-1)/3*(p_gap_lic-p_gap_ae),IF(E21="AE",p_gap_ae,IF(D21="Low income",p_gap_lic,p_gap_em)))*(1-p_reform*p_reform_close) -> 0.27 | DZ21: =IF(AND(p_use_pefa=1,ISNUMBER(BD21)),"PEFA PI-11","Income-group default (IMF 2015)") -> Income-group default (IMF 2015) | EA21: =IF(E21="AE",p_ps_ae,IF(E21="China",p_ps_chn,p_ps_emdc)) -> 0.4 | EB21: =(1-EA21)+EA21/(1-DY21) -> 1.1479452 | EC21: =Results_Country!F21 -> 88.087913 | ED21: =IF(CH21="",0,CH21*EC21) -> 10583.975 | EE21: =IF(CJ21="",0,CJ21*EC21) -> 9829.4535 | EF21: =IF(CH21="",0,EC21) -> 88.087913
A22: SAU | B22: Saudi Arabia | C22: Middle East & North Africa | D22: High income | E22: EMDC | F22: 1254.141 | G22: 2539.368 | H22: 4.502 | I22: 3.115 | J22: 33.962757 | K22: 558.375 | L22: 764.069 | M22: 764.069 | N22: 190.30287 | O22: 156.18307 | P22: 0.51140502 | Q22: 1.0940905 | R22: 0 | S22: 3.6768209 | T22: 0 | U22: 0 | V22: 0 | W22: 0 | X22: 0 | Y22: 29.866366 | Z22: 24.034807 | AA22: 2.9310254 | AB22: 1.1830869 | AC22: 22.004855 | AD22: 0.828 | AE22: 0.784905 | AF22: 0.583053 | AG22: 0.7498 | AH22: 0.5433453 | AI22: 7.124 | AJ22: 14.02195 | AK22: 5.575 | AL22: 8.9069833 | AM22: 5.307 | AN22: 10.6697 | AO22: 4.646 | AP22: 4.797584 | AQ22: 16.459369 | AR22: 4.9009114 | AS22: 9.4292535 | AT22: 5.203443 | AU22: 0.094961755 | AV22: 0.1081 | AW22: 1.205327 | AX22: 0.067898 | AY22: 0.26820899 | AZ22: 0.070128 | BA22: 25.854 | BB22: 0.332 | BC22: 113.284 | BF22: 0 | BH22: 4.2 | BI22: 2017 | BJ22: 1 | BQ22: 2024 | BR22: 454.64 | BS22: 0 | BT22: 287.98 | BU22: 156.84 | BV22: =F22*(1+N(H22)/100)*(1+N(I22)/100)^5 -> 1527.8482 | BW22: =IF(N(G22)>0,G22,F22) -> 2539.368 | BX22: =F22/BW22 -> 0.49387919 | BY22: =IF(ISNUMBER(K22),1,0) -> 1 | BZ22: =IF(BY22=0,"",N(N22)+N(O22)+N(P22)) -> 346.99734 | CA22: =IF(BY22=0,"",(N(Y22)*34.2+N(Z22)*38.6)/1000) -> 1.9491733 | CB22: =IF(BY22=0,"",N(O22)*0.0036+N(R22)+N(V22)+(N(AA22)*25.3+N(AB22)*37)/1000) -> 0.6801882 | CC22: =IF(BY22=0,"",N(N22)*0.0036+N(Q22)+N(U22)+N(T22)+N(X22)+N(AC22)*38/1000) -> 2.6153653 | CD22: =IF(BY22=0,"",N(Q22)+N(R22)+N(S22)+N(T22)+N(U22)+N(V22)+N(W22)+N(X22)+(N(Y22)*34.2+N(Z22)*38.6+N(AA22)*25.3+N(AB22)*37+N(AC22)*38)/1000) -> 7.6741983 | CE22: =IF(BY22=0,"",MAX(0,N(L22)-N(K22))+MAX(0,N(M22)-N(L22))) -> 205.694 | CF22: =IF(BY22=0,"",N(Y22)*N(AD22)+N(Z22)*N(AE22)+N(AA22)*N(AF22)+N(AB22)*N(AG22)+N(AC22)*N(AH22)+N(U22)*N(AI22)+N(V22)*N(AJ22)+N(W22)*N(AK22)+N(X22)*N(AL22)+N(Q22)*N(AM22)+N(R22)*N(AN22)+N(S22)*N(AO22)+N(T22)*N(AP22)) -> 81.035496 | CG22: =IF(AND(BY22=1,N(K22)>0),K22,0) -> 558.375 | CH22: =IF(CG22>0,CF22*1000/CG22,"") -> 145.12737 | CI22: =IF(BY22=0,"",N(AQ22)+p_road*(N(AR22)+N(AS22)+N(AT22))) -> 16.459369 | CJ22: =IF(CG22>0,CI22*1000/CG22,"") -> 29.477267 | CK22: =IF(CH22="",1,MIN(p_idx_max,MAX(p_idx_min,CH22/p_fc_world))) -> 0.90137112 | CL22: =IF(CJ22="",1,MIN(p_idx_max,MAX(p_idx_min,CJ22/p_cb_world))) -> 0.56050241 | CM22: =p_b*(1-p_wb_idx+p_wb_idx*CK22) -> 0.11988236 | CN22: =p_c*(1-p_wc_idx+p_wc_idx*CL22) -> 0.072304811 | CO22: =IF(N(BR22)>0,(N(BS22)+N(BT22)+N(BU22))/BR22,"") -> 0.97840049 | CP22: =N(BS22)+N(BT22)+N(BU22) -> 444.82 | CQ22: =IF(CP22>0,N(BS22)/CP22,"") -> 0 | CR22: =IF(CP22>0,N(BT22)/CP22,"") -> 0.64740794 | CS22: =IF(CP22>0,N(BU22)/CP22,"") -> 0.35259206 | CT22: =1000*(p_sh_pv*p_cf_pv/p_capex_pv+(1-p_sh_pv)*p_cf_wind/p_capex_wind)*8760 -> 2301.2886 | CU22: =IF(AND(ISNUMBER(CO22),ISNUMBER(CQ22),BY22=1),1,0) -> 1 | CV22: =IF(CU22=0,"",CQ22*p_hr_coal*N(AK22)+CR22*p_hr_gas*N(AO22)+CS22*p_hr_oil*N(AH22)/p_gj_l_oil) -> 74.672453 | CW22: =IF(CU22=0,"",CQ22*p_hr_coal*p_ef_coal+CR22*p_hr_gas*p_ef_gas+CS22*p_hr_oil*p_ef_oil) -> 0.55894846 | CX22: =IF(CU22=0,"",CQ22*p_hr_coal*N(AW22)+CR22*p_hr_gas*N(AX22)+CS22*p_hr_oil*N(AY22)/p_gj_l_oil) -> 26.054237 | CY22: =IF(CU22=0,"",CO22*CW22) -> 0.54687545 | CZ22: =IF(CU22=0,"",CT22*CO22*CV22/1000/1000-p_om_re) -> 0.15313114 | DA22: =IF(CU22=0,"",CT22*CO22*CX22/1000/1000) -> 0.058663247 | DB22: =IF(CU22=0,"",CT22*CO22*CW22/1000) -> 1.2585182 | DC22: =IF(AND(CU22=1,ISNUMBER(AD22),ISNUMBER(AV22)),1,0) -> 1 | DD22: =IF(DC22=0,"",p_ev_km*p_ice_l/100*AD22-p_ev_km*p_ev_kwh*AV22+p_ev_km*p_ev_maint) -> 819.63 | DE22: =IF(DC22=0,"",DD22/p_ev_prem) -> 0.163926 | DF22: =IF(DC22=0,"",p_ev_km*p_ice_l/100*N(AZ22)/p_ev_prem) -> 0.0157788 | DG22: =IF(DC22=0,"",1000/p_ev_prem*(p_ev_km*p_ice_l/100*p_gj_l_gso*p_ef_gso-p_ev_km*p_ev_kwh/1000*CY22)) -> 0.23795076 | DH22: =IFERROR(IF(INDEX(Damodaran!$D:$D,MATCH(A22,Damodaran!$A:$A,0))="","",INDEX(Damodaran!$D:$D,MATCH(A22,Damodaran!$A:$A,0))),"") | DI22: =IFERROR(IF(INDEX(Damodaran!$E:$E,MATCH(A22,Damodaran!$A:$A,0))="","",INDEX(Damodaran!$E:$E,MATCH(A22,Damodaran!$A:$A,0))),"") | DJ22: =IFERROR(IF(INDEX(Damodaran!$G:$G,MATCH(A22,Damodaran!$A:$A,0))="","",INDEX(Damodaran!$G:$G,MATCH(A22,Damodaran!$A:$A,0))),"") | DK22: =IF(ISNUMBER(BG22),(1+BG22/100)*(1+p_infl)-1,"") | DL22: =IF(ISNUMBER(BH22),BH22/100,"") -> 0.042 | DM22: =IF(COUNT(DK22,DL22)=0,"",AVERAGE(DK22,DL22)) -> 0.042 | DN22: =IF(OR(DH22="",DI22=""),"",p_dv*(p_rf+DH22)*(1-IF(DJ22="",p_tax_def,DJ22))+(1-p_dv)*(p_rf+p_beta*p_erp+p_lambda*DI22)) | DO22: =IF(AND(ISNUMBER(DM22),ISNUMBER(DN22)),1,0) -> 0 | DP22: =IF(DO22=1,DM22,0) -> 0 | DQ22: =IF(DO22=1,DN22,0) -> 0 | DR22: =IF(DN22="","",DN22+p_shift) | DS22: =IF(E22="AE",p_r_ae,IF(E22="China",p_r_chn,p_r_emdc)) -> 0.105 | DT22: =IF(E22="AE",p_rh_ae,IF(E22="China",p_rh_chn,p_rh_emdc)) -> 0.15 | DU22: =IF(AND(p_use_obs=1,ISNUMBER(DM22)),DM22,IF(AND(p_use_dam=1,ISNUMBER(DR22)),DR22,DS22)) -> 0.042 | DV22: =IF(AND(p_use_obs=1,ISNUMBER(DM22)),"Observed (IRENA/Steffen)",IF(AND(p_use_dam=1,ISNUMBER(DR22)),"Damodaran (eq. 5)","Group default (IHLEG)")) -> Observed (IRENA/Steffen) | DW22: =IF(p_basis=1,(1+DU22)/(1+p_infl)-1,DU22) -> 0.042 | DX22: =DW22+(DT22-DS22) -> 0.087 | DY22: =IF(AND(p_use_pefa=1,ISNUMBER(BD22)),p_gap_lic-(BD22-1)/3*(p_gap_lic-p_gap_ae),IF(E22="AE",p_gap_ae,IF(D22="Low income",p_gap_lic,p_gap_em)))*(1-p_reform*p_reform_close) -> 0.27 | DZ22: =IF(AND(p_use_pefa=1,ISNUMBER(BD22)),"PEFA PI-11","Income-group default (IMF 2015)") -> Income-group default (IMF 2015) | EA22: =IF(E22="AE",p_ps_ae,IF(E22="China",p_ps_chn,p_ps_emdc)) -> 0.4 | EB22: =(1-EA22)+EA22/(1-DY22) -> 1.1479452 | EC22: =Results_Country!F22 -> 78.141322 | ED22: =IF(CH22="",0,CH22*EC22) -> 11340.445 | EE22: =IF(CJ22="",0,CJ22*EC22) -> 2303.3926 | EF22: =IF(CH22="",0,EC22) -> 78.141322
A23: NLD | B23: Netherlands | C23: Europe & Central Asia | D23: High income | E23: AE | F23: 1214.562 | G23: 1459.737 | H23: 1.856 | I23: 1.233 | J23: 18.228742 | K23: 122.936 | L23: 151.045 | M23: 155.145 | N23: 64.819024 | O23: 17.709391 | P23: 2.2300838 | Q23: 0.24894056 | R23: 0.59189964 | S23: 0.12314312 | T23: 0.0028417927 | U23: 0.035738612 | V23: 0.0008772737 | W23: 0.09927593 | X23: 0 | Y23: 4.4067933 | Z23: 6.4165727 | AA23: 0.48052333 | AB23: 0.0160347 | AC23: 6.0792003 | AD23: 0.908709 | AE23: 0.809495 | AF23: 0.538655 | AG23: 0.705476 | AH23: 0.49319664 | AI23: 9.912 | AJ23: 16.03613 | AK23: 6.635 | AL23: 7.5575191 | AM23: 12.708 | AN23: 27.84089 | AO23: 12.708 | AP23: 21.999812 | AQ23: 0.32836656 | AR23: 0.44026718 | AS23: 0.087783183 | AT23: 0.076059607 | AU23: 0.65157659 | AV23: 0.344826 | AW23: 1.866565 | AX23: 0.07615 | AY23: 0.19146803 | AZ23: 0.062384 | BA23: 43.748 | BB23: 0.992 | BF23: 0 | BH23: 2.327 | BI23: 2020 | BJ23: 1 | BQ23: 2025 | BR23: 134.961 | BS23: 9.55 | BT23: 47.09 | BU23: 5.23 | BV23: =F23*(1+N(H23)/100)*(1+N(I23)/100)^5 -> 1315.2758 | BW23: =IF(N(G23)>0,G23,F23) -> 1459.737 | BX23: =F23/BW23 -> 0.83204166 | BY23: =IF(ISNUMBER(K23),1,0) -> 1 | BZ23: =IF(BY23=0,"",N(N23)+N(O23)+N(P23)) -> 84.758499 | CA23: =IF(BY23=0,"",(N(Y23)*34.2+N(Z23)*38.6)/1000) -> 0.39839204 | CB23: =IF(BY23=0,"",N(O23)*0.0036+N(R23)+N(V23)+(N(AA23)*25.3+N(AB23)*37)/1000) -> 0.66928124 | CC23: =IF(BY23=0,"",N(N23)*0.0036+N(Q23)+N(U23)+N(T23)+N(X23)+N(AC23)*38/1000) -> 0.75187906 | CD23: =IF(BY23=0,"",N(Q23)+N(R23)+N(S23)+N(T23)+N(U23)+N(V23)+N(W23)+N(X23)+(N(Y23)*34.2+N(Z23)*38.6+N(AA23)*25.3+N(AB23)*37+N(AC23)*38)/1000) -> 1.7448691 | CE23: =IF(BY23=0,"",MAX(0,N(L23)-N(K23))+MAX(0,N(M23)-N(L23))) -> 32.209 | CF23: =IF(BY23=0,"",N(Y23)*N(AD23)+N(Z23)*N(AE23)+N(AA23)*N(AF23)+N(AB23)*N(AG23)+N(AC23)*N(AH23)+N(U23)*N(AI23)+N(V23)*N(AJ23)+N(W23)*N(AK23)+N(X23)*N(AL23)+N(Q23)*N(AM23)+N(R23)*N(AN23)+N(S23)*N(AO23)+N(T23)*N(AP23)) -> 34.764042 | CG23: =IF(AND(BY23=1,N(K23)>0),K23,0) -> 122.936 | CH23: =IF(CG23>0,CF23*1000/CG23,"") -> 282.78163 | CI23: =IF(BY23=0,"",N(AQ23)+p_road*(N(AR23)+N(AS23)+N(AT23))) -> 0.32836656 | CJ23: =IF(CG23>0,CI23*1000/CG23,"") -> 2.6710366 | CK23: =IF(CH23="",1,MIN(p_idx_max,MAX(p_idx_min,CH23/p_fc_world))) -> 1.7563275 | CL23: =IF(CJ23="",1,MIN(p_idx_max,MAX(p_idx_min,CJ23/p_cb_world))) -> 0.25 | CM23: =p_b*(1-p_wb_idx+p_wb_idx*CK23) -> 0.23359156 | CN23: =p_c*(1-p_wc_idx+p_wc_idx*CL23) -> 0.03225 | CO23: =IF(N(BR23)>0,(N(BS23)+N(BT23)+N(BU23))/BR23,"") -> 0.45842873 | CP23: =N(BS23)+N(BT23)+N(BU23) -> 61.87 | CQ23: =IF(CP23>0,N(BS23)/CP23,"") -> 0.15435591 | CR23: =IF(CP23>0,N(BT23)/CP23,"") -> 0.76111201 | CS23: =IF(CP23>0,N(BU23)/CP23,"") -> 0.084532083 | CT23: =1000*(p_sh_pv*p_cf_pv/p_capex_pv+(1-p_sh_pv)*p_cf_wind/p_capex_wind)*8760 -> 2301.2886 | CU23: =IF(AND(ISNUMBER(CO23),ISNUMBER(CQ23),BY23=1),1,0) -> 1 | CV23: =IF(CU23=0,"",CQ23*p_hr_coal*N(AK23)+CR23*p_hr_gas*N(AO23)+CS23*p_hr_oil*N(AH23)/p_gj_l_oil) -> 94.1239 | CW23: =IF(CU23=0,"",CQ23*p_hr_coal*p_ef_coal+CR23*p_hr_gas*p_ef_gas+CS23*p_hr_oil*p_ef_oil) -> 0.53495779 | CX23: =IF(CU23=0,"",CQ23*p_hr_coal*N(AW23)+CR23*p_hr_gas*N(AX23)+CS23*p_hr_oil*N(AY23)/p_gj_l_oil) -> 7.7185509 | CY23: =IF(CU23=0,"",CO23*CW23) -> 0.24524002 | CZ23: =IF(CU23=0,"",CT23*CO23*CV23/1000/1000-p_om_re) -> 0.08429853 | DA23: =IF(CU23=0,"",CT23*CO23*CX23/1000/1000) -> 0.0081428921 | DB23: =IF(CU23=0,"",CT23*CO23*CW23/1000) -> 0.56436806 | DC23: =IF(AND(CU23=1,ISNUMBER(AD23),ISNUMBER(AV23)),1,0) -> 1 | DD23: =IF(DC23=0,"",p_ev_km*p_ice_l/100*AD23-p_ev_km*p_ev_kwh*AV23+p_ev_km*p_ev_maint) -> 271.26743 | DE23: =IF(DC23=0,"",DD23/p_ev_prem) -> 0.054253485 | DF23: =IF(DC23=0,"",p_ev_km*p_ice_l/100*N(AZ23)/p_ev_prem) -> 0.0140364 | DG23: =IF(DC23=0,"",1000/p_ev_prem*(p_ev_km*p_ice_l/100*p_gj_l_gso*p_ef_gso-p_ev_km*p_ev_kwh/1000*CY23)) -> 0.40083389 | DH23: =IFERROR(IF(INDEX(Damodaran!$D:$D,MATCH(A23,Damodaran!$A:$A,0))="","",INDEX(Damodaran!$D:$D,MATCH(A23,Damodaran!$A:$A,0))),"") | DI23: =IFERROR(IF(INDEX(Damodaran!$E:$E,MATCH(A23,Damodaran!$A:$A,0))="","",INDEX(Damodaran!$E:$E,MATCH(A23,Damodaran!$A:$A,0))),"") | DJ23: =IFERROR(IF(INDEX(Damodaran!$G:$G,MATCH(A23,Damodaran!$A:$A,0))="","",INDEX(Damodaran!$G:$G,MATCH(A23,Damodaran!$A:$A,0))),"") | DK23: =IF(ISNUMBER(BG23),(1+BG23/100)*(1+p_infl)-1,"") | DL23: =IF(ISNUMBER(BH23),BH23/100,"") -> 0.02327 | DM23: =IF(COUNT(DK23,DL23)=0,"",AVERAGE(DK23,DL23)) -> 0.02327 | DN23: =IF(OR(DH23="",DI23=""),"",p_dv*(p_rf+DH23)*(1-IF(DJ23="",p_tax_def,DJ23))+(1-p_dv)*(p_rf+p_beta*p_erp+p_lambda*DI23)) | DO23: =IF(AND(ISNUMBER(DM23),ISNUMBER(DN23)),1,0) -> 0 | DP23: =IF(DO23=1,DM23,0) -> 0 | DQ23: =IF(DO23=1,DN23,0) -> 0 | DR23: =IF(DN23="","",DN23+p_shift) | DS23: =IF(E23="AE",p_r_ae,IF(E23="China",p_r_chn,p_r_emdc)) -> 0.055 | DT23: =IF(E23="AE",p_rh_ae,IF(E23="China",p_rh_chn,p_rh_emdc)) -> 0.07 | DU23: =IF(AND(p_use_obs=1,ISNUMBER(DM23)),DM23,IF(AND(p_use_dam=1,ISNUMBER(DR23)),DR23,DS23)) -> 0.02327 | DV23: =IF(AND(p_use_obs=1,ISNUMBER(DM23)),"Observed (IRENA/Steffen)",IF(AND(p_use_dam=1,ISNUMBER(DR23)),"Damodaran (eq. 5)","Group default (IHLEG)")) -> Observed (IRENA/Steffen) | DW23: =IF(p_basis=1,(1+DU23)/(1+p_infl)-1,DU23) -> 0.02327 | DX23: =DW23+(DT23-DS23) -> 0.03827 | DY23: =IF(AND(p_use_pefa=1,ISNUMBER(BD23)),p_gap_lic-(BD23-1)/3*(p_gap_lic-p_gap_ae),IF(E23="AE",p_gap_ae,IF(D23="Low income",p_gap_lic,p_gap_em)))*(1-p_reform*p_reform_close) -> 0.13 | DZ23: =IF(AND(p_use_pefa=1,ISNUMBER(BD23)),"PEFA PI-11","Income-group default (IMF 2015)") -> Income-group default (IMF 2015) | EA23: =IF(E23="AE",p_ps_ae,IF(E23="China",p_ps_chn,p_ps_emdc)) -> 0.3 | EB23: =(1-EA23)+EA23/(1-DY23) -> 1.0448276 | EC23: =Results_Country!F23 -> 33.897552 | ED23: =IF(CH23="",0,CH23*EC23) -> 9585.6048 | EE23: =IF(CJ23="",0,CJ23*EC23) -> 90.541602 | EF23: =IF(CH23="",0,EC23) -> 33.897552
A24: CHE | B24: Switzerland | C24: Europe & Central Asia | D24: High income | E24: AE | F24: 970.19 | G24: 884.806 | H24: 1.272 | I24: 1.342 | J24: 8.921981 | K24: 35.583 | L24: 45.202 | M24: 43.278 | N24: 30.391922 | O24: 17.680583 | P24: 3.0249407 | Q24: 0.036887206 | R24: 0.095917069 | S24: 0 | T24: 0.0032802538 | U24: 0.0040925262 | V24: 0.00012600182 | W24: 0 | X24: 0 | Y24: 2.6219858 | Z24: 5.8446758 | AA24: 0.17912618 | AB24: 0.044150223 | AC24: 0.21099441 | AD24: 0.779428 | AE24: 0.789515 | AF24: 0.513 | AG24: 0.591 | AH24: 0.51946289 | AI24: 7.124 | AJ24: 13.360185 | AK24: 5.47 | AL24: 7.3102665 | AM24: 40.254 | AN24: 46.614714 | AO24: 40.254 | AP24: 44.847986 | AQ24: 0.11319753 | AR24: 3.1793593 | AS24: 0.11726723 | AT24: 0 | AU24: 0.72877674 | AV24: 0.350656 | AW24: 0.289363 | AX24: 0.116301 | AY24: 0.064949204 | AZ24: 0.055729 | BA24: 40.493 | BB24: 0.43 | BF24: 0 | BH24: 3.97 | BI24: 2017 | BJ24: 1 | BQ24: 2025 | BR24: 65.02 | BT24: 0.27 | BU24: 1.23 | BV24: =F24*(1+N(H24)/100)*(1+N(I24)/100)^5 -> 1050.252 | BW24: =IF(N(G24)>0,G24,F24) -> 884.806 | BX24: =F24/BW24 -> 1.0965002 | BY24: =IF(ISNUMBER(K24),1,0) -> 1 | BZ24: =IF(BY24=0,"",N(N24)+N(O24)+N(P24)) -> 51.097446 | CA24: =IF(BY24=0,"",(N(Y24)*34.2+N(Z24)*38.6)/1000) -> 0.3152764 | CB24: =IF(BY24=0,"",N(O24)*0.0036+N(R24)+N(V24)+(N(AA24)*25.3+N(AB24)*37)/1000) -> 0.16585862 | CC24: =IF(BY24=0,"",N(N24)*0.0036+N(Q24)+N(U24)+N(T24)+N(X24)+N(AC24)*38/1000) -> 0.16168869 | CD24: =IF(BY24=0,"",N(Q24)+N(R24)+N(S24)+N(T24)+N(U24)+N(V24)+N(W24)+N(X24)+(N(Y24)*34.2+N(Z24)*38.6+N(AA24)*25.3+N(AB24)*37+N(AC24)*38)/1000) -> 0.4697627 | CE24: =IF(BY24=0,"",MAX(0,N(L24)-N(K24))+MAX(0,N(M24)-N(L24))) -> 9.619 | CF24: =IF(BY24=0,"",N(Y24)*N(AD24)+N(Z24)*N(AE24)+N(AA24)*N(AF24)+N(AB24)*N(AG24)+N(AC24)*N(AH24)+N(U24)*N(AI24)+N(V24)*N(AJ24)+N(W24)*N(AK24)+N(X24)*N(AL24)+N(Q24)*N(AM24)+N(R24)*N(AN24)+N(S24)*N(AO24)+N(T24)*N(AP24)) -> 13.019652 | CG24: =IF(AND(BY24=1,N(K24)>0),K24,0) -> 35.583 | CH24: =IF(CG24>0,CF24*1000/CG24,"") -> 365.8953 | CI24: =IF(BY24=0,"",N(AQ24)+p_road*(N(AR24)+N(AS24)+N(AT24))) -> 0.11319753 | CJ24: =IF(CG24>0,CI24*1000/CG24,"") -> 3.1812251 | CK24: =IF(CH24="",1,MIN(p_idx_max,MAX(p_idx_min,CH24/p_fc_world))) -> 2.2725379 | CL24: =IF(CJ24="",1,MIN(p_idx_max,MAX(p_idx_min,CJ24/p_cb_world))) -> 0.25 | CM24: =p_b*(1-p_wb_idx+p_wb_idx*CK24) -> 0.30224754 | CN24: =p_c*(1-p_wc_idx+p_wc_idx*CL24) -> 0.03225 | CO24: =IF(N(BR24)>0,(N(BS24)+N(BT24)+N(BU24))/BR24,"") -> 0.023069825 | CP24: =N(BS24)+N(BT24)+N(BU24) -> 1.5 | CQ24: =IF(CP24>0,N(BS24)/CP24,"") -> 0 | CR24: =IF(CP24>0,N(BT24)/CP24,"") -> 0.18 | CS24: =IF(CP24>0,N(BU24)/CP24,"") -> 0.82 | CT24: =1000*(p_sh_pv*p_cf_pv/p_capex_pv+(1-p_sh_pv)*p_cf_wind/p_capex_wind)*8760 -> 2301.2886 | CU24: =IF(AND(ISNUMBER(CO24),ISNUMBER(CQ24),BY24=1),1,0) -> 1 | CV24: =IF(CU24=0,"",CQ24*p_hr_coal*N(AK24)+CR24*p_hr_gas*N(AO24)+CS24*p_hr_oil*N(AH24)/p_gj_l_oil) -> 170.21273 | CW24: =IF(CU24=0,"",CQ24*p_hr_coal*p_ef_coal+CR24*p_hr_gas*p_ef_gas+CS24*p_hr_oil*p_ef_oil) -> 0.742149 | CX24: =IF(CU24=0,"",CQ24*p_hr_coal*N(AW24)+CR24*p_hr_gas*N(AX24)+CS24*p_hr_oil*N(AY24)/p_gj_l_oil) -> 14.644381 | CY24: =IF(CU24=0,"",CO24*CW24) -> 0.017121247 | CZ24: =IF(CU24=0,"",CT24*CO24*CV24/1000/1000-p_om_re) -> -0.005963351 | DA24: =IF(CU24=0,"",CT24*CO24*CX24/1000/1000) -> 0.0007774749 | DB24: =IF(CU24=0,"",CT24*CO24*CW24/1000) -> 0.039400931 | DC24: =IF(AND(CU24=1,ISNUMBER(AD24),ISNUMBER(AV24)),1,0) -> 1 | DD24: =IF(DC24=0,"",p_ev_km*p_ice_l/100*AD24-p_ev_km*p_ev_kwh*AV24+p_ev_km*p_ev_maint) -> 110.0853 | DE24: =IF(DC24=0,"",DD24/p_ev_prem) -> 0.02201706 | DF24: =IF(DC24=0,"",p_ev_km*p_ice_l/100*N(AZ24)/p_ev_prem) -> 0.012539025 | DG24: =IF(DC24=0,"",1000/p_ev_prem*(p_ev_km*p_ice_l/100*p_gj_l_gso*p_ef_gso-p_ev_km*p_ev_kwh/1000*CY24)) -> 0.52401803 | DH24: =IFERROR(IF(INDEX(Damodaran!$D:$D,MATCH(A24,Damodaran!$A:$A,0))="","",INDEX(Damodaran!$D:$D,MATCH(A24,Damodaran!$A:$A,0))),"") | DI24: =IFERROR(IF(INDEX(Damodaran!$E:$E,MATCH(A24,Damodaran!$A:$A,0))="","",INDEX(Damodaran!$E:$E,MATCH(A24,Damodaran!$A:$A,0))),"") | DJ24: =IFERROR(IF(INDEX(Damodaran!$G:$G,MATCH(A24,Damodaran!$A:$A,0))="","",INDEX(Damodaran!$G:$G,MATCH(A24,Damodaran!$A:$A,0))),"") | DK24: =IF(ISNUMBER(BG24),(1+BG24/100)*(1+p_infl)-1,"") | DL24: =IF(ISNUMBER(BH24),BH24/100,"") -> 0.0397 | DM24: =IF(COUNT(DK24,DL24)=0,"",AVERAGE(DK24,DL24)) -> 0.0397 | DN24: =IF(OR(DH24="",DI24=""),"",p_dv*(p_rf+DH24)*(1-IF(DJ24="",p_tax_def,DJ24))+(1-p_dv)*(p_rf+p_beta*p_erp+p_lambda*DI24)) | DO24: =IF(AND(ISNUMBER(DM24),ISNUMBER(DN24)),1,0) -> 0 | DP24: =IF(DO24=1,DM24,0) -> 0 | DQ24: =IF(DO24=1,DN24,0) -> 0 | DR24: =IF(DN24="","",DN24+p_shift) | DS24: =IF(E24="AE",p_r_ae,IF(E24="China",p_r_chn,p_r_emdc)) -> 0.055 | DT24: =IF(E24="AE",p_rh_ae,IF(E24="China",p_rh_chn,p_rh_emdc)) -> 0.07 | DU24: =IF(AND(p_use_obs=1,ISNUMBER(DM24)),DM24,IF(AND(p_use_dam=1,ISNUMBER(DR24)),DR24,DS24)) -> 0.0397 | DV24: =IF(AND(p_use_obs=1,ISNUMBER(DM24)),"Observed (IRENA/Steffen)",IF(AND(p_use_dam=1,ISNUMBER(DR24)),"Damodaran (eq. 5)","Group default (IHLEG)")) -> Observed (IRENA/Steffen) | DW24: =IF(p_basis=1,(1+DU24)/(1+p_infl)-1,DU24) -> 0.0397 | DX24: =DW24+(DT24-DS24) -> 0.0547 | DY24: =IF(AND(p_use_pefa=1,ISNUMBER(BD24)),p_gap_lic-(BD24-1)/3*(p_gap_lic-p_gap_ae),IF(E24="AE",p_gap_ae,IF(D24="Low income",p_gap_lic,p_gap_em)))*(1-p_reform*p_reform_close) -> 0.13 | DZ24: =IF(AND(p_use_pefa=1,ISNUMBER(BD24)),"PEFA PI-11","Income-group default (IMF 2015)") -> Income-group default (IMF 2015) | EA24: =IF(E24="AE",p_ps_ae,IF(E24="China",p_ps_chn,p_ps_emdc)) -> 0.3 | EB24: =(1-EA24)+EA24/(1-DY24) -> 1.0448276 | EC24: =Results_Country!F24 -> 21.923407 | ED24: =IF(CH24="",0,CH24*EC24) -> 8021.6717 | EE24: =IF(CJ24="",0,CJ24*EC24) -> 69.743293 | EF24: =IF(CH24="",0,EC24) -> 21.923407
A25: POL | B25: Poland | C25: Europe & Central Asia | D25: High income | E25: EMDC | F25: 917.623 | G25: 1911.834 | H25: 3.573 | I25: 3.324 | J25: 38.539201 | K25: 353.737 | L25: 423.937 | M25: 403.79 | N25: 154.81278 | O25: 43.133768 | P25: 4.3839259 | Q25: 0.28686658 | R25: 0.33526696 | S25: 0.3124551 | T25: 0.0011439725 | U25: 0.31271441 | V25: 0.3084291 | W25: 1.1734954 | X25: 0 | Y25: 6.349233 | Z25: 21.728192 | AA25: 4.6596652 | AB25: 0.03726715 | AC25: 2.8183426 | AD25: 0.970332 | AE25: 0.90033 | AF25: 0.535461 | AG25: 0.591 | AH25: 0.51946289 | AI25: 8.462 | AJ25: 16.27536 | AK25: 6.682 | AL25: 8.6408916 | AM25: 21.653 | AN25: 28.66392 | AO25: 21.212 | AP25: 24.020605 | AQ25: 38.379041 | AR25: 0.45712134 | AS25: 0.66908654 | AT25: 2.3535459 | AU25: 0.37242984 | AV25: -0.005601 | AW25: 5.917777 | AX25: 0.227125 | AY25: 0.059902381 | AZ25: 0.092528 | BA25: 55.089 | BB25: 5.134 | BC25: 87.212 | BF25: 0 | BG25: 3.9 | BH25: 5.62 | BI25: 2020 | BJ25: 2 | BQ25: 2025 | BR25: 172.58 | BS25: 87.4 | BT25: 24.81 | BU25: 6.43 | BV25: =F25*(1+N(H25)/100)*(1+N(I25)/100)^5 -> 1119.2237 | BW25: =IF(N(G25)>0,G25,F25) -> 1911.834 | BX25: =F25/BW25 -> 0.47997002 | BY25: =IF(ISNUMBER(K25),1,0) -> 1 | BZ25: =IF(BY25=0,"",N(N25)+N(O25)+N(P25)) -> 202.33047 | CA25: =IF(BY25=0,"",(N(Y25)*34.2+N(Z25)*38.6)/1000) -> 1.055852 | CB25: =IF(BY25=0,"",N(O25)*0.0036+N(R25)+N(V25)+(N(AA25)*25.3+N(AB25)*37)/1000) -> 0.91824604 | CC25: =IF(BY25=0,"",N(N25)*0.0036+N(Q25)+N(U25)+N(T25)+N(X25)+N(AC25)*38/1000) -> 1.265148 | CD25: =IF(BY25=0,"",N(Q25)+N(R25)+N(S25)+N(T25)+N(U25)+N(V25)+N(W25)+N(X25)+(N(Y25)*34.2+N(Z25)*38.6+N(AA25)*25.3+N(AB25)*37+N(AC25)*38)/1000) -> 4.0125889 | CE25: =IF(BY25=0,"",MAX(0,N(L25)-N(K25))+MAX(0,N(M25)-N(L25))) -> 70.2 | CF25: =IF(BY25=0,"",N(Y25)*N(AD25)+N(Z25)*N(AE25)+N(AA25)*N(AF25)+N(AB25)*N(AG25)+N(AC25)*N(AH25)+N(U25)*N(AI25)+N(V25)*N(AJ25)+N(W25)*N(AK25)+N(X25)*N(AL25)+N(Q25)*N(AM25)+N(R25)*N(AN25)+N(S25)*N(AO25)+N(T25)*N(AP25)) -> 67.688669 | CG25: =IF(AND(BY25=1,N(K25)>0),K25,0) -> 353.737 | CH25: =IF(CG25>0,CF25*1000/CG25,"") -> 191.35309 | CI25: =IF(BY25=0,"",N(AQ25)+p_road*(N(AR25)+N(AS25)+N(AT25))) -> 38.379041 | CJ25: =IF(CG25>0,CI25*1000/CG25,"") -> 108.49598 | CK25: =IF(CH25="",1,MIN(p_idx_max,MAX(p_idx_min,CH25/p_fc_world))) -> 1.1884743 | CL25: =IF(CJ25="",1,MIN(p_idx_max,MAX(p_idx_min,CJ25/p_cb_world))) -> 2.0630222 | CM25: =p_b*(1-p_wb_idx+p_wb_idx*CK25) -> 0.15806708 | CN25: =p_c*(1-p_wc_idx+p_wc_idx*CL25) -> 0.26612986 | CO25: =IF(N(BR25)>0,(N(BS25)+N(BT25)+N(BU25))/BR25,"") -> 0.6874493 | CP25: =N(BS25)+N(BT25)+N(BU25) -> 118.64 | CQ25: =IF(CP25>0,N(BS25)/CP25,"") -> 0.7366824 | CR25: =IF(CP25>0,N(BT25)/CP25,"") -> 0.20912003 | CS25: =IF(CP25>0,N(BU25)/CP25,"") -> 0.054197572 | CT25: =1000*(p_sh_pv*p_cf_pv/p_capex_pv+(1-p_sh_pv)*p_cf_wind/p_capex_wind)*8760 -> 2301.2886 | CU25: =IF(AND(ISNUMBER(CO25),ISNUMBER(CQ25),BY25=1),1,0) -> 1 | CV25: =IF(CU25=0,"",CQ25*p_hr_coal*N(AK25)+CR25*p_hr_gas*N(AO25)+CS25*p_hr_oil*N(AH25)/p_gj_l_oil) -> 90.152393 | CW25: =IF(CU25=0,"",CQ25*p_hr_coal*p_ef_coal+CR25*p_hr_gas*p_ef_gas+CS25*p_hr_oil*p_ef_oil) -> 0.82893517 | CX25: =IF(CU25=0,"",CQ25*p_hr_coal*N(AW25)+CR25*p_hr_gas*N(AX25)+CS25*p_hr_oil*N(AY25)/p_gj_l_oil) -> 44.834577 | CY25: =IF(CU25=0,"",CO25*CW25) -> 0.5698509 | CZ25: =IF(CU25=0,"",CT25*CO25*CV25/1000/1000-p_om_re) -> 0.12762282 | DA25: =IF(CU25=0,"",CT25*CO25*CX25/1000/1000) -> 0.070929162 | DB25: =IF(CU25=0,"",CT25*CO25*CW25/1000) -> 1.3113914 | DC25: =IF(AND(CU25=1,ISNUMBER(AD25),ISNUMBER(AV25)),1,0) -> 1 | DD25: =IF(DC25=0,"",p_ev_km*p_ice_l/100*AD25-p_ev_km*p_ev_kwh*AV25+p_ev_km*p_ev_maint) -> 1286.7462 | DE25: =IF(DC25=0,"",DD25/p_ev_prem) -> 0.25734924 | DF25: =IF(DC25=0,"",p_ev_km*p_ice_l/100*N(AZ25)/p_ev_prem) -> 0.0208188 | DG25: =IF(DC25=0,"",1000/p_ev_prem*(p_ev_km*p_ice_l/100*p_gj_l_gso*p_ef_gso-p_ev_km*p_ev_kwh/1000*CY25)) -> 0.22554401 | DH25: =IFERROR(IF(INDEX(Damodaran!$D:$D,MATCH(A25,Damodaran!$A:$A,0))="","",INDEX(Damodaran!$D:$D,MATCH(A25,Damodaran!$A:$A,0))),"") | DI25: =IFERROR(IF(INDEX(Damodaran!$E:$E,MATCH(A25,Damodaran!$A:$A,0))="","",INDEX(Damodaran!$E:$E,MATCH(A25,Damodaran!$A:$A,0))),"") | DJ25: =IFERROR(IF(INDEX(Damodaran!$G:$G,MATCH(A25,Damodaran!$A:$A,0))="","",INDEX(Damodaran!$G:$G,MATCH(A25,Damodaran!$A:$A,0))),"") | DK25: =IF(ISNUMBER(BG25),(1+BG25/100)*(1+p_infl)-1,"") -> 0.05978 | DL25: =IF(ISNUMBER(BH25),BH25/100,"") -> 0.0562 | DM25: =IF(COUNT(DK25,DL25)=0,"",AVERAGE(DK25,DL25)) -> 0.05799 | DN25: =IF(OR(DH25="",DI25=""),"",p_dv*(p_rf+DH25)*(1-IF(DJ25="",p_tax_def,DJ25))+(1-p_dv)*(p_rf+p_beta*p_erp+p_lambda*DI25)) | DO25: =IF(AND(ISNUMBER(DM25),ISNUMBER(DN25)),1,0) -> 0 | DP25: =IF(DO25=1,DM25,0) -> 0 | DQ25: =IF(DO25=1,DN25,0) -> 0 | DR25: =IF(DN25="","",DN25+p_shift) | DS25: =IF(E25="AE",p_r_ae,IF(E25="China",p_r_chn,p_r_emdc)) -> 0.105 | DT25: =IF(E25="AE",p_rh_ae,IF(E25="China",p_rh_chn,p_rh_emdc)) -> 0.15 | DU25: =IF(AND(p_use_obs=1,ISNUMBER(DM25)),DM25,IF(AND(p_use_dam=1,ISNUMBER(DR25)),DR25,DS25)) -> 0.05799 | DV25: =IF(AND(p_use_obs=1,ISNUMBER(DM25)),"Observed (IRENA/Steffen)",IF(AND(p_use_dam=1,ISNUMBER(DR25)),"Damodaran (eq. 5)","Group default (IHLEG)")) -> Observed (IRENA/Steffen) | DW25: =IF(p_basis=1,(1+DU25)/(1+p_infl)-1,DU25) -> 0.05799 | DX25: =DW25+(DT25-DS25) -> 0.10299 | DY25: =IF(AND(p_use_pefa=1,ISNUMBER(BD25)),p_gap_lic-(BD25-1)/3*(p_gap_lic-p_gap_ae),IF(E25="AE",p_gap_ae,IF(D25="Low income",p_gap_lic,p_gap_em)))*(1-p_reform*p_reform_close) -> 0.27 | DZ25: =IF(AND(p_use_pefa=1,ISNUMBER(BD25)),"PEFA PI-11","Income-group default (IMF 2015)") -> Income-group default (IMF 2015) | EA25: =IF(E25="AE",p_ps_ae,IF(E25="China",p_ps_chn,p_ps_emdc)) -> 0.4 | EB25: =(1-EA25)+EA25/(1-DY25) -> 1.1479452 | EC25: =Results_Country!F25 -> 51.435154 | ED25: =IF(CH25="",0,CH25*EC25) -> 9842.2758 | EE25: =IF(CJ25="",0,CJ25*EC25) -> 5580.5072 | EF25: =IF(CH25="",0,EC25) -> 51.435154
A26: TWN | B26: Taiwan Province of China | C26: East Asia & Pacific | D26: High income | E26: AE | F26: 801.495 | G26: 1881.151 | H26: 8.676 | I26: 5.181 | BQ26: 2025 | BR26: 288.88 | BS26: 104.55 | BT26: 140.64 | BU26: 4.66 | BV26: =F26*(1+N(H26)/100)*(1+N(I26)/100)^5 -> 1121.2977 | BW26: =IF(N(G26)>0,G26,F26) -> 1881.151 | BX26: =F26/BW26 -> 0.42606628 | BY26: =IF(ISNUMBER(K26),1,0) -> 0 | BZ26: =IF(BY26=0,"",N(N26)+N(O26)+N(P26)) | CA26: =IF(BY26=0,"",(N(Y26)*34.2+N(Z26)*38.6)/1000) | CB26: =IF(BY26=0,"",N(O26)*0.0036+N(R26)+N(V26)+(N(AA26)*25.3+N(AB26)*37)/1000) | CC26: =IF(BY26=0,"",N(N26)*0.0036+N(Q26)+N(U26)+N(T26)+N(X26)+N(AC26)*38/1000) | CD26: =IF(BY26=0,"",N(Q26)+N(R26)+N(S26)+N(T26)+N(U26)+N(V26)+N(W26)+N(X26)+(N(Y26)*34.2+N(Z26)*38.6+N(AA26)*25.3+N(AB26)*37+N(AC26)*38)/1000) | CE26: =IF(BY26=0,"",MAX(0,N(L26)-N(K26))+MAX(0,N(M26)-N(L26))) | CF26: =IF(BY26=0,"",N(Y26)*N(AD26)+N(Z26)*N(AE26)+N(AA26)*N(AF26)+N(AB26)*N(AG26)+N(AC26)*N(AH26)+N(U26)*N(AI26)+N(V26)*N(AJ26)+N(W26)*N(AK26)+N(X26)*N(AL26)+N(Q26)*N(AM26)+N(R26)*N(AN26)+N(S26)*N(AO26)+N(T26)*N(AP26)) | CG26: =IF(AND(BY26=1,N(K26)>0),K26,0) -> 0 | CH26: =IF(CG26>0,CF26*1000/CG26,"") | CI26: =IF(BY26=0,"",N(AQ26)+p_road*(N(AR26)+N(AS26)+N(AT26))) | CJ26: =IF(CG26>0,CI26*1000/CG26,"") | CK26: =IF(CH26="",1,MIN(p_idx_max,MAX(p_idx_min,CH26/p_fc_world))) -> 1 | CL26: =IF(CJ26="",1,MIN(p_idx_max,MAX(p_idx_min,CJ26/p_cb_world))) -> 1 | CM26: =p_b*(1-p_wb_idx+p_wb_idx*CK26) -> 0.133 | CN26: =p_c*(1-p_wc_idx+p_wc_idx*CL26) -> 0.129 | CO26: =IF(N(BR26)>0,(N(BS26)+N(BT26)+N(BU26))/BR26,"") -> 0.864892 | CP26: =N(BS26)+N(BT26)+N(BU26) -> 249.85 | CQ26: =IF(CP26>0,N(BS26)/CP26,"") -> 0.41845107 | CR26: =IF(CP26>0,N(BT26)/CP26,"") -> 0.56289774 | CS26: =IF(CP26>0,N(BU26)/CP26,"") -> 0.018651191 | CT26: =1000*(p_sh_pv*p_cf_pv/p_capex_pv+(1-p_sh_pv)*p_cf_wind/p_capex_wind)*8760 -> 2301.2886 | CU26: =IF(AND(ISNUMBER(CO26),ISNUMBER(CQ26),BY26=1),1,0) -> 0 | CV26: =IF(CU26=0,"",CQ26*p_hr_coal*N(AK26)+CR26*p_hr_gas*N(AO26)+CS26*p_hr_oil*N(AH26)/p_gj_l_oil) | CW26: =IF(CU26=0,"",CQ26*p_hr_coal*p_ef_coal+CR26*p_hr_gas*p_ef_gas+CS26*p_hr_oil*p_ef_oil) | CX26: =IF(CU26=0,"",CQ26*p_hr_coal*N(AW26)+CR26*p_hr_gas*N(AX26)+CS26*p_hr_oil*N(AY26)/p_gj_l_oil) | CY26: =IF(CU26=0,"",CO26*CW26) | CZ26: =IF(CU26=0,"",CT26*CO26*CV26/1000/1000-p_om_re) | DA26: =IF(CU26=0,"",CT26*CO26*CX26/1000/1000) | DB26: =IF(CU26=0,"",CT26*CO26*CW26/1000) | DC26: =IF(AND(CU26=1,ISNUMBER(AD26),ISNUMBER(AV26)),1,0) -> 0 | DD26: =IF(DC26=0,"",p_ev_km*p_ice_l/100*AD26-p_ev_km*p_ev_kwh*AV26+p_ev_km*p_ev_maint) | DE26: =IF(DC26=0,"",DD26/p_ev_prem) | DF26: =IF(DC26=0,"",p_ev_km*p_ice_l/100*N(AZ26)/p_ev_prem) | DG26: =IF(DC26=0,"",1000/p_ev_prem*(p_ev_km*p_ice_l/100*p_gj_l_gso*p_ef_gso-p_ev_km*p_ev_kwh/1000*CY26)) | DH26: =IFERROR(IF(INDEX(Damodaran!$D:$D,MATCH(A26,Damodaran!$A:$A,0))="","",INDEX(Damodaran!$D:$D,MATCH(A26,Damodaran!$A:$A,0))),"") | DI26: =IFERROR(IF(INDEX(Damodaran!$E:$E,MATCH(A26,Damodaran!$A:$A,0))="","",INDEX(Damodaran!$E:$E,MATCH(A26,Damodaran!$A:$A,0))),"") | DJ26: =IFERROR(IF(INDEX(Damodaran!$G:$G,MATCH(A26,Damodaran!$A:$A,0))="","",INDEX(Damodaran!$G:$G,MATCH(A26,Damodaran!$A:$A,0))),"") | DK26: =IF(ISNUMBER(BG26),(1+BG26/100)*(1+p_infl)-1,"") | DL26: =IF(ISNUMBER(BH26),BH26/100,"") | DM26: =IF(COUNT(DK26,DL26)=0,"",AVERAGE(DK26,DL26)) | DN26: =IF(OR(DH26="",DI26=""),"",p_dv*(p_rf+DH26)*(1-IF(DJ26="",p_tax_def,DJ26))+(1-p_dv)*(p_rf+p_beta*p_erp+p_lambda*DI26)) | DO26: =IF(AND(ISNUMBER(DM26),ISNUMBER(DN26)),1,0) -> 0 | DP26: =IF(DO26=1,DM26,0) -> 0 | DQ26: =IF(DO26=1,DN26,0) -> 0 | DR26: =IF(DN26="","",DN26+p_shift) | DS26: =IF(E26="AE",p_r_ae,IF(E26="China",p_r_chn,p_r_emdc)) -> 0.055 | DT26: =IF(E26="AE",p_rh_ae,IF(E26="China",p_rh_chn,p_rh_emdc)) -> 0.07 | DU26: =IF(AND(p_use_obs=1,ISNUMBER(DM26)),DM26,IF(AND(p_use_dam=1,ISNUMBER(DR26)),DR26,DS26)) -> 0.055 | DV26: =IF(AND(p_use_obs=1,ISNUMBER(DM26)),"Observed (IRENA/Steffen)",IF(AND(p_use_dam=1,ISNUMBER(DR26)),"Damodaran (eq. 5)","Group default (IHLEG)")) -> Group default (IHLEG) | DW26: =IF(p_basis=1,(1+DU26)/(1+p_infl)-1,DU26) -> 0.055 | DX26: =DW26+(DT26-DS26) -> 0.07 | DY26: =IF(AND(p_use_pefa=1,ISNUMBER(BD26)),p_gap_lic-(BD26-1)/3*(p_gap_lic-p_gap_ae),IF(E26="AE",p_gap_ae,IF(D26="Low income",p_gap_lic,p_gap_em)))*(1-p_reform*p_reform_close) -> 0.13 | DZ26: =IF(AND(p_use_pefa=1,ISNUMBER(BD26)),"PEFA PI-11","Income-group default (IMF 2015)") -> Income-group default (IMF 2015) | EA26: =IF(E26="AE",p_ps_ae,IF(E26="China",p_ps_chn,p_ps_emdc)) -> 0.3 | EB26: =(1-EA26)+EA26/(1-DY26) -> 1.0448276 | EC26: =Results_Country!F26 -> 40.395093 | ED26: =IF(CH26="",0,CH26*EC26) -> 0 | EE26: =IF(CJ26="",0,CJ26*EC26) -> 0 | EF26: =IF(CH26="",0,EC26) -> 0
