Workbook
Name ELAST: _xlfn.LAMBDA(_xlpm.kind,_xlpm.fuel,_xlpm.group,INDEX(Data_Elast!$D:$G, MATCH(_xlpm.kind&"_"&_xlpm.fuel, Data_Elast!$A:$A, 0), MATCH(_xlpm.group, Data_Elast!$D$1:$G$1, 0)))
Name OUTCODE: _xlfn.LAMBDA(_xlpm.country,_xlpm.vname,_xlpm.sector,_xlpm.fuel,_xlpm.scen,_xlpm.country&".mit."&_xlpm.vname&"."&_xlpm.sector&"."&_xlpm.fuel&".e."&_xlpm.scen)
Name POSTTAX: _xlfn.LAMBDA(_xlpm.ptp,_xlpm.nce,_xlpm.tcf,_xlpm.ptp+_xlpm.nce*_xlpm.tcf)
Name SHADOW: _xlfn.LAMBDA(_xlpm.atp,_xlpm.sigma,_xlpm.ssc,_xlpm.atp+_xlpm.sigma*_xlpm.ssc)

Sheet Settings
A1: CPAT industry kernel - Egypt prototype v0.2 (LAMBDA build)
A3: Country code | B3: egy | C3: First component of every code; CPAT convention (egy.mit.<var>.<sector>.<fuel>.<type>.<scenario>)
A4: Price group for industry sectors | B4: ind | C4: C2 retail-price group the four sectors read (pow / res / ind / tra)
A5: Elasticity column | B5: Industries | C5: Column of the master elasticity table (Transport / Residential / Industries / Services)
A6: Base year | B6: 2022 | C6: MTInputs FirstYearCalculations; energy in the base year is read from Data_Energy, later years from the kernel
A7: Additional policy-induced efficiency (alpha+) | B7: =INDEX(MTInputs!$F$8:$F$415,MATCH("AdditionalEfficiencyIndustrial",MTInputs!$H$8:$H$415,0)) -> 0 | C7: Read from the MTInputs column by NameOfParameter; this is the only MTInputs dependency of the kernel rows
A8: Carbon price start year (info) | B8: =INDEX(MTInputs!$F$8:$F$415,MATCH("CPIntro",MTInputs!$H$8:$H$415,0)) -> 2026 | C8: For reference: the policy scenario new-policy wedge (nce) starts here
A9: Carbon price target (info) | B9: =INDEX(MTInputs!$F$8:$F$415,MATCH("CPLevelTarget",MTInputs!$H$8:$H$415,0)) -> 50 | C9: $/tCO2
A12: Kernel (every energy cell, year t >= 2023):
A13: F(t) = F(t-1) * (1+g)^(eY*delta) * (1+psi) * (p(t)/p(t-1))^eU * [ (s(t)/s(t-1))^eF / (1 + a + a+) ]^(1+eU)
A14: p = post-tax price (atp), s = shadow price (shp) = atp + sigma*ssc, g = post-policy GDP growth, delta = income-elasticity discount, psi = exogenous shock
A16: Sheets
A17: Mitigation_Industry | C17: Kernel sheet in the CPAT Mitigation layout (columns A-AI, years K-AI): 4 CBAM sectors x 2 scenarios. All formulas; codes built from components.
A18: MTInputs | C18: The 415-row CPAT parameter column, copied unchanged (columns A-I of the MTInputs sheet).
A19: Data_Energy | C19: Base-year energy matrix, fuel x sector, ktoe (Mitigation B4 rows 583-602).
A20: Data_Prices | C20: Pre-tax price before new policies (pbc), new-policy wedge (nce), shadow price (shp), sector coverage (tcf), share of shadow price on efficiency (ssc); both scenarios.
A21: Data_Macro | C21: GDP growth, income-elasticity discount factor, exogenous shock; both scenarios.
A22: Data_Elast | C22: Master elasticity table (income, usage, efficiency, AEEI) by fuel group x sector group, plus the fuel-group map.
A23: Check | C23: Kernel output against the values stored in CPAT_1_0pre_456 for the same rows; max absolute and relative differences.

Sheet Mitigation_Industry
B1: Fuel | C1: Sector | D1: Description | E1: Unit | F1: Source | G1: Input Code | H1: Output Code | I1: Note | J1: Helper | K1: 2021 | L1: 2022 | M1: 2023 | N1: 2024 | O1: 2025 | P1: 2026 | Q1: 2027 | R1: 2028 | S1: 2029 | T1: 2030 | U1: 2031 | V1: 2032 | W1: 2033 | X1: 2034 | Y1: 2035 | Z1: 2036 | AA1: 2037 | AB1: 2038 | AC1: 2039 | AD1: 2040 | AE1: 2041 | AF1: 2042 | AG1: 2043 | AH1: 2044 | AI1: 2045
A3: 7 | B3: Industrial sector - Baseline (CBAM sectors: iron and steel, cement, non-ferrous metals, mining & chemicals)
B5: Iron and steel | C5: irn | D5: Fuel Type | E5: Unit | F5: Variable Code | G5: Input Code (data-table key) | H5: Output Code | I5: Scenario | J5: 1 | K5: 2021 | L5: 2022 | M5: 2023 | N5: 2024 | O5: 2025 | P5: 2026 | Q5: 2027 | R5: 2028 | S5: 2029 | T5: 2030 | U5: 2031 | V5: 2032 | W5: 2033 | X5: 2034 | Y5: 2035 | Z5: 2036 | AA5: 2037 | AB5: 2038 | AC5: 2039 | AD5: 2040 | AE5: 2041 | AF5: 2042 | AG5: 2043 | AH5: 2044 | AI5: 2045
B6: Pre-tax price: price before any new policy (supply cost + VAT + existing excise, subsidies and carbon prices)
B7: coa | C7: =$C$5 -> irn | D7: Coal | E7: $/GJ | F7: ptp | G7: =Settings!$B$3&".mit.pbc."&Settings!$B$4&"."&$B7&".a."&$J$5 -> egy.mit.pbc.ind.coa.a.1 | H7: =OUTCODE(Settings!$B$3,"ptp",$C$5,$B7,$J$5) -> egy.mit.ptp.irn.coa.e.1 | K7: =INDEX(Data_Prices!K:K,MATCH($G7,Data_Prices!$A:$A,0)) -> 11.182902 | L7: =INDEX(Data_Prices!L:L,MATCH($G7,Data_Prices!$A:$A,0)) -> 10.523361 | M7: =INDEX(Data_Prices!M:M,MATCH($G7,Data_Prices!$A:$A,0)) -> 10.299561 | N7: =INDEX(Data_Prices!N:N,MATCH($G7,Data_Prices!$A:$A,0)) -> 9.5775284 | O7: =INDEX(Data_Prices!O:O,MATCH($G7,Data_Prices!$A:$A,0)) -> 8.4854783 | P7: =INDEX(Data_Prices!P:P,MATCH($G7,Data_Prices!$A:$A,0)) -> 9.0871922 | Q7: =INDEX(Data_Prices!Q:Q,MATCH($G7,Data_Prices!$A:$A,0)) -> 9.2229237 | R7: =INDEX(Data_Prices!R:R,MATCH($G7,Data_Prices!$A:$A,0)) -> 9.158565 | S7: =INDEX(Data_Prices!S:S,MATCH($G7,Data_Prices!$A:$A,0)) -> 9.0895479 | T7: =INDEX(Data_Prices!T:T,MATCH($G7,Data_Prices!$A:$A,0)) -> 9.0156817 | U7: =INDEX(Data_Prices!U:U,MATCH($G7,Data_Prices!$A:$A,0)) -> 8.9443978 | V7: =INDEX(Data_Prices!V:V,MATCH($G7,Data_Prices!$A:$A,0)) -> 8.9443978 | W7: =INDEX(Data_Prices!W:W,MATCH($G7,Data_Prices!$A:$A,0)) -> 8.9443978 | X7: =INDEX(Data_Prices!X:X,MATCH($G7,Data_Prices!$A:$A,0)) -> 8.9443978 | Y7: =INDEX(Data_Prices!Y:Y,MATCH($G7,Data_Prices!$A:$A,0)) -> 8.9443978 | Z7: =INDEX(Data_Prices!Z:Z,MATCH($G7,Data_Prices!$A:$A,0)) -> 8.9443978 | AA7: =INDEX(Data_Prices!AA:AA,MATCH($G7,Data_Prices!$A:$A,0)) -> 8.9443978 | AB7: =INDEX(Data_Prices!AB:AB,MATCH($G7,Data_Prices!$A:$A,0)) -> 8.9443978 | AC7: =INDEX(Data_Prices!AC:AC,MATCH($G7,Data_Prices!$A:$A,0)) -> 8.9443978 | AD7: =INDEX(Data_Prices!AD:AD,MATCH($G7,Data_Prices!$A:$A,0)) -> 8.9443978 | AE7: =INDEX(Data_Prices!AE:AE,MATCH($G7,Data_Prices!$A:$A,0)) -> 8.9443978
B8: nga | C8: =$C$5 -> irn | D8: Natural gas | E8: $/GJ | F8: ptp | G8: =Settings!$B$3&".mit.pbc."&Settings!$B$4&"."&$B8&".a."&$J$5 -> egy.mit.pbc.ind.nga.a.1 | H8: =OUTCODE(Settings!$B$3,"ptp",$C$5,$B8,$J$5) -> egy.mit.ptp.irn.nga.e.1 | K8: =INDEX(Data_Prices!K:K,MATCH($G8,Data_Prices!$A:$A,0)) -> 6.0634636 | L8: =INDEX(Data_Prices!L:L,MATCH($G8,Data_Prices!$A:$A,0)) -> 5.4510151 | M8: =INDEX(Data_Prices!M:M,MATCH($G8,Data_Prices!$A:$A,0)) -> 5.1193563 | N8: =INDEX(Data_Prices!N:N,MATCH($G8,Data_Prices!$A:$A,0)) -> 5.0821846 | O8: =INDEX(Data_Prices!O:O,MATCH($G8,Data_Prices!$A:$A,0)) -> 5.0821846 | P8: =INDEX(Data_Prices!P:P,MATCH($G8,Data_Prices!$A:$A,0)) -> 5.0821846 | Q8: =INDEX(Data_Prices!Q:Q,MATCH($G8,Data_Prices!$A:$A,0)) -> 5.0821846 | R8: =INDEX(Data_Prices!R:R,MATCH($G8,Data_Prices!$A:$A,0)) -> 5.0821846 | S8: =INDEX(Data_Prices!S:S,MATCH($G8,Data_Prices!$A:$A,0)) -> 5.0821846 | T8: =INDEX(Data_Prices!T:T,MATCH($G8,Data_Prices!$A:$A,0)) -> 5.0821846 | U8: =INDEX(Data_Prices!U:U,MATCH($G8,Data_Prices!$A:$A,0)) -> 5.0821846 | V8: =INDEX(Data_Prices!V:V,MATCH($G8,Data_Prices!$A:$A,0)) -> 5.0821846 | W8: =INDEX(Data_Prices!W:W,MATCH($G8,Data_Prices!$A:$A,0)) -> 5.0821846 | X8: =INDEX(Data_Prices!X:X,MATCH($G8,Data_Prices!$A:$A,0)) -> 5.0821846 | Y8: =INDEX(Data_Prices!Y:Y,MATCH($G8,Data_Prices!$A:$A,0)) -> 5.0821846 | Z8: =INDEX(Data_Prices!Z:Z,MATCH($G8,Data_Prices!$A:$A,0)) -> 5.0821846 | AA8: =INDEX(Data_Prices!AA:AA,MATCH($G8,Data_Prices!$A:$A,0)) -> 5.0821846 | AB8: =INDEX(Data_Prices!AB:AB,MATCH($G8,Data_Prices!$A:$A,0)) -> 5.0821846 | AC8: =INDEX(Data_Prices!AC:AC,MATCH($G8,Data_Prices!$A:$A,0)) -> 5.0821846 | AD8: =INDEX(Data_Prices!AD:AD,MATCH($G8,Data_Prices!$A:$A,0)) -> 5.0821846 | AE8: =INDEX(Data_Prices!AE:AE,MATCH($G8,Data_Prices!$A:$A,0)) -> 5.0821846
B9: gso | C9: =$C$5 -> irn | D9: Gasoline | E9: $/liter | F9: ptp | G9: =Settings!$B$3&".mit.pbc."&Settings!$B$4&"."&$B9&".a."&$J$5 -> egy.mit.pbc.ind.gso.a.1 | H9: =OUTCODE(Settings!$B$3,"ptp",$C$5,$B9,$J$5) -> egy.mit.ptp.irn.gso.e.1 | K9: =INDEX(Data_Prices!K:K,MATCH($G9,Data_Prices!$A:$A,0)) -> 0.67114653 | L9: =INDEX(Data_Prices!L:L,MATCH($G9,Data_Prices!$A:$A,0)) -> 0.61197798 | M9: =INDEX(Data_Prices!M:M,MATCH($G9,Data_Prices!$A:$A,0)) -> 0.61180975 | N9: =INDEX(Data_Prices!N:N,MATCH($G9,Data_Prices!$A:$A,0)) -> 0.6035831 | O9: =INDEX(Data_Prices!O:O,MATCH($G9,Data_Prices!$A:$A,0)) -> 0.6035831 | P9: =INDEX(Data_Prices!P:P,MATCH($G9,Data_Prices!$A:$A,0)) -> 0.6035831 | Q9: =INDEX(Data_Prices!Q:Q,MATCH($G9,Data_Prices!$A:$A,0)) -> 0.6035831 | R9: =INDEX(Data_Prices!R:R,MATCH($G9,Data_Prices!$A:$A,0)) -> 0.6035831 | S9: =INDEX(Data_Prices!S:S,MATCH($G9,Data_Prices!$A:$A,0)) -> 0.6035831 | T9: =INDEX(Data_Prices!T:T,MATCH($G9,Data_Prices!$A:$A,0)) -> 0.6035831 | U9: =INDEX(Data_Prices!U:U,MATCH($G9,Data_Prices!$A:$A,0)) -> 0.6035831 | V9: =INDEX(Data_Prices!V:V,MATCH($G9,Data_Prices!$A:$A,0)) -> 0.6035831 | W9: =INDEX(Data_Prices!W:W,MATCH($G9,Data_Prices!$A:$A,0)) -> 0.6035831 | X9: =INDEX(Data_Prices!X:X,MATCH($G9,Data_Prices!$A:$A,0)) -> 0.6035831 | Y9: =INDEX(Data_Prices!Y:Y,MATCH($G9,Data_Prices!$A:$A,0)) -> 0.6035831 | Z9: =INDEX(Data_Prices!Z:Z,MATCH($G9,Data_Prices!$A:$A,0)) -> 0.6035831 | AA9: =INDEX(Data_Prices!AA:AA,MATCH($G9,Data_Prices!$A:$A,0)) -> 0.6035831 | AB9: =INDEX(Data_Prices!AB:AB,MATCH($G9,Data_Prices!$A:$A,0)) -> 0.6035831 | AC9: =INDEX(Data_Prices!AC:AC,MATCH($G9,Data_Prices!$A:$A,0)) -> 0.6035831 | AD9: =INDEX(Data_Prices!AD:AD,MATCH($G9,Data_Prices!$A:$A,0)) -> 0.6035831 | AE9: =INDEX(Data_Prices!AE:AE,MATCH($G9,Data_Prices!$A:$A,0)) -> 0.6035831
B10: die | C10: =$C$5 -> irn | D10: Diesel | E10: $/liter | F10: ptp | G10: =Settings!$B$3&".mit.pbc."&Settings!$B$4&"."&$B10&".a."&$J$5 -> egy.mit.pbc.ind.die.a.1 | H10: =OUTCODE(Settings!$B$3,"ptp",$C$5,$B10,$J$5) -> egy.mit.ptp.irn.die.e.1 | K10: =INDEX(Data_Prices!K:K,MATCH($G10,Data_Prices!$A:$A,0)) -> 0.55971121 | L10: =INDEX(Data_Prices!L:L,MATCH($G10,Data_Prices!$A:$A,0)) -> 0.49458873 | M10: =INDEX(Data_Prices!M:M,MATCH($G10,Data_Prices!$A:$A,0)) -> 0.50778655 | N10: =INDEX(Data_Prices!N:N,MATCH($G10,Data_Prices!$A:$A,0)) -> 0.47043643 | O10: =INDEX(Data_Prices!O:O,MATCH($G10,Data_Prices!$A:$A,0)) -> 0.47043643 | P10: =INDEX(Data_Prices!P:P,MATCH($G10,Data_Prices!$A:$A,0)) -> 0.47043643 | Q10: =INDEX(Data_Prices!Q:Q,MATCH($G10,Data_Prices!$A:$A,0)) -> 0.47043643 | R10: =INDEX(Data_Prices!R:R,MATCH($G10,Data_Prices!$A:$A,0)) -> 0.47043643 | S10: =INDEX(Data_Prices!S:S,MATCH($G10,Data_Prices!$A:$A,0)) -> 0.47043643 | T10: =INDEX(Data_Prices!T:T,MATCH($G10,Data_Prices!$A:$A,0)) -> 0.47043643 | U10: =INDEX(Data_Prices!U:U,MATCH($G10,Data_Prices!$A:$A,0)) -> 0.47043643 | V10: =INDEX(Data_Prices!V:V,MATCH($G10,Data_Prices!$A:$A,0)) -> 0.47043643 | W10: =INDEX(Data_Prices!W:W,MATCH($G10,Data_Prices!$A:$A,0)) -> 0.47043643 | X10: =INDEX(Data_Prices!X:X,MATCH($G10,Data_Prices!$A:$A,0)) -> 0.47043643 | Y10: =INDEX(Data_Prices!Y:Y,MATCH($G10,Data_Prices!$A:$A,0)) -> 0.47043643 | Z10: =INDEX(Data_Prices!Z:Z,MATCH($G10,Data_Prices!$A:$A,0)) -> 0.47043643 | AA10: =INDEX(Data_Prices!AA:AA,MATCH($G10,Data_Prices!$A:$A,0)) -> 0.47043643 | AB10: =INDEX(Data_Prices!AB:AB,MATCH($G10,Data_Prices!$A:$A,0)) -> 0.47043643 | AC10: =INDEX(Data_Prices!AC:AC,MATCH($G10,Data_Prices!$A:$A,0)) -> 0.47043643 | AD10: =INDEX(Data_Prices!AD:AD,MATCH($G10,Data_Prices!$A:$A,0)) -> 0.47043643 | AE10: =INDEX(Data_Prices!AE:AE,MATCH($G10,Data_Prices!$A:$A,0)) -> 0.47043643
B11: lpg | C11: =$C$5 -> irn | D11: LPG | E11: $/liter | F11: ptp | G11: =Settings!$B$3&".mit.pbc."&Settings!$B$4&"."&$B11&".a."&$J$5 -> egy.mit.pbc.ind.lpg.a.1 | H11: =OUTCODE(Settings!$B$3,"ptp",$C$5,$B11,$J$5) -> egy.mit.ptp.irn.lpg.e.1 | K11: =INDEX(Data_Prices!K:K,MATCH($G11,Data_Prices!$A:$A,0)) -> 0.20036669 | L11: =INDEX(Data_Prices!L:L,MATCH($G11,Data_Prices!$A:$A,0)) -> 0.15734474 | M11: =INDEX(Data_Prices!M:M,MATCH($G11,Data_Prices!$A:$A,0)) -> 0.16448404 | N11: =INDEX(Data_Prices!N:N,MATCH($G11,Data_Prices!$A:$A,0)) -> 0.15070908 | O11: =INDEX(Data_Prices!O:O,MATCH($G11,Data_Prices!$A:$A,0)) -> 0.15070908 | P11: =INDEX(Data_Prices!P:P,MATCH($G11,Data_Prices!$A:$A,0)) -> 0.15070908 | Q11: =INDEX(Data_Prices!Q:Q,MATCH($G11,Data_Prices!$A:$A,0)) -> 0.15070908 | R11: =INDEX(Data_Prices!R:R,MATCH($G11,Data_Prices!$A:$A,0)) -> 0.15070908 | S11: =INDEX(Data_Prices!S:S,MATCH($G11,Data_Prices!$A:$A,0)) -> 0.15070908 | T11: =INDEX(Data_Prices!T:T,MATCH($G11,Data_Prices!$A:$A,0)) -> 0.15070908 | U11: =INDEX(Data_Prices!U:U,MATCH($G11,Data_Prices!$A:$A,0)) -> 0.15070908 | V11: =INDEX(Data_Prices!V:V,MATCH($G11,Data_Prices!$A:$A,0)) -> 0.15070908 | W11: =INDEX(Data_Prices!W:W,MATCH($G11,Data_Prices!$A:$A,0)) -> 0.15070908 | X11: =INDEX(Data_Prices!X:X,MATCH($G11,Data_Prices!$A:$A,0)) -> 0.15070908 | Y11: =INDEX(Data_Prices!Y:Y,MATCH($G11,Data_Prices!$A:$A,0)) -> 0.15070908 | Z11: =INDEX(Data_Prices!Z:Z,MATCH($G11,Data_Prices!$A:$A,0)) -> 0.15070908 | AA11: =INDEX(Data_Prices!AA:AA,MATCH($G11,Data_Prices!$A:$A,0)) -> 0.15070908 | AB11: =INDEX(Data_Prices!AB:AB,MATCH($G11,Data_Prices!$A:$A,0)) -> 0.15070908 | AC11: =INDEX(Data_Prices!AC:AC,MATCH($G11,Data_Prices!$A:$A,0)) -> 0.15070908 | AD11: =INDEX(Data_Prices!AD:AD,MATCH($G11,Data_Prices!$A:$A,0)) -> 0.15070908 | AE11: =INDEX(Data_Prices!AE:AE,MATCH($G11,Data_Prices!$A:$A,0)) -> 0.15070908
B12: ker | C12: =$C$5 -> irn | D12: Kerosene | E12: $/liter | F12: ptp | G12: =Settings!$B$3&".mit.pbc."&Settings!$B$4&"."&$B12&".a."&$J$5 -> egy.mit.pbc.ind.ker.a.1 | H12: =OUTCODE(Settings!$B$3,"ptp",$C$5,$B12,$J$5) -> egy.mit.ptp.irn.ker.e.1 | K12: =INDEX(Data_Prices!K:K,MATCH($G12,Data_Prices!$A:$A,0)) -> 0.48429424 | L12: =INDEX(Data_Prices!L:L,MATCH($G12,Data_Prices!$A:$A,0)) -> 0.45642817 | M12: =INDEX(Data_Prices!M:M,MATCH($G12,Data_Prices!$A:$A,0)) -> 0.4316892 | N12: =INDEX(Data_Prices!N:N,MATCH($G12,Data_Prices!$A:$A,0)) -> 0.42507558 | O12: =INDEX(Data_Prices!O:O,MATCH($G12,Data_Prices!$A:$A,0)) -> 0.42507558 | P12: =INDEX(Data_Prices!P:P,MATCH($G12,Data_Prices!$A:$A,0)) -> 0.42507558 | Q12: =INDEX(Data_Prices!Q:Q,MATCH($G12,Data_Prices!$A:$A,0)) -> 0.42507558 | R12: =INDEX(Data_Prices!R:R,MATCH($G12,Data_Prices!$A:$A,0)) -> 0.42507558 | S12: =INDEX(Data_Prices!S:S,MATCH($G12,Data_Prices!$A:$A,0)) -> 0.42507558 | T12: =INDEX(Data_Prices!T:T,MATCH($G12,Data_Prices!$A:$A,0)) -> 0.42507558 | U12: =INDEX(Data_Prices!U:U,MATCH($G12,Data_Prices!$A:$A,0)) -> 0.42507558 | V12: =INDEX(Data_Prices!V:V,MATCH($G12,Data_Prices!$A:$A,0)) -> 0.42507558 | W12: =INDEX(Data_Prices!W:W,MATCH($G12,Data_Prices!$A:$A,0)) -> 0.42507558 | X12: =INDEX(Data_Prices!X:X,MATCH($G12,Data_Prices!$A:$A,0)) -> 0.42507558 | Y12: =INDEX(Data_Prices!Y:Y,MATCH($G12,Data_Prices!$A:$A,0)) -> 0.42507558 | Z12: =INDEX(Data_Prices!Z:Z,MATCH($G12,Data_Prices!$A:$A,0)) -> 0.42507558 | AA12: =INDEX(Data_Prices!AA:AA,MATCH($G12,Data_Prices!$A:$A,0)) -> 0.42507558 | AB12: =INDEX(Data_Prices!AB:AB,MATCH($G12,Data_Prices!$A:$A,0)) -> 0.42507558 | AC12: =INDEX(Data_Prices!AC:AC,MATCH($G12,Data_Prices!$A:$A,0)) -> 0.42507558 | AD12: =INDEX(Data_Prices!AD:AD,MATCH($G12,Data_Prices!$A:$A,0)) -> 0.42507558 | AE12: =INDEX(Data_Prices!AE:AE,MATCH($G12,Data_Prices!$A:$A,0)) -> 0.42507558
B13: oop | C13: =$C$5 -> irn | D13: Other oil products | E13: $/bbl | F13: ptp | G13: =Settings!$B$3&".mit.pbc."&Settings!$B$4&"."&$B13&".a."&$J$5 -> egy.mit.pbc.ind.oop.a.1 | H13: =OUTCODE(Settings!$B$3,"ptp",$C$5,$B13,$J$5) -> egy.mit.ptp.irn.oop.e.1 | K13: =INDEX(Data_Prices!K:K,MATCH($G13,Data_Prices!$A:$A,0)) -> 41.500338 | L13: =INDEX(Data_Prices!L:L,MATCH($G13,Data_Prices!$A:$A,0)) -> 34.41537 | M13: =INDEX(Data_Prices!M:M,MATCH($G13,Data_Prices!$A:$A,0)) -> 37.368961 | N13: =INDEX(Data_Prices!N:N,MATCH($G13,Data_Prices!$A:$A,0)) -> 28.982761 | O13: =INDEX(Data_Prices!O:O,MATCH($G13,Data_Prices!$A:$A,0)) -> 15 | P13: =INDEX(Data_Prices!P:P,MATCH($G13,Data_Prices!$A:$A,0)) -> 24.25863 | Q13: =INDEX(Data_Prices!Q:Q,MATCH($G13,Data_Prices!$A:$A,0)) -> 15 | R13: =INDEX(Data_Prices!R:R,MATCH($G13,Data_Prices!$A:$A,0)) -> 15 | S13: =INDEX(Data_Prices!S:S,MATCH($G13,Data_Prices!$A:$A,0)) -> 15 | T13: =INDEX(Data_Prices!T:T,MATCH($G13,Data_Prices!$A:$A,0)) -> 15 | U13: =INDEX(Data_Prices!U:U,MATCH($G13,Data_Prices!$A:$A,0)) -> 15 | V13: =INDEX(Data_Prices!V:V,MATCH($G13,Data_Prices!$A:$A,0)) -> 15 | W13: =INDEX(Data_Prices!W:W,MATCH($G13,Data_Prices!$A:$A,0)) -> 15 | X13: =INDEX(Data_Prices!X:X,MATCH($G13,Data_Prices!$A:$A,0)) -> 15 | Y13: =INDEX(Data_Prices!Y:Y,MATCH($G13,Data_Prices!$A:$A,0)) -> 15 | Z13: =INDEX(Data_Prices!Z:Z,MATCH($G13,Data_Prices!$A:$A,0)) -> 15 | AA13: =INDEX(Data_Prices!AA:AA,MATCH($G13,Data_Prices!$A:$A,0)) -> 15 | AB13: =INDEX(Data_Prices!AB:AB,MATCH($G13,Data_Prices!$A:$A,0)) -> 15 | AC13: =INDEX(Data_Prices!AC:AC,MATCH($G13,Data_Prices!$A:$A,0)) -> 15 | AD13: =INDEX(Data_Prices!AD:AD,MATCH($G13,Data_Prices!$A:$A,0)) -> 15 | AE13: =INDEX(Data_Prices!AE:AE,MATCH($G13,Data_Prices!$A:$A,0)) -> 15
B14: bio | C14: =$C$5 -> irn | D14: Biomass | E14: $/GJ | F14: ptp | G14: =Settings!$B$3&".mit.pbc."&Settings!$B$4&"."&$B14&".a."&$J$5 -> egy.mit.pbc.ind.bio.a.1 | H14: =OUTCODE(Settings!$B$3,"ptp",$C$5,$B14,$J$5) -> egy.mit.ptp.irn.bio.e.1 | K14: =INDEX(Data_Prices!K:K,MATCH($G14,Data_Prices!$A:$A,0)) -> 15.334551 | L14: =INDEX(Data_Prices!L:L,MATCH($G14,Data_Prices!$A:$A,0)) -> 14.199528 | M14: =INDEX(Data_Prices!M:M,MATCH($G14,Data_Prices!$A:$A,0)) -> 13.840442 | N14: =INDEX(Data_Prices!N:N,MATCH($G14,Data_Prices!$A:$A,0)) -> 13.567727 | O14: =INDEX(Data_Prices!O:O,MATCH($G14,Data_Prices!$A:$A,0)) -> 13.567727 | P14: =INDEX(Data_Prices!P:P,MATCH($G14,Data_Prices!$A:$A,0)) -> 13.567727 | Q14: =INDEX(Data_Prices!Q:Q,MATCH($G14,Data_Prices!$A:$A,0)) -> 13.567727 | R14: =INDEX(Data_Prices!R:R,MATCH($G14,Data_Prices!$A:$A,0)) -> 13.567727 | S14: =INDEX(Data_Prices!S:S,MATCH($G14,Data_Prices!$A:$A,0)) -> 13.567727 | T14: =INDEX(Data_Prices!T:T,MATCH($G14,Data_Prices!$A:$A,0)) -> 13.567727 | U14: =INDEX(Data_Prices!U:U,MATCH($G14,Data_Prices!$A:$A,0)) -> 13.567727 | V14: =INDEX(Data_Prices!V:V,MATCH($G14,Data_Prices!$A:$A,0)) -> 13.567727 | W14: =INDEX(Data_Prices!W:W,MATCH($G14,Data_Prices!$A:$A,0)) -> 13.567727 | X14: =INDEX(Data_Prices!X:X,MATCH($G14,Data_Prices!$A:$A,0)) -> 13.567727 | Y14: =INDEX(Data_Prices!Y:Y,MATCH($G14,Data_Prices!$A:$A,0)) -> 13.567727 | Z14: =INDEX(Data_Prices!Z:Z,MATCH($G14,Data_Prices!$A:$A,0)) -> 13.567727 | AA14: =INDEX(Data_Prices!AA:AA,MATCH($G14,Data_Prices!$A:$A,0)) -> 13.567727 | AB14: =INDEX(Data_Prices!AB:AB,MATCH($G14,Data_Prices!$A:$A,0)) -> 13.567727 | AC14: =INDEX(Data_Prices!AC:AC,MATCH($G14,Data_Prices!$A:$A,0)) -> 13.567727 | AD14: =INDEX(Data_Prices!AD:AD,MATCH($G14,Data_Prices!$A:$A,0)) -> 13.567727 | AE14: =INDEX(Data_Prices!AE:AE,MATCH($G14,Data_Prices!$A:$A,0)) -> 13.567727
B15: ren | C15: =$C$5 -> irn | D15: Self-generated renewables | E15: $/kwh | F15: ptp | G15: =Settings!$B$3&".mit.pbc."&Settings!$B$4&"."&$B15&".a."&$J$5 -> egy.mit.pbc.ind.ren.a.1 | H15: =OUTCODE(Settings!$B$3,"ptp",$C$5,$B15,$J$5) -> egy.mit.ptp.irn.ren.e.1 | K15: =INDEX(Data_Prices!K:K,MATCH($G15,Data_Prices!$A:$A,0)) -> 0 | L15: =INDEX(Data_Prices!L:L,MATCH($G15,Data_Prices!$A:$A,0)) -> 0.14404499 | M15: =INDEX(Data_Prices!M:M,MATCH($G15,Data_Prices!$A:$A,0)) -> 0.14102041 | N15: =INDEX(Data_Prices!N:N,MATCH($G15,Data_Prices!$A:$A,0)) -> 0.13511636 | O15: =INDEX(Data_Prices!O:O,MATCH($G15,Data_Prices!$A:$A,0)) -> 0.13098826 | P15: =INDEX(Data_Prices!P:P,MATCH($G15,Data_Prices!$A:$A,0)) -> 0.12790842 | Q15: =INDEX(Data_Prices!Q:Q,MATCH($G15,Data_Prices!$A:$A,0)) -> 0.12481431 | R15: =INDEX(Data_Prices!R:R,MATCH($G15,Data_Prices!$A:$A,0)) -> 0.12146026 | S15: =INDEX(Data_Prices!S:S,MATCH($G15,Data_Prices!$A:$A,0)) -> 0.11795074 | T15: =INDEX(Data_Prices!T:T,MATCH($G15,Data_Prices!$A:$A,0)) -> 0.11419916 | U15: =INDEX(Data_Prices!U:U,MATCH($G15,Data_Prices!$A:$A,0)) -> 0.1136651 | V15: =INDEX(Data_Prices!V:V,MATCH($G15,Data_Prices!$A:$A,0)) -> 0.11301693 | W15: =INDEX(Data_Prices!W:W,MATCH($G15,Data_Prices!$A:$A,0)) -> 0.11231407 | X15: =INDEX(Data_Prices!X:X,MATCH($G15,Data_Prices!$A:$A,0)) -> 0.11142204 | Y15: =INDEX(Data_Prices!Y:Y,MATCH($G15,Data_Prices!$A:$A,0)) -> 0.11043412 | Z15: =INDEX(Data_Prices!Z:Z,MATCH($G15,Data_Prices!$A:$A,0)) -> 0.10948397 | AA15: =INDEX(Data_Prices!AA:AA,MATCH($G15,Data_Prices!$A:$A,0)) -> 0.10839192 | AB15: =INDEX(Data_Prices!AB:AB,MATCH($G15,Data_Prices!$A:$A,0)) -> 0.10735443 | AC15: =INDEX(Data_Prices!AC:AC,MATCH($G15,Data_Prices!$A:$A,0)) -> 0.10516868 | AD15: =INDEX(Data_Prices!AD:AD,MATCH($G15,Data_Prices!$A:$A,0)) -> 0.10305798 | AE15: =INDEX(Data_Prices!AE:AE,MATCH($G15,Data_Prices!$A:$A,0)) -> 0.10093184
B16: Post-tax price: pre-tax + new-policy wedge x sector coverage factor (= CPAT atp row)
B17: coa | C17: =$C$5 -> irn | D17: Coal | E17: $/GJ | F17: atp | G17: =Settings!$B$3&".mit.nce."&Settings!$B$4&"."&$B17&".a."&$J$5 -> egy.mit.nce.ind.coa.a.1 | H17: =OUTCODE(Settings!$B$3,"atp",$C$5,$B17,$J$5) -> egy.mit.atp.irn.coa.e.1 | K17: =POSTTAX(K7,INDEX(Data_Prices!K:K,MATCH($G17,Data_Prices!$A:$A,0)),K$37) -> 11.182902 | L17: =POSTTAX(L7,INDEX(Data_Prices!L:L,MATCH($G17,Data_Prices!$A:$A,0)),L$37) -> 10.523361 | M17: =POSTTAX(M7,INDEX(Data_Prices!M:M,MATCH($G17,Data_Prices!$A:$A,0)),M$37) -> 10.299561 | N17: =POSTTAX(N7,INDEX(Data_Prices!N:N,MATCH($G17,Data_Prices!$A:$A,0)),N$37) -> 9.5775284 | O17: =POSTTAX(O7,INDEX(Data_Prices!O:O,MATCH($G17,Data_Prices!$A:$A,0)),O$37) -> 8.4854783 | P17: =POSTTAX(P7,INDEX(Data_Prices!P:P,MATCH($G17,Data_Prices!$A:$A,0)),P$37) -> 9.0871922 | Q17: =POSTTAX(Q7,INDEX(Data_Prices!Q:Q,MATCH($G17,Data_Prices!$A:$A,0)),Q$37) -> 9.2229237 | R17: =POSTTAX(R7,INDEX(Data_Prices!R:R,MATCH($G17,Data_Prices!$A:$A,0)),R$37) -> 9.158565 | S17: =POSTTAX(S7,INDEX(Data_Prices!S:S,MATCH($G17,Data_Prices!$A:$A,0)),S$37) -> 9.0895479 | T17: =POSTTAX(T7,INDEX(Data_Prices!T:T,MATCH($G17,Data_Prices!$A:$A,0)),T$37) -> 9.0156817 | U17: =POSTTAX(U7,INDEX(Data_Prices!U:U,MATCH($G17,Data_Prices!$A:$A,0)),U$37) -> 8.9443978 | V17: =POSTTAX(V7,INDEX(Data_Prices!V:V,MATCH($G17,Data_Prices!$A:$A,0)),V$37) -> 8.9443978 | W17: =POSTTAX(W7,INDEX(Data_Prices!W:W,MATCH($G17,Data_Prices!$A:$A,0)),W$37) -> 8.9443978 | X17: =POSTTAX(X7,INDEX(Data_Prices!X:X,MATCH($G17,Data_Prices!$A:$A,0)),X$37) -> 8.9443978 | Y17: =POSTTAX(Y7,INDEX(Data_Prices!Y:Y,MATCH($G17,Data_Prices!$A:$A,0)),Y$37) -> 8.9443978 | Z17: =POSTTAX(Z7,INDEX(Data_Prices!Z:Z,MATCH($G17,Data_Prices!$A:$A,0)),Z$37) -> 8.9443978 | AA17: =POSTTAX(AA7,INDEX(Data_Prices!AA:AA,MATCH($G17,Data_Prices!$A:$A,0)),AA$37) -> 8.9443978 | AB17: =POSTTAX(AB7,INDEX(Data_Prices!AB:AB,MATCH($G17,Data_Prices!$A:$A,0)),AB$37) -> 8.9443978 | AC17: =POSTTAX(AC7,INDEX(Data_Prices!AC:AC,MATCH($G17,Data_Prices!$A:$A,0)),AC$37) -> 8.9443978 | AD17: =POSTTAX(AD7,INDEX(Data_Prices!AD:AD,MATCH($G17,Data_Prices!$A:$A,0)),AD$37) -> 8.9443978 | AE17: =POSTTAX(AE7,INDEX(Data_Prices!AE:AE,MATCH($G17,Data_Prices!$A:$A,0)),AE$37) -> 8.9443978
B18: nga | C18: =$C$5 -> irn | D18: Natural gas | E18: $/GJ | F18: atp | G18: =Settings!$B$3&".mit.nce."&Settings!$B$4&"."&$B18&".a."&$J$5 -> egy.mit.nce.ind.nga.a.1 | H18: =OUTCODE(Settings!$B$3,"atp",$C$5,$B18,$J$5) -> egy.mit.atp.irn.nga.e.1 | K18: =POSTTAX(K8,INDEX(Data_Prices!K:K,MATCH($G18,Data_Prices!$A:$A,0)),K$37) -> 6.0634636 | L18: =POSTTAX(L8,INDEX(Data_Prices!L:L,MATCH($G18,Data_Prices!$A:$A,0)),L$37) -> 5.4510151 | M18: =POSTTAX(M8,INDEX(Data_Prices!M:M,MATCH($G18,Data_Prices!$A:$A,0)),M$37) -> 5.1193563 | N18: =POSTTAX(N8,INDEX(Data_Prices!N:N,MATCH($G18,Data_Prices!$A:$A,0)),N$37) -> 5.0821846 | O18: =POSTTAX(O8,INDEX(Data_Prices!O:O,MATCH($G18,Data_Prices!$A:$A,0)),O$37) -> 5.0821846 | P18: =POSTTAX(P8,INDEX(Data_Prices!P:P,MATCH($G18,Data_Prices!$A:$A,0)),P$37) -> 5.0821846 | Q18: =POSTTAX(Q8,INDEX(Data_Prices!Q:Q,MATCH($G18,Data_Prices!$A:$A,0)),Q$37) -> 5.0821846 | R18: =POSTTAX(R8,INDEX(Data_Prices!R:R,MATCH($G18,Data_Prices!$A:$A,0)),R$37) -> 5.0821846 | S18: =POSTTAX(S8,INDEX(Data_Prices!S:S,MATCH($G18,Data_Prices!$A:$A,0)),S$37) -> 5.0821846 | T18: =POSTTAX(T8,INDEX(Data_Prices!T:T,MATCH($G18,Data_Prices!$A:$A,0)),T$37) -> 5.0821846 | U18: =POSTTAX(U8,INDEX(Data_Prices!U:U,MATCH($G18,Data_Prices!$A:$A,0)),U$37) -> 5.0821846 | V18: =POSTTAX(V8,INDEX(Data_Prices!V:V,MATCH($G18,Data_Prices!$A:$A,0)),V$37) -> 5.0821846 | W18: =POSTTAX(W8,INDEX(Data_Prices!W:W,MATCH($G18,Data_Prices!$A:$A,0)),W$37) -> 5.0821846 | X18: =POSTTAX(X8,INDEX(Data_Prices!X:X,MATCH($G18,Data_Prices!$A:$A,0)),X$37) -> 5.0821846 | Y18: =POSTTAX(Y8,INDEX(Data_Prices!Y:Y,MATCH($G18,Data_Prices!$A:$A,0)),Y$37) -> 5.0821846 | Z18: =POSTTAX(Z8,INDEX(Data_Prices!Z:Z,MATCH($G18,Data_Prices!$A:$A,0)),Z$37) -> 5.0821846 | AA18: =POSTTAX(AA8,INDEX(Data_Prices!AA:AA,MATCH($G18,Data_Prices!$A:$A,0)),AA$37) -> 5.0821846 | AB18: =POSTTAX(AB8,INDEX(Data_Prices!AB:AB,MATCH($G18,Data_Prices!$A:$A,0)),AB$37) -> 5.0821846 | AC18: =POSTTAX(AC8,INDEX(Data_Prices!AC:AC,MATCH($G18,Data_Prices!$A:$A,0)),AC$37) -> 5.0821846 | AD18: =POSTTAX(AD8,INDEX(Data_Prices!AD:AD,MATCH($G18,Data_Prices!$A:$A,0)),AD$37) -> 5.0821846 | AE18: =POSTTAX(AE8,INDEX(Data_Prices!AE:AE,MATCH($G18,Data_Prices!$A:$A,0)),AE$37) -> 5.0821846
B19: gso | C19: =$C$5 -> irn | D19: Gasoline | E19: $/liter | F19: atp | G19: =Settings!$B$3&".mit.nce."&Settings!$B$4&"."&$B19&".a."&$J$5 -> egy.mit.nce.ind.gso.a.1 | H19: =OUTCODE(Settings!$B$3,"atp",$C$5,$B19,$J$5) -> egy.mit.atp.irn.gso.e.1 | K19: =POSTTAX(K9,INDEX(Data_Prices!K:K,MATCH($G19,Data_Prices!$A:$A,0)),K$37) -> 0.67114653 | L19: =POSTTAX(L9,INDEX(Data_Prices!L:L,MATCH($G19,Data_Prices!$A:$A,0)),L$37) -> 0.61197798 | M19: =POSTTAX(M9,INDEX(Data_Prices!M:M,MATCH($G19,Data_Prices!$A:$A,0)),M$37) -> 0.61180975 | N19: =POSTTAX(N9,INDEX(Data_Prices!N:N,MATCH($G19,Data_Prices!$A:$A,0)),N$37) -> 0.6035831 | O19: =POSTTAX(O9,INDEX(Data_Prices!O:O,MATCH($G19,Data_Prices!$A:$A,0)),O$37) -> 0.6035831 | P19: =POSTTAX(P9,INDEX(Data_Prices!P:P,MATCH($G19,Data_Prices!$A:$A,0)),P$37) -> 0.6035831 | Q19: =POSTTAX(Q9,INDEX(Data_Prices!Q:Q,MATCH($G19,Data_Prices!$A:$A,0)),Q$37) -> 0.6035831 | R19: =POSTTAX(R9,INDEX(Data_Prices!R:R,MATCH($G19,Data_Prices!$A:$A,0)),R$37) -> 0.6035831 | S19: =POSTTAX(S9,INDEX(Data_Prices!S:S,MATCH($G19,Data_Prices!$A:$A,0)),S$37) -> 0.6035831 | T19: =POSTTAX(T9,INDEX(Data_Prices!T:T,MATCH($G19,Data_Prices!$A:$A,0)),T$37) -> 0.6035831 | U19: =POSTTAX(U9,INDEX(Data_Prices!U:U,MATCH($G19,Data_Prices!$A:$A,0)),U$37) -> 0.6035831 | V19: =POSTTAX(V9,INDEX(Data_Prices!V:V,MATCH($G19,Data_Prices!$A:$A,0)),V$37) -> 0.6035831 | W19: =POSTTAX(W9,INDEX(Data_Prices!W:W,MATCH($G19,Data_Prices!$A:$A,0)),W$37) -> 0.6035831 | X19: =POSTTAX(X9,INDEX(Data_Prices!X:X,MATCH($G19,Data_Prices!$A:$A,0)),X$37) -> 0.6035831 | Y19: =POSTTAX(Y9,INDEX(Data_Prices!Y:Y,MATCH($G19,Data_Prices!$A:$A,0)),Y$37) -> 0.6035831 | Z19: =POSTTAX(Z9,INDEX(Data_Prices!Z:Z,MATCH($G19,Data_Prices!$A:$A,0)),Z$37) -> 0.6035831 | AA19: =POSTTAX(AA9,INDEX(Data_Prices!AA:AA,MATCH($G19,Data_Prices!$A:$A,0)),AA$37) -> 0.6035831 | AB19: =POSTTAX(AB9,INDEX(Data_Prices!AB:AB,MATCH($G19,Data_Prices!$A:$A,0)),AB$37) -> 0.6035831 | AC19: =POSTTAX(AC9,INDEX(Data_Prices!AC:AC,MATCH($G19,Data_Prices!$A:$A,0)),AC$37) -> 0.6035831 | AD19: =POSTTAX(AD9,INDEX(Data_Prices!AD:AD,MATCH($G19,Data_Prices!$A:$A,0)),AD$37) -> 0.6035831 | AE19: =POSTTAX(AE9,INDEX(Data_Prices!AE:AE,MATCH($G19,Data_Prices!$A:$A,0)),AE$37) -> 0.6035831
B20: die | C20: =$C$5 -> irn | D20: Diesel | E20: $/liter | F20: atp | G20: =Settings!$B$3&".mit.nce."&Settings!$B$4&"."&$B20&".a."&$J$5 -> egy.mit.nce.ind.die.a.1 | H20: =OUTCODE(Settings!$B$3,"atp",$C$5,$B20,$J$5) -> egy.mit.atp.irn.die.e.1 | K20: =POSTTAX(K10,INDEX(Data_Prices!K:K,MATCH($G20,Data_Prices!$A:$A,0)),K$37) -> 0.55971121 | L20: =POSTTAX(L10,INDEX(Data_Prices!L:L,MATCH($G20,Data_Prices!$A:$A,0)),L$37) -> 0.49458873 | M20: =POSTTAX(M10,INDEX(Data_Prices!M:M,MATCH($G20,Data_Prices!$A:$A,0)),M$37) -> 0.50778655 | N20: =POSTTAX(N10,INDEX(Data_Prices!N:N,MATCH($G20,Data_Prices!$A:$A,0)),N$37) -> 0.47043643 | O20: =POSTTAX(O10,INDEX(Data_Prices!O:O,MATCH($G20,Data_Prices!$A:$A,0)),O$37) -> 0.47043643 | P20: =POSTTAX(P10,INDEX(Data_Prices!P:P,MATCH($G20,Data_Prices!$A:$A,0)),P$37) -> 0.47043643 | Q20: =POSTTAX(Q10,INDEX(Data_Prices!Q:Q,MATCH($G20,Data_Prices!$A:$A,0)),Q$37) -> 0.47043643 | R20: =POSTTAX(R10,INDEX(Data_Prices!R:R,MATCH($G20,Data_Prices!$A:$A,0)),R$37) -> 0.47043643 | S20: =POSTTAX(S10,INDEX(Data_Prices!S:S,MATCH($G20,Data_Prices!$A:$A,0)),S$37) -> 0.47043643 | T20: =POSTTAX(T10,INDEX(Data_Prices!T:T,MATCH($G20,Data_Prices!$A:$A,0)),T$37) -> 0.47043643 | U20: =POSTTAX(U10,INDEX(Data_Prices!U:U,MATCH($G20,Data_Prices!$A:$A,0)),U$37) -> 0.47043643 | V20: =POSTTAX(V10,INDEX(Data_Prices!V:V,MATCH($G20,Data_Prices!$A:$A,0)),V$37) -> 0.47043643 | W20: =POSTTAX(W10,INDEX(Data_Prices!W:W,MATCH($G20,Data_Prices!$A:$A,0)),W$37) -> 0.47043643 | X20: =POSTTAX(X10,INDEX(Data_Prices!X:X,MATCH($G20,Data_Prices!$A:$A,0)),X$37) -> 0.47043643 | Y20: =POSTTAX(Y10,INDEX(Data_Prices!Y:Y,MATCH($G20,Data_Prices!$A:$A,0)),Y$37) -> 0.47043643 | Z20: =POSTTAX(Z10,INDEX(Data_Prices!Z:Z,MATCH($G20,Data_Prices!$A:$A,0)),Z$37) -> 0.47043643 | AA20: =POSTTAX(AA10,INDEX(Data_Prices!AA:AA,MATCH($G20,Data_Prices!$A:$A,0)),AA$37) -> 0.47043643 | AB20: =POSTTAX(AB10,INDEX(Data_Prices!AB:AB,MATCH($G20,Data_Prices!$A:$A,0)),AB$37) -> 0.47043643 | AC20: =POSTTAX(AC10,INDEX(Data_Prices!AC:AC,MATCH($G20,Data_Prices!$A:$A,0)),AC$37) -> 0.47043643 | AD20: =POSTTAX(AD10,INDEX(Data_Prices!AD:AD,MATCH($G20,Data_Prices!$A:$A,0)),AD$37) -> 0.47043643 | AE20: =POSTTAX(AE10,INDEX(Data_Prices!AE:AE,MATCH($G20,Data_Prices!$A:$A,0)),AE$37) -> 0.47043643
B21: lpg | C21: =$C$5 -> irn | D21: LPG | E21: $/liter | F21: atp | G21: =Settings!$B$3&".mit.nce."&Settings!$B$4&"."&$B21&".a."&$J$5 -> egy.mit.nce.ind.lpg.a.1 | H21: =OUTCODE(Settings!$B$3,"atp",$C$5,$B21,$J$5) -> egy.mit.atp.irn.lpg.e.1 | K21: =POSTTAX(K11,INDEX(Data_Prices!K:K,MATCH($G21,Data_Prices!$A:$A,0)),K$37) -> 0.20036669 | L21: =POSTTAX(L11,INDEX(Data_Prices!L:L,MATCH($G21,Data_Prices!$A:$A,0)),L$37) -> 0.15734474 | M21: =POSTTAX(M11,INDEX(Data_Prices!M:M,MATCH($G21,Data_Prices!$A:$A,0)),M$37) -> 0.16448404 | N21: =POSTTAX(N11,INDEX(Data_Prices!N:N,MATCH($G21,Data_Prices!$A:$A,0)),N$37) -> 0.15070908 | O21: =POSTTAX(O11,INDEX(Data_Prices!O:O,MATCH($G21,Data_Prices!$A:$A,0)),O$37) -> 0.15070908 | P21: =POSTTAX(P11,INDEX(Data_Prices!P:P,MATCH($G21,Data_Prices!$A:$A,0)),P$37) -> 0.15070908 | Q21: =POSTTAX(Q11,INDEX(Data_Prices!Q:Q,MATCH($G21,Data_Prices!$A:$A,0)),Q$37) -> 0.15070908 | R21: =POSTTAX(R11,INDEX(Data_Prices!R:R,MATCH($G21,Data_Prices!$A:$A,0)),R$37) -> 0.15070908 | S21: =POSTTAX(S11,INDEX(Data_Prices!S:S,MATCH($G21,Data_Prices!$A:$A,0)),S$37) -> 0.15070908 | T21: =POSTTAX(T11,INDEX(Data_Prices!T:T,MATCH($G21,Data_Prices!$A:$A,0)),T$37) -> 0.15070908 | U21: =POSTTAX(U11,INDEX(Data_Prices!U:U,MATCH($G21,Data_Prices!$A:$A,0)),U$37) -> 0.15070908 | V21: =POSTTAX(V11,INDEX(Data_Prices!V:V,MATCH($G21,Data_Prices!$A:$A,0)),V$37) -> 0.15070908 | W21: =POSTTAX(W11,INDEX(Data_Prices!W:W,MATCH($G21,Data_Prices!$A:$A,0)),W$37) -> 0.15070908 | X21: =POSTTAX(X11,INDEX(Data_Prices!X:X,MATCH($G21,Data_Prices!$A:$A,0)),X$37) -> 0.15070908 | Y21: =POSTTAX(Y11,INDEX(Data_Prices!Y:Y,MATCH($G21,Data_Prices!$A:$A,0)),Y$37) -> 0.15070908 | Z21: =POSTTAX(Z11,INDEX(Data_Prices!Z:Z,MATCH($G21,Data_Prices!$A:$A,0)),Z$37) -> 0.15070908 | AA21: =POSTTAX(AA11,INDEX(Data_Prices!AA:AA,MATCH($G21,Data_Prices!$A:$A,0)),AA$37) -> 0.15070908 | AB21: =POSTTAX(AB11,INDEX(Data_Prices!AB:AB,MATCH($G21,Data_Prices!$A:$A,0)),AB$37) -> 0.15070908 | AC21: =POSTTAX(AC11,INDEX(Data_Prices!AC:AC,MATCH($G21,Data_Prices!$A:$A,0)),AC$37) -> 0.15070908 | AD21: =POSTTAX(AD11,INDEX(Data_Prices!AD:AD,MATCH($G21,Data_Prices!$A:$A,0)),AD$37) -> 0.15070908 | AE21: =POSTTAX(AE11,INDEX(Data_Prices!AE:AE,MATCH($G21,Data_Prices!$A:$A,0)),AE$37) -> 0.15070908
B22: ker | C22: =$C$5 -> irn | D22: Kerosene | E22: $/liter | F22: atp | G22: =Settings!$B$3&".mit.nce."&Settings!$B$4&"."&$B22&".a."&$J$5 -> egy.mit.nce.ind.ker.a.1 | H22: =OUTCODE(Settings!$B$3,"atp",$C$5,$B22,$J$5) -> egy.mit.atp.irn.ker.e.1 | K22: =POSTTAX(K12,INDEX(Data_Prices!K:K,MATCH($G22,Data_Prices!$A:$A,0)),K$37) -> 0.48429424 | L22: =POSTTAX(L12,INDEX(Data_Prices!L:L,MATCH($G22,Data_Prices!$A:$A,0)),L$37) -> 0.45642817 | M22: =POSTTAX(M12,INDEX(Data_Prices!M:M,MATCH($G22,Data_Prices!$A:$A,0)),M$37) -> 0.4316892 | N22: =POSTTAX(N12,INDEX(Data_Prices!N:N,MATCH($G22,Data_Prices!$A:$A,0)),N$37) -> 0.42507558 | O22: =POSTTAX(O12,INDEX(Data_Prices!O:O,MATCH($G22,Data_Prices!$A:$A,0)),O$37) -> 0.42507558 | P22: =POSTTAX(P12,INDEX(Data_Prices!P:P,MATCH($G22,Data_Prices!$A:$A,0)),P$37) -> 0.42507558 | Q22: =POSTTAX(Q12,INDEX(Data_Prices!Q:Q,MATCH($G22,Data_Prices!$A:$A,0)),Q$37) -> 0.42507558 | R22: =POSTTAX(R12,INDEX(Data_Prices!R:R,MATCH($G22,Data_Prices!$A:$A,0)),R$37) -> 0.42507558 | S22: =POSTTAX(S12,INDEX(Data_Prices!S:S,MATCH($G22,Data_Prices!$A:$A,0)),S$37) -> 0.42507558 | T22: =POSTTAX(T12,INDEX(Data_Prices!T:T,MATCH($G22,Data_Prices!$A:$A,0)),T$37) -> 0.42507558 | U22: =POSTTAX(U12,INDEX(Data_Prices!U:U,MATCH($G22,Data_Prices!$A:$A,0)),U$37) -> 0.42507558 | V22: =POSTTAX(V12,INDEX(Data_Prices!V:V,MATCH($G22,Data_Prices!$A:$A,0)),V$37) -> 0.42507558 | W22: =POSTTAX(W12,INDEX(Data_Prices!W:W,MATCH($G22,Data_Prices!$A:$A,0)),W$37) -> 0.42507558 | X22: =POSTTAX(X12,INDEX(Data_Prices!X:X,MATCH($G22,Data_Prices!$A:$A,0)),X$37) -> 0.42507558 | Y22: =POSTTAX(Y12,INDEX(Data_Prices!Y:Y,MATCH($G22,Data_Prices!$A:$A,0)),Y$37) -> 0.42507558 | Z22: =POSTTAX(Z12,INDEX(Data_Prices!Z:Z,MATCH($G22,Data_Prices!$A:$A,0)),Z$37) -> 0.42507558 | AA22: =POSTTAX(AA12,INDEX(Data_Prices!AA:AA,MATCH($G22,Data_Prices!$A:$A,0)),AA$37) -> 0.42507558 | AB22: =POSTTAX(AB12,INDEX(Data_Prices!AB:AB,MATCH($G22,Data_Prices!$A:$A,0)),AB$37) -> 0.42507558 | AC22: =POSTTAX(AC12,INDEX(Data_Prices!AC:AC,MATCH($G22,Data_Prices!$A:$A,0)),AC$37) -> 0.42507558 | AD22: =POSTTAX(AD12,INDEX(Data_Prices!AD:AD,MATCH($G22,Data_Prices!$A:$A,0)),AD$37) -> 0.42507558 | AE22: =POSTTAX(AE12,INDEX(Data_Prices!AE:AE,MATCH($G22,Data_Prices!$A:$A,0)),AE$37) -> 0.42507558
B23: oop | C23: =$C$5 -> irn | D23: Other oil products | E23: $/bbl | F23: atp | G23: =Settings!$B$3&".mit.nce."&Settings!$B$4&"."&$B23&".a."&$J$5 -> egy.mit.nce.ind.oop.a.1 | H23: =OUTCODE(Settings!$B$3,"atp",$C$5,$B23,$J$5) -> egy.mit.atp.irn.oop.e.1 | K23: =POSTTAX(K13,INDEX(Data_Prices!K:K,MATCH($G23,Data_Prices!$A:$A,0)),K$37) -> 41.500338 | L23: =POSTTAX(L13,INDEX(Data_Prices!L:L,MATCH($G23,Data_Prices!$A:$A,0)),L$37) -> 34.41537 | M23: =POSTTAX(M13,INDEX(Data_Prices!M:M,MATCH($G23,Data_Prices!$A:$A,0)),M$37) -> 37.368961 | N23: =POSTTAX(N13,INDEX(Data_Prices!N:N,MATCH($G23,Data_Prices!$A:$A,0)),N$37) -> 28.982761 | O23: =POSTTAX(O13,INDEX(Data_Prices!O:O,MATCH($G23,Data_Prices!$A:$A,0)),O$37) -> 15 | P23: =POSTTAX(P13,INDEX(Data_Prices!P:P,MATCH($G23,Data_Prices!$A:$A,0)),P$37) -> 24.25863 | Q23: =POSTTAX(Q13,INDEX(Data_Prices!Q:Q,MATCH($G23,Data_Prices!$A:$A,0)),Q$37) -> 15 | R23: =POSTTAX(R13,INDEX(Data_Prices!R:R,MATCH($G23,Data_Prices!$A:$A,0)),R$37) -> 15 | S23: =POSTTAX(S13,INDEX(Data_Prices!S:S,MATCH($G23,Data_Prices!$A:$A,0)),S$37) -> 15 | T23: =POSTTAX(T13,INDEX(Data_Prices!T:T,MATCH($G23,Data_Prices!$A:$A,0)),T$37) -> 15 | U23: =POSTTAX(U13,INDEX(Data_Prices!U:U,MATCH($G23,Data_Prices!$A:$A,0)),U$37) -> 15 | V23: =POSTTAX(V13,INDEX(Data_Prices!V:V,MATCH($G23,Data_Prices!$A:$A,0)),V$37) -> 15 | W23: =POSTTAX(W13,INDEX(Data_Prices!W:W,MATCH($G23,Data_Prices!$A:$A,0)),W$37) -> 15 | X23: =POSTTAX(X13,INDEX(Data_Prices!X:X,MATCH($G23,Data_Prices!$A:$A,0)),X$37) -> 15 | Y23: =POSTTAX(Y13,INDEX(Data_Prices!Y:Y,MATCH($G23,Data_Prices!$A:$A,0)),Y$37) -> 15 | Z23: =POSTTAX(Z13,INDEX(Data_Prices!Z:Z,MATCH($G23,Data_Prices!$A:$A,0)),Z$37) -> 15 | AA23: =POSTTAX(AA13,INDEX(Data_Prices!AA:AA,MATCH($G23,Data_Prices!$A:$A,0)),AA$37) -> 15 | AB23: =POSTTAX(AB13,INDEX(Data_Prices!AB:AB,MATCH($G23,Data_Prices!$A:$A,0)),AB$37) -> 15 | AC23: =POSTTAX(AC13,INDEX(Data_Prices!AC:AC,MATCH($G23,Data_Prices!$A:$A,0)),AC$37) -> 15 | AD23: =POSTTAX(AD13,INDEX(Data_Prices!AD:AD,MATCH($G23,Data_Prices!$A:$A,0)),AD$37) -> 15 | AE23: =POSTTAX(AE13,INDEX(Data_Prices!AE:AE,MATCH($G23,Data_Prices!$A:$A,0)),AE$37) -> 15
B24: bio | C24: =$C$5 -> irn | D24: Biomass | E24: $/GJ | F24: atp | G24: =Settings!$B$3&".mit.nce."&Settings!$B$4&"."&$B24&".a."&$J$5 -> egy.mit.nce.ind.bio.a.1 | H24: =OUTCODE(Settings!$B$3,"atp",$C$5,$B24,$J$5) -> egy.mit.atp.irn.bio.e.1 | K24: =POSTTAX(K14,INDEX(Data_Prices!K:K,MATCH($G24,Data_Prices!$A:$A,0)),K$37) -> 15.334551 | L24: =POSTTAX(L14,INDEX(Data_Prices!L:L,MATCH($G24,Data_Prices!$A:$A,0)),L$37) -> 14.199528 | M24: =POSTTAX(M14,INDEX(Data_Prices!M:M,MATCH($G24,Data_Prices!$A:$A,0)),M$37) -> 13.840442 | N24: =POSTTAX(N14,INDEX(Data_Prices!N:N,MATCH($G24,Data_Prices!$A:$A,0)),N$37) -> 13.567727 | O24: =POSTTAX(O14,INDEX(Data_Prices!O:O,MATCH($G24,Data_Prices!$A:$A,0)),O$37) -> 13.567727 | P24: =POSTTAX(P14,INDEX(Data_Prices!P:P,MATCH($G24,Data_Prices!$A:$A,0)),P$37) -> 13.567727 | Q24: =POSTTAX(Q14,INDEX(Data_Prices!Q:Q,MATCH($G24,Data_Prices!$A:$A,0)),Q$37) -> 13.567727 | R24: =POSTTAX(R14,INDEX(Data_Prices!R:R,MATCH($G24,Data_Prices!$A:$A,0)),R$37) -> 13.567727 | S24: =POSTTAX(S14,INDEX(Data_Prices!S:S,MATCH($G24,Data_Prices!$A:$A,0)),S$37) -> 13.567727 | T24: =POSTTAX(T14,INDEX(Data_Prices!T:T,MATCH($G24,Data_Prices!$A:$A,0)),T$37) -> 13.567727 | U24: =POSTTAX(U14,INDEX(Data_Prices!U:U,MATCH($G24,Data_Prices!$A:$A,0)),U$37) -> 13.567727 | V24: =POSTTAX(V14,INDEX(Data_Prices!V:V,MATCH($G24,Data_Prices!$A:$A,0)),V$37) -> 13.567727 | W24: =POSTTAX(W14,INDEX(Data_Prices!W:W,MATCH($G24,Data_Prices!$A:$A,0)),W$37) -> 13.567727 | X24: =POSTTAX(X14,INDEX(Data_Prices!X:X,MATCH($G24,Data_Prices!$A:$A,0)),X$37) -> 13.567727 | Y24: =POSTTAX(Y14,INDEX(Data_Prices!Y:Y,MATCH($G24,Data_Prices!$A:$A,0)),Y$37) -> 13.567727 | Z24: =POSTTAX(Z14,INDEX(Data_Prices!Z:Z,MATCH($G24,Data_Prices!$A:$A,0)),Z$37) -> 13.567727 | AA24: =POSTTAX(AA14,INDEX(Data_Prices!AA:AA,MATCH($G24,Data_Prices!$A:$A,0)),AA$37) -> 13.567727 | AB24: =POSTTAX(AB14,INDEX(Data_Prices!AB:AB,MATCH($G24,Data_Prices!$A:$A,0)),AB$37) -> 13.567727 | AC24: =POSTTAX(AC14,INDEX(Data_Prices!AC:AC,MATCH($G24,Data_Prices!$A:$A,0)),AC$37) -> 13.567727 | AD24: =POSTTAX(AD14,INDEX(Data_Prices!AD:AD,MATCH($G24,Data_Prices!$A:$A,0)),AD$37) -> 13.567727 | AE24: =POSTTAX(AE14,INDEX(Data_Prices!AE:AE,MATCH($G24,Data_Prices!$A:$A,0)),AE$37) -> 13.567727
B25: ren | C25: =$C$5 -> irn | D25: Self-generated renewables | E25: $/kwh | F25: atp | G25: =Settings!$B$3&".mit.nce."&Settings!$B$4&"."&$B25&".a."&$J$5 -> egy.mit.nce.ind.ren.a.1 | H25: =OUTCODE(Settings!$B$3,"atp",$C$5,$B25,$J$5) -> egy.mit.atp.irn.ren.e.1 | K25: =POSTTAX(K15,INDEX(Data_Prices!K:K,MATCH($G25,Data_Prices!$A:$A,0)),K$37) -> 0 | L25: =POSTTAX(L15,INDEX(Data_Prices!L:L,MATCH($G25,Data_Prices!$A:$A,0)),L$37) -> 0.14404499 | M25: =POSTTAX(M15,INDEX(Data_Prices!M:M,MATCH($G25,Data_Prices!$A:$A,0)),M$37) -> 0.14102041 | N25: =POSTTAX(N15,INDEX(Data_Prices!N:N,MATCH($G25,Data_Prices!$A:$A,0)),N$37) -> 0.13511636 | O25: =POSTTAX(O15,INDEX(Data_Prices!O:O,MATCH($G25,Data_Prices!$A:$A,0)),O$37) -> 0.13098826 | P25: =POSTTAX(P15,INDEX(Data_Prices!P:P,MATCH($G25,Data_Prices!$A:$A,0)),P$37) -> 0.12790842 | Q25: =POSTTAX(Q15,INDEX(Data_Prices!Q:Q,MATCH($G25,Data_Prices!$A:$A,0)),Q$37) -> 0.12481431 | R25: =POSTTAX(R15,INDEX(Data_Prices!R:R,MATCH($G25,Data_Prices!$A:$A,0)),R$37) -> 0.12146026 | S25: =POSTTAX(S15,INDEX(Data_Prices!S:S,MATCH($G25,Data_Prices!$A:$A,0)),S$37) -> 0.11795074 | T25: =POSTTAX(T15,INDEX(Data_Prices!T:T,MATCH($G25,Data_Prices!$A:$A,0)),T$37) -> 0.11419916 | U25: =POSTTAX(U15,INDEX(Data_Prices!U:U,MATCH($G25,Data_Prices!$A:$A,0)),U$37) -> 0.1136651 | V25: =POSTTAX(V15,INDEX(Data_Prices!V:V,MATCH($G25,Data_Prices!$A:$A,0)),V$37) -> 0.11301693 | W25: =POSTTAX(W15,INDEX(Data_Prices!W:W,MATCH($G25,Data_Prices!$A:$A,0)),W$37) -> 0.11231407 | X25: =POSTTAX(X15,INDEX(Data_Prices!X:X,MATCH($G25,Data_Prices!$A:$A,0)),X$37) -> 0.11142204 | Y25: =POSTTAX(Y15,INDEX(Data_Prices!Y:Y,MATCH($G25,Data_Prices!$A:$A,0)),Y$37) -> 0.11043412 | Z25: =POSTTAX(Z15,INDEX(Data_Prices!Z:Z,MATCH($G25,Data_Prices!$A:$A,0)),Z$37) -> 0.10948397 | AA25: =POSTTAX(AA15,INDEX(Data_Prices!AA:AA,MATCH($G25,Data_Prices!$A:$A,0)),AA$37) -> 0.10839192 | AB25: =POSTTAX(AB15,INDEX(Data_Prices!AB:AB,MATCH($G25,Data_Prices!$A:$A,0)),AB$37) -> 0.10735443 | AC25: =POSTTAX(AC15,INDEX(Data_Prices!AC:AC,MATCH($G25,Data_Prices!$A:$A,0)),AC$37) -> 0.10516868 | AD25: =POSTTAX(AD15,INDEX(Data_Prices!AD:AD,MATCH($G25,Data_Prices!$A:$A,0)),AD$37) -> 0.10305798 | AE25: =POSTTAX(AE15,INDEX(Data_Prices!AE:AE,MATCH($G25,Data_Prices!$A:$A,0)),AE$37) -> 0.10093184
B26: Shadow price: post-tax + shadow price of non-price policies x share acting on efficiency
B27: coa | C27: =$C$5 -> irn | D27: Coal | E27: $/GJ | F27: shp | G27: =Settings!$B$3&".mit.shp."&$B27&"."&Settings!$B$4&"."&$J$5 -> egy.mit.shp.coa.ind.1 | H27: =OUTCODE(Settings!$B$3,"shp",$C$5,$B27,$J$5) -> egy.mit.shp.irn.coa.e.1 | K27: =SHADOW(K17,INDEX(Data_Prices!K:K,MATCH($G27,Data_Prices!$A:$A,0)),K$38) -> 11.182902 | L27: =SHADOW(L17,INDEX(Data_Prices!L:L,MATCH($G27,Data_Prices!$A:$A,0)),L$38) -> 10.523361 | M27: =SHADOW(M17,INDEX(Data_Prices!M:M,MATCH($G27,Data_Prices!$A:$A,0)),M$38) -> 10.299561 | N27: =SHADOW(N17,INDEX(Data_Prices!N:N,MATCH($G27,Data_Prices!$A:$A,0)),N$38) -> 9.5775284 | O27: =SHADOW(O17,INDEX(Data_Prices!O:O,MATCH($G27,Data_Prices!$A:$A,0)),O$38) -> 8.4854783 | P27: =SHADOW(P17,INDEX(Data_Prices!P:P,MATCH($G27,Data_Prices!$A:$A,0)),P$38) -> 9.0871922 | Q27: =SHADOW(Q17,INDEX(Data_Prices!Q:Q,MATCH($G27,Data_Prices!$A:$A,0)),Q$38) -> 9.2229237 | R27: =SHADOW(R17,INDEX(Data_Prices!R:R,MATCH($G27,Data_Prices!$A:$A,0)),R$38) -> 9.158565 | S27: =SHADOW(S17,INDEX(Data_Prices!S:S,MATCH($G27,Data_Prices!$A:$A,0)),S$38) -> 9.0895479 | T27: =SHADOW(T17,INDEX(Data_Prices!T:T,MATCH($G27,Data_Prices!$A:$A,0)),T$38) -> 9.0156817 | U27: =SHADOW(U17,INDEX(Data_Prices!U:U,MATCH($G27,Data_Prices!$A:$A,0)),U$38) -> 8.9443978 | V27: =SHADOW(V17,INDEX(Data_Prices!V:V,MATCH($G27,Data_Prices!$A:$A,0)),V$38) -> 8.9443978 | W27: =SHADOW(W17,INDEX(Data_Prices!W:W,MATCH($G27,Data_Prices!$A:$A,0)),W$38) -> 8.9443978 | X27: =SHADOW(X17,INDEX(Data_Prices!X:X,MATCH($G27,Data_Prices!$A:$A,0)),X$38) -> 8.9443978 | Y27: =SHADOW(Y17,INDEX(Data_Prices!Y:Y,MATCH($G27,Data_Prices!$A:$A,0)),Y$38) -> 8.9443978 | Z27: =SHADOW(Z17,INDEX(Data_Prices!Z:Z,MATCH($G27,Data_Prices!$A:$A,0)),Z$38) -> 8.9443978 | AA27: =SHADOW(AA17,INDEX(Data_Prices!AA:AA,MATCH($G27,Data_Prices!$A:$A,0)),AA$38) -> 8.9443978 | AB27: =SHADOW(AB17,INDEX(Data_Prices!AB:AB,MATCH($G27,Data_Prices!$A:$A,0)),AB$38) -> 8.9443978 | AC27: =SHADOW(AC17,INDEX(Data_Prices!AC:AC,MATCH($G27,Data_Prices!$A:$A,0)),AC$38) -> 8.9443978 | AD27: =SHADOW(AD17,INDEX(Data_Prices!AD:AD,MATCH($G27,Data_Prices!$A:$A,0)),AD$38) -> 8.9443978 | AE27: =SHADOW(AE17,INDEX(Data_Prices!AE:AE,MATCH($G27,Data_Prices!$A:$A,0)),AE$38) -> 8.9443978
B28: nga | C28: =$C$5 -> irn | D28: Natural gas | E28: $/GJ | F28: shp | G28: =Settings!$B$3&".mit.shp."&$B28&"."&Settings!$B$4&"."&$J$5 -> egy.mit.shp.nga.ind.1 | H28: =OUTCODE(Settings!$B$3,"shp",$C$5,$B28,$J$5) -> egy.mit.shp.irn.nga.e.1 | K28: =SHADOW(K18,INDEX(Data_Prices!K:K,MATCH($G28,Data_Prices!$A:$A,0)),K$38) -> 6.0634636 | L28: =SHADOW(L18,INDEX(Data_Prices!L:L,MATCH($G28,Data_Prices!$A:$A,0)),L$38) -> 5.4510151 | M28: =SHADOW(M18,INDEX(Data_Prices!M:M,MATCH($G28,Data_Prices!$A:$A,0)),M$38) -> 5.1193563 | N28: =SHADOW(N18,INDEX(Data_Prices!N:N,MATCH($G28,Data_Prices!$A:$A,0)),N$38) -> 5.0821846 | O28: =SHADOW(O18,INDEX(Data_Prices!O:O,MATCH($G28,Data_Prices!$A:$A,0)),O$38) -> 5.0821846 | P28: =SHADOW(P18,INDEX(Data_Prices!P:P,MATCH($G28,Data_Prices!$A:$A,0)),P$38) -> 5.0821846 | Q28: =SHADOW(Q18,INDEX(Data_Prices!Q:Q,MATCH($G28,Data_Prices!$A:$A,0)),Q$38) -> 5.0821846 | R28: =SHADOW(R18,INDEX(Data_Prices!R:R,MATCH($G28,Data_Prices!$A:$A,0)),R$38) -> 5.0821846 | S28: =SHADOW(S18,INDEX(Data_Prices!S:S,MATCH($G28,Data_Prices!$A:$A,0)),S$38) -> 5.0821846 | T28: =SHADOW(T18,INDEX(Data_Prices!T:T,MATCH($G28,Data_Prices!$A:$A,0)),T$38) -> 5.0821846 | U28: =SHADOW(U18,INDEX(Data_Prices!U:U,MATCH($G28,Data_Prices!$A:$A,0)),U$38) -> 5.0821846 | V28: =SHADOW(V18,INDEX(Data_Prices!V:V,MATCH($G28,Data_Prices!$A:$A,0)),V$38) -> 5.0821846 | W28: =SHADOW(W18,INDEX(Data_Prices!W:W,MATCH($G28,Data_Prices!$A:$A,0)),W$38) -> 5.0821846 | X28: =SHADOW(X18,INDEX(Data_Prices!X:X,MATCH($G28,Data_Prices!$A:$A,0)),X$38) -> 5.0821846 | Y28: =SHADOW(Y18,INDEX(Data_Prices!Y:Y,MATCH($G28,Data_Prices!$A:$A,0)),Y$38) -> 5.0821846 | Z28: =SHADOW(Z18,INDEX(Data_Prices!Z:Z,MATCH($G28,Data_Prices!$A:$A,0)),Z$38) -> 5.0821846 | AA28: =SHADOW(AA18,INDEX(Data_Prices!AA:AA,MATCH($G28,Data_Prices!$A:$A,0)),AA$38) -> 5.0821846 | AB28: =SHADOW(AB18,INDEX(Data_Prices!AB:AB,MATCH($G28,Data_Prices!$A:$A,0)),AB$38) -> 5.0821846 | AC28: =SHADOW(AC18,INDEX(Data_Prices!AC:AC,MATCH($G28,Data_Prices!$A:$A,0)),AC$38) -> 5.0821846 | AD28: =SHADOW(AD18,INDEX(Data_Prices!AD:AD,MATCH($G28,Data_Prices!$A:$A,0)),AD$38) -> 5.0821846 | AE28: =SHADOW(AE18,INDEX(Data_Prices!AE:AE,MATCH($G28,Data_Prices!$A:$A,0)),AE$38) -> 5.0821846
B29: gso | C29: =$C$5 -> irn | D29: Gasoline | E29: $/liter | F29: shp | G29: =Settings!$B$3&".mit.shp."&$B29&"."&Settings!$B$4&"."&$J$5 -> egy.mit.shp.gso.ind.1 | H29: =OUTCODE(Settings!$B$3,"shp",$C$5,$B29,$J$5) -> egy.mit.shp.irn.gso.e.1 | K29: =SHADOW(K19,INDEX(Data_Prices!K:K,MATCH($G29,Data_Prices!$A:$A,0)),K$38) -> 0.67114653 | L29: =SHADOW(L19,INDEX(Data_Prices!L:L,MATCH($G29,Data_Prices!$A:$A,0)),L$38) -> 0.61197798 | M29: =SHADOW(M19,INDEX(Data_Prices!M:M,MATCH($G29,Data_Prices!$A:$A,0)),M$38) -> 0.61180975 | N29: =SHADOW(N19,INDEX(Data_Prices!N:N,MATCH($G29,Data_Prices!$A:$A,0)),N$38) -> 0.6035831 | O29: =SHADOW(O19,INDEX(Data_Prices!O:O,MATCH($G29,Data_Prices!$A:$A,0)),O$38) -> 0.6035831 | P29: =SHADOW(P19,INDEX(Data_Prices!P:P,MATCH($G29,Data_Prices!$A:$A,0)),P$38) -> 0.6035831 | Q29: =SHADOW(Q19,INDEX(Data_Prices!Q:Q,MATCH($G29,Data_Prices!$A:$A,0)),Q$38) -> 0.6035831 | R29: =SHADOW(R19,INDEX(Data_Prices!R:R,MATCH($G29,Data_Prices!$A:$A,0)),R$38) -> 0.6035831 | S29: =SHADOW(S19,INDEX(Data_Prices!S:S,MATCH($G29,Data_Prices!$A:$A,0)),S$38) -> 0.6035831 | T29: =SHADOW(T19,INDEX(Data_Prices!T:T,MATCH($G29,Data_Prices!$A:$A,0)),T$38) -> 0.6035831 | U29: =SHADOW(U19,INDEX(Data_Prices!U:U,MATCH($G29,Data_Prices!$A:$A,0)),U$38) -> 0.6035831 | V29: =SHADOW(V19,INDEX(Data_Prices!V:V,MATCH($G29,Data_Prices!$A:$A,0)),V$38) -> 0.6035831 | W29: =SHADOW(W19,INDEX(Data_Prices!W:W,MATCH($G29,Data_Prices!$A:$A,0)),W$38) -> 0.6035831 | X29: =SHADOW(X19,INDEX(Data_Prices!X:X,MATCH($G29,Data_Prices!$A:$A,0)),X$38) -> 0.6035831 | Y29: =SHADOW(Y19,INDEX(Data_Prices!Y:Y,MATCH($G29,Data_Prices!$A:$A,0)),Y$38) -> 0.6035831 | Z29: =SHADOW(Z19,INDEX(Data_Prices!Z:Z,MATCH($G29,Data_Prices!$A:$A,0)),Z$38) -> 0.6035831 | AA29: =SHADOW(AA19,INDEX(Data_Prices!AA:AA,MATCH($G29,Data_Prices!$A:$A,0)),AA$38) -> 0.6035831 | AB29: =SHADOW(AB19,INDEX(Data_Prices!AB:AB,MATCH($G29,Data_Prices!$A:$A,0)),AB$38) -> 0.6035831 | AC29: =SHADOW(AC19,INDEX(Data_Prices!AC:AC,MATCH($G29,Data_Prices!$A:$A,0)),AC$38) -> 0.6035831 | AD29: =SHADOW(AD19,INDEX(Data_Prices!AD:AD,MATCH($G29,Data_Prices!$A:$A,0)),AD$38) -> 0.6035831 | AE29: =SHADOW(AE19,INDEX(Data_Prices!AE:AE,MATCH($G29,Data_Prices!$A:$A,0)),AE$38) -> 0.6035831
B30: die | C30: =$C$5 -> irn | D30: Diesel | E30: $/liter | F30: shp | G30: =Settings!$B$3&".mit.shp."&$B30&"."&Settings!$B$4&"."&$J$5 -> egy.mit.shp.die.ind.1 | H30: =OUTCODE(Settings!$B$3,"shp",$C$5,$B30,$J$5) -> egy.mit.shp.irn.die.e.1 | K30: =SHADOW(K20,INDEX(Data_Prices!K:K,MATCH($G30,Data_Prices!$A:$A,0)),K$38) -> 0.55971121 | L30: =SHADOW(L20,INDEX(Data_Prices!L:L,MATCH($G30,Data_Prices!$A:$A,0)),L$38) -> 0.49458873 | M30: =SHADOW(M20,INDEX(Data_Prices!M:M,MATCH($G30,Data_Prices!$A:$A,0)),M$38) -> 0.50778655 | N30: =SHADOW(N20,INDEX(Data_Prices!N:N,MATCH($G30,Data_Prices!$A:$A,0)),N$38) -> 0.47043643 | O30: =SHADOW(O20,INDEX(Data_Prices!O:O,MATCH($G30,Data_Prices!$A:$A,0)),O$38) -> 0.47043643 | P30: =SHADOW(P20,INDEX(Data_Prices!P:P,MATCH($G30,Data_Prices!$A:$A,0)),P$38) -> 0.47043643 | Q30: =SHADOW(Q20,INDEX(Data_Prices!Q:Q,MATCH($G30,Data_Prices!$A:$A,0)),Q$38) -> 0.47043643 | R30: =SHADOW(R20,INDEX(Data_Prices!R:R,MATCH($G30,Data_Prices!$A:$A,0)),R$38) -> 0.47043643 | S30: =SHADOW(S20,INDEX(Data_Prices!S:S,MATCH($G30,Data_Prices!$A:$A,0)),S$38) -> 0.47043643 | T30: =SHADOW(T20,INDEX(Data_Prices!T:T,MATCH($G30,Data_Prices!$A:$A,0)),T$38) -> 0.47043643 | U30: =SHADOW(U20,INDEX(Data_Prices!U:U,MATCH($G30,Data_Prices!$A:$A,0)),U$38) -> 0.47043643 | V30: =SHADOW(V20,INDEX(Data_Prices!V:V,MATCH($G30,Data_Prices!$A:$A,0)),V$38) -> 0.47043643 | W30: =SHADOW(W20,INDEX(Data_Prices!W:W,MATCH($G30,Data_Prices!$A:$A,0)),W$38) -> 0.47043643 | X30: =SHADOW(X20,INDEX(Data_Prices!X:X,MATCH($G30,Data_Prices!$A:$A,0)),X$38) -> 0.47043643 | Y30: =SHADOW(Y20,INDEX(Data_Prices!Y:Y,MATCH($G30,Data_Prices!$A:$A,0)),Y$38) -> 0.47043643 | Z30: =SHADOW(Z20,INDEX(Data_Prices!Z:Z,MATCH($G30,Data_Prices!$A:$A,0)),Z$38) -> 0.47043643 | AA30: =SHADOW(AA20,INDEX(Data_Prices!AA:AA,MATCH($G30,Data_Prices!$A:$A,0)),AA$38) -> 0.47043643 | AB30: =SHADOW(AB20,INDEX(Data_Prices!AB:AB,MATCH($G30,Data_Prices!$A:$A,0)),AB$38) -> 0.47043643 | AC30: =SHADOW(AC20,INDEX(Data_Prices!AC:AC,MATCH($G30,Data_Prices!$A:$A,0)),AC$38) -> 0.47043643 | AD30: =SHADOW(AD20,INDEX(Data_Prices!AD:AD,MATCH($G30,Data_Prices!$A:$A,0)),AD$38) -> 0.47043643 | AE30: =SHADOW(AE20,INDEX(Data_Prices!AE:AE,MATCH($G30,Data_Prices!$A:$A,0)),AE$38) -> 0.47043643
B31: lpg | C31: =$C$5 -> irn | D31: LPG | E31: $/liter | F31: shp | G31: =Settings!$B$3&".mit.shp."&$B31&"."&Settings!$B$4&"."&$J$5 -> egy.mit.shp.lpg.ind.1 | H31: =OUTCODE(Settings!$B$3,"shp",$C$5,$B31,$J$5) -> egy.mit.shp.irn.lpg.e.1 | K31: =SHADOW(K21,INDEX(Data_Prices!K:K,MATCH($G31,Data_Prices!$A:$A,0)),K$38) -> 0.20036669 | L31: =SHADOW(L21,INDEX(Data_Prices!L:L,MATCH($G31,Data_Prices!$A:$A,0)),L$38) -> 0.15734474 | M31: =SHADOW(M21,INDEX(Data_Prices!M:M,MATCH($G31,Data_Prices!$A:$A,0)),M$38) -> 0.16448404 | N31: =SHADOW(N21,INDEX(Data_Prices!N:N,MATCH($G31,Data_Prices!$A:$A,0)),N$38) -> 0.15070908 | O31: =SHADOW(O21,INDEX(Data_Prices!O:O,MATCH($G31,Data_Prices!$A:$A,0)),O$38) -> 0.15070908 | P31: =SHADOW(P21,INDEX(Data_Prices!P:P,MATCH($G31,Data_Prices!$A:$A,0)),P$38) -> 0.15070908 | Q31: =SHADOW(Q21,INDEX(Data_Prices!Q:Q,MATCH($G31,Data_Prices!$A:$A,0)),Q$38) -> 0.15070908 | R31: =SHADOW(R21,INDEX(Data_Prices!R:R,MATCH($G31,Data_Prices!$A:$A,0)),R$38) -> 0.15070908 | S31: =SHADOW(S21,INDEX(Data_Prices!S:S,MATCH($G31,Data_Prices!$A:$A,0)),S$38) -> 0.15070908 | T31: =SHADOW(T21,INDEX(Data_Prices!T:T,MATCH($G31,Data_Prices!$A:$A,0)),T$38) -> 0.15070908 | U31: =SHADOW(U21,INDEX(Data_Prices!U:U,MATCH($G31,Data_Prices!$A:$A,0)),U$38) -> 0.15070908 | V31: =SHADOW(V21,INDEX(Data_Prices!V:V,MATCH($G31,Data_Prices!$A:$A,0)),V$38) -> 0.15070908 | W31: =SHADOW(W21,INDEX(Data_Prices!W:W,MATCH($G31,Data_Prices!$A:$A,0)),W$38) -> 0.15070908 | X31: =SHADOW(X21,INDEX(Data_Prices!X:X,MATCH($G31,Data_Prices!$A:$A,0)),X$38) -> 0.15070908 | Y31: =SHADOW(Y21,INDEX(Data_Prices!Y:Y,MATCH($G31,Data_Prices!$A:$A,0)),Y$38) -> 0.15070908 | Z31: =SHADOW(Z21,INDEX(Data_Prices!Z:Z,MATCH($G31,Data_Prices!$A:$A,0)),Z$38) -> 0.15070908 | AA31: =SHADOW(AA21,INDEX(Data_Prices!AA:AA,MATCH($G31,Data_Prices!$A:$A,0)),AA$38) -> 0.15070908 | AB31: =SHADOW(AB21,INDEX(Data_Prices!AB:AB,MATCH($G31,Data_Prices!$A:$A,0)),AB$38) -> 0.15070908 | AC31: =SHADOW(AC21,INDEX(Data_Prices!AC:AC,MATCH($G31,Data_Prices!$A:$A,0)),AC$38) -> 0.15070908 | AD31: =SHADOW(AD21,INDEX(Data_Prices!AD:AD,MATCH($G31,Data_Prices!$A:$A,0)),AD$38) -> 0.15070908 | AE31: =SHADOW(AE21,INDEX(Data_Prices!AE:AE,MATCH($G31,Data_Prices!$A:$A,0)),AE$38) -> 0.15070908
B32: ker | C32: =$C$5 -> irn | D32: Kerosene | E32: $/liter | F32: shp | G32: =Settings!$B$3&".mit.shp."&$B32&"."&Settings!$B$4&"."&$J$5 -> egy.mit.shp.ker.ind.1 | H32: =OUTCODE(Settings!$B$3,"shp",$C$5,$B32,$J$5) -> egy.mit.shp.irn.ker.e.1 | K32: =SHADOW(K22,INDEX(Data_Prices!K:K,MATCH($G32,Data_Prices!$A:$A,0)),K$38) -> 0.48429424 | L32: =SHADOW(L22,INDEX(Data_Prices!L:L,MATCH($G32,Data_Prices!$A:$A,0)),L$38) -> 0.45642817 | M32: =SHADOW(M22,INDEX(Data_Prices!M:M,MATCH($G32,Data_Prices!$A:$A,0)),M$38) -> 0.4316892 | N32: =SHADOW(N22,INDEX(Data_Prices!N:N,MATCH($G32,Data_Prices!$A:$A,0)),N$38) -> 0.42507558 | O32: =SHADOW(O22,INDEX(Data_Prices!O:O,MATCH($G32,Data_Prices!$A:$A,0)),O$38) -> 0.42507558 | P32: =SHADOW(P22,INDEX(Data_Prices!P:P,MATCH($G32,Data_Prices!$A:$A,0)),P$38) -> 0.42507558 | Q32: =SHADOW(Q22,INDEX(Data_Prices!Q:Q,MATCH($G32,Data_Prices!$A:$A,0)),Q$38) -> 0.42507558 | R32: =SHADOW(R22,INDEX(Data_Prices!R:R,MATCH($G32,Data_Prices!$A:$A,0)),R$38) -> 0.42507558 | S32: =SHADOW(S22,INDEX(Data_Prices!S:S,MATCH($G32,Data_Prices!$A:$A,0)),S$38) -> 0.42507558 | T32: =SHADOW(T22,INDEX(Data_Prices!T:T,MATCH($G32,Data_Prices!$A:$A,0)),T$38) -> 0.42507558 | U32: =SHADOW(U22,INDEX(Data_Prices!U:U,MATCH($G32,Data_Prices!$A:$A,0)),U$38) -> 0.42507558 | V32: =SHADOW(V22,INDEX(Data_Prices!V:V,MATCH($G32,Data_Prices!$A:$A,0)),V$38) -> 0.42507558 | W32: =SHADOW(W22,INDEX(Data_Prices!W:W,MATCH($G32,Data_Prices!$A:$A,0)),W$38) -> 0.42507558 | X32: =SHADOW(X22,INDEX(Data_Prices!X:X,MATCH($G32,Data_Prices!$A:$A,0)),X$38) -> 0.42507558 | Y32: =SHADOW(Y22,INDEX(Data_Prices!Y:Y,MATCH($G32,Data_Prices!$A:$A,0)),Y$38) -> 0.42507558 | Z32: =SHADOW(Z22,INDEX(Data_Prices!Z:Z,MATCH($G32,Data_Prices!$A:$A,0)),Z$38) -> 0.42507558 | AA32: =SHADOW(AA22,INDEX(Data_Prices!AA:AA,MATCH($G32,Data_Prices!$A:$A,0)),AA$38) -> 0.42507558 | AB32: =SHADOW(AB22,INDEX(Data_Prices!AB:AB,MATCH($G32,Data_Prices!$A:$A,0)),AB$38) -> 0.42507558 | AC32: =SHADOW(AC22,INDEX(Data_Prices!AC:AC,MATCH($G32,Data_Prices!$A:$A,0)),AC$38) -> 0.42507558 | AD32: =SHADOW(AD22,INDEX(Data_Prices!AD:AD,MATCH($G32,Data_Prices!$A:$A,0)),AD$38) -> 0.42507558 | AE32: =SHADOW(AE22,INDEX(Data_Prices!AE:AE,MATCH($G32,Data_Prices!$A:$A,0)),AE$38) -> 0.42507558
B33: oop | C33: =$C$5 -> irn | D33: Other oil products | E33: $/bbl | F33: shp | G33: =Settings!$B$3&".mit.shp."&$B33&"."&Settings!$B$4&"."&$J$5 -> egy.mit.shp.oop.ind.1 | H33: =OUTCODE(Settings!$B$3,"shp",$C$5,$B33,$J$5) -> egy.mit.shp.irn.oop.e.1 | K33: =SHADOW(K23,INDEX(Data_Prices!K:K,MATCH($G33,Data_Prices!$A:$A,0)),K$38) -> 41.500338 | L33: =SHADOW(L23,INDEX(Data_Prices!L:L,MATCH($G33,Data_Prices!$A:$A,0)),L$38) -> 34.41537 | M33: =SHADOW(M23,INDEX(Data_Prices!M:M,MATCH($G33,Data_Prices!$A:$A,0)),M$38) -> 37.368961 | N33: =SHADOW(N23,INDEX(Data_Prices!N:N,MATCH($G33,Data_Prices!$A:$A,0)),N$38) -> 28.982761 | O33: =SHADOW(O23,INDEX(Data_Prices!O:O,MATCH($G33,Data_Prices!$A:$A,0)),O$38) -> 15 | P33: =SHADOW(P23,INDEX(Data_Prices!P:P,MATCH($G33,Data_Prices!$A:$A,0)),P$38) -> 24.25863 | Q33: =SHADOW(Q23,INDEX(Data_Prices!Q:Q,MATCH($G33,Data_Prices!$A:$A,0)),Q$38) -> 15 | R33: =SHADOW(R23,INDEX(Data_Prices!R:R,MATCH($G33,Data_Prices!$A:$A,0)),R$38) -> 15 | S33: =SHADOW(S23,INDEX(Data_Prices!S:S,MATCH($G33,Data_Prices!$A:$A,0)),S$38) -> 15 | T33: =SHADOW(T23,INDEX(Data_Prices!T:T,MATCH($G33,Data_Prices!$A:$A,0)),T$38) -> 15 | U33: =SHADOW(U23,INDEX(Data_Prices!U:U,MATCH($G33,Data_Prices!$A:$A,0)),U$38) -> 15 | V33: =SHADOW(V23,INDEX(Data_Prices!V:V,MATCH($G33,Data_Prices!$A:$A,0)),V$38) -> 15 | W33: =SHADOW(W23,INDEX(Data_Prices!W:W,MATCH($G33,Data_Prices!$A:$A,0)),W$38) -> 15 | X33: =SHADOW(X23,INDEX(Data_Prices!X:X,MATCH($G33,Data_Prices!$A:$A,0)),X$38) -> 15 | Y33: =SHADOW(Y23,INDEX(Data_Prices!Y:Y,MATCH($G33,Data_Prices!$A:$A,0)),Y$38) -> 15 | Z33: =SHADOW(Z23,INDEX(Data_Prices!Z:Z,MATCH($G33,Data_Prices!$A:$A,0)),Z$38) -> 15 | AA33: =SHADOW(AA23,INDEX(Data_Prices!AA:AA,MATCH($G33,Data_Prices!$A:$A,0)),AA$38) -> 15 | AB33: =SHADOW(AB23,INDEX(Data_Prices!AB:AB,MATCH($G33,Data_Prices!$A:$A,0)),AB$38) -> 15 | AC33: =SHADOW(AC23,INDEX(Data_Prices!AC:AC,MATCH($G33,Data_Prices!$A:$A,0)),AC$38) -> 15 | AD33: =SHADOW(AD23,INDEX(Data_Prices!AD:AD,MATCH($G33,Data_Prices!$A:$A,0)),AD$38) -> 15 | AE33: =SHADOW(AE23,INDEX(Data_Prices!AE:AE,MATCH($G33,Data_Prices!$A:$A,0)),AE$38) -> 15
B34: bio | C34: =$C$5 -> irn | D34: Biomass | E34: $/GJ | F34: shp | G34: =Settings!$B$3&".mit.shp."&$B34&"."&Settings!$B$4&"."&$J$5 -> egy.mit.shp.bio.ind.1 | H34: =OUTCODE(Settings!$B$3,"shp",$C$5,$B34,$J$5) -> egy.mit.shp.irn.bio.e.1 | K34: =SHADOW(K24,INDEX(Data_Prices!K:K,MATCH($G34,Data_Prices!$A:$A,0)),K$38) -> 15.334551 | L34: =SHADOW(L24,INDEX(Data_Prices!L:L,MATCH($G34,Data_Prices!$A:$A,0)),L$38) -> 14.199528 | M34: =SHADOW(M24,INDEX(Data_Prices!M:M,MATCH($G34,Data_Prices!$A:$A,0)),M$38) -> 13.840442 | N34: =SHADOW(N24,INDEX(Data_Prices!N:N,MATCH($G34,Data_Prices!$A:$A,0)),N$38) -> 13.567727 | O34: =SHADOW(O24,INDEX(Data_Prices!O:O,MATCH($G34,Data_Prices!$A:$A,0)),O$38) -> 13.567727 | P34: =SHADOW(P24,INDEX(Data_Prices!P:P,MATCH($G34,Data_Prices!$A:$A,0)),P$38) -> 13.567727 | Q34: =SHADOW(Q24,INDEX(Data_Prices!Q:Q,MATCH($G34,Data_Prices!$A:$A,0)),Q$38) -> 13.567727 | R34: =SHADOW(R24,INDEX(Data_Prices!R:R,MATCH($G34,Data_Prices!$A:$A,0)),R$38) -> 13.567727 | S34: =SHADOW(S24,INDEX(Data_Prices!S:S,MATCH($G34,Data_Prices!$A:$A,0)),S$38) -> 13.567727 | T34: =SHADOW(T24,INDEX(Data_Prices!T:T,MATCH($G34,Data_Prices!$A:$A,0)),T$38) -> 13.567727 | U34: =SHADOW(U24,INDEX(Data_Prices!U:U,MATCH($G34,Data_Prices!$A:$A,0)),U$38) -> 13.567727 | V34: =SHADOW(V24,INDEX(Data_Prices!V:V,MATCH($G34,Data_Prices!$A:$A,0)),V$38) -> 13.567727 | W34: =SHADOW(W24,INDEX(Data_Prices!W:W,MATCH($G34,Data_Prices!$A:$A,0)),W$38) -> 13.567727 | X34: =SHADOW(X24,INDEX(Data_Prices!X:X,MATCH($G34,Data_Prices!$A:$A,0)),X$38) -> 13.567727 | Y34: =SHADOW(Y24,INDEX(Data_Prices!Y:Y,MATCH($G34,Data_Prices!$A:$A,0)),Y$38) -> 13.567727 | Z34: =SHADOW(Z24,INDEX(Data_Prices!Z:Z,MATCH($G34,Data_Prices!$A:$A,0)),Z$38) -> 13.567727 | AA34: =SHADOW(AA24,INDEX(Data_Prices!AA:AA,MATCH($G34,Data_Prices!$A:$A,0)),AA$38) -> 13.567727 | AB34: =SHADOW(AB24,INDEX(Data_Prices!AB:AB,MATCH($G34,Data_Prices!$A:$A,0)),AB$38) -> 13.567727 | AC34: =SHADOW(AC24,INDEX(Data_Prices!AC:AC,MATCH($G34,Data_Prices!$A:$A,0)),AC$38) -> 13.567727 | AD34: =SHADOW(AD24,INDEX(Data_Prices!AD:AD,MATCH($G34,Data_Prices!$A:$A,0)),AD$38) -> 13.567727 | AE34: =SHADOW(AE24,INDEX(Data_Prices!AE:AE,MATCH($G34,Data_Prices!$A:$A,0)),AE$38) -> 13.567727
B35: ren | C35: =$C$5 -> irn | D35: Self-generated renewables | E35: $/kwh | F35: shp | G35: =Settings!$B$3&".mit.shp."&$B35&"."&Settings!$B$4&"."&$J$5 -> egy.mit.shp.ren.ind.1 | H35: =OUTCODE(Settings!$B$3,"shp",$C$5,$B35,$J$5) -> egy.mit.shp.irn.ren.e.1 | K35: =SHADOW(K25,INDEX(Data_Prices!K:K,MATCH($G35,Data_Prices!$A:$A,0)),K$38) -> 0 | L35: =SHADOW(L25,INDEX(Data_Prices!L:L,MATCH($G35,Data_Prices!$A:$A,0)),L$38) -> 0.14404499 | M35: =SHADOW(M25,INDEX(Data_Prices!M:M,MATCH($G35,Data_Prices!$A:$A,0)),M$38) -> 0.14102041 | N35: =SHADOW(N25,INDEX(Data_Prices!N:N,MATCH($G35,Data_Prices!$A:$A,0)),N$38) -> 0.13511636 | O35: =SHADOW(O25,INDEX(Data_Prices!O:O,MATCH($G35,Data_Prices!$A:$A,0)),O$38) -> 0.13098826 | P35: =SHADOW(P25,INDEX(Data_Prices!P:P,MATCH($G35,Data_Prices!$A:$A,0)),P$38) -> 0.12790842 | Q35: =SHADOW(Q25,INDEX(Data_Prices!Q:Q,MATCH($G35,Data_Prices!$A:$A,0)),Q$38) -> 0.12481431 | R35: =SHADOW(R25,INDEX(Data_Prices!R:R,MATCH($G35,Data_Prices!$A:$A,0)),R$38) -> 0.12146026 | S35: =SHADOW(S25,INDEX(Data_Prices!S:S,MATCH($G35,Data_Prices!$A:$A,0)),S$38) -> 0.11795074 | T35: =SHADOW(T25,INDEX(Data_Prices!T:T,MATCH($G35,Data_Prices!$A:$A,0)),T$38) -> 0.11419916 | U35: =SHADOW(U25,INDEX(Data_Prices!U:U,MATCH($G35,Data_Prices!$A:$A,0)),U$38) -> 0.1136651 | V35: =SHADOW(V25,INDEX(Data_Prices!V:V,MATCH($G35,Data_Prices!$A:$A,0)),V$38) -> 0.11301693 | W35: =SHADOW(W25,INDEX(Data_Prices!W:W,MATCH($G35,Data_Prices!$A:$A,0)),W$38) -> 0.11231407 | X35: =SHADOW(X25,INDEX(Data_Prices!X:X,MATCH($G35,Data_Prices!$A:$A,0)),X$38) -> 0.11142204 | Y35: =SHADOW(Y25,INDEX(Data_Prices!Y:Y,MATCH($G35,Data_Prices!$A:$A,0)),Y$38) -> 0.11043412 | Z35: =SHADOW(Z25,INDEX(Data_Prices!Z:Z,MATCH($G35,Data_Prices!$A:$A,0)),Z$38) -> 0.10948397 | AA35: =SHADOW(AA25,INDEX(Data_Prices!AA:AA,MATCH($G35,Data_Prices!$A:$A,0)),AA$38) -> 0.10839192 | AB35: =SHADOW(AB25,INDEX(Data_Prices!AB:AB,MATCH($G35,Data_Prices!$A:$A,0)),AB$38) -> 0.10735443 | AC35: =SHADOW(AC25,INDEX(Data_Prices!AC:AC,MATCH($G35,Data_Prices!$A:$A,0)),AC$38) -> 0.10516868 | AD35: =SHADOW(AD25,INDEX(Data_Prices!AD:AD,MATCH($G35,Data_Prices!$A:$A,0)),AD$38) -> 0.10305798 | AE35: =SHADOW(AE25,INDEX(Data_Prices!AE:AE,MATCH($G35,Data_Prices!$A:$A,0)),AE$38) -> 0.10093184
B36: Sector policy and macro drivers
B37: - | C37: =$C$5 -> irn | D37: Sector coverage factor of the new-policy wedge | E37: share | F37: tcf | G37: =Settings!$B$3&".mit.tcf."&$C$5&"."&$J$5 -> egy.mit.tcf.irn.1 | K37: =INDEX(Data_Prices!K:K,MATCH($G37,Data_Prices!$A:$A,0)) -> 0 | L37: =INDEX(Data_Prices!L:L,MATCH($G37,Data_Prices!$A:$A,0)) -> 0 | M37: =INDEX(Data_Prices!M:M,MATCH($G37,Data_Prices!$A:$A,0)) -> 0 | N37: =INDEX(Data_Prices!N:N,MATCH($G37,Data_Prices!$A:$A,0)) -> 0 | O37: =INDEX(Data_Prices!O:O,MATCH($G37,Data_Prices!$A:$A,0)) -> 0 | P37: =INDEX(Data_Prices!P:P,MATCH($G37,Data_Prices!$A:$A,0)) -> 0 | Q37: =INDEX(Data_Prices!Q:Q,MATCH($G37,Data_Prices!$A:$A,0)) -> 0 | R37: =INDEX(Data_Prices!R:R,MATCH($G37,Data_Prices!$A:$A,0)) -> 0 | S37: =INDEX(Data_Prices!S:S,MATCH($G37,Data_Prices!$A:$A,0)) -> 0 | T37: =INDEX(Data_Prices!T:T,MATCH($G37,Data_Prices!$A:$A,0)) -> 0 | U37: =INDEX(Data_Prices!U:U,MATCH($G37,Data_Prices!$A:$A,0)) -> 0 | V37: =INDEX(Data_Prices!V:V,MATCH($G37,Data_Prices!$A:$A,0)) -> 0 | W37: =INDEX(Data_Prices!W:W,MATCH($G37,Data_Prices!$A:$A,0)) -> 0 | X37: =INDEX(Data_Prices!X:X,MATCH($G37,Data_Prices!$A:$A,0)) -> 0 | Y37: =INDEX(Data_Prices!Y:Y,MATCH($G37,Data_Prices!$A:$A,0)) -> 0 | Z37: =INDEX(Data_Prices!Z:Z,MATCH($G37,Data_Prices!$A:$A,0)) -> 0 | AA37: =INDEX(Data_Prices!AA:AA,MATCH($G37,Data_Prices!$A:$A,0)) -> 0 | AB37: =INDEX(Data_Prices!AB:AB,MATCH($G37,Data_Prices!$A:$A,0)) -> 0 | AC37: =INDEX(Data_Prices!AC:AC,MATCH($G37,Data_Prices!$A:$A,0)) -> 0 | AD37: =INDEX(Data_Prices!AD:AD,MATCH($G37,Data_Prices!$A:$A,0)) -> 0 | AE37: =INDEX(Data_Prices!AE:AE,MATCH($G37,Data_Prices!$A:$A,0)) -> 0
B38: - | C38: =$C$5 -> irn | D38: Share of shadow price acting on efficiency | E38: share | F38: ssc | G38: =Settings!$B$3&".mit.ssc."&$C$5&"."&$J$5 -> egy.mit.ssc.irn.1 | K38: =INDEX(Data_Prices!K:K,MATCH($G38,Data_Prices!$A:$A,0)) -> 0 | L38: =INDEX(Data_Prices!L:L,MATCH($G38,Data_Prices!$A:$A,0)) -> 0 | M38: =INDEX(Data_Prices!M:M,MATCH($G38,Data_Prices!$A:$A,0)) -> 0 | N38: =INDEX(Data_Prices!N:N,MATCH($G38,Data_Prices!$A:$A,0)) -> 0 | O38: =INDEX(Data_Prices!O:O,MATCH($G38,Data_Prices!$A:$A,0)) -> 0 | P38: =INDEX(Data_Prices!P:P,MATCH($G38,Data_Prices!$A:$A,0)) -> 0 | Q38: =INDEX(Data_Prices!Q:Q,MATCH($G38,Data_Prices!$A:$A,0)) -> 0 | R38: =INDEX(Data_Prices!R:R,MATCH($G38,Data_Prices!$A:$A,0)) -> 0 | S38: =INDEX(Data_Prices!S:S,MATCH($G38,Data_Prices!$A:$A,0)) -> 0 | T38: =INDEX(Data_Prices!T:T,MATCH($G38,Data_Prices!$A:$A,0)) -> 0 | U38: =INDEX(Data_Prices!U:U,MATCH($G38,Data_Prices!$A:$A,0)) -> 0 | V38: =INDEX(Data_Prices!V:V,MATCH($G38,Data_Prices!$A:$A,0)) -> 0 | W38: =INDEX(Data_Prices!W:W,MATCH($G38,Data_Prices!$A:$A,0)) -> 0 | X38: =INDEX(Data_Prices!X:X,MATCH($G38,Data_Prices!$A:$A,0)) -> 0 | Y38: =INDEX(Data_Prices!Y:Y,MATCH($G38,Data_Prices!$A:$A,0)) -> 0 | Z38: =INDEX(Data_Prices!Z:Z,MATCH($G38,Data_Prices!$A:$A,0)) -> 0 | AA38: =INDEX(Data_Prices!AA:AA,MATCH($G38,Data_Prices!$A:$A,0)) -> 0 | AB38: =INDEX(Data_Prices!AB:AB,MATCH($G38,Data_Prices!$A:$A,0)) -> 0 | AC38: =INDEX(Data_Prices!AC:AC,MATCH($G38,Data_Prices!$A:$A,0)) -> 0 | AD38: =INDEX(Data_Prices!AD:AD,MATCH($G38,Data_Prices!$A:$A,0)) -> 0 | AE38: =INDEX(Data_Prices!AE:AE,MATCH($G38,Data_Prices!$A:$A,0)) -> 0
B39: - | C39: =$C$5 -> irn | D39: Post-policy real GDP growth | E39: % | F39: g | G39: =Settings!$B$3&".mit.gdp.pos.pct."&$J$5 -> egy.mit.gdp.pos.pct.1 | K39: =INDEX(Data_Macro!K:K,MATCH($G39,Data_Macro!$A:$A,0)) -> 0 | L39: =INDEX(Data_Macro!L:L,MATCH($G39,Data_Macro!$A:$A,0)) -> 0.06651345 | M39: =INDEX(Data_Macro!M:M,MATCH($G39,Data_Macro!$A:$A,0)) -> 0.03760281 | N39: =INDEX(Data_Macro!N:N,MATCH($G39,Data_Macro!$A:$A,0)) -> 0.02398801 | O39: =INDEX(Data_Macro!O:O,MATCH($G39,Data_Macro!$A:$A,0)) -> 0.04392387 | P39: =INDEX(Data_Macro!P:P,MATCH($G39,Data_Macro!$A:$A,0)) -> 0.04239706 | Q39: =INDEX(Data_Macro!Q:Q,MATCH($G39,Data_Macro!$A:$A,0)) -> 0.04829218 | R39: =INDEX(Data_Macro!R:R,MATCH($G39,Data_Macro!$A:$A,0)) -> 0.05535316 | S39: =INDEX(Data_Macro!S:S,MATCH($G39,Data_Macro!$A:$A,0)) -> 0.05226606 | T39: =INDEX(Data_Macro!T:T,MATCH($G39,Data_Macro!$A:$A,0)) -> 0.04841877 | U39: =INDEX(Data_Macro!U:U,MATCH($G39,Data_Macro!$A:$A,0)) -> 0.04788736 | V39: =INDEX(Data_Macro!V:V,MATCH($G39,Data_Macro!$A:$A,0)) -> 0.04735595 | W39: =INDEX(Data_Macro!W:W,MATCH($G39,Data_Macro!$A:$A,0)) -> 0.04682454 | X39: =INDEX(Data_Macro!X:X,MATCH($G39,Data_Macro!$A:$A,0)) -> 0.04629313 | Y39: =INDEX(Data_Macro!Y:Y,MATCH($G39,Data_Macro!$A:$A,0)) -> 0.04576172 | Z39: =INDEX(Data_Macro!Z:Z,MATCH($G39,Data_Macro!$A:$A,0)) -> 0.04523031 | AA39: =INDEX(Data_Macro!AA:AA,MATCH($G39,Data_Macro!$A:$A,0)) -> 0.0446989 | AB39: =INDEX(Data_Macro!AB:AB,MATCH($G39,Data_Macro!$A:$A,0)) -> 0.04416749 | AC39: =INDEX(Data_Macro!AC:AC,MATCH($G39,Data_Macro!$A:$A,0)) -> 0.04363608 | AD39: =INDEX(Data_Macro!AD:AD,MATCH($G39,Data_Macro!$A:$A,0)) -> 0.04310467 | AE39: =INDEX(Data_Macro!AE:AE,MATCH($G39,Data_Macro!$A:$A,0)) -> 0.04257326
B40: - | C40: =$C$5 -> irn | D40: Income-elasticity discount factor | E40: ratio | F40: delta | G40: =Settings!$B$3&".mit.inc.ela.adj."&$J$5 -> egy.mit.inc.ela.adj.1 | K40: =INDEX(Data_Macro!K:K,MATCH($G40,Data_Macro!$A:$A,0)) -> 0 | L40: =INDEX(Data_Macro!L:L,MATCH($G40,Data_Macro!$A:$A,0)) -> 1.0271517 | M40: =INDEX(Data_Macro!M:M,MATCH($G40,Data_Macro!$A:$A,0)) -> 1.0271517 | N40: =INDEX(Data_Macro!N:N,MATCH($G40,Data_Macro!$A:$A,0)) -> 1.0205698 | O40: =INDEX(Data_Macro!O:O,MATCH($G40,Data_Macro!$A:$A,0)) -> 1.0173344 | P40: =INDEX(Data_Macro!P:P,MATCH($G40,Data_Macro!$A:$A,0)) -> 1.0076683 | Q40: =INDEX(Data_Macro!Q:Q,MATCH($G40,Data_Macro!$A:$A,0)) -> 1.0007443 | R40: =INDEX(Data_Macro!R:R,MATCH($G40,Data_Macro!$A:$A,0)) -> 0.99188649 | S40: =INDEX(Data_Macro!S:S,MATCH($G40,Data_Macro!$A:$A,0)) -> 0.9806554 | T40: =INDEX(Data_Macro!T:T,MATCH($G40,Data_Macro!$A:$A,0)) -> 0.9702094 | U40: =INDEX(Data_Macro!U:U,MATCH($G40,Data_Macro!$A:$A,0)) -> 0.96419266 | V40: =INDEX(Data_Macro!V:V,MATCH($G40,Data_Macro!$A:$A,0)) -> 0.96161287 | W40: =INDEX(Data_Macro!W:W,MATCH($G40,Data_Macro!$A:$A,0)) -> 0.95919845 | X40: =INDEX(Data_Macro!X:X,MATCH($G40,Data_Macro!$A:$A,0)) -> 0.95695125 | Y40: =INDEX(Data_Macro!Y:Y,MATCH($G40,Data_Macro!$A:$A,0)) -> 0.95487298 | Z40: =INDEX(Data_Macro!Z:Z,MATCH($G40,Data_Macro!$A:$A,0)) -> 0.95296514 | AA40: =INDEX(Data_Macro!AA:AA,MATCH($G40,Data_Macro!$A:$A,0)) -> 0.9512291 | AB40: =INDEX(Data_Macro!AB:AB,MATCH($G40,Data_Macro!$A:$A,0)) -> 0.94966609 | AC40: =INDEX(Data_Macro!AC:AC,MATCH($G40,Data_Macro!$A:$A,0)) -> 0.94827716 | AD40: =INDEX(Data_Macro!AD:AD,MATCH($G40,Data_Macro!$A:$A,0)) -> 0.94706328 | AE40: =INDEX(Data_Macro!AE:AE,MATCH($G40,Data_Macro!$A:$A,0)) -> 0.94602527
B41: - | C41: =$C$5 -> irn | D41: Exogenous shock on energy consumption | E41: ratio | F41: psi | G41: =Settings!$B$3&".mit.shock."&$J$5 -> egy.mit.shock.1 | K41: =INDEX(Data_Macro!K:K,MATCH($G41,Data_Macro!$A:$A,0)) -> 0 | L41: =INDEX(Data_Macro!L:L,MATCH($G41,Data_Macro!$A:$A,0)) -> 0 | M41: =INDEX(Data_Macro!M:M,MATCH($G41,Data_Macro!$A:$A,0)) -> -0.20813308 | N41: =INDEX(Data_Macro!N:N,MATCH($G41,Data_Macro!$A:$A,0)) -> 0.092371429 | O41: =INDEX(Data_Macro!O:O,MATCH($G41,Data_Macro!$A:$A,0)) -> 0 | P41: =INDEX(Data_Macro!P:P,MATCH($G41,Data_Macro!$A:$A,0)) -> 0 | Q41: =INDEX(Data_Macro!Q:Q,MATCH($G41,Data_Macro!$A:$A,0)) -> 0 | R41: =INDEX(Data_Macro!R:R,MATCH($G41,Data_Macro!$A:$A,0)) -> 0 | S41: =INDEX(Data_Macro!S:S,MATCH($G41,Data_Macro!$A:$A,0)) -> 0 | T41: =INDEX(Data_Macro!T:T,MATCH($G41,Data_Macro!$A:$A,0)) -> 0 | U41: =INDEX(Data_Macro!U:U,MATCH($G41,Data_Macro!$A:$A,0)) -> 0 | V41: =INDEX(Data_Macro!V:V,MATCH($G41,Data_Macro!$A:$A,0)) -> 0 | W41: =INDEX(Data_Macro!W:W,MATCH($G41,Data_Macro!$A:$A,0)) -> 0 | X41: =INDEX(Data_Macro!X:X,MATCH($G41,Data_Macro!$A:$A,0)) -> 0 | Y41: =INDEX(Data_Macro!Y:Y,MATCH($G41,Data_Macro!$A:$A,0)) -> 0 | Z41: =INDEX(Data_Macro!Z:Z,MATCH($G41,Data_Macro!$A:$A,0)) -> 0 | AA41: =INDEX(Data_Macro!AA:AA,MATCH($G41,Data_Macro!$A:$A,0)) -> 0 | AB41: =INDEX(Data_Macro!AB:AB,MATCH($G41,Data_Macro!$A:$A,0)) -> 0 | AC41: =INDEX(Data_Macro!AC:AC,MATCH($G41,Data_Macro!$A:$A,0)) -> 0 | AD41: =INDEX(Data_Macro!AD:AD,MATCH($G41,Data_Macro!$A:$A,0)) -> 0 | AE41: =INDEX(Data_Macro!AE:AE,MATCH($G41,Data_Macro!$A:$A,0)) -> 0
B42: Kernel parameters (looked up from Data_Elast; column = Settings elasticity group)
B43: Fuel | C43: Sector | D43: Description | E43: Income el. (eY) | F43: Usage el. (eU) | G43: Efficiency el. (eF) | H43: AEEI (a) | I43: Add. efficiency (a+) | J43: Elasticity fuel group
B44: coa | C44: =$C$5 -> irn | D44: Parameters: Coal | E44: =ELAST("el_inc",$J44,Settings!$B$5) -> 0.5 | F44: =ELAST("el_dem",$J44,Settings!$B$5) -> -0.3 | G44: =ELAST("el_eff",$J44,Settings!$B$5) -> -0.4 | H44: =ELAST("eff_imp",INDEX(Data_Elast!$K:$K,MATCH($B44,Data_Elast!$I:$I,0)),Settings!$B$5) -> 0.005 | I44: =Settings!$B$7 -> 0 | J44: =INDEX(Data_Elast!$J:$J,MATCH($B44,Data_Elast!$I:$I,0)) -> coa
B45: nga | C45: =$C$5 -> irn | D45: Parameters: Natural gas | E45: =ELAST("el_inc",$J45,Settings!$B$5) -> 1 | F45: =ELAST("el_dem",$J45,Settings!$B$5) -> -0.5 | G45: =ELAST("el_eff",$J45,Settings!$B$5) -> -0.5 | H45: =ELAST("eff_imp",INDEX(Data_Elast!$K:$K,MATCH($B45,Data_Elast!$I:$I,0)),Settings!$B$5) -> 0.01 | I45: =Settings!$B$7 -> 0 | J45: =INDEX(Data_Elast!$J:$J,MATCH($B45,Data_Elast!$I:$I,0)) -> nga
B46: gso | C46: =$C$5 -> irn | D46: Parameters: Gasoline | E46: =ELAST("el_inc",$J46,Settings!$B$5) -> 0.5 | F46: =ELAST("el_dem",$J46,Settings!$B$5) -> -0.4 | G46: =ELAST("el_eff",$J46,Settings!$B$5) -> -0.7 | H46: =ELAST("eff_imp",INDEX(Data_Elast!$K:$K,MATCH($B46,Data_Elast!$I:$I,0)),Settings!$B$5) -> 0.005 | I46: =Settings!$B$7 -> 0 | J46: =INDEX(Data_Elast!$J:$J,MATCH($B46,Data_Elast!$I:$I,0)) -> gso
B47: die | C47: =$C$5 -> irn | D47: Parameters: Diesel | E47: =ELAST("el_inc",$J47,Settings!$B$5) -> 0.5 | F47: =ELAST("el_dem",$J47,Settings!$B$5) -> -0.7 | G47: =ELAST("el_eff",$J47,Settings!$B$5) -> -1.2 | H47: =ELAST("eff_imp",INDEX(Data_Elast!$K:$K,MATCH($B47,Data_Elast!$I:$I,0)),Settings!$B$5) -> 0.005 | I47: =Settings!$B$7 -> 0 | J47: =INDEX(Data_Elast!$J:$J,MATCH($B47,Data_Elast!$I:$I,0)) -> die
B48: lpg | C48: =$C$5 -> irn | D48: Parameters: LPG | E48: =ELAST("el_inc",$J48,Settings!$B$5) -> 0.8 | F48: =ELAST("el_dem",$J48,Settings!$B$5) -> -0.4 | G48: =ELAST("el_eff",$J48,Settings!$B$5) -> -0.4 | H48: =ELAST("eff_imp",INDEX(Data_Elast!$K:$K,MATCH($B48,Data_Elast!$I:$I,0)),Settings!$B$5) -> 0.005 | I48: =Settings!$B$7 -> 0 | J48: =INDEX(Data_Elast!$J:$J,MATCH($B48,Data_Elast!$I:$I,0)) -> oil
B49: ker | C49: =$C$5 -> irn | D49: Parameters: Kerosene | E49: =ELAST("el_inc",$J49,Settings!$B$5) -> 0.8 | F49: =ELAST("el_dem",$J49,Settings!$B$5) -> -0.4 | G49: =ELAST("el_eff",$J49,Settings!$B$5) -> -0.4 | H49: =ELAST("eff_imp",INDEX(Data_Elast!$K:$K,MATCH($B49,Data_Elast!$I:$I,0)),Settings!$B$5) -> 0.005 | I49: =Settings!$B$7 -> 0 | J49: =INDEX(Data_Elast!$J:$J,MATCH($B49,Data_Elast!$I:$I,0)) -> oil
B50: oop | C50: =$C$5 -> irn | D50: Parameters: Other oil products | E50: =ELAST("el_inc",$J50,Settings!$B$5) -> 0.8 | F50: =ELAST("el_dem",$J50,Settings!$B$5) -> -0.4 | G50: =ELAST("el_eff",$J50,Settings!$B$5) -> -0.4 | H50: =ELAST("eff_imp",INDEX(Data_Elast!$K:$K,MATCH($B50,Data_Elast!$I:$I,0)),Settings!$B$5) -> 0.005 | I50: =Settings!$B$7 -> 0 | J50: =INDEX(Data_Elast!$J:$J,MATCH($B50,Data_Elast!$I:$I,0)) -> oil
B51: bio | C51: =$C$5 -> irn | D51: Parameters: Biomass | E51: =ELAST("el_inc",$J51,Settings!$B$5) -> 0.1 | F51: =ELAST("el_dem",$J51,Settings!$B$5) -> -0.3 | G51: =ELAST("el_eff",$J51,Settings!$B$5) -> -0.2 | H51: =ELAST("eff_imp",INDEX(Data_Elast!$K:$K,MATCH($B51,Data_Elast!$I:$I,0)),Settings!$B$5) -> 0.005 | I51: =Settings!$B$7 -> 0 | J51: =INDEX(Data_Elast!$J:$J,MATCH($B51,Data_Elast!$I:$I,0)) -> bio
B52: ren | C52: =$C$5 -> irn | D52: Parameters: Self-generated renewables | E52: =ELAST("el_inc",$J52,Settings!$B$5) -> 0.8 | F52: =ELAST("el_dem",$J52,Settings!$B$5) -> -0.5 | G52: =ELAST("el_eff",$J52,Settings!$B$5) -> -0.4 | H52: =ELAST("eff_imp",INDEX(Data_Elast!$K:$K,MATCH($B52,Data_Elast!$I:$I,0)),Settings!$B$5) -> 0.005 | I52: =Settings!$B$7 -> 0 | J52: =INDEX(Data_Elast!$J:$J,MATCH($B52,Data_Elast!$I:$I,0)) -> ren
B53: Energy use: base year from Data_Energy, later years from the kernel (= CPAT ener rows)
B54: coa | C54: =$C$5 -> irn | D54: Coal | E54: ktoe | F54: ener | G54: =Settings!$B$3&".mit.enc."&$B54 -> egy.mit.enc.coa | H54: =OUTCODE(Settings!$B$3,"ener",$C$5,$B54,$J$5) -> egy.mit.ener.irn.coa.e.1 | L54: =INDEX(Data_Energy!$D$3:$U$22,MATCH($B54,Data_Energy!$C$3:$C$22,0),MATCH($C54,Data_Energy!$D$2:$U$2,0)) -> 232.65735 | M54: =FUELUSE(L54,L17,M17,L27,M27,M$39,M$40,M$41,$E44,$F44,$G44,$H44,$I44) -> 189.45266 | N54: =FUELUSE(M54,M17,N17,M27,N27,N$39,N$40,N$41,$E44,$F44,$G44,$H44,$I44) -> 217.72884 | O54: =FUELUSE(N54,N17,O17,N27,O27,O$39,O$40,O$41,$E44,$F44,$G44,$H44,$I44) -> 237.89793 | P54: =FUELUSE(O54,O17,P17,O27,P27,P$39,P$40,P$41,$E44,$F44,$G44,$H44,$I44) -> 232.65007 | Q54: =FUELUSE(P54,P17,Q17,P27,Q27,Q$39,Q$40,Q$41,$E44,$F44,$G44,$H44,$I44) -> 235.34294 | R54: =FUELUSE(Q54,Q17,R17,Q27,R27,R$39,R$40,R$41,$E44,$F44,$G44,$H44,$I44) -> 241.85374 | S54: =FUELUSE(R54,R17,S17,R27,S27,S$39,S$40,S$41,$E44,$F44,$G44,$H44,$I44) -> 248.19369 | T54: =FUELUSE(S54,S17,T17,S27,T27,T$39,T$40,T$41,$E44,$F44,$G44,$H44,$I44) -> 254.2678 | ... AE54: =FUELUSE(AD54,AD17,AE17,AD27,AE27,AE$39,AE$40,AE$41,$E44,$F44,$G44,$H44,$I44) -> 310.04019
B55: nga | C55: =$C$5 -> irn | D55: Natural gas | E55: ktoe | F55: ener | G55: =Settings!$B$3&".mit.enc."&$B55 -> egy.mit.enc.nga | H55: =OUTCODE(Settings!$B$3,"ener",$C$5,$B55,$J$5) -> egy.mit.ener.irn.nga.e.1 | L55: =INDEX(Data_Energy!$D$3:$U$22,MATCH($B55,Data_Energy!$C$3:$C$22,0),MATCH($C55,Data_Energy!$D$2:$U$2,0)) -> 1669.0567 | M55: =FUELUSE(L55,L18,M18,L28,M28,M$39,M$40,M$41,$E45,$F45,$G45,$H45,$I45) -> 1431.7775 | N55: =FUELUSE(M55,M18,N18,M28,N28,N$39,N$40,N$41,$E45,$F45,$G45,$H45,$I45) -> 1603.1181 | O55: =FUELUSE(N55,N18,O18,N28,O28,O$39,O$40,O$41,$E45,$F45,$G45,$H45,$I45) -> 1666.4691 | P55: =FUELUSE(O55,O18,P18,O28,P28,P$39,P$40,P$41,$E45,$F45,$G45,$H45,$I45) -> 1729.052 | Q55: =FUELUSE(P55,P18,Q18,P28,Q28,Q$39,Q$40,Q$41,$E45,$F45,$G45,$H45,$I45) -> 1803.6196 | R55: =FUELUSE(Q55,Q18,R18,Q28,R28,R$39,R$40,R$41,$E45,$F45,$G45,$H45,$I45) -> 1893.1814 | S55: =FUELUSE(R55,R18,S18,R28,S28,S$39,S$40,S$41,$E45,$F45,$G45,$H45,$I45) -> 1980.2914 | T55: =FUELUSE(S55,S18,T18,S28,T28,T$39,T$40,T$41,$E45,$F45,$G45,$H45,$I45) -> 2062.9631 | ... AE55: =FUELUSE(AD55,AD18,AE18,AD28,AE28,AE$39,AE$40,AE$41,$E45,$F45,$G45,$H45,$I45) -> 3106.9586
B56: gso | C56: =$C$5 -> irn | D56: Gasoline | E56: ktoe | F56: ener | G56: =Settings!$B$3&".mit.enc."&$B56 -> egy.mit.enc.gso | H56: =OUTCODE(Settings!$B$3,"ener",$C$5,$B56,$J$5) -> egy.mit.ener.irn.gso.e.1 | L56: =INDEX(Data_Energy!$D$3:$U$22,MATCH($B56,Data_Energy!$C$3:$C$22,0),MATCH($C56,Data_Energy!$D$2:$U$2,0)) -> 0 | M56: =FUELUSE(L56,L19,M19,L29,M29,M$39,M$40,M$41,$E46,$F46,$G46,$H46,$I46) -> 0 | N56: =FUELUSE(M56,M19,N19,M29,N29,N$39,N$40,N$41,$E46,$F46,$G46,$H46,$I46) -> 0 | O56: =FUELUSE(N56,N19,O19,N29,O29,O$39,O$40,O$41,$E46,$F46,$G46,$H46,$I46) -> 0 | P56: =FUELUSE(O56,O19,P19,O29,P29,P$39,P$40,P$41,$E46,$F46,$G46,$H46,$I46) -> 0 | Q56: =FUELUSE(P56,P19,Q19,P29,Q29,Q$39,Q$40,Q$41,$E46,$F46,$G46,$H46,$I46) -> 0 | R56: =FUELUSE(Q56,Q19,R19,Q29,R29,R$39,R$40,R$41,$E46,$F46,$G46,$H46,$I46) -> 0 | S56: =FUELUSE(R56,R19,S19,R29,S29,S$39,S$40,S$41,$E46,$F46,$G46,$H46,$I46) -> 0 | T56: =FUELUSE(S56,S19,T19,S29,T29,T$39,T$40,T$41,$E46,$F46,$G46,$H46,$I46) -> 0 | ... AE56: =FUELUSE(AD56,AD19,AE19,AD29,AE29,AE$39,AE$40,AE$41,$E46,$F46,$G46,$H46,$I46) -> 0
B57: die | C57: =$C$5 -> irn | D57: Diesel | E57: ktoe | F57: ener | G57: =Settings!$B$3&".mit.enc."&$B57 -> egy.mit.enc.die | H57: =OUTCODE(Settings!$B$3,"ener",$C$5,$B57,$J$5) -> egy.mit.ener.irn.die.e.1 | L57: =INDEX(Data_Energy!$D$3:$U$22,MATCH($B57,Data_Energy!$C$3:$C$22,0),MATCH($C57,Data_Energy!$D$2:$U$2,0)) -> 0 | M57: =FUELUSE(L57,L20,M20,L30,M30,M$39,M$40,M$41,$E47,$F47,$G47,$H47,$I47) -> 0 | N57: =FUELUSE(M57,M20,N20,M30,N30,N$39,N$40,N$41,$E47,$F47,$G47,$H47,$I47) -> 0 | O57: =FUELUSE(N57,N20,O20,N30,O30,O$39,O$40,O$41,$E47,$F47,$G47,$H47,$I47) -> 0 | P57: =FUELUSE(O57,O20,P20,O30,P30,P$39,P$40,P$41,$E47,$F47,$G47,$H47,$I47) -> 0 | Q57: =FUELUSE(P57,P20,Q20,P30,Q30,Q$39,Q$40,Q$41,$E47,$F47,$G47,$H47,$I47) -> 0 | R57: =FUELUSE(Q57,Q20,R20,Q30,R30,R$39,R$40,R$41,$E47,$F47,$G47,$H47,$I47) -> 0 | S57: =FUELUSE(R57,R20,S20,R30,S30,S$39,S$40,S$41,$E47,$F47,$G47,$H47,$I47) -> 0 | T57: =FUELUSE(S57,S20,T20,S30,T30,T$39,T$40,T$41,$E47,$F47,$G47,$H47,$I47) -> 0 | ... AE57: =FUELUSE(AD57,AD20,AE20,AD30,AE30,AE$39,AE$40,AE$41,$E47,$F47,$G47,$H47,$I47) -> 0
B58: lpg | C58: =$C$5 -> irn | D58: LPG | E58: ktoe | F58: ener | G58: =Settings!$B$3&".mit.enc."&$B58 -> egy.mit.enc.lpg | H58: =OUTCODE(Settings!$B$3,"ener",$C$5,$B58,$J$5) -> egy.mit.ener.irn.lpg.e.1 | L58: =INDEX(Data_Energy!$D$3:$U$22,MATCH($B58,Data_Energy!$C$3:$C$22,0),MATCH($C58,Data_Energy!$D$2:$U$2,0)) -> 0 | M58: =FUELUSE(L58,L21,M21,L31,M31,M$39,M$40,M$41,$E48,$F48,$G48,$H48,$I48) -> 0 | N58: =FUELUSE(M58,M21,N21,M31,N31,N$39,N$40,N$41,$E48,$F48,$G48,$H48,$I48) -> 0 | O58: =FUELUSE(N58,N21,O21,N31,O31,O$39,O$40,O$41,$E48,$F48,$G48,$H48,$I48) -> 0 | P58: =FUELUSE(O58,O21,P21,O31,P31,P$39,P$40,P$41,$E48,$F48,$G48,$H48,$I48) -> 0 | Q58: =FUELUSE(P58,P21,Q21,P31,Q31,Q$39,Q$40,Q$41,$E48,$F48,$G48,$H48,$I48) -> 0 | R58: =FUELUSE(Q58,Q21,R21,Q31,R31,R$39,R$40,R$41,$E48,$F48,$G48,$H48,$I48) -> 0 | S58: =FUELUSE(R58,R21,S21,R31,S31,S$39,S$40,S$41,$E48,$F48,$G48,$H48,$I48) -> 0 | T58: =FUELUSE(S58,S21,T21,S31,T31,T$39,T$40,T$41,$E48,$F48,$G48,$H48,$I48) -> 0 | ... AE58: =FUELUSE(AD58,AD21,AE21,AD31,AE31,AE$39,AE$40,AE$41,$E48,$F48,$G48,$H48,$I48) -> 0
B59: ker | C59: =$C$5 -> irn | D59: Kerosene | E59: ktoe | F59: ener | G59: =Settings!$B$3&".mit.enc."&$B59 -> egy.mit.enc.ker | H59: =OUTCODE(Settings!$B$3,"ener",$C$5,$B59,$J$5) -> egy.mit.ener.irn.ker.e.1 | L59: =INDEX(Data_Energy!$D$3:$U$22,MATCH($B59,Data_Energy!$C$3:$C$22,0),MATCH($C59,Data_Energy!$D$2:$U$2,0)) -> 0 | M59: =FUELUSE(L59,L22,M22,L32,M32,M$39,M$40,M$41,$E49,$F49,$G49,$H49,$I49) -> 0 | N59: =FUELUSE(M59,M22,N22,M32,N32,N$39,N$40,N$41,$E49,$F49,$G49,$H49,$I49) -> 0 | O59: =FUELUSE(N59,N22,O22,N32,O32,O$39,O$40,O$41,$E49,$F49,$G49,$H49,$I49) -> 0 | P59: =FUELUSE(O59,O22,P22,O32,P32,P$39,P$40,P$41,$E49,$F49,$G49,$H49,$I49) -> 0 | Q59: =FUELUSE(P59,P22,Q22,P32,Q32,Q$39,Q$40,Q$41,$E49,$F49,$G49,$H49,$I49) -> 0 | R59: =FUELUSE(Q59,Q22,R22,Q32,R32,R$39,R$40,R$41,$E49,$F49,$G49,$H49,$I49) -> 0 | S59: =FUELUSE(R59,R22,S22,R32,S32,S$39,S$40,S$41,$E49,$F49,$G49,$H49,$I49) -> 0 | T59: =FUELUSE(S59,S22,T22,S32,T32,T$39,T$40,T$41,$E49,$F49,$G49,$H49,$I49) -> 0 | ... AE59: =FUELUSE(AD59,AD22,AE22,AD32,AE32,AE$39,AE$40,AE$41,$E49,$F49,$G49,$H49,$I49) -> 0
B60: oop | C60: =$C$5 -> irn | D60: Other oil products | E60: ktoe | F60: ener | G60: =Settings!$B$3&".mit.enc."&$B60 -> egy.mit.enc.oop | H60: =OUTCODE(Settings!$B$3,"ener",$C$5,$B60,$J$5) -> egy.mit.ener.irn.oop.e.1 | L60: =INDEX(Data_Energy!$D$3:$U$22,MATCH($B60,Data_Energy!$C$3:$C$22,0),MATCH($C60,Data_Energy!$D$2:$U$2,0)) -> 0 | M60: =FUELUSE(L60,L23,M23,L33,M33,M$39,M$40,M$41,$E50,$F50,$G50,$H50,$I50) -> 0 | N60: =FUELUSE(M60,M23,N23,M33,N33,N$39,N$40,N$41,$E50,$F50,$G50,$H50,$I50) -> 0 | O60: =FUELUSE(N60,N23,O23,N33,O33,O$39,O$40,O$41,$E50,$F50,$G50,$H50,$I50) -> 0 | P60: =FUELUSE(O60,O23,P23,O33,P33,P$39,P$40,P$41,$E50,$F50,$G50,$H50,$I50) -> 0 | Q60: =FUELUSE(P60,P23,Q23,P33,Q33,Q$39,Q$40,Q$41,$E50,$F50,$G50,$H50,$I50) -> 0 | R60: =FUELUSE(Q60,Q23,R23,Q33,R33,R$39,R$40,R$41,$E50,$F50,$G50,$H50,$I50) -> 0 | S60: =FUELUSE(R60,R23,S23,R33,S33,S$39,S$40,S$41,$E50,$F50,$G50,$H50,$I50) -> 0 | T60: =FUELUSE(S60,S23,T23,S33,T33,T$39,T$40,T$41,$E50,$F50,$G50,$H50,$I50) -> 0 | ... AE60: =FUELUSE(AD60,AD23,AE23,AD33,AE33,AE$39,AE$40,AE$41,$E50,$F50,$G50,$H50,$I50) -> 0
B61: bio | C61: =$C$5 -> irn | D61: Biomass | E61: ktoe | F61: ener | G61: =Settings!$B$3&".mit.enc."&$B61 -> egy.mit.enc.bio | H61: =OUTCODE(Settings!$B$3,"ener",$C$5,$B61,$J$5) -> egy.mit.ener.irn.bio.e.1 | L61: =INDEX(Data_Energy!$D$3:$U$22,MATCH($B61,Data_Energy!$C$3:$C$22,0),MATCH($C61,Data_Energy!$D$2:$U$2,0)) -> 0 | M61: =FUELUSE(L61,L24,M24,L34,M34,M$39,M$40,M$41,$E51,$F51,$G51,$H51,$I51) -> 0 | N61: =FUELUSE(M61,M24,N24,M34,N34,N$39,N$40,N$41,$E51,$F51,$G51,$H51,$I51) -> 0 | O61: =FUELUSE(N61,N24,O24,N34,O34,O$39,O$40,O$41,$E51,$F51,$G51,$H51,$I51) -> 0 | P61: =FUELUSE(O61,O24,P24,O34,P34,P$39,P$40,P$41,$E51,$F51,$G51,$H51,$I51) -> 0 | Q61: =FUELUSE(P61,P24,Q24,P34,Q34,Q$39,Q$40,Q$41,$E51,$F51,$G51,$H51,$I51) -> 0 | R61: =FUELUSE(Q61,Q24,R24,Q34,R34,R$39,R$40,R$41,$E51,$F51,$G51,$H51,$I51) -> 0 | S61: =FUELUSE(R61,R24,S24,R34,S34,S$39,S$40,S$41,$E51,$F51,$G51,$H51,$I51) -> 0 | T61: =FUELUSE(S61,S24,T24,S34,T34,T$39,T$40,T$41,$E51,$F51,$G51,$H51,$I51) -> 0 | ... AE61: =FUELUSE(AD61,AD24,AE24,AD34,AE34,AE$39,AE$40,AE$41,$E51,$F51,$G51,$H51,$I51) -> 0
B62: ren | C62: =$C$5 -> irn | D62: Self-generated renewables | E62: ktoe | F62: ener | G62: =Settings!$B$3&".mit.enc."&$B62 -> egy.mit.enc.ren | H62: =OUTCODE(Settings!$B$3,"ener",$C$5,$B62,$J$5) -> egy.mit.ener.irn.ren.e.1 | L62: =INDEX(Data_Energy!$D$3:$U$22,MATCH($B62,Data_Energy!$C$3:$C$22,0),MATCH($C62,Data_Energy!$D$2:$U$2,0)) -> 0 | M62: =FUELUSE(L62,L25,M25,L35,M35,M$39,M$40,M$41,$E52,$F52,$G52,$H52,$I52) -> 0 | N62: =FUELUSE(M62,M25,N25,M35,N35,N$39,N$40,N$41,$E52,$F52,$G52,$H52,$I52) -> 0 | O62: =FUELUSE(N62,N25,O25,N35,O35,O$39,O$40,O$41,$E52,$F52,$G52,$H52,$I52) -> 0 | P62: =FUELUSE(O62,O25,P25,O35,P35,P$39,P$40,P$41,$E52,$F52,$G52,$H52,$I52) -> 0 | Q62: =FUELUSE(P62,P25,Q25,P35,Q35,Q$39,Q$40,Q$41,$E52,$F52,$G52,$H52,$I52) -> 0 | R62: =FUELUSE(Q62,Q25,R25,Q35,R35,R$39,R$40,R$41,$E52,$F52,$G52,$H52,$I52) -> 0 | S62: =FUELUSE(R62,R25,S25,R35,S35,S$39,S$40,S$41,$E52,$F52,$G52,$H52,$I52) -> 0 | T62: =FUELUSE(S62,S25,T25,S35,T35,T$39,T$40,T$41,$E52,$F52,$G52,$H52,$I52) -> 0 | ... AE62: =FUELUSE(AD62,AD25,AE25,AD35,AE35,AE$39,AE$40,AE$41,$E52,$F52,$G52,$H52,$I52) -> 0
B63: tot | C63: =$C$5 -> irn | D63: Total | E63: ktoe | F63: ener | H63: =OUTCODE(Settings!$B$3,"ener",$C$5,"tot",$J$5) -> egy.mit.ener.irn.tot.e.1 | L63: =SUM(L54:L62) -> 1901.7141 | M63: =SUM(M54:M62) -> 1621.2302 | N63: =SUM(N54:N62) -> 1820.8469 | O63: =SUM(O54:O62) -> 1904.367 | P63: =SUM(P54:P62) -> 1961.702 | Q63: =SUM(Q54:Q62) -> 2038.9625 | R63: =SUM(R54:R62) -> 2135.0352 | S63: =SUM(S54:S62) -> 2228.4851 | ... AE63: =SUM(AE54:AE62) -> 3416.9988
B65: Cement | C65: cem | D65: Fuel Type | E65: Unit | F65: Variable Code | G65: Input Code (data-table key) | H65: Output Code | I65: Scenario | J65: 1 | K65: 2021 | L65: 2022 | M65: 2023 | N65: 2024 | O65: 2025 | P65: 2026 | Q65: 2027 | R65: 2028 | S65: 2029 | T65: 2030 | U65: 2031 | V65: 2032 | W65: 2033 | X65: 2034 | Y65: 2035 | Z65: 2036 | AA65: 2037 | AB65: 2038 | AC65: 2039 | AD65: 2040 | AE65: 2041 | AF65: 2042 | AG65: 2043 | AH65: 2044 | AI65: 2045
B66: Pre-tax price: price before any new policy (supply cost + VAT + existing excise, subsidies and carbon prices)
B67: coa | C67: =$C$65 -> cem | D67: Coal | E67: $/GJ | F67: ptp | G67: =Settings!$B$3&".mit.pbc."&Settings!$B$4&"."&$B67&".a."&$J$65 -> egy.mit.pbc.ind.coa.a.1 | H67: =OUTCODE(Settings!$B$3,"ptp",$C$65,$B67,$J$65) -> egy.mit.ptp.cem.coa.e.1 | K67: =INDEX(Data_Prices!K:K,MATCH($G67,Data_Prices!$A:$A,0)) -> 11.182902 | L67: =INDEX(Data_Prices!L:L,MATCH($G67,Data_Prices!$A:$A,0)) -> 10.523361 | M67: =INDEX(Data_Prices!M:M,MATCH($G67,Data_Prices!$A:$A,0)) -> 10.299561 | N67: =INDEX(Data_Prices!N:N,MATCH($G67,Data_Prices!$A:$A,0)) -> 9.5775284 | O67: =INDEX(Data_Prices!O:O,MATCH($G67,Data_Prices!$A:$A,0)) -> 8.4854783 | P67: =INDEX(Data_Prices!P:P,MATCH($G67,Data_Prices!$A:$A,0)) -> 9.0871922 | Q67: =INDEX(Data_Prices!Q:Q,MATCH($G67,Data_Prices!$A:$A,0)) -> 9.2229237 | R67: =INDEX(Data_Prices!R:R,MATCH($G67,Data_Prices!$A:$A,0)) -> 9.158565 | S67: =INDEX(Data_Prices!S:S,MATCH($G67,Data_Prices!$A:$A,0)) -> 9.0895479 | T67: =INDEX(Data_Prices!T:T,MATCH($G67,Data_Prices!$A:$A,0)) -> 9.0156817 | U67: =INDEX(Data_Prices!U:U,MATCH($G67,Data_Prices!$A:$A,0)) -> 8.9443978 | V67: =INDEX(Data_Prices!V:V,MATCH($G67,Data_Prices!$A:$A,0)) -> 8.9443978 | W67: =INDEX(Data_Prices!W:W,MATCH($G67,Data_Prices!$A:$A,0)) -> 8.9443978 | X67: =INDEX(Data_Prices!X:X,MATCH($G67,Data_Prices!$A:$A,0)) -> 8.9443978 | Y67: =INDEX(Data_Prices!Y:Y,MATCH($G67,Data_Prices!$A:$A,0)) -> 8.9443978 | Z67: =INDEX(Data_Prices!Z:Z,MATCH($G67,Data_Prices!$A:$A,0)) -> 8.9443978 | AA67: =INDEX(Data_Prices!AA:AA,MATCH($G67,Data_Prices!$A:$A,0)) -> 8.9443978 | AB67: =INDEX(Data_Prices!AB:AB,MATCH($G67,Data_Prices!$A:$A,0)) -> 8.9443978 | AC67: =INDEX(Data_Prices!AC:AC,MATCH($G67,Data_Prices!$A:$A,0)) -> 8.9443978 | AD67: =INDEX(Data_Prices!AD:AD,MATCH($G67,Data_Prices!$A:$A,0)) -> 8.9443978 | AE67: =INDEX(Data_Prices!AE:AE,MATCH($G67,Data_Prices!$A:$A,0)) -> 8.9443978
B68: nga | C68: =$C$65 -> cem | D68: Natural gas | E68: $/GJ | F68: ptp | G68: =Settings!$B$3&".mit.pbc."&Settings!$B$4&"."&$B68&".a."&$J$65 -> egy.mit.pbc.ind.nga.a.1 | H68: =OUTCODE(Settings!$B$3,"ptp",$C$65,$B68,$J$65) -> egy.mit.ptp.cem.nga.e.1 | K68: =INDEX(Data_Prices!K:K,MATCH($G68,Data_Prices!$A:$A,0)) -> 6.0634636 | L68: =INDEX(Data_Prices!L:L,MATCH($G68,Data_Prices!$A:$A,0)) -> 5.4510151 | M68: =INDEX(Data_Prices!M:M,MATCH($G68,Data_Prices!$A:$A,0)) -> 5.1193563 | N68: =INDEX(Data_Prices!N:N,MATCH($G68,Data_Prices!$A:$A,0)) -> 5.0821846 | O68: =INDEX(Data_Prices!O:O,MATCH($G68,Data_Prices!$A:$A,0)) -> 5.0821846 | P68: =INDEX(Data_Prices!P:P,MATCH($G68,Data_Prices!$A:$A,0)) -> 5.0821846 | Q68: =INDEX(Data_Prices!Q:Q,MATCH($G68,Data_Prices!$A:$A,0)) -> 5.0821846 | R68: =INDEX(Data_Prices!R:R,MATCH($G68,Data_Prices!$A:$A,0)) -> 5.0821846 | S68: =INDEX(Data_Prices!S:S,MATCH($G68,Data_Prices!$A:$A,0)) -> 5.0821846 | T68: =INDEX(Data_Prices!T:T,MATCH($G68,Data_Prices!$A:$A,0)) -> 5.0821846 | U68: =INDEX(Data_Prices!U:U,MATCH($G68,Data_Prices!$A:$A,0)) -> 5.0821846 | V68: =INDEX(Data_Prices!V:V,MATCH($G68,Data_Prices!$A:$A,0)) -> 5.0821846 | W68: =INDEX(Data_Prices!W:W,MATCH($G68,Data_Prices!$A:$A,0)) -> 5.0821846 | X68: =INDEX(Data_Prices!X:X,MATCH($G68,Data_Prices!$A:$A,0)) -> 5.0821846 | Y68: =INDEX(Data_Prices!Y:Y,MATCH($G68,Data_Prices!$A:$A,0)) -> 5.0821846 | Z68: =INDEX(Data_Prices!Z:Z,MATCH($G68,Data_Prices!$A:$A,0)) -> 5.0821846 | AA68: =INDEX(Data_Prices!AA:AA,MATCH($G68,Data_Prices!$A:$A,0)) -> 5.0821846 | AB68: =INDEX(Data_Prices!AB:AB,MATCH($G68,Data_Prices!$A:$A,0)) -> 5.0821846 | AC68: =INDEX(Data_Prices!AC:AC,MATCH($G68,Data_Prices!$A:$A,0)) -> 5.0821846 | AD68: =INDEX(Data_Prices!AD:AD,MATCH($G68,Data_Prices!$A:$A,0)) -> 5.0821846 | AE68: =INDEX(Data_Prices!AE:AE,MATCH($G68,Data_Prices!$A:$A,0)) -> 5.0821846
B69: gso | C69: =$C$65 -> cem | D69: Gasoline | E69: $/liter | F69: ptp | G69: =Settings!$B$3&".mit.pbc."&Settings!$B$4&"."&$B69&".a."&$J$65 -> egy.mit.pbc.ind.gso.a.1 | H69: =OUTCODE(Settings!$B$3,"ptp",$C$65,$B69,$J$65) -> egy.mit.ptp.cem.gso.e.1 | K69: =INDEX(Data_Prices!K:K,MATCH($G69,Data_Prices!$A:$A,0)) -> 0.67114653 | L69: =INDEX(Data_Prices!L:L,MATCH($G69,Data_Prices!$A:$A,0)) -> 0.61197798 | M69: =INDEX(Data_Prices!M:M,MATCH($G69,Data_Prices!$A:$A,0)) -> 0.61180975 | N69: =INDEX(Data_Prices!N:N,MATCH($G69,Data_Prices!$A:$A,0)) -> 0.6035831 | O69: =INDEX(Data_Prices!O:O,MATCH($G69,Data_Prices!$A:$A,0)) -> 0.6035831 | P69: =INDEX(Data_Prices!P:P,MATCH($G69,Data_Prices!$A:$A,0)) -> 0.6035831 | Q69: =INDEX(Data_Prices!Q:Q,MATCH($G69,Data_Prices!$A:$A,0)) -> 0.6035831 | R69: =INDEX(Data_Prices!R:R,MATCH($G69,Data_Prices!$A:$A,0)) -> 0.6035831 | S69: =INDEX(Data_Prices!S:S,MATCH($G69,Data_Prices!$A:$A,0)) -> 0.6035831 | T69: =INDEX(Data_Prices!T:T,MATCH($G69,Data_Prices!$A:$A,0)) -> 0.6035831 | U69: =INDEX(Data_Prices!U:U,MATCH($G69,Data_Prices!$A:$A,0)) -> 0.6035831 | V69: =INDEX(Data_Prices!V:V,MATCH($G69,Data_Prices!$A:$A,0)) -> 0.6035831 | W69: =INDEX(Data_Prices!W:W,MATCH($G69,Data_Prices!$A:$A,0)) -> 0.6035831 | X69: =INDEX(Data_Prices!X:X,MATCH($G69,Data_Prices!$A:$A,0)) -> 0.6035831 | Y69: =INDEX(Data_Prices!Y:Y,MATCH($G69,Data_Prices!$A:$A,0)) -> 0.6035831 | Z69: =INDEX(Data_Prices!Z:Z,MATCH($G69,Data_Prices!$A:$A,0)) -> 0.6035831 | AA69: =INDEX(Data_Prices!AA:AA,MATCH($G69,Data_Prices!$A:$A,0)) -> 0.6035831 | AB69: =INDEX(Data_Prices!AB:AB,MATCH($G69,Data_Prices!$A:$A,0)) -> 0.6035831 | AC69: =INDEX(Data_Prices!AC:AC,MATCH($G69,Data_Prices!$A:$A,0)) -> 0.6035831 | AD69: =INDEX(Data_Prices!AD:AD,MATCH($G69,Data_Prices!$A:$A,0)) -> 0.6035831 | AE69: =INDEX(Data_Prices!AE:AE,MATCH($G69,Data_Prices!$A:$A,0)) -> 0.6035831
B70: die | C70: =$C$65 -> cem | D70: Diesel | E70: $/liter | F70: ptp | G70: =Settings!$B$3&".mit.pbc."&Settings!$B$4&"."&$B70&".a."&$J$65 -> egy.mit.pbc.ind.die.a.1 | H70: =OUTCODE(Settings!$B$3,"ptp",$C$65,$B70,$J$65) -> egy.mit.ptp.cem.die.e.1 | K70: =INDEX(Data_Prices!K:K,MATCH($G70,Data_Prices!$A:$A,0)) -> 0.55971121 | L70: =INDEX(Data_Prices!L:L,MATCH($G70,Data_Prices!$A:$A,0)) -> 0.49458873 | M70: =INDEX(Data_Prices!M:M,MATCH($G70,Data_Prices!$A:$A,0)) -> 0.50778655 | N70: =INDEX(Data_Prices!N:N,MATCH($G70,Data_Prices!$A:$A,0)) -> 0.47043643 | O70: =INDEX(Data_Prices!O:O,MATCH($G70,Data_Prices!$A:$A,0)) -> 0.47043643 | P70: =INDEX(Data_Prices!P:P,MATCH($G70,Data_Prices!$A:$A,0)) -> 0.47043643 | Q70: =INDEX(Data_Prices!Q:Q,MATCH($G70,Data_Prices!$A:$A,0)) -> 0.47043643 | R70: =INDEX(Data_Prices!R:R,MATCH($G70,Data_Prices!$A:$A,0)) -> 0.47043643 | S70: =INDEX(Data_Prices!S:S,MATCH($G70,Data_Prices!$A:$A,0)) -> 0.47043643 | T70: =INDEX(Data_Prices!T:T,MATCH($G70,Data_Prices!$A:$A,0)) -> 0.47043643 | U70: =INDEX(Data_Prices!U:U,MATCH($G70,Data_Prices!$A:$A,0)) -> 0.47043643 | V70: =INDEX(Data_Prices!V:V,MATCH($G70,Data_Prices!$A:$A,0)) -> 0.47043643 | W70: =INDEX(Data_Prices!W:W,MATCH($G70,Data_Prices!$A:$A,0)) -> 0.47043643 | X70: =INDEX(Data_Prices!X:X,MATCH($G70,Data_Prices!$A:$A,0)) -> 0.47043643 | Y70: =INDEX(Data_Prices!Y:Y,MATCH($G70,Data_Prices!$A:$A,0)) -> 0.47043643 | Z70: =INDEX(Data_Prices!Z:Z,MATCH($G70,Data_Prices!$A:$A,0)) -> 0.47043643 | AA70: =INDEX(Data_Prices!AA:AA,MATCH($G70,Data_Prices!$A:$A,0)) -> 0.47043643 | AB70: =INDEX(Data_Prices!AB:AB,MATCH($G70,Data_Prices!$A:$A,0)) -> 0.47043643 | AC70: =INDEX(Data_Prices!AC:AC,MATCH($G70,Data_Prices!$A:$A,0)) -> 0.47043643 | AD70: =INDEX(Data_Prices!AD:AD,MATCH($G70,Data_Prices!$A:$A,0)) -> 0.47043643 | AE70: =INDEX(Data_Prices!AE:AE,MATCH($G70,Data_Prices!$A:$A,0)) -> 0.47043643
B71: lpg | C71: =$C$65 -> cem | D71: LPG | E71: $/liter | F71: ptp | G71: =Settings!$B$3&".mit.pbc."&Settings!$B$4&"."&$B71&".a."&$J$65 -> egy.mit.pbc.ind.lpg.a.1 | H71: =OUTCODE(Settings!$B$3,"ptp",$C$65,$B71,$J$65) -> egy.mit.ptp.cem.lpg.e.1 | K71: =INDEX(Data_Prices!K:K,MATCH($G71,Data_Prices!$A:$A,0)) -> 0.20036669 | L71: =INDEX(Data_Prices!L:L,MATCH($G71,Data_Prices!$A:$A,0)) -> 0.15734474 | M71: =INDEX(Data_Prices!M:M,MATCH($G71,Data_Prices!$A:$A,0)) -> 0.16448404 | N71: =INDEX(Data_Prices!N:N,MATCH($G71,Data_Prices!$A:$A,0)) -> 0.15070908 | O71: =INDEX(Data_Prices!O:O,MATCH($G71,Data_Prices!$A:$A,0)) -> 0.15070908 | P71: =INDEX(Data_Prices!P:P,MATCH($G71,Data_Prices!$A:$A,0)) -> 0.15070908 | Q71: =INDEX(Data_Prices!Q:Q,MATCH($G71,Data_Prices!$A:$A,0)) -> 0.15070908 | R71: =INDEX(Data_Prices!R:R,MATCH($G71,Data_Prices!$A:$A,0)) -> 0.15070908 | S71: =INDEX(Data_Prices!S:S,MATCH($G71,Data_Prices!$A:$A,0)) -> 0.15070908 | T71: =INDEX(Data_Prices!T:T,MATCH($G71,Data_Prices!$A:$A,0)) -> 0.15070908 | U71: =INDEX(Data_Prices!U:U,MATCH($G71,Data_Prices!$A:$A,0)) -> 0.15070908 | V71: =INDEX(Data_Prices!V:V,MATCH($G71,Data_Prices!$A:$A,0)) -> 0.15070908 | W71: =INDEX(Data_Prices!W:W,MATCH($G71,Data_Prices!$A:$A,0)) -> 0.15070908 | X71: =INDEX(Data_Prices!X:X,MATCH($G71,Data_Prices!$A:$A,0)) -> 0.15070908 | Y71: =INDEX(Data_Prices!Y:Y,MATCH($G71,Data_Prices!$A:$A,0)) -> 0.15070908 | Z71: =INDEX(Data_Prices!Z:Z,MATCH($G71,Data_Prices!$A:$A,0)) -> 0.15070908 | AA71: =INDEX(Data_Prices!AA:AA,MATCH($G71,Data_Prices!$A:$A,0)) -> 0.15070908 | AB71: =INDEX(Data_Prices!AB:AB,MATCH($G71,Data_Prices!$A:$A,0)) -> 0.15070908 | AC71: =INDEX(Data_Prices!AC:AC,MATCH($G71,Data_Prices!$A:$A,0)) -> 0.15070908 | AD71: =INDEX(Data_Prices!AD:AD,MATCH($G71,Data_Prices!$A:$A,0)) -> 0.15070908 | AE71: =INDEX(Data_Prices!AE:AE,MATCH($G71,Data_Prices!$A:$A,0)) -> 0.15070908
B72: ker | C72: =$C$65 -> cem | D72: Kerosene | E72: $/liter | F72: ptp | G72: =Settings!$B$3&".mit.pbc."&Settings!$B$4&"."&$B72&".a."&$J$65 -> egy.mit.pbc.ind.ker.a.1 | H72: =OUTCODE(Settings!$B$3,"ptp",$C$65,$B72,$J$65) -> egy.mit.ptp.cem.ker.e.1 | K72: =INDEX(Data_Prices!K:K,MATCH($G72,Data_Prices!$A:$A,0)) -> 0.48429424 | L72: =INDEX(Data_Prices!L:L,MATCH($G72,Data_Prices!$A:$A,0)) -> 0.45642817 | M72: =INDEX(Data_Prices!M:M,MATCH($G72,Data_Prices!$A:$A,0)) -> 0.4316892 | N72: =INDEX(Data_Prices!N:N,MATCH($G72,Data_Prices!$A:$A,0)) -> 0.42507558 | O72: =INDEX(Data_Prices!O:O,MATCH($G72,Data_Prices!$A:$A,0)) -> 0.42507558 | P72: =INDEX(Data_Prices!P:P,MATCH($G72,Data_Prices!$A:$A,0)) -> 0.42507558 | Q72: =INDEX(Data_Prices!Q:Q,MATCH($G72,Data_Prices!$A:$A,0)) -> 0.42507558 | R72: =INDEX(Data_Prices!R:R,MATCH($G72,Data_Prices!$A:$A,0)) -> 0.42507558 | S72: =INDEX(Data_Prices!S:S,MATCH($G72,Data_Prices!$A:$A,0)) -> 0.42507558 | T72: =INDEX(Data_Prices!T:T,MATCH($G72,Data_Prices!$A:$A,0)) -> 0.42507558 | U72: =INDEX(Data_Prices!U:U,MATCH($G72,Data_Prices!$A:$A,0)) -> 0.42507558 | V72: =INDEX(Data_Prices!V:V,MATCH($G72,Data_Prices!$A:$A,0)) -> 0.42507558 | W72: =INDEX(Data_Prices!W:W,MATCH($G72,Data_Prices!$A:$A,0)) -> 0.42507558 | X72: =INDEX(Data_Prices!X:X,MATCH($G72,Data_Prices!$A:$A,0)) -> 0.42507558 | Y72: =INDEX(Data_Prices!Y:Y,MATCH($G72,Data_Prices!$A:$A,0)) -> 0.42507558 | Z72: =INDEX(Data_Prices!Z:Z,MATCH($G72,Data_Prices!$A:$A,0)) -> 0.42507558 | AA72: =INDEX(Data_Prices!AA:AA,MATCH($G72,Data_Prices!$A:$A,0)) -> 0.42507558 | AB72: =INDEX(Data_Prices!AB:AB,MATCH($G72,Data_Prices!$A:$A,0)) -> 0.42507558 | AC72: =INDEX(Data_Prices!AC:AC,MATCH($G72,Data_Prices!$A:$A,0)) -> 0.42507558 | AD72: =INDEX(Data_Prices!AD:AD,MATCH($G72,Data_Prices!$A:$A,0)) -> 0.42507558 | AE72: =INDEX(Data_Prices!AE:AE,MATCH($G72,Data_Prices!$A:$A,0)) -> 0.42507558
B73: oop | C73: =$C$65 -> cem | D73: Other oil products | E73: $/bbl | F73: ptp | G73: =Settings!$B$3&".mit.pbc."&Settings!$B$4&"."&$B73&".a."&$J$65 -> egy.mit.pbc.ind.oop.a.1 | H73: =OUTCODE(Settings!$B$3,"ptp",$C$65,$B73,$J$65) -> egy.mit.ptp.cem.oop.e.1 | K73: =INDEX(Data_Prices!K:K,MATCH($G73,Data_Prices!$A:$A,0)) -> 41.500338 | L73: =INDEX(Data_Prices!L:L,MATCH($G73,Data_Prices!$A:$A,0)) -> 34.41537 | M73: =INDEX(Data_Prices!M:M,MATCH($G73,Data_Prices!$A:$A,0)) -> 37.368961 | N73: =INDEX(Data_Prices!N:N,MATCH($G73,Data_Prices!$A:$A,0)) -> 28.982761 | O73: =INDEX(Data_Prices!O:O,MATCH($G73,Data_Prices!$A:$A,0)) -> 15 | P73: =INDEX(Data_Prices!P:P,MATCH($G73,Data_Prices!$A:$A,0)) -> 24.25863 | Q73: =INDEX(Data_Prices!Q:Q,MATCH($G73,Data_Prices!$A:$A,0)) -> 15 | R73: =INDEX(Data_Prices!R:R,MATCH($G73,Data_Prices!$A:$A,0)) -> 15 | S73: =INDEX(Data_Prices!S:S,MATCH($G73,Data_Prices!$A:$A,0)) -> 15 | T73: =INDEX(Data_Prices!T:T,MATCH($G73,Data_Prices!$A:$A,0)) -> 15 | U73: =INDEX(Data_Prices!U:U,MATCH($G73,Data_Prices!$A:$A,0)) -> 15 | V73: =INDEX(Data_Prices!V:V,MATCH($G73,Data_Prices!$A:$A,0)) -> 15 | W73: =INDEX(Data_Prices!W:W,MATCH($G73,Data_Prices!$A:$A,0)) -> 15 | X73: =INDEX(Data_Prices!X:X,MATCH($G73,Data_Prices!$A:$A,0)) -> 15 | Y73: =INDEX(Data_Prices!Y:Y,MATCH($G73,Data_Prices!$A:$A,0)) -> 15 | Z73: =INDEX(Data_Prices!Z:Z,MATCH($G73,Data_Prices!$A:$A,0)) -> 15 | AA73: =INDEX(Data_Prices!AA:AA,MATCH($G73,Data_Prices!$A:$A,0)) -> 15 | AB73: =INDEX(Data_Prices!AB:AB,MATCH($G73,Data_Prices!$A:$A,0)) -> 15 | AC73: =INDEX(Data_Prices!AC:AC,MATCH($G73,Data_Prices!$A:$A,0)) -> 15 | AD73: =INDEX(Data_Prices!AD:AD,MATCH($G73,Data_Prices!$A:$A,0)) -> 15 | AE73: =INDEX(Data_Prices!AE:AE,MATCH($G73,Data_Prices!$A:$A,0)) -> 15
B74: bio | C74: =$C$65 -> cem | D74: Biomass | E74: $/GJ | F74: ptp | G74: =Settings!$B$3&".mit.pbc."&Settings!$B$4&"."&$B74&".a."&$J$65 -> egy.mit.pbc.ind.bio.a.1 | H74: =OUTCODE(Settings!$B$3,"ptp",$C$65,$B74,$J$65) -> egy.mit.ptp.cem.bio.e.1 | K74: =INDEX(Data_Prices!K:K,MATCH($G74,Data_Prices!$A:$A,0)) -> 15.334551 | L74: =INDEX(Data_Prices!L:L,MATCH($G74,Data_Prices!$A:$A,0)) -> 14.199528 | M74: =INDEX(Data_Prices!M:M,MATCH($G74,Data_Prices!$A:$A,0)) -> 13.840442 | N74: =INDEX(Data_Prices!N:N,MATCH($G74,Data_Prices!$A:$A,0)) -> 13.567727 | O74: =INDEX(Data_Prices!O:O,MATCH($G74,Data_Prices!$A:$A,0)) -> 13.567727 | P74: =INDEX(Data_Prices!P:P,MATCH($G74,Data_Prices!$A:$A,0)) -> 13.567727 | Q74: =INDEX(Data_Prices!Q:Q,MATCH($G74,Data_Prices!$A:$A,0)) -> 13.567727 | R74: =INDEX(Data_Prices!R:R,MATCH($G74,Data_Prices!$A:$A,0)) -> 13.567727 | S74: =INDEX(Data_Prices!S:S,MATCH($G74,Data_Prices!$A:$A,0)) -> 13.567727 | T74: =INDEX(Data_Prices!T:T,MATCH($G74,Data_Prices!$A:$A,0)) -> 13.567727 | U74: =INDEX(Data_Prices!U:U,MATCH($G74,Data_Prices!$A:$A,0)) -> 13.567727 | V74: =INDEX(Data_Prices!V:V,MATCH($G74,Data_Prices!$A:$A,0)) -> 13.567727 | W74: =INDEX(Data_Prices!W:W,MATCH($G74,Data_Prices!$A:$A,0)) -> 13.567727 | X74: =INDEX(Data_Prices!X:X,MATCH($G74,Data_Prices!$A:$A,0)) -> 13.567727 | Y74: =INDEX(Data_Prices!Y:Y,MATCH($G74,Data_Prices!$A:$A,0)) -> 13.567727 | Z74: =INDEX(Data_Prices!Z:Z,MATCH($G74,Data_Prices!$A:$A,0)) -> 13.567727 | AA74: =INDEX(Data_Prices!AA:AA,MATCH($G74,Data_Prices!$A:$A,0)) -> 13.567727 | AB74: =INDEX(Data_Prices!AB:AB,MATCH($G74,Data_Prices!$A:$A,0)) -> 13.567727 | AC74: =INDEX(Data_Prices!AC:AC,MATCH($G74,Data_Prices!$A:$A,0)) -> 13.567727 | AD74: =INDEX(Data_Prices!AD:AD,MATCH($G74,Data_Prices!$A:$A,0)) -> 13.567727 | AE74: =INDEX(Data_Prices!AE:AE,MATCH($G74,Data_Prices!$A:$A,0)) -> 13.567727
B75: ren | C75: =$C$65 -> cem | D75: Self-generated renewables | E75: $/kwh | F75: ptp | G75: =Settings!$B$3&".mit.pbc."&Settings!$B$4&"."&$B75&".a."&$J$65 -> egy.mit.pbc.ind.ren.a.1 | H75: =OUTCODE(Settings!$B$3,"ptp",$C$65,$B75,$J$65) -> egy.mit.ptp.cem.ren.e.1 | K75: =INDEX(Data_Prices!K:K,MATCH($G75,Data_Prices!$A:$A,0)) -> 0 | L75: =INDEX(Data_Prices!L:L,MATCH($G75,Data_Prices!$A:$A,0)) -> 0.14404499 | M75: =INDEX(Data_Prices!M:M,MATCH($G75,Data_Prices!$A:$A,0)) -> 0.14102041 | N75: =INDEX(Data_Prices!N:N,MATCH($G75,Data_Prices!$A:$A,0)) -> 0.13511636 | O75: =INDEX(Data_Prices!O:O,MATCH($G75,Data_Prices!$A:$A,0)) -> 0.13098826 | P75: =INDEX(Data_Prices!P:P,MATCH($G75,Data_Prices!$A:$A,0)) -> 0.12790842 | Q75: =INDEX(Data_Prices!Q:Q,MATCH($G75,Data_Prices!$A:$A,0)) -> 0.12481431 | R75: =INDEX(Data_Prices!R:R,MATCH($G75,Data_Prices!$A:$A,0)) -> 0.12146026 | S75: =INDEX(Data_Prices!S:S,MATCH($G75,Data_Prices!$A:$A,0)) -> 0.11795074 | T75: =INDEX(Data_Prices!T:T,MATCH($G75,Data_Prices!$A:$A,0)) -> 0.11419916 | U75: =INDEX(Data_Prices!U:U,MATCH($G75,Data_Prices!$A:$A,0)) -> 0.1136651 | V75: =INDEX(Data_Prices!V:V,MATCH($G75,Data_Prices!$A:$A,0)) -> 0.11301693 | W75: =INDEX(Data_Prices!W:W,MATCH($G75,Data_Prices!$A:$A,0)) -> 0.11231407 | X75: =INDEX(Data_Prices!X:X,MATCH($G75,Data_Prices!$A:$A,0)) -> 0.11142204 | Y75: =INDEX(Data_Prices!Y:Y,MATCH($G75,Data_Prices!$A:$A,0)) -> 0.11043412 | Z75: =INDEX(Data_Prices!Z:Z,MATCH($G75,Data_Prices!$A:$A,0)) -> 0.10948397 | AA75: =INDEX(Data_Prices!AA:AA,MATCH($G75,Data_Prices!$A:$A,0)) -> 0.10839192 | AB75: =INDEX(Data_Prices!AB:AB,MATCH($G75,Data_Prices!$A:$A,0)) -> 0.10735443 | AC75: =INDEX(Data_Prices!AC:AC,MATCH($G75,Data_Prices!$A:$A,0)) -> 0.10516868 | AD75: =INDEX(Data_Prices!AD:AD,MATCH($G75,Data_Prices!$A:$A,0)) -> 0.10305798 | AE75: =INDEX(Data_Prices!AE:AE,MATCH($G75,Data_Prices!$A:$A,0)) -> 0.10093184
B76: Post-tax price: pre-tax + new-policy wedge x sector coverage factor (= CPAT atp row)
B77: coa | C77: =$C$65 -> cem | D77: Coal | E77: $/GJ | F77: atp | G77: =Settings!$B$3&".mit.nce."&Settings!$B$4&"."&$B77&".a."&$J$65 -> egy.mit.nce.ind.coa.a.1 | H77: =OUTCODE(Settings!$B$3,"atp",$C$65,$B77,$J$65) -> egy.mit.atp.cem.coa.e.1 | K77: =POSTTAX(K67,INDEX(Data_Prices!K:K,MATCH($G77,Data_Prices!$A:$A,0)),K$97) -> 11.182902 | L77: =POSTTAX(L67,INDEX(Data_Prices!L:L,MATCH($G77,Data_Prices!$A:$A,0)),L$97) -> 10.523361 | M77: =POSTTAX(M67,INDEX(Data_Prices!M:M,MATCH($G77,Data_Prices!$A:$A,0)),M$97) -> 10.299561 | N77: =POSTTAX(N67,INDEX(Data_Prices!N:N,MATCH($G77,Data_Prices!$A:$A,0)),N$97) -> 9.5775284 | O77: =POSTTAX(O67,INDEX(Data_Prices!O:O,MATCH($G77,Data_Prices!$A:$A,0)),O$97) -> 8.4854783 | P77: =POSTTAX(P67,INDEX(Data_Prices!P:P,MATCH($G77,Data_Prices!$A:$A,0)),P$97) -> 9.0871922 | Q77: =POSTTAX(Q67,INDEX(Data_Prices!Q:Q,MATCH($G77,Data_Prices!$A:$A,0)),Q$97) -> 9.2229237 | R77: =POSTTAX(R67,INDEX(Data_Prices!R:R,MATCH($G77,Data_Prices!$A:$A,0)),R$97) -> 9.158565 | S77: =POSTTAX(S67,INDEX(Data_Prices!S:S,MATCH($G77,Data_Prices!$A:$A,0)),S$97) -> 9.0895479 | T77: =POSTTAX(T67,INDEX(Data_Prices!T:T,MATCH($G77,Data_Prices!$A:$A,0)),T$97) -> 9.0156817 | U77: =POSTTAX(U67,INDEX(Data_Prices!U:U,MATCH($G77,Data_Prices!$A:$A,0)),U$97) -> 8.9443978 | V77: =POSTTAX(V67,INDEX(Data_Prices!V:V,MATCH($G77,Data_Prices!$A:$A,0)),V$97) -> 8.9443978 | W77: =POSTTAX(W67,INDEX(Data_Prices!W:W,MATCH($G77,Data_Prices!$A:$A,0)),W$97) -> 8.9443978 | X77: =POSTTAX(X67,INDEX(Data_Prices!X:X,MATCH($G77,Data_Prices!$A:$A,0)),X$97) -> 8.9443978 | Y77: =POSTTAX(Y67,INDEX(Data_Prices!Y:Y,MATCH($G77,Data_Prices!$A:$A,0)),Y$97) -> 8.9443978 | Z77: =POSTTAX(Z67,INDEX(Data_Prices!Z:Z,MATCH($G77,Data_Prices!$A:$A,0)),Z$97) -> 8.9443978 | AA77: =POSTTAX(AA67,INDEX(Data_Prices!AA:AA,MATCH($G77,Data_Prices!$A:$A,0)),AA$97) -> 8.9443978 | AB77: =POSTTAX(AB67,INDEX(Data_Prices!AB:AB,MATCH($G77,Data_Prices!$A:$A,0)),AB$97) -> 8.9443978 | AC77: =POSTTAX(AC67,INDEX(Data_Prices!AC:AC,MATCH($G77,Data_Prices!$A:$A,0)),AC$97) -> 8.9443978 | AD77: =POSTTAX(AD67,INDEX(Data_Prices!AD:AD,MATCH($G77,Data_Prices!$A:$A,0)),AD$97) -> 8.9443978 | AE77: =POSTTAX(AE67,INDEX(Data_Prices!AE:AE,MATCH($G77,Data_Prices!$A:$A,0)),AE$97) -> 8.9443978
B78: nga | C78: =$C$65 -> cem | D78: Natural gas | E78: $/GJ | F78: atp | G78: =Settings!$B$3&".mit.nce."&Settings!$B$4&"."&$B78&".a."&$J$65 -> egy.mit.nce.ind.nga.a.1 | H78: =OUTCODE(Settings!$B$3,"atp",$C$65,$B78,$J$65) -> egy.mit.atp.cem.nga.e.1 | K78: =POSTTAX(K68,INDEX(Data_Prices!K:K,MATCH($G78,Data_Prices!$A:$A,0)),K$97) -> 6.0634636 | L78: =POSTTAX(L68,INDEX(Data_Prices!L:L,MATCH($G78,Data_Prices!$A:$A,0)),L$97) -> 5.4510151 | M78: =POSTTAX(M68,INDEX(Data_Prices!M:M,MATCH($G78,Data_Prices!$A:$A,0)),M$97) -> 5.1193563 | N78: =POSTTAX(N68,INDEX(Data_Prices!N:N,MATCH($G78,Data_Prices!$A:$A,0)),N$97) -> 5.0821846 | O78: =POSTTAX(O68,INDEX(Data_Prices!O:O,MATCH($G78,Data_Prices!$A:$A,0)),O$97) -> 5.0821846 | P78: =POSTTAX(P68,INDEX(Data_Prices!P:P,MATCH($G78,Data_Prices!$A:$A,0)),P$97) -> 5.0821846 | Q78: =POSTTAX(Q68,INDEX(Data_Prices!Q:Q,MATCH($G78,Data_Prices!$A:$A,0)),Q$97) -> 5.0821846 | R78: =POSTTAX(R68,INDEX(Data_Prices!R:R,MATCH($G78,Data_Prices!$A:$A,0)),R$97) -> 5.0821846 | S78: =POSTTAX(S68,INDEX(Data_Prices!S:S,MATCH($G78,Data_Prices!$A:$A,0)),S$97) -> 5.0821846 | T78: =POSTTAX(T68,INDEX(Data_Prices!T:T,MATCH($G78,Data_Prices!$A:$A,0)),T$97) -> 5.0821846 | U78: =POSTTAX(U68,INDEX(Data_Prices!U:U,MATCH($G78,Data_Prices!$A:$A,0)),U$97) -> 5.0821846 | V78: =POSTTAX(V68,INDEX(Data_Prices!V:V,MATCH($G78,Data_Prices!$A:$A,0)),V$97) -> 5.0821846 | W78: =POSTTAX(W68,INDEX(Data_Prices!W:W,MATCH($G78,Data_Prices!$A:$A,0)),W$97) -> 5.0821846 | X78: =POSTTAX(X68,INDEX(Data_Prices!X:X,MATCH($G78,Data_Prices!$A:$A,0)),X$97) -> 5.0821846 | Y78: =POSTTAX(Y68,INDEX(Data_Prices!Y:Y,MATCH($G78,Data_Prices!$A:$A,0)),Y$97) -> 5.0821846 | Z78: =POSTTAX(Z68,INDEX(Data_Prices!Z:Z,MATCH($G78,Data_Prices!$A:$A,0)),Z$97) -> 5.0821846 | AA78: =POSTTAX(AA68,INDEX(Data_Prices!AA:AA,MATCH($G78,Data_Prices!$A:$A,0)),AA$97) -> 5.0821846 | AB78: =POSTTAX(AB68,INDEX(Data_Prices!AB:AB,MATCH($G78,Data_Prices!$A:$A,0)),AB$97) -> 5.0821846 | AC78: =POSTTAX(AC68,INDEX(Data_Prices!AC:AC,MATCH($G78,Data_Prices!$A:$A,0)),AC$97) -> 5.0821846 | AD78: =POSTTAX(AD68,INDEX(Data_Prices!AD:AD,MATCH($G78,Data_Prices!$A:$A,0)),AD$97) -> 5.0821846 | AE78: =POSTTAX(AE68,INDEX(Data_Prices!AE:AE,MATCH($G78,Data_Prices!$A:$A,0)),AE$97) -> 5.0821846
B79: gso | C79: =$C$65 -> cem | D79: Gasoline | E79: $/liter | F79: atp | G79: =Settings!$B$3&".mit.nce."&Settings!$B$4&"."&$B79&".a."&$J$65 -> egy.mit.nce.ind.gso.a.1 | H79: =OUTCODE(Settings!$B$3,"atp",$C$65,$B79,$J$65) -> egy.mit.atp.cem.gso.e.1 | K79: =POSTTAX(K69,INDEX(Data_Prices!K:K,MATCH($G79,Data_Prices!$A:$A,0)),K$97) -> 0.67114653 | L79: =POSTTAX(L69,INDEX(Data_Prices!L:L,MATCH($G79,Data_Prices!$A:$A,0)),L$97) -> 0.61197798 | M79: =POSTTAX(M69,INDEX(Data_Prices!M:M,MATCH($G79,Data_Prices!$A:$A,0)),M$97) -> 0.61180975 | N79: =POSTTAX(N69,INDEX(Data_Prices!N:N,MATCH($G79,Data_Prices!$A:$A,0)),N$97) -> 0.6035831 | O79: =POSTTAX(O69,INDEX(Data_Prices!O:O,MATCH($G79,Data_Prices!$A:$A,0)),O$97) -> 0.6035831 | P79: =POSTTAX(P69,INDEX(Data_Prices!P:P,MATCH($G79,Data_Prices!$A:$A,0)),P$97) -> 0.6035831 | Q79: =POSTTAX(Q69,INDEX(Data_Prices!Q:Q,MATCH($G79,Data_Prices!$A:$A,0)),Q$97) -> 0.6035831 | R79: =POSTTAX(R69,INDEX(Data_Prices!R:R,MATCH($G79,Data_Prices!$A:$A,0)),R$97) -> 0.6035831 | S79: =POSTTAX(S69,INDEX(Data_Prices!S:S,MATCH($G79,Data_Prices!$A:$A,0)),S$97) -> 0.6035831 | T79: =POSTTAX(T69,INDEX(Data_Prices!T:T,MATCH($G79,Data_Prices!$A:$A,0)),T$97) -> 0.6035831 | U79: =POSTTAX(U69,INDEX(Data_Prices!U:U,MATCH($G79,Data_Prices!$A:$A,0)),U$97) -> 0.6035831 | V79: =POSTTAX(V69,INDEX(Data_Prices!V:V,MATCH($G79,Data_Prices!$A:$A,0)),V$97) -> 0.6035831 | W79: =POSTTAX(W69,INDEX(Data_Prices!W:W,MATCH($G79,Data_Prices!$A:$A,0)),W$97) -> 0.6035831 | X79: =POSTTAX(X69,INDEX(Data_Prices!X:X,MATCH($G79,Data_Prices!$A:$A,0)),X$97) -> 0.6035831 | Y79: =POSTTAX(Y69,INDEX(Data_Prices!Y:Y,MATCH($G79,Data_Prices!$A:$A,0)),Y$97) -> 0.6035831 | Z79: =POSTTAX(Z69,INDEX(Data_Prices!Z:Z,MATCH($G79,Data_Prices!$A:$A,0)),Z$97) -> 0.6035831 | AA79: =POSTTAX(AA69,INDEX(Data_Prices!AA:AA,MATCH($G79,Data_Prices!$A:$A,0)),AA$97) -> 0.6035831 | AB79: =POSTTAX(AB69,INDEX(Data_Prices!AB:AB,MATCH($G79,Data_Prices!$A:$A,0)),AB$97) -> 0.6035831 | AC79: =POSTTAX(AC69,INDEX(Data_Prices!AC:AC,MATCH($G79,Data_Prices!$A:$A,0)),AC$97) -> 0.6035831 | AD79: =POSTTAX(AD69,INDEX(Data_Prices!AD:AD,MATCH($G79,Data_Prices!$A:$A,0)),AD$97) -> 0.6035831 | AE79: =POSTTAX(AE69,INDEX(Data_Prices!AE:AE,MATCH($G79,Data_Prices!$A:$A,0)),AE$97) -> 0.6035831
B80: die | C80: =$C$65 -> cem | D80: Diesel | E80: $/liter | F80: atp | G80: =Settings!$B$3&".mit.nce."&Settings!$B$4&"."&$B80&".a."&$J$65 -> egy.mit.nce.ind.die.a.1 | H80: =OUTCODE(Settings!$B$3,"atp",$C$65,$B80,$J$65) -> egy.mit.atp.cem.die.e.1 | K80: =POSTTAX(K70,INDEX(Data_Prices!K:K,MATCH($G80,Data_Prices!$A:$A,0)),K$97) -> 0.55971121 | L80: =POSTTAX(L70,INDEX(Data_Prices!L:L,MATCH($G80,Data_Prices!$A:$A,0)),L$97) -> 0.49458873 | M80: =POSTTAX(M70,INDEX(Data_Prices!M:M,MATCH($G80,Data_Prices!$A:$A,0)),M$97) -> 0.50778655 | N80: =POSTTAX(N70,INDEX(Data_Prices!N:N,MATCH($G80,Data_Prices!$A:$A,0)),N$97) -> 0.47043643 | O80: =POSTTAX(O70,INDEX(Data_Prices!O:O,MATCH($G80,Data_Prices!$A:$A,0)),O$97) -> 0.47043643 | P80: =POSTTAX(P70,INDEX(Data_Prices!P:P,MATCH($G80,Data_Prices!$A:$A,0)),P$97) -> 0.47043643 | Q80: =POSTTAX(Q70,INDEX(Data_Prices!Q:Q,MATCH($G80,Data_Prices!$A:$A,0)),Q$97) -> 0.47043643 | R80: =POSTTAX(R70,INDEX(Data_Prices!R:R,MATCH($G80,Data_Prices!$A:$A,0)),R$97) -> 0.47043643 | S80: =POSTTAX(S70,INDEX(Data_Prices!S:S,MATCH($G80,Data_Prices!$A:$A,0)),S$97) -> 0.47043643 | T80: =POSTTAX(T70,INDEX(Data_Prices!T:T,MATCH($G80,Data_Prices!$A:$A,0)),T$97) -> 0.47043643 | U80: =POSTTAX(U70,INDEX(Data_Prices!U:U,MATCH($G80,Data_Prices!$A:$A,0)),U$97) -> 0.47043643 | V80: =POSTTAX(V70,INDEX(Data_Prices!V:V,MATCH($G80,Data_Prices!$A:$A,0)),V$97) -> 0.47043643 | W80: =POSTTAX(W70,INDEX(Data_Prices!W:W,MATCH($G80,Data_Prices!$A:$A,0)),W$97) -> 0.47043643 | X80: =POSTTAX(X70,INDEX(Data_Prices!X:X,MATCH($G80,Data_Prices!$A:$A,0)),X$97) -> 0.47043643 | Y80: =POSTTAX(Y70,INDEX(Data_Prices!Y:Y,MATCH($G80,Data_Prices!$A:$A,0)),Y$97) -> 0.47043643 | Z80: =POSTTAX(Z70,INDEX(Data_Prices!Z:Z,MATCH($G80,Data_Prices!$A:$A,0)),Z$97) -> 0.47043643 | AA80: =POSTTAX(AA70,INDEX(Data_Prices!AA:AA,MATCH($G80,Data_Prices!$A:$A,0)),AA$97) -> 0.47043643 | AB80: =POSTTAX(AB70,INDEX(Data_Prices!AB:AB,MATCH($G80,Data_Prices!$A:$A,0)),AB$97) -> 0.47043643 | AC80: =POSTTAX(AC70,INDEX(Data_Prices!AC:AC,MATCH($G80,Data_Prices!$A:$A,0)),AC$97) -> 0.47043643 | AD80: =POSTTAX(AD70,INDEX(Data_Prices!AD:AD,MATCH($G80,Data_Prices!$A:$A,0)),AD$97) -> 0.47043643 | AE80: =POSTTAX(AE70,INDEX(Data_Prices!AE:AE,MATCH($G80,Data_Prices!$A:$A,0)),AE$97) -> 0.47043643
B81: lpg | C81: =$C$65 -> cem | D81: LPG | E81: $/liter | F81: atp | G81: =Settings!$B$3&".mit.nce."&Settings!$B$4&"."&$B81&".a."&$J$65 -> egy.mit.nce.ind.lpg.a.1 | H81: =OUTCODE(Settings!$B$3,"atp",$C$65,$B81,$J$65) -> egy.mit.atp.cem.lpg.e.1 | K81: =POSTTAX(K71,INDEX(Data_Prices!K:K,MATCH($G81,Data_Prices!$A:$A,0)),K$97) -> 0.20036669 | L81: =POSTTAX(L71,INDEX(Data_Prices!L:L,MATCH($G81,Data_Prices!$A:$A,0)),L$97) -> 0.15734474 | M81: =POSTTAX(M71,INDEX(Data_Prices!M:M,MATCH($G81,Data_Prices!$A:$A,0)),M$97) -> 0.16448404 | N81: =POSTTAX(N71,INDEX(Data_Prices!N:N,MATCH($G81,Data_Prices!$A:$A,0)),N$97) -> 0.15070908 | O81: =POSTTAX(O71,INDEX(Data_Prices!O:O,MATCH($G81,Data_Prices!$A:$A,0)),O$97) -> 0.15070908 | P81: =POSTTAX(P71,INDEX(Data_Prices!P:P,MATCH($G81,Data_Prices!$A:$A,0)),P$97) -> 0.15070908 | Q81: =POSTTAX(Q71,INDEX(Data_Prices!Q:Q,MATCH($G81,Data_Prices!$A:$A,0)),Q$97) -> 0.15070908 | R81: =POSTTAX(R71,INDEX(Data_Prices!R:R,MATCH($G81,Data_Prices!$A:$A,0)),R$97) -> 0.15070908 | S81: =POSTTAX(S71,INDEX(Data_Prices!S:S,MATCH($G81,Data_Prices!$A:$A,0)),S$97) -> 0.15070908 | T81: =POSTTAX(T71,INDEX(Data_Prices!T:T,MATCH($G81,Data_Prices!$A:$A,0)),T$97) -> 0.15070908 | U81: =POSTTAX(U71,INDEX(Data_Prices!U:U,MATCH($G81,Data_Prices!$A:$A,0)),U$97) -> 0.15070908 | V81: =POSTTAX(V71,INDEX(Data_Prices!V:V,MATCH($G81,Data_Prices!$A:$A,0)),V$97) -> 0.15070908 | W81: =POSTTAX(W71,INDEX(Data_Prices!W:W,MATCH($G81,Data_Prices!$A:$A,0)),W$97) -> 0.15070908 | X81: =POSTTAX(X71,INDEX(Data_Prices!X:X,MATCH($G81,Data_Prices!$A:$A,0)),X$97) -> 0.15070908 | Y81: =POSTTAX(Y71,INDEX(Data_Prices!Y:Y,MATCH($G81,Data_Prices!$A:$A,0)),Y$97) -> 0.15070908 | Z81: =POSTTAX(Z71,INDEX(Data_Prices!Z:Z,MATCH($G81,Data_Prices!$A:$A,0)),Z$97) -> 0.15070908 | AA81: =POSTTAX(AA71,INDEX(Data_Prices!AA:AA,MATCH($G81,Data_Prices!$A:$A,0)),AA$97) -> 0.15070908 | AB81: =POSTTAX(AB71,INDEX(Data_Prices!AB:AB,MATCH($G81,Data_Prices!$A:$A,0)),AB$97) -> 0.15070908 | AC81: =POSTTAX(AC71,INDEX(Data_Prices!AC:AC,MATCH($G81,Data_Prices!$A:$A,0)),AC$97) -> 0.15070908 | AD81: =POSTTAX(AD71,INDEX(Data_Prices!AD:AD,MATCH($G81,Data_Prices!$A:$A,0)),AD$97) -> 0.15070908 | AE81: =POSTTAX(AE71,INDEX(Data_Prices!AE:AE,MATCH($G81,Data_Prices!$A:$A,0)),AE$97) -> 0.15070908
B82: ker | C82: =$C$65 -> cem | D82: Kerosene | E82: $/liter | F82: atp | G82: =Settings!$B$3&".mit.nce."&Settings!$B$4&"."&$B82&".a."&$J$65 -> egy.mit.nce.ind.ker.a.1 | H82: =OUTCODE(Settings!$B$3,"atp",$C$65,$B82,$J$65) -> egy.mit.atp.cem.ker.e.1 | K82: =POSTTAX(K72,INDEX(Data_Prices!K:K,MATCH($G82,Data_Prices!$A:$A,0)),K$97) -> 0.48429424 | L82: =POSTTAX(L72,INDEX(Data_Prices!L:L,MATCH($G82,Data_Prices!$A:$A,0)),L$97) -> 0.45642817 | M82: =POSTTAX(M72,INDEX(Data_Prices!M:M,MATCH($G82,Data_Prices!$A:$A,0)),M$97) -> 0.4316892 | N82: =POSTTAX(N72,INDEX(Data_Prices!N:N,MATCH($G82,Data_Prices!$A:$A,0)),N$97) -> 0.42507558 | O82: =POSTTAX(O72,INDEX(Data_Prices!O:O,MATCH($G82,Data_Prices!$A:$A,0)),O$97) -> 0.42507558 | P82: =POSTTAX(P72,INDEX(Data_Prices!P:P,MATCH($G82,Data_Prices!$A:$A,0)),P$97) -> 0.42507558 | Q82: =POSTTAX(Q72,INDEX(Data_Prices!Q:Q,MATCH($G82,Data_Prices!$A:$A,0)),Q$97) -> 0.42507558 | R82: =POSTTAX(R72,INDEX(Data_Prices!R:R,MATCH($G82,Data_Prices!$A:$A,0)),R$97) -> 0.42507558 | S82: =POSTTAX(S72,INDEX(Data_Prices!S:S,MATCH($G82,Data_Prices!$A:$A,0)),S$97) -> 0.42507558 | T82: =POSTTAX(T72,INDEX(Data_Prices!T:T,MATCH($G82,Data_Prices!$A:$A,0)),T$97) -> 0.42507558 | U82: =POSTTAX(U72,INDEX(Data_Prices!U:U,MATCH($G82,Data_Prices!$A:$A,0)),U$97) -> 0.42507558 | V82: =POSTTAX(V72,INDEX(Data_Prices!V:V,MATCH($G82,Data_Prices!$A:$A,0)),V$97) -> 0.42507558 | W82: =POSTTAX(W72,INDEX(Data_Prices!W:W,MATCH($G82,Data_Prices!$A:$A,0)),W$97) -> 0.42507558 | X82: =POSTTAX(X72,INDEX(Data_Prices!X:X,MATCH($G82,Data_Prices!$A:$A,0)),X$97) -> 0.42507558 | Y82: =POSTTAX(Y72,INDEX(Data_Prices!Y:Y,MATCH($G82,Data_Prices!$A:$A,0)),Y$97) -> 0.42507558 | Z82: =POSTTAX(Z72,INDEX(Data_Prices!Z:Z,MATCH($G82,Data_Prices!$A:$A,0)),Z$97) -> 0.42507558 | AA82: =POSTTAX(AA72,INDEX(Data_Prices!AA:AA,MATCH($G82,Data_Prices!$A:$A,0)),AA$97) -> 0.42507558 | AB82: =POSTTAX(AB72,INDEX(Data_Prices!AB:AB,MATCH($G82,Data_Prices!$A:$A,0)),AB$97) -> 0.42507558 | AC82: =POSTTAX(AC72,INDEX(Data_Prices!AC:AC,MATCH($G82,Data_Prices!$A:$A,0)),AC$97) -> 0.42507558 | AD82: =POSTTAX(AD72,INDEX(Data_Prices!AD:AD,MATCH($G82,Data_Prices!$A:$A,0)),AD$97) -> 0.42507558 | AE82: =POSTTAX(AE72,INDEX(Data_Prices!AE:AE,MATCH($G82,Data_Prices!$A:$A,0)),AE$97) -> 0.42507558
B83: oop | C83: =$C$65 -> cem | D83: Other oil products | E83: $/bbl | F83: atp | G83: =Settings!$B$3&".mit.nce."&Settings!$B$4&"."&$B83&".a."&$J$65 -> egy.mit.nce.ind.oop.a.1 | H83: =OUTCODE(Settings!$B$3,"atp",$C$65,$B83,$J$65) -> egy.mit.atp.cem.oop.e.1 | K83: =POSTTAX(K73,INDEX(Data_Prices!K:K,MATCH($G83,Data_Prices!$A:$A,0)),K$97) -> 41.500338 | L83: =POSTTAX(L73,INDEX(Data_Prices!L:L,MATCH($G83,Data_Prices!$A:$A,0)),L$97) -> 34.41537 | M83: =POSTTAX(M73,INDEX(Data_Prices!M:M,MATCH($G83,Data_Prices!$A:$A,0)),M$97) -> 37.368961 | N83: =POSTTAX(N73,INDEX(Data_Prices!N:N,MATCH($G83,Data_Prices!$A:$A,0)),N$97) -> 28.982761 | O83: =POSTTAX(O73,INDEX(Data_Prices!O:O,MATCH($G83,Data_Prices!$A:$A,0)),O$97) -> 15 | P83: =POSTTAX(P73,INDEX(Data_Prices!P:P,MATCH($G83,Data_Prices!$A:$A,0)),P$97) -> 24.25863 | Q83: =POSTTAX(Q73,INDEX(Data_Prices!Q:Q,MATCH($G83,Data_Prices!$A:$A,0)),Q$97) -> 15 | R83: =POSTTAX(R73,INDEX(Data_Prices!R:R,MATCH($G83,Data_Prices!$A:$A,0)),R$97) -> 15 | S83: =POSTTAX(S73,INDEX(Data_Prices!S:S,MATCH($G83,Data_Prices!$A:$A,0)),S$97) -> 15 | T83: =POSTTAX(T73,INDEX(Data_Prices!T:T,MATCH($G83,Data_Prices!$A:$A,0)),T$97) -> 15 | U83: =POSTTAX(U73,INDEX(Data_Prices!U:U,MATCH($G83,Data_Prices!$A:$A,0)),U$97) -> 15 | V83: =POSTTAX(V73,INDEX(Data_Prices!V:V,MATCH($G83,Data_Prices!$A:$A,0)),V$97) -> 15 | W83: =POSTTAX(W73,INDEX(Data_Prices!W:W,MATCH($G83,Data_Prices!$A:$A,0)),W$97) -> 15 | X83: =POSTTAX(X73,INDEX(Data_Prices!X:X,MATCH($G83,Data_Prices!$A:$A,0)),X$97) -> 15 | Y83: =POSTTAX(Y73,INDEX(Data_Prices!Y:Y,MATCH($G83,Data_Prices!$A:$A,0)),Y$97) -> 15 | Z83: =POSTTAX(Z73,INDEX(Data_Prices!Z:Z,MATCH($G83,Data_Prices!$A:$A,0)),Z$97) -> 15 | AA83: =POSTTAX(AA73,INDEX(Data_Prices!AA:AA,MATCH($G83,Data_Prices!$A:$A,0)),AA$97) -> 15 | AB83: =POSTTAX(AB73,INDEX(Data_Prices!AB:AB,MATCH($G83,Data_Prices!$A:$A,0)),AB$97) -> 15 | AC83: =POSTTAX(AC73,INDEX(Data_Prices!AC:AC,MATCH($G83,Data_Prices!$A:$A,0)),AC$97) -> 15 | AD83: =POSTTAX(AD73,INDEX(Data_Prices!AD:AD,MATCH($G83,Data_Prices!$A:$A,0)),AD$97) -> 15 | AE83: =POSTTAX(AE73,INDEX(Data_Prices!AE:AE,MATCH($G83,Data_Prices!$A:$A,0)),AE$97) -> 15
B84: bio | C84: =$C$65 -> cem | D84: Biomass | E84: $/GJ | F84: atp | G84: =Settings!$B$3&".mit.nce."&Settings!$B$4&"."&$B84&".a."&$J$65 -> egy.mit.nce.ind.bio.a.1 | H84: =OUTCODE(Settings!$B$3,"atp",$C$65,$B84,$J$65) -> egy.mit.atp.cem.bio.e.1 | K84: =POSTTAX(K74,INDEX(Data_Prices!K:K,MATCH($G84,Data_Prices!$A:$A,0)),K$97) -> 15.334551 | L84: =POSTTAX(L74,INDEX(Data_Prices!L:L,MATCH($G84,Data_Prices!$A:$A,0)),L$97) -> 14.199528 | M84: =POSTTAX(M74,INDEX(Data_Prices!M:M,MATCH($G84,Data_Prices!$A:$A,0)),M$97) -> 13.840442 | N84: =POSTTAX(N74,INDEX(Data_Prices!N:N,MATCH($G84,Data_Prices!$A:$A,0)),N$97) -> 13.567727 | O84: =POSTTAX(O74,INDEX(Data_Prices!O:O,MATCH($G84,Data_Prices!$A:$A,0)),O$97) -> 13.567727 | P84: =POSTTAX(P74,INDEX(Data_Prices!P:P,MATCH($G84,Data_Prices!$A:$A,0)),P$97) -> 13.567727 | Q84: =POSTTAX(Q74,INDEX(Data_Prices!Q:Q,MATCH($G84,Data_Prices!$A:$A,0)),Q$97) -> 13.567727 | R84: =POSTTAX(R74,INDEX(Data_Prices!R:R,MATCH($G84,Data_Prices!$A:$A,0)),R$97) -> 13.567727 | S84: =POSTTAX(S74,INDEX(Data_Prices!S:S,MATCH($G84,Data_Prices!$A:$A,0)),S$97) -> 13.567727 | T84: =POSTTAX(T74,INDEX(Data_Prices!T:T,MATCH($G84,Data_Prices!$A:$A,0)),T$97) -> 13.567727 | U84: =POSTTAX(U74,INDEX(Data_Prices!U:U,MATCH($G84,Data_Prices!$A:$A,0)),U$97) -> 13.567727 | V84: =POSTTAX(V74,INDEX(Data_Prices!V:V,MATCH($G84,Data_Prices!$A:$A,0)),V$97) -> 13.567727 | W84: =POSTTAX(W74,INDEX(Data_Prices!W:W,MATCH($G84,Data_Prices!$A:$A,0)),W$97) -> 13.567727 | X84: =POSTTAX(X74,INDEX(Data_Prices!X:X,MATCH($G84,Data_Prices!$A:$A,0)),X$97) -> 13.567727 | Y84: =POSTTAX(Y74,INDEX(Data_Prices!Y:Y,MATCH($G84,Data_Prices!$A:$A,0)),Y$97) -> 13.567727 | Z84: =POSTTAX(Z74,INDEX(Data_Prices!Z:Z,MATCH($G84,Data_Prices!$A:$A,0)),Z$97) -> 13.567727 | AA84: =POSTTAX(AA74,INDEX(Data_Prices!AA:AA,MATCH($G84,Data_Prices!$A:$A,0)),AA$97) -> 13.567727 | AB84: =POSTTAX(AB74,INDEX(Data_Prices!AB:AB,MATCH($G84,Data_Prices!$A:$A,0)),AB$97) -> 13.567727 | AC84: =POSTTAX(AC74,INDEX(Data_Prices!AC:AC,MATCH($G84,Data_Prices!$A:$A,0)),AC$97) -> 13.567727 | AD84: =POSTTAX(AD74,INDEX(Data_Prices!AD:AD,MATCH($G84,Data_Prices!$A:$A,0)),AD$97) -> 13.567727 | AE84: =POSTTAX(AE74,INDEX(Data_Prices!AE:AE,MATCH($G84,Data_Prices!$A:$A,0)),AE$97) -> 13.567727
B85: ren | C85: =$C$65 -> cem | D85: Self-generated renewables | E85: $/kwh | F85: atp | G85: =Settings!$B$3&".mit.nce."&Settings!$B$4&"."&$B85&".a."&$J$65 -> egy.mit.nce.ind.ren.a.1 | H85: =OUTCODE(Settings!$B$3,"atp",$C$65,$B85,$J$65) -> egy.mit.atp.cem.ren.e.1 | K85: =POSTTAX(K75,INDEX(Data_Prices!K:K,MATCH($G85,Data_Prices!$A:$A,0)),K$97) -> 0 | L85: =POSTTAX(L75,INDEX(Data_Prices!L:L,MATCH($G85,Data_Prices!$A:$A,0)),L$97) -> 0.14404499 | M85: =POSTTAX(M75,INDEX(Data_Prices!M:M,MATCH($G85,Data_Prices!$A:$A,0)),M$97) -> 0.14102041 | N85: =POSTTAX(N75,INDEX(Data_Prices!N:N,MATCH($G85,Data_Prices!$A:$A,0)),N$97) -> 0.13511636 | O85: =POSTTAX(O75,INDEX(Data_Prices!O:O,MATCH($G85,Data_Prices!$A:$A,0)),O$97) -> 0.13098826 | P85: =POSTTAX(P75,INDEX(Data_Prices!P:P,MATCH($G85,Data_Prices!$A:$A,0)),P$97) -> 0.12790842 | Q85: =POSTTAX(Q75,INDEX(Data_Prices!Q:Q,MATCH($G85,Data_Prices!$A:$A,0)),Q$97) -> 0.12481431 | R85: =POSTTAX(R75,INDEX(Data_Prices!R:R,MATCH($G85,Data_Prices!$A:$A,0)),R$97) -> 0.12146026 | S85: =POSTTAX(S75,INDEX(Data_Prices!S:S,MATCH($G85,Data_Prices!$A:$A,0)),S$97) -> 0.11795074 | T85: =POSTTAX(T75,INDEX(Data_Prices!T:T,MATCH($G85,Data_Prices!$A:$A,0)),T$97) -> 0.11419916 | U85: =POSTTAX(U75,INDEX(Data_Prices!U:U,MATCH($G85,Data_Prices!$A:$A,0)),U$97) -> 0.1136651 | V85: =POSTTAX(V75,INDEX(Data_Prices!V:V,MATCH($G85,Data_Prices!$A:$A,0)),V$97) -> 0.11301693 | W85: =POSTTAX(W75,INDEX(Data_Prices!W:W,MATCH($G85,Data_Prices!$A:$A,0)),W$97) -> 0.11231407 | X85: =POSTTAX(X75,INDEX(Data_Prices!X:X,MATCH($G85,Data_Prices!$A:$A,0)),X$97) -> 0.11142204 | Y85: =POSTTAX(Y75,INDEX(Data_Prices!Y:Y,MATCH($G85,Data_Prices!$A:$A,0)),Y$97) -> 0.11043412 | Z85: =POSTTAX(Z75,INDEX(Data_Prices!Z:Z,MATCH($G85,Data_Prices!$A:$A,0)),Z$97) -> 0.10948397 | AA85: =POSTTAX(AA75,INDEX(Data_Prices!AA:AA,MATCH($G85,Data_Prices!$A:$A,0)),AA$97) -> 0.10839192 | AB85: =POSTTAX(AB75,INDEX(Data_Prices!AB:AB,MATCH($G85,Data_Prices!$A:$A,0)),AB$97) -> 0.10735443 | AC85: =POSTTAX(AC75,INDEX(Data_Prices!AC:AC,MATCH($G85,Data_Prices!$A:$A,0)),AC$97) -> 0.10516868 | AD85: =POSTTAX(AD75,INDEX(Data_Prices!AD:AD,MATCH($G85,Data_Prices!$A:$A,0)),AD$97) -> 0.10305798 | AE85: =POSTTAX(AE75,INDEX(Data_Prices!AE:AE,MATCH($G85,Data_Prices!$A:$A,0)),AE$97) -> 0.10093184
B86: Shadow price: post-tax + shadow price of non-price policies x share acting on efficiency
B87: coa | C87: =$C$65 -> cem | D87: Coal | E87: $/GJ | F87: shp | G87: =Settings!$B$3&".mit.shp."&$B87&"."&Settings!$B$4&"."&$J$65 -> egy.mit.shp.coa.ind.1 | H87: =OUTCODE(Settings!$B$3,"shp",$C$65,$B87,$J$65) -> egy.mit.shp.cem.coa.e.1 | K87: =SHADOW(K77,INDEX(Data_Prices!K:K,MATCH($G87,Data_Prices!$A:$A,0)),K$98) -> 11.182902 | L87: =SHADOW(L77,INDEX(Data_Prices!L:L,MATCH($G87,Data_Prices!$A:$A,0)),L$98) -> 10.523361 | M87: =SHADOW(M77,INDEX(Data_Prices!M:M,MATCH($G87,Data_Prices!$A:$A,0)),M$98) -> 10.299561 | N87: =SHADOW(N77,INDEX(Data_Prices!N:N,MATCH($G87,Data_Prices!$A:$A,0)),N$98) -> 9.5775284 | O87: =SHADOW(O77,INDEX(Data_Prices!O:O,MATCH($G87,Data_Prices!$A:$A,0)),O$98) -> 8.4854783 | P87: =SHADOW(P77,INDEX(Data_Prices!P:P,MATCH($G87,Data_Prices!$A:$A,0)),P$98) -> 9.0871922 | Q87: =SHADOW(Q77,INDEX(Data_Prices!Q:Q,MATCH($G87,Data_Prices!$A:$A,0)),Q$98) -> 9.2229237 | R87: =SHADOW(R77,INDEX(Data_Prices!R:R,MATCH($G87,Data_Prices!$A:$A,0)),R$98) -> 9.158565 | S87: =SHADOW(S77,INDEX(Data_Prices!S:S,MATCH($G87,Data_Prices!$A:$A,0)),S$98) -> 9.0895479 | T87: =SHADOW(T77,INDEX(Data_Prices!T:T,MATCH($G87,Data_Prices!$A:$A,0)),T$98) -> 9.0156817 | U87: =SHADOW(U77,INDEX(Data_Prices!U:U,MATCH($G87,Data_Prices!$A:$A,0)),U$98) -> 8.9443978 | V87: =SHADOW(V77,INDEX(Data_Prices!V:V,MATCH($G87,Data_Prices!$A:$A,0)),V$98) -> 8.9443978 | W87: =SHADOW(W77,INDEX(Data_Prices!W:W,MATCH($G87,Data_Prices!$A:$A,0)),W$98) -> 8.9443978 | X87: =SHADOW(X77,INDEX(Data_Prices!X:X,MATCH($G87,Data_Prices!$A:$A,0)),X$98) -> 8.9443978 | Y87: =SHADOW(Y77,INDEX(Data_Prices!Y:Y,MATCH($G87,Data_Prices!$A:$A,0)),Y$98) -> 8.9443978 | Z87: =SHADOW(Z77,INDEX(Data_Prices!Z:Z,MATCH($G87,Data_Prices!$A:$A,0)),Z$98) -> 8.9443978 | AA87: =SHADOW(AA77,INDEX(Data_Prices!AA:AA,MATCH($G87,Data_Prices!$A:$A,0)),AA$98) -> 8.9443978 | AB87: =SHADOW(AB77,INDEX(Data_Prices!AB:AB,MATCH($G87,Data_Prices!$A:$A,0)),AB$98) -> 8.9443978 | AC87: =SHADOW(AC77,INDEX(Data_Prices!AC:AC,MATCH($G87,Data_Prices!$A:$A,0)),AC$98) -> 8.9443978 | AD87: =SHADOW(AD77,INDEX(Data_Prices!AD:AD,MATCH($G87,Data_Prices!$A:$A,0)),AD$98) -> 8.9443978 | AE87: =SHADOW(AE77,INDEX(Data_Prices!AE:AE,MATCH($G87,Data_Prices!$A:$A,0)),AE$98) -> 8.9443978
B88: nga | C88: =$C$65 -> cem | D88: Natural gas | E88: $/GJ | F88: shp | G88: =Settings!$B$3&".mit.shp."&$B88&"."&Settings!$B$4&"."&$J$65 -> egy.mit.shp.nga.ind.1 | H88: =OUTCODE(Settings!$B$3,"shp",$C$65,$B88,$J$65) -> egy.mit.shp.cem.nga.e.1 | K88: =SHADOW(K78,INDEX(Data_Prices!K:K,MATCH($G88,Data_Prices!$A:$A,0)),K$98) -> 6.0634636 | L88: =SHADOW(L78,INDEX(Data_Prices!L:L,MATCH($G88,Data_Prices!$A:$A,0)),L$98) -> 5.4510151 | M88: =SHADOW(M78,INDEX(Data_Prices!M:M,MATCH($G88,Data_Prices!$A:$A,0)),M$98) -> 5.1193563 | N88: =SHADOW(N78,INDEX(Data_Prices!N:N,MATCH($G88,Data_Prices!$A:$A,0)),N$98) -> 5.0821846 | O88: =SHADOW(O78,INDEX(Data_Prices!O:O,MATCH($G88,Data_Prices!$A:$A,0)),O$98) -> 5.0821846 | P88: =SHADOW(P78,INDEX(Data_Prices!P:P,MATCH($G88,Data_Prices!$A:$A,0)),P$98) -> 5.0821846 | Q88: =SHADOW(Q78,INDEX(Data_Prices!Q:Q,MATCH($G88,Data_Prices!$A:$A,0)),Q$98) -> 5.0821846 | R88: =SHADOW(R78,INDEX(Data_Prices!R:R,MATCH($G88,Data_Prices!$A:$A,0)),R$98) -> 5.0821846 | S88: =SHADOW(S78,INDEX(Data_Prices!S:S,MATCH($G88,Data_Prices!$A:$A,0)),S$98) -> 5.0821846 | T88: =SHADOW(T78,INDEX(Data_Prices!T:T,MATCH($G88,Data_Prices!$A:$A,0)),T$98) -> 5.0821846 | U88: =SHADOW(U78,INDEX(Data_Prices!U:U,MATCH($G88,Data_Prices!$A:$A,0)),U$98) -> 5.0821846 | V88: =SHADOW(V78,INDEX(Data_Prices!V:V,MATCH($G88,Data_Prices!$A:$A,0)),V$98) -> 5.0821846 | W88: =SHADOW(W78,INDEX(Data_Prices!W:W,MATCH($G88,Data_Prices!$A:$A,0)),W$98) -> 5.0821846 | X88: =SHADOW(X78,INDEX(Data_Prices!X:X,MATCH($G88,Data_Prices!$A:$A,0)),X$98) -> 5.0821846 | Y88: =SHADOW(Y78,INDEX(Data_Prices!Y:Y,MATCH($G88,Data_Prices!$A:$A,0)),Y$98) -> 5.0821846 | Z88: =SHADOW(Z78,INDEX(Data_Prices!Z:Z,MATCH($G88,Data_Prices!$A:$A,0)),Z$98) -> 5.0821846 | AA88: =SHADOW(AA78,INDEX(Data_Prices!AA:AA,MATCH($G88,Data_Prices!$A:$A,0)),AA$98) -> 5.0821846 | AB88: =SHADOW(AB78,INDEX(Data_Prices!AB:AB,MATCH($G88,Data_Prices!$A:$A,0)),AB$98) -> 5.0821846 | AC88: =SHADOW(AC78,INDEX(Data_Prices!AC:AC,MATCH($G88,Data_Prices!$A:$A,0)),AC$98) -> 5.0821846 | AD88: =SHADOW(AD78,INDEX(Data_Prices!AD:AD,MATCH($G88,Data_Prices!$A:$A,0)),AD$98) -> 5.0821846 | AE88: =SHADOW(AE78,INDEX(Data_Prices!AE:AE,MATCH($G88,Data_Prices!$A:$A,0)),AE$98) -> 5.0821846
B89: gso | C89: =$C$65 -> cem | D89: Gasoline | E89: $/liter | F89: shp | G89: =Settings!$B$3&".mit.shp."&$B89&"."&Settings!$B$4&"."&$J$65 -> egy.mit.shp.gso.ind.1 | H89: =OUTCODE(Settings!$B$3,"shp",$C$65,$B89,$J$65) -> egy.mit.shp.cem.gso.e.1 | K89: =SHADOW(K79,INDEX(Data_Prices!K:K,MATCH($G89,Data_Prices!$A:$A,0)),K$98) -> 0.67114653 | L89: =SHADOW(L79,INDEX(Data_Prices!L:L,MATCH($G89,Data_Prices!$A:$A,0)),L$98) -> 0.61197798 | M89: =SHADOW(M79,INDEX(Data_Prices!M:M,MATCH($G89,Data_Prices!$A:$A,0)),M$98) -> 0.61180975 | N89: =SHADOW(N79,INDEX(Data_Prices!N:N,MATCH($G89,Data_Prices!$A:$A,0)),N$98) -> 0.6035831 | O89: =SHADOW(O79,INDEX(Data_Prices!O:O,MATCH($G89,Data_Prices!$A:$A,0)),O$98) -> 0.6035831 | P89: =SHADOW(P79,INDEX(Data_Prices!P:P,MATCH($G89,Data_Prices!$A:$A,0)),P$98) -> 0.6035831 | Q89: =SHADOW(Q79,INDEX(Data_Prices!Q:Q,MATCH($G89,Data_Prices!$A:$A,0)),Q$98) -> 0.6035831 | R89: =SHADOW(R79,INDEX(Data_Prices!R:R,MATCH($G89,Data_Prices!$A:$A,0)),R$98) -> 0.6035831 | S89: =SHADOW(S79,INDEX(Data_Prices!S:S,MATCH($G89,Data_Prices!$A:$A,0)),S$98) -> 0.6035831 | T89: =SHADOW(T79,INDEX(Data_Prices!T:T,MATCH($G89,Data_Prices!$A:$A,0)),T$98) -> 0.6035831 | U89: =SHADOW(U79,INDEX(Data_Prices!U:U,MATCH($G89,Data_Prices!$A:$A,0)),U$98) -> 0.6035831 | V89: =SHADOW(V79,INDEX(Data_Prices!V:V,MATCH($G89,Data_Prices!$A:$A,0)),V$98) -> 0.6035831 | W89: =SHADOW(W79,INDEX(Data_Prices!W:W,MATCH($G89,Data_Prices!$A:$A,0)),W$98) -> 0.6035831 | X89: =SHADOW(X79,INDEX(Data_Prices!X:X,MATCH($G89,Data_Prices!$A:$A,0)),X$98) -> 0.6035831 | Y89: =SHADOW(Y79,INDEX(Data_Prices!Y:Y,MATCH($G89,Data_Prices!$A:$A,0)),Y$98) -> 0.6035831 | Z89: =SHADOW(Z79,INDEX(Data_Prices!Z:Z,MATCH($G89,Data_Prices!$A:$A,0)),Z$98) -> 0.6035831 | AA89: =SHADOW(AA79,INDEX(Data_Prices!AA:AA,MATCH($G89,Data_Prices!$A:$A,0)),AA$98) -> 0.6035831 | AB89: =SHADOW(AB79,INDEX(Data_Prices!AB:AB,MATCH($G89,Data_Prices!$A:$A,0)),AB$98) -> 0.6035831 | AC89: =SHADOW(AC79,INDEX(Data_Prices!AC:AC,MATCH($G89,Data_Prices!$A:$A,0)),AC$98) -> 0.6035831 | AD89: =SHADOW(AD79,INDEX(Data_Prices!AD:AD,MATCH($G89,Data_Prices!$A:$A,0)),AD$98) -> 0.6035831 | AE89: =SHADOW(AE79,INDEX(Data_Prices!AE:AE,MATCH($G89,Data_Prices!$A:$A,0)),AE$98) -> 0.6035831
B90: die | C90: =$C$65 -> cem | D90: Diesel | E90: $/liter | F90: shp | G90: =Settings!$B$3&".mit.shp."&$B90&"."&Settings!$B$4&"."&$J$65 -> egy.mit.shp.die.ind.1 | H90: =OUTCODE(Settings!$B$3,"shp",$C$65,$B90,$J$65) -> egy.mit.shp.cem.die.e.1 | K90: =SHADOW(K80,INDEX(Data_Prices!K:K,MATCH($G90,Data_Prices!$A:$A,0)),K$98) -> 0.55971121 | L90: =SHADOW(L80,INDEX(Data_Prices!L:L,MATCH($G90,Data_Prices!$A:$A,0)),L$98) -> 0.49458873 | M90: =SHADOW(M80,INDEX(Data_Prices!M:M,MATCH($G90,Data_Prices!$A:$A,0)),M$98) -> 0.50778655 | N90: =SHADOW(N80,INDEX(Data_Prices!N:N,MATCH($G90,Data_Prices!$A:$A,0)),N$98) -> 0.47043643 | O90: =SHADOW(O80,INDEX(Data_Prices!O:O,MATCH($G90,Data_Prices!$A:$A,0)),O$98) -> 0.47043643 | P90: =SHADOW(P80,INDEX(Data_Prices!P:P,MATCH($G90,Data_Prices!$A:$A,0)),P$98) -> 0.47043643 | Q90: =SHADOW(Q80,INDEX(Data_Prices!Q:Q,MATCH($G90,Data_Prices!$A:$A,0)),Q$98) -> 0.47043643 | R90: =SHADOW(R80,INDEX(Data_Prices!R:R,MATCH($G90,Data_Prices!$A:$A,0)),R$98) -> 0.47043643 | S90: =SHADOW(S80,INDEX(Data_Prices!S:S,MATCH($G90,Data_Prices!$A:$A,0)),S$98) -> 0.47043643 | T90: =SHADOW(T80,INDEX(Data_Prices!T:T,MATCH($G90,Data_Prices!$A:$A,0)),T$98) -> 0.47043643 | U90: =SHADOW(U80,INDEX(Data_Prices!U:U,MATCH($G90,Data_Prices!$A:$A,0)),U$98) -> 0.47043643 | V90: =SHADOW(V80,INDEX(Data_Prices!V:V,MATCH($G90,Data_Prices!$A:$A,0)),V$98) -> 0.47043643 | W90: =SHADOW(W80,INDEX(Data_Prices!W:W,MATCH($G90,Data_Prices!$A:$A,0)),W$98) -> 0.47043643 | X90: =SHADOW(X80,INDEX(Data_Prices!X:X,MATCH($G90,Data_Prices!$A:$A,0)),X$98) -> 0.47043643 | Y90: =SHADOW(Y80,INDEX(Data_Prices!Y:Y,MATCH($G90,Data_Prices!$A:$A,0)),Y$98) -> 0.47043643 | Z90: =SHADOW(Z80,INDEX(Data_Prices!Z:Z,MATCH($G90,Data_Prices!$A:$A,0)),Z$98) -> 0.47043643 | AA90: =SHADOW(AA80,INDEX(Data_Prices!AA:AA,MATCH($G90,Data_Prices!$A:$A,0)),AA$98) -> 0.47043643 | AB90: =SHADOW(AB80,INDEX(Data_Prices!AB:AB,MATCH($G90,Data_Prices!$A:$A,0)),AB$98) -> 0.47043643 | AC90: =SHADOW(AC80,INDEX(Data_Prices!AC:AC,MATCH($G90,Data_Prices!$A:$A,0)),AC$98) -> 0.47043643 | AD90: =SHADOW(AD80,INDEX(Data_Prices!AD:AD,MATCH($G90,Data_Prices!$A:$A,0)),AD$98) -> 0.47043643 | AE90: =SHADOW(AE80,INDEX(Data_Prices!AE:AE,MATCH($G90,Data_Prices!$A:$A,0)),AE$98) -> 0.47043643
B91: lpg | C91: =$C$65 -> cem | D91: LPG | E91: $/liter | F91: shp | G91: =Settings!$B$3&".mit.shp."&$B91&"."&Settings!$B$4&"."&$J$65 -> egy.mit.shp.lpg.ind.1 | H91: =OUTCODE(Settings!$B$3,"shp",$C$65,$B91,$J$65) -> egy.mit.shp.cem.lpg.e.1 | K91: =SHADOW(K81,INDEX(Data_Prices!K:K,MATCH($G91,Data_Prices!$A:$A,0)),K$98) -> 0.20036669 | L91: =SHADOW(L81,INDEX(Data_Prices!L:L,MATCH($G91,Data_Prices!$A:$A,0)),L$98) -> 0.15734474 | M91: =SHADOW(M81,INDEX(Data_Prices!M:M,MATCH($G91,Data_Prices!$A:$A,0)),M$98) -> 0.16448404 | N91: =SHADOW(N81,INDEX(Data_Prices!N:N,MATCH($G91,Data_Prices!$A:$A,0)),N$98) -> 0.15070908 | O91: =SHADOW(O81,INDEX(Data_Prices!O:O,MATCH($G91,Data_Prices!$A:$A,0)),O$98) -> 0.15070908 | P91: =SHADOW(P81,INDEX(Data_Prices!P:P,MATCH($G91,Data_Prices!$A:$A,0)),P$98) -> 0.15070908 | Q91: =SHADOW(Q81,INDEX(Data_Prices!Q:Q,MATCH($G91,Data_Prices!$A:$A,0)),Q$98) -> 0.15070908 | R91: =SHADOW(R81,INDEX(Data_Prices!R:R,MATCH($G91,Data_Prices!$A:$A,0)),R$98) -> 0.15070908 | S91: =SHADOW(S81,INDEX(Data_Prices!S:S,MATCH($G91,Data_Prices!$A:$A,0)),S$98) -> 0.15070908 | T91: =SHADOW(T81,INDEX(Data_Prices!T:T,MATCH($G91,Data_Prices!$A:$A,0)),T$98) -> 0.15070908 | U91: =SHADOW(U81,INDEX(Data_Prices!U:U,MATCH($G91,Data_Prices!$A:$A,0)),U$98) -> 0.15070908 | V91: =SHADOW(V81,INDEX(Data_Prices!V:V,MATCH($G91,Data_Prices!$A:$A,0)),V$98) -> 0.15070908 | W91: =SHADOW(W81,INDEX(Data_Prices!W:W,MATCH($G91,Data_Prices!$A:$A,0)),W$98) -> 0.15070908 | X91: =SHADOW(X81,INDEX(Data_Prices!X:X,MATCH($G91,Data_Prices!$A:$A,0)),X$98) -> 0.15070908 | Y91: =SHADOW(Y81,INDEX(Data_Prices!Y:Y,MATCH($G91,Data_Prices!$A:$A,0)),Y$98) -> 0.15070908 | Z91: =SHADOW(Z81,INDEX(Data_Prices!Z:Z,MATCH($G91,Data_Prices!$A:$A,0)),Z$98) -> 0.15070908 | AA91: =SHADOW(AA81,INDEX(Data_Prices!AA:AA,MATCH($G91,Data_Prices!$A:$A,0)),AA$98) -> 0.15070908 | AB91: =SHADOW(AB81,INDEX(Data_Prices!AB:AB,MATCH($G91,Data_Prices!$A:$A,0)),AB$98) -> 0.15070908 | AC91: =SHADOW(AC81,INDEX(Data_Prices!AC:AC,MATCH($G91,Data_Prices!$A:$A,0)),AC$98) -> 0.15070908 | AD91: =SHADOW(AD81,INDEX(Data_Prices!AD:AD,MATCH($G91,Data_Prices!$A:$A,0)),AD$98) -> 0.15070908 | AE91: =SHADOW(AE81,INDEX(Data_Prices!AE:AE,MATCH($G91,Data_Prices!$A:$A,0)),AE$98) -> 0.15070908
B92: ker | C92: =$C$65 -> cem | D92: Kerosene | E92: $/liter | F92: shp | G92: =Settings!$B$3&".mit.shp."&$B92&"."&Settings!$B$4&"."&$J$65 -> egy.mit.shp.ker.ind.1 | H92: =OUTCODE(Settings!$B$3,"shp",$C$65,$B92,$J$65) -> egy.mit.shp.cem.ker.e.1 | K92: =SHADOW(K82,INDEX(Data_Prices!K:K,MATCH($G92,Data_Prices!$A:$A,0)),K$98) -> 0.48429424 | L92: =SHADOW(L82,INDEX(Data_Prices!L:L,MATCH($G92,Data_Prices!$A:$A,0)),L$98) -> 0.45642817 | M92: =SHADOW(M82,INDEX(Data_Prices!M:M,MATCH($G92,Data_Prices!$A:$A,0)),M$98) -> 0.4316892 | N92: =SHADOW(N82,INDEX(Data_Prices!N:N,MATCH($G92,Data_Prices!$A:$A,0)),N$98) -> 0.42507558 | O92: =SHADOW(O82,INDEX(Data_Prices!O:O,MATCH($G92,Data_Prices!$A:$A,0)),O$98) -> 0.42507558 | P92: =SHADOW(P82,INDEX(Data_Prices!P:P,MATCH($G92,Data_Prices!$A:$A,0)),P$98) -> 0.42507558 | Q92: =SHADOW(Q82,INDEX(Data_Prices!Q:Q,MATCH($G92,Data_Prices!$A:$A,0)),Q$98) -> 0.42507558 | R92: =SHADOW(R82,INDEX(Data_Prices!R:R,MATCH($G92,Data_Prices!$A:$A,0)),R$98) -> 0.42507558 | S92: =SHADOW(S82,INDEX(Data_Prices!S:S,MATCH($G92,Data_Prices!$A:$A,0)),S$98) -> 0.42507558 | T92: =SHADOW(T82,INDEX(Data_Prices!T:T,MATCH($G92,Data_Prices!$A:$A,0)),T$98) -> 0.42507558 | U92: =SHADOW(U82,INDEX(Data_Prices!U:U,MATCH($G92,Data_Prices!$A:$A,0)),U$98) -> 0.42507558 | V92: =SHADOW(V82,INDEX(Data_Prices!V:V,MATCH($G92,Data_Prices!$A:$A,0)),V$98) -> 0.42507558 | W92: =SHADOW(W82,INDEX(Data_Prices!W:W,MATCH($G92,Data_Prices!$A:$A,0)),W$98) -> 0.42507558 | X92: =SHADOW(X82,INDEX(Data_Prices!X:X,MATCH($G92,Data_Prices!$A:$A,0)),X$98) -> 0.42507558 | Y92: =SHADOW(Y82,INDEX(Data_Prices!Y:Y,MATCH($G92,Data_Prices!$A:$A,0)),Y$98) -> 0.42507558 | Z92: =SHADOW(Z82,INDEX(Data_Prices!Z:Z,MATCH($G92,Data_Prices!$A:$A,0)),Z$98) -> 0.42507558 | AA92: =SHADOW(AA82,INDEX(Data_Prices!AA:AA,MATCH($G92,Data_Prices!$A:$A,0)),AA$98) -> 0.42507558 | AB92: =SHADOW(AB82,INDEX(Data_Prices!AB:AB,MATCH($G92,Data_Prices!$A:$A,0)),AB$98) -> 0.42507558 | AC92: =SHADOW(AC82,INDEX(Data_Prices!AC:AC,MATCH($G92,Data_Prices!$A:$A,0)),AC$98) -> 0.42507558 | AD92: =SHADOW(AD82,INDEX(Data_Prices!AD:AD,MATCH($G92,Data_Prices!$A:$A,0)),AD$98) -> 0.42507558 | AE92: =SHADOW(AE82,INDEX(Data_Prices!AE:AE,MATCH($G92,Data_Prices!$A:$A,0)),AE$98) -> 0.42507558
B93: oop | C93: =$C$65 -> cem | D93: Other oil products | E93: $/bbl | F93: shp | G93: =Settings!$B$3&".mit.shp."&$B93&"."&Settings!$B$4&"."&$J$65 -> egy.mit.shp.oop.ind.1 | H93: =OUTCODE(Settings!$B$3,"shp",$C$65,$B93,$J$65) -> egy.mit.shp.cem.oop.e.1 | K93: =SHADOW(K83,INDEX(Data_Prices!K:K,MATCH($G93,Data_Prices!$A:$A,0)),K$98) -> 41.500338 | L93: =SHADOW(L83,INDEX(Data_Prices!L:L,MATCH($G93,Data_Prices!$A:$A,0)),L$98) -> 34.41537 | M93: =SHADOW(M83,INDEX(Data_Prices!M:M,MATCH($G93,Data_Prices!$A:$A,0)),M$98) -> 37.368961 | N93: =SHADOW(N83,INDEX(Data_Prices!N:N,MATCH($G93,Data_Prices!$A:$A,0)),N$98) -> 28.982761 | O93: =SHADOW(O83,INDEX(Data_Prices!O:O,MATCH($G93,Data_Prices!$A:$A,0)),O$98) -> 15 | P93: =SHADOW(P83,INDEX(Data_Prices!P:P,MATCH($G93,Data_Prices!$A:$A,0)),P$98) -> 24.25863 | Q93: =SHADOW(Q83,INDEX(Data_Prices!Q:Q,MATCH($G93,Data_Prices!$A:$A,0)),Q$98) -> 15 | R93: =SHADOW(R83,INDEX(Data_Prices!R:R,MATCH($G93,Data_Prices!$A:$A,0)),R$98) -> 15 | S93: =SHADOW(S83,INDEX(Data_Prices!S:S,MATCH($G93,Data_Prices!$A:$A,0)),S$98) -> 15 | T93: =SHADOW(T83,INDEX(Data_Prices!T:T,MATCH($G93,Data_Prices!$A:$A,0)),T$98) -> 15 | U93: =SHADOW(U83,INDEX(Data_Prices!U:U,MATCH($G93,Data_Prices!$A:$A,0)),U$98) -> 15 | V93: =SHADOW(V83,INDEX(Data_Prices!V:V,MATCH($G93,Data_Prices!$A:$A,0)),V$98) -> 15 | W93: =SHADOW(W83,INDEX(Data_Prices!W:W,MATCH($G93,Data_Prices!$A:$A,0)),W$98) -> 15 | X93: =SHADOW(X83,INDEX(Data_Prices!X:X,MATCH($G93,Data_Prices!$A:$A,0)),X$98) -> 15 | Y93: =SHADOW(Y83,INDEX(Data_Prices!Y:Y,MATCH($G93,Data_Prices!$A:$A,0)),Y$98) -> 15 | Z93: =SHADOW(Z83,INDEX(Data_Prices!Z:Z,MATCH($G93,Data_Prices!$A:$A,0)),Z$98) -> 15 | AA93: =SHADOW(AA83,INDEX(Data_Prices!AA:AA,MATCH($G93,Data_Prices!$A:$A,0)),AA$98) -> 15 | AB93: =SHADOW(AB83,INDEX(Data_Prices!AB:AB,MATCH($G93,Data_Prices!$A:$A,0)),AB$98) -> 15 | AC93: =SHADOW(AC83,INDEX(Data_Prices!AC:AC,MATCH($G93,Data_Prices!$A:$A,0)),AC$98) -> 15 | AD93: =SHADOW(AD83,INDEX(Data_Prices!AD:AD,MATCH($G93,Data_Prices!$A:$A,0)),AD$98) -> 15 | AE93: =SHADOW(AE83,INDEX(Data_Prices!AE:AE,MATCH($G93,Data_Prices!$A:$A,0)),AE$98) -> 15
B94: bio | C94: =$C$65 -> cem | D94: Biomass | E94: $/GJ | F94: shp | G94: =Settings!$B$3&".mit.shp."&$B94&"."&Settings!$B$4&"."&$J$65 -> egy.mit.shp.bio.ind.1 | H94: =OUTCODE(Settings!$B$3,"shp",$C$65,$B94,$J$65) -> egy.mit.shp.cem.bio.e.1 | K94: =SHADOW(K84,INDEX(Data_Prices!K:K,MATCH($G94,Data_Prices!$A:$A,0)),K$98) -> 15.334551 | L94: =SHADOW(L84,INDEX(Data_Prices!L:L,MATCH($G94,Data_Prices!$A:$A,0)),L$98) -> 14.199528 | M94: =SHADOW(M84,INDEX(Data_Prices!M:M,MATCH($G94,Data_Prices!$A:$A,0)),M$98) -> 13.840442 | N94: =SHADOW(N84,INDEX(Data_Prices!N:N,MATCH($G94,Data_Prices!$A:$A,0)),N$98) -> 13.567727 | O94: =SHADOW(O84,INDEX(Data_Prices!O:O,MATCH($G94,Data_Prices!$A:$A,0)),O$98) -> 13.567727 | P94: =SHADOW(P84,INDEX(Data_Prices!P:P,MATCH($G94,Data_Prices!$A:$A,0)),P$98) -> 13.567727 | Q94: =SHADOW(Q84,INDEX(Data_Prices!Q:Q,MATCH($G94,Data_Prices!$A:$A,0)),Q$98) -> 13.567727 | R94: =SHADOW(R84,INDEX(Data_Prices!R:R,MATCH($G94,Data_Prices!$A:$A,0)),R$98) -> 13.567727 | S94: =SHADOW(S84,INDEX(Data_Prices!S:S,MATCH($G94,Data_Prices!$A:$A,0)),S$98) -> 13.567727 | T94: =SHADOW(T84,INDEX(Data_Prices!T:T,MATCH($G94,Data_Prices!$A:$A,0)),T$98) -> 13.567727 | U94: =SHADOW(U84,INDEX(Data_Prices!U:U,MATCH($G94,Data_Prices!$A:$A,0)),U$98) -> 13.567727 | V94: =SHADOW(V84,INDEX(Data_Prices!V:V,MATCH($G94,Data_Prices!$A:$A,0)),V$98) -> 13.567727 | W94: =SHADOW(W84,INDEX(Data_Prices!W:W,MATCH($G94,Data_Prices!$A:$A,0)),W$98) -> 13.567727 | X94: =SHADOW(X84,INDEX(Data_Prices!X:X,MATCH($G94,Data_Prices!$A:$A,0)),X$98) -> 13.567727 | Y94: =SHADOW(Y84,INDEX(Data_Prices!Y:Y,MATCH($G94,Data_Prices!$A:$A,0)),Y$98) -> 13.567727 | Z94: =SHADOW(Z84,INDEX(Data_Prices!Z:Z,MATCH($G94,Data_Prices!$A:$A,0)),Z$98) -> 13.567727 | AA94: =SHADOW(AA84,INDEX(Data_Prices!AA:AA,MATCH($G94,Data_Prices!$A:$A,0)),AA$98) -> 13.567727 | AB94: =SHADOW(AB84,INDEX(Data_Prices!AB:AB,MATCH($G94,Data_Prices!$A:$A,0)),AB$98) -> 13.567727 | AC94: =SHADOW(AC84,INDEX(Data_Prices!AC:AC,MATCH($G94,Data_Prices!$A:$A,0)),AC$98) -> 13.567727 | AD94: =SHADOW(AD84,INDEX(Data_Prices!AD:AD,MATCH($G94,Data_Prices!$A:$A,0)),AD$98) -> 13.567727 | AE94: =SHADOW(AE84,INDEX(Data_Prices!AE:AE,MATCH($G94,Data_Prices!$A:$A,0)),AE$98) -> 13.567727
B95: ren | C95: =$C$65 -> cem | D95: Self-generated renewables | E95: $/kwh | F95: shp | G95: =Settings!$B$3&".mit.shp."&$B95&"."&Settings!$B$4&"."&$J$65 -> egy.mit.shp.ren.ind.1 | H95: =OUTCODE(Settings!$B$3,"shp",$C$65,$B95,$J$65) -> egy.mit.shp.cem.ren.e.1 | K95: =SHADOW(K85,INDEX(Data_Prices!K:K,MATCH($G95,Data_Prices!$A:$A,0)),K$98) -> 0 | L95: =SHADOW(L85,INDEX(Data_Prices!L:L,MATCH($G95,Data_Prices!$A:$A,0)),L$98) -> 0.14404499 | M95: =SHADOW(M85,INDEX(Data_Prices!M:M,MATCH($G95,Data_Prices!$A:$A,0)),M$98) -> 0.14102041 | N95: =SHADOW(N85,INDEX(Data_Prices!N:N,MATCH($G95,Data_Prices!$A:$A,0)),N$98) -> 0.13511636 | O95: =SHADOW(O85,INDEX(Data_Prices!O:O,MATCH($G95,Data_Prices!$A:$A,0)),O$98) -> 0.13098826 | P95: =SHADOW(P85,INDEX(Data_Prices!P:P,MATCH($G95,Data_Prices!$A:$A,0)),P$98) -> 0.12790842 | Q95: =SHADOW(Q85,INDEX(Data_Prices!Q:Q,MATCH($G95,Data_Prices!$A:$A,0)),Q$98) -> 0.12481431 | R95: =SHADOW(R85,INDEX(Data_Prices!R:R,MATCH($G95,Data_Prices!$A:$A,0)),R$98) -> 0.12146026 | S95: =SHADOW(S85,INDEX(Data_Prices!S:S,MATCH($G95,Data_Prices!$A:$A,0)),S$98) -> 0.11795074 | T95: =SHADOW(T85,INDEX(Data_Prices!T:T,MATCH($G95,Data_Prices!$A:$A,0)),T$98) -> 0.11419916 | U95: =SHADOW(U85,INDEX(Data_Prices!U:U,MATCH($G95,Data_Prices!$A:$A,0)),U$98) -> 0.1136651 | V95: =SHADOW(V85,INDEX(Data_Prices!V:V,MATCH($G95,Data_Prices!$A:$A,0)),V$98) -> 0.11301693 | W95: =SHADOW(W85,INDEX(Data_Prices!W:W,MATCH($G95,Data_Prices!$A:$A,0)),W$98) -> 0.11231407 | X95: =SHADOW(X85,INDEX(Data_Prices!X:X,MATCH($G95,Data_Prices!$A:$A,0)),X$98) -> 0.11142204 | Y95: =SHADOW(Y85,INDEX(Data_Prices!Y:Y,MATCH($G95,Data_Prices!$A:$A,0)),Y$98) -> 0.11043412 | Z95: =SHADOW(Z85,INDEX(Data_Prices!Z:Z,MATCH($G95,Data_Prices!$A:$A,0)),Z$98) -> 0.10948397 | AA95: =SHADOW(AA85,INDEX(Data_Prices!AA:AA,MATCH($G95,Data_Prices!$A:$A,0)),AA$98) -> 0.10839192 | AB95: =SHADOW(AB85,INDEX(Data_Prices!AB:AB,MATCH($G95,Data_Prices!$A:$A,0)),AB$98) -> 0.10735443 | AC95: =SHADOW(AC85,INDEX(Data_Prices!AC:AC,MATCH($G95,Data_Prices!$A:$A,0)),AC$98) -> 0.10516868 | AD95: =SHADOW(AD85,INDEX(Data_Prices!AD:AD,MATCH($G95,Data_Prices!$A:$A,0)),AD$98) -> 0.10305798 | AE95: =SHADOW(AE85,INDEX(Data_Prices!AE:AE,MATCH($G95,Data_Prices!$A:$A,0)),AE$98) -> 0.10093184
B96: Sector policy and macro drivers
B97: - | C97: =$C$65 -> cem | D97: Sector coverage factor of the new-policy wedge | E97: share | F97: tcf | G97: =Settings!$B$3&".mit.tcf."&$C$65&"."&$J$65 -> egy.mit.tcf.cem.1 | K97: =INDEX(Data_Prices!K:K,MATCH($G97,Data_Prices!$A:$A,0)) -> 0 | L97: =INDEX(Data_Prices!L:L,MATCH($G97,Data_Prices!$A:$A,0)) -> 0 | M97: =INDEX(Data_Prices!M:M,MATCH($G97,Data_Prices!$A:$A,0)) -> 0 | N97: =INDEX(Data_Prices!N:N,MATCH($G97,Data_Prices!$A:$A,0)) -> 0 | O97: =INDEX(Data_Prices!O:O,MATCH($G97,Data_Prices!$A:$A,0)) -> 0 | P97: =INDEX(Data_Prices!P:P,MATCH($G97,Data_Prices!$A:$A,0)) -> 0 | Q97: =INDEX(Data_Prices!Q:Q,MATCH($G97,Data_Prices!$A:$A,0)) -> 0 | R97: =INDEX(Data_Prices!R:R,MATCH($G97,Data_Prices!$A:$A,0)) -> 0 | S97: =INDEX(Data_Prices!S:S,MATCH($G97,Data_Prices!$A:$A,0)) -> 0 | T97: =INDEX(Data_Prices!T:T,MATCH($G97,Data_Prices!$A:$A,0)) -> 0 | U97: =INDEX(Data_Prices!U:U,MATCH($G97,Data_Prices!$A:$A,0)) -> 0 | V97: =INDEX(Data_Prices!V:V,MATCH($G97,Data_Prices!$A:$A,0)) -> 0 | W97: =INDEX(Data_Prices!W:W,MATCH($G97,Data_Prices!$A:$A,0)) -> 0 | X97: =INDEX(Data_Prices!X:X,MATCH($G97,Data_Prices!$A:$A,0)) -> 0 | Y97: =INDEX(Data_Prices!Y:Y,MATCH($G97,Data_Prices!$A:$A,0)) -> 0 | Z97: =INDEX(Data_Prices!Z:Z,MATCH($G97,Data_Prices!$A:$A,0)) -> 0 | AA97: =INDEX(Data_Prices!AA:AA,MATCH($G97,Data_Prices!$A:$A,0)) -> 0 | AB97: =INDEX(Data_Prices!AB:AB,MATCH($G97,Data_Prices!$A:$A,0)) -> 0 | AC97: =INDEX(Data_Prices!AC:AC,MATCH($G97,Data_Prices!$A:$A,0)) -> 0 | AD97: =INDEX(Data_Prices!AD:AD,MATCH($G97,Data_Prices!$A:$A,0)) -> 0 | AE97: =INDEX(Data_Prices!AE:AE,MATCH($G97,Data_Prices!$A:$A,0)) -> 0
B98: - | C98: =$C$65 -> cem | D98: Share of shadow price acting on efficiency | E98: share | F98: ssc | G98: =Settings!$B$3&".mit.ssc."&$C$65&"."&$J$65 -> egy.mit.ssc.cem.1 | K98: =INDEX(Data_Prices!K:K,MATCH($G98,Data_Prices!$A:$A,0)) -> 0 | L98: =INDEX(Data_Prices!L:L,MATCH($G98,Data_Prices!$A:$A,0)) -> 0 | M98: =INDEX(Data_Prices!M:M,MATCH($G98,Data_Prices!$A:$A,0)) -> 0 | N98: =INDEX(Data_Prices!N:N,MATCH($G98,Data_Prices!$A:$A,0)) -> 0 | O98: =INDEX(Data_Prices!O:O,MATCH($G98,Data_Prices!$A:$A,0)) -> 0 | P98: =INDEX(Data_Prices!P:P,MATCH($G98,Data_Prices!$A:$A,0)) -> 0 | Q98: =INDEX(Data_Prices!Q:Q,MATCH($G98,Data_Prices!$A:$A,0)) -> 0 | R98: =INDEX(Data_Prices!R:R,MATCH($G98,Data_Prices!$A:$A,0)) -> 0 | S98: =INDEX(Data_Prices!S:S,MATCH($G98,Data_Prices!$A:$A,0)) -> 0 | T98: =INDEX(Data_Prices!T:T,MATCH($G98,Data_Prices!$A:$A,0)) -> 0 | U98: =INDEX(Data_Prices!U:U,MATCH($G98,Data_Prices!$A:$A,0)) -> 0 | V98: =INDEX(Data_Prices!V:V,MATCH($G98,Data_Prices!$A:$A,0)) -> 0 | W98: =INDEX(Data_Prices!W:W,MATCH($G98,Data_Prices!$A:$A,0)) -> 0 | X98: =INDEX(Data_Prices!X:X,MATCH($G98,Data_Prices!$A:$A,0)) -> 0 | Y98: =INDEX(Data_Prices!Y:Y,MATCH($G98,Data_Prices!$A:$A,0)) -> 0 | Z98: =INDEX(Data_Prices!Z:Z,MATCH($G98,Data_Prices!$A:$A,0)) -> 0 | AA98: =INDEX(Data_Prices!AA:AA,MATCH($G98,Data_Prices!$A:$A,0)) -> 0 | AB98: =INDEX(Data_Prices!AB:AB,MATCH($G98,Data_Prices!$A:$A,0)) -> 0 | AC98: =INDEX(Data_Prices!AC:AC,MATCH($G98,Data_Prices!$A:$A,0)) -> 0 | AD98: =INDEX(Data_Prices!AD:AD,MATCH($G98,Data_Prices!$A:$A,0)) -> 0 | AE98: =INDEX(Data_Prices!AE:AE,MATCH($G98,Data_Prices!$A:$A,0)) -> 0
B99: - | C99: =$C$65 -> cem | D99: Post-policy real GDP growth | E99: % | F99: g | G99: =Settings!$B$3&".mit.gdp.pos.pct."&$J$65 -> egy.mit.gdp.pos.pct.1 | K99: =INDEX(Data_Macro!K:K,MATCH($G99,Data_Macro!$A:$A,0)) -> 0 | L99: =INDEX(Data_Macro!L:L,MATCH($G99,Data_Macro!$A:$A,0)) -> 0.06651345 | M99: =INDEX(Data_Macro!M:M,MATCH($G99,Data_Macro!$A:$A,0)) -> 0.03760281 | N99: =INDEX(Data_Macro!N:N,MATCH($G99,Data_Macro!$A:$A,0)) -> 0.02398801 | O99: =INDEX(Data_Macro!O:O,MATCH($G99,Data_Macro!$A:$A,0)) -> 0.04392387 | P99: =INDEX(Data_Macro!P:P,MATCH($G99,Data_Macro!$A:$A,0)) -> 0.04239706 | Q99: =INDEX(Data_Macro!Q:Q,MATCH($G99,Data_Macro!$A:$A,0)) -> 0.04829218 | R99: =INDEX(Data_Macro!R:R,MATCH($G99,Data_Macro!$A:$A,0)) -> 0.05535316 | S99: =INDEX(Data_Macro!S:S,MATCH($G99,Data_Macro!$A:$A,0)) -> 0.05226606 | T99: =INDEX(Data_Macro!T:T,MATCH($G99,Data_Macro!$A:$A,0)) -> 0.04841877 | U99: =INDEX(Data_Macro!U:U,MATCH($G99,Data_Macro!$A:$A,0)) -> 0.04788736 | V99: =INDEX(Data_Macro!V:V,MATCH($G99,Data_Macro!$A:$A,0)) -> 0.04735595 | W99: =INDEX(Data_Macro!W:W,MATCH($G99,Data_Macro!$A:$A,0)) -> 0.04682454 | X99: =INDEX(Data_Macro!X:X,MATCH($G99,Data_Macro!$A:$A,0)) -> 0.04629313 | Y99: =INDEX(Data_Macro!Y:Y,MATCH($G99,Data_Macro!$A:$A,0)) -> 0.04576172 | Z99: =INDEX(Data_Macro!Z:Z,MATCH($G99,Data_Macro!$A:$A,0)) -> 0.04523031 | AA99: =INDEX(Data_Macro!AA:AA,MATCH($G99,Data_Macro!$A:$A,0)) -> 0.0446989 | AB99: =INDEX(Data_Macro!AB:AB,MATCH($G99,Data_Macro!$A:$A,0)) -> 0.04416749 | AC99: =INDEX(Data_Macro!AC:AC,MATCH($G99,Data_Macro!$A:$A,0)) -> 0.04363608 | AD99: =INDEX(Data_Macro!AD:AD,MATCH($G99,Data_Macro!$A:$A,0)) -> 0.04310467 | AE99: =INDEX(Data_Macro!AE:AE,MATCH($G99,Data_Macro!$A:$A,0)) -> 0.04257326
B100: - | C100: =$C$65 -> cem | D100: Income-elasticity discount factor | E100: ratio | F100: delta | G100: =Settings!$B$3&".mit.inc.ela.adj."&$J$65 -> egy.mit.inc.ela.adj.1 | K100: =INDEX(Data_Macro!K:K,MATCH($G100,Data_Macro!$A:$A,0)) -> 0 | L100: =INDEX(Data_Macro!L:L,MATCH($G100,Data_Macro!$A:$A,0)) -> 1.0271517 | M100: =INDEX(Data_Macro!M:M,MATCH($G100,Data_Macro!$A:$A,0)) -> 1.0271517 | N100: =INDEX(Data_Macro!N:N,MATCH($G100,Data_Macro!$A:$A,0)) -> 1.0205698 | O100: =INDEX(Data_Macro!O:O,MATCH($G100,Data_Macro!$A:$A,0)) -> 1.0173344 | P100: =INDEX(Data_Macro!P:P,MATCH($G100,Data_Macro!$A:$A,0)) -> 1.0076683 | Q100: =INDEX(Data_Macro!Q:Q,MATCH($G100,Data_Macro!$A:$A,0)) -> 1.0007443 | R100: =INDEX(Data_Macro!R:R,MATCH($G100,Data_Macro!$A:$A,0)) -> 0.99188649 | S100: =INDEX(Data_Macro!S:S,MATCH($G100,Data_Macro!$A:$A,0)) -> 0.9806554 | T100: =INDEX(Data_Macro!T:T,MATCH($G100,Data_Macro!$A:$A,0)) -> 0.9702094 | U100: =INDEX(Data_Macro!U:U,MATCH($G100,Data_Macro!$A:$A,0)) -> 0.96419266 | V100: =INDEX(Data_Macro!V:V,MATCH($G100,Data_Macro!$A:$A,0)) -> 0.96161287 | W100: =INDEX(Data_Macro!W:W,MATCH($G100,Data_Macro!$A:$A,0)) -> 0.95919845 | X100: =INDEX(Data_Macro!X:X,MATCH($G100,Data_Macro!$A:$A,0)) -> 0.95695125 | Y100: =INDEX(Data_Macro!Y:Y,MATCH($G100,Data_Macro!$A:$A,0)) -> 0.95487298 | Z100: =INDEX(Data_Macro!Z:Z,MATCH($G100,Data_Macro!$A:$A,0)) -> 0.95296514 | AA100: =INDEX(Data_Macro!AA:AA,MATCH($G100,Data_Macro!$A:$A,0)) -> 0.9512291 | AB100: =INDEX(Data_Macro!AB:AB,MATCH($G100,Data_Macro!$A:$A,0)) -> 0.94966609 | AC100: =INDEX(Data_Macro!AC:AC,MATCH($G100,Data_Macro!$A:$A,0)) -> 0.94827716 | AD100: =INDEX(Data_Macro!AD:AD,MATCH($G100,Data_Macro!$A:$A,0)) -> 0.94706328 | AE100: =INDEX(Data_Macro!AE:AE,MATCH($G100,Data_Macro!$A:$A,0)) -> 0.94602527
B101: - | C101: =$C$65 -> cem | D101: Exogenous shock on energy consumption | E101: ratio | F101: psi | G101: =Settings!$B$3&".mit.shock."&$J$65 -> egy.mit.shock.1 | K101: =INDEX(Data_Macro!K:K,MATCH($G101,Data_Macro!$A:$A,0)) -> 0 | L101: =INDEX(Data_Macro!L:L,MATCH($G101,Data_Macro!$A:$A,0)) -> 0 | M101: =INDEX(Data_Macro!M:M,MATCH($G101,Data_Macro!$A:$A,0)) -> -0.20813308 | N101: =INDEX(Data_Macro!N:N,MATCH($G101,Data_Macro!$A:$A,0)) -> 0.092371429 | O101: =INDEX(Data_Macro!O:O,MATCH($G101,Data_Macro!$A:$A,0)) -> 0 | P101: =INDEX(Data_Macro!P:P,MATCH($G101,Data_Macro!$A:$A,0)) -> 0 | Q101: =INDEX(Data_Macro!Q:Q,MATCH($G101,Data_Macro!$A:$A,0)) -> 0 | R101: =INDEX(Data_Macro!R:R,MATCH($G101,Data_Macro!$A:$A,0)) -> 0 | S101: =INDEX(Data_Macro!S:S,MATCH($G101,Data_Macro!$A:$A,0)) -> 0 | T101: =INDEX(Data_Macro!T:T,MATCH($G101,Data_Macro!$A:$A,0)) -> 0 | U101: =INDEX(Data_Macro!U:U,MATCH($G101,Data_Macro!$A:$A,0)) -> 0 | V101: =INDEX(Data_Macro!V:V,MATCH($G101,Data_Macro!$A:$A,0)) -> 0 | W101: =INDEX(Data_Macro!W:W,MATCH($G101,Data_Macro!$A:$A,0)) -> 0 | X101: =INDEX(Data_Macro!X:X,MATCH($G101,Data_Macro!$A:$A,0)) -> 0 | Y101: =INDEX(Data_Macro!Y:Y,MATCH($G101,Data_Macro!$A:$A,0)) -> 0 | Z101: =INDEX(Data_Macro!Z:Z,MATCH($G101,Data_Macro!$A:$A,0)) -> 0 | AA101: =INDEX(Data_Macro!AA:AA,MATCH($G101,Data_Macro!$A:$A,0)) -> 0 | AB101: =INDEX(Data_Macro!AB:AB,MATCH($G101,Data_Macro!$A:$A,0)) -> 0 | AC101: =INDEX(Data_Macro!AC:AC,MATCH($G101,Data_Macro!$A:$A,0)) -> 0 | AD101: =INDEX(Data_Macro!AD:AD,MATCH($G101,Data_Macro!$A:$A,0)) -> 0 | AE101: =INDEX(Data_Macro!AE:AE,MATCH($G101,Data_Macro!$A:$A,0)) -> 0
B102: Kernel parameters (looked up from Data_Elast; column = Settings elasticity group)
B103: Fuel | C103: Sector | D103: Description | E103: Income el. (eY) | F103: Usage el. (eU) | G103: Efficiency el. (eF) | H103: AEEI (a) | I103: Add. efficiency (a+) | J103: Elasticity fuel group
...

Sheet _Lambdas
A1: Named LAMBDA functions defined in Name Manager (workbook scope)
A2: Parameter names avoid Excel function names (hence dlt, vname). Requires Excel 365 / Excel 2021 or later. Stored as _xlfn.LAMBDA(_xlpm.param, ...) so Excel recognises them on open; the sheet is set to recalculate fully on load.
A4: Name | B4: Signature | C4: Definition (as typed in Name Manager) | D4: What it does | E4: Stored text (workbook.xml)
A5: FUELUSE | B5: FUELUSE(F_prev, p_prev, p_now, s_prev, s_now, g, dlt, psi, eY, eU, eF, a, a_add) | C5: =_xludf.LAMBDA(F_prev, p_prev, p_now, s_prev, s_now, g, dlt, psi, eY, eU, eF, a, a_add, _xludf.LET(pr, IF(p_prev<=0,1,p_now/p_prev), sr, IF(s_prev<=0,1,s_now/s_prev), F_prev*(1+g)^(eY*dlt)*(1+psi)*pr^eU*((sr^eF)/(1+a+a_add))^(1+eU))) -> #NAME? | D5: The fuel-use kernel. Prices p (post-tax) and s (shadow) in the same native unit; returns F(t) in ktoe. | E5: _xlfn.LAMBDA(_xlpm.F_prev,_xlpm.p_prev,_xlpm.p_now,_xlpm.s_prev,_xlpm.s_now,_xlpm.g,_xlpm.dlt,_xlpm.psi,_xlpm.eY,_xlpm.eU,_xlpm.eF,_xlpm.a,_xlpm.a_add,_xlfn.LET(_xlpm.pr, IF(_xlpm.p_prev<=0,1,_xlpm.p_now/_xlpm.p_prev), _xlpm.sr, IF(_xlpm.s_prev<=0,1,_xlpm.s_now/_xlpm.s_prev), _xlpm.F_prev*(1+_xlpm.g)^(_xlpm.eY*_xlpm.dlt)*(1+_xlpm.psi)*_xlpm.pr^_xlpm.eU*((_xlpm.sr^_xlpm.eF)/(1+_xlpm.a+_xlpm.a_add))^(1+_xlpm.eU)))
A6: ELAST | B6: ELAST(kind, fuel, group) | C6: =_xludf.LAMBDA(kind, fuel, group, INDEX(Data_Elast!$D:$G, MATCH(kind&"_"&fuel, Data_Elast!$A:$A, 0), MATCH(group, Data_Elast!$D$1:$G$1, 0))) -> #NAME? | D6: One number from the master elasticity table: kind = el_inc | el_dem | el_eff | eff_imp, fuel = elasticity fuel group, group = Transport | Residential | Industries | Services. | E6: _xlfn.LAMBDA(_xlpm.kind,_xlpm.fuel,_xlpm.group,INDEX(Data_Elast!$D:$G, MATCH(_xlpm.kind&"_"&_xlpm.fuel, Data_Elast!$A:$A, 0), MATCH(_xlpm.group, Data_Elast!$D$1:$G$1, 0)))
A7: POSTTAX | B7: POSTTAX(ptp, nce, tcf) | C7: =_xludf.LAMBDA(ptp, nce, tcf, ptp+nce*tcf) -> #NAME? | D7: Post-tax price = pre-tax price + new-policy wedge x sector coverage factor. | E7: _xlfn.LAMBDA(_xlpm.ptp,_xlpm.nce,_xlpm.tcf,_xlpm.ptp+_xlpm.nce*_xlpm.tcf)
A8: SHADOW | B8: SHADOW(atp, sigma, ssc) | C8: =_xludf.LAMBDA(atp, sigma, ssc, atp+sigma*ssc) -> #NAME? | D8: Shadow price = post-tax price + shadow price of non-price policies x share acting on efficiency. | E8: _xlfn.LAMBDA(_xlpm.atp,_xlpm.sigma,_xlpm.ssc,_xlpm.atp+_xlpm.sigma*_xlpm.ssc)
A9: OUTCODE | B9: OUTCODE(country, vname, sector, fuel, scen) | C9: =_xludf.LAMBDA(country, vname, sector, fuel, scen, country&".mit."&vname&"."&sector&"."&fuel&".e."&scen) -> #NAME? | D9: CPAT output code built from components, e.g. egy.mit.ener.irn.coa.e.1. | E9: _xlfn.LAMBDA(_xlpm.country,_xlpm.vname,_xlpm.sector,_xlpm.fuel,_xlpm.scen,_xlpm.country&".mit."&_xlpm.vname&"."&_xlpm.sector&"."&_xlpm.fuel&".e."&_xlpm.scen)
A11: Worked example (iron and steel, coal, 2023, baseline):
A12: F_prev (2022, ktoe) | B12: 232.65735
A13: p_prev / p_now (post-tax, $/GJ) | B13: 10.5234 / 10.2996
A14: s_prev / s_now (shadow, $/GJ) | B14: 10.5234 / 10.2996
A15: g, delta, psi (2023) | B15: 0.03760, 1.02715, -0.20813
A16: eY, eU, eF, a, a+ | B16: 0.5, -0.3, -0.4, 0.005, 0
A17: FUELUSE(...) expected | B17: 189.452656106887 ktoe
A18: Live call | B18: =FUELUSE(232.657354770131,10.5233613454312,10.2995608274442,10.5233613454312,10.2995608274442,0.03760281,1.02715172471961,-0.208133083020442,0.5,-0.3,-0.4,0.005,0) -> 189.45266
A20: How the cells use them:
A21: Energy, year t: =FUELUSE(F(t-1), atp(t-1), atp(t), shp(t-1), shp(t), g(t), dlt(t), psi(t), eY, eU, eF, a, a+) - all arguments are cells in the same block
A22: Post-tax price: =POSTTAX(ptp, nce, tcf) Shadow price: =SHADOW(atp, sigma, ssc)
A23: Parameters: =ELAST("el_inc", fuel group, Settings!elasticity column) etc.; AEEI uses ELAST("eff_imp", AEEI group, ...)
A24: Output codes: =OUTCODE(country, "ener", sector, fuel, scenario) -> egy.mit.ener.irn.coa.e.1
A25: To switch a cell back to a plain formula, paste the LET body with the arguments substituted; v0.1 of this file is that expanded version.

Sheet MTInputs
B1: CPAT Inputs | E1: Links ----> | F1: Dashboard
B2: Explanation: this tabs is used for running MT as well as being a convenient place for all CPAT policy and parameter inputs to be viewed
B3: NB: Please do not change any cells. Make sure that "MT is active" switch is "False"
C5: FALSE | D5: <-- Should normally be "FALSE"!
D6: 6
B7: Parameters | C7: unit | D7: MT values | E7: "Dashboard" values | F7: Used for calculation | G7: Defaults | H7: NameOfParameter | I7: Use Dashboard even if Defaults selected
B8: Country | D8: 0 | E8: Egypt | F8: Egypt | G8: Egypt | H8: Countryname | I8: Y
B9: Scenario identification
B10: Scenario ID | C10: # | D10: 0 | E10: N/A | F10: N/A | G10: N/A | H10: MSTScenarioID
B11: Scenario status | C11: switch | D11: 0 | E11: N/A | F11: N/A | G11: N/A
B12: Scenario name | C12: name | D12: 0 | E12: N/A | F12: N/A | G12: N/A
B13: Chosen policy | C13: switch | D13: 0 | E13: - Carbon tax | F13: - Carbon tax | G13: - Carbon tax | H13: ScenarioSelected
B14: Scenario status for macro | C14: # | D14: 0 | E14: N/A | F14: N/A | G14: N/A
B15: Scenario parameters override? | C15: # | D15: 0 | E15: N/A | F15: N/A | G15: N/A
B16: CPAT-side parameters override? | C16: switch | D16: 0 | E16: Manual* | F16: Manual* | G16: Manual* | H16: CPATDefaultsOrUserDefined
B17: Carbon pricing: main inputs
A18: X | B18: Carbon pricing start year | C18: year | D18: 0 | E18: 2026 | F18: 2026 | G18: 2027 | H18: CPIntro | I18: Y
A19: X | B19: Starting carbon price | C19: nom. USD/tCO2 | D19: 0 | E19: 0 | F19: 0 | G19: 20 | H19: CPLevelStart | I19: Y
B20: Target level of carbon price | C20: nom. USD/tCO2 | D20: 0 | E20: 50 | F20: 50 | G20: 50 | H20: CPLevelTarget | I20: Y
A21: X | B21: Year to reach target level | C21: year | D21: 0 | E21: 2030 | F21: 2030 | G21: 2035 | H21: CPOutro | I21: Y
B22: Carbon pricing: fuel coverage
B23: Apply tax to coal? | C23: switch | D23: 0 | E23: TRUE | F23: TRUE | G23: TRUE | H23: MCovCoa | I23: Y
B24: Apply tax to natural gas? | C24: switch | D24: 0 | E24: TRUE | F24: TRUE | G24: TRUE | H24: MCovNga | I24: Y
B25: Apply tax to gasoline? | C25: switch | D25: 0 | E25: TRUE | F25: TRUE | G25: TRUE | H25: MCovGso | I25: Y
B26: Apply tax to diesel? | C26: switch | D26: 0 | E26: TRUE | F26: TRUE | G26: TRUE | H26: MCovDie | I26: Y
B27: Apply tax to LPG? | C27: switch | D27: 0 | E27: TRUE | F27: TRUE | G27: TRUE | H27: MCovLpg | I27: Y
B28: Apply tax to kerosene? | C28: switch | D28: 0 | E28: TRUE | F28: TRUE | G28: TRUE | H28: MCovKer | I28: Y
B29: Apply tax to non-road oil products? | C29: switch | D29: 0 | E29: TRUE | F29: TRUE | G29: TRUE | H29: MCovOop | I29: Y
B30: Carbon pricing: sector coverage
B31: Apply tax to power sector? | C31: switch | D31: 0 | E31: TRUE | F31: TRUE | G31: TRUE | H31: MCovPow | I31: Y
B32: Apply tax to road transportation? | C32: switch | D32: 0 | E32: TRUE | F32: TRUE | G32: TRUE | H32: MCovRod | I32: Y
B33: Apply tax to rail transportation? | C33: switch | D33: 0 | E33: TRUE | F33: TRUE | G33: TRUE | H33: MCovRal | I33: Y
B34: Apply tax to domestic aviation? | C34: switch | D34: 0 | E34: TRUE | F34: TRUE | G34: TRUE | H34: MCovAvi | I34: Y
B35: Apply tax to domestic shipping? | C35: switch | D35: 0 | E35: TRUE | F35: TRUE | G35: TRUE | H35: MCovNav | I35: Y
B36: Apply tax to residential sector? | C36: switch | D36: 0 | E36: TRUE | F36: TRUE | G36: TRUE | H36: MCovRes | I36: Y
B37: Apply tax to food & forestry? | C37: switch | D37: 0 | E37: TRUE | F37: TRUE | G37: TRUE | H37: MCovFoo | I37: Y
B38: Apply tax to services (private / public)? | C38: switch | D38: 0 | E38: TRUE | F38: TRUE | G38: TRUE | H38: MCovSrv | I38: Y
B39: Apply tax to mining & chemicals? | C39: switch | D39: 0 | E39: TRUE | F39: TRUE | G39: TRUE | H39: MCovMch | I39: Y
B40: Apply tax to iron and steel? | C40: switch | D40: 0 | E40: TRUE | F40: TRUE | G40: TRUE | H40: MCovIrn | I40: Y
B41: Apply tax to non-ferrous metals? | C41: switch | D41: 0 | E41: TRUE | F41: TRUE | G41: TRUE | H41: MCovNfm | I41: Y
B42: Apply tax to machinery? | C42: switch | D42: 0 | E42: TRUE | F42: TRUE | G42: TRUE | H42: MCovMac | I42: Y
... B47: Apply tax to other energy use? | C47: switch | D47: 0 | E47: TRUE | F47: TRUE | G47: TRUE | H47: MCovOen | I47: Y
B48: Exemptions phaseout
B49: Apply exemption phaseout? | C49: switch | D49: 0 | E49: FALSE | F49: FALSE | G49: FALSE | H49: ExemptPhaseout | I49: Y
B50: Year to start exemption phaseout (if applicable) | C50: year | D50: 0 | E50: 2027 | F50: 2027 | G50: 2027 | H50: YearPha | I50: Y
B51: Period to reach full exemption phaseout (if applicable) | C51: year | D51: 0 | E51: 5 | F51: 5 | G51: 5 | H51: ExemptPhaseoutPeriod | I51: Y
B52: Feebates: Starting and End Date
B53: Start date | D53: 0 | E53: 2027 | F53: 2027 | G53: 2027 | H53: D_FeebateIntro
B54: Target date | D54: 0 | E54: 2035 | F54: 2035 | G54: 2035 | H54: D_FeebateOutro
B55: Feebates: Feebate starting rate
B56: Power sector | C56: USD/tCO2 | D56: 0 | E56: 0 | F56: 0 | G56: 0 | H56: D_Feb_Level_Start_Pow
B57: Transport | C57: USD/tCO2 | D57: 0 | E57: 0 | F57: 0 | G57: 0 | H57: D_Feb_Level_Start_Trans
B58: Residential | C58: USD/tCO2 | D58: 0 | E58: 0 | F58: 0 | G58: 0 | H58: D_Feb_Level_Start_Res
B59: Industry | C59: USD/tCO2 | D59: 0 | F59: 0 | G59: 0 | H59: D_Feb_Level_Start_Ind
B60: Feebates: Feebate target rate
B61: Power sector | C61: USD/tCO2 | D61: 0 | E61: 0 | F61: 0 | G61: 0 | H61: D_Feb_Level_Target_Pow
B62: Transport | C62: USD/tCO2 | D62: 0 | E62: 0 | F62: 0 | G62: 0 | H62: D_Feb_Level_Target_Trans
B63: Residential | C63: USD/tCO2 | D63: 0 | E63: 0 | F63: 0 | G63: 0 | H63: D_Feb_Level_Target_Res
B64: Industry | C64: USD/tCO2 | D64: 0 | F64: 0 | G64: 0 | H64: D_Feb_Level_Target_Ind
B65: Feebates sector coverage
B66: Apply tax to power sector? | C66: switch | D66: 0 | E66: FALSE | F66: FALSE | G66: TRUE | I66: Y
B67: Apply tax to road transportation? | D67: 0 | E67: FALSE | F67: FALSE | G67: FALSE | I67: Y
B68: Apply tax to rail transportation? | D68: 0 | E68: FALSE | F68: FALSE | G68: FALSE | I68: Y
B69: Apply tax to domestic aviation? | D69: 0 | E69: FALSE | F69: FALSE | G69: FALSE | I69: Y
B70: Apply tax to domestic shipping? | D70: 0 | E70: FALSE | F70: FALSE | G70: FALSE | I70: Y
B71: Apply tax to residential sector? | C71: switch | D71: 0 | E71: FALSE | F71: FALSE | G71: TRUE | I71: Y
B72: Apply tax to food & forestry? | D72: 0 | E72: FALSE | F72: FALSE | G72: TRUE | I72: Y
B73: Apply tax to services (private / public)? | D73: 0 | E73: FALSE | F73: FALSE | G73: TRUE | I73: Y
B74: Apply tax to mining & chemicals? | D74: 0 | E74: TRUE | F74: TRUE | G74: TRUE | I74: Y
B75: Apply tax to iron and steel? | D75: 0 | E75: FALSE | F75: FALSE | G75: TRUE | I75: Y
B76: Apply tax to non-ferrous metals? | D76: 0 | E76: TRUE | F76: TRUE | G76: TRUE | I76: Y
B77: Apply tax to machinery? | D77: 0 | E77: TRUE | F77: TRUE | G77: TRUE | I77: Y
B78: Apply tax to cement? | D78: 0 | E78: TRUE | F78: TRUE | G78: TRUE | I78: Y
B79: Apply tax to other manucfacturing? | D79: 0 | E79: TRUE | F79: TRUE | G79: TRUE | I79: Y
B80: Apply tax to construction? | D80: 0 | E80: TRUE | F80: TRUE | G80: TRUE | I80: Y
B81: Apply tax to fuel transformation? | D81: 0 | E81: TRUE | F81: TRUE | G81: TRUE
B82: Apply tax to other energy use? | D82: 0 | E82: TRUE | F82: TRUE | G82: TRUE
B83: ETS Main Characteristics
B84: Apply new ETS? | D84: 0 | E84: No | F84: No | G84: No | H84: D_NewETS
B85: Change Relative to Baseline in Start Year | D85: 0 | E85: 0 | F85: 0 | G85: 0 | H85: D_ETSChangeRelStart
B86: Change Relative to Baseline in Target Year | D86: 0 | E86: 0 | F86: 0 | G86: 0 | H86: D_ETSChangeRelTarget
B87: Cap continuation after target year? | D87: 0 | E87: Constant | F87: Constant | G87: KeepRelativeCapConstant | H87: D_ETSCapCont
B88: ETS Start Year | D88: 0 | E88: 2027 | F88: 2027 | G88: 2026 | H88: D_ETSIntro
B89: ETS Target Year | D89: 0 | E89: 2035 | F89: 2035 | G89: 2035 | H89: D_ETSOutro
B90: Proportion Auctioned in Starting Year | D90: 0 | E90: 0 | F90: 0 | G90: 0 | H90: D_ETSAuctStart
B91: Proportion Auctioned in Target Year | D91: 0 | E91: 0 | F91: 0 | G91: 1 | H91: D_ETSAuctTarget
B92: Auction proportion continuation after target year? | D92: 0 | E92: Constant | F92: Constant | G92: Constant | H92: D_ETSAuctCont
B93: Override ETS price | D93: 0 | E93: No | F93: No | G93: No | H93: D_ETSPriceOverride
B94: ETS: modelling assumptions
B95: ETS Volatility | D95: 0 | E95: Medium* | F95: Medium* | G95: Medium* | H95: D_ETSVolatility
B96: Impact of Volatility on Abatement Costs | D96: 0 | E96: Medium* | F96: Medium* | G96: Medium* | H96: D_ETSVolImpact
B97: Carbon Tax Policy Risk | D97: 0 | E97: 0.2 | F97: 0.2 | G97: 0.2 | H97: D_ETSCTRisk
B98: ETS: sector coverage
B99: power sector | C99: switch | D99: 0 | E99: TRUE | F99: TRUE | G99: TRUE | I99: Y
B100: road transportation | D100: 0 | E100: FALSE | F100: FALSE | G100: TRUE | I100: Y
B101: rail transportation | D101: 0 | E101: FALSE | F101: FALSE | G101: TRUE | I101: Y
B102: domestic aviation | D102: 0 | E102: FALSE | F102: FALSE | G102: TRUE | I102: Y
B103: domestic shipping | D103: 0 | E103: FALSE | F103: FALSE | G103: TRUE | I103: Y
B104: residential | C104: switch | D104: 0 | E104: FALSE | F104: FALSE | G104: TRUE | I104: Y
B105: food & forestry | D105: 0 | E105: FALSE | F105: FALSE | G105: TRUE | I105: Y
...

Sheet Data_Energy
A1: Base-year energy use by fuel and sector, ktoe (CPAT_1_0pre_456, Mitigation rows 583-602, Egypt) | D1: Energy used in power generation (ktoe) | E1: Road | F1: Rail | G1: Domestic aviation | H1: Domestic navigation | I1: Residential | J1: Food & forestry | K1: Services (public & private) | L1: Mining & Chemicals | M1: Iron and steel | N1: Other metals | O1: Machinery | P1: Cement | Q1: Other manufacturing | R1: Construction | S1: Fuel transformation | T1: Other - energy use | U1: Other - non-energy use
A2: CPAT code | B2: Fuel | C2: fuel | D2: pow | E2: rod | F2: ral | G2: avi | H2: nav | I2: res | J2: foo | K2: srv | L2: mch | M2: irn | N2: nfm | O2: mac | P2: cem | Q2: omn | R2: cst | S2: ftr | T2: oen
A3: egy.mit.enc.ele | B3: Electricity | C3: ele | D3: -19492.336 | E3: 0 | F3: 47.63187 | G3: 0 | H3: 0 | I3: 6382.1425 | J3: 1257.2945 | K3: 4021.5309 | L3: 411.49546 | M3: 751.85311 | N3: 6.1925553 | O3: 573.08412 | P3: 1270.6461 | Q3: 773.84879 | R3: 0 | S3: 591.84357 | T3: 0 | U3: -3573.4183
A4: egy.mit.enc.coa | B4: Coal | C4: coa | D4: 0 | E4: 0 | F4: 0 | G4: 0 | H4: 0 | I4: 1.6729073 | J4: 0 | K4: 0 | L4: 0 | M4: 232.65735 | N4: 0 | O4: 0 | P4: 1463.0552 | Q4: 0 | R4: 0 | S4: 0 | T4: 0 | U4: -165.39924
A5: egy.mit.enc.nga | B5: Natural gas | C5: nga | D5: 31743.441 | E5: 541.70399 | F5: 0 | G5: 0 | H5: 0 | I5: 2035.4604 | J5: 0 | K5: 0 | L5: 0 | M5: 1669.0567 | N5: 0 | O5: 0 | P5: 1747.3915 | Q5: 960.13004 | R5: 0 | S5: 7454.0058 | T5: 0 | U5: 8778.2669
A6: egy.mit.enc.oop | B6: Other oil products | C6: oop | D6: 4928.2673 | E6: 0 | F6: 0 | G6: 0 | H6: 290.7095 | I6: 0 | J6: 0 | K6: 0 | L6: 0 | M6: 0 | N6: 0 | O6: 0 | P6: 0 | Q6: 2347.5275 | R6: 0 | S6: 293.09921 | T6: 100.67884 | U6: -17958.527
A7: egy.mit.enc.gso | B7: Gasoline | C7: gso | D7: 0 | E7: 7577.2964 | F7: 0 | G7: 0 | H7: 0 | I7: 0 | J7: 0 | K7: 0 | L7: 0 | M7: 0 | N7: 0 | O7: 0 | P7: 0 | Q7: 0 | R7: 0 | S7: 0 | T7: 0 | U7: 5735.9845
A8: egy.mit.enc.die | B8: Diesel | C8: die | D8: 21.620807 | E8: 10207.632 | F8: 0 | G8: 0 | H8: 0 | I8: 0 | J8: 927.02173 | K8: 0 | L8: 0 | M8: 0 | N8: 0 | O8: 0 | P8: 0 | Q8: 3819.2342 | R8: 0 | S8: 824.80009 | T8: 0 | U8: 11791.23
A9: egy.mit.enc.ker | B9: Kerosene | C9: ker | D9: 0 | E9: 0 | F9: 0 | G9: 0 | H9: 0 | I9: 2.7690054 | J9: 0.34429649 | K9: 0 | L9: 0 | M9: 0 | N9: 0 | O9: 0 | P9: 0 | Q9: 4.3837261 | R9: 0 | S9: 0 | T9: 0 | U9: 26.738322
A10: egy.mit.enc.lpg | B10: LPG | C10: lpg | D10: 0 | E10: 0 | F10: 0 | G10: 0 | H10: 0 | I10: 3182.2559 | J10: 0 | K10: 0 | L10: 0 | M10: 0 | N10: 0 | O10: 0 | P10: 0 | Q10: 17.432083 | R10: 0 | S10: 2465.7624 | T10: 0 | U10: 6147.5679
A11: egy.mit.enc.jfu | B11: Jet fuel | C11: jfu | D11: 0 | E11: 0 | F11: 0 | G11: 706.87671 | H11: 0 | I11: 0 | J11: 0 | K11: 0 | L11: 0 | M11: 0 | N11: 0 | O11: 0 | P11: 0 | Q11: 0 | R11: 0 | S11: 0 | T11: 0 | U11: 1730.0491
A12: egy.mit.enc.wnd | B12: Wind | C12: wnd | D12: 537.36938 | E12: 0 | F12: 0 | G12: 0 | H12: 0 | I12: 0 | J12: 0 | K12: 0 | L12: 0 | M12: 0 | N12: 0 | O12: 0 | P12: 0 | Q12: 0 | R12: 0 | S12: 0 | T12: 0 | U12: 10.207473
A13: egy.mit.enc.sol | B13: Solar | C13: sol | D13: 439.51537 | E13: 0 | F13: 0 | G13: 0 | H13: 0 | I13: 0 | J13: 0 | K13: 0 | L13: 0 | M13: 0 | N13: 0 | O13: 0 | P13: 0 | Q13: 0 | R13: 0 | S13: 0 | T13: 0 | U13: -12.588175
A14: egy.mit.enc.hyd | B14: Hydro | C14: hyd | D14: 1347.5903 | E14: 0 | F14: 0 | G14: 0 | H14: 0 | I14: 0 | J14: 0 | K14: 0 | L14: 0 | M14: 0 | N14: 0 | O14: 0 | P14: 0 | Q14: 0 | R14: 0 | S14: 0 | T14: 0 | U14: 25.925993
... A21: egy.mit.enc.heat | B21: Heat | C21: heat | D21: 0 | E21: 0 | F21: 0 | G21: 0 | H21: 0 | I21: 0 | J21: 0 | K21: 0 | L21: 0 | M21: 0 | N21: 0 | O21: 0 | P21: 0 | Q21: 0 | R21: 0 | S21: 0 | T21: 0 | U21: 0
B22: Total self-generated renewables (nonbiomass) | C22: ren | D22: 2324.475 | E22: 0 | F22: 0 | G22: 0 | H22: 0 | I22: 0 | J22: 0 | K22: 0 | L22: 0 | M22: 0 | N22: 0 | O22: 0 | P22: 0 | Q22: 0 | R22: 0 | S22: 0 | T22: 0

Sheet Data_Prices
A1: Code | B1: Fuel | C1: Sector / group | D1: Variable | E1: Scenario | F1: Unit | G1: Description | H1: CPAT source row | I1: Source code | J1: Helper | K1: 2021 | L1: 2022 | M1: 2023 | N1: 2024 | O1: 2025 | P1: 2026 | Q1: 2027 | R1: 2028 | S1: 2029 | T1: 2030 | U1: 2031 | V1: 2032 | W1: 2033 | X1: 2034 | Y1: 2035 | Z1: 2036 | AA1: 2037 | AB1: 2038 | AC1: 2039 | AD1: 2040 | AE1: 2041 | AF1: 2042 | AG1: 2043 | AH1: 2044 | AI1: 2045
A2: egy.mit.pbc.ind.coa.a.1 | B2: coa | C2: ind | D2: pbc | E2: 1 | F2: $/GJ | G2: Price before any new policy (supply cost + VAT + existing excise, subsidies, carbon prices) | H2: 2513 | I2: egy.mit.pbc.ind.coa.a.1 | K2: 11.182902 | L2: 10.523361 | M2: 10.299561 | N2: 9.5775284 | O2: 8.4854783 | P2: 9.0871922 | Q2: 9.2229237 | R2: 9.158565 | S2: 9.0895479 | T2: 9.0156817 | U2: 8.9443978 | V2: 8.9443978 | W2: 8.9443978 | X2: 8.9443978 | Y2: 8.9443978 | Z2: 8.9443978 | AA2: 8.9443978 | AB2: 8.9443978 | AC2: 8.9443978 | AD2: 8.9443978 | AE2: 8.9443978
A3: egy.mit.nce.ind.coa.a.1 | B3: coa | C3: ind | D3: nce | E3: 1 | F3: $/GJ | G3: Total new policy wedge before sector coverage | H3: 2514 | I3: egy.mit.nce.ind.coa.a.1 | K3: 0 | L3: 0 | M3: 0 | N3: 0 | O3: 0 | P3: 0 | Q3: 0 | R3: 0 | S3: 0 | T3: 0 | U3: 0 | V3: 0 | W3: 0 | X3: 0 | Y3: 0 | Z3: 0 | AA3: 0 | AB3: 0 | AC3: 0 | AD3: 0 | AE3: 0
A4: egy.mit.pbc.ind.nga.a.1 | B4: nga | C4: ind | D4: pbc | E4: 1 | F4: $/GJ | G4: Price before any new policy (supply cost + VAT + existing excise, subsidies, carbon prices) | H4: 2582 | I4: egy.mit.pbc.ind.nga.a.1 | K4: 6.0634636 | L4: 5.4510151 | M4: 5.1193563 | N4: 5.0821846 | O4: 5.0821846 | P4: 5.0821846 | Q4: 5.0821846 | R4: 5.0821846 | S4: 5.0821846 | T4: 5.0821846 | U4: 5.0821846 | V4: 5.0821846 | W4: 5.0821846 | X4: 5.0821846 | Y4: 5.0821846 | Z4: 5.0821846 | AA4: 5.0821846 | AB4: 5.0821846 | AC4: 5.0821846 | AD4: 5.0821846 | AE4: 5.0821846
A5: egy.mit.nce.ind.nga.a.1 | B5: nga | C5: ind | D5: nce | E5: 1 | F5: $/GJ | G5: Total new policy wedge before sector coverage | H5: 2583 | I5: egy.mit.nce.ind.nga.a.1 | K5: 0 | L5: 0 | M5: 0 | N5: 0 | O5: 0 | P5: 0 | Q5: 0 | R5: 0 | S5: 0 | T5: 0 | U5: 0 | V5: 0 | W5: 0 | X5: 0 | Y5: 0 | Z5: 0 | AA5: 0 | AB5: 0 | AC5: 0 | AD5: 0 | AE5: 0
A6: egy.mit.pbc.ind.gso.a.1 | B6: gso | C6: ind | D6: pbc | E6: 1 | F6: $/liter | G6: Price before any new policy (supply cost + VAT + existing excise, subsidies, carbon prices) | H6: 2605 | I6: egy.mit.pbc.all.gso.a.1 | K6: 0.67114653 | L6: 0.61197798 | M6: 0.61180975 | N6: 0.6035831 | O6: 0.6035831 | P6: 0.6035831 | Q6: 0.6035831 | R6: 0.6035831 | S6: 0.6035831 | T6: 0.6035831 | U6: 0.6035831 | V6: 0.6035831 | W6: 0.6035831 | X6: 0.6035831 | Y6: 0.6035831 | Z6: 0.6035831 | AA6: 0.6035831 | AB6: 0.6035831 | AC6: 0.6035831 | AD6: 0.6035831 | AE6: 0.6035831
A7: egy.mit.nce.ind.gso.a.1 | B7: gso | C7: ind | D7: nce | E7: 1 | F7: $/liter | G7: Total new policy wedge before sector coverage | H7: 2606 | I7: egy.mit.nce.all.gso.a.1 | K7: 0 | L7: 0 | M7: 0 | N7: 0 | O7: 0 | P7: 0 | Q7: 0 | R7: 0 | S7: 0 | T7: 0 | U7: 0 | V7: 0 | W7: 0 | X7: 0 | Y7: 0 | Z7: 0 | AA7: 0 | AB7: 0 | AC7: 0 | AD7: 0 | AE7: 0
A8: egy.mit.pbc.ind.die.a.1 | B8: die | C8: ind | D8: pbc | E8: 1 | F8: $/liter | G8: Price before any new policy (supply cost + VAT + existing excise, subsidies, carbon prices) | H8: 2628 | I8: egy.mit.pbc.all.die.a.1 | K8: 0.55971121 | L8: 0.49458873 | M8: 0.50778655 | N8: 0.47043643 | O8: 0.47043643 | P8: 0.47043643 | Q8: 0.47043643 | R8: 0.47043643 | S8: 0.47043643 | T8: 0.47043643 | U8: 0.47043643 | V8: 0.47043643 | W8: 0.47043643 | X8: 0.47043643 | Y8: 0.47043643 | Z8: 0.47043643 | AA8: 0.47043643 | AB8: 0.47043643 | AC8: 0.47043643 | AD8: 0.47043643 | AE8: 0.47043643
A9: egy.mit.nce.ind.die.a.1 | B9: die | C9: ind | D9: nce | E9: 1 | F9: $/liter | G9: Total new policy wedge before sector coverage | H9: 2629 | I9: egy.mit.nce.all.die.a.1 | K9: 0 | L9: 0 | M9: 0 | N9: 0 | O9: 0 | P9: 0 | Q9: 0 | R9: 0 | S9: 0 | T9: 0 | U9: 0 | V9: 0 | W9: 0 | X9: 0 | Y9: 0 | Z9: 0 | AA9: 0 | AB9: 0 | AC9: 0 | AD9: 0 | AE9: 0
A10: egy.mit.pbc.ind.lpg.a.1 | B10: lpg | C10: ind | D10: pbc | E10: 1 | F10: $/liter | G10: Price before any new policy (supply cost + VAT + existing excise, subsidies, carbon prices) | H10: 2651 | I10: egy.mit.pbc.all.lpg.a.1 | K10: 0.20036669 | L10: 0.15734474 | M10: 0.16448404 | N10: 0.15070908 | O10: 0.15070908 | P10: 0.15070908 | Q10: 0.15070908 | R10: 0.15070908 | S10: 0.15070908 | T10: 0.15070908 | U10: 0.15070908 | V10: 0.15070908 | W10: 0.15070908 | X10: 0.15070908 | Y10: 0.15070908 | Z10: 0.15070908 | AA10: 0.15070908 | AB10: 0.15070908 | AC10: 0.15070908 | AD10: 0.15070908 | AE10: 0.15070908
A11: egy.mit.nce.ind.lpg.a.1 | B11: lpg | C11: ind | D11: nce | E11: 1 | F11: $/liter | G11: Total new policy wedge before sector coverage | H11: 2652 | I11: egy.mit.nce.all.lpg.a.1 | K11: 0 | L11: 0 | M11: 0 | N11: 0 | O11: 0 | P11: 0 | Q11: 0 | R11: 0 | S11: 0 | T11: 0 | U11: 0 | V11: 0 | W11: 0 | X11: 0 | Y11: 0 | Z11: 0 | AA11: 0 | AB11: 0 | AC11: 0 | AD11: 0 | AE11: 0
A12: egy.mit.pbc.ind.ker.a.1 | B12: ker | C12: ind | D12: pbc | E12: 1 | F12: $/liter | G12: Price before any new policy (supply cost + VAT + existing excise, subsidies, carbon prices) | H12: 2674 | I12: egy.mit.pbc.ker.a.1 | K12: 0.48429424 | L12: 0.45642817 | M12: 0.4316892 | N12: 0.42507558 | O12: 0.42507558 | P12: 0.42507558 | Q12: 0.42507558 | R12: 0.42507558 | S12: 0.42507558 | T12: 0.42507558 | U12: 0.42507558 | V12: 0.42507558 | W12: 0.42507558 | X12: 0.42507558 | Y12: 0.42507558 | Z12: 0.42507558 | AA12: 0.42507558 | AB12: 0.42507558 | AC12: 0.42507558 | AD12: 0.42507558 | AE12: 0.42507558
A13: egy.mit.nce.ind.ker.a.1 | B13: ker | C13: ind | D13: nce | E13: 1 | F13: $/liter | G13: Total new policy wedge before sector coverage | H13: 2675 | I13: egy.mit.nce.ker.a.1 | K13: 0 | L13: 0 | M13: 0 | N13: 0 | O13: 0 | P13: 0 | Q13: 0 | R13: 0 | S13: 0 | T13: 0 | U13: 0 | V13: 0 | W13: 0 | X13: 0 | Y13: 0 | Z13: 0 | AA13: 0 | AB13: 0 | AC13: 0 | AD13: 0 | AE13: 0
... A17: egy.mit.nce.ind.bio.a.1 | B17: bio | C17: ind | D17: nce | E17: 1 | F17: $/GJ | G17: Total new policy wedge before sector coverage | H17: 2721 | I17: egy.mit.nce.all.bio.a.1 | K17: 0 | L17: 0 | M17: 0 | N17: 0 | O17: 0 | P17: 0 | Q17: 0 | R17: 0 | S17: 0 | T17: 0 | U17: 0 | V17: 0 | W17: 0 | X17: 0 | Y17: 0 | Z17: 0 | AA17: 0 | AB17: 0 | AC17: 0 | AD17: 0 | AE17: 0
A18: egy.mit.pbc.ind.ren.a.1 | B18: ren | C18: ind | D18: pbc | E18: 1 | F18: $/kwh | G18: Price before any new policy (supply cost + VAT + existing excise, subsidies, carbon prices) | H18: 2809 | I18: egy.mit.pbc.ren.ind.1 | L18: 0.14404499 | M18: 0.14102041 | N18: 0.13511636 | O18: 0.13098826 | P18: 0.12790842 | Q18: 0.12481431 | R18: 0.12146026 | S18: 0.11795074 | T18: 0.11419916 | U18: 0.1136651 | V18: 0.11301693 | W18: 0.11231407 | X18: 0.11142204 | Y18: 0.11043412 | Z18: 0.10948397 | AA18: 0.10839192 | AB18: 0.10735443 | AC18: 0.10516868 | AD18: 0.10305798 | AE18: 0.10093184
A19: egy.mit.nce.ind.ren.a.1 | B19: ren | C19: ind | D19: nce | E19: 1 | F19: $/kwh | G19: Total new policy wedge before sector coverage | H19: 2810 | I19: egy.mit.nce.ren.ind.1 | L19: 0 | M19: 0 | N19: 0 | O19: 0 | P19: 0 | Q19: 0 | R19: 0 | S19: 0 | T19: 0 | U19: 0 | V19: 0 | W19: 0 | X19: 0 | Y19: 0 | Z19: 0 | AA19: 0 | AB19: 0 | AC19: 0 | AD19: 0 | AE19: 0
A20: egy.mit.shp.coa.ind.1 | B20: coa | C20: ind | D20: shp | E20: 1 | F20: $/GJ | G20: Shadow price of non-price policies ($/unit) | H20: 2379 | I20: egy.mit.shp.coa.ind.1 | L20: 0 | M20: 0 | N20: 0 | O20: 0 | P20: 0 | Q20: 0 | R20: 0 | S20: 0 | T20: 0 | U20: 0 | V20: 0 | W20: 0 | X20: 0 | Y20: 0 | Z20: 0 | AA20: 0 | AB20: 0 | AC20: 0 | AD20: 0 | AE20: 0
A21: egy.mit.shp.nga.ind.1 | B21: nga | C21: ind | D21: shp | E21: 1 | F21: $/GJ | G21: Shadow price of non-price policies ($/unit) | H21: 2382 | I21: egy.mit.shp.nga.ind.1 | L21: 0 | M21: 0 | N21: 0 | O21: 0 | P21: 0 | Q21: 0 | R21: 0 | S21: 0 | T21: 0 | U21: 0 | V21: 0 | W21: 0 | X21: 0 | Y21: 0 | Z21: 0 | AA21: 0 | AB21: 0 | AC21: 0 | AD21: 0 | AE21: 0
A22: egy.mit.shp.gso.ind.1 | B22: gso | C22: ind | D22: shp | E22: 1 | F22: $/liter | G22: Shadow price of non-price policies ($/unit) | H22: 2383 | I22: egy.mit.shp.gso.all.1 | L22: 0 | M22: 0 | N22: 0 | O22: 0 | P22: 0 | Q22: 0 | R22: 0 | S22: 0 | T22: 0 | U22: 0 | V22: 0 | W22: 0 | X22: 0 | Y22: 0 | Z22: 0 | AA22: 0 | AB22: 0 | AC22: 0 | AD22: 0 | AE22: 0
A23: egy.mit.shp.die.ind.1 | B23: die | C23: ind | D23: shp | E23: 1 | F23: $/liter | G23: Shadow price of non-price policies ($/unit) | H23: 2384 | I23: egy.mit.shp.die.all.1 | L23: 0 | M23: 0 | N23: 0 | O23: 0 | P23: 0 | Q23: 0 | R23: 0 | S23: 0 | T23: 0 | U23: 0 | V23: 0 | W23: 0 | X23: 0 | Y23: 0 | Z23: 0 | AA23: 0 | AB23: 0 | AC23: 0 | AD23: 0 | AE23: 0
A24: egy.mit.shp.lpg.ind.1 | B24: lpg | C24: ind | D24: shp | E24: 1 | F24: $/liter | G24: Shadow price of non-price policies ($/unit) | H24: 2385 | I24: egy.mit.shp.lpg.all.1 | L24: 0 | M24: 0 | N24: 0 | O24: 0 | P24: 0 | Q24: 0 | R24: 0 | S24: 0 | T24: 0 | U24: 0 | V24: 0 | W24: 0 | X24: 0 | Y24: 0 | Z24: 0 | AA24: 0 | AB24: 0 | AC24: 0 | AD24: 0 | AE24: 0
A25: egy.mit.shp.ker.ind.1 | B25: ker | C25: ind | D25: shp | E25: 1 | F25: $/liter | G25: Shadow price of non-price policies ($/unit) | H25: 2386 | I25: egy.mit.shp.ker.all.1 | L25: 0 | M25: 0 | N25: 0 | O25: 0 | P25: 0 | Q25: 0 | R25: 0 | S25: 0 | T25: 0 | U25: 0 | V25: 0 | W25: 0 | X25: 0 | Y25: 0 | Z25: 0 | AA25: 0 | AB25: 0 | AC25: 0 | AD25: 0 | AE25: 0
A26: egy.mit.shp.oop.ind.1 | B26: oop | C26: ind | D26: shp | E26: 1 | F26: $/bbl | G26: Shadow price of non-price policies ($/unit) | H26: 2387 | I26: egy.mit.shp.oop.all.1 | L26: 0 | M26: 0 | N26: 0 | O26: 0 | P26: 0 | Q26: 0 | R26: 0 | S26: 0 | T26: 0 | U26: 0 | V26: 0 | W26: 0 | X26: 0 | Y26: 0 | Z26: 0 | AA26: 0 | AB26: 0 | AC26: 0 | AD26: 0 | AE26: 0
A27: egy.mit.shp.bio.ind.1 | B27: bio | C27: ind | D27: shp | E27: 1 | F27: $/GJ | G27: Shadow price of non-price policies ($/unit) | H27: 2388 | I27: egy.mit.shp.bio.all.1 | L27: 0 | M27: 0 | N27: 0 | O27: 0 | P27: 0 | Q27: 0 | R27: 0 | S27: 0 | T27: 0 | U27: 0 | V27: 0 | W27: 0 | X27: 0 | Y27: 0 | Z27: 0 | AA27: 0 | AB27: 0 | AC27: 0 | AD27: 0 | AE27: 0
A28: egy.mit.shp.ren.ind.1 | B28: ren | C28: ind | D28: shp | E28: 1 | F28: $/kwh | G28: Shadow price of non-price policies (no CPAT row for self-generated renewables: set to 0) | H28: - | I28: - | K28: 0 | L28: 0 | M28: 0 | N28: 0 | O28: 0 | P28: 0 | Q28: 0 | R28: 0 | S28: 0 | T28: 0 | U28: 0 | V28: 0 | W28: 0 | X28: 0 | Y28: 0 | Z28: 0 | AA28: 0 | AB28: 0 | AC28: 0 | AD28: 0 | AE28: 0
A29: egy.mit.tcf.pow.1 | B29: - | C29: pow | D29: tcf | E29: 1 | F29: share | G29: Sector coverage factor of the new policy wedge | H29: 2270 | I29: egy.mit.tcf.pow.1 | L29: 0 | M29: 0 | N29: 0 | O29: 0 | P29: 0 | Q29: 0 | R29: 0 | S29: 0 | T29: 0 | U29: 0 | V29: 0 | W29: 0 | X29: 0 | Y29: 0 | Z29: 0 | AA29: 0 | AB29: 0 | AC29: 0 | AD29: 0 | AE29: 0
A30: egy.mit.tcf.rod.1 | B30: - | C30: rod | D30: tcf | E30: 1 | F30: share | G30: Sector coverage factor of the new policy wedge | H30: 2271 | I30: egy.mit.tcf.rod.1 | L30: 0 | M30: 0 | N30: 0 | O30: 0 | P30: 0 | Q30: 0 | R30: 0 | S30: 0 | T30: 0 | U30: 0 | V30: 0 | W30: 0 | X30: 0 | Y30: 0 | Z30: 0 | AA30: 0 | AB30: 0 | AC30: 0 | AD30: 0 | AE30: 0
A31: egy.mit.tcf.ral.1 | B31: - | C31: ral | D31: tcf | E31: 1 | F31: share | G31: Sector coverage factor of the new policy wedge | H31: 2272 | I31: egy.mit.tcf.ral.1 | L31: 0 | M31: 0 | N31: 0 | O31: 0 | P31: 0 | Q31: 0 | R31: 0 | S31: 0 | T31: 0 | U31: 0 | V31: 0 | W31: 0 | X31: 0 | Y31: 0 | Z31: 0 | AA31: 0 | AB31: 0 | AC31: 0 | AD31: 0 | AE31: 0
A32: egy.mit.tcf.nav.1 | B32: - | C32: nav | D32: tcf | E32: 1 | F32: share | G32: Sector coverage factor of the new policy wedge | H32: 2273 | I32: egy.mit.tcf.nav.1 | L32: 0 | M32: 0 | N32: 0 | O32: 0 | P32: 0 | Q32: 0 | R32: 0 | S32: 0 | T32: 0 | U32: 0 | V32: 0 | W32: 0 | X32: 0 | Y32: 0 | Z32: 0 | AA32: 0 | AB32: 0 | AC32: 0 | AD32: 0 | AE32: 0
A33: egy.mit.tcf.avi.1 | B33: - | C33: avi | D33: tcf | E33: 1 | F33: share | G33: Sector coverage factor of the new policy wedge | H33: 2274 | I33: egy.mit.tcf.avi.1 | L33: 0 | M33: 0 | N33: 0 | O33: 0 | P33: 0 | Q33: 0 | R33: 0 | S33: 0 | T33: 0 | U33: 0 | V33: 0 | W33: 0 | X33: 0 | Y33: 0 | Z33: 0 | AA33: 0 | AB33: 0 | AC33: 0 | AD33: 0 | AE33: 0
A34: egy.mit.tcf.res.1 | B34: - | C34: res | D34: tcf | E34: 1 | F34: share | G34: Sector coverage factor of the new policy wedge | H34: 2275 | I34: egy.mit.tcf.res.1 | L34: 0 | M34: 0 | N34: 0 | O34: 0 | P34: 0 | Q34: 0 | R34: 0 | S34: 0 | T34: 0 | U34: 0 | V34: 0 | W34: 0 | X34: 0 | Y34: 0 | Z34: 0 | AA34: 0 | AB34: 0 | AC34: 0 | AD34: 0 | AE34: 0
A35: egy.mit.tcf.foo.1 | B35: - | C35: foo | D35: tcf | E35: 1 | F35: share | G35: Sector coverage factor of the new policy wedge | H35: 2276 | I35: egy.mit.tcf.foo.1 | L35: 0 | M35: 0 | N35: 0 | O35: 0 | P35: 0 | Q35: 0 | R35: 0 | S35: 0 | T35: 0 | U35: 0 | V35: 0 | W35: 0 | X35: 0 | Y35: 0 | Z35: 0 | AA35: 0 | AB35: 0 | AC35: 0 | AD35: 0 | AE35: 0
A36: egy.mit.tcf.srv.1 | B36: - | C36: srv | D36: tcf | E36: 1 | F36: share | G36: Sector coverage factor of the new policy wedge | H36: 2277 | I36: egy.mit.tcf.srv.1 | L36: 0 | M36: 0 | N36: 0 | O36: 0 | P36: 0 | Q36: 0 | R36: 0 | S36: 0 | T36: 0 | U36: 0 | V36: 0 | W36: 0 | X36: 0 | Y36: 0 | Z36: 0 | AA36: 0 | AB36: 0 | AC36: 0 | AD36: 0 | AE36: 0
A37: egy.mit.tcf.mch.1 | B37: - | C37: mch | D37: tcf | E37: 1 | F37: share | G37: Sector coverage factor of the new policy wedge | H37: 2278 | I37: egy.mit.tcf.mch.1 | L37: 0 | M37: 0 | N37: 0 | O37: 0 | P37: 0 | Q37: 0 | R37: 0 | S37: 0 | T37: 0 | U37: 0 | V37: 0 | W37: 0 | X37: 0 | Y37: 0 | Z37: 0 | AA37: 0 | AB37: 0 | AC37: 0 | AD37: 0 | AE37: 0
A38: egy.mit.tcf.irn.1 | B38: - | C38: irn | D38: tcf | E38: 1 | F38: share | G38: Sector coverage factor of the new policy wedge | H38: 2279 | I38: egy.mit.tcf.irn.1 | L38: 0 | M38: 0 | N38: 0 | O38: 0 | P38: 0 | Q38: 0 | R38: 0 | S38: 0 | T38: 0 | U38: 0 | V38: 0 | W38: 0 | X38: 0 | Y38: 0 | Z38: 0 | AA38: 0 | AB38: 0 | AC38: 0 | AD38: 0 | AE38: 0
A39: egy.mit.tcf.nfm.1 | B39: - | C39: nfm | D39: tcf | E39: 1 | F39: share | G39: Sector coverage factor of the new policy wedge | H39: 2280 | I39: egy.mit.tcf.nfm.1 | L39: 0 | M39: 0 | N39: 0 | O39: 0 | P39: 0 | Q39: 0 | R39: 0 | S39: 0 | T39: 0 | U39: 0 | V39: 0 | W39: 0 | X39: 0 | Y39: 0 | Z39: 0 | AA39: 0 | AB39: 0 | AC39: 0 | AD39: 0 | AE39: 0
A40: egy.mit.tcf.mac.1 | B40: - | C40: mac | D40: tcf | E40: 1 | F40: share | G40: Sector coverage factor of the new policy wedge | H40: 2281 | I40: egy.mit.tcf.mac.1 | L40: 0 | M40: 0 | N40: 0 | O40: 0 | P40: 0 | Q40: 0 | R40: 0 | S40: 0 | T40: 0 | U40: 0 | V40: 0 | W40: 0 | X40: 0 | Y40: 0 | Z40: 0 | AA40: 0 | AB40: 0 | AC40: 0 | AD40: 0 | AE40: 0
... A62: egy.mit.ssc.oen.1 | B62: - | C62: oen | D62: ssc | E62: 1 | F62: share | G62: Share of shadow price acting on efficiency | H62: 2419 | I62: egy.mit.ssc.oen.1 | L62: 0 | M62: 0 | N62: 0 | O62: 0 | P62: 0 | Q62: 0 | R62: 0 | S62: 0 | T62: 0 | U62: 0 | V62: 0 | W62: 0 | X62: 0 | Y62: 0 | Z62: 0 | AA62: 0 | AB62: 0 | AC62: 0 | AD62: 0 | AE62: 0
A63: egy.mit.pbc.ind.coa.a.2 | B63: coa | C63: ind | D63: pbc | E63: 2 | F63: $/GJ | G63: Price before any new policy (supply cost + VAT + existing excise, subsidies, carbon prices) | H63: 8844 | I63: egy.mit.pbc.ind.coa.a.2 | K63: 11.182902 | L63: 10.523361 | M63: 10.299561 | N63: 9.5775284 | O63: 8.4854783 | P63: 9.0871922 | Q63: 9.2229237 | R63: 9.158565 | S63: 9.0895479 | T63: 9.0156817 | U63: 8.9443978 | V63: 8.9443978 | W63: 8.9443978 | X63: 8.9443978 | Y63: 8.9443978 | Z63: 8.9443978 | AA63: 8.9443978 | AB63: 8.9443978 | AC63: 8.9443978 | AD63: 8.9443978 | AE63: 8.9443978
A64: egy.mit.nce.ind.coa.a.2 | B64: coa | C64: ind | D64: nce | E64: 2 | F64: $/GJ | G64: Total new policy wedge before sector coverage | H64: 8845 | I64: egy.mit.nce.ind.coa.a.2 | K64: 0 | L64: 0 | M64: 0 | N64: 0 | O64: 0 | P64: 0 | Q64: 1.25 | R64: 2.5 | S64: 3.75 | T64: 5 | U64: 6.25 | V64: 7.5 | W64: 8.75 | X64: 10 | Y64: 11.25 | Z64: 12.5 | AA64: 13.75 | AB64: 15 | AC64: 16.25 | AD64: 17.5 | AE64: 18.75
A65: egy.mit.pbc.ind.nga.a.2 | B65: nga | C65: ind | D65: pbc | E65: 2 | F65: $/GJ | G65: Price before any new policy (supply cost + VAT + existing excise, subsidies, carbon prices) | H65: 8913 | I65: egy.mit.pbc.ind.nga.a.2 | K65: 6.0634636 | L65: 5.4510151 | M65: 5.1193563 | N65: 5.0821846 | O65: 5.0821846 | P65: 5.0821846 | Q65: 5.0821846 | R65: 5.0821846 | S65: 5.0821846 | T65: 5.0821846 | U65: 5.0821846 | V65: 5.0821846 | W65: 5.0821846 | X65: 5.0821846 | Y65: 5.0821846 | Z65: 5.0821846 | AA65: 5.0821846 | AB65: 5.0821846 | AC65: 5.0821846 | AD65: 5.0821846 | AE65: 5.0821846
A66: egy.mit.nce.ind.nga.a.2 | B66: nga | C66: ind | D66: nce | E66: 2 | F66: $/GJ | G66: Total new policy wedge before sector coverage | H66: 8914 | I66: egy.mit.nce.ind.nga.a.2 | K66: 0 | L66: 0 | M66: 0 | N66: 0 | O66: 0 | P66: 0 | Q66: 0.6975 | R66: 1.395 | S66: 2.0925 | T66: 2.79 | U66: 3.4875 | V66: 4.185 | W66: 4.8825 | X66: 5.58 | Y66: 6.2775 | Z66: 6.975 | AA66: 7.6725 | AB66: 8.37 | AC66: 9.0675 | AD66: 9.765 | AE66: 10.4625
A67: egy.mit.pbc.ind.gso.a.2 | B67: gso | C67: ind | D67: pbc | E67: 2 | F67: $/liter | G67: Price before any new policy (supply cost + VAT + existing excise, subsidies, carbon prices) | H67: 8936 | I67: egy.mit.pbc.all.gso.a.2 | K67: 0.67114653 | L67: 0.61197798 | M67: 0.61180975 | N67: 0.6035831 | O67: 0.6035831 | P67: 0.6035831 | Q67: 0.6035831 | R67: 0.6035831 | S67: 0.6035831 | T67: 0.6035831 | U67: 0.6035831 | V67: 0.6035831 | W67: 0.6035831 | X67: 0.6035831 | Y67: 0.6035831 | Z67: 0.6035831 | AA67: 0.6035831 | AB67: 0.6035831 | AC67: 0.6035831 | AD67: 0.6035831 | AE67: 0.6035831
A68: egy.mit.nce.ind.gso.a.2 | B68: gso | C68: ind | D68: nce | E68: 2 | F68: $/liter | G68: Total new policy wedge before sector coverage | H68: 8937 | I68: egy.mit.nce.all.gso.a.2 | K68: 0 | L68: 0 | M68: 0 | N68: 0 | O68: 0 | P68: 0 | Q68: 0.028927843 | R68: 0.057855686 | S68: 0.08678353 | T68: 0.11571137 | U68: 0.14463922 | V68: 0.17356706 | W68: 0.2024949 | X68: 0.23142275 | Y68: 0.26035059 | Z68: 0.28927843 | AA68: 0.31820627 | AB68: 0.34713412 | AC68: 0.37606196 | AD68: 0.4049898 | AE68: 0.43391765
A69: egy.mit.pbc.ind.die.a.2 | B69: die | C69: ind | D69: pbc | E69: 2 | F69: $/liter | G69: Price before any new policy (supply cost + VAT + existing excise, subsidies, carbon prices) | H69: 8959 | I69: egy.mit.pbc.all.die.a.2 | K69: 0.55971121 | L69: 0.49458873 | M69: 0.50778655 | N69: 0.47043643 | O69: 0.47043643 | P69: 0.47043643 | Q69: 0.47043643 | R69: 0.47043643 | S69: 0.47043643 | T69: 0.47043643 | U69: 0.47043643 | V69: 0.47043643 | W69: 0.47043643 | X69: 0.47043643 | Y69: 0.47043643 | Z69: 0.47043643 | AA69: 0.47043643 | AB69: 0.47043643 | AC69: 0.47043643 | AD69: 0.47043643 | AE69: 0.47043643
A70: egy.mit.nce.ind.die.a.2 | B70: die | C70: ind | D70: nce | E70: 2 | F70: $/liter | G70: Total new policy wedge before sector coverage | H70: 8960 | I70: egy.mit.nce.all.die.a.2 | K70: 0 | L70: 0 | M70: 0 | N70: 0 | O70: 0 | P70: 0 | Q70: 0.033010439 | R70: 0.066020878 | S70: 0.099031317 | T70: 0.13204176 | U70: 0.16505219 | V70: 0.19806263 | W70: 0.23107307 | X70: 0.26408351 | Y70: 0.29709395 | Z70: 0.33010439 | AA70: 0.36311483 | AB70: 0.39612527 | AC70: 0.42913571 | AD70: 0.46214614 | AE70: 0.49515658
A71: egy.mit.pbc.ind.lpg.a.2 | B71: lpg | C71: ind | D71: pbc | E71: 2 | F71: $/liter | G71: Price before any new policy (supply cost + VAT + existing excise, subsidies, carbon prices) | H71: 8982 | I71: egy.mit.pbc.all.lpg.a.2 | K71: 0.20036669 | L71: 0.15734474 | M71: 0.16448404 | N71: 0.15070908 | O71: 0.15070908 | P71: 0.15070908 | Q71: 0.15070908 | R71: 0.15070908 | S71: 0.15070908 | T71: 0.15070908 | U71: 0.15070908 | V71: 0.15070908 | W71: 0.15070908 | X71: 0.15070908 | Y71: 0.15070908 | Z71: 0.15070908 | AA71: 0.15070908 | AB71: 0.15070908 | AC71: 0.15070908 | AD71: 0.15070908 | AE71: 0.15070908
A72: egy.mit.nce.ind.lpg.a.2 | B72: lpg | C72: ind | D72: nce | E72: 2 | F72: $/liter | G72: Total new policy wedge before sector coverage | H72: 8983 | I72: egy.mit.nce.all.lpg.a.2 | K72: 0 | L72: 0 | M72: 0 | N72: 0 | O72: 0 | P72: 0 | Q72: 0.022106083 | R72: 0.044212166 | S72: 0.066318249 | T72: 0.088424332 | U72: 0.11053041 | V72: 0.1326365 | W72: 0.15474258 | X72: 0.17684866 | Y72: 0.19895475 | Z72: 0.22106083 | AA72: 0.24316691 | AB72: 0.265273 | AC72: 0.28737908 | AD72: 0.30948516 | AE72: 0.33159124
A73: egy.mit.pbc.ind.ker.a.2 | B73: ker | C73: ind | D73: pbc | E73: 2 | F73: $/liter | G73: Price before any new policy (supply cost + VAT + existing excise, subsidies, carbon prices) | H73: 9005 | I73: egy.mit.pbc.ker.a.2 | K73: 0.48429424 | L73: 0.45642817 | M73: 0.4316892 | N73: 0.42507558 | O73: 0.42507558 | P73: 0.42507558 | Q73: 0.42507558 | R73: 0.42507558 | S73: 0.42507558 | T73: 0.42507558 | U73: 0.42507558 | V73: 0.42507558 | W73: 0.42507558 | X73: 0.42507558 | Y73: 0.42507558 | Z73: 0.42507558 | AA73: 0.42507558 | AB73: 0.42507558 | AC73: 0.42507558 | AD73: 0.42507558 | AE73: 0.42507558
A74: egy.mit.nce.ind.ker.a.2 | B74: ker | C74: ind | D74: nce | E74: 2 | F74: $/liter | G74: Total new policy wedge before sector coverage | H74: 9006 | I74: egy.mit.nce.ker.a.2 | K74: 0 | L74: 0 | M74: 0 | N74: 0 | O74: 0 | P74: 0 | Q74: 0.03198883 | R74: 0.06397766 | S74: 0.09596649 | T74: 0.12795532 | U74: 0.15994415 | V74: 0.19193298 | W74: 0.22392181 | X74: 0.25591064 | Y74: 0.28789947 | Z74: 0.3198883 | AA74: 0.35187713 | AB74: 0.38386596 | AC74: 0.41585479 | AD74: 0.44784362 | AE74: 0.47983245
... A78: egy.mit.nce.ind.bio.a.2 | B78: bio | C78: ind | D78: nce | E78: 2 | F78: $/GJ | G78: Total new policy wedge before sector coverage | H78: 9052 | I78: egy.mit.nce.all.bio.a.2 | K78: 0 | L78: 0 | M78: 0 | N78: 0 | O78: 0 | P78: 0 | Q78: 0 | R78: 0 | S78: 0 | T78: 0 | U78: 0 | V78: 0 | W78: 0 | X78: 0 | Y78: 0 | Z78: 0 | AA78: 0 | AB78: 0 | AC78: 0 | AD78: 0 | AE78: 0
A79: egy.mit.pbc.ind.ren.a.2 | B79: ren | C79: ind | D79: pbc | E79: 2 | F79: $/kwh | G79: Price before any new policy (supply cost + VAT + existing excise, subsidies, carbon prices) | H79: 9140 | I79: egy.mit.pbc.ren.ind.2 | L79: 0.14404499 | M79: 0.14138624 | N79: 0.13539757 | O79: 0.13152289 | P79: 0.12882611 | Q79: 0.12594201 | R79: 0.12311327 | S79: 0.11939174 | T79: 0.11554419 | U79: 0.11492423 | V79: 0.11434691 | W79: 0.11373871 | X79: 0.1129999 | Y79: 0.11217769 | Z79: 0.1114179 | AA79: 0.11052582 | AB79: 0.10969957 | AC79: 0.10772679 | AD79: 0.10582092 | AE79: 0.1038556
A80: egy.mit.nce.ind.ren.a.2 | B80: ren | C80: ind | D80: nce | E80: 2 | F80: $/kwh | G80: Total new policy wedge before sector coverage | H80: 9141 | I80: egy.mit.nce.ren.ind.2 | L80: 0 | M80: 0 | N80: 0 | O80: 0 | P80: 0 | Q80: 0 | R80: 0 | S80: 0 | T80: 0 | U80: 0 | V80: 0 | W80: 0 | X80: 0 | Y80: 0 | Z80: 0 | AA80: 0 | AB80: 0 | AC80: 0 | AD80: 0 | AE80: 0
A81: egy.mit.shp.coa.ind.2 | B81: coa | C81: ind | D81: shp | E81: 2 | F81: $/GJ | G81: Shadow price of non-price policies ($/unit) | H81: 8710 | I81: egy.mit.shp.coa.ind.2 | L81: 0 | M81: 0 | N81: 0 | O81: 0 | P81: 0 | Q81: 0 | R81: 0 | S81: 0 | T81: 0 | U81: 0 | V81: 0 | W81: 0 | X81: 0 | Y81: 0 | Z81: 0 | AA81: 0 | AB81: 0 | AC81: 0 | AD81: 0 | AE81: 0
A82: egy.mit.shp.nga.ind.2 | B82: nga | C82: ind | D82: shp | E82: 2 | F82: $/GJ | G82: Shadow price of non-price policies ($/unit) | H82: 8713 | I82: egy.mit.shp.nga.ind.2 | L82: 0 | M82: 0 | N82: 0 | O82: 0 | P82: 0 | Q82: 0 | R82: 0 | S82: 0 | T82: 0 | U82: 0 | V82: 0 | W82: 0 | X82: 0 | Y82: 0 | Z82: 0 | AA82: 0 | AB82: 0 | AC82: 0 | AD82: 0 | AE82: 0
A83: egy.mit.shp.gso.ind.2 | B83: gso | C83: ind | D83: shp | E83: 2 | F83: $/liter | G83: Shadow price of non-price policies ($/unit) | H83: 8714 | I83: egy.mit.shp.gso.all.2 | L83: 0 | M83: 0 | N83: 0 | O83: 0 | P83: 0 | Q83: 0 | R83: 0 | S83: 0 | T83: 0 | U83: 0 | V83: 0 | W83: 0 | X83: 0 | Y83: 0 | Z83: 0 | AA83: 0 | AB83: 0 | AC83: 0 | AD83: 0 | AE83: 0
A84: egy.mit.shp.die.ind.2 | B84: die | C84: ind | D84: shp | E84: 2 | F84: $/liter | G84: Shadow price of non-price policies ($/unit) | H84: 8715 | I84: egy.mit.shp.die.all.2 | L84: 0 | M84: 0 | N84: 0 | O84: 0 | P84: 0 | Q84: 0 | R84: 0 | S84: 0 | T84: 0 | U84: 0 | V84: 0 | W84: 0 | X84: 0 | Y84: 0 | Z84: 0 | AA84: 0 | AB84: 0 | AC84: 0 | AD84: 0 | AE84: 0
A85: egy.mit.shp.lpg.ind.2 | B85: lpg | C85: ind | D85: shp | E85: 2 | F85: $/liter | G85: Shadow price of non-price policies ($/unit) | H85: 8716 | I85: egy.mit.shp.lpg.all.2 | L85: 0 | M85: 0 | N85: 0 | O85: 0 | P85: 0 | Q85: 0 | R85: 0 | S85: 0 | T85: 0 | U85: 0 | V85: 0 | W85: 0 | X85: 0 | Y85: 0 | Z85: 0 | AA85: 0 | AB85: 0 | AC85: 0 | AD85: 0 | AE85: 0
A86: egy.mit.shp.ker.ind.2 | B86: ker | C86: ind | D86: shp | E86: 2 | F86: $/liter | G86: Shadow price of non-price policies ($/unit) | H86: 8717 | I86: egy.mit.shp.ker.all.2 | L86: 0 | M86: 0 | N86: 0 | O86: 0 | P86: 0 | Q86: 0 | R86: 0 | S86: 0 | T86: 0 | U86: 0 | V86: 0 | W86: 0 | X86: 0 | Y86: 0 | Z86: 0 | AA86: 0 | AB86: 0 | AC86: 0 | AD86: 0 | AE86: 0
A87: egy.mit.shp.oop.ind.2 | B87: oop | C87: ind | D87: shp | E87: 2 | F87: $/bbl | G87: Shadow price of non-price policies ($/unit) | H87: 8718 | I87: egy.mit.shp.oop.all.2 | L87: 0 | M87: 0 | N87: 0 | O87: 0 | P87: 0 | Q87: 0 | R87: 0 | S87: 0 | T87: 0 | U87: 0 | V87: 0 | W87: 0 | X87: 0 | Y87: 0 | Z87: 0 | AA87: 0 | AB87: 0 | AC87: 0 | AD87: 0 | AE87: 0
A88: egy.mit.shp.bio.ind.2 | B88: bio | C88: ind | D88: shp | E88: 2 | F88: $/GJ | G88: Shadow price of non-price policies ($/unit) | H88: 8719 | I88: egy.mit.shp.bio.all.2 | L88: 0 | M88: 0 | N88: 0 | O88: 0 | P88: 0 | Q88: 0 | R88: 0 | S88: 0 | T88: 0 | U88: 0 | V88: 0 | W88: 0 | X88: 0 | Y88: 0 | Z88: 0 | AA88: 0 | AB88: 0 | AC88: 0 | AD88: 0 | AE88: 0
A89: egy.mit.shp.ren.ind.2 | B89: ren | C89: ind | D89: shp | E89: 2 | F89: $/kwh | G89: Shadow price of non-price policies (no CPAT row for self-generated renewables: set to 0) | H89: - | I89: - | K89: 0 | L89: 0 | M89: 0 | N89: 0 | O89: 0 | P89: 0 | Q89: 0 | R89: 0 | S89: 0 | T89: 0 | U89: 0 | V89: 0 | W89: 0 | X89: 0 | Y89: 0 | Z89: 0 | AA89: 0 | AB89: 0 | AC89: 0 | AD89: 0 | AE89: 0
A90: egy.mit.tcf.pow.2 | B90: - | C90: pow | D90: tcf | E90: 2 | F90: share | G90: Sector coverage factor of the new policy wedge | H90: 8601 | I90: egy.mit.tcf.pow.2 | L90: 0 | M90: 0 | N90: 0 | O90: 0 | P90: 1 | Q90: 1 | R90: 1 | S90: 1 | T90: 1 | U90: 1 | V90: 1 | W90: 1 | X90: 1 | Y90: 1 | Z90: 1 | AA90: 1 | AB90: 1 | AC90: 1 | AD90: 1 | AE90: 1
A91: egy.mit.tcf.rod.2 | B91: - | C91: rod | D91: tcf | E91: 2 | F91: share | G91: Sector coverage factor of the new policy wedge | H91: 8602 | I91: egy.mit.tcf.rod.2 | L91: 0 | M91: 0 | N91: 0 | O91: 0 | P91: 1 | Q91: 1 | R91: 1 | S91: 1 | T91: 1 | U91: 1 | V91: 1 | W91: 1 | X91: 1 | Y91: 1 | Z91: 1 | AA91: 1 | AB91: 1 | AC91: 1 | AD91: 1 | AE91: 1
A92: egy.mit.tcf.ral.2 | B92: - | C92: ral | D92: tcf | E92: 2 | F92: share | G92: Sector coverage factor of the new policy wedge | H92: 8603 | I92: egy.mit.tcf.ral.2 | L92: 0 | M92: 0 | N92: 0 | O92: 0 | P92: 1 | Q92: 1 | R92: 1 | S92: 1 | T92: 1 | U92: 1 | V92: 1 | W92: 1 | X92: 1 | Y92: 1 | Z92: 1 | AA92: 1 | AB92: 1 | AC92: 1 | AD92: 1 | AE92: 1
A93: egy.mit.tcf.nav.2 | B93: - | C93: nav | D93: tcf | E93: 2 | F93: share | G93: Sector coverage factor of the new policy wedge | H93: 8604 | I93: egy.mit.tcf.nav.2 | L93: 0 | M93: 0 | N93: 0 | O93: 0 | P93: 1 | Q93: 1 | R93: 1 | S93: 1 | T93: 1 | U93: 1 | V93: 1 | W93: 1 | X93: 1 | Y93: 1 | Z93: 1 | AA93: 1 | AB93: 1 | AC93: 1 | AD93: 1 | AE93: 1
A94: egy.mit.tcf.avi.2 | B94: - | C94: avi | D94: tcf | E94: 2 | F94: share | G94: Sector coverage factor of the new policy wedge | H94: 8605 | I94: egy.mit.tcf.avi.2 | L94: 0 | M94: 0 | N94: 0 | O94: 0 | P94: 1 | Q94: 1 | R94: 1 | S94: 1 | T94: 1 | U94: 1 | V94: 1 | W94: 1 | X94: 1 | Y94: 1 | Z94: 1 | AA94: 1 | AB94: 1 | AC94: 1 | AD94: 1 | AE94: 1
A95: egy.mit.tcf.res.2 | B95: - | C95: res | D95: tcf | E95: 2 | F95: share | G95: Sector coverage factor of the new policy wedge | H95: 8606 | I95: egy.mit.tcf.res.2 | L95: 0 | M95: 0 | N95: 0 | O95: 0 | P95: 1 | Q95: 1 | R95: 1 | S95: 1 | T95: 1 | U95: 1 | V95: 1 | W95: 1 | X95: 1 | Y95: 1 | Z95: 1 | AA95: 1 | AB95: 1 | AC95: 1 | AD95: 1 | AE95: 1
A96: egy.mit.tcf.foo.2 | B96: - | C96: foo | D96: tcf | E96: 2 | F96: share | G96: Sector coverage factor of the new policy wedge | H96: 8607 | I96: egy.mit.tcf.foo.2 | L96: 0 | M96: 0 | N96: 0 | O96: 0 | P96: 1 | Q96: 1 | R96: 1 | S96: 1 | T96: 1 | U96: 1 | V96: 1 | W96: 1 | X96: 1 | Y96: 1 | Z96: 1 | AA96: 1 | AB96: 1 | AC96: 1 | AD96: 1 | AE96: 1
A97: egy.mit.tcf.srv.2 | B97: - | C97: srv | D97: tcf | E97: 2 | F97: share | G97: Sector coverage factor of the new policy wedge | H97: 8608 | I97: egy.mit.tcf.srv.2 | L97: 0 | M97: 0 | N97: 0 | O97: 0 | P97: 1 | Q97: 1 | R97: 1 | S97: 1 | T97: 1 | U97: 1 | V97: 1 | W97: 1 | X97: 1 | Y97: 1 | Z97: 1 | AA97: 1 | AB97: 1 | AC97: 1 | AD97: 1 | AE97: 1
A98: egy.mit.tcf.mch.2 | B98: - | C98: mch | D98: tcf | E98: 2 | F98: share | G98: Sector coverage factor of the new policy wedge | H98: 8609 | I98: egy.mit.tcf.mch.2 | L98: 0 | M98: 0 | N98: 0 | O98: 0 | P98: 1 | Q98: 1 | R98: 1 | S98: 1 | T98: 1 | U98: 1 | V98: 1 | W98: 1 | X98: 1 | Y98: 1 | Z98: 1 | AA98: 1 | AB98: 1 | AC98: 1 | AD98: 1 | AE98: 1
A99: egy.mit.tcf.irn.2 | B99: - | C99: irn | D99: tcf | E99: 2 | F99: share | G99: Sector coverage factor of the new policy wedge | H99: 8610 | I99: egy.mit.tcf.irn.2 | L99: 0 | M99: 0 | N99: 0 | O99: 0 | P99: 1 | Q99: 1 | R99: 1 | S99: 1 | T99: 1 | U99: 1 | V99: 1 | W99: 1 | X99: 1 | Y99: 1 | Z99: 1 | AA99: 1 | AB99: 1 | AC99: 1 | AD99: 1 | AE99: 1
A100: egy.mit.tcf.nfm.2 | B100: - | C100: nfm | D100: tcf | E100: 2 | F100: share | G100: Sector coverage factor of the new policy wedge | H100: 8611 | I100: egy.mit.tcf.nfm.2 | L100: 0 | M100: 0 | N100: 0 | O100: 0 | P100: 1 | Q100: 1 | R100: 1 | S100: 1 | T100: 1 | U100: 1 | V100: 1 | W100: 1 | X100: 1 | Y100: 1 | Z100: 1 | AA100: 1 | AB100: 1 | AC100: 1 | AD100: 1 | AE100: 1
A101: egy.mit.tcf.mac.2 | B101: - | C101: mac | D101: tcf | E101: 2 | F101: share | G101: Sector coverage factor of the new policy wedge | H101: 8612 | I101: egy.mit.tcf.mac.2 | L101: 0 | M101: 0 | N101: 0 | O101: 0 | P101: 1 | Q101: 1 | R101: 1 | S101: 1 | T101: 1 | U101: 1 | V101: 1 | W101: 1 | X101: 1 | Y101: 1 | Z101: 1 | AA101: 1 | AB101: 1 | AC101: 1 | AD101: 1 | AE101: 1
... A123: egy.mit.ssc.oen.2 | B123: - | C123: oen | D123: ssc | E123: 2 | F123: share | G123: Share of shadow price acting on efficiency | H123: 8750 | I123: egy.mit.ssc.oen.2 | L123: 0 | M123: 0 | N123: 0 | O123: 0 | P123: 0 | Q123: 0 | R123: 0 | S123: 0 | T123: 0 | U123: 0 | V123: 0 | W123: 0 | X123: 0 | Y123: 0 | Z123: 0 | AA123: 0 | AB123: 0 | AC123: 0 | AD123: 0 | AE123: 0

Sheet Data_Macro
A1: Code | B1: Variable | C1: Scenario | D1: Description | E1: CPAT source row | K1: 2021 | L1: 2022 | M1: 2023 | N1: 2024 | O1: 2025 | P1: 2026 | Q1: 2027 | R1: 2028 | S1: 2029 | T1: 2030 | U1: 2031 | V1: 2032 | W1: 2033 | X1: 2034 | Y1: 2035 | Z1: 2036 | AA1: 2037 | AB1: 2038 | AC1: 2039 | AD1: 2040 | AE1: 2041 | AF1: 2042 | AG1: 2043 | AH1: 2044 | AI1: 2045
A2: egy.mit.gdp.pos.pct.1 | B2: g | C2: 1 | D2: Post-policy real GDP growth | E2: 2446 | L2: 0.06651345 | M2: 0.03760281 | N2: 0.02398801 | O2: 0.04392387 | P2: 0.04239706 | Q2: 0.04829218 | R2: 0.05535316 | S2: 0.05226606 | T2: 0.04841877 | U2: 0.04788736 | V2: 0.04735595 | W2: 0.04682454 | X2: 0.04629313 | Y2: 0.04576172 | Z2: 0.04523031 | AA2: 0.0446989 | AB2: 0.04416749 | AC2: 0.04363608 | AD2: 0.04310467 | AE2: 0.04257326
A3: egy.mit.inc.ela.adj.1 | B3: delta | C3: 1 | D3: Income-elasticity discount factor (Gertler reverse-U) | E3: 2433 | L3: 1.0271517 | M3: 1.0271517 | N3: 1.0205698 | O3: 1.0173344 | P3: 1.0076683 | Q3: 1.0007443 | R3: 0.99188649 | S3: 0.9806554 | T3: 0.9702094 | U3: 0.96419266 | V3: 0.96161287 | W3: 0.95919845 | X3: 0.95695125 | Y3: 0.95487298 | Z3: 0.95296514 | AA3: 0.9512291 | AB3: 0.94966609 | AC3: 0.94827716 | AD3: 0.94706328 | AE3: 0.94602527
A4: egy.mit.shock.1 | B4: psi | C4: 1 | D4: Exogenous shock on energy consumption (Covid calibration; no CPAT code) | E4: 2439 | K4: 0 | L4: 0 | M4: -0.20813308 | N4: 0.092371429 | O4: 0 | P4: 0 | Q4: 0 | R4: 0 | S4: 0 | T4: 0 | U4: 0 | V4: 0 | W4: 0 | X4: 0 | Y4: 0 | Z4: 0 | AA4: 0 | AB4: 0 | AC4: 0 | AD4: 0 | AE4: 0
