Workbook

Sheet ReadMe
A2: CPAT mitigation module - copy-pasteable prototype v0.1
A4: Purpose | B4: Auditable, copy-pasteable replacement of the CPAT mitigation price -> fuel-use chain. Every block has one formula (same R1C1 text) across all its projection cells; a whole scenario group copies to the next group position and keeps working.
A5: Status | B5: v0.1 prototype. Price -> fuel use only (no emissions, power or revenue yet).
A6: Layout (design 2) | B6: Columns: descriptors A-J (NORMS 1.1), keys K-P, parameter sets Q-AJ, then one column group per scenario (15 columns: label, base year, 2023-2035). Rows: macro rows 4-8, then blocks.
A7: Nesting | B7: Across: scenario (outer) > year (inner). Down: variable block (outer) > subsector > fuel (inner). 16 CPAT energy-use subsectors x 8 fuels = 128 rows per block.
A8: Blocks | B8: Pre-tax price (row 10), Tax (row 140), Post-tax price (row 270), Fuel use (row 400), Totals (row 530).
A9: Pre-tax price | B9: base year: Prices_dom supply cost (mit.sp) / GJ per price unit; then p(t) = p(t-1) x (1 + P1 growth).
A10: Tax | B10: tax(t) = P1 base tax + carbon price(t) x P2 EF x P3 coverage. Base tax = (retail - supply cost) / GJ per unit, so it includes existing excise, subsidies and VAT.
A11: Post-tax price | B11: pre-tax + tax (same row in the blocks above, fixed offsets).
A12: Fuel use | B12: F(t) = F(t-1) x (1/(1+alpha))^(1+eps_U) x (1+g)^eps_Y x (p(t)/p(t-1))^eps_U x (p(t)/p(t-1))^(eps_F(1+eps_U)) - CPAT documentation 3.3.3, without the Covid factor and shadow price.
A13: Parameters | B13: Each row has 4 parameter sets of 5 slots (P5 = buffer). Set 1 holds the lookups; sets 2-4 link to set 1 - overwrite a cell to make a parameter scenario-specific. Formulas pick the set with INDEX(row, (scenario number - 1) x 5 + slot).
A14: Lookups by country | B14: Settings!C4 selects the country. Elasticities (via income group) and prices cover all CPAT countries; base-year energy use, GDP growth and EFs are Egypt only so far (other countries return #N/A until their rows are added).
A15: Add a scenario | B15: (1) Copy columns AZ:BN (a whole group) and paste at the next free group position (column BO). (2) Type the new scenario number in its label cell (row 4). (3) Edit the carbon prices in row 8. (4) Optionally overwrite parameter set N on the left. Up to 4 scenarios fit without inserting parameter columns.
... A19: Checks | B19: Row 558 (sum by fuel - sum by subsector) should be 0. check_v0_1.py tests formula uniformity, the scenario-copy behaviour and an independent recomputation.

Sheet Settings
A2: Settings
B4: Country code | C4: EGY
B5: Country name | C5: =INDEX(Countries!$B$4:$B$1000,MATCH($C$4,Countries!$A$4:$A$1000,0))
B6: Income group (selects elasticities) | C6: =INDEX(Countries!$D$4:$D$1000,MATCH($C$4,Countries!$A$4:$A$1000,0))
B7: Base year | C7: 2022
B9: Scenario number | C9: Scenario name
B10: 1 | C10: Baseline (no carbon price)
B11: 2 | C11: Carbon price $20/tCO2 from 2027
B12: 3 | C12: Spare (copy a group here)
B13: 4 | C13: Spare (copy a group here)
B16: Version log
B17: Version | C17: Date | D17: Description | E17: Max abs regression diff
B18: 0.1 | C18: 2026-10-08 | D18: First build: design 2 price -> fuel-use prototype, Egypt base data, 2 scenarios. | E18: n/a (first version)

Sheet Mitigation
B1: Fuel | C1: Sector | D1: Description | E1: Unit | F1: Source | G1: Input Code | H1: Output Code | I1: Note | J1: Helper (group) | K1: Elasticity sector | L1: Elasticity fuel | M1: AEEI fuel | N1: Price code | O1: EF sector | P1: GJ per price unit | Q1: S1 P1 | R1: S1 P2 | S1: S1 P3 | T1: S1 P4 | U1: S1 P5 | V1: S2 P1 | W1: S2 P2 | X1: S2 P3 | Y1: S2 P4 | Z1: S2 P5 | AA1: S3 P1 | AB1: S3 P2 | AC1: S3 P3 | AD1: S3 P4 | AE1: S3 P5 | AF1: S4 P1 | AG1: S4 P2 | AH1: S4 P3 | AI1: S4 P4 | AJ1: S4 P5 | AK1: Scenario group 1 | AZ1: Scenario group 2
A2: Mitigation module - price to fuel use (copy-pasteable, design 2)
A3: Scenario and macro inputs (one column group per scenario; copy a whole group to add a scenario)
D4: Scenario number | E4: no. | AK4: 1 | AL4: =AK4 | AM4: =AL4 | AN4: =AM4 | AO4: =AN4 | AP4: =AO4 | AQ4: =AP4 | AR4: =AQ4 | AS4: =AR4 | ... AY4: =AX4 | AZ4: 2 | BA4: =AZ4 | BB4: =BA4 | BC4: =BB4 | BD4: =BC4 | BE4: =BD4 | BF4: =BE4 | BG4: =BF4 | BH4: =BG4 | ... BN4: =BM4
D5: Year | E5: year | AK5: base -> | AL5: =Settings!$C$7 | AM5: =AL5+1 | AN5: =AM5+1 | AO5: =AN5+1 | AP5: =AO5+1 | AQ5: =AP5+1 | AR5: =AQ5+1 | AS5: =AR5+1 | AT5: =AS5+1 | ... AY5: =AX5+1 | AZ5: base -> | BA5: =Settings!$C$7 | BB5: =BA5+1 | BC5: =BB5+1 | BD5: =BC5+1 | BE5: =BD5+1 | BF5: =BE5+1 | BG5: =BF5+1 | BH5: =BG5+1 | BI5: =BH5+1 | ... BN5: =BM5+1
D6: Scenario name | AL6: =INDEX(Settings!$C$10:$C$13,AL$4) | BA6: =INDEX(Settings!$C$10:$C$13,BA$4)
D7: Real GDP growth | E7: % | F7: WEO (by country) | H7: mit.gdp.pos.pct | AL7: =INDEX(WEO!$F$4:$AZ$1000,MATCH(Settings!$C$4&"|gdp_growth",WEO!$A$4:$A$1000,0),MATCH(AL$5,WEO!$F$3:$AZ$3,0)) | AM7: =INDEX(WEO!$F$4:$AZ$1000,MATCH(Settings!$C$4&"|gdp_growth",WEO!$A$4:$A$1000,0),MATCH(AM$5,WEO!$F$3:$AZ$3,0)) | AN7: =INDEX(WEO!$F$4:$AZ$1000,MATCH(Settings!$C$4&"|gdp_growth",WEO!$A$4:$A$1000,0),MATCH(AN$5,WEO!$F$3:$AZ$3,0)) | AO7: =INDEX(WEO!$F$4:$AZ$1000,MATCH(Settings!$C$4&"|gdp_growth",WEO!$A$4:$A$1000,0),MATCH(AO$5,WEO!$F$3:$AZ$3,0)) | AP7: =INDEX(WEO!$F$4:$AZ$1000,MATCH(Settings!$C$4&"|gdp_growth",WEO!$A$4:$A$1000,0),MATCH(AP$5,WEO!$F$3:$AZ$3,0)) | AQ7: =INDEX(WEO!$F$4:$AZ$1000,MATCH(Settings!$C$4&"|gdp_growth",WEO!$A$4:$A$1000,0),MATCH(AQ$5,WEO!$F$3:$AZ$3,0)) | AR7: =INDEX(WEO!$F$4:$AZ$1000,MATCH(Settings!$C$4&"|gdp_growth",WEO!$A$4:$A$1000,0),MATCH(AR$5,WEO!$F$3:$AZ$3,0)) | AS7: =INDEX(WEO!$F$4:$AZ$1000,MATCH(Settings!$C$4&"|gdp_growth",WEO!$A$4:$A$1000,0),MATCH(AS$5,WEO!$F$3:$AZ$3,0)) | ... AY7: =INDEX(WEO!$F$4:$AZ$1000,MATCH(Settings!$C$4&"|gdp_growth",WEO!$A$4:$A$1000,0),MATCH(AY$5,WEO!$F$3:$AZ$3,0)) | BA7: =INDEX(WEO!$F$4:$AZ$1000,MATCH(Settings!$C$4&"|gdp_growth",WEO!$A$4:$A$1000,0),MATCH(BA$5,WEO!$F$3:$AZ$3,0)) | BB7: =INDEX(WEO!$F$4:$AZ$1000,MATCH(Settings!$C$4&"|gdp_growth",WEO!$A$4:$A$1000,0),MATCH(BB$5,WEO!$F$3:$AZ$3,0)) | BC7: =INDEX(WEO!$F$4:$AZ$1000,MATCH(Settings!$C$4&"|gdp_growth",WEO!$A$4:$A$1000,0),MATCH(BC$5,WEO!$F$3:$AZ$3,0)) | BD7: =INDEX(WEO!$F$4:$AZ$1000,MATCH(Settings!$C$4&"|gdp_growth",WEO!$A$4:$A$1000,0),MATCH(BD$5,WEO!$F$3:$AZ$3,0)) | BE7: =INDEX(WEO!$F$4:$AZ$1000,MATCH(Settings!$C$4&"|gdp_growth",WEO!$A$4:$A$1000,0),MATCH(BE$5,WEO!$F$3:$AZ$3,0)) | BF7: =INDEX(WEO!$F$4:$AZ$1000,MATCH(Settings!$C$4&"|gdp_growth",WEO!$A$4:$A$1000,0),MATCH(BF$5,WEO!$F$3:$AZ$3,0)) | BG7: =INDEX(WEO!$F$4:$AZ$1000,MATCH(Settings!$C$4&"|gdp_growth",WEO!$A$4:$A$1000,0),MATCH(BG$5,WEO!$F$3:$AZ$3,0)) | BH7: =INDEX(WEO!$F$4:$AZ$1000,MATCH(Settings!$C$4&"|gdp_growth",WEO!$A$4:$A$1000,0),MATCH(BH$5,WEO!$F$3:$AZ$3,0)) | ... BN7: =INDEX(WEO!$F$4:$AZ$1000,MATCH(Settings!$C$4&"|gdp_growth",WEO!$A$4:$A$1000,0),MATCH(BN$5,WEO!$F$3:$AZ$3,0))
D8: Carbon price | E8: $/tCO2 | F8: Scenario input | H8: mit.cp | AL8: 0 | AM8: 0 | AN8: 0 | AO8: 0 | AP8: 0 | AQ8: 0 | AR8: 0 | AS8: 0 | AT8: 0 | AU8: 0 | AV8: 0 | AW8: 0 | AX8: 0 | AY8: 0 | BA8: 0 | BB8: 0 | BC8: 0 | BD8: 0 | BE8: 0 | BF8: 20 | BG8: 20 | BH8: 20 | BI8: 20 | BJ8: 20 | BK8: 20 | BL8: 20 | BM8: 20 | BN8: 20
A10: Pre-tax price (supply cost) | Q10: Annual growth | R10: - | S10: - | T10: - | U10: buffer | V10: Annual growth | W10: - | X10: - | Y10: - | Z10: buffer | AA10: Annual growth | AB10: - | AC10: - | AD10: - | AE10: buffer | AF10: Annual growth | AG10: - | AH10: - | AI10: - | AJ10: buffer
B11: coa | C11: rod | D11: Pre-tax price | Road | Coal | E11: $/GJ | F11: Prices_dom (base year), then growth | G11: mit.sp.coa | H11: mit.pbt.coa.rod | J11: =INDEX(Mapping!$C$5:$C$20,MATCH($C11,Mapping!$A$5:$A$20,0)) | K11: =INDEX(Mapping!$D$5:$D$20,MATCH($C11,Mapping!$A$5:$A$20,0)) | L11: =INDEX(Mapping!$C$24:$C$31,MATCH($B11,Mapping!$A$24:$A$31,0)) | M11: =INDEX(Mapping!$D$24:$D$31,MATCH($B11,Mapping!$A$24:$A$31,0)) | N11: =$B11&"."&IF(INDEX(Mapping!$E$24:$E$31,MATCH($B11,Mapping!$A$24:$A$31,0))="sub",INDEX(Mapping!$F$5:$F$20,MATCH($C11,Mapping!$A$5:$A$20,0)),"all") | O11: =INDEX(Mapping!$E$5:$E$20,MATCH($C11,Mapping!$A$5:$A$20,0)) | P11: =INDEX(Mapping!$G$24:$G$31,MATCH($B11,Mapping!$A$24:$A$31,0)) | Q11: 0 | V11: =Q11 | AA11: =Q11 | AF11: =Q11 | AL11: =INDEX(Prices_dom!$A$6:$CU$2000,MATCH(Settings!$C$4&AL$5,Prices_dom!$A$6:$A$2000,0),MATCH("mit.sp."&$N11,Prices_dom!$A$5:$CU$5,0))/$P11 | AM11: =AL11*(1+INDEX($Q11:$AJ11,1,(AM$4-1)*5+1)) | AN11: =AM11*(1+INDEX($Q11:$AJ11,1,(AN$4-1)*5+1)) | AO11: =AN11*(1+INDEX($Q11:$AJ11,1,(AO$4-1)*5+1)) | AP11: =AO11*(1+INDEX($Q11:$AJ11,1,(AP$4-1)*5+1)) | AQ11: =AP11*(1+INDEX($Q11:$AJ11,1,(AQ$4-1)*5+1)) | AR11: =AQ11*(1+INDEX($Q11:$AJ11,1,(AR$4-1)*5+1)) | AS11: =AR11*(1+INDEX($Q11:$AJ11,1,(AS$4-1)*5+1)) | AT11: =AS11*(1+INDEX($Q11:$AJ11,1,(AT$4-1)*5+1)) | ... AY11: =AX11*(1+INDEX($Q11:$AJ11,1,(AY$4-1)*5+1)) | BA11: =INDEX(Prices_dom!$A$6:$CU$2000,MATCH(Settings!$C$4&BA$5,Prices_dom!$A$6:$A$2000,0),MATCH("mit.sp."&$N11,Prices_dom!$A$5:$CU$5,0))/$P11 | BB11: =BA11*(1+INDEX($Q11:$AJ11,1,(BB$4-1)*5+1)) | BC11: =BB11*(1+INDEX($Q11:$AJ11,1,(BC$4-1)*5+1)) | BD11: =BC11*(1+INDEX($Q11:$AJ11,1,(BD$4-1)*5+1)) | BE11: =BD11*(1+INDEX($Q11:$AJ11,1,(BE$4-1)*5+1)) | BF11: =BE11*(1+INDEX($Q11:$AJ11,1,(BF$4-1)*5+1)) | BG11: =BF11*(1+INDEX($Q11:$AJ11,1,(BG$4-1)*5+1)) | BH11: =BG11*(1+INDEX($Q11:$AJ11,1,(BH$4-1)*5+1)) | BI11: =BH11*(1+INDEX($Q11:$AJ11,1,(BI$4-1)*5+1)) | ... BN11: =BM11*(1+INDEX($Q11:$AJ11,1,(BN$4-1)*5+1))
B12: nga | C12: rod | D12: Pre-tax price | Road | Natural gas | E12: $/GJ | F12: Prices_dom (base year), then growth | G12: mit.sp.nga | H12: mit.pbt.nga.rod | J12: =INDEX(Mapping!$C$5:$C$20,MATCH($C12,Mapping!$A$5:$A$20,0)) | K12: =INDEX(Mapping!$D$5:$D$20,MATCH($C12,Mapping!$A$5:$A$20,0)) | L12: =INDEX(Mapping!$C$24:$C$31,MATCH($B12,Mapping!$A$24:$A$31,0)) | M12: =INDEX(Mapping!$D$24:$D$31,MATCH($B12,Mapping!$A$24:$A$31,0)) | N12: =$B12&"."&IF(INDEX(Mapping!$E$24:$E$31,MATCH($B12,Mapping!$A$24:$A$31,0))="sub",INDEX(Mapping!$F$5:$F$20,MATCH($C12,Mapping!$A$5:$A$20,0)),"all") | O12: =INDEX(Mapping!$E$5:$E$20,MATCH($C12,Mapping!$A$5:$A$20,0)) | P12: =INDEX(Mapping!$G$24:$G$31,MATCH($B12,Mapping!$A$24:$A$31,0)) | Q12: 0 | V12: =Q12 | AA12: =Q12 | AF12: =Q12 | AL12: =INDEX(Prices_dom!$A$6:$CU$2000,MATCH(Settings!$C$4&AL$5,Prices_dom!$A$6:$A$2000,0),MATCH("mit.sp."&$N12,Prices_dom!$A$5:$CU$5,0))/$P12 | AM12: =AL12*(1+INDEX($Q12:$AJ12,1,(AM$4-1)*5+1)) | AN12: =AM12*(1+INDEX($Q12:$AJ12,1,(AN$4-1)*5+1)) | AO12: =AN12*(1+INDEX($Q12:$AJ12,1,(AO$4-1)*5+1)) | AP12: =AO12*(1+INDEX($Q12:$AJ12,1,(AP$4-1)*5+1)) | AQ12: =AP12*(1+INDEX($Q12:$AJ12,1,(AQ$4-1)*5+1)) | AR12: =AQ12*(1+INDEX($Q12:$AJ12,1,(AR$4-1)*5+1)) | AS12: =AR12*(1+INDEX($Q12:$AJ12,1,(AS$4-1)*5+1)) | AT12: =AS12*(1+INDEX($Q12:$AJ12,1,(AT$4-1)*5+1)) | ... AY12: =AX12*(1+INDEX($Q12:$AJ12,1,(AY$4-1)*5+1)) | BA12: =INDEX(Prices_dom!$A$6:$CU$2000,MATCH(Settings!$C$4&BA$5,Prices_dom!$A$6:$A$2000,0),MATCH("mit.sp."&$N12,Prices_dom!$A$5:$CU$5,0))/$P12 | BB12: =BA12*(1+INDEX($Q12:$AJ12,1,(BB$4-1)*5+1)) | BC12: =BB12*(1+INDEX($Q12:$AJ12,1,(BC$4-1)*5+1)) | BD12: =BC12*(1+INDEX($Q12:$AJ12,1,(BD$4-1)*5+1)) | BE12: =BD12*(1+INDEX($Q12:$AJ12,1,(BE$4-1)*5+1)) | BF12: =BE12*(1+INDEX($Q12:$AJ12,1,(BF$4-1)*5+1)) | BG12: =BF12*(1+INDEX($Q12:$AJ12,1,(BG$4-1)*5+1)) | BH12: =BG12*(1+INDEX($Q12:$AJ12,1,(BH$4-1)*5+1)) | BI12: =BH12*(1+INDEX($Q12:$AJ12,1,(BI$4-1)*5+1)) | ... BN12: =BM12*(1+INDEX($Q12:$AJ12,1,(BN$4-1)*5+1))
B13: gso | C13: rod | D13: Pre-tax price | Road | Gasoline | E13: $/GJ | F13: Prices_dom (base year), then growth | G13: mit.sp.gso | H13: mit.pbt.gso.rod | J13: =INDEX(Mapping!$C$5:$C$20,MATCH($C13,Mapping!$A$5:$A$20,0)) | K13: =INDEX(Mapping!$D$5:$D$20,MATCH($C13,Mapping!$A$5:$A$20,0)) | L13: =INDEX(Mapping!$C$24:$C$31,MATCH($B13,Mapping!$A$24:$A$31,0)) | M13: =INDEX(Mapping!$D$24:$D$31,MATCH($B13,Mapping!$A$24:$A$31,0)) | N13: =$B13&"."&IF(INDEX(Mapping!$E$24:$E$31,MATCH($B13,Mapping!$A$24:$A$31,0))="sub",INDEX(Mapping!$F$5:$F$20,MATCH($C13,Mapping!$A$5:$A$20,0)),"all") | O13: =INDEX(Mapping!$E$5:$E$20,MATCH($C13,Mapping!$A$5:$A$20,0)) | P13: =INDEX(Mapping!$G$24:$G$31,MATCH($B13,Mapping!$A$24:$A$31,0)) | Q13: 0 | V13: =Q13 | AA13: =Q13 | AF13: =Q13 | AL13: =INDEX(Prices_dom!$A$6:$CU$2000,MATCH(Settings!$C$4&AL$5,Prices_dom!$A$6:$A$2000,0),MATCH("mit.sp."&$N13,Prices_dom!$A$5:$CU$5,0))/$P13 | AM13: =AL13*(1+INDEX($Q13:$AJ13,1,(AM$4-1)*5+1)) | AN13: =AM13*(1+INDEX($Q13:$AJ13,1,(AN$4-1)*5+1)) | AO13: =AN13*(1+INDEX($Q13:$AJ13,1,(AO$4-1)*5+1)) | AP13: =AO13*(1+INDEX($Q13:$AJ13,1,(AP$4-1)*5+1)) | AQ13: =AP13*(1+INDEX($Q13:$AJ13,1,(AQ$4-1)*5+1)) | AR13: =AQ13*(1+INDEX($Q13:$AJ13,1,(AR$4-1)*5+1)) | AS13: =AR13*(1+INDEX($Q13:$AJ13,1,(AS$4-1)*5+1)) | AT13: =AS13*(1+INDEX($Q13:$AJ13,1,(AT$4-1)*5+1)) | ... AY13: =AX13*(1+INDEX($Q13:$AJ13,1,(AY$4-1)*5+1)) | BA13: =INDEX(Prices_dom!$A$6:$CU$2000,MATCH(Settings!$C$4&BA$5,Prices_dom!$A$6:$A$2000,0),MATCH("mit.sp."&$N13,Prices_dom!$A$5:$CU$5,0))/$P13 | BB13: =BA13*(1+INDEX($Q13:$AJ13,1,(BB$4-1)*5+1)) | BC13: =BB13*(1+INDEX($Q13:$AJ13,1,(BC$4-1)*5+1)) | BD13: =BC13*(1+INDEX($Q13:$AJ13,1,(BD$4-1)*5+1)) | BE13: =BD13*(1+INDEX($Q13:$AJ13,1,(BE$4-1)*5+1)) | BF13: =BE13*(1+INDEX($Q13:$AJ13,1,(BF$4-1)*5+1)) | BG13: =BF13*(1+INDEX($Q13:$AJ13,1,(BG$4-1)*5+1)) | BH13: =BG13*(1+INDEX($Q13:$AJ13,1,(BH$4-1)*5+1)) | BI13: =BH13*(1+INDEX($Q13:$AJ13,1,(BI$4-1)*5+1)) | ... BN13: =BM13*(1+INDEX($Q13:$AJ13,1,(BN$4-1)*5+1))
B14: die | C14: rod | D14: Pre-tax price | Road | Diesel | E14: $/GJ | F14: Prices_dom (base year), then growth | G14: mit.sp.die | H14: mit.pbt.die.rod | J14: =INDEX(Mapping!$C$5:$C$20,MATCH($C14,Mapping!$A$5:$A$20,0)) | K14: =INDEX(Mapping!$D$5:$D$20,MATCH($C14,Mapping!$A$5:$A$20,0)) | L14: =INDEX(Mapping!$C$24:$C$31,MATCH($B14,Mapping!$A$24:$A$31,0)) | M14: =INDEX(Mapping!$D$24:$D$31,MATCH($B14,Mapping!$A$24:$A$31,0)) | N14: =$B14&"."&IF(INDEX(Mapping!$E$24:$E$31,MATCH($B14,Mapping!$A$24:$A$31,0))="sub",INDEX(Mapping!$F$5:$F$20,MATCH($C14,Mapping!$A$5:$A$20,0)),"all") | O14: =INDEX(Mapping!$E$5:$E$20,MATCH($C14,Mapping!$A$5:$A$20,0)) | P14: =INDEX(Mapping!$G$24:$G$31,MATCH($B14,Mapping!$A$24:$A$31,0)) | Q14: 0 | V14: =Q14 | AA14: =Q14 | AF14: =Q14 | AL14: =INDEX(Prices_dom!$A$6:$CU$2000,MATCH(Settings!$C$4&AL$5,Prices_dom!$A$6:$A$2000,0),MATCH("mit.sp."&$N14,Prices_dom!$A$5:$CU$5,0))/$P14 | AM14: =AL14*(1+INDEX($Q14:$AJ14,1,(AM$4-1)*5+1)) | AN14: =AM14*(1+INDEX($Q14:$AJ14,1,(AN$4-1)*5+1)) | AO14: =AN14*(1+INDEX($Q14:$AJ14,1,(AO$4-1)*5+1)) | AP14: =AO14*(1+INDEX($Q14:$AJ14,1,(AP$4-1)*5+1)) | AQ14: =AP14*(1+INDEX($Q14:$AJ14,1,(AQ$4-1)*5+1)) | AR14: =AQ14*(1+INDEX($Q14:$AJ14,1,(AR$4-1)*5+1)) | AS14: =AR14*(1+INDEX($Q14:$AJ14,1,(AS$4-1)*5+1)) | AT14: =AS14*(1+INDEX($Q14:$AJ14,1,(AT$4-1)*5+1)) | ... AY14: =AX14*(1+INDEX($Q14:$AJ14,1,(AY$4-1)*5+1)) | BA14: =INDEX(Prices_dom!$A$6:$CU$2000,MATCH(Settings!$C$4&BA$5,Prices_dom!$A$6:$A$2000,0),MATCH("mit.sp."&$N14,Prices_dom!$A$5:$CU$5,0))/$P14 | BB14: =BA14*(1+INDEX($Q14:$AJ14,1,(BB$4-1)*5+1)) | BC14: =BB14*(1+INDEX($Q14:$AJ14,1,(BC$4-1)*5+1)) | BD14: =BC14*(1+INDEX($Q14:$AJ14,1,(BD$4-1)*5+1)) | BE14: =BD14*(1+INDEX($Q14:$AJ14,1,(BE$4-1)*5+1)) | BF14: =BE14*(1+INDEX($Q14:$AJ14,1,(BF$4-1)*5+1)) | BG14: =BF14*(1+INDEX($Q14:$AJ14,1,(BG$4-1)*5+1)) | BH14: =BG14*(1+INDEX($Q14:$AJ14,1,(BH$4-1)*5+1)) | BI14: =BH14*(1+INDEX($Q14:$AJ14,1,(BI$4-1)*5+1)) | ... BN14: =BM14*(1+INDEX($Q14:$AJ14,1,(BN$4-1)*5+1))
B15: lpg | C15: rod | D15: Pre-tax price | Road | LPG | E15: $/GJ | F15: Prices_dom (base year), then growth | G15: mit.sp.lpg | H15: mit.pbt.lpg.rod | J15: =INDEX(Mapping!$C$5:$C$20,MATCH($C15,Mapping!$A$5:$A$20,0)) | K15: =INDEX(Mapping!$D$5:$D$20,MATCH($C15,Mapping!$A$5:$A$20,0)) | L15: =INDEX(Mapping!$C$24:$C$31,MATCH($B15,Mapping!$A$24:$A$31,0)) | M15: =INDEX(Mapping!$D$24:$D$31,MATCH($B15,Mapping!$A$24:$A$31,0)) | N15: =$B15&"."&IF(INDEX(Mapping!$E$24:$E$31,MATCH($B15,Mapping!$A$24:$A$31,0))="sub",INDEX(Mapping!$F$5:$F$20,MATCH($C15,Mapping!$A$5:$A$20,0)),"all") | O15: =INDEX(Mapping!$E$5:$E$20,MATCH($C15,Mapping!$A$5:$A$20,0)) | P15: =INDEX(Mapping!$G$24:$G$31,MATCH($B15,Mapping!$A$24:$A$31,0)) | Q15: 0 | V15: =Q15 | AA15: =Q15 | AF15: =Q15 | AL15: =INDEX(Prices_dom!$A$6:$CU$2000,MATCH(Settings!$C$4&AL$5,Prices_dom!$A$6:$A$2000,0),MATCH("mit.sp."&$N15,Prices_dom!$A$5:$CU$5,0))/$P15 | AM15: =AL15*(1+INDEX($Q15:$AJ15,1,(AM$4-1)*5+1)) | AN15: =AM15*(1+INDEX($Q15:$AJ15,1,(AN$4-1)*5+1)) | AO15: =AN15*(1+INDEX($Q15:$AJ15,1,(AO$4-1)*5+1)) | AP15: =AO15*(1+INDEX($Q15:$AJ15,1,(AP$4-1)*5+1)) | AQ15: =AP15*(1+INDEX($Q15:$AJ15,1,(AQ$4-1)*5+1)) | AR15: =AQ15*(1+INDEX($Q15:$AJ15,1,(AR$4-1)*5+1)) | AS15: =AR15*(1+INDEX($Q15:$AJ15,1,(AS$4-1)*5+1)) | AT15: =AS15*(1+INDEX($Q15:$AJ15,1,(AT$4-1)*5+1)) | ... AY15: =AX15*(1+INDEX($Q15:$AJ15,1,(AY$4-1)*5+1)) | BA15: =INDEX(Prices_dom!$A$6:$CU$2000,MATCH(Settings!$C$4&BA$5,Prices_dom!$A$6:$A$2000,0),MATCH("mit.sp."&$N15,Prices_dom!$A$5:$CU$5,0))/$P15 | BB15: =BA15*(1+INDEX($Q15:$AJ15,1,(BB$4-1)*5+1)) | BC15: =BB15*(1+INDEX($Q15:$AJ15,1,(BC$4-1)*5+1)) | BD15: =BC15*(1+INDEX($Q15:$AJ15,1,(BD$4-1)*5+1)) | BE15: =BD15*(1+INDEX($Q15:$AJ15,1,(BE$4-1)*5+1)) | BF15: =BE15*(1+INDEX($Q15:$AJ15,1,(BF$4-1)*5+1)) | BG15: =BF15*(1+INDEX($Q15:$AJ15,1,(BG$4-1)*5+1)) | BH15: =BG15*(1+INDEX($Q15:$AJ15,1,(BH$4-1)*5+1)) | BI15: =BH15*(1+INDEX($Q15:$AJ15,1,(BI$4-1)*5+1)) | ... BN15: =BM15*(1+INDEX($Q15:$AJ15,1,(BN$4-1)*5+1))
B16: ker | C16: rod | D16: Pre-tax price | Road | Kerosene | E16: $/GJ | F16: Prices_dom (base year), then growth | G16: mit.sp.ker | H16: mit.pbt.ker.rod | J16: =INDEX(Mapping!$C$5:$C$20,MATCH($C16,Mapping!$A$5:$A$20,0)) | K16: =INDEX(Mapping!$D$5:$D$20,MATCH($C16,Mapping!$A$5:$A$20,0)) | L16: =INDEX(Mapping!$C$24:$C$31,MATCH($B16,Mapping!$A$24:$A$31,0)) | M16: =INDEX(Mapping!$D$24:$D$31,MATCH($B16,Mapping!$A$24:$A$31,0)) | N16: =$B16&"."&IF(INDEX(Mapping!$E$24:$E$31,MATCH($B16,Mapping!$A$24:$A$31,0))="sub",INDEX(Mapping!$F$5:$F$20,MATCH($C16,Mapping!$A$5:$A$20,0)),"all") | O16: =INDEX(Mapping!$E$5:$E$20,MATCH($C16,Mapping!$A$5:$A$20,0)) | P16: =INDEX(Mapping!$G$24:$G$31,MATCH($B16,Mapping!$A$24:$A$31,0)) | Q16: 0 | V16: =Q16 | AA16: =Q16 | AF16: =Q16 | AL16: =INDEX(Prices_dom!$A$6:$CU$2000,MATCH(Settings!$C$4&AL$5,Prices_dom!$A$6:$A$2000,0),MATCH("mit.sp."&$N16,Prices_dom!$A$5:$CU$5,0))/$P16 | AM16: =AL16*(1+INDEX($Q16:$AJ16,1,(AM$4-1)*5+1)) | AN16: =AM16*(1+INDEX($Q16:$AJ16,1,(AN$4-1)*5+1)) | AO16: =AN16*(1+INDEX($Q16:$AJ16,1,(AO$4-1)*5+1)) | AP16: =AO16*(1+INDEX($Q16:$AJ16,1,(AP$4-1)*5+1)) | AQ16: =AP16*(1+INDEX($Q16:$AJ16,1,(AQ$4-1)*5+1)) | AR16: =AQ16*(1+INDEX($Q16:$AJ16,1,(AR$4-1)*5+1)) | AS16: =AR16*(1+INDEX($Q16:$AJ16,1,(AS$4-1)*5+1)) | AT16: =AS16*(1+INDEX($Q16:$AJ16,1,(AT$4-1)*5+1)) | ... AY16: =AX16*(1+INDEX($Q16:$AJ16,1,(AY$4-1)*5+1)) | BA16: =INDEX(Prices_dom!$A$6:$CU$2000,MATCH(Settings!$C$4&BA$5,Prices_dom!$A$6:$A$2000,0),MATCH("mit.sp."&$N16,Prices_dom!$A$5:$CU$5,0))/$P16 | BB16: =BA16*(1+INDEX($Q16:$AJ16,1,(BB$4-1)*5+1)) | BC16: =BB16*(1+INDEX($Q16:$AJ16,1,(BC$4-1)*5+1)) | BD16: =BC16*(1+INDEX($Q16:$AJ16,1,(BD$4-1)*5+1)) | BE16: =BD16*(1+INDEX($Q16:$AJ16,1,(BE$4-1)*5+1)) | BF16: =BE16*(1+INDEX($Q16:$AJ16,1,(BF$4-1)*5+1)) | BG16: =BF16*(1+INDEX($Q16:$AJ16,1,(BG$4-1)*5+1)) | BH16: =BG16*(1+INDEX($Q16:$AJ16,1,(BH$4-1)*5+1)) | BI16: =BH16*(1+INDEX($Q16:$AJ16,1,(BI$4-1)*5+1)) | ... BN16: =BM16*(1+INDEX($Q16:$AJ16,1,(BN$4-1)*5+1))
B17: oop | C17: rod | D17: Pre-tax price | Road | Other oil products | E17: $/GJ | F17: Prices_dom (base year), then growth | G17: mit.sp.oop | H17: mit.pbt.oop.rod | J17: =INDEX(Mapping!$C$5:$C$20,MATCH($C17,Mapping!$A$5:$A$20,0)) | K17: =INDEX(Mapping!$D$5:$D$20,MATCH($C17,Mapping!$A$5:$A$20,0)) | L17: =INDEX(Mapping!$C$24:$C$31,MATCH($B17,Mapping!$A$24:$A$31,0)) | M17: =INDEX(Mapping!$D$24:$D$31,MATCH($B17,Mapping!$A$24:$A$31,0)) | N17: =$B17&"."&IF(INDEX(Mapping!$E$24:$E$31,MATCH($B17,Mapping!$A$24:$A$31,0))="sub",INDEX(Mapping!$F$5:$F$20,MATCH($C17,Mapping!$A$5:$A$20,0)),"all") | O17: =INDEX(Mapping!$E$5:$E$20,MATCH($C17,Mapping!$A$5:$A$20,0)) | P17: =INDEX(Mapping!$G$24:$G$31,MATCH($B17,Mapping!$A$24:$A$31,0)) | Q17: 0 | V17: =Q17 | AA17: =Q17 | AF17: =Q17 | AL17: =INDEX(Prices_dom!$A$6:$CU$2000,MATCH(Settings!$C$4&AL$5,Prices_dom!$A$6:$A$2000,0),MATCH("mit.sp."&$N17,Prices_dom!$A$5:$CU$5,0))/$P17 | AM17: =AL17*(1+INDEX($Q17:$AJ17,1,(AM$4-1)*5+1)) | AN17: =AM17*(1+INDEX($Q17:$AJ17,1,(AN$4-1)*5+1)) | AO17: =AN17*(1+INDEX($Q17:$AJ17,1,(AO$4-1)*5+1)) | AP17: =AO17*(1+INDEX($Q17:$AJ17,1,(AP$4-1)*5+1)) | AQ17: =AP17*(1+INDEX($Q17:$AJ17,1,(AQ$4-1)*5+1)) | AR17: =AQ17*(1+INDEX($Q17:$AJ17,1,(AR$4-1)*5+1)) | AS17: =AR17*(1+INDEX($Q17:$AJ17,1,(AS$4-1)*5+1)) | AT17: =AS17*(1+INDEX($Q17:$AJ17,1,(AT$4-1)*5+1)) | ... AY17: =AX17*(1+INDEX($Q17:$AJ17,1,(AY$4-1)*5+1)) | BA17: =INDEX(Prices_dom!$A$6:$CU$2000,MATCH(Settings!$C$4&BA$5,Prices_dom!$A$6:$A$2000,0),MATCH("mit.sp."&$N17,Prices_dom!$A$5:$CU$5,0))/$P17 | BB17: =BA17*(1+INDEX($Q17:$AJ17,1,(BB$4-1)*5+1)) | BC17: =BB17*(1+INDEX($Q17:$AJ17,1,(BC$4-1)*5+1)) | BD17: =BC17*(1+INDEX($Q17:$AJ17,1,(BD$4-1)*5+1)) | BE17: =BD17*(1+INDEX($Q17:$AJ17,1,(BE$4-1)*5+1)) | BF17: =BE17*(1+INDEX($Q17:$AJ17,1,(BF$4-1)*5+1)) | BG17: =BF17*(1+INDEX($Q17:$AJ17,1,(BG$4-1)*5+1)) | BH17: =BG17*(1+INDEX($Q17:$AJ17,1,(BH$4-1)*5+1)) | BI17: =BH17*(1+INDEX($Q17:$AJ17,1,(BI$4-1)*5+1)) | ... BN17: =BM17*(1+INDEX($Q17:$AJ17,1,(BN$4-1)*5+1))
B18: bio | C18: rod | D18: Pre-tax price | Road | Biomass | E18: $/GJ | F18: Prices_dom (base year), then growth | G18: mit.sp.bio | H18: mit.pbt.bio.rod | J18: =INDEX(Mapping!$C$5:$C$20,MATCH($C18,Mapping!$A$5:$A$20,0)) | K18: =INDEX(Mapping!$D$5:$D$20,MATCH($C18,Mapping!$A$5:$A$20,0)) | L18: =INDEX(Mapping!$C$24:$C$31,MATCH($B18,Mapping!$A$24:$A$31,0)) | M18: =INDEX(Mapping!$D$24:$D$31,MATCH($B18,Mapping!$A$24:$A$31,0)) | N18: =$B18&"."&IF(INDEX(Mapping!$E$24:$E$31,MATCH($B18,Mapping!$A$24:$A$31,0))="sub",INDEX(Mapping!$F$5:$F$20,MATCH($C18,Mapping!$A$5:$A$20,0)),"all") | O18: =INDEX(Mapping!$E$5:$E$20,MATCH($C18,Mapping!$A$5:$A$20,0)) | P18: =INDEX(Mapping!$G$24:$G$31,MATCH($B18,Mapping!$A$24:$A$31,0)) | Q18: 0 | V18: =Q18 | AA18: =Q18 | AF18: =Q18 | AL18: =INDEX(Prices_dom!$A$6:$CU$2000,MATCH(Settings!$C$4&AL$5,Prices_dom!$A$6:$A$2000,0),MATCH("mit.sp."&$N18,Prices_dom!$A$5:$CU$5,0))/$P18 | AM18: =AL18*(1+INDEX($Q18:$AJ18,1,(AM$4-1)*5+1)) | AN18: =AM18*(1+INDEX($Q18:$AJ18,1,(AN$4-1)*5+1)) | AO18: =AN18*(1+INDEX($Q18:$AJ18,1,(AO$4-1)*5+1)) | AP18: =AO18*(1+INDEX($Q18:$AJ18,1,(AP$4-1)*5+1)) | AQ18: =AP18*(1+INDEX($Q18:$AJ18,1,(AQ$4-1)*5+1)) | AR18: =AQ18*(1+INDEX($Q18:$AJ18,1,(AR$4-1)*5+1)) | AS18: =AR18*(1+INDEX($Q18:$AJ18,1,(AS$4-1)*5+1)) | AT18: =AS18*(1+INDEX($Q18:$AJ18,1,(AT$4-1)*5+1)) | ... AY18: =AX18*(1+INDEX($Q18:$AJ18,1,(AY$4-1)*5+1)) | BA18: =INDEX(Prices_dom!$A$6:$CU$2000,MATCH(Settings!$C$4&BA$5,Prices_dom!$A$6:$A$2000,0),MATCH("mit.sp."&$N18,Prices_dom!$A$5:$CU$5,0))/$P18 | BB18: =BA18*(1+INDEX($Q18:$AJ18,1,(BB$4-1)*5+1)) | BC18: =BB18*(1+INDEX($Q18:$AJ18,1,(BC$4-1)*5+1)) | BD18: =BC18*(1+INDEX($Q18:$AJ18,1,(BD$4-1)*5+1)) | BE18: =BD18*(1+INDEX($Q18:$AJ18,1,(BE$4-1)*5+1)) | BF18: =BE18*(1+INDEX($Q18:$AJ18,1,(BF$4-1)*5+1)) | BG18: =BF18*(1+INDEX($Q18:$AJ18,1,(BG$4-1)*5+1)) | BH18: =BG18*(1+INDEX($Q18:$AJ18,1,(BH$4-1)*5+1)) | BI18: =BH18*(1+INDEX($Q18:$AJ18,1,(BI$4-1)*5+1)) | ... BN18: =BM18*(1+INDEX($Q18:$AJ18,1,(BN$4-1)*5+1))
B19: coa | C19: ral | D19: Pre-tax price | Rail | Coal | E19: $/GJ | F19: Prices_dom (base year), then growth | G19: mit.sp.coa | H19: mit.pbt.coa.ral | J19: =INDEX(Mapping!$C$5:$C$20,MATCH($C19,Mapping!$A$5:$A$20,0)) | K19: =INDEX(Mapping!$D$5:$D$20,MATCH($C19,Mapping!$A$5:$A$20,0)) | L19: =INDEX(Mapping!$C$24:$C$31,MATCH($B19,Mapping!$A$24:$A$31,0)) | M19: =INDEX(Mapping!$D$24:$D$31,MATCH($B19,Mapping!$A$24:$A$31,0)) | N19: =$B19&"."&IF(INDEX(Mapping!$E$24:$E$31,MATCH($B19,Mapping!$A$24:$A$31,0))="sub",INDEX(Mapping!$F$5:$F$20,MATCH($C19,Mapping!$A$5:$A$20,0)),"all") | O19: =INDEX(Mapping!$E$5:$E$20,MATCH($C19,Mapping!$A$5:$A$20,0)) | P19: =INDEX(Mapping!$G$24:$G$31,MATCH($B19,Mapping!$A$24:$A$31,0)) | Q19: 0 | V19: =Q19 | AA19: =Q19 | AF19: =Q19 | AL19: =INDEX(Prices_dom!$A$6:$CU$2000,MATCH(Settings!$C$4&AL$5,Prices_dom!$A$6:$A$2000,0),MATCH("mit.sp."&$N19,Prices_dom!$A$5:$CU$5,0))/$P19 | AM19: =AL19*(1+INDEX($Q19:$AJ19,1,(AM$4-1)*5+1)) | AN19: =AM19*(1+INDEX($Q19:$AJ19,1,(AN$4-1)*5+1)) | AO19: =AN19*(1+INDEX($Q19:$AJ19,1,(AO$4-1)*5+1)) | AP19: =AO19*(1+INDEX($Q19:$AJ19,1,(AP$4-1)*5+1)) | AQ19: =AP19*(1+INDEX($Q19:$AJ19,1,(AQ$4-1)*5+1)) | AR19: =AQ19*(1+INDEX($Q19:$AJ19,1,(AR$4-1)*5+1)) | AS19: =AR19*(1+INDEX($Q19:$AJ19,1,(AS$4-1)*5+1)) | AT19: =AS19*(1+INDEX($Q19:$AJ19,1,(AT$4-1)*5+1)) | ... AY19: =AX19*(1+INDEX($Q19:$AJ19,1,(AY$4-1)*5+1)) | BA19: =INDEX(Prices_dom!$A$6:$CU$2000,MATCH(Settings!$C$4&BA$5,Prices_dom!$A$6:$A$2000,0),MATCH("mit.sp."&$N19,Prices_dom!$A$5:$CU$5,0))/$P19 | BB19: =BA19*(1+INDEX($Q19:$AJ19,1,(BB$4-1)*5+1)) | BC19: =BB19*(1+INDEX($Q19:$AJ19,1,(BC$4-1)*5+1)) | BD19: =BC19*(1+INDEX($Q19:$AJ19,1,(BD$4-1)*5+1)) | BE19: =BD19*(1+INDEX($Q19:$AJ19,1,(BE$4-1)*5+1)) | BF19: =BE19*(1+INDEX($Q19:$AJ19,1,(BF$4-1)*5+1)) | BG19: =BF19*(1+INDEX($Q19:$AJ19,1,(BG$4-1)*5+1)) | BH19: =BG19*(1+INDEX($Q19:$AJ19,1,(BH$4-1)*5+1)) | BI19: =BH19*(1+INDEX($Q19:$AJ19,1,(BI$4-1)*5+1)) | ... BN19: =BM19*(1+INDEX($Q19:$AJ19,1,(BN$4-1)*5+1))
B20: nga | C20: ral | D20: Pre-tax price | Rail | Natural gas | E20: $/GJ | F20: Prices_dom (base year), then growth | G20: mit.sp.nga | H20: mit.pbt.nga.ral | J20: =INDEX(Mapping!$C$5:$C$20,MATCH($C20,Mapping!$A$5:$A$20,0)) | K20: =INDEX(Mapping!$D$5:$D$20,MATCH($C20,Mapping!$A$5:$A$20,0)) | L20: =INDEX(Mapping!$C$24:$C$31,MATCH($B20,Mapping!$A$24:$A$31,0)) | M20: =INDEX(Mapping!$D$24:$D$31,MATCH($B20,Mapping!$A$24:$A$31,0)) | N20: =$B20&"."&IF(INDEX(Mapping!$E$24:$E$31,MATCH($B20,Mapping!$A$24:$A$31,0))="sub",INDEX(Mapping!$F$5:$F$20,MATCH($C20,Mapping!$A$5:$A$20,0)),"all") | O20: =INDEX(Mapping!$E$5:$E$20,MATCH($C20,Mapping!$A$5:$A$20,0)) | P20: =INDEX(Mapping!$G$24:$G$31,MATCH($B20,Mapping!$A$24:$A$31,0)) | Q20: 0 | V20: =Q20 | AA20: =Q20 | AF20: =Q20 | AL20: =INDEX(Prices_dom!$A$6:$CU$2000,MATCH(Settings!$C$4&AL$5,Prices_dom!$A$6:$A$2000,0),MATCH("mit.sp."&$N20,Prices_dom!$A$5:$CU$5,0))/$P20 | AM20: =AL20*(1+INDEX($Q20:$AJ20,1,(AM$4-1)*5+1)) | AN20: =AM20*(1+INDEX($Q20:$AJ20,1,(AN$4-1)*5+1)) | AO20: =AN20*(1+INDEX($Q20:$AJ20,1,(AO$4-1)*5+1)) | AP20: =AO20*(1+INDEX($Q20:$AJ20,1,(AP$4-1)*5+1)) | AQ20: =AP20*(1+INDEX($Q20:$AJ20,1,(AQ$4-1)*5+1)) | AR20: =AQ20*(1+INDEX($Q20:$AJ20,1,(AR$4-1)*5+1)) | AS20: =AR20*(1+INDEX($Q20:$AJ20,1,(AS$4-1)*5+1)) | AT20: =AS20*(1+INDEX($Q20:$AJ20,1,(AT$4-1)*5+1)) | ... AY20: =AX20*(1+INDEX($Q20:$AJ20,1,(AY$4-1)*5+1)) | BA20: =INDEX(Prices_dom!$A$6:$CU$2000,MATCH(Settings!$C$4&BA$5,Prices_dom!$A$6:$A$2000,0),MATCH("mit.sp."&$N20,Prices_dom!$A$5:$CU$5,0))/$P20 | BB20: =BA20*(1+INDEX($Q20:$AJ20,1,(BB$4-1)*5+1)) | BC20: =BB20*(1+INDEX($Q20:$AJ20,1,(BC$4-1)*5+1)) | BD20: =BC20*(1+INDEX($Q20:$AJ20,1,(BD$4-1)*5+1)) | BE20: =BD20*(1+INDEX($Q20:$AJ20,1,(BE$4-1)*5+1)) | BF20: =BE20*(1+INDEX($Q20:$AJ20,1,(BF$4-1)*5+1)) | BG20: =BF20*(1+INDEX($Q20:$AJ20,1,(BG$4-1)*5+1)) | BH20: =BG20*(1+INDEX($Q20:$AJ20,1,(BH$4-1)*5+1)) | BI20: =BH20*(1+INDEX($Q20:$AJ20,1,(BI$4-1)*5+1)) | ... BN20: =BM20*(1+INDEX($Q20:$AJ20,1,(BN$4-1)*5+1))
B21: gso | C21: ral | D21: Pre-tax price | Rail | Gasoline | E21: $/GJ | F21: Prices_dom (base year), then growth | G21: mit.sp.gso | H21: mit.pbt.gso.ral | J21: =INDEX(Mapping!$C$5:$C$20,MATCH($C21,Mapping!$A$5:$A$20,0)) | K21: =INDEX(Mapping!$D$5:$D$20,MATCH($C21,Mapping!$A$5:$A$20,0)) | L21: =INDEX(Mapping!$C$24:$C$31,MATCH($B21,Mapping!$A$24:$A$31,0)) | M21: =INDEX(Mapping!$D$24:$D$31,MATCH($B21,Mapping!$A$24:$A$31,0)) | N21: =$B21&"."&IF(INDEX(Mapping!$E$24:$E$31,MATCH($B21,Mapping!$A$24:$A$31,0))="sub",INDEX(Mapping!$F$5:$F$20,MATCH($C21,Mapping!$A$5:$A$20,0)),"all") | O21: =INDEX(Mapping!$E$5:$E$20,MATCH($C21,Mapping!$A$5:$A$20,0)) | P21: =INDEX(Mapping!$G$24:$G$31,MATCH($B21,Mapping!$A$24:$A$31,0)) | Q21: 0 | V21: =Q21 | AA21: =Q21 | AF21: =Q21 | AL21: =INDEX(Prices_dom!$A$6:$CU$2000,MATCH(Settings!$C$4&AL$5,Prices_dom!$A$6:$A$2000,0),MATCH("mit.sp."&$N21,Prices_dom!$A$5:$CU$5,0))/$P21 | AM21: =AL21*(1+INDEX($Q21:$AJ21,1,(AM$4-1)*5+1)) | AN21: =AM21*(1+INDEX($Q21:$AJ21,1,(AN$4-1)*5+1)) | AO21: =AN21*(1+INDEX($Q21:$AJ21,1,(AO$4-1)*5+1)) | AP21: =AO21*(1+INDEX($Q21:$AJ21,1,(AP$4-1)*5+1)) | AQ21: =AP21*(1+INDEX($Q21:$AJ21,1,(AQ$4-1)*5+1)) | AR21: =AQ21*(1+INDEX($Q21:$AJ21,1,(AR$4-1)*5+1)) | AS21: =AR21*(1+INDEX($Q21:$AJ21,1,(AS$4-1)*5+1)) | AT21: =AS21*(1+INDEX($Q21:$AJ21,1,(AT$4-1)*5+1)) | ... AY21: =AX21*(1+INDEX($Q21:$AJ21,1,(AY$4-1)*5+1)) | BA21: =INDEX(Prices_dom!$A$6:$CU$2000,MATCH(Settings!$C$4&BA$5,Prices_dom!$A$6:$A$2000,0),MATCH("mit.sp."&$N21,Prices_dom!$A$5:$CU$5,0))/$P21 | BB21: =BA21*(1+INDEX($Q21:$AJ21,1,(BB$4-1)*5+1)) | BC21: =BB21*(1+INDEX($Q21:$AJ21,1,(BC$4-1)*5+1)) | BD21: =BC21*(1+INDEX($Q21:$AJ21,1,(BD$4-1)*5+1)) | BE21: =BD21*(1+INDEX($Q21:$AJ21,1,(BE$4-1)*5+1)) | BF21: =BE21*(1+INDEX($Q21:$AJ21,1,(BF$4-1)*5+1)) | BG21: =BF21*(1+INDEX($Q21:$AJ21,1,(BG$4-1)*5+1)) | BH21: =BG21*(1+INDEX($Q21:$AJ21,1,(BH$4-1)*5+1)) | BI21: =BH21*(1+INDEX($Q21:$AJ21,1,(BI$4-1)*5+1)) | ... BN21: =BM21*(1+INDEX($Q21:$AJ21,1,(BN$4-1)*5+1))
B22: die | C22: ral | D22: Pre-tax price | Rail | Diesel | E22: $/GJ | F22: Prices_dom (base year), then growth | G22: mit.sp.die | H22: mit.pbt.die.ral | J22: =INDEX(Mapping!$C$5:$C$20,MATCH($C22,Mapping!$A$5:$A$20,0)) | K22: =INDEX(Mapping!$D$5:$D$20,MATCH($C22,Mapping!$A$5:$A$20,0)) | L22: =INDEX(Mapping!$C$24:$C$31,MATCH($B22,Mapping!$A$24:$A$31,0)) | M22: =INDEX(Mapping!$D$24:$D$31,MATCH($B22,Mapping!$A$24:$A$31,0)) | N22: =$B22&"."&IF(INDEX(Mapping!$E$24:$E$31,MATCH($B22,Mapping!$A$24:$A$31,0))="sub",INDEX(Mapping!$F$5:$F$20,MATCH($C22,Mapping!$A$5:$A$20,0)),"all") | O22: =INDEX(Mapping!$E$5:$E$20,MATCH($C22,Mapping!$A$5:$A$20,0)) | P22: =INDEX(Mapping!$G$24:$G$31,MATCH($B22,Mapping!$A$24:$A$31,0)) | Q22: 0 | V22: =Q22 | AA22: =Q22 | AF22: =Q22 | AL22: =INDEX(Prices_dom!$A$6:$CU$2000,MATCH(Settings!$C$4&AL$5,Prices_dom!$A$6:$A$2000,0),MATCH("mit.sp."&$N22,Prices_dom!$A$5:$CU$5,0))/$P22 | AM22: =AL22*(1+INDEX($Q22:$AJ22,1,(AM$4-1)*5+1)) | AN22: =AM22*(1+INDEX($Q22:$AJ22,1,(AN$4-1)*5+1)) | AO22: =AN22*(1+INDEX($Q22:$AJ22,1,(AO$4-1)*5+1)) | AP22: =AO22*(1+INDEX($Q22:$AJ22,1,(AP$4-1)*5+1)) | AQ22: =AP22*(1+INDEX($Q22:$AJ22,1,(AQ$4-1)*5+1)) | AR22: =AQ22*(1+INDEX($Q22:$AJ22,1,(AR$4-1)*5+1)) | AS22: =AR22*(1+INDEX($Q22:$AJ22,1,(AS$4-1)*5+1)) | AT22: =AS22*(1+INDEX($Q22:$AJ22,1,(AT$4-1)*5+1)) | ... AY22: =AX22*(1+INDEX($Q22:$AJ22,1,(AY$4-1)*5+1)) | BA22: =INDEX(Prices_dom!$A$6:$CU$2000,MATCH(Settings!$C$4&BA$5,Prices_dom!$A$6:$A$2000,0),MATCH("mit.sp."&$N22,Prices_dom!$A$5:$CU$5,0))/$P22 | BB22: =BA22*(1+INDEX($Q22:$AJ22,1,(BB$4-1)*5+1)) | BC22: =BB22*(1+INDEX($Q22:$AJ22,1,(BC$4-1)*5+1)) | BD22: =BC22*(1+INDEX($Q22:$AJ22,1,(BD$4-1)*5+1)) | BE22: =BD22*(1+INDEX($Q22:$AJ22,1,(BE$4-1)*5+1)) | BF22: =BE22*(1+INDEX($Q22:$AJ22,1,(BF$4-1)*5+1)) | BG22: =BF22*(1+INDEX($Q22:$AJ22,1,(BG$4-1)*5+1)) | BH22: =BG22*(1+INDEX($Q22:$AJ22,1,(BH$4-1)*5+1)) | BI22: =BH22*(1+INDEX($Q22:$AJ22,1,(BI$4-1)*5+1)) | ... BN22: =BM22*(1+INDEX($Q22:$AJ22,1,(BN$4-1)*5+1))
... B138: bio | C138: oen | D138: Pre-tax price | Other energy use | Biomass | E138: $/GJ | F138: Prices_dom (base year), then growth | G138: mit.sp.bio | H138: mit.pbt.bio.oen | J138: =INDEX(Mapping!$C$5:$C$20,MATCH($C138,Mapping!$A$5:$A$20,0)) | K138: =INDEX(Mapping!$D$5:$D$20,MATCH($C138,Mapping!$A$5:$A$20,0)) | L138: =INDEX(Mapping!$C$24:$C$31,MATCH($B138,Mapping!$A$24:$A$31,0)) | M138: =INDEX(Mapping!$D$24:$D$31,MATCH($B138,Mapping!$A$24:$A$31,0)) | N138: =$B138&"."&IF(INDEX(Mapping!$E$24:$E$31,MATCH($B138,Mapping!$A$24:$A$31,0))="sub",INDEX(Mapping!$F$5:$F$20,MATCH($C138,Mapping!$A$5:$A$20,0)),"all") | O138: =INDEX(Mapping!$E$5:$E$20,MATCH($C138,Mapping!$A$5:$A$20,0)) | P138: =INDEX(Mapping!$G$24:$G$31,MATCH($B138,Mapping!$A$24:$A$31,0)) | Q138: 0 | V138: =Q138 | AA138: =Q138 | AF138: =Q138 | AL138: =INDEX(Prices_dom!$A$6:$CU$2000,MATCH(Settings!$C$4&AL$5,Prices_dom!$A$6:$A$2000,0),MATCH("mit.sp."&$N138,Prices_dom!$A$5:$CU$5,0))/$P138 | AM138: =AL138*(1+INDEX($Q138:$AJ138,1,(AM$4-1)*5+1)) | AN138: =AM138*(1+INDEX($Q138:$AJ138,1,(AN$4-1)*5+1)) | AO138: =AN138*(1+INDEX($Q138:$AJ138,1,(AO$4-1)*5+1)) | AP138: =AO138*(1+INDEX($Q138:$AJ138,1,(AP$4-1)*5+1)) | AQ138: =AP138*(1+INDEX($Q138:$AJ138,1,(AQ$4-1)*5+1)) | AR138: =AQ138*(1+INDEX($Q138:$AJ138,1,(AR$4-1)*5+1)) | AS138: =AR138*(1+INDEX($Q138:$AJ138,1,(AS$4-1)*5+1)) | AT138: =AS138*(1+INDEX($Q138:$AJ138,1,(AT$4-1)*5+1)) | ... AY138: =AX138*(1+INDEX($Q138:$AJ138,1,(AY$4-1)*5+1)) | BA138: =INDEX(Prices_dom!$A$6:$CU$2000,MATCH(Settings!$C$4&BA$5,Prices_dom!$A$6:$A$2000,0),MATCH("mit.sp."&$N138,Prices_dom!$A$5:$CU$5,0))/$P138 | BB138: =BA138*(1+INDEX($Q138:$AJ138,1,(BB$4-1)*5+1)) | BC138: =BB138*(1+INDEX($Q138:$AJ138,1,(BC$4-1)*5+1)) | BD138: =BC138*(1+INDEX($Q138:$AJ138,1,(BD$4-1)*5+1)) | BE138: =BD138*(1+INDEX($Q138:$AJ138,1,(BE$4-1)*5+1)) | BF138: =BE138*(1+INDEX($Q138:$AJ138,1,(BF$4-1)*5+1)) | BG138: =BF138*(1+INDEX($Q138:$AJ138,1,(BG$4-1)*5+1)) | BH138: =BG138*(1+INDEX($Q138:$AJ138,1,(BH$4-1)*5+1)) | BI138: =BH138*(1+INDEX($Q138:$AJ138,1,(BI$4-1)*5+1)) | ... BN138: =BM138*(1+INDEX($Q138:$AJ138,1,(BN$4-1)*5+1))
A140: Tax: base tax + carbon price x EF x coverage | Q140: Base tax ($/GJ) | R140: EF (tCO2/GJ) | S140: Coverage | T140: - | U140: buffer | V140: Base tax ($/GJ) | W140: EF (tCO2/GJ) | X140: Coverage | Y140: - | Z140: buffer | AA140: Base tax ($/GJ) | AB140: EF (tCO2/GJ) | AC140: Coverage | AD140: - | AE140: buffer | AF140: Base tax ($/GJ) | AG140: EF (tCO2/GJ) | AH140: Coverage | AI140: - | AJ140: buffer
B141: coa | C141: rod | D141: Tax | Road | Coal | E141: $/GJ | F141: Prices_dom, EF_GHG, Mapping | G141: mit.rp.coa | H141: mit.tax.coa.rod | J141: =INDEX(Mapping!$C$5:$C$20,MATCH($C141,Mapping!$A$5:$A$20,0)) | K141: =INDEX(Mapping!$D$5:$D$20,MATCH($C141,Mapping!$A$5:$A$20,0)) | L141: =INDEX(Mapping!$C$24:$C$31,MATCH($B141,Mapping!$A$24:$A$31,0)) | M141: =INDEX(Mapping!$D$24:$D$31,MATCH($B141,Mapping!$A$24:$A$31,0)) | N141: =$B141&"."&IF(INDEX(Mapping!$E$24:$E$31,MATCH($B141,Mapping!$A$24:$A$31,0))="sub",INDEX(Mapping!$F$5:$F$20,MATCH($C141,Mapping!$A$5:$A$20,0)),"all") | O141: =INDEX(Mapping!$E$5:$E$20,MATCH($C141,Mapping!$A$5:$A$20,0)) | P141: =INDEX(Mapping!$G$24:$G$31,MATCH($B141,Mapping!$A$24:$A$31,0)) | Q141: =(INDEX(Prices_dom!$A$6:$CU$2000,MATCH(Settings!$C$4&Settings!$C$7,Prices_dom!$A$6:$A$2000,0),MATCH("mit.rp."&$N141,Prices_dom!$A$5:$CU$5,0))-INDEX(Prices_dom!$A$6:$CU$2000,MATCH(Settings!$C$4&Settings!$C$7,Prices_dom!$A$6:$A$2000,0),MATCH("mit.sp."&$N141,Prices_dom!$A$5:$CU$5,0)))/$P141 | R141: =INDEX(EF_GHG!$E$4:$E$1000,MATCH(Settings!$C$4&"|"&$B141&"|"&$O141,EF_GHG!$A$4:$A$1000,0)) | S141: =INDEX(Mapping!$G$5:$G$20,MATCH($C141,Mapping!$A$5:$A$20,0)) | V141: =Q141 | W141: =R141 | X141: =S141 | AA141: =Q141 | AB141: =R141 | AC141: =S141 | AF141: =Q141 | AG141: =R141 | AH141: =S141 | AL141: =INDEX($Q141:$AJ141,1,(AL$4-1)*5+1)+AL$8*INDEX($Q141:$AJ141,1,(AL$4-1)*5+2)*INDEX($Q141:$AJ141,1,(AL$4-1)*5+3) | AM141: =INDEX($Q141:$AJ141,1,(AM$4-1)*5+1)+AM$8*INDEX($Q141:$AJ141,1,(AM$4-1)*5+2)*INDEX($Q141:$AJ141,1,(AM$4-1)*5+3) | AN141: =INDEX($Q141:$AJ141,1,(AN$4-1)*5+1)+AN$8*INDEX($Q141:$AJ141,1,(AN$4-1)*5+2)*INDEX($Q141:$AJ141,1,(AN$4-1)*5+3) | AO141: =INDEX($Q141:$AJ141,1,(AO$4-1)*5+1)+AO$8*INDEX($Q141:$AJ141,1,(AO$4-1)*5+2)*INDEX($Q141:$AJ141,1,(AO$4-1)*5+3) | AP141: =INDEX($Q141:$AJ141,1,(AP$4-1)*5+1)+AP$8*INDEX($Q141:$AJ141,1,(AP$4-1)*5+2)*INDEX($Q141:$AJ141,1,(AP$4-1)*5+3) | AQ141: =INDEX($Q141:$AJ141,1,(AQ$4-1)*5+1)+AQ$8*INDEX($Q141:$AJ141,1,(AQ$4-1)*5+2)*INDEX($Q141:$AJ141,1,(AQ$4-1)*5+3) | AR141: =INDEX($Q141:$AJ141,1,(AR$4-1)*5+1)+AR$8*INDEX($Q141:$AJ141,1,(AR$4-1)*5+2)*INDEX($Q141:$AJ141,1,(AR$4-1)*5+3) | AS141: =INDEX($Q141:$AJ141,1,(AS$4-1)*5+1)+AS$8*INDEX($Q141:$AJ141,1,(AS$4-1)*5+2)*INDEX($Q141:$AJ141,1,(AS$4-1)*5+3) | ... AY141: =INDEX($Q141:$AJ141,1,(AY$4-1)*5+1)+AY$8*INDEX($Q141:$AJ141,1,(AY$4-1)*5+2)*INDEX($Q141:$AJ141,1,(AY$4-1)*5+3) | BA141: =INDEX($Q141:$AJ141,1,(BA$4-1)*5+1)+BA$8*INDEX($Q141:$AJ141,1,(BA$4-1)*5+2)*INDEX($Q141:$AJ141,1,(BA$4-1)*5+3) | BB141: =INDEX($Q141:$AJ141,1,(BB$4-1)*5+1)+BB$8*INDEX($Q141:$AJ141,1,(BB$4-1)*5+2)*INDEX($Q141:$AJ141,1,(BB$4-1)*5+3) | BC141: =INDEX($Q141:$AJ141,1,(BC$4-1)*5+1)+BC$8*INDEX($Q141:$AJ141,1,(BC$4-1)*5+2)*INDEX($Q141:$AJ141,1,(BC$4-1)*5+3) | BD141: =INDEX($Q141:$AJ141,1,(BD$4-1)*5+1)+BD$8*INDEX($Q141:$AJ141,1,(BD$4-1)*5+2)*INDEX($Q141:$AJ141,1,(BD$4-1)*5+3) | BE141: =INDEX($Q141:$AJ141,1,(BE$4-1)*5+1)+BE$8*INDEX($Q141:$AJ141,1,(BE$4-1)*5+2)*INDEX($Q141:$AJ141,1,(BE$4-1)*5+3) | BF141: =INDEX($Q141:$AJ141,1,(BF$4-1)*5+1)+BF$8*INDEX($Q141:$AJ141,1,(BF$4-1)*5+2)*INDEX($Q141:$AJ141,1,(BF$4-1)*5+3) | BG141: =INDEX($Q141:$AJ141,1,(BG$4-1)*5+1)+BG$8*INDEX($Q141:$AJ141,1,(BG$4-1)*5+2)*INDEX($Q141:$AJ141,1,(BG$4-1)*5+3) | BH141: =INDEX($Q141:$AJ141,1,(BH$4-1)*5+1)+BH$8*INDEX($Q141:$AJ141,1,(BH$4-1)*5+2)*INDEX($Q141:$AJ141,1,(BH$4-1)*5+3) | ... BN141: =INDEX($Q141:$AJ141,1,(BN$4-1)*5+1)+BN$8*INDEX($Q141:$AJ141,1,(BN$4-1)*5+2)*INDEX($Q141:$AJ141,1,(BN$4-1)*5+3)
B142: nga | C142: rod | D142: Tax | Road | Natural gas | E142: $/GJ | F142: Prices_dom, EF_GHG, Mapping | G142: mit.rp.nga | H142: mit.tax.nga.rod | J142: =INDEX(Mapping!$C$5:$C$20,MATCH($C142,Mapping!$A$5:$A$20,0)) | K142: =INDEX(Mapping!$D$5:$D$20,MATCH($C142,Mapping!$A$5:$A$20,0)) | L142: =INDEX(Mapping!$C$24:$C$31,MATCH($B142,Mapping!$A$24:$A$31,0)) | M142: =INDEX(Mapping!$D$24:$D$31,MATCH($B142,Mapping!$A$24:$A$31,0)) | N142: =$B142&"."&IF(INDEX(Mapping!$E$24:$E$31,MATCH($B142,Mapping!$A$24:$A$31,0))="sub",INDEX(Mapping!$F$5:$F$20,MATCH($C142,Mapping!$A$5:$A$20,0)),"all") | O142: =INDEX(Mapping!$E$5:$E$20,MATCH($C142,Mapping!$A$5:$A$20,0)) | P142: =INDEX(Mapping!$G$24:$G$31,MATCH($B142,Mapping!$A$24:$A$31,0)) | Q142: =(INDEX(Prices_dom!$A$6:$CU$2000,MATCH(Settings!$C$4&Settings!$C$7,Prices_dom!$A$6:$A$2000,0),MATCH("mit.rp."&$N142,Prices_dom!$A$5:$CU$5,0))-INDEX(Prices_dom!$A$6:$CU$2000,MATCH(Settings!$C$4&Settings!$C$7,Prices_dom!$A$6:$A$2000,0),MATCH("mit.sp."&$N142,Prices_dom!$A$5:$CU$5,0)))/$P142 | R142: =INDEX(EF_GHG!$E$4:$E$1000,MATCH(Settings!$C$4&"|"&$B142&"|"&$O142,EF_GHG!$A$4:$A$1000,0)) | S142: =INDEX(Mapping!$G$5:$G$20,MATCH($C142,Mapping!$A$5:$A$20,0)) | V142: =Q142 | W142: =R142 | X142: =S142 | AA142: =Q142 | AB142: =R142 | AC142: =S142 | AF142: =Q142 | AG142: =R142 | AH142: =S142 | AL142: =INDEX($Q142:$AJ142,1,(AL$4-1)*5+1)+AL$8*INDEX($Q142:$AJ142,1,(AL$4-1)*5+2)*INDEX($Q142:$AJ142,1,(AL$4-1)*5+3) | AM142: =INDEX($Q142:$AJ142,1,(AM$4-1)*5+1)+AM$8*INDEX($Q142:$AJ142,1,(AM$4-1)*5+2)*INDEX($Q142:$AJ142,1,(AM$4-1)*5+3) | AN142: =INDEX($Q142:$AJ142,1,(AN$4-1)*5+1)+AN$8*INDEX($Q142:$AJ142,1,(AN$4-1)*5+2)*INDEX($Q142:$AJ142,1,(AN$4-1)*5+3) | AO142: =INDEX($Q142:$AJ142,1,(AO$4-1)*5+1)+AO$8*INDEX($Q142:$AJ142,1,(AO$4-1)*5+2)*INDEX($Q142:$AJ142,1,(AO$4-1)*5+3) | AP142: =INDEX($Q142:$AJ142,1,(AP$4-1)*5+1)+AP$8*INDEX($Q142:$AJ142,1,(AP$4-1)*5+2)*INDEX($Q142:$AJ142,1,(AP$4-1)*5+3) | AQ142: =INDEX($Q142:$AJ142,1,(AQ$4-1)*5+1)+AQ$8*INDEX($Q142:$AJ142,1,(AQ$4-1)*5+2)*INDEX($Q142:$AJ142,1,(AQ$4-1)*5+3) | AR142: =INDEX($Q142:$AJ142,1,(AR$4-1)*5+1)+AR$8*INDEX($Q142:$AJ142,1,(AR$4-1)*5+2)*INDEX($Q142:$AJ142,1,(AR$4-1)*5+3) | AS142: =INDEX($Q142:$AJ142,1,(AS$4-1)*5+1)+AS$8*INDEX($Q142:$AJ142,1,(AS$4-1)*5+2)*INDEX($Q142:$AJ142,1,(AS$4-1)*5+3) | ... AY142: =INDEX($Q142:$AJ142,1,(AY$4-1)*5+1)+AY$8*INDEX($Q142:$AJ142,1,(AY$4-1)*5+2)*INDEX($Q142:$AJ142,1,(AY$4-1)*5+3) | BA142: =INDEX($Q142:$AJ142,1,(BA$4-1)*5+1)+BA$8*INDEX($Q142:$AJ142,1,(BA$4-1)*5+2)*INDEX($Q142:$AJ142,1,(BA$4-1)*5+3) | BB142: =INDEX($Q142:$AJ142,1,(BB$4-1)*5+1)+BB$8*INDEX($Q142:$AJ142,1,(BB$4-1)*5+2)*INDEX($Q142:$AJ142,1,(BB$4-1)*5+3) | BC142: =INDEX($Q142:$AJ142,1,(BC$4-1)*5+1)+BC$8*INDEX($Q142:$AJ142,1,(BC$4-1)*5+2)*INDEX($Q142:$AJ142,1,(BC$4-1)*5+3) | BD142: =INDEX($Q142:$AJ142,1,(BD$4-1)*5+1)+BD$8*INDEX($Q142:$AJ142,1,(BD$4-1)*5+2)*INDEX($Q142:$AJ142,1,(BD$4-1)*5+3) | BE142: =INDEX($Q142:$AJ142,1,(BE$4-1)*5+1)+BE$8*INDEX($Q142:$AJ142,1,(BE$4-1)*5+2)*INDEX($Q142:$AJ142,1,(BE$4-1)*5+3) | BF142: =INDEX($Q142:$AJ142,1,(BF$4-1)*5+1)+BF$8*INDEX($Q142:$AJ142,1,(BF$4-1)*5+2)*INDEX($Q142:$AJ142,1,(BF$4-1)*5+3) | BG142: =INDEX($Q142:$AJ142,1,(BG$4-1)*5+1)+BG$8*INDEX($Q142:$AJ142,1,(BG$4-1)*5+2)*INDEX($Q142:$AJ142,1,(BG$4-1)*5+3) | BH142: =INDEX($Q142:$AJ142,1,(BH$4-1)*5+1)+BH$8*INDEX($Q142:$AJ142,1,(BH$4-1)*5+2)*INDEX($Q142:$AJ142,1,(BH$4-1)*5+3) | ... BN142: =INDEX($Q142:$AJ142,1,(BN$4-1)*5+1)+BN$8*INDEX($Q142:$AJ142,1,(BN$4-1)*5+2)*INDEX($Q142:$AJ142,1,(BN$4-1)*5+3)
B143: gso | C143: rod | D143: Tax | Road | Gasoline | E143: $/GJ | F143: Prices_dom, EF_GHG, Mapping | G143: mit.rp.gso | H143: mit.tax.gso.rod | J143: =INDEX(Mapping!$C$5:$C$20,MATCH($C143,Mapping!$A$5:$A$20,0)) | K143: =INDEX(Mapping!$D$5:$D$20,MATCH($C143,Mapping!$A$5:$A$20,0)) | L143: =INDEX(Mapping!$C$24:$C$31,MATCH($B143,Mapping!$A$24:$A$31,0)) | M143: =INDEX(Mapping!$D$24:$D$31,MATCH($B143,Mapping!$A$24:$A$31,0)) | N143: =$B143&"."&IF(INDEX(Mapping!$E$24:$E$31,MATCH($B143,Mapping!$A$24:$A$31,0))="sub",INDEX(Mapping!$F$5:$F$20,MATCH($C143,Mapping!$A$5:$A$20,0)),"all") | O143: =INDEX(Mapping!$E$5:$E$20,MATCH($C143,Mapping!$A$5:$A$20,0)) | P143: =INDEX(Mapping!$G$24:$G$31,MATCH($B143,Mapping!$A$24:$A$31,0)) | Q143: =(INDEX(Prices_dom!$A$6:$CU$2000,MATCH(Settings!$C$4&Settings!$C$7,Prices_dom!$A$6:$A$2000,0),MATCH("mit.rp."&$N143,Prices_dom!$A$5:$CU$5,0))-INDEX(Prices_dom!$A$6:$CU$2000,MATCH(Settings!$C$4&Settings!$C$7,Prices_dom!$A$6:$A$2000,0),MATCH("mit.sp."&$N143,Prices_dom!$A$5:$CU$5,0)))/$P143 | R143: =INDEX(EF_GHG!$E$4:$E$1000,MATCH(Settings!$C$4&"|"&$B143&"|"&$O143,EF_GHG!$A$4:$A$1000,0)) | S143: =INDEX(Mapping!$G$5:$G$20,MATCH($C143,Mapping!$A$5:$A$20,0)) | V143: =Q143 | W143: =R143 | X143: =S143 | AA143: =Q143 | AB143: =R143 | AC143: =S143 | AF143: =Q143 | AG143: =R143 | AH143: =S143 | AL143: =INDEX($Q143:$AJ143,1,(AL$4-1)*5+1)+AL$8*INDEX($Q143:$AJ143,1,(AL$4-1)*5+2)*INDEX($Q143:$AJ143,1,(AL$4-1)*5+3) | AM143: =INDEX($Q143:$AJ143,1,(AM$4-1)*5+1)+AM$8*INDEX($Q143:$AJ143,1,(AM$4-1)*5+2)*INDEX($Q143:$AJ143,1,(AM$4-1)*5+3) | AN143: =INDEX($Q143:$AJ143,1,(AN$4-1)*5+1)+AN$8*INDEX($Q143:$AJ143,1,(AN$4-1)*5+2)*INDEX($Q143:$AJ143,1,(AN$4-1)*5+3) | AO143: =INDEX($Q143:$AJ143,1,(AO$4-1)*5+1)+AO$8*INDEX($Q143:$AJ143,1,(AO$4-1)*5+2)*INDEX($Q143:$AJ143,1,(AO$4-1)*5+3) | AP143: =INDEX($Q143:$AJ143,1,(AP$4-1)*5+1)+AP$8*INDEX($Q143:$AJ143,1,(AP$4-1)*5+2)*INDEX($Q143:$AJ143,1,(AP$4-1)*5+3) | AQ143: =INDEX($Q143:$AJ143,1,(AQ$4-1)*5+1)+AQ$8*INDEX($Q143:$AJ143,1,(AQ$4-1)*5+2)*INDEX($Q143:$AJ143,1,(AQ$4-1)*5+3) | AR143: =INDEX($Q143:$AJ143,1,(AR$4-1)*5+1)+AR$8*INDEX($Q143:$AJ143,1,(AR$4-1)*5+2)*INDEX($Q143:$AJ143,1,(AR$4-1)*5+3) | AS143: =INDEX($Q143:$AJ143,1,(AS$4-1)*5+1)+AS$8*INDEX($Q143:$AJ143,1,(AS$4-1)*5+2)*INDEX($Q143:$AJ143,1,(AS$4-1)*5+3) | ... AY143: =INDEX($Q143:$AJ143,1,(AY$4-1)*5+1)+AY$8*INDEX($Q143:$AJ143,1,(AY$4-1)*5+2)*INDEX($Q143:$AJ143,1,(AY$4-1)*5+3) | BA143: =INDEX($Q143:$AJ143,1,(BA$4-1)*5+1)+BA$8*INDEX($Q143:$AJ143,1,(BA$4-1)*5+2)*INDEX($Q143:$AJ143,1,(BA$4-1)*5+3) | BB143: =INDEX($Q143:$AJ143,1,(BB$4-1)*5+1)+BB$8*INDEX($Q143:$AJ143,1,(BB$4-1)*5+2)*INDEX($Q143:$AJ143,1,(BB$4-1)*5+3) | BC143: =INDEX($Q143:$AJ143,1,(BC$4-1)*5+1)+BC$8*INDEX($Q143:$AJ143,1,(BC$4-1)*5+2)*INDEX($Q143:$AJ143,1,(BC$4-1)*5+3) | BD143: =INDEX($Q143:$AJ143,1,(BD$4-1)*5+1)+BD$8*INDEX($Q143:$AJ143,1,(BD$4-1)*5+2)*INDEX($Q143:$AJ143,1,(BD$4-1)*5+3) | BE143: =INDEX($Q143:$AJ143,1,(BE$4-1)*5+1)+BE$8*INDEX($Q143:$AJ143,1,(BE$4-1)*5+2)*INDEX($Q143:$AJ143,1,(BE$4-1)*5+3) | BF143: =INDEX($Q143:$AJ143,1,(BF$4-1)*5+1)+BF$8*INDEX($Q143:$AJ143,1,(BF$4-1)*5+2)*INDEX($Q143:$AJ143,1,(BF$4-1)*5+3) | BG143: =INDEX($Q143:$AJ143,1,(BG$4-1)*5+1)+BG$8*INDEX($Q143:$AJ143,1,(BG$4-1)*5+2)*INDEX($Q143:$AJ143,1,(BG$4-1)*5+3) | BH143: =INDEX($Q143:$AJ143,1,(BH$4-1)*5+1)+BH$8*INDEX($Q143:$AJ143,1,(BH$4-1)*5+2)*INDEX($Q143:$AJ143,1,(BH$4-1)*5+3) | ... BN143: =INDEX($Q143:$AJ143,1,(BN$4-1)*5+1)+BN$8*INDEX($Q143:$AJ143,1,(BN$4-1)*5+2)*INDEX($Q143:$AJ143,1,(BN$4-1)*5+3)
B144: die | C144: rod | D144: Tax | Road | Diesel | E144: $/GJ | F144: Prices_dom, EF_GHG, Mapping | G144: mit.rp.die | H144: mit.tax.die.rod | J144: =INDEX(Mapping!$C$5:$C$20,MATCH($C144,Mapping!$A$5:$A$20,0)) | K144: =INDEX(Mapping!$D$5:$D$20,MATCH($C144,Mapping!$A$5:$A$20,0)) | L144: =INDEX(Mapping!$C$24:$C$31,MATCH($B144,Mapping!$A$24:$A$31,0)) | M144: =INDEX(Mapping!$D$24:$D$31,MATCH($B144,Mapping!$A$24:$A$31,0)) | N144: =$B144&"."&IF(INDEX(Mapping!$E$24:$E$31,MATCH($B144,Mapping!$A$24:$A$31,0))="sub",INDEX(Mapping!$F$5:$F$20,MATCH($C144,Mapping!$A$5:$A$20,0)),"all") | O144: =INDEX(Mapping!$E$5:$E$20,MATCH($C144,Mapping!$A$5:$A$20,0)) | P144: =INDEX(Mapping!$G$24:$G$31,MATCH($B144,Mapping!$A$24:$A$31,0)) | Q144: =(INDEX(Prices_dom!$A$6:$CU$2000,MATCH(Settings!$C$4&Settings!$C$7,Prices_dom!$A$6:$A$2000,0),MATCH("mit.rp."&$N144,Prices_dom!$A$5:$CU$5,0))-INDEX(Prices_dom!$A$6:$CU$2000,MATCH(Settings!$C$4&Settings!$C$7,Prices_dom!$A$6:$A$2000,0),MATCH("mit.sp."&$N144,Prices_dom!$A$5:$CU$5,0)))/$P144 | R144: =INDEX(EF_GHG!$E$4:$E$1000,MATCH(Settings!$C$4&"|"&$B144&"|"&$O144,EF_GHG!$A$4:$A$1000,0)) | S144: =INDEX(Mapping!$G$5:$G$20,MATCH($C144,Mapping!$A$5:$A$20,0)) | V144: =Q144 | W144: =R144 | X144: =S144 | AA144: =Q144 | AB144: =R144 | AC144: =S144 | AF144: =Q144 | AG144: =R144 | AH144: =S144 | AL144: =INDEX($Q144:$AJ144,1,(AL$4-1)*5+1)+AL$8*INDEX($Q144:$AJ144,1,(AL$4-1)*5+2)*INDEX($Q144:$AJ144,1,(AL$4-1)*5+3) | AM144: =INDEX($Q144:$AJ144,1,(AM$4-1)*5+1)+AM$8*INDEX($Q144:$AJ144,1,(AM$4-1)*5+2)*INDEX($Q144:$AJ144,1,(AM$4-1)*5+3) | AN144: =INDEX($Q144:$AJ144,1,(AN$4-1)*5+1)+AN$8*INDEX($Q144:$AJ144,1,(AN$4-1)*5+2)*INDEX($Q144:$AJ144,1,(AN$4-1)*5+3) | AO144: =INDEX($Q144:$AJ144,1,(AO$4-1)*5+1)+AO$8*INDEX($Q144:$AJ144,1,(AO$4-1)*5+2)*INDEX($Q144:$AJ144,1,(AO$4-1)*5+3) | AP144: =INDEX($Q144:$AJ144,1,(AP$4-1)*5+1)+AP$8*INDEX($Q144:$AJ144,1,(AP$4-1)*5+2)*INDEX($Q144:$AJ144,1,(AP$4-1)*5+3) | AQ144: =INDEX($Q144:$AJ144,1,(AQ$4-1)*5+1)+AQ$8*INDEX($Q144:$AJ144,1,(AQ$4-1)*5+2)*INDEX($Q144:$AJ144,1,(AQ$4-1)*5+3) | AR144: =INDEX($Q144:$AJ144,1,(AR$4-1)*5+1)+AR$8*INDEX($Q144:$AJ144,1,(AR$4-1)*5+2)*INDEX($Q144:$AJ144,1,(AR$4-1)*5+3) | AS144: =INDEX($Q144:$AJ144,1,(AS$4-1)*5+1)+AS$8*INDEX($Q144:$AJ144,1,(AS$4-1)*5+2)*INDEX($Q144:$AJ144,1,(AS$4-1)*5+3) | ... AY144: =INDEX($Q144:$AJ144,1,(AY$4-1)*5+1)+AY$8*INDEX($Q144:$AJ144,1,(AY$4-1)*5+2)*INDEX($Q144:$AJ144,1,(AY$4-1)*5+3) | BA144: =INDEX($Q144:$AJ144,1,(BA$4-1)*5+1)+BA$8*INDEX($Q144:$AJ144,1,(BA$4-1)*5+2)*INDEX($Q144:$AJ144,1,(BA$4-1)*5+3) | BB144: =INDEX($Q144:$AJ144,1,(BB$4-1)*5+1)+BB$8*INDEX($Q144:$AJ144,1,(BB$4-1)*5+2)*INDEX($Q144:$AJ144,1,(BB$4-1)*5+3) | BC144: =INDEX($Q144:$AJ144,1,(BC$4-1)*5+1)+BC$8*INDEX($Q144:$AJ144,1,(BC$4-1)*5+2)*INDEX($Q144:$AJ144,1,(BC$4-1)*5+3) | BD144: =INDEX($Q144:$AJ144,1,(BD$4-1)*5+1)+BD$8*INDEX($Q144:$AJ144,1,(BD$4-1)*5+2)*INDEX($Q144:$AJ144,1,(BD$4-1)*5+3) | BE144: =INDEX($Q144:$AJ144,1,(BE$4-1)*5+1)+BE$8*INDEX($Q144:$AJ144,1,(BE$4-1)*5+2)*INDEX($Q144:$AJ144,1,(BE$4-1)*5+3) | BF144: =INDEX($Q144:$AJ144,1,(BF$4-1)*5+1)+BF$8*INDEX($Q144:$AJ144,1,(BF$4-1)*5+2)*INDEX($Q144:$AJ144,1,(BF$4-1)*5+3) | BG144: =INDEX($Q144:$AJ144,1,(BG$4-1)*5+1)+BG$8*INDEX($Q144:$AJ144,1,(BG$4-1)*5+2)*INDEX($Q144:$AJ144,1,(BG$4-1)*5+3) | BH144: =INDEX($Q144:$AJ144,1,(BH$4-1)*5+1)+BH$8*INDEX($Q144:$AJ144,1,(BH$4-1)*5+2)*INDEX($Q144:$AJ144,1,(BH$4-1)*5+3) | ... BN144: =INDEX($Q144:$AJ144,1,(BN$4-1)*5+1)+BN$8*INDEX($Q144:$AJ144,1,(BN$4-1)*5+2)*INDEX($Q144:$AJ144,1,(BN$4-1)*5+3)
B145: lpg | C145: rod | D145: Tax | Road | LPG | E145: $/GJ | F145: Prices_dom, EF_GHG, Mapping | G145: mit.rp.lpg | H145: mit.tax.lpg.rod | J145: =INDEX(Mapping!$C$5:$C$20,MATCH($C145,Mapping!$A$5:$A$20,0)) | K145: =INDEX(Mapping!$D$5:$D$20,MATCH($C145,Mapping!$A$5:$A$20,0)) | L145: =INDEX(Mapping!$C$24:$C$31,MATCH($B145,Mapping!$A$24:$A$31,0)) | M145: =INDEX(Mapping!$D$24:$D$31,MATCH($B145,Mapping!$A$24:$A$31,0)) | N145: =$B145&"."&IF(INDEX(Mapping!$E$24:$E$31,MATCH($B145,Mapping!$A$24:$A$31,0))="sub",INDEX(Mapping!$F$5:$F$20,MATCH($C145,Mapping!$A$5:$A$20,0)),"all") | O145: =INDEX(Mapping!$E$5:$E$20,MATCH($C145,Mapping!$A$5:$A$20,0)) | P145: =INDEX(Mapping!$G$24:$G$31,MATCH($B145,Mapping!$A$24:$A$31,0)) | Q145: =(INDEX(Prices_dom!$A$6:$CU$2000,MATCH(Settings!$C$4&Settings!$C$7,Prices_dom!$A$6:$A$2000,0),MATCH("mit.rp."&$N145,Prices_dom!$A$5:$CU$5,0))-INDEX(Prices_dom!$A$6:$CU$2000,MATCH(Settings!$C$4&Settings!$C$7,Prices_dom!$A$6:$A$2000,0),MATCH("mit.sp."&$N145,Prices_dom!$A$5:$CU$5,0)))/$P145 | R145: =INDEX(EF_GHG!$E$4:$E$1000,MATCH(Settings!$C$4&"|"&$B145&"|"&$O145,EF_GHG!$A$4:$A$1000,0)) | S145: =INDEX(Mapping!$G$5:$G$20,MATCH($C145,Mapping!$A$5:$A$20,0)) | V145: =Q145 | W145: =R145 | X145: =S145 | AA145: =Q145 | AB145: =R145 | AC145: =S145 | AF145: =Q145 | AG145: =R145 | AH145: =S145 | AL145: =INDEX($Q145:$AJ145,1,(AL$4-1)*5+1)+AL$8*INDEX($Q145:$AJ145,1,(AL$4-1)*5+2)*INDEX($Q145:$AJ145,1,(AL$4-1)*5+3) | AM145: =INDEX($Q145:$AJ145,1,(AM$4-1)*5+1)+AM$8*INDEX($Q145:$AJ145,1,(AM$4-1)*5+2)*INDEX($Q145:$AJ145,1,(AM$4-1)*5+3) | AN145: =INDEX($Q145:$AJ145,1,(AN$4-1)*5+1)+AN$8*INDEX($Q145:$AJ145,1,(AN$4-1)*5+2)*INDEX($Q145:$AJ145,1,(AN$4-1)*5+3) | AO145: =INDEX($Q145:$AJ145,1,(AO$4-1)*5+1)+AO$8*INDEX($Q145:$AJ145,1,(AO$4-1)*5+2)*INDEX($Q145:$AJ145,1,(AO$4-1)*5+3) | AP145: =INDEX($Q145:$AJ145,1,(AP$4-1)*5+1)+AP$8*INDEX($Q145:$AJ145,1,(AP$4-1)*5+2)*INDEX($Q145:$AJ145,1,(AP$4-1)*5+3) | AQ145: =INDEX($Q145:$AJ145,1,(AQ$4-1)*5+1)+AQ$8*INDEX($Q145:$AJ145,1,(AQ$4-1)*5+2)*INDEX($Q145:$AJ145,1,(AQ$4-1)*5+3) | AR145: =INDEX($Q145:$AJ145,1,(AR$4-1)*5+1)+AR$8*INDEX($Q145:$AJ145,1,(AR$4-1)*5+2)*INDEX($Q145:$AJ145,1,(AR$4-1)*5+3) | AS145: =INDEX($Q145:$AJ145,1,(AS$4-1)*5+1)+AS$8*INDEX($Q145:$AJ145,1,(AS$4-1)*5+2)*INDEX($Q145:$AJ145,1,(AS$4-1)*5+3) | ... AY145: =INDEX($Q145:$AJ145,1,(AY$4-1)*5+1)+AY$8*INDEX($Q145:$AJ145,1,(AY$4-1)*5+2)*INDEX($Q145:$AJ145,1,(AY$4-1)*5+3) | BA145: =INDEX($Q145:$AJ145,1,(BA$4-1)*5+1)+BA$8*INDEX($Q145:$AJ145,1,(BA$4-1)*5+2)*INDEX($Q145:$AJ145,1,(BA$4-1)*5+3) | BB145: =INDEX($Q145:$AJ145,1,(BB$4-1)*5+1)+BB$8*INDEX($Q145:$AJ145,1,(BB$4-1)*5+2)*INDEX($Q145:$AJ145,1,(BB$4-1)*5+3) | BC145: =INDEX($Q145:$AJ145,1,(BC$4-1)*5+1)+BC$8*INDEX($Q145:$AJ145,1,(BC$4-1)*5+2)*INDEX($Q145:$AJ145,1,(BC$4-1)*5+3) | BD145: =INDEX($Q145:$AJ145,1,(BD$4-1)*5+1)+BD$8*INDEX($Q145:$AJ145,1,(BD$4-1)*5+2)*INDEX($Q145:$AJ145,1,(BD$4-1)*5+3) | BE145: =INDEX($Q145:$AJ145,1,(BE$4-1)*5+1)+BE$8*INDEX($Q145:$AJ145,1,(BE$4-1)*5+2)*INDEX($Q145:$AJ145,1,(BE$4-1)*5+3) | BF145: =INDEX($Q145:$AJ145,1,(BF$4-1)*5+1)+BF$8*INDEX($Q145:$AJ145,1,(BF$4-1)*5+2)*INDEX($Q145:$AJ145,1,(BF$4-1)*5+3) | BG145: =INDEX($Q145:$AJ145,1,(BG$4-1)*5+1)+BG$8*INDEX($Q145:$AJ145,1,(BG$4-1)*5+2)*INDEX($Q145:$AJ145,1,(BG$4-1)*5+3) | BH145: =INDEX($Q145:$AJ145,1,(BH$4-1)*5+1)+BH$8*INDEX($Q145:$AJ145,1,(BH$4-1)*5+2)*INDEX($Q145:$AJ145,1,(BH$4-1)*5+3) | ... BN145: =INDEX($Q145:$AJ145,1,(BN$4-1)*5+1)+BN$8*INDEX($Q145:$AJ145,1,(BN$4-1)*5+2)*INDEX($Q145:$AJ145,1,(BN$4-1)*5+3)
B146: ker | C146: rod | D146: Tax | Road | Kerosene | E146: $/GJ | F146: Prices_dom, EF_GHG, Mapping | G146: mit.rp.ker | H146: mit.tax.ker.rod | J146: =INDEX(Mapping!$C$5:$C$20,MATCH($C146,Mapping!$A$5:$A$20,0)) | K146: =INDEX(Mapping!$D$5:$D$20,MATCH($C146,Mapping!$A$5:$A$20,0)) | L146: =INDEX(Mapping!$C$24:$C$31,MATCH($B146,Mapping!$A$24:$A$31,0)) | M146: =INDEX(Mapping!$D$24:$D$31,MATCH($B146,Mapping!$A$24:$A$31,0)) | N146: =$B146&"."&IF(INDEX(Mapping!$E$24:$E$31,MATCH($B146,Mapping!$A$24:$A$31,0))="sub",INDEX(Mapping!$F$5:$F$20,MATCH($C146,Mapping!$A$5:$A$20,0)),"all") | O146: =INDEX(Mapping!$E$5:$E$20,MATCH($C146,Mapping!$A$5:$A$20,0)) | P146: =INDEX(Mapping!$G$24:$G$31,MATCH($B146,Mapping!$A$24:$A$31,0)) | Q146: =(INDEX(Prices_dom!$A$6:$CU$2000,MATCH(Settings!$C$4&Settings!$C$7,Prices_dom!$A$6:$A$2000,0),MATCH("mit.rp."&$N146,Prices_dom!$A$5:$CU$5,0))-INDEX(Prices_dom!$A$6:$CU$2000,MATCH(Settings!$C$4&Settings!$C$7,Prices_dom!$A$6:$A$2000,0),MATCH("mit.sp."&$N146,Prices_dom!$A$5:$CU$5,0)))/$P146 | R146: =INDEX(EF_GHG!$E$4:$E$1000,MATCH(Settings!$C$4&"|"&$B146&"|"&$O146,EF_GHG!$A$4:$A$1000,0)) | S146: =INDEX(Mapping!$G$5:$G$20,MATCH($C146,Mapping!$A$5:$A$20,0)) | V146: =Q146 | W146: =R146 | X146: =S146 | AA146: =Q146 | AB146: =R146 | AC146: =S146 | AF146: =Q146 | AG146: =R146 | AH146: =S146 | AL146: =INDEX($Q146:$AJ146,1,(AL$4-1)*5+1)+AL$8*INDEX($Q146:$AJ146,1,(AL$4-1)*5+2)*INDEX($Q146:$AJ146,1,(AL$4-1)*5+3) | AM146: =INDEX($Q146:$AJ146,1,(AM$4-1)*5+1)+AM$8*INDEX($Q146:$AJ146,1,(AM$4-1)*5+2)*INDEX($Q146:$AJ146,1,(AM$4-1)*5+3) | AN146: =INDEX($Q146:$AJ146,1,(AN$4-1)*5+1)+AN$8*INDEX($Q146:$AJ146,1,(AN$4-1)*5+2)*INDEX($Q146:$AJ146,1,(AN$4-1)*5+3) | AO146: =INDEX($Q146:$AJ146,1,(AO$4-1)*5+1)+AO$8*INDEX($Q146:$AJ146,1,(AO$4-1)*5+2)*INDEX($Q146:$AJ146,1,(AO$4-1)*5+3) | AP146: =INDEX($Q146:$AJ146,1,(AP$4-1)*5+1)+AP$8*INDEX($Q146:$AJ146,1,(AP$4-1)*5+2)*INDEX($Q146:$AJ146,1,(AP$4-1)*5+3) | AQ146: =INDEX($Q146:$AJ146,1,(AQ$4-1)*5+1)+AQ$8*INDEX($Q146:$AJ146,1,(AQ$4-1)*5+2)*INDEX($Q146:$AJ146,1,(AQ$4-1)*5+3) | AR146: =INDEX($Q146:$AJ146,1,(AR$4-1)*5+1)+AR$8*INDEX($Q146:$AJ146,1,(AR$4-1)*5+2)*INDEX($Q146:$AJ146,1,(AR$4-1)*5+3) | AS146: =INDEX($Q146:$AJ146,1,(AS$4-1)*5+1)+AS$8*INDEX($Q146:$AJ146,1,(AS$4-1)*5+2)*INDEX($Q146:$AJ146,1,(AS$4-1)*5+3) | ... AY146: =INDEX($Q146:$AJ146,1,(AY$4-1)*5+1)+AY$8*INDEX($Q146:$AJ146,1,(AY$4-1)*5+2)*INDEX($Q146:$AJ146,1,(AY$4-1)*5+3) | BA146: =INDEX($Q146:$AJ146,1,(BA$4-1)*5+1)+BA$8*INDEX($Q146:$AJ146,1,(BA$4-1)*5+2)*INDEX($Q146:$AJ146,1,(BA$4-1)*5+3) | BB146: =INDEX($Q146:$AJ146,1,(BB$4-1)*5+1)+BB$8*INDEX($Q146:$AJ146,1,(BB$4-1)*5+2)*INDEX($Q146:$AJ146,1,(BB$4-1)*5+3) | BC146: =INDEX($Q146:$AJ146,1,(BC$4-1)*5+1)+BC$8*INDEX($Q146:$AJ146,1,(BC$4-1)*5+2)*INDEX($Q146:$AJ146,1,(BC$4-1)*5+3) | BD146: =INDEX($Q146:$AJ146,1,(BD$4-1)*5+1)+BD$8*INDEX($Q146:$AJ146,1,(BD$4-1)*5+2)*INDEX($Q146:$AJ146,1,(BD$4-1)*5+3) | BE146: =INDEX($Q146:$AJ146,1,(BE$4-1)*5+1)+BE$8*INDEX($Q146:$AJ146,1,(BE$4-1)*5+2)*INDEX($Q146:$AJ146,1,(BE$4-1)*5+3) | BF146: =INDEX($Q146:$AJ146,1,(BF$4-1)*5+1)+BF$8*INDEX($Q146:$AJ146,1,(BF$4-1)*5+2)*INDEX($Q146:$AJ146,1,(BF$4-1)*5+3) | BG146: =INDEX($Q146:$AJ146,1,(BG$4-1)*5+1)+BG$8*INDEX($Q146:$AJ146,1,(BG$4-1)*5+2)*INDEX($Q146:$AJ146,1,(BG$4-1)*5+3) | BH146: =INDEX($Q146:$AJ146,1,(BH$4-1)*5+1)+BH$8*INDEX($Q146:$AJ146,1,(BH$4-1)*5+2)*INDEX($Q146:$AJ146,1,(BH$4-1)*5+3) | ... BN146: =INDEX($Q146:$AJ146,1,(BN$4-1)*5+1)+BN$8*INDEX($Q146:$AJ146,1,(BN$4-1)*5+2)*INDEX($Q146:$AJ146,1,(BN$4-1)*5+3)
B147: oop | C147: rod | D147: Tax | Road | Other oil products | E147: $/GJ | F147: Prices_dom, EF_GHG, Mapping | G147: mit.rp.oop | H147: mit.tax.oop.rod | J147: =INDEX(Mapping!$C$5:$C$20,MATCH($C147,Mapping!$A$5:$A$20,0)) | K147: =INDEX(Mapping!$D$5:$D$20,MATCH($C147,Mapping!$A$5:$A$20,0)) | L147: =INDEX(Mapping!$C$24:$C$31,MATCH($B147,Mapping!$A$24:$A$31,0)) | M147: =INDEX(Mapping!$D$24:$D$31,MATCH($B147,Mapping!$A$24:$A$31,0)) | N147: =$B147&"."&IF(INDEX(Mapping!$E$24:$E$31,MATCH($B147,Mapping!$A$24:$A$31,0))="sub",INDEX(Mapping!$F$5:$F$20,MATCH($C147,Mapping!$A$5:$A$20,0)),"all") | O147: =INDEX(Mapping!$E$5:$E$20,MATCH($C147,Mapping!$A$5:$A$20,0)) | P147: =INDEX(Mapping!$G$24:$G$31,MATCH($B147,Mapping!$A$24:$A$31,0)) | Q147: =(INDEX(Prices_dom!$A$6:$CU$2000,MATCH(Settings!$C$4&Settings!$C$7,Prices_dom!$A$6:$A$2000,0),MATCH("mit.rp."&$N147,Prices_dom!$A$5:$CU$5,0))-INDEX(Prices_dom!$A$6:$CU$2000,MATCH(Settings!$C$4&Settings!$C$7,Prices_dom!$A$6:$A$2000,0),MATCH("mit.sp."&$N147,Prices_dom!$A$5:$CU$5,0)))/$P147 | R147: =INDEX(EF_GHG!$E$4:$E$1000,MATCH(Settings!$C$4&"|"&$B147&"|"&$O147,EF_GHG!$A$4:$A$1000,0)) | S147: =INDEX(Mapping!$G$5:$G$20,MATCH($C147,Mapping!$A$5:$A$20,0)) | V147: =Q147 | W147: =R147 | X147: =S147 | AA147: =Q147 | AB147: =R147 | AC147: =S147 | AF147: =Q147 | AG147: =R147 | AH147: =S147 | AL147: =INDEX($Q147:$AJ147,1,(AL$4-1)*5+1)+AL$8*INDEX($Q147:$AJ147,1,(AL$4-1)*5+2)*INDEX($Q147:$AJ147,1,(AL$4-1)*5+3) | AM147: =INDEX($Q147:$AJ147,1,(AM$4-1)*5+1)+AM$8*INDEX($Q147:$AJ147,1,(AM$4-1)*5+2)*INDEX($Q147:$AJ147,1,(AM$4-1)*5+3) | AN147: =INDEX($Q147:$AJ147,1,(AN$4-1)*5+1)+AN$8*INDEX($Q147:$AJ147,1,(AN$4-1)*5+2)*INDEX($Q147:$AJ147,1,(AN$4-1)*5+3) | AO147: =INDEX($Q147:$AJ147,1,(AO$4-1)*5+1)+AO$8*INDEX($Q147:$AJ147,1,(AO$4-1)*5+2)*INDEX($Q147:$AJ147,1,(AO$4-1)*5+3) | AP147: =INDEX($Q147:$AJ147,1,(AP$4-1)*5+1)+AP$8*INDEX($Q147:$AJ147,1,(AP$4-1)*5+2)*INDEX($Q147:$AJ147,1,(AP$4-1)*5+3) | AQ147: =INDEX($Q147:$AJ147,1,(AQ$4-1)*5+1)+AQ$8*INDEX($Q147:$AJ147,1,(AQ$4-1)*5+2)*INDEX($Q147:$AJ147,1,(AQ$4-1)*5+3) | AR147: =INDEX($Q147:$AJ147,1,(AR$4-1)*5+1)+AR$8*INDEX($Q147:$AJ147,1,(AR$4-1)*5+2)*INDEX($Q147:$AJ147,1,(AR$4-1)*5+3) | AS147: =INDEX($Q147:$AJ147,1,(AS$4-1)*5+1)+AS$8*INDEX($Q147:$AJ147,1,(AS$4-1)*5+2)*INDEX($Q147:$AJ147,1,(AS$4-1)*5+3) | ... AY147: =INDEX($Q147:$AJ147,1,(AY$4-1)*5+1)+AY$8*INDEX($Q147:$AJ147,1,(AY$4-1)*5+2)*INDEX($Q147:$AJ147,1,(AY$4-1)*5+3) | BA147: =INDEX($Q147:$AJ147,1,(BA$4-1)*5+1)+BA$8*INDEX($Q147:$AJ147,1,(BA$4-1)*5+2)*INDEX($Q147:$AJ147,1,(BA$4-1)*5+3) | BB147: =INDEX($Q147:$AJ147,1,(BB$4-1)*5+1)+BB$8*INDEX($Q147:$AJ147,1,(BB$4-1)*5+2)*INDEX($Q147:$AJ147,1,(BB$4-1)*5+3) | BC147: =INDEX($Q147:$AJ147,1,(BC$4-1)*5+1)+BC$8*INDEX($Q147:$AJ147,1,(BC$4-1)*5+2)*INDEX($Q147:$AJ147,1,(BC$4-1)*5+3) | BD147: =INDEX($Q147:$AJ147,1,(BD$4-1)*5+1)+BD$8*INDEX($Q147:$AJ147,1,(BD$4-1)*5+2)*INDEX($Q147:$AJ147,1,(BD$4-1)*5+3) | BE147: =INDEX($Q147:$AJ147,1,(BE$4-1)*5+1)+BE$8*INDEX($Q147:$AJ147,1,(BE$4-1)*5+2)*INDEX($Q147:$AJ147,1,(BE$4-1)*5+3) | BF147: =INDEX($Q147:$AJ147,1,(BF$4-1)*5+1)+BF$8*INDEX($Q147:$AJ147,1,(BF$4-1)*5+2)*INDEX($Q147:$AJ147,1,(BF$4-1)*5+3) | BG147: =INDEX($Q147:$AJ147,1,(BG$4-1)*5+1)+BG$8*INDEX($Q147:$AJ147,1,(BG$4-1)*5+2)*INDEX($Q147:$AJ147,1,(BG$4-1)*5+3) | BH147: =INDEX($Q147:$AJ147,1,(BH$4-1)*5+1)+BH$8*INDEX($Q147:$AJ147,1,(BH$4-1)*5+2)*INDEX($Q147:$AJ147,1,(BH$4-1)*5+3) | ... BN147: =INDEX($Q147:$AJ147,1,(BN$4-1)*5+1)+BN$8*INDEX($Q147:$AJ147,1,(BN$4-1)*5+2)*INDEX($Q147:$AJ147,1,(BN$4-1)*5+3)
B148: bio | C148: rod | D148: Tax | Road | Biomass | E148: $/GJ | F148: Prices_dom, EF_GHG, Mapping | G148: mit.rp.bio | H148: mit.tax.bio.rod | J148: =INDEX(Mapping!$C$5:$C$20,MATCH($C148,Mapping!$A$5:$A$20,0)) | K148: =INDEX(Mapping!$D$5:$D$20,MATCH($C148,Mapping!$A$5:$A$20,0)) | L148: =INDEX(Mapping!$C$24:$C$31,MATCH($B148,Mapping!$A$24:$A$31,0)) | M148: =INDEX(Mapping!$D$24:$D$31,MATCH($B148,Mapping!$A$24:$A$31,0)) | N148: =$B148&"."&IF(INDEX(Mapping!$E$24:$E$31,MATCH($B148,Mapping!$A$24:$A$31,0))="sub",INDEX(Mapping!$F$5:$F$20,MATCH($C148,Mapping!$A$5:$A$20,0)),"all") | O148: =INDEX(Mapping!$E$5:$E$20,MATCH($C148,Mapping!$A$5:$A$20,0)) | P148: =INDEX(Mapping!$G$24:$G$31,MATCH($B148,Mapping!$A$24:$A$31,0)) | Q148: =(INDEX(Prices_dom!$A$6:$CU$2000,MATCH(Settings!$C$4&Settings!$C$7,Prices_dom!$A$6:$A$2000,0),MATCH("mit.rp."&$N148,Prices_dom!$A$5:$CU$5,0))-INDEX(Prices_dom!$A$6:$CU$2000,MATCH(Settings!$C$4&Settings!$C$7,Prices_dom!$A$6:$A$2000,0),MATCH("mit.sp."&$N148,Prices_dom!$A$5:$CU$5,0)))/$P148 | R148: =INDEX(EF_GHG!$E$4:$E$1000,MATCH(Settings!$C$4&"|"&$B148&"|"&$O148,EF_GHG!$A$4:$A$1000,0)) | S148: =INDEX(Mapping!$G$5:$G$20,MATCH($C148,Mapping!$A$5:$A$20,0)) | V148: =Q148 | W148: =R148 | X148: =S148 | AA148: =Q148 | AB148: =R148 | AC148: =S148 | AF148: =Q148 | AG148: =R148 | AH148: =S148 | AL148: =INDEX($Q148:$AJ148,1,(AL$4-1)*5+1)+AL$8*INDEX($Q148:$AJ148,1,(AL$4-1)*5+2)*INDEX($Q148:$AJ148,1,(AL$4-1)*5+3) | AM148: =INDEX($Q148:$AJ148,1,(AM$4-1)*5+1)+AM$8*INDEX($Q148:$AJ148,1,(AM$4-1)*5+2)*INDEX($Q148:$AJ148,1,(AM$4-1)*5+3) | AN148: =INDEX($Q148:$AJ148,1,(AN$4-1)*5+1)+AN$8*INDEX($Q148:$AJ148,1,(AN$4-1)*5+2)*INDEX($Q148:$AJ148,1,(AN$4-1)*5+3) | AO148: =INDEX($Q148:$AJ148,1,(AO$4-1)*5+1)+AO$8*INDEX($Q148:$AJ148,1,(AO$4-1)*5+2)*INDEX($Q148:$AJ148,1,(AO$4-1)*5+3) | AP148: =INDEX($Q148:$AJ148,1,(AP$4-1)*5+1)+AP$8*INDEX($Q148:$AJ148,1,(AP$4-1)*5+2)*INDEX($Q148:$AJ148,1,(AP$4-1)*5+3) | AQ148: =INDEX($Q148:$AJ148,1,(AQ$4-1)*5+1)+AQ$8*INDEX($Q148:$AJ148,1,(AQ$4-1)*5+2)*INDEX($Q148:$AJ148,1,(AQ$4-1)*5+3) | AR148: =INDEX($Q148:$AJ148,1,(AR$4-1)*5+1)+AR$8*INDEX($Q148:$AJ148,1,(AR$4-1)*5+2)*INDEX($Q148:$AJ148,1,(AR$4-1)*5+3) | AS148: =INDEX($Q148:$AJ148,1,(AS$4-1)*5+1)+AS$8*INDEX($Q148:$AJ148,1,(AS$4-1)*5+2)*INDEX($Q148:$AJ148,1,(AS$4-1)*5+3) | ... AY148: =INDEX($Q148:$AJ148,1,(AY$4-1)*5+1)+AY$8*INDEX($Q148:$AJ148,1,(AY$4-1)*5+2)*INDEX($Q148:$AJ148,1,(AY$4-1)*5+3) | BA148: =INDEX($Q148:$AJ148,1,(BA$4-1)*5+1)+BA$8*INDEX($Q148:$AJ148,1,(BA$4-1)*5+2)*INDEX($Q148:$AJ148,1,(BA$4-1)*5+3) | BB148: =INDEX($Q148:$AJ148,1,(BB$4-1)*5+1)+BB$8*INDEX($Q148:$AJ148,1,(BB$4-1)*5+2)*INDEX($Q148:$AJ148,1,(BB$4-1)*5+3) | BC148: =INDEX($Q148:$AJ148,1,(BC$4-1)*5+1)+BC$8*INDEX($Q148:$AJ148,1,(BC$4-1)*5+2)*INDEX($Q148:$AJ148,1,(BC$4-1)*5+3) | BD148: =INDEX($Q148:$AJ148,1,(BD$4-1)*5+1)+BD$8*INDEX($Q148:$AJ148,1,(BD$4-1)*5+2)*INDEX($Q148:$AJ148,1,(BD$4-1)*5+3) | BE148: =INDEX($Q148:$AJ148,1,(BE$4-1)*5+1)+BE$8*INDEX($Q148:$AJ148,1,(BE$4-1)*5+2)*INDEX($Q148:$AJ148,1,(BE$4-1)*5+3) | BF148: =INDEX($Q148:$AJ148,1,(BF$4-1)*5+1)+BF$8*INDEX($Q148:$AJ148,1,(BF$4-1)*5+2)*INDEX($Q148:$AJ148,1,(BF$4-1)*5+3) | BG148: =INDEX($Q148:$AJ148,1,(BG$4-1)*5+1)+BG$8*INDEX($Q148:$AJ148,1,(BG$4-1)*5+2)*INDEX($Q148:$AJ148,1,(BG$4-1)*5+3) | BH148: =INDEX($Q148:$AJ148,1,(BH$4-1)*5+1)+BH$8*INDEX($Q148:$AJ148,1,(BH$4-1)*5+2)*INDEX($Q148:$AJ148,1,(BH$4-1)*5+3) | ... BN148: =INDEX($Q148:$AJ148,1,(BN$4-1)*5+1)+BN$8*INDEX($Q148:$AJ148,1,(BN$4-1)*5+2)*INDEX($Q148:$AJ148,1,(BN$4-1)*5+3)
B149: coa | C149: ral | D149: Tax | Rail | Coal | E149: $/GJ | F149: Prices_dom, EF_GHG, Mapping | G149: mit.rp.coa | H149: mit.tax.coa.ral | J149: =INDEX(Mapping!$C$5:$C$20,MATCH($C149,Mapping!$A$5:$A$20,0)) | K149: =INDEX(Mapping!$D$5:$D$20,MATCH($C149,Mapping!$A$5:$A$20,0)) | L149: =INDEX(Mapping!$C$24:$C$31,MATCH($B149,Mapping!$A$24:$A$31,0)) | M149: =INDEX(Mapping!$D$24:$D$31,MATCH($B149,Mapping!$A$24:$A$31,0)) | N149: =$B149&"."&IF(INDEX(Mapping!$E$24:$E$31,MATCH($B149,Mapping!$A$24:$A$31,0))="sub",INDEX(Mapping!$F$5:$F$20,MATCH($C149,Mapping!$A$5:$A$20,0)),"all") | O149: =INDEX(Mapping!$E$5:$E$20,MATCH($C149,Mapping!$A$5:$A$20,0)) | P149: =INDEX(Mapping!$G$24:$G$31,MATCH($B149,Mapping!$A$24:$A$31,0)) | Q149: =(INDEX(Prices_dom!$A$6:$CU$2000,MATCH(Settings!$C$4&Settings!$C$7,Prices_dom!$A$6:$A$2000,0),MATCH("mit.rp."&$N149,Prices_dom!$A$5:$CU$5,0))-INDEX(Prices_dom!$A$6:$CU$2000,MATCH(Settings!$C$4&Settings!$C$7,Prices_dom!$A$6:$A$2000,0),MATCH("mit.sp."&$N149,Prices_dom!$A$5:$CU$5,0)))/$P149 | R149: =INDEX(EF_GHG!$E$4:$E$1000,MATCH(Settings!$C$4&"|"&$B149&"|"&$O149,EF_GHG!$A$4:$A$1000,0)) | S149: =INDEX(Mapping!$G$5:$G$20,MATCH($C149,Mapping!$A$5:$A$20,0)) | V149: =Q149 | W149: =R149 | X149: =S149 | AA149: =Q149 | AB149: =R149 | AC149: =S149 | AF149: =Q149 | AG149: =R149 | AH149: =S149 | AL149: =INDEX($Q149:$AJ149,1,(AL$4-1)*5+1)+AL$8*INDEX($Q149:$AJ149,1,(AL$4-1)*5+2)*INDEX($Q149:$AJ149,1,(AL$4-1)*5+3) | AM149: =INDEX($Q149:$AJ149,1,(AM$4-1)*5+1)+AM$8*INDEX($Q149:$AJ149,1,(AM$4-1)*5+2)*INDEX($Q149:$AJ149,1,(AM$4-1)*5+3) | AN149: =INDEX($Q149:$AJ149,1,(AN$4-1)*5+1)+AN$8*INDEX($Q149:$AJ149,1,(AN$4-1)*5+2)*INDEX($Q149:$AJ149,1,(AN$4-1)*5+3) | AO149: =INDEX($Q149:$AJ149,1,(AO$4-1)*5+1)+AO$8*INDEX($Q149:$AJ149,1,(AO$4-1)*5+2)*INDEX($Q149:$AJ149,1,(AO$4-1)*5+3) | AP149: =INDEX($Q149:$AJ149,1,(AP$4-1)*5+1)+AP$8*INDEX($Q149:$AJ149,1,(AP$4-1)*5+2)*INDEX($Q149:$AJ149,1,(AP$4-1)*5+3) | AQ149: =INDEX($Q149:$AJ149,1,(AQ$4-1)*5+1)+AQ$8*INDEX($Q149:$AJ149,1,(AQ$4-1)*5+2)*INDEX($Q149:$AJ149,1,(AQ$4-1)*5+3) | AR149: =INDEX($Q149:$AJ149,1,(AR$4-1)*5+1)+AR$8*INDEX($Q149:$AJ149,1,(AR$4-1)*5+2)*INDEX($Q149:$AJ149,1,(AR$4-1)*5+3) | AS149: =INDEX($Q149:$AJ149,1,(AS$4-1)*5+1)+AS$8*INDEX($Q149:$AJ149,1,(AS$4-1)*5+2)*INDEX($Q149:$AJ149,1,(AS$4-1)*5+3) | ... AY149: =INDEX($Q149:$AJ149,1,(AY$4-1)*5+1)+AY$8*INDEX($Q149:$AJ149,1,(AY$4-1)*5+2)*INDEX($Q149:$AJ149,1,(AY$4-1)*5+3) | BA149: =INDEX($Q149:$AJ149,1,(BA$4-1)*5+1)+BA$8*INDEX($Q149:$AJ149,1,(BA$4-1)*5+2)*INDEX($Q149:$AJ149,1,(BA$4-1)*5+3) | BB149: =INDEX($Q149:$AJ149,1,(BB$4-1)*5+1)+BB$8*INDEX($Q149:$AJ149,1,(BB$4-1)*5+2)*INDEX($Q149:$AJ149,1,(BB$4-1)*5+3) | BC149: =INDEX($Q149:$AJ149,1,(BC$4-1)*5+1)+BC$8*INDEX($Q149:$AJ149,1,(BC$4-1)*5+2)*INDEX($Q149:$AJ149,1,(BC$4-1)*5+3) | BD149: =INDEX($Q149:$AJ149,1,(BD$4-1)*5+1)+BD$8*INDEX($Q149:$AJ149,1,(BD$4-1)*5+2)*INDEX($Q149:$AJ149,1,(BD$4-1)*5+3) | BE149: =INDEX($Q149:$AJ149,1,(BE$4-1)*5+1)+BE$8*INDEX($Q149:$AJ149,1,(BE$4-1)*5+2)*INDEX($Q149:$AJ149,1,(BE$4-1)*5+3) | BF149: =INDEX($Q149:$AJ149,1,(BF$4-1)*5+1)+BF$8*INDEX($Q149:$AJ149,1,(BF$4-1)*5+2)*INDEX($Q149:$AJ149,1,(BF$4-1)*5+3) | BG149: =INDEX($Q149:$AJ149,1,(BG$4-1)*5+1)+BG$8*INDEX($Q149:$AJ149,1,(BG$4-1)*5+2)*INDEX($Q149:$AJ149,1,(BG$4-1)*5+3) | BH149: =INDEX($Q149:$AJ149,1,(BH$4-1)*5+1)+BH$8*INDEX($Q149:$AJ149,1,(BH$4-1)*5+2)*INDEX($Q149:$AJ149,1,(BH$4-1)*5+3) | ... BN149: =INDEX($Q149:$AJ149,1,(BN$4-1)*5+1)+BN$8*INDEX($Q149:$AJ149,1,(BN$4-1)*5+2)*INDEX($Q149:$AJ149,1,(BN$4-1)*5+3)
B150: nga | C150: ral | D150: Tax | Rail | Natural gas | E150: $/GJ | F150: Prices_dom, EF_GHG, Mapping | G150: mit.rp.nga | H150: mit.tax.nga.ral | J150: =INDEX(Mapping!$C$5:$C$20,MATCH($C150,Mapping!$A$5:$A$20,0)) | K150: =INDEX(Mapping!$D$5:$D$20,MATCH($C150,Mapping!$A$5:$A$20,0)) | L150: =INDEX(Mapping!$C$24:$C$31,MATCH($B150,Mapping!$A$24:$A$31,0)) | M150: =INDEX(Mapping!$D$24:$D$31,MATCH($B150,Mapping!$A$24:$A$31,0)) | N150: =$B150&"."&IF(INDEX(Mapping!$E$24:$E$31,MATCH($B150,Mapping!$A$24:$A$31,0))="sub",INDEX(Mapping!$F$5:$F$20,MATCH($C150,Mapping!$A$5:$A$20,0)),"all") | O150: =INDEX(Mapping!$E$5:$E$20,MATCH($C150,Mapping!$A$5:$A$20,0)) | P150: =INDEX(Mapping!$G$24:$G$31,MATCH($B150,Mapping!$A$24:$A$31,0)) | Q150: =(INDEX(Prices_dom!$A$6:$CU$2000,MATCH(Settings!$C$4&Settings!$C$7,Prices_dom!$A$6:$A$2000,0),MATCH("mit.rp."&$N150,Prices_dom!$A$5:$CU$5,0))-INDEX(Prices_dom!$A$6:$CU$2000,MATCH(Settings!$C$4&Settings!$C$7,Prices_dom!$A$6:$A$2000,0),MATCH("mit.sp."&$N150,Prices_dom!$A$5:$CU$5,0)))/$P150 | R150: =INDEX(EF_GHG!$E$4:$E$1000,MATCH(Settings!$C$4&"|"&$B150&"|"&$O150,EF_GHG!$A$4:$A$1000,0)) | S150: =INDEX(Mapping!$G$5:$G$20,MATCH($C150,Mapping!$A$5:$A$20,0)) | V150: =Q150 | W150: =R150 | X150: =S150 | AA150: =Q150 | AB150: =R150 | AC150: =S150 | AF150: =Q150 | AG150: =R150 | AH150: =S150 | AL150: =INDEX($Q150:$AJ150,1,(AL$4-1)*5+1)+AL$8*INDEX($Q150:$AJ150,1,(AL$4-1)*5+2)*INDEX($Q150:$AJ150,1,(AL$4-1)*5+3) | AM150: =INDEX($Q150:$AJ150,1,(AM$4-1)*5+1)+AM$8*INDEX($Q150:$AJ150,1,(AM$4-1)*5+2)*INDEX($Q150:$AJ150,1,(AM$4-1)*5+3) | AN150: =INDEX($Q150:$AJ150,1,(AN$4-1)*5+1)+AN$8*INDEX($Q150:$AJ150,1,(AN$4-1)*5+2)*INDEX($Q150:$AJ150,1,(AN$4-1)*5+3) | AO150: =INDEX($Q150:$AJ150,1,(AO$4-1)*5+1)+AO$8*INDEX($Q150:$AJ150,1,(AO$4-1)*5+2)*INDEX($Q150:$AJ150,1,(AO$4-1)*5+3) | AP150: =INDEX($Q150:$AJ150,1,(AP$4-1)*5+1)+AP$8*INDEX($Q150:$AJ150,1,(AP$4-1)*5+2)*INDEX($Q150:$AJ150,1,(AP$4-1)*5+3) | AQ150: =INDEX($Q150:$AJ150,1,(AQ$4-1)*5+1)+AQ$8*INDEX($Q150:$AJ150,1,(AQ$4-1)*5+2)*INDEX($Q150:$AJ150,1,(AQ$4-1)*5+3) | AR150: =INDEX($Q150:$AJ150,1,(AR$4-1)*5+1)+AR$8*INDEX($Q150:$AJ150,1,(AR$4-1)*5+2)*INDEX($Q150:$AJ150,1,(AR$4-1)*5+3) | AS150: =INDEX($Q150:$AJ150,1,(AS$4-1)*5+1)+AS$8*INDEX($Q150:$AJ150,1,(AS$4-1)*5+2)*INDEX($Q150:$AJ150,1,(AS$4-1)*5+3) | ... AY150: =INDEX($Q150:$AJ150,1,(AY$4-1)*5+1)+AY$8*INDEX($Q150:$AJ150,1,(AY$4-1)*5+2)*INDEX($Q150:$AJ150,1,(AY$4-1)*5+3) | BA150: =INDEX($Q150:$AJ150,1,(BA$4-1)*5+1)+BA$8*INDEX($Q150:$AJ150,1,(BA$4-1)*5+2)*INDEX($Q150:$AJ150,1,(BA$4-1)*5+3) | BB150: =INDEX($Q150:$AJ150,1,(BB$4-1)*5+1)+BB$8*INDEX($Q150:$AJ150,1,(BB$4-1)*5+2)*INDEX($Q150:$AJ150,1,(BB$4-1)*5+3) | BC150: =INDEX($Q150:$AJ150,1,(BC$4-1)*5+1)+BC$8*INDEX($Q150:$AJ150,1,(BC$4-1)*5+2)*INDEX($Q150:$AJ150,1,(BC$4-1)*5+3) | BD150: =INDEX($Q150:$AJ150,1,(BD$4-1)*5+1)+BD$8*INDEX($Q150:$AJ150,1,(BD$4-1)*5+2)*INDEX($Q150:$AJ150,1,(BD$4-1)*5+3) | BE150: =INDEX($Q150:$AJ150,1,(BE$4-1)*5+1)+BE$8*INDEX($Q150:$AJ150,1,(BE$4-1)*5+2)*INDEX($Q150:$AJ150,1,(BE$4-1)*5+3) | BF150: =INDEX($Q150:$AJ150,1,(BF$4-1)*5+1)+BF$8*INDEX($Q150:$AJ150,1,(BF$4-1)*5+2)*INDEX($Q150:$AJ150,1,(BF$4-1)*5+3) | BG150: =INDEX($Q150:$AJ150,1,(BG$4-1)*5+1)+BG$8*INDEX($Q150:$AJ150,1,(BG$4-1)*5+2)*INDEX($Q150:$AJ150,1,(BG$4-1)*5+3) | BH150: =INDEX($Q150:$AJ150,1,(BH$4-1)*5+1)+BH$8*INDEX($Q150:$AJ150,1,(BH$4-1)*5+2)*INDEX($Q150:$AJ150,1,(BH$4-1)*5+3) | ... BN150: =INDEX($Q150:$AJ150,1,(BN$4-1)*5+1)+BN$8*INDEX($Q150:$AJ150,1,(BN$4-1)*5+2)*INDEX($Q150:$AJ150,1,(BN$4-1)*5+3)
B151: gso | C151: ral | D151: Tax | Rail | Gasoline | E151: $/GJ | F151: Prices_dom, EF_GHG, Mapping | G151: mit.rp.gso | H151: mit.tax.gso.ral | J151: =INDEX(Mapping!$C$5:$C$20,MATCH($C151,Mapping!$A$5:$A$20,0)) | K151: =INDEX(Mapping!$D$5:$D$20,MATCH($C151,Mapping!$A$5:$A$20,0)) | L151: =INDEX(Mapping!$C$24:$C$31,MATCH($B151,Mapping!$A$24:$A$31,0)) | M151: =INDEX(Mapping!$D$24:$D$31,MATCH($B151,Mapping!$A$24:$A$31,0)) | N151: =$B151&"."&IF(INDEX(Mapping!$E$24:$E$31,MATCH($B151,Mapping!$A$24:$A$31,0))="sub",INDEX(Mapping!$F$5:$F$20,MATCH($C151,Mapping!$A$5:$A$20,0)),"all") | O151: =INDEX(Mapping!$E$5:$E$20,MATCH($C151,Mapping!$A$5:$A$20,0)) | P151: =INDEX(Mapping!$G$24:$G$31,MATCH($B151,Mapping!$A$24:$A$31,0)) | Q151: =(INDEX(Prices_dom!$A$6:$CU$2000,MATCH(Settings!$C$4&Settings!$C$7,Prices_dom!$A$6:$A$2000,0),MATCH("mit.rp."&$N151,Prices_dom!$A$5:$CU$5,0))-INDEX(Prices_dom!$A$6:$CU$2000,MATCH(Settings!$C$4&Settings!$C$7,Prices_dom!$A$6:$A$2000,0),MATCH("mit.sp."&$N151,Prices_dom!$A$5:$CU$5,0)))/$P151 | R151: =INDEX(EF_GHG!$E$4:$E$1000,MATCH(Settings!$C$4&"|"&$B151&"|"&$O151,EF_GHG!$A$4:$A$1000,0)) | S151: =INDEX(Mapping!$G$5:$G$20,MATCH($C151,Mapping!$A$5:$A$20,0)) | V151: =Q151 | W151: =R151 | X151: =S151 | AA151: =Q151 | AB151: =R151 | AC151: =S151 | AF151: =Q151 | AG151: =R151 | AH151: =S151 | AL151: =INDEX($Q151:$AJ151,1,(AL$4-1)*5+1)+AL$8*INDEX($Q151:$AJ151,1,(AL$4-1)*5+2)*INDEX($Q151:$AJ151,1,(AL$4-1)*5+3) | AM151: =INDEX($Q151:$AJ151,1,(AM$4-1)*5+1)+AM$8*INDEX($Q151:$AJ151,1,(AM$4-1)*5+2)*INDEX($Q151:$AJ151,1,(AM$4-1)*5+3) | AN151: =INDEX($Q151:$AJ151,1,(AN$4-1)*5+1)+AN$8*INDEX($Q151:$AJ151,1,(AN$4-1)*5+2)*INDEX($Q151:$AJ151,1,(AN$4-1)*5+3) | AO151: =INDEX($Q151:$AJ151,1,(AO$4-1)*5+1)+AO$8*INDEX($Q151:$AJ151,1,(AO$4-1)*5+2)*INDEX($Q151:$AJ151,1,(AO$4-1)*5+3) | AP151: =INDEX($Q151:$AJ151,1,(AP$4-1)*5+1)+AP$8*INDEX($Q151:$AJ151,1,(AP$4-1)*5+2)*INDEX($Q151:$AJ151,1,(AP$4-1)*5+3) | AQ151: =INDEX($Q151:$AJ151,1,(AQ$4-1)*5+1)+AQ$8*INDEX($Q151:$AJ151,1,(AQ$4-1)*5+2)*INDEX($Q151:$AJ151,1,(AQ$4-1)*5+3) | AR151: =INDEX($Q151:$AJ151,1,(AR$4-1)*5+1)+AR$8*INDEX($Q151:$AJ151,1,(AR$4-1)*5+2)*INDEX($Q151:$AJ151,1,(AR$4-1)*5+3) | AS151: =INDEX($Q151:$AJ151,1,(AS$4-1)*5+1)+AS$8*INDEX($Q151:$AJ151,1,(AS$4-1)*5+2)*INDEX($Q151:$AJ151,1,(AS$4-1)*5+3) | ... AY151: =INDEX($Q151:$AJ151,1,(AY$4-1)*5+1)+AY$8*INDEX($Q151:$AJ151,1,(AY$4-1)*5+2)*INDEX($Q151:$AJ151,1,(AY$4-1)*5+3) | BA151: =INDEX($Q151:$AJ151,1,(BA$4-1)*5+1)+BA$8*INDEX($Q151:$AJ151,1,(BA$4-1)*5+2)*INDEX($Q151:$AJ151,1,(BA$4-1)*5+3) | BB151: =INDEX($Q151:$AJ151,1,(BB$4-1)*5+1)+BB$8*INDEX($Q151:$AJ151,1,(BB$4-1)*5+2)*INDEX($Q151:$AJ151,1,(BB$4-1)*5+3) | BC151: =INDEX($Q151:$AJ151,1,(BC$4-1)*5+1)+BC$8*INDEX($Q151:$AJ151,1,(BC$4-1)*5+2)*INDEX($Q151:$AJ151,1,(BC$4-1)*5+3) | BD151: =INDEX($Q151:$AJ151,1,(BD$4-1)*5+1)+BD$8*INDEX($Q151:$AJ151,1,(BD$4-1)*5+2)*INDEX($Q151:$AJ151,1,(BD$4-1)*5+3) | BE151: =INDEX($Q151:$AJ151,1,(BE$4-1)*5+1)+BE$8*INDEX($Q151:$AJ151,1,(BE$4-1)*5+2)*INDEX($Q151:$AJ151,1,(BE$4-1)*5+3) | BF151: =INDEX($Q151:$AJ151,1,(BF$4-1)*5+1)+BF$8*INDEX($Q151:$AJ151,1,(BF$4-1)*5+2)*INDEX($Q151:$AJ151,1,(BF$4-1)*5+3) | BG151: =INDEX($Q151:$AJ151,1,(BG$4-1)*5+1)+BG$8*INDEX($Q151:$AJ151,1,(BG$4-1)*5+2)*INDEX($Q151:$AJ151,1,(BG$4-1)*5+3) | BH151: =INDEX($Q151:$AJ151,1,(BH$4-1)*5+1)+BH$8*INDEX($Q151:$AJ151,1,(BH$4-1)*5+2)*INDEX($Q151:$AJ151,1,(BH$4-1)*5+3) | ... BN151: =INDEX($Q151:$AJ151,1,(BN$4-1)*5+1)+BN$8*INDEX($Q151:$AJ151,1,(BN$4-1)*5+2)*INDEX($Q151:$AJ151,1,(BN$4-1)*5+3)
B152: die | C152: ral | D152: Tax | Rail | Diesel | E152: $/GJ | F152: Prices_dom, EF_GHG, Mapping | G152: mit.rp.die | H152: mit.tax.die.ral | J152: =INDEX(Mapping!$C$5:$C$20,MATCH($C152,Mapping!$A$5:$A$20,0)) | K152: =INDEX(Mapping!$D$5:$D$20,MATCH($C152,Mapping!$A$5:$A$20,0)) | L152: =INDEX(Mapping!$C$24:$C$31,MATCH($B152,Mapping!$A$24:$A$31,0)) | M152: =INDEX(Mapping!$D$24:$D$31,MATCH($B152,Mapping!$A$24:$A$31,0)) | N152: =$B152&"."&IF(INDEX(Mapping!$E$24:$E$31,MATCH($B152,Mapping!$A$24:$A$31,0))="sub",INDEX(Mapping!$F$5:$F$20,MATCH($C152,Mapping!$A$5:$A$20,0)),"all") | O152: =INDEX(Mapping!$E$5:$E$20,MATCH($C152,Mapping!$A$5:$A$20,0)) | P152: =INDEX(Mapping!$G$24:$G$31,MATCH($B152,Mapping!$A$24:$A$31,0)) | Q152: =(INDEX(Prices_dom!$A$6:$CU$2000,MATCH(Settings!$C$4&Settings!$C$7,Prices_dom!$A$6:$A$2000,0),MATCH("mit.rp."&$N152,Prices_dom!$A$5:$CU$5,0))-INDEX(Prices_dom!$A$6:$CU$2000,MATCH(Settings!$C$4&Settings!$C$7,Prices_dom!$A$6:$A$2000,0),MATCH("mit.sp."&$N152,Prices_dom!$A$5:$CU$5,0)))/$P152 | R152: =INDEX(EF_GHG!$E$4:$E$1000,MATCH(Settings!$C$4&"|"&$B152&"|"&$O152,EF_GHG!$A$4:$A$1000,0)) | S152: =INDEX(Mapping!$G$5:$G$20,MATCH($C152,Mapping!$A$5:$A$20,0)) | V152: =Q152 | W152: =R152 | X152: =S152 | AA152: =Q152 | AB152: =R152 | AC152: =S152 | AF152: =Q152 | AG152: =R152 | AH152: =S152 | AL152: =INDEX($Q152:$AJ152,1,(AL$4-1)*5+1)+AL$8*INDEX($Q152:$AJ152,1,(AL$4-1)*5+2)*INDEX($Q152:$AJ152,1,(AL$4-1)*5+3) | AM152: =INDEX($Q152:$AJ152,1,(AM$4-1)*5+1)+AM$8*INDEX($Q152:$AJ152,1,(AM$4-1)*5+2)*INDEX($Q152:$AJ152,1,(AM$4-1)*5+3) | AN152: =INDEX($Q152:$AJ152,1,(AN$4-1)*5+1)+AN$8*INDEX($Q152:$AJ152,1,(AN$4-1)*5+2)*INDEX($Q152:$AJ152,1,(AN$4-1)*5+3) | AO152: =INDEX($Q152:$AJ152,1,(AO$4-1)*5+1)+AO$8*INDEX($Q152:$AJ152,1,(AO$4-1)*5+2)*INDEX($Q152:$AJ152,1,(AO$4-1)*5+3) | AP152: =INDEX($Q152:$AJ152,1,(AP$4-1)*5+1)+AP$8*INDEX($Q152:$AJ152,1,(AP$4-1)*5+2)*INDEX($Q152:$AJ152,1,(AP$4-1)*5+3) | AQ152: =INDEX($Q152:$AJ152,1,(AQ$4-1)*5+1)+AQ$8*INDEX($Q152:$AJ152,1,(AQ$4-1)*5+2)*INDEX($Q152:$AJ152,1,(AQ$4-1)*5+3) | AR152: =INDEX($Q152:$AJ152,1,(AR$4-1)*5+1)+AR$8*INDEX($Q152:$AJ152,1,(AR$4-1)*5+2)*INDEX($Q152:$AJ152,1,(AR$4-1)*5+3) | AS152: =INDEX($Q152:$AJ152,1,(AS$4-1)*5+1)+AS$8*INDEX($Q152:$AJ152,1,(AS$4-1)*5+2)*INDEX($Q152:$AJ152,1,(AS$4-1)*5+3) | ... AY152: =INDEX($Q152:$AJ152,1,(AY$4-1)*5+1)+AY$8*INDEX($Q152:$AJ152,1,(AY$4-1)*5+2)*INDEX($Q152:$AJ152,1,(AY$4-1)*5+3) | BA152: =INDEX($Q152:$AJ152,1,(BA$4-1)*5+1)+BA$8*INDEX($Q152:$AJ152,1,(BA$4-1)*5+2)*INDEX($Q152:$AJ152,1,(BA$4-1)*5+3) | BB152: =INDEX($Q152:$AJ152,1,(BB$4-1)*5+1)+BB$8*INDEX($Q152:$AJ152,1,(BB$4-1)*5+2)*INDEX($Q152:$AJ152,1,(BB$4-1)*5+3) | BC152: =INDEX($Q152:$AJ152,1,(BC$4-1)*5+1)+BC$8*INDEX($Q152:$AJ152,1,(BC$4-1)*5+2)*INDEX($Q152:$AJ152,1,(BC$4-1)*5+3) | BD152: =INDEX($Q152:$AJ152,1,(BD$4-1)*5+1)+BD$8*INDEX($Q152:$AJ152,1,(BD$4-1)*5+2)*INDEX($Q152:$AJ152,1,(BD$4-1)*5+3) | BE152: =INDEX($Q152:$AJ152,1,(BE$4-1)*5+1)+BE$8*INDEX($Q152:$AJ152,1,(BE$4-1)*5+2)*INDEX($Q152:$AJ152,1,(BE$4-1)*5+3) | BF152: =INDEX($Q152:$AJ152,1,(BF$4-1)*5+1)+BF$8*INDEX($Q152:$AJ152,1,(BF$4-1)*5+2)*INDEX($Q152:$AJ152,1,(BF$4-1)*5+3) | BG152: =INDEX($Q152:$AJ152,1,(BG$4-1)*5+1)+BG$8*INDEX($Q152:$AJ152,1,(BG$4-1)*5+2)*INDEX($Q152:$AJ152,1,(BG$4-1)*5+3) | BH152: =INDEX($Q152:$AJ152,1,(BH$4-1)*5+1)+BH$8*INDEX($Q152:$AJ152,1,(BH$4-1)*5+2)*INDEX($Q152:$AJ152,1,(BH$4-1)*5+3) | ... BN152: =INDEX($Q152:$AJ152,1,(BN$4-1)*5+1)+BN$8*INDEX($Q152:$AJ152,1,(BN$4-1)*5+2)*INDEX($Q152:$AJ152,1,(BN$4-1)*5+3)
... B268: bio | C268: oen | D268: Tax | Other energy use | Biomass | E268: $/GJ | F268: Prices_dom, EF_GHG, Mapping | G268: mit.rp.bio | H268: mit.tax.bio.oen | J268: =INDEX(Mapping!$C$5:$C$20,MATCH($C268,Mapping!$A$5:$A$20,0)) | K268: =INDEX(Mapping!$D$5:$D$20,MATCH($C268,Mapping!$A$5:$A$20,0)) | L268: =INDEX(Mapping!$C$24:$C$31,MATCH($B268,Mapping!$A$24:$A$31,0)) | M268: =INDEX(Mapping!$D$24:$D$31,MATCH($B268,Mapping!$A$24:$A$31,0)) | N268: =$B268&"."&IF(INDEX(Mapping!$E$24:$E$31,MATCH($B268,Mapping!$A$24:$A$31,0))="sub",INDEX(Mapping!$F$5:$F$20,MATCH($C268,Mapping!$A$5:$A$20,0)),"all") | O268: =INDEX(Mapping!$E$5:$E$20,MATCH($C268,Mapping!$A$5:$A$20,0)) | P268: =INDEX(Mapping!$G$24:$G$31,MATCH($B268,Mapping!$A$24:$A$31,0)) | Q268: =(INDEX(Prices_dom!$A$6:$CU$2000,MATCH(Settings!$C$4&Settings!$C$7,Prices_dom!$A$6:$A$2000,0),MATCH("mit.rp."&$N268,Prices_dom!$A$5:$CU$5,0))-INDEX(Prices_dom!$A$6:$CU$2000,MATCH(Settings!$C$4&Settings!$C$7,Prices_dom!$A$6:$A$2000,0),MATCH("mit.sp."&$N268,Prices_dom!$A$5:$CU$5,0)))/$P268 | R268: =INDEX(EF_GHG!$E$4:$E$1000,MATCH(Settings!$C$4&"|"&$B268&"|"&$O268,EF_GHG!$A$4:$A$1000,0)) | S268: =INDEX(Mapping!$G$5:$G$20,MATCH($C268,Mapping!$A$5:$A$20,0)) | V268: =Q268 | W268: =R268 | X268: =S268 | AA268: =Q268 | AB268: =R268 | AC268: =S268 | AF268: =Q268 | AG268: =R268 | AH268: =S268 | AL268: =INDEX($Q268:$AJ268,1,(AL$4-1)*5+1)+AL$8*INDEX($Q268:$AJ268,1,(AL$4-1)*5+2)*INDEX($Q268:$AJ268,1,(AL$4-1)*5+3) | AM268: =INDEX($Q268:$AJ268,1,(AM$4-1)*5+1)+AM$8*INDEX($Q268:$AJ268,1,(AM$4-1)*5+2)*INDEX($Q268:$AJ268,1,(AM$4-1)*5+3) | AN268: =INDEX($Q268:$AJ268,1,(AN$4-1)*5+1)+AN$8*INDEX($Q268:$AJ268,1,(AN$4-1)*5+2)*INDEX($Q268:$AJ268,1,(AN$4-1)*5+3) | AO268: =INDEX($Q268:$AJ268,1,(AO$4-1)*5+1)+AO$8*INDEX($Q268:$AJ268,1,(AO$4-1)*5+2)*INDEX($Q268:$AJ268,1,(AO$4-1)*5+3) | AP268: =INDEX($Q268:$AJ268,1,(AP$4-1)*5+1)+AP$8*INDEX($Q268:$AJ268,1,(AP$4-1)*5+2)*INDEX($Q268:$AJ268,1,(AP$4-1)*5+3) | AQ268: =INDEX($Q268:$AJ268,1,(AQ$4-1)*5+1)+AQ$8*INDEX($Q268:$AJ268,1,(AQ$4-1)*5+2)*INDEX($Q268:$AJ268,1,(AQ$4-1)*5+3) | AR268: =INDEX($Q268:$AJ268,1,(AR$4-1)*5+1)+AR$8*INDEX($Q268:$AJ268,1,(AR$4-1)*5+2)*INDEX($Q268:$AJ268,1,(AR$4-1)*5+3) | AS268: =INDEX($Q268:$AJ268,1,(AS$4-1)*5+1)+AS$8*INDEX($Q268:$AJ268,1,(AS$4-1)*5+2)*INDEX($Q268:$AJ268,1,(AS$4-1)*5+3) | ... AY268: =INDEX($Q268:$AJ268,1,(AY$4-1)*5+1)+AY$8*INDEX($Q268:$AJ268,1,(AY$4-1)*5+2)*INDEX($Q268:$AJ268,1,(AY$4-1)*5+3) | BA268: =INDEX($Q268:$AJ268,1,(BA$4-1)*5+1)+BA$8*INDEX($Q268:$AJ268,1,(BA$4-1)*5+2)*INDEX($Q268:$AJ268,1,(BA$4-1)*5+3) | BB268: =INDEX($Q268:$AJ268,1,(BB$4-1)*5+1)+BB$8*INDEX($Q268:$AJ268,1,(BB$4-1)*5+2)*INDEX($Q268:$AJ268,1,(BB$4-1)*5+3) | BC268: =INDEX($Q268:$AJ268,1,(BC$4-1)*5+1)+BC$8*INDEX($Q268:$AJ268,1,(BC$4-1)*5+2)*INDEX($Q268:$AJ268,1,(BC$4-1)*5+3) | BD268: =INDEX($Q268:$AJ268,1,(BD$4-1)*5+1)+BD$8*INDEX($Q268:$AJ268,1,(BD$4-1)*5+2)*INDEX($Q268:$AJ268,1,(BD$4-1)*5+3) | BE268: =INDEX($Q268:$AJ268,1,(BE$4-1)*5+1)+BE$8*INDEX($Q268:$AJ268,1,(BE$4-1)*5+2)*INDEX($Q268:$AJ268,1,(BE$4-1)*5+3) | BF268: =INDEX($Q268:$AJ268,1,(BF$4-1)*5+1)+BF$8*INDEX($Q268:$AJ268,1,(BF$4-1)*5+2)*INDEX($Q268:$AJ268,1,(BF$4-1)*5+3) | BG268: =INDEX($Q268:$AJ268,1,(BG$4-1)*5+1)+BG$8*INDEX($Q268:$AJ268,1,(BG$4-1)*5+2)*INDEX($Q268:$AJ268,1,(BG$4-1)*5+3) | BH268: =INDEX($Q268:$AJ268,1,(BH$4-1)*5+1)+BH$8*INDEX($Q268:$AJ268,1,(BH$4-1)*5+2)*INDEX($Q268:$AJ268,1,(BH$4-1)*5+3) | ... BN268: =INDEX($Q268:$AJ268,1,(BN$4-1)*5+1)+BN$8*INDEX($Q268:$AJ268,1,(BN$4-1)*5+2)*INDEX($Q268:$AJ268,1,(BN$4-1)*5+3)
A270: Post-tax price = pre-tax + tax | Q270: - | R270: - | S270: - | T270: - | U270: buffer | V270: - | W270: - | X270: - | Y270: - | Z270: buffer | AA270: - | AB270: - | AC270: - | AD270: - | AE270: buffer | AF270: - | AG270: - | AH270: - | AI270: - | AJ270: buffer
B271: coa | C271: rod | D271: Post-tax price | Road | Coal | E271: $/GJ | F271: Calculation | H271: mit.ptp.coa.rod | J271: =INDEX(Mapping!$C$5:$C$20,MATCH($C271,Mapping!$A$5:$A$20,0)) | K271: =INDEX(Mapping!$D$5:$D$20,MATCH($C271,Mapping!$A$5:$A$20,0)) | L271: =INDEX(Mapping!$C$24:$C$31,MATCH($B271,Mapping!$A$24:$A$31,0)) | M271: =INDEX(Mapping!$D$24:$D$31,MATCH($B271,Mapping!$A$24:$A$31,0)) | N271: =$B271&"."&IF(INDEX(Mapping!$E$24:$E$31,MATCH($B271,Mapping!$A$24:$A$31,0))="sub",INDEX(Mapping!$F$5:$F$20,MATCH($C271,Mapping!$A$5:$A$20,0)),"all") | O271: =INDEX(Mapping!$E$5:$E$20,MATCH($C271,Mapping!$A$5:$A$20,0)) | P271: =INDEX(Mapping!$G$24:$G$31,MATCH($B271,Mapping!$A$24:$A$31,0)) | AL271: =AL11+AL141 | AM271: =AM11+AM141 | AN271: =AN11+AN141 | AO271: =AO11+AO141 | AP271: =AP11+AP141 | AQ271: =AQ11+AQ141 | AR271: =AR11+AR141 | AS271: =AS11+AS141 | ... AY271: =AY11+AY141 | BA271: =BA11+BA141 | BB271: =BB11+BB141 | BC271: =BC11+BC141 | BD271: =BD11+BD141 | BE271: =BE11+BE141 | BF271: =BF11+BF141 | BG271: =BG11+BG141 | BH271: =BH11+BH141 | ... BN271: =BN11+BN141
B272: nga | C272: rod | D272: Post-tax price | Road | Natural gas | E272: $/GJ | F272: Calculation | H272: mit.ptp.nga.rod | J272: =INDEX(Mapping!$C$5:$C$20,MATCH($C272,Mapping!$A$5:$A$20,0)) | K272: =INDEX(Mapping!$D$5:$D$20,MATCH($C272,Mapping!$A$5:$A$20,0)) | L272: =INDEX(Mapping!$C$24:$C$31,MATCH($B272,Mapping!$A$24:$A$31,0)) | M272: =INDEX(Mapping!$D$24:$D$31,MATCH($B272,Mapping!$A$24:$A$31,0)) | N272: =$B272&"."&IF(INDEX(Mapping!$E$24:$E$31,MATCH($B272,Mapping!$A$24:$A$31,0))="sub",INDEX(Mapping!$F$5:$F$20,MATCH($C272,Mapping!$A$5:$A$20,0)),"all") | O272: =INDEX(Mapping!$E$5:$E$20,MATCH($C272,Mapping!$A$5:$A$20,0)) | P272: =INDEX(Mapping!$G$24:$G$31,MATCH($B272,Mapping!$A$24:$A$31,0)) | AL272: =AL12+AL142 | AM272: =AM12+AM142 | AN272: =AN12+AN142 | AO272: =AO12+AO142 | AP272: =AP12+AP142 | AQ272: =AQ12+AQ142 | AR272: =AR12+AR142 | AS272: =AS12+AS142 | ... AY272: =AY12+AY142 | BA272: =BA12+BA142 | BB272: =BB12+BB142 | BC272: =BC12+BC142 | BD272: =BD12+BD142 | BE272: =BE12+BE142 | BF272: =BF12+BF142 | BG272: =BG12+BG142 | BH272: =BH12+BH142 | ... BN272: =BN12+BN142
B273: gso | C273: rod | D273: Post-tax price | Road | Gasoline | E273: $/GJ | F273: Calculation | H273: mit.ptp.gso.rod | J273: =INDEX(Mapping!$C$5:$C$20,MATCH($C273,Mapping!$A$5:$A$20,0)) | K273: =INDEX(Mapping!$D$5:$D$20,MATCH($C273,Mapping!$A$5:$A$20,0)) | L273: =INDEX(Mapping!$C$24:$C$31,MATCH($B273,Mapping!$A$24:$A$31,0)) | M273: =INDEX(Mapping!$D$24:$D$31,MATCH($B273,Mapping!$A$24:$A$31,0)) | N273: =$B273&"."&IF(INDEX(Mapping!$E$24:$E$31,MATCH($B273,Mapping!$A$24:$A$31,0))="sub",INDEX(Mapping!$F$5:$F$20,MATCH($C273,Mapping!$A$5:$A$20,0)),"all") | O273: =INDEX(Mapping!$E$5:$E$20,MATCH($C273,Mapping!$A$5:$A$20,0)) | P273: =INDEX(Mapping!$G$24:$G$31,MATCH($B273,Mapping!$A$24:$A$31,0)) | AL273: =AL13+AL143 | AM273: =AM13+AM143 | AN273: =AN13+AN143 | AO273: =AO13+AO143 | AP273: =AP13+AP143 | AQ273: =AQ13+AQ143 | AR273: =AR13+AR143 | AS273: =AS13+AS143 | ... AY273: =AY13+AY143 | BA273: =BA13+BA143 | BB273: =BB13+BB143 | BC273: =BC13+BC143 | BD273: =BD13+BD143 | BE273: =BE13+BE143 | BF273: =BF13+BF143 | BG273: =BG13+BG143 | BH273: =BH13+BH143 | ... BN273: =BN13+BN143
B274: die | C274: rod | D274: Post-tax price | Road | Diesel | E274: $/GJ | F274: Calculation | H274: mit.ptp.die.rod | J274: =INDEX(Mapping!$C$5:$C$20,MATCH($C274,Mapping!$A$5:$A$20,0)) | K274: =INDEX(Mapping!$D$5:$D$20,MATCH($C274,Mapping!$A$5:$A$20,0)) | L274: =INDEX(Mapping!$C$24:$C$31,MATCH($B274,Mapping!$A$24:$A$31,0)) | M274: =INDEX(Mapping!$D$24:$D$31,MATCH($B274,Mapping!$A$24:$A$31,0)) | N274: =$B274&"."&IF(INDEX(Mapping!$E$24:$E$31,MATCH($B274,Mapping!$A$24:$A$31,0))="sub",INDEX(Mapping!$F$5:$F$20,MATCH($C274,Mapping!$A$5:$A$20,0)),"all") | O274: =INDEX(Mapping!$E$5:$E$20,MATCH($C274,Mapping!$A$5:$A$20,0)) | P274: =INDEX(Mapping!$G$24:$G$31,MATCH($B274,Mapping!$A$24:$A$31,0)) | AL274: =AL14+AL144 | AM274: =AM14+AM144 | AN274: =AN14+AN144 | AO274: =AO14+AO144 | AP274: =AP14+AP144 | AQ274: =AQ14+AQ144 | AR274: =AR14+AR144 | AS274: =AS14+AS144 | ... AY274: =AY14+AY144 | BA274: =BA14+BA144 | BB274: =BB14+BB144 | BC274: =BC14+BC144 | BD274: =BD14+BD144 | BE274: =BE14+BE144 | BF274: =BF14+BF144 | BG274: =BG14+BG144 | BH274: =BH14+BH144 | ... BN274: =BN14+BN144
B275: lpg | C275: rod | D275: Post-tax price | Road | LPG | E275: $/GJ | F275: Calculation | H275: mit.ptp.lpg.rod | J275: =INDEX(Mapping!$C$5:$C$20,MATCH($C275,Mapping!$A$5:$A$20,0)) | K275: =INDEX(Mapping!$D$5:$D$20,MATCH($C275,Mapping!$A$5:$A$20,0)) | L275: =INDEX(Mapping!$C$24:$C$31,MATCH($B275,Mapping!$A$24:$A$31,0)) | M275: =INDEX(Mapping!$D$24:$D$31,MATCH($B275,Mapping!$A$24:$A$31,0)) | N275: =$B275&"."&IF(INDEX(Mapping!$E$24:$E$31,MATCH($B275,Mapping!$A$24:$A$31,0))="sub",INDEX(Mapping!$F$5:$F$20,MATCH($C275,Mapping!$A$5:$A$20,0)),"all") | O275: =INDEX(Mapping!$E$5:$E$20,MATCH($C275,Mapping!$A$5:$A$20,0)) | P275: =INDEX(Mapping!$G$24:$G$31,MATCH($B275,Mapping!$A$24:$A$31,0)) | AL275: =AL15+AL145 | AM275: =AM15+AM145 | AN275: =AN15+AN145 | AO275: =AO15+AO145 | AP275: =AP15+AP145 | AQ275: =AQ15+AQ145 | AR275: =AR15+AR145 | AS275: =AS15+AS145 | ... AY275: =AY15+AY145 | BA275: =BA15+BA145 | BB275: =BB15+BB145 | BC275: =BC15+BC145 | BD275: =BD15+BD145 | BE275: =BE15+BE145 | BF275: =BF15+BF145 | BG275: =BG15+BG145 | BH275: =BH15+BH145 | ... BN275: =BN15+BN145
B276: ker | C276: rod | D276: Post-tax price | Road | Kerosene | E276: $/GJ | F276: Calculation | H276: mit.ptp.ker.rod | J276: =INDEX(Mapping!$C$5:$C$20,MATCH($C276,Mapping!$A$5:$A$20,0)) | K276: =INDEX(Mapping!$D$5:$D$20,MATCH($C276,Mapping!$A$5:$A$20,0)) | L276: =INDEX(Mapping!$C$24:$C$31,MATCH($B276,Mapping!$A$24:$A$31,0)) | M276: =INDEX(Mapping!$D$24:$D$31,MATCH($B276,Mapping!$A$24:$A$31,0)) | N276: =$B276&"."&IF(INDEX(Mapping!$E$24:$E$31,MATCH($B276,Mapping!$A$24:$A$31,0))="sub",INDEX(Mapping!$F$5:$F$20,MATCH($C276,Mapping!$A$5:$A$20,0)),"all") | O276: =INDEX(Mapping!$E$5:$E$20,MATCH($C276,Mapping!$A$5:$A$20,0)) | P276: =INDEX(Mapping!$G$24:$G$31,MATCH($B276,Mapping!$A$24:$A$31,0)) | AL276: =AL16+AL146 | AM276: =AM16+AM146 | AN276: =AN16+AN146 | AO276: =AO16+AO146 | AP276: =AP16+AP146 | AQ276: =AQ16+AQ146 | AR276: =AR16+AR146 | AS276: =AS16+AS146 | ... AY276: =AY16+AY146 | BA276: =BA16+BA146 | BB276: =BB16+BB146 | BC276: =BC16+BC146 | BD276: =BD16+BD146 | BE276: =BE16+BE146 | BF276: =BF16+BF146 | BG276: =BG16+BG146 | BH276: =BH16+BH146 | ... BN276: =BN16+BN146
B277: oop | C277: rod | D277: Post-tax price | Road | Other oil products | E277: $/GJ | F277: Calculation | H277: mit.ptp.oop.rod | J277: =INDEX(Mapping!$C$5:$C$20,MATCH($C277,Mapping!$A$5:$A$20,0)) | K277: =INDEX(Mapping!$D$5:$D$20,MATCH($C277,Mapping!$A$5:$A$20,0)) | L277: =INDEX(Mapping!$C$24:$C$31,MATCH($B277,Mapping!$A$24:$A$31,0)) | M277: =INDEX(Mapping!$D$24:$D$31,MATCH($B277,Mapping!$A$24:$A$31,0)) | N277: =$B277&"."&IF(INDEX(Mapping!$E$24:$E$31,MATCH($B277,Mapping!$A$24:$A$31,0))="sub",INDEX(Mapping!$F$5:$F$20,MATCH($C277,Mapping!$A$5:$A$20,0)),"all") | O277: =INDEX(Mapping!$E$5:$E$20,MATCH($C277,Mapping!$A$5:$A$20,0)) | P277: =INDEX(Mapping!$G$24:$G$31,MATCH($B277,Mapping!$A$24:$A$31,0)) | AL277: =AL17+AL147 | AM277: =AM17+AM147 | AN277: =AN17+AN147 | AO277: =AO17+AO147 | AP277: =AP17+AP147 | AQ277: =AQ17+AQ147 | AR277: =AR17+AR147 | AS277: =AS17+AS147 | ... AY277: =AY17+AY147 | BA277: =BA17+BA147 | BB277: =BB17+BB147 | BC277: =BC17+BC147 | BD277: =BD17+BD147 | BE277: =BE17+BE147 | BF277: =BF17+BF147 | BG277: =BG17+BG147 | BH277: =BH17+BH147 | ... BN277: =BN17+BN147
B278: bio | C278: rod | D278: Post-tax price | Road | Biomass | E278: $/GJ | F278: Calculation | H278: mit.ptp.bio.rod | J278: =INDEX(Mapping!$C$5:$C$20,MATCH($C278,Mapping!$A$5:$A$20,0)) | K278: =INDEX(Mapping!$D$5:$D$20,MATCH($C278,Mapping!$A$5:$A$20,0)) | L278: =INDEX(Mapping!$C$24:$C$31,MATCH($B278,Mapping!$A$24:$A$31,0)) | M278: =INDEX(Mapping!$D$24:$D$31,MATCH($B278,Mapping!$A$24:$A$31,0)) | N278: =$B278&"."&IF(INDEX(Mapping!$E$24:$E$31,MATCH($B278,Mapping!$A$24:$A$31,0))="sub",INDEX(Mapping!$F$5:$F$20,MATCH($C278,Mapping!$A$5:$A$20,0)),"all") | O278: =INDEX(Mapping!$E$5:$E$20,MATCH($C278,Mapping!$A$5:$A$20,0)) | P278: =INDEX(Mapping!$G$24:$G$31,MATCH($B278,Mapping!$A$24:$A$31,0)) | AL278: =AL18+AL148 | AM278: =AM18+AM148 | AN278: =AN18+AN148 | AO278: =AO18+AO148 | AP278: =AP18+AP148 | AQ278: =AQ18+AQ148 | AR278: =AR18+AR148 | AS278: =AS18+AS148 | ... AY278: =AY18+AY148 | BA278: =BA18+BA148 | BB278: =BB18+BB148 | BC278: =BC18+BC148 | BD278: =BD18+BD148 | BE278: =BE18+BE148 | BF278: =BF18+BF148 | BG278: =BG18+BG148 | BH278: =BH18+BH148 | ... BN278: =BN18+BN148
B279: coa | C279: ral | D279: Post-tax price | Rail | Coal | E279: $/GJ | F279: Calculation | H279: mit.ptp.coa.ral | J279: =INDEX(Mapping!$C$5:$C$20,MATCH($C279,Mapping!$A$5:$A$20,0)) | K279: =INDEX(Mapping!$D$5:$D$20,MATCH($C279,Mapping!$A$5:$A$20,0)) | L279: =INDEX(Mapping!$C$24:$C$31,MATCH($B279,Mapping!$A$24:$A$31,0)) | M279: =INDEX(Mapping!$D$24:$D$31,MATCH($B279,Mapping!$A$24:$A$31,0)) | N279: =$B279&"."&IF(INDEX(Mapping!$E$24:$E$31,MATCH($B279,Mapping!$A$24:$A$31,0))="sub",INDEX(Mapping!$F$5:$F$20,MATCH($C279,Mapping!$A$5:$A$20,0)),"all") | O279: =INDEX(Mapping!$E$5:$E$20,MATCH($C279,Mapping!$A$5:$A$20,0)) | P279: =INDEX(Mapping!$G$24:$G$31,MATCH($B279,Mapping!$A$24:$A$31,0)) | AL279: =AL19+AL149 | AM279: =AM19+AM149 | AN279: =AN19+AN149 | AO279: =AO19+AO149 | AP279: =AP19+AP149 | AQ279: =AQ19+AQ149 | AR279: =AR19+AR149 | AS279: =AS19+AS149 | ... AY279: =AY19+AY149 | BA279: =BA19+BA149 | BB279: =BB19+BB149 | BC279: =BC19+BC149 | BD279: =BD19+BD149 | BE279: =BE19+BE149 | BF279: =BF19+BF149 | BG279: =BG19+BG149 | BH279: =BH19+BH149 | ... BN279: =BN19+BN149
B280: nga | C280: ral | D280: Post-tax price | Rail | Natural gas | E280: $/GJ | F280: Calculation | H280: mit.ptp.nga.ral | J280: =INDEX(Mapping!$C$5:$C$20,MATCH($C280,Mapping!$A$5:$A$20,0)) | K280: =INDEX(Mapping!$D$5:$D$20,MATCH($C280,Mapping!$A$5:$A$20,0)) | L280: =INDEX(Mapping!$C$24:$C$31,MATCH($B280,Mapping!$A$24:$A$31,0)) | M280: =INDEX(Mapping!$D$24:$D$31,MATCH($B280,Mapping!$A$24:$A$31,0)) | N280: =$B280&"."&IF(INDEX(Mapping!$E$24:$E$31,MATCH($B280,Mapping!$A$24:$A$31,0))="sub",INDEX(Mapping!$F$5:$F$20,MATCH($C280,Mapping!$A$5:$A$20,0)),"all") | O280: =INDEX(Mapping!$E$5:$E$20,MATCH($C280,Mapping!$A$5:$A$20,0)) | P280: =INDEX(Mapping!$G$24:$G$31,MATCH($B280,Mapping!$A$24:$A$31,0)) | AL280: =AL20+AL150 | AM280: =AM20+AM150 | AN280: =AN20+AN150 | AO280: =AO20+AO150 | AP280: =AP20+AP150 | AQ280: =AQ20+AQ150 | AR280: =AR20+AR150 | AS280: =AS20+AS150 | ... AY280: =AY20+AY150 | BA280: =BA20+BA150 | BB280: =BB20+BB150 | BC280: =BC20+BC150 | BD280: =BD20+BD150 | BE280: =BE20+BE150 | BF280: =BF20+BF150 | BG280: =BG20+BG150 | BH280: =BH20+BH150 | ... BN280: =BN20+BN150
B281: gso | C281: ral | D281: Post-tax price | Rail | Gasoline | E281: $/GJ | F281: Calculation | H281: mit.ptp.gso.ral | J281: =INDEX(Mapping!$C$5:$C$20,MATCH($C281,Mapping!$A$5:$A$20,0)) | K281: =INDEX(Mapping!$D$5:$D$20,MATCH($C281,Mapping!$A$5:$A$20,0)) | L281: =INDEX(Mapping!$C$24:$C$31,MATCH($B281,Mapping!$A$24:$A$31,0)) | M281: =INDEX(Mapping!$D$24:$D$31,MATCH($B281,Mapping!$A$24:$A$31,0)) | N281: =$B281&"."&IF(INDEX(Mapping!$E$24:$E$31,MATCH($B281,Mapping!$A$24:$A$31,0))="sub",INDEX(Mapping!$F$5:$F$20,MATCH($C281,Mapping!$A$5:$A$20,0)),"all") | O281: =INDEX(Mapping!$E$5:$E$20,MATCH($C281,Mapping!$A$5:$A$20,0)) | P281: =INDEX(Mapping!$G$24:$G$31,MATCH($B281,Mapping!$A$24:$A$31,0)) | AL281: =AL21+AL151 | AM281: =AM21+AM151 | AN281: =AN21+AN151 | AO281: =AO21+AO151 | AP281: =AP21+AP151 | AQ281: =AQ21+AQ151 | AR281: =AR21+AR151 | AS281: =AS21+AS151 | ... AY281: =AY21+AY151 | BA281: =BA21+BA151 | BB281: =BB21+BB151 | BC281: =BC21+BC151 | BD281: =BD21+BD151 | BE281: =BE21+BE151 | BF281: =BF21+BF151 | BG281: =BG21+BG151 | BH281: =BH21+BH151 | ... BN281: =BN21+BN151
B282: die | C282: ral | D282: Post-tax price | Rail | Diesel | E282: $/GJ | F282: Calculation | H282: mit.ptp.die.ral | J282: =INDEX(Mapping!$C$5:$C$20,MATCH($C282,Mapping!$A$5:$A$20,0)) | K282: =INDEX(Mapping!$D$5:$D$20,MATCH($C282,Mapping!$A$5:$A$20,0)) | L282: =INDEX(Mapping!$C$24:$C$31,MATCH($B282,Mapping!$A$24:$A$31,0)) | M282: =INDEX(Mapping!$D$24:$D$31,MATCH($B282,Mapping!$A$24:$A$31,0)) | N282: =$B282&"."&IF(INDEX(Mapping!$E$24:$E$31,MATCH($B282,Mapping!$A$24:$A$31,0))="sub",INDEX(Mapping!$F$5:$F$20,MATCH($C282,Mapping!$A$5:$A$20,0)),"all") | O282: =INDEX(Mapping!$E$5:$E$20,MATCH($C282,Mapping!$A$5:$A$20,0)) | P282: =INDEX(Mapping!$G$24:$G$31,MATCH($B282,Mapping!$A$24:$A$31,0)) | AL282: =AL22+AL152 | AM282: =AM22+AM152 | AN282: =AN22+AN152 | AO282: =AO22+AO152 | AP282: =AP22+AP152 | AQ282: =AQ22+AQ152 | AR282: =AR22+AR152 | AS282: =AS22+AS152 | ... AY282: =AY22+AY152 | BA282: =BA22+BA152 | BB282: =BB22+BB152 | BC282: =BC22+BC152 | BD282: =BD22+BD152 | BE282: =BE22+BE152 | BF282: =BF22+BF152 | BG282: =BG22+BG152 | BH282: =BH22+BH152 | ... BN282: =BN22+BN152
... B398: bio | C398: oen | D398: Post-tax price | Other energy use | Biomass | E398: $/GJ | F398: Calculation | H398: mit.ptp.bio.oen | J398: =INDEX(Mapping!$C$5:$C$20,MATCH($C398,Mapping!$A$5:$A$20,0)) | K398: =INDEX(Mapping!$D$5:$D$20,MATCH($C398,Mapping!$A$5:$A$20,0)) | L398: =INDEX(Mapping!$C$24:$C$31,MATCH($B398,Mapping!$A$24:$A$31,0)) | M398: =INDEX(Mapping!$D$24:$D$31,MATCH($B398,Mapping!$A$24:$A$31,0)) | N398: =$B398&"."&IF(INDEX(Mapping!$E$24:$E$31,MATCH($B398,Mapping!$A$24:$A$31,0))="sub",INDEX(Mapping!$F$5:$F$20,MATCH($C398,Mapping!$A$5:$A$20,0)),"all") | O398: =INDEX(Mapping!$E$5:$E$20,MATCH($C398,Mapping!$A$5:$A$20,0)) | P398: =INDEX(Mapping!$G$24:$G$31,MATCH($B398,Mapping!$A$24:$A$31,0)) | AL398: =AL138+AL268 | AM398: =AM138+AM268 | AN398: =AN138+AN268 | AO398: =AO138+AO268 | AP398: =AP138+AP268 | AQ398: =AQ138+AQ268 | AR398: =AR138+AR268 | AS398: =AS138+AS268 | ... AY398: =AY138+AY268 | BA398: =BA138+BA268 | BB398: =BB138+BB268 | BC398: =BC138+BC268 | BD398: =BD138+BD268 | BE398: =BE138+BE268 | BF398: =BF138+BF268 | BG398: =BG138+BG268 | BH398: =BH138+BH268 | ... BN398: =BN138+BN268
A400: Fuel use (CPAT docs 3.3.3) | Q400: eps_Y GDP | R400: eps_U usage | S400: eps_F efficiency | T400: alpha AEEI | U400: buffer | V400: eps_Y GDP | W400: eps_U usage | X400: eps_F efficiency | Y400: alpha AEEI | Z400: buffer | AA400: eps_Y GDP | AB400: eps_U usage | AC400: eps_F efficiency | AD400: alpha AEEI | AE400: buffer | AF400: eps_Y GDP | AG400: eps_U usage | AH400: eps_F efficiency | AI400: alpha AEEI | AJ400: buffer
B401: coa | C401: rod | D401: Fuel use | Road | Coal | E401: ktoe | F401: EnergyCons (base year), Elasticities | G401: mit.enc.coa.rod | H401: mit.enc.coa.rod | J401: =INDEX(Mapping!$C$5:$C$20,MATCH($C401,Mapping!$A$5:$A$20,0)) | K401: =INDEX(Mapping!$D$5:$D$20,MATCH($C401,Mapping!$A$5:$A$20,0)) | L401: =INDEX(Mapping!$C$24:$C$31,MATCH($B401,Mapping!$A$24:$A$31,0)) | M401: =INDEX(Mapping!$D$24:$D$31,MATCH($B401,Mapping!$A$24:$A$31,0)) | N401: =$B401&"."&IF(INDEX(Mapping!$E$24:$E$31,MATCH($B401,Mapping!$A$24:$A$31,0))="sub",INDEX(Mapping!$F$5:$F$20,MATCH($C401,Mapping!$A$5:$A$20,0)),"all") | O401: =INDEX(Mapping!$E$5:$E$20,MATCH($C401,Mapping!$A$5:$A$20,0)) | P401: =INDEX(Mapping!$G$24:$G$31,MATCH($B401,Mapping!$A$24:$A$31,0)) | Q401: =INDEX(Elasticities!$F$4:$I$200,MATCH("inc|"&$L401&"|"&$K401,Elasticities!$A$4:$A$200,0),MATCH(Settings!$C$6,Elasticities!$F$3:$I$3,0)) | R401: =INDEX(Elasticities!$F$4:$I$200,MATCH("usg|"&$L401&"|"&$K401,Elasticities!$A$4:$A$200,0),MATCH(Settings!$C$6,Elasticities!$F$3:$I$3,0)) | S401: =INDEX(Elasticities!$F$4:$I$200,MATCH("eff|"&$L401&"|"&$K401,Elasticities!$A$4:$A$200,0),MATCH(Settings!$C$6,Elasticities!$F$3:$I$3,0)) | T401: =INDEX(Elasticities!$F$4:$I$200,MATCH("aei|"&$M401&"|"&$K401,Elasticities!$A$4:$A$200,0),MATCH(Settings!$C$6,Elasticities!$F$3:$I$3,0)) | V401: =Q401 | W401: =R401 | X401: =S401 | Y401: =T401 | AA401: =Q401 | AB401: =R401 | AC401: =S401 | AD401: =T401 | AF401: =Q401 | AG401: =R401 | AH401: =S401 | AI401: =T401 | AL401: =INDEX(EnergyCons!$F$4:$F$5000,MATCH(Settings!$C$4&"|"&AL$5&"|"&$C401&"|"&$B401,EnergyCons!$A$4:$A$5000,0)) | AM401: =AL401*(1/(1+INDEX($Q401:$AJ401,1,(AM$4-1)*5+4)))^(1+INDEX($Q401:$AJ401,1,(AM$4-1)*5+2))*(1+AM$7)^INDEX($Q401:$AJ401,1,(AM$4-1)*5+1)*(AM271/AL271)^INDEX($Q401:$AJ401,1,(AM$4-1)*5+2)*(AM271/AL271)^(INDEX($Q401:$AJ401,1,(AM$4-1)*5+3)*(1+INDEX($Q401:$AJ401,1,(AM$4-1)*5+2))) | AN401: =AM401*(1/(1+INDEX($Q401:$AJ401,1,(AN$4-1)*5+4)))^(1+INDEX($Q401:$AJ401,1,(AN$4-1)*5+2))*(1+AN$7)^INDEX($Q401:$AJ401,1,(AN$4-1)*5+1)*(AN271/AM271)^INDEX($Q401:$AJ401,1,(AN$4-1)*5+2)*(AN271/AM271)^(INDEX($Q401:$AJ401,1,(AN$4-1)*5+3)*(1+INDEX($Q401:$AJ401,1,(AN$4-1)*5+2))) | AO401: =AN401*(1/(1+INDEX($Q401:$AJ401,1,(AO$4-1)*5+4)))^(1+INDEX($Q401:$AJ401,1,(AO$4-1)*5+2))*(1+AO$7)^INDEX($Q401:$AJ401,1,(AO$4-1)*5+1)*(AO271/AN271)^INDEX($Q401:$AJ401,1,(AO$4-1)*5+2)*(AO271/AN271)^(INDEX($Q401:$AJ401,1,(AO$4-1)*5+3)*(1+INDEX($Q401:$AJ401,1,(AO$4-1)*5+2))) | AP401: =AO401*(1/(1+INDEX($Q401:$AJ401,1,(AP$4-1)*5+4)))^(1+INDEX($Q401:$AJ401,1,(AP$4-1)*5+2))*(1+AP$7)^INDEX($Q401:$AJ401,1,(AP$4-1)*5+1)*(AP271/AO271)^INDEX($Q401:$AJ401,1,(AP$4-1)*5+2)*(AP271/AO271)^(INDEX($Q401:$AJ401,1,(AP$4-1)*5+3)*(1+INDEX($Q401:$AJ401,1,(AP$4-1)*5+2))) | AQ401: =AP401*(1/(1+INDEX($Q401:$AJ401,1,(AQ$4-1)*5+4)))^(1+INDEX($Q401:$AJ401,1,(AQ$4-1)*5+2))*(1+AQ$7)^INDEX($Q401:$AJ401,1,(AQ$4-1)*5+1)*(AQ271/AP271)^INDEX($Q401:$AJ401,1,(AQ$4-1)*5+2)*(AQ271/AP271)^(INDEX($Q401:$AJ401,1,(AQ$4-1)*5+3)*(1+INDEX($Q401:$AJ401,1,(AQ$4-1)*5+2))) | AR401: =AQ401*(1/(1+INDEX($Q401:$AJ401,1,(AR$4-1)*5+4)))^(1+INDEX($Q401:$AJ401,1,(AR$4-1)*5+2))*(1+AR$7)^INDEX($Q401:$AJ401,1,(AR$4-1)*5+1)*(AR271/AQ271)^INDEX($Q401:$AJ401,1,(AR$4-1)*5+2)*(AR271/AQ271)^(INDEX($Q401:$AJ401,1,(AR$4-1)*5+3)*(1+INDEX($Q401:$AJ401,1,(AR$4-1)*5+2))) | AS401: =AR401*(1/(1+INDEX($Q401:$AJ401,1,(AS$4-1)*5+4)))^(1+INDEX($Q401:$AJ401,1,(AS$4-1)*5+2))*(1+AS$7)^INDEX($Q401:$AJ401,1,(AS$4-1)*5+1)*(AS271/AR271)^INDEX($Q401:$AJ401,1,(AS$4-1)*5+2)*(AS271/AR271)^(INDEX($Q401:$AJ401,1,(AS$4-1)*5+3)*(1+INDEX($Q401:$AJ401,1,(AS$4-1)*5+2))) | AT401: =AS401*(1/(1+INDEX($Q401:$AJ401,1,(AT$4-1)*5+4)))^(1+INDEX($Q401:$AJ401,1,(AT$4-1)*5+2))*(1+AT$7)^INDEX($Q401:$AJ401,1,(AT$4-1)*5+1)*(AT271/AS271)^INDEX($Q401:$AJ401,1,(AT$4-1)*5+2)*(AT271/AS271)^(INDEX($Q401:$AJ401,1,(AT$4-1)*5+3)*(1+INDEX($Q401:$AJ401,1,(AT$4-1)*5+2))) | ... AY401: =AX401*(1/(1+INDEX($Q401:$AJ401,1,(AY$4-1)*5+4)))^(1+INDEX($Q401:$AJ401,1,(AY$4-1)*5+2))*(1+AY$7)^INDEX($Q401:$AJ401,1,(AY$4-1)*5+1)*(AY271/AX271)^INDEX($Q401:$AJ401,1,(AY$4-1)*5+2)*(AY271/AX271)^(INDEX($Q401:$AJ401,1,(AY$4-1)*5+3)*(1+INDEX($Q401:$AJ401,1,(AY$4-1)*5+2))) | BA401: =INDEX(EnergyCons!$F$4:$F$5000,MATCH(Settings!$C$4&"|"&BA$5&"|"&$C401&"|"&$B401,EnergyCons!$A$4:$A$5000,0)) | BB401: =BA401*(1/(1+INDEX($Q401:$AJ401,1,(BB$4-1)*5+4)))^(1+INDEX($Q401:$AJ401,1,(BB$4-1)*5+2))*(1+BB$7)^INDEX($Q401:$AJ401,1,(BB$4-1)*5+1)*(BB271/BA271)^INDEX($Q401:$AJ401,1,(BB$4-1)*5+2)*(BB271/BA271)^(INDEX($Q401:$AJ401,1,(BB$4-1)*5+3)*(1+INDEX($Q401:$AJ401,1,(BB$4-1)*5+2))) | BC401: =BB401*(1/(1+INDEX($Q401:$AJ401,1,(BC$4-1)*5+4)))^(1+INDEX($Q401:$AJ401,1,(BC$4-1)*5+2))*(1+BC$7)^INDEX($Q401:$AJ401,1,(BC$4-1)*5+1)*(BC271/BB271)^INDEX($Q401:$AJ401,1,(BC$4-1)*5+2)*(BC271/BB271)^(INDEX($Q401:$AJ401,1,(BC$4-1)*5+3)*(1+INDEX($Q401:$AJ401,1,(BC$4-1)*5+2))) | BD401: =BC401*(1/(1+INDEX($Q401:$AJ401,1,(BD$4-1)*5+4)))^(1+INDEX($Q401:$AJ401,1,(BD$4-1)*5+2))*(1+BD$7)^INDEX($Q401:$AJ401,1,(BD$4-1)*5+1)*(BD271/BC271)^INDEX($Q401:$AJ401,1,(BD$4-1)*5+2)*(BD271/BC271)^(INDEX($Q401:$AJ401,1,(BD$4-1)*5+3)*(1+INDEX($Q401:$AJ401,1,(BD$4-1)*5+2))) | BE401: =BD401*(1/(1+INDEX($Q401:$AJ401,1,(BE$4-1)*5+4)))^(1+INDEX($Q401:$AJ401,1,(BE$4-1)*5+2))*(1+BE$7)^INDEX($Q401:$AJ401,1,(BE$4-1)*5+1)*(BE271/BD271)^INDEX($Q401:$AJ401,1,(BE$4-1)*5+2)*(BE271/BD271)^(INDEX($Q401:$AJ401,1,(BE$4-1)*5+3)*(1+INDEX($Q401:$AJ401,1,(BE$4-1)*5+2))) | BF401: =BE401*(1/(1+INDEX($Q401:$AJ401,1,(BF$4-1)*5+4)))^(1+INDEX($Q401:$AJ401,1,(BF$4-1)*5+2))*(1+BF$7)^INDEX($Q401:$AJ401,1,(BF$4-1)*5+1)*(BF271/BE271)^INDEX($Q401:$AJ401,1,(BF$4-1)*5+2)*(BF271/BE271)^(INDEX($Q401:$AJ401,1,(BF$4-1)*5+3)*(1+INDEX($Q401:$AJ401,1,(BF$4-1)*5+2))) | BG401: =BF401*(1/(1+INDEX($Q401:$AJ401,1,(BG$4-1)*5+4)))^(1+INDEX($Q401:$AJ401,1,(BG$4-1)*5+2))*(1+BG$7)^INDEX($Q401:$AJ401,1,(BG$4-1)*5+1)*(BG271/BF271)^INDEX($Q401:$AJ401,1,(BG$4-1)*5+2)*(BG271/BF271)^(INDEX($Q401:$AJ401,1,(BG$4-1)*5+3)*(1+INDEX($Q401:$AJ401,1,(BG$4-1)*5+2))) | BH401: =BG401*(1/(1+INDEX($Q401:$AJ401,1,(BH$4-1)*5+4)))^(1+INDEX($Q401:$AJ401,1,(BH$4-1)*5+2))*(1+BH$7)^INDEX($Q401:$AJ401,1,(BH$4-1)*5+1)*(BH271/BG271)^INDEX($Q401:$AJ401,1,(BH$4-1)*5+2)*(BH271/BG271)^(INDEX($Q401:$AJ401,1,(BH$4-1)*5+3)*(1+INDEX($Q401:$AJ401,1,(BH$4-1)*5+2))) | BI401: =BH401*(1/(1+INDEX($Q401:$AJ401,1,(BI$4-1)*5+4)))^(1+INDEX($Q401:$AJ401,1,(BI$4-1)*5+2))*(1+BI$7)^INDEX($Q401:$AJ401,1,(BI$4-1)*5+1)*(BI271/BH271)^INDEX($Q401:$AJ401,1,(BI$4-1)*5+2)*(BI271/BH271)^(INDEX($Q401:$AJ401,1,(BI$4-1)*5+3)*(1+INDEX($Q401:$AJ401,1,(BI$4-1)*5+2))) | ... BN401: =BM401*(1/(1+INDEX($Q401:$AJ401,1,(BN$4-1)*5+4)))^(1+INDEX($Q401:$AJ401,1,(BN$4-1)*5+2))*(1+BN$7)^INDEX($Q401:$AJ401,1,(BN$4-1)*5+1)*(BN271/BM271)^INDEX($Q401:$AJ401,1,(BN$4-1)*5+2)*(BN271/BM271)^(INDEX($Q401:$AJ401,1,(BN$4-1)*5+3)*(1+INDEX($Q401:$AJ401,1,(BN$4-1)*5+2)))
B402: nga | C402: rod | D402: Fuel use | Road | Natural gas | E402: ktoe | F402: EnergyCons (base year), Elasticities | G402: mit.enc.nga.rod | H402: mit.enc.nga.rod | J402: =INDEX(Mapping!$C$5:$C$20,MATCH($C402,Mapping!$A$5:$A$20,0)) | K402: =INDEX(Mapping!$D$5:$D$20,MATCH($C402,Mapping!$A$5:$A$20,0)) | L402: =INDEX(Mapping!$C$24:$C$31,MATCH($B402,Mapping!$A$24:$A$31,0)) | M402: =INDEX(Mapping!$D$24:$D$31,MATCH($B402,Mapping!$A$24:$A$31,0)) | N402: =$B402&"."&IF(INDEX(Mapping!$E$24:$E$31,MATCH($B402,Mapping!$A$24:$A$31,0))="sub",INDEX(Mapping!$F$5:$F$20,MATCH($C402,Mapping!$A$5:$A$20,0)),"all") | O402: =INDEX(Mapping!$E$5:$E$20,MATCH($C402,Mapping!$A$5:$A$20,0)) | P402: =INDEX(Mapping!$G$24:$G$31,MATCH($B402,Mapping!$A$24:$A$31,0)) | Q402: =INDEX(Elasticities!$F$4:$I$200,MATCH("inc|"&$L402&"|"&$K402,Elasticities!$A$4:$A$200,0),MATCH(Settings!$C$6,Elasticities!$F$3:$I$3,0)) | R402: =INDEX(Elasticities!$F$4:$I$200,MATCH("usg|"&$L402&"|"&$K402,Elasticities!$A$4:$A$200,0),MATCH(Settings!$C$6,Elasticities!$F$3:$I$3,0)) | S402: =INDEX(Elasticities!$F$4:$I$200,MATCH("eff|"&$L402&"|"&$K402,Elasticities!$A$4:$A$200,0),MATCH(Settings!$C$6,Elasticities!$F$3:$I$3,0)) | T402: =INDEX(Elasticities!$F$4:$I$200,MATCH("aei|"&$M402&"|"&$K402,Elasticities!$A$4:$A$200,0),MATCH(Settings!$C$6,Elasticities!$F$3:$I$3,0)) | V402: =Q402 | W402: =R402 | X402: =S402 | Y402: =T402 | AA402: =Q402 | AB402: =R402 | AC402: =S402 | AD402: =T402 | AF402: =Q402 | AG402: =R402 | AH402: =S402 | AI402: =T402 | AL402: =INDEX(EnergyCons!$F$4:$F$5000,MATCH(Settings!$C$4&"|"&AL$5&"|"&$C402&"|"&$B402,EnergyCons!$A$4:$A$5000,0)) | AM402: =AL402*(1/(1+INDEX($Q402:$AJ402,1,(AM$4-1)*5+4)))^(1+INDEX($Q402:$AJ402,1,(AM$4-1)*5+2))*(1+AM$7)^INDEX($Q402:$AJ402,1,(AM$4-1)*5+1)*(AM272/AL272)^INDEX($Q402:$AJ402,1,(AM$4-1)*5+2)*(AM272/AL272)^(INDEX($Q402:$AJ402,1,(AM$4-1)*5+3)*(1+INDEX($Q402:$AJ402,1,(AM$4-1)*5+2))) | AN402: =AM402*(1/(1+INDEX($Q402:$AJ402,1,(AN$4-1)*5+4)))^(1+INDEX($Q402:$AJ402,1,(AN$4-1)*5+2))*(1+AN$7)^INDEX($Q402:$AJ402,1,(AN$4-1)*5+1)*(AN272/AM272)^INDEX($Q402:$AJ402,1,(AN$4-1)*5+2)*(AN272/AM272)^(INDEX($Q402:$AJ402,1,(AN$4-1)*5+3)*(1+INDEX($Q402:$AJ402,1,(AN$4-1)*5+2))) | AO402: =AN402*(1/(1+INDEX($Q402:$AJ402,1,(AO$4-1)*5+4)))^(1+INDEX($Q402:$AJ402,1,(AO$4-1)*5+2))*(1+AO$7)^INDEX($Q402:$AJ402,1,(AO$4-1)*5+1)*(AO272/AN272)^INDEX($Q402:$AJ402,1,(AO$4-1)*5+2)*(AO272/AN272)^(INDEX($Q402:$AJ402,1,(AO$4-1)*5+3)*(1+INDEX($Q402:$AJ402,1,(AO$4-1)*5+2))) | AP402: =AO402*(1/(1+INDEX($Q402:$AJ402,1,(AP$4-1)*5+4)))^(1+INDEX($Q402:$AJ402,1,(AP$4-1)*5+2))*(1+AP$7)^INDEX($Q402:$AJ402,1,(AP$4-1)*5+1)*(AP272/AO272)^INDEX($Q402:$AJ402,1,(AP$4-1)*5+2)*(AP272/AO272)^(INDEX($Q402:$AJ402,1,(AP$4-1)*5+3)*(1+INDEX($Q402:$AJ402,1,(AP$4-1)*5+2))) | AQ402: =AP402*(1/(1+INDEX($Q402:$AJ402,1,(AQ$4-1)*5+4)))^(1+INDEX($Q402:$AJ402,1,(AQ$4-1)*5+2))*(1+AQ$7)^INDEX($Q402:$AJ402,1,(AQ$4-1)*5+1)*(AQ272/AP272)^INDEX($Q402:$AJ402,1,(AQ$4-1)*5+2)*(AQ272/AP272)^(INDEX($Q402:$AJ402,1,(AQ$4-1)*5+3)*(1+INDEX($Q402:$AJ402,1,(AQ$4-1)*5+2))) | AR402: =AQ402*(1/(1+INDEX($Q402:$AJ402,1,(AR$4-1)*5+4)))^(1+INDEX($Q402:$AJ402,1,(AR$4-1)*5+2))*(1+AR$7)^INDEX($Q402:$AJ402,1,(AR$4-1)*5+1)*(AR272/AQ272)^INDEX($Q402:$AJ402,1,(AR$4-1)*5+2)*(AR272/AQ272)^(INDEX($Q402:$AJ402,1,(AR$4-1)*5+3)*(1+INDEX($Q402:$AJ402,1,(AR$4-1)*5+2))) | AS402: =AR402*(1/(1+INDEX($Q402:$AJ402,1,(AS$4-1)*5+4)))^(1+INDEX($Q402:$AJ402,1,(AS$4-1)*5+2))*(1+AS$7)^INDEX($Q402:$AJ402,1,(AS$4-1)*5+1)*(AS272/AR272)^INDEX($Q402:$AJ402,1,(AS$4-1)*5+2)*(AS272/AR272)^(INDEX($Q402:$AJ402,1,(AS$4-1)*5+3)*(1+INDEX($Q402:$AJ402,1,(AS$4-1)*5+2))) | AT402: =AS402*(1/(1+INDEX($Q402:$AJ402,1,(AT$4-1)*5+4)))^(1+INDEX($Q402:$AJ402,1,(AT$4-1)*5+2))*(1+AT$7)^INDEX($Q402:$AJ402,1,(AT$4-1)*5+1)*(AT272/AS272)^INDEX($Q402:$AJ402,1,(AT$4-1)*5+2)*(AT272/AS272)^(INDEX($Q402:$AJ402,1,(AT$4-1)*5+3)*(1+INDEX($Q402:$AJ402,1,(AT$4-1)*5+2))) | ... AY402: =AX402*(1/(1+INDEX($Q402:$AJ402,1,(AY$4-1)*5+4)))^(1+INDEX($Q402:$AJ402,1,(AY$4-1)*5+2))*(1+AY$7)^INDEX($Q402:$AJ402,1,(AY$4-1)*5+1)*(AY272/AX272)^INDEX($Q402:$AJ402,1,(AY$4-1)*5+2)*(AY272/AX272)^(INDEX($Q402:$AJ402,1,(AY$4-1)*5+3)*(1+INDEX($Q402:$AJ402,1,(AY$4-1)*5+2))) | BA402: =INDEX(EnergyCons!$F$4:$F$5000,MATCH(Settings!$C$4&"|"&BA$5&"|"&$C402&"|"&$B402,EnergyCons!$A$4:$A$5000,0)) | BB402: =BA402*(1/(1+INDEX($Q402:$AJ402,1,(BB$4-1)*5+4)))^(1+INDEX($Q402:$AJ402,1,(BB$4-1)*5+2))*(1+BB$7)^INDEX($Q402:$AJ402,1,(BB$4-1)*5+1)*(BB272/BA272)^INDEX($Q402:$AJ402,1,(BB$4-1)*5+2)*(BB272/BA272)^(INDEX($Q402:$AJ402,1,(BB$4-1)*5+3)*(1+INDEX($Q402:$AJ402,1,(BB$4-1)*5+2))) | BC402: =BB402*(1/(1+INDEX($Q402:$AJ402,1,(BC$4-1)*5+4)))^(1+INDEX($Q402:$AJ402,1,(BC$4-1)*5+2))*(1+BC$7)^INDEX($Q402:$AJ402,1,(BC$4-1)*5+1)*(BC272/BB272)^INDEX($Q402:$AJ402,1,(BC$4-1)*5+2)*(BC272/BB272)^(INDEX($Q402:$AJ402,1,(BC$4-1)*5+3)*(1+INDEX($Q402:$AJ402,1,(BC$4-1)*5+2))) | BD402: =BC402*(1/(1+INDEX($Q402:$AJ402,1,(BD$4-1)*5+4)))^(1+INDEX($Q402:$AJ402,1,(BD$4-1)*5+2))*(1+BD$7)^INDEX($Q402:$AJ402,1,(BD$4-1)*5+1)*(BD272/BC272)^INDEX($Q402:$AJ402,1,(BD$4-1)*5+2)*(BD272/BC272)^(INDEX($Q402:$AJ402,1,(BD$4-1)*5+3)*(1+INDEX($Q402:$AJ402,1,(BD$4-1)*5+2))) | BE402: =BD402*(1/(1+INDEX($Q402:$AJ402,1,(BE$4-1)*5+4)))^(1+INDEX($Q402:$AJ402,1,(BE$4-1)*5+2))*(1+BE$7)^INDEX($Q402:$AJ402,1,(BE$4-1)*5+1)*(BE272/BD272)^INDEX($Q402:$AJ402,1,(BE$4-1)*5+2)*(BE272/BD272)^(INDEX($Q402:$AJ402,1,(BE$4-1)*5+3)*(1+INDEX($Q402:$AJ402,1,(BE$4-1)*5+2))) | BF402: =BE402*(1/(1+INDEX($Q402:$AJ402,1,(BF$4-1)*5+4)))^(1+INDEX($Q402:$AJ402,1,(BF$4-1)*5+2))*(1+BF$7)^INDEX($Q402:$AJ402,1,(BF$4-1)*5+1)*(BF272/BE272)^INDEX($Q402:$AJ402,1,(BF$4-1)*5+2)*(BF272/BE272)^(INDEX($Q402:$AJ402,1,(BF$4-1)*5+3)*(1+INDEX($Q402:$AJ402,1,(BF$4-1)*5+2))) | BG402: =BF402*(1/(1+INDEX($Q402:$AJ402,1,(BG$4-1)*5+4)))^(1+INDEX($Q402:$AJ402,1,(BG$4-1)*5+2))*(1+BG$7)^INDEX($Q402:$AJ402,1,(BG$4-1)*5+1)*(BG272/BF272)^INDEX($Q402:$AJ402,1,(BG$4-1)*5+2)*(BG272/BF272)^(INDEX($Q402:$AJ402,1,(BG$4-1)*5+3)*(1+INDEX($Q402:$AJ402,1,(BG$4-1)*5+2))) | BH402: =BG402*(1/(1+INDEX($Q402:$AJ402,1,(BH$4-1)*5+4)))^(1+INDEX($Q402:$AJ402,1,(BH$4-1)*5+2))*(1+BH$7)^INDEX($Q402:$AJ402,1,(BH$4-1)*5+1)*(BH272/BG272)^INDEX($Q402:$AJ402,1,(BH$4-1)*5+2)*(BH272/BG272)^(INDEX($Q402:$AJ402,1,(BH$4-1)*5+3)*(1+INDEX($Q402:$AJ402,1,(BH$4-1)*5+2))) | BI402: =BH402*(1/(1+INDEX($Q402:$AJ402,1,(BI$4-1)*5+4)))^(1+INDEX($Q402:$AJ402,1,(BI$4-1)*5+2))*(1+BI$7)^INDEX($Q402:$AJ402,1,(BI$4-1)*5+1)*(BI272/BH272)^INDEX($Q402:$AJ402,1,(BI$4-1)*5+2)*(BI272/BH272)^(INDEX($Q402:$AJ402,1,(BI$4-1)*5+3)*(1+INDEX($Q402:$AJ402,1,(BI$4-1)*5+2))) | ... BN402: =BM402*(1/(1+INDEX($Q402:$AJ402,1,(BN$4-1)*5+4)))^(1+INDEX($Q402:$AJ402,1,(BN$4-1)*5+2))*(1+BN$7)^INDEX($Q402:$AJ402,1,(BN$4-1)*5+1)*(BN272/BM272)^INDEX($Q402:$AJ402,1,(BN$4-1)*5+2)*(BN272/BM272)^(INDEX($Q402:$AJ402,1,(BN$4-1)*5+3)*(1+INDEX($Q402:$AJ402,1,(BN$4-1)*5+2)))
B403: gso | C403: rod | D403: Fuel use | Road | Gasoline | E403: ktoe | F403: EnergyCons (base year), Elasticities | G403: mit.enc.gso.rod | H403: mit.enc.gso.rod | J403: =INDEX(Mapping!$C$5:$C$20,MATCH($C403,Mapping!$A$5:$A$20,0)) | K403: =INDEX(Mapping!$D$5:$D$20,MATCH($C403,Mapping!$A$5:$A$20,0)) | L403: =INDEX(Mapping!$C$24:$C$31,MATCH($B403,Mapping!$A$24:$A$31,0)) | M403: =INDEX(Mapping!$D$24:$D$31,MATCH($B403,Mapping!$A$24:$A$31,0)) | N403: =$B403&"."&IF(INDEX(Mapping!$E$24:$E$31,MATCH($B403,Mapping!$A$24:$A$31,0))="sub",INDEX(Mapping!$F$5:$F$20,MATCH($C403,Mapping!$A$5:$A$20,0)),"all") | O403: =INDEX(Mapping!$E$5:$E$20,MATCH($C403,Mapping!$A$5:$A$20,0)) | P403: =INDEX(Mapping!$G$24:$G$31,MATCH($B403,Mapping!$A$24:$A$31,0)) | Q403: =INDEX(Elasticities!$F$4:$I$200,MATCH("inc|"&$L403&"|"&$K403,Elasticities!$A$4:$A$200,0),MATCH(Settings!$C$6,Elasticities!$F$3:$I$3,0)) | R403: =INDEX(Elasticities!$F$4:$I$200,MATCH("usg|"&$L403&"|"&$K403,Elasticities!$A$4:$A$200,0),MATCH(Settings!$C$6,Elasticities!$F$3:$I$3,0)) | S403: =INDEX(Elasticities!$F$4:$I$200,MATCH("eff|"&$L403&"|"&$K403,Elasticities!$A$4:$A$200,0),MATCH(Settings!$C$6,Elasticities!$F$3:$I$3,0)) | T403: =INDEX(Elasticities!$F$4:$I$200,MATCH("aei|"&$M403&"|"&$K403,Elasticities!$A$4:$A$200,0),MATCH(Settings!$C$6,Elasticities!$F$3:$I$3,0)) | V403: =Q403 | W403: =R403 | X403: =S403 | Y403: =T403 | AA403: =Q403 | AB403: =R403 | AC403: =S403 | AD403: =T403 | AF403: =Q403 | AG403: =R403 | AH403: =S403 | AI403: =T403 | AL403: =INDEX(EnergyCons!$F$4:$F$5000,MATCH(Settings!$C$4&"|"&AL$5&"|"&$C403&"|"&$B403,EnergyCons!$A$4:$A$5000,0)) | AM403: =AL403*(1/(1+INDEX($Q403:$AJ403,1,(AM$4-1)*5+4)))^(1+INDEX($Q403:$AJ403,1,(AM$4-1)*5+2))*(1+AM$7)^INDEX($Q403:$AJ403,1,(AM$4-1)*5+1)*(AM273/AL273)^INDEX($Q403:$AJ403,1,(AM$4-1)*5+2)*(AM273/AL273)^(INDEX($Q403:$AJ403,1,(AM$4-1)*5+3)*(1+INDEX($Q403:$AJ403,1,(AM$4-1)*5+2))) | AN403: =AM403*(1/(1+INDEX($Q403:$AJ403,1,(AN$4-1)*5+4)))^(1+INDEX($Q403:$AJ403,1,(AN$4-1)*5+2))*(1+AN$7)^INDEX($Q403:$AJ403,1,(AN$4-1)*5+1)*(AN273/AM273)^INDEX($Q403:$AJ403,1,(AN$4-1)*5+2)*(AN273/AM273)^(INDEX($Q403:$AJ403,1,(AN$4-1)*5+3)*(1+INDEX($Q403:$AJ403,1,(AN$4-1)*5+2))) | AO403: =AN403*(1/(1+INDEX($Q403:$AJ403,1,(AO$4-1)*5+4)))^(1+INDEX($Q403:$AJ403,1,(AO$4-1)*5+2))*(1+AO$7)^INDEX($Q403:$AJ403,1,(AO$4-1)*5+1)*(AO273/AN273)^INDEX($Q403:$AJ403,1,(AO$4-1)*5+2)*(AO273/AN273)^(INDEX($Q403:$AJ403,1,(AO$4-1)*5+3)*(1+INDEX($Q403:$AJ403,1,(AO$4-1)*5+2))) | AP403: =AO403*(1/(1+INDEX($Q403:$AJ403,1,(AP$4-1)*5+4)))^(1+INDEX($Q403:$AJ403,1,(AP$4-1)*5+2))*(1+AP$7)^INDEX($Q403:$AJ403,1,(AP$4-1)*5+1)*(AP273/AO273)^INDEX($Q403:$AJ403,1,(AP$4-1)*5+2)*(AP273/AO273)^(INDEX($Q403:$AJ403,1,(AP$4-1)*5+3)*(1+INDEX($Q403:$AJ403,1,(AP$4-1)*5+2))) | AQ403: =AP403*(1/(1+INDEX($Q403:$AJ403,1,(AQ$4-1)*5+4)))^(1+INDEX($Q403:$AJ403,1,(AQ$4-1)*5+2))*(1+AQ$7)^INDEX($Q403:$AJ403,1,(AQ$4-1)*5+1)*(AQ273/AP273)^INDEX($Q403:$AJ403,1,(AQ$4-1)*5+2)*(AQ273/AP273)^(INDEX($Q403:$AJ403,1,(AQ$4-1)*5+3)*(1+INDEX($Q403:$AJ403,1,(AQ$4-1)*5+2))) | AR403: =AQ403*(1/(1+INDEX($Q403:$AJ403,1,(AR$4-1)*5+4)))^(1+INDEX($Q403:$AJ403,1,(AR$4-1)*5+2))*(1+AR$7)^INDEX($Q403:$AJ403,1,(AR$4-1)*5+1)*(AR273/AQ273)^INDEX($Q403:$AJ403,1,(AR$4-1)*5+2)*(AR273/AQ273)^(INDEX($Q403:$AJ403,1,(AR$4-1)*5+3)*(1+INDEX($Q403:$AJ403,1,(AR$4-1)*5+2))) | AS403: =AR403*(1/(1+INDEX($Q403:$AJ403,1,(AS$4-1)*5+4)))^(1+INDEX($Q403:$AJ403,1,(AS$4-1)*5+2))*(1+AS$7)^INDEX($Q403:$AJ403,1,(AS$4-1)*5+1)*(AS273/AR273)^INDEX($Q403:$AJ403,1,(AS$4-1)*5+2)*(AS273/AR273)^(INDEX($Q403:$AJ403,1,(AS$4-1)*5+3)*(1+INDEX($Q403:$AJ403,1,(AS$4-1)*5+2))) | AT403: =AS403*(1/(1+INDEX($Q403:$AJ403,1,(AT$4-1)*5+4)))^(1+INDEX($Q403:$AJ403,1,(AT$4-1)*5+2))*(1+AT$7)^INDEX($Q403:$AJ403,1,(AT$4-1)*5+1)*(AT273/AS273)^INDEX($Q403:$AJ403,1,(AT$4-1)*5+2)*(AT273/AS273)^(INDEX($Q403:$AJ403,1,(AT$4-1)*5+3)*(1+INDEX($Q403:$AJ403,1,(AT$4-1)*5+2))) | ... AY403: =AX403*(1/(1+INDEX($Q403:$AJ403,1,(AY$4-1)*5+4)))^(1+INDEX($Q403:$AJ403,1,(AY$4-1)*5+2))*(1+AY$7)^INDEX($Q403:$AJ403,1,(AY$4-1)*5+1)*(AY273/AX273)^INDEX($Q403:$AJ403,1,(AY$4-1)*5+2)*(AY273/AX273)^(INDEX($Q403:$AJ403,1,(AY$4-1)*5+3)*(1+INDEX($Q403:$AJ403,1,(AY$4-1)*5+2))) | BA403: =INDEX(EnergyCons!$F$4:$F$5000,MATCH(Settings!$C$4&"|"&BA$5&"|"&$C403&"|"&$B403,EnergyCons!$A$4:$A$5000,0)) | BB403: =BA403*(1/(1+INDEX($Q403:$AJ403,1,(BB$4-1)*5+4)))^(1+INDEX($Q403:$AJ403,1,(BB$4-1)*5+2))*(1+BB$7)^INDEX($Q403:$AJ403,1,(BB$4-1)*5+1)*(BB273/BA273)^INDEX($Q403:$AJ403,1,(BB$4-1)*5+2)*(BB273/BA273)^(INDEX($Q403:$AJ403,1,(BB$4-1)*5+3)*(1+INDEX($Q403:$AJ403,1,(BB$4-1)*5+2))) | BC403: =BB403*(1/(1+INDEX($Q403:$AJ403,1,(BC$4-1)*5+4)))^(1+INDEX($Q403:$AJ403,1,(BC$4-1)*5+2))*(1+BC$7)^INDEX($Q403:$AJ403,1,(BC$4-1)*5+1)*(BC273/BB273)^INDEX($Q403:$AJ403,1,(BC$4-1)*5+2)*(BC273/BB273)^(INDEX($Q403:$AJ403,1,(BC$4-1)*5+3)*(1+INDEX($Q403:$AJ403,1,(BC$4-1)*5+2))) | BD403: =BC403*(1/(1+INDEX($Q403:$AJ403,1,(BD$4-1)*5+4)))^(1+INDEX($Q403:$AJ403,1,(BD$4-1)*5+2))*(1+BD$7)^INDEX($Q403:$AJ403,1,(BD$4-1)*5+1)*(BD273/BC273)^INDEX($Q403:$AJ403,1,(BD$4-1)*5+2)*(BD273/BC273)^(INDEX($Q403:$AJ403,1,(BD$4-1)*5+3)*(1+INDEX($Q403:$AJ403,1,(BD$4-1)*5+2))) | BE403: =BD403*(1/(1+INDEX($Q403:$AJ403,1,(BE$4-1)*5+4)))^(1+INDEX($Q403:$AJ403,1,(BE$4-1)*5+2))*(1+BE$7)^INDEX($Q403:$AJ403,1,(BE$4-1)*5+1)*(BE273/BD273)^INDEX($Q403:$AJ403,1,(BE$4-1)*5+2)*(BE273/BD273)^(INDEX($Q403:$AJ403,1,(BE$4-1)*5+3)*(1+INDEX($Q403:$AJ403,1,(BE$4-1)*5+2))) | BF403: =BE403*(1/(1+INDEX($Q403:$AJ403,1,(BF$4-1)*5+4)))^(1+INDEX($Q403:$AJ403,1,(BF$4-1)*5+2))*(1+BF$7)^INDEX($Q403:$AJ403,1,(BF$4-1)*5+1)*(BF273/BE273)^INDEX($Q403:$AJ403,1,(BF$4-1)*5+2)*(BF273/BE273)^(INDEX($Q403:$AJ403,1,(BF$4-1)*5+3)*(1+INDEX($Q403:$AJ403,1,(BF$4-1)*5+2))) | BG403: =BF403*(1/(1+INDEX($Q403:$AJ403,1,(BG$4-1)*5+4)))^(1+INDEX($Q403:$AJ403,1,(BG$4-1)*5+2))*(1+BG$7)^INDEX($Q403:$AJ403,1,(BG$4-1)*5+1)*(BG273/BF273)^INDEX($Q403:$AJ403,1,(BG$4-1)*5+2)*(BG273/BF273)^(INDEX($Q403:$AJ403,1,(BG$4-1)*5+3)*(1+INDEX($Q403:$AJ403,1,(BG$4-1)*5+2))) | BH403: =BG403*(1/(1+INDEX($Q403:$AJ403,1,(BH$4-1)*5+4)))^(1+INDEX($Q403:$AJ403,1,(BH$4-1)*5+2))*(1+BH$7)^INDEX($Q403:$AJ403,1,(BH$4-1)*5+1)*(BH273/BG273)^INDEX($Q403:$AJ403,1,(BH$4-1)*5+2)*(BH273/BG273)^(INDEX($Q403:$AJ403,1,(BH$4-1)*5+3)*(1+INDEX($Q403:$AJ403,1,(BH$4-1)*5+2))) | BI403: =BH403*(1/(1+INDEX($Q403:$AJ403,1,(BI$4-1)*5+4)))^(1+INDEX($Q403:$AJ403,1,(BI$4-1)*5+2))*(1+BI$7)^INDEX($Q403:$AJ403,1,(BI$4-1)*5+1)*(BI273/BH273)^INDEX($Q403:$AJ403,1,(BI$4-1)*5+2)*(BI273/BH273)^(INDEX($Q403:$AJ403,1,(BI$4-1)*5+3)*(1+INDEX($Q403:$AJ403,1,(BI$4-1)*5+2))) | ... BN403: =BM403*(1/(1+INDEX($Q403:$AJ403,1,(BN$4-1)*5+4)))^(1+INDEX($Q403:$AJ403,1,(BN$4-1)*5+2))*(1+BN$7)^INDEX($Q403:$AJ403,1,(BN$4-1)*5+1)*(BN273/BM273)^INDEX($Q403:$AJ403,1,(BN$4-1)*5+2)*(BN273/BM273)^(INDEX($Q403:$AJ403,1,(BN$4-1)*5+3)*(1+INDEX($Q403:$AJ403,1,(BN$4-1)*5+2)))
B404: die | C404: rod | D404: Fuel use | Road | Diesel | E404: ktoe | F404: EnergyCons (base year), Elasticities | G404: mit.enc.die.rod | H404: mit.enc.die.rod | J404: =INDEX(Mapping!$C$5:$C$20,MATCH($C404,Mapping!$A$5:$A$20,0)) | K404: =INDEX(Mapping!$D$5:$D$20,MATCH($C404,Mapping!$A$5:$A$20,0)) | L404: =INDEX(Mapping!$C$24:$C$31,MATCH($B404,Mapping!$A$24:$A$31,0)) | M404: =INDEX(Mapping!$D$24:$D$31,MATCH($B404,Mapping!$A$24:$A$31,0)) | N404: =$B404&"."&IF(INDEX(Mapping!$E$24:$E$31,MATCH($B404,Mapping!$A$24:$A$31,0))="sub",INDEX(Mapping!$F$5:$F$20,MATCH($C404,Mapping!$A$5:$A$20,0)),"all") | O404: =INDEX(Mapping!$E$5:$E$20,MATCH($C404,Mapping!$A$5:$A$20,0)) | P404: =INDEX(Mapping!$G$24:$G$31,MATCH($B404,Mapping!$A$24:$A$31,0)) | Q404: =INDEX(Elasticities!$F$4:$I$200,MATCH("inc|"&$L404&"|"&$K404,Elasticities!$A$4:$A$200,0),MATCH(Settings!$C$6,Elasticities!$F$3:$I$3,0)) | R404: =INDEX(Elasticities!$F$4:$I$200,MATCH("usg|"&$L404&"|"&$K404,Elasticities!$A$4:$A$200,0),MATCH(Settings!$C$6,Elasticities!$F$3:$I$3,0)) | S404: =INDEX(Elasticities!$F$4:$I$200,MATCH("eff|"&$L404&"|"&$K404,Elasticities!$A$4:$A$200,0),MATCH(Settings!$C$6,Elasticities!$F$3:$I$3,0)) | T404: =INDEX(Elasticities!$F$4:$I$200,MATCH("aei|"&$M404&"|"&$K404,Elasticities!$A$4:$A$200,0),MATCH(Settings!$C$6,Elasticities!$F$3:$I$3,0)) | V404: =Q404 | W404: =R404 | X404: =S404 | Y404: =T404 | AA404: =Q404 | AB404: =R404 | AC404: =S404 | AD404: =T404 | AF404: =Q404 | AG404: =R404 | AH404: =S404 | AI404: =T404 | AL404: =INDEX(EnergyCons!$F$4:$F$5000,MATCH(Settings!$C$4&"|"&AL$5&"|"&$C404&"|"&$B404,EnergyCons!$A$4:$A$5000,0)) | AM404: =AL404*(1/(1+INDEX($Q404:$AJ404,1,(AM$4-1)*5+4)))^(1+INDEX($Q404:$AJ404,1,(AM$4-1)*5+2))*(1+AM$7)^INDEX($Q404:$AJ404,1,(AM$4-1)*5+1)*(AM274/AL274)^INDEX($Q404:$AJ404,1,(AM$4-1)*5+2)*(AM274/AL274)^(INDEX($Q404:$AJ404,1,(AM$4-1)*5+3)*(1+INDEX($Q404:$AJ404,1,(AM$4-1)*5+2))) | AN404: =AM404*(1/(1+INDEX($Q404:$AJ404,1,(AN$4-1)*5+4)))^(1+INDEX($Q404:$AJ404,1,(AN$4-1)*5+2))*(1+AN$7)^INDEX($Q404:$AJ404,1,(AN$4-1)*5+1)*(AN274/AM274)^INDEX($Q404:$AJ404,1,(AN$4-1)*5+2)*(AN274/AM274)^(INDEX($Q404:$AJ404,1,(AN$4-1)*5+3)*(1+INDEX($Q404:$AJ404,1,(AN$4-1)*5+2))) | AO404: =AN404*(1/(1+INDEX($Q404:$AJ404,1,(AO$4-1)*5+4)))^(1+INDEX($Q404:$AJ404,1,(AO$4-1)*5+2))*(1+AO$7)^INDEX($Q404:$AJ404,1,(AO$4-1)*5+1)*(AO274/AN274)^INDEX($Q404:$AJ404,1,(AO$4-1)*5+2)*(AO274/AN274)^(INDEX($Q404:$AJ404,1,(AO$4-1)*5+3)*(1+INDEX($Q404:$AJ404,1,(AO$4-1)*5+2))) | AP404: =AO404*(1/(1+INDEX($Q404:$AJ404,1,(AP$4-1)*5+4)))^(1+INDEX($Q404:$AJ404,1,(AP$4-1)*5+2))*(1+AP$7)^INDEX($Q404:$AJ404,1,(AP$4-1)*5+1)*(AP274/AO274)^INDEX($Q404:$AJ404,1,(AP$4-1)*5+2)*(AP274/AO274)^(INDEX($Q404:$AJ404,1,(AP$4-1)*5+3)*(1+INDEX($Q404:$AJ404,1,(AP$4-1)*5+2))) | AQ404: =AP404*(1/(1+INDEX($Q404:$AJ404,1,(AQ$4-1)*5+4)))^(1+INDEX($Q404:$AJ404,1,(AQ$4-1)*5+2))*(1+AQ$7)^INDEX($Q404:$AJ404,1,(AQ$4-1)*5+1)*(AQ274/AP274)^INDEX($Q404:$AJ404,1,(AQ$4-1)*5+2)*(AQ274/AP274)^(INDEX($Q404:$AJ404,1,(AQ$4-1)*5+3)*(1+INDEX($Q404:$AJ404,1,(AQ$4-1)*5+2))) | AR404: =AQ404*(1/(1+INDEX($Q404:$AJ404,1,(AR$4-1)*5+4)))^(1+INDEX($Q404:$AJ404,1,(AR$4-1)*5+2))*(1+AR$7)^INDEX($Q404:$AJ404,1,(AR$4-1)*5+1)*(AR274/AQ274)^INDEX($Q404:$AJ404,1,(AR$4-1)*5+2)*(AR274/AQ274)^(INDEX($Q404:$AJ404,1,(AR$4-1)*5+3)*(1+INDEX($Q404:$AJ404,1,(AR$4-1)*5+2))) | AS404: =AR404*(1/(1+INDEX($Q404:$AJ404,1,(AS$4-1)*5+4)))^(1+INDEX($Q404:$AJ404,1,(AS$4-1)*5+2))*(1+AS$7)^INDEX($Q404:$AJ404,1,(AS$4-1)*5+1)*(AS274/AR274)^INDEX($Q404:$AJ404,1,(AS$4-1)*5+2)*(AS274/AR274)^(INDEX($Q404:$AJ404,1,(AS$4-1)*5+3)*(1+INDEX($Q404:$AJ404,1,(AS$4-1)*5+2))) | AT404: =AS404*(1/(1+INDEX($Q404:$AJ404,1,(AT$4-1)*5+4)))^(1+INDEX($Q404:$AJ404,1,(AT$4-1)*5+2))*(1+AT$7)^INDEX($Q404:$AJ404,1,(AT$4-1)*5+1)*(AT274/AS274)^INDEX($Q404:$AJ404,1,(AT$4-1)*5+2)*(AT274/AS274)^(INDEX($Q404:$AJ404,1,(AT$4-1)*5+3)*(1+INDEX($Q404:$AJ404,1,(AT$4-1)*5+2))) | ... AY404: =AX404*(1/(1+INDEX($Q404:$AJ404,1,(AY$4-1)*5+4)))^(1+INDEX($Q404:$AJ404,1,(AY$4-1)*5+2))*(1+AY$7)^INDEX($Q404:$AJ404,1,(AY$4-1)*5+1)*(AY274/AX274)^INDEX($Q404:$AJ404,1,(AY$4-1)*5+2)*(AY274/AX274)^(INDEX($Q404:$AJ404,1,(AY$4-1)*5+3)*(1+INDEX($Q404:$AJ404,1,(AY$4-1)*5+2))) | BA404: =INDEX(EnergyCons!$F$4:$F$5000,MATCH(Settings!$C$4&"|"&BA$5&"|"&$C404&"|"&$B404,EnergyCons!$A$4:$A$5000,0)) | BB404: =BA404*(1/(1+INDEX($Q404:$AJ404,1,(BB$4-1)*5+4)))^(1+INDEX($Q404:$AJ404,1,(BB$4-1)*5+2))*(1+BB$7)^INDEX($Q404:$AJ404,1,(BB$4-1)*5+1)*(BB274/BA274)^INDEX($Q404:$AJ404,1,(BB$4-1)*5+2)*(BB274/BA274)^(INDEX($Q404:$AJ404,1,(BB$4-1)*5+3)*(1+INDEX($Q404:$AJ404,1,(BB$4-1)*5+2))) | BC404: =BB404*(1/(1+INDEX($Q404:$AJ404,1,(BC$4-1)*5+4)))^(1+INDEX($Q404:$AJ404,1,(BC$4-1)*5+2))*(1+BC$7)^INDEX($Q404:$AJ404,1,(BC$4-1)*5+1)*(BC274/BB274)^INDEX($Q404:$AJ404,1,(BC$4-1)*5+2)*(BC274/BB274)^(INDEX($Q404:$AJ404,1,(BC$4-1)*5+3)*(1+INDEX($Q404:$AJ404,1,(BC$4-1)*5+2))) | BD404: =BC404*(1/(1+INDEX($Q404:$AJ404,1,(BD$4-1)*5+4)))^(1+INDEX($Q404:$AJ404,1,(BD$4-1)*5+2))*(1+BD$7)^INDEX($Q404:$AJ404,1,(BD$4-1)*5+1)*(BD274/BC274)^INDEX($Q404:$AJ404,1,(BD$4-1)*5+2)*(BD274/BC274)^(INDEX($Q404:$AJ404,1,(BD$4-1)*5+3)*(1+INDEX($Q404:$AJ404,1,(BD$4-1)*5+2))) | BE404: =BD404*(1/(1+INDEX($Q404:$AJ404,1,(BE$4-1)*5+4)))^(1+INDEX($Q404:$AJ404,1,(BE$4-1)*5+2))*(1+BE$7)^INDEX($Q404:$AJ404,1,(BE$4-1)*5+1)*(BE274/BD274)^INDEX($Q404:$AJ404,1,(BE$4-1)*5+2)*(BE274/BD274)^(INDEX($Q404:$AJ404,1,(BE$4-1)*5+3)*(1+INDEX($Q404:$AJ404,1,(BE$4-1)*5+2))) | BF404: =BE404*(1/(1+INDEX($Q404:$AJ404,1,(BF$4-1)*5+4)))^(1+INDEX($Q404:$AJ404,1,(BF$4-1)*5+2))*(1+BF$7)^INDEX($Q404:$AJ404,1,(BF$4-1)*5+1)*(BF274/BE274)^INDEX($Q404:$AJ404,1,(BF$4-1)*5+2)*(BF274/BE274)^(INDEX($Q404:$AJ404,1,(BF$4-1)*5+3)*(1+INDEX($Q404:$AJ404,1,(BF$4-1)*5+2))) | BG404: =BF404*(1/(1+INDEX($Q404:$AJ404,1,(BG$4-1)*5+4)))^(1+INDEX($Q404:$AJ404,1,(BG$4-1)*5+2))*(1+BG$7)^INDEX($Q404:$AJ404,1,(BG$4-1)*5+1)*(BG274/BF274)^INDEX($Q404:$AJ404,1,(BG$4-1)*5+2)*(BG274/BF274)^(INDEX($Q404:$AJ404,1,(BG$4-1)*5+3)*(1+INDEX($Q404:$AJ404,1,(BG$4-1)*5+2))) | BH404: =BG404*(1/(1+INDEX($Q404:$AJ404,1,(BH$4-1)*5+4)))^(1+INDEX($Q404:$AJ404,1,(BH$4-1)*5+2))*(1+BH$7)^INDEX($Q404:$AJ404,1,(BH$4-1)*5+1)*(BH274/BG274)^INDEX($Q404:$AJ404,1,(BH$4-1)*5+2)*(BH274/BG274)^(INDEX($Q404:$AJ404,1,(BH$4-1)*5+3)*(1+INDEX($Q404:$AJ404,1,(BH$4-1)*5+2))) | BI404: =BH404*(1/(1+INDEX($Q404:$AJ404,1,(BI$4-1)*5+4)))^(1+INDEX($Q404:$AJ404,1,(BI$4-1)*5+2))*(1+BI$7)^INDEX($Q404:$AJ404,1,(BI$4-1)*5+1)*(BI274/BH274)^INDEX($Q404:$AJ404,1,(BI$4-1)*5+2)*(BI274/BH274)^(INDEX($Q404:$AJ404,1,(BI$4-1)*5+3)*(1+INDEX($Q404:$AJ404,1,(BI$4-1)*5+2))) | ... BN404: =BM404*(1/(1+INDEX($Q404:$AJ404,1,(BN$4-1)*5+4)))^(1+INDEX($Q404:$AJ404,1,(BN$4-1)*5+2))*(1+BN$7)^INDEX($Q404:$AJ404,1,(BN$4-1)*5+1)*(BN274/BM274)^INDEX($Q404:$AJ404,1,(BN$4-1)*5+2)*(BN274/BM274)^(INDEX($Q404:$AJ404,1,(BN$4-1)*5+3)*(1+INDEX($Q404:$AJ404,1,(BN$4-1)*5+2)))
B405: lpg | C405: rod | D405: Fuel use | Road | LPG | E405: ktoe | F405: EnergyCons (base year), Elasticities | G405: mit.enc.lpg.rod | H405: mit.enc.lpg.rod | J405: =INDEX(Mapping!$C$5:$C$20,MATCH($C405,Mapping!$A$5:$A$20,0)) | K405: =INDEX(Mapping!$D$5:$D$20,MATCH($C405,Mapping!$A$5:$A$20,0)) | L405: =INDEX(Mapping!$C$24:$C$31,MATCH($B405,Mapping!$A$24:$A$31,0)) | M405: =INDEX(Mapping!$D$24:$D$31,MATCH($B405,Mapping!$A$24:$A$31,0)) | N405: =$B405&"."&IF(INDEX(Mapping!$E$24:$E$31,MATCH($B405,Mapping!$A$24:$A$31,0))="sub",INDEX(Mapping!$F$5:$F$20,MATCH($C405,Mapping!$A$5:$A$20,0)),"all") | O405: =INDEX(Mapping!$E$5:$E$20,MATCH($C405,Mapping!$A$5:$A$20,0)) | P405: =INDEX(Mapping!$G$24:$G$31,MATCH($B405,Mapping!$A$24:$A$31,0)) | Q405: =INDEX(Elasticities!$F$4:$I$200,MATCH("inc|"&$L405&"|"&$K405,Elasticities!$A$4:$A$200,0),MATCH(Settings!$C$6,Elasticities!$F$3:$I$3,0)) | R405: =INDEX(Elasticities!$F$4:$I$200,MATCH("usg|"&$L405&"|"&$K405,Elasticities!$A$4:$A$200,0),MATCH(Settings!$C$6,Elasticities!$F$3:$I$3,0)) | S405: =INDEX(Elasticities!$F$4:$I$200,MATCH("eff|"&$L405&"|"&$K405,Elasticities!$A$4:$A$200,0),MATCH(Settings!$C$6,Elasticities!$F$3:$I$3,0)) | T405: =INDEX(Elasticities!$F$4:$I$200,MATCH("aei|"&$M405&"|"&$K405,Elasticities!$A$4:$A$200,0),MATCH(Settings!$C$6,Elasticities!$F$3:$I$3,0)) | V405: =Q405 | W405: =R405 | X405: =S405 | Y405: =T405 | AA405: =Q405 | AB405: =R405 | AC405: =S405 | AD405: =T405 | AF405: =Q405 | AG405: =R405 | AH405: =S405 | AI405: =T405 | AL405: =INDEX(EnergyCons!$F$4:$F$5000,MATCH(Settings!$C$4&"|"&AL$5&"|"&$C405&"|"&$B405,EnergyCons!$A$4:$A$5000,0)) | AM405: =AL405*(1/(1+INDEX($Q405:$AJ405,1,(AM$4-1)*5+4)))^(1+INDEX($Q405:$AJ405,1,(AM$4-1)*5+2))*(1+AM$7)^INDEX($Q405:$AJ405,1,(AM$4-1)*5+1)*(AM275/AL275)^INDEX($Q405:$AJ405,1,(AM$4-1)*5+2)*(AM275/AL275)^(INDEX($Q405:$AJ405,1,(AM$4-1)*5+3)*(1+INDEX($Q405:$AJ405,1,(AM$4-1)*5+2))) | AN405: =AM405*(1/(1+INDEX($Q405:$AJ405,1,(AN$4-1)*5+4)))^(1+INDEX($Q405:$AJ405,1,(AN$4-1)*5+2))*(1+AN$7)^INDEX($Q405:$AJ405,1,(AN$4-1)*5+1)*(AN275/AM275)^INDEX($Q405:$AJ405,1,(AN$4-1)*5+2)*(AN275/AM275)^(INDEX($Q405:$AJ405,1,(AN$4-1)*5+3)*(1+INDEX($Q405:$AJ405,1,(AN$4-1)*5+2))) | AO405: =AN405*(1/(1+INDEX($Q405:$AJ405,1,(AO$4-1)*5+4)))^(1+INDEX($Q405:$AJ405,1,(AO$4-1)*5+2))*(1+AO$7)^INDEX($Q405:$AJ405,1,(AO$4-1)*5+1)*(AO275/AN275)^INDEX($Q405:$AJ405,1,(AO$4-1)*5+2)*(AO275/AN275)^(INDEX($Q405:$AJ405,1,(AO$4-1)*5+3)*(1+INDEX($Q405:$AJ405,1,(AO$4-1)*5+2))) | AP405: =AO405*(1/(1+INDEX($Q405:$AJ405,1,(AP$4-1)*5+4)))^(1+INDEX($Q405:$AJ405,1,(AP$4-1)*5+2))*(1+AP$7)^INDEX($Q405:$AJ405,1,(AP$4-1)*5+1)*(AP275/AO275)^INDEX($Q405:$AJ405,1,(AP$4-1)*5+2)*(AP275/AO275)^(INDEX($Q405:$AJ405,1,(AP$4-1)*5+3)*(1+INDEX($Q405:$AJ405,1,(AP$4-1)*5+2))) | AQ405: =AP405*(1/(1+INDEX($Q405:$AJ405,1,(AQ$4-1)*5+4)))^(1+INDEX($Q405:$AJ405,1,(AQ$4-1)*5+2))*(1+AQ$7)^INDEX($Q405:$AJ405,1,(AQ$4-1)*5+1)*(AQ275/AP275)^INDEX($Q405:$AJ405,1,(AQ$4-1)*5+2)*(AQ275/AP275)^(INDEX($Q405:$AJ405,1,(AQ$4-1)*5+3)*(1+INDEX($Q405:$AJ405,1,(AQ$4-1)*5+2))) | AR405: =AQ405*(1/(1+INDEX($Q405:$AJ405,1,(AR$4-1)*5+4)))^(1+INDEX($Q405:$AJ405,1,(AR$4-1)*5+2))*(1+AR$7)^INDEX($Q405:$AJ405,1,(AR$4-1)*5+1)*(AR275/AQ275)^INDEX($Q405:$AJ405,1,(AR$4-1)*5+2)*(AR275/AQ275)^(INDEX($Q405:$AJ405,1,(AR$4-1)*5+3)*(1+INDEX($Q405:$AJ405,1,(AR$4-1)*5+2))) | AS405: =AR405*(1/(1+INDEX($Q405:$AJ405,1,(AS$4-1)*5+4)))^(1+INDEX($Q405:$AJ405,1,(AS$4-1)*5+2))*(1+AS$7)^INDEX($Q405:$AJ405,1,(AS$4-1)*5+1)*(AS275/AR275)^INDEX($Q405:$AJ405,1,(AS$4-1)*5+2)*(AS275/AR275)^(INDEX($Q405:$AJ405,1,(AS$4-1)*5+3)*(1+INDEX($Q405:$AJ405,1,(AS$4-1)*5+2))) | AT405: =AS405*(1/(1+INDEX($Q405:$AJ405,1,(AT$4-1)*5+4)))^(1+INDEX($Q405:$AJ405,1,(AT$4-1)*5+2))*(1+AT$7)^INDEX($Q405:$AJ405,1,(AT$4-1)*5+1)*(AT275/AS275)^INDEX($Q405:$AJ405,1,(AT$4-1)*5+2)*(AT275/AS275)^(INDEX($Q405:$AJ405,1,(AT$4-1)*5+3)*(1+INDEX($Q405:$AJ405,1,(AT$4-1)*5+2))) | ... AY405: =AX405*(1/(1+INDEX($Q405:$AJ405,1,(AY$4-1)*5+4)))^(1+INDEX($Q405:$AJ405,1,(AY$4-1)*5+2))*(1+AY$7)^INDEX($Q405:$AJ405,1,(AY$4-1)*5+1)*(AY275/AX275)^INDEX($Q405:$AJ405,1,(AY$4-1)*5+2)*(AY275/AX275)^(INDEX($Q405:$AJ405,1,(AY$4-1)*5+3)*(1+INDEX($Q405:$AJ405,1,(AY$4-1)*5+2))) | BA405: =INDEX(EnergyCons!$F$4:$F$5000,MATCH(Settings!$C$4&"|"&BA$5&"|"&$C405&"|"&$B405,EnergyCons!$A$4:$A$5000,0)) | BB405: =BA405*(1/(1+INDEX($Q405:$AJ405,1,(BB$4-1)*5+4)))^(1+INDEX($Q405:$AJ405,1,(BB$4-1)*5+2))*(1+BB$7)^INDEX($Q405:$AJ405,1,(BB$4-1)*5+1)*(BB275/BA275)^INDEX($Q405:$AJ405,1,(BB$4-1)*5+2)*(BB275/BA275)^(INDEX($Q405:$AJ405,1,(BB$4-1)*5+3)*(1+INDEX($Q405:$AJ405,1,(BB$4-1)*5+2))) | BC405: =BB405*(1/(1+INDEX($Q405:$AJ405,1,(BC$4-1)*5+4)))^(1+INDEX($Q405:$AJ405,1,(BC$4-1)*5+2))*(1+BC$7)^INDEX($Q405:$AJ405,1,(BC$4-1)*5+1)*(BC275/BB275)^INDEX($Q405:$AJ405,1,(BC$4-1)*5+2)*(BC275/BB275)^(INDEX($Q405:$AJ405,1,(BC$4-1)*5+3)*(1+INDEX($Q405:$AJ405,1,(BC$4-1)*5+2))) | BD405: =BC405*(1/(1+INDEX($Q405:$AJ405,1,(BD$4-1)*5+4)))^(1+INDEX($Q405:$AJ405,1,(BD$4-1)*5+2))*(1+BD$7)^INDEX($Q405:$AJ405,1,(BD$4-1)*5+1)*(BD275/BC275)^INDEX($Q405:$AJ405,1,(BD$4-1)*5+2)*(BD275/BC275)^(INDEX($Q405:$AJ405,1,(BD$4-1)*5+3)*(1+INDEX($Q405:$AJ405,1,(BD$4-1)*5+2))) | BE405: =BD405*(1/(1+INDEX($Q405:$AJ405,1,(BE$4-1)*5+4)))^(1+INDEX($Q405:$AJ405,1,(BE$4-1)*5+2))*(1+BE$7)^INDEX($Q405:$AJ405,1,(BE$4-1)*5+1)*(BE275/BD275)^INDEX($Q405:$AJ405,1,(BE$4-1)*5+2)*(BE275/BD275)^(INDEX($Q405:$AJ405,1,(BE$4-1)*5+3)*(1+INDEX($Q405:$AJ405,1,(BE$4-1)*5+2))) | BF405: =BE405*(1/(1+INDEX($Q405:$AJ405,1,(BF$4-1)*5+4)))^(1+INDEX($Q405:$AJ405,1,(BF$4-1)*5+2))*(1+BF$7)^INDEX($Q405:$AJ405,1,(BF$4-1)*5+1)*(BF275/BE275)^INDEX($Q405:$AJ405,1,(BF$4-1)*5+2)*(BF275/BE275)^(INDEX($Q405:$AJ405,1,(BF$4-1)*5+3)*(1+INDEX($Q405:$AJ405,1,(BF$4-1)*5+2))) | BG405: =BF405*(1/(1+INDEX($Q405:$AJ405,1,(BG$4-1)*5+4)))^(1+INDEX($Q405:$AJ405,1,(BG$4-1)*5+2))*(1+BG$7)^INDEX($Q405:$AJ405,1,(BG$4-1)*5+1)*(BG275/BF275)^INDEX($Q405:$AJ405,1,(BG$4-1)*5+2)*(BG275/BF275)^(INDEX($Q405:$AJ405,1,(BG$4-1)*5+3)*(1+INDEX($Q405:$AJ405,1,(BG$4-1)*5+2))) | BH405: =BG405*(1/(1+INDEX($Q405:$AJ405,1,(BH$4-1)*5+4)))^(1+INDEX($Q405:$AJ405,1,(BH$4-1)*5+2))*(1+BH$7)^INDEX($Q405:$AJ405,1,(BH$4-1)*5+1)*(BH275/BG275)^INDEX($Q405:$AJ405,1,(BH$4-1)*5+2)*(BH275/BG275)^(INDEX($Q405:$AJ405,1,(BH$4-1)*5+3)*(1+INDEX($Q405:$AJ405,1,(BH$4-1)*5+2))) | BI405: =BH405*(1/(1+INDEX($Q405:$AJ405,1,(BI$4-1)*5+4)))^(1+INDEX($Q405:$AJ405,1,(BI$4-1)*5+2))*(1+BI$7)^INDEX($Q405:$AJ405,1,(BI$4-1)*5+1)*(BI275/BH275)^INDEX($Q405:$AJ405,1,(BI$4-1)*5+2)*(BI275/BH275)^(INDEX($Q405:$AJ405,1,(BI$4-1)*5+3)*(1+INDEX($Q405:$AJ405,1,(BI$4-1)*5+2))) | ... BN405: =BM405*(1/(1+INDEX($Q405:$AJ405,1,(BN$4-1)*5+4)))^(1+INDEX($Q405:$AJ405,1,(BN$4-1)*5+2))*(1+BN$7)^INDEX($Q405:$AJ405,1,(BN$4-1)*5+1)*(BN275/BM275)^INDEX($Q405:$AJ405,1,(BN$4-1)*5+2)*(BN275/BM275)^(INDEX($Q405:$AJ405,1,(BN$4-1)*5+3)*(1+INDEX($Q405:$AJ405,1,(BN$4-1)*5+2)))
B406: ker | C406: rod | D406: Fuel use | Road | Kerosene | E406: ktoe | F406: EnergyCons (base year), Elasticities | G406: mit.enc.ker.rod | H406: mit.enc.ker.rod | J406: =INDEX(Mapping!$C$5:$C$20,MATCH($C406,Mapping!$A$5:$A$20,0)) | K406: =INDEX(Mapping!$D$5:$D$20,MATCH($C406,Mapping!$A$5:$A$20,0)) | L406: =INDEX(Mapping!$C$24:$C$31,MATCH($B406,Mapping!$A$24:$A$31,0)) | M406: =INDEX(Mapping!$D$24:$D$31,MATCH($B406,Mapping!$A$24:$A$31,0)) | N406: =$B406&"."&IF(INDEX(Mapping!$E$24:$E$31,MATCH($B406,Mapping!$A$24:$A$31,0))="sub",INDEX(Mapping!$F$5:$F$20,MATCH($C406,Mapping!$A$5:$A$20,0)),"all") | O406: =INDEX(Mapping!$E$5:$E$20,MATCH($C406,Mapping!$A$5:$A$20,0)) | P406: =INDEX(Mapping!$G$24:$G$31,MATCH($B406,Mapping!$A$24:$A$31,0)) | Q406: =INDEX(Elasticities!$F$4:$I$200,MATCH("inc|"&$L406&"|"&$K406,Elasticities!$A$4:$A$200,0),MATCH(Settings!$C$6,Elasticities!$F$3:$I$3,0)) | R406: =INDEX(Elasticities!$F$4:$I$200,MATCH("usg|"&$L406&"|"&$K406,Elasticities!$A$4:$A$200,0),MATCH(Settings!$C$6,Elasticities!$F$3:$I$3,0)) | S406: =INDEX(Elasticities!$F$4:$I$200,MATCH("eff|"&$L406&"|"&$K406,Elasticities!$A$4:$A$200,0),MATCH(Settings!$C$6,Elasticities!$F$3:$I$3,0)) | T406: =INDEX(Elasticities!$F$4:$I$200,MATCH("aei|"&$M406&"|"&$K406,Elasticities!$A$4:$A$200,0),MATCH(Settings!$C$6,Elasticities!$F$3:$I$3,0)) | V406: =Q406 | W406: =R406 | X406: =S406 | Y406: =T406 | AA406: =Q406 | AB406: =R406 | AC406: =S406 | AD406: =T406 | AF406: =Q406 | AG406: =R406 | AH406: =S406 | AI406: =T406 | AL406: =INDEX(EnergyCons!$F$4:$F$5000,MATCH(Settings!$C$4&"|"&AL$5&"|"&$C406&"|"&$B406,EnergyCons!$A$4:$A$5000,0)) | AM406: =AL406*(1/(1+INDEX($Q406:$AJ406,1,(AM$4-1)*5+4)))^(1+INDEX($Q406:$AJ406,1,(AM$4-1)*5+2))*(1+AM$7)^INDEX($Q406:$AJ406,1,(AM$4-1)*5+1)*(AM276/AL276)^INDEX($Q406:$AJ406,1,(AM$4-1)*5+2)*(AM276/AL276)^(INDEX($Q406:$AJ406,1,(AM$4-1)*5+3)*(1+INDEX($Q406:$AJ406,1,(AM$4-1)*5+2))) | AN406: =AM406*(1/(1+INDEX($Q406:$AJ406,1,(AN$4-1)*5+4)))^(1+INDEX($Q406:$AJ406,1,(AN$4-1)*5+2))*(1+AN$7)^INDEX($Q406:$AJ406,1,(AN$4-1)*5+1)*(AN276/AM276)^INDEX($Q406:$AJ406,1,(AN$4-1)*5+2)*(AN276/AM276)^(INDEX($Q406:$AJ406,1,(AN$4-1)*5+3)*(1+INDEX($Q406:$AJ406,1,(AN$4-1)*5+2))) | AO406: =AN406*(1/(1+INDEX($Q406:$AJ406,1,(AO$4-1)*5+4)))^(1+INDEX($Q406:$AJ406,1,(AO$4-1)*5+2))*(1+AO$7)^INDEX($Q406:$AJ406,1,(AO$4-1)*5+1)*(AO276/AN276)^INDEX($Q406:$AJ406,1,(AO$4-1)*5+2)*(AO276/AN276)^(INDEX($Q406:$AJ406,1,(AO$4-1)*5+3)*(1+INDEX($Q406:$AJ406,1,(AO$4-1)*5+2))) | AP406: =AO406*(1/(1+INDEX($Q406:$AJ406,1,(AP$4-1)*5+4)))^(1+INDEX($Q406:$AJ406,1,(AP$4-1)*5+2))*(1+AP$7)^INDEX($Q406:$AJ406,1,(AP$4-1)*5+1)*(AP276/AO276)^INDEX($Q406:$AJ406,1,(AP$4-1)*5+2)*(AP276/AO276)^(INDEX($Q406:$AJ406,1,(AP$4-1)*5+3)*(1+INDEX($Q406:$AJ406,1,(AP$4-1)*5+2))) | AQ406: =AP406*(1/(1+INDEX($Q406:$AJ406,1,(AQ$4-1)*5+4)))^(1+INDEX($Q406:$AJ406,1,(AQ$4-1)*5+2))*(1+AQ$7)^INDEX($Q406:$AJ406,1,(AQ$4-1)*5+1)*(AQ276/AP276)^INDEX($Q406:$AJ406,1,(AQ$4-1)*5+2)*(AQ276/AP276)^(INDEX($Q406:$AJ406,1,(AQ$4-1)*5+3)*(1+INDEX($Q406:$AJ406,1,(AQ$4-1)*5+2))) | AR406: =AQ406*(1/(1+INDEX($Q406:$AJ406,1,(AR$4-1)*5+4)))^(1+INDEX($Q406:$AJ406,1,(AR$4-1)*5+2))*(1+AR$7)^INDEX($Q406:$AJ406,1,(AR$4-1)*5+1)*(AR276/AQ276)^INDEX($Q406:$AJ406,1,(AR$4-1)*5+2)*(AR276/AQ276)^(INDEX($Q406:$AJ406,1,(AR$4-1)*5+3)*(1+INDEX($Q406:$AJ406,1,(AR$4-1)*5+2))) | AS406: =AR406*(1/(1+INDEX($Q406:$AJ406,1,(AS$4-1)*5+4)))^(1+INDEX($Q406:$AJ406,1,(AS$4-1)*5+2))*(1+AS$7)^INDEX($Q406:$AJ406,1,(AS$4-1)*5+1)*(AS276/AR276)^INDEX($Q406:$AJ406,1,(AS$4-1)*5+2)*(AS276/AR276)^(INDEX($Q406:$AJ406,1,(AS$4-1)*5+3)*(1+INDEX($Q406:$AJ406,1,(AS$4-1)*5+2))) | AT406: =AS406*(1/(1+INDEX($Q406:$AJ406,1,(AT$4-1)*5+4)))^(1+INDEX($Q406:$AJ406,1,(AT$4-1)*5+2))*(1+AT$7)^INDEX($Q406:$AJ406,1,(AT$4-1)*5+1)*(AT276/AS276)^INDEX($Q406:$AJ406,1,(AT$4-1)*5+2)*(AT276/AS276)^(INDEX($Q406:$AJ406,1,(AT$4-1)*5+3)*(1+INDEX($Q406:$AJ406,1,(AT$4-1)*5+2))) | ... AY406: =AX406*(1/(1+INDEX($Q406:$AJ406,1,(AY$4-1)*5+4)))^(1+INDEX($Q406:$AJ406,1,(AY$4-1)*5+2))*(1+AY$7)^INDEX($Q406:$AJ406,1,(AY$4-1)*5+1)*(AY276/AX276)^INDEX($Q406:$AJ406,1,(AY$4-1)*5+2)*(AY276/AX276)^(INDEX($Q406:$AJ406,1,(AY$4-1)*5+3)*(1+INDEX($Q406:$AJ406,1,(AY$4-1)*5+2))) | BA406: =INDEX(EnergyCons!$F$4:$F$5000,MATCH(Settings!$C$4&"|"&BA$5&"|"&$C406&"|"&$B406,EnergyCons!$A$4:$A$5000,0)) | BB406: =BA406*(1/(1+INDEX($Q406:$AJ406,1,(BB$4-1)*5+4)))^(1+INDEX($Q406:$AJ406,1,(BB$4-1)*5+2))*(1+BB$7)^INDEX($Q406:$AJ406,1,(BB$4-1)*5+1)*(BB276/BA276)^INDEX($Q406:$AJ406,1,(BB$4-1)*5+2)*(BB276/BA276)^(INDEX($Q406:$AJ406,1,(BB$4-1)*5+3)*(1+INDEX($Q406:$AJ406,1,(BB$4-1)*5+2))) | BC406: =BB406*(1/(1+INDEX($Q406:$AJ406,1,(BC$4-1)*5+4)))^(1+INDEX($Q406:$AJ406,1,(BC$4-1)*5+2))*(1+BC$7)^INDEX($Q406:$AJ406,1,(BC$4-1)*5+1)*(BC276/BB276)^INDEX($Q406:$AJ406,1,(BC$4-1)*5+2)*(BC276/BB276)^(INDEX($Q406:$AJ406,1,(BC$4-1)*5+3)*(1+INDEX($Q406:$AJ406,1,(BC$4-1)*5+2))) | BD406: =BC406*(1/(1+INDEX($Q406:$AJ406,1,(BD$4-1)*5+4)))^(1+INDEX($Q406:$AJ406,1,(BD$4-1)*5+2))*(1+BD$7)^INDEX($Q406:$AJ406,1,(BD$4-1)*5+1)*(BD276/BC276)^INDEX($Q406:$AJ406,1,(BD$4-1)*5+2)*(BD276/BC276)^(INDEX($Q406:$AJ406,1,(BD$4-1)*5+3)*(1+INDEX($Q406:$AJ406,1,(BD$4-1)*5+2))) | BE406: =BD406*(1/(1+INDEX($Q406:$AJ406,1,(BE$4-1)*5+4)))^(1+INDEX($Q406:$AJ406,1,(BE$4-1)*5+2))*(1+BE$7)^INDEX($Q406:$AJ406,1,(BE$4-1)*5+1)*(BE276/BD276)^INDEX($Q406:$AJ406,1,(BE$4-1)*5+2)*(BE276/BD276)^(INDEX($Q406:$AJ406,1,(BE$4-1)*5+3)*(1+INDEX($Q406:$AJ406,1,(BE$4-1)*5+2))) | BF406: =BE406*(1/(1+INDEX($Q406:$AJ406,1,(BF$4-1)*5+4)))^(1+INDEX($Q406:$AJ406,1,(BF$4-1)*5+2))*(1+BF$7)^INDEX($Q406:$AJ406,1,(BF$4-1)*5+1)*(BF276/BE276)^INDEX($Q406:$AJ406,1,(BF$4-1)*5+2)*(BF276/BE276)^(INDEX($Q406:$AJ406,1,(BF$4-1)*5+3)*(1+INDEX($Q406:$AJ406,1,(BF$4-1)*5+2))) | BG406: =BF406*(1/(1+INDEX($Q406:$AJ406,1,(BG$4-1)*5+4)))^(1+INDEX($Q406:$AJ406,1,(BG$4-1)*5+2))*(1+BG$7)^INDEX($Q406:$AJ406,1,(BG$4-1)*5+1)*(BG276/BF276)^INDEX($Q406:$AJ406,1,(BG$4-1)*5+2)*(BG276/BF276)^(INDEX($Q406:$AJ406,1,(BG$4-1)*5+3)*(1+INDEX($Q406:$AJ406,1,(BG$4-1)*5+2))) | BH406: =BG406*(1/(1+INDEX($Q406:$AJ406,1,(BH$4-1)*5+4)))^(1+INDEX($Q406:$AJ406,1,(BH$4-1)*5+2))*(1+BH$7)^INDEX($Q406:$AJ406,1,(BH$4-1)*5+1)*(BH276/BG276)^INDEX($Q406:$AJ406,1,(BH$4-1)*5+2)*(BH276/BG276)^(INDEX($Q406:$AJ406,1,(BH$4-1)*5+3)*(1+INDEX($Q406:$AJ406,1,(BH$4-1)*5+2))) | BI406: =BH406*(1/(1+INDEX($Q406:$AJ406,1,(BI$4-1)*5+4)))^(1+INDEX($Q406:$AJ406,1,(BI$4-1)*5+2))*(1+BI$7)^INDEX($Q406:$AJ406,1,(BI$4-1)*5+1)*(BI276/BH276)^INDEX($Q406:$AJ406,1,(BI$4-1)*5+2)*(BI276/BH276)^(INDEX($Q406:$AJ406,1,(BI$4-1)*5+3)*(1+INDEX($Q406:$AJ406,1,(BI$4-1)*5+2))) | ... BN406: =BM406*(1/(1+INDEX($Q406:$AJ406,1,(BN$4-1)*5+4)))^(1+INDEX($Q406:$AJ406,1,(BN$4-1)*5+2))*(1+BN$7)^INDEX($Q406:$AJ406,1,(BN$4-1)*5+1)*(BN276/BM276)^INDEX($Q406:$AJ406,1,(BN$4-1)*5+2)*(BN276/BM276)^(INDEX($Q406:$AJ406,1,(BN$4-1)*5+3)*(1+INDEX($Q406:$AJ406,1,(BN$4-1)*5+2)))
B407: oop | C407: rod | D407: Fuel use | Road | Other oil products | E407: ktoe | F407: EnergyCons (base year), Elasticities | G407: mit.enc.oop.rod | H407: mit.enc.oop.rod | J407: =INDEX(Mapping!$C$5:$C$20,MATCH($C407,Mapping!$A$5:$A$20,0)) | K407: =INDEX(Mapping!$D$5:$D$20,MATCH($C407,Mapping!$A$5:$A$20,0)) | L407: =INDEX(Mapping!$C$24:$C$31,MATCH($B407,Mapping!$A$24:$A$31,0)) | M407: =INDEX(Mapping!$D$24:$D$31,MATCH($B407,Mapping!$A$24:$A$31,0)) | N407: =$B407&"."&IF(INDEX(Mapping!$E$24:$E$31,MATCH($B407,Mapping!$A$24:$A$31,0))="sub",INDEX(Mapping!$F$5:$F$20,MATCH($C407,Mapping!$A$5:$A$20,0)),"all") | O407: =INDEX(Mapping!$E$5:$E$20,MATCH($C407,Mapping!$A$5:$A$20,0)) | P407: =INDEX(Mapping!$G$24:$G$31,MATCH($B407,Mapping!$A$24:$A$31,0)) | Q407: =INDEX(Elasticities!$F$4:$I$200,MATCH("inc|"&$L407&"|"&$K407,Elasticities!$A$4:$A$200,0),MATCH(Settings!$C$6,Elasticities!$F$3:$I$3,0)) | R407: =INDEX(Elasticities!$F$4:$I$200,MATCH("usg|"&$L407&"|"&$K407,Elasticities!$A$4:$A$200,0),MATCH(Settings!$C$6,Elasticities!$F$3:$I$3,0)) | S407: =INDEX(Elasticities!$F$4:$I$200,MATCH("eff|"&$L407&"|"&$K407,Elasticities!$A$4:$A$200,0),MATCH(Settings!$C$6,Elasticities!$F$3:$I$3,0)) | T407: =INDEX(Elasticities!$F$4:$I$200,MATCH("aei|"&$M407&"|"&$K407,Elasticities!$A$4:$A$200,0),MATCH(Settings!$C$6,Elasticities!$F$3:$I$3,0)) | V407: =Q407 | W407: =R407 | X407: =S407 | Y407: =T407 | AA407: =Q407 | AB407: =R407 | AC407: =S407 | AD407: =T407 | AF407: =Q407 | AG407: =R407 | AH407: =S407 | AI407: =T407 | AL407: =INDEX(EnergyCons!$F$4:$F$5000,MATCH(Settings!$C$4&"|"&AL$5&"|"&$C407&"|"&$B407,EnergyCons!$A$4:$A$5000,0)) | AM407: =AL407*(1/(1+INDEX($Q407:$AJ407,1,(AM$4-1)*5+4)))^(1+INDEX($Q407:$AJ407,1,(AM$4-1)*5+2))*(1+AM$7)^INDEX($Q407:$AJ407,1,(AM$4-1)*5+1)*(AM277/AL277)^INDEX($Q407:$AJ407,1,(AM$4-1)*5+2)*(AM277/AL277)^(INDEX($Q407:$AJ407,1,(AM$4-1)*5+3)*(1+INDEX($Q407:$AJ407,1,(AM$4-1)*5+2))) | AN407: =AM407*(1/(1+INDEX($Q407:$AJ407,1,(AN$4-1)*5+4)))^(1+INDEX($Q407:$AJ407,1,(AN$4-1)*5+2))*(1+AN$7)^INDEX($Q407:$AJ407,1,(AN$4-1)*5+1)*(AN277/AM277)^INDEX($Q407:$AJ407,1,(AN$4-1)*5+2)*(AN277/AM277)^(INDEX($Q407:$AJ407,1,(AN$4-1)*5+3)*(1+INDEX($Q407:$AJ407,1,(AN$4-1)*5+2))) | AO407: =AN407*(1/(1+INDEX($Q407:$AJ407,1,(AO$4-1)*5+4)))^(1+INDEX($Q407:$AJ407,1,(AO$4-1)*5+2))*(1+AO$7)^INDEX($Q407:$AJ407,1,(AO$4-1)*5+1)*(AO277/AN277)^INDEX($Q407:$AJ407,1,(AO$4-1)*5+2)*(AO277/AN277)^(INDEX($Q407:$AJ407,1,(AO$4-1)*5+3)*(1+INDEX($Q407:$AJ407,1,(AO$4-1)*5+2))) | AP407: =AO407*(1/(1+INDEX($Q407:$AJ407,1,(AP$4-1)*5+4)))^(1+INDEX($Q407:$AJ407,1,(AP$4-1)*5+2))*(1+AP$7)^INDEX($Q407:$AJ407,1,(AP$4-1)*5+1)*(AP277/AO277)^INDEX($Q407:$AJ407,1,(AP$4-1)*5+2)*(AP277/AO277)^(INDEX($Q407:$AJ407,1,(AP$4-1)*5+3)*(1+INDEX($Q407:$AJ407,1,(AP$4-1)*5+2))) | AQ407: =AP407*(1/(1+INDEX($Q407:$AJ407,1,(AQ$4-1)*5+4)))^(1+INDEX($Q407:$AJ407,1,(AQ$4-1)*5+2))*(1+AQ$7)^INDEX($Q407:$AJ407,1,(AQ$4-1)*5+1)*(AQ277/AP277)^INDEX($Q407:$AJ407,1,(AQ$4-1)*5+2)*(AQ277/AP277)^(INDEX($Q407:$AJ407,1,(AQ$4-1)*5+3)*(1+INDEX($Q407:$AJ407,1,(AQ$4-1)*5+2))) | AR407: =AQ407*(1/(1+INDEX($Q407:$AJ407,1,(AR$4-1)*5+4)))^(1+INDEX($Q407:$AJ407,1,(AR$4-1)*5+2))*(1+AR$7)^INDEX($Q407:$AJ407,1,(AR$4-1)*5+1)*(AR277/AQ277)^INDEX($Q407:$AJ407,1,(AR$4-1)*5+2)*(AR277/AQ277)^(INDEX($Q407:$AJ407,1,(AR$4-1)*5+3)*(1+INDEX($Q407:$AJ407,1,(AR$4-1)*5+2))) | AS407: =AR407*(1/(1+INDEX($Q407:$AJ407,1,(AS$4-1)*5+4)))^(1+INDEX($Q407:$AJ407,1,(AS$4-1)*5+2))*(1+AS$7)^INDEX($Q407:$AJ407,1,(AS$4-1)*5+1)*(AS277/AR277)^INDEX($Q407:$AJ407,1,(AS$4-1)*5+2)*(AS277/AR277)^(INDEX($Q407:$AJ407,1,(AS$4-1)*5+3)*(1+INDEX($Q407:$AJ407,1,(AS$4-1)*5+2))) | AT407: =AS407*(1/(1+INDEX($Q407:$AJ407,1,(AT$4-1)*5+4)))^(1+INDEX($Q407:$AJ407,1,(AT$4-1)*5+2))*(1+AT$7)^INDEX($Q407:$AJ407,1,(AT$4-1)*5+1)*(AT277/AS277)^INDEX($Q407:$AJ407,1,(AT$4-1)*5+2)*(AT277/AS277)^(INDEX($Q407:$AJ407,1,(AT$4-1)*5+3)*(1+INDEX($Q407:$AJ407,1,(AT$4-1)*5+2))) | ... AY407: =AX407*(1/(1+INDEX($Q407:$AJ407,1,(AY$4-1)*5+4)))^(1+INDEX($Q407:$AJ407,1,(AY$4-1)*5+2))*(1+AY$7)^INDEX($Q407:$AJ407,1,(AY$4-1)*5+1)*(AY277/AX277)^INDEX($Q407:$AJ407,1,(AY$4-1)*5+2)*(AY277/AX277)^(INDEX($Q407:$AJ407,1,(AY$4-1)*5+3)*(1+INDEX($Q407:$AJ407,1,(AY$4-1)*5+2))) | BA407: =INDEX(EnergyCons!$F$4:$F$5000,MATCH(Settings!$C$4&"|"&BA$5&"|"&$C407&"|"&$B407,EnergyCons!$A$4:$A$5000,0)) | BB407: =BA407*(1/(1+INDEX($Q407:$AJ407,1,(BB$4-1)*5+4)))^(1+INDEX($Q407:$AJ407,1,(BB$4-1)*5+2))*(1+BB$7)^INDEX($Q407:$AJ407,1,(BB$4-1)*5+1)*(BB277/BA277)^INDEX($Q407:$AJ407,1,(BB$4-1)*5+2)*(BB277/BA277)^(INDEX($Q407:$AJ407,1,(BB$4-1)*5+3)*(1+INDEX($Q407:$AJ407,1,(BB$4-1)*5+2))) | BC407: =BB407*(1/(1+INDEX($Q407:$AJ407,1,(BC$4-1)*5+4)))^(1+INDEX($Q407:$AJ407,1,(BC$4-1)*5+2))*(1+BC$7)^INDEX($Q407:$AJ407,1,(BC$4-1)*5+1)*(BC277/BB277)^INDEX($Q407:$AJ407,1,(BC$4-1)*5+2)*(BC277/BB277)^(INDEX($Q407:$AJ407,1,(BC$4-1)*5+3)*(1+INDEX($Q407:$AJ407,1,(BC$4-1)*5+2))) | BD407: =BC407*(1/(1+INDEX($Q407:$AJ407,1,(BD$4-1)*5+4)))^(1+INDEX($Q407:$AJ407,1,(BD$4-1)*5+2))*(1+BD$7)^INDEX($Q407:$AJ407,1,(BD$4-1)*5+1)*(BD277/BC277)^INDEX($Q407:$AJ407,1,(BD$4-1)*5+2)*(BD277/BC277)^(INDEX($Q407:$AJ407,1,(BD$4-1)*5+3)*(1+INDEX($Q407:$AJ407,1,(BD$4-1)*5+2))) | BE407: =BD407*(1/(1+INDEX($Q407:$AJ407,1,(BE$4-1)*5+4)))^(1+INDEX($Q407:$AJ407,1,(BE$4-1)*5+2))*(1+BE$7)^INDEX($Q407:$AJ407,1,(BE$4-1)*5+1)*(BE277/BD277)^INDEX($Q407:$AJ407,1,(BE$4-1)*5+2)*(BE277/BD277)^(INDEX($Q407:$AJ407,1,(BE$4-1)*5+3)*(1+INDEX($Q407:$AJ407,1,(BE$4-1)*5+2))) | BF407: =BE407*(1/(1+INDEX($Q407:$AJ407,1,(BF$4-1)*5+4)))^(1+INDEX($Q407:$AJ407,1,(BF$4-1)*5+2))*(1+BF$7)^INDEX($Q407:$AJ407,1,(BF$4-1)*5+1)*(BF277/BE277)^INDEX($Q407:$AJ407,1,(BF$4-1)*5+2)*(BF277/BE277)^(INDEX($Q407:$AJ407,1,(BF$4-1)*5+3)*(1+INDEX($Q407:$AJ407,1,(BF$4-1)*5+2))) | BG407: =BF407*(1/(1+INDEX($Q407:$AJ407,1,(BG$4-1)*5+4)))^(1+INDEX($Q407:$AJ407,1,(BG$4-1)*5+2))*(1+BG$7)^INDEX($Q407:$AJ407,1,(BG$4-1)*5+1)*(BG277/BF277)^INDEX($Q407:$AJ407,1,(BG$4-1)*5+2)*(BG277/BF277)^(INDEX($Q407:$AJ407,1,(BG$4-1)*5+3)*(1+INDEX($Q407:$AJ407,1,(BG$4-1)*5+2))) | BH407: =BG407*(1/(1+INDEX($Q407:$AJ407,1,(BH$4-1)*5+4)))^(1+INDEX($Q407:$AJ407,1,(BH$4-1)*5+2))*(1+BH$7)^INDEX($Q407:$AJ407,1,(BH$4-1)*5+1)*(BH277/BG277)^INDEX($Q407:$AJ407,1,(BH$4-1)*5+2)*(BH277/BG277)^(INDEX($Q407:$AJ407,1,(BH$4-1)*5+3)*(1+INDEX($Q407:$AJ407,1,(BH$4-1)*5+2))) | BI407: =BH407*(1/(1+INDEX($Q407:$AJ407,1,(BI$4-1)*5+4)))^(1+INDEX($Q407:$AJ407,1,(BI$4-1)*5+2))*(1+BI$7)^INDEX($Q407:$AJ407,1,(BI$4-1)*5+1)*(BI277/BH277)^INDEX($Q407:$AJ407,1,(BI$4-1)*5+2)*(BI277/BH277)^(INDEX($Q407:$AJ407,1,(BI$4-1)*5+3)*(1+INDEX($Q407:$AJ407,1,(BI$4-1)*5+2))) | ... BN407: =BM407*(1/(1+INDEX($Q407:$AJ407,1,(BN$4-1)*5+4)))^(1+INDEX($Q407:$AJ407,1,(BN$4-1)*5+2))*(1+BN$7)^INDEX($Q407:$AJ407,1,(BN$4-1)*5+1)*(BN277/BM277)^INDEX($Q407:$AJ407,1,(BN$4-1)*5+2)*(BN277/BM277)^(INDEX($Q407:$AJ407,1,(BN$4-1)*5+3)*(1+INDEX($Q407:$AJ407,1,(BN$4-1)*5+2)))
B408: bio | C408: rod | D408: Fuel use | Road | Biomass | E408: ktoe | F408: EnergyCons (base year), Elasticities | G408: mit.enc.bio.rod | H408: mit.enc.bio.rod | J408: =INDEX(Mapping!$C$5:$C$20,MATCH($C408,Mapping!$A$5:$A$20,0)) | K408: =INDEX(Mapping!$D$5:$D$20,MATCH($C408,Mapping!$A$5:$A$20,0)) | L408: =INDEX(Mapping!$C$24:$C$31,MATCH($B408,Mapping!$A$24:$A$31,0)) | M408: =INDEX(Mapping!$D$24:$D$31,MATCH($B408,Mapping!$A$24:$A$31,0)) | N408: =$B408&"."&IF(INDEX(Mapping!$E$24:$E$31,MATCH($B408,Mapping!$A$24:$A$31,0))="sub",INDEX(Mapping!$F$5:$F$20,MATCH($C408,Mapping!$A$5:$A$20,0)),"all") | O408: =INDEX(Mapping!$E$5:$E$20,MATCH($C408,Mapping!$A$5:$A$20,0)) | P408: =INDEX(Mapping!$G$24:$G$31,MATCH($B408,Mapping!$A$24:$A$31,0)) | Q408: =INDEX(Elasticities!$F$4:$I$200,MATCH("inc|"&$L408&"|"&$K408,Elasticities!$A$4:$A$200,0),MATCH(Settings!$C$6,Elasticities!$F$3:$I$3,0)) | R408: =INDEX(Elasticities!$F$4:$I$200,MATCH("usg|"&$L408&"|"&$K408,Elasticities!$A$4:$A$200,0),MATCH(Settings!$C$6,Elasticities!$F$3:$I$3,0)) | S408: =INDEX(Elasticities!$F$4:$I$200,MATCH("eff|"&$L408&"|"&$K408,Elasticities!$A$4:$A$200,0),MATCH(Settings!$C$6,Elasticities!$F$3:$I$3,0)) | T408: =INDEX(Elasticities!$F$4:$I$200,MATCH("aei|"&$M408&"|"&$K408,Elasticities!$A$4:$A$200,0),MATCH(Settings!$C$6,Elasticities!$F$3:$I$3,0)) | V408: =Q408 | W408: =R408 | X408: =S408 | Y408: =T408 | AA408: =Q408 | AB408: =R408 | AC408: =S408 | AD408: =T408 | AF408: =Q408 | AG408: =R408 | AH408: =S408 | AI408: =T408 | AL408: =INDEX(EnergyCons!$F$4:$F$5000,MATCH(Settings!$C$4&"|"&AL$5&"|"&$C408&"|"&$B408,EnergyCons!$A$4:$A$5000,0)) | AM408: =AL408*(1/(1+INDEX($Q408:$AJ408,1,(AM$4-1)*5+4)))^(1+INDEX($Q408:$AJ408,1,(AM$4-1)*5+2))*(1+AM$7)^INDEX($Q408:$AJ408,1,(AM$4-1)*5+1)*(AM278/AL278)^INDEX($Q408:$AJ408,1,(AM$4-1)*5+2)*(AM278/AL278)^(INDEX($Q408:$AJ408,1,(AM$4-1)*5+3)*(1+INDEX($Q408:$AJ408,1,(AM$4-1)*5+2))) | AN408: =AM408*(1/(1+INDEX($Q408:$AJ408,1,(AN$4-1)*5+4)))^(1+INDEX($Q408:$AJ408,1,(AN$4-1)*5+2))*(1+AN$7)^INDEX($Q408:$AJ408,1,(AN$4-1)*5+1)*(AN278/AM278)^INDEX($Q408:$AJ408,1,(AN$4-1)*5+2)*(AN278/AM278)^(INDEX($Q408:$AJ408,1,(AN$4-1)*5+3)*(1+INDEX($Q408:$AJ408,1,(AN$4-1)*5+2))) | AO408: =AN408*(1/(1+INDEX($Q408:$AJ408,1,(AO$4-1)*5+4)))^(1+INDEX($Q408:$AJ408,1,(AO$4-1)*5+2))*(1+AO$7)^INDEX($Q408:$AJ408,1,(AO$4-1)*5+1)*(AO278/AN278)^INDEX($Q408:$AJ408,1,(AO$4-1)*5+2)*(AO278/AN278)^(INDEX($Q408:$AJ408,1,(AO$4-1)*5+3)*(1+INDEX($Q408:$AJ408,1,(AO$4-1)*5+2))) | AP408: =AO408*(1/(1+INDEX($Q408:$AJ408,1,(AP$4-1)*5+4)))^(1+INDEX($Q408:$AJ408,1,(AP$4-1)*5+2))*(1+AP$7)^INDEX($Q408:$AJ408,1,(AP$4-1)*5+1)*(AP278/AO278)^INDEX($Q408:$AJ408,1,(AP$4-1)*5+2)*(AP278/AO278)^(INDEX($Q408:$AJ408,1,(AP$4-1)*5+3)*(1+INDEX($Q408:$AJ408,1,(AP$4-1)*5+2))) | AQ408: =AP408*(1/(1+INDEX($Q408:$AJ408,1,(AQ$4-1)*5+4)))^(1+INDEX($Q408:$AJ408,1,(AQ$4-1)*5+2))*(1+AQ$7)^INDEX($Q408:$AJ408,1,(AQ$4-1)*5+1)*(AQ278/AP278)^INDEX($Q408:$AJ408,1,(AQ$4-1)*5+2)*(AQ278/AP278)^(INDEX($Q408:$AJ408,1,(AQ$4-1)*5+3)*(1+INDEX($Q408:$AJ408,1,(AQ$4-1)*5+2))) | AR408: =AQ408*(1/(1+INDEX($Q408:$AJ408,1,(AR$4-1)*5+4)))^(1+INDEX($Q408:$AJ408,1,(AR$4-1)*5+2))*(1+AR$7)^INDEX($Q408:$AJ408,1,(AR$4-1)*5+1)*(AR278/AQ278)^INDEX($Q408:$AJ408,1,(AR$4-1)*5+2)*(AR278/AQ278)^(INDEX($Q408:$AJ408,1,(AR$4-1)*5+3)*(1+INDEX($Q408:$AJ408,1,(AR$4-1)*5+2))) | AS408: =AR408*(1/(1+INDEX($Q408:$AJ408,1,(AS$4-1)*5+4)))^(1+INDEX($Q408:$AJ408,1,(AS$4-1)*5+2))*(1+AS$7)^INDEX($Q408:$AJ408,1,(AS$4-1)*5+1)*(AS278/AR278)^INDEX($Q408:$AJ408,1,(AS$4-1)*5+2)*(AS278/AR278)^(INDEX($Q408:$AJ408,1,(AS$4-1)*5+3)*(1+INDEX($Q408:$AJ408,1,(AS$4-1)*5+2))) | AT408: =AS408*(1/(1+INDEX($Q408:$AJ408,1,(AT$4-1)*5+4)))^(1+INDEX($Q408:$AJ408,1,(AT$4-1)*5+2))*(1+AT$7)^INDEX($Q408:$AJ408,1,(AT$4-1)*5+1)*(AT278/AS278)^INDEX($Q408:$AJ408,1,(AT$4-1)*5+2)*(AT278/AS278)^(INDEX($Q408:$AJ408,1,(AT$4-1)*5+3)*(1+INDEX($Q408:$AJ408,1,(AT$4-1)*5+2))) | ... AY408: =AX408*(1/(1+INDEX($Q408:$AJ408,1,(AY$4-1)*5+4)))^(1+INDEX($Q408:$AJ408,1,(AY$4-1)*5+2))*(1+AY$7)^INDEX($Q408:$AJ408,1,(AY$4-1)*5+1)*(AY278/AX278)^INDEX($Q408:$AJ408,1,(AY$4-1)*5+2)*(AY278/AX278)^(INDEX($Q408:$AJ408,1,(AY$4-1)*5+3)*(1+INDEX($Q408:$AJ408,1,(AY$4-1)*5+2))) | BA408: =INDEX(EnergyCons!$F$4:$F$5000,MATCH(Settings!$C$4&"|"&BA$5&"|"&$C408&"|"&$B408,EnergyCons!$A$4:$A$5000,0)) | BB408: =BA408*(1/(1+INDEX($Q408:$AJ408,1,(BB$4-1)*5+4)))^(1+INDEX($Q408:$AJ408,1,(BB$4-1)*5+2))*(1+BB$7)^INDEX($Q408:$AJ408,1,(BB$4-1)*5+1)*(BB278/BA278)^INDEX($Q408:$AJ408,1,(BB$4-1)*5+2)*(BB278/BA278)^(INDEX($Q408:$AJ408,1,(BB$4-1)*5+3)*(1+INDEX($Q408:$AJ408,1,(BB$4-1)*5+2))) | BC408: =BB408*(1/(1+INDEX($Q408:$AJ408,1,(BC$4-1)*5+4)))^(1+INDEX($Q408:$AJ408,1,(BC$4-1)*5+2))*(1+BC$7)^INDEX($Q408:$AJ408,1,(BC$4-1)*5+1)*(BC278/BB278)^INDEX($Q408:$AJ408,1,(BC$4-1)*5+2)*(BC278/BB278)^(INDEX($Q408:$AJ408,1,(BC$4-1)*5+3)*(1+INDEX($Q408:$AJ408,1,(BC$4-1)*5+2))) | BD408: =BC408*(1/(1+INDEX($Q408:$AJ408,1,(BD$4-1)*5+4)))^(1+INDEX($Q408:$AJ408,1,(BD$4-1)*5+2))*(1+BD$7)^INDEX($Q408:$AJ408,1,(BD$4-1)*5+1)*(BD278/BC278)^INDEX($Q408:$AJ408,1,(BD$4-1)*5+2)*(BD278/BC278)^(INDEX($Q408:$AJ408,1,(BD$4-1)*5+3)*(1+INDEX($Q408:$AJ408,1,(BD$4-1)*5+2))) | BE408: =BD408*(1/(1+INDEX($Q408:$AJ408,1,(BE$4-1)*5+4)))^(1+INDEX($Q408:$AJ408,1,(BE$4-1)*5+2))*(1+BE$7)^INDEX($Q408:$AJ408,1,(BE$4-1)*5+1)*(BE278/BD278)^INDEX($Q408:$AJ408,1,(BE$4-1)*5+2)*(BE278/BD278)^(INDEX($Q408:$AJ408,1,(BE$4-1)*5+3)*(1+INDEX($Q408:$AJ408,1,(BE$4-1)*5+2))) | BF408: =BE408*(1/(1+INDEX($Q408:$AJ408,1,(BF$4-1)*5+4)))^(1+INDEX($Q408:$AJ408,1,(BF$4-1)*5+2))*(1+BF$7)^INDEX($Q408:$AJ408,1,(BF$4-1)*5+1)*(BF278/BE278)^INDEX($Q408:$AJ408,1,(BF$4-1)*5+2)*(BF278/BE278)^(INDEX($Q408:$AJ408,1,(BF$4-1)*5+3)*(1+INDEX($Q408:$AJ408,1,(BF$4-1)*5+2))) | BG408: =BF408*(1/(1+INDEX($Q408:$AJ408,1,(BG$4-1)*5+4)))^(1+INDEX($Q408:$AJ408,1,(BG$4-1)*5+2))*(1+BG$7)^INDEX($Q408:$AJ408,1,(BG$4-1)*5+1)*(BG278/BF278)^INDEX($Q408:$AJ408,1,(BG$4-1)*5+2)*(BG278/BF278)^(INDEX($Q408:$AJ408,1,(BG$4-1)*5+3)*(1+INDEX($Q408:$AJ408,1,(BG$4-1)*5+2))) | BH408: =BG408*(1/(1+INDEX($Q408:$AJ408,1,(BH$4-1)*5+4)))^(1+INDEX($Q408:$AJ408,1,(BH$4-1)*5+2))*(1+BH$7)^INDEX($Q408:$AJ408,1,(BH$4-1)*5+1)*(BH278/BG278)^INDEX($Q408:$AJ408,1,(BH$4-1)*5+2)*(BH278/BG278)^(INDEX($Q408:$AJ408,1,(BH$4-1)*5+3)*(1+INDEX($Q408:$AJ408,1,(BH$4-1)*5+2))) | BI408: =BH408*(1/(1+INDEX($Q408:$AJ408,1,(BI$4-1)*5+4)))^(1+INDEX($Q408:$AJ408,1,(BI$4-1)*5+2))*(1+BI$7)^INDEX($Q408:$AJ408,1,(BI$4-1)*5+1)*(BI278/BH278)^INDEX($Q408:$AJ408,1,(BI$4-1)*5+2)*(BI278/BH278)^(INDEX($Q408:$AJ408,1,(BI$4-1)*5+3)*(1+INDEX($Q408:$AJ408,1,(BI$4-1)*5+2))) | ... BN408: =BM408*(1/(1+INDEX($Q408:$AJ408,1,(BN$4-1)*5+4)))^(1+INDEX($Q408:$AJ408,1,(BN$4-1)*5+2))*(1+BN$7)^INDEX($Q408:$AJ408,1,(BN$4-1)*5+1)*(BN278/BM278)^INDEX($Q408:$AJ408,1,(BN$4-1)*5+2)*(BN278/BM278)^(INDEX($Q408:$AJ408,1,(BN$4-1)*5+3)*(1+INDEX($Q408:$AJ408,1,(BN$4-1)*5+2)))
B409: coa | C409: ral | D409: Fuel use | Rail | Coal | E409: ktoe | F409: EnergyCons (base year), Elasticities | G409: mit.enc.coa.ral | H409: mit.enc.coa.ral | J409: =INDEX(Mapping!$C$5:$C$20,MATCH($C409,Mapping!$A$5:$A$20,0)) | K409: =INDEX(Mapping!$D$5:$D$20,MATCH($C409,Mapping!$A$5:$A$20,0)) | L409: =INDEX(Mapping!$C$24:$C$31,MATCH($B409,Mapping!$A$24:$A$31,0)) | M409: =INDEX(Mapping!$D$24:$D$31,MATCH($B409,Mapping!$A$24:$A$31,0)) | N409: =$B409&"."&IF(INDEX(Mapping!$E$24:$E$31,MATCH($B409,Mapping!$A$24:$A$31,0))="sub",INDEX(Mapping!$F$5:$F$20,MATCH($C409,Mapping!$A$5:$A$20,0)),"all") | O409: =INDEX(Mapping!$E$5:$E$20,MATCH($C409,Mapping!$A$5:$A$20,0)) | P409: =INDEX(Mapping!$G$24:$G$31,MATCH($B409,Mapping!$A$24:$A$31,0)) | Q409: =INDEX(Elasticities!$F$4:$I$200,MATCH("inc|"&$L409&"|"&$K409,Elasticities!$A$4:$A$200,0),MATCH(Settings!$C$6,Elasticities!$F$3:$I$3,0)) | R409: =INDEX(Elasticities!$F$4:$I$200,MATCH("usg|"&$L409&"|"&$K409,Elasticities!$A$4:$A$200,0),MATCH(Settings!$C$6,Elasticities!$F$3:$I$3,0)) | S409: =INDEX(Elasticities!$F$4:$I$200,MATCH("eff|"&$L409&"|"&$K409,Elasticities!$A$4:$A$200,0),MATCH(Settings!$C$6,Elasticities!$F$3:$I$3,0)) | T409: =INDEX(Elasticities!$F$4:$I$200,MATCH("aei|"&$M409&"|"&$K409,Elasticities!$A$4:$A$200,0),MATCH(Settings!$C$6,Elasticities!$F$3:$I$3,0)) | V409: =Q409 | W409: =R409 | X409: =S409 | Y409: =T409 | AA409: =Q409 | AB409: =R409 | AC409: =S409 | AD409: =T409 | AF409: =Q409 | AG409: =R409 | AH409: =S409 | AI409: =T409 | AL409: =INDEX(EnergyCons!$F$4:$F$5000,MATCH(Settings!$C$4&"|"&AL$5&"|"&$C409&"|"&$B409,EnergyCons!$A$4:$A$5000,0)) | AM409: =AL409*(1/(1+INDEX($Q409:$AJ409,1,(AM$4-1)*5+4)))^(1+INDEX($Q409:$AJ409,1,(AM$4-1)*5+2))*(1+AM$7)^INDEX($Q409:$AJ409,1,(AM$4-1)*5+1)*(AM279/AL279)^INDEX($Q409:$AJ409,1,(AM$4-1)*5+2)*(AM279/AL279)^(INDEX($Q409:$AJ409,1,(AM$4-1)*5+3)*(1+INDEX($Q409:$AJ409,1,(AM$4-1)*5+2))) | AN409: =AM409*(1/(1+INDEX($Q409:$AJ409,1,(AN$4-1)*5+4)))^(1+INDEX($Q409:$AJ409,1,(AN$4-1)*5+2))*(1+AN$7)^INDEX($Q409:$AJ409,1,(AN$4-1)*5+1)*(AN279/AM279)^INDEX($Q409:$AJ409,1,(AN$4-1)*5+2)*(AN279/AM279)^(INDEX($Q409:$AJ409,1,(AN$4-1)*5+3)*(1+INDEX($Q409:$AJ409,1,(AN$4-1)*5+2))) | AO409: =AN409*(1/(1+INDEX($Q409:$AJ409,1,(AO$4-1)*5+4)))^(1+INDEX($Q409:$AJ409,1,(AO$4-1)*5+2))*(1+AO$7)^INDEX($Q409:$AJ409,1,(AO$4-1)*5+1)*(AO279/AN279)^INDEX($Q409:$AJ409,1,(AO$4-1)*5+2)*(AO279/AN279)^(INDEX($Q409:$AJ409,1,(AO$4-1)*5+3)*(1+INDEX($Q409:$AJ409,1,(AO$4-1)*5+2))) | AP409: =AO409*(1/(1+INDEX($Q409:$AJ409,1,(AP$4-1)*5+4)))^(1+INDEX($Q409:$AJ409,1,(AP$4-1)*5+2))*(1+AP$7)^INDEX($Q409:$AJ409,1,(AP$4-1)*5+1)*(AP279/AO279)^INDEX($Q409:$AJ409,1,(AP$4-1)*5+2)*(AP279/AO279)^(INDEX($Q409:$AJ409,1,(AP$4-1)*5+3)*(1+INDEX($Q409:$AJ409,1,(AP$4-1)*5+2))) | AQ409: =AP409*(1/(1+INDEX($Q409:$AJ409,1,(AQ$4-1)*5+4)))^(1+INDEX($Q409:$AJ409,1,(AQ$4-1)*5+2))*(1+AQ$7)^INDEX($Q409:$AJ409,1,(AQ$4-1)*5+1)*(AQ279/AP279)^INDEX($Q409:$AJ409,1,(AQ$4-1)*5+2)*(AQ279/AP279)^(INDEX($Q409:$AJ409,1,(AQ$4-1)*5+3)*(1+INDEX($Q409:$AJ409,1,(AQ$4-1)*5+2))) | AR409: =AQ409*(1/(1+INDEX($Q409:$AJ409,1,(AR$4-1)*5+4)))^(1+INDEX($Q409:$AJ409,1,(AR$4-1)*5+2))*(1+AR$7)^INDEX($Q409:$AJ409,1,(AR$4-1)*5+1)*(AR279/AQ279)^INDEX($Q409:$AJ409,1,(AR$4-1)*5+2)*(AR279/AQ279)^(INDEX($Q409:$AJ409,1,(AR$4-1)*5+3)*(1+INDEX($Q409:$AJ409,1,(AR$4-1)*5+2))) | AS409: =AR409*(1/(1+INDEX($Q409:$AJ409,1,(AS$4-1)*5+4)))^(1+INDEX($Q409:$AJ409,1,(AS$4-1)*5+2))*(1+AS$7)^INDEX($Q409:$AJ409,1,(AS$4-1)*5+1)*(AS279/AR279)^INDEX($Q409:$AJ409,1,(AS$4-1)*5+2)*(AS279/AR279)^(INDEX($Q409:$AJ409,1,(AS$4-1)*5+3)*(1+INDEX($Q409:$AJ409,1,(AS$4-1)*5+2))) | AT409: =AS409*(1/(1+INDEX($Q409:$AJ409,1,(AT$4-1)*5+4)))^(1+INDEX($Q409:$AJ409,1,(AT$4-1)*5+2))*(1+AT$7)^INDEX($Q409:$AJ409,1,(AT$4-1)*5+1)*(AT279/AS279)^INDEX($Q409:$AJ409,1,(AT$4-1)*5+2)*(AT279/AS279)^(INDEX($Q409:$AJ409,1,(AT$4-1)*5+3)*(1+INDEX($Q409:$AJ409,1,(AT$4-1)*5+2))) | ... AY409: =AX409*(1/(1+INDEX($Q409:$AJ409,1,(AY$4-1)*5+4)))^(1+INDEX($Q409:$AJ409,1,(AY$4-1)*5+2))*(1+AY$7)^INDEX($Q409:$AJ409,1,(AY$4-1)*5+1)*(AY279/AX279)^INDEX($Q409:$AJ409,1,(AY$4-1)*5+2)*(AY279/AX279)^(INDEX($Q409:$AJ409,1,(AY$4-1)*5+3)*(1+INDEX($Q409:$AJ409,1,(AY$4-1)*5+2))) | BA409: =INDEX(EnergyCons!$F$4:$F$5000,MATCH(Settings!$C$4&"|"&BA$5&"|"&$C409&"|"&$B409,EnergyCons!$A$4:$A$5000,0)) | BB409: =BA409*(1/(1+INDEX($Q409:$AJ409,1,(BB$4-1)*5+4)))^(1+INDEX($Q409:$AJ409,1,(BB$4-1)*5+2))*(1+BB$7)^INDEX($Q409:$AJ409,1,(BB$4-1)*5+1)*(BB279/BA279)^INDEX($Q409:$AJ409,1,(BB$4-1)*5+2)*(BB279/BA279)^(INDEX($Q409:$AJ409,1,(BB$4-1)*5+3)*(1+INDEX($Q409:$AJ409,1,(BB$4-1)*5+2))) | BC409: =BB409*(1/(1+INDEX($Q409:$AJ409,1,(BC$4-1)*5+4)))^(1+INDEX($Q409:$AJ409,1,(BC$4-1)*5+2))*(1+BC$7)^INDEX($Q409:$AJ409,1,(BC$4-1)*5+1)*(BC279/BB279)^INDEX($Q409:$AJ409,1,(BC$4-1)*5+2)*(BC279/BB279)^(INDEX($Q409:$AJ409,1,(BC$4-1)*5+3)*(1+INDEX($Q409:$AJ409,1,(BC$4-1)*5+2))) | BD409: =BC409*(1/(1+INDEX($Q409:$AJ409,1,(BD$4-1)*5+4)))^(1+INDEX($Q409:$AJ409,1,(BD$4-1)*5+2))*(1+BD$7)^INDEX($Q409:$AJ409,1,(BD$4-1)*5+1)*(BD279/BC279)^INDEX($Q409:$AJ409,1,(BD$4-1)*5+2)*(BD279/BC279)^(INDEX($Q409:$AJ409,1,(BD$4-1)*5+3)*(1+INDEX($Q409:$AJ409,1,(BD$4-1)*5+2))) | BE409: =BD409*(1/(1+INDEX($Q409:$AJ409,1,(BE$4-1)*5+4)))^(1+INDEX($Q409:$AJ409,1,(BE$4-1)*5+2))*(1+BE$7)^INDEX($Q409:$AJ409,1,(BE$4-1)*5+1)*(BE279/BD279)^INDEX($Q409:$AJ409,1,(BE$4-1)*5+2)*(BE279/BD279)^(INDEX($Q409:$AJ409,1,(BE$4-1)*5+3)*(1+INDEX($Q409:$AJ409,1,(BE$4-1)*5+2))) | BF409: =BE409*(1/(1+INDEX($Q409:$AJ409,1,(BF$4-1)*5+4)))^(1+INDEX($Q409:$AJ409,1,(BF$4-1)*5+2))*(1+BF$7)^INDEX($Q409:$AJ409,1,(BF$4-1)*5+1)*(BF279/BE279)^INDEX($Q409:$AJ409,1,(BF$4-1)*5+2)*(BF279/BE279)^(INDEX($Q409:$AJ409,1,(BF$4-1)*5+3)*(1+INDEX($Q409:$AJ409,1,(BF$4-1)*5+2))) | BG409: =BF409*(1/(1+INDEX($Q409:$AJ409,1,(BG$4-1)*5+4)))^(1+INDEX($Q409:$AJ409,1,(BG$4-1)*5+2))*(1+BG$7)^INDEX($Q409:$AJ409,1,(BG$4-1)*5+1)*(BG279/BF279)^INDEX($Q409:$AJ409,1,(BG$4-1)*5+2)*(BG279/BF279)^(INDEX($Q409:$AJ409,1,(BG$4-1)*5+3)*(1+INDEX($Q409:$AJ409,1,(BG$4-1)*5+2))) | BH409: =BG409*(1/(1+INDEX($Q409:$AJ409,1,(BH$4-1)*5+4)))^(1+INDEX($Q409:$AJ409,1,(BH$4-1)*5+2))*(1+BH$7)^INDEX($Q409:$AJ409,1,(BH$4-1)*5+1)*(BH279/BG279)^INDEX($Q409:$AJ409,1,(BH$4-1)*5+2)*(BH279/BG279)^(INDEX($Q409:$AJ409,1,(BH$4-1)*5+3)*(1+INDEX($Q409:$AJ409,1,(BH$4-1)*5+2))) | BI409: =BH409*(1/(1+INDEX($Q409:$AJ409,1,(BI$4-1)*5+4)))^(1+INDEX($Q409:$AJ409,1,(BI$4-1)*5+2))*(1+BI$7)^INDEX($Q409:$AJ409,1,(BI$4-1)*5+1)*(BI279/BH279)^INDEX($Q409:$AJ409,1,(BI$4-1)*5+2)*(BI279/BH279)^(INDEX($Q409:$AJ409,1,(BI$4-1)*5+3)*(1+INDEX($Q409:$AJ409,1,(BI$4-1)*5+2))) | ... BN409: =BM409*(1/(1+INDEX($Q409:$AJ409,1,(BN$4-1)*5+4)))^(1+INDEX($Q409:$AJ409,1,(BN$4-1)*5+2))*(1+BN$7)^INDEX($Q409:$AJ409,1,(BN$4-1)*5+1)*(BN279/BM279)^INDEX($Q409:$AJ409,1,(BN$4-1)*5+2)*(BN279/BM279)^(INDEX($Q409:$AJ409,1,(BN$4-1)*5+3)*(1+INDEX($Q409:$AJ409,1,(BN$4-1)*5+2)))
B410: nga | C410: ral | D410: Fuel use | Rail | Natural gas | E410: ktoe | F410: EnergyCons (base year), Elasticities | G410: mit.enc.nga.ral | H410: mit.enc.nga.ral | J410: =INDEX(Mapping!$C$5:$C$20,MATCH($C410,Mapping!$A$5:$A$20,0)) | K410: =INDEX(Mapping!$D$5:$D$20,MATCH($C410,Mapping!$A$5:$A$20,0)) | L410: =INDEX(Mapping!$C$24:$C$31,MATCH($B410,Mapping!$A$24:$A$31,0)) | M410: =INDEX(Mapping!$D$24:$D$31,MATCH($B410,Mapping!$A$24:$A$31,0)) | N410: =$B410&"."&IF(INDEX(Mapping!$E$24:$E$31,MATCH($B410,Mapping!$A$24:$A$31,0))="sub",INDEX(Mapping!$F$5:$F$20,MATCH($C410,Mapping!$A$5:$A$20,0)),"all") | O410: =INDEX(Mapping!$E$5:$E$20,MATCH($C410,Mapping!$A$5:$A$20,0)) | P410: =INDEX(Mapping!$G$24:$G$31,MATCH($B410,Mapping!$A$24:$A$31,0)) | Q410: =INDEX(Elasticities!$F$4:$I$200,MATCH("inc|"&$L410&"|"&$K410,Elasticities!$A$4:$A$200,0),MATCH(Settings!$C$6,Elasticities!$F$3:$I$3,0)) | R410: =INDEX(Elasticities!$F$4:$I$200,MATCH("usg|"&$L410&"|"&$K410,Elasticities!$A$4:$A$200,0),MATCH(Settings!$C$6,Elasticities!$F$3:$I$3,0)) | S410: =INDEX(Elasticities!$F$4:$I$200,MATCH("eff|"&$L410&"|"&$K410,Elasticities!$A$4:$A$200,0),MATCH(Settings!$C$6,Elasticities!$F$3:$I$3,0)) | T410: =INDEX(Elasticities!$F$4:$I$200,MATCH("aei|"&$M410&"|"&$K410,Elasticities!$A$4:$A$200,0),MATCH(Settings!$C$6,Elasticities!$F$3:$I$3,0)) | V410: =Q410 | W410: =R410 | X410: =S410 | Y410: =T410 | AA410: =Q410 | AB410: =R410 | AC410: =S410 | AD410: =T410 | AF410: =Q410 | AG410: =R410 | AH410: =S410 | AI410: =T410 | AL410: =INDEX(EnergyCons!$F$4:$F$5000,MATCH(Settings!$C$4&"|"&AL$5&"|"&$C410&"|"&$B410,EnergyCons!$A$4:$A$5000,0)) | AM410: =AL410*(1/(1+INDEX($Q410:$AJ410,1,(AM$4-1)*5+4)))^(1+INDEX($Q410:$AJ410,1,(AM$4-1)*5+2))*(1+AM$7)^INDEX($Q410:$AJ410,1,(AM$4-1)*5+1)*(AM280/AL280)^INDEX($Q410:$AJ410,1,(AM$4-1)*5+2)*(AM280/AL280)^(INDEX($Q410:$AJ410,1,(AM$4-1)*5+3)*(1+INDEX($Q410:$AJ410,1,(AM$4-1)*5+2))) | AN410: =AM410*(1/(1+INDEX($Q410:$AJ410,1,(AN$4-1)*5+4)))^(1+INDEX($Q410:$AJ410,1,(AN$4-1)*5+2))*(1+AN$7)^INDEX($Q410:$AJ410,1,(AN$4-1)*5+1)*(AN280/AM280)^INDEX($Q410:$AJ410,1,(AN$4-1)*5+2)*(AN280/AM280)^(INDEX($Q410:$AJ410,1,(AN$4-1)*5+3)*(1+INDEX($Q410:$AJ410,1,(AN$4-1)*5+2))) | AO410: =AN410*(1/(1+INDEX($Q410:$AJ410,1,(AO$4-1)*5+4)))^(1+INDEX($Q410:$AJ410,1,(AO$4-1)*5+2))*(1+AO$7)^INDEX($Q410:$AJ410,1,(AO$4-1)*5+1)*(AO280/AN280)^INDEX($Q410:$AJ410,1,(AO$4-1)*5+2)*(AO280/AN280)^(INDEX($Q410:$AJ410,1,(AO$4-1)*5+3)*(1+INDEX($Q410:$AJ410,1,(AO$4-1)*5+2))) | AP410: =AO410*(1/(1+INDEX($Q410:$AJ410,1,(AP$4-1)*5+4)))^(1+INDEX($Q410:$AJ410,1,(AP$4-1)*5+2))*(1+AP$7)^INDEX($Q410:$AJ410,1,(AP$4-1)*5+1)*(AP280/AO280)^INDEX($Q410:$AJ410,1,(AP$4-1)*5+2)*(AP280/AO280)^(INDEX($Q410:$AJ410,1,(AP$4-1)*5+3)*(1+INDEX($Q410:$AJ410,1,(AP$4-1)*5+2))) | AQ410: =AP410*(1/(1+INDEX($Q410:$AJ410,1,(AQ$4-1)*5+4)))^(1+INDEX($Q410:$AJ410,1,(AQ$4-1)*5+2))*(1+AQ$7)^INDEX($Q410:$AJ410,1,(AQ$4-1)*5+1)*(AQ280/AP280)^INDEX($Q410:$AJ410,1,(AQ$4-1)*5+2)*(AQ280/AP280)^(INDEX($Q410:$AJ410,1,(AQ$4-1)*5+3)*(1+INDEX($Q410:$AJ410,1,(AQ$4-1)*5+2))) | AR410: =AQ410*(1/(1+INDEX($Q410:$AJ410,1,(AR$4-1)*5+4)))^(1+INDEX($Q410:$AJ410,1,(AR$4-1)*5+2))*(1+AR$7)^INDEX($Q410:$AJ410,1,(AR$4-1)*5+1)*(AR280/AQ280)^INDEX($Q410:$AJ410,1,(AR$4-1)*5+2)*(AR280/AQ280)^(INDEX($Q410:$AJ410,1,(AR$4-1)*5+3)*(1+INDEX($Q410:$AJ410,1,(AR$4-1)*5+2))) | AS410: =AR410*(1/(1+INDEX($Q410:$AJ410,1,(AS$4-1)*5+4)))^(1+INDEX($Q410:$AJ410,1,(AS$4-1)*5+2))*(1+AS$7)^INDEX($Q410:$AJ410,1,(AS$4-1)*5+1)*(AS280/AR280)^INDEX($Q410:$AJ410,1,(AS$4-1)*5+2)*(AS280/AR280)^(INDEX($Q410:$AJ410,1,(AS$4-1)*5+3)*(1+INDEX($Q410:$AJ410,1,(AS$4-1)*5+2))) | AT410: =AS410*(1/(1+INDEX($Q410:$AJ410,1,(AT$4-1)*5+4)))^(1+INDEX($Q410:$AJ410,1,(AT$4-1)*5+2))*(1+AT$7)^INDEX($Q410:$AJ410,1,(AT$4-1)*5+1)*(AT280/AS280)^INDEX($Q410:$AJ410,1,(AT$4-1)*5+2)*(AT280/AS280)^(INDEX($Q410:$AJ410,1,(AT$4-1)*5+3)*(1+INDEX($Q410:$AJ410,1,(AT$4-1)*5+2))) | ... AY410: =AX410*(1/(1+INDEX($Q410:$AJ410,1,(AY$4-1)*5+4)))^(1+INDEX($Q410:$AJ410,1,(AY$4-1)*5+2))*(1+AY$7)^INDEX($Q410:$AJ410,1,(AY$4-1)*5+1)*(AY280/AX280)^INDEX($Q410:$AJ410,1,(AY$4-1)*5+2)*(AY280/AX280)^(INDEX($Q410:$AJ410,1,(AY$4-1)*5+3)*(1+INDEX($Q410:$AJ410,1,(AY$4-1)*5+2))) | BA410: =INDEX(EnergyCons!$F$4:$F$5000,MATCH(Settings!$C$4&"|"&BA$5&"|"&$C410&"|"&$B410,EnergyCons!$A$4:$A$5000,0)) | BB410: =BA410*(1/(1+INDEX($Q410:$AJ410,1,(BB$4-1)*5+4)))^(1+INDEX($Q410:$AJ410,1,(BB$4-1)*5+2))*(1+BB$7)^INDEX($Q410:$AJ410,1,(BB$4-1)*5+1)*(BB280/BA280)^INDEX($Q410:$AJ410,1,(BB$4-1)*5+2)*(BB280/BA280)^(INDEX($Q410:$AJ410,1,(BB$4-1)*5+3)*(1+INDEX($Q410:$AJ410,1,(BB$4-1)*5+2))) | BC410: =BB410*(1/(1+INDEX($Q410:$AJ410,1,(BC$4-1)*5+4)))^(1+INDEX($Q410:$AJ410,1,(BC$4-1)*5+2))*(1+BC$7)^INDEX($Q410:$AJ410,1,(BC$4-1)*5+1)*(BC280/BB280)^INDEX($Q410:$AJ410,1,(BC$4-1)*5+2)*(BC280/BB280)^(INDEX($Q410:$AJ410,1,(BC$4-1)*5+3)*(1+INDEX($Q410:$AJ410,1,(BC$4-1)*5+2))) | BD410: =BC410*(1/(1+INDEX($Q410:$AJ410,1,(BD$4-1)*5+4)))^(1+INDEX($Q410:$AJ410,1,(BD$4-1)*5+2))*(1+BD$7)^INDEX($Q410:$AJ410,1,(BD$4-1)*5+1)*(BD280/BC280)^INDEX($Q410:$AJ410,1,(BD$4-1)*5+2)*(BD280/BC280)^(INDEX($Q410:$AJ410,1,(BD$4-1)*5+3)*(1+INDEX($Q410:$AJ410,1,(BD$4-1)*5+2))) | BE410: =BD410*(1/(1+INDEX($Q410:$AJ410,1,(BE$4-1)*5+4)))^(1+INDEX($Q410:$AJ410,1,(BE$4-1)*5+2))*(1+BE$7)^INDEX($Q410:$AJ410,1,(BE$4-1)*5+1)*(BE280/BD280)^INDEX($Q410:$AJ410,1,(BE$4-1)*5+2)*(BE280/BD280)^(INDEX($Q410:$AJ410,1,(BE$4-1)*5+3)*(1+INDEX($Q410:$AJ410,1,(BE$4-1)*5+2))) | BF410: =BE410*(1/(1+INDEX($Q410:$AJ410,1,(BF$4-1)*5+4)))^(1+INDEX($Q410:$AJ410,1,(BF$4-1)*5+2))*(1+BF$7)^INDEX($Q410:$AJ410,1,(BF$4-1)*5+1)*(BF280/BE280)^INDEX($Q410:$AJ410,1,(BF$4-1)*5+2)*(BF280/BE280)^(INDEX($Q410:$AJ410,1,(BF$4-1)*5+3)*(1+INDEX($Q410:$AJ410,1,(BF$4-1)*5+2))) | BG410: =BF410*(1/(1+INDEX($Q410:$AJ410,1,(BG$4-1)*5+4)))^(1+INDEX($Q410:$AJ410,1,(BG$4-1)*5+2))*(1+BG$7)^INDEX($Q410:$AJ410,1,(BG$4-1)*5+1)*(BG280/BF280)^INDEX($Q410:$AJ410,1,(BG$4-1)*5+2)*(BG280/BF280)^(INDEX($Q410:$AJ410,1,(BG$4-1)*5+3)*(1+INDEX($Q410:$AJ410,1,(BG$4-1)*5+2))) | BH410: =BG410*(1/(1+INDEX($Q410:$AJ410,1,(BH$4-1)*5+4)))^(1+INDEX($Q410:$AJ410,1,(BH$4-1)*5+2))*(1+BH$7)^INDEX($Q410:$AJ410,1,(BH$4-1)*5+1)*(BH280/BG280)^INDEX($Q410:$AJ410,1,(BH$4-1)*5+2)*(BH280/BG280)^(INDEX($Q410:$AJ410,1,(BH$4-1)*5+3)*(1+INDEX($Q410:$AJ410,1,(BH$4-1)*5+2))) | BI410: =BH410*(1/(1+INDEX($Q410:$AJ410,1,(BI$4-1)*5+4)))^(1+INDEX($Q410:$AJ410,1,(BI$4-1)*5+2))*(1+BI$7)^INDEX($Q410:$AJ410,1,(BI$4-1)*5+1)*(BI280/BH280)^INDEX($Q410:$AJ410,1,(BI$4-1)*5+2)*(BI280/BH280)^(INDEX($Q410:$AJ410,1,(BI$4-1)*5+3)*(1+INDEX($Q410:$AJ410,1,(BI$4-1)*5+2))) | ... BN410: =BM410*(1/(1+INDEX($Q410:$AJ410,1,(BN$4-1)*5+4)))^(1+INDEX($Q410:$AJ410,1,(BN$4-1)*5+2))*(1+BN$7)^INDEX($Q410:$AJ410,1,(BN$4-1)*5+1)*(BN280/BM280)^INDEX($Q410:$AJ410,1,(BN$4-1)*5+2)*(BN280/BM280)^(INDEX($Q410:$AJ410,1,(BN$4-1)*5+3)*(1+INDEX($Q410:$AJ410,1,(BN$4-1)*5+2)))
B411: gso | C411: ral | D411: Fuel use | Rail | Gasoline | E411: ktoe | F411: EnergyCons (base year), Elasticities | G411: mit.enc.gso.ral | H411: mit.enc.gso.ral | J411: =INDEX(Mapping!$C$5:$C$20,MATCH($C411,Mapping!$A$5:$A$20,0)) | K411: =INDEX(Mapping!$D$5:$D$20,MATCH($C411,Mapping!$A$5:$A$20,0)) | L411: =INDEX(Mapping!$C$24:$C$31,MATCH($B411,Mapping!$A$24:$A$31,0)) | M411: =INDEX(Mapping!$D$24:$D$31,MATCH($B411,Mapping!$A$24:$A$31,0)) | N411: =$B411&"."&IF(INDEX(Mapping!$E$24:$E$31,MATCH($B411,Mapping!$A$24:$A$31,0))="sub",INDEX(Mapping!$F$5:$F$20,MATCH($C411,Mapping!$A$5:$A$20,0)),"all") | O411: =INDEX(Mapping!$E$5:$E$20,MATCH($C411,Mapping!$A$5:$A$20,0)) | P411: =INDEX(Mapping!$G$24:$G$31,MATCH($B411,Mapping!$A$24:$A$31,0)) | Q411: =INDEX(Elasticities!$F$4:$I$200,MATCH("inc|"&$L411&"|"&$K411,Elasticities!$A$4:$A$200,0),MATCH(Settings!$C$6,Elasticities!$F$3:$I$3,0)) | R411: =INDEX(Elasticities!$F$4:$I$200,MATCH("usg|"&$L411&"|"&$K411,Elasticities!$A$4:$A$200,0),MATCH(Settings!$C$6,Elasticities!$F$3:$I$3,0)) | S411: =INDEX(Elasticities!$F$4:$I$200,MATCH("eff|"&$L411&"|"&$K411,Elasticities!$A$4:$A$200,0),MATCH(Settings!$C$6,Elasticities!$F$3:$I$3,0)) | T411: =INDEX(Elasticities!$F$4:$I$200,MATCH("aei|"&$M411&"|"&$K411,Elasticities!$A$4:$A$200,0),MATCH(Settings!$C$6,Elasticities!$F$3:$I$3,0)) | V411: =Q411 | W411: =R411 | X411: =S411 | Y411: =T411 | AA411: =Q411 | AB411: =R411 | AC411: =S411 | AD411: =T411 | AF411: =Q411 | AG411: =R411 | AH411: =S411 | AI411: =T411 | AL411: =INDEX(EnergyCons!$F$4:$F$5000,MATCH(Settings!$C$4&"|"&AL$5&"|"&$C411&"|"&$B411,EnergyCons!$A$4:$A$5000,0)) | AM411: =AL411*(1/(1+INDEX($Q411:$AJ411,1,(AM$4-1)*5+4)))^(1+INDEX($Q411:$AJ411,1,(AM$4-1)*5+2))*(1+AM$7)^INDEX($Q411:$AJ411,1,(AM$4-1)*5+1)*(AM281/AL281)^INDEX($Q411:$AJ411,1,(AM$4-1)*5+2)*(AM281/AL281)^(INDEX($Q411:$AJ411,1,(AM$4-1)*5+3)*(1+INDEX($Q411:$AJ411,1,(AM$4-1)*5+2))) | AN411: =AM411*(1/(1+INDEX($Q411:$AJ411,1,(AN$4-1)*5+4)))^(1+INDEX($Q411:$AJ411,1,(AN$4-1)*5+2))*(1+AN$7)^INDEX($Q411:$AJ411,1,(AN$4-1)*5+1)*(AN281/AM281)^INDEX($Q411:$AJ411,1,(AN$4-1)*5+2)*(AN281/AM281)^(INDEX($Q411:$AJ411,1,(AN$4-1)*5+3)*(1+INDEX($Q411:$AJ411,1,(AN$4-1)*5+2))) | AO411: =AN411*(1/(1+INDEX($Q411:$AJ411,1,(AO$4-1)*5+4)))^(1+INDEX($Q411:$AJ411,1,(AO$4-1)*5+2))*(1+AO$7)^INDEX($Q411:$AJ411,1,(AO$4-1)*5+1)*(AO281/AN281)^INDEX($Q411:$AJ411,1,(AO$4-1)*5+2)*(AO281/AN281)^(INDEX($Q411:$AJ411,1,(AO$4-1)*5+3)*(1+INDEX($Q411:$AJ411,1,(AO$4-1)*5+2))) | AP411: =AO411*(1/(1+INDEX($Q411:$AJ411,1,(AP$4-1)*5+4)))^(1+INDEX($Q411:$AJ411,1,(AP$4-1)*5+2))*(1+AP$7)^INDEX($Q411:$AJ411,1,(AP$4-1)*5+1)*(AP281/AO281)^INDEX($Q411:$AJ411,1,(AP$4-1)*5+2)*(AP281/AO281)^(INDEX($Q411:$AJ411,1,(AP$4-1)*5+3)*(1+INDEX($Q411:$AJ411,1,(AP$4-1)*5+2))) | AQ411: =AP411*(1/(1+INDEX($Q411:$AJ411,1,(AQ$4-1)*5+4)))^(1+INDEX($Q411:$AJ411,1,(AQ$4-1)*5+2))*(1+AQ$7)^INDEX($Q411:$AJ411,1,(AQ$4-1)*5+1)*(AQ281/AP281)^INDEX($Q411:$AJ411,1,(AQ$4-1)*5+2)*(AQ281/AP281)^(INDEX($Q411:$AJ411,1,(AQ$4-1)*5+3)*(1+INDEX($Q411:$AJ411,1,(AQ$4-1)*5+2))) | AR411: =AQ411*(1/(1+INDEX($Q411:$AJ411,1,(AR$4-1)*5+4)))^(1+INDEX($Q411:$AJ411,1,(AR$4-1)*5+2))*(1+AR$7)^INDEX($Q411:$AJ411,1,(AR$4-1)*5+1)*(AR281/AQ281)^INDEX($Q411:$AJ411,1,(AR$4-1)*5+2)*(AR281/AQ281)^(INDEX($Q411:$AJ411,1,(AR$4-1)*5+3)*(1+INDEX($Q411:$AJ411,1,(AR$4-1)*5+2))) | AS411: =AR411*(1/(1+INDEX($Q411:$AJ411,1,(AS$4-1)*5+4)))^(1+INDEX($Q411:$AJ411,1,(AS$4-1)*5+2))*(1+AS$7)^INDEX($Q411:$AJ411,1,(AS$4-1)*5+1)*(AS281/AR281)^INDEX($Q411:$AJ411,1,(AS$4-1)*5+2)*(AS281/AR281)^(INDEX($Q411:$AJ411,1,(AS$4-1)*5+3)*(1+INDEX($Q411:$AJ411,1,(AS$4-1)*5+2))) | AT411: =AS411*(1/(1+INDEX($Q411:$AJ411,1,(AT$4-1)*5+4)))^(1+INDEX($Q411:$AJ411,1,(AT$4-1)*5+2))*(1+AT$7)^INDEX($Q411:$AJ411,1,(AT$4-1)*5+1)*(AT281/AS281)^INDEX($Q411:$AJ411,1,(AT$4-1)*5+2)*(AT281/AS281)^(INDEX($Q411:$AJ411,1,(AT$4-1)*5+3)*(1+INDEX($Q411:$AJ411,1,(AT$4-1)*5+2))) | ... AY411: =AX411*(1/(1+INDEX($Q411:$AJ411,1,(AY$4-1)*5+4)))^(1+INDEX($Q411:$AJ411,1,(AY$4-1)*5+2))*(1+AY$7)^INDEX($Q411:$AJ411,1,(AY$4-1)*5+1)*(AY281/AX281)^INDEX($Q411:$AJ411,1,(AY$4-1)*5+2)*(AY281/AX281)^(INDEX($Q411:$AJ411,1,(AY$4-1)*5+3)*(1+INDEX($Q411:$AJ411,1,(AY$4-1)*5+2))) | BA411: =INDEX(EnergyCons!$F$4:$F$5000,MATCH(Settings!$C$4&"|"&BA$5&"|"&$C411&"|"&$B411,EnergyCons!$A$4:$A$5000,0)) | BB411: =BA411*(1/(1+INDEX($Q411:$AJ411,1,(BB$4-1)*5+4)))^(1+INDEX($Q411:$AJ411,1,(BB$4-1)*5+2))*(1+BB$7)^INDEX($Q411:$AJ411,1,(BB$4-1)*5+1)*(BB281/BA281)^INDEX($Q411:$AJ411,1,(BB$4-1)*5+2)*(BB281/BA281)^(INDEX($Q411:$AJ411,1,(BB$4-1)*5+3)*(1+INDEX($Q411:$AJ411,1,(BB$4-1)*5+2))) | BC411: =BB411*(1/(1+INDEX($Q411:$AJ411,1,(BC$4-1)*5+4)))^(1+INDEX($Q411:$AJ411,1,(BC$4-1)*5+2))*(1+BC$7)^INDEX($Q411:$AJ411,1,(BC$4-1)*5+1)*(BC281/BB281)^INDEX($Q411:$AJ411,1,(BC$4-1)*5+2)*(BC281/BB281)^(INDEX($Q411:$AJ411,1,(BC$4-1)*5+3)*(1+INDEX($Q411:$AJ411,1,(BC$4-1)*5+2))) | BD411: =BC411*(1/(1+INDEX($Q411:$AJ411,1,(BD$4-1)*5+4)))^(1+INDEX($Q411:$AJ411,1,(BD$4-1)*5+2))*(1+BD$7)^INDEX($Q411:$AJ411,1,(BD$4-1)*5+1)*(BD281/BC281)^INDEX($Q411:$AJ411,1,(BD$4-1)*5+2)*(BD281/BC281)^(INDEX($Q411:$AJ411,1,(BD$4-1)*5+3)*(1+INDEX($Q411:$AJ411,1,(BD$4-1)*5+2))) | BE411: =BD411*(1/(1+INDEX($Q411:$AJ411,1,(BE$4-1)*5+4)))^(1+INDEX($Q411:$AJ411,1,(BE$4-1)*5+2))*(1+BE$7)^INDEX($Q411:$AJ411,1,(BE$4-1)*5+1)*(BE281/BD281)^INDEX($Q411:$AJ411,1,(BE$4-1)*5+2)*(BE281/BD281)^(INDEX($Q411:$AJ411,1,(BE$4-1)*5+3)*(1+INDEX($Q411:$AJ411,1,(BE$4-1)*5+2))) | BF411: =BE411*(1/(1+INDEX($Q411:$AJ411,1,(BF$4-1)*5+4)))^(1+INDEX($Q411:$AJ411,1,(BF$4-1)*5+2))*(1+BF$7)^INDEX($Q411:$AJ411,1,(BF$4-1)*5+1)*(BF281/BE281)^INDEX($Q411:$AJ411,1,(BF$4-1)*5+2)*(BF281/BE281)^(INDEX($Q411:$AJ411,1,(BF$4-1)*5+3)*(1+INDEX($Q411:$AJ411,1,(BF$4-1)*5+2))) | BG411: =BF411*(1/(1+INDEX($Q411:$AJ411,1,(BG$4-1)*5+4)))^(1+INDEX($Q411:$AJ411,1,(BG$4-1)*5+2))*(1+BG$7)^INDEX($Q411:$AJ411,1,(BG$4-1)*5+1)*(BG281/BF281)^INDEX($Q411:$AJ411,1,(BG$4-1)*5+2)*(BG281/BF281)^(INDEX($Q411:$AJ411,1,(BG$4-1)*5+3)*(1+INDEX($Q411:$AJ411,1,(BG$4-1)*5+2))) | BH411: =BG411*(1/(1+INDEX($Q411:$AJ411,1,(BH$4-1)*5+4)))^(1+INDEX($Q411:$AJ411,1,(BH$4-1)*5+2))*(1+BH$7)^INDEX($Q411:$AJ411,1,(BH$4-1)*5+1)*(BH281/BG281)^INDEX($Q411:$AJ411,1,(BH$4-1)*5+2)*(BH281/BG281)^(INDEX($Q411:$AJ411,1,(BH$4-1)*5+3)*(1+INDEX($Q411:$AJ411,1,(BH$4-1)*5+2))) | BI411: =BH411*(1/(1+INDEX($Q411:$AJ411,1,(BI$4-1)*5+4)))^(1+INDEX($Q411:$AJ411,1,(BI$4-1)*5+2))*(1+BI$7)^INDEX($Q411:$AJ411,1,(BI$4-1)*5+1)*(BI281/BH281)^INDEX($Q411:$AJ411,1,(BI$4-1)*5+2)*(BI281/BH281)^(INDEX($Q411:$AJ411,1,(BI$4-1)*5+3)*(1+INDEX($Q411:$AJ411,1,(BI$4-1)*5+2))) | ... BN411: =BM411*(1/(1+INDEX($Q411:$AJ411,1,(BN$4-1)*5+4)))^(1+INDEX($Q411:$AJ411,1,(BN$4-1)*5+2))*(1+BN$7)^INDEX($Q411:$AJ411,1,(BN$4-1)*5+1)*(BN281/BM281)^INDEX($Q411:$AJ411,1,(BN$4-1)*5+2)*(BN281/BM281)^(INDEX($Q411:$AJ411,1,(BN$4-1)*5+3)*(1+INDEX($Q411:$AJ411,1,(BN$4-1)*5+2)))
B412: die | C412: ral | D412: Fuel use | Rail | Diesel | E412: ktoe | F412: EnergyCons (base year), Elasticities | G412: mit.enc.die.ral | H412: mit.enc.die.ral | J412: =INDEX(Mapping!$C$5:$C$20,MATCH($C412,Mapping!$A$5:$A$20,0)) | K412: =INDEX(Mapping!$D$5:$D$20,MATCH($C412,Mapping!$A$5:$A$20,0)) | L412: =INDEX(Mapping!$C$24:$C$31,MATCH($B412,Mapping!$A$24:$A$31,0)) | M412: =INDEX(Mapping!$D$24:$D$31,MATCH($B412,Mapping!$A$24:$A$31,0)) | N412: =$B412&"."&IF(INDEX(Mapping!$E$24:$E$31,MATCH($B412,Mapping!$A$24:$A$31,0))="sub",INDEX(Mapping!$F$5:$F$20,MATCH($C412,Mapping!$A$5:$A$20,0)),"all") | O412: =INDEX(Mapping!$E$5:$E$20,MATCH($C412,Mapping!$A$5:$A$20,0)) | P412: =INDEX(Mapping!$G$24:$G$31,MATCH($B412,Mapping!$A$24:$A$31,0)) | Q412: =INDEX(Elasticities!$F$4:$I$200,MATCH("inc|"&$L412&"|"&$K412,Elasticities!$A$4:$A$200,0),MATCH(Settings!$C$6,Elasticities!$F$3:$I$3,0)) | R412: =INDEX(Elasticities!$F$4:$I$200,MATCH("usg|"&$L412&"|"&$K412,Elasticities!$A$4:$A$200,0),MATCH(Settings!$C$6,Elasticities!$F$3:$I$3,0)) | S412: =INDEX(Elasticities!$F$4:$I$200,MATCH("eff|"&$L412&"|"&$K412,Elasticities!$A$4:$A$200,0),MATCH(Settings!$C$6,Elasticities!$F$3:$I$3,0)) | T412: =INDEX(Elasticities!$F$4:$I$200,MATCH("aei|"&$M412&"|"&$K412,Elasticities!$A$4:$A$200,0),MATCH(Settings!$C$6,Elasticities!$F$3:$I$3,0)) | V412: =Q412 | W412: =R412 | X412: =S412 | Y412: =T412 | AA412: =Q412 | AB412: =R412 | AC412: =S412 | AD412: =T412 | AF412: =Q412 | AG412: =R412 | AH412: =S412 | AI412: =T412 | AL412: =INDEX(EnergyCons!$F$4:$F$5000,MATCH(Settings!$C$4&"|"&AL$5&"|"&$C412&"|"&$B412,EnergyCons!$A$4:$A$5000,0)) | AM412: =AL412*(1/(1+INDEX($Q412:$AJ412,1,(AM$4-1)*5+4)))^(1+INDEX($Q412:$AJ412,1,(AM$4-1)*5+2))*(1+AM$7)^INDEX($Q412:$AJ412,1,(AM$4-1)*5+1)*(AM282/AL282)^INDEX($Q412:$AJ412,1,(AM$4-1)*5+2)*(AM282/AL282)^(INDEX($Q412:$AJ412,1,(AM$4-1)*5+3)*(1+INDEX($Q412:$AJ412,1,(AM$4-1)*5+2))) | AN412: =AM412*(1/(1+INDEX($Q412:$AJ412,1,(AN$4-1)*5+4)))^(1+INDEX($Q412:$AJ412,1,(AN$4-1)*5+2))*(1+AN$7)^INDEX($Q412:$AJ412,1,(AN$4-1)*5+1)*(AN282/AM282)^INDEX($Q412:$AJ412,1,(AN$4-1)*5+2)*(AN282/AM282)^(INDEX($Q412:$AJ412,1,(AN$4-1)*5+3)*(1+INDEX($Q412:$AJ412,1,(AN$4-1)*5+2))) | AO412: =AN412*(1/(1+INDEX($Q412:$AJ412,1,(AO$4-1)*5+4)))^(1+INDEX($Q412:$AJ412,1,(AO$4-1)*5+2))*(1+AO$7)^INDEX($Q412:$AJ412,1,(AO$4-1)*5+1)*(AO282/AN282)^INDEX($Q412:$AJ412,1,(AO$4-1)*5+2)*(AO282/AN282)^(INDEX($Q412:$AJ412,1,(AO$4-1)*5+3)*(1+INDEX($Q412:$AJ412,1,(AO$4-1)*5+2))) | AP412: =AO412*(1/(1+INDEX($Q412:$AJ412,1,(AP$4-1)*5+4)))^(1+INDEX($Q412:$AJ412,1,(AP$4-1)*5+2))*(1+AP$7)^INDEX($Q412:$AJ412,1,(AP$4-1)*5+1)*(AP282/AO282)^INDEX($Q412:$AJ412,1,(AP$4-1)*5+2)*(AP282/AO282)^(INDEX($Q412:$AJ412,1,(AP$4-1)*5+3)*(1+INDEX($Q412:$AJ412,1,(AP$4-1)*5+2))) | AQ412: =AP412*(1/(1+INDEX($Q412:$AJ412,1,(AQ$4-1)*5+4)))^(1+INDEX($Q412:$AJ412,1,(AQ$4-1)*5+2))*(1+AQ$7)^INDEX($Q412:$AJ412,1,(AQ$4-1)*5+1)*(AQ282/AP282)^INDEX($Q412:$AJ412,1,(AQ$4-1)*5+2)*(AQ282/AP282)^(INDEX($Q412:$AJ412,1,(AQ$4-1)*5+3)*(1+INDEX($Q412:$AJ412,1,(AQ$4-1)*5+2))) | AR412: =AQ412*(1/(1+INDEX($Q412:$AJ412,1,(AR$4-1)*5+4)))^(1+INDEX($Q412:$AJ412,1,(AR$4-1)*5+2))*(1+AR$7)^INDEX($Q412:$AJ412,1,(AR$4-1)*5+1)*(AR282/AQ282)^INDEX($Q412:$AJ412,1,(AR$4-1)*5+2)*(AR282/AQ282)^(INDEX($Q412:$AJ412,1,(AR$4-1)*5+3)*(1+INDEX($Q412:$AJ412,1,(AR$4-1)*5+2))) | AS412: =AR412*(1/(1+INDEX($Q412:$AJ412,1,(AS$4-1)*5+4)))^(1+INDEX($Q412:$AJ412,1,(AS$4-1)*5+2))*(1+AS$7)^INDEX($Q412:$AJ412,1,(AS$4-1)*5+1)*(AS282/AR282)^INDEX($Q412:$AJ412,1,(AS$4-1)*5+2)*(AS282/AR282)^(INDEX($Q412:$AJ412,1,(AS$4-1)*5+3)*(1+INDEX($Q412:$AJ412,1,(AS$4-1)*5+2))) | AT412: =AS412*(1/(1+INDEX($Q412:$AJ412,1,(AT$4-1)*5+4)))^(1+INDEX($Q412:$AJ412,1,(AT$4-1)*5+2))*(1+AT$7)^INDEX($Q412:$AJ412,1,(AT$4-1)*5+1)*(AT282/AS282)^INDEX($Q412:$AJ412,1,(AT$4-1)*5+2)*(AT282/AS282)^(INDEX($Q412:$AJ412,1,(AT$4-1)*5+3)*(1+INDEX($Q412:$AJ412,1,(AT$4-1)*5+2))) | ... AY412: =AX412*(1/(1+INDEX($Q412:$AJ412,1,(AY$4-1)*5+4)))^(1+INDEX($Q412:$AJ412,1,(AY$4-1)*5+2))*(1+AY$7)^INDEX($Q412:$AJ412,1,(AY$4-1)*5+1)*(AY282/AX282)^INDEX($Q412:$AJ412,1,(AY$4-1)*5+2)*(AY282/AX282)^(INDEX($Q412:$AJ412,1,(AY$4-1)*5+3)*(1+INDEX($Q412:$AJ412,1,(AY$4-1)*5+2))) | BA412: =INDEX(EnergyCons!$F$4:$F$5000,MATCH(Settings!$C$4&"|"&BA$5&"|"&$C412&"|"&$B412,EnergyCons!$A$4:$A$5000,0)) | BB412: =BA412*(1/(1+INDEX($Q412:$AJ412,1,(BB$4-1)*5+4)))^(1+INDEX($Q412:$AJ412,1,(BB$4-1)*5+2))*(1+BB$7)^INDEX($Q412:$AJ412,1,(BB$4-1)*5+1)*(BB282/BA282)^INDEX($Q412:$AJ412,1,(BB$4-1)*5+2)*(BB282/BA282)^(INDEX($Q412:$AJ412,1,(BB$4-1)*5+3)*(1+INDEX($Q412:$AJ412,1,(BB$4-1)*5+2))) | BC412: =BB412*(1/(1+INDEX($Q412:$AJ412,1,(BC$4-1)*5+4)))^(1+INDEX($Q412:$AJ412,1,(BC$4-1)*5+2))*(1+BC$7)^INDEX($Q412:$AJ412,1,(BC$4-1)*5+1)*(BC282/BB282)^INDEX($Q412:$AJ412,1,(BC$4-1)*5+2)*(BC282/BB282)^(INDEX($Q412:$AJ412,1,(BC$4-1)*5+3)*(1+INDEX($Q412:$AJ412,1,(BC$4-1)*5+2))) | BD412: =BC412*(1/(1+INDEX($Q412:$AJ412,1,(BD$4-1)*5+4)))^(1+INDEX($Q412:$AJ412,1,(BD$4-1)*5+2))*(1+BD$7)^INDEX($Q412:$AJ412,1,(BD$4-1)*5+1)*(BD282/BC282)^INDEX($Q412:$AJ412,1,(BD$4-1)*5+2)*(BD282/BC282)^(INDEX($Q412:$AJ412,1,(BD$4-1)*5+3)*(1+INDEX($Q412:$AJ412,1,(BD$4-1)*5+2))) | BE412: =BD412*(1/(1+INDEX($Q412:$AJ412,1,(BE$4-1)*5+4)))^(1+INDEX($Q412:$AJ412,1,(BE$4-1)*5+2))*(1+BE$7)^INDEX($Q412:$AJ412,1,(BE$4-1)*5+1)*(BE282/BD282)^INDEX($Q412:$AJ412,1,(BE$4-1)*5+2)*(BE282/BD282)^(INDEX($Q412:$AJ412,1,(BE$4-1)*5+3)*(1+INDEX($Q412:$AJ412,1,(BE$4-1)*5+2))) | BF412: =BE412*(1/(1+INDEX($Q412:$AJ412,1,(BF$4-1)*5+4)))^(1+INDEX($Q412:$AJ412,1,(BF$4-1)*5+2))*(1+BF$7)^INDEX($Q412:$AJ412,1,(BF$4-1)*5+1)*(BF282/BE282)^INDEX($Q412:$AJ412,1,(BF$4-1)*5+2)*(BF282/BE282)^(INDEX($Q412:$AJ412,1,(BF$4-1)*5+3)*(1+INDEX($Q412:$AJ412,1,(BF$4-1)*5+2))) | BG412: =BF412*(1/(1+INDEX($Q412:$AJ412,1,(BG$4-1)*5+4)))^(1+INDEX($Q412:$AJ412,1,(BG$4-1)*5+2))*(1+BG$7)^INDEX($Q412:$AJ412,1,(BG$4-1)*5+1)*(BG282/BF282)^INDEX($Q412:$AJ412,1,(BG$4-1)*5+2)*(BG282/BF282)^(INDEX($Q412:$AJ412,1,(BG$4-1)*5+3)*(1+INDEX($Q412:$AJ412,1,(BG$4-1)*5+2))) | BH412: =BG412*(1/(1+INDEX($Q412:$AJ412,1,(BH$4-1)*5+4)))^(1+INDEX($Q412:$AJ412,1,(BH$4-1)*5+2))*(1+BH$7)^INDEX($Q412:$AJ412,1,(BH$4-1)*5+1)*(BH282/BG282)^INDEX($Q412:$AJ412,1,(BH$4-1)*5+2)*(BH282/BG282)^(INDEX($Q412:$AJ412,1,(BH$4-1)*5+3)*(1+INDEX($Q412:$AJ412,1,(BH$4-1)*5+2))) | BI412: =BH412*(1/(1+INDEX($Q412:$AJ412,1,(BI$4-1)*5+4)))^(1+INDEX($Q412:$AJ412,1,(BI$4-1)*5+2))*(1+BI$7)^INDEX($Q412:$AJ412,1,(BI$4-1)*5+1)*(BI282/BH282)^INDEX($Q412:$AJ412,1,(BI$4-1)*5+2)*(BI282/BH282)^(INDEX($Q412:$AJ412,1,(BI$4-1)*5+3)*(1+INDEX($Q412:$AJ412,1,(BI$4-1)*5+2))) | ... BN412: =BM412*(1/(1+INDEX($Q412:$AJ412,1,(BN$4-1)*5+4)))^(1+INDEX($Q412:$AJ412,1,(BN$4-1)*5+2))*(1+BN$7)^INDEX($Q412:$AJ412,1,(BN$4-1)*5+1)*(BN282/BM282)^INDEX($Q412:$AJ412,1,(BN$4-1)*5+2)*(BN282/BM282)^(INDEX($Q412:$AJ412,1,(BN$4-1)*5+3)*(1+INDEX($Q412:$AJ412,1,(BN$4-1)*5+2)))
... B528: bio | C528: oen | D528: Fuel use | Other energy use | Biomass | E528: ktoe | F528: EnergyCons (base year), Elasticities | G528: mit.enc.bio.oen | H528: mit.enc.bio.oen | J528: =INDEX(Mapping!$C$5:$C$20,MATCH($C528,Mapping!$A$5:$A$20,0)) | K528: =INDEX(Mapping!$D$5:$D$20,MATCH($C528,Mapping!$A$5:$A$20,0)) | L528: =INDEX(Mapping!$C$24:$C$31,MATCH($B528,Mapping!$A$24:$A$31,0)) | M528: =INDEX(Mapping!$D$24:$D$31,MATCH($B528,Mapping!$A$24:$A$31,0)) | N528: =$B528&"."&IF(INDEX(Mapping!$E$24:$E$31,MATCH($B528,Mapping!$A$24:$A$31,0))="sub",INDEX(Mapping!$F$5:$F$20,MATCH($C528,Mapping!$A$5:$A$20,0)),"all") | O528: =INDEX(Mapping!$E$5:$E$20,MATCH($C528,Mapping!$A$5:$A$20,0)) | P528: =INDEX(Mapping!$G$24:$G$31,MATCH($B528,Mapping!$A$24:$A$31,0)) | Q528: =INDEX(Elasticities!$F$4:$I$200,MATCH("inc|"&$L528&"|"&$K528,Elasticities!$A$4:$A$200,0),MATCH(Settings!$C$6,Elasticities!$F$3:$I$3,0)) | R528: =INDEX(Elasticities!$F$4:$I$200,MATCH("usg|"&$L528&"|"&$K528,Elasticities!$A$4:$A$200,0),MATCH(Settings!$C$6,Elasticities!$F$3:$I$3,0)) | S528: =INDEX(Elasticities!$F$4:$I$200,MATCH("eff|"&$L528&"|"&$K528,Elasticities!$A$4:$A$200,0),MATCH(Settings!$C$6,Elasticities!$F$3:$I$3,0)) | T528: =INDEX(Elasticities!$F$4:$I$200,MATCH("aei|"&$M528&"|"&$K528,Elasticities!$A$4:$A$200,0),MATCH(Settings!$C$6,Elasticities!$F$3:$I$3,0)) | V528: =Q528 | W528: =R528 | X528: =S528 | Y528: =T528 | AA528: =Q528 | AB528: =R528 | AC528: =S528 | AD528: =T528 | AF528: =Q528 | AG528: =R528 | AH528: =S528 | AI528: =T528 | AL528: =INDEX(EnergyCons!$F$4:$F$5000,MATCH(Settings!$C$4&"|"&AL$5&"|"&$C528&"|"&$B528,EnergyCons!$A$4:$A$5000,0)) | AM528: =AL528*(1/(1+INDEX($Q528:$AJ528,1,(AM$4-1)*5+4)))^(1+INDEX($Q528:$AJ528,1,(AM$4-1)*5+2))*(1+AM$7)^INDEX($Q528:$AJ528,1,(AM$4-1)*5+1)*(AM398/AL398)^INDEX($Q528:$AJ528,1,(AM$4-1)*5+2)*(AM398/AL398)^(INDEX($Q528:$AJ528,1,(AM$4-1)*5+3)*(1+INDEX($Q528:$AJ528,1,(AM$4-1)*5+2))) | AN528: =AM528*(1/(1+INDEX($Q528:$AJ528,1,(AN$4-1)*5+4)))^(1+INDEX($Q528:$AJ528,1,(AN$4-1)*5+2))*(1+AN$7)^INDEX($Q528:$AJ528,1,(AN$4-1)*5+1)*(AN398/AM398)^INDEX($Q528:$AJ528,1,(AN$4-1)*5+2)*(AN398/AM398)^(INDEX($Q528:$AJ528,1,(AN$4-1)*5+3)*(1+INDEX($Q528:$AJ528,1,(AN$4-1)*5+2))) | AO528: =AN528*(1/(1+INDEX($Q528:$AJ528,1,(AO$4-1)*5+4)))^(1+INDEX($Q528:$AJ528,1,(AO$4-1)*5+2))*(1+AO$7)^INDEX($Q528:$AJ528,1,(AO$4-1)*5+1)*(AO398/AN398)^INDEX($Q528:$AJ528,1,(AO$4-1)*5+2)*(AO398/AN398)^(INDEX($Q528:$AJ528,1,(AO$4-1)*5+3)*(1+INDEX($Q528:$AJ528,1,(AO$4-1)*5+2))) | AP528: =AO528*(1/(1+INDEX($Q528:$AJ528,1,(AP$4-1)*5+4)))^(1+INDEX($Q528:$AJ528,1,(AP$4-1)*5+2))*(1+AP$7)^INDEX($Q528:$AJ528,1,(AP$4-1)*5+1)*(AP398/AO398)^INDEX($Q528:$AJ528,1,(AP$4-1)*5+2)*(AP398/AO398)^(INDEX($Q528:$AJ528,1,(AP$4-1)*5+3)*(1+INDEX($Q528:$AJ528,1,(AP$4-1)*5+2))) | AQ528: =AP528*(1/(1+INDEX($Q528:$AJ528,1,(AQ$4-1)*5+4)))^(1+INDEX($Q528:$AJ528,1,(AQ$4-1)*5+2))*(1+AQ$7)^INDEX($Q528:$AJ528,1,(AQ$4-1)*5+1)*(AQ398/AP398)^INDEX($Q528:$AJ528,1,(AQ$4-1)*5+2)*(AQ398/AP398)^(INDEX($Q528:$AJ528,1,(AQ$4-1)*5+3)*(1+INDEX($Q528:$AJ528,1,(AQ$4-1)*5+2))) | AR528: =AQ528*(1/(1+INDEX($Q528:$AJ528,1,(AR$4-1)*5+4)))^(1+INDEX($Q528:$AJ528,1,(AR$4-1)*5+2))*(1+AR$7)^INDEX($Q528:$AJ528,1,(AR$4-1)*5+1)*(AR398/AQ398)^INDEX($Q528:$AJ528,1,(AR$4-1)*5+2)*(AR398/AQ398)^(INDEX($Q528:$AJ528,1,(AR$4-1)*5+3)*(1+INDEX($Q528:$AJ528,1,(AR$4-1)*5+2))) | AS528: =AR528*(1/(1+INDEX($Q528:$AJ528,1,(AS$4-1)*5+4)))^(1+INDEX($Q528:$AJ528,1,(AS$4-1)*5+2))*(1+AS$7)^INDEX($Q528:$AJ528,1,(AS$4-1)*5+1)*(AS398/AR398)^INDEX($Q528:$AJ528,1,(AS$4-1)*5+2)*(AS398/AR398)^(INDEX($Q528:$AJ528,1,(AS$4-1)*5+3)*(1+INDEX($Q528:$AJ528,1,(AS$4-1)*5+2))) | AT528: =AS528*(1/(1+INDEX($Q528:$AJ528,1,(AT$4-1)*5+4)))^(1+INDEX($Q528:$AJ528,1,(AT$4-1)*5+2))*(1+AT$7)^INDEX($Q528:$AJ528,1,(AT$4-1)*5+1)*(AT398/AS398)^INDEX($Q528:$AJ528,1,(AT$4-1)*5+2)*(AT398/AS398)^(INDEX($Q528:$AJ528,1,(AT$4-1)*5+3)*(1+INDEX($Q528:$AJ528,1,(AT$4-1)*5+2))) | ... AY528: =AX528*(1/(1+INDEX($Q528:$AJ528,1,(AY$4-1)*5+4)))^(1+INDEX($Q528:$AJ528,1,(AY$4-1)*5+2))*(1+AY$7)^INDEX($Q528:$AJ528,1,(AY$4-1)*5+1)*(AY398/AX398)^INDEX($Q528:$AJ528,1,(AY$4-1)*5+2)*(AY398/AX398)^(INDEX($Q528:$AJ528,1,(AY$4-1)*5+3)*(1+INDEX($Q528:$AJ528,1,(AY$4-1)*5+2))) | BA528: =INDEX(EnergyCons!$F$4:$F$5000,MATCH(Settings!$C$4&"|"&BA$5&"|"&$C528&"|"&$B528,EnergyCons!$A$4:$A$5000,0)) | BB528: =BA528*(1/(1+INDEX($Q528:$AJ528,1,(BB$4-1)*5+4)))^(1+INDEX($Q528:$AJ528,1,(BB$4-1)*5+2))*(1+BB$7)^INDEX($Q528:$AJ528,1,(BB$4-1)*5+1)*(BB398/BA398)^INDEX($Q528:$AJ528,1,(BB$4-1)*5+2)*(BB398/BA398)^(INDEX($Q528:$AJ528,1,(BB$4-1)*5+3)*(1+INDEX($Q528:$AJ528,1,(BB$4-1)*5+2))) | BC528: =BB528*(1/(1+INDEX($Q528:$AJ528,1,(BC$4-1)*5+4)))^(1+INDEX($Q528:$AJ528,1,(BC$4-1)*5+2))*(1+BC$7)^INDEX($Q528:$AJ528,1,(BC$4-1)*5+1)*(BC398/BB398)^INDEX($Q528:$AJ528,1,(BC$4-1)*5+2)*(BC398/BB398)^(INDEX($Q528:$AJ528,1,(BC$4-1)*5+3)*(1+INDEX($Q528:$AJ528,1,(BC$4-1)*5+2))) | BD528: =BC528*(1/(1+INDEX($Q528:$AJ528,1,(BD$4-1)*5+4)))^(1+INDEX($Q528:$AJ528,1,(BD$4-1)*5+2))*(1+BD$7)^INDEX($Q528:$AJ528,1,(BD$4-1)*5+1)*(BD398/BC398)^INDEX($Q528:$AJ528,1,(BD$4-1)*5+2)*(BD398/BC398)^(INDEX($Q528:$AJ528,1,(BD$4-1)*5+3)*(1+INDEX($Q528:$AJ528,1,(BD$4-1)*5+2))) | BE528: =BD528*(1/(1+INDEX($Q528:$AJ528,1,(BE$4-1)*5+4)))^(1+INDEX($Q528:$AJ528,1,(BE$4-1)*5+2))*(1+BE$7)^INDEX($Q528:$AJ528,1,(BE$4-1)*5+1)*(BE398/BD398)^INDEX($Q528:$AJ528,1,(BE$4-1)*5+2)*(BE398/BD398)^(INDEX($Q528:$AJ528,1,(BE$4-1)*5+3)*(1+INDEX($Q528:$AJ528,1,(BE$4-1)*5+2))) | BF528: =BE528*(1/(1+INDEX($Q528:$AJ528,1,(BF$4-1)*5+4)))^(1+INDEX($Q528:$AJ528,1,(BF$4-1)*5+2))*(1+BF$7)^INDEX($Q528:$AJ528,1,(BF$4-1)*5+1)*(BF398/BE398)^INDEX($Q528:$AJ528,1,(BF$4-1)*5+2)*(BF398/BE398)^(INDEX($Q528:$AJ528,1,(BF$4-1)*5+3)*(1+INDEX($Q528:$AJ528,1,(BF$4-1)*5+2))) | BG528: =BF528*(1/(1+INDEX($Q528:$AJ528,1,(BG$4-1)*5+4)))^(1+INDEX($Q528:$AJ528,1,(BG$4-1)*5+2))*(1+BG$7)^INDEX($Q528:$AJ528,1,(BG$4-1)*5+1)*(BG398/BF398)^INDEX($Q528:$AJ528,1,(BG$4-1)*5+2)*(BG398/BF398)^(INDEX($Q528:$AJ528,1,(BG$4-1)*5+3)*(1+INDEX($Q528:$AJ528,1,(BG$4-1)*5+2))) | BH528: =BG528*(1/(1+INDEX($Q528:$AJ528,1,(BH$4-1)*5+4)))^(1+INDEX($Q528:$AJ528,1,(BH$4-1)*5+2))*(1+BH$7)^INDEX($Q528:$AJ528,1,(BH$4-1)*5+1)*(BH398/BG398)^INDEX($Q528:$AJ528,1,(BH$4-1)*5+2)*(BH398/BG398)^(INDEX($Q528:$AJ528,1,(BH$4-1)*5+3)*(1+INDEX($Q528:$AJ528,1,(BH$4-1)*5+2))) | BI528: =BH528*(1/(1+INDEX($Q528:$AJ528,1,(BI$4-1)*5+4)))^(1+INDEX($Q528:$AJ528,1,(BI$4-1)*5+2))*(1+BI$7)^INDEX($Q528:$AJ528,1,(BI$4-1)*5+1)*(BI398/BH398)^INDEX($Q528:$AJ528,1,(BI$4-1)*5+2)*(BI398/BH398)^(INDEX($Q528:$AJ528,1,(BI$4-1)*5+3)*(1+INDEX($Q528:$AJ528,1,(BI$4-1)*5+2))) | ... BN528: =BM528*(1/(1+INDEX($Q528:$AJ528,1,(BN$4-1)*5+4)))^(1+INDEX($Q528:$AJ528,1,(BN$4-1)*5+2))*(1+BN$7)^INDEX($Q528:$AJ528,1,(BN$4-1)*5+1)*(BN398/BM398)^INDEX($Q528:$AJ528,1,(BN$4-1)*5+2)*(BN398/BM398)^(INDEX($Q528:$AJ528,1,(BN$4-1)*5+3)*(1+INDEX($Q528:$AJ528,1,(BN$4-1)*5+2)))
A530: Totals - fuel use (ktoe)
B531: all | C531: rod | D531: Total fuel use | Road | E531: ktoe | H531: mit.enc.all.rod | AL531: =SUMIF($C$401:$C$528,$C531,AL$401:AL$528) | AM531: =SUMIF($C$401:$C$528,$C531,AM$401:AM$528) | AN531: =SUMIF($C$401:$C$528,$C531,AN$401:AN$528) | AO531: =SUMIF($C$401:$C$528,$C531,AO$401:AO$528) | AP531: =SUMIF($C$401:$C$528,$C531,AP$401:AP$528) | AQ531: =SUMIF($C$401:$C$528,$C531,AQ$401:AQ$528) | AR531: =SUMIF($C$401:$C$528,$C531,AR$401:AR$528) | AS531: =SUMIF($C$401:$C$528,$C531,AS$401:AS$528) | ... AY531: =SUMIF($C$401:$C$528,$C531,AY$401:AY$528) | BA531: =SUMIF($C$401:$C$528,$C531,BA$401:BA$528) | BB531: =SUMIF($C$401:$C$528,$C531,BB$401:BB$528) | BC531: =SUMIF($C$401:$C$528,$C531,BC$401:BC$528) | BD531: =SUMIF($C$401:$C$528,$C531,BD$401:BD$528) | BE531: =SUMIF($C$401:$C$528,$C531,BE$401:BE$528) | BF531: =SUMIF($C$401:$C$528,$C531,BF$401:BF$528) | BG531: =SUMIF($C$401:$C$528,$C531,BG$401:BG$528) | BH531: =SUMIF($C$401:$C$528,$C531,BH$401:BH$528) | ... BN531: =SUMIF($C$401:$C$528,$C531,BN$401:BN$528)
B532: all | C532: ral | D532: Total fuel use | Rail | E532: ktoe | H532: mit.enc.all.ral | AL532: =SUMIF($C$401:$C$528,$C532,AL$401:AL$528) | AM532: =SUMIF($C$401:$C$528,$C532,AM$401:AM$528) | AN532: =SUMIF($C$401:$C$528,$C532,AN$401:AN$528) | AO532: =SUMIF($C$401:$C$528,$C532,AO$401:AO$528) | AP532: =SUMIF($C$401:$C$528,$C532,AP$401:AP$528) | AQ532: =SUMIF($C$401:$C$528,$C532,AQ$401:AQ$528) | AR532: =SUMIF($C$401:$C$528,$C532,AR$401:AR$528) | AS532: =SUMIF($C$401:$C$528,$C532,AS$401:AS$528) | ... AY532: =SUMIF($C$401:$C$528,$C532,AY$401:AY$528) | BA532: =SUMIF($C$401:$C$528,$C532,BA$401:BA$528) | BB532: =SUMIF($C$401:$C$528,$C532,BB$401:BB$528) | BC532: =SUMIF($C$401:$C$528,$C532,BC$401:BC$528) | BD532: =SUMIF($C$401:$C$528,$C532,BD$401:BD$528) | BE532: =SUMIF($C$401:$C$528,$C532,BE$401:BE$528) | BF532: =SUMIF($C$401:$C$528,$C532,BF$401:BF$528) | BG532: =SUMIF($C$401:$C$528,$C532,BG$401:BG$528) | BH532: =SUMIF($C$401:$C$528,$C532,BH$401:BH$528) | ... BN532: =SUMIF($C$401:$C$528,$C532,BN$401:BN$528)
B533: all | C533: avi | D533: Total fuel use | Domestic aviation | E533: ktoe | H533: mit.enc.all.avi | AL533: =SUMIF($C$401:$C$528,$C533,AL$401:AL$528) | AM533: =SUMIF($C$401:$C$528,$C533,AM$401:AM$528) | AN533: =SUMIF($C$401:$C$528,$C533,AN$401:AN$528) | AO533: =SUMIF($C$401:$C$528,$C533,AO$401:AO$528) | AP533: =SUMIF($C$401:$C$528,$C533,AP$401:AP$528) | AQ533: =SUMIF($C$401:$C$528,$C533,AQ$401:AQ$528) | AR533: =SUMIF($C$401:$C$528,$C533,AR$401:AR$528) | AS533: =SUMIF($C$401:$C$528,$C533,AS$401:AS$528) | ... AY533: =SUMIF($C$401:$C$528,$C533,AY$401:AY$528) | BA533: =SUMIF($C$401:$C$528,$C533,BA$401:BA$528) | BB533: =SUMIF($C$401:$C$528,$C533,BB$401:BB$528) | BC533: =SUMIF($C$401:$C$528,$C533,BC$401:BC$528) | BD533: =SUMIF($C$401:$C$528,$C533,BD$401:BD$528) | BE533: =SUMIF($C$401:$C$528,$C533,BE$401:BE$528) | BF533: =SUMIF($C$401:$C$528,$C533,BF$401:BF$528) | BG533: =SUMIF($C$401:$C$528,$C533,BG$401:BG$528) | BH533: =SUMIF($C$401:$C$528,$C533,BH$401:BH$528) | ... BN533: =SUMIF($C$401:$C$528,$C533,BN$401:BN$528)
B534: all | C534: nav | D534: Total fuel use | Domestic navigation | E534: ktoe | H534: mit.enc.all.nav | AL534: =SUMIF($C$401:$C$528,$C534,AL$401:AL$528) | AM534: =SUMIF($C$401:$C$528,$C534,AM$401:AM$528) | AN534: =SUMIF($C$401:$C$528,$C534,AN$401:AN$528) | AO534: =SUMIF($C$401:$C$528,$C534,AO$401:AO$528) | AP534: =SUMIF($C$401:$C$528,$C534,AP$401:AP$528) | AQ534: =SUMIF($C$401:$C$528,$C534,AQ$401:AQ$528) | AR534: =SUMIF($C$401:$C$528,$C534,AR$401:AR$528) | AS534: =SUMIF($C$401:$C$528,$C534,AS$401:AS$528) | ... AY534: =SUMIF($C$401:$C$528,$C534,AY$401:AY$528) | BA534: =SUMIF($C$401:$C$528,$C534,BA$401:BA$528) | BB534: =SUMIF($C$401:$C$528,$C534,BB$401:BB$528) | BC534: =SUMIF($C$401:$C$528,$C534,BC$401:BC$528) | BD534: =SUMIF($C$401:$C$528,$C534,BD$401:BD$528) | BE534: =SUMIF($C$401:$C$528,$C534,BE$401:BE$528) | BF534: =SUMIF($C$401:$C$528,$C534,BF$401:BF$528) | BG534: =SUMIF($C$401:$C$528,$C534,BG$401:BG$528) | BH534: =SUMIF($C$401:$C$528,$C534,BH$401:BH$528) | ... BN534: =SUMIF($C$401:$C$528,$C534,BN$401:BN$528)
B535: all | C535: res | D535: Total fuel use | Residential | E535: ktoe | H535: mit.enc.all.res | AL535: =SUMIF($C$401:$C$528,$C535,AL$401:AL$528) | AM535: =SUMIF($C$401:$C$528,$C535,AM$401:AM$528) | AN535: =SUMIF($C$401:$C$528,$C535,AN$401:AN$528) | AO535: =SUMIF($C$401:$C$528,$C535,AO$401:AO$528) | AP535: =SUMIF($C$401:$C$528,$C535,AP$401:AP$528) | AQ535: =SUMIF($C$401:$C$528,$C535,AQ$401:AQ$528) | AR535: =SUMIF($C$401:$C$528,$C535,AR$401:AR$528) | AS535: =SUMIF($C$401:$C$528,$C535,AS$401:AS$528) | ... AY535: =SUMIF($C$401:$C$528,$C535,AY$401:AY$528) | BA535: =SUMIF($C$401:$C$528,$C535,BA$401:BA$528) | BB535: =SUMIF($C$401:$C$528,$C535,BB$401:BB$528) | BC535: =SUMIF($C$401:$C$528,$C535,BC$401:BC$528) | BD535: =SUMIF($C$401:$C$528,$C535,BD$401:BD$528) | BE535: =SUMIF($C$401:$C$528,$C535,BE$401:BE$528) | BF535: =SUMIF($C$401:$C$528,$C535,BF$401:BF$528) | BG535: =SUMIF($C$401:$C$528,$C535,BG$401:BG$528) | BH535: =SUMIF($C$401:$C$528,$C535,BH$401:BH$528) | ... BN535: =SUMIF($C$401:$C$528,$C535,BN$401:BN$528)
B536: all | C536: foo | D536: Total fuel use | Food & forestry | E536: ktoe | H536: mit.enc.all.foo | AL536: =SUMIF($C$401:$C$528,$C536,AL$401:AL$528) | AM536: =SUMIF($C$401:$C$528,$C536,AM$401:AM$528) | AN536: =SUMIF($C$401:$C$528,$C536,AN$401:AN$528) | AO536: =SUMIF($C$401:$C$528,$C536,AO$401:AO$528) | AP536: =SUMIF($C$401:$C$528,$C536,AP$401:AP$528) | AQ536: =SUMIF($C$401:$C$528,$C536,AQ$401:AQ$528) | AR536: =SUMIF($C$401:$C$528,$C536,AR$401:AR$528) | AS536: =SUMIF($C$401:$C$528,$C536,AS$401:AS$528) | ... AY536: =SUMIF($C$401:$C$528,$C536,AY$401:AY$528) | BA536: =SUMIF($C$401:$C$528,$C536,BA$401:BA$528) | BB536: =SUMIF($C$401:$C$528,$C536,BB$401:BB$528) | BC536: =SUMIF($C$401:$C$528,$C536,BC$401:BC$528) | BD536: =SUMIF($C$401:$C$528,$C536,BD$401:BD$528) | BE536: =SUMIF($C$401:$C$528,$C536,BE$401:BE$528) | BF536: =SUMIF($C$401:$C$528,$C536,BF$401:BF$528) | BG536: =SUMIF($C$401:$C$528,$C536,BG$401:BG$528) | BH536: =SUMIF($C$401:$C$528,$C536,BH$401:BH$528) | ... BN536: =SUMIF($C$401:$C$528,$C536,BN$401:BN$528)
B537: all | C537: srv | D537: Total fuel use | Services (public & private) | E537: ktoe | H537: mit.enc.all.srv | AL537: =SUMIF($C$401:$C$528,$C537,AL$401:AL$528) | AM537: =SUMIF($C$401:$C$528,$C537,AM$401:AM$528) | AN537: =SUMIF($C$401:$C$528,$C537,AN$401:AN$528) | AO537: =SUMIF($C$401:$C$528,$C537,AO$401:AO$528) | AP537: =SUMIF($C$401:$C$528,$C537,AP$401:AP$528) | AQ537: =SUMIF($C$401:$C$528,$C537,AQ$401:AQ$528) | AR537: =SUMIF($C$401:$C$528,$C537,AR$401:AR$528) | AS537: =SUMIF($C$401:$C$528,$C537,AS$401:AS$528) | ... AY537: =SUMIF($C$401:$C$528,$C537,AY$401:AY$528) | BA537: =SUMIF($C$401:$C$528,$C537,BA$401:BA$528) | BB537: =SUMIF($C$401:$C$528,$C537,BB$401:BB$528) | BC537: =SUMIF($C$401:$C$528,$C537,BC$401:BC$528) | BD537: =SUMIF($C$401:$C$528,$C537,BD$401:BD$528) | BE537: =SUMIF($C$401:$C$528,$C537,BE$401:BE$528) | BF537: =SUMIF($C$401:$C$528,$C537,BF$401:BF$528) | BG537: =SUMIF($C$401:$C$528,$C537,BG$401:BG$528) | BH537: =SUMIF($C$401:$C$528,$C537,BH$401:BH$528) | ... BN537: =SUMIF($C$401:$C$528,$C537,BN$401:BN$528)
B538: all | C538: mch | D538: Total fuel use | Mining & chemicals | E538: ktoe | H538: mit.enc.all.mch | AL538: =SUMIF($C$401:$C$528,$C538,AL$401:AL$528) | AM538: =SUMIF($C$401:$C$528,$C538,AM$401:AM$528) | AN538: =SUMIF($C$401:$C$528,$C538,AN$401:AN$528) | AO538: =SUMIF($C$401:$C$528,$C538,AO$401:AO$528) | AP538: =SUMIF($C$401:$C$528,$C538,AP$401:AP$528) | AQ538: =SUMIF($C$401:$C$528,$C538,AQ$401:AQ$528) | AR538: =SUMIF($C$401:$C$528,$C538,AR$401:AR$528) | AS538: =SUMIF($C$401:$C$528,$C538,AS$401:AS$528) | ... AY538: =SUMIF($C$401:$C$528,$C538,AY$401:AY$528) | BA538: =SUMIF($C$401:$C$528,$C538,BA$401:BA$528) | BB538: =SUMIF($C$401:$C$528,$C538,BB$401:BB$528) | BC538: =SUMIF($C$401:$C$528,$C538,BC$401:BC$528) | BD538: =SUMIF($C$401:$C$528,$C538,BD$401:BD$528) | BE538: =SUMIF($C$401:$C$528,$C538,BE$401:BE$528) | BF538: =SUMIF($C$401:$C$528,$C538,BF$401:BF$528) | BG538: =SUMIF($C$401:$C$528,$C538,BG$401:BG$528) | BH538: =SUMIF($C$401:$C$528,$C538,BH$401:BH$528) | ... BN538: =SUMIF($C$401:$C$528,$C538,BN$401:BN$528)
B539: all | C539: irn | D539: Total fuel use | Iron & steel | E539: ktoe | H539: mit.enc.all.irn | AL539: =SUMIF($C$401:$C$528,$C539,AL$401:AL$528) | AM539: =SUMIF($C$401:$C$528,$C539,AM$401:AM$528) | AN539: =SUMIF($C$401:$C$528,$C539,AN$401:AN$528) | AO539: =SUMIF($C$401:$C$528,$C539,AO$401:AO$528) | AP539: =SUMIF($C$401:$C$528,$C539,AP$401:AP$528) | AQ539: =SUMIF($C$401:$C$528,$C539,AQ$401:AQ$528) | AR539: =SUMIF($C$401:$C$528,$C539,AR$401:AR$528) | AS539: =SUMIF($C$401:$C$528,$C539,AS$401:AS$528) | ... AY539: =SUMIF($C$401:$C$528,$C539,AY$401:AY$528) | BA539: =SUMIF($C$401:$C$528,$C539,BA$401:BA$528) | BB539: =SUMIF($C$401:$C$528,$C539,BB$401:BB$528) | BC539: =SUMIF($C$401:$C$528,$C539,BC$401:BC$528) | BD539: =SUMIF($C$401:$C$528,$C539,BD$401:BD$528) | BE539: =SUMIF($C$401:$C$528,$C539,BE$401:BE$528) | BF539: =SUMIF($C$401:$C$528,$C539,BF$401:BF$528) | BG539: =SUMIF($C$401:$C$528,$C539,BG$401:BG$528) | BH539: =SUMIF($C$401:$C$528,$C539,BH$401:BH$528) | ... BN539: =SUMIF($C$401:$C$528,$C539,BN$401:BN$528)
B540: all | C540: nfm | D540: Total fuel use | Other metals | E540: ktoe | H540: mit.enc.all.nfm | AL540: =SUMIF($C$401:$C$528,$C540,AL$401:AL$528) | AM540: =SUMIF($C$401:$C$528,$C540,AM$401:AM$528) | AN540: =SUMIF($C$401:$C$528,$C540,AN$401:AN$528) | AO540: =SUMIF($C$401:$C$528,$C540,AO$401:AO$528) | AP540: =SUMIF($C$401:$C$528,$C540,AP$401:AP$528) | AQ540: =SUMIF($C$401:$C$528,$C540,AQ$401:AQ$528) | AR540: =SUMIF($C$401:$C$528,$C540,AR$401:AR$528) | AS540: =SUMIF($C$401:$C$528,$C540,AS$401:AS$528) | ... AY540: =SUMIF($C$401:$C$528,$C540,AY$401:AY$528) | BA540: =SUMIF($C$401:$C$528,$C540,BA$401:BA$528) | BB540: =SUMIF($C$401:$C$528,$C540,BB$401:BB$528) | BC540: =SUMIF($C$401:$C$528,$C540,BC$401:BC$528) | BD540: =SUMIF($C$401:$C$528,$C540,BD$401:BD$528) | BE540: =SUMIF($C$401:$C$528,$C540,BE$401:BE$528) | BF540: =SUMIF($C$401:$C$528,$C540,BF$401:BF$528) | BG540: =SUMIF($C$401:$C$528,$C540,BG$401:BG$528) | BH540: =SUMIF($C$401:$C$528,$C540,BH$401:BH$528) | ... BN540: =SUMIF($C$401:$C$528,$C540,BN$401:BN$528)
B541: all | C541: mac | D541: Total fuel use | Machinery | E541: ktoe | H541: mit.enc.all.mac | AL541: =SUMIF($C$401:$C$528,$C541,AL$401:AL$528) | AM541: =SUMIF($C$401:$C$528,$C541,AM$401:AM$528) | AN541: =SUMIF($C$401:$C$528,$C541,AN$401:AN$528) | AO541: =SUMIF($C$401:$C$528,$C541,AO$401:AO$528) | AP541: =SUMIF($C$401:$C$528,$C541,AP$401:AP$528) | AQ541: =SUMIF($C$401:$C$528,$C541,AQ$401:AQ$528) | AR541: =SUMIF($C$401:$C$528,$C541,AR$401:AR$528) | AS541: =SUMIF($C$401:$C$528,$C541,AS$401:AS$528) | ... AY541: =SUMIF($C$401:$C$528,$C541,AY$401:AY$528) | BA541: =SUMIF($C$401:$C$528,$C541,BA$401:BA$528) | BB541: =SUMIF($C$401:$C$528,$C541,BB$401:BB$528) | BC541: =SUMIF($C$401:$C$528,$C541,BC$401:BC$528) | BD541: =SUMIF($C$401:$C$528,$C541,BD$401:BD$528) | BE541: =SUMIF($C$401:$C$528,$C541,BE$401:BE$528) | BF541: =SUMIF($C$401:$C$528,$C541,BF$401:BF$528) | BG541: =SUMIF($C$401:$C$528,$C541,BG$401:BG$528) | BH541: =SUMIF($C$401:$C$528,$C541,BH$401:BH$528) | ... BN541: =SUMIF($C$401:$C$528,$C541,BN$401:BN$528)
B542: all | C542: cem | D542: Total fuel use | Cement | E542: ktoe | H542: mit.enc.all.cem | AL542: =SUMIF($C$401:$C$528,$C542,AL$401:AL$528) | AM542: =SUMIF($C$401:$C$528,$C542,AM$401:AM$528) | AN542: =SUMIF($C$401:$C$528,$C542,AN$401:AN$528) | AO542: =SUMIF($C$401:$C$528,$C542,AO$401:AO$528) | AP542: =SUMIF($C$401:$C$528,$C542,AP$401:AP$528) | AQ542: =SUMIF($C$401:$C$528,$C542,AQ$401:AQ$528) | AR542: =SUMIF($C$401:$C$528,$C542,AR$401:AR$528) | AS542: =SUMIF($C$401:$C$528,$C542,AS$401:AS$528) | ... AY542: =SUMIF($C$401:$C$528,$C542,AY$401:AY$528) | BA542: =SUMIF($C$401:$C$528,$C542,BA$401:BA$528) | BB542: =SUMIF($C$401:$C$528,$C542,BB$401:BB$528) | BC542: =SUMIF($C$401:$C$528,$C542,BC$401:BC$528) | BD542: =SUMIF($C$401:$C$528,$C542,BD$401:BD$528) | BE542: =SUMIF($C$401:$C$528,$C542,BE$401:BE$528) | BF542: =SUMIF($C$401:$C$528,$C542,BF$401:BF$528) | BG542: =SUMIF($C$401:$C$528,$C542,BG$401:BG$528) | BH542: =SUMIF($C$401:$C$528,$C542,BH$401:BH$528) | ... BN542: =SUMIF($C$401:$C$528,$C542,BN$401:BN$528)
... B546: all | C546: oen | D546: Total fuel use | Other energy use | E546: ktoe | H546: mit.enc.all.oen | AL546: =SUMIF($C$401:$C$528,$C546,AL$401:AL$528) | AM546: =SUMIF($C$401:$C$528,$C546,AM$401:AM$528) | AN546: =SUMIF($C$401:$C$528,$C546,AN$401:AN$528) | AO546: =SUMIF($C$401:$C$528,$C546,AO$401:AO$528) | AP546: =SUMIF($C$401:$C$528,$C546,AP$401:AP$528) | AQ546: =SUMIF($C$401:$C$528,$C546,AQ$401:AQ$528) | AR546: =SUMIF($C$401:$C$528,$C546,AR$401:AR$528) | AS546: =SUMIF($C$401:$C$528,$C546,AS$401:AS$528) | ... AY546: =SUMIF($C$401:$C$528,$C546,AY$401:AY$528) | BA546: =SUMIF($C$401:$C$528,$C546,BA$401:BA$528) | BB546: =SUMIF($C$401:$C$528,$C546,BB$401:BB$528) | BC546: =SUMIF($C$401:$C$528,$C546,BC$401:BC$528) | BD546: =SUMIF($C$401:$C$528,$C546,BD$401:BD$528) | BE546: =SUMIF($C$401:$C$528,$C546,BE$401:BE$528) | BF546: =SUMIF($C$401:$C$528,$C546,BF$401:BF$528) | BG546: =SUMIF($C$401:$C$528,$C546,BG$401:BG$528) | BH546: =SUMIF($C$401:$C$528,$C546,BH$401:BH$528) | ... BN546: =SUMIF($C$401:$C$528,$C546,BN$401:BN$528)
B548: coa | C548: all | D548: Total fuel use | Coal | E548: ktoe | H548: mit.enc.coa.all | AL548: =SUMIF($B$401:$B$528,$B548,AL$401:AL$528) | AM548: =SUMIF($B$401:$B$528,$B548,AM$401:AM$528) | AN548: =SUMIF($B$401:$B$528,$B548,AN$401:AN$528) | AO548: =SUMIF($B$401:$B$528,$B548,AO$401:AO$528) | AP548: =SUMIF($B$401:$B$528,$B548,AP$401:AP$528) | AQ548: =SUMIF($B$401:$B$528,$B548,AQ$401:AQ$528) | AR548: =SUMIF($B$401:$B$528,$B548,AR$401:AR$528) | AS548: =SUMIF($B$401:$B$528,$B548,AS$401:AS$528) | ... AY548: =SUMIF($B$401:$B$528,$B548,AY$401:AY$528) | BA548: =SUMIF($B$401:$B$528,$B548,BA$401:BA$528) | BB548: =SUMIF($B$401:$B$528,$B548,BB$401:BB$528) | BC548: =SUMIF($B$401:$B$528,$B548,BC$401:BC$528) | BD548: =SUMIF($B$401:$B$528,$B548,BD$401:BD$528) | BE548: =SUMIF($B$401:$B$528,$B548,BE$401:BE$528) | BF548: =SUMIF($B$401:$B$528,$B548,BF$401:BF$528) | BG548: =SUMIF($B$401:$B$528,$B548,BG$401:BG$528) | BH548: =SUMIF($B$401:$B$528,$B548,BH$401:BH$528) | ... BN548: =SUMIF($B$401:$B$528,$B548,BN$401:BN$528)
B549: nga | C549: all | D549: Total fuel use | Natural gas | E549: ktoe | H549: mit.enc.nga.all | AL549: =SUMIF($B$401:$B$528,$B549,AL$401:AL$528) | AM549: =SUMIF($B$401:$B$528,$B549,AM$401:AM$528) | AN549: =SUMIF($B$401:$B$528,$B549,AN$401:AN$528) | AO549: =SUMIF($B$401:$B$528,$B549,AO$401:AO$528) | AP549: =SUMIF($B$401:$B$528,$B549,AP$401:AP$528) | AQ549: =SUMIF($B$401:$B$528,$B549,AQ$401:AQ$528) | AR549: =SUMIF($B$401:$B$528,$B549,AR$401:AR$528) | AS549: =SUMIF($B$401:$B$528,$B549,AS$401:AS$528) | ... AY549: =SUMIF($B$401:$B$528,$B549,AY$401:AY$528) | BA549: =SUMIF($B$401:$B$528,$B549,BA$401:BA$528) | BB549: =SUMIF($B$401:$B$528,$B549,BB$401:BB$528) | BC549: =SUMIF($B$401:$B$528,$B549,BC$401:BC$528) | BD549: =SUMIF($B$401:$B$528,$B549,BD$401:BD$528) | BE549: =SUMIF($B$401:$B$528,$B549,BE$401:BE$528) | BF549: =SUMIF($B$401:$B$528,$B549,BF$401:BF$528) | BG549: =SUMIF($B$401:$B$528,$B549,BG$401:BG$528) | BH549: =SUMIF($B$401:$B$528,$B549,BH$401:BH$528) | ... BN549: =SUMIF($B$401:$B$528,$B549,BN$401:BN$528)
B550: gso | C550: all | D550: Total fuel use | Gasoline | E550: ktoe | H550: mit.enc.gso.all | AL550: =SUMIF($B$401:$B$528,$B550,AL$401:AL$528) | AM550: =SUMIF($B$401:$B$528,$B550,AM$401:AM$528) | AN550: =SUMIF($B$401:$B$528,$B550,AN$401:AN$528) | AO550: =SUMIF($B$401:$B$528,$B550,AO$401:AO$528) | AP550: =SUMIF($B$401:$B$528,$B550,AP$401:AP$528) | AQ550: =SUMIF($B$401:$B$528,$B550,AQ$401:AQ$528) | AR550: =SUMIF($B$401:$B$528,$B550,AR$401:AR$528) | AS550: =SUMIF($B$401:$B$528,$B550,AS$401:AS$528) | ... AY550: =SUMIF($B$401:$B$528,$B550,AY$401:AY$528) | BA550: =SUMIF($B$401:$B$528,$B550,BA$401:BA$528) | BB550: =SUMIF($B$401:$B$528,$B550,BB$401:BB$528) | BC550: =SUMIF($B$401:$B$528,$B550,BC$401:BC$528) | BD550: =SUMIF($B$401:$B$528,$B550,BD$401:BD$528) | BE550: =SUMIF($B$401:$B$528,$B550,BE$401:BE$528) | BF550: =SUMIF($B$401:$B$528,$B550,BF$401:BF$528) | BG550: =SUMIF($B$401:$B$528,$B550,BG$401:BG$528) | BH550: =SUMIF($B$401:$B$528,$B550,BH$401:BH$528) | ... BN550: =SUMIF($B$401:$B$528,$B550,BN$401:BN$528)
B551: die | C551: all | D551: Total fuel use | Diesel | E551: ktoe | H551: mit.enc.die.all | AL551: =SUMIF($B$401:$B$528,$B551,AL$401:AL$528) | AM551: =SUMIF($B$401:$B$528,$B551,AM$401:AM$528) | AN551: =SUMIF($B$401:$B$528,$B551,AN$401:AN$528) | AO551: =SUMIF($B$401:$B$528,$B551,AO$401:AO$528) | AP551: =SUMIF($B$401:$B$528,$B551,AP$401:AP$528) | AQ551: =SUMIF($B$401:$B$528,$B551,AQ$401:AQ$528) | AR551: =SUMIF($B$401:$B$528,$B551,AR$401:AR$528) | AS551: =SUMIF($B$401:$B$528,$B551,AS$401:AS$528) | ... AY551: =SUMIF($B$401:$B$528,$B551,AY$401:AY$528) | BA551: =SUMIF($B$401:$B$528,$B551,BA$401:BA$528) | BB551: =SUMIF($B$401:$B$528,$B551,BB$401:BB$528) | BC551: =SUMIF($B$401:$B$528,$B551,BC$401:BC$528) | BD551: =SUMIF($B$401:$B$528,$B551,BD$401:BD$528) | BE551: =SUMIF($B$401:$B$528,$B551,BE$401:BE$528) | BF551: =SUMIF($B$401:$B$528,$B551,BF$401:BF$528) | BG551: =SUMIF($B$401:$B$528,$B551,BG$401:BG$528) | BH551: =SUMIF($B$401:$B$528,$B551,BH$401:BH$528) | ... BN551: =SUMIF($B$401:$B$528,$B551,BN$401:BN$528)
