Workbook
Name ETSPRICE: _xlfn.LAMBDA(_xlpm.apply,_xlpm.year,_xlpm.start_year,_xlpm.carbon_price,IF(AND(LEFT(_xlpm.apply,3)="Yes",_xlpm.year>=_xlpm.start_year),_xlpm.carbon_price,0))
Name ETSCOVER: _xlfn.LAMBDA(_xlpm.apply,_xlpm.year,_xlpm.start_year,_xlpm.covered,IF(AND(LEFT(_xlpm.apply,3)="Yes",_xlpm.year>=_xlpm.start_year),IF(_xlpm.covered,1,0),0))
Name SHADOWSECTOR: _xlfn.LAMBDA(_xlpm.feebate,_xlpm.regulation,_xlpm.feebate+_xlpm.regulation)
Name SHADOWSHARE: _xlfn.LAMBDA(_xlpm.coverage,_xlpm.adjustment,IF(_xlpm.coverage,1,0)*_xlpm.adjustment)
Name RETAILPRICE: _xlfn.LAMBDA(_xlpm.sp,_xlpm.txo,_xlpm.vat_rate,(_xlpm.sp+_xlpm.txo)*(1+_xlpm.vat_rate))
Name VATPAY: _xlfn.LAMBDA(_xlpm.sp,_xlpm.txo,_xlpm.vat_rate,(_xlpm.sp+_xlpm.txo)*_xlpm.vat_rate)
Name TAXPART: _xlfn.LAMBDA(_xlpm.txo,MAX(_xlpm.txo,0))
Name SUBSIDYPART: _xlfn.LAMBDA(_xlpm.txo,MAX(-_xlpm.txo,0))
Name PERUNIT: _xlfn.LAMBDA(_xlpm.value_gj,_xlpm.gj_per_unit,_xlpm.value_gj*_xlpm.gj_per_unit)
Name CARBONTAX: _xlfn.LAMBDA(_xlpm.price,_xlpm.ef,_xlpm.fuel_cov,_xlpm.sector_cov,_xlpm.ets_cov,_xlpm.price*_xlpm.ef*_xlpm.fuel_cov*_xlpm.sector_cov*(1-_xlpm.ets_cov))
Name ETSCOST: _xlfn.LAMBDA(_xlpm.price,_xlpm.ef,_xlpm.ets_cov,_xlpm.price*_xlpm.ef*_xlpm.ets_cov)
Name NEWEXCISE: _xlfn.LAMBDA(_xlpm.increase,_xlpm.gj_per_unit,_xlpm.increase/_xlpm.gj_per_unit)
Name NEWPOLICY: _xlfn.LAMBDA(_xlpm.carbon_tax,_xlpm.ets,_xlpm.excise,_xlpm.carbon_tax+_xlpm.ets+_xlpm.excise)
Name POSTTAX: _xlfn.LAMBDA(_xlpm.pre_policy_p,_xlpm.new_policy,_xlpm.vat_rate,MAX(_xlpm.pre_policy_p+_xlpm.new_policy*(1+_xlpm.vat_rate),0.01))
Name SHADOWEFF: _xlfn.LAMBDA(_xlpm.sector_price,_xlpm.ef,_xlpm.share,_xlpm.sector_price*_xlpm.ef*_xlpm.share)
Name REVENUE: _xlfn.LAMBDA(_xlpm.fuel_use,_xlpm.pj_per_ktoe,_xlpm.rate,_xlpm.fuel_use*_xlpm.pj_per_ktoe*_xlpm.rate)
Name NEWREVRATE: _xlfn.LAMBDA(_xlpm.carbon_tax,_xlpm.excise,_xlpm.ets,_xlpm.auct_share,_xlpm.new_policy,_xlpm.vat_rate,_xlpm.carbon_tax+_xlpm.excise+_xlpm.ets*_xlpm.auct_share+_xlpm.new_policy*_xlpm.vat_rate)

Sheet ReadMe
A2: CPAT mitigation module - copy-pasteable prototype v0.12
A4: Purpose | B4: Auditable, copy-pasteable replacement of the CPAT mitigation price -> fuel-use chain. Each variable has one formula across all subsectors, fuels and years, and a whole scenario group copies to a new scenario and keeps working.
A5: Status | B5: v0.12 prototype to 2040: policies (carbon tax, new ETS, fuel price reform, feebates with sectoral shadow prices), domestic prices with existing taxes and subsidies, and price -> fuel use for transport, buildings, industry and other energy use, and revenues (section 12). Power, electricity prices and emissions not yet. Differences with legacy: sheet LegacyDiff.
A6: Layout (as legacy CPAT) | B6: Sections: 1. Policies (row 11), 2. Retail energy prices (row 197), 3. Power sector (row 298, placeholder), 5. Transport (row 301), 6. Buildings (row 668), 7. Industrial (row 944), 8. Other energy use (row 1675), 11. Results - energy consumption (row 1769). Numbers follow the legacy Mitigation sheet.
A7: Nesting | B7: Across: scenario (outer) > year (inner). Down: sector section > subsector > variable > fuel. Each subsector: a heading line (its total fuel use), then ctxnew, ets, ntx, nce, atp, shp, ener, rtx, rsub, rnew, each over the 8 fuels with one blank row (91 rows per subsector). Section 2: sp, txo, rpb over the 12 price fuels (coal and gas x power / residential / industry; gasoline, diesel, LPG, kerosene, other oil products, biomass for all sectors).
A8: ASSUMPTIONS: units | B8: All prices, taxes and policy values are in REAL US DOLLARS OF THE RESULTS YEAR (MTInputs ResultsYear, 2026; Settings C8), per GJ. There is no inflation after the conversion: a constant real price is a constant number. Fuel use is in ktoe.
A9: ASSUMPTIONS: two indices | B9: Row 8 infl = US CPI(ResultsYear) / US CPI(year) converts nominal DOMESTIC data (IMF price dataset: supply cost, taxes, retail price, margin, production cost) and nominal policy inputs. Row 9 defl = US GDP deflator(ResultsYear) / deflator(year) converts nominal INTERNATIONAL prices (legacy uses the deflator there). The two differ by up to 1.2% before 2030 (2022: 1.137 vs 1.124), so both are kept. The CPI is held flat after 2031 in the legacy data (WEO horizon); results after 2030 are not compared with legacy.
A10: ASSUMPTIONS: inputs | B10: Domestic price data are nominal USD of their year -> x infl of that year. International prices are nominal -> x defl; only their year-on-year ratios move the supply cost, so their units and level drop out. MTInputs policy values are REAL (ResultsYear USD): carbon price, feebate rates and fuel price reform increases. Only the carbon price has a switch: NomorReal = Nominal makes it nominal, then x infl (legacy row 2249). Margins and production costs are base-year (2022) nominal values -> x infl(2022), held constant in real terms.
A11: ASSUMPTIONS: history | B11: Years up to the last historical price year (Settings C10, 2024) take prices from data (Inputs_prices); later years are projected. Base-year (2022) fuel use is data; fuel use from 2023 on is modelled with these prices (also in 2023-2024).
A12: ASSUMPTIONS: global vs scenario | B12: Global (Settings, from MTInputs scenario 1): ResultsYear, government price controls (pass-through), last historical year, gas market of the country. Per scenario (MTInputs column): international price source and adjustment, carbon price and its nominal/real switch, fuel price reform, feebates, coverage.
A13: ASSUMPTIONS: legacy quirk | B13: Legacy rule kept: with pass-through 0.5 or 0.8 txo jumps in the first projected year. See PriceProjection_Method_v0.3.md.
A14: ASSUMPTIONS: DATA CHANGED (v0.10) | B14: Bright yellow cells with red text in Inputs_prices: (1) other oil products take pass-through and margin from the dataset like the other oil products (legacy hardcodes 1 and 0, which drove their retail price to the 0.01 floor); (2) VAT rate: dataset rate where filled, else the general VAT rate VAT_WEO (Egypt 14%) for residential coal and gas and all-sector oil products; power, industry and biomass 0. New policies pay this VAT.
A15: Price projection | B15: gp = international price (source, gas market, High/Low factor after the last historical year). sp = fixsp + (sp(t-1) - fixsp) x gp(t) / gp(t-1), fixsp = margin + pass-through x production cost (coal, gas). txo = txo_L x pcc + cs, cs = (sp_L - sp + txo_L(1 - pcc)) x (1 - pcc), not below txo_L(1 - pcc) if that is >= 0. rpb = (sp + txo) x (1 + VAT rate). atp = max(rpb + nce x (1 + VAT rate), 0.01): new policies are fully passed through and pay VAT. Pass-through 0 keeps rpb at its last historical value (Egypt gas and oil products); 1 passes supply-cost changes on in full.
... A28: Data | B28: Countries, Elasticities, Prices_dom, Prices_int, PriceAssump, EnergyCons, WEO, EF_GHG; Mapping; Variables; MTInputs. Built by build_v0_12.py; checked by check_v0_12.py.

Sheet LegacyDiff
A2: Differences with legacy CPAT (decisions, assumptions, simplifications, not yet modelled)
A3: Keep this list current with each version. Type: Decision = user decision; Assumption = data assumption (bright yellow in Inputs_prices); Simplification; Not yet; Data; Design; Same.
A4: # | B4: Area | C4: Legacy CPAT | D4: This model | E4: Why | F4: Effect | G4: Type
A5: 1 | B5: Elasticities: food & forestry | C5: Industry elasticities (cpat_coded EC_SECTORS) | D5: Services (buildings) elasticities | E5: User decision v0.11; legacy groups food & forestry with services as Commercial | F5: Food & forestry fuel response | G5: Decision
A6: 2 | B6: Other oil products: pass-through and margin | C6: Hardcoded 1 and 0 | D6: From the IMF dataset like the other oil products (Egypt 0 and 7.95 $/bbl) | E6: User decision v0.10: the legacy rule drove the retail price to the 0.01 floor and fuel use 10x by 2030 | F6: Large: other oil products, total fuel use | G6: Decision
A7: 3 | B7: VAT rate where the dataset is blank | C7: 0 | D7: General VAT rate VAT_WEO (Egypt 14%) for residential coal and gas and all-sector oil products; 0 for power, industry, biomass | E7: User decision v0.10; matches the retail prices in the Egypt dataset | F7: Historical oil-product retail prices +14%; VAT on new policies | G7: Assumption
A8: 4 | B8: Oil-product share in the VAT of transport fuels | C8: VAT rate x oil-product share | D8: Share = 1 | E8: Not yet extracted | F8: None for Egypt today | G8: Simplification
A9: 5 | B9: New ETS price | C9: Endogenous: cap relative to baseline emissions (MTInputs 85-87) | D9: Carbon price inputs (cptraj) once the ETS applies; replaces the carbon tax in ETS-covered sectors | E9: User decision v0.11: ETS as effective as a carbon tax; emissions not yet modelled | F9: ETS scenarios | G9: Simplification
A10: 6 | B10: ETS free allocation | C10: Non-auctioned share can act as a shadow price | D10: Full permit price in the retail price; auction share only for revenue | E10: As effective as a carbon tax (marginal incentive unchanged) | F10: Price level in ETS sectors; revenue | G10: Simplification
A11: 7 | B11: Existing ETS and existing carbon taxes | C11: Included where they exist | D11: Not modelled | E11: None for Egypt | F11: Other countries | G11: Not yet
A12: 8 | B12: Sectoral shadow prices | C12: Feebates + non-auctioned ETS + regulations | D12: Feebates + regulations (placeholder 0) | E12: Regulations not yet; ETS in the price | F12: Regulation scenarios | G12: Not yet
A13: 9 | B13: Policy paths after the target year | C13: Per instrument (carbon price: MTInputs switch) | D13: Linear continuation for fuel price reform and feebates; carbon price keeps the switch; ETS auction share constant | E13: User decision v0.8 (one default) | F13: Post-target years | G13: Decision
A14: 10 | B14: Feebate grouping | C14: Main grouping (buildings = residential rate) | D14: Same: food & forestry and services take the residential rate; other energy use the industry rate | E14: User decision v0.8 | F14: None | G14: Same
A15: 11 | B15: Biomass carbon-tax coverage | C15: No switch | D15: TRUE (EF 0) | E15: User decision v0.8 | F15: None | G15: Decision
A16: 12 | B16: Margins and production costs | C16: cpat_coded applies no inflation conversion | D16: x CPI index of the base year | E16: Consistent real terms (assumption A4) | F16: Coal and gas supply cost level | G16: To check (bucket 5)
... A26: 22 | B26: Formula structure | C26: Different formulas by block and year | D26: One formula per variable block; LAMBDA in the right column (2040) with the history/projection IF inside | E26: Auditability and copy-paste | F26: None (numerically identical) | G26: Design

Sheet Settings
A2: Settings
B4: Country code | C4: EGY
B5: Country name | C5: =INDEX(Countries!$B$4:$B$1000,MATCH($C$4,Countries!$A$4:$A$1000,0))
B6: Income group (selects elasticities) | C6: =INDEX(Countries!$D$4:$D$1000,MATCH($C$4,Countries!$A$4:$A$1000,0))
B7: Base year | C7: 2022
B8: Results in real USD of year (MTInputs ResultsYear, scenario 1) | C8: =INDEX(MTInputs!$J$8:$J$415,MATCH("ResultsYear",MTInputs!$H$8:$H$415,0))
B9: Government energy price controls (MTInputs GovPriceControls, scenario 1) | C9: =INDEX(MTInputs!$J$8:$J$415,MATCH("GovPriceControls",MTInputs!$H$8:$H$415,0))
B10: Last historical price year (IMF price dataset) | C10: 2024
B11: Gas market (PriceAssump, by country name) | C11: =INDEX(PriceAssump!$C$4:$C$400,MATCH($C$5,PriceAssump!$A$4:$A$400,0))
B12: Gas price commodity key (Prices_int) | C12: =IF($C$11="LNG","lng",IF($C$11="Europe","eur",IF($C$11="North Am","nam","glo")))
B13: PJ per ktoe (fuel use ktoe x PJ/ktoe x $/GJ = USD million) | C13: 0.041868
B15: Version log
B16: Version | C16: Date | D16: Description | E16: Max abs regression diff
B17: 0.1 | C17: 2026-10-08 | D17: First build: design 2 price -> fuel-use prototype, Egypt base data, 2 scenarios. | E17: n/a (first version)
B18: 0.2 | C18: 2026-10-08 | D18: Inputs sheet by fuel|subsector (lookups separated from formulas); 4 hidden parameter columns D:G, global parameters; base year 2022 in column L; named LAMBDAs in 2035. | E18: 0 (vs v0.1)
B19: 0.3 | C19: 2026-10-08 | D19: Variable codes in column A; labels from Variables; code column per scenario with full CPAT codes (auto-numbered). | E19: 0 (vs v0.2)
B20: 0.4 | C20: 2026-10-08 | D20: Row outline: blocks roll up. | E20: 0 (vs v0.3)
B21: 0.5 | C21: 2026-10-08 | D21: White band text; summary lines under bands. | E21: 0 (vs v0.4)
B22: 0.6 | C22: 2026-10-08 | D22: MTInputs sheet per scenario; carbon price from MTInputs. | E22: 0 (vs v0.5)
B23: 0.7 | C23: 2026-10-08 | D23: Legacy CPAT section layout (1 Policies, 3 Power, 5-8 sectors, 11 Results; subsector > variable > fuel); policy wedges: new carbon tax with MTInputs coverage, new excise (fuel price reform), total new policy; feebate shadow price (not yet used). | E23: 0 (common codes vs v0.6)
B24: 0.8 | C24: 2026-10-08 | D24: Shadow price on the efficiency margin of fuel use; shadow prices by sector and share impacting efficiency in section 1; all policy paths continue linearly; biomass carbon-tax coverage TRUE. | E24: 0 (common codes vs v0.7, no feebate)
B25: 0.9 | C25: 2026-10-08 | D25: Domestic price projection (legacy method) in section 2: international prices by source, supply cost, excise and other taxes with pass-through, retail price before new policies; real USD of ResultsYear (CPI and deflator indices); historical prices 2022-2024 from data; per subsector atp = rpb + nce x (1 + VAT). | E25: intended change: all prices and fuel use (see check report)
B26: 0.10 | C26: 2026-10-08 | D26: Other oil products treated like the other oil products (pass-through and margin from data); VAT-rate assumption where data blank (VAT_WEO for residential and oil products); changed data marked bright yellow. | E26: intended change: prices with VAT, other oil products, fuel use
B27: 0.11 | C27: 2026-10-09 | D27: Horizon 2040; food & forestry with services elasticities; new ETS (price = carbon price inputs, replaces the carbon tax where it covers); sectoral shadow prices (feebates + regulations placeholder); section 2: VAT payment, existing taxes and subsidies, subsidy per price unit; LAMBDA in the right column of every calculated row; separate history / projection column blocks; LegacyDiff sheet; 12. Revenues prepared. | E27: 0 to 2035 on unaffected codes (see check report); foo and horizon changes intended
B28: 0.12 | C28: 2026-10-09 | D28: Revenues: existing tax revenue, existing subsidy cost and new-policy revenue as separate calculations per subsector and fuel; section 12 totals by sector, net existing, total and change vs scenario 1. | E28: 0 on all v0.11 codes

Sheet MTInputs
B1: MTInputs template - row structure copied exactly from legacy CPAT MTInputs
B2: Do not insert/delete rows. Columns D:E are hidden placeholders (MT values, Dashboard values).
B3: Rows must match legacy exactly. Green (EBF1DE) = used by module; grey (F2F2F2) = unused. See NORMS.md section 4. | J3: Scenario columns (Used for calculation): number in row 5, name in row 6. Red = changed from the template value. Copy the last column one to the right to add a scenario.
C5: FALSE | D5: <-- Should normally be "FALSE"! | J5: 1 | K5: =J5+1
D6: 6 | J6: Baseline (no carbon price) | K6: Carbon price $20/tCO2 from 2027
B7: Parameters | C7: unit | D7: MT values | E7: "Dashboard" values | F7: Used for calculation | G7: Defaults | H7: NameOfParameter | J7: Used for calculation | K7: Used for calculation
B8: Country | F8: Egypt | G8: Egypt | H8: Countryname | J8: Egypt | K8: Egypt
B9: Scenario identification
B10: Scenario ID | C10: # | F10: N/A | G10: N/A | H10: MSTScenarioID | J10: =J$5 | K10: =K$5
B11: Scenario status | C11: switch | F11: N/A | G11: N/A | J11: N/A | K11: N/A
B12: Scenario name | C12: name | F12: N/A | G12: N/A | J12: =J$6 | K12: =K$6
B13: Chosen policy | C13: switch | F13: - Carbon tax | G13: - Carbon tax | H13: ScenarioSelected | J13: - Carbon tax | K13: - Carbon tax
B14: Scenario status for macro | C14: # | F14: N/A | G14: N/A | J14: N/A | K14: N/A
B15: Scenario parameters override? | C15: # | F15: N/A | G15: N/A | J15: N/A | K15: N/A
B16: CPAT-side parameters override? | C16: switch | F16: Manual* | G16: Manual* | H16: CPATDefaultsOrUserDefined | J16: Manual* | K16: Manual*
B17: Carbon pricing: main inputs
A18: X | B18: Carbon pricing start year | C18: year | F18: 2026 | G18: 2027 | H18: CPIntro | J18: 2027 | K18: 2027
A19: X | B19: Starting carbon price | C19: nom. USD/tCO2 | F19: 0 | G19: 20 | H19: CPLevelStart | J19: 0 | K19: 20
B20: Target level of carbon price | C20: nom. USD/tCO2 | F20: 50 | G20: 50 | H20: CPLevelTarget | J20: 0 | K20: 20
A21: X | B21: Year to reach target level | C21: year | F21: 2030 | G21: 2035 | H21: CPOutro | J21: 2030 | K21: 2030
B22: Carbon pricing: fuel coverage
B23: Apply tax to coal? | C23: switch | F23: TRUE | G23: TRUE | H23: MCovCoa | J23: TRUE | K23: TRUE
B24: Apply tax to natural gas? | C24: switch | F24: TRUE | G24: TRUE | H24: MCovNga | J24: TRUE | K24: TRUE
B25: Apply tax to gasoline? | C25: switch | F25: TRUE | G25: TRUE | H25: MCovGso | J25: TRUE | K25: TRUE
B26: Apply tax to diesel? | C26: switch | F26: TRUE | G26: TRUE | H26: MCovDie | J26: TRUE | K26: TRUE
B27: Apply tax to LPG? | C27: switch | F27: TRUE | G27: TRUE | H27: MCovLpg | J27: TRUE | K27: TRUE
B28: Apply tax to kerosene? | C28: switch | F28: TRUE | G28: TRUE | H28: MCovKer | J28: TRUE | K28: TRUE
B29: Apply tax to non-road oil products? | C29: switch | F29: TRUE | G29: TRUE | H29: MCovOop | J29: TRUE | K29: TRUE
B30: Carbon pricing: sector coverage
B31: Apply tax to power sector? | C31: switch | F31: TRUE | G31: TRUE | H31: MCovPow | J31: TRUE | K31: TRUE
B32: Apply tax to road transportation? | C32: switch | F32: TRUE | G32: TRUE | H32: MCovRod | J32: TRUE | K32: TRUE
B33: Apply tax to rail transportation? | C33: switch | F33: TRUE | G33: TRUE | H33: MCovRal | J33: TRUE | K33: TRUE
B34: Apply tax to domestic aviation? | C34: switch | F34: TRUE | G34: TRUE | H34: MCovAvi | J34: TRUE | K34: TRUE
B35: Apply tax to domestic shipping? | C35: switch | F35: TRUE | G35: TRUE | H35: MCovNav | J35: TRUE | K35: TRUE
B36: Apply tax to residential sector? | C36: switch | F36: TRUE | G36: TRUE | H36: MCovRes | J36: TRUE | K36: TRUE
B37: Apply tax to food & forestry? | C37: switch | F37: TRUE | G37: TRUE | H37: MCovFoo | J37: TRUE | K37: TRUE
B38: Apply tax to services (private / public)? | C38: switch | F38: TRUE | G38: TRUE | H38: MCovSrv | J38: TRUE | K38: TRUE
B39: Apply tax to mining & chemicals? | C39: switch | F39: TRUE | G39: TRUE | H39: MCovMch | J39: TRUE | K39: TRUE
B40: Apply tax to iron and steel? | C40: switch | F40: TRUE | G40: TRUE | H40: MCovIrn | J40: TRUE | K40: TRUE
B41: Apply tax to non-ferrous metals? | C41: switch | F41: TRUE | G41: TRUE | H41: MCovNfm | J41: TRUE | K41: TRUE
B42: Apply tax to machinery? | C42: switch | F42: TRUE | G42: TRUE | H42: MCovMac | J42: TRUE | K42: TRUE
... B47: Apply tax to other energy use? | C47: switch | F47: TRUE | G47: TRUE | H47: MCovOen | J47: FALSE | K47: FALSE
B48: Exemptions phaseout
B49: Apply exemption phaseout? | C49: switch | F49: FALSE | G49: FALSE | H49: ExemptPhaseout | J49: FALSE | K49: FALSE
B50: Year to start exemption phaseout (if applicable) | C50: year | F50: 2027 | G50: 2027 | H50: YearPha | J50: 2027 | K50: 2027
B51: Period to reach full exemption phaseout (if applicable) | C51: year | F51: 5 | G51: 5 | H51: ExemptPhaseoutPeriod | J51: 5 | K51: 5
B52: Feebates: Starting and End Date
B53: Start date | F53: 2027 | G53: 2027 | H53: D_FeebateIntro | J53: 2027 | K53: 2027
B54: Target date | F54: 2035 | G54: 2035 | H54: D_FeebateOutro | J54: 2035 | K54: 2035
B55: Feebates: Feebate starting rate
B56: Power sector | C56: USD/tCO2 | F56: 0 | G56: 0 | H56: D_Feb_Level_Start_Pow | J56: 0 | K56: 0
B57: Transport | C57: USD/tCO2 | F57: 0 | G57: 0 | H57: D_Feb_Level_Start_Trans | J57: 0 | K57: 0
B58: Residential | C58: USD/tCO2 | F58: 0 | G58: 0 | H58: D_Feb_Level_Start_Res | J58: 0 | K58: 0
B59: Industry | C59: USD/tCO2 | F59: 0 | G59: 0 | H59: D_Feb_Level_Start_Ind | J59: 0 | K59: 0
B60: Feebates: Feebate target rate
B61: Power sector | C61: USD/tCO2 | F61: 0 | G61: 0 | H61: D_Feb_Level_Target_Pow | J61: 0 | K61: 0
B62: Transport | C62: USD/tCO2 | F62: 0 | G62: 0 | H62: D_Feb_Level_Target_Trans | J62: 0 | K62: 0
B63: Residential | C63: USD/tCO2 | F63: 0 | G63: 0 | H63: D_Feb_Level_Target_Res | J63: 0 | K63: 0
B64: Industry | C64: USD/tCO2 | F64: 0 | G64: 0 | H64: D_Feb_Level_Target_Ind | J64: 0 | K64: 0
B65: Feebates sector coverage
B66: Apply tax to power sector? | C66: switch | F66: FALSE | G66: TRUE | J66: FALSE | K66: FALSE
B67: Apply tax to road transportation? | F67: FALSE | G67: FALSE | J67: FALSE | K67: FALSE
B68: Apply tax to rail transportation? | F68: FALSE | G68: FALSE | J68: FALSE | K68: FALSE
B69: Apply tax to domestic aviation? | F69: FALSE | G69: FALSE | J69: FALSE | K69: FALSE
B70: Apply tax to domestic shipping? | F70: FALSE | G70: FALSE | J70: FALSE | K70: FALSE
B71: Apply tax to residential sector? | C71: switch | F71: FALSE | G71: TRUE | J71: FALSE | K71: FALSE
B72: Apply tax to food & forestry? | F72: FALSE | G72: TRUE | J72: FALSE | K72: FALSE
B73: Apply tax to services (private / public)? | F73: FALSE | G73: TRUE | J73: FALSE | K73: FALSE
B74: Apply tax to mining & chemicals? | F74: TRUE | G74: TRUE | J74: TRUE | K74: TRUE
B75: Apply tax to iron and steel? | F75: FALSE | G75: TRUE | J75: FALSE | K75: FALSE
B76: Apply tax to non-ferrous metals? | F76: TRUE | G76: TRUE | J76: TRUE | K76: TRUE
B77: Apply tax to machinery? | F77: TRUE | G77: TRUE | J77: TRUE | K77: TRUE
B78: Apply tax to cement? | F78: TRUE | G78: TRUE | J78: TRUE | K78: TRUE
B79: Apply tax to other manucfacturing? | F79: TRUE | G79: TRUE | J79: TRUE | K79: TRUE
B80: Apply tax to construction? | F80: TRUE | G80: TRUE | J80: TRUE | K80: TRUE
B81: Apply tax to fuel transformation? | F81: TRUE | G81: TRUE | J81: TRUE | K81: TRUE
B82: Apply tax to other energy use? | F82: TRUE | G82: TRUE | J82: TRUE | K82: TRUE
B83: ETS Main Characteristics
B84: Apply new ETS? | F84: No | G84: No | H84: D_NewETS | J84: No | K84: No
B85: Change Relative to Baseline in Start Year | F85: 0 | G85: 0 | H85: D_ETSChangeRelStart | J85: 0 | K85: 0
B86: Change Relative to Baseline in Target Year | F86: 0 | G86: 0 | H86: D_ETSChangeRelTarget | J86: 0 | K86: 0
B87: Cap continuation after target year? | F87: Constant | G87: KeepRelativeCapConstant | H87: D_ETSCapCont | J87: Constant | K87: Constant
B88: ETS Start Year | F88: 2027 | G88: 2026 | H88: D_ETSIntro | J88: 2027 | K88: 2027
B89: ETS Target Year | F89: 2035 | G89: 2035 | H89: D_ETSOutro | J89: 2035 | K89: 2035
B90: Proportion Auctioned in Starting Year | F90: 0 | G90: 0 | H90: D_ETSAuctStart | J90: 0 | K90: 0
B91: Proportion Auctioned in Target Year | F91: 0 | G91: 1 | H91: D_ETSAuctTarget | J91: 0 | K91: 0
B92: Auction proportion continuation after target year? | F92: Constant | G92: Constant | H92: D_ETSAuctCont | J92: Constant | K92: Constant
B93: Override ETS price | F93: No | G93: No | H93: D_ETSPriceOverride | J93: No | K93: No
B94: ETS: modelling assumptions
B95: ETS Volatility | F95: Medium* | G95: Medium* | H95: D_ETSVolatility | J95: Medium* | K95: Medium*
B96: Impact of Volatility on Abatement Costs | F96: Medium* | G96: Medium* | H96: D_ETSVolImpact | J96: Medium* | K96: Medium*
B97: Carbon Tax Policy Risk | F97: 0.2 | G97: 0.2 | H97: D_ETSCTRisk | J97: 0.2 | K97: 0.2
B98: ETS: sector coverage
B99: power sector | C99: switch | F99: TRUE | G99: TRUE | J99: TRUE | K99: TRUE
B100: road transportation | F100: FALSE | G100: TRUE | J100: FALSE | K100: FALSE
B101: rail transportation | F101: FALSE | G101: TRUE | J101: FALSE | K101: FALSE
B102: domestic aviation | F102: FALSE | G102: TRUE | J102: FALSE | K102: FALSE
B103: domestic shipping | F103: FALSE | G103: TRUE | J103: FALSE | K103: FALSE
B104: residential | C104: switch | F104: FALSE | G104: TRUE | J104: FALSE | K104: FALSE
B105: food & forestry | F105: FALSE | G105: TRUE | J105: FALSE | K105: FALSE
...

Sheet Mitigation
A1: Variable | B1: Fuel | C1: Sector | D1: Param 1 | E1: Param 2 | F1: Param 3 | G1: Param 4 | H1: Description | I1: Unit | J1: Source | K1: Scenario 1: output code | AE1: Scenario 2: output code
A2: Mitigation module - price to fuel use (copy-pasteable, design 2, legacy CPAT sections)
A3: Scenario assumptions (one column group per scenario: code column + years; copy a whole group to add a scenario)
H4: Year | L4: =Settings!$C$7 | M4: =L4+1 | N4: =M4+1 | O4: =N4+1 | P4: =O4+1 | Q4: =P4+1 | R4: =Q4+1 | S4: =R4+1 | T4: =S4+1 | ... AD4: =AC4+1 | AF4: =Settings!$C$7 | AG4: =AF4+1 | AH4: =AG4+1 | AI4: =AH4+1 | AJ4: =AI4+1 | AK4: =AJ4+1 | AL4: =AK4+1 | AM4: =AL4+1 | AN4: =AM4+1 | ... AX4: =AW4+1
H5: Scenario number (MTInputs column) | K5: 1 | L5: =K5 | M5: =L5 | N5: =M5 | O5: =N5 | P5: =O5 | Q5: =P5 | R5: =Q5 | S5: =R5 | ... AD5: =AC5 | AE5: =K5+1 | AF5: =AE5 | AG5: =AF5 | AH5: =AG5 | AI5: =AH5 | AJ5: =AI5 | AK5: =AJ5 | AL5: =AK5 | AM5: =AL5 | ... AX5: =AW5
H6: Scenario name (from MTInputs) | L6: =INDEX(MTInputs!$J$6:$AZ$6,MATCH(L$5,MTInputs!$J$5:$AZ$5,0)) | AF6: =INDEX(MTInputs!$J$6:$AZ$6,MATCH(AF$5,MTInputs!$J$5:$AZ$5,0))
A7: gdp.pos.pct | H7: =INDEX(Variables!$B$5:$B$105,MATCH($A7,Variables!$A$5:$A$105,0))&IF($C7="",""," | "&INDEX(Mapping!$B$5:$B$26,MATCH($C7,Mapping!$A$5:$A$26,0))&" | "&INDEX(Mapping!$B$30:$B$41,MATCH($B7,Mapping!$A$30:$A$41,0))) | I7: =INDEX(Variables!$C$5:$C$105,MATCH($A7,Variables!$A$5:$A$105,0)) | J7: =INDEX(Variables!$E$5:$E$105,MATCH($A7,Variables!$A$5:$A$105,0)) | K7: =LOWER(Settings!$C$4)&".mit."&$A7&IF($C7="","","."&$C7&"."&$B7)&IF(INDEX(Variables!$D$5:$D$105,MATCH($A7,Variables!$A$5:$A$105,0))="","","."&INDEX(Variables!$D$5:$D$105,MATCH($A7,Variables!$A$5:$A$105,0)))&"."&K$5 | L7: =INDEX(WEO!$F$4:$AZ$1000,MATCH(Settings!$C$4&"|gdp_growth",WEO!$A$4:$A$1000,0),MATCH(L$4,WEO!$F$3:$AZ$3,0)) | M7: =INDEX(WEO!$F$4:$AZ$1000,MATCH(Settings!$C$4&"|gdp_growth",WEO!$A$4:$A$1000,0),MATCH(M$4,WEO!$F$3:$AZ$3,0)) | N7: =INDEX(WEO!$F$4:$AZ$1000,MATCH(Settings!$C$4&"|gdp_growth",WEO!$A$4:$A$1000,0),MATCH(N$4,WEO!$F$3:$AZ$3,0)) | O7: =INDEX(WEO!$F$4:$AZ$1000,MATCH(Settings!$C$4&"|gdp_growth",WEO!$A$4:$A$1000,0),MATCH(O$4,WEO!$F$3:$AZ$3,0)) | P7: =INDEX(WEO!$F$4:$AZ$1000,MATCH(Settings!$C$4&"|gdp_growth",WEO!$A$4:$A$1000,0),MATCH(P$4,WEO!$F$3:$AZ$3,0)) | Q7: =INDEX(WEO!$F$4:$AZ$1000,MATCH(Settings!$C$4&"|gdp_growth",WEO!$A$4:$A$1000,0),MATCH(Q$4,WEO!$F$3:$AZ$3,0)) | R7: =INDEX(WEO!$F$4:$AZ$1000,MATCH(Settings!$C$4&"|gdp_growth",WEO!$A$4:$A$1000,0),MATCH(R$4,WEO!$F$3:$AZ$3,0)) | S7: =INDEX(WEO!$F$4:$AZ$1000,MATCH(Settings!$C$4&"|gdp_growth",WEO!$A$4:$A$1000,0),MATCH(S$4,WEO!$F$3:$AZ$3,0)) | ... AD7: =INDEX(WEO!$F$4:$AZ$1000,MATCH(Settings!$C$4&"|gdp_growth",WEO!$A$4:$A$1000,0),MATCH(AD$4,WEO!$F$3:$AZ$3,0)) | AE7: =LOWER(Settings!$C$4)&".mit."&$A7&IF($C7="","","."&$C7&"."&$B7)&IF(INDEX(Variables!$D$5:$D$105,MATCH($A7,Variables!$A$5:$A$105,0))="","","."&INDEX(Variables!$D$5:$D$105,MATCH($A7,Variables!$A$5:$A$105,0)))&"."&AE$5 | AF7: =INDEX(WEO!$F$4:$AZ$1000,MATCH(Settings!$C$4&"|gdp_growth",WEO!$A$4:$A$1000,0),MATCH(AF$4,WEO!$F$3:$AZ$3,0)) | AG7: =INDEX(WEO!$F$4:$AZ$1000,MATCH(Settings!$C$4&"|gdp_growth",WEO!$A$4:$A$1000,0),MATCH(AG$4,WEO!$F$3:$AZ$3,0)) | AH7: =INDEX(WEO!$F$4:$AZ$1000,MATCH(Settings!$C$4&"|gdp_growth",WEO!$A$4:$A$1000,0),MATCH(AH$4,WEO!$F$3:$AZ$3,0)) | AI7: =INDEX(WEO!$F$4:$AZ$1000,MATCH(Settings!$C$4&"|gdp_growth",WEO!$A$4:$A$1000,0),MATCH(AI$4,WEO!$F$3:$AZ$3,0)) | AJ7: =INDEX(WEO!$F$4:$AZ$1000,MATCH(Settings!$C$4&"|gdp_growth",WEO!$A$4:$A$1000,0),MATCH(AJ$4,WEO!$F$3:$AZ$3,0)) | AK7: =INDEX(WEO!$F$4:$AZ$1000,MATCH(Settings!$C$4&"|gdp_growth",WEO!$A$4:$A$1000,0),MATCH(AK$4,WEO!$F$3:$AZ$3,0)) | AL7: =INDEX(WEO!$F$4:$AZ$1000,MATCH(Settings!$C$4&"|gdp_growth",WEO!$A$4:$A$1000,0),MATCH(AL$4,WEO!$F$3:$AZ$3,0)) | AM7: =INDEX(WEO!$F$4:$AZ$1000,MATCH(Settings!$C$4&"|gdp_growth",WEO!$A$4:$A$1000,0),MATCH(AM$4,WEO!$F$3:$AZ$3,0)) | ... AX7: =INDEX(WEO!$F$4:$AZ$1000,MATCH(Settings!$C$4&"|gdp_growth",WEO!$A$4:$A$1000,0),MATCH(AX$4,WEO!$F$3:$AZ$3,0))
A8: infl | H8: =INDEX(Variables!$B$5:$B$105,MATCH($A8,Variables!$A$5:$A$105,0))&IF($C8="",""," | "&INDEX(Mapping!$B$5:$B$26,MATCH($C8,Mapping!$A$5:$A$26,0))&" | "&INDEX(Mapping!$B$30:$B$41,MATCH($B8,Mapping!$A$30:$A$41,0))) | I8: =INDEX(Variables!$C$5:$C$105,MATCH($A8,Variables!$A$5:$A$105,0)) | J8: =INDEX(Variables!$E$5:$E$105,MATCH($A8,Variables!$A$5:$A$105,0)) | K8: =LOWER(Settings!$C$4)&".mit."&$A8&IF($C8="","","."&$C8&"."&$B8)&IF(INDEX(Variables!$D$5:$D$105,MATCH($A8,Variables!$A$5:$A$105,0))="","","."&INDEX(Variables!$D$5:$D$105,MATCH($A8,Variables!$A$5:$A$105,0)))&"."&K$5 | L8: =INDEX(WEO!$F$4:$AZ$1000,MATCH("USA|pcpi",WEO!$A$4:$A$1000,0),MATCH(Settings!$C$8,WEO!$F$3:$AZ$3,0))/INDEX(WEO!$F$4:$AZ$1000,MATCH("USA|pcpi",WEO!$A$4:$A$1000,0),MATCH(L$4,WEO!$F$3:$AZ$3,0)) | M8: =INDEX(WEO!$F$4:$AZ$1000,MATCH("USA|pcpi",WEO!$A$4:$A$1000,0),MATCH(Settings!$C$8,WEO!$F$3:$AZ$3,0))/INDEX(WEO!$F$4:$AZ$1000,MATCH("USA|pcpi",WEO!$A$4:$A$1000,0),MATCH(M$4,WEO!$F$3:$AZ$3,0)) | N8: =INDEX(WEO!$F$4:$AZ$1000,MATCH("USA|pcpi",WEO!$A$4:$A$1000,0),MATCH(Settings!$C$8,WEO!$F$3:$AZ$3,0))/INDEX(WEO!$F$4:$AZ$1000,MATCH("USA|pcpi",WEO!$A$4:$A$1000,0),MATCH(N$4,WEO!$F$3:$AZ$3,0)) | O8: =INDEX(WEO!$F$4:$AZ$1000,MATCH("USA|pcpi",WEO!$A$4:$A$1000,0),MATCH(Settings!$C$8,WEO!$F$3:$AZ$3,0))/INDEX(WEO!$F$4:$AZ$1000,MATCH("USA|pcpi",WEO!$A$4:$A$1000,0),MATCH(O$4,WEO!$F$3:$AZ$3,0)) | P8: =INDEX(WEO!$F$4:$AZ$1000,MATCH("USA|pcpi",WEO!$A$4:$A$1000,0),MATCH(Settings!$C$8,WEO!$F$3:$AZ$3,0))/INDEX(WEO!$F$4:$AZ$1000,MATCH("USA|pcpi",WEO!$A$4:$A$1000,0),MATCH(P$4,WEO!$F$3:$AZ$3,0)) | Q8: =INDEX(WEO!$F$4:$AZ$1000,MATCH("USA|pcpi",WEO!$A$4:$A$1000,0),MATCH(Settings!$C$8,WEO!$F$3:$AZ$3,0))/INDEX(WEO!$F$4:$AZ$1000,MATCH("USA|pcpi",WEO!$A$4:$A$1000,0),MATCH(Q$4,WEO!$F$3:$AZ$3,0)) | R8: =INDEX(WEO!$F$4:$AZ$1000,MATCH("USA|pcpi",WEO!$A$4:$A$1000,0),MATCH(Settings!$C$8,WEO!$F$3:$AZ$3,0))/INDEX(WEO!$F$4:$AZ$1000,MATCH("USA|pcpi",WEO!$A$4:$A$1000,0),MATCH(R$4,WEO!$F$3:$AZ$3,0)) | S8: =INDEX(WEO!$F$4:$AZ$1000,MATCH("USA|pcpi",WEO!$A$4:$A$1000,0),MATCH(Settings!$C$8,WEO!$F$3:$AZ$3,0))/INDEX(WEO!$F$4:$AZ$1000,MATCH("USA|pcpi",WEO!$A$4:$A$1000,0),MATCH(S$4,WEO!$F$3:$AZ$3,0)) | ... AD8: =INDEX(WEO!$F$4:$AZ$1000,MATCH("USA|pcpi",WEO!$A$4:$A$1000,0),MATCH(Settings!$C$8,WEO!$F$3:$AZ$3,0))/INDEX(WEO!$F$4:$AZ$1000,MATCH("USA|pcpi",WEO!$A$4:$A$1000,0),MATCH(AD$4,WEO!$F$3:$AZ$3,0)) | AE8: =LOWER(Settings!$C$4)&".mit."&$A8&IF($C8="","","."&$C8&"."&$B8)&IF(INDEX(Variables!$D$5:$D$105,MATCH($A8,Variables!$A$5:$A$105,0))="","","."&INDEX(Variables!$D$5:$D$105,MATCH($A8,Variables!$A$5:$A$105,0)))&"."&AE$5 | AF8: =INDEX(WEO!$F$4:$AZ$1000,MATCH("USA|pcpi",WEO!$A$4:$A$1000,0),MATCH(Settings!$C$8,WEO!$F$3:$AZ$3,0))/INDEX(WEO!$F$4:$AZ$1000,MATCH("USA|pcpi",WEO!$A$4:$A$1000,0),MATCH(AF$4,WEO!$F$3:$AZ$3,0)) | AG8: =INDEX(WEO!$F$4:$AZ$1000,MATCH("USA|pcpi",WEO!$A$4:$A$1000,0),MATCH(Settings!$C$8,WEO!$F$3:$AZ$3,0))/INDEX(WEO!$F$4:$AZ$1000,MATCH("USA|pcpi",WEO!$A$4:$A$1000,0),MATCH(AG$4,WEO!$F$3:$AZ$3,0)) | AH8: =INDEX(WEO!$F$4:$AZ$1000,MATCH("USA|pcpi",WEO!$A$4:$A$1000,0),MATCH(Settings!$C$8,WEO!$F$3:$AZ$3,0))/INDEX(WEO!$F$4:$AZ$1000,MATCH("USA|pcpi",WEO!$A$4:$A$1000,0),MATCH(AH$4,WEO!$F$3:$AZ$3,0)) | AI8: =INDEX(WEO!$F$4:$AZ$1000,MATCH("USA|pcpi",WEO!$A$4:$A$1000,0),MATCH(Settings!$C$8,WEO!$F$3:$AZ$3,0))/INDEX(WEO!$F$4:$AZ$1000,MATCH("USA|pcpi",WEO!$A$4:$A$1000,0),MATCH(AI$4,WEO!$F$3:$AZ$3,0)) | AJ8: =INDEX(WEO!$F$4:$AZ$1000,MATCH("USA|pcpi",WEO!$A$4:$A$1000,0),MATCH(Settings!$C$8,WEO!$F$3:$AZ$3,0))/INDEX(WEO!$F$4:$AZ$1000,MATCH("USA|pcpi",WEO!$A$4:$A$1000,0),MATCH(AJ$4,WEO!$F$3:$AZ$3,0)) | AK8: =INDEX(WEO!$F$4:$AZ$1000,MATCH("USA|pcpi",WEO!$A$4:$A$1000,0),MATCH(Settings!$C$8,WEO!$F$3:$AZ$3,0))/INDEX(WEO!$F$4:$AZ$1000,MATCH("USA|pcpi",WEO!$A$4:$A$1000,0),MATCH(AK$4,WEO!$F$3:$AZ$3,0)) | AL8: =INDEX(WEO!$F$4:$AZ$1000,MATCH("USA|pcpi",WEO!$A$4:$A$1000,0),MATCH(Settings!$C$8,WEO!$F$3:$AZ$3,0))/INDEX(WEO!$F$4:$AZ$1000,MATCH("USA|pcpi",WEO!$A$4:$A$1000,0),MATCH(AL$4,WEO!$F$3:$AZ$3,0)) | AM8: =INDEX(WEO!$F$4:$AZ$1000,MATCH("USA|pcpi",WEO!$A$4:$A$1000,0),MATCH(Settings!$C$8,WEO!$F$3:$AZ$3,0))/INDEX(WEO!$F$4:$AZ$1000,MATCH("USA|pcpi",WEO!$A$4:$A$1000,0),MATCH(AM$4,WEO!$F$3:$AZ$3,0)) | ... AX8: =INDEX(WEO!$F$4:$AZ$1000,MATCH("USA|pcpi",WEO!$A$4:$A$1000,0),MATCH(Settings!$C$8,WEO!$F$3:$AZ$3,0))/INDEX(WEO!$F$4:$AZ$1000,MATCH("USA|pcpi",WEO!$A$4:$A$1000,0),MATCH(AX$4,WEO!$F$3:$AZ$3,0))
A9: defl | H9: =INDEX(Variables!$B$5:$B$105,MATCH($A9,Variables!$A$5:$A$105,0))&IF($C9="",""," | "&INDEX(Mapping!$B$5:$B$26,MATCH($C9,Mapping!$A$5:$A$26,0))&" | "&INDEX(Mapping!$B$30:$B$41,MATCH($B9,Mapping!$A$30:$A$41,0))) | I9: =INDEX(Variables!$C$5:$C$105,MATCH($A9,Variables!$A$5:$A$105,0)) | J9: =INDEX(Variables!$E$5:$E$105,MATCH($A9,Variables!$A$5:$A$105,0)) | K9: =LOWER(Settings!$C$4)&".mit."&$A9&IF($C9="","","."&$C9&"."&$B9)&IF(INDEX(Variables!$D$5:$D$105,MATCH($A9,Variables!$A$5:$A$105,0))="","","."&INDEX(Variables!$D$5:$D$105,MATCH($A9,Variables!$A$5:$A$105,0)))&"."&K$5 | L9: =INDEX(WEO!$F$4:$AZ$1000,MATCH("USA|ngdp_d",WEO!$A$4:$A$1000,0),MATCH(Settings!$C$8,WEO!$F$3:$AZ$3,0))/INDEX(WEO!$F$4:$AZ$1000,MATCH("USA|ngdp_d",WEO!$A$4:$A$1000,0),MATCH(L$4,WEO!$F$3:$AZ$3,0)) | M9: =INDEX(WEO!$F$4:$AZ$1000,MATCH("USA|ngdp_d",WEO!$A$4:$A$1000,0),MATCH(Settings!$C$8,WEO!$F$3:$AZ$3,0))/INDEX(WEO!$F$4:$AZ$1000,MATCH("USA|ngdp_d",WEO!$A$4:$A$1000,0),MATCH(M$4,WEO!$F$3:$AZ$3,0)) | N9: =INDEX(WEO!$F$4:$AZ$1000,MATCH("USA|ngdp_d",WEO!$A$4:$A$1000,0),MATCH(Settings!$C$8,WEO!$F$3:$AZ$3,0))/INDEX(WEO!$F$4:$AZ$1000,MATCH("USA|ngdp_d",WEO!$A$4:$A$1000,0),MATCH(N$4,WEO!$F$3:$AZ$3,0)) | O9: =INDEX(WEO!$F$4:$AZ$1000,MATCH("USA|ngdp_d",WEO!$A$4:$A$1000,0),MATCH(Settings!$C$8,WEO!$F$3:$AZ$3,0))/INDEX(WEO!$F$4:$AZ$1000,MATCH("USA|ngdp_d",WEO!$A$4:$A$1000,0),MATCH(O$4,WEO!$F$3:$AZ$3,0)) | P9: =INDEX(WEO!$F$4:$AZ$1000,MATCH("USA|ngdp_d",WEO!$A$4:$A$1000,0),MATCH(Settings!$C$8,WEO!$F$3:$AZ$3,0))/INDEX(WEO!$F$4:$AZ$1000,MATCH("USA|ngdp_d",WEO!$A$4:$A$1000,0),MATCH(P$4,WEO!$F$3:$AZ$3,0)) | Q9: =INDEX(WEO!$F$4:$AZ$1000,MATCH("USA|ngdp_d",WEO!$A$4:$A$1000,0),MATCH(Settings!$C$8,WEO!$F$3:$AZ$3,0))/INDEX(WEO!$F$4:$AZ$1000,MATCH("USA|ngdp_d",WEO!$A$4:$A$1000,0),MATCH(Q$4,WEO!$F$3:$AZ$3,0)) | R9: =INDEX(WEO!$F$4:$AZ$1000,MATCH("USA|ngdp_d",WEO!$A$4:$A$1000,0),MATCH(Settings!$C$8,WEO!$F$3:$AZ$3,0))/INDEX(WEO!$F$4:$AZ$1000,MATCH("USA|ngdp_d",WEO!$A$4:$A$1000,0),MATCH(R$4,WEO!$F$3:$AZ$3,0)) | S9: =INDEX(WEO!$F$4:$AZ$1000,MATCH("USA|ngdp_d",WEO!$A$4:$A$1000,0),MATCH(Settings!$C$8,WEO!$F$3:$AZ$3,0))/INDEX(WEO!$F$4:$AZ$1000,MATCH("USA|ngdp_d",WEO!$A$4:$A$1000,0),MATCH(S$4,WEO!$F$3:$AZ$3,0)) | ... AD9: =INDEX(WEO!$F$4:$AZ$1000,MATCH("USA|ngdp_d",WEO!$A$4:$A$1000,0),MATCH(Settings!$C$8,WEO!$F$3:$AZ$3,0))/INDEX(WEO!$F$4:$AZ$1000,MATCH("USA|ngdp_d",WEO!$A$4:$A$1000,0),MATCH(AD$4,WEO!$F$3:$AZ$3,0)) | AE9: =LOWER(Settings!$C$4)&".mit."&$A9&IF($C9="","","."&$C9&"."&$B9)&IF(INDEX(Variables!$D$5:$D$105,MATCH($A9,Variables!$A$5:$A$105,0))="","","."&INDEX(Variables!$D$5:$D$105,MATCH($A9,Variables!$A$5:$A$105,0)))&"."&AE$5 | AF9: =INDEX(WEO!$F$4:$AZ$1000,MATCH("USA|ngdp_d",WEO!$A$4:$A$1000,0),MATCH(Settings!$C$8,WEO!$F$3:$AZ$3,0))/INDEX(WEO!$F$4:$AZ$1000,MATCH("USA|ngdp_d",WEO!$A$4:$A$1000,0),MATCH(AF$4,WEO!$F$3:$AZ$3,0)) | AG9: =INDEX(WEO!$F$4:$AZ$1000,MATCH("USA|ngdp_d",WEO!$A$4:$A$1000,0),MATCH(Settings!$C$8,WEO!$F$3:$AZ$3,0))/INDEX(WEO!$F$4:$AZ$1000,MATCH("USA|ngdp_d",WEO!$A$4:$A$1000,0),MATCH(AG$4,WEO!$F$3:$AZ$3,0)) | AH9: =INDEX(WEO!$F$4:$AZ$1000,MATCH("USA|ngdp_d",WEO!$A$4:$A$1000,0),MATCH(Settings!$C$8,WEO!$F$3:$AZ$3,0))/INDEX(WEO!$F$4:$AZ$1000,MATCH("USA|ngdp_d",WEO!$A$4:$A$1000,0),MATCH(AH$4,WEO!$F$3:$AZ$3,0)) | AI9: =INDEX(WEO!$F$4:$AZ$1000,MATCH("USA|ngdp_d",WEO!$A$4:$A$1000,0),MATCH(Settings!$C$8,WEO!$F$3:$AZ$3,0))/INDEX(WEO!$F$4:$AZ$1000,MATCH("USA|ngdp_d",WEO!$A$4:$A$1000,0),MATCH(AI$4,WEO!$F$3:$AZ$3,0)) | AJ9: =INDEX(WEO!$F$4:$AZ$1000,MATCH("USA|ngdp_d",WEO!$A$4:$A$1000,0),MATCH(Settings!$C$8,WEO!$F$3:$AZ$3,0))/INDEX(WEO!$F$4:$AZ$1000,MATCH("USA|ngdp_d",WEO!$A$4:$A$1000,0),MATCH(AJ$4,WEO!$F$3:$AZ$3,0)) | AK9: =INDEX(WEO!$F$4:$AZ$1000,MATCH("USA|ngdp_d",WEO!$A$4:$A$1000,0),MATCH(Settings!$C$8,WEO!$F$3:$AZ$3,0))/INDEX(WEO!$F$4:$AZ$1000,MATCH("USA|ngdp_d",WEO!$A$4:$A$1000,0),MATCH(AK$4,WEO!$F$3:$AZ$3,0)) | AL9: =INDEX(WEO!$F$4:$AZ$1000,MATCH("USA|ngdp_d",WEO!$A$4:$A$1000,0),MATCH(Settings!$C$8,WEO!$F$3:$AZ$3,0))/INDEX(WEO!$F$4:$AZ$1000,MATCH("USA|ngdp_d",WEO!$A$4:$A$1000,0),MATCH(AL$4,WEO!$F$3:$AZ$3,0)) | AM9: =INDEX(WEO!$F$4:$AZ$1000,MATCH("USA|ngdp_d",WEO!$A$4:$A$1000,0),MATCH(Settings!$C$8,WEO!$F$3:$AZ$3,0))/INDEX(WEO!$F$4:$AZ$1000,MATCH("USA|ngdp_d",WEO!$A$4:$A$1000,0),MATCH(AM$4,WEO!$F$3:$AZ$3,0)) | ... AX9: =INDEX(WEO!$F$4:$AZ$1000,MATCH("USA|ngdp_d",WEO!$A$4:$A$1000,0),MATCH(Settings!$C$8,WEO!$F$3:$AZ$3,0))/INDEX(WEO!$F$4:$AZ$1000,MATCH("USA|ngdp_d",WEO!$A$4:$A$1000,0),MATCH(AX$4,WEO!$F$3:$AZ$3,0))
A11: 1. Policies (scenario inputs from MTInputs by row and scenario number; policy paths) | D11: MTInputs row
A12: cptraj | H12: =INDEX(Variables!$B$5:$B$105,MATCH($A12,Variables!$A$5:$A$105,0))&IF($C12="",""," | "&INDEX(Mapping!$B$5:$B$26,MATCH($C12,Mapping!$A$5:$A$26,0))&" | "&INDEX(Mapping!$B$30:$B$41,MATCH($B12,Mapping!$A$30:$A$41,0))) | I12: =INDEX(Variables!$C$5:$C$105,MATCH($A12,Variables!$A$5:$A$105,0)) | J12: =INDEX(Variables!$E$5:$E$105,MATCH($A12,Variables!$A$5:$A$105,0)) | K12: =LOWER(Settings!$C$4)&".mit."&$A12&IF($C12="","","."&$C12&"."&$B12)&IF(INDEX(Variables!$D$5:$D$105,MATCH($A12,Variables!$A$5:$A$105,0))="","","."&INDEX(Variables!$D$5:$D$105,MATCH($A12,Variables!$A$5:$A$105,0)))&"."&K$5 | L12: =(IF(L$4<L$14,0,L$15+(L$16-L$15)/MAX(L$17-L$14,1)*IF(OR(L$4<=L$17,L$18="Linear*"),L$4-L$14,L$17-L$14)))*IF(LEFT(L$19,7)="Nominal",L$8,1) | M12: =(IF(M$4<M$14,0,M$15+(M$16-M$15)/MAX(M$17-M$14,1)*IF(OR(M$4<=M$17,M$18="Linear*"),M$4-M$14,M$17-M$14)))*IF(LEFT(M$19,7)="Nominal",M$8,1) | N12: =(IF(N$4<N$14,0,N$15+(N$16-N$15)/MAX(N$17-N$14,1)*IF(OR(N$4<=N$17,N$18="Linear*"),N$4-N$14,N$17-N$14)))*IF(LEFT(N$19,7)="Nominal",N$8,1) | O12: =(IF(O$4<O$14,0,O$15+(O$16-O$15)/MAX(O$17-O$14,1)*IF(OR(O$4<=O$17,O$18="Linear*"),O$4-O$14,O$17-O$14)))*IF(LEFT(O$19,7)="Nominal",O$8,1) | P12: =(IF(P$4<P$14,0,P$15+(P$16-P$15)/MAX(P$17-P$14,1)*IF(OR(P$4<=P$17,P$18="Linear*"),P$4-P$14,P$17-P$14)))*IF(LEFT(P$19,7)="Nominal",P$8,1) | Q12: =(IF(Q$4<Q$14,0,Q$15+(Q$16-Q$15)/MAX(Q$17-Q$14,1)*IF(OR(Q$4<=Q$17,Q$18="Linear*"),Q$4-Q$14,Q$17-Q$14)))*IF(LEFT(Q$19,7)="Nominal",Q$8,1) | R12: =(IF(R$4<R$14,0,R$15+(R$16-R$15)/MAX(R$17-R$14,1)*IF(OR(R$4<=R$17,R$18="Linear*"),R$4-R$14,R$17-R$14)))*IF(LEFT(R$19,7)="Nominal",R$8,1) | S12: =(IF(S$4<S$14,0,S$15+(S$16-S$15)/MAX(S$17-S$14,1)*IF(OR(S$4<=S$17,S$18="Linear*"),S$4-S$14,S$17-S$14)))*IF(LEFT(S$19,7)="Nominal",S$8,1) | ... AC12: =(IF(AC$4<AC$14,0,AC$15+(AC$16-AC$15)/MAX(AC$17-AC$14,1)*IF(OR(AC$4<=AC$17,AC$18="Linear*"),AC$4-AC$14,AC$17-AC$14)))*IF(LEFT(AC$19,7)="Nominal",AC$8,1) | AD12: =PATH(AD$4,AD$14,AD$17,AD$15,AD$16,AD$18="Linear*")*IF(LEFT(AD$19,7)="Nominal",AD$8,1) | AE12: =LOWER(Settings!$C$4)&".mit."&$A12&IF($C12="","","."&$C12&"."&$B12)&IF(INDEX(Variables!$D$5:$D$105,MATCH($A12,Variables!$A$5:$A$105,0))="","","."&INDEX(Variables!$D$5:$D$105,MATCH($A12,Variables!$A$5:$A$105,0)))&"."&AE$5 | AF12: =(IF(AF$4<AF$14,0,AF$15+(AF$16-AF$15)/MAX(AF$17-AF$14,1)*IF(OR(AF$4<=AF$17,AF$18="Linear*"),AF$4-AF$14,AF$17-AF$14)))*IF(LEFT(AF$19,7)="Nominal",AF$8,1) | AG12: =(IF(AG$4<AG$14,0,AG$15+(AG$16-AG$15)/MAX(AG$17-AG$14,1)*IF(OR(AG$4<=AG$17,AG$18="Linear*"),AG$4-AG$14,AG$17-AG$14)))*IF(LEFT(AG$19,7)="Nominal",AG$8,1) | AH12: =(IF(AH$4<AH$14,0,AH$15+(AH$16-AH$15)/MAX(AH$17-AH$14,1)*IF(OR(AH$4<=AH$17,AH$18="Linear*"),AH$4-AH$14,AH$17-AH$14)))*IF(LEFT(AH$19,7)="Nominal",AH$8,1) | AI12: =(IF(AI$4<AI$14,0,AI$15+(AI$16-AI$15)/MAX(AI$17-AI$14,1)*IF(OR(AI$4<=AI$17,AI$18="Linear*"),AI$4-AI$14,AI$17-AI$14)))*IF(LEFT(AI$19,7)="Nominal",AI$8,1) | AJ12: =(IF(AJ$4<AJ$14,0,AJ$15+(AJ$16-AJ$15)/MAX(AJ$17-AJ$14,1)*IF(OR(AJ$4<=AJ$17,AJ$18="Linear*"),AJ$4-AJ$14,AJ$17-AJ$14)))*IF(LEFT(AJ$19,7)="Nominal",AJ$8,1) | AK12: =(IF(AK$4<AK$14,0,AK$15+(AK$16-AK$15)/MAX(AK$17-AK$14,1)*IF(OR(AK$4<=AK$17,AK$18="Linear*"),AK$4-AK$14,AK$17-AK$14)))*IF(LEFT(AK$19,7)="Nominal",AK$8,1) | AL12: =(IF(AL$4<AL$14,0,AL$15+(AL$16-AL$15)/MAX(AL$17-AL$14,1)*IF(OR(AL$4<=AL$17,AL$18="Linear*"),AL$4-AL$14,AL$17-AL$14)))*IF(LEFT(AL$19,7)="Nominal",AL$8,1) | AM12: =(IF(AM$4<AM$14,0,AM$15+(AM$16-AM$15)/MAX(AM$17-AM$14,1)*IF(OR(AM$4<=AM$17,AM$18="Linear*"),AM$4-AM$14,AM$17-AM$14)))*IF(LEFT(AM$19,7)="Nominal",AM$8,1) | ... AW12: =(IF(AW$4<AW$14,0,AW$15+(AW$16-AW$15)/MAX(AW$17-AW$14,1)*IF(OR(AW$4<=AW$17,AW$18="Linear*"),AW$4-AW$14,AW$17-AW$14)))*IF(LEFT(AW$19,7)="Nominal",AW$8,1) | AX12: =PATH(AX$4,AX$14,AX$17,AX$15,AX$16,AX$18="Linear*")*IF(LEFT(AX$19,7)="Nominal",AX$8,1)
H13: Carbon tax (MTInputs rows 18-21, 265, 266)
A14: CPIntro | D14: 18 | H14: =INDEX(Variables!$B$5:$B$105,MATCH($A14,Variables!$A$5:$A$105,0))&IF($C14="",""," | "&INDEX(Mapping!$B$5:$B$26,MATCH($C14,Mapping!$A$5:$A$26,0))&" | "&INDEX(Mapping!$B$30:$B$41,MATCH($B14,Mapping!$A$30:$A$41,0))) | I14: =INDEX(Variables!$C$5:$C$105,MATCH($A14,Variables!$A$5:$A$105,0)) | J14: =INDEX(Variables!$E$5:$E$105,MATCH($A14,Variables!$A$5:$A$105,0)) | K14: =LOWER(Settings!$C$4)&".mit."&$A14&IF($C14="","","."&$C14&"."&$B14)&IF(INDEX(Variables!$D$5:$D$105,MATCH($A14,Variables!$A$5:$A$105,0))="","","."&INDEX(Variables!$D$5:$D$105,MATCH($A14,Variables!$A$5:$A$105,0)))&"."&K$5 | L14: =INDEX(MTInputs!$J$1:$AZ$415,$D14,MATCH(L$5,MTInputs!$J$5:$AZ$5,0)) | M14: =INDEX(MTInputs!$J$1:$AZ$415,$D14,MATCH(M$5,MTInputs!$J$5:$AZ$5,0)) | N14: =INDEX(MTInputs!$J$1:$AZ$415,$D14,MATCH(N$5,MTInputs!$J$5:$AZ$5,0)) | O14: =INDEX(MTInputs!$J$1:$AZ$415,$D14,MATCH(O$5,MTInputs!$J$5:$AZ$5,0)) | P14: =INDEX(MTInputs!$J$1:$AZ$415,$D14,MATCH(P$5,MTInputs!$J$5:$AZ$5,0)) | Q14: =INDEX(MTInputs!$J$1:$AZ$415,$D14,MATCH(Q$5,MTInputs!$J$5:$AZ$5,0)) | R14: =INDEX(MTInputs!$J$1:$AZ$415,$D14,MATCH(R$5,MTInputs!$J$5:$AZ$5,0)) | S14: =INDEX(MTInputs!$J$1:$AZ$415,$D14,MATCH(S$5,MTInputs!$J$5:$AZ$5,0)) | ... AD14: =INDEX(MTInputs!$J$1:$AZ$415,$D14,MATCH(AD$5,MTInputs!$J$5:$AZ$5,0)) | AE14: =LOWER(Settings!$C$4)&".mit."&$A14&IF($C14="","","."&$C14&"."&$B14)&IF(INDEX(Variables!$D$5:$D$105,MATCH($A14,Variables!$A$5:$A$105,0))="","","."&INDEX(Variables!$D$5:$D$105,MATCH($A14,Variables!$A$5:$A$105,0)))&"."&AE$5 | AF14: =INDEX(MTInputs!$J$1:$AZ$415,$D14,MATCH(AF$5,MTInputs!$J$5:$AZ$5,0)) | AG14: =INDEX(MTInputs!$J$1:$AZ$415,$D14,MATCH(AG$5,MTInputs!$J$5:$AZ$5,0)) | AH14: =INDEX(MTInputs!$J$1:$AZ$415,$D14,MATCH(AH$5,MTInputs!$J$5:$AZ$5,0)) | AI14: =INDEX(MTInputs!$J$1:$AZ$415,$D14,MATCH(AI$5,MTInputs!$J$5:$AZ$5,0)) | AJ14: =INDEX(MTInputs!$J$1:$AZ$415,$D14,MATCH(AJ$5,MTInputs!$J$5:$AZ$5,0)) | AK14: =INDEX(MTInputs!$J$1:$AZ$415,$D14,MATCH(AK$5,MTInputs!$J$5:$AZ$5,0)) | AL14: =INDEX(MTInputs!$J$1:$AZ$415,$D14,MATCH(AL$5,MTInputs!$J$5:$AZ$5,0)) | AM14: =INDEX(MTInputs!$J$1:$AZ$415,$D14,MATCH(AM$5,MTInputs!$J$5:$AZ$5,0)) | ... AX14: =INDEX(MTInputs!$J$1:$AZ$415,$D14,MATCH(AX$5,MTInputs!$J$5:$AZ$5,0))
A15: CPLevelStart | D15: 19 | H15: =INDEX(Variables!$B$5:$B$105,MATCH($A15,Variables!$A$5:$A$105,0))&IF($C15="",""," | "&INDEX(Mapping!$B$5:$B$26,MATCH($C15,Mapping!$A$5:$A$26,0))&" | "&INDEX(Mapping!$B$30:$B$41,MATCH($B15,Mapping!$A$30:$A$41,0))) | I15: =INDEX(Variables!$C$5:$C$105,MATCH($A15,Variables!$A$5:$A$105,0)) | J15: =INDEX(Variables!$E$5:$E$105,MATCH($A15,Variables!$A$5:$A$105,0)) | K15: =LOWER(Settings!$C$4)&".mit."&$A15&IF($C15="","","."&$C15&"."&$B15)&IF(INDEX(Variables!$D$5:$D$105,MATCH($A15,Variables!$A$5:$A$105,0))="","","."&INDEX(Variables!$D$5:$D$105,MATCH($A15,Variables!$A$5:$A$105,0)))&"."&K$5 | L15: =INDEX(MTInputs!$J$1:$AZ$415,$D15,MATCH(L$5,MTInputs!$J$5:$AZ$5,0)) | M15: =INDEX(MTInputs!$J$1:$AZ$415,$D15,MATCH(M$5,MTInputs!$J$5:$AZ$5,0)) | N15: =INDEX(MTInputs!$J$1:$AZ$415,$D15,MATCH(N$5,MTInputs!$J$5:$AZ$5,0)) | O15: =INDEX(MTInputs!$J$1:$AZ$415,$D15,MATCH(O$5,MTInputs!$J$5:$AZ$5,0)) | P15: =INDEX(MTInputs!$J$1:$AZ$415,$D15,MATCH(P$5,MTInputs!$J$5:$AZ$5,0)) | Q15: =INDEX(MTInputs!$J$1:$AZ$415,$D15,MATCH(Q$5,MTInputs!$J$5:$AZ$5,0)) | R15: =INDEX(MTInputs!$J$1:$AZ$415,$D15,MATCH(R$5,MTInputs!$J$5:$AZ$5,0)) | S15: =INDEX(MTInputs!$J$1:$AZ$415,$D15,MATCH(S$5,MTInputs!$J$5:$AZ$5,0)) | ... AD15: =INDEX(MTInputs!$J$1:$AZ$415,$D15,MATCH(AD$5,MTInputs!$J$5:$AZ$5,0)) | AE15: =LOWER(Settings!$C$4)&".mit."&$A15&IF($C15="","","."&$C15&"."&$B15)&IF(INDEX(Variables!$D$5:$D$105,MATCH($A15,Variables!$A$5:$A$105,0))="","","."&INDEX(Variables!$D$5:$D$105,MATCH($A15,Variables!$A$5:$A$105,0)))&"."&AE$5 | AF15: =INDEX(MTInputs!$J$1:$AZ$415,$D15,MATCH(AF$5,MTInputs!$J$5:$AZ$5,0)) | AG15: =INDEX(MTInputs!$J$1:$AZ$415,$D15,MATCH(AG$5,MTInputs!$J$5:$AZ$5,0)) | AH15: =INDEX(MTInputs!$J$1:$AZ$415,$D15,MATCH(AH$5,MTInputs!$J$5:$AZ$5,0)) | AI15: =INDEX(MTInputs!$J$1:$AZ$415,$D15,MATCH(AI$5,MTInputs!$J$5:$AZ$5,0)) | AJ15: =INDEX(MTInputs!$J$1:$AZ$415,$D15,MATCH(AJ$5,MTInputs!$J$5:$AZ$5,0)) | AK15: =INDEX(MTInputs!$J$1:$AZ$415,$D15,MATCH(AK$5,MTInputs!$J$5:$AZ$5,0)) | AL15: =INDEX(MTInputs!$J$1:$AZ$415,$D15,MATCH(AL$5,MTInputs!$J$5:$AZ$5,0)) | AM15: =INDEX(MTInputs!$J$1:$AZ$415,$D15,MATCH(AM$5,MTInputs!$J$5:$AZ$5,0)) | ... AX15: =INDEX(MTInputs!$J$1:$AZ$415,$D15,MATCH(AX$5,MTInputs!$J$5:$AZ$5,0))
A16: CPLevelTarget | D16: 20 | H16: =INDEX(Variables!$B$5:$B$105,MATCH($A16,Variables!$A$5:$A$105,0))&IF($C16="",""," | "&INDEX(Mapping!$B$5:$B$26,MATCH($C16,Mapping!$A$5:$A$26,0))&" | "&INDEX(Mapping!$B$30:$B$41,MATCH($B16,Mapping!$A$30:$A$41,0))) | I16: =INDEX(Variables!$C$5:$C$105,MATCH($A16,Variables!$A$5:$A$105,0)) | J16: =INDEX(Variables!$E$5:$E$105,MATCH($A16,Variables!$A$5:$A$105,0)) | K16: =LOWER(Settings!$C$4)&".mit."&$A16&IF($C16="","","."&$C16&"."&$B16)&IF(INDEX(Variables!$D$5:$D$105,MATCH($A16,Variables!$A$5:$A$105,0))="","","."&INDEX(Variables!$D$5:$D$105,MATCH($A16,Variables!$A$5:$A$105,0)))&"."&K$5 | L16: =INDEX(MTInputs!$J$1:$AZ$415,$D16,MATCH(L$5,MTInputs!$J$5:$AZ$5,0)) | M16: =INDEX(MTInputs!$J$1:$AZ$415,$D16,MATCH(M$5,MTInputs!$J$5:$AZ$5,0)) | N16: =INDEX(MTInputs!$J$1:$AZ$415,$D16,MATCH(N$5,MTInputs!$J$5:$AZ$5,0)) | O16: =INDEX(MTInputs!$J$1:$AZ$415,$D16,MATCH(O$5,MTInputs!$J$5:$AZ$5,0)) | P16: =INDEX(MTInputs!$J$1:$AZ$415,$D16,MATCH(P$5,MTInputs!$J$5:$AZ$5,0)) | Q16: =INDEX(MTInputs!$J$1:$AZ$415,$D16,MATCH(Q$5,MTInputs!$J$5:$AZ$5,0)) | R16: =INDEX(MTInputs!$J$1:$AZ$415,$D16,MATCH(R$5,MTInputs!$J$5:$AZ$5,0)) | S16: =INDEX(MTInputs!$J$1:$AZ$415,$D16,MATCH(S$5,MTInputs!$J$5:$AZ$5,0)) | ... AD16: =INDEX(MTInputs!$J$1:$AZ$415,$D16,MATCH(AD$5,MTInputs!$J$5:$AZ$5,0)) | AE16: =LOWER(Settings!$C$4)&".mit."&$A16&IF($C16="","","."&$C16&"."&$B16)&IF(INDEX(Variables!$D$5:$D$105,MATCH($A16,Variables!$A$5:$A$105,0))="","","."&INDEX(Variables!$D$5:$D$105,MATCH($A16,Variables!$A$5:$A$105,0)))&"."&AE$5 | AF16: =INDEX(MTInputs!$J$1:$AZ$415,$D16,MATCH(AF$5,MTInputs!$J$5:$AZ$5,0)) | AG16: =INDEX(MTInputs!$J$1:$AZ$415,$D16,MATCH(AG$5,MTInputs!$J$5:$AZ$5,0)) | AH16: =INDEX(MTInputs!$J$1:$AZ$415,$D16,MATCH(AH$5,MTInputs!$J$5:$AZ$5,0)) | AI16: =INDEX(MTInputs!$J$1:$AZ$415,$D16,MATCH(AI$5,MTInputs!$J$5:$AZ$5,0)) | AJ16: =INDEX(MTInputs!$J$1:$AZ$415,$D16,MATCH(AJ$5,MTInputs!$J$5:$AZ$5,0)) | AK16: =INDEX(MTInputs!$J$1:$AZ$415,$D16,MATCH(AK$5,MTInputs!$J$5:$AZ$5,0)) | AL16: =INDEX(MTInputs!$J$1:$AZ$415,$D16,MATCH(AL$5,MTInputs!$J$5:$AZ$5,0)) | AM16: =INDEX(MTInputs!$J$1:$AZ$415,$D16,MATCH(AM$5,MTInputs!$J$5:$AZ$5,0)) | ... AX16: =INDEX(MTInputs!$J$1:$AZ$415,$D16,MATCH(AX$5,MTInputs!$J$5:$AZ$5,0))
A17: CPOutro | D17: 21 | H17: =INDEX(Variables!$B$5:$B$105,MATCH($A17,Variables!$A$5:$A$105,0))&IF($C17="",""," | "&INDEX(Mapping!$B$5:$B$26,MATCH($C17,Mapping!$A$5:$A$26,0))&" | "&INDEX(Mapping!$B$30:$B$41,MATCH($B17,Mapping!$A$30:$A$41,0))) | I17: =INDEX(Variables!$C$5:$C$105,MATCH($A17,Variables!$A$5:$A$105,0)) | J17: =INDEX(Variables!$E$5:$E$105,MATCH($A17,Variables!$A$5:$A$105,0)) | K17: =LOWER(Settings!$C$4)&".mit."&$A17&IF($C17="","","."&$C17&"."&$B17)&IF(INDEX(Variables!$D$5:$D$105,MATCH($A17,Variables!$A$5:$A$105,0))="","","."&INDEX(Variables!$D$5:$D$105,MATCH($A17,Variables!$A$5:$A$105,0)))&"."&K$5 | L17: =INDEX(MTInputs!$J$1:$AZ$415,$D17,MATCH(L$5,MTInputs!$J$5:$AZ$5,0)) | M17: =INDEX(MTInputs!$J$1:$AZ$415,$D17,MATCH(M$5,MTInputs!$J$5:$AZ$5,0)) | N17: =INDEX(MTInputs!$J$1:$AZ$415,$D17,MATCH(N$5,MTInputs!$J$5:$AZ$5,0)) | O17: =INDEX(MTInputs!$J$1:$AZ$415,$D17,MATCH(O$5,MTInputs!$J$5:$AZ$5,0)) | P17: =INDEX(MTInputs!$J$1:$AZ$415,$D17,MATCH(P$5,MTInputs!$J$5:$AZ$5,0)) | Q17: =INDEX(MTInputs!$J$1:$AZ$415,$D17,MATCH(Q$5,MTInputs!$J$5:$AZ$5,0)) | R17: =INDEX(MTInputs!$J$1:$AZ$415,$D17,MATCH(R$5,MTInputs!$J$5:$AZ$5,0)) | S17: =INDEX(MTInputs!$J$1:$AZ$415,$D17,MATCH(S$5,MTInputs!$J$5:$AZ$5,0)) | ... AD17: =INDEX(MTInputs!$J$1:$AZ$415,$D17,MATCH(AD$5,MTInputs!$J$5:$AZ$5,0)) | AE17: =LOWER(Settings!$C$4)&".mit."&$A17&IF($C17="","","."&$C17&"."&$B17)&IF(INDEX(Variables!$D$5:$D$105,MATCH($A17,Variables!$A$5:$A$105,0))="","","."&INDEX(Variables!$D$5:$D$105,MATCH($A17,Variables!$A$5:$A$105,0)))&"."&AE$5 | AF17: =INDEX(MTInputs!$J$1:$AZ$415,$D17,MATCH(AF$5,MTInputs!$J$5:$AZ$5,0)) | AG17: =INDEX(MTInputs!$J$1:$AZ$415,$D17,MATCH(AG$5,MTInputs!$J$5:$AZ$5,0)) | AH17: =INDEX(MTInputs!$J$1:$AZ$415,$D17,MATCH(AH$5,MTInputs!$J$5:$AZ$5,0)) | AI17: =INDEX(MTInputs!$J$1:$AZ$415,$D17,MATCH(AI$5,MTInputs!$J$5:$AZ$5,0)) | AJ17: =INDEX(MTInputs!$J$1:$AZ$415,$D17,MATCH(AJ$5,MTInputs!$J$5:$AZ$5,0)) | AK17: =INDEX(MTInputs!$J$1:$AZ$415,$D17,MATCH(AK$5,MTInputs!$J$5:$AZ$5,0)) | AL17: =INDEX(MTInputs!$J$1:$AZ$415,$D17,MATCH(AL$5,MTInputs!$J$5:$AZ$5,0)) | AM17: =INDEX(MTInputs!$J$1:$AZ$415,$D17,MATCH(AM$5,MTInputs!$J$5:$AZ$5,0)) | ... AX17: =INDEX(MTInputs!$J$1:$AZ$415,$D17,MATCH(AX$5,MTInputs!$J$5:$AZ$5,0))
A18: ExtendCarbonPriceBeyondOutro | D18: 265 | H18: =INDEX(Variables!$B$5:$B$105,MATCH($A18,Variables!$A$5:$A$105,0))&IF($C18="",""," | "&INDEX(Mapping!$B$5:$B$26,MATCH($C18,Mapping!$A$5:$A$26,0))&" | "&INDEX(Mapping!$B$30:$B$41,MATCH($B18,Mapping!$A$30:$A$41,0))) | I18: =INDEX(Variables!$C$5:$C$105,MATCH($A18,Variables!$A$5:$A$105,0)) | J18: =INDEX(Variables!$E$5:$E$105,MATCH($A18,Variables!$A$5:$A$105,0)) | K18: =LOWER(Settings!$C$4)&".mit."&$A18&IF($C18="","","."&$C18&"."&$B18)&IF(INDEX(Variables!$D$5:$D$105,MATCH($A18,Variables!$A$5:$A$105,0))="","","."&INDEX(Variables!$D$5:$D$105,MATCH($A18,Variables!$A$5:$A$105,0)))&"."&K$5 | L18: =INDEX(MTInputs!$J$1:$AZ$415,$D18,MATCH(L$5,MTInputs!$J$5:$AZ$5,0)) | M18: =INDEX(MTInputs!$J$1:$AZ$415,$D18,MATCH(M$5,MTInputs!$J$5:$AZ$5,0)) | N18: =INDEX(MTInputs!$J$1:$AZ$415,$D18,MATCH(N$5,MTInputs!$J$5:$AZ$5,0)) | O18: =INDEX(MTInputs!$J$1:$AZ$415,$D18,MATCH(O$5,MTInputs!$J$5:$AZ$5,0)) | P18: =INDEX(MTInputs!$J$1:$AZ$415,$D18,MATCH(P$5,MTInputs!$J$5:$AZ$5,0)) | Q18: =INDEX(MTInputs!$J$1:$AZ$415,$D18,MATCH(Q$5,MTInputs!$J$5:$AZ$5,0)) | R18: =INDEX(MTInputs!$J$1:$AZ$415,$D18,MATCH(R$5,MTInputs!$J$5:$AZ$5,0)) | S18: =INDEX(MTInputs!$J$1:$AZ$415,$D18,MATCH(S$5,MTInputs!$J$5:$AZ$5,0)) | ... AD18: =INDEX(MTInputs!$J$1:$AZ$415,$D18,MATCH(AD$5,MTInputs!$J$5:$AZ$5,0)) | AE18: =LOWER(Settings!$C$4)&".mit."&$A18&IF($C18="","","."&$C18&"."&$B18)&IF(INDEX(Variables!$D$5:$D$105,MATCH($A18,Variables!$A$5:$A$105,0))="","","."&INDEX(Variables!$D$5:$D$105,MATCH($A18,Variables!$A$5:$A$105,0)))&"."&AE$5 | AF18: =INDEX(MTInputs!$J$1:$AZ$415,$D18,MATCH(AF$5,MTInputs!$J$5:$AZ$5,0)) | AG18: =INDEX(MTInputs!$J$1:$AZ$415,$D18,MATCH(AG$5,MTInputs!$J$5:$AZ$5,0)) | AH18: =INDEX(MTInputs!$J$1:$AZ$415,$D18,MATCH(AH$5,MTInputs!$J$5:$AZ$5,0)) | AI18: =INDEX(MTInputs!$J$1:$AZ$415,$D18,MATCH(AI$5,MTInputs!$J$5:$AZ$5,0)) | AJ18: =INDEX(MTInputs!$J$1:$AZ$415,$D18,MATCH(AJ$5,MTInputs!$J$5:$AZ$5,0)) | AK18: =INDEX(MTInputs!$J$1:$AZ$415,$D18,MATCH(AK$5,MTInputs!$J$5:$AZ$5,0)) | AL18: =INDEX(MTInputs!$J$1:$AZ$415,$D18,MATCH(AL$5,MTInputs!$J$5:$AZ$5,0)) | AM18: =INDEX(MTInputs!$J$1:$AZ$415,$D18,MATCH(AM$5,MTInputs!$J$5:$AZ$5,0)) | ... AX18: =INDEX(MTInputs!$J$1:$AZ$415,$D18,MATCH(AX$5,MTInputs!$J$5:$AZ$5,0))
A19: NomorReal | D19: 266 | H19: =INDEX(Variables!$B$5:$B$105,MATCH($A19,Variables!$A$5:$A$105,0))&IF($C19="",""," | "&INDEX(Mapping!$B$5:$B$26,MATCH($C19,Mapping!$A$5:$A$26,0))&" | "&INDEX(Mapping!$B$30:$B$41,MATCH($B19,Mapping!$A$30:$A$41,0))) | I19: =INDEX(Variables!$C$5:$C$105,MATCH($A19,Variables!$A$5:$A$105,0)) | J19: =INDEX(Variables!$E$5:$E$105,MATCH($A19,Variables!$A$5:$A$105,0)) | K19: =LOWER(Settings!$C$4)&".mit."&$A19&IF($C19="","","."&$C19&"."&$B19)&IF(INDEX(Variables!$D$5:$D$105,MATCH($A19,Variables!$A$5:$A$105,0))="","","."&INDEX(Variables!$D$5:$D$105,MATCH($A19,Variables!$A$5:$A$105,0)))&"."&K$5 | L19: =INDEX(MTInputs!$J$1:$AZ$415,$D19,MATCH(L$5,MTInputs!$J$5:$AZ$5,0)) | M19: =INDEX(MTInputs!$J$1:$AZ$415,$D19,MATCH(M$5,MTInputs!$J$5:$AZ$5,0)) | N19: =INDEX(MTInputs!$J$1:$AZ$415,$D19,MATCH(N$5,MTInputs!$J$5:$AZ$5,0)) | O19: =INDEX(MTInputs!$J$1:$AZ$415,$D19,MATCH(O$5,MTInputs!$J$5:$AZ$5,0)) | P19: =INDEX(MTInputs!$J$1:$AZ$415,$D19,MATCH(P$5,MTInputs!$J$5:$AZ$5,0)) | Q19: =INDEX(MTInputs!$J$1:$AZ$415,$D19,MATCH(Q$5,MTInputs!$J$5:$AZ$5,0)) | R19: =INDEX(MTInputs!$J$1:$AZ$415,$D19,MATCH(R$5,MTInputs!$J$5:$AZ$5,0)) | S19: =INDEX(MTInputs!$J$1:$AZ$415,$D19,MATCH(S$5,MTInputs!$J$5:$AZ$5,0)) | ... AD19: =INDEX(MTInputs!$J$1:$AZ$415,$D19,MATCH(AD$5,MTInputs!$J$5:$AZ$5,0)) | AE19: =LOWER(Settings!$C$4)&".mit."&$A19&IF($C19="","","."&$C19&"."&$B19)&IF(INDEX(Variables!$D$5:$D$105,MATCH($A19,Variables!$A$5:$A$105,0))="","","."&INDEX(Variables!$D$5:$D$105,MATCH($A19,Variables!$A$5:$A$105,0)))&"."&AE$5 | AF19: =INDEX(MTInputs!$J$1:$AZ$415,$D19,MATCH(AF$5,MTInputs!$J$5:$AZ$5,0)) | AG19: =INDEX(MTInputs!$J$1:$AZ$415,$D19,MATCH(AG$5,MTInputs!$J$5:$AZ$5,0)) | AH19: =INDEX(MTInputs!$J$1:$AZ$415,$D19,MATCH(AH$5,MTInputs!$J$5:$AZ$5,0)) | AI19: =INDEX(MTInputs!$J$1:$AZ$415,$D19,MATCH(AI$5,MTInputs!$J$5:$AZ$5,0)) | AJ19: =INDEX(MTInputs!$J$1:$AZ$415,$D19,MATCH(AJ$5,MTInputs!$J$5:$AZ$5,0)) | AK19: =INDEX(MTInputs!$J$1:$AZ$415,$D19,MATCH(AK$5,MTInputs!$J$5:$AZ$5,0)) | AL19: =INDEX(MTInputs!$J$1:$AZ$415,$D19,MATCH(AL$5,MTInputs!$J$5:$AZ$5,0)) | AM19: =INDEX(MTInputs!$J$1:$AZ$415,$D19,MATCH(AM$5,MTInputs!$J$5:$AZ$5,0)) | ... AX19: =INDEX(MTInputs!$J$1:$AZ$415,$D19,MATCH(AX$5,MTInputs!$J$5:$AZ$5,0))
H20: Carbon tax coverage: fuels (MTInputs rows 23-29)
A21: ctcov | B21: coa | C21: all | D21: 23 | H21: =INDEX(Variables!$B$5:$B$105,MATCH($A21,Variables!$A$5:$A$105,0))&IF($C21="",""," | "&INDEX(Mapping!$B$5:$B$26,MATCH($C21,Mapping!$A$5:$A$26,0))&" | "&INDEX(Mapping!$B$30:$B$41,MATCH($B21,Mapping!$A$30:$A$41,0))) | I21: =INDEX(Variables!$C$5:$C$105,MATCH($A21,Variables!$A$5:$A$105,0)) | J21: =INDEX(Variables!$E$5:$E$105,MATCH($A21,Variables!$A$5:$A$105,0)) | K21: =LOWER(Settings!$C$4)&".mit."&$A21&IF($C21="","","."&$C21&"."&$B21)&IF(INDEX(Variables!$D$5:$D$105,MATCH($A21,Variables!$A$5:$A$105,0))="","","."&INDEX(Variables!$D$5:$D$105,MATCH($A21,Variables!$A$5:$A$105,0)))&"."&K$5 | L21: =INDEX(MTInputs!$J$1:$AZ$415,$D21,MATCH(L$5,MTInputs!$J$5:$AZ$5,0)) | M21: =INDEX(MTInputs!$J$1:$AZ$415,$D21,MATCH(M$5,MTInputs!$J$5:$AZ$5,0)) | N21: =INDEX(MTInputs!$J$1:$AZ$415,$D21,MATCH(N$5,MTInputs!$J$5:$AZ$5,0)) | O21: =INDEX(MTInputs!$J$1:$AZ$415,$D21,MATCH(O$5,MTInputs!$J$5:$AZ$5,0)) | P21: =INDEX(MTInputs!$J$1:$AZ$415,$D21,MATCH(P$5,MTInputs!$J$5:$AZ$5,0)) | Q21: =INDEX(MTInputs!$J$1:$AZ$415,$D21,MATCH(Q$5,MTInputs!$J$5:$AZ$5,0)) | R21: =INDEX(MTInputs!$J$1:$AZ$415,$D21,MATCH(R$5,MTInputs!$J$5:$AZ$5,0)) | S21: =INDEX(MTInputs!$J$1:$AZ$415,$D21,MATCH(S$5,MTInputs!$J$5:$AZ$5,0)) | ... AD21: =INDEX(MTInputs!$J$1:$AZ$415,$D21,MATCH(AD$5,MTInputs!$J$5:$AZ$5,0)) | AE21: =LOWER(Settings!$C$4)&".mit."&$A21&IF($C21="","","."&$C21&"."&$B21)&IF(INDEX(Variables!$D$5:$D$105,MATCH($A21,Variables!$A$5:$A$105,0))="","","."&INDEX(Variables!$D$5:$D$105,MATCH($A21,Variables!$A$5:$A$105,0)))&"."&AE$5 | AF21: =INDEX(MTInputs!$J$1:$AZ$415,$D21,MATCH(AF$5,MTInputs!$J$5:$AZ$5,0)) | AG21: =INDEX(MTInputs!$J$1:$AZ$415,$D21,MATCH(AG$5,MTInputs!$J$5:$AZ$5,0)) | AH21: =INDEX(MTInputs!$J$1:$AZ$415,$D21,MATCH(AH$5,MTInputs!$J$5:$AZ$5,0)) | AI21: =INDEX(MTInputs!$J$1:$AZ$415,$D21,MATCH(AI$5,MTInputs!$J$5:$AZ$5,0)) | AJ21: =INDEX(MTInputs!$J$1:$AZ$415,$D21,MATCH(AJ$5,MTInputs!$J$5:$AZ$5,0)) | AK21: =INDEX(MTInputs!$J$1:$AZ$415,$D21,MATCH(AK$5,MTInputs!$J$5:$AZ$5,0)) | AL21: =INDEX(MTInputs!$J$1:$AZ$415,$D21,MATCH(AL$5,MTInputs!$J$5:$AZ$5,0)) | AM21: =INDEX(MTInputs!$J$1:$AZ$415,$D21,MATCH(AM$5,MTInputs!$J$5:$AZ$5,0)) | ... AX21: =INDEX(MTInputs!$J$1:$AZ$415,$D21,MATCH(AX$5,MTInputs!$J$5:$AZ$5,0))
A22: ctcov | B22: nga | C22: all | D22: 24 | H22: =INDEX(Variables!$B$5:$B$105,MATCH($A22,Variables!$A$5:$A$105,0))&IF($C22="",""," | "&INDEX(Mapping!$B$5:$B$26,MATCH($C22,Mapping!$A$5:$A$26,0))&" | "&INDEX(Mapping!$B$30:$B$41,MATCH($B22,Mapping!$A$30:$A$41,0))) | I22: =INDEX(Variables!$C$5:$C$105,MATCH($A22,Variables!$A$5:$A$105,0)) | J22: =INDEX(Variables!$E$5:$E$105,MATCH($A22,Variables!$A$5:$A$105,0)) | K22: =LOWER(Settings!$C$4)&".mit."&$A22&IF($C22="","","."&$C22&"."&$B22)&IF(INDEX(Variables!$D$5:$D$105,MATCH($A22,Variables!$A$5:$A$105,0))="","","."&INDEX(Variables!$D$5:$D$105,MATCH($A22,Variables!$A$5:$A$105,0)))&"."&K$5 | L22: =INDEX(MTInputs!$J$1:$AZ$415,$D22,MATCH(L$5,MTInputs!$J$5:$AZ$5,0)) | M22: =INDEX(MTInputs!$J$1:$AZ$415,$D22,MATCH(M$5,MTInputs!$J$5:$AZ$5,0)) | N22: =INDEX(MTInputs!$J$1:$AZ$415,$D22,MATCH(N$5,MTInputs!$J$5:$AZ$5,0)) | O22: =INDEX(MTInputs!$J$1:$AZ$415,$D22,MATCH(O$5,MTInputs!$J$5:$AZ$5,0)) | P22: =INDEX(MTInputs!$J$1:$AZ$415,$D22,MATCH(P$5,MTInputs!$J$5:$AZ$5,0)) | Q22: =INDEX(MTInputs!$J$1:$AZ$415,$D22,MATCH(Q$5,MTInputs!$J$5:$AZ$5,0)) | R22: =INDEX(MTInputs!$J$1:$AZ$415,$D22,MATCH(R$5,MTInputs!$J$5:$AZ$5,0)) | S22: =INDEX(MTInputs!$J$1:$AZ$415,$D22,MATCH(S$5,MTInputs!$J$5:$AZ$5,0)) | ... AD22: =INDEX(MTInputs!$J$1:$AZ$415,$D22,MATCH(AD$5,MTInputs!$J$5:$AZ$5,0)) | AE22: =LOWER(Settings!$C$4)&".mit."&$A22&IF($C22="","","."&$C22&"."&$B22)&IF(INDEX(Variables!$D$5:$D$105,MATCH($A22,Variables!$A$5:$A$105,0))="","","."&INDEX(Variables!$D$5:$D$105,MATCH($A22,Variables!$A$5:$A$105,0)))&"."&AE$5 | AF22: =INDEX(MTInputs!$J$1:$AZ$415,$D22,MATCH(AF$5,MTInputs!$J$5:$AZ$5,0)) | AG22: =INDEX(MTInputs!$J$1:$AZ$415,$D22,MATCH(AG$5,MTInputs!$J$5:$AZ$5,0)) | AH22: =INDEX(MTInputs!$J$1:$AZ$415,$D22,MATCH(AH$5,MTInputs!$J$5:$AZ$5,0)) | AI22: =INDEX(MTInputs!$J$1:$AZ$415,$D22,MATCH(AI$5,MTInputs!$J$5:$AZ$5,0)) | AJ22: =INDEX(MTInputs!$J$1:$AZ$415,$D22,MATCH(AJ$5,MTInputs!$J$5:$AZ$5,0)) | AK22: =INDEX(MTInputs!$J$1:$AZ$415,$D22,MATCH(AK$5,MTInputs!$J$5:$AZ$5,0)) | AL22: =INDEX(MTInputs!$J$1:$AZ$415,$D22,MATCH(AL$5,MTInputs!$J$5:$AZ$5,0)) | AM22: =INDEX(MTInputs!$J$1:$AZ$415,$D22,MATCH(AM$5,MTInputs!$J$5:$AZ$5,0)) | ... AX22: =INDEX(MTInputs!$J$1:$AZ$415,$D22,MATCH(AX$5,MTInputs!$J$5:$AZ$5,0))
A23: ctcov | B23: gso | C23: all | D23: 25 | H23: =INDEX(Variables!$B$5:$B$105,MATCH($A23,Variables!$A$5:$A$105,0))&IF($C23="",""," | "&INDEX(Mapping!$B$5:$B$26,MATCH($C23,Mapping!$A$5:$A$26,0))&" | "&INDEX(Mapping!$B$30:$B$41,MATCH($B23,Mapping!$A$30:$A$41,0))) | I23: =INDEX(Variables!$C$5:$C$105,MATCH($A23,Variables!$A$5:$A$105,0)) | J23: =INDEX(Variables!$E$5:$E$105,MATCH($A23,Variables!$A$5:$A$105,0)) | K23: =LOWER(Settings!$C$4)&".mit."&$A23&IF($C23="","","."&$C23&"."&$B23)&IF(INDEX(Variables!$D$5:$D$105,MATCH($A23,Variables!$A$5:$A$105,0))="","","."&INDEX(Variables!$D$5:$D$105,MATCH($A23,Variables!$A$5:$A$105,0)))&"."&K$5 | L23: =INDEX(MTInputs!$J$1:$AZ$415,$D23,MATCH(L$5,MTInputs!$J$5:$AZ$5,0)) | M23: =INDEX(MTInputs!$J$1:$AZ$415,$D23,MATCH(M$5,MTInputs!$J$5:$AZ$5,0)) | N23: =INDEX(MTInputs!$J$1:$AZ$415,$D23,MATCH(N$5,MTInputs!$J$5:$AZ$5,0)) | O23: =INDEX(MTInputs!$J$1:$AZ$415,$D23,MATCH(O$5,MTInputs!$J$5:$AZ$5,0)) | P23: =INDEX(MTInputs!$J$1:$AZ$415,$D23,MATCH(P$5,MTInputs!$J$5:$AZ$5,0)) | Q23: =INDEX(MTInputs!$J$1:$AZ$415,$D23,MATCH(Q$5,MTInputs!$J$5:$AZ$5,0)) | R23: =INDEX(MTInputs!$J$1:$AZ$415,$D23,MATCH(R$5,MTInputs!$J$5:$AZ$5,0)) | S23: =INDEX(MTInputs!$J$1:$AZ$415,$D23,MATCH(S$5,MTInputs!$J$5:$AZ$5,0)) | ... AD23: =INDEX(MTInputs!$J$1:$AZ$415,$D23,MATCH(AD$5,MTInputs!$J$5:$AZ$5,0)) | AE23: =LOWER(Settings!$C$4)&".mit."&$A23&IF($C23="","","."&$C23&"."&$B23)&IF(INDEX(Variables!$D$5:$D$105,MATCH($A23,Variables!$A$5:$A$105,0))="","","."&INDEX(Variables!$D$5:$D$105,MATCH($A23,Variables!$A$5:$A$105,0)))&"."&AE$5 | AF23: =INDEX(MTInputs!$J$1:$AZ$415,$D23,MATCH(AF$5,MTInputs!$J$5:$AZ$5,0)) | AG23: =INDEX(MTInputs!$J$1:$AZ$415,$D23,MATCH(AG$5,MTInputs!$J$5:$AZ$5,0)) | AH23: =INDEX(MTInputs!$J$1:$AZ$415,$D23,MATCH(AH$5,MTInputs!$J$5:$AZ$5,0)) | AI23: =INDEX(MTInputs!$J$1:$AZ$415,$D23,MATCH(AI$5,MTInputs!$J$5:$AZ$5,0)) | AJ23: =INDEX(MTInputs!$J$1:$AZ$415,$D23,MATCH(AJ$5,MTInputs!$J$5:$AZ$5,0)) | AK23: =INDEX(MTInputs!$J$1:$AZ$415,$D23,MATCH(AK$5,MTInputs!$J$5:$AZ$5,0)) | AL23: =INDEX(MTInputs!$J$1:$AZ$415,$D23,MATCH(AL$5,MTInputs!$J$5:$AZ$5,0)) | AM23: =INDEX(MTInputs!$J$1:$AZ$415,$D23,MATCH(AM$5,MTInputs!$J$5:$AZ$5,0)) | ... AX23: =INDEX(MTInputs!$J$1:$AZ$415,$D23,MATCH(AX$5,MTInputs!$J$5:$AZ$5,0))
A24: ctcov | B24: die | C24: all | D24: 26 | H24: =INDEX(Variables!$B$5:$B$105,MATCH($A24,Variables!$A$5:$A$105,0))&IF($C24="",""," | "&INDEX(Mapping!$B$5:$B$26,MATCH($C24,Mapping!$A$5:$A$26,0))&" | "&INDEX(Mapping!$B$30:$B$41,MATCH($B24,Mapping!$A$30:$A$41,0))) | I24: =INDEX(Variables!$C$5:$C$105,MATCH($A24,Variables!$A$5:$A$105,0)) | J24: =INDEX(Variables!$E$5:$E$105,MATCH($A24,Variables!$A$5:$A$105,0)) | K24: =LOWER(Settings!$C$4)&".mit."&$A24&IF($C24="","","."&$C24&"."&$B24)&IF(INDEX(Variables!$D$5:$D$105,MATCH($A24,Variables!$A$5:$A$105,0))="","","."&INDEX(Variables!$D$5:$D$105,MATCH($A24,Variables!$A$5:$A$105,0)))&"."&K$5 | L24: =INDEX(MTInputs!$J$1:$AZ$415,$D24,MATCH(L$5,MTInputs!$J$5:$AZ$5,0)) | M24: =INDEX(MTInputs!$J$1:$AZ$415,$D24,MATCH(M$5,MTInputs!$J$5:$AZ$5,0)) | N24: =INDEX(MTInputs!$J$1:$AZ$415,$D24,MATCH(N$5,MTInputs!$J$5:$AZ$5,0)) | O24: =INDEX(MTInputs!$J$1:$AZ$415,$D24,MATCH(O$5,MTInputs!$J$5:$AZ$5,0)) | P24: =INDEX(MTInputs!$J$1:$AZ$415,$D24,MATCH(P$5,MTInputs!$J$5:$AZ$5,0)) | Q24: =INDEX(MTInputs!$J$1:$AZ$415,$D24,MATCH(Q$5,MTInputs!$J$5:$AZ$5,0)) | R24: =INDEX(MTInputs!$J$1:$AZ$415,$D24,MATCH(R$5,MTInputs!$J$5:$AZ$5,0)) | S24: =INDEX(MTInputs!$J$1:$AZ$415,$D24,MATCH(S$5,MTInputs!$J$5:$AZ$5,0)) | ... AD24: =INDEX(MTInputs!$J$1:$AZ$415,$D24,MATCH(AD$5,MTInputs!$J$5:$AZ$5,0)) | AE24: =LOWER(Settings!$C$4)&".mit."&$A24&IF($C24="","","."&$C24&"."&$B24)&IF(INDEX(Variables!$D$5:$D$105,MATCH($A24,Variables!$A$5:$A$105,0))="","","."&INDEX(Variables!$D$5:$D$105,MATCH($A24,Variables!$A$5:$A$105,0)))&"."&AE$5 | AF24: =INDEX(MTInputs!$J$1:$AZ$415,$D24,MATCH(AF$5,MTInputs!$J$5:$AZ$5,0)) | AG24: =INDEX(MTInputs!$J$1:$AZ$415,$D24,MATCH(AG$5,MTInputs!$J$5:$AZ$5,0)) | AH24: =INDEX(MTInputs!$J$1:$AZ$415,$D24,MATCH(AH$5,MTInputs!$J$5:$AZ$5,0)) | AI24: =INDEX(MTInputs!$J$1:$AZ$415,$D24,MATCH(AI$5,MTInputs!$J$5:$AZ$5,0)) | AJ24: =INDEX(MTInputs!$J$1:$AZ$415,$D24,MATCH(AJ$5,MTInputs!$J$5:$AZ$5,0)) | AK24: =INDEX(MTInputs!$J$1:$AZ$415,$D24,MATCH(AK$5,MTInputs!$J$5:$AZ$5,0)) | AL24: =INDEX(MTInputs!$J$1:$AZ$415,$D24,MATCH(AL$5,MTInputs!$J$5:$AZ$5,0)) | AM24: =INDEX(MTInputs!$J$1:$AZ$415,$D24,MATCH(AM$5,MTInputs!$J$5:$AZ$5,0)) | ... AX24: =INDEX(MTInputs!$J$1:$AZ$415,$D24,MATCH(AX$5,MTInputs!$J$5:$AZ$5,0))
A25: ctcov | B25: lpg | C25: all | D25: 27 | H25: =INDEX(Variables!$B$5:$B$105,MATCH($A25,Variables!$A$5:$A$105,0))&IF($C25="",""," | "&INDEX(Mapping!$B$5:$B$26,MATCH($C25,Mapping!$A$5:$A$26,0))&" | "&INDEX(Mapping!$B$30:$B$41,MATCH($B25,Mapping!$A$30:$A$41,0))) | I25: =INDEX(Variables!$C$5:$C$105,MATCH($A25,Variables!$A$5:$A$105,0)) | J25: =INDEX(Variables!$E$5:$E$105,MATCH($A25,Variables!$A$5:$A$105,0)) | K25: =LOWER(Settings!$C$4)&".mit."&$A25&IF($C25="","","."&$C25&"."&$B25)&IF(INDEX(Variables!$D$5:$D$105,MATCH($A25,Variables!$A$5:$A$105,0))="","","."&INDEX(Variables!$D$5:$D$105,MATCH($A25,Variables!$A$5:$A$105,0)))&"."&K$5 | L25: =INDEX(MTInputs!$J$1:$AZ$415,$D25,MATCH(L$5,MTInputs!$J$5:$AZ$5,0)) | M25: =INDEX(MTInputs!$J$1:$AZ$415,$D25,MATCH(M$5,MTInputs!$J$5:$AZ$5,0)) | N25: =INDEX(MTInputs!$J$1:$AZ$415,$D25,MATCH(N$5,MTInputs!$J$5:$AZ$5,0)) | O25: =INDEX(MTInputs!$J$1:$AZ$415,$D25,MATCH(O$5,MTInputs!$J$5:$AZ$5,0)) | P25: =INDEX(MTInputs!$J$1:$AZ$415,$D25,MATCH(P$5,MTInputs!$J$5:$AZ$5,0)) | Q25: =INDEX(MTInputs!$J$1:$AZ$415,$D25,MATCH(Q$5,MTInputs!$J$5:$AZ$5,0)) | R25: =INDEX(MTInputs!$J$1:$AZ$415,$D25,MATCH(R$5,MTInputs!$J$5:$AZ$5,0)) | S25: =INDEX(MTInputs!$J$1:$AZ$415,$D25,MATCH(S$5,MTInputs!$J$5:$AZ$5,0)) | ... AD25: =INDEX(MTInputs!$J$1:$AZ$415,$D25,MATCH(AD$5,MTInputs!$J$5:$AZ$5,0)) | AE25: =LOWER(Settings!$C$4)&".mit."&$A25&IF($C25="","","."&$C25&"."&$B25)&IF(INDEX(Variables!$D$5:$D$105,MATCH($A25,Variables!$A$5:$A$105,0))="","","."&INDEX(Variables!$D$5:$D$105,MATCH($A25,Variables!$A$5:$A$105,0)))&"."&AE$5 | AF25: =INDEX(MTInputs!$J$1:$AZ$415,$D25,MATCH(AF$5,MTInputs!$J$5:$AZ$5,0)) | AG25: =INDEX(MTInputs!$J$1:$AZ$415,$D25,MATCH(AG$5,MTInputs!$J$5:$AZ$5,0)) | AH25: =INDEX(MTInputs!$J$1:$AZ$415,$D25,MATCH(AH$5,MTInputs!$J$5:$AZ$5,0)) | AI25: =INDEX(MTInputs!$J$1:$AZ$415,$D25,MATCH(AI$5,MTInputs!$J$5:$AZ$5,0)) | AJ25: =INDEX(MTInputs!$J$1:$AZ$415,$D25,MATCH(AJ$5,MTInputs!$J$5:$AZ$5,0)) | AK25: =INDEX(MTInputs!$J$1:$AZ$415,$D25,MATCH(AK$5,MTInputs!$J$5:$AZ$5,0)) | AL25: =INDEX(MTInputs!$J$1:$AZ$415,$D25,MATCH(AL$5,MTInputs!$J$5:$AZ$5,0)) | AM25: =INDEX(MTInputs!$J$1:$AZ$415,$D25,MATCH(AM$5,MTInputs!$J$5:$AZ$5,0)) | ... AX25: =INDEX(MTInputs!$J$1:$AZ$415,$D25,MATCH(AX$5,MTInputs!$J$5:$AZ$5,0))
A26: ctcov | B26: ker | C26: all | D26: 28 | H26: =INDEX(Variables!$B$5:$B$105,MATCH($A26,Variables!$A$5:$A$105,0))&IF($C26="",""," | "&INDEX(Mapping!$B$5:$B$26,MATCH($C26,Mapping!$A$5:$A$26,0))&" | "&INDEX(Mapping!$B$30:$B$41,MATCH($B26,Mapping!$A$30:$A$41,0))) | I26: =INDEX(Variables!$C$5:$C$105,MATCH($A26,Variables!$A$5:$A$105,0)) | J26: =INDEX(Variables!$E$5:$E$105,MATCH($A26,Variables!$A$5:$A$105,0)) | K26: =LOWER(Settings!$C$4)&".mit."&$A26&IF($C26="","","."&$C26&"."&$B26)&IF(INDEX(Variables!$D$5:$D$105,MATCH($A26,Variables!$A$5:$A$105,0))="","","."&INDEX(Variables!$D$5:$D$105,MATCH($A26,Variables!$A$5:$A$105,0)))&"."&K$5 | L26: =INDEX(MTInputs!$J$1:$AZ$415,$D26,MATCH(L$5,MTInputs!$J$5:$AZ$5,0)) | M26: =INDEX(MTInputs!$J$1:$AZ$415,$D26,MATCH(M$5,MTInputs!$J$5:$AZ$5,0)) | N26: =INDEX(MTInputs!$J$1:$AZ$415,$D26,MATCH(N$5,MTInputs!$J$5:$AZ$5,0)) | O26: =INDEX(MTInputs!$J$1:$AZ$415,$D26,MATCH(O$5,MTInputs!$J$5:$AZ$5,0)) | P26: =INDEX(MTInputs!$J$1:$AZ$415,$D26,MATCH(P$5,MTInputs!$J$5:$AZ$5,0)) | Q26: =INDEX(MTInputs!$J$1:$AZ$415,$D26,MATCH(Q$5,MTInputs!$J$5:$AZ$5,0)) | R26: =INDEX(MTInputs!$J$1:$AZ$415,$D26,MATCH(R$5,MTInputs!$J$5:$AZ$5,0)) | S26: =INDEX(MTInputs!$J$1:$AZ$415,$D26,MATCH(S$5,MTInputs!$J$5:$AZ$5,0)) | ... AD26: =INDEX(MTInputs!$J$1:$AZ$415,$D26,MATCH(AD$5,MTInputs!$J$5:$AZ$5,0)) | AE26: =LOWER(Settings!$C$4)&".mit."&$A26&IF($C26="","","."&$C26&"."&$B26)&IF(INDEX(Variables!$D$5:$D$105,MATCH($A26,Variables!$A$5:$A$105,0))="","","."&INDEX(Variables!$D$5:$D$105,MATCH($A26,Variables!$A$5:$A$105,0)))&"."&AE$5 | AF26: =INDEX(MTInputs!$J$1:$AZ$415,$D26,MATCH(AF$5,MTInputs!$J$5:$AZ$5,0)) | AG26: =INDEX(MTInputs!$J$1:$AZ$415,$D26,MATCH(AG$5,MTInputs!$J$5:$AZ$5,0)) | AH26: =INDEX(MTInputs!$J$1:$AZ$415,$D26,MATCH(AH$5,MTInputs!$J$5:$AZ$5,0)) | AI26: =INDEX(MTInputs!$J$1:$AZ$415,$D26,MATCH(AI$5,MTInputs!$J$5:$AZ$5,0)) | AJ26: =INDEX(MTInputs!$J$1:$AZ$415,$D26,MATCH(AJ$5,MTInputs!$J$5:$AZ$5,0)) | AK26: =INDEX(MTInputs!$J$1:$AZ$415,$D26,MATCH(AK$5,MTInputs!$J$5:$AZ$5,0)) | AL26: =INDEX(MTInputs!$J$1:$AZ$415,$D26,MATCH(AL$5,MTInputs!$J$5:$AZ$5,0)) | AM26: =INDEX(MTInputs!$J$1:$AZ$415,$D26,MATCH(AM$5,MTInputs!$J$5:$AZ$5,0)) | ... AX26: =INDEX(MTInputs!$J$1:$AZ$415,$D26,MATCH(AX$5,MTInputs!$J$5:$AZ$5,0))
A27: ctcov | B27: oop | C27: all | D27: 29 | H27: =INDEX(Variables!$B$5:$B$105,MATCH($A27,Variables!$A$5:$A$105,0))&IF($C27="",""," | "&INDEX(Mapping!$B$5:$B$26,MATCH($C27,Mapping!$A$5:$A$26,0))&" | "&INDEX(Mapping!$B$30:$B$41,MATCH($B27,Mapping!$A$30:$A$41,0))) | I27: =INDEX(Variables!$C$5:$C$105,MATCH($A27,Variables!$A$5:$A$105,0)) | J27: =INDEX(Variables!$E$5:$E$105,MATCH($A27,Variables!$A$5:$A$105,0)) | K27: =LOWER(Settings!$C$4)&".mit."&$A27&IF($C27="","","."&$C27&"."&$B27)&IF(INDEX(Variables!$D$5:$D$105,MATCH($A27,Variables!$A$5:$A$105,0))="","","."&INDEX(Variables!$D$5:$D$105,MATCH($A27,Variables!$A$5:$A$105,0)))&"."&K$5 | L27: =INDEX(MTInputs!$J$1:$AZ$415,$D27,MATCH(L$5,MTInputs!$J$5:$AZ$5,0)) | M27: =INDEX(MTInputs!$J$1:$AZ$415,$D27,MATCH(M$5,MTInputs!$J$5:$AZ$5,0)) | N27: =INDEX(MTInputs!$J$1:$AZ$415,$D27,MATCH(N$5,MTInputs!$J$5:$AZ$5,0)) | O27: =INDEX(MTInputs!$J$1:$AZ$415,$D27,MATCH(O$5,MTInputs!$J$5:$AZ$5,0)) | P27: =INDEX(MTInputs!$J$1:$AZ$415,$D27,MATCH(P$5,MTInputs!$J$5:$AZ$5,0)) | Q27: =INDEX(MTInputs!$J$1:$AZ$415,$D27,MATCH(Q$5,MTInputs!$J$5:$AZ$5,0)) | R27: =INDEX(MTInputs!$J$1:$AZ$415,$D27,MATCH(R$5,MTInputs!$J$5:$AZ$5,0)) | S27: =INDEX(MTInputs!$J$1:$AZ$415,$D27,MATCH(S$5,MTInputs!$J$5:$AZ$5,0)) | ... AD27: =INDEX(MTInputs!$J$1:$AZ$415,$D27,MATCH(AD$5,MTInputs!$J$5:$AZ$5,0)) | AE27: =LOWER(Settings!$C$4)&".mit."&$A27&IF($C27="","","."&$C27&"."&$B27)&IF(INDEX(Variables!$D$5:$D$105,MATCH($A27,Variables!$A$5:$A$105,0))="","","."&INDEX(Variables!$D$5:$D$105,MATCH($A27,Variables!$A$5:$A$105,0)))&"."&AE$5 | AF27: =INDEX(MTInputs!$J$1:$AZ$415,$D27,MATCH(AF$5,MTInputs!$J$5:$AZ$5,0)) | AG27: =INDEX(MTInputs!$J$1:$AZ$415,$D27,MATCH(AG$5,MTInputs!$J$5:$AZ$5,0)) | AH27: =INDEX(MTInputs!$J$1:$AZ$415,$D27,MATCH(AH$5,MTInputs!$J$5:$AZ$5,0)) | AI27: =INDEX(MTInputs!$J$1:$AZ$415,$D27,MATCH(AI$5,MTInputs!$J$5:$AZ$5,0)) | AJ27: =INDEX(MTInputs!$J$1:$AZ$415,$D27,MATCH(AJ$5,MTInputs!$J$5:$AZ$5,0)) | AK27: =INDEX(MTInputs!$J$1:$AZ$415,$D27,MATCH(AK$5,MTInputs!$J$5:$AZ$5,0)) | AL27: =INDEX(MTInputs!$J$1:$AZ$415,$D27,MATCH(AL$5,MTInputs!$J$5:$AZ$5,0)) | AM27: =INDEX(MTInputs!$J$1:$AZ$415,$D27,MATCH(AM$5,MTInputs!$J$5:$AZ$5,0)) | ... AX27: =INDEX(MTInputs!$J$1:$AZ$415,$D27,MATCH(AX$5,MTInputs!$J$5:$AZ$5,0))
A28: ctcov | B28: bio | C28: all | H28: =INDEX(Variables!$B$5:$B$105,MATCH($A28,Variables!$A$5:$A$105,0))&IF($C28="",""," | "&INDEX(Mapping!$B$5:$B$26,MATCH($C28,Mapping!$A$5:$A$26,0))&" | "&INDEX(Mapping!$B$30:$B$41,MATCH($B28,Mapping!$A$30:$A$41,0))) | I28: =INDEX(Variables!$C$5:$C$105,MATCH($A28,Variables!$A$5:$A$105,0)) | J28: =INDEX(Variables!$E$5:$E$105,MATCH($A28,Variables!$A$5:$A$105,0)) | K28: =LOWER(Settings!$C$4)&".mit."&$A28&IF($C28="","","."&$C28&"."&$B28)&IF(INDEX(Variables!$D$5:$D$105,MATCH($A28,Variables!$A$5:$A$105,0))="","","."&INDEX(Variables!$D$5:$D$105,MATCH($A28,Variables!$A$5:$A$105,0)))&"."&K$5 | L28: TRUE | M28: TRUE | N28: TRUE | O28: TRUE | P28: TRUE | Q28: TRUE | R28: TRUE | S28: TRUE | T28: TRUE | U28: TRUE | V28: TRUE | W28: TRUE | X28: TRUE | Y28: TRUE | Z28: TRUE | AA28: TRUE | AB28: TRUE | AC28: TRUE | AD28: TRUE | AE28: =LOWER(Settings!$C$4)&".mit."&$A28&IF($C28="","","."&$C28&"."&$B28)&IF(INDEX(Variables!$D$5:$D$105,MATCH($A28,Variables!$A$5:$A$105,0))="","","."&INDEX(Variables!$D$5:$D$105,MATCH($A28,Variables!$A$5:$A$105,0)))&"."&AE$5 | AF28: TRUE | AG28: TRUE | AH28: TRUE | AI28: TRUE | AJ28: TRUE | AK28: TRUE | AL28: TRUE | AM28: TRUE | AN28: TRUE | AO28: TRUE | AP28: TRUE | AQ28: TRUE | AR28: TRUE | AS28: TRUE | AT28: TRUE | AU28: TRUE | AV28: TRUE | AW28: TRUE | AX28: TRUE
H29: Carbon tax coverage: sectors (MTInputs rows 31-47)
A30: ctcov | B30: all | C30: pow | D30: 31 | H30: =INDEX(Variables!$B$5:$B$105,MATCH($A30,Variables!$A$5:$A$105,0))&IF($C30="",""," | "&INDEX(Mapping!$B$5:$B$26,MATCH($C30,Mapping!$A$5:$A$26,0))&" | "&INDEX(Mapping!$B$30:$B$41,MATCH($B30,Mapping!$A$30:$A$41,0))) | I30: =INDEX(Variables!$C$5:$C$105,MATCH($A30,Variables!$A$5:$A$105,0)) | J30: =INDEX(Variables!$E$5:$E$105,MATCH($A30,Variables!$A$5:$A$105,0)) | K30: =LOWER(Settings!$C$4)&".mit."&$A30&IF($C30="","","."&$C30&"."&$B30)&IF(INDEX(Variables!$D$5:$D$105,MATCH($A30,Variables!$A$5:$A$105,0))="","","."&INDEX(Variables!$D$5:$D$105,MATCH($A30,Variables!$A$5:$A$105,0)))&"."&K$5 | L30: =INDEX(MTInputs!$J$1:$AZ$415,$D30,MATCH(L$5,MTInputs!$J$5:$AZ$5,0)) | M30: =INDEX(MTInputs!$J$1:$AZ$415,$D30,MATCH(M$5,MTInputs!$J$5:$AZ$5,0)) | N30: =INDEX(MTInputs!$J$1:$AZ$415,$D30,MATCH(N$5,MTInputs!$J$5:$AZ$5,0)) | O30: =INDEX(MTInputs!$J$1:$AZ$415,$D30,MATCH(O$5,MTInputs!$J$5:$AZ$5,0)) | P30: =INDEX(MTInputs!$J$1:$AZ$415,$D30,MATCH(P$5,MTInputs!$J$5:$AZ$5,0)) | Q30: =INDEX(MTInputs!$J$1:$AZ$415,$D30,MATCH(Q$5,MTInputs!$J$5:$AZ$5,0)) | R30: =INDEX(MTInputs!$J$1:$AZ$415,$D30,MATCH(R$5,MTInputs!$J$5:$AZ$5,0)) | S30: =INDEX(MTInputs!$J$1:$AZ$415,$D30,MATCH(S$5,MTInputs!$J$5:$AZ$5,0)) | ... AD30: =INDEX(MTInputs!$J$1:$AZ$415,$D30,MATCH(AD$5,MTInputs!$J$5:$AZ$5,0)) | AE30: =LOWER(Settings!$C$4)&".mit."&$A30&IF($C30="","","."&$C30&"."&$B30)&IF(INDEX(Variables!$D$5:$D$105,MATCH($A30,Variables!$A$5:$A$105,0))="","","."&INDEX(Variables!$D$5:$D$105,MATCH($A30,Variables!$A$5:$A$105,0)))&"."&AE$5 | AF30: =INDEX(MTInputs!$J$1:$AZ$415,$D30,MATCH(AF$5,MTInputs!$J$5:$AZ$5,0)) | AG30: =INDEX(MTInputs!$J$1:$AZ$415,$D30,MATCH(AG$5,MTInputs!$J$5:$AZ$5,0)) | AH30: =INDEX(MTInputs!$J$1:$AZ$415,$D30,MATCH(AH$5,MTInputs!$J$5:$AZ$5,0)) | AI30: =INDEX(MTInputs!$J$1:$AZ$415,$D30,MATCH(AI$5,MTInputs!$J$5:$AZ$5,0)) | AJ30: =INDEX(MTInputs!$J$1:$AZ$415,$D30,MATCH(AJ$5,MTInputs!$J$5:$AZ$5,0)) | AK30: =INDEX(MTInputs!$J$1:$AZ$415,$D30,MATCH(AK$5,MTInputs!$J$5:$AZ$5,0)) | AL30: =INDEX(MTInputs!$J$1:$AZ$415,$D30,MATCH(AL$5,MTInputs!$J$5:$AZ$5,0)) | AM30: =INDEX(MTInputs!$J$1:$AZ$415,$D30,MATCH(AM$5,MTInputs!$J$5:$AZ$5,0)) | ... AX30: =INDEX(MTInputs!$J$1:$AZ$415,$D30,MATCH(AX$5,MTInputs!$J$5:$AZ$5,0))
A31: ctcov | B31: all | C31: rod | D31: 32 | H31: =INDEX(Variables!$B$5:$B$105,MATCH($A31,Variables!$A$5:$A$105,0))&IF($C31="",""," | "&INDEX(Mapping!$B$5:$B$26,MATCH($C31,Mapping!$A$5:$A$26,0))&" | "&INDEX(Mapping!$B$30:$B$41,MATCH($B31,Mapping!$A$30:$A$41,0))) | I31: =INDEX(Variables!$C$5:$C$105,MATCH($A31,Variables!$A$5:$A$105,0)) | J31: =INDEX(Variables!$E$5:$E$105,MATCH($A31,Variables!$A$5:$A$105,0)) | K31: =LOWER(Settings!$C$4)&".mit."&$A31&IF($C31="","","."&$C31&"."&$B31)&IF(INDEX(Variables!$D$5:$D$105,MATCH($A31,Variables!$A$5:$A$105,0))="","","."&INDEX(Variables!$D$5:$D$105,MATCH($A31,Variables!$A$5:$A$105,0)))&"."&K$5 | L31: =INDEX(MTInputs!$J$1:$AZ$415,$D31,MATCH(L$5,MTInputs!$J$5:$AZ$5,0)) | M31: =INDEX(MTInputs!$J$1:$AZ$415,$D31,MATCH(M$5,MTInputs!$J$5:$AZ$5,0)) | N31: =INDEX(MTInputs!$J$1:$AZ$415,$D31,MATCH(N$5,MTInputs!$J$5:$AZ$5,0)) | O31: =INDEX(MTInputs!$J$1:$AZ$415,$D31,MATCH(O$5,MTInputs!$J$5:$AZ$5,0)) | P31: =INDEX(MTInputs!$J$1:$AZ$415,$D31,MATCH(P$5,MTInputs!$J$5:$AZ$5,0)) | Q31: =INDEX(MTInputs!$J$1:$AZ$415,$D31,MATCH(Q$5,MTInputs!$J$5:$AZ$5,0)) | R31: =INDEX(MTInputs!$J$1:$AZ$415,$D31,MATCH(R$5,MTInputs!$J$5:$AZ$5,0)) | S31: =INDEX(MTInputs!$J$1:$AZ$415,$D31,MATCH(S$5,MTInputs!$J$5:$AZ$5,0)) | ... AD31: =INDEX(MTInputs!$J$1:$AZ$415,$D31,MATCH(AD$5,MTInputs!$J$5:$AZ$5,0)) | AE31: =LOWER(Settings!$C$4)&".mit."&$A31&IF($C31="","","."&$C31&"."&$B31)&IF(INDEX(Variables!$D$5:$D$105,MATCH($A31,Variables!$A$5:$A$105,0))="","","."&INDEX(Variables!$D$5:$D$105,MATCH($A31,Variables!$A$5:$A$105,0)))&"."&AE$5 | AF31: =INDEX(MTInputs!$J$1:$AZ$415,$D31,MATCH(AF$5,MTInputs!$J$5:$AZ$5,0)) | AG31: =INDEX(MTInputs!$J$1:$AZ$415,$D31,MATCH(AG$5,MTInputs!$J$5:$AZ$5,0)) | AH31: =INDEX(MTInputs!$J$1:$AZ$415,$D31,MATCH(AH$5,MTInputs!$J$5:$AZ$5,0)) | AI31: =INDEX(MTInputs!$J$1:$AZ$415,$D31,MATCH(AI$5,MTInputs!$J$5:$AZ$5,0)) | AJ31: =INDEX(MTInputs!$J$1:$AZ$415,$D31,MATCH(AJ$5,MTInputs!$J$5:$AZ$5,0)) | AK31: =INDEX(MTInputs!$J$1:$AZ$415,$D31,MATCH(AK$5,MTInputs!$J$5:$AZ$5,0)) | AL31: =INDEX(MTInputs!$J$1:$AZ$415,$D31,MATCH(AL$5,MTInputs!$J$5:$AZ$5,0)) | AM31: =INDEX(MTInputs!$J$1:$AZ$415,$D31,MATCH(AM$5,MTInputs!$J$5:$AZ$5,0)) | ... AX31: =INDEX(MTInputs!$J$1:$AZ$415,$D31,MATCH(AX$5,MTInputs!$J$5:$AZ$5,0))
A32: ctcov | B32: all | C32: ral | D32: 33 | H32: =INDEX(Variables!$B$5:$B$105,MATCH($A32,Variables!$A$5:$A$105,0))&IF($C32="",""," | "&INDEX(Mapping!$B$5:$B$26,MATCH($C32,Mapping!$A$5:$A$26,0))&" | "&INDEX(Mapping!$B$30:$B$41,MATCH($B32,Mapping!$A$30:$A$41,0))) | I32: =INDEX(Variables!$C$5:$C$105,MATCH($A32,Variables!$A$5:$A$105,0)) | J32: =INDEX(Variables!$E$5:$E$105,MATCH($A32,Variables!$A$5:$A$105,0)) | K32: =LOWER(Settings!$C$4)&".mit."&$A32&IF($C32="","","."&$C32&"."&$B32)&IF(INDEX(Variables!$D$5:$D$105,MATCH($A32,Variables!$A$5:$A$105,0))="","","."&INDEX(Variables!$D$5:$D$105,MATCH($A32,Variables!$A$5:$A$105,0)))&"."&K$5 | L32: =INDEX(MTInputs!$J$1:$AZ$415,$D32,MATCH(L$5,MTInputs!$J$5:$AZ$5,0)) | M32: =INDEX(MTInputs!$J$1:$AZ$415,$D32,MATCH(M$5,MTInputs!$J$5:$AZ$5,0)) | N32: =INDEX(MTInputs!$J$1:$AZ$415,$D32,MATCH(N$5,MTInputs!$J$5:$AZ$5,0)) | O32: =INDEX(MTInputs!$J$1:$AZ$415,$D32,MATCH(O$5,MTInputs!$J$5:$AZ$5,0)) | P32: =INDEX(MTInputs!$J$1:$AZ$415,$D32,MATCH(P$5,MTInputs!$J$5:$AZ$5,0)) | Q32: =INDEX(MTInputs!$J$1:$AZ$415,$D32,MATCH(Q$5,MTInputs!$J$5:$AZ$5,0)) | R32: =INDEX(MTInputs!$J$1:$AZ$415,$D32,MATCH(R$5,MTInputs!$J$5:$AZ$5,0)) | S32: =INDEX(MTInputs!$J$1:$AZ$415,$D32,MATCH(S$5,MTInputs!$J$5:$AZ$5,0)) | ... AD32: =INDEX(MTInputs!$J$1:$AZ$415,$D32,MATCH(AD$5,MTInputs!$J$5:$AZ$5,0)) | AE32: =LOWER(Settings!$C$4)&".mit."&$A32&IF($C32="","","."&$C32&"."&$B32)&IF(INDEX(Variables!$D$5:$D$105,MATCH($A32,Variables!$A$5:$A$105,0))="","","."&INDEX(Variables!$D$5:$D$105,MATCH($A32,Variables!$A$5:$A$105,0)))&"."&AE$5 | AF32: =INDEX(MTInputs!$J$1:$AZ$415,$D32,MATCH(AF$5,MTInputs!$J$5:$AZ$5,0)) | AG32: =INDEX(MTInputs!$J$1:$AZ$415,$D32,MATCH(AG$5,MTInputs!$J$5:$AZ$5,0)) | AH32: =INDEX(MTInputs!$J$1:$AZ$415,$D32,MATCH(AH$5,MTInputs!$J$5:$AZ$5,0)) | AI32: =INDEX(MTInputs!$J$1:$AZ$415,$D32,MATCH(AI$5,MTInputs!$J$5:$AZ$5,0)) | AJ32: =INDEX(MTInputs!$J$1:$AZ$415,$D32,MATCH(AJ$5,MTInputs!$J$5:$AZ$5,0)) | AK32: =INDEX(MTInputs!$J$1:$AZ$415,$D32,MATCH(AK$5,MTInputs!$J$5:$AZ$5,0)) | AL32: =INDEX(MTInputs!$J$1:$AZ$415,$D32,MATCH(AL$5,MTInputs!$J$5:$AZ$5,0)) | AM32: =INDEX(MTInputs!$J$1:$AZ$415,$D32,MATCH(AM$5,MTInputs!$J$5:$AZ$5,0)) | ... AX32: =INDEX(MTInputs!$J$1:$AZ$415,$D32,MATCH(AX$5,MTInputs!$J$5:$AZ$5,0))
A33: ctcov | B33: all | C33: avi | D33: 34 | H33: =INDEX(Variables!$B$5:$B$105,MATCH($A33,Variables!$A$5:$A$105,0))&IF($C33="",""," | "&INDEX(Mapping!$B$5:$B$26,MATCH($C33,Mapping!$A$5:$A$26,0))&" | "&INDEX(Mapping!$B$30:$B$41,MATCH($B33,Mapping!$A$30:$A$41,0))) | I33: =INDEX(Variables!$C$5:$C$105,MATCH($A33,Variables!$A$5:$A$105,0)) | J33: =INDEX(Variables!$E$5:$E$105,MATCH($A33,Variables!$A$5:$A$105,0)) | K33: =LOWER(Settings!$C$4)&".mit."&$A33&IF($C33="","","."&$C33&"."&$B33)&IF(INDEX(Variables!$D$5:$D$105,MATCH($A33,Variables!$A$5:$A$105,0))="","","."&INDEX(Variables!$D$5:$D$105,MATCH($A33,Variables!$A$5:$A$105,0)))&"."&K$5 | L33: =INDEX(MTInputs!$J$1:$AZ$415,$D33,MATCH(L$5,MTInputs!$J$5:$AZ$5,0)) | M33: =INDEX(MTInputs!$J$1:$AZ$415,$D33,MATCH(M$5,MTInputs!$J$5:$AZ$5,0)) | N33: =INDEX(MTInputs!$J$1:$AZ$415,$D33,MATCH(N$5,MTInputs!$J$5:$AZ$5,0)) | O33: =INDEX(MTInputs!$J$1:$AZ$415,$D33,MATCH(O$5,MTInputs!$J$5:$AZ$5,0)) | P33: =INDEX(MTInputs!$J$1:$AZ$415,$D33,MATCH(P$5,MTInputs!$J$5:$AZ$5,0)) | Q33: =INDEX(MTInputs!$J$1:$AZ$415,$D33,MATCH(Q$5,MTInputs!$J$5:$AZ$5,0)) | R33: =INDEX(MTInputs!$J$1:$AZ$415,$D33,MATCH(R$5,MTInputs!$J$5:$AZ$5,0)) | S33: =INDEX(MTInputs!$J$1:$AZ$415,$D33,MATCH(S$5,MTInputs!$J$5:$AZ$5,0)) | ... AD33: =INDEX(MTInputs!$J$1:$AZ$415,$D33,MATCH(AD$5,MTInputs!$J$5:$AZ$5,0)) | AE33: =LOWER(Settings!$C$4)&".mit."&$A33&IF($C33="","","."&$C33&"."&$B33)&IF(INDEX(Variables!$D$5:$D$105,MATCH($A33,Variables!$A$5:$A$105,0))="","","."&INDEX(Variables!$D$5:$D$105,MATCH($A33,Variables!$A$5:$A$105,0)))&"."&AE$5 | AF33: =INDEX(MTInputs!$J$1:$AZ$415,$D33,MATCH(AF$5,MTInputs!$J$5:$AZ$5,0)) | AG33: =INDEX(MTInputs!$J$1:$AZ$415,$D33,MATCH(AG$5,MTInputs!$J$5:$AZ$5,0)) | AH33: =INDEX(MTInputs!$J$1:$AZ$415,$D33,MATCH(AH$5,MTInputs!$J$5:$AZ$5,0)) | AI33: =INDEX(MTInputs!$J$1:$AZ$415,$D33,MATCH(AI$5,MTInputs!$J$5:$AZ$5,0)) | AJ33: =INDEX(MTInputs!$J$1:$AZ$415,$D33,MATCH(AJ$5,MTInputs!$J$5:$AZ$5,0)) | AK33: =INDEX(MTInputs!$J$1:$AZ$415,$D33,MATCH(AK$5,MTInputs!$J$5:$AZ$5,0)) | AL33: =INDEX(MTInputs!$J$1:$AZ$415,$D33,MATCH(AL$5,MTInputs!$J$5:$AZ$5,0)) | AM33: =INDEX(MTInputs!$J$1:$AZ$415,$D33,MATCH(AM$5,MTInputs!$J$5:$AZ$5,0)) | ... AX33: =INDEX(MTInputs!$J$1:$AZ$415,$D33,MATCH(AX$5,MTInputs!$J$5:$AZ$5,0))
A34: ctcov | B34: all | C34: nav | D34: 35 | H34: =INDEX(Variables!$B$5:$B$105,MATCH($A34,Variables!$A$5:$A$105,0))&IF($C34="",""," | "&INDEX(Mapping!$B$5:$B$26,MATCH($C34,Mapping!$A$5:$A$26,0))&" | "&INDEX(Mapping!$B$30:$B$41,MATCH($B34,Mapping!$A$30:$A$41,0))) | I34: =INDEX(Variables!$C$5:$C$105,MATCH($A34,Variables!$A$5:$A$105,0)) | J34: =INDEX(Variables!$E$5:$E$105,MATCH($A34,Variables!$A$5:$A$105,0)) | K34: =LOWER(Settings!$C$4)&".mit."&$A34&IF($C34="","","."&$C34&"."&$B34)&IF(INDEX(Variables!$D$5:$D$105,MATCH($A34,Variables!$A$5:$A$105,0))="","","."&INDEX(Variables!$D$5:$D$105,MATCH($A34,Variables!$A$5:$A$105,0)))&"."&K$5 | L34: =INDEX(MTInputs!$J$1:$AZ$415,$D34,MATCH(L$5,MTInputs!$J$5:$AZ$5,0)) | M34: =INDEX(MTInputs!$J$1:$AZ$415,$D34,MATCH(M$5,MTInputs!$J$5:$AZ$5,0)) | N34: =INDEX(MTInputs!$J$1:$AZ$415,$D34,MATCH(N$5,MTInputs!$J$5:$AZ$5,0)) | O34: =INDEX(MTInputs!$J$1:$AZ$415,$D34,MATCH(O$5,MTInputs!$J$5:$AZ$5,0)) | P34: =INDEX(MTInputs!$J$1:$AZ$415,$D34,MATCH(P$5,MTInputs!$J$5:$AZ$5,0)) | Q34: =INDEX(MTInputs!$J$1:$AZ$415,$D34,MATCH(Q$5,MTInputs!$J$5:$AZ$5,0)) | R34: =INDEX(MTInputs!$J$1:$AZ$415,$D34,MATCH(R$5,MTInputs!$J$5:$AZ$5,0)) | S34: =INDEX(MTInputs!$J$1:$AZ$415,$D34,MATCH(S$5,MTInputs!$J$5:$AZ$5,0)) | ... AD34: =INDEX(MTInputs!$J$1:$AZ$415,$D34,MATCH(AD$5,MTInputs!$J$5:$AZ$5,0)) | AE34: =LOWER(Settings!$C$4)&".mit."&$A34&IF($C34="","","."&$C34&"."&$B34)&IF(INDEX(Variables!$D$5:$D$105,MATCH($A34,Variables!$A$5:$A$105,0))="","","."&INDEX(Variables!$D$5:$D$105,MATCH($A34,Variables!$A$5:$A$105,0)))&"."&AE$5 | AF34: =INDEX(MTInputs!$J$1:$AZ$415,$D34,MATCH(AF$5,MTInputs!$J$5:$AZ$5,0)) | AG34: =INDEX(MTInputs!$J$1:$AZ$415,$D34,MATCH(AG$5,MTInputs!$J$5:$AZ$5,0)) | AH34: =INDEX(MTInputs!$J$1:$AZ$415,$D34,MATCH(AH$5,MTInputs!$J$5:$AZ$5,0)) | AI34: =INDEX(MTInputs!$J$1:$AZ$415,$D34,MATCH(AI$5,MTInputs!$J$5:$AZ$5,0)) | AJ34: =INDEX(MTInputs!$J$1:$AZ$415,$D34,MATCH(AJ$5,MTInputs!$J$5:$AZ$5,0)) | AK34: =INDEX(MTInputs!$J$1:$AZ$415,$D34,MATCH(AK$5,MTInputs!$J$5:$AZ$5,0)) | AL34: =INDEX(MTInputs!$J$1:$AZ$415,$D34,MATCH(AL$5,MTInputs!$J$5:$AZ$5,0)) | AM34: =INDEX(MTInputs!$J$1:$AZ$415,$D34,MATCH(AM$5,MTInputs!$J$5:$AZ$5,0)) | ... AX34: =INDEX(MTInputs!$J$1:$AZ$415,$D34,MATCH(AX$5,MTInputs!$J$5:$AZ$5,0))
A35: ctcov | B35: all | C35: res | D35: 36 | H35: =INDEX(Variables!$B$5:$B$105,MATCH($A35,Variables!$A$5:$A$105,0))&IF($C35="",""," | "&INDEX(Mapping!$B$5:$B$26,MATCH($C35,Mapping!$A$5:$A$26,0))&" | "&INDEX(Mapping!$B$30:$B$41,MATCH($B35,Mapping!$A$30:$A$41,0))) | I35: =INDEX(Variables!$C$5:$C$105,MATCH($A35,Variables!$A$5:$A$105,0)) | J35: =INDEX(Variables!$E$5:$E$105,MATCH($A35,Variables!$A$5:$A$105,0)) | K35: =LOWER(Settings!$C$4)&".mit."&$A35&IF($C35="","","."&$C35&"."&$B35)&IF(INDEX(Variables!$D$5:$D$105,MATCH($A35,Variables!$A$5:$A$105,0))="","","."&INDEX(Variables!$D$5:$D$105,MATCH($A35,Variables!$A$5:$A$105,0)))&"."&K$5 | L35: =INDEX(MTInputs!$J$1:$AZ$415,$D35,MATCH(L$5,MTInputs!$J$5:$AZ$5,0)) | M35: =INDEX(MTInputs!$J$1:$AZ$415,$D35,MATCH(M$5,MTInputs!$J$5:$AZ$5,0)) | N35: =INDEX(MTInputs!$J$1:$AZ$415,$D35,MATCH(N$5,MTInputs!$J$5:$AZ$5,0)) | O35: =INDEX(MTInputs!$J$1:$AZ$415,$D35,MATCH(O$5,MTInputs!$J$5:$AZ$5,0)) | P35: =INDEX(MTInputs!$J$1:$AZ$415,$D35,MATCH(P$5,MTInputs!$J$5:$AZ$5,0)) | Q35: =INDEX(MTInputs!$J$1:$AZ$415,$D35,MATCH(Q$5,MTInputs!$J$5:$AZ$5,0)) | R35: =INDEX(MTInputs!$J$1:$AZ$415,$D35,MATCH(R$5,MTInputs!$J$5:$AZ$5,0)) | S35: =INDEX(MTInputs!$J$1:$AZ$415,$D35,MATCH(S$5,MTInputs!$J$5:$AZ$5,0)) | ... AD35: =INDEX(MTInputs!$J$1:$AZ$415,$D35,MATCH(AD$5,MTInputs!$J$5:$AZ$5,0)) | AE35: =LOWER(Settings!$C$4)&".mit."&$A35&IF($C35="","","."&$C35&"."&$B35)&IF(INDEX(Variables!$D$5:$D$105,MATCH($A35,Variables!$A$5:$A$105,0))="","","."&INDEX(Variables!$D$5:$D$105,MATCH($A35,Variables!$A$5:$A$105,0)))&"."&AE$5 | AF35: =INDEX(MTInputs!$J$1:$AZ$415,$D35,MATCH(AF$5,MTInputs!$J$5:$AZ$5,0)) | AG35: =INDEX(MTInputs!$J$1:$AZ$415,$D35,MATCH(AG$5,MTInputs!$J$5:$AZ$5,0)) | AH35: =INDEX(MTInputs!$J$1:$AZ$415,$D35,MATCH(AH$5,MTInputs!$J$5:$AZ$5,0)) | AI35: =INDEX(MTInputs!$J$1:$AZ$415,$D35,MATCH(AI$5,MTInputs!$J$5:$AZ$5,0)) | AJ35: =INDEX(MTInputs!$J$1:$AZ$415,$D35,MATCH(AJ$5,MTInputs!$J$5:$AZ$5,0)) | AK35: =INDEX(MTInputs!$J$1:$AZ$415,$D35,MATCH(AK$5,MTInputs!$J$5:$AZ$5,0)) | AL35: =INDEX(MTInputs!$J$1:$AZ$415,$D35,MATCH(AL$5,MTInputs!$J$5:$AZ$5,0)) | AM35: =INDEX(MTInputs!$J$1:$AZ$415,$D35,MATCH(AM$5,MTInputs!$J$5:$AZ$5,0)) | ... AX35: =INDEX(MTInputs!$J$1:$AZ$415,$D35,MATCH(AX$5,MTInputs!$J$5:$AZ$5,0))
A36: ctcov | B36: all | C36: foo | D36: 37 | H36: =INDEX(Variables!$B$5:$B$105,MATCH($A36,Variables!$A$5:$A$105,0))&IF($C36="",""," | "&INDEX(Mapping!$B$5:$B$26,MATCH($C36,Mapping!$A$5:$A$26,0))&" | "&INDEX(Mapping!$B$30:$B$41,MATCH($B36,Mapping!$A$30:$A$41,0))) | I36: =INDEX(Variables!$C$5:$C$105,MATCH($A36,Variables!$A$5:$A$105,0)) | J36: =INDEX(Variables!$E$5:$E$105,MATCH($A36,Variables!$A$5:$A$105,0)) | K36: =LOWER(Settings!$C$4)&".mit."&$A36&IF($C36="","","."&$C36&"."&$B36)&IF(INDEX(Variables!$D$5:$D$105,MATCH($A36,Variables!$A$5:$A$105,0))="","","."&INDEX(Variables!$D$5:$D$105,MATCH($A36,Variables!$A$5:$A$105,0)))&"."&K$5 | L36: =INDEX(MTInputs!$J$1:$AZ$415,$D36,MATCH(L$5,MTInputs!$J$5:$AZ$5,0)) | M36: =INDEX(MTInputs!$J$1:$AZ$415,$D36,MATCH(M$5,MTInputs!$J$5:$AZ$5,0)) | N36: =INDEX(MTInputs!$J$1:$AZ$415,$D36,MATCH(N$5,MTInputs!$J$5:$AZ$5,0)) | O36: =INDEX(MTInputs!$J$1:$AZ$415,$D36,MATCH(O$5,MTInputs!$J$5:$AZ$5,0)) | P36: =INDEX(MTInputs!$J$1:$AZ$415,$D36,MATCH(P$5,MTInputs!$J$5:$AZ$5,0)) | Q36: =INDEX(MTInputs!$J$1:$AZ$415,$D36,MATCH(Q$5,MTInputs!$J$5:$AZ$5,0)) | R36: =INDEX(MTInputs!$J$1:$AZ$415,$D36,MATCH(R$5,MTInputs!$J$5:$AZ$5,0)) | S36: =INDEX(MTInputs!$J$1:$AZ$415,$D36,MATCH(S$5,MTInputs!$J$5:$AZ$5,0)) | ... AD36: =INDEX(MTInputs!$J$1:$AZ$415,$D36,MATCH(AD$5,MTInputs!$J$5:$AZ$5,0)) | AE36: =LOWER(Settings!$C$4)&".mit."&$A36&IF($C36="","","."&$C36&"."&$B36)&IF(INDEX(Variables!$D$5:$D$105,MATCH($A36,Variables!$A$5:$A$105,0))="","","."&INDEX(Variables!$D$5:$D$105,MATCH($A36,Variables!$A$5:$A$105,0)))&"."&AE$5 | AF36: =INDEX(MTInputs!$J$1:$AZ$415,$D36,MATCH(AF$5,MTInputs!$J$5:$AZ$5,0)) | AG36: =INDEX(MTInputs!$J$1:$AZ$415,$D36,MATCH(AG$5,MTInputs!$J$5:$AZ$5,0)) | AH36: =INDEX(MTInputs!$J$1:$AZ$415,$D36,MATCH(AH$5,MTInputs!$J$5:$AZ$5,0)) | AI36: =INDEX(MTInputs!$J$1:$AZ$415,$D36,MATCH(AI$5,MTInputs!$J$5:$AZ$5,0)) | AJ36: =INDEX(MTInputs!$J$1:$AZ$415,$D36,MATCH(AJ$5,MTInputs!$J$5:$AZ$5,0)) | AK36: =INDEX(MTInputs!$J$1:$AZ$415,$D36,MATCH(AK$5,MTInputs!$J$5:$AZ$5,0)) | AL36: =INDEX(MTInputs!$J$1:$AZ$415,$D36,MATCH(AL$5,MTInputs!$J$5:$AZ$5,0)) | AM36: =INDEX(MTInputs!$J$1:$AZ$415,$D36,MATCH(AM$5,MTInputs!$J$5:$AZ$5,0)) | ... AX36: =INDEX(MTInputs!$J$1:$AZ$415,$D36,MATCH(AX$5,MTInputs!$J$5:$AZ$5,0))
A37: ctcov | B37: all | C37: srv | D37: 38 | H37: =INDEX(Variables!$B$5:$B$105,MATCH($A37,Variables!$A$5:$A$105,0))&IF($C37="",""," | "&INDEX(Mapping!$B$5:$B$26,MATCH($C37,Mapping!$A$5:$A$26,0))&" | "&INDEX(Mapping!$B$30:$B$41,MATCH($B37,Mapping!$A$30:$A$41,0))) | I37: =INDEX(Variables!$C$5:$C$105,MATCH($A37,Variables!$A$5:$A$105,0)) | J37: =INDEX(Variables!$E$5:$E$105,MATCH($A37,Variables!$A$5:$A$105,0)) | K37: =LOWER(Settings!$C$4)&".mit."&$A37&IF($C37="","","."&$C37&"."&$B37)&IF(INDEX(Variables!$D$5:$D$105,MATCH($A37,Variables!$A$5:$A$105,0))="","","."&INDEX(Variables!$D$5:$D$105,MATCH($A37,Variables!$A$5:$A$105,0)))&"."&K$5 | L37: =INDEX(MTInputs!$J$1:$AZ$415,$D37,MATCH(L$5,MTInputs!$J$5:$AZ$5,0)) | M37: =INDEX(MTInputs!$J$1:$AZ$415,$D37,MATCH(M$5,MTInputs!$J$5:$AZ$5,0)) | N37: =INDEX(MTInputs!$J$1:$AZ$415,$D37,MATCH(N$5,MTInputs!$J$5:$AZ$5,0)) | O37: =INDEX(MTInputs!$J$1:$AZ$415,$D37,MATCH(O$5,MTInputs!$J$5:$AZ$5,0)) | P37: =INDEX(MTInputs!$J$1:$AZ$415,$D37,MATCH(P$5,MTInputs!$J$5:$AZ$5,0)) | Q37: =INDEX(MTInputs!$J$1:$AZ$415,$D37,MATCH(Q$5,MTInputs!$J$5:$AZ$5,0)) | R37: =INDEX(MTInputs!$J$1:$AZ$415,$D37,MATCH(R$5,MTInputs!$J$5:$AZ$5,0)) | S37: =INDEX(MTInputs!$J$1:$AZ$415,$D37,MATCH(S$5,MTInputs!$J$5:$AZ$5,0)) | ... AD37: =INDEX(MTInputs!$J$1:$AZ$415,$D37,MATCH(AD$5,MTInputs!$J$5:$AZ$5,0)) | AE37: =LOWER(Settings!$C$4)&".mit."&$A37&IF($C37="","","."&$C37&"."&$B37)&IF(INDEX(Variables!$D$5:$D$105,MATCH($A37,Variables!$A$5:$A$105,0))="","","."&INDEX(Variables!$D$5:$D$105,MATCH($A37,Variables!$A$5:$A$105,0)))&"."&AE$5 | AF37: =INDEX(MTInputs!$J$1:$AZ$415,$D37,MATCH(AF$5,MTInputs!$J$5:$AZ$5,0)) | AG37: =INDEX(MTInputs!$J$1:$AZ$415,$D37,MATCH(AG$5,MTInputs!$J$5:$AZ$5,0)) | AH37: =INDEX(MTInputs!$J$1:$AZ$415,$D37,MATCH(AH$5,MTInputs!$J$5:$AZ$5,0)) | AI37: =INDEX(MTInputs!$J$1:$AZ$415,$D37,MATCH(AI$5,MTInputs!$J$5:$AZ$5,0)) | AJ37: =INDEX(MTInputs!$J$1:$AZ$415,$D37,MATCH(AJ$5,MTInputs!$J$5:$AZ$5,0)) | AK37: =INDEX(MTInputs!$J$1:$AZ$415,$D37,MATCH(AK$5,MTInputs!$J$5:$AZ$5,0)) | AL37: =INDEX(MTInputs!$J$1:$AZ$415,$D37,MATCH(AL$5,MTInputs!$J$5:$AZ$5,0)) | AM37: =INDEX(MTInputs!$J$1:$AZ$415,$D37,MATCH(AM$5,MTInputs!$J$5:$AZ$5,0)) | ... AX37: =INDEX(MTInputs!$J$1:$AZ$415,$D37,MATCH(AX$5,MTInputs!$J$5:$AZ$5,0))
A38: ctcov | B38: all | C38: mch | D38: 39 | H38: =INDEX(Variables!$B$5:$B$105,MATCH($A38,Variables!$A$5:$A$105,0))&IF($C38="",""," | "&INDEX(Mapping!$B$5:$B$26,MATCH($C38,Mapping!$A$5:$A$26,0))&" | "&INDEX(Mapping!$B$30:$B$41,MATCH($B38,Mapping!$A$30:$A$41,0))) | I38: =INDEX(Variables!$C$5:$C$105,MATCH($A38,Variables!$A$5:$A$105,0)) | J38: =INDEX(Variables!$E$5:$E$105,MATCH($A38,Variables!$A$5:$A$105,0)) | K38: =LOWER(Settings!$C$4)&".mit."&$A38&IF($C38="","","."&$C38&"."&$B38)&IF(INDEX(Variables!$D$5:$D$105,MATCH($A38,Variables!$A$5:$A$105,0))="","","."&INDEX(Variables!$D$5:$D$105,MATCH($A38,Variables!$A$5:$A$105,0)))&"."&K$5 | L38: =INDEX(MTInputs!$J$1:$AZ$415,$D38,MATCH(L$5,MTInputs!$J$5:$AZ$5,0)) | M38: =INDEX(MTInputs!$J$1:$AZ$415,$D38,MATCH(M$5,MTInputs!$J$5:$AZ$5,0)) | N38: =INDEX(MTInputs!$J$1:$AZ$415,$D38,MATCH(N$5,MTInputs!$J$5:$AZ$5,0)) | O38: =INDEX(MTInputs!$J$1:$AZ$415,$D38,MATCH(O$5,MTInputs!$J$5:$AZ$5,0)) | P38: =INDEX(MTInputs!$J$1:$AZ$415,$D38,MATCH(P$5,MTInputs!$J$5:$AZ$5,0)) | Q38: =INDEX(MTInputs!$J$1:$AZ$415,$D38,MATCH(Q$5,MTInputs!$J$5:$AZ$5,0)) | R38: =INDEX(MTInputs!$J$1:$AZ$415,$D38,MATCH(R$5,MTInputs!$J$5:$AZ$5,0)) | S38: =INDEX(MTInputs!$J$1:$AZ$415,$D38,MATCH(S$5,MTInputs!$J$5:$AZ$5,0)) | ... AD38: =INDEX(MTInputs!$J$1:$AZ$415,$D38,MATCH(AD$5,MTInputs!$J$5:$AZ$5,0)) | AE38: =LOWER(Settings!$C$4)&".mit."&$A38&IF($C38="","","."&$C38&"."&$B38)&IF(INDEX(Variables!$D$5:$D$105,MATCH($A38,Variables!$A$5:$A$105,0))="","","."&INDEX(Variables!$D$5:$D$105,MATCH($A38,Variables!$A$5:$A$105,0)))&"."&AE$5 | AF38: =INDEX(MTInputs!$J$1:$AZ$415,$D38,MATCH(AF$5,MTInputs!$J$5:$AZ$5,0)) | AG38: =INDEX(MTInputs!$J$1:$AZ$415,$D38,MATCH(AG$5,MTInputs!$J$5:$AZ$5,0)) | AH38: =INDEX(MTInputs!$J$1:$AZ$415,$D38,MATCH(AH$5,MTInputs!$J$5:$AZ$5,0)) | AI38: =INDEX(MTInputs!$J$1:$AZ$415,$D38,MATCH(AI$5,MTInputs!$J$5:$AZ$5,0)) | AJ38: =INDEX(MTInputs!$J$1:$AZ$415,$D38,MATCH(AJ$5,MTInputs!$J$5:$AZ$5,0)) | AK38: =INDEX(MTInputs!$J$1:$AZ$415,$D38,MATCH(AK$5,MTInputs!$J$5:$AZ$5,0)) | AL38: =INDEX(MTInputs!$J$1:$AZ$415,$D38,MATCH(AL$5,MTInputs!$J$5:$AZ$5,0)) | AM38: =INDEX(MTInputs!$J$1:$AZ$415,$D38,MATCH(AM$5,MTInputs!$J$5:$AZ$5,0)) | ... AX38: =INDEX(MTInputs!$J$1:$AZ$415,$D38,MATCH(AX$5,MTInputs!$J$5:$AZ$5,0))
A39: ctcov | B39: all | C39: irn | D39: 40 | H39: =INDEX(Variables!$B$5:$B$105,MATCH($A39,Variables!$A$5:$A$105,0))&IF($C39="",""," | "&INDEX(Mapping!$B$5:$B$26,MATCH($C39,Mapping!$A$5:$A$26,0))&" | "&INDEX(Mapping!$B$30:$B$41,MATCH($B39,Mapping!$A$30:$A$41,0))) | I39: =INDEX(Variables!$C$5:$C$105,MATCH($A39,Variables!$A$5:$A$105,0)) | J39: =INDEX(Variables!$E$5:$E$105,MATCH($A39,Variables!$A$5:$A$105,0)) | K39: =LOWER(Settings!$C$4)&".mit."&$A39&IF($C39="","","."&$C39&"."&$B39)&IF(INDEX(Variables!$D$5:$D$105,MATCH($A39,Variables!$A$5:$A$105,0))="","","."&INDEX(Variables!$D$5:$D$105,MATCH($A39,Variables!$A$5:$A$105,0)))&"."&K$5 | L39: =INDEX(MTInputs!$J$1:$AZ$415,$D39,MATCH(L$5,MTInputs!$J$5:$AZ$5,0)) | M39: =INDEX(MTInputs!$J$1:$AZ$415,$D39,MATCH(M$5,MTInputs!$J$5:$AZ$5,0)) | N39: =INDEX(MTInputs!$J$1:$AZ$415,$D39,MATCH(N$5,MTInputs!$J$5:$AZ$5,0)) | O39: =INDEX(MTInputs!$J$1:$AZ$415,$D39,MATCH(O$5,MTInputs!$J$5:$AZ$5,0)) | P39: =INDEX(MTInputs!$J$1:$AZ$415,$D39,MATCH(P$5,MTInputs!$J$5:$AZ$5,0)) | Q39: =INDEX(MTInputs!$J$1:$AZ$415,$D39,MATCH(Q$5,MTInputs!$J$5:$AZ$5,0)) | R39: =INDEX(MTInputs!$J$1:$AZ$415,$D39,MATCH(R$5,MTInputs!$J$5:$AZ$5,0)) | S39: =INDEX(MTInputs!$J$1:$AZ$415,$D39,MATCH(S$5,MTInputs!$J$5:$AZ$5,0)) | ... AD39: =INDEX(MTInputs!$J$1:$AZ$415,$D39,MATCH(AD$5,MTInputs!$J$5:$AZ$5,0)) | AE39: =LOWER(Settings!$C$4)&".mit."&$A39&IF($C39="","","."&$C39&"."&$B39)&IF(INDEX(Variables!$D$5:$D$105,MATCH($A39,Variables!$A$5:$A$105,0))="","","."&INDEX(Variables!$D$5:$D$105,MATCH($A39,Variables!$A$5:$A$105,0)))&"."&AE$5 | AF39: =INDEX(MTInputs!$J$1:$AZ$415,$D39,MATCH(AF$5,MTInputs!$J$5:$AZ$5,0)) | AG39: =INDEX(MTInputs!$J$1:$AZ$415,$D39,MATCH(AG$5,MTInputs!$J$5:$AZ$5,0)) | AH39: =INDEX(MTInputs!$J$1:$AZ$415,$D39,MATCH(AH$5,MTInputs!$J$5:$AZ$5,0)) | AI39: =INDEX(MTInputs!$J$1:$AZ$415,$D39,MATCH(AI$5,MTInputs!$J$5:$AZ$5,0)) | AJ39: =INDEX(MTInputs!$J$1:$AZ$415,$D39,MATCH(AJ$5,MTInputs!$J$5:$AZ$5,0)) | AK39: =INDEX(MTInputs!$J$1:$AZ$415,$D39,MATCH(AK$5,MTInputs!$J$5:$AZ$5,0)) | AL39: =INDEX(MTInputs!$J$1:$AZ$415,$D39,MATCH(AL$5,MTInputs!$J$5:$AZ$5,0)) | AM39: =INDEX(MTInputs!$J$1:$AZ$415,$D39,MATCH(AM$5,MTInputs!$J$5:$AZ$5,0)) | ... AX39: =INDEX(MTInputs!$J$1:$AZ$415,$D39,MATCH(AX$5,MTInputs!$J$5:$AZ$5,0))
A40: ctcov | B40: all | C40: nfm | D40: 41 | H40: =INDEX(Variables!$B$5:$B$105,MATCH($A40,Variables!$A$5:$A$105,0))&IF($C40="",""," | "&INDEX(Mapping!$B$5:$B$26,MATCH($C40,Mapping!$A$5:$A$26,0))&" | "&INDEX(Mapping!$B$30:$B$41,MATCH($B40,Mapping!$A$30:$A$41,0))) | I40: =INDEX(Variables!$C$5:$C$105,MATCH($A40,Variables!$A$5:$A$105,0)) | J40: =INDEX(Variables!$E$5:$E$105,MATCH($A40,Variables!$A$5:$A$105,0)) | K40: =LOWER(Settings!$C$4)&".mit."&$A40&IF($C40="","","."&$C40&"."&$B40)&IF(INDEX(Variables!$D$5:$D$105,MATCH($A40,Variables!$A$5:$A$105,0))="","","."&INDEX(Variables!$D$5:$D$105,MATCH($A40,Variables!$A$5:$A$105,0)))&"."&K$5 | L40: =INDEX(MTInputs!$J$1:$AZ$415,$D40,MATCH(L$5,MTInputs!$J$5:$AZ$5,0)) | M40: =INDEX(MTInputs!$J$1:$AZ$415,$D40,MATCH(M$5,MTInputs!$J$5:$AZ$5,0)) | N40: =INDEX(MTInputs!$J$1:$AZ$415,$D40,MATCH(N$5,MTInputs!$J$5:$AZ$5,0)) | O40: =INDEX(MTInputs!$J$1:$AZ$415,$D40,MATCH(O$5,MTInputs!$J$5:$AZ$5,0)) | P40: =INDEX(MTInputs!$J$1:$AZ$415,$D40,MATCH(P$5,MTInputs!$J$5:$AZ$5,0)) | Q40: =INDEX(MTInputs!$J$1:$AZ$415,$D40,MATCH(Q$5,MTInputs!$J$5:$AZ$5,0)) | R40: =INDEX(MTInputs!$J$1:$AZ$415,$D40,MATCH(R$5,MTInputs!$J$5:$AZ$5,0)) | S40: =INDEX(MTInputs!$J$1:$AZ$415,$D40,MATCH(S$5,MTInputs!$J$5:$AZ$5,0)) | ... AD40: =INDEX(MTInputs!$J$1:$AZ$415,$D40,MATCH(AD$5,MTInputs!$J$5:$AZ$5,0)) | AE40: =LOWER(Settings!$C$4)&".mit."&$A40&IF($C40="","","."&$C40&"."&$B40)&IF(INDEX(Variables!$D$5:$D$105,MATCH($A40,Variables!$A$5:$A$105,0))="","","."&INDEX(Variables!$D$5:$D$105,MATCH($A40,Variables!$A$5:$A$105,0)))&"."&AE$5 | AF40: =INDEX(MTInputs!$J$1:$AZ$415,$D40,MATCH(AF$5,MTInputs!$J$5:$AZ$5,0)) | AG40: =INDEX(MTInputs!$J$1:$AZ$415,$D40,MATCH(AG$5,MTInputs!$J$5:$AZ$5,0)) | AH40: =INDEX(MTInputs!$J$1:$AZ$415,$D40,MATCH(AH$5,MTInputs!$J$5:$AZ$5,0)) | AI40: =INDEX(MTInputs!$J$1:$AZ$415,$D40,MATCH(AI$5,MTInputs!$J$5:$AZ$5,0)) | AJ40: =INDEX(MTInputs!$J$1:$AZ$415,$D40,MATCH(AJ$5,MTInputs!$J$5:$AZ$5,0)) | AK40: =INDEX(MTInputs!$J$1:$AZ$415,$D40,MATCH(AK$5,MTInputs!$J$5:$AZ$5,0)) | AL40: =INDEX(MTInputs!$J$1:$AZ$415,$D40,MATCH(AL$5,MTInputs!$J$5:$AZ$5,0)) | AM40: =INDEX(MTInputs!$J$1:$AZ$415,$D40,MATCH(AM$5,MTInputs!$J$5:$AZ$5,0)) | ... AX40: =INDEX(MTInputs!$J$1:$AZ$415,$D40,MATCH(AX$5,MTInputs!$J$5:$AZ$5,0))
A41: ctcov | B41: all | C41: mac | D41: 42 | H41: =INDEX(Variables!$B$5:$B$105,MATCH($A41,Variables!$A$5:$A$105,0))&IF($C41="",""," | "&INDEX(Mapping!$B$5:$B$26,MATCH($C41,Mapping!$A$5:$A$26,0))&" | "&INDEX(Mapping!$B$30:$B$41,MATCH($B41,Mapping!$A$30:$A$41,0))) | I41: =INDEX(Variables!$C$5:$C$105,MATCH($A41,Variables!$A$5:$A$105,0)) | J41: =INDEX(Variables!$E$5:$E$105,MATCH($A41,Variables!$A$5:$A$105,0)) | K41: =LOWER(Settings!$C$4)&".mit."&$A41&IF($C41="","","."&$C41&"."&$B41)&IF(INDEX(Variables!$D$5:$D$105,MATCH($A41,Variables!$A$5:$A$105,0))="","","."&INDEX(Variables!$D$5:$D$105,MATCH($A41,Variables!$A$5:$A$105,0)))&"."&K$5 | L41: =INDEX(MTInputs!$J$1:$AZ$415,$D41,MATCH(L$5,MTInputs!$J$5:$AZ$5,0)) | M41: =INDEX(MTInputs!$J$1:$AZ$415,$D41,MATCH(M$5,MTInputs!$J$5:$AZ$5,0)) | N41: =INDEX(MTInputs!$J$1:$AZ$415,$D41,MATCH(N$5,MTInputs!$J$5:$AZ$5,0)) | O41: =INDEX(MTInputs!$J$1:$AZ$415,$D41,MATCH(O$5,MTInputs!$J$5:$AZ$5,0)) | P41: =INDEX(MTInputs!$J$1:$AZ$415,$D41,MATCH(P$5,MTInputs!$J$5:$AZ$5,0)) | Q41: =INDEX(MTInputs!$J$1:$AZ$415,$D41,MATCH(Q$5,MTInputs!$J$5:$AZ$5,0)) | R41: =INDEX(MTInputs!$J$1:$AZ$415,$D41,MATCH(R$5,MTInputs!$J$5:$AZ$5,0)) | S41: =INDEX(MTInputs!$J$1:$AZ$415,$D41,MATCH(S$5,MTInputs!$J$5:$AZ$5,0)) | ... AD41: =INDEX(MTInputs!$J$1:$AZ$415,$D41,MATCH(AD$5,MTInputs!$J$5:$AZ$5,0)) | AE41: =LOWER(Settings!$C$4)&".mit."&$A41&IF($C41="","","."&$C41&"."&$B41)&IF(INDEX(Variables!$D$5:$D$105,MATCH($A41,Variables!$A$5:$A$105,0))="","","."&INDEX(Variables!$D$5:$D$105,MATCH($A41,Variables!$A$5:$A$105,0)))&"."&AE$5 | AF41: =INDEX(MTInputs!$J$1:$AZ$415,$D41,MATCH(AF$5,MTInputs!$J$5:$AZ$5,0)) | AG41: =INDEX(MTInputs!$J$1:$AZ$415,$D41,MATCH(AG$5,MTInputs!$J$5:$AZ$5,0)) | AH41: =INDEX(MTInputs!$J$1:$AZ$415,$D41,MATCH(AH$5,MTInputs!$J$5:$AZ$5,0)) | AI41: =INDEX(MTInputs!$J$1:$AZ$415,$D41,MATCH(AI$5,MTInputs!$J$5:$AZ$5,0)) | AJ41: =INDEX(MTInputs!$J$1:$AZ$415,$D41,MATCH(AJ$5,MTInputs!$J$5:$AZ$5,0)) | AK41: =INDEX(MTInputs!$J$1:$AZ$415,$D41,MATCH(AK$5,MTInputs!$J$5:$AZ$5,0)) | AL41: =INDEX(MTInputs!$J$1:$AZ$415,$D41,MATCH(AL$5,MTInputs!$J$5:$AZ$5,0)) | AM41: =INDEX(MTInputs!$J$1:$AZ$415,$D41,MATCH(AM$5,MTInputs!$J$5:$AZ$5,0)) | ... AX41: =INDEX(MTInputs!$J$1:$AZ$415,$D41,MATCH(AX$5,MTInputs!$J$5:$AZ$5,0))
... A46: ctcov | B46: all | C46: oen | D46: 47 | H46: =INDEX(Variables!$B$5:$B$105,MATCH($A46,Variables!$A$5:$A$105,0))&IF($C46="",""," | "&INDEX(Mapping!$B$5:$B$26,MATCH($C46,Mapping!$A$5:$A$26,0))&" | "&INDEX(Mapping!$B$30:$B$41,MATCH($B46,Mapping!$A$30:$A$41,0))) | I46: =INDEX(Variables!$C$5:$C$105,MATCH($A46,Variables!$A$5:$A$105,0)) | J46: =INDEX(Variables!$E$5:$E$105,MATCH($A46,Variables!$A$5:$A$105,0)) | K46: =LOWER(Settings!$C$4)&".mit."&$A46&IF($C46="","","."&$C46&"."&$B46)&IF(INDEX(Variables!$D$5:$D$105,MATCH($A46,Variables!$A$5:$A$105,0))="","","."&INDEX(Variables!$D$5:$D$105,MATCH($A46,Variables!$A$5:$A$105,0)))&"."&K$5 | L46: =INDEX(MTInputs!$J$1:$AZ$415,$D46,MATCH(L$5,MTInputs!$J$5:$AZ$5,0)) | M46: =INDEX(MTInputs!$J$1:$AZ$415,$D46,MATCH(M$5,MTInputs!$J$5:$AZ$5,0)) | N46: =INDEX(MTInputs!$J$1:$AZ$415,$D46,MATCH(N$5,MTInputs!$J$5:$AZ$5,0)) | O46: =INDEX(MTInputs!$J$1:$AZ$415,$D46,MATCH(O$5,MTInputs!$J$5:$AZ$5,0)) | P46: =INDEX(MTInputs!$J$1:$AZ$415,$D46,MATCH(P$5,MTInputs!$J$5:$AZ$5,0)) | Q46: =INDEX(MTInputs!$J$1:$AZ$415,$D46,MATCH(Q$5,MTInputs!$J$5:$AZ$5,0)) | R46: =INDEX(MTInputs!$J$1:$AZ$415,$D46,MATCH(R$5,MTInputs!$J$5:$AZ$5,0)) | S46: =INDEX(MTInputs!$J$1:$AZ$415,$D46,MATCH(S$5,MTInputs!$J$5:$AZ$5,0)) | ... AD46: =INDEX(MTInputs!$J$1:$AZ$415,$D46,MATCH(AD$5,MTInputs!$J$5:$AZ$5,0)) | AE46: =LOWER(Settings!$C$4)&".mit."&$A46&IF($C46="","","."&$C46&"."&$B46)&IF(INDEX(Variables!$D$5:$D$105,MATCH($A46,Variables!$A$5:$A$105,0))="","","."&INDEX(Variables!$D$5:$D$105,MATCH($A46,Variables!$A$5:$A$105,0)))&"."&AE$5 | AF46: =INDEX(MTInputs!$J$1:$AZ$415,$D46,MATCH(AF$5,MTInputs!$J$5:$AZ$5,0)) | AG46: =INDEX(MTInputs!$J$1:$AZ$415,$D46,MATCH(AG$5,MTInputs!$J$5:$AZ$5,0)) | AH46: =INDEX(MTInputs!$J$1:$AZ$415,$D46,MATCH(AH$5,MTInputs!$J$5:$AZ$5,0)) | AI46: =INDEX(MTInputs!$J$1:$AZ$415,$D46,MATCH(AI$5,MTInputs!$J$5:$AZ$5,0)) | AJ46: =INDEX(MTInputs!$J$1:$AZ$415,$D46,MATCH(AJ$5,MTInputs!$J$5:$AZ$5,0)) | AK46: =INDEX(MTInputs!$J$1:$AZ$415,$D46,MATCH(AK$5,MTInputs!$J$5:$AZ$5,0)) | AL46: =INDEX(MTInputs!$J$1:$AZ$415,$D46,MATCH(AL$5,MTInputs!$J$5:$AZ$5,0)) | AM46: =INDEX(MTInputs!$J$1:$AZ$415,$D46,MATCH(AM$5,MTInputs!$J$5:$AZ$5,0)) | ... AX46: =INDEX(MTInputs!$J$1:$AZ$415,$D46,MATCH(AX$5,MTInputs!$J$5:$AZ$5,0))
H47: Fuel price reform (MTInputs rows 140-169; increases in price units)
A48: fpr.yr0 | D48: 140 | H48: =INDEX(Variables!$B$5:$B$105,MATCH($A48,Variables!$A$5:$A$105,0))&IF($C48="",""," | "&INDEX(Mapping!$B$5:$B$26,MATCH($C48,Mapping!$A$5:$A$26,0))&" | "&INDEX(Mapping!$B$30:$B$41,MATCH($B48,Mapping!$A$30:$A$41,0))) | I48: =INDEX(Variables!$C$5:$C$105,MATCH($A48,Variables!$A$5:$A$105,0)) | J48: =INDEX(Variables!$E$5:$E$105,MATCH($A48,Variables!$A$5:$A$105,0)) | K48: =LOWER(Settings!$C$4)&".mit."&$A48&IF($C48="","","."&$C48&"."&$B48)&IF(INDEX(Variables!$D$5:$D$105,MATCH($A48,Variables!$A$5:$A$105,0))="","","."&INDEX(Variables!$D$5:$D$105,MATCH($A48,Variables!$A$5:$A$105,0)))&"."&K$5 | L48: =INDEX(MTInputs!$J$1:$AZ$415,$D48,MATCH(L$5,MTInputs!$J$5:$AZ$5,0)) | M48: =INDEX(MTInputs!$J$1:$AZ$415,$D48,MATCH(M$5,MTInputs!$J$5:$AZ$5,0)) | N48: =INDEX(MTInputs!$J$1:$AZ$415,$D48,MATCH(N$5,MTInputs!$J$5:$AZ$5,0)) | O48: =INDEX(MTInputs!$J$1:$AZ$415,$D48,MATCH(O$5,MTInputs!$J$5:$AZ$5,0)) | P48: =INDEX(MTInputs!$J$1:$AZ$415,$D48,MATCH(P$5,MTInputs!$J$5:$AZ$5,0)) | Q48: =INDEX(MTInputs!$J$1:$AZ$415,$D48,MATCH(Q$5,MTInputs!$J$5:$AZ$5,0)) | R48: =INDEX(MTInputs!$J$1:$AZ$415,$D48,MATCH(R$5,MTInputs!$J$5:$AZ$5,0)) | S48: =INDEX(MTInputs!$J$1:$AZ$415,$D48,MATCH(S$5,MTInputs!$J$5:$AZ$5,0)) | ... AD48: =INDEX(MTInputs!$J$1:$AZ$415,$D48,MATCH(AD$5,MTInputs!$J$5:$AZ$5,0)) | AE48: =LOWER(Settings!$C$4)&".mit."&$A48&IF($C48="","","."&$C48&"."&$B48)&IF(INDEX(Variables!$D$5:$D$105,MATCH($A48,Variables!$A$5:$A$105,0))="","","."&INDEX(Variables!$D$5:$D$105,MATCH($A48,Variables!$A$5:$A$105,0)))&"."&AE$5 | AF48: =INDEX(MTInputs!$J$1:$AZ$415,$D48,MATCH(AF$5,MTInputs!$J$5:$AZ$5,0)) | AG48: =INDEX(MTInputs!$J$1:$AZ$415,$D48,MATCH(AG$5,MTInputs!$J$5:$AZ$5,0)) | AH48: =INDEX(MTInputs!$J$1:$AZ$415,$D48,MATCH(AH$5,MTInputs!$J$5:$AZ$5,0)) | AI48: =INDEX(MTInputs!$J$1:$AZ$415,$D48,MATCH(AI$5,MTInputs!$J$5:$AZ$5,0)) | AJ48: =INDEX(MTInputs!$J$1:$AZ$415,$D48,MATCH(AJ$5,MTInputs!$J$5:$AZ$5,0)) | AK48: =INDEX(MTInputs!$J$1:$AZ$415,$D48,MATCH(AK$5,MTInputs!$J$5:$AZ$5,0)) | AL48: =INDEX(MTInputs!$J$1:$AZ$415,$D48,MATCH(AL$5,MTInputs!$J$5:$AZ$5,0)) | AM48: =INDEX(MTInputs!$J$1:$AZ$415,$D48,MATCH(AM$5,MTInputs!$J$5:$AZ$5,0)) | ... AX48: =INDEX(MTInputs!$J$1:$AZ$415,$D48,MATCH(AX$5,MTInputs!$J$5:$AZ$5,0))
A49: fpr.yr1 | D49: 141 | H49: =INDEX(Variables!$B$5:$B$105,MATCH($A49,Variables!$A$5:$A$105,0))&IF($C49="",""," | "&INDEX(Mapping!$B$5:$B$26,MATCH($C49,Mapping!$A$5:$A$26,0))&" | "&INDEX(Mapping!$B$30:$B$41,MATCH($B49,Mapping!$A$30:$A$41,0))) | I49: =INDEX(Variables!$C$5:$C$105,MATCH($A49,Variables!$A$5:$A$105,0)) | J49: =INDEX(Variables!$E$5:$E$105,MATCH($A49,Variables!$A$5:$A$105,0)) | K49: =LOWER(Settings!$C$4)&".mit."&$A49&IF($C49="","","."&$C49&"."&$B49)&IF(INDEX(Variables!$D$5:$D$105,MATCH($A49,Variables!$A$5:$A$105,0))="","","."&INDEX(Variables!$D$5:$D$105,MATCH($A49,Variables!$A$5:$A$105,0)))&"."&K$5 | L49: =INDEX(MTInputs!$J$1:$AZ$415,$D49,MATCH(L$5,MTInputs!$J$5:$AZ$5,0)) | M49: =INDEX(MTInputs!$J$1:$AZ$415,$D49,MATCH(M$5,MTInputs!$J$5:$AZ$5,0)) | N49: =INDEX(MTInputs!$J$1:$AZ$415,$D49,MATCH(N$5,MTInputs!$J$5:$AZ$5,0)) | O49: =INDEX(MTInputs!$J$1:$AZ$415,$D49,MATCH(O$5,MTInputs!$J$5:$AZ$5,0)) | P49: =INDEX(MTInputs!$J$1:$AZ$415,$D49,MATCH(P$5,MTInputs!$J$5:$AZ$5,0)) | Q49: =INDEX(MTInputs!$J$1:$AZ$415,$D49,MATCH(Q$5,MTInputs!$J$5:$AZ$5,0)) | R49: =INDEX(MTInputs!$J$1:$AZ$415,$D49,MATCH(R$5,MTInputs!$J$5:$AZ$5,0)) | S49: =INDEX(MTInputs!$J$1:$AZ$415,$D49,MATCH(S$5,MTInputs!$J$5:$AZ$5,0)) | ... AD49: =INDEX(MTInputs!$J$1:$AZ$415,$D49,MATCH(AD$5,MTInputs!$J$5:$AZ$5,0)) | AE49: =LOWER(Settings!$C$4)&".mit."&$A49&IF($C49="","","."&$C49&"."&$B49)&IF(INDEX(Variables!$D$5:$D$105,MATCH($A49,Variables!$A$5:$A$105,0))="","","."&INDEX(Variables!$D$5:$D$105,MATCH($A49,Variables!$A$5:$A$105,0)))&"."&AE$5 | AF49: =INDEX(MTInputs!$J$1:$AZ$415,$D49,MATCH(AF$5,MTInputs!$J$5:$AZ$5,0)) | AG49: =INDEX(MTInputs!$J$1:$AZ$415,$D49,MATCH(AG$5,MTInputs!$J$5:$AZ$5,0)) | AH49: =INDEX(MTInputs!$J$1:$AZ$415,$D49,MATCH(AH$5,MTInputs!$J$5:$AZ$5,0)) | AI49: =INDEX(MTInputs!$J$1:$AZ$415,$D49,MATCH(AI$5,MTInputs!$J$5:$AZ$5,0)) | AJ49: =INDEX(MTInputs!$J$1:$AZ$415,$D49,MATCH(AJ$5,MTInputs!$J$5:$AZ$5,0)) | AK49: =INDEX(MTInputs!$J$1:$AZ$415,$D49,MATCH(AK$5,MTInputs!$J$5:$AZ$5,0)) | AL49: =INDEX(MTInputs!$J$1:$AZ$415,$D49,MATCH(AL$5,MTInputs!$J$5:$AZ$5,0)) | AM49: =INDEX(MTInputs!$J$1:$AZ$415,$D49,MATCH(AM$5,MTInputs!$J$5:$AZ$5,0)) | ... AX49: =INDEX(MTInputs!$J$1:$AZ$415,$D49,MATCH(AX$5,MTInputs!$J$5:$AZ$5,0))
A50: fpr.s | B50: coa | C50: pow | D50: 142 | H50: =INDEX(Variables!$B$5:$B$105,MATCH($A50,Variables!$A$5:$A$105,0))&IF($C50="",""," | "&INDEX(Mapping!$B$5:$B$26,MATCH($C50,Mapping!$A$5:$A$26,0))&" | "&INDEX(Mapping!$B$30:$B$41,MATCH($B50,Mapping!$A$30:$A$41,0))) | I50: =INDEX(Variables!$C$5:$C$105,MATCH($A50,Variables!$A$5:$A$105,0)) | J50: =INDEX(Variables!$E$5:$E$105,MATCH($A50,Variables!$A$5:$A$105,0)) | K50: =LOWER(Settings!$C$4)&".mit."&$A50&IF($C50="","","."&$C50&"."&$B50)&IF(INDEX(Variables!$D$5:$D$105,MATCH($A50,Variables!$A$5:$A$105,0))="","","."&INDEX(Variables!$D$5:$D$105,MATCH($A50,Variables!$A$5:$A$105,0)))&"."&K$5 | L50: =INDEX(MTInputs!$J$1:$AZ$415,$D50,MATCH(L$5,MTInputs!$J$5:$AZ$5,0)) | M50: =INDEX(MTInputs!$J$1:$AZ$415,$D50,MATCH(M$5,MTInputs!$J$5:$AZ$5,0)) | N50: =INDEX(MTInputs!$J$1:$AZ$415,$D50,MATCH(N$5,MTInputs!$J$5:$AZ$5,0)) | O50: =INDEX(MTInputs!$J$1:$AZ$415,$D50,MATCH(O$5,MTInputs!$J$5:$AZ$5,0)) | P50: =INDEX(MTInputs!$J$1:$AZ$415,$D50,MATCH(P$5,MTInputs!$J$5:$AZ$5,0)) | Q50: =INDEX(MTInputs!$J$1:$AZ$415,$D50,MATCH(Q$5,MTInputs!$J$5:$AZ$5,0)) | R50: =INDEX(MTInputs!$J$1:$AZ$415,$D50,MATCH(R$5,MTInputs!$J$5:$AZ$5,0)) | S50: =INDEX(MTInputs!$J$1:$AZ$415,$D50,MATCH(S$5,MTInputs!$J$5:$AZ$5,0)) | ... AD50: =INDEX(MTInputs!$J$1:$AZ$415,$D50,MATCH(AD$5,MTInputs!$J$5:$AZ$5,0)) | AE50: =LOWER(Settings!$C$4)&".mit."&$A50&IF($C50="","","."&$C50&"."&$B50)&IF(INDEX(Variables!$D$5:$D$105,MATCH($A50,Variables!$A$5:$A$105,0))="","","."&INDEX(Variables!$D$5:$D$105,MATCH($A50,Variables!$A$5:$A$105,0)))&"."&AE$5 | AF50: =INDEX(MTInputs!$J$1:$AZ$415,$D50,MATCH(AF$5,MTInputs!$J$5:$AZ$5,0)) | AG50: =INDEX(MTInputs!$J$1:$AZ$415,$D50,MATCH(AG$5,MTInputs!$J$5:$AZ$5,0)) | AH50: =INDEX(MTInputs!$J$1:$AZ$415,$D50,MATCH(AH$5,MTInputs!$J$5:$AZ$5,0)) | AI50: =INDEX(MTInputs!$J$1:$AZ$415,$D50,MATCH(AI$5,MTInputs!$J$5:$AZ$5,0)) | AJ50: =INDEX(MTInputs!$J$1:$AZ$415,$D50,MATCH(AJ$5,MTInputs!$J$5:$AZ$5,0)) | AK50: =INDEX(MTInputs!$J$1:$AZ$415,$D50,MATCH(AK$5,MTInputs!$J$5:$AZ$5,0)) | AL50: =INDEX(MTInputs!$J$1:$AZ$415,$D50,MATCH(AL$5,MTInputs!$J$5:$AZ$5,0)) | AM50: =INDEX(MTInputs!$J$1:$AZ$415,$D50,MATCH(AM$5,MTInputs!$J$5:$AZ$5,0)) | ... AX50: =INDEX(MTInputs!$J$1:$AZ$415,$D50,MATCH(AX$5,MTInputs!$J$5:$AZ$5,0))
A51: fpr.s | B51: coa | C51: res | D51: 143 | H51: =INDEX(Variables!$B$5:$B$105,MATCH($A51,Variables!$A$5:$A$105,0))&IF($C51="",""," | "&INDEX(Mapping!$B$5:$B$26,MATCH($C51,Mapping!$A$5:$A$26,0))&" | "&INDEX(Mapping!$B$30:$B$41,MATCH($B51,Mapping!$A$30:$A$41,0))) | I51: =INDEX(Variables!$C$5:$C$105,MATCH($A51,Variables!$A$5:$A$105,0)) | J51: =INDEX(Variables!$E$5:$E$105,MATCH($A51,Variables!$A$5:$A$105,0)) | K51: =LOWER(Settings!$C$4)&".mit."&$A51&IF($C51="","","."&$C51&"."&$B51)&IF(INDEX(Variables!$D$5:$D$105,MATCH($A51,Variables!$A$5:$A$105,0))="","","."&INDEX(Variables!$D$5:$D$105,MATCH($A51,Variables!$A$5:$A$105,0)))&"."&K$5 | L51: =INDEX(MTInputs!$J$1:$AZ$415,$D51,MATCH(L$5,MTInputs!$J$5:$AZ$5,0)) | M51: =INDEX(MTInputs!$J$1:$AZ$415,$D51,MATCH(M$5,MTInputs!$J$5:$AZ$5,0)) | N51: =INDEX(MTInputs!$J$1:$AZ$415,$D51,MATCH(N$5,MTInputs!$J$5:$AZ$5,0)) | O51: =INDEX(MTInputs!$J$1:$AZ$415,$D51,MATCH(O$5,MTInputs!$J$5:$AZ$5,0)) | P51: =INDEX(MTInputs!$J$1:$AZ$415,$D51,MATCH(P$5,MTInputs!$J$5:$AZ$5,0)) | Q51: =INDEX(MTInputs!$J$1:$AZ$415,$D51,MATCH(Q$5,MTInputs!$J$5:$AZ$5,0)) | R51: =INDEX(MTInputs!$J$1:$AZ$415,$D51,MATCH(R$5,MTInputs!$J$5:$AZ$5,0)) | S51: =INDEX(MTInputs!$J$1:$AZ$415,$D51,MATCH(S$5,MTInputs!$J$5:$AZ$5,0)) | ... AD51: =INDEX(MTInputs!$J$1:$AZ$415,$D51,MATCH(AD$5,MTInputs!$J$5:$AZ$5,0)) | AE51: =LOWER(Settings!$C$4)&".mit."&$A51&IF($C51="","","."&$C51&"."&$B51)&IF(INDEX(Variables!$D$5:$D$105,MATCH($A51,Variables!$A$5:$A$105,0))="","","."&INDEX(Variables!$D$5:$D$105,MATCH($A51,Variables!$A$5:$A$105,0)))&"."&AE$5 | AF51: =INDEX(MTInputs!$J$1:$AZ$415,$D51,MATCH(AF$5,MTInputs!$J$5:$AZ$5,0)) | AG51: =INDEX(MTInputs!$J$1:$AZ$415,$D51,MATCH(AG$5,MTInputs!$J$5:$AZ$5,0)) | AH51: =INDEX(MTInputs!$J$1:$AZ$415,$D51,MATCH(AH$5,MTInputs!$J$5:$AZ$5,0)) | AI51: =INDEX(MTInputs!$J$1:$AZ$415,$D51,MATCH(AI$5,MTInputs!$J$5:$AZ$5,0)) | AJ51: =INDEX(MTInputs!$J$1:$AZ$415,$D51,MATCH(AJ$5,MTInputs!$J$5:$AZ$5,0)) | AK51: =INDEX(MTInputs!$J$1:$AZ$415,$D51,MATCH(AK$5,MTInputs!$J$5:$AZ$5,0)) | AL51: =INDEX(MTInputs!$J$1:$AZ$415,$D51,MATCH(AL$5,MTInputs!$J$5:$AZ$5,0)) | AM51: =INDEX(MTInputs!$J$1:$AZ$415,$D51,MATCH(AM$5,MTInputs!$J$5:$AZ$5,0)) | ... AX51: =INDEX(MTInputs!$J$1:$AZ$415,$D51,MATCH(AX$5,MTInputs!$J$5:$AZ$5,0))
A52: fpr.s | B52: coa | C52: ind | D52: 144 | H52: =INDEX(Variables!$B$5:$B$105,MATCH($A52,Variables!$A$5:$A$105,0))&IF($C52="",""," | "&INDEX(Mapping!$B$5:$B$26,MATCH($C52,Mapping!$A$5:$A$26,0))&" | "&INDEX(Mapping!$B$30:$B$41,MATCH($B52,Mapping!$A$30:$A$41,0))) | I52: =INDEX(Variables!$C$5:$C$105,MATCH($A52,Variables!$A$5:$A$105,0)) | J52: =INDEX(Variables!$E$5:$E$105,MATCH($A52,Variables!$A$5:$A$105,0)) | K52: =LOWER(Settings!$C$4)&".mit."&$A52&IF($C52="","","."&$C52&"."&$B52)&IF(INDEX(Variables!$D$5:$D$105,MATCH($A52,Variables!$A$5:$A$105,0))="","","."&INDEX(Variables!$D$5:$D$105,MATCH($A52,Variables!$A$5:$A$105,0)))&"."&K$5 | L52: =INDEX(MTInputs!$J$1:$AZ$415,$D52,MATCH(L$5,MTInputs!$J$5:$AZ$5,0)) | M52: =INDEX(MTInputs!$J$1:$AZ$415,$D52,MATCH(M$5,MTInputs!$J$5:$AZ$5,0)) | N52: =INDEX(MTInputs!$J$1:$AZ$415,$D52,MATCH(N$5,MTInputs!$J$5:$AZ$5,0)) | O52: =INDEX(MTInputs!$J$1:$AZ$415,$D52,MATCH(O$5,MTInputs!$J$5:$AZ$5,0)) | P52: =INDEX(MTInputs!$J$1:$AZ$415,$D52,MATCH(P$5,MTInputs!$J$5:$AZ$5,0)) | Q52: =INDEX(MTInputs!$J$1:$AZ$415,$D52,MATCH(Q$5,MTInputs!$J$5:$AZ$5,0)) | R52: =INDEX(MTInputs!$J$1:$AZ$415,$D52,MATCH(R$5,MTInputs!$J$5:$AZ$5,0)) | S52: =INDEX(MTInputs!$J$1:$AZ$415,$D52,MATCH(S$5,MTInputs!$J$5:$AZ$5,0)) | ... AD52: =INDEX(MTInputs!$J$1:$AZ$415,$D52,MATCH(AD$5,MTInputs!$J$5:$AZ$5,0)) | AE52: =LOWER(Settings!$C$4)&".mit."&$A52&IF($C52="","","."&$C52&"."&$B52)&IF(INDEX(Variables!$D$5:$D$105,MATCH($A52,Variables!$A$5:$A$105,0))="","","."&INDEX(Variables!$D$5:$D$105,MATCH($A52,Variables!$A$5:$A$105,0)))&"."&AE$5 | AF52: =INDEX(MTInputs!$J$1:$AZ$415,$D52,MATCH(AF$5,MTInputs!$J$5:$AZ$5,0)) | AG52: =INDEX(MTInputs!$J$1:$AZ$415,$D52,MATCH(AG$5,MTInputs!$J$5:$AZ$5,0)) | AH52: =INDEX(MTInputs!$J$1:$AZ$415,$D52,MATCH(AH$5,MTInputs!$J$5:$AZ$5,0)) | AI52: =INDEX(MTInputs!$J$1:$AZ$415,$D52,MATCH(AI$5,MTInputs!$J$5:$AZ$5,0)) | AJ52: =INDEX(MTInputs!$J$1:$AZ$415,$D52,MATCH(AJ$5,MTInputs!$J$5:$AZ$5,0)) | AK52: =INDEX(MTInputs!$J$1:$AZ$415,$D52,MATCH(AK$5,MTInputs!$J$5:$AZ$5,0)) | AL52: =INDEX(MTInputs!$J$1:$AZ$415,$D52,MATCH(AL$5,MTInputs!$J$5:$AZ$5,0)) | AM52: =INDEX(MTInputs!$J$1:$AZ$415,$D52,MATCH(AM$5,MTInputs!$J$5:$AZ$5,0)) | ... AX52: =INDEX(MTInputs!$J$1:$AZ$415,$D52,MATCH(AX$5,MTInputs!$J$5:$AZ$5,0))
A53: fpr.s | B53: nga | C53: pow | D53: 145 | H53: =INDEX(Variables!$B$5:$B$105,MATCH($A53,Variables!$A$5:$A$105,0))&IF($C53="",""," | "&INDEX(Mapping!$B$5:$B$26,MATCH($C53,Mapping!$A$5:$A$26,0))&" | "&INDEX(Mapping!$B$30:$B$41,MATCH($B53,Mapping!$A$30:$A$41,0))) | I53: =INDEX(Variables!$C$5:$C$105,MATCH($A53,Variables!$A$5:$A$105,0)) | J53: =INDEX(Variables!$E$5:$E$105,MATCH($A53,Variables!$A$5:$A$105,0)) | K53: =LOWER(Settings!$C$4)&".mit."&$A53&IF($C53="","","."&$C53&"."&$B53)&IF(INDEX(Variables!$D$5:$D$105,MATCH($A53,Variables!$A$5:$A$105,0))="","","."&INDEX(Variables!$D$5:$D$105,MATCH($A53,Variables!$A$5:$A$105,0)))&"."&K$5 | L53: =INDEX(MTInputs!$J$1:$AZ$415,$D53,MATCH(L$5,MTInputs!$J$5:$AZ$5,0)) | M53: =INDEX(MTInputs!$J$1:$AZ$415,$D53,MATCH(M$5,MTInputs!$J$5:$AZ$5,0)) | N53: =INDEX(MTInputs!$J$1:$AZ$415,$D53,MATCH(N$5,MTInputs!$J$5:$AZ$5,0)) | O53: =INDEX(MTInputs!$J$1:$AZ$415,$D53,MATCH(O$5,MTInputs!$J$5:$AZ$5,0)) | P53: =INDEX(MTInputs!$J$1:$AZ$415,$D53,MATCH(P$5,MTInputs!$J$5:$AZ$5,0)) | Q53: =INDEX(MTInputs!$J$1:$AZ$415,$D53,MATCH(Q$5,MTInputs!$J$5:$AZ$5,0)) | R53: =INDEX(MTInputs!$J$1:$AZ$415,$D53,MATCH(R$5,MTInputs!$J$5:$AZ$5,0)) | S53: =INDEX(MTInputs!$J$1:$AZ$415,$D53,MATCH(S$5,MTInputs!$J$5:$AZ$5,0)) | ... AD53: =INDEX(MTInputs!$J$1:$AZ$415,$D53,MATCH(AD$5,MTInputs!$J$5:$AZ$5,0)) | AE53: =LOWER(Settings!$C$4)&".mit."&$A53&IF($C53="","","."&$C53&"."&$B53)&IF(INDEX(Variables!$D$5:$D$105,MATCH($A53,Variables!$A$5:$A$105,0))="","","."&INDEX(Variables!$D$5:$D$105,MATCH($A53,Variables!$A$5:$A$105,0)))&"."&AE$5 | AF53: =INDEX(MTInputs!$J$1:$AZ$415,$D53,MATCH(AF$5,MTInputs!$J$5:$AZ$5,0)) | AG53: =INDEX(MTInputs!$J$1:$AZ$415,$D53,MATCH(AG$5,MTInputs!$J$5:$AZ$5,0)) | AH53: =INDEX(MTInputs!$J$1:$AZ$415,$D53,MATCH(AH$5,MTInputs!$J$5:$AZ$5,0)) | AI53: =INDEX(MTInputs!$J$1:$AZ$415,$D53,MATCH(AI$5,MTInputs!$J$5:$AZ$5,0)) | AJ53: =INDEX(MTInputs!$J$1:$AZ$415,$D53,MATCH(AJ$5,MTInputs!$J$5:$AZ$5,0)) | AK53: =INDEX(MTInputs!$J$1:$AZ$415,$D53,MATCH(AK$5,MTInputs!$J$5:$AZ$5,0)) | AL53: =INDEX(MTInputs!$J$1:$AZ$415,$D53,MATCH(AL$5,MTInputs!$J$5:$AZ$5,0)) | AM53: =INDEX(MTInputs!$J$1:$AZ$415,$D53,MATCH(AM$5,MTInputs!$J$5:$AZ$5,0)) | ... AX53: =INDEX(MTInputs!$J$1:$AZ$415,$D53,MATCH(AX$5,MTInputs!$J$5:$AZ$5,0))
A54: fpr.s | B54: nga | C54: res | D54: 146 | H54: =INDEX(Variables!$B$5:$B$105,MATCH($A54,Variables!$A$5:$A$105,0))&IF($C54="",""," | "&INDEX(Mapping!$B$5:$B$26,MATCH($C54,Mapping!$A$5:$A$26,0))&" | "&INDEX(Mapping!$B$30:$B$41,MATCH($B54,Mapping!$A$30:$A$41,0))) | I54: =INDEX(Variables!$C$5:$C$105,MATCH($A54,Variables!$A$5:$A$105,0)) | J54: =INDEX(Variables!$E$5:$E$105,MATCH($A54,Variables!$A$5:$A$105,0)) | K54: =LOWER(Settings!$C$4)&".mit."&$A54&IF($C54="","","."&$C54&"."&$B54)&IF(INDEX(Variables!$D$5:$D$105,MATCH($A54,Variables!$A$5:$A$105,0))="","","."&INDEX(Variables!$D$5:$D$105,MATCH($A54,Variables!$A$5:$A$105,0)))&"."&K$5 | L54: =INDEX(MTInputs!$J$1:$AZ$415,$D54,MATCH(L$5,MTInputs!$J$5:$AZ$5,0)) | M54: =INDEX(MTInputs!$J$1:$AZ$415,$D54,MATCH(M$5,MTInputs!$J$5:$AZ$5,0)) | N54: =INDEX(MTInputs!$J$1:$AZ$415,$D54,MATCH(N$5,MTInputs!$J$5:$AZ$5,0)) | O54: =INDEX(MTInputs!$J$1:$AZ$415,$D54,MATCH(O$5,MTInputs!$J$5:$AZ$5,0)) | P54: =INDEX(MTInputs!$J$1:$AZ$415,$D54,MATCH(P$5,MTInputs!$J$5:$AZ$5,0)) | Q54: =INDEX(MTInputs!$J$1:$AZ$415,$D54,MATCH(Q$5,MTInputs!$J$5:$AZ$5,0)) | R54: =INDEX(MTInputs!$J$1:$AZ$415,$D54,MATCH(R$5,MTInputs!$J$5:$AZ$5,0)) | S54: =INDEX(MTInputs!$J$1:$AZ$415,$D54,MATCH(S$5,MTInputs!$J$5:$AZ$5,0)) | ... AD54: =INDEX(MTInputs!$J$1:$AZ$415,$D54,MATCH(AD$5,MTInputs!$J$5:$AZ$5,0)) | AE54: =LOWER(Settings!$C$4)&".mit."&$A54&IF($C54="","","."&$C54&"."&$B54)&IF(INDEX(Variables!$D$5:$D$105,MATCH($A54,Variables!$A$5:$A$105,0))="","","."&INDEX(Variables!$D$5:$D$105,MATCH($A54,Variables!$A$5:$A$105,0)))&"."&AE$5 | AF54: =INDEX(MTInputs!$J$1:$AZ$415,$D54,MATCH(AF$5,MTInputs!$J$5:$AZ$5,0)) | AG54: =INDEX(MTInputs!$J$1:$AZ$415,$D54,MATCH(AG$5,MTInputs!$J$5:$AZ$5,0)) | AH54: =INDEX(MTInputs!$J$1:$AZ$415,$D54,MATCH(AH$5,MTInputs!$J$5:$AZ$5,0)) | AI54: =INDEX(MTInputs!$J$1:$AZ$415,$D54,MATCH(AI$5,MTInputs!$J$5:$AZ$5,0)) | AJ54: =INDEX(MTInputs!$J$1:$AZ$415,$D54,MATCH(AJ$5,MTInputs!$J$5:$AZ$5,0)) | AK54: =INDEX(MTInputs!$J$1:$AZ$415,$D54,MATCH(AK$5,MTInputs!$J$5:$AZ$5,0)) | AL54: =INDEX(MTInputs!$J$1:$AZ$415,$D54,MATCH(AL$5,MTInputs!$J$5:$AZ$5,0)) | AM54: =INDEX(MTInputs!$J$1:$AZ$415,$D54,MATCH(AM$5,MTInputs!$J$5:$AZ$5,0)) | ... AX54: =INDEX(MTInputs!$J$1:$AZ$415,$D54,MATCH(AX$5,MTInputs!$J$5:$AZ$5,0))
A55: fpr.s | B55: nga | C55: ind | D55: 147 | H55: =INDEX(Variables!$B$5:$B$105,MATCH($A55,Variables!$A$5:$A$105,0))&IF($C55="",""," | "&INDEX(Mapping!$B$5:$B$26,MATCH($C55,Mapping!$A$5:$A$26,0))&" | "&INDEX(Mapping!$B$30:$B$41,MATCH($B55,Mapping!$A$30:$A$41,0))) | I55: =INDEX(Variables!$C$5:$C$105,MATCH($A55,Variables!$A$5:$A$105,0)) | J55: =INDEX(Variables!$E$5:$E$105,MATCH($A55,Variables!$A$5:$A$105,0)) | K55: =LOWER(Settings!$C$4)&".mit."&$A55&IF($C55="","","."&$C55&"."&$B55)&IF(INDEX(Variables!$D$5:$D$105,MATCH($A55,Variables!$A$5:$A$105,0))="","","."&INDEX(Variables!$D$5:$D$105,MATCH($A55,Variables!$A$5:$A$105,0)))&"."&K$5 | L55: =INDEX(MTInputs!$J$1:$AZ$415,$D55,MATCH(L$5,MTInputs!$J$5:$AZ$5,0)) | M55: =INDEX(MTInputs!$J$1:$AZ$415,$D55,MATCH(M$5,MTInputs!$J$5:$AZ$5,0)) | N55: =INDEX(MTInputs!$J$1:$AZ$415,$D55,MATCH(N$5,MTInputs!$J$5:$AZ$5,0)) | O55: =INDEX(MTInputs!$J$1:$AZ$415,$D55,MATCH(O$5,MTInputs!$J$5:$AZ$5,0)) | P55: =INDEX(MTInputs!$J$1:$AZ$415,$D55,MATCH(P$5,MTInputs!$J$5:$AZ$5,0)) | Q55: =INDEX(MTInputs!$J$1:$AZ$415,$D55,MATCH(Q$5,MTInputs!$J$5:$AZ$5,0)) | R55: =INDEX(MTInputs!$J$1:$AZ$415,$D55,MATCH(R$5,MTInputs!$J$5:$AZ$5,0)) | S55: =INDEX(MTInputs!$J$1:$AZ$415,$D55,MATCH(S$5,MTInputs!$J$5:$AZ$5,0)) | ... AD55: =INDEX(MTInputs!$J$1:$AZ$415,$D55,MATCH(AD$5,MTInputs!$J$5:$AZ$5,0)) | AE55: =LOWER(Settings!$C$4)&".mit."&$A55&IF($C55="","","."&$C55&"."&$B55)&IF(INDEX(Variables!$D$5:$D$105,MATCH($A55,Variables!$A$5:$A$105,0))="","","."&INDEX(Variables!$D$5:$D$105,MATCH($A55,Variables!$A$5:$A$105,0)))&"."&AE$5 | AF55: =INDEX(MTInputs!$J$1:$AZ$415,$D55,MATCH(AF$5,MTInputs!$J$5:$AZ$5,0)) | AG55: =INDEX(MTInputs!$J$1:$AZ$415,$D55,MATCH(AG$5,MTInputs!$J$5:$AZ$5,0)) | AH55: =INDEX(MTInputs!$J$1:$AZ$415,$D55,MATCH(AH$5,MTInputs!$J$5:$AZ$5,0)) | AI55: =INDEX(MTInputs!$J$1:$AZ$415,$D55,MATCH(AI$5,MTInputs!$J$5:$AZ$5,0)) | AJ55: =INDEX(MTInputs!$J$1:$AZ$415,$D55,MATCH(AJ$5,MTInputs!$J$5:$AZ$5,0)) | AK55: =INDEX(MTInputs!$J$1:$AZ$415,$D55,MATCH(AK$5,MTInputs!$J$5:$AZ$5,0)) | AL55: =INDEX(MTInputs!$J$1:$AZ$415,$D55,MATCH(AL$5,MTInputs!$J$5:$AZ$5,0)) | AM55: =INDEX(MTInputs!$J$1:$AZ$415,$D55,MATCH(AM$5,MTInputs!$J$5:$AZ$5,0)) | ... AX55: =INDEX(MTInputs!$J$1:$AZ$415,$D55,MATCH(AX$5,MTInputs!$J$5:$AZ$5,0))
A56: fpr.s | B56: ecy | C56: res | D56: 148 | H56: =INDEX(Variables!$B$5:$B$105,MATCH($A56,Variables!$A$5:$A$105,0))&IF($C56="",""," | "&INDEX(Mapping!$B$5:$B$26,MATCH($C56,Mapping!$A$5:$A$26,0))&" | "&INDEX(Mapping!$B$30:$B$41,MATCH($B56,Mapping!$A$30:$A$41,0))) | I56: =INDEX(Variables!$C$5:$C$105,MATCH($A56,Variables!$A$5:$A$105,0)) | J56: =INDEX(Variables!$E$5:$E$105,MATCH($A56,Variables!$A$5:$A$105,0)) | K56: =LOWER(Settings!$C$4)&".mit."&$A56&IF($C56="","","."&$C56&"."&$B56)&IF(INDEX(Variables!$D$5:$D$105,MATCH($A56,Variables!$A$5:$A$105,0))="","","."&INDEX(Variables!$D$5:$D$105,MATCH($A56,Variables!$A$5:$A$105,0)))&"."&K$5 | L56: =INDEX(MTInputs!$J$1:$AZ$415,$D56,MATCH(L$5,MTInputs!$J$5:$AZ$5,0)) | M56: =INDEX(MTInputs!$J$1:$AZ$415,$D56,MATCH(M$5,MTInputs!$J$5:$AZ$5,0)) | N56: =INDEX(MTInputs!$J$1:$AZ$415,$D56,MATCH(N$5,MTInputs!$J$5:$AZ$5,0)) | O56: =INDEX(MTInputs!$J$1:$AZ$415,$D56,MATCH(O$5,MTInputs!$J$5:$AZ$5,0)) | P56: =INDEX(MTInputs!$J$1:$AZ$415,$D56,MATCH(P$5,MTInputs!$J$5:$AZ$5,0)) | Q56: =INDEX(MTInputs!$J$1:$AZ$415,$D56,MATCH(Q$5,MTInputs!$J$5:$AZ$5,0)) | R56: =INDEX(MTInputs!$J$1:$AZ$415,$D56,MATCH(R$5,MTInputs!$J$5:$AZ$5,0)) | S56: =INDEX(MTInputs!$J$1:$AZ$415,$D56,MATCH(S$5,MTInputs!$J$5:$AZ$5,0)) | ... AD56: =INDEX(MTInputs!$J$1:$AZ$415,$D56,MATCH(AD$5,MTInputs!$J$5:$AZ$5,0)) | AE56: =LOWER(Settings!$C$4)&".mit."&$A56&IF($C56="","","."&$C56&"."&$B56)&IF(INDEX(Variables!$D$5:$D$105,MATCH($A56,Variables!$A$5:$A$105,0))="","","."&INDEX(Variables!$D$5:$D$105,MATCH($A56,Variables!$A$5:$A$105,0)))&"."&AE$5 | AF56: =INDEX(MTInputs!$J$1:$AZ$415,$D56,MATCH(AF$5,MTInputs!$J$5:$AZ$5,0)) | AG56: =INDEX(MTInputs!$J$1:$AZ$415,$D56,MATCH(AG$5,MTInputs!$J$5:$AZ$5,0)) | AH56: =INDEX(MTInputs!$J$1:$AZ$415,$D56,MATCH(AH$5,MTInputs!$J$5:$AZ$5,0)) | AI56: =INDEX(MTInputs!$J$1:$AZ$415,$D56,MATCH(AI$5,MTInputs!$J$5:$AZ$5,0)) | AJ56: =INDEX(MTInputs!$J$1:$AZ$415,$D56,MATCH(AJ$5,MTInputs!$J$5:$AZ$5,0)) | AK56: =INDEX(MTInputs!$J$1:$AZ$415,$D56,MATCH(AK$5,MTInputs!$J$5:$AZ$5,0)) | AL56: =INDEX(MTInputs!$J$1:$AZ$415,$D56,MATCH(AL$5,MTInputs!$J$5:$AZ$5,0)) | AM56: =INDEX(MTInputs!$J$1:$AZ$415,$D56,MATCH(AM$5,MTInputs!$J$5:$AZ$5,0)) | ... AX56: =INDEX(MTInputs!$J$1:$AZ$415,$D56,MATCH(AX$5,MTInputs!$J$5:$AZ$5,0))
A57: fpr.s | B57: ecy | C57: ind | D57: 149 | H57: =INDEX(Variables!$B$5:$B$105,MATCH($A57,Variables!$A$5:$A$105,0))&IF($C57="",""," | "&INDEX(Mapping!$B$5:$B$26,MATCH($C57,Mapping!$A$5:$A$26,0))&" | "&INDEX(Mapping!$B$30:$B$41,MATCH($B57,Mapping!$A$30:$A$41,0))) | I57: =INDEX(Variables!$C$5:$C$105,MATCH($A57,Variables!$A$5:$A$105,0)) | J57: =INDEX(Variables!$E$5:$E$105,MATCH($A57,Variables!$A$5:$A$105,0)) | K57: =LOWER(Settings!$C$4)&".mit."&$A57&IF($C57="","","."&$C57&"."&$B57)&IF(INDEX(Variables!$D$5:$D$105,MATCH($A57,Variables!$A$5:$A$105,0))="","","."&INDEX(Variables!$D$5:$D$105,MATCH($A57,Variables!$A$5:$A$105,0)))&"."&K$5 | L57: =INDEX(MTInputs!$J$1:$AZ$415,$D57,MATCH(L$5,MTInputs!$J$5:$AZ$5,0)) | M57: =INDEX(MTInputs!$J$1:$AZ$415,$D57,MATCH(M$5,MTInputs!$J$5:$AZ$5,0)) | N57: =INDEX(MTInputs!$J$1:$AZ$415,$D57,MATCH(N$5,MTInputs!$J$5:$AZ$5,0)) | O57: =INDEX(MTInputs!$J$1:$AZ$415,$D57,MATCH(O$5,MTInputs!$J$5:$AZ$5,0)) | P57: =INDEX(MTInputs!$J$1:$AZ$415,$D57,MATCH(P$5,MTInputs!$J$5:$AZ$5,0)) | Q57: =INDEX(MTInputs!$J$1:$AZ$415,$D57,MATCH(Q$5,MTInputs!$J$5:$AZ$5,0)) | R57: =INDEX(MTInputs!$J$1:$AZ$415,$D57,MATCH(R$5,MTInputs!$J$5:$AZ$5,0)) | S57: =INDEX(MTInputs!$J$1:$AZ$415,$D57,MATCH(S$5,MTInputs!$J$5:$AZ$5,0)) | ... AD57: =INDEX(MTInputs!$J$1:$AZ$415,$D57,MATCH(AD$5,MTInputs!$J$5:$AZ$5,0)) | AE57: =LOWER(Settings!$C$4)&".mit."&$A57&IF($C57="","","."&$C57&"."&$B57)&IF(INDEX(Variables!$D$5:$D$105,MATCH($A57,Variables!$A$5:$A$105,0))="","","."&INDEX(Variables!$D$5:$D$105,MATCH($A57,Variables!$A$5:$A$105,0)))&"."&AE$5 | AF57: =INDEX(MTInputs!$J$1:$AZ$415,$D57,MATCH(AF$5,MTInputs!$J$5:$AZ$5,0)) | AG57: =INDEX(MTInputs!$J$1:$AZ$415,$D57,MATCH(AG$5,MTInputs!$J$5:$AZ$5,0)) | AH57: =INDEX(MTInputs!$J$1:$AZ$415,$D57,MATCH(AH$5,MTInputs!$J$5:$AZ$5,0)) | AI57: =INDEX(MTInputs!$J$1:$AZ$415,$D57,MATCH(AI$5,MTInputs!$J$5:$AZ$5,0)) | AJ57: =INDEX(MTInputs!$J$1:$AZ$415,$D57,MATCH(AJ$5,MTInputs!$J$5:$AZ$5,0)) | AK57: =INDEX(MTInputs!$J$1:$AZ$415,$D57,MATCH(AK$5,MTInputs!$J$5:$AZ$5,0)) | AL57: =INDEX(MTInputs!$J$1:$AZ$415,$D57,MATCH(AL$5,MTInputs!$J$5:$AZ$5,0)) | AM57: =INDEX(MTInputs!$J$1:$AZ$415,$D57,MATCH(AM$5,MTInputs!$J$5:$AZ$5,0)) | ... AX57: =INDEX(MTInputs!$J$1:$AZ$415,$D57,MATCH(AX$5,MTInputs!$J$5:$AZ$5,0))
A58: fpr.s | B58: gso | C58: all | D58: 150 | H58: =INDEX(Variables!$B$5:$B$105,MATCH($A58,Variables!$A$5:$A$105,0))&IF($C58="",""," | "&INDEX(Mapping!$B$5:$B$26,MATCH($C58,Mapping!$A$5:$A$26,0))&" | "&INDEX(Mapping!$B$30:$B$41,MATCH($B58,Mapping!$A$30:$A$41,0))) | I58: =INDEX(Variables!$C$5:$C$105,MATCH($A58,Variables!$A$5:$A$105,0)) | J58: =INDEX(Variables!$E$5:$E$105,MATCH($A58,Variables!$A$5:$A$105,0)) | K58: =LOWER(Settings!$C$4)&".mit."&$A58&IF($C58="","","."&$C58&"."&$B58)&IF(INDEX(Variables!$D$5:$D$105,MATCH($A58,Variables!$A$5:$A$105,0))="","","."&INDEX(Variables!$D$5:$D$105,MATCH($A58,Variables!$A$5:$A$105,0)))&"."&K$5 | L58: =INDEX(MTInputs!$J$1:$AZ$415,$D58,MATCH(L$5,MTInputs!$J$5:$AZ$5,0)) | M58: =INDEX(MTInputs!$J$1:$AZ$415,$D58,MATCH(M$5,MTInputs!$J$5:$AZ$5,0)) | N58: =INDEX(MTInputs!$J$1:$AZ$415,$D58,MATCH(N$5,MTInputs!$J$5:$AZ$5,0)) | O58: =INDEX(MTInputs!$J$1:$AZ$415,$D58,MATCH(O$5,MTInputs!$J$5:$AZ$5,0)) | P58: =INDEX(MTInputs!$J$1:$AZ$415,$D58,MATCH(P$5,MTInputs!$J$5:$AZ$5,0)) | Q58: =INDEX(MTInputs!$J$1:$AZ$415,$D58,MATCH(Q$5,MTInputs!$J$5:$AZ$5,0)) | R58: =INDEX(MTInputs!$J$1:$AZ$415,$D58,MATCH(R$5,MTInputs!$J$5:$AZ$5,0)) | S58: =INDEX(MTInputs!$J$1:$AZ$415,$D58,MATCH(S$5,MTInputs!$J$5:$AZ$5,0)) | ... AD58: =INDEX(MTInputs!$J$1:$AZ$415,$D58,MATCH(AD$5,MTInputs!$J$5:$AZ$5,0)) | AE58: =LOWER(Settings!$C$4)&".mit."&$A58&IF($C58="","","."&$C58&"."&$B58)&IF(INDEX(Variables!$D$5:$D$105,MATCH($A58,Variables!$A$5:$A$105,0))="","","."&INDEX(Variables!$D$5:$D$105,MATCH($A58,Variables!$A$5:$A$105,0)))&"."&AE$5 | AF58: =INDEX(MTInputs!$J$1:$AZ$415,$D58,MATCH(AF$5,MTInputs!$J$5:$AZ$5,0)) | AG58: =INDEX(MTInputs!$J$1:$AZ$415,$D58,MATCH(AG$5,MTInputs!$J$5:$AZ$5,0)) | AH58: =INDEX(MTInputs!$J$1:$AZ$415,$D58,MATCH(AH$5,MTInputs!$J$5:$AZ$5,0)) | AI58: =INDEX(MTInputs!$J$1:$AZ$415,$D58,MATCH(AI$5,MTInputs!$J$5:$AZ$5,0)) | AJ58: =INDEX(MTInputs!$J$1:$AZ$415,$D58,MATCH(AJ$5,MTInputs!$J$5:$AZ$5,0)) | AK58: =INDEX(MTInputs!$J$1:$AZ$415,$D58,MATCH(AK$5,MTInputs!$J$5:$AZ$5,0)) | AL58: =INDEX(MTInputs!$J$1:$AZ$415,$D58,MATCH(AL$5,MTInputs!$J$5:$AZ$5,0)) | AM58: =INDEX(MTInputs!$J$1:$AZ$415,$D58,MATCH(AM$5,MTInputs!$J$5:$AZ$5,0)) | ... AX58: =INDEX(MTInputs!$J$1:$AZ$415,$D58,MATCH(AX$5,MTInputs!$J$5:$AZ$5,0))
A59: fpr.s | B59: die | C59: all | D59: 151 | H59: =INDEX(Variables!$B$5:$B$105,MATCH($A59,Variables!$A$5:$A$105,0))&IF($C59="",""," | "&INDEX(Mapping!$B$5:$B$26,MATCH($C59,Mapping!$A$5:$A$26,0))&" | "&INDEX(Mapping!$B$30:$B$41,MATCH($B59,Mapping!$A$30:$A$41,0))) | I59: =INDEX(Variables!$C$5:$C$105,MATCH($A59,Variables!$A$5:$A$105,0)) | J59: =INDEX(Variables!$E$5:$E$105,MATCH($A59,Variables!$A$5:$A$105,0)) | K59: =LOWER(Settings!$C$4)&".mit."&$A59&IF($C59="","","."&$C59&"."&$B59)&IF(INDEX(Variables!$D$5:$D$105,MATCH($A59,Variables!$A$5:$A$105,0))="","","."&INDEX(Variables!$D$5:$D$105,MATCH($A59,Variables!$A$5:$A$105,0)))&"."&K$5 | L59: =INDEX(MTInputs!$J$1:$AZ$415,$D59,MATCH(L$5,MTInputs!$J$5:$AZ$5,0)) | M59: =INDEX(MTInputs!$J$1:$AZ$415,$D59,MATCH(M$5,MTInputs!$J$5:$AZ$5,0)) | N59: =INDEX(MTInputs!$J$1:$AZ$415,$D59,MATCH(N$5,MTInputs!$J$5:$AZ$5,0)) | O59: =INDEX(MTInputs!$J$1:$AZ$415,$D59,MATCH(O$5,MTInputs!$J$5:$AZ$5,0)) | P59: =INDEX(MTInputs!$J$1:$AZ$415,$D59,MATCH(P$5,MTInputs!$J$5:$AZ$5,0)) | Q59: =INDEX(MTInputs!$J$1:$AZ$415,$D59,MATCH(Q$5,MTInputs!$J$5:$AZ$5,0)) | R59: =INDEX(MTInputs!$J$1:$AZ$415,$D59,MATCH(R$5,MTInputs!$J$5:$AZ$5,0)) | S59: =INDEX(MTInputs!$J$1:$AZ$415,$D59,MATCH(S$5,MTInputs!$J$5:$AZ$5,0)) | ... AD59: =INDEX(MTInputs!$J$1:$AZ$415,$D59,MATCH(AD$5,MTInputs!$J$5:$AZ$5,0)) | AE59: =LOWER(Settings!$C$4)&".mit."&$A59&IF($C59="","","."&$C59&"."&$B59)&IF(INDEX(Variables!$D$5:$D$105,MATCH($A59,Variables!$A$5:$A$105,0))="","","."&INDEX(Variables!$D$5:$D$105,MATCH($A59,Variables!$A$5:$A$105,0)))&"."&AE$5 | AF59: =INDEX(MTInputs!$J$1:$AZ$415,$D59,MATCH(AF$5,MTInputs!$J$5:$AZ$5,0)) | AG59: =INDEX(MTInputs!$J$1:$AZ$415,$D59,MATCH(AG$5,MTInputs!$J$5:$AZ$5,0)) | AH59: =INDEX(MTInputs!$J$1:$AZ$415,$D59,MATCH(AH$5,MTInputs!$J$5:$AZ$5,0)) | AI59: =INDEX(MTInputs!$J$1:$AZ$415,$D59,MATCH(AI$5,MTInputs!$J$5:$AZ$5,0)) | AJ59: =INDEX(MTInputs!$J$1:$AZ$415,$D59,MATCH(AJ$5,MTInputs!$J$5:$AZ$5,0)) | AK59: =INDEX(MTInputs!$J$1:$AZ$415,$D59,MATCH(AK$5,MTInputs!$J$5:$AZ$5,0)) | AL59: =INDEX(MTInputs!$J$1:$AZ$415,$D59,MATCH(AL$5,MTInputs!$J$5:$AZ$5,0)) | AM59: =INDEX(MTInputs!$J$1:$AZ$415,$D59,MATCH(AM$5,MTInputs!$J$5:$AZ$5,0)) | ... AX59: =INDEX(MTInputs!$J$1:$AZ$415,$D59,MATCH(AX$5,MTInputs!$J$5:$AZ$5,0))
A60: fpr.s | B60: lpg | C60: all | D60: 152 | H60: =INDEX(Variables!$B$5:$B$105,MATCH($A60,Variables!$A$5:$A$105,0))&IF($C60="",""," | "&INDEX(Mapping!$B$5:$B$26,MATCH($C60,Mapping!$A$5:$A$26,0))&" | "&INDEX(Mapping!$B$30:$B$41,MATCH($B60,Mapping!$A$30:$A$41,0))) | I60: =INDEX(Variables!$C$5:$C$105,MATCH($A60,Variables!$A$5:$A$105,0)) | J60: =INDEX(Variables!$E$5:$E$105,MATCH($A60,Variables!$A$5:$A$105,0)) | K60: =LOWER(Settings!$C$4)&".mit."&$A60&IF($C60="","","."&$C60&"."&$B60)&IF(INDEX(Variables!$D$5:$D$105,MATCH($A60,Variables!$A$5:$A$105,0))="","","."&INDEX(Variables!$D$5:$D$105,MATCH($A60,Variables!$A$5:$A$105,0)))&"."&K$5 | L60: =INDEX(MTInputs!$J$1:$AZ$415,$D60,MATCH(L$5,MTInputs!$J$5:$AZ$5,0)) | M60: =INDEX(MTInputs!$J$1:$AZ$415,$D60,MATCH(M$5,MTInputs!$J$5:$AZ$5,0)) | N60: =INDEX(MTInputs!$J$1:$AZ$415,$D60,MATCH(N$5,MTInputs!$J$5:$AZ$5,0)) | O60: =INDEX(MTInputs!$J$1:$AZ$415,$D60,MATCH(O$5,MTInputs!$J$5:$AZ$5,0)) | P60: =INDEX(MTInputs!$J$1:$AZ$415,$D60,MATCH(P$5,MTInputs!$J$5:$AZ$5,0)) | Q60: =INDEX(MTInputs!$J$1:$AZ$415,$D60,MATCH(Q$5,MTInputs!$J$5:$AZ$5,0)) | R60: =INDEX(MTInputs!$J$1:$AZ$415,$D60,MATCH(R$5,MTInputs!$J$5:$AZ$5,0)) | S60: =INDEX(MTInputs!$J$1:$AZ$415,$D60,MATCH(S$5,MTInputs!$J$5:$AZ$5,0)) | ... AD60: =INDEX(MTInputs!$J$1:$AZ$415,$D60,MATCH(AD$5,MTInputs!$J$5:$AZ$5,0)) | AE60: =LOWER(Settings!$C$4)&".mit."&$A60&IF($C60="","","."&$C60&"."&$B60)&IF(INDEX(Variables!$D$5:$D$105,MATCH($A60,Variables!$A$5:$A$105,0))="","","."&INDEX(Variables!$D$5:$D$105,MATCH($A60,Variables!$A$5:$A$105,0)))&"."&AE$5 | AF60: =INDEX(MTInputs!$J$1:$AZ$415,$D60,MATCH(AF$5,MTInputs!$J$5:$AZ$5,0)) | AG60: =INDEX(MTInputs!$J$1:$AZ$415,$D60,MATCH(AG$5,MTInputs!$J$5:$AZ$5,0)) | AH60: =INDEX(MTInputs!$J$1:$AZ$415,$D60,MATCH(AH$5,MTInputs!$J$5:$AZ$5,0)) | AI60: =INDEX(MTInputs!$J$1:$AZ$415,$D60,MATCH(AI$5,MTInputs!$J$5:$AZ$5,0)) | AJ60: =INDEX(MTInputs!$J$1:$AZ$415,$D60,MATCH(AJ$5,MTInputs!$J$5:$AZ$5,0)) | AK60: =INDEX(MTInputs!$J$1:$AZ$415,$D60,MATCH(AK$5,MTInputs!$J$5:$AZ$5,0)) | AL60: =INDEX(MTInputs!$J$1:$AZ$415,$D60,MATCH(AL$5,MTInputs!$J$5:$AZ$5,0)) | AM60: =INDEX(MTInputs!$J$1:$AZ$415,$D60,MATCH(AM$5,MTInputs!$J$5:$AZ$5,0)) | ... AX60: =INDEX(MTInputs!$J$1:$AZ$415,$D60,MATCH(AX$5,MTInputs!$J$5:$AZ$5,0))
A61: fpr.s | B61: ker | C61: all | D61: 153 | H61: =INDEX(Variables!$B$5:$B$105,MATCH($A61,Variables!$A$5:$A$105,0))&IF($C61="",""," | "&INDEX(Mapping!$B$5:$B$26,MATCH($C61,Mapping!$A$5:$A$26,0))&" | "&INDEX(Mapping!$B$30:$B$41,MATCH($B61,Mapping!$A$30:$A$41,0))) | I61: =INDEX(Variables!$C$5:$C$105,MATCH($A61,Variables!$A$5:$A$105,0)) | J61: =INDEX(Variables!$E$5:$E$105,MATCH($A61,Variables!$A$5:$A$105,0)) | K61: =LOWER(Settings!$C$4)&".mit."&$A61&IF($C61="","","."&$C61&"."&$B61)&IF(INDEX(Variables!$D$5:$D$105,MATCH($A61,Variables!$A$5:$A$105,0))="","","."&INDEX(Variables!$D$5:$D$105,MATCH($A61,Variables!$A$5:$A$105,0)))&"."&K$5 | L61: =INDEX(MTInputs!$J$1:$AZ$415,$D61,MATCH(L$5,MTInputs!$J$5:$AZ$5,0)) | M61: =INDEX(MTInputs!$J$1:$AZ$415,$D61,MATCH(M$5,MTInputs!$J$5:$AZ$5,0)) | N61: =INDEX(MTInputs!$J$1:$AZ$415,$D61,MATCH(N$5,MTInputs!$J$5:$AZ$5,0)) | O61: =INDEX(MTInputs!$J$1:$AZ$415,$D61,MATCH(O$5,MTInputs!$J$5:$AZ$5,0)) | P61: =INDEX(MTInputs!$J$1:$AZ$415,$D61,MATCH(P$5,MTInputs!$J$5:$AZ$5,0)) | Q61: =INDEX(MTInputs!$J$1:$AZ$415,$D61,MATCH(Q$5,MTInputs!$J$5:$AZ$5,0)) | R61: =INDEX(MTInputs!$J$1:$AZ$415,$D61,MATCH(R$5,MTInputs!$J$5:$AZ$5,0)) | S61: =INDEX(MTInputs!$J$1:$AZ$415,$D61,MATCH(S$5,MTInputs!$J$5:$AZ$5,0)) | ... AD61: =INDEX(MTInputs!$J$1:$AZ$415,$D61,MATCH(AD$5,MTInputs!$J$5:$AZ$5,0)) | AE61: =LOWER(Settings!$C$4)&".mit."&$A61&IF($C61="","","."&$C61&"."&$B61)&IF(INDEX(Variables!$D$5:$D$105,MATCH($A61,Variables!$A$5:$A$105,0))="","","."&INDEX(Variables!$D$5:$D$105,MATCH($A61,Variables!$A$5:$A$105,0)))&"."&AE$5 | AF61: =INDEX(MTInputs!$J$1:$AZ$415,$D61,MATCH(AF$5,MTInputs!$J$5:$AZ$5,0)) | AG61: =INDEX(MTInputs!$J$1:$AZ$415,$D61,MATCH(AG$5,MTInputs!$J$5:$AZ$5,0)) | AH61: =INDEX(MTInputs!$J$1:$AZ$415,$D61,MATCH(AH$5,MTInputs!$J$5:$AZ$5,0)) | AI61: =INDEX(MTInputs!$J$1:$AZ$415,$D61,MATCH(AI$5,MTInputs!$J$5:$AZ$5,0)) | AJ61: =INDEX(MTInputs!$J$1:$AZ$415,$D61,MATCH(AJ$5,MTInputs!$J$5:$AZ$5,0)) | AK61: =INDEX(MTInputs!$J$1:$AZ$415,$D61,MATCH(AK$5,MTInputs!$J$5:$AZ$5,0)) | AL61: =INDEX(MTInputs!$J$1:$AZ$415,$D61,MATCH(AL$5,MTInputs!$J$5:$AZ$5,0)) | AM61: =INDEX(MTInputs!$J$1:$AZ$415,$D61,MATCH(AM$5,MTInputs!$J$5:$AZ$5,0)) | ... AX61: =INDEX(MTInputs!$J$1:$AZ$415,$D61,MATCH(AX$5,MTInputs!$J$5:$AZ$5,0))
... A77: fpr.f | B77: bio | C77: all | D77: 169 | H77: =INDEX(Variables!$B$5:$B$105,MATCH($A77,Variables!$A$5:$A$105,0))&IF($C77="",""," | "&INDEX(Mapping!$B$5:$B$26,MATCH($C77,Mapping!$A$5:$A$26,0))&" | "&INDEX(Mapping!$B$30:$B$41,MATCH($B77,Mapping!$A$30:$A$41,0))) | I77: =INDEX(Variables!$C$5:$C$105,MATCH($A77,Variables!$A$5:$A$105,0)) | J77: =INDEX(Variables!$E$5:$E$105,MATCH($A77,Variables!$A$5:$A$105,0)) | K77: =LOWER(Settings!$C$4)&".mit."&$A77&IF($C77="","","."&$C77&"."&$B77)&IF(INDEX(Variables!$D$5:$D$105,MATCH($A77,Variables!$A$5:$A$105,0))="","","."&INDEX(Variables!$D$5:$D$105,MATCH($A77,Variables!$A$5:$A$105,0)))&"."&K$5 | L77: =INDEX(MTInputs!$J$1:$AZ$415,$D77,MATCH(L$5,MTInputs!$J$5:$AZ$5,0)) | M77: =INDEX(MTInputs!$J$1:$AZ$415,$D77,MATCH(M$5,MTInputs!$J$5:$AZ$5,0)) | N77: =INDEX(MTInputs!$J$1:$AZ$415,$D77,MATCH(N$5,MTInputs!$J$5:$AZ$5,0)) | O77: =INDEX(MTInputs!$J$1:$AZ$415,$D77,MATCH(O$5,MTInputs!$J$5:$AZ$5,0)) | P77: =INDEX(MTInputs!$J$1:$AZ$415,$D77,MATCH(P$5,MTInputs!$J$5:$AZ$5,0)) | Q77: =INDEX(MTInputs!$J$1:$AZ$415,$D77,MATCH(Q$5,MTInputs!$J$5:$AZ$5,0)) | R77: =INDEX(MTInputs!$J$1:$AZ$415,$D77,MATCH(R$5,MTInputs!$J$5:$AZ$5,0)) | S77: =INDEX(MTInputs!$J$1:$AZ$415,$D77,MATCH(S$5,MTInputs!$J$5:$AZ$5,0)) | ... AD77: =INDEX(MTInputs!$J$1:$AZ$415,$D77,MATCH(AD$5,MTInputs!$J$5:$AZ$5,0)) | AE77: =LOWER(Settings!$C$4)&".mit."&$A77&IF($C77="","","."&$C77&"."&$B77)&IF(INDEX(Variables!$D$5:$D$105,MATCH($A77,Variables!$A$5:$A$105,0))="","","."&INDEX(Variables!$D$5:$D$105,MATCH($A77,Variables!$A$5:$A$105,0)))&"."&AE$5 | AF77: =INDEX(MTInputs!$J$1:$AZ$415,$D77,MATCH(AF$5,MTInputs!$J$5:$AZ$5,0)) | AG77: =INDEX(MTInputs!$J$1:$AZ$415,$D77,MATCH(AG$5,MTInputs!$J$5:$AZ$5,0)) | AH77: =INDEX(MTInputs!$J$1:$AZ$415,$D77,MATCH(AH$5,MTInputs!$J$5:$AZ$5,0)) | AI77: =INDEX(MTInputs!$J$1:$AZ$415,$D77,MATCH(AI$5,MTInputs!$J$5:$AZ$5,0)) | AJ77: =INDEX(MTInputs!$J$1:$AZ$415,$D77,MATCH(AJ$5,MTInputs!$J$5:$AZ$5,0)) | AK77: =INDEX(MTInputs!$J$1:$AZ$415,$D77,MATCH(AK$5,MTInputs!$J$5:$AZ$5,0)) | AL77: =INDEX(MTInputs!$J$1:$AZ$415,$D77,MATCH(AL$5,MTInputs!$J$5:$AZ$5,0)) | AM77: =INDEX(MTInputs!$J$1:$AZ$415,$D77,MATCH(AM$5,MTInputs!$J$5:$AZ$5,0)) | ... AX77: =INDEX(MTInputs!$J$1:$AZ$415,$D77,MATCH(AX$5,MTInputs!$J$5:$AZ$5,0))
A78: fpr | B78: coa | C78: pow | H78: =INDEX(Variables!$B$5:$B$105,MATCH($A78,Variables!$A$5:$A$105,0))&IF($C78="",""," | "&INDEX(Mapping!$B$5:$B$26,MATCH($C78,Mapping!$A$5:$A$26,0))&" | "&INDEX(Mapping!$B$30:$B$41,MATCH($B78,Mapping!$A$30:$A$41,0))) | I78: =INDEX(Variables!$C$5:$C$105,MATCH($A78,Variables!$A$5:$A$105,0)) | J78: =INDEX(Variables!$E$5:$E$105,MATCH($A78,Variables!$A$5:$A$105,0)) | K78: =LOWER(Settings!$C$4)&".mit."&$A78&IF($C78="","","."&$C78&"."&$B78)&IF(INDEX(Variables!$D$5:$D$105,MATCH($A78,Variables!$A$5:$A$105,0))="","","."&INDEX(Variables!$D$5:$D$105,MATCH($A78,Variables!$A$5:$A$105,0)))&"."&K$5 | L78: =IF(L$4<L$48,0,L50+(L64-L50)/MAX(L$49-L$48,1)*(L$4-L$48)) | M78: =IF(M$4<M$48,0,M50+(M64-M50)/MAX(M$49-M$48,1)*(M$4-M$48)) | N78: =IF(N$4<N$48,0,N50+(N64-N50)/MAX(N$49-N$48,1)*(N$4-N$48)) | O78: =IF(O$4<O$48,0,O50+(O64-O50)/MAX(O$49-O$48,1)*(O$4-O$48)) | P78: =IF(P$4<P$48,0,P50+(P64-P50)/MAX(P$49-P$48,1)*(P$4-P$48)) | Q78: =IF(Q$4<Q$48,0,Q50+(Q64-Q50)/MAX(Q$49-Q$48,1)*(Q$4-Q$48)) | R78: =IF(R$4<R$48,0,R50+(R64-R50)/MAX(R$49-R$48,1)*(R$4-R$48)) | S78: =IF(S$4<S$48,0,S50+(S64-S50)/MAX(S$49-S$48,1)*(S$4-S$48)) | ... AC78: =IF(AC$4<AC$48,0,AC50+(AC64-AC50)/MAX(AC$49-AC$48,1)*(AC$4-AC$48)) | AD78: =PATH(AD$4,AD$48,AD$49,AD50,AD64,TRUE) | AE78: =LOWER(Settings!$C$4)&".mit."&$A78&IF($C78="","","."&$C78&"."&$B78)&IF(INDEX(Variables!$D$5:$D$105,MATCH($A78,Variables!$A$5:$A$105,0))="","","."&INDEX(Variables!$D$5:$D$105,MATCH($A78,Variables!$A$5:$A$105,0)))&"."&AE$5 | AF78: =IF(AF$4<AF$48,0,AF50+(AF64-AF50)/MAX(AF$49-AF$48,1)*(AF$4-AF$48)) | AG78: =IF(AG$4<AG$48,0,AG50+(AG64-AG50)/MAX(AG$49-AG$48,1)*(AG$4-AG$48)) | AH78: =IF(AH$4<AH$48,0,AH50+(AH64-AH50)/MAX(AH$49-AH$48,1)*(AH$4-AH$48)) | AI78: =IF(AI$4<AI$48,0,AI50+(AI64-AI50)/MAX(AI$49-AI$48,1)*(AI$4-AI$48)) | AJ78: =IF(AJ$4<AJ$48,0,AJ50+(AJ64-AJ50)/MAX(AJ$49-AJ$48,1)*(AJ$4-AJ$48)) | AK78: =IF(AK$4<AK$48,0,AK50+(AK64-AK50)/MAX(AK$49-AK$48,1)*(AK$4-AK$48)) | AL78: =IF(AL$4<AL$48,0,AL50+(AL64-AL50)/MAX(AL$49-AL$48,1)*(AL$4-AL$48)) | AM78: =IF(AM$4<AM$48,0,AM50+(AM64-AM50)/MAX(AM$49-AM$48,1)*(AM$4-AM$48)) | ... AW78: =IF(AW$4<AW$48,0,AW50+(AW64-AW50)/MAX(AW$49-AW$48,1)*(AW$4-AW$48)) | AX78: =PATH(AX$4,AX$48,AX$49,AX50,AX64,TRUE)
A79: fpr | B79: coa | C79: res | H79: =INDEX(Variables!$B$5:$B$105,MATCH($A79,Variables!$A$5:$A$105,0))&IF($C79="",""," | "&INDEX(Mapping!$B$5:$B$26,MATCH($C79,Mapping!$A$5:$A$26,0))&" | "&INDEX(Mapping!$B$30:$B$41,MATCH($B79,Mapping!$A$30:$A$41,0))) | I79: =INDEX(Variables!$C$5:$C$105,MATCH($A79,Variables!$A$5:$A$105,0)) | J79: =INDEX(Variables!$E$5:$E$105,MATCH($A79,Variables!$A$5:$A$105,0)) | K79: =LOWER(Settings!$C$4)&".mit."&$A79&IF($C79="","","."&$C79&"."&$B79)&IF(INDEX(Variables!$D$5:$D$105,MATCH($A79,Variables!$A$5:$A$105,0))="","","."&INDEX(Variables!$D$5:$D$105,MATCH($A79,Variables!$A$5:$A$105,0)))&"."&K$5 | L79: =IF(L$4<L$48,0,L51+(L65-L51)/MAX(L$49-L$48,1)*(L$4-L$48)) | M79: =IF(M$4<M$48,0,M51+(M65-M51)/MAX(M$49-M$48,1)*(M$4-M$48)) | N79: =IF(N$4<N$48,0,N51+(N65-N51)/MAX(N$49-N$48,1)*(N$4-N$48)) | O79: =IF(O$4<O$48,0,O51+(O65-O51)/MAX(O$49-O$48,1)*(O$4-O$48)) | P79: =IF(P$4<P$48,0,P51+(P65-P51)/MAX(P$49-P$48,1)*(P$4-P$48)) | Q79: =IF(Q$4<Q$48,0,Q51+(Q65-Q51)/MAX(Q$49-Q$48,1)*(Q$4-Q$48)) | R79: =IF(R$4<R$48,0,R51+(R65-R51)/MAX(R$49-R$48,1)*(R$4-R$48)) | S79: =IF(S$4<S$48,0,S51+(S65-S51)/MAX(S$49-S$48,1)*(S$4-S$48)) | ... AC79: =IF(AC$4<AC$48,0,AC51+(AC65-AC51)/MAX(AC$49-AC$48,1)*(AC$4-AC$48)) | AD79: =PATH(AD$4,AD$48,AD$49,AD51,AD65,TRUE) | AE79: =LOWER(Settings!$C$4)&".mit."&$A79&IF($C79="","","."&$C79&"."&$B79)&IF(INDEX(Variables!$D$5:$D$105,MATCH($A79,Variables!$A$5:$A$105,0))="","","."&INDEX(Variables!$D$5:$D$105,MATCH($A79,Variables!$A$5:$A$105,0)))&"."&AE$5 | AF79: =IF(AF$4<AF$48,0,AF51+(AF65-AF51)/MAX(AF$49-AF$48,1)*(AF$4-AF$48)) | AG79: =IF(AG$4<AG$48,0,AG51+(AG65-AG51)/MAX(AG$49-AG$48,1)*(AG$4-AG$48)) | AH79: =IF(AH$4<AH$48,0,AH51+(AH65-AH51)/MAX(AH$49-AH$48,1)*(AH$4-AH$48)) | AI79: =IF(AI$4<AI$48,0,AI51+(AI65-AI51)/MAX(AI$49-AI$48,1)*(AI$4-AI$48)) | AJ79: =IF(AJ$4<AJ$48,0,AJ51+(AJ65-AJ51)/MAX(AJ$49-AJ$48,1)*(AJ$4-AJ$48)) | AK79: =IF(AK$4<AK$48,0,AK51+(AK65-AK51)/MAX(AK$49-AK$48,1)*(AK$4-AK$48)) | AL79: =IF(AL$4<AL$48,0,AL51+(AL65-AL51)/MAX(AL$49-AL$48,1)*(AL$4-AL$48)) | AM79: =IF(AM$4<AM$48,0,AM51+(AM65-AM51)/MAX(AM$49-AM$48,1)*(AM$4-AM$48)) | ... AW79: =IF(AW$4<AW$48,0,AW51+(AW65-AW51)/MAX(AW$49-AW$48,1)*(AW$4-AW$48)) | AX79: =PATH(AX$4,AX$48,AX$49,AX51,AX65,TRUE)
A80: fpr | B80: coa | C80: ind | H80: =INDEX(Variables!$B$5:$B$105,MATCH($A80,Variables!$A$5:$A$105,0))&IF($C80="",""," | "&INDEX(Mapping!$B$5:$B$26,MATCH($C80,Mapping!$A$5:$A$26,0))&" | "&INDEX(Mapping!$B$30:$B$41,MATCH($B80,Mapping!$A$30:$A$41,0))) | I80: =INDEX(Variables!$C$5:$C$105,MATCH($A80,Variables!$A$5:$A$105,0)) | J80: =INDEX(Variables!$E$5:$E$105,MATCH($A80,Variables!$A$5:$A$105,0)) | K80: =LOWER(Settings!$C$4)&".mit."&$A80&IF($C80="","","."&$C80&"."&$B80)&IF(INDEX(Variables!$D$5:$D$105,MATCH($A80,Variables!$A$5:$A$105,0))="","","."&INDEX(Variables!$D$5:$D$105,MATCH($A80,Variables!$A$5:$A$105,0)))&"."&K$5 | L80: =IF(L$4<L$48,0,L52+(L66-L52)/MAX(L$49-L$48,1)*(L$4-L$48)) | M80: =IF(M$4<M$48,0,M52+(M66-M52)/MAX(M$49-M$48,1)*(M$4-M$48)) | N80: =IF(N$4<N$48,0,N52+(N66-N52)/MAX(N$49-N$48,1)*(N$4-N$48)) | O80: =IF(O$4<O$48,0,O52+(O66-O52)/MAX(O$49-O$48,1)*(O$4-O$48)) | P80: =IF(P$4<P$48,0,P52+(P66-P52)/MAX(P$49-P$48,1)*(P$4-P$48)) | Q80: =IF(Q$4<Q$48,0,Q52+(Q66-Q52)/MAX(Q$49-Q$48,1)*(Q$4-Q$48)) | R80: =IF(R$4<R$48,0,R52+(R66-R52)/MAX(R$49-R$48,1)*(R$4-R$48)) | S80: =IF(S$4<S$48,0,S52+(S66-S52)/MAX(S$49-S$48,1)*(S$4-S$48)) | ... AC80: =IF(AC$4<AC$48,0,AC52+(AC66-AC52)/MAX(AC$49-AC$48,1)*(AC$4-AC$48)) | AD80: =PATH(AD$4,AD$48,AD$49,AD52,AD66,TRUE) | AE80: =LOWER(Settings!$C$4)&".mit."&$A80&IF($C80="","","."&$C80&"."&$B80)&IF(INDEX(Variables!$D$5:$D$105,MATCH($A80,Variables!$A$5:$A$105,0))="","","."&INDEX(Variables!$D$5:$D$105,MATCH($A80,Variables!$A$5:$A$105,0)))&"."&AE$5 | AF80: =IF(AF$4<AF$48,0,AF52+(AF66-AF52)/MAX(AF$49-AF$48,1)*(AF$4-AF$48)) | AG80: =IF(AG$4<AG$48,0,AG52+(AG66-AG52)/MAX(AG$49-AG$48,1)*(AG$4-AG$48)) | AH80: =IF(AH$4<AH$48,0,AH52+(AH66-AH52)/MAX(AH$49-AH$48,1)*(AH$4-AH$48)) | AI80: =IF(AI$4<AI$48,0,AI52+(AI66-AI52)/MAX(AI$49-AI$48,1)*(AI$4-AI$48)) | AJ80: =IF(AJ$4<AJ$48,0,AJ52+(AJ66-AJ52)/MAX(AJ$49-AJ$48,1)*(AJ$4-AJ$48)) | AK80: =IF(AK$4<AK$48,0,AK52+(AK66-AK52)/MAX(AK$49-AK$48,1)*(AK$4-AK$48)) | AL80: =IF(AL$4<AL$48,0,AL52+(AL66-AL52)/MAX(AL$49-AL$48,1)*(AL$4-AL$48)) | AM80: =IF(AM$4<AM$48,0,AM52+(AM66-AM52)/MAX(AM$49-AM$48,1)*(AM$4-AM$48)) | ... AW80: =IF(AW$4<AW$48,0,AW52+(AW66-AW52)/MAX(AW$49-AW$48,1)*(AW$4-AW$48)) | AX80: =PATH(AX$4,AX$48,AX$49,AX52,AX66,TRUE)
A81: fpr | B81: nga | C81: pow | H81: =INDEX(Variables!$B$5:$B$105,MATCH($A81,Variables!$A$5:$A$105,0))&IF($C81="",""," | "&INDEX(Mapping!$B$5:$B$26,MATCH($C81,Mapping!$A$5:$A$26,0))&" | "&INDEX(Mapping!$B$30:$B$41,MATCH($B81,Mapping!$A$30:$A$41,0))) | I81: =INDEX(Variables!$C$5:$C$105,MATCH($A81,Variables!$A$5:$A$105,0)) | J81: =INDEX(Variables!$E$5:$E$105,MATCH($A81,Variables!$A$5:$A$105,0)) | K81: =LOWER(Settings!$C$4)&".mit."&$A81&IF($C81="","","."&$C81&"."&$B81)&IF(INDEX(Variables!$D$5:$D$105,MATCH($A81,Variables!$A$5:$A$105,0))="","","."&INDEX(Variables!$D$5:$D$105,MATCH($A81,Variables!$A$5:$A$105,0)))&"."&K$5 | L81: =IF(L$4<L$48,0,L53+(L67-L53)/MAX(L$49-L$48,1)*(L$4-L$48)) | M81: =IF(M$4<M$48,0,M53+(M67-M53)/MAX(M$49-M$48,1)*(M$4-M$48)) | N81: =IF(N$4<N$48,0,N53+(N67-N53)/MAX(N$49-N$48,1)*(N$4-N$48)) | O81: =IF(O$4<O$48,0,O53+(O67-O53)/MAX(O$49-O$48,1)*(O$4-O$48)) | P81: =IF(P$4<P$48,0,P53+(P67-P53)/MAX(P$49-P$48,1)*(P$4-P$48)) | Q81: =IF(Q$4<Q$48,0,Q53+(Q67-Q53)/MAX(Q$49-Q$48,1)*(Q$4-Q$48)) | R81: =IF(R$4<R$48,0,R53+(R67-R53)/MAX(R$49-R$48,1)*(R$4-R$48)) | S81: =IF(S$4<S$48,0,S53+(S67-S53)/MAX(S$49-S$48,1)*(S$4-S$48)) | ... AC81: =IF(AC$4<AC$48,0,AC53+(AC67-AC53)/MAX(AC$49-AC$48,1)*(AC$4-AC$48)) | AD81: =PATH(AD$4,AD$48,AD$49,AD53,AD67,TRUE) | AE81: =LOWER(Settings!$C$4)&".mit."&$A81&IF($C81="","","."&$C81&"."&$B81)&IF(INDEX(Variables!$D$5:$D$105,MATCH($A81,Variables!$A$5:$A$105,0))="","","."&INDEX(Variables!$D$5:$D$105,MATCH($A81,Variables!$A$5:$A$105,0)))&"."&AE$5 | AF81: =IF(AF$4<AF$48,0,AF53+(AF67-AF53)/MAX(AF$49-AF$48,1)*(AF$4-AF$48)) | AG81: =IF(AG$4<AG$48,0,AG53+(AG67-AG53)/MAX(AG$49-AG$48,1)*(AG$4-AG$48)) | AH81: =IF(AH$4<AH$48,0,AH53+(AH67-AH53)/MAX(AH$49-AH$48,1)*(AH$4-AH$48)) | AI81: =IF(AI$4<AI$48,0,AI53+(AI67-AI53)/MAX(AI$49-AI$48,1)*(AI$4-AI$48)) | AJ81: =IF(AJ$4<AJ$48,0,AJ53+(AJ67-AJ53)/MAX(AJ$49-AJ$48,1)*(AJ$4-AJ$48)) | AK81: =IF(AK$4<AK$48,0,AK53+(AK67-AK53)/MAX(AK$49-AK$48,1)*(AK$4-AK$48)) | AL81: =IF(AL$4<AL$48,0,AL53+(AL67-AL53)/MAX(AL$49-AL$48,1)*(AL$4-AL$48)) | AM81: =IF(AM$4<AM$48,0,AM53+(AM67-AM53)/MAX(AM$49-AM$48,1)*(AM$4-AM$48)) | ... AW81: =IF(AW$4<AW$48,0,AW53+(AW67-AW53)/MAX(AW$49-AW$48,1)*(AW$4-AW$48)) | AX81: =PATH(AX$4,AX$48,AX$49,AX53,AX67,TRUE)
A82: fpr | B82: nga | C82: res | H82: =INDEX(Variables!$B$5:$B$105,MATCH($A82,Variables!$A$5:$A$105,0))&IF($C82="",""," | "&INDEX(Mapping!$B$5:$B$26,MATCH($C82,Mapping!$A$5:$A$26,0))&" | "&INDEX(Mapping!$B$30:$B$41,MATCH($B82,Mapping!$A$30:$A$41,0))) | I82: =INDEX(Variables!$C$5:$C$105,MATCH($A82,Variables!$A$5:$A$105,0)) | J82: =INDEX(Variables!$E$5:$E$105,MATCH($A82,Variables!$A$5:$A$105,0)) | K82: =LOWER(Settings!$C$4)&".mit."&$A82&IF($C82="","","."&$C82&"."&$B82)&IF(INDEX(Variables!$D$5:$D$105,MATCH($A82,Variables!$A$5:$A$105,0))="","","."&INDEX(Variables!$D$5:$D$105,MATCH($A82,Variables!$A$5:$A$105,0)))&"."&K$5 | L82: =IF(L$4<L$48,0,L54+(L68-L54)/MAX(L$49-L$48,1)*(L$4-L$48)) | M82: =IF(M$4<M$48,0,M54+(M68-M54)/MAX(M$49-M$48,1)*(M$4-M$48)) | N82: =IF(N$4<N$48,0,N54+(N68-N54)/MAX(N$49-N$48,1)*(N$4-N$48)) | O82: =IF(O$4<O$48,0,O54+(O68-O54)/MAX(O$49-O$48,1)*(O$4-O$48)) | P82: =IF(P$4<P$48,0,P54+(P68-P54)/MAX(P$49-P$48,1)*(P$4-P$48)) | Q82: =IF(Q$4<Q$48,0,Q54+(Q68-Q54)/MAX(Q$49-Q$48,1)*(Q$4-Q$48)) | R82: =IF(R$4<R$48,0,R54+(R68-R54)/MAX(R$49-R$48,1)*(R$4-R$48)) | S82: =IF(S$4<S$48,0,S54+(S68-S54)/MAX(S$49-S$48,1)*(S$4-S$48)) | ... AC82: =IF(AC$4<AC$48,0,AC54+(AC68-AC54)/MAX(AC$49-AC$48,1)*(AC$4-AC$48)) | AD82: =PATH(AD$4,AD$48,AD$49,AD54,AD68,TRUE) | AE82: =LOWER(Settings!$C$4)&".mit."&$A82&IF($C82="","","."&$C82&"."&$B82)&IF(INDEX(Variables!$D$5:$D$105,MATCH($A82,Variables!$A$5:$A$105,0))="","","."&INDEX(Variables!$D$5:$D$105,MATCH($A82,Variables!$A$5:$A$105,0)))&"."&AE$5 | AF82: =IF(AF$4<AF$48,0,AF54+(AF68-AF54)/MAX(AF$49-AF$48,1)*(AF$4-AF$48)) | AG82: =IF(AG$4<AG$48,0,AG54+(AG68-AG54)/MAX(AG$49-AG$48,1)*(AG$4-AG$48)) | AH82: =IF(AH$4<AH$48,0,AH54+(AH68-AH54)/MAX(AH$49-AH$48,1)*(AH$4-AH$48)) | AI82: =IF(AI$4<AI$48,0,AI54+(AI68-AI54)/MAX(AI$49-AI$48,1)*(AI$4-AI$48)) | AJ82: =IF(AJ$4<AJ$48,0,AJ54+(AJ68-AJ54)/MAX(AJ$49-AJ$48,1)*(AJ$4-AJ$48)) | AK82: =IF(AK$4<AK$48,0,AK54+(AK68-AK54)/MAX(AK$49-AK$48,1)*(AK$4-AK$48)) | AL82: =IF(AL$4<AL$48,0,AL54+(AL68-AL54)/MAX(AL$49-AL$48,1)*(AL$4-AL$48)) | AM82: =IF(AM$4<AM$48,0,AM54+(AM68-AM54)/MAX(AM$49-AM$48,1)*(AM$4-AM$48)) | ... AW82: =IF(AW$4<AW$48,0,AW54+(AW68-AW54)/MAX(AW$49-AW$48,1)*(AW$4-AW$48)) | AX82: =PATH(AX$4,AX$48,AX$49,AX54,AX68,TRUE)
A83: fpr | B83: nga | C83: ind | H83: =INDEX(Variables!$B$5:$B$105,MATCH($A83,Variables!$A$5:$A$105,0))&IF($C83="",""," | "&INDEX(Mapping!$B$5:$B$26,MATCH($C83,Mapping!$A$5:$A$26,0))&" | "&INDEX(Mapping!$B$30:$B$41,MATCH($B83,Mapping!$A$30:$A$41,0))) | I83: =INDEX(Variables!$C$5:$C$105,MATCH($A83,Variables!$A$5:$A$105,0)) | J83: =INDEX(Variables!$E$5:$E$105,MATCH($A83,Variables!$A$5:$A$105,0)) | K83: =LOWER(Settings!$C$4)&".mit."&$A83&IF($C83="","","."&$C83&"."&$B83)&IF(INDEX(Variables!$D$5:$D$105,MATCH($A83,Variables!$A$5:$A$105,0))="","","."&INDEX(Variables!$D$5:$D$105,MATCH($A83,Variables!$A$5:$A$105,0)))&"."&K$5 | L83: =IF(L$4<L$48,0,L55+(L69-L55)/MAX(L$49-L$48,1)*(L$4-L$48)) | M83: =IF(M$4<M$48,0,M55+(M69-M55)/MAX(M$49-M$48,1)*(M$4-M$48)) | N83: =IF(N$4<N$48,0,N55+(N69-N55)/MAX(N$49-N$48,1)*(N$4-N$48)) | O83: =IF(O$4<O$48,0,O55+(O69-O55)/MAX(O$49-O$48,1)*(O$4-O$48)) | P83: =IF(P$4<P$48,0,P55+(P69-P55)/MAX(P$49-P$48,1)*(P$4-P$48)) | Q83: =IF(Q$4<Q$48,0,Q55+(Q69-Q55)/MAX(Q$49-Q$48,1)*(Q$4-Q$48)) | R83: =IF(R$4<R$48,0,R55+(R69-R55)/MAX(R$49-R$48,1)*(R$4-R$48)) | S83: =IF(S$4<S$48,0,S55+(S69-S55)/MAX(S$49-S$48,1)*(S$4-S$48)) | ... AC83: =IF(AC$4<AC$48,0,AC55+(AC69-AC55)/MAX(AC$49-AC$48,1)*(AC$4-AC$48)) | AD83: =PATH(AD$4,AD$48,AD$49,AD55,AD69,TRUE) | AE83: =LOWER(Settings!$C$4)&".mit."&$A83&IF($C83="","","."&$C83&"."&$B83)&IF(INDEX(Variables!$D$5:$D$105,MATCH($A83,Variables!$A$5:$A$105,0))="","","."&INDEX(Variables!$D$5:$D$105,MATCH($A83,Variables!$A$5:$A$105,0)))&"."&AE$5 | AF83: =IF(AF$4<AF$48,0,AF55+(AF69-AF55)/MAX(AF$49-AF$48,1)*(AF$4-AF$48)) | AG83: =IF(AG$4<AG$48,0,AG55+(AG69-AG55)/MAX(AG$49-AG$48,1)*(AG$4-AG$48)) | AH83: =IF(AH$4<AH$48,0,AH55+(AH69-AH55)/MAX(AH$49-AH$48,1)*(AH$4-AH$48)) | AI83: =IF(AI$4<AI$48,0,AI55+(AI69-AI55)/MAX(AI$49-AI$48,1)*(AI$4-AI$48)) | AJ83: =IF(AJ$4<AJ$48,0,AJ55+(AJ69-AJ55)/MAX(AJ$49-AJ$48,1)*(AJ$4-AJ$48)) | AK83: =IF(AK$4<AK$48,0,AK55+(AK69-AK55)/MAX(AK$49-AK$48,1)*(AK$4-AK$48)) | AL83: =IF(AL$4<AL$48,0,AL55+(AL69-AL55)/MAX(AL$49-AL$48,1)*(AL$4-AL$48)) | AM83: =IF(AM$4<AM$48,0,AM55+(AM69-AM55)/MAX(AM$49-AM$48,1)*(AM$4-AM$48)) | ... AW83: =IF(AW$4<AW$48,0,AW55+(AW69-AW55)/MAX(AW$49-AW$48,1)*(AW$4-AW$48)) | AX83: =PATH(AX$4,AX$48,AX$49,AX55,AX69,TRUE)
A84: fpr | B84: ecy | C84: res | H84: =INDEX(Variables!$B$5:$B$105,MATCH($A84,Variables!$A$5:$A$105,0))&IF($C84="",""," | "&INDEX(Mapping!$B$5:$B$26,MATCH($C84,Mapping!$A$5:$A$26,0))&" | "&INDEX(Mapping!$B$30:$B$41,MATCH($B84,Mapping!$A$30:$A$41,0))) | I84: =INDEX(Variables!$C$5:$C$105,MATCH($A84,Variables!$A$5:$A$105,0)) | J84: =INDEX(Variables!$E$5:$E$105,MATCH($A84,Variables!$A$5:$A$105,0)) | K84: =LOWER(Settings!$C$4)&".mit."&$A84&IF($C84="","","."&$C84&"."&$B84)&IF(INDEX(Variables!$D$5:$D$105,MATCH($A84,Variables!$A$5:$A$105,0))="","","."&INDEX(Variables!$D$5:$D$105,MATCH($A84,Variables!$A$5:$A$105,0)))&"."&K$5 | L84: =IF(L$4<L$48,0,L56+(L70-L56)/MAX(L$49-L$48,1)*(L$4-L$48)) | M84: =IF(M$4<M$48,0,M56+(M70-M56)/MAX(M$49-M$48,1)*(M$4-M$48)) | N84: =IF(N$4<N$48,0,N56+(N70-N56)/MAX(N$49-N$48,1)*(N$4-N$48)) | O84: =IF(O$4<O$48,0,O56+(O70-O56)/MAX(O$49-O$48,1)*(O$4-O$48)) | P84: =IF(P$4<P$48,0,P56+(P70-P56)/MAX(P$49-P$48,1)*(P$4-P$48)) | Q84: =IF(Q$4<Q$48,0,Q56+(Q70-Q56)/MAX(Q$49-Q$48,1)*(Q$4-Q$48)) | R84: =IF(R$4<R$48,0,R56+(R70-R56)/MAX(R$49-R$48,1)*(R$4-R$48)) | S84: =IF(S$4<S$48,0,S56+(S70-S56)/MAX(S$49-S$48,1)*(S$4-S$48)) | ... AC84: =IF(AC$4<AC$48,0,AC56+(AC70-AC56)/MAX(AC$49-AC$48,1)*(AC$4-AC$48)) | AD84: =PATH(AD$4,AD$48,AD$49,AD56,AD70,TRUE) | AE84: =LOWER(Settings!$C$4)&".mit."&$A84&IF($C84="","","."&$C84&"."&$B84)&IF(INDEX(Variables!$D$5:$D$105,MATCH($A84,Variables!$A$5:$A$105,0))="","","."&INDEX(Variables!$D$5:$D$105,MATCH($A84,Variables!$A$5:$A$105,0)))&"."&AE$5 | AF84: =IF(AF$4<AF$48,0,AF56+(AF70-AF56)/MAX(AF$49-AF$48,1)*(AF$4-AF$48)) | AG84: =IF(AG$4<AG$48,0,AG56+(AG70-AG56)/MAX(AG$49-AG$48,1)*(AG$4-AG$48)) | AH84: =IF(AH$4<AH$48,0,AH56+(AH70-AH56)/MAX(AH$49-AH$48,1)*(AH$4-AH$48)) | AI84: =IF(AI$4<AI$48,0,AI56+(AI70-AI56)/MAX(AI$49-AI$48,1)*(AI$4-AI$48)) | AJ84: =IF(AJ$4<AJ$48,0,AJ56+(AJ70-AJ56)/MAX(AJ$49-AJ$48,1)*(AJ$4-AJ$48)) | AK84: =IF(AK$4<AK$48,0,AK56+(AK70-AK56)/MAX(AK$49-AK$48,1)*(AK$4-AK$48)) | AL84: =IF(AL$4<AL$48,0,AL56+(AL70-AL56)/MAX(AL$49-AL$48,1)*(AL$4-AL$48)) | AM84: =IF(AM$4<AM$48,0,AM56+(AM70-AM56)/MAX(AM$49-AM$48,1)*(AM$4-AM$48)) | ... AW84: =IF(AW$4<AW$48,0,AW56+(AW70-AW56)/MAX(AW$49-AW$48,1)*(AW$4-AW$48)) | AX84: =PATH(AX$4,AX$48,AX$49,AX56,AX70,TRUE)
A85: fpr | B85: ecy | C85: ind | H85: =INDEX(Variables!$B$5:$B$105,MATCH($A85,Variables!$A$5:$A$105,0))&IF($C85="",""," | "&INDEX(Mapping!$B$5:$B$26,MATCH($C85,Mapping!$A$5:$A$26,0))&" | "&INDEX(Mapping!$B$30:$B$41,MATCH($B85,Mapping!$A$30:$A$41,0))) | I85: =INDEX(Variables!$C$5:$C$105,MATCH($A85,Variables!$A$5:$A$105,0)) | J85: =INDEX(Variables!$E$5:$E$105,MATCH($A85,Variables!$A$5:$A$105,0)) | K85: =LOWER(Settings!$C$4)&".mit."&$A85&IF($C85="","","."&$C85&"."&$B85)&IF(INDEX(Variables!$D$5:$D$105,MATCH($A85,Variables!$A$5:$A$105,0))="","","."&INDEX(Variables!$D$5:$D$105,MATCH($A85,Variables!$A$5:$A$105,0)))&"."&K$5 | L85: =IF(L$4<L$48,0,L57+(L71-L57)/MAX(L$49-L$48,1)*(L$4-L$48)) | M85: =IF(M$4<M$48,0,M57+(M71-M57)/MAX(M$49-M$48,1)*(M$4-M$48)) | N85: =IF(N$4<N$48,0,N57+(N71-N57)/MAX(N$49-N$48,1)*(N$4-N$48)) | O85: =IF(O$4<O$48,0,O57+(O71-O57)/MAX(O$49-O$48,1)*(O$4-O$48)) | P85: =IF(P$4<P$48,0,P57+(P71-P57)/MAX(P$49-P$48,1)*(P$4-P$48)) | Q85: =IF(Q$4<Q$48,0,Q57+(Q71-Q57)/MAX(Q$49-Q$48,1)*(Q$4-Q$48)) | R85: =IF(R$4<R$48,0,R57+(R71-R57)/MAX(R$49-R$48,1)*(R$4-R$48)) | S85: =IF(S$4<S$48,0,S57+(S71-S57)/MAX(S$49-S$48,1)*(S$4-S$48)) | ... AC85: =IF(AC$4<AC$48,0,AC57+(AC71-AC57)/MAX(AC$49-AC$48,1)*(AC$4-AC$48)) | AD85: =PATH(AD$4,AD$48,AD$49,AD57,AD71,TRUE) | AE85: =LOWER(Settings!$C$4)&".mit."&$A85&IF($C85="","","."&$C85&"."&$B85)&IF(INDEX(Variables!$D$5:$D$105,MATCH($A85,Variables!$A$5:$A$105,0))="","","."&INDEX(Variables!$D$5:$D$105,MATCH($A85,Variables!$A$5:$A$105,0)))&"."&AE$5 | AF85: =IF(AF$4<AF$48,0,AF57+(AF71-AF57)/MAX(AF$49-AF$48,1)*(AF$4-AF$48)) | AG85: =IF(AG$4<AG$48,0,AG57+(AG71-AG57)/MAX(AG$49-AG$48,1)*(AG$4-AG$48)) | AH85: =IF(AH$4<AH$48,0,AH57+(AH71-AH57)/MAX(AH$49-AH$48,1)*(AH$4-AH$48)) | AI85: =IF(AI$4<AI$48,0,AI57+(AI71-AI57)/MAX(AI$49-AI$48,1)*(AI$4-AI$48)) | AJ85: =IF(AJ$4<AJ$48,0,AJ57+(AJ71-AJ57)/MAX(AJ$49-AJ$48,1)*(AJ$4-AJ$48)) | AK85: =IF(AK$4<AK$48,0,AK57+(AK71-AK57)/MAX(AK$49-AK$48,1)*(AK$4-AK$48)) | AL85: =IF(AL$4<AL$48,0,AL57+(AL71-AL57)/MAX(AL$49-AL$48,1)*(AL$4-AL$48)) | AM85: =IF(AM$4<AM$48,0,AM57+(AM71-AM57)/MAX(AM$49-AM$48,1)*(AM$4-AM$48)) | ... AW85: =IF(AW$4<AW$48,0,AW57+(AW71-AW57)/MAX(AW$49-AW$48,1)*(AW$4-AW$48)) | AX85: =PATH(AX$4,AX$48,AX$49,AX57,AX71,TRUE)
A86: fpr | B86: gso | C86: all | H86: =INDEX(Variables!$B$5:$B$105,MATCH($A86,Variables!$A$5:$A$105,0))&IF($C86="",""," | "&INDEX(Mapping!$B$5:$B$26,MATCH($C86,Mapping!$A$5:$A$26,0))&" | "&INDEX(Mapping!$B$30:$B$41,MATCH($B86,Mapping!$A$30:$A$41,0))) | I86: =INDEX(Variables!$C$5:$C$105,MATCH($A86,Variables!$A$5:$A$105,0)) | J86: =INDEX(Variables!$E$5:$E$105,MATCH($A86,Variables!$A$5:$A$105,0)) | K86: =LOWER(Settings!$C$4)&".mit."&$A86&IF($C86="","","."&$C86&"."&$B86)&IF(INDEX(Variables!$D$5:$D$105,MATCH($A86,Variables!$A$5:$A$105,0))="","","."&INDEX(Variables!$D$5:$D$105,MATCH($A86,Variables!$A$5:$A$105,0)))&"."&K$5 | L86: =IF(L$4<L$48,0,L58+(L72-L58)/MAX(L$49-L$48,1)*(L$4-L$48)) | M86: =IF(M$4<M$48,0,M58+(M72-M58)/MAX(M$49-M$48,1)*(M$4-M$48)) | N86: =IF(N$4<N$48,0,N58+(N72-N58)/MAX(N$49-N$48,1)*(N$4-N$48)) | O86: =IF(O$4<O$48,0,O58+(O72-O58)/MAX(O$49-O$48,1)*(O$4-O$48)) | P86: =IF(P$4<P$48,0,P58+(P72-P58)/MAX(P$49-P$48,1)*(P$4-P$48)) | Q86: =IF(Q$4<Q$48,0,Q58+(Q72-Q58)/MAX(Q$49-Q$48,1)*(Q$4-Q$48)) | R86: =IF(R$4<R$48,0,R58+(R72-R58)/MAX(R$49-R$48,1)*(R$4-R$48)) | S86: =IF(S$4<S$48,0,S58+(S72-S58)/MAX(S$49-S$48,1)*(S$4-S$48)) | ... AC86: =IF(AC$4<AC$48,0,AC58+(AC72-AC58)/MAX(AC$49-AC$48,1)*(AC$4-AC$48)) | AD86: =PATH(AD$4,AD$48,AD$49,AD58,AD72,TRUE) | AE86: =LOWER(Settings!$C$4)&".mit."&$A86&IF($C86="","","."&$C86&"."&$B86)&IF(INDEX(Variables!$D$5:$D$105,MATCH($A86,Variables!$A$5:$A$105,0))="","","."&INDEX(Variables!$D$5:$D$105,MATCH($A86,Variables!$A$5:$A$105,0)))&"."&AE$5 | AF86: =IF(AF$4<AF$48,0,AF58+(AF72-AF58)/MAX(AF$49-AF$48,1)*(AF$4-AF$48)) | AG86: =IF(AG$4<AG$48,0,AG58+(AG72-AG58)/MAX(AG$49-AG$48,1)*(AG$4-AG$48)) | AH86: =IF(AH$4<AH$48,0,AH58+(AH72-AH58)/MAX(AH$49-AH$48,1)*(AH$4-AH$48)) | AI86: =IF(AI$4<AI$48,0,AI58+(AI72-AI58)/MAX(AI$49-AI$48,1)*(AI$4-AI$48)) | AJ86: =IF(AJ$4<AJ$48,0,AJ58+(AJ72-AJ58)/MAX(AJ$49-AJ$48,1)*(AJ$4-AJ$48)) | AK86: =IF(AK$4<AK$48,0,AK58+(AK72-AK58)/MAX(AK$49-AK$48,1)*(AK$4-AK$48)) | AL86: =IF(AL$4<AL$48,0,AL58+(AL72-AL58)/MAX(AL$49-AL$48,1)*(AL$4-AL$48)) | AM86: =IF(AM$4<AM$48,0,AM58+(AM72-AM58)/MAX(AM$49-AM$48,1)*(AM$4-AM$48)) | ... AW86: =IF(AW$4<AW$48,0,AW58+(AW72-AW58)/MAX(AW$49-AW$48,1)*(AW$4-AW$48)) | AX86: =PATH(AX$4,AX$48,AX$49,AX58,AX72,TRUE)
A87: fpr | B87: die | C87: all | H87: =INDEX(Variables!$B$5:$B$105,MATCH($A87,Variables!$A$5:$A$105,0))&IF($C87="",""," | "&INDEX(Mapping!$B$5:$B$26,MATCH($C87,Mapping!$A$5:$A$26,0))&" | "&INDEX(Mapping!$B$30:$B$41,MATCH($B87,Mapping!$A$30:$A$41,0))) | I87: =INDEX(Variables!$C$5:$C$105,MATCH($A87,Variables!$A$5:$A$105,0)) | J87: =INDEX(Variables!$E$5:$E$105,MATCH($A87,Variables!$A$5:$A$105,0)) | K87: =LOWER(Settings!$C$4)&".mit."&$A87&IF($C87="","","."&$C87&"."&$B87)&IF(INDEX(Variables!$D$5:$D$105,MATCH($A87,Variables!$A$5:$A$105,0))="","","."&INDEX(Variables!$D$5:$D$105,MATCH($A87,Variables!$A$5:$A$105,0)))&"."&K$5 | L87: =IF(L$4<L$48,0,L59+(L73-L59)/MAX(L$49-L$48,1)*(L$4-L$48)) | M87: =IF(M$4<M$48,0,M59+(M73-M59)/MAX(M$49-M$48,1)*(M$4-M$48)) | N87: =IF(N$4<N$48,0,N59+(N73-N59)/MAX(N$49-N$48,1)*(N$4-N$48)) | O87: =IF(O$4<O$48,0,O59+(O73-O59)/MAX(O$49-O$48,1)*(O$4-O$48)) | P87: =IF(P$4<P$48,0,P59+(P73-P59)/MAX(P$49-P$48,1)*(P$4-P$48)) | Q87: =IF(Q$4<Q$48,0,Q59+(Q73-Q59)/MAX(Q$49-Q$48,1)*(Q$4-Q$48)) | R87: =IF(R$4<R$48,0,R59+(R73-R59)/MAX(R$49-R$48,1)*(R$4-R$48)) | S87: =IF(S$4<S$48,0,S59+(S73-S59)/MAX(S$49-S$48,1)*(S$4-S$48)) | ... AC87: =IF(AC$4<AC$48,0,AC59+(AC73-AC59)/MAX(AC$49-AC$48,1)*(AC$4-AC$48)) | AD87: =PATH(AD$4,AD$48,AD$49,AD59,AD73,TRUE) | AE87: =LOWER(Settings!$C$4)&".mit."&$A87&IF($C87="","","."&$C87&"."&$B87)&IF(INDEX(Variables!$D$5:$D$105,MATCH($A87,Variables!$A$5:$A$105,0))="","","."&INDEX(Variables!$D$5:$D$105,MATCH($A87,Variables!$A$5:$A$105,0)))&"."&AE$5 | AF87: =IF(AF$4<AF$48,0,AF59+(AF73-AF59)/MAX(AF$49-AF$48,1)*(AF$4-AF$48)) | AG87: =IF(AG$4<AG$48,0,AG59+(AG73-AG59)/MAX(AG$49-AG$48,1)*(AG$4-AG$48)) | AH87: =IF(AH$4<AH$48,0,AH59+(AH73-AH59)/MAX(AH$49-AH$48,1)*(AH$4-AH$48)) | AI87: =IF(AI$4<AI$48,0,AI59+(AI73-AI59)/MAX(AI$49-AI$48,1)*(AI$4-AI$48)) | AJ87: =IF(AJ$4<AJ$48,0,AJ59+(AJ73-AJ59)/MAX(AJ$49-AJ$48,1)*(AJ$4-AJ$48)) | AK87: =IF(AK$4<AK$48,0,AK59+(AK73-AK59)/MAX(AK$49-AK$48,1)*(AK$4-AK$48)) | AL87: =IF(AL$4<AL$48,0,AL59+(AL73-AL59)/MAX(AL$49-AL$48,1)*(AL$4-AL$48)) | AM87: =IF(AM$4<AM$48,0,AM59+(AM73-AM59)/MAX(AM$49-AM$48,1)*(AM$4-AM$48)) | ... AW87: =IF(AW$4<AW$48,0,AW59+(AW73-AW59)/MAX(AW$49-AW$48,1)*(AW$4-AW$48)) | AX87: =PATH(AX$4,AX$48,AX$49,AX59,AX73,TRUE)
A88: fpr | B88: lpg | C88: all | H88: =INDEX(Variables!$B$5:$B$105,MATCH($A88,Variables!$A$5:$A$105,0))&IF($C88="",""," | "&INDEX(Mapping!$B$5:$B$26,MATCH($C88,Mapping!$A$5:$A$26,0))&" | "&INDEX(Mapping!$B$30:$B$41,MATCH($B88,Mapping!$A$30:$A$41,0))) | I88: =INDEX(Variables!$C$5:$C$105,MATCH($A88,Variables!$A$5:$A$105,0)) | J88: =INDEX(Variables!$E$5:$E$105,MATCH($A88,Variables!$A$5:$A$105,0)) | K88: =LOWER(Settings!$C$4)&".mit."&$A88&IF($C88="","","."&$C88&"."&$B88)&IF(INDEX(Variables!$D$5:$D$105,MATCH($A88,Variables!$A$5:$A$105,0))="","","."&INDEX(Variables!$D$5:$D$105,MATCH($A88,Variables!$A$5:$A$105,0)))&"."&K$5 | L88: =IF(L$4<L$48,0,L60+(L74-L60)/MAX(L$49-L$48,1)*(L$4-L$48)) | M88: =IF(M$4<M$48,0,M60+(M74-M60)/MAX(M$49-M$48,1)*(M$4-M$48)) | N88: =IF(N$4<N$48,0,N60+(N74-N60)/MAX(N$49-N$48,1)*(N$4-N$48)) | O88: =IF(O$4<O$48,0,O60+(O74-O60)/MAX(O$49-O$48,1)*(O$4-O$48)) | P88: =IF(P$4<P$48,0,P60+(P74-P60)/MAX(P$49-P$48,1)*(P$4-P$48)) | Q88: =IF(Q$4<Q$48,0,Q60+(Q74-Q60)/MAX(Q$49-Q$48,1)*(Q$4-Q$48)) | R88: =IF(R$4<R$48,0,R60+(R74-R60)/MAX(R$49-R$48,1)*(R$4-R$48)) | S88: =IF(S$4<S$48,0,S60+(S74-S60)/MAX(S$49-S$48,1)*(S$4-S$48)) | ... AC88: =IF(AC$4<AC$48,0,AC60+(AC74-AC60)/MAX(AC$49-AC$48,1)*(AC$4-AC$48)) | AD88: =PATH(AD$4,AD$48,AD$49,AD60,AD74,TRUE) | AE88: =LOWER(Settings!$C$4)&".mit."&$A88&IF($C88="","","."&$C88&"."&$B88)&IF(INDEX(Variables!$D$5:$D$105,MATCH($A88,Variables!$A$5:$A$105,0))="","","."&INDEX(Variables!$D$5:$D$105,MATCH($A88,Variables!$A$5:$A$105,0)))&"."&AE$5 | AF88: =IF(AF$4<AF$48,0,AF60+(AF74-AF60)/MAX(AF$49-AF$48,1)*(AF$4-AF$48)) | AG88: =IF(AG$4<AG$48,0,AG60+(AG74-AG60)/MAX(AG$49-AG$48,1)*(AG$4-AG$48)) | AH88: =IF(AH$4<AH$48,0,AH60+(AH74-AH60)/MAX(AH$49-AH$48,1)*(AH$4-AH$48)) | AI88: =IF(AI$4<AI$48,0,AI60+(AI74-AI60)/MAX(AI$49-AI$48,1)*(AI$4-AI$48)) | AJ88: =IF(AJ$4<AJ$48,0,AJ60+(AJ74-AJ60)/MAX(AJ$49-AJ$48,1)*(AJ$4-AJ$48)) | AK88: =IF(AK$4<AK$48,0,AK60+(AK74-AK60)/MAX(AK$49-AK$48,1)*(AK$4-AK$48)) | AL88: =IF(AL$4<AL$48,0,AL60+(AL74-AL60)/MAX(AL$49-AL$48,1)*(AL$4-AL$48)) | AM88: =IF(AM$4<AM$48,0,AM60+(AM74-AM60)/MAX(AM$49-AM$48,1)*(AM$4-AM$48)) | ... AW88: =IF(AW$4<AW$48,0,AW60+(AW74-AW60)/MAX(AW$49-AW$48,1)*(AW$4-AW$48)) | AX88: =PATH(AX$4,AX$48,AX$49,AX60,AX74,TRUE)
A89: fpr | B89: ker | C89: all | H89: =INDEX(Variables!$B$5:$B$105,MATCH($A89,Variables!$A$5:$A$105,0))&IF($C89="",""," | "&INDEX(Mapping!$B$5:$B$26,MATCH($C89,Mapping!$A$5:$A$26,0))&" | "&INDEX(Mapping!$B$30:$B$41,MATCH($B89,Mapping!$A$30:$A$41,0))) | I89: =INDEX(Variables!$C$5:$C$105,MATCH($A89,Variables!$A$5:$A$105,0)) | J89: =INDEX(Variables!$E$5:$E$105,MATCH($A89,Variables!$A$5:$A$105,0)) | K89: =LOWER(Settings!$C$4)&".mit."&$A89&IF($C89="","","."&$C89&"."&$B89)&IF(INDEX(Variables!$D$5:$D$105,MATCH($A89,Variables!$A$5:$A$105,0))="","","."&INDEX(Variables!$D$5:$D$105,MATCH($A89,Variables!$A$5:$A$105,0)))&"."&K$5 | L89: =IF(L$4<L$48,0,L61+(L75-L61)/MAX(L$49-L$48,1)*(L$4-L$48)) | M89: =IF(M$4<M$48,0,M61+(M75-M61)/MAX(M$49-M$48,1)*(M$4-M$48)) | N89: =IF(N$4<N$48,0,N61+(N75-N61)/MAX(N$49-N$48,1)*(N$4-N$48)) | O89: =IF(O$4<O$48,0,O61+(O75-O61)/MAX(O$49-O$48,1)*(O$4-O$48)) | P89: =IF(P$4<P$48,0,P61+(P75-P61)/MAX(P$49-P$48,1)*(P$4-P$48)) | Q89: =IF(Q$4<Q$48,0,Q61+(Q75-Q61)/MAX(Q$49-Q$48,1)*(Q$4-Q$48)) | R89: =IF(R$4<R$48,0,R61+(R75-R61)/MAX(R$49-R$48,1)*(R$4-R$48)) | S89: =IF(S$4<S$48,0,S61+(S75-S61)/MAX(S$49-S$48,1)*(S$4-S$48)) | ... AC89: =IF(AC$4<AC$48,0,AC61+(AC75-AC61)/MAX(AC$49-AC$48,1)*(AC$4-AC$48)) | AD89: =PATH(AD$4,AD$48,AD$49,AD61,AD75,TRUE) | AE89: =LOWER(Settings!$C$4)&".mit."&$A89&IF($C89="","","."&$C89&"."&$B89)&IF(INDEX(Variables!$D$5:$D$105,MATCH($A89,Variables!$A$5:$A$105,0))="","","."&INDEX(Variables!$D$5:$D$105,MATCH($A89,Variables!$A$5:$A$105,0)))&"."&AE$5 | AF89: =IF(AF$4<AF$48,0,AF61+(AF75-AF61)/MAX(AF$49-AF$48,1)*(AF$4-AF$48)) | AG89: =IF(AG$4<AG$48,0,AG61+(AG75-AG61)/MAX(AG$49-AG$48,1)*(AG$4-AG$48)) | AH89: =IF(AH$4<AH$48,0,AH61+(AH75-AH61)/MAX(AH$49-AH$48,1)*(AH$4-AH$48)) | AI89: =IF(AI$4<AI$48,0,AI61+(AI75-AI61)/MAX(AI$49-AI$48,1)*(AI$4-AI$48)) | AJ89: =IF(AJ$4<AJ$48,0,AJ61+(AJ75-AJ61)/MAX(AJ$49-AJ$48,1)*(AJ$4-AJ$48)) | AK89: =IF(AK$4<AK$48,0,AK61+(AK75-AK61)/MAX(AK$49-AK$48,1)*(AK$4-AK$48)) | AL89: =IF(AL$4<AL$48,0,AL61+(AL75-AL61)/MAX(AL$49-AL$48,1)*(AL$4-AL$48)) | AM89: =IF(AM$4<AM$48,0,AM61+(AM75-AM61)/MAX(AM$49-AM$48,1)*(AM$4-AM$48)) | ... AW89: =IF(AW$4<AW$48,0,AW61+(AW75-AW61)/MAX(AW$49-AW$48,1)*(AW$4-AW$48)) | AX89: =PATH(AX$4,AX$48,AX$49,AX61,AX75,TRUE)
... A91: fpr | B91: bio | C91: all | H91: =INDEX(Variables!$B$5:$B$105,MATCH($A91,Variables!$A$5:$A$105,0))&IF($C91="",""," | "&INDEX(Mapping!$B$5:$B$26,MATCH($C91,Mapping!$A$5:$A$26,0))&" | "&INDEX(Mapping!$B$30:$B$41,MATCH($B91,Mapping!$A$30:$A$41,0))) | I91: =INDEX(Variables!$C$5:$C$105,MATCH($A91,Variables!$A$5:$A$105,0)) | J91: =INDEX(Variables!$E$5:$E$105,MATCH($A91,Variables!$A$5:$A$105,0)) | K91: =LOWER(Settings!$C$4)&".mit."&$A91&IF($C91="","","."&$C91&"."&$B91)&IF(INDEX(Variables!$D$5:$D$105,MATCH($A91,Variables!$A$5:$A$105,0))="","","."&INDEX(Variables!$D$5:$D$105,MATCH($A91,Variables!$A$5:$A$105,0)))&"."&K$5 | L91: =IF(L$4<L$48,0,L63+(L77-L63)/MAX(L$49-L$48,1)*(L$4-L$48)) | M91: =IF(M$4<M$48,0,M63+(M77-M63)/MAX(M$49-M$48,1)*(M$4-M$48)) | N91: =IF(N$4<N$48,0,N63+(N77-N63)/MAX(N$49-N$48,1)*(N$4-N$48)) | O91: =IF(O$4<O$48,0,O63+(O77-O63)/MAX(O$49-O$48,1)*(O$4-O$48)) | P91: =IF(P$4<P$48,0,P63+(P77-P63)/MAX(P$49-P$48,1)*(P$4-P$48)) | Q91: =IF(Q$4<Q$48,0,Q63+(Q77-Q63)/MAX(Q$49-Q$48,1)*(Q$4-Q$48)) | R91: =IF(R$4<R$48,0,R63+(R77-R63)/MAX(R$49-R$48,1)*(R$4-R$48)) | S91: =IF(S$4<S$48,0,S63+(S77-S63)/MAX(S$49-S$48,1)*(S$4-S$48)) | ... AC91: =IF(AC$4<AC$48,0,AC63+(AC77-AC63)/MAX(AC$49-AC$48,1)*(AC$4-AC$48)) | AD91: =PATH(AD$4,AD$48,AD$49,AD63,AD77,TRUE) | AE91: =LOWER(Settings!$C$4)&".mit."&$A91&IF($C91="","","."&$C91&"."&$B91)&IF(INDEX(Variables!$D$5:$D$105,MATCH($A91,Variables!$A$5:$A$105,0))="","","."&INDEX(Variables!$D$5:$D$105,MATCH($A91,Variables!$A$5:$A$105,0)))&"."&AE$5 | AF91: =IF(AF$4<AF$48,0,AF63+(AF77-AF63)/MAX(AF$49-AF$48,1)*(AF$4-AF$48)) | AG91: =IF(AG$4<AG$48,0,AG63+(AG77-AG63)/MAX(AG$49-AG$48,1)*(AG$4-AG$48)) | AH91: =IF(AH$4<AH$48,0,AH63+(AH77-AH63)/MAX(AH$49-AH$48,1)*(AH$4-AH$48)) | AI91: =IF(AI$4<AI$48,0,AI63+(AI77-AI63)/MAX(AI$49-AI$48,1)*(AI$4-AI$48)) | AJ91: =IF(AJ$4<AJ$48,0,AJ63+(AJ77-AJ63)/MAX(AJ$49-AJ$48,1)*(AJ$4-AJ$48)) | AK91: =IF(AK$4<AK$48,0,AK63+(AK77-AK63)/MAX(AK$49-AK$48,1)*(AK$4-AK$48)) | AL91: =IF(AL$4<AL$48,0,AL63+(AL77-AL63)/MAX(AL$49-AL$48,1)*(AL$4-AL$48)) | AM91: =IF(AM$4<AM$48,0,AM63+(AM77-AM63)/MAX(AM$49-AM$48,1)*(AM$4-AM$48)) | ... AW91: =IF(AW$4<AW$48,0,AW63+(AW77-AW63)/MAX(AW$49-AW$48,1)*(AW$4-AW$48)) | AX91: =PATH(AX$4,AX$48,AX$49,AX63,AX77,TRUE)
H92: New ETS (MTInputs rows 84-92; permit price = carbon price inputs, as effective as a carbon tax; replaces the carbon tax in covered sectors)
A93: D_NewETS | D93: 84 | H93: =INDEX(Variables!$B$5:$B$105,MATCH($A93,Variables!$A$5:$A$105,0))&IF($C93="",""," | "&INDEX(Mapping!$B$5:$B$26,MATCH($C93,Mapping!$A$5:$A$26,0))&" | "&INDEX(Mapping!$B$30:$B$41,MATCH($B93,Mapping!$A$30:$A$41,0))) | I93: =INDEX(Variables!$C$5:$C$105,MATCH($A93,Variables!$A$5:$A$105,0)) | J93: =INDEX(Variables!$E$5:$E$105,MATCH($A93,Variables!$A$5:$A$105,0)) | K93: =LOWER(Settings!$C$4)&".mit."&$A93&IF($C93="","","."&$C93&"."&$B93)&IF(INDEX(Variables!$D$5:$D$105,MATCH($A93,Variables!$A$5:$A$105,0))="","","."&INDEX(Variables!$D$5:$D$105,MATCH($A93,Variables!$A$5:$A$105,0)))&"."&K$5 | L93: =INDEX(MTInputs!$J$1:$AZ$415,$D93,MATCH(L$5,MTInputs!$J$5:$AZ$5,0)) | M93: =INDEX(MTInputs!$J$1:$AZ$415,$D93,MATCH(M$5,MTInputs!$J$5:$AZ$5,0)) | N93: =INDEX(MTInputs!$J$1:$AZ$415,$D93,MATCH(N$5,MTInputs!$J$5:$AZ$5,0)) | O93: =INDEX(MTInputs!$J$1:$AZ$415,$D93,MATCH(O$5,MTInputs!$J$5:$AZ$5,0)) | P93: =INDEX(MTInputs!$J$1:$AZ$415,$D93,MATCH(P$5,MTInputs!$J$5:$AZ$5,0)) | Q93: =INDEX(MTInputs!$J$1:$AZ$415,$D93,MATCH(Q$5,MTInputs!$J$5:$AZ$5,0)) | R93: =INDEX(MTInputs!$J$1:$AZ$415,$D93,MATCH(R$5,MTInputs!$J$5:$AZ$5,0)) | S93: =INDEX(MTInputs!$J$1:$AZ$415,$D93,MATCH(S$5,MTInputs!$J$5:$AZ$5,0)) | ... AD93: =INDEX(MTInputs!$J$1:$AZ$415,$D93,MATCH(AD$5,MTInputs!$J$5:$AZ$5,0)) | AE93: =LOWER(Settings!$C$4)&".mit."&$A93&IF($C93="","","."&$C93&"."&$B93)&IF(INDEX(Variables!$D$5:$D$105,MATCH($A93,Variables!$A$5:$A$105,0))="","","."&INDEX(Variables!$D$5:$D$105,MATCH($A93,Variables!$A$5:$A$105,0)))&"."&AE$5 | AF93: =INDEX(MTInputs!$J$1:$AZ$415,$D93,MATCH(AF$5,MTInputs!$J$5:$AZ$5,0)) | AG93: =INDEX(MTInputs!$J$1:$AZ$415,$D93,MATCH(AG$5,MTInputs!$J$5:$AZ$5,0)) | AH93: =INDEX(MTInputs!$J$1:$AZ$415,$D93,MATCH(AH$5,MTInputs!$J$5:$AZ$5,0)) | AI93: =INDEX(MTInputs!$J$1:$AZ$415,$D93,MATCH(AI$5,MTInputs!$J$5:$AZ$5,0)) | AJ93: =INDEX(MTInputs!$J$1:$AZ$415,$D93,MATCH(AJ$5,MTInputs!$J$5:$AZ$5,0)) | AK93: =INDEX(MTInputs!$J$1:$AZ$415,$D93,MATCH(AK$5,MTInputs!$J$5:$AZ$5,0)) | AL93: =INDEX(MTInputs!$J$1:$AZ$415,$D93,MATCH(AL$5,MTInputs!$J$5:$AZ$5,0)) | AM93: =INDEX(MTInputs!$J$1:$AZ$415,$D93,MATCH(AM$5,MTInputs!$J$5:$AZ$5,0)) | ... AX93: =INDEX(MTInputs!$J$1:$AZ$415,$D93,MATCH(AX$5,MTInputs!$J$5:$AZ$5,0))
A94: D_ETSIntro | D94: 88 | H94: =INDEX(Variables!$B$5:$B$105,MATCH($A94,Variables!$A$5:$A$105,0))&IF($C94="",""," | "&INDEX(Mapping!$B$5:$B$26,MATCH($C94,Mapping!$A$5:$A$26,0))&" | "&INDEX(Mapping!$B$30:$B$41,MATCH($B94,Mapping!$A$30:$A$41,0))) | I94: =INDEX(Variables!$C$5:$C$105,MATCH($A94,Variables!$A$5:$A$105,0)) | J94: =INDEX(Variables!$E$5:$E$105,MATCH($A94,Variables!$A$5:$A$105,0)) | K94: =LOWER(Settings!$C$4)&".mit."&$A94&IF($C94="","","."&$C94&"."&$B94)&IF(INDEX(Variables!$D$5:$D$105,MATCH($A94,Variables!$A$5:$A$105,0))="","","."&INDEX(Variables!$D$5:$D$105,MATCH($A94,Variables!$A$5:$A$105,0)))&"."&K$5 | L94: =INDEX(MTInputs!$J$1:$AZ$415,$D94,MATCH(L$5,MTInputs!$J$5:$AZ$5,0)) | M94: =INDEX(MTInputs!$J$1:$AZ$415,$D94,MATCH(M$5,MTInputs!$J$5:$AZ$5,0)) | N94: =INDEX(MTInputs!$J$1:$AZ$415,$D94,MATCH(N$5,MTInputs!$J$5:$AZ$5,0)) | O94: =INDEX(MTInputs!$J$1:$AZ$415,$D94,MATCH(O$5,MTInputs!$J$5:$AZ$5,0)) | P94: =INDEX(MTInputs!$J$1:$AZ$415,$D94,MATCH(P$5,MTInputs!$J$5:$AZ$5,0)) | Q94: =INDEX(MTInputs!$J$1:$AZ$415,$D94,MATCH(Q$5,MTInputs!$J$5:$AZ$5,0)) | R94: =INDEX(MTInputs!$J$1:$AZ$415,$D94,MATCH(R$5,MTInputs!$J$5:$AZ$5,0)) | S94: =INDEX(MTInputs!$J$1:$AZ$415,$D94,MATCH(S$5,MTInputs!$J$5:$AZ$5,0)) | ... AD94: =INDEX(MTInputs!$J$1:$AZ$415,$D94,MATCH(AD$5,MTInputs!$J$5:$AZ$5,0)) | AE94: =LOWER(Settings!$C$4)&".mit."&$A94&IF($C94="","","."&$C94&"."&$B94)&IF(INDEX(Variables!$D$5:$D$105,MATCH($A94,Variables!$A$5:$A$105,0))="","","."&INDEX(Variables!$D$5:$D$105,MATCH($A94,Variables!$A$5:$A$105,0)))&"."&AE$5 | AF94: =INDEX(MTInputs!$J$1:$AZ$415,$D94,MATCH(AF$5,MTInputs!$J$5:$AZ$5,0)) | AG94: =INDEX(MTInputs!$J$1:$AZ$415,$D94,MATCH(AG$5,MTInputs!$J$5:$AZ$5,0)) | AH94: =INDEX(MTInputs!$J$1:$AZ$415,$D94,MATCH(AH$5,MTInputs!$J$5:$AZ$5,0)) | AI94: =INDEX(MTInputs!$J$1:$AZ$415,$D94,MATCH(AI$5,MTInputs!$J$5:$AZ$5,0)) | AJ94: =INDEX(MTInputs!$J$1:$AZ$415,$D94,MATCH(AJ$5,MTInputs!$J$5:$AZ$5,0)) | AK94: =INDEX(MTInputs!$J$1:$AZ$415,$D94,MATCH(AK$5,MTInputs!$J$5:$AZ$5,0)) | AL94: =INDEX(MTInputs!$J$1:$AZ$415,$D94,MATCH(AL$5,MTInputs!$J$5:$AZ$5,0)) | AM94: =INDEX(MTInputs!$J$1:$AZ$415,$D94,MATCH(AM$5,MTInputs!$J$5:$AZ$5,0)) | ... AX94: =INDEX(MTInputs!$J$1:$AZ$415,$D94,MATCH(AX$5,MTInputs!$J$5:$AZ$5,0))
A95: D_ETSOutro | D95: 89 | H95: =INDEX(Variables!$B$5:$B$105,MATCH($A95,Variables!$A$5:$A$105,0))&IF($C95="",""," | "&INDEX(Mapping!$B$5:$B$26,MATCH($C95,Mapping!$A$5:$A$26,0))&" | "&INDEX(Mapping!$B$30:$B$41,MATCH($B95,Mapping!$A$30:$A$41,0))) | I95: =INDEX(Variables!$C$5:$C$105,MATCH($A95,Variables!$A$5:$A$105,0)) | J95: =INDEX(Variables!$E$5:$E$105,MATCH($A95,Variables!$A$5:$A$105,0)) | K95: =LOWER(Settings!$C$4)&".mit."&$A95&IF($C95="","","."&$C95&"."&$B95)&IF(INDEX(Variables!$D$5:$D$105,MATCH($A95,Variables!$A$5:$A$105,0))="","","."&INDEX(Variables!$D$5:$D$105,MATCH($A95,Variables!$A$5:$A$105,0)))&"."&K$5 | L95: =INDEX(MTInputs!$J$1:$AZ$415,$D95,MATCH(L$5,MTInputs!$J$5:$AZ$5,0)) | M95: =INDEX(MTInputs!$J$1:$AZ$415,$D95,MATCH(M$5,MTInputs!$J$5:$AZ$5,0)) | N95: =INDEX(MTInputs!$J$1:$AZ$415,$D95,MATCH(N$5,MTInputs!$J$5:$AZ$5,0)) | O95: =INDEX(MTInputs!$J$1:$AZ$415,$D95,MATCH(O$5,MTInputs!$J$5:$AZ$5,0)) | P95: =INDEX(MTInputs!$J$1:$AZ$415,$D95,MATCH(P$5,MTInputs!$J$5:$AZ$5,0)) | Q95: =INDEX(MTInputs!$J$1:$AZ$415,$D95,MATCH(Q$5,MTInputs!$J$5:$AZ$5,0)) | R95: =INDEX(MTInputs!$J$1:$AZ$415,$D95,MATCH(R$5,MTInputs!$J$5:$AZ$5,0)) | S95: =INDEX(MTInputs!$J$1:$AZ$415,$D95,MATCH(S$5,MTInputs!$J$5:$AZ$5,0)) | ... AD95: =INDEX(MTInputs!$J$1:$AZ$415,$D95,MATCH(AD$5,MTInputs!$J$5:$AZ$5,0)) | AE95: =LOWER(Settings!$C$4)&".mit."&$A95&IF($C95="","","."&$C95&"."&$B95)&IF(INDEX(Variables!$D$5:$D$105,MATCH($A95,Variables!$A$5:$A$105,0))="","","."&INDEX(Variables!$D$5:$D$105,MATCH($A95,Variables!$A$5:$A$105,0)))&"."&AE$5 | AF95: =INDEX(MTInputs!$J$1:$AZ$415,$D95,MATCH(AF$5,MTInputs!$J$5:$AZ$5,0)) | AG95: =INDEX(MTInputs!$J$1:$AZ$415,$D95,MATCH(AG$5,MTInputs!$J$5:$AZ$5,0)) | AH95: =INDEX(MTInputs!$J$1:$AZ$415,$D95,MATCH(AH$5,MTInputs!$J$5:$AZ$5,0)) | AI95: =INDEX(MTInputs!$J$1:$AZ$415,$D95,MATCH(AI$5,MTInputs!$J$5:$AZ$5,0)) | AJ95: =INDEX(MTInputs!$J$1:$AZ$415,$D95,MATCH(AJ$5,MTInputs!$J$5:$AZ$5,0)) | AK95: =INDEX(MTInputs!$J$1:$AZ$415,$D95,MATCH(AK$5,MTInputs!$J$5:$AZ$5,0)) | AL95: =INDEX(MTInputs!$J$1:$AZ$415,$D95,MATCH(AL$5,MTInputs!$J$5:$AZ$5,0)) | AM95: =INDEX(MTInputs!$J$1:$AZ$415,$D95,MATCH(AM$5,MTInputs!$J$5:$AZ$5,0)) | ... AX95: =INDEX(MTInputs!$J$1:$AZ$415,$D95,MATCH(AX$5,MTInputs!$J$5:$AZ$5,0))
A96: D_ETSAuctStart | D96: 90 | H96: =INDEX(Variables!$B$5:$B$105,MATCH($A96,Variables!$A$5:$A$105,0))&IF($C96="",""," | "&INDEX(Mapping!$B$5:$B$26,MATCH($C96,Mapping!$A$5:$A$26,0))&" | "&INDEX(Mapping!$B$30:$B$41,MATCH($B96,Mapping!$A$30:$A$41,0))) | I96: =INDEX(Variables!$C$5:$C$105,MATCH($A96,Variables!$A$5:$A$105,0)) | J96: =INDEX(Variables!$E$5:$E$105,MATCH($A96,Variables!$A$5:$A$105,0)) | K96: =LOWER(Settings!$C$4)&".mit."&$A96&IF($C96="","","."&$C96&"."&$B96)&IF(INDEX(Variables!$D$5:$D$105,MATCH($A96,Variables!$A$5:$A$105,0))="","","."&INDEX(Variables!$D$5:$D$105,MATCH($A96,Variables!$A$5:$A$105,0)))&"."&K$5 | L96: =INDEX(MTInputs!$J$1:$AZ$415,$D96,MATCH(L$5,MTInputs!$J$5:$AZ$5,0)) | M96: =INDEX(MTInputs!$J$1:$AZ$415,$D96,MATCH(M$5,MTInputs!$J$5:$AZ$5,0)) | N96: =INDEX(MTInputs!$J$1:$AZ$415,$D96,MATCH(N$5,MTInputs!$J$5:$AZ$5,0)) | O96: =INDEX(MTInputs!$J$1:$AZ$415,$D96,MATCH(O$5,MTInputs!$J$5:$AZ$5,0)) | P96: =INDEX(MTInputs!$J$1:$AZ$415,$D96,MATCH(P$5,MTInputs!$J$5:$AZ$5,0)) | Q96: =INDEX(MTInputs!$J$1:$AZ$415,$D96,MATCH(Q$5,MTInputs!$J$5:$AZ$5,0)) | R96: =INDEX(MTInputs!$J$1:$AZ$415,$D96,MATCH(R$5,MTInputs!$J$5:$AZ$5,0)) | S96: =INDEX(MTInputs!$J$1:$AZ$415,$D96,MATCH(S$5,MTInputs!$J$5:$AZ$5,0)) | ... AD96: =INDEX(MTInputs!$J$1:$AZ$415,$D96,MATCH(AD$5,MTInputs!$J$5:$AZ$5,0)) | AE96: =LOWER(Settings!$C$4)&".mit."&$A96&IF($C96="","","."&$C96&"."&$B96)&IF(INDEX(Variables!$D$5:$D$105,MATCH($A96,Variables!$A$5:$A$105,0))="","","."&INDEX(Variables!$D$5:$D$105,MATCH($A96,Variables!$A$5:$A$105,0)))&"."&AE$5 | AF96: =INDEX(MTInputs!$J$1:$AZ$415,$D96,MATCH(AF$5,MTInputs!$J$5:$AZ$5,0)) | AG96: =INDEX(MTInputs!$J$1:$AZ$415,$D96,MATCH(AG$5,MTInputs!$J$5:$AZ$5,0)) | AH96: =INDEX(MTInputs!$J$1:$AZ$415,$D96,MATCH(AH$5,MTInputs!$J$5:$AZ$5,0)) | AI96: =INDEX(MTInputs!$J$1:$AZ$415,$D96,MATCH(AI$5,MTInputs!$J$5:$AZ$5,0)) | AJ96: =INDEX(MTInputs!$J$1:$AZ$415,$D96,MATCH(AJ$5,MTInputs!$J$5:$AZ$5,0)) | AK96: =INDEX(MTInputs!$J$1:$AZ$415,$D96,MATCH(AK$5,MTInputs!$J$5:$AZ$5,0)) | AL96: =INDEX(MTInputs!$J$1:$AZ$415,$D96,MATCH(AL$5,MTInputs!$J$5:$AZ$5,0)) | AM96: =INDEX(MTInputs!$J$1:$AZ$415,$D96,MATCH(AM$5,MTInputs!$J$5:$AZ$5,0)) | ... AX96: =INDEX(MTInputs!$J$1:$AZ$415,$D96,MATCH(AX$5,MTInputs!$J$5:$AZ$5,0))
A97: D_ETSAuctTarget | D97: 91 | H97: =INDEX(Variables!$B$5:$B$105,MATCH($A97,Variables!$A$5:$A$105,0))&IF($C97="",""," | "&INDEX(Mapping!$B$5:$B$26,MATCH($C97,Mapping!$A$5:$A$26,0))&" | "&INDEX(Mapping!$B$30:$B$41,MATCH($B97,Mapping!$A$30:$A$41,0))) | I97: =INDEX(Variables!$C$5:$C$105,MATCH($A97,Variables!$A$5:$A$105,0)) | J97: =INDEX(Variables!$E$5:$E$105,MATCH($A97,Variables!$A$5:$A$105,0)) | K97: =LOWER(Settings!$C$4)&".mit."&$A97&IF($C97="","","."&$C97&"."&$B97)&IF(INDEX(Variables!$D$5:$D$105,MATCH($A97,Variables!$A$5:$A$105,0))="","","."&INDEX(Variables!$D$5:$D$105,MATCH($A97,Variables!$A$5:$A$105,0)))&"."&K$5 | L97: =INDEX(MTInputs!$J$1:$AZ$415,$D97,MATCH(L$5,MTInputs!$J$5:$AZ$5,0)) | M97: =INDEX(MTInputs!$J$1:$AZ$415,$D97,MATCH(M$5,MTInputs!$J$5:$AZ$5,0)) | N97: =INDEX(MTInputs!$J$1:$AZ$415,$D97,MATCH(N$5,MTInputs!$J$5:$AZ$5,0)) | O97: =INDEX(MTInputs!$J$1:$AZ$415,$D97,MATCH(O$5,MTInputs!$J$5:$AZ$5,0)) | P97: =INDEX(MTInputs!$J$1:$AZ$415,$D97,MATCH(P$5,MTInputs!$J$5:$AZ$5,0)) | Q97: =INDEX(MTInputs!$J$1:$AZ$415,$D97,MATCH(Q$5,MTInputs!$J$5:$AZ$5,0)) | R97: =INDEX(MTInputs!$J$1:$AZ$415,$D97,MATCH(R$5,MTInputs!$J$5:$AZ$5,0)) | S97: =INDEX(MTInputs!$J$1:$AZ$415,$D97,MATCH(S$5,MTInputs!$J$5:$AZ$5,0)) | ... AD97: =INDEX(MTInputs!$J$1:$AZ$415,$D97,MATCH(AD$5,MTInputs!$J$5:$AZ$5,0)) | AE97: =LOWER(Settings!$C$4)&".mit."&$A97&IF($C97="","","."&$C97&"."&$B97)&IF(INDEX(Variables!$D$5:$D$105,MATCH($A97,Variables!$A$5:$A$105,0))="","","."&INDEX(Variables!$D$5:$D$105,MATCH($A97,Variables!$A$5:$A$105,0)))&"."&AE$5 | AF97: =INDEX(MTInputs!$J$1:$AZ$415,$D97,MATCH(AF$5,MTInputs!$J$5:$AZ$5,0)) | AG97: =INDEX(MTInputs!$J$1:$AZ$415,$D97,MATCH(AG$5,MTInputs!$J$5:$AZ$5,0)) | AH97: =INDEX(MTInputs!$J$1:$AZ$415,$D97,MATCH(AH$5,MTInputs!$J$5:$AZ$5,0)) | AI97: =INDEX(MTInputs!$J$1:$AZ$415,$D97,MATCH(AI$5,MTInputs!$J$5:$AZ$5,0)) | AJ97: =INDEX(MTInputs!$J$1:$AZ$415,$D97,MATCH(AJ$5,MTInputs!$J$5:$AZ$5,0)) | AK97: =INDEX(MTInputs!$J$1:$AZ$415,$D97,MATCH(AK$5,MTInputs!$J$5:$AZ$5,0)) | AL97: =INDEX(MTInputs!$J$1:$AZ$415,$D97,MATCH(AL$5,MTInputs!$J$5:$AZ$5,0)) | AM97: =INDEX(MTInputs!$J$1:$AZ$415,$D97,MATCH(AM$5,MTInputs!$J$5:$AZ$5,0)) | ... AX97: =INDEX(MTInputs!$J$1:$AZ$415,$D97,MATCH(AX$5,MTInputs!$J$5:$AZ$5,0))
A98: D_ETSAuctCont | D98: 92 | H98: =INDEX(Variables!$B$5:$B$105,MATCH($A98,Variables!$A$5:$A$105,0))&IF($C98="",""," | "&INDEX(Mapping!$B$5:$B$26,MATCH($C98,Mapping!$A$5:$A$26,0))&" | "&INDEX(Mapping!$B$30:$B$41,MATCH($B98,Mapping!$A$30:$A$41,0))) | I98: =INDEX(Variables!$C$5:$C$105,MATCH($A98,Variables!$A$5:$A$105,0)) | J98: =INDEX(Variables!$E$5:$E$105,MATCH($A98,Variables!$A$5:$A$105,0)) | K98: =LOWER(Settings!$C$4)&".mit."&$A98&IF($C98="","","."&$C98&"."&$B98)&IF(INDEX(Variables!$D$5:$D$105,MATCH($A98,Variables!$A$5:$A$105,0))="","","."&INDEX(Variables!$D$5:$D$105,MATCH($A98,Variables!$A$5:$A$105,0)))&"."&K$5 | L98: =INDEX(MTInputs!$J$1:$AZ$415,$D98,MATCH(L$5,MTInputs!$J$5:$AZ$5,0)) | M98: =INDEX(MTInputs!$J$1:$AZ$415,$D98,MATCH(M$5,MTInputs!$J$5:$AZ$5,0)) | N98: =INDEX(MTInputs!$J$1:$AZ$415,$D98,MATCH(N$5,MTInputs!$J$5:$AZ$5,0)) | O98: =INDEX(MTInputs!$J$1:$AZ$415,$D98,MATCH(O$5,MTInputs!$J$5:$AZ$5,0)) | P98: =INDEX(MTInputs!$J$1:$AZ$415,$D98,MATCH(P$5,MTInputs!$J$5:$AZ$5,0)) | Q98: =INDEX(MTInputs!$J$1:$AZ$415,$D98,MATCH(Q$5,MTInputs!$J$5:$AZ$5,0)) | R98: =INDEX(MTInputs!$J$1:$AZ$415,$D98,MATCH(R$5,MTInputs!$J$5:$AZ$5,0)) | S98: =INDEX(MTInputs!$J$1:$AZ$415,$D98,MATCH(S$5,MTInputs!$J$5:$AZ$5,0)) | ... AD98: =INDEX(MTInputs!$J$1:$AZ$415,$D98,MATCH(AD$5,MTInputs!$J$5:$AZ$5,0)) | AE98: =LOWER(Settings!$C$4)&".mit."&$A98&IF($C98="","","."&$C98&"."&$B98)&IF(INDEX(Variables!$D$5:$D$105,MATCH($A98,Variables!$A$5:$A$105,0))="","","."&INDEX(Variables!$D$5:$D$105,MATCH($A98,Variables!$A$5:$A$105,0)))&"."&AE$5 | AF98: =INDEX(MTInputs!$J$1:$AZ$415,$D98,MATCH(AF$5,MTInputs!$J$5:$AZ$5,0)) | AG98: =INDEX(MTInputs!$J$1:$AZ$415,$D98,MATCH(AG$5,MTInputs!$J$5:$AZ$5,0)) | AH98: =INDEX(MTInputs!$J$1:$AZ$415,$D98,MATCH(AH$5,MTInputs!$J$5:$AZ$5,0)) | AI98: =INDEX(MTInputs!$J$1:$AZ$415,$D98,MATCH(AI$5,MTInputs!$J$5:$AZ$5,0)) | AJ98: =INDEX(MTInputs!$J$1:$AZ$415,$D98,MATCH(AJ$5,MTInputs!$J$5:$AZ$5,0)) | AK98: =INDEX(MTInputs!$J$1:$AZ$415,$D98,MATCH(AK$5,MTInputs!$J$5:$AZ$5,0)) | AL98: =INDEX(MTInputs!$J$1:$AZ$415,$D98,MATCH(AL$5,MTInputs!$J$5:$AZ$5,0)) | AM98: =INDEX(MTInputs!$J$1:$AZ$415,$D98,MATCH(AM$5,MTInputs!$J$5:$AZ$5,0)) | ... AX98: =INDEX(MTInputs!$J$1:$AZ$415,$D98,MATCH(AX$5,MTInputs!$J$5:$AZ$5,0))
H99: ETS sector coverage (MTInputs rows 99-115) and effective coverage (ETS applied and started)
A100: etscov | B100: all | C100: pow | D100: 99 | H100: =INDEX(Variables!$B$5:$B$105,MATCH($A100,Variables!$A$5:$A$105,0))&IF($C100="",""," | "&INDEX(Mapping!$B$5:$B$26,MATCH($C100,Mapping!$A$5:$A$26,0))&" | "&INDEX(Mapping!$B$30:$B$41,MATCH($B100,Mapping!$A$30:$A$41,0))) | I100: =INDEX(Variables!$C$5:$C$105,MATCH($A100,Variables!$A$5:$A$105,0)) | J100: =INDEX(Variables!$E$5:$E$105,MATCH($A100,Variables!$A$5:$A$105,0)) | K100: =LOWER(Settings!$C$4)&".mit."&$A100&IF($C100="","","."&$C100&"."&$B100)&IF(INDEX(Variables!$D$5:$D$105,MATCH($A100,Variables!$A$5:$A$105,0))="","","."&INDEX(Variables!$D$5:$D$105,MATCH($A100,Variables!$A$5:$A$105,0)))&"."&K$5 | L100: =INDEX(MTInputs!$J$1:$AZ$415,$D100,MATCH(L$5,MTInputs!$J$5:$AZ$5,0)) | M100: =INDEX(MTInputs!$J$1:$AZ$415,$D100,MATCH(M$5,MTInputs!$J$5:$AZ$5,0)) | N100: =INDEX(MTInputs!$J$1:$AZ$415,$D100,MATCH(N$5,MTInputs!$J$5:$AZ$5,0)) | O100: =INDEX(MTInputs!$J$1:$AZ$415,$D100,MATCH(O$5,MTInputs!$J$5:$AZ$5,0)) | P100: =INDEX(MTInputs!$J$1:$AZ$415,$D100,MATCH(P$5,MTInputs!$J$5:$AZ$5,0)) | Q100: =INDEX(MTInputs!$J$1:$AZ$415,$D100,MATCH(Q$5,MTInputs!$J$5:$AZ$5,0)) | R100: =INDEX(MTInputs!$J$1:$AZ$415,$D100,MATCH(R$5,MTInputs!$J$5:$AZ$5,0)) | S100: =INDEX(MTInputs!$J$1:$AZ$415,$D100,MATCH(S$5,MTInputs!$J$5:$AZ$5,0)) | ... AD100: =INDEX(MTInputs!$J$1:$AZ$415,$D100,MATCH(AD$5,MTInputs!$J$5:$AZ$5,0)) | AE100: =LOWER(Settings!$C$4)&".mit."&$A100&IF($C100="","","."&$C100&"."&$B100)&IF(INDEX(Variables!$D$5:$D$105,MATCH($A100,Variables!$A$5:$A$105,0))="","","."&INDEX(Variables!$D$5:$D$105,MATCH($A100,Variables!$A$5:$A$105,0)))&"."&AE$5 | AF100: =INDEX(MTInputs!$J$1:$AZ$415,$D100,MATCH(AF$5,MTInputs!$J$5:$AZ$5,0)) | AG100: =INDEX(MTInputs!$J$1:$AZ$415,$D100,MATCH(AG$5,MTInputs!$J$5:$AZ$5,0)) | AH100: =INDEX(MTInputs!$J$1:$AZ$415,$D100,MATCH(AH$5,MTInputs!$J$5:$AZ$5,0)) | AI100: =INDEX(MTInputs!$J$1:$AZ$415,$D100,MATCH(AI$5,MTInputs!$J$5:$AZ$5,0)) | AJ100: =INDEX(MTInputs!$J$1:$AZ$415,$D100,MATCH(AJ$5,MTInputs!$J$5:$AZ$5,0)) | AK100: =INDEX(MTInputs!$J$1:$AZ$415,$D100,MATCH(AK$5,MTInputs!$J$5:$AZ$5,0)) | AL100: =INDEX(MTInputs!$J$1:$AZ$415,$D100,MATCH(AL$5,MTInputs!$J$5:$AZ$5,0)) | AM100: =INDEX(MTInputs!$J$1:$AZ$415,$D100,MATCH(AM$5,MTInputs!$J$5:$AZ$5,0)) | ... AX100: =INDEX(MTInputs!$J$1:$AZ$415,$D100,MATCH(AX$5,MTInputs!$J$5:$AZ$5,0))
A101: etscov | B101: all | C101: rod | D101: 100 | H101: =INDEX(Variables!$B$5:$B$105,MATCH($A101,Variables!$A$5:$A$105,0))&IF($C101="",""," | "&INDEX(Mapping!$B$5:$B$26,MATCH($C101,Mapping!$A$5:$A$26,0))&" | "&INDEX(Mapping!$B$30:$B$41,MATCH($B101,Mapping!$A$30:$A$41,0))) | I101: =INDEX(Variables!$C$5:$C$105,MATCH($A101,Variables!$A$5:$A$105,0)) | J101: =INDEX(Variables!$E$5:$E$105,MATCH($A101,Variables!$A$5:$A$105,0)) | K101: =LOWER(Settings!$C$4)&".mit."&$A101&IF($C101="","","."&$C101&"."&$B101)&IF(INDEX(Variables!$D$5:$D$105,MATCH($A101,Variables!$A$5:$A$105,0))="","","."&INDEX(Variables!$D$5:$D$105,MATCH($A101,Variables!$A$5:$A$105,0)))&"."&K$5 | L101: =INDEX(MTInputs!$J$1:$AZ$415,$D101,MATCH(L$5,MTInputs!$J$5:$AZ$5,0)) | M101: =INDEX(MTInputs!$J$1:$AZ$415,$D101,MATCH(M$5,MTInputs!$J$5:$AZ$5,0)) | N101: =INDEX(MTInputs!$J$1:$AZ$415,$D101,MATCH(N$5,MTInputs!$J$5:$AZ$5,0)) | O101: =INDEX(MTInputs!$J$1:$AZ$415,$D101,MATCH(O$5,MTInputs!$J$5:$AZ$5,0)) | P101: =INDEX(MTInputs!$J$1:$AZ$415,$D101,MATCH(P$5,MTInputs!$J$5:$AZ$5,0)) | Q101: =INDEX(MTInputs!$J$1:$AZ$415,$D101,MATCH(Q$5,MTInputs!$J$5:$AZ$5,0)) | R101: =INDEX(MTInputs!$J$1:$AZ$415,$D101,MATCH(R$5,MTInputs!$J$5:$AZ$5,0)) | S101: =INDEX(MTInputs!$J$1:$AZ$415,$D101,MATCH(S$5,MTInputs!$J$5:$AZ$5,0)) | ... AD101: =INDEX(MTInputs!$J$1:$AZ$415,$D101,MATCH(AD$5,MTInputs!$J$5:$AZ$5,0)) | AE101: =LOWER(Settings!$C$4)&".mit."&$A101&IF($C101="","","."&$C101&"."&$B101)&IF(INDEX(Variables!$D$5:$D$105,MATCH($A101,Variables!$A$5:$A$105,0))="","","."&INDEX(Variables!$D$5:$D$105,MATCH($A101,Variables!$A$5:$A$105,0)))&"."&AE$5 | AF101: =INDEX(MTInputs!$J$1:$AZ$415,$D101,MATCH(AF$5,MTInputs!$J$5:$AZ$5,0)) | AG101: =INDEX(MTInputs!$J$1:$AZ$415,$D101,MATCH(AG$5,MTInputs!$J$5:$AZ$5,0)) | AH101: =INDEX(MTInputs!$J$1:$AZ$415,$D101,MATCH(AH$5,MTInputs!$J$5:$AZ$5,0)) | AI101: =INDEX(MTInputs!$J$1:$AZ$415,$D101,MATCH(AI$5,MTInputs!$J$5:$AZ$5,0)) | AJ101: =INDEX(MTInputs!$J$1:$AZ$415,$D101,MATCH(AJ$5,MTInputs!$J$5:$AZ$5,0)) | AK101: =INDEX(MTInputs!$J$1:$AZ$415,$D101,MATCH(AK$5,MTInputs!$J$5:$AZ$5,0)) | AL101: =INDEX(MTInputs!$J$1:$AZ$415,$D101,MATCH(AL$5,MTInputs!$J$5:$AZ$5,0)) | AM101: =INDEX(MTInputs!$J$1:$AZ$415,$D101,MATCH(AM$5,MTInputs!$J$5:$AZ$5,0)) | ... AX101: =INDEX(MTInputs!$J$1:$AZ$415,$D101,MATCH(AX$5,MTInputs!$J$5:$AZ$5,0))
A102: etscov | B102: all | C102: ral | D102: 101 | H102: =INDEX(Variables!$B$5:$B$105,MATCH($A102,Variables!$A$5:$A$105,0))&IF($C102="",""," | "&INDEX(Mapping!$B$5:$B$26,MATCH($C102,Mapping!$A$5:$A$26,0))&" | "&INDEX(Mapping!$B$30:$B$41,MATCH($B102,Mapping!$A$30:$A$41,0))) | I102: =INDEX(Variables!$C$5:$C$105,MATCH($A102,Variables!$A$5:$A$105,0)) | J102: =INDEX(Variables!$E$5:$E$105,MATCH($A102,Variables!$A$5:$A$105,0)) | K102: =LOWER(Settings!$C$4)&".mit."&$A102&IF($C102="","","."&$C102&"."&$B102)&IF(INDEX(Variables!$D$5:$D$105,MATCH($A102,Variables!$A$5:$A$105,0))="","","."&INDEX(Variables!$D$5:$D$105,MATCH($A102,Variables!$A$5:$A$105,0)))&"."&K$5 | L102: =INDEX(MTInputs!$J$1:$AZ$415,$D102,MATCH(L$5,MTInputs!$J$5:$AZ$5,0)) | M102: =INDEX(MTInputs!$J$1:$AZ$415,$D102,MATCH(M$5,MTInputs!$J$5:$AZ$5,0)) | N102: =INDEX(MTInputs!$J$1:$AZ$415,$D102,MATCH(N$5,MTInputs!$J$5:$AZ$5,0)) | O102: =INDEX(MTInputs!$J$1:$AZ$415,$D102,MATCH(O$5,MTInputs!$J$5:$AZ$5,0)) | P102: =INDEX(MTInputs!$J$1:$AZ$415,$D102,MATCH(P$5,MTInputs!$J$5:$AZ$5,0)) | Q102: =INDEX(MTInputs!$J$1:$AZ$415,$D102,MATCH(Q$5,MTInputs!$J$5:$AZ$5,0)) | R102: =INDEX(MTInputs!$J$1:$AZ$415,$D102,MATCH(R$5,MTInputs!$J$5:$AZ$5,0)) | S102: =INDEX(MTInputs!$J$1:$AZ$415,$D102,MATCH(S$5,MTInputs!$J$5:$AZ$5,0)) | ... AD102: =INDEX(MTInputs!$J$1:$AZ$415,$D102,MATCH(AD$5,MTInputs!$J$5:$AZ$5,0)) | AE102: =LOWER(Settings!$C$4)&".mit."&$A102&IF($C102="","","."&$C102&"."&$B102)&IF(INDEX(Variables!$D$5:$D$105,MATCH($A102,Variables!$A$5:$A$105,0))="","","."&INDEX(Variables!$D$5:$D$105,MATCH($A102,Variables!$A$5:$A$105,0)))&"."&AE$5 | AF102: =INDEX(MTInputs!$J$1:$AZ$415,$D102,MATCH(AF$5,MTInputs!$J$5:$AZ$5,0)) | AG102: =INDEX(MTInputs!$J$1:$AZ$415,$D102,MATCH(AG$5,MTInputs!$J$5:$AZ$5,0)) | AH102: =INDEX(MTInputs!$J$1:$AZ$415,$D102,MATCH(AH$5,MTInputs!$J$5:$AZ$5,0)) | AI102: =INDEX(MTInputs!$J$1:$AZ$415,$D102,MATCH(AI$5,MTInputs!$J$5:$AZ$5,0)) | AJ102: =INDEX(MTInputs!$J$1:$AZ$415,$D102,MATCH(AJ$5,MTInputs!$J$5:$AZ$5,0)) | AK102: =INDEX(MTInputs!$J$1:$AZ$415,$D102,MATCH(AK$5,MTInputs!$J$5:$AZ$5,0)) | AL102: =INDEX(MTInputs!$J$1:$AZ$415,$D102,MATCH(AL$5,MTInputs!$J$5:$AZ$5,0)) | AM102: =INDEX(MTInputs!$J$1:$AZ$415,$D102,MATCH(AM$5,MTInputs!$J$5:$AZ$5,0)) | ... AX102: =INDEX(MTInputs!$J$1:$AZ$415,$D102,MATCH(AX$5,MTInputs!$J$5:$AZ$5,0))
A103: etscov | B103: all | C103: avi | D103: 102 | H103: =INDEX(Variables!$B$5:$B$105,MATCH($A103,Variables!$A$5:$A$105,0))&IF($C103="",""," | "&INDEX(Mapping!$B$5:$B$26,MATCH($C103,Mapping!$A$5:$A$26,0))&" | "&INDEX(Mapping!$B$30:$B$41,MATCH($B103,Mapping!$A$30:$A$41,0))) | I103: =INDEX(Variables!$C$5:$C$105,MATCH($A103,Variables!$A$5:$A$105,0)) | J103: =INDEX(Variables!$E$5:$E$105,MATCH($A103,Variables!$A$5:$A$105,0)) | K103: =LOWER(Settings!$C$4)&".mit."&$A103&IF($C103="","","."&$C103&"."&$B103)&IF(INDEX(Variables!$D$5:$D$105,MATCH($A103,Variables!$A$5:$A$105,0))="","","."&INDEX(Variables!$D$5:$D$105,MATCH($A103,Variables!$A$5:$A$105,0)))&"."&K$5 | L103: =INDEX(MTInputs!$J$1:$AZ$415,$D103,MATCH(L$5,MTInputs!$J$5:$AZ$5,0)) | M103: =INDEX(MTInputs!$J$1:$AZ$415,$D103,MATCH(M$5,MTInputs!$J$5:$AZ$5,0)) | N103: =INDEX(MTInputs!$J$1:$AZ$415,$D103,MATCH(N$5,MTInputs!$J$5:$AZ$5,0)) | O103: =INDEX(MTInputs!$J$1:$AZ$415,$D103,MATCH(O$5,MTInputs!$J$5:$AZ$5,0)) | P103: =INDEX(MTInputs!$J$1:$AZ$415,$D103,MATCH(P$5,MTInputs!$J$5:$AZ$5,0)) | Q103: =INDEX(MTInputs!$J$1:$AZ$415,$D103,MATCH(Q$5,MTInputs!$J$5:$AZ$5,0)) | R103: =INDEX(MTInputs!$J$1:$AZ$415,$D103,MATCH(R$5,MTInputs!$J$5:$AZ$5,0)) | S103: =INDEX(MTInputs!$J$1:$AZ$415,$D103,MATCH(S$5,MTInputs!$J$5:$AZ$5,0)) | ... AD103: =INDEX(MTInputs!$J$1:$AZ$415,$D103,MATCH(AD$5,MTInputs!$J$5:$AZ$5,0)) | AE103: =LOWER(Settings!$C$4)&".mit."&$A103&IF($C103="","","."&$C103&"."&$B103)&IF(INDEX(Variables!$D$5:$D$105,MATCH($A103,Variables!$A$5:$A$105,0))="","","."&INDEX(Variables!$D$5:$D$105,MATCH($A103,Variables!$A$5:$A$105,0)))&"."&AE$5 | AF103: =INDEX(MTInputs!$J$1:$AZ$415,$D103,MATCH(AF$5,MTInputs!$J$5:$AZ$5,0)) | AG103: =INDEX(MTInputs!$J$1:$AZ$415,$D103,MATCH(AG$5,MTInputs!$J$5:$AZ$5,0)) | AH103: =INDEX(MTInputs!$J$1:$AZ$415,$D103,MATCH(AH$5,MTInputs!$J$5:$AZ$5,0)) | AI103: =INDEX(MTInputs!$J$1:$AZ$415,$D103,MATCH(AI$5,MTInputs!$J$5:$AZ$5,0)) | AJ103: =INDEX(MTInputs!$J$1:$AZ$415,$D103,MATCH(AJ$5,MTInputs!$J$5:$AZ$5,0)) | AK103: =INDEX(MTInputs!$J$1:$AZ$415,$D103,MATCH(AK$5,MTInputs!$J$5:$AZ$5,0)) | AL103: =INDEX(MTInputs!$J$1:$AZ$415,$D103,MATCH(AL$5,MTInputs!$J$5:$AZ$5,0)) | AM103: =INDEX(MTInputs!$J$1:$AZ$415,$D103,MATCH(AM$5,MTInputs!$J$5:$AZ$5,0)) | ... AX103: =INDEX(MTInputs!$J$1:$AZ$415,$D103,MATCH(AX$5,MTInputs!$J$5:$AZ$5,0))
A104: etscov | B104: all | C104: nav | D104: 103 | H104: =INDEX(Variables!$B$5:$B$105,MATCH($A104,Variables!$A$5:$A$105,0))&IF($C104="",""," | "&INDEX(Mapping!$B$5:$B$26,MATCH($C104,Mapping!$A$5:$A$26,0))&" | "&INDEX(Mapping!$B$30:$B$41,MATCH($B104,Mapping!$A$30:$A$41,0))) | I104: =INDEX(Variables!$C$5:$C$105,MATCH($A104,Variables!$A$5:$A$105,0)) | J104: =INDEX(Variables!$E$5:$E$105,MATCH($A104,Variables!$A$5:$A$105,0)) | K104: =LOWER(Settings!$C$4)&".mit."&$A104&IF($C104="","","."&$C104&"."&$B104)&IF(INDEX(Variables!$D$5:$D$105,MATCH($A104,Variables!$A$5:$A$105,0))="","","."&INDEX(Variables!$D$5:$D$105,MATCH($A104,Variables!$A$5:$A$105,0)))&"."&K$5 | L104: =INDEX(MTInputs!$J$1:$AZ$415,$D104,MATCH(L$5,MTInputs!$J$5:$AZ$5,0)) | M104: =INDEX(MTInputs!$J$1:$AZ$415,$D104,MATCH(M$5,MTInputs!$J$5:$AZ$5,0)) | N104: =INDEX(MTInputs!$J$1:$AZ$415,$D104,MATCH(N$5,MTInputs!$J$5:$AZ$5,0)) | O104: =INDEX(MTInputs!$J$1:$AZ$415,$D104,MATCH(O$5,MTInputs!$J$5:$AZ$5,0)) | P104: =INDEX(MTInputs!$J$1:$AZ$415,$D104,MATCH(P$5,MTInputs!$J$5:$AZ$5,0)) | Q104: =INDEX(MTInputs!$J$1:$AZ$415,$D104,MATCH(Q$5,MTInputs!$J$5:$AZ$5,0)) | R104: =INDEX(MTInputs!$J$1:$AZ$415,$D104,MATCH(R$5,MTInputs!$J$5:$AZ$5,0)) | S104: =INDEX(MTInputs!$J$1:$AZ$415,$D104,MATCH(S$5,MTInputs!$J$5:$AZ$5,0)) | ... AD104: =INDEX(MTInputs!$J$1:$AZ$415,$D104,MATCH(AD$5,MTInputs!$J$5:$AZ$5,0)) | AE104: =LOWER(Settings!$C$4)&".mit."&$A104&IF($C104="","","."&$C104&"."&$B104)&IF(INDEX(Variables!$D$5:$D$105,MATCH($A104,Variables!$A$5:$A$105,0))="","","."&INDEX(Variables!$D$5:$D$105,MATCH($A104,Variables!$A$5:$A$105,0)))&"."&AE$5 | AF104: =INDEX(MTInputs!$J$1:$AZ$415,$D104,MATCH(AF$5,MTInputs!$J$5:$AZ$5,0)) | AG104: =INDEX(MTInputs!$J$1:$AZ$415,$D104,MATCH(AG$5,MTInputs!$J$5:$AZ$5,0)) | AH104: =INDEX(MTInputs!$J$1:$AZ$415,$D104,MATCH(AH$5,MTInputs!$J$5:$AZ$5,0)) | AI104: =INDEX(MTInputs!$J$1:$AZ$415,$D104,MATCH(AI$5,MTInputs!$J$5:$AZ$5,0)) | AJ104: =INDEX(MTInputs!$J$1:$AZ$415,$D104,MATCH(AJ$5,MTInputs!$J$5:$AZ$5,0)) | AK104: =INDEX(MTInputs!$J$1:$AZ$415,$D104,MATCH(AK$5,MTInputs!$J$5:$AZ$5,0)) | AL104: =INDEX(MTInputs!$J$1:$AZ$415,$D104,MATCH(AL$5,MTInputs!$J$5:$AZ$5,0)) | AM104: =INDEX(MTInputs!$J$1:$AZ$415,$D104,MATCH(AM$5,MTInputs!$J$5:$AZ$5,0)) | ... AX104: =INDEX(MTInputs!$J$1:$AZ$415,$D104,MATCH(AX$5,MTInputs!$J$5:$AZ$5,0))
A105: etscov | B105: all | C105: res | D105: 104 | H105: =INDEX(Variables!$B$5:$B$105,MATCH($A105,Variables!$A$5:$A$105,0))&IF($C105="",""," | "&INDEX(Mapping!$B$5:$B$26,MATCH($C105,Mapping!$A$5:$A$26,0))&" | "&INDEX(Mapping!$B$30:$B$41,MATCH($B105,Mapping!$A$30:$A$41,0))) | I105: =INDEX(Variables!$C$5:$C$105,MATCH($A105,Variables!$A$5:$A$105,0)) | J105: =INDEX(Variables!$E$5:$E$105,MATCH($A105,Variables!$A$5:$A$105,0)) | K105: =LOWER(Settings!$C$4)&".mit."&$A105&IF($C105="","","."&$C105&"."&$B105)&IF(INDEX(Variables!$D$5:$D$105,MATCH($A105,Variables!$A$5:$A$105,0))="","","."&INDEX(Variables!$D$5:$D$105,MATCH($A105,Variables!$A$5:$A$105,0)))&"."&K$5 | L105: =INDEX(MTInputs!$J$1:$AZ$415,$D105,MATCH(L$5,MTInputs!$J$5:$AZ$5,0)) | M105: =INDEX(MTInputs!$J$1:$AZ$415,$D105,MATCH(M$5,MTInputs!$J$5:$AZ$5,0)) | N105: =INDEX(MTInputs!$J$1:$AZ$415,$D105,MATCH(N$5,MTInputs!$J$5:$AZ$5,0)) | O105: =INDEX(MTInputs!$J$1:$AZ$415,$D105,MATCH(O$5,MTInputs!$J$5:$AZ$5,0)) | P105: =INDEX(MTInputs!$J$1:$AZ$415,$D105,MATCH(P$5,MTInputs!$J$5:$AZ$5,0)) | Q105: =INDEX(MTInputs!$J$1:$AZ$415,$D105,MATCH(Q$5,MTInputs!$J$5:$AZ$5,0)) | R105: =INDEX(MTInputs!$J$1:$AZ$415,$D105,MATCH(R$5,MTInputs!$J$5:$AZ$5,0)) | S105: =INDEX(MTInputs!$J$1:$AZ$415,$D105,MATCH(S$5,MTInputs!$J$5:$AZ$5,0)) | ... AD105: =INDEX(MTInputs!$J$1:$AZ$415,$D105,MATCH(AD$5,MTInputs!$J$5:$AZ$5,0)) | AE105: =LOWER(Settings!$C$4)&".mit."&$A105&IF($C105="","","."&$C105&"."&$B105)&IF(INDEX(Variables!$D$5:$D$105,MATCH($A105,Variables!$A$5:$A$105,0))="","","."&INDEX(Variables!$D$5:$D$105,MATCH($A105,Variables!$A$5:$A$105,0)))&"."&AE$5 | AF105: =INDEX(MTInputs!$J$1:$AZ$415,$D105,MATCH(AF$5,MTInputs!$J$5:$AZ$5,0)) | AG105: =INDEX(MTInputs!$J$1:$AZ$415,$D105,MATCH(AG$5,MTInputs!$J$5:$AZ$5,0)) | AH105: =INDEX(MTInputs!$J$1:$AZ$415,$D105,MATCH(AH$5,MTInputs!$J$5:$AZ$5,0)) | AI105: =INDEX(MTInputs!$J$1:$AZ$415,$D105,MATCH(AI$5,MTInputs!$J$5:$AZ$5,0)) | AJ105: =INDEX(MTInputs!$J$1:$AZ$415,$D105,MATCH(AJ$5,MTInputs!$J$5:$AZ$5,0)) | AK105: =INDEX(MTInputs!$J$1:$AZ$415,$D105,MATCH(AK$5,MTInputs!$J$5:$AZ$5,0)) | AL105: =INDEX(MTInputs!$J$1:$AZ$415,$D105,MATCH(AL$5,MTInputs!$J$5:$AZ$5,0)) | AM105: =INDEX(MTInputs!$J$1:$AZ$415,$D105,MATCH(AM$5,MTInputs!$J$5:$AZ$5,0)) | ... AX105: =INDEX(MTInputs!$J$1:$AZ$415,$D105,MATCH(AX$5,MTInputs!$J$5:$AZ$5,0))
A106: etscov | B106: all | C106: foo | D106: 105 | H106: =INDEX(Variables!$B$5:$B$105,MATCH($A106,Variables!$A$5:$A$105,0))&IF($C106="",""," | "&INDEX(Mapping!$B$5:$B$26,MATCH($C106,Mapping!$A$5:$A$26,0))&" | "&INDEX(Mapping!$B$30:$B$41,MATCH($B106,Mapping!$A$30:$A$41,0))) | I106: =INDEX(Variables!$C$5:$C$105,MATCH($A106,Variables!$A$5:$A$105,0)) | J106: =INDEX(Variables!$E$5:$E$105,MATCH($A106,Variables!$A$5:$A$105,0)) | K106: =LOWER(Settings!$C$4)&".mit."&$A106&IF($C106="","","."&$C106&"."&$B106)&IF(INDEX(Variables!$D$5:$D$105,MATCH($A106,Variables!$A$5:$A$105,0))="","","."&INDEX(Variables!$D$5:$D$105,MATCH($A106,Variables!$A$5:$A$105,0)))&"."&K$5 | L106: =INDEX(MTInputs!$J$1:$AZ$415,$D106,MATCH(L$5,MTInputs!$J$5:$AZ$5,0)) | M106: =INDEX(MTInputs!$J$1:$AZ$415,$D106,MATCH(M$5,MTInputs!$J$5:$AZ$5,0)) | N106: =INDEX(MTInputs!$J$1:$AZ$415,$D106,MATCH(N$5,MTInputs!$J$5:$AZ$5,0)) | O106: =INDEX(MTInputs!$J$1:$AZ$415,$D106,MATCH(O$5,MTInputs!$J$5:$AZ$5,0)) | P106: =INDEX(MTInputs!$J$1:$AZ$415,$D106,MATCH(P$5,MTInputs!$J$5:$AZ$5,0)) | Q106: =INDEX(MTInputs!$J$1:$AZ$415,$D106,MATCH(Q$5,MTInputs!$J$5:$AZ$5,0)) | R106: =INDEX(MTInputs!$J$1:$AZ$415,$D106,MATCH(R$5,MTInputs!$J$5:$AZ$5,0)) | S106: =INDEX(MTInputs!$J$1:$AZ$415,$D106,MATCH(S$5,MTInputs!$J$5:$AZ$5,0)) | ... AD106: =INDEX(MTInputs!$J$1:$AZ$415,$D106,MATCH(AD$5,MTInputs!$J$5:$AZ$5,0)) | AE106: =LOWER(Settings!$C$4)&".mit."&$A106&IF($C106="","","."&$C106&"."&$B106)&IF(INDEX(Variables!$D$5:$D$105,MATCH($A106,Variables!$A$5:$A$105,0))="","","."&INDEX(Variables!$D$5:$D$105,MATCH($A106,Variables!$A$5:$A$105,0)))&"."&AE$5 | AF106: =INDEX(MTInputs!$J$1:$AZ$415,$D106,MATCH(AF$5,MTInputs!$J$5:$AZ$5,0)) | AG106: =INDEX(MTInputs!$J$1:$AZ$415,$D106,MATCH(AG$5,MTInputs!$J$5:$AZ$5,0)) | AH106: =INDEX(MTInputs!$J$1:$AZ$415,$D106,MATCH(AH$5,MTInputs!$J$5:$AZ$5,0)) | AI106: =INDEX(MTInputs!$J$1:$AZ$415,$D106,MATCH(AI$5,MTInputs!$J$5:$AZ$5,0)) | AJ106: =INDEX(MTInputs!$J$1:$AZ$415,$D106,MATCH(AJ$5,MTInputs!$J$5:$AZ$5,0)) | AK106: =INDEX(MTInputs!$J$1:$AZ$415,$D106,MATCH(AK$5,MTInputs!$J$5:$AZ$5,0)) | AL106: =INDEX(MTInputs!$J$1:$AZ$415,$D106,MATCH(AL$5,MTInputs!$J$5:$AZ$5,0)) | AM106: =INDEX(MTInputs!$J$1:$AZ$415,$D106,MATCH(AM$5,MTInputs!$J$5:$AZ$5,0)) | ... AX106: =INDEX(MTInputs!$J$1:$AZ$415,$D106,MATCH(AX$5,MTInputs!$J$5:$AZ$5,0))
A107: etscov | B107: all | C107: srv | D107: 106 | H107: =INDEX(Variables!$B$5:$B$105,MATCH($A107,Variables!$A$5:$A$105,0))&IF($C107="",""," | "&INDEX(Mapping!$B$5:$B$26,MATCH($C107,Mapping!$A$5:$A$26,0))&" | "&INDEX(Mapping!$B$30:$B$41,MATCH($B107,Mapping!$A$30:$A$41,0))) | I107: =INDEX(Variables!$C$5:$C$105,MATCH($A107,Variables!$A$5:$A$105,0)) | J107: =INDEX(Variables!$E$5:$E$105,MATCH($A107,Variables!$A$5:$A$105,0)) | K107: =LOWER(Settings!$C$4)&".mit."&$A107&IF($C107="","","."&$C107&"."&$B107)&IF(INDEX(Variables!$D$5:$D$105,MATCH($A107,Variables!$A$5:$A$105,0))="","","."&INDEX(Variables!$D$5:$D$105,MATCH($A107,Variables!$A$5:$A$105,0)))&"."&K$5 | L107: =INDEX(MTInputs!$J$1:$AZ$415,$D107,MATCH(L$5,MTInputs!$J$5:$AZ$5,0)) | M107: =INDEX(MTInputs!$J$1:$AZ$415,$D107,MATCH(M$5,MTInputs!$J$5:$AZ$5,0)) | N107: =INDEX(MTInputs!$J$1:$AZ$415,$D107,MATCH(N$5,MTInputs!$J$5:$AZ$5,0)) | O107: =INDEX(MTInputs!$J$1:$AZ$415,$D107,MATCH(O$5,MTInputs!$J$5:$AZ$5,0)) | P107: =INDEX(MTInputs!$J$1:$AZ$415,$D107,MATCH(P$5,MTInputs!$J$5:$AZ$5,0)) | Q107: =INDEX(MTInputs!$J$1:$AZ$415,$D107,MATCH(Q$5,MTInputs!$J$5:$AZ$5,0)) | R107: =INDEX(MTInputs!$J$1:$AZ$415,$D107,MATCH(R$5,MTInputs!$J$5:$AZ$5,0)) | S107: =INDEX(MTInputs!$J$1:$AZ$415,$D107,MATCH(S$5,MTInputs!$J$5:$AZ$5,0)) | ... AD107: =INDEX(MTInputs!$J$1:$AZ$415,$D107,MATCH(AD$5,MTInputs!$J$5:$AZ$5,0)) | AE107: =LOWER(Settings!$C$4)&".mit."&$A107&IF($C107="","","."&$C107&"."&$B107)&IF(INDEX(Variables!$D$5:$D$105,MATCH($A107,Variables!$A$5:$A$105,0))="","","."&INDEX(Variables!$D$5:$D$105,MATCH($A107,Variables!$A$5:$A$105,0)))&"."&AE$5 | AF107: =INDEX(MTInputs!$J$1:$AZ$415,$D107,MATCH(AF$5,MTInputs!$J$5:$AZ$5,0)) | AG107: =INDEX(MTInputs!$J$1:$AZ$415,$D107,MATCH(AG$5,MTInputs!$J$5:$AZ$5,0)) | AH107: =INDEX(MTInputs!$J$1:$AZ$415,$D107,MATCH(AH$5,MTInputs!$J$5:$AZ$5,0)) | AI107: =INDEX(MTInputs!$J$1:$AZ$415,$D107,MATCH(AI$5,MTInputs!$J$5:$AZ$5,0)) | AJ107: =INDEX(MTInputs!$J$1:$AZ$415,$D107,MATCH(AJ$5,MTInputs!$J$5:$AZ$5,0)) | AK107: =INDEX(MTInputs!$J$1:$AZ$415,$D107,MATCH(AK$5,MTInputs!$J$5:$AZ$5,0)) | AL107: =INDEX(MTInputs!$J$1:$AZ$415,$D107,MATCH(AL$5,MTInputs!$J$5:$AZ$5,0)) | AM107: =INDEX(MTInputs!$J$1:$AZ$415,$D107,MATCH(AM$5,MTInputs!$J$5:$AZ$5,0)) | ... AX107: =INDEX(MTInputs!$J$1:$AZ$415,$D107,MATCH(AX$5,MTInputs!$J$5:$AZ$5,0))
A108: etscov | B108: all | C108: mch | D108: 107 | H108: =INDEX(Variables!$B$5:$B$105,MATCH($A108,Variables!$A$5:$A$105,0))&IF($C108="",""," | "&INDEX(Mapping!$B$5:$B$26,MATCH($C108,Mapping!$A$5:$A$26,0))&" | "&INDEX(Mapping!$B$30:$B$41,MATCH($B108,Mapping!$A$30:$A$41,0))) | I108: =INDEX(Variables!$C$5:$C$105,MATCH($A108,Variables!$A$5:$A$105,0)) | J108: =INDEX(Variables!$E$5:$E$105,MATCH($A108,Variables!$A$5:$A$105,0)) | K108: =LOWER(Settings!$C$4)&".mit."&$A108&IF($C108="","","."&$C108&"."&$B108)&IF(INDEX(Variables!$D$5:$D$105,MATCH($A108,Variables!$A$5:$A$105,0))="","","."&INDEX(Variables!$D$5:$D$105,MATCH($A108,Variables!$A$5:$A$105,0)))&"."&K$5 | L108: =INDEX(MTInputs!$J$1:$AZ$415,$D108,MATCH(L$5,MTInputs!$J$5:$AZ$5,0)) | M108: =INDEX(MTInputs!$J$1:$AZ$415,$D108,MATCH(M$5,MTInputs!$J$5:$AZ$5,0)) | N108: =INDEX(MTInputs!$J$1:$AZ$415,$D108,MATCH(N$5,MTInputs!$J$5:$AZ$5,0)) | O108: =INDEX(MTInputs!$J$1:$AZ$415,$D108,MATCH(O$5,MTInputs!$J$5:$AZ$5,0)) | P108: =INDEX(MTInputs!$J$1:$AZ$415,$D108,MATCH(P$5,MTInputs!$J$5:$AZ$5,0)) | Q108: =INDEX(MTInputs!$J$1:$AZ$415,$D108,MATCH(Q$5,MTInputs!$J$5:$AZ$5,0)) | R108: =INDEX(MTInputs!$J$1:$AZ$415,$D108,MATCH(R$5,MTInputs!$J$5:$AZ$5,0)) | S108: =INDEX(MTInputs!$J$1:$AZ$415,$D108,MATCH(S$5,MTInputs!$J$5:$AZ$5,0)) | ... AD108: =INDEX(MTInputs!$J$1:$AZ$415,$D108,MATCH(AD$5,MTInputs!$J$5:$AZ$5,0)) | AE108: =LOWER(Settings!$C$4)&".mit."&$A108&IF($C108="","","."&$C108&"."&$B108)&IF(INDEX(Variables!$D$5:$D$105,MATCH($A108,Variables!$A$5:$A$105,0))="","","."&INDEX(Variables!$D$5:$D$105,MATCH($A108,Variables!$A$5:$A$105,0)))&"."&AE$5 | AF108: =INDEX(MTInputs!$J$1:$AZ$415,$D108,MATCH(AF$5,MTInputs!$J$5:$AZ$5,0)) | AG108: =INDEX(MTInputs!$J$1:$AZ$415,$D108,MATCH(AG$5,MTInputs!$J$5:$AZ$5,0)) | AH108: =INDEX(MTInputs!$J$1:$AZ$415,$D108,MATCH(AH$5,MTInputs!$J$5:$AZ$5,0)) | AI108: =INDEX(MTInputs!$J$1:$AZ$415,$D108,MATCH(AI$5,MTInputs!$J$5:$AZ$5,0)) | AJ108: =INDEX(MTInputs!$J$1:$AZ$415,$D108,MATCH(AJ$5,MTInputs!$J$5:$AZ$5,0)) | AK108: =INDEX(MTInputs!$J$1:$AZ$415,$D108,MATCH(AK$5,MTInputs!$J$5:$AZ$5,0)) | AL108: =INDEX(MTInputs!$J$1:$AZ$415,$D108,MATCH(AL$5,MTInputs!$J$5:$AZ$5,0)) | AM108: =INDEX(MTInputs!$J$1:$AZ$415,$D108,MATCH(AM$5,MTInputs!$J$5:$AZ$5,0)) | ... AX108: =INDEX(MTInputs!$J$1:$AZ$415,$D108,MATCH(AX$5,MTInputs!$J$5:$AZ$5,0))
A109: etscov | B109: all | C109: irn | D109: 108 | H109: =INDEX(Variables!$B$5:$B$105,MATCH($A109,Variables!$A$5:$A$105,0))&IF($C109="",""," | "&INDEX(Mapping!$B$5:$B$26,MATCH($C109,Mapping!$A$5:$A$26,0))&" | "&INDEX(Mapping!$B$30:$B$41,MATCH($B109,Mapping!$A$30:$A$41,0))) | I109: =INDEX(Variables!$C$5:$C$105,MATCH($A109,Variables!$A$5:$A$105,0)) | J109: =INDEX(Variables!$E$5:$E$105,MATCH($A109,Variables!$A$5:$A$105,0)) | K109: =LOWER(Settings!$C$4)&".mit."&$A109&IF($C109="","","."&$C109&"."&$B109)&IF(INDEX(Variables!$D$5:$D$105,MATCH($A109,Variables!$A$5:$A$105,0))="","","."&INDEX(Variables!$D$5:$D$105,MATCH($A109,Variables!$A$5:$A$105,0)))&"."&K$5 | L109: =INDEX(MTInputs!$J$1:$AZ$415,$D109,MATCH(L$5,MTInputs!$J$5:$AZ$5,0)) | M109: =INDEX(MTInputs!$J$1:$AZ$415,$D109,MATCH(M$5,MTInputs!$J$5:$AZ$5,0)) | N109: =INDEX(MTInputs!$J$1:$AZ$415,$D109,MATCH(N$5,MTInputs!$J$5:$AZ$5,0)) | O109: =INDEX(MTInputs!$J$1:$AZ$415,$D109,MATCH(O$5,MTInputs!$J$5:$AZ$5,0)) | P109: =INDEX(MTInputs!$J$1:$AZ$415,$D109,MATCH(P$5,MTInputs!$J$5:$AZ$5,0)) | Q109: =INDEX(MTInputs!$J$1:$AZ$415,$D109,MATCH(Q$5,MTInputs!$J$5:$AZ$5,0)) | R109: =INDEX(MTInputs!$J$1:$AZ$415,$D109,MATCH(R$5,MTInputs!$J$5:$AZ$5,0)) | S109: =INDEX(MTInputs!$J$1:$AZ$415,$D109,MATCH(S$5,MTInputs!$J$5:$AZ$5,0)) | ... AD109: =INDEX(MTInputs!$J$1:$AZ$415,$D109,MATCH(AD$5,MTInputs!$J$5:$AZ$5,0)) | AE109: =LOWER(Settings!$C$4)&".mit."&$A109&IF($C109="","","."&$C109&"."&$B109)&IF(INDEX(Variables!$D$5:$D$105,MATCH($A109,Variables!$A$5:$A$105,0))="","","."&INDEX(Variables!$D$5:$D$105,MATCH($A109,Variables!$A$5:$A$105,0)))&"."&AE$5 | AF109: =INDEX(MTInputs!$J$1:$AZ$415,$D109,MATCH(AF$5,MTInputs!$J$5:$AZ$5,0)) | AG109: =INDEX(MTInputs!$J$1:$AZ$415,$D109,MATCH(AG$5,MTInputs!$J$5:$AZ$5,0)) | AH109: =INDEX(MTInputs!$J$1:$AZ$415,$D109,MATCH(AH$5,MTInputs!$J$5:$AZ$5,0)) | AI109: =INDEX(MTInputs!$J$1:$AZ$415,$D109,MATCH(AI$5,MTInputs!$J$5:$AZ$5,0)) | AJ109: =INDEX(MTInputs!$J$1:$AZ$415,$D109,MATCH(AJ$5,MTInputs!$J$5:$AZ$5,0)) | AK109: =INDEX(MTInputs!$J$1:$AZ$415,$D109,MATCH(AK$5,MTInputs!$J$5:$AZ$5,0)) | AL109: =INDEX(MTInputs!$J$1:$AZ$415,$D109,MATCH(AL$5,MTInputs!$J$5:$AZ$5,0)) | AM109: =INDEX(MTInputs!$J$1:$AZ$415,$D109,MATCH(AM$5,MTInputs!$J$5:$AZ$5,0)) | ... AX109: =INDEX(MTInputs!$J$1:$AZ$415,$D109,MATCH(AX$5,MTInputs!$J$5:$AZ$5,0))
