Workbook

Sheet Results
A1: Egypt carbon pricing and CBAM: results, 2030
A2: Results only. Every number is a link (green) to the Calculations sheet, where the working is explained row by row. Columns C to H are the six scenarios.
A4: Results in 2030 | B4: Unit | C4: =Calculations!C66 -> 1A | D4: =Calculations!D66 -> 2A | E4: =Calculations!E66 -> 2B | F4: =Calculations!F66 -> 3A | G4: =Calculations!G66 -> 3B | H4: =Calculations!H66 -> 3C
A5: Scenario | C5: =Calculations!C67 -> Comprehensive levy | D5: =Calculations!D67 -> Upstream levy | E5: =Calculations!E67 -> Upstream levy, household refunds | F5: =Calculations!F67 -> Downstream industry price | G5: =Calculations!G67 -> 3A with feebate (revenue neutral) | H5: =Calculations!H67 -> 3A with abatement fund
A6: What is priced | C6: Energy CO2, all sectors, plus CBAM process emissions | D6: Energy CO2, all sectors | E6: Energy CO2, all sectors | F6: CBAM products: energy and process emissions | G6: As 3A | H6: As 3A | I6: CBAM products: the seven EU CBAM goods made in Egypt. In 3A to 3C, diesel and gasoline are excluded from the price.
A7: Use of revenue | C7: Public investment (1) | D7: Public investment (1) | E7: Household refunds (2) | F7: Household refunds (2) | G7: Returned to firms per unit of output (feebate) | H7: Abatement fund for industry | I7: (1) Public investment raises GDP (in CPAT, 2030 GDP is about 0.4% higher than with household refunds), which raises energy demand; this is why 2A cuts less than 2B. (2) Refunds to the bottom 40% of households, assuming 90% coverage.
A8: Carbon price ($/t CO2) | B8: $/t | C8: =Calculations!C73 -> 20 | D8: =Calculations!D73 -> 20 | E8: =Calculations!E73 -> 20 | F8: =Calculations!F73 -> 20 | G8: =Calculations!G73 -> 20 | H8: =Calculations!H73 -> 20 | I8: Carbon price in 2030 (input, Calculations 2a).
A9: Share of national emissions priced | B9: % | C9: =Calculations!C35 -> 0.71499793 | D9: =Calculations!D35 -> 0.6419205 | E9: =Calculations!E35 -> 0.6419725 | F9: =Calculations!F35 -> 0.14998937 | G9: =Calculations!G35 -> 0.14998937 | H9: =Calculations!H35 -> 0.14998937 | I9: Share of national emissions that face a carbon price. National emissions use Egypt's 2022 inventory shares (energy CO2 about 65% of the total; see Calculations, Walk 2). 3A to 3C price the seven CBAM products only, so their coverage is the block's emissions (65.3 Mt in 2030) ÷ national GHG (Walk 5).
A10: Carbon revenue, $bn | B10: $bn | C10: =Calculations!C25 -> 5.5989499 | D10: =Calculations!D25 -> 5.0351389 | E10: =Calculations!E25 -> 4.9651389 | F10: =Calculations!F25 -> 1.1481353 | G10: =Calculations!G25 -> 0 | H10: =Calculations!H25 -> 0 | I10: Carbon revenue in 2030. Gross where revenue is used for public investment (1A, 2A) or household refunds (2B, 3A): the figure is before the money is spent. Net where it is rebated to firms (3B) or put into a fund (3C), so these show zero.
A11: Emission cut, Mt CO2e | B11: Mt | C11: =Calculations!C12 -> 40.683839 | D11: =Calculations!D12 -> 37.546416 | E11: =Calculations!E12 -> 41.098416 | F11: =Calculations!F12 -> 7.8078388 | G11: =Calculations!G12 -> 5.7961617 | H11: =Calculations!H12 -> 12.972229 | I11: Cut in national GHG, adjusted for the CBAM block.
A12: Cut as share of national emissions | B12: % | C12: =Calculations!C17 -> 0.093474164 | D12: =Calculations!D17 -> 0.086265701 | E12: =Calculations!E17 -> 0.094426687 | F12: =Calculations!F17 -> 0.017939094 | G12: =Calculations!G17 -> 0.013317115 | H12: =Calculations!H17 -> 0.029804666 | I12: The cut as a share of baseline national GHG (435 Mt in 2030: CPAT's energy CO2 at the inventory's 65% share; CPAT's own total is 536 Mt).
A13: Share of heavy-industry emissions priced | B13: % | C13: =Calculations!C45 -> 1 | D13: =Calculations!D45 -> 0.4825602 | E13: =Calculations!E45 -> 0.4825602 | F13: =Calculations!F45 -> 1 | G13: =Calculations!G45 -> 1 | H13: =Calculations!H45 -> 1 | I13: Share of CBAM-block emissions that face the price.
A14: Heavy industry: total emissions | B14: % | C14: =Calculations!C43 -> -0.12062876 | D14: =Calculations!D43 -> -0.072568933 | E14: =Calculations!E43 -> -0.072568933 | F14: =Calculations!F43 -> -0.12062876 | G14: =Calculations!G43 -> -0.08869515 | H14: =Calculations!H43 -> -0.19811444 | I14: Total block emissions change: output and efficiency together.
A15: of which emissions intensity | B15: % | C15: =Calculations!C44 -> -0.088745466 | D15: =Calculations!D44 -> -0.055166747 | E15: =Calculations!E44 -> -0.055166747 | F15: =Calculations!F44 -> -0.088745466 | G15: =Calculations!G44 -> -0.08869515 | H15: =Calculations!H44 -> -0.16904055 | I15: Change in emissions per tonne of output, products weighted by their emissions at policy output.
A16: of which output, emissions-weighted | B16: % | C16: =(1+C14)/(1+C15)-1 -> -0.034988347 | D16: =(1+D14)/(1+D15)-1 -> -0.018418261 | E16: =(1+E14)/(1+E15)-1 -> -0.018418261 | F16: =(1+F14)/(1+F15)-1 -> -0.034988347 | G16: =(1+G14)/(1+G15)-1 -> 0 | H16: =(1+H14)/(1+H15)-1 -> -0.034988347 | I16: (1 + T) ÷ (1 + N) − 1: the output effect on block emissions, i.e. output change weighted by each product's emissions.
A17: EU border charge per tonne exported | B17: % | C17: =Calculations!C52 -> -0.38618183 | D17: =Calculations!D52 -> -0.20602871 | E17: =Calculations!E52 -> -0.20602871 | F17: =Calculations!F52 -> -0.38618183 | G17: =Calculations!G52 -> -0.083994426 | H17: =Calculations!H52 -> -0.43710282 | I17: Change in the obligation per tonne of EU exports. Credit rules: an explicit carbon price counts; an output-based rebate (3B) makes it ineligible; a decarbonization fund (3C) does not add to the price credited but does not invalidate it.
A18: of which emissions intensity of EU exports | B18: % | C18: =Calculations!C53 -> -0.083994426 | D18: =Calculations!D53 -> -0.055287267 | E18: =Calculations!E53 -> -0.055287267 | F18: =Calculations!F53 -> -0.083994426 | G18: =Calculations!G53 -> -0.083994426 | H18: =Calculations!H53 -> -0.15998421 | I18: Change in emissions per tonne of EU exports, products weighted by their EU exports.
A19: of which Egyptian carbon price credit | B19: % | C19: =Calculations!C54 -> -0.30218741 | D19: =Calculations!D54 -> -0.15074144 | E19: =Calculations!E54 -> -0.15074144 | F19: =Calculations!F54 -> -0.30218741 | G19: =Calculations!G54 -> 0 | H19: =Calculations!H54 -> -0.27711861 | I19: The EU deducts the carbon price effectively paid in Egypt: the carbon price weighted by its coverage. Under the current interpretation of the rules, an output-based rebate (3B) invalidates the credit; an abatement fund (3C) does not, but earns no extra credit.
A20: Premature deaths avoided in 2030 | B20: deaths | C20: =Calculations!C30 -> 1659.0841 | D20: =Calculations!D30 -> 1639.2941 | E20: =Calculations!E30 -> 1799.3912 | F20: =Calculations!F30 -> 60.623943 | G20: =Calculations!G30 -> 45.004282 | H20: =Calculations!H30 -> 100.72284 | I20: Deaths avoided in the year 2030 (annual, not cumulative) from lower local air pollution. 3A and 3C scale 3B by the total emission cut (see Calculations, Walk 4). In 1A to 2B, mostly from lower fuel use in food and agriculture (about 60% of the fall in fine-particle pollution in CPAT) and road transport (about 25%).
A22: Memo: checks
A23: Credit eligible (1 = yes) | B23: flag | C23: =Calculations!C55 -> 1 | D23: =Calculations!D55 -> 1 | E23: =Calculations!E55 -> 1 | F23: =Calculations!F55 -> 1 | G23: =Calculations!G55 -> 0 | H23: =Calculations!H55 -> 1 | I23: 0 in 3B: the output-based rebate makes the Egyptian price ineligible.
A24: Shortcut: obligation change = −r − (1 − r) × τ^EGY ÷ τ^EU | B24: % | C24: =Calculations!C63 -> -0.38618183 | D24: =Calculations!D63 -> -0.20568092 | E24: =Calculations!E63 -> -0.20568092 | F24: =Calculations!F63 -> -0.38618183 | G24: =Calculations!G63 -> -0.083994426 | H24: =Calculations!H63 -> -0.43710282 | I24: r is the fall in emissions per tonne of EU exports; τ^EGY = τ × S × (1 − θ), the Egyptian carbon price credited (feebates not creditable); τ^EU = γ × p^EU, the EU price after phase-in (0.485 × 125 ≈ 61). See Calculations, Walk 8.
A26: Scope: the CBAM block is the seven products with production in Egypt (BF-BOF steel is excluded as it has no output).
A27: Left out to keep it simple: solving the fund price (a fixed shadow price of $20 is used) and output effects of the fund.
A28: All six CPAT runs are final (raw results of 7 October). In 3A to 3C diesel and gasoline are excluded from the carbon price.
A29: Timing: results apply long-run responses in full by 2030. With a price rising linearly from 2026 to $20 in 2030, about 40% of the response is likely by 2030 (about 70% if the full price applies from 2027); see rows 31 to 51 and methodology Appendix H.
A31: Alternative: 2030 with partial adjustment (methodology Appendix H)
A32: Share of the long-run response achieved by 2030, k | B32: share | C32: 1 | I32: Input. Share of the long-run response reached by 2030. Published adjustment speeds (about a third of the remaining gap closed each year) give about 70% for a $20 price in place from 2027 and about 40% for a price rising linearly from zero in 2026 to $20 in 2030. Set to 100% to reproduce the main table.
A35: Results in 2030, partial adjustment | B35: Unit | C35: =C4 -> 1A | D35: =D4 -> 2A | E35: =E4 -> 2B | F35: =F4 -> 3A | G35: =G4 -> 3B | H35: =H4 -> 3C
A36: Scenario | C36: =C5 -> Comprehensive levy | D36: =D5 -> Upstream levy | E36: =E5 -> Upstream levy, household refunds | F36: =F5 -> Downstream industry price | G36: =G5 -> 3A with feebate (revenue neutral) | H36: =H5 -> 3A with abatement fund
A37: What is priced | C37: =C6 -> Energy CO2, all sectors, plus CBAM process emissions | D37: =D6 -> Energy CO2, all sectors | E37: =E6 -> Energy CO2, all sectors | F37: =F6 -> CBAM products: energy and process emissions | G37: =G6 -> As 3A | H37: =H6 -> As 3A | I37: CBAM products: the seven EU CBAM goods made in Egypt. In 3A to 3C, diesel and gasoline are excluded from the price.
A38: Use of revenue | C38: =C7 -> Public investment (1) | D38: =D7 -> Public investment (1) | E38: =E7 -> Household refunds (2) | F38: =F7 -> Household refunds (2) | G38: =G7 -> Returned to firms per unit of output (feebate) | H38: =H7 -> Abatement fund for industry | I38: (1) Public investment raises GDP (in CPAT, 2030 GDP is about 0.4% higher than with household refunds), which raises energy demand; this is why 2A cuts less than 2B. (2) Refunds to the bottom 40% of households, assuming 90% coverage.
A39: Carbon price ($/t CO2) | B39: $/t | C39: =C8 -> 20 | D39: =D8 -> 20 | E39: =E8 -> 20 | F39: =F8 -> 20 | G39: =G8 -> 20 | H39: =H8 -> 20 | I39: Unchanged.
A40: Share of national emissions priced | B40: % | C40: =C9 -> 0.71499793 | D40: =D9 -> 0.6419205 | E40: =E9 -> 0.6419725 | F40: =F9 -> 0.14998937 | G40: =G9 -> 0.14998937 | H40: =H9 -> 0.14998937 | I40: Unchanged.
A41: Carbon revenue, $bn | B41: $bn | C41: =IF(C10=0,0,C10+C$8*(1-$C$32)*C11/1000) -> 5.5989499 | D41: =IF(D10=0,0,D10+D$8*(1-$C$32)*D11/1000) -> 5.0351389 | E41: =IF(E10=0,0,E10+E$8*(1-$C$32)*E11/1000) -> 4.9651389 | F41: =IF(F10=0,0,F10+F$8*(1-$C$32)*F11/1000) -> 1.1481353 | G41: =IF(G10=0,0,G10+G$8*(1-$C$32)*G11/1000) -> 0 | H41: =IF(H10=0,0,H10+H$8*(1-$C$32)*H11/1000) -> 0 | I41: Main revenue plus τ × (1 − k) × cut: less abatement leaves more emissions to tax. Zero stays zero for 3B and 3C (net of refunds and fund).
A42: Emission cut, Mt CO2e | B42: Mt | C42: =$C$32*C11 -> 40.683839 | D42: =$C$32*D11 -> 37.546416 | E42: =$C$32*E11 -> 41.098416 | F42: =$C$32*F11 -> 7.8078388 | G42: =$C$32*G11 -> 5.7961617 | H42: =$C$32*H11 -> 12.972229 | I42: k × main cut.
A43: Cut as share of national emissions | B43: % | C43: =$C$32*C12 -> 0.093474164 | D43: =$C$32*D12 -> 0.086265701 | E43: =$C$32*E12 -> 0.094426687 | F43: =$C$32*F12 -> 0.017939094 | G43: =$C$32*G12 -> 0.013317115 | H43: =$C$32*H12 -> 0.029804666 | I43: k × main share.
A44: Share of heavy-industry emissions priced | B44: % | C44: =C13 -> 1 | D44: =D13 -> 0.4825602 | E44: =E13 -> 0.4825602 | F44: =F13 -> 1 | G44: =G13 -> 1 | H44: =H13 -> 1 | I44: Unchanged.
A45: Heavy industry: total emissions | B45: % | C45: =(1+C14)^$C$32-1 -> -0.12062876 | D45: =(1+D14)^$C$32-1 -> -0.072568933 | E45: =(1+E14)^$C$32-1 -> -0.072568933 | F45: =(1+F14)^$C$32-1 -> -0.12062876 | G45: =(1+G14)^$C$32-1 -> -0.08869515 | H45: =(1+H14)^$C$32-1 -> -0.19811444 | I45: (1 + main change)^k − 1.
A46: of which emissions intensity | B46: % | C46: =(1+C15)^$C$32-1 -> -0.088745466 | D46: =(1+D15)^$C$32-1 -> -0.055166747 | E46: =(1+E15)^$C$32-1 -> -0.055166747 | F46: =(1+F15)^$C$32-1 -> -0.088745466 | G46: =(1+G15)^$C$32-1 -> -0.08869515 | H46: =(1+H15)^$C$32-1 -> -0.16904055 | I46: (1 + main change)^k − 1.
A47: of which output, emissions-weighted | B47: % | C47: =(1+C45)/(1+C46)-1 -> -0.034988347 | D47: =(1+D45)/(1+D46)-1 -> -0.018418261 | E47: =(1+E45)/(1+E46)-1 -> -0.018418261 | F47: =(1+F45)/(1+F46)-1 -> -0.034988347 | G47: =(1+G45)/(1+G46)-1 -> 0 | H47: =(1+H45)/(1+H46)-1 -> -0.034988347 | I47: (1 + total) ÷ (1 + intensity) − 1, as in the main table.
A48: EU border charge per tonne exported | B48: % | C48: =C49+C50 -> -0.38618183 | D48: =D49+D50 -> -0.20602871 | E48: =E49+E50 -> -0.20602871 | F48: =F49+F50 -> -0.38618183 | G48: =G49+G50 -> -0.083994426 | H48: =H49+H50 -> -0.43710282 | I48: Sum of the two lines below.
A49: of which emissions intensity of EU exports | B49: % | C49: =(1+C18)^$C$32-1 -> -0.083994426 | D49: =(1+D18)^$C$32-1 -> -0.055287267 | E49: =(1+E18)^$C$32-1 -> -0.055287267 | F49: =(1+F18)^$C$32-1 -> -0.083994426 | G49: =(1+G18)^$C$32-1 -> -0.083994426 | H49: =(1+H18)^$C$32-1 -> -0.15998421 | I49: (1 + main change)^k − 1.
A50: of which Egyptian carbon price credit | B50: % | C50: =C19*(1+C49)/(1+C18) -> -0.30218741 | D50: =D19*(1+D49)/(1+D18) -> -0.15074144 | E50: =E19*(1+E49)/(1+E18) -> -0.15074144 | F50: =F19*(1+F49)/(1+F18) -> -0.30218741 | G50: =G19*(1+G49)/(1+G18) -> 0 | H50: =H19*(1+H49)/(1+H18) -> -0.27711861 | I50: Main credit × (1 + this intensity change) ÷ (1 + main intensity change): the credit scales with the emissions paid for per tonne.
A51: Premature deaths avoided in 2030 | B51: deaths | C51: =$C$32*C20 -> 1659.0841 | D51: =$C$32*D20 -> 1639.2941 | E51: =$C$32*E20 -> 1799.3912 | F51: =$C$32*F20 -> 60.623943 | G51: =$C$32*G20 -> 45.004282 | H51: =$C$32*H20 -> 100.72284 | I51: k × main deaths avoided.

Sheet Calculations
A1: Egypt carbon pricing and CBAM: calculations, 2030
A2: THE STORY. For each result we start from the CPAT answer and make a few adjustments for the seven CBAM products, which CPAT only treats roughly. Section 1 walks through each result: CPAT, then Adjustment 1, 2, 3, then the result. The Results sheet repeats the final lines. Section 2 holds the inputs (blue). Section 3 gathers the numbers the walks use (click + at the left to open the detail). The product-by-product work is on the Product detail sheet. Columns C to H are the six scenarios; column I explains each row.
A3: Scenario | C3: =C66 -> 1A | D3: =D66 -> 2A | E3: =E66 -> 2B | F3: =F66 -> 3A | G3: =G66 -> 3B | H3: =H66 -> 3C
A4: 1. THE WALKS: from the CPAT answer to each result
A5: Each walk starts from what CPAT says, then makes the adjustments for the CBAM products, one line each. The last line (bold) is the result shown on the Results sheet.
A6: Walk 1. Emission cut, −ΔE_tot
A7: CPAT gives a national cut. It already includes a rough cut for the CBAM products, so we take that out and put in the cut we calculate for them: fuel first, then process.
A8: CPAT: national emission cut | B8: Mt | C8: =C115 -> 37.757 | D8: =D115 -> 37.757 | E8: =E115 -> 41.309 | F8: =F115 -> 4.881 | G8: =G115 -> 2.058 | H8: =H115 -> 5.143 | I8: From CPAT.
A9: Adjustment 1: remove CPAT's own cut for the CBAM products | B9: Mt | C9: =C136+C137 -> -4.948 | D9: =D136+D137 -> -4.948 | E9: =E136+E137 -> -4.948 | F9: =F136+F137 -> -4.948 | G9: =G136+G137 -> -2.052 | H9: =H136+H137 -> -5.104 | I9: What CPAT assumed for fuel and process emissions of the block (3d).
A10: Adjustment 2: add the block's fuel cut | B10: Mt | C10: =-C134 -> 4.6029975 | D10: =-D134 -> 4.2590572 | E10: =-E134 -> 4.2590572 | F10: =-F134 -> 4.6029975 | G10: =-G134 -> 3.61319 | H10: =-H134 -> 7.719358 | I10: Our calculated fuel cut: price response, output response and fund.
A11: Adjustment 3: add the block's process cut | B11: Mt | C11: =-C135 -> 3.2718412 | D11: =-D135 -> 0.4783592 | E11: =-E135 -> 0.4783592 | F11: =-F135 -> 3.2718412 | G11: =-G135 -> 2.1769717 | H11: =-H135 -> 5.2138708 | I11: Our calculated process cut (zero unless process emissions are priced, or the fund applies).
A12: Emission cut, −ΔE_tot | B12: Mt | C12: =SUM(C8:C11) -> 40.683839 | D12: =SUM(D8:D11) -> 37.546416 | E12: =SUM(E8:E11) -> 41.098416 | F12: =SUM(F8:F11) -> 7.8078388 | G12: =SUM(G8:G11) -> 5.7961617 | H12: =SUM(H8:H11) -> 12.972229 | I12: Sum of the lines above.
A13: Walk 2. Cut as a share of national GHG, −ΔE_tot/E^0_tot
A14: The cut from Walk 1 divided by baseline national GHG. National GHG keeps CPAT's 2030 energy CO2 but uses the 2022 inventory's energy share (65%).
A15: Emission cut, −ΔE_tot | B15: Mt | C15: =C12 -> 40.683839 | D15: =D12 -> 37.546416 | E15: =E12 -> 41.098416 | F15: =F12 -> 7.8078388 | G15: =G12 -> 5.7961617 | H15: =H12 -> 12.972229 | I15: From Walk 1.
A16: Baseline national GHG, E^0_tot (inventory shares) | B16: Mt | C16: =C94/$C$85 -> 435.24154 | D16: =D94/$C$85 -> 435.24154 | E16: =E94/$C$85 -> 435.24154 | F16: =F94/$C$85 -> 435.24154 | G16: =G94/$C$85 -> 435.24154 | H16: =H94/$C$85 -> 435.24154 | I16: CPAT baseline energy CO2 ÷ its share of national GHG in Egypt's 2022 inventory (65%, input in 2b). Replaces CPAT's own total (row 92), which has more waste and process emissions than the inventory.
A17: Cut, % of national GHG, −ΔE_tot/E^0_tot | B17: % | C17: =C15/C16 -> 0.093474164 | D17: =D15/D16 -> 0.086265701 | E17: =E15/E16 -> 0.094426687 | F17: =F15/F16 -> 0.017939094 | G17: =G15/G16 -> 0.013317115 | H17: =H15/H16 -> 0.029804666 | I17: K ÷ baseline GHG.
A18: Walk 3. Carbon revenue, R
A19: CPAT gives the receipts it collects. We correct the part that comes from the CBAM products, add fees on their process emissions, and subtract anything handed back (feebate refund, fund).
A20: CPAT: carbon receipts | B20: US$bn | C20: =C117 -> 5.07 | D20: =D117 -> 5.07 | E20: =E117 -> 5 | F20: =F117 -> 0.32 | G20: =G117 -> 0 | H20: =H117 -> 0.32 | I20: From CPAT.
A21: Adjustment 1: correct fuel payments for the CBAM products | B21: US$bn | C21: =IF(C$72=1,C139-C117,C$73*C138/1000) -> -0.041739951 | D21: =IF(D$72=1,D139-D117,D$73*D138/1000) -> -0.034861144 | E21: =IF(E$72=1,E139-E117,E$73*E138/1000) -> -0.034861144 | F21: =IF(F$72=1,F139-F117,F$73*F138/1000) -> 0.25744552 | G21: =IF(G$72=1,G139-G117,G$73*G138/1000) -> 0.59724167 | H21: =IF(H$72=1,H139-H117,H$73*H138/1000) -> 0.19511831 | I21: CBAM-sector-only runs: replace CPAT receipts by the block's own fuel payments. Full-coverage runs: price × fuel adjustment.
A22: Adjustment 2: add fees on process emissions | B22: US$bn | C22: =C140 -> 0.57068981 | D22: =D140 -> 0 | E22: =E140 -> 0 | F22: =F140 -> 0.57068981 | G22: =G140 -> 0.5925872 | H22: =H140 -> 0.53184922 | I22: Zero where process emissions are not priced.
A23: Adjustment 3: subtract the feebate refund | B23: US$bn | C23: =-C141 -> 0 | D23: =-D141 -> 0 | E23: =-E141 -> 0 | F23: =-F141 -> 0 | G23: =-G141 -> -1.1898289 | H23: =-H141 -> 0 | I23: 3B only.
A24: Adjustment 4: subtract the fund outlay | B24: US$bn | C24: =-C142 -> 0 | D24: =-D142 -> 0 | E24: =-E142 -> 0 | F24: =-F142 -> 0 | G24: =-G142 -> 0 | H24: =-H142 -> -1.0469675 | I24: 3C only.
A25: Carbon revenue, R | B25: US$bn | C25: =SUM(C20:C24) -> 5.5989499 | D25: =SUM(D20:D24) -> 5.0351389 | E25: =SUM(E20:E24) -> 4.9651389 | F25: =SUM(F20:F24) -> 1.1481353 | G25: =SUM(G20:G24) -> 0 | H25: =SUM(H20:H24) -> 0 | I25: Sum of the lines above.
A26: Walk 4. Premature deaths avoided, D
A27: CPAT reports deaths avoided in each year; we use 2030 (annual, not cumulative). We scale CPAT's count by the block's fuel adjustment. In 3A and 3C, CPAT's counts are distorted by fuel switching (they even show more deaths), so their deaths avoided are 3B's, scaled by the total emission cut (K) relative to 3B.
A28: CPAT: deaths avoided | B28: deaths | C28: =C118 -> 1539 | D28: =D118 -> 1539 | E28: =E118 -> 1698 | F28: =F118 -> -38 | G28: =G118 -> 13 | H28: =H118 -> -30 | I28: From CPAT: deaths averted in 2030 by age group (annual, not cumulative).
A29: Adjustment 1: deaths from the block's fuel adjustment | B29: deaths | C29: =IF(C116=0,$C$119*C138,C118*C138/C116) -> 120.08409 | D29: =IF(D116=0,$C$119*D138,D118*D138/D116) -> 100.29405 | E29: =IF(E116=0,$C$119*E138,E118*E138/E116) -> 101.39122 | F29: =$G$30*F12/$G$12-F118 -> 98.623943 | G29: =IF(G116=0,$C$119*G138,G118*G138/G116) -> 32.004282 | H29: =$G$30*H12/$G$12-H118 -> 130.72284 | I29: 1A to 2B and 3B: CPAT deaths × (1 + fuel adjustment ÷ CPAT energy CO2 change). 3A and 3C: 3B deaths avoided × (scenario K ÷ 3B K), minus CPAT's own count.
A30: Premature deaths avoided, D | B30: deaths | C30: =SUM(C28:C29) -> 1659.0841 | D30: =SUM(D28:D29) -> 1639.2941 | E30: =SUM(E28:E29) -> 1799.3912 | F30: =SUM(F28:F29) -> 60.623943 | G30: =SUM(G28:G29) -> 45.004282 | H30: =SUM(H28:H29) -> 100.72284 | I30: Sum of the lines above.
A31: Walk 5. Coverage of national GHG, C
A32: 1A to 2B: CPAT tells us how much of energy CO2 is priced, and we add the CBAM products' process emissions when they are priced. 3A to 3C: coverage is the CBAM block's own emissions. All are shares of national GHG as defined in Walk 2 (inventory shares).
A33: CPAT: priced energy CO2 as a share of national GHG | B33: % | C33: =C91*C94/C16 -> 0.6419205 | D33: =D91*D94/D16 -> 0.6419205 | E33: =E91*E94/E16 -> 0.6419725 | F33: =F91*F94/F16 -> 0.035984 | G33: =G91*G94/G16 -> 0.039091 | H33: =H91*H94/H16 -> 0.035971 | I33: CPAT coverage × baseline energy CO2 ÷ national GHG (Walk 2).
A34: Adjustment 1: add CBAM process emissions, if priced | B34: % | C34: =C$69*C122/C16 -> 0.073077427 | D34: =D$69*D122/D16 -> 0 | E34: =E$69*E122/E16 -> 0 | F34: =F$69*F122/F16 -> 0.073077427 | G34: =G$69*G122/G16 -> 0.073077427 | H34: =H$69*H122/H16 -> 0.073077427 | I34: Zero where process emissions are not priced.
A35: Coverage of national GHG, C | B35: % | C35: =IF(C$72=1,(C121+C122)/C16,SUM(C33:C34)) -> 0.71499793 | D35: =IF(D$72=1,(D121+D122)/D16,SUM(D33:D34)) -> 0.6419205 | E35: =IF(E$72=1,(E121+E122)/E16,SUM(E33:E34)) -> 0.6419725 | F35: =IF(F$72=1,(F121+F122)/F16,SUM(F33:F34)) -> 0.14998937 | G35: =IF(G$72=1,(G121+G122)/G16,SUM(G33:G34)) -> 0.14998937 | H35: =IF(H$72=1,(H121+H122)/H16,SUM(H33:H34)) -> 0.14998937 | I35: 1A to 2B: CPAT's priced energy CO2 plus CBAM process emissions if priced. 3A to 3C price the seven CBAM products only, so coverage is the block's baseline emissions (fuel plus process) ÷ national GHG. CPAT cannot isolate these products: its sub-industry energy data for Egypt are empty except iron and steel (methodology Appendix G).
A36: Walk 6. CBAM block emissions (ΔE_CBAM/E^0_CBAM, I, S)
A37: We start from baseline emissions of the seven products and add the effect of lower output, then of higher fuel efficiency, then of lower process emissions per tonne.
A38: Baseline block emissions | B38: Mt | C38: =C121+C122 -> 65.281605 | D38: =D121+D122 -> 65.281605 | E38: =E121+E122 -> 65.281605 | F38: =F121+F122 -> 65.281605 | G38: =G121+G122 -> 65.281605 | H38: =H121+H122 -> 65.281605 | I38: Fuel plus process, from Product detail.
A39: Adjustment 1: output effect | B39: Mt | C39: =(C125+C126)-C38 -> -2.2840954 | D39: =(D125+D126)-D38 -> -1.2023737 | E39: =(E125+E126)-E38 -> -1.2023737 | F39: =(F125+F126)-F38 -> -2.2840954 | G39: =(G125+G126)-G38 -> 0 | H39: =(H125+H126)-H38 -> -2.2840954 | I39: Less output at baseline intensity. Driven by the product elasticities.
A40: Adjustment 2: fuel efficiency effect | B40: Mt | C40: =C123-C125 -> -3.4934274 | D40: =D123-D125 -> -3.5350428 | E40: =E123-E125 -> -3.5350428 | F40: =F123-F125 -> -3.4934274 | G40: =G123-G125 -> -3.61319 | H40: =H123-H125 -> -6.6097879 | I40: Cleaner fuel use per tonne. Includes the fund.
A41: Adjustment 3: process efficiency effect | B41: Mt | C41: =C124-C126 -> -2.097316 | D41: =D124-D126 -> 0 | E41: =E124-E126 -> 0 | F41: =F124-F126 -> -2.097316 | G41: =G124-G126 -> -2.1769717 | H41: =H124-H126 -> -4.0393455 | I41: Lower process emissions per tonne. Includes the fund.
A42: Policy block emissions | B42: Mt | C42: =SUM(C38:C41) -> 57.406766 | D42: =SUM(D38:D41) -> 60.544189 | E42: =SUM(E38:E41) -> 60.544189 | F42: =SUM(F38:F41) -> 57.406766 | G42: =SUM(G38:G41) -> 59.491443 | H42: =SUM(H38:H41) -> 52.348376 | I42: Sum of the lines above.
A43: CBAM block emissions change, ΔE_CBAM/E^0_CBAM | B43: % | C43: =C42/C38-1 -> -0.12062876 | D43: =D42/D38-1 -> -0.072568933 | E43: =E42/E38-1 -> -0.072568933 | F43: =F42/F38-1 -> -0.12062876 | G43: =G42/G38-1 -> -0.08869515 | H43: =H42/H38-1 -> -0.19811444 | I43: Policy ÷ baseline block emissions, minus 1. Output and efficiency together.
A44: Emissions intensity change, I | B44: % | C44: =C42/(C125+C126)-1 -> -0.088745466 | D44: =D42/(D125+D126)-1 -> -0.055166747 | E44: =E42/(E125+E126)-1 -> -0.055166747 | F44: =F42/(F125+F126)-1 -> -0.088745466 | G44: =G42/(G125+G126)-1 -> -0.08869515 | H44: =H42/(H125+H126)-1 -> -0.16904055 | I44: Policy emissions ÷ emissions at baseline intensity, minus 1. Efficiency alone.
A45: Priced share of block emissions, S | B45: % | C45: =(C123+C$69*C124)/(C123+C124) -> 1 | D45: =(D123+D$69*D124)/(D123+D124) -> 0.4825602 | E45: =(E123+E$69*E124)/(E123+E124) -> 0.4825602 | F45: =(F123+F$69*F124)/(F123+F124) -> 1 | G45: =(G123+G$69*G124)/(G123+G124) -> 1 | H45: =(H123+H$69*H124)/(H123+H124) -> 1 | I45: Priced emissions (fuel always, process if priced) ÷ all block emissions.
A46: Walk 7. CBAM obligation per tonne of EU exports (ΔΩ/Ω^0)
A47: Per tonne exported, so export volume does not enter. The obligation is the EU price after phase-in times the emissions per tonne of EU exports, minus the carbon price paid in Egypt where it is eligible for credit. Credit rules: an explicit carbon price counts; an output-based rebate (the 3B feebate) makes it ineligible; a fund for decarbonization (3C) does not add to the price credited, but does not invalidate it.
A48: Baseline obligation per tonne of EU exports (US$/t) | B48: US$m | C48: =$C$81*$C$80*C128 -> 34.565933 | D48: =$C$81*$C$80*D128 -> 34.565933 | E48: =$C$81*$C$80*E128 -> 34.565933 | F48: =$C$81*$C$80*F128 -> 34.565933 | G48: =$C$81*$C$80*G128 -> 34.565933 | H48: =$C$81*$C$80*H128 -> 34.565933 | I48: EU price × phase-in factor × baseline emissions per tonne of EU exports.
A49: Adjustment 1: cleaner exports | B49: US$m | C49: =$C$81*$C$80*(C129-C128) -> -2.9033457 | D49: =$C$81*$C$80*(D129-D128) -> -1.911056 | E49: =$C$81*$C$80*(E129-E128) -> -1.911056 | F49: =$C$81*$C$80*(F129-F128) -> -2.9033457 | G49: =$C$81*$C$80*(G129-G128) -> -2.9033457 | H49: =$C$81*$C$80*(H129-H128) -> -5.5300036 | I49: EU price × phase-in × change in emissions per tonne.
A50: Adjustment 2: credit for the carbon price paid in Egypt | B50: US$m | C50: =-MIN($C$81*$C$80*C129,$C$82*MAX(0,C130)*C55) -> -10.44539 | D50: =-MIN($C$81*$C$80*D129,$C$82*MAX(0,D130)*D55) -> -5.2105187 | E50: =-MIN($C$81*$C$80*E129,$C$82*MAX(0,E130)*E55) -> -5.2105187 | F50: =-MIN($C$81*$C$80*F129,$C$82*MAX(0,F130)*F55) -> -10.44539 | G50: =-MIN($C$81*$C$80*G129,$C$82*MAX(0,G130)*G55) -> 0 | H50: =-MIN($C$81*$C$80*H129,$C$82*MAX(0,H130)*H55) -> -9.5788635 | I50: Carbon paid per tonne of EU exports, if eligible (line 55); the obligation cannot go below zero. The fund shadow price is not part of the price credited.
A51: Policy obligation per tonne after the credit (US$/t) | B51: US$m | C51: =SUM(C48:C50) -> 21.217198 | D51: =SUM(D48:D50) -> 27.444359 | E51: =SUM(E48:E50) -> 27.444359 | F51: =SUM(F48:F50) -> 21.217198 | G51: =SUM(G48:G50) -> 31.662588 | H51: =SUM(H48:H50) -> 19.457066 | I51: Sum of the lines above.
A52: Obligation per tonne, change after the Egyptian credit, ΔΩ/Ω^0 | B52: US$m | C52: =C51/C48-1 -> -0.38618183 | D52: =D51/D48-1 -> -0.20602871 | E52: =E51/E48-1 -> -0.20602871 | F52: =F51/F48-1 -> -0.38618183 | G52: =G51/G48-1 -> -0.083994426 | H52: =H51/H48-1 -> -0.43710282 | I52: Policy obligation ÷ baseline obligation, minus 1. Main obligation result.
A53: Memo: of which cleaner exports | B53: % | C53: =C49/C48 -> -0.083994426 | D53: =D49/D48 -> -0.055287267 | E53: =E49/E48 -> -0.055287267 | F53: =F49/F48 -> -0.083994426 | G53: =G49/G48 -> -0.083994426 | H53: =H49/H48 -> -0.15998421 | I53: Adjustment 1 ÷ baseline. The EU price and phase-in cancel.
A54: Memo: of which carbon price credit | B54: % | C54: =C50/C48 -> -0.30218741 | D54: =D50/D48 -> -0.15074144 | E54: =E50/E48 -> -0.15074144 | F54: =F50/F48 -> -0.30218741 | G54: =G50/G48 -> 0 | H54: =H50/H48 -> -0.27711861 | I54: Adjustment 2 ÷ baseline.
A55: Credit eligible (1 = yes) | B55: % | C55: =1-C$70 -> 1 | D55: =1-D$70 -> 1 | E55: =1-E$70 -> 1 | F55: =1-F$70 -> 1 | G55: =1-G$70 -> 0 | H55: =1-H$70 -> 1 | I55: 1 minus the rebate share: an output-based rebate (3B) makes the Egyptian price ineligible.
A56: Walk 8. CBAM obligation, simple check (memo)
A57: A shortcut check on Walk 7, also per tonne exported. Cleaner exports cut the obligation by r. The carbon price paid in Egypt, τ^EGY = τ × S × (1 − θ), is then credited against the EU price after phase-in, τ^EU = γ × p^EU (0.485 × 125 ≈ 61), on the priced share S of emissions. So the obligation changes by −r − (1 − r) × τ^EGY ÷ τ^EU.
A58: Baseline obligation (index) | B58: % | C58: =0 -> 0 | D58: =0 -> 0 | E58: =0 -> 0 | F58: =0 -> 0 | G58: =0 -> 0 | H58: =0 -> 0 | I58: Starting point: no change.
A59: Adjustment 1: cleaner exports, −r | B59: % | C59: =C53 -> -0.083994426 | D59: =D53 -> -0.055287267 | E59: =E53 -> -0.055287267 | F59: =F53 -> -0.083994426 | G59: =G53 -> -0.083994426 | H59: =H53 -> -0.15998421 | I59: r is the fall in emissions per tonne of EU exports (the cleaner-exports part of Walk 7), shown as a negative change.
A60: τ^EGY: carbon price credited, τ × S × (1 − θ) | B60: US$/t | C60: =C$73*C45*(1-C$70) -> 20 | D60: =D$73*D45*(1-D$70) -> 9.6512041 | E60: =E$73*E45*(1-E$70) -> 9.6512041 | F60: =F$73*F45*(1-F$70) -> 20 | G60: =G$73*G45*(1-G$70) -> 0 | H60: =H$73*H45*(1-H$70) -> 20 | I60: τ × S (priced CBAM emissions ÷ all CBAM emissions) × (1 − θ). Feebates are not creditable, so a fully refunded price (3B) earns no credit.
A61: τ^EGY ÷ τ^EU | B61: share | C61: =MIN(1,C60/($C$80*$C$81)) -> 0.32989691 | D61: =MIN(1,D60/($C$80*$C$81)) -> 0.15919512 | E61: =MIN(1,E60/($C$80*$C$81)) -> 0.15919512 | F61: =MIN(1,F60/($C$80*$C$81)) -> 0.32989691 | G61: =MIN(1,G60/($C$80*$C$81)) -> 0 | H61: =MIN(1,H60/($C$80*$C$81)) -> 0.32989691 | I61: τ^EU = γ × p^EU = 0.485 × 125 ≈ 61. The ratio is capped at 100%, as the obligation cannot go below zero.
A62: Adjustment 2: credit for the Egyptian carbon price, −(1 − r) × τ^EGY ÷ τ^EU | B62: % | C62: =-(1+C59)*C61 -> -0.30218741 | D62: =-(1+D59)*D61 -> -0.15039366 | E62: =-(1+E59)*E61 -> -0.15039366 | F62: =-(1+F59)*F61 -> -0.30218741 | G62: =-(1+G59)*G61 -> 0 | H62: =-(1+H59)*H61 -> -0.27711861 | I62: Shown as a negative change. (1 − r) is 1 plus the negative change in the line above.
A63: Obligation change, shortcut: −r − (1 − r) × τ^EGY ÷ τ^EU | B63: % | C63: =C58+C59+C62 -> -0.38618183 | D63: =D58+D59+D62 -> -0.20568092 | E63: =E58+E59+E62 -> -0.20568092 | F63: =F58+F59+F62 -> -0.38618183 | G63: =G58+G59+G62 -> -0.083994426 | H63: =H58+H59+H62 -> -0.43710282 | I63: Baseline + adjustment 1 + adjustment 2. Compare with the memo line in Walk 7.
A64: 2. INPUTS (blue = typed input)
A65: 2a. Scenario settings
A66: Scenario | C66: 1A | D66: 2A | E66: 2B | F66: 3A | G66: 3B | H66: 3C
A67: Scenario name | C67: Comprehensive levy | D67: Upstream levy | E67: Upstream levy, household refunds | F67: Downstream industry price | G67: 3A with feebate (revenue neutral) | H67: 3A with abatement fund | I67: From the methodology, section 3.
A68: CPAT run | C68: EGY1A | D68: EGY2A | E68: EGY2B | F68: EGY3A | G68: EGY3B | H68: EGY3C | I68: Which CPAT run each scenario reads (raw results of 7 Oct). In 3A to 3C diesel and gasoline are excluded from the price, so the runs no longer include the transport fuel price rise; 3B now reads its own run again.
A69: Process emissions priced, π (1 = yes) | B69: flag | C69: 1 | D69: 0 | E69: 0 | F69: 1 | G69: 1 | H69: 1 | I69: 1A and 3A to 3C charge the CBAM process emissions (σ^np and σ^no) as well as fuel; 2A and 2B charge fuel only.
A70: Rebate (feebate) share, θ (1 = revenue neutral) | B70: share | C70: 0 | D70: 0 | E70: 0 | F70: 0 | G70: 1 | H70: 0 | I70: 3B only. The block's charges are refunded per unit of output, so output is protected but the intensity incentive stays.
A71: Fund switch, φ | B71: share | C71: 0 | D71: 0 | E71: 0 | F71: 0 | G71: 0 | H71: 1 | I71: 3C only. Share of block payments recycled into an abatement fund.
A72: Run prices CBAM sectors only (1 = yes) | B72: flag | C72: 0 | D72: 0 | E72: 0 | F72: 1 | G72: 1 | H72: 1 | I72: 3A to 3C price the heavy-industry (CBAM) sectors only, so CPAT's whole industry response belongs to the block.
A73: Carbon price on the CBAM block, τ | B73: US$/t | C73: 20 | D73: 20 | E73: 20 | F73: 20 | G73: 20 | H73: 20 | I73: Study design: US$20/t in 2030 in every scenario.
A74: 2b. Parameters (single values)
A75: CPAT industry fuel response to price (output + intensity) | B75: per US$/t | C75: =LN(C97/C96)/C73 -> -0.0068041578 | I75: Calculated as: ln(industry energy CO2 policy ÷ baseline) in the 1A CPAT run ÷ carbon price. Live from the CPAT results. Both margins together: less activity and lower emissions per unit.
A76: Output part of the fuel response (block, fuel cost only) | B76: per US$/t | C76: =LN(D125/D121)/C73 -> -0.0010932828 | I76: Calculated as: ln(block fuel emissions at policy output ÷ baseline) in 2A ÷ carbon price. The output effect of a price on fuel only, from the block's price elasticities of physical output. 2A is used because CPAT's industry response is to fuel prices; process charges (1A) are not part of it.
A77: Fuel-intensity response (−β^f) | B77: per US$/t | C77: =IF(ISBLANK(C86),C75-C76,-C86) -> -0.0057108749 | I77: Calculated as: CPAT's industry fuel response minus the block's own output effect, so the residual is the fall in fuel emissions per tonne (efficiency and fuel switching), unless an override is entered in row 86. Fuel emissions per tonne are multiplied by e^(this value × (τ + φψ)). The methodology writes it as a positive semi-elasticity, β^f = 0.0057, with e^(−β^f × (τ + φψ)).
A78: Years from 2024 to 2030 | B78: years | C78: 6 | I78: Production data is for 2024 and grows to 2030.
A79: Fund shadow price, ψ | B79: US$/t | C79: 20 | I79: Methodology Section 5. Added to the price for the intensity response when φ = 1.
A80: EU certificate price, p^EU | B80: US$/t | C80: 125 | I80: EU ETS price in 2030: €109/t, average of nine analysts' forecasts (Reuters survey, July 2026), at US$1.15 per euro. Used only in the obligation memo and the alternative formula.
A81: CBAM phase-in factor, γ (2030) | B81: share | C81: 0.485 | I81: 2030 CBAM phase-in factor under Regulation (EU) 2023/956. Set to 1 for no phase-in.
A82: Deduction scaling, κ | B82: share | C82: 1 | I82: Study assumption: Egyptian carbon price deducted in full.
A83: Reference run for deaths per Mt | B83: run code | C83: EGY3A | I83: Used only where a run has no energy CO2 change (for example the feebate run), to turn block abatement into deaths avoided.
A84: Product data (output, prices, emission factors, elasticities, exports) are inputs too. They sit at the top of the Product detail sheet, next to the product calculations that use them.
A85: Energy CO2 share of national GHG, inventory, s_en | B85: share | C85: 0.65 | I85: Egypt's 2022 GHG inventory (First Biennial Transparency Report, 2024): national GHG 386 Mt CO2e, of which energy 66%. Less the small non-CO2 part of energy emissions, energy CO2 is about 65%. Used to set national GHG in 2030 (Walk 2) because CPAT's 2030 baseline has far more waste and process emissions than the inventory (energy CO2 only 53% of 536 Mt).
A86: Fuel-intensity override, β^f (blank = residual) | B86: per US$/t | I86: Leave blank to use the residual (row 77). Enter a positive value to test another response: the literature consensus is about 0.005 (range 0.0037 to 0.0075); see methodology Appendix F.
A87: 3. NUMBERS THE WALKS USE
A88: CPAT numbers are looked up from the Data sheet; the CBAM block numbers are linked from the Product detail sheet (green).
A89: 3a. CPAT detail: values looked up by code (column B) and the scenario run. Click + at the left to open.
A90: CPAT carbon price (US$/t) | B90: egy.mit.cptraj.2 | C90: =INDEX(Data!$A$2:$AD$20000,MATCH($B90&"_"&C$68,Data!$F$2:$F$20000,0),MATCH(Data!$AG$1,Data!$A$1:$AD$1,0)) -> 20 | D90: =INDEX(Data!$A$2:$AD$20000,MATCH($B90&"_"&D$68,Data!$F$2:$F$20000,0),MATCH(Data!$AG$1,Data!$A$1:$AD$1,0)) -> 20 | E90: =INDEX(Data!$A$2:$AD$20000,MATCH($B90&"_"&E$68,Data!$F$2:$F$20000,0),MATCH(Data!$AG$1,Data!$A$1:$AD$1,0)) -> 20 | F90: =INDEX(Data!$A$2:$AD$20000,MATCH($B90&"_"&F$68,Data!$F$2:$F$20000,0),MATCH(Data!$AG$1,Data!$A$1:$AD$1,0)) -> 20 | G90: =INDEX(Data!$A$2:$AD$20000,MATCH($B90&"_"&G$68,Data!$F$2:$F$20000,0),MATCH(Data!$AG$1,Data!$A$1:$AD$1,0)) -> 0 | H90: =INDEX(Data!$A$2:$AD$20000,MATCH($B90&"_"&H$68,Data!$F$2:$F$20000,0),MATCH(Data!$AG$1,Data!$A$1:$AD$1,0)) -> 20 | I90: For information only, not used in the calculations. 3B shows 0 because the feebate run's net carbon price is zero (the refund offsets the tax); the price used in the block is the input in 2a.
A91: Coverage, share of energy CO2 (share) | B91: egy.mit.co2cov.2 | C91: =INDEX(Data!$A$2:$AD$20000,MATCH($B91&"_"&C$68,Data!$F$2:$F$20000,0),MATCH(Data!$AG$1,Data!$A$1:$AD$1,0)) -> 0.98757 | D91: =INDEX(Data!$A$2:$AD$20000,MATCH($B91&"_"&D$68,Data!$F$2:$F$20000,0),MATCH(Data!$AG$1,Data!$A$1:$AD$1,0)) -> 0.98757 | E91: =INDEX(Data!$A$2:$AD$20000,MATCH($B91&"_"&E$68,Data!$F$2:$F$20000,0),MATCH(Data!$AG$1,Data!$A$1:$AD$1,0)) -> 0.98765 | F91: =INDEX(Data!$A$2:$AD$20000,MATCH($B91&"_"&F$68,Data!$F$2:$F$20000,0),MATCH(Data!$AG$1,Data!$A$1:$AD$1,0)) -> 0.05536 | G91: =INDEX(Data!$A$2:$AD$20000,MATCH($B91&"_"&G$68,Data!$F$2:$F$20000,0),MATCH(Data!$AG$1,Data!$A$1:$AD$1,0)) -> 0.06014 | H91: =INDEX(Data!$A$2:$AD$20000,MATCH($B91&"_"&H$68,Data!$F$2:$F$20000,0),MATCH(Data!$AG$1,Data!$A$1:$AD$1,0)) -> 0.05534 | I91: Looked up: code in column B, run from the run row.
A92: GHG incl. LULUCF, baseline, E^0_tot (Mt) | B92: egy.mit.ghg.tot.inc.1 | C92: =INDEX(Data!$A$2:$AD$20000,MATCH($B92&"_"&C$68,Data!$F$2:$F$20000,0),MATCH(Data!$AG$1,Data!$A$1:$AD$1,0)) -> 535.623 | D92: =INDEX(Data!$A$2:$AD$20000,MATCH($B92&"_"&D$68,Data!$F$2:$F$20000,0),MATCH(Data!$AG$1,Data!$A$1:$AD$1,0)) -> 535.623 | E92: =INDEX(Data!$A$2:$AD$20000,MATCH($B92&"_"&E$68,Data!$F$2:$F$20000,0),MATCH(Data!$AG$1,Data!$A$1:$AD$1,0)) -> 535.623 | F92: =INDEX(Data!$A$2:$AD$20000,MATCH($B92&"_"&F$68,Data!$F$2:$F$20000,0),MATCH(Data!$AG$1,Data!$A$1:$AD$1,0)) -> 535.623 | G92: =INDEX(Data!$A$2:$AD$20000,MATCH($B92&"_"&G$68,Data!$F$2:$F$20000,0),MATCH(Data!$AG$1,Data!$A$1:$AD$1,0)) -> 535.623 | H92: =INDEX(Data!$A$2:$AD$20000,MATCH($B92&"_"&H$68,Data!$F$2:$F$20000,0),MATCH(Data!$AG$1,Data!$A$1:$AD$1,0)) -> 535.623 | I92: Looked up: code in column B, run from the run row.
A93: GHG incl. LULUCF, policy, Ê_tot (Mt) | B93: egy.mit.ghg.tot.inc.2 | C93: =INDEX(Data!$A$2:$AD$20000,MATCH($B93&"_"&C$68,Data!$F$2:$F$20000,0),MATCH(Data!$AG$1,Data!$A$1:$AD$1,0)) -> 497.866 | D93: =INDEX(Data!$A$2:$AD$20000,MATCH($B93&"_"&D$68,Data!$F$2:$F$20000,0),MATCH(Data!$AG$1,Data!$A$1:$AD$1,0)) -> 497.866 | E93: =INDEX(Data!$A$2:$AD$20000,MATCH($B93&"_"&E$68,Data!$F$2:$F$20000,0),MATCH(Data!$AG$1,Data!$A$1:$AD$1,0)) -> 494.314 | F93: =INDEX(Data!$A$2:$AD$20000,MATCH($B93&"_"&F$68,Data!$F$2:$F$20000,0),MATCH(Data!$AG$1,Data!$A$1:$AD$1,0)) -> 530.742 | G93: =INDEX(Data!$A$2:$AD$20000,MATCH($B93&"_"&G$68,Data!$F$2:$F$20000,0),MATCH(Data!$AG$1,Data!$A$1:$AD$1,0)) -> 533.565 | H93: =INDEX(Data!$A$2:$AD$20000,MATCH($B93&"_"&H$68,Data!$F$2:$F$20000,0),MATCH(Data!$AG$1,Data!$A$1:$AD$1,0)) -> 530.48 | I93: Looked up: code in column B, run from the run row.
A94: Energy CO2, baseline, E^0_en (Mt) | B94: egy.mit.co2.enr.tot.1 | C94: =INDEX(Data!$A$2:$AD$20000,MATCH($B94&"_"&C$68,Data!$F$2:$F$20000,0),MATCH(Data!$AG$1,Data!$A$1:$AD$1,0)) -> 282.907 | D94: =INDEX(Data!$A$2:$AD$20000,MATCH($B94&"_"&D$68,Data!$F$2:$F$20000,0),MATCH(Data!$AG$1,Data!$A$1:$AD$1,0)) -> 282.907 | E94: =INDEX(Data!$A$2:$AD$20000,MATCH($B94&"_"&E$68,Data!$F$2:$F$20000,0),MATCH(Data!$AG$1,Data!$A$1:$AD$1,0)) -> 282.907 | F94: =INDEX(Data!$A$2:$AD$20000,MATCH($B94&"_"&F$68,Data!$F$2:$F$20000,0),MATCH(Data!$AG$1,Data!$A$1:$AD$1,0)) -> 282.907 | G94: =INDEX(Data!$A$2:$AD$20000,MATCH($B94&"_"&G$68,Data!$F$2:$F$20000,0),MATCH(Data!$AG$1,Data!$A$1:$AD$1,0)) -> 282.907 | H94: =INDEX(Data!$A$2:$AD$20000,MATCH($B94&"_"&H$68,Data!$F$2:$F$20000,0),MATCH(Data!$AG$1,Data!$A$1:$AD$1,0)) -> 282.907 | I94: Looked up: code in column B, run from the run row.
A95: Energy CO2, policy, Ê_en (Mt) | B95: egy.mit.co2.enr.tot.2 | C95: =INDEX(Data!$A$2:$AD$20000,MATCH($B95&"_"&C$68,Data!$F$2:$F$20000,0),MATCH(Data!$AG$1,Data!$A$1:$AD$1,0)) -> 256.16 | D95: =INDEX(Data!$A$2:$AD$20000,MATCH($B95&"_"&D$68,Data!$F$2:$F$20000,0),MATCH(Data!$AG$1,Data!$A$1:$AD$1,0)) -> 256.16 | E95: =INDEX(Data!$A$2:$AD$20000,MATCH($B95&"_"&E$68,Data!$F$2:$F$20000,0),MATCH(Data!$AG$1,Data!$A$1:$AD$1,0)) -> 253.716 | F95: =INDEX(Data!$A$2:$AD$20000,MATCH($B95&"_"&F$68,Data!$F$2:$F$20000,0),MATCH(Data!$AG$1,Data!$A$1:$AD$1,0)) -> 280.472 | G95: =INDEX(Data!$A$2:$AD$20000,MATCH($B95&"_"&G$68,Data!$F$2:$F$20000,0),MATCH(Data!$AG$1,Data!$A$1:$AD$1,0)) -> 281.863 | H95: =INDEX(Data!$A$2:$AD$20000,MATCH($B95&"_"&H$68,Data!$F$2:$F$20000,0),MATCH(Data!$AG$1,Data!$A$1:$AD$1,0)) -> 280.291 | I95: Looked up: code in column B, run from the run row.
A96: Industry energy CO2, baseline, E^0_ind (Mt) | B96: egy.mit.co2.ind.1 | C96: =INDEX(Data!$A$2:$AD$20000,MATCH($B96&"_"&C$68,Data!$F$2:$F$20000,0),MATCH(Data!$AG$1,Data!$A$1:$AD$1,0)) -> 88.399 | D96: =INDEX(Data!$A$2:$AD$20000,MATCH($B96&"_"&D$68,Data!$F$2:$F$20000,0),MATCH(Data!$AG$1,Data!$A$1:$AD$1,0)) -> 88.399 | E96: =INDEX(Data!$A$2:$AD$20000,MATCH($B96&"_"&E$68,Data!$F$2:$F$20000,0),MATCH(Data!$AG$1,Data!$A$1:$AD$1,0)) -> 88.399 | F96: =INDEX(Data!$A$2:$AD$20000,MATCH($B96&"_"&F$68,Data!$F$2:$F$20000,0),MATCH(Data!$AG$1,Data!$A$1:$AD$1,0)) -> 88.399 | G96: =INDEX(Data!$A$2:$AD$20000,MATCH($B96&"_"&G$68,Data!$F$2:$F$20000,0),MATCH(Data!$AG$1,Data!$A$1:$AD$1,0)) -> 88.399 | H96: =INDEX(Data!$A$2:$AD$20000,MATCH($B96&"_"&H$68,Data!$F$2:$F$20000,0),MATCH(Data!$AG$1,Data!$A$1:$AD$1,0)) -> 88.399 | I96: Looked up: code in column B, run from the run row.
A97: Industry energy CO2, policy, Ê_ind (Mt) | B97: egy.mit.co2.ind.2 | C97: =INDEX(Data!$A$2:$AD$20000,MATCH($B97&"_"&C$68,Data!$F$2:$F$20000,0),MATCH(Data!$AG$1,Data!$A$1:$AD$1,0)) -> 77.152 | D97: =INDEX(Data!$A$2:$AD$20000,MATCH($B97&"_"&D$68,Data!$F$2:$F$20000,0),MATCH(Data!$AG$1,Data!$A$1:$AD$1,0)) -> 77.152 | E97: =INDEX(Data!$A$2:$AD$20000,MATCH($B97&"_"&E$68,Data!$F$2:$F$20000,0),MATCH(Data!$AG$1,Data!$A$1:$AD$1,0)) -> 76.055 | F97: =INDEX(Data!$A$2:$AD$20000,MATCH($B97&"_"&F$68,Data!$F$2:$F$20000,0),MATCH(Data!$AG$1,Data!$A$1:$AD$1,0)) -> 85.883 | G97: =INDEX(Data!$A$2:$AD$20000,MATCH($B97&"_"&G$68,Data!$F$2:$F$20000,0),MATCH(Data!$AG$1,Data!$A$1:$AD$1,0)) -> 87.356 | H97: =INDEX(Data!$A$2:$AD$20000,MATCH($B97&"_"&H$68,Data!$F$2:$F$20000,0),MATCH(Data!$AG$1,Data!$A$1:$AD$1,0)) -> 85.804 | I97: Looked up: code in column B, run from the run row.
A98: IPPU GHG, baseline (Mt) | B98: egy.mit.ghg.ipr.tot.1 | C98: =INDEX(Data!$A$2:$AD$20000,MATCH($B98&"_"&C$68,Data!$F$2:$F$20000,0),MATCH(Data!$AG$1,Data!$A$1:$AD$1,0)) -> 85.454 | D98: =INDEX(Data!$A$2:$AD$20000,MATCH($B98&"_"&D$68,Data!$F$2:$F$20000,0),MATCH(Data!$AG$1,Data!$A$1:$AD$1,0)) -> 85.454 | E98: =INDEX(Data!$A$2:$AD$20000,MATCH($B98&"_"&E$68,Data!$F$2:$F$20000,0),MATCH(Data!$AG$1,Data!$A$1:$AD$1,0)) -> 85.454 | F98: =INDEX(Data!$A$2:$AD$20000,MATCH($B98&"_"&F$68,Data!$F$2:$F$20000,0),MATCH(Data!$AG$1,Data!$A$1:$AD$1,0)) -> 85.454 | G98: =INDEX(Data!$A$2:$AD$20000,MATCH($B98&"_"&G$68,Data!$F$2:$F$20000,0),MATCH(Data!$AG$1,Data!$A$1:$AD$1,0)) -> 85.454 | H98: =INDEX(Data!$A$2:$AD$20000,MATCH($B98&"_"&H$68,Data!$F$2:$F$20000,0),MATCH(Data!$AG$1,Data!$A$1:$AD$1,0)) -> 85.454 | I98: Looked up: code in column B, run from the run row.
A99: IPPU GHG, policy (Mt) | B99: egy.mit.ghg.ipr.tot.2 | C99: =INDEX(Data!$A$2:$AD$20000,MATCH($B99&"_"&C$68,Data!$F$2:$F$20000,0),MATCH(Data!$AG$1,Data!$A$1:$AD$1,0)) -> 74.581 | D99: =INDEX(Data!$A$2:$AD$20000,MATCH($B99&"_"&D$68,Data!$F$2:$F$20000,0),MATCH(Data!$AG$1,Data!$A$1:$AD$1,0)) -> 74.581 | E99: =INDEX(Data!$A$2:$AD$20000,MATCH($B99&"_"&E$68,Data!$F$2:$F$20000,0),MATCH(Data!$AG$1,Data!$A$1:$AD$1,0)) -> 73.521 | F99: =INDEX(Data!$A$2:$AD$20000,MATCH($B99&"_"&F$68,Data!$F$2:$F$20000,0),MATCH(Data!$AG$1,Data!$A$1:$AD$1,0)) -> 83.022 | G99: =INDEX(Data!$A$2:$AD$20000,MATCH($B99&"_"&G$68,Data!$F$2:$F$20000,0),MATCH(Data!$AG$1,Data!$A$1:$AD$1,0)) -> 84.445 | H99: =INDEX(Data!$A$2:$AD$20000,MATCH($B99&"_"&H$68,Data!$F$2:$F$20000,0),MATCH(Data!$AG$1,Data!$A$1:$AD$1,0)) -> 82.945 | I99: Looked up: code in column B, run from the run row.
A100: Carbon receipts, coal (US$bn) | B100: egy.mit.rev.new.coa.usd.2 | C100: =INDEX(Data!$A$2:$AD$20000,MATCH($B100&"_"&C$68,Data!$F$2:$F$20000,0),MATCH(Data!$AG$1,Data!$A$1:$AD$1,0)) -> 0.16 | D100: =INDEX(Data!$A$2:$AD$20000,MATCH($B100&"_"&D$68,Data!$F$2:$F$20000,0),MATCH(Data!$AG$1,Data!$A$1:$AD$1,0)) -> 0.16 | E100: =INDEX(Data!$A$2:$AD$20000,MATCH($B100&"_"&E$68,Data!$F$2:$F$20000,0),MATCH(Data!$AG$1,Data!$A$1:$AD$1,0)) -> 0.15 | F100: =INDEX(Data!$A$2:$AD$20000,MATCH($B100&"_"&F$68,Data!$F$2:$F$20000,0),MATCH(Data!$AG$1,Data!$A$1:$AD$1,0)) -> 0.16 | G100: =INDEX(Data!$A$2:$AD$20000,MATCH($B100&"_"&G$68,Data!$F$2:$F$20000,0),MATCH(Data!$AG$1,Data!$A$1:$AD$1,0)) -> 0 | H100: =INDEX(Data!$A$2:$AD$20000,MATCH($B100&"_"&H$68,Data!$F$2:$F$20000,0),MATCH(Data!$AG$1,Data!$A$1:$AD$1,0)) -> 0.16 | I100: Looked up: CPAT carbon-tax receipts for this fuel.
...

Sheet Product detail
A1: Egypt CBAM block: calculations for each product, 2030
A2: This sheet holds the seven-product calculation. Inputs (blue) come first, then the baseline, then six steps, each a table with products in rows and scenarios in columns. The last block adds the products up into the few totals that the Calculations sheet uses. Scenario settings and parameters are linked in green from the Calculations sheet.
A4: A. Linked settings (from the Calculations sheet)
A5: Scenario | C5: =Calculations!C66 -> 1A | D5: =Calculations!D66 -> 2A | E5: =Calculations!E66 -> 2B | F5: =Calculations!F66 -> 3A | G5: =Calculations!G66 -> 3B | H5: =Calculations!H66 -> 3C
A6: Carbon price on the CBAM block, τ | B6: US$/t | C6: =Calculations!C73 -> 20 | D6: =Calculations!D73 -> 20 | E6: =Calculations!E73 -> 20 | F6: =Calculations!F73 -> 20 | G6: =Calculations!G73 -> 20 | H6: =Calculations!H73 -> 20 | I6: Linked from the Calculations sheet.
A7: Process emissions priced, π (1 = yes) | B7: flag | C7: =Calculations!C69 -> 1 | D7: =Calculations!D69 -> 0 | E7: =Calculations!E69 -> 0 | F7: =Calculations!F69 -> 1 | G7: =Calculations!G69 -> 1 | H7: =Calculations!H69 -> 1 | I7: Linked from the Calculations sheet.
A8: Rebate (feebate) share, θ | B8: share | C8: =Calculations!C70 -> 0 | D8: =Calculations!D70 -> 0 | E8: =Calculations!E70 -> 0 | F8: =Calculations!F70 -> 0 | G8: =Calculations!G70 -> 1 | H8: =Calculations!H70 -> 0 | I8: Linked from the Calculations sheet.
A9: Fund switch, φ | B9: share | C9: =Calculations!C71 -> 0 | D9: =Calculations!D71 -> 0 | E9: =Calculations!E71 -> 0 | F9: =Calculations!F71 -> 0 | G9: =Calculations!G71 -> 0 | H9: =Calculations!H71 -> 1 | I9: Linked from the Calculations sheet.
A10: Fuel-intensity response (−β^f) | B10: per US$/t | C10: =Calculations!$C$77 -> -0.0057108749 | I10: Linked from the Calculations sheet.
A11: Years from 2024 to 2030 | B11: years | C11: =Calculations!$C$78 -> 6 | I11: Linked from the Calculations sheet.
A12: Fund shadow price, ψ | B12: US$/t | C12: =Calculations!$C$79 -> 20 | I12: Linked from the Calculations sheet.
A14: B. Product inputs (blue = typed input)
A15: B1. Production, prices and emission factors | C15: 2024 output, Y^2024 (kt) | D15: Growth per year, g | E15: Fuel EF, σ^f = σ^fc + σ^fp (t/t) | F15: Process CO2 EF, σ^np (t/t) | G15: Non-CO2 process EF, σ^no (t/t) | H15: Price, p (US$/t)
A16: DRI-EAF steel | C16: 6400 | D16: 0.02 | E16: 0.57099077 | F16: 0.03790102 | G16: 0 | H16: 530 | I16: 2024 output: DRI-EAF steel = Midrex DRI production 6.37 Mt (2024), taken as steel tonnes; scrap-EAF = worldsteel crude steel 10.7 Mt less DRI-EAF; clinker = USGS cement 50 Mt x 0.8 clinker ratio (assumed); ammonia = USGS 3.9 Mt N (2024) = 4.74 Mt NH3; urea = 7.0 Mt (capacity 7.2-7.3 Mt running at full rates, Argus 2026; exports about 4.5 Mt a year); ammonium nitrate = 1.5 Mt (nitrogen balance: USGS ammonia N less urea N, about 100 kt merchant ammonia; Abu Qir alone has 0.88 Mt capacity). The earlier EBRD total of 6.18 Mt covered only plants exporting to the EU; aluminum = Egyptalum capacity about 310 kt, flat to 2030. Growth 2024-30: products not limited by capacity grow with IMF real GDP forecasts (about 5% a year): scrap-EAF steel and clinker (clinker capacity 60 Mt, USGS). Fertilizers 2.9% a year: 2.5 Mt of announced additions (Daily News Egypt, Sept 2026) on 13.2 Mt. DRI-EAF 2%: DRI plants run at rated capacity, so growth assumes half of the idle 1.76 Mt ESISCO plant restarts (Midrex). Aluminum 0%: no new line before 2030. Prices: see note on the aluminum row. Emission factors: methodology Appendix D.
A17: Scrap-EAF steel | C17: 4300 | D17: 0.05 | E17: 0.04488 | F17: 0.04398115 | G17: 0 | H17: 530
A18: Gray clinker | C18: 40000 | D18: 0.05 | E18: 0.3135685 | F18: 0.53702616 | G18: 0 | H18: 35
A19: Ammonia | C19: 4736 | D19: 0.0293 | E19: 1.97472 | F19: 0 | G19: 0 | H19: 400
A20: Urea | C20: 7000 | D20: 0.0293 | E20: 0.1122 | F20: 0 | G20: 0 | H20: 340
A21: Ammonium nitrate | C21: 1500 | D21: 0.0293 | E21: 0.1122 | F21: 0 | G21: 0.9944125 | H21: 320
A22: Primary aluminum | C22: 300 | D22: 0 | E22: 0.12342 | F22: 1.623493 | G22: 0.774 | H22: 2600 | I22: Prices (2024 basis, $/t): steel billet 530 for both steel routes (Egyptian billet ex-works $521–533, SteelOrbis 2026); clinker 35 (Mediterranean clinker FOB, CW Research); ammonia 400 (Middle East FOB, 2024 range about $300–450, Argus/QCIntel); urea 340 (World Bank Pink Sheet 2024 average, $338); ammonium nitrate 320 (urea price × Egypt's domestic AN/urea price ratio, 0.93); aluminum 2,600 (Egyptalum export value $452m / 174 kt, FY2023/24; LME 2024 average $2,419).
A23: B2. Product responses and exports | C23: Price elasticity of physical output, ε | D23: EU exports, X (kt) | E23: Process semi-elasticity, β^np (per US$/t) | F23: Process semi-elasticity, β^no (per US$/t)
A24: DRI-EAF steel | C24: -0.4 | D24: 610 | E24: 0.0034469507 | F24: 0 | I24: EU exports: aluminum = Egyptalum exports 174 kt (FY2023/24) x 96% to EU markets; fertilizers = EBRD 1.45 Mt to the EU, split by product (assumed); steel scaled to EU iron and steel imports from Egypt (US$0.6bn, UN Comtrade) with an assumed split; clinker is a study assumption. Elasticities and semi-elasticities: methodology Appendix C.
A25: Scrap-EAF steel | C25: -0.4 | D25: 320 | E25: 0.0016366491 | F25: 0
A26: Gray clinker | C26: -0.1 | D26: 800 | E26: 0.0033464675 | F26: 0
A27: Ammonia | C27: -0.4 | D27: 97 | E27: 0 | F27: 0
A28: Urea | C28: -0.4 | D28: 1289 | E28: 0 | F28: 0
A29: Ammonium nitrate | C29: -0.4 | D29: 64 | E29: 0 | F29: 0.0078858436
A30: Primary aluminum | C30: -0.5 | D30: 167 | E30: 0.0019988245 | F30: 0.0019988245
A32: C. Baseline for each product, 2030 (independent of scenario)
A33: C1. Baseline | C33: Output (kt) | D33: Fuel emissions (Mt) | E33: Process emissions (Mt) | F33: Intensity (t/t) | G33: Exports × intensity
A34: DRI-EAF steel | C34: =C16*(1+D16)^$C$11 -> 7207.4395 | D34: =C34*E16/1000 -> 4.1153814 | E34: =C34*(F16+G16)/1000 -> 0.27316931 | F34: =E16+F16+G16 -> 0.60889179 | G34: =D24*F34 -> 371.42399 | I34: Output Y^0 = Y^2024 × (1 + g)^years. Fuel emissions E^f,0 = Y^0 × σ^f ÷ 1000 (kt to Mt). Process emissions E^p,0 = Y^0 × (σ^np + σ^no) ÷ 1000 (kt to Mt). Emissions per tonne σ^0 = σ^f + σ^np + σ^no. Exports × intensity = X × σ^0.
A35: Scrap-EAF steel | C35: =C17*(1+D17)^$C$11 -> 5762.4113 | D35: =C35*E17/1000 -> 0.25861702 | E35: =C35*(F17+G17)/1000 -> 0.25343747 | F35: =E17+F17+G17 -> 0.08886115 | G35: =D25*F35 -> 28.435568
A36: Gray clinker | C36: =C18*(1+D18)^$C$11 -> 53603.826 | D36: =C36*E18/1000 -> 16.808471 | E36: =C36*(F18+G18)/1000 -> 28.786657 | F36: =E18+F18+G18 -> 0.85059466 | G36: =D26*F36 -> 680.47573
A37: Ammonia | C37: =C19*(1+D19)^$C$11 -> 5632.0115 | D37: =C37*E19/1000 -> 11.121646 | E37: =C37*(F19+G19)/1000 -> 0 | F37: =E19+F19+G19 -> 1.97472 | G37: =D27*F37 -> 191.54784
A38: Urea | C38: =C20*(1+D20)^$C$11 -> 8324.3413 | D38: =C38*E20/1000 -> 0.93399109 | E38: =C38*(F20+G20)/1000 -> 0 | F38: =E20+F20+G20 -> 0.1122 | G38: =D28*F38 -> 144.6258
A39: Ammonium nitrate | C39: =C21*(1+D21)^$C$11 -> 1783.7874 | D39: =C39*E21/1000 -> 0.20014095 | E39: =C39*(F21+G21)/1000 -> 1.7738205 | F39: =E21+F21+G21 -> 1.1066125 | G39: =D29*F39 -> 70.8232
A40: Primary aluminum | C40: =C22*(1+D22)^$C$11 -> 300 | D40: =C40*E22/1000 -> 0.037026 | E40: =C40*(F22+G22)/1000 -> 0.71924791 | F40: =E22+F22+G22 -> 2.520913 | G40: =D30*F40 -> 420.99248
A41: Total | D41: =SUM(D34:D40) -> 33.475273 | E41: =SUM(E34:E40) -> 31.806332 | G41: =SUM(G34:G40) -> 1908.3246
A43: D. Product calculations under each scenario
A44: Six steps, in order. Rows are products and columns are scenarios.
A45: Step 1. Net cost increase as a share of the product price
A46: DRI-EAF steel | C46: =(1-C$8)*C$6*($E16+C$7*($F16+$G16))/$H16 -> 0.022977049 | D46: =(1-D$8)*D$6*($E16+D$7*($F16+$G16))/$H16 -> 0.021546822 | E46: =(1-E$8)*E$6*($E16+E$7*($F16+$G16))/$H16 -> 0.021546822 | F46: =(1-F$8)*F$6*($E16+F$7*($F16+$G16))/$H16 -> 0.022977049 | G46: =(1-G$8)*G$6*($E16+G$7*($F16+$G16))/$H16 -> 0 | H46: =(1-H$8)*H$6*($E16+H$7*($F16+$G16))/$H16 -> 0.022977049 | I46: δ = (1 − θ) × τ × (σ^f + π × (σ^np + σ^no)) ÷ p. The refund cancels the cost when θ = 1.
A47: Scrap-EAF steel | C47: =(1-C$8)*C$6*($E17+C$7*($F17+$G17))/$H17 -> 0.0033532509 | D47: =(1-D$8)*D$6*($E17+D$7*($F17+$G17))/$H17 -> 0.0016935849 | E47: =(1-E$8)*E$6*($E17+E$7*($F17+$G17))/$H17 -> 0.0016935849 | F47: =(1-F$8)*F$6*($E17+F$7*($F17+$G17))/$H17 -> 0.0033532509 | G47: =(1-G$8)*G$6*($E17+G$7*($F17+$G17))/$H17 -> 0 | H47: =(1-H$8)*H$6*($E17+H$7*($F17+$G17))/$H17 -> 0.0033532509
A48: Gray clinker | C48: =(1-C$8)*C$6*($E18+C$7*($F18+$G18))/$H18 -> 0.48605409 | D48: =(1-D$8)*D$6*($E18+D$7*($F18+$G18))/$H18 -> 0.179182 | E48: =(1-E$8)*E$6*($E18+E$7*($F18+$G18))/$H18 -> 0.179182 | F48: =(1-F$8)*F$6*($E18+F$7*($F18+$G18))/$H18 -> 0.48605409 | G48: =(1-G$8)*G$6*($E18+G$7*($F18+$G18))/$H18 -> 0 | H48: =(1-H$8)*H$6*($E18+H$7*($F18+$G18))/$H18 -> 0.48605409
A49: Ammonia | C49: =(1-C$8)*C$6*($E19+C$7*($F19+$G19))/$H19 -> 0.098736 | D49: =(1-D$8)*D$6*($E19+D$7*($F19+$G19))/$H19 -> 0.098736 | E49: =(1-E$8)*E$6*($E19+E$7*($F19+$G19))/$H19 -> 0.098736 | F49: =(1-F$8)*F$6*($E19+F$7*($F19+$G19))/$H19 -> 0.098736 | G49: =(1-G$8)*G$6*($E19+G$7*($F19+$G19))/$H19 -> 0 | H49: =(1-H$8)*H$6*($E19+H$7*($F19+$G19))/$H19 -> 0.098736
A50: Urea | C50: =(1-C$8)*C$6*($E20+C$7*($F20+$G20))/$H20 -> 0.0066 | D50: =(1-D$8)*D$6*($E20+D$7*($F20+$G20))/$H20 -> 0.0066 | E50: =(1-E$8)*E$6*($E20+E$7*($F20+$G20))/$H20 -> 0.0066 | F50: =(1-F$8)*F$6*($E20+F$7*($F20+$G20))/$H20 -> 0.0066 | G50: =(1-G$8)*G$6*($E20+G$7*($F20+$G20))/$H20 -> 0 | H50: =(1-H$8)*H$6*($E20+H$7*($F20+$G20))/$H20 -> 0.0066
A51: Ammonium nitrate | C51: =(1-C$8)*C$6*($E21+C$7*($F21+$G21))/$H21 -> 0.069163281 | D51: =(1-D$8)*D$6*($E21+D$7*($F21+$G21))/$H21 -> 0.0070125 | E51: =(1-E$8)*E$6*($E21+E$7*($F21+$G21))/$H21 -> 0.0070125 | F51: =(1-F$8)*F$6*($E21+F$7*($F21+$G21))/$H21 -> 0.069163281 | G51: =(1-G$8)*G$6*($E21+G$7*($F21+$G21))/$H21 -> 0 | H51: =(1-H$8)*H$6*($E21+H$7*($F21+$G21))/$H21 -> 0.069163281
A52: Primary aluminum | C52: =(1-C$8)*C$6*($E22+C$7*($F22+$G22))/$H22 -> 0.019391639 | D52: =(1-D$8)*D$6*($E22+D$7*($F22+$G22))/$H22 -> 0.00094938462 | E52: =(1-E$8)*E$6*($E22+E$7*($F22+$G22))/$H22 -> 0.00094938462 | F52: =(1-F$8)*F$6*($E22+F$7*($F22+$G22))/$H22 -> 0.019391639 | G52: =(1-G$8)*G$6*($E22+G$7*($F22+$G22))/$H22 -> 0 | H52: =(1-H$8)*H$6*($E22+H$7*($F22+$G22))/$H22 -> 0.019391639
A53: Step 2. Output (kt)
A54: DRI-EAF steel | C54: =$C34*(1+C46)^$C24 -> 7142.2434 | D54: =$C34*(1+D46)^$C24 -> 7146.2416 | E54: =$C34*(1+E46)^$C24 -> 7146.2416 | F54: =$C34*(1+F46)^$C24 -> 7142.2434 | G54: =$C34*(1+G46)^$C24 -> 7207.4395 | H54: =$C34*(1+H46)^$C24 -> 7142.2434 | I54: Y = Y^0 × (1 + δ)^ε. Only the net cost moves output.
A55: Scrap-EAF steel | C55: =$C35*(1+C47)^$C25 -> 5754.7002 | D55: =$C35*(1+D47)^$C25 -> 5758.5122 | E55: =$C35*(1+E47)^$C25 -> 5758.5122 | F55: =$C35*(1+F47)^$C25 -> 5754.7002 | G55: =$C35*(1+G47)^$C25 -> 5762.4113 | H55: =$C35*(1+H47)^$C25 -> 5754.7002
A56: Gray clinker | C56: =$C36*(1+C48)^$C26 -> 51521.954 | D56: =$C36*(1+D48)^$C26 -> 52727.563 | E56: =$C36*(1+E48)^$C26 -> 52727.563 | F56: =$C36*(1+F48)^$C26 -> 51521.954 | G56: =$C36*(1+G48)^$C26 -> 53603.826 | H56: =$C36*(1+H48)^$C26 -> 51521.954
A57: Ammonia | C57: =$C37*(1+C49)^$C27 -> 5423.8315 | D57: =$C37*(1+D49)^$C27 -> 5423.8315 | E57: =$C37*(1+E49)^$C27 -> 5423.8315 | F57: =$C37*(1+F49)^$C27 -> 5423.8315 | G57: =$C37*(1+G49)^$C27 -> 5632.0115 | H57: =$C37*(1+H49)^$C27 -> 5423.8315
A58: Urea | C58: =$C38*(1+C50)^$C28 -> 8302.466 | D58: =$C38*(1+D50)^$C28 -> 8302.466 | E58: =$C38*(1+E50)^$C28 -> 8302.466 | F58: =$C38*(1+F50)^$C28 -> 8302.466 | G58: =$C38*(1+G50)^$C28 -> 8324.3413 | H58: =$C38*(1+H50)^$C28 -> 8302.466
A59: Ammonium nitrate | C59: =$C39*(1+C51)^$C29 -> 1736.7027 | D59: =$C39*(1+D51)^$C29 -> 1778.8083 | E59: =$C39*(1+E51)^$C29 -> 1778.8083 | F59: =$C39*(1+F51)^$C29 -> 1736.7027 | G59: =$C39*(1+G51)^$C29 -> 1783.7874 | H59: =$C39*(1+H51)^$C29 -> 1736.7027
A60: Primary aluminum | C60: =$C40*(1+C52)^$C30 -> 297.13289 | D60: =$C40*(1+D52)^$C30 -> 299.85769 | E60: =$C40*(1+E52)^$C30 -> 299.85769 | F60: =$C40*(1+F52)^$C30 -> 297.13289 | G60: =$C40*(1+G52)^$C30 -> 300 | H60: =$C40*(1+H52)^$C30 -> 297.13289
A61: Total | C61: =SUM(C54:C60) -> 80179.031 | D61: =SUM(D54:D60) -> 81437.281 | E61: =SUM(E54:E60) -> 81437.281 | F61: =SUM(F54:F60) -> 80179.031 | G61: =SUM(G54:G60) -> 82613.817 | H61: =SUM(H54:H60) -> 80179.031
A62: Step 3. Fuel emissions after policy (Mt)
A63: DRI-EAF steel | C63: =C54*$E16*EXP($C$10*(C$6+C$9*$C$12))/1000 -> 3.637975 | D63: =D54*$E16*EXP($C$10*(D$6+D$9*$C$12))/1000 -> 3.6400115 | E63: =E54*$E16*EXP($C$10*(E$6+E$9*$C$12))/1000 -> 3.6400115 | F63: =F54*$E16*EXP($C$10*(F$6+F$9*$C$12))/1000 -> 3.637975 | G63: =G54*$E16*EXP($C$10*(G$6+G$9*$C$12))/1000 -> 3.6711832 | H63: =H54*$E16*EXP($C$10*(H$6+H$9*$C$12))/1000 -> 3.2453062 | I63: E^f = Y × σ^f × e^(−β^f × (τ + φψ)) ÷ 1000 (kt to Mt). Fuel use per tonne falls with the full price, including the fund shadow price.
A64: Scrap-EAF steel | C64: =C55*$E17*EXP($C$10*(C$6+C$9*$C$12))/1000 -> 0.23039419 | D64: =D55*$E17*EXP($C$10*(D$6+D$9*$C$12))/1000 -> 0.23054681 | E64: =E55*$E17*EXP($C$10*(E$6+E$9*$C$12))/1000 -> 0.23054681 | F64: =F55*$E17*EXP($C$10*(F$6+F$9*$C$12))/1000 -> 0.23039419 | G64: =G55*$E17*EXP($C$10*(G$6+G$9*$C$12))/1000 -> 0.23070291 | H64: =H55*$E17*EXP($C$10*(H$6+H$9*$C$12))/1000 -> 0.20552634
A65: Gray clinker | C65: =C56*$E18*EXP($C$10*(C$6+C$9*$C$12))/1000 -> 14.411883 | D65: =D56*$E18*EXP($C$10*(D$6+D$9*$C$12))/1000 -> 14.74912 | E65: =E56*$E18*EXP($C$10*(E$6+E$9*$C$12))/1000 -> 14.74912 | F65: =F56*$E18*EXP($C$10*(F$6+F$9*$C$12))/1000 -> 14.411883 | G65: =G56*$E18*EXP($C$10*(G$6+G$9*$C$12))/1000 -> 14.994231 | H65: =H56*$E18*EXP($C$10*(H$6+H$9*$C$12))/1000 -> 12.856321
A66: Ammonia | C66: =C57*$E19*EXP($C$10*(C$6+C$9*$C$12))/1000 -> 9.5544938 | D66: =D57*$E19*EXP($C$10*(D$6+D$9*$C$12))/1000 -> 9.5544938 | E66: =E57*$E19*EXP($C$10*(E$6+E$9*$C$12))/1000 -> 9.5544938 | F66: =F57*$E19*EXP($C$10*(F$6+F$9*$C$12))/1000 -> 9.5544938 | G66: =G57*$E19*EXP($C$10*(G$6+G$9*$C$12))/1000 -> 9.9212188 | H66: =H57*$E19*EXP($C$10*(H$6+H$9*$C$12))/1000 -> 8.5232191
A67: Urea | C67: =C58*$E20*EXP($C$10*(C$6+C$9*$C$12))/1000 -> 0.83099026 | D67: =D58*$E20*EXP($C$10*(D$6+D$9*$C$12))/1000 -> 0.83099026 | E67: =E58*$E20*EXP($C$10*(E$6+E$9*$C$12))/1000 -> 0.83099026 | F67: =F58*$E20*EXP($C$10*(F$6+F$9*$C$12))/1000 -> 0.83099026 | G67: =G58*$E20*EXP($C$10*(G$6+G$9*$C$12))/1000 -> 0.83317975 | H67: =H58*$E20*EXP($C$10*(H$6+H$9*$C$12))/1000 -> 0.74129642
A68: Ammonium nitrate | C68: =C59*$E21*EXP($C$10*(C$6+C$9*$C$12))/1000 -> 0.17382583 | D68: =D59*$E21*EXP($C$10*(D$6+D$9*$C$12))/1000 -> 0.17804016 | E68: =E59*$E21*EXP($C$10*(E$6+E$9*$C$12))/1000 -> 0.17804016 | F68: =F59*$E21*EXP($C$10*(F$6+F$9*$C$12))/1000 -> 0.17382583 | G68: =G59*$E21*EXP($C$10*(G$6+G$9*$C$12))/1000 -> 0.17853852 | H68: =H59*$E21*EXP($C$10*(H$6+H$9*$C$12))/1000 -> 0.15506375
A69: Primary aluminum | C69: =C60*$E22*EXP($C$10*(C$6+C$9*$C$12))/1000 -> 0.032713893 | D69: =D60*$E22*EXP($C$10*(D$6+D$9*$C$12))/1000 -> 0.033013891 | E69: =E60*$E22*EXP($C$10*(E$6+E$9*$C$12))/1000 -> 0.033013891 | F69: =F60*$E22*EXP($C$10*(F$6+F$9*$C$12))/1000 -> 0.032713893 | G69: =G60*$E22*EXP($C$10*(G$6+G$9*$C$12))/1000 -> 0.033029558 | H69: =H60*$E22*EXP($C$10*(H$6+H$9*$C$12))/1000 -> 0.029182884
A70: Total | C70: =SUM(C63:C69) -> 28.872276 | D70: =SUM(D63:D69) -> 29.216216 | E70: =SUM(E63:E69) -> 29.216216 | F70: =SUM(F63:F69) -> 28.872276 | G70: =SUM(G63:G69) -> 29.862083 | H70: =SUM(H63:H69) -> 25.755915
A71: Step 4. Process emissions after policy (Mt)
A72: DRI-EAF steel | C72: =C54*($F16*EXP(-$E24*(C$6*C$7+C$9*$C$12))+$G16*EXP(-$F24*(C$6*C$7+C$9*$C$12)))/1000 -> 0.25266536 | D72: =D54*($F16*EXP(-$E24*(D$6*D$7+D$9*$C$12))+$G16*EXP(-$F24*(D$6*D$7+D$9*$C$12)))/1000 -> 0.27084985 | E72: =E54*($F16*EXP(-$E24*(E$6*E$7+E$9*$C$12))+$G16*EXP(-$F24*(E$6*E$7+E$9*$C$12)))/1000 -> 0.27084985 | F72: =F54*($F16*EXP(-$E24*(F$6*F$7+F$9*$C$12))+$G16*EXP(-$F24*(F$6*F$7+F$9*$C$12)))/1000 -> 0.25266536 | G72: =G54*($F16*EXP(-$E24*(G$6*G$7+G$9*$C$12))+$G16*EXP(-$F24*(G$6*G$7+G$9*$C$12)))/1000 -> 0.25497175 | H72: =H54*($F16*EXP(-$E24*(H$6*H$7+H$9*$C$12))+$G16*EXP(-$F24*(H$6*H$7+H$9*$C$12)))/1000 -> 0.23583371 | I72: E^p = Y × (σ^np × e^(−β^np × (πτ + φψ)) + σ^no × e^(−β^no × (πτ + φψ))) ÷ 1000 (kt to Mt).
A73: Scrap-EAF steel | C73: =C55*($F17*EXP(-$E25*(C$6*C$7+C$9*$C$12))+$G17*EXP(-$F25*(C$6*C$7+C$9*$C$12)))/1000 -> 0.24494779 | D73: =D55*($F17*EXP(-$E25*(D$6*D$7+D$9*$C$12))+$G17*EXP(-$F25*(D$6*D$7+D$9*$C$12)))/1000 -> 0.25326599 | E73: =E55*($F17*EXP(-$E25*(E$6*E$7+E$9*$C$12))+$G17*EXP(-$F25*(E$6*E$7+E$9*$C$12)))/1000 -> 0.25326599 | F73: =F55*($F17*EXP(-$E25*(F$6*F$7+F$9*$C$12))+$G17*EXP(-$F25*(F$6*F$7+F$9*$C$12)))/1000 -> 0.24494779 | G73: =G55*($F17*EXP(-$E25*(G$6*G$7+G$9*$C$12))+$G17*EXP(-$F25*(G$6*G$7+G$9*$C$12)))/1000 -> 0.24527601 | H73: =H55*($F17*EXP(-$E25*(H$6*H$7+H$9*$C$12))+$G17*EXP(-$F25*(H$6*H$7+H$9*$C$12)))/1000 -> 0.23705973
A74: Gray clinker | C74: =C56*($F18*EXP(-$E26*(C$6*C$7+C$9*$C$12))+$G18*EXP(-$F26*(C$6*C$7+C$9*$C$12)))/1000 -> 25.877405 | D74: =D56*($F18*EXP(-$E26*(D$6*D$7+D$9*$C$12))+$G18*EXP(-$F26*(D$6*D$7+D$9*$C$12)))/1000 -> 28.316081 | E74: =E56*($F18*EXP(-$E26*(E$6*E$7+E$9*$C$12))+$G18*EXP(-$F26*(E$6*E$7+E$9*$C$12)))/1000 -> 28.316081 | F74: =F56*($F18*EXP(-$E26*(F$6*F$7+F$9*$C$12))+$G18*EXP(-$F26*(F$6*F$7+F$9*$C$12)))/1000 -> 25.877405 | G74: =G56*($F18*EXP(-$E26*(G$6*G$7+G$9*$C$12))+$G18*EXP(-$F26*(G$6*G$7+G$9*$C$12)))/1000 -> 26.923045 | H74: =H56*($F18*EXP(-$E26*(H$6*H$7+H$9*$C$12))+$G18*EXP(-$F26*(H$6*H$7+H$9*$C$12)))/1000 -> 24.202135
A75: Ammonia | C75: =C57*($F19*EXP(-$E27*(C$6*C$7+C$9*$C$12))+$G19*EXP(-$F27*(C$6*C$7+C$9*$C$12)))/1000 -> 0 | D75: =D57*($F19*EXP(-$E27*(D$6*D$7+D$9*$C$12))+$G19*EXP(-$F27*(D$6*D$7+D$9*$C$12)))/1000 -> 0 | E75: =E57*($F19*EXP(-$E27*(E$6*E$7+E$9*$C$12))+$G19*EXP(-$F27*(E$6*E$7+E$9*$C$12)))/1000 -> 0 | F75: =F57*($F19*EXP(-$E27*(F$6*F$7+F$9*$C$12))+$G19*EXP(-$F27*(F$6*F$7+F$9*$C$12)))/1000 -> 0 | G75: =G57*($F19*EXP(-$E27*(G$6*G$7+G$9*$C$12))+$G19*EXP(-$F27*(G$6*G$7+G$9*$C$12)))/1000 -> 0 | H75: =H57*($F19*EXP(-$E27*(H$6*H$7+H$9*$C$12))+$G19*EXP(-$F27*(H$6*H$7+H$9*$C$12)))/1000 -> 0
A76: Urea | C76: =C58*($F20*EXP(-$E28*(C$6*C$7+C$9*$C$12))+$G20*EXP(-$F28*(C$6*C$7+C$9*$C$12)))/1000 -> 0 | D76: =D58*($F20*EXP(-$E28*(D$6*D$7+D$9*$C$12))+$G20*EXP(-$F28*(D$6*D$7+D$9*$C$12)))/1000 -> 0 | E76: =E58*($F20*EXP(-$E28*(E$6*E$7+E$9*$C$12))+$G20*EXP(-$F28*(E$6*E$7+E$9*$C$12)))/1000 -> 0 | F76: =F58*($F20*EXP(-$E28*(F$6*F$7+F$9*$C$12))+$G20*EXP(-$F28*(F$6*F$7+F$9*$C$12)))/1000 -> 0 | G76: =G58*($F20*EXP(-$E28*(G$6*G$7+G$9*$C$12))+$G20*EXP(-$F28*(G$6*G$7+G$9*$C$12)))/1000 -> 0 | H76: =H58*($F20*EXP(-$E28*(H$6*H$7+H$9*$C$12))+$G20*EXP(-$F28*(H$6*H$7+H$9*$C$12)))/1000 -> 0
A77: Ammonium nitrate | C77: =C59*($F21*EXP(-$E29*(C$6*C$7+C$9*$C$12))+$G21*EXP(-$F29*(C$6*C$7+C$9*$C$12)))/1000 -> 1.4750152 | D77: =D59*($F21*EXP(-$E29*(D$6*D$7+D$9*$C$12))+$G21*EXP(-$F29*(D$6*D$7+D$9*$C$12)))/1000 -> 1.7688692 | E77: =E59*($F21*EXP(-$E29*(E$6*E$7+E$9*$C$12))+$G21*EXP(-$F29*(E$6*E$7+E$9*$C$12)))/1000 -> 1.7688692 | F77: =F59*($F21*EXP(-$E29*(F$6*F$7+F$9*$C$12))+$G21*EXP(-$F29*(F$6*F$7+F$9*$C$12)))/1000 -> 1.4750152 | G77: =G59*($F21*EXP(-$E29*(G$6*G$7+G$9*$C$12))+$G21*EXP(-$F29*(G$6*G$7+G$9*$C$12)))/1000 -> 1.5150051 | H77: =H59*($F21*EXP(-$E29*(H$6*H$7+H$9*$C$12))+$G21*EXP(-$F29*(H$6*H$7+H$9*$C$12)))/1000 -> 1.259798
A78: Primary aluminum | C78: =C60*($F22*EXP(-$E30*(C$6*C$7+C$9*$C$12))+$G22*EXP(-$F30*(C$6*C$7+C$9*$C$12)))/1000 -> 0.68445753 | D78: =D60*($F22*EXP(-$E30*(D$6*D$7+D$9*$C$12))+$G22*EXP(-$F30*(D$6*D$7+D$9*$C$12)))/1000 -> 0.71890673 | E78: =E60*($F22*EXP(-$E30*(E$6*E$7+E$9*$C$12))+$G22*EXP(-$F30*(E$6*E$7+E$9*$C$12)))/1000 -> 0.71890673 | F78: =F60*($F22*EXP(-$E30*(F$6*F$7+F$9*$C$12))+$G22*EXP(-$F30*(F$6*F$7+F$9*$C$12)))/1000 -> 0.68445753 | G78: =G60*($F22*EXP(-$E30*(G$6*G$7+G$9*$C$12))+$G22*EXP(-$F30*(G$6*G$7+G$9*$C$12)))/1000 -> 0.69106204 | H78: =H60*($F22*EXP(-$E30*(H$6*H$7+H$9*$C$12))+$G22*EXP(-$F30*(H$6*H$7+H$9*$C$12)))/1000 -> 0.65763503
A79: Total | C79: =SUM(C72:C78) -> 28.534491 | D79: =SUM(D72:D78) -> 31.327973 | E79: =SUM(E72:E78) -> 31.327973 | F79: =SUM(F72:F78) -> 28.534491 | G79: =SUM(G72:G78) -> 29.62936 | H79: =SUM(H72:H78) -> 26.592461
A80: Step 5. Emission intensity after policy (t per t of product)
A81: DRI-EAF steel | C81: =$E16*EXP($C$10*(C$6+C$9*$C$12))+$F16*EXP(-$E24*(C$6*C$7+C$9*$C$12))+$G16*EXP(-$F24*(C$6*C$7+C$9*$C$12)) -> 0.54473645 | D81: =$E16*EXP($C$10*(D$6+D$9*$C$12))+$F16*EXP(-$E24*(D$6*D$7+D$9*$C$12))+$G16*EXP(-$F24*(D$6*D$7+D$9*$C$12)) -> 0.54726128 | E81: =$E16*EXP($C$10*(E$6+E$9*$C$12))+$F16*EXP(-$E24*(E$6*E$7+E$9*$C$12))+$G16*EXP(-$F24*(E$6*E$7+E$9*$C$12)) -> 0.54726128 | F81: =$E16*EXP($C$10*(F$6+F$9*$C$12))+$F16*EXP(-$E24*(F$6*F$7+F$9*$C$12))+$G16*EXP(-$F24*(F$6*F$7+F$9*$C$12)) -> 0.54473645 | G81: =$E16*EXP($C$10*(G$6+G$9*$C$12))+$F16*EXP(-$E24*(G$6*G$7+G$9*$C$12))+$G16*EXP(-$F24*(G$6*G$7+G$9*$C$12)) -> 0.54473645 | H81: =$E16*EXP($C$10*(H$6+H$9*$C$12))+$F16*EXP(-$E24*(H$6*H$7+H$9*$C$12))+$G16*EXP(-$F24*(H$6*H$7+H$9*$C$12)) -> 0.48740146 | I81: σ = 1000 (kt to Mt) × (E^f + E^p) ÷ Y: emissions per tonne after the responses.
A82: Scrap-EAF steel | C82: =$E17*EXP($C$10*(C$6+C$9*$C$12))+$F17*EXP(-$E25*(C$6*C$7+C$9*$C$12))+$G17*EXP(-$F25*(C$6*C$7+C$9*$C$12)) -> 0.082600651 | D82: =$E17*EXP($C$10*(D$6+D$9*$C$12))+$F17*EXP(-$E25*(D$6*D$7+D$9*$C$12))+$G17*EXP(-$F25*(D$6*D$7+D$9*$C$12)) -> 0.084016978 | E82: =$E17*EXP($C$10*(E$6+E$9*$C$12))+$F17*EXP(-$E25*(E$6*E$7+E$9*$C$12))+$G17*EXP(-$F25*(E$6*E$7+E$9*$C$12)) -> 0.084016978 | F82: =$E17*EXP($C$10*(F$6+F$9*$C$12))+$F17*EXP(-$E25*(F$6*F$7+F$9*$C$12))+$G17*EXP(-$F25*(F$6*F$7+F$9*$C$12)) -> 0.082600651 | G82: =$E17*EXP($C$10*(G$6+G$9*$C$12))+$F17*EXP(-$E25*(G$6*G$7+G$9*$C$12))+$G17*EXP(-$F25*(G$6*G$7+G$9*$C$12)) -> 0.082600651 | H82: =$E17*EXP($C$10*(H$6+H$9*$C$12))+$F17*EXP(-$E25*(H$6*H$7+H$9*$C$12))+$G17*EXP(-$F25*(H$6*H$7+H$9*$C$12)) -> 0.076908623
A83: Gray clinker | C83: =$E18*EXP($C$10*(C$6+C$9*$C$12))+$F18*EXP(-$E26*(C$6*C$7+C$9*$C$12))+$G18*EXP(-$F26*(C$6*C$7+C$9*$C$12)) -> 0.78198291 | D83: =$E18*EXP($C$10*(D$6+D$9*$C$12))+$F18*EXP(-$E26*(D$6*D$7+D$9*$C$12))+$G18*EXP(-$F26*(D$6*D$7+D$9*$C$12)) -> 0.8167493 | E83: =$E18*EXP($C$10*(E$6+E$9*$C$12))+$F18*EXP(-$E26*(E$6*E$7+E$9*$C$12))+$G18*EXP(-$F26*(E$6*E$7+E$9*$C$12)) -> 0.8167493 | F83: =$E18*EXP($C$10*(F$6+F$9*$C$12))+$F18*EXP(-$E26*(F$6*F$7+F$9*$C$12))+$G18*EXP(-$F26*(F$6*F$7+F$9*$C$12)) -> 0.78198291 | G83: =$E18*EXP($C$10*(G$6+G$9*$C$12))+$F18*EXP(-$E26*(G$6*G$7+G$9*$C$12))+$G18*EXP(-$F26*(G$6*G$7+G$9*$C$12)) -> 0.78198291 | H83: =$E18*EXP($C$10*(H$6+H$9*$C$12))+$F18*EXP(-$E26*(H$6*H$7+H$9*$C$12))+$G18*EXP(-$F26*(H$6*H$7+H$9*$C$12)) -> 0.71927504
A84: Ammonia | C84: =$E19*EXP($C$10*(C$6+C$9*$C$12))+$F19*EXP(-$E27*(C$6*C$7+C$9*$C$12))+$G19*EXP(-$F27*(C$6*C$7+C$9*$C$12)) -> 1.7615764 | D84: =$E19*EXP($C$10*(D$6+D$9*$C$12))+$F19*EXP(-$E27*(D$6*D$7+D$9*$C$12))+$G19*EXP(-$F27*(D$6*D$7+D$9*$C$12)) -> 1.7615764 | E84: =$E19*EXP($C$10*(E$6+E$9*$C$12))+$F19*EXP(-$E27*(E$6*E$7+E$9*$C$12))+$G19*EXP(-$F27*(E$6*E$7+E$9*$C$12)) -> 1.7615764 | F84: =$E19*EXP($C$10*(F$6+F$9*$C$12))+$F19*EXP(-$E27*(F$6*F$7+F$9*$C$12))+$G19*EXP(-$F27*(F$6*F$7+F$9*$C$12)) -> 1.7615764 | G84: =$E19*EXP($C$10*(G$6+G$9*$C$12))+$F19*EXP(-$E27*(G$6*G$7+G$9*$C$12))+$G19*EXP(-$F27*(G$6*G$7+G$9*$C$12)) -> 1.7615764 | H84: =$E19*EXP($C$10*(H$6+H$9*$C$12))+$F19*EXP(-$E27*(H$6*H$7+H$9*$C$12))+$G19*EXP(-$F27*(H$6*H$7+H$9*$C$12)) -> 1.5714388
A85: Urea | C85: =$E20*EXP($C$10*(C$6+C$9*$C$12))+$F20*EXP(-$E28*(C$6*C$7+C$9*$C$12))+$G20*EXP(-$F28*(C$6*C$7+C$9*$C$12)) -> 0.10008957 | D85: =$E20*EXP($C$10*(D$6+D$9*$C$12))+$F20*EXP(-$E28*(D$6*D$7+D$9*$C$12))+$G20*EXP(-$F28*(D$6*D$7+D$9*$C$12)) -> 0.10008957 | E85: =$E20*EXP($C$10*(E$6+E$9*$C$12))+$F20*EXP(-$E28*(E$6*E$7+E$9*$C$12))+$G20*EXP(-$F28*(E$6*E$7+E$9*$C$12)) -> 0.10008957 | F85: =$E20*EXP($C$10*(F$6+F$9*$C$12))+$F20*EXP(-$E28*(F$6*F$7+F$9*$C$12))+$G20*EXP(-$F28*(F$6*F$7+F$9*$C$12)) -> 0.10008957 | G85: =$E20*EXP($C$10*(G$6+G$9*$C$12))+$F20*EXP(-$E28*(G$6*G$7+G$9*$C$12))+$G20*EXP(-$F28*(G$6*G$7+G$9*$C$12)) -> 0.10008957 | H85: =$E20*EXP($C$10*(H$6+H$9*$C$12))+$F20*EXP(-$E28*(H$6*H$7+H$9*$C$12))+$G20*EXP(-$F28*(H$6*H$7+H$9*$C$12)) -> 0.089286294
A86: Ammonium nitrate | C86: =$E21*EXP($C$10*(C$6+C$9*$C$12))+$F21*EXP(-$E29*(C$6*C$7+C$9*$C$12))+$G21*EXP(-$F29*(C$6*C$7+C$9*$C$12)) -> 0.9494089 | D86: =$E21*EXP($C$10*(D$6+D$9*$C$12))+$F21*EXP(-$E29*(D$6*D$7+D$9*$C$12))+$G21*EXP(-$F29*(D$6*D$7+D$9*$C$12)) -> 1.0945021 | E86: =$E21*EXP($C$10*(E$6+E$9*$C$12))+$F21*EXP(-$E29*(E$6*E$7+E$9*$C$12))+$G21*EXP(-$F29*(E$6*E$7+E$9*$C$12)) -> 1.0945021 | F86: =$E21*EXP($C$10*(F$6+F$9*$C$12))+$F21*EXP(-$E29*(F$6*F$7+F$9*$C$12))+$G21*EXP(-$F29*(F$6*F$7+F$9*$C$12)) -> 0.9494089 | G86: =$E21*EXP($C$10*(G$6+G$9*$C$12))+$F21*EXP(-$E29*(G$6*G$7+G$9*$C$12))+$G21*EXP(-$F29*(G$6*G$7+G$9*$C$12)) -> 0.9494089 | H86: =$E21*EXP($C$10*(H$6+H$9*$C$12))+$F21*EXP(-$E29*(H$6*H$7+H$9*$C$12))+$G21*EXP(-$F29*(H$6*H$7+H$9*$C$12)) -> 0.81468277
A87: Primary aluminum | C87: =$E22*EXP($C$10*(C$6+C$9*$C$12))+$F22*EXP(-$E30*(C$6*C$7+C$9*$C$12))+$G22*EXP(-$F30*(C$6*C$7+C$9*$C$12)) -> 2.4136387 | D87: =$E22*EXP($C$10*(D$6+D$9*$C$12))+$F22*EXP(-$E30*(D$6*D$7+D$9*$C$12))+$G22*EXP(-$F30*(D$6*D$7+D$9*$C$12)) -> 2.5075916 | E87: =$E22*EXP($C$10*(E$6+E$9*$C$12))+$F22*EXP(-$E30*(E$6*E$7+E$9*$C$12))+$G22*EXP(-$F30*(E$6*E$7+E$9*$C$12)) -> 2.5075916 | F87: =$E22*EXP($C$10*(F$6+F$9*$C$12))+$F22*EXP(-$E30*(F$6*F$7+F$9*$C$12))+$G22*EXP(-$F30*(F$6*F$7+F$9*$C$12)) -> 2.4136387 | G87: =$E22*EXP($C$10*(G$6+G$9*$C$12))+$F22*EXP(-$E30*(G$6*G$7+G$9*$C$12))+$G22*EXP(-$F30*(G$6*G$7+G$9*$C$12)) -> 2.4136387 | H87: =$E22*EXP($C$10*(H$6+H$9*$C$12))+$F22*EXP(-$E30*(H$6*H$7+H$9*$C$12))+$G22*EXP(-$F30*(H$6*H$7+H$9*$C$12)) -> 2.311484
A88: Step 6. Egyptian carbon paid per tonne, net of any refund (US$/t)
A89: DRI-EAF steel | C89: =C$6*C63*1000/C54+C$6*C$7*C72*1000/C54-C$8*C$6*($E16+C$7*($F16+$G16)) -> 10.894729 | D89: =D$6*D63*1000/D54+D$6*D$7*D72*1000/D54-D$8*D$6*($E16+D$7*($F16+$G16)) -> 10.187205 | E89: =E$6*E63*1000/E54+E$6*E$7*E72*1000/E54-E$8*E$6*($E16+E$7*($F16+$G16)) -> 10.187205 | F89: =F$6*F63*1000/F54+F$6*F$7*F72*1000/F54-F$8*F$6*($E16+F$7*($F16+$G16)) -> 10.894729 | G89: =G$6*G63*1000/G54+G$6*G$7*G72*1000/G54-G$8*G$6*($E16+G$7*($F16+$G16)) -> -1.2831068 | H89: =H$6*H63*1000/H54+H$6*H$7*H72*1000/H54-H$8*H$6*($E16+H$7*($F16+$G16)) -> 9.7480292 | I89: Calculated as: price × fuel emissions per tonne + process price × process emissions per tonne - refund (refund share × price × baseline EF). This is what the CBAM can credit.
A90: Scrap-EAF steel | C90: =C$6*C64*1000/C55+C$6*C$7*C73*1000/C55-C$8*C$6*($E17+C$7*($F17+$G17)) -> 1.652013 | D90: =D$6*D64*1000/D55+D$6*D$7*D73*1000/D55-D$8*D$6*($E17+D$7*($F17+$G17)) -> 0.80071657 | E90: =E$6*E64*1000/E55+E$6*E$7*E73*1000/E55-E$8*E$6*($E17+E$7*($F17+$G17)) -> 0.80071657 | F90: =F$6*F64*1000/F55+F$6*F$7*F73*1000/F55-F$8*F$6*($E17+F$7*($F17+$G17)) -> 1.652013 | G90: =G$6*G64*1000/G55+G$6*G$7*G73*1000/G55-G$8*G$6*($E17+G$7*($F17+$G17)) -> -0.12520998 | H90: =H$6*H64*1000/H55+H$6*H$7*H73*1000/H55-H$8*H$6*($E17+H$7*($F17+$G17)) -> 1.5381725
A91: Gray clinker | C91: =C$6*C65*1000/C56+C$6*C$7*C74*1000/C56-C$8*C$6*($E18+C$7*($F18+$G18)) -> 15.639658 | D91: =D$6*D65*1000/D56+D$6*D$7*D74*1000/D56-D$8*D$6*($E18+D$7*($F18+$G18)) -> 5.5944629 | E91: =E$6*E65*1000/E56+E$6*E$7*E74*1000/E56-E$8*E$6*($E18+E$7*($F18+$G18)) -> 5.5944629 | F91: =F$6*F65*1000/F56+F$6*F$7*F74*1000/F56-F$8*F$6*($E18+F$7*($F18+$G18)) -> 15.639658 | G91: =G$6*G65*1000/G56+G$6*G$7*G74*1000/G56-G$8*G$6*($E18+G$7*($F18+$G18)) -> -1.3722349 | H91: =H$6*H65*1000/H56+H$6*H$7*H74*1000/H56-H$8*H$6*($E18+H$7*($F18+$G18)) -> 14.385501
A92: Ammonia | C92: =C$6*C66*1000/C57+C$6*C$7*C75*1000/C57-C$8*C$6*($E19+C$7*($F19+$G19)) -> 35.231529 | D92: =D$6*D66*1000/D57+D$6*D$7*D75*1000/D57-D$8*D$6*($E19+D$7*($F19+$G19)) -> 35.231529 | E92: =E$6*E66*1000/E57+E$6*E$7*E75*1000/E57-E$8*E$6*($E19+E$7*($F19+$G19)) -> 35.231529 | F92: =F$6*F66*1000/F57+F$6*F$7*F75*1000/F57-F$8*F$6*($E19+F$7*($F19+$G19)) -> 35.231529 | G92: =G$6*G66*1000/G57+G$6*G$7*G75*1000/G57-G$8*G$6*($E19+G$7*($F19+$G19)) -> -4.262871 | H92: =H$6*H66*1000/H57+H$6*H$7*H75*1000/H57-H$8*H$6*($E19+H$7*($F19+$G19)) -> 31.428776
A93: Urea | C93: =C$6*C67*1000/C58+C$6*C$7*C76*1000/C58-C$8*C$6*($E20+C$7*($F20+$G20)) -> 2.0017914 | D93: =D$6*D67*1000/D58+D$6*D$7*D76*1000/D58-D$8*D$6*($E20+D$7*($F20+$G20)) -> 2.0017914 | E93: =E$6*E67*1000/E58+E$6*E$7*E76*1000/E58-E$8*E$6*($E20+E$7*($F20+$G20)) -> 2.0017914 | F93: =F$6*F67*1000/F58+F$6*F$7*F76*1000/F58-F$8*F$6*($E20+F$7*($F20+$G20)) -> 2.0017914 | G93: =G$6*G67*1000/G58+G$6*G$7*G76*1000/G58-G$8*G$6*($E20+G$7*($F20+$G20)) -> -0.24220858 | H93: =H$6*H67*1000/H58+H$6*H$7*H76*1000/H58-H$8*H$6*($E20+H$7*($F20+$G20)) -> 1.7857259
A94: Ammonium nitrate | C94: =C$6*C68*1000/C59+C$6*C$7*C77*1000/C59-C$8*C$6*($E21+C$7*($F21+$G21)) -> 18.988178 | D94: =D$6*D68*1000/D59+D$6*D$7*D77*1000/D59-D$8*D$6*($E21+D$7*($F21+$G21)) -> 2.0017914 | E94: =E$6*E68*1000/E59+E$6*E$7*E77*1000/E59-E$8*E$6*($E21+E$7*($F21+$G21)) -> 2.0017914 | F94: =F$6*F68*1000/F59+F$6*F$7*F77*1000/F59-F$8*F$6*($E21+F$7*($F21+$G21)) -> 18.988178 | G94: =G$6*G68*1000/G59+G$6*G$7*G77*1000/G59-G$8*G$6*($E21+G$7*($F21+$G21)) -> -3.144072 | H94: =H$6*H68*1000/H59+H$6*H$7*H77*1000/H59-H$8*H$6*($E21+H$7*($F21+$G21)) -> 16.293655
A95: Primary aluminum | C95: =C$6*C69*1000/C60+C$6*C$7*C78*1000/C60-C$8*C$6*($E22+C$7*($F22+$G22)) -> 48.272774 | D95: =D$6*D69*1000/D60+D$6*D$7*D78*1000/D60-D$8*D$6*($E22+D$7*($F22+$G22)) -> 2.2019706 | E95: =E$6*E69*1000/E60+E$6*E$7*E78*1000/E60-E$8*E$6*($E22+E$7*($F22+$G22)) -> 2.2019706 | F95: =F$6*F69*1000/F60+F$6*F$7*F78*1000/F60-F$8*F$6*($E22+F$7*($F22+$G22)) -> 48.272774 | G95: =G$6*G69*1000/G60+G$6*G$7*G78*1000/G60-G$8*G$6*($E22+G$7*($F22+$G22)) -> -2.1454873 | H95: =H$6*H69*1000/H60+H$6*H$7*H78*1000/H60-H$8*H$6*($E22+H$7*($F22+$G22)) -> 46.22968
A97: E. Roll-up: the totals the Calculations sheet uses
A98: Each row adds the products up. The Calculations sheet reads these rows only.
A99: Fuel emissions after policy | B99: Mt | C99: =SUM(C63:C69) -> 28.872276 | D99: =SUM(D63:D69) -> 29.216216 | E99: =SUM(E63:E69) -> 29.216216 | F99: =SUM(F63:F69) -> 28.872276 | G99: =SUM(G63:G69) -> 29.862083 | H99: =SUM(H63:H69) -> 25.755915 | I99: Total of step 3. Includes the fund shadow price.
A100: Process emissions after policy | B100: Mt | C100: =SUM(C72:C78) -> 28.534491 | D100: =SUM(D72:D78) -> 31.327973 | E100: =SUM(E72:E78) -> 31.327973 | F100: =SUM(F72:F78) -> 28.534491 | G100: =SUM(G72:G78) -> 29.62936 | H100: =SUM(H72:H78) -> 26.592461 | I100: Total of step 4. Includes the fund shadow price.
A101: Fuel emissions at baseline intensity, policy output | B101: Mt | C101: =SUMPRODUCT(C54:C60,$E$16:$E$22)/1000 -> 32.365703 | D101: =SUMPRODUCT(D54:D60,$E$16:$E$22)/1000 -> 32.751259 | E101: =SUMPRODUCT(E54:E60,$E$16:$E$22)/1000 -> 32.751259 | F101: =SUMPRODUCT(F54:F60,$E$16:$E$22)/1000 -> 32.365703 | G101: =SUMPRODUCT(G54:G60,$E$16:$E$22)/1000 -> 33.475273 | H101: =SUMPRODUCT(H54:H60,$E$16:$E$22)/1000 -> 32.365703 | I101: Policy output × baseline fuel EF ÷ 1000 (kt to Mt). What fuel emissions would be if only output had changed.
A102: Process emissions at baseline intensity, policy output | B102: Mt | C102: =SUMPRODUCT(C54:C60,$F$16:$F$22+$G$16:$G$22)/1000 -> 30.631807 | D102: =SUMPRODUCT(D54:D60,$F$16:$F$22+$G$16:$G$22)/1000 -> 31.327973 | E102: =SUMPRODUCT(E54:E60,$F$16:$F$22+$G$16:$G$22)/1000 -> 31.327973 | F102: =SUMPRODUCT(F54:F60,$F$16:$F$22+$G$16:$G$22)/1000 -> 30.631807 | G102: =SUMPRODUCT(G54:G60,$F$16:$F$22+$G$16:$G$22)/1000 -> 31.806332 | H102: =SUMPRODUCT(H54:H60,$F$16:$F$22+$G$16:$G$22)/1000 -> 30.631807 | I102: Policy output × baseline process EF (σ^np + σ^no) ÷ 1000 (kt to Mt).
A103: EU exports × intensity after policy | B103: kt CO2 | C103: =SUMPRODUCT($D$24:$D$30,C81:C87) -> 1748.036 | D103: =SUMPRODUCT($D$24:$D$30,D81:D87) -> 1802.8186 | E103: =SUMPRODUCT($D$24:$D$30,E81:E87) -> 1802.8186 | F103: =SUMPRODUCT($D$24:$D$30,F81:F87) -> 1748.036 | G103: =SUMPRODUCT($D$24:$D$30,G81:G87) -> 1748.036 | H103: =SUMPRODUCT($D$24:$D$30,H81:H87) -> 1603.0228 | I103: Σ EU exports × step 5 intensity. Divided by total exports gives the aggregate intensity of EU exports.
A104: EU exports × carbon paid per tonne | B104: US$k | C104: =SUMPRODUCT($D$24:$D$30,C89:C95) -> 34960.72 | D104: =SUMPRODUCT($D$24:$D$30,D89:D95) -> 17439.606 | E104: =SUMPRODUCT($D$24:$D$30,E89:E95) -> 17439.606 | F104: =SUMPRODUCT($D$24:$D$30,F89:F95) -> 34960.72 | G104: =SUMPRODUCT($D$24:$D$30,G89:G95) -> -3205.7726 | H104: =SUMPRODUCT($D$24:$D$30,H89:H95) -> 32060.456 | I104: Σ EU exports × step 6 carbon paid. Divided by total exports gives the aggregate carbon paid per tonne.
A105: EU exports × output index | B105: kt | C105: =SUMPRODUCT($D$24:$D$30,C54:C60/$C$34:$C$40) -> 3299.7253 | D105: =SUMPRODUCT($D$24:$D$30,D54:D60/$C$34:$C$40) -> 3321.2957 | E105: =SUMPRODUCT($D$24:$D$30,E54:E60/$C$34:$C$40) -> 3321.2957 | F105: =SUMPRODUCT($D$24:$D$30,F54:F60/$C$34:$C$40) -> 3299.7253 | G105: =SUMPRODUCT($D$24:$D$30,G54:G60/$C$34:$C$40) -> 3347 | H105: =SUMPRODUCT($D$24:$D$30,H54:H60/$C$34:$C$40) -> 3299.7253 | I105: Σ EU exports × (policy output ÷ baseline output). Exports are assumed to move with output. Divided by total exports gives the export volume index.
...

Sheet Data
A1: Include | B1: Country | C1: Scenario | D1: CPATIndicator | E1: CPATCode | F1: MTCode | G1: Tab | H1: Variable | I1: Unit | J1: SubScenario | K1: 2022 | L1: 2023 | M1: 2024 | N1: 2025 | O1: 2026 | P1: 2027 | Q1: 2028 | R1: 2029 | S1: 2030 | T1: 2031 | U1: 2032 | V1: 2033 | W1: 2034 | X1: 2035 | Y1: 2036 | Z1: 2037 | AA1: 2038 | AB1: 2039 | AC1: 2040 | AD1: 2041 | AF1: Year read by the lookups | AG1: 2030
B2: Egypt | C2: EGY1A | D2: Emissions coverage | E2: egy.mit.co2cov.2 | F2: egy.mit.co2cov.2_EGY1A | G2: mit | H2: co2cov | I2: pc | J2: 2 | K2: 0 | L2: 0 | M2: 0 | N2: 0 | O2: 0.98816 | P2: 0.98743 | Q2: 0.98751 | R2: 0.98747 | S2: 0.98757 | T2: 0.98764 | U2: 0.98774 | V2: 0.98783 | W2: 0.98794 | X2: 0.98804 | Y2: 0.98815 | Z2: 0.98826 | AA2: 0.98838 | AB2: 0.98852 | AC2: 0.98867 | AD2: 0.98879 | AF2: Raw CPAT results: paste the full export (all columns, header in row 1) over columns A to AD. Lookups match the MTCode in column F and read the year in AG1 from the header row.
B3: Egypt | C3: EGY1A | D3: Carbon tax trajectory | E3: egy.mit.cptraj.2 | F3: egy.mit.cptraj.2_EGY1A | G3: mit | H3: cptraj | I3: usdtco2 | J3: 2 | K3: 0 | L3: 0 | M3: 0 | N3: 0 | O3: 20 | P3: 20 | Q3: 20 | R3: 20 | S3: 20 | T3: 20 | U3: 20 | V3: 20 | W3: 20 | X3: 20 | Y3: 20 | Z3: 20 | AA3: 20 | AB3: 20 | AC3: 20 | AD3: 20
B4: Egypt | C4: EGY1A | D4: Effective carbon tax trajectory | E4: egy.mit.eff.cptraj.2 | F4: egy.mit.eff.cptraj.2_EGY1A | G4: mit | H4: effcptraj | I4: usdtco2 | J4: 2 | K4: 0 | L4: 0 | M4: 0 | N4: 0 | O4: 19.763 | P4: 19.749 | Q4: 19.75 | R4: 19.749 | S4: 19.751 | T4: 19.753 | U4: 19.755 | V4: 19.757 | W4: 19.759 | X4: 19.761 | Y4: 19.763 | Z4: 19.765 | AA4: 19.768 | AB4: 19.77 | AC4: 19.773 | AD4: 19.776
B5: Egypt | C5: EGY1A | D5: ETS Trajector\y | E5: egy.mit.etstraj.2 | F5: egy.mit.etstraj.2_EGY1A | G5: mit | H5: etstraj | I5: usdtco2 | J5: 2 | K5: 0 | L5: 0 | M5: 0 | N5: 0 | O5: 0 | P5: 0 | Q5: 0 | R5: 0 | S5: 0 | T5: 0 | U5: 0 | V5: 0 | W5: 0 | X5: 0 | Y5: 0 | Z5: 0 | AA5: 0 | AB5: 0 | AC5: 0 | AD5: 0
B6: Egypt | C6: EGY1A | D6: Emissions covered by sector: power sector | E6: egy.mit.co2cov.pow.cont.2 | F6: egy.mit.co2cov.pow.cont.2_EGY1A | G6: mit | H6: co2cov | I6: pc | J6: 2 | K6: 0 | L6: 0 | M6: 0 | N6: 0 | O6: 0.41588 | P6: 0.37506 | Q6: 0.37217 | R6: 0.36238 | S6: 0.35499 | T6: 0.34396 | U6: 0.3344 | V6: 0.32517 | W6: 0.31744 | X6: 0.31089 | Y6: 0.30582 | Z6: 0.30217 | AA6: 0.29995 | AB6: 0.29931 | AC6: 0.29971 | AD6: 0.29987
B7: Egypt | C7: EGY1A | D7: Emissions covered, transport sector | E7: egy.mit.co2cov.tra.cont.2 | F7: egy.mit.co2cov.tra.cont.2_EGY1A | G7: mit | H7: co2cov | I7: pc | J7: 2 | K7: 0 | L7: 0 | M7: 0 | N7: 0 | O7: 0.20507 | P7: 0.22464 | Q7: 0.23215 | R7: 0.24313 | S7: 0.25567 | T7: 0.27133 | U7: 0.28647 | V7: 0.30132 | W7: 0.31507 | X7: 0.32769 | Y7: 0.33898 | Z7: 0.34908 | AA7: 0.35805 | AB7: 0.36579 | AC7: 0.37257 | AD7: 0.37897
B8: Egypt | C8: EGY1A | D8: Emissions covered, residential sector | E8: egy.mit.co2cov.res.cont.2 | F8: egy.mit.co2cov.res.cont.2_EGY1A | G8: mit | H8: co2cov | I8: pc | J8: 2 | K8: 0 | L8: 0 | M8: 0 | N8: 0 | O8: 0.0811 | P8: 0.08257 | Q8: 0.0797 | R8: 0.07794 | S8: 0.07581 | T8: 0.07391 | U8: 0.07186 | V8: 0.06983 | W8: 0.06773 | X8: 0.06564 | Y8: 0.06355 | Z8: 0.06149 | AA8: 0.05942 | AB8: 0.05734 | AC8: 0.05529 | AD8: 0.05339
B9: Egypt | C9: EGY1A | D9: Emissions covered, industry | E9: egy.mit.co2cov.ind.cont.2 | F9: egy.mit.co2cov.ind.cont.2_EGY1A | G9: mit | H9: co2cov | I9: pc | J9: 2 | K9: 0 | L9: 0 | M9: 0 | N9: 0 | O9: 0.28621 | P9: 0.30527 | Q9: 0.30359 | R9: 0.30412 | S9: 0.30119 | T9: 0.29853 | U9: 0.2951 | V9: 0.29162 | W9: 0.28779 | X9: 0.28391 | Y9: 0.27988 | Z9: 0.27561 | AA9: 0.27106 | AB9: 0.26617 | AC9: 0.26118 | AD9: 0.25664
B10: Egypt | C10: EGY1A | D10: Emissions covered, other energy use | E10: egy.mit.co2cov.oth.cont.2 | F10: egy.mit.co2cov.oth.cont.2_EGY1A | G10: mit | H10: co2cov | I10: pc | J10: 2 | K10: 0 | L10: 0 | M10: 0 | N10: 0 | O10: 0 | P10: 0 | Q10: 0 | R10: 0 | S10: 0 | T10: 0 | U10: 0 | V10: 0 | W10: 0 | X10: 0 | Y10: 0 | Z10: 0 | AA10: 0 | AB10: 0 | AC10: 0 | AD10: 0
B11: Egypt | C11: EGY1A | D11: Effect on GDP: Baseline GDP growth | E11: egy.mit.gdp.pre.pct.2 | F11: egy.mit.gdp.pre.pct.2_EGY1A | G11: mit | H11: gdp | I11: pc | J11: 2 | K11: 0.06651 | L11: 0.0376 | M11: 0.02399 | N11: 0.04392 | O11: 0.0424 | P11: 0.04829 | Q11: 0.05535 | R11: 0.05227 | S11: 0.04842 | T11: 0.04789 | U11: 0.04736 | V11: 0.04682 | W11: 0.04629 | X11: 0.04576 | Y11: 0.04523 | Z11: 0.0447 | AA11: 0.04417 | AB11: 0.04364 | AC11: 0.0431 | AD11: 0.04257
B12: Egypt | C12: EGY1A | D12: Effect on GDP: - Carbon tax | E12: egy.mit.gdp.exc.pct.2 | F12: egy.mit.gdp.exc.pct.2_EGY1A | G12: mit | H12: gdp | I12: pc | J12: 2 | K12: 0 | L12: 0 | M12: 0 | N12: 0 | O12: -0.00455 | P12: -0.00723 | Q12: -0.00684 | R12: -0.0069 | S12: -0.00623 | T12: -0.00555 | U12: -0.00531 | V12: -0.00484 | W12: -0.0043 | X12: -0.00385 | Y12: -0.0036 | Z12: -0.0036 | AA12: -0.00361 | AB12: -0.00361 | AC12: -0.00351 | AD12: -0.00337
B13: Egypt | C13: EGY1A | D13: Effect on GDP: Personal income tax | E13: egy.mit.gdp.pit.pct.2 | F13: egy.mit.gdp.pit.pct.2_EGY1A | G13: mit | H13: gdp | I13: pc | J13: 2 | K13: 0 | L13: 0 | M13: 0 | N13: 0 | O13: 0 | P13: 0 | Q13: 0 | R13: 0 | S13: 0 | T13: 0 | U13: 0 | V13: 0 | W13: 0 | X13: 0 | Y13: 0 | Z13: 0 | AA13: 0 | AB13: 0 | AC13: 0 | AD13: 0
B14: Egypt | C14: EGY1A | D14: Effect on GDP: Public investment | E14: egy.mit.gdp.inv.pct.2 | F14: egy.mit.gdp.inv.pct.2_EGY1A | G14: mit | H14: gdp | I14: pc | J14: 2 | K14: 0 | L14: 0 | M14: 0 | N14: 0 | O14: 0.00762 | P14: 0.00932 | Q14: 0.009 | R14: 0.0083 | S14: 0.00857 | T14: 0.00942 | U14: 0.0106 | V14: 0.01164 | W14: 0.0137 | X14: 0.01509 | Y14: 0.0163 | Z14: 0.01672 | AA14: 0.01701 | AB14: 0.01736 | AC14: 0.01753 | AD14: 0.0177
... B21: Egypt | C21: EGY1A | D21: Total revenues, % of GDP (policy) | E21: egy.mit.rev.new.pct.2 | F21: egy.mit.rev.new.pct.2_EGY1A | G21: mit | H21: rev | I21: pc | J21: 2 | K21: -0.05845 | L21: -0.04678 | M21: -0.06658 | N21: -0.06182 | O21: -0.0499 | P21: -0.04395 | Q21: -0.04232 | R21: -0.04065 | S21: -0.03945 | T21: -0.03788 | U21: -0.03659 | V21: -0.03523 | W21: -0.03384 | X21: -0.0324 | Y21: -0.03083 | Z21: -0.0292 | AA21: -0.02745 | AB21: -0.02561 | AC21: -0.02398 | AD21: -0.02409
B22: Egypt | C22: EGY1A | D22: Base erosion, % of GDP | E22: egy.mit.ers | F22: egy.mit.ers_EGY1A | J22: 2 | K22: 0 | L22: 2.844543e-05 | M22: 2.4134132e-05 | N22: 2.2817555e-05 | O22: 0.0053636661 | P22: 0.0053659141 | Q22: 0.0046214763 | R22: 0.0044533418 | S22: 0.0043312021 | T22: 0.0043848434 | U22: 0.0044145522 | V22: 0.0044542808 | W22: 0.0044620307 | X22: 0.0044483116 | Y22: 0.0044052265 | Z22: 0.004334692 | AA22: 0.004253877 | AB22: 0.0041590791 | AC22: 0.0040817358 | AD22: 0.0039995942
B23: Egypt | C23: EGY1A | D23: Revenues - Carbon tax, % of GDP | E23: egy.mit.rcp | F23: egy.mit.rcp_EGY1A | J23: 2 | K23: 0 | L23: 0 | M23: 0 | N23: 0 | O23: 0.0070282371 | P23: 0.006701828 | Q23: 0.0067128398 | R23: 0.0066464777 | S23: 0.0066269031 | T23: 0.0065958403 | U23: 0.0065890349 | V23: 0.0065916109 | W23: 0.0066108686 | X23: 0.0066452374 | Y23: 0.0066940648 | Z23: 0.0067584028 | AA23: 0.0068350129 | AB23: 0.0069255174 | AC23: 0.0070254208 | AD23: 0.0071193586
B24: Egypt | C24: EGY1A | D24: Power sector carbon tax revenues | E24: egy.mit.rcp.pow | F24: egy.mit.rcp.pow_EGY1A | J24: 2 | K24: 0 | L24: 0 | M24: 0 | N24: 0 | O24: 0.0029270922 | P24: 0.0025178419 | Q24: 0.002502541 | R24: 0.0024125462 | S24: 0.0023562919 | T24: 0.0022722221 | U24: 0.0022066032 | V24: 0.0021463513 | W24: 0.0021013205 | X24: 0.0020685205 | Y24: 0.0020496382 | Z24: 0.0020444865 | AA24: 0.002052318 | AB24: 0.0020749249 | AC24: 0.0021075771 | AD24: 0.0021368177
B25: Egypt | C25: EGY1A | D25: Transport sector carbon tax revenues | E25: egy.mit.rcp.trs | F25: egy.mit.rcp.trs_EGY1A | J25: 2 | K25: 0 | L25: 0 | M25: 0 | N25: 0 | O25: 0.0015159442 | P25: 0.0015803728 | Q25: 0.0016329483 | R25: 0.0016902768 | S25: 0.0017682525 | T25: 0.0018632853 | U25: 0.0019609651 | V25: 0.0020594437 | W25: 0.0021561355 | X25: 0.0022509149 | Y25: 0.0023427458 | Z25: 0.0024331066 | AA25: 0.0025214725 | AB25: 0.002607871 | AC25: 0.0026924358 | AD25: 0.0027733899
B26: Egypt | C26: EGY1A | D26: Buildings sector carbon tax revenues | E26: egy.mit.rcp.bld | F26: egy.mit.rcp.bld_EGY1A | J26: 2 | K26: 0 | L26: 0 | M26: 0 | N26: 0 | O26: 0.00057080737 | P26: 0.00055429561 | Q26: 0.00053593011 | R26: 0.00051891866 | S26: 0.00050321994 | T26: 0.00048827703 | U26: 0.0004741956 | V26: 0.0004609044 | W26: 0.0004483774 | X26: 0.00043676856 | Y26: 0.00042588811 | Z26: 0.00041603046 | AA26: 0.00040658211 | AB26: 0.00039750716 | AC26: 0.0003888042 | AD26: 0.00038044664
B27: Egypt | C27: EGY1A | D27: Industry sector carbon tax revenues | E27: egy.mit.rcp.ind | F27: egy.mit.rcp.ind_EGY1A | J27: 2 | K27: 0 | L27: 0 | M27: 0 | N27: 0 | O27: 0.0020143933 | P27: 0.0020493177 | Q27: 0.0020414204 | R27: 0.0020247361 | S27: 0.0019991388 | T27: 0.0019720558 | U27: 0.001947271 | V27: 0.0019249114 | W27: 0.0019050352 | X27: 0.0018890334 | Y27: 0.0018757926 | Z27: 0.0018647792 | AA27: 0.0018546403 | AB27: 0.0018452143 | AC27: 0.0018366036 | AD27: 0.0018287044
B28: Egypt | C28: EGY1A | D28: Baseline ln(GDP per capita) | E28: egy.mit.ln.gdppc | F28: egy.mit.ln.gdppc_EGY1A | G28: mit | H28: lngdppc | I28: unitless | J28: 1 | K28: 6.3 | L28: 6.34 | M28: 6.37 | N28: 6.41 | O28: 6.45 | P28: 6.5 | Q28: 6.55 | R28: 6.6 | S28: 6.65 | T28: 6.7 | U28: 6.74 | V28: 6.79 | W28: 6.83 | X28: 6.88 | Y28: 6.92 | Z28: 6.97 | AA28: 7.01 | AB28: 7.05 | AC28: 7.09 | AD28: 7.14
B29: Egypt | C29: EGY1A | D29: Baseline GDP | E29: egy.mit.gdp.pre.lvl.1 | F29: egy.mit.gdp.pre.lvl.1_EGY1A | G29: mit | H29: gdp | I29: usdbn | J29: 1 | K29: 546.97092 | L29: 567.53857 | M29: 581.15269 | N29: 606.67916 | O29: 632.40058 | P29: 662.94058 | Q29: 699.63644 | R29: 736.20368 | S29: 771.84975 | T29: 808.8116 | U29: 847.11364 | V29: 886.77935 | W29: 927.83114 | X29: 970.29029 | Y29: 1014.1768 | Z29: 1059.5094 | AA29: 1106.3053 | AB29: 1154.5801 | AC29: 1204.3479 | AD29: 1255.6209
B30: Egypt | C30: EGY1A | D30: Post-policy GDP | E30: egy.mit.gdp.pst.lvl.2 | F30: egy.mit.gdp.pst.lvl.2_EGY1A | G30: mit | H30: gdp | I30: usdbn | J30: 2 | K30: 546.97092 | L30: 567.53857 | M30: 581.15269 | N30: 606.67916 | O30: 632.40064 | P30: 664.88294 | Q30: 701.01918 | R30: 737.7146 | S30: 772.87859 | T30: 810.61479 | U30: 850.24184 | V30: 891.25848 | W30: 933.85896 | X30: 979.01452 | Y30: 1025.089 | Z30: 1072.388 | AA30: 1120.206 | AB30: 1169.4007 | AC30: 1220.2219 | AD30: 1272.507
B31: Egypt | C31: EGY1A | D31: Population | E31: egy.mit.pop.mn | F31: egy.mit.pop.mn_EGY1A | G31: mit | H31: pop | I31: mn | J31: 1 | K31: 103.6 | L31: 105.2 | M31: 106.6 | N31: 107.9 | O31: 110.058 | P31: 112.25916 | Q31: 114.50434 | R31: 116.79443 | S31: 120.29826 | T31: 125.11019 | U31: 130.1146 | V31: 135.31918 | W31: 140.73195 | X31: 146.36123 | Y31: 152.21568 | Z31: 158.3043 | AA31: 164.63647 | AB31: 171.22193 | AC31: 178.07081 | AD31: 185.19364
B32: Egypt | C32: EGY1A | D32: Total GHG emissions, exc. LULUCF (baseline) | E32: egy.mit.ghg.tot.exc.1 | F32: egy.mit.ghg.tot.exc.1_EGY1A | G32: mit | H32: emis | I32: mtco2e | J32: 1 | K32: 400.912 | L32: 412.105 | M32: 450.924 | N32: 467.515 | O32: 473.648 | P32: 484.763 | Q32: 501.104 | R32: 518.139 | S32: 535.623 | T32: 555.043 | U32: 576.999 | V32: 601.287 | W32: 626.831 | X32: 653.747 | Y32: 682.01 | Z32: 711.827 | AA32: 743.304 | AB32: 776.605 | AC32: 811.925 | AD32: 848.157
B33: Egypt | C33: EGY1A | D33: Total GHG emissions, inc. LULUCF (baseline) | E33: egy.mit.ghg.tot.inc.1 | F33: egy.mit.ghg.tot.inc.1_EGY1A | G33: mit | H33: emis | I33: mtco2e | J33: 1 | K33: 400.912 | L33: 412.105 | M33: 450.924 | N33: 467.515 | O33: 473.648 | P33: 484.763 | Q33: 501.104 | R33: 518.139 | S33: 535.623 | T33: 555.043 | U33: 576.999 | V33: 601.287 | W33: 626.831 | X33: 653.747 | Y33: 682.01 | Z33: 711.827 | AA33: 743.304 | AB33: 776.605 | AC33: 811.925 | AD33: 848.157
B34: Egypt | C34: EGY1A | D34: Energy-related GHG emissions (baseline) | E34: egy.mit.ghg.enr.tot.1 | F34: egy.mit.ghg.enr.tot.1_EGY1A | G34: mit | H34: emis | I34: mtco2e | J34: 1 | K34: 213.939 | L34: 210.133 | M34: 236.548 | N34: 245.532 | O34: 247.516 | P34: 253.847 | Q34: 264.069 | R34: 274.969 | S34: 286.428 | T34: 299.23 | U34: 312.897 | V34: 327.613 | W34: 343.276 | X34: 359.992 | Y34: 377.725 | Z34: 396.674 | AA34: 416.933 | AB34: 438.654 | AC34: 462.022 | AD34: 485.918
B35: Egypt | C35: EGY1A | D35: Industrial processes GHG emissions (baseline) | E35: egy.mit.ghg.ipr.tot.1 | F35: egy.mit.ghg.ipr.tot.1_EGY1A | G35: mit | H35: emis | I35: mtco2e | J35: 1 | K35: 52.2 | L35: 56.903 | M35: 67.059 | N35: 72.5 | O35: 74.569 | P35: 76.99 | Q35: 79.929 | R35: 82.77 | S35: 85.454 | T35: 88.177 | U35: 90.929 | V35: 93.73 | W35: 96.58 | X35: 99.478 | Y35: 102.424 | Z35: 105.418 | AA35: 108.459 | AB35: 111.547 | AC35: 114.681 | AD35: 117.86
B36: Egypt | C36: EGY1A | D36: Agriculture, GHG emissions (baseline) | E36: egy.mit.ghg.agr.tot.1 | F36: egy.mit.ghg.agr.tot.1_EGY1A | G36: mit | H36: emis | I36: mtco2e | J36: 1 | K36: 41.563 | L36: 43.505 | M36: 44.234 | N36: 44.885 | O36: 45.614 | P36: 46.396 | Q36: 47.424 | R36: 48.524 | S36: 49.628 | T36: 50.838 | U36: 52.455 | V36: 54.397 | W36: 56.407 | X36: 58.486 | Y36: 60.638 | Z36: 62.864 | AA36: 65.166 | AB36: 67.548 | AC36: 70.012 | AD36: 72.56
B37: Egypt | C37: EGY1A | D37: Waste GHG emissions (baseline) | E37: egy.mit.ghg.wst.tot.1 | F37: egy.mit.ghg.wst.tot.1_EGY1A | G37: mit | H37: emis | I37: mtco2e | J37: 1 | K37: 93.209 | L37: 101.564 | M37: 103.083 | N37: 104.597 | O37: 105.948 | P37: 107.531 | Q37: 109.682 | R37: 111.875 | S37: 114.113 | T37: 116.798 | U37: 120.718 | V37: 125.546 | W37: 130.568 | X37: 135.791 | Y37: 141.223 | Z37: 146.872 | AA37: 152.746 | AB37: 158.856 | AC37: 165.21 | AD37: 171.819
B38: Egypt | C38: EGY1A | D38: LULUCF, GHG emissions (baseline) | E38: egy.mit.ghg.lucf.tot.1 | F38: egy.mit.ghg.lucf.tot.1_EGY1A | G38: mit | H38: emis | I38: mtco2e | J38: 1 | K38: 0 | L38: 0 | M38: 0 | N38: 0 | O38: 0 | P38: 0 | Q38: 0 | R38: 0 | S38: 0 | T38: 0 | U38: 0 | V38: 0 | W38: 0 | X38: 0 | Y38: 0 | Z38: 0 | AA38: 0 | AB38: 0 | AC38: 0 | AD38: 0
B39: Egypt | C39: EGY1A | D39: Total CO2 emissions - baseline | E39: egy.mit.co2.tot.1 | F39: egy.mit.co2.tot.1_EGY1A | G39: mit | H39: emis | I39: mtco2 | J39: 1 | K39: 307.637 | L39: 315.625 | M39: 350.605 | N39: 364.723 | O39: 369.176 | P39: 378.155 | Q39: 391.945 | R39: 406.364 | S39: 421.246 | T39: 437.519 | U39: 455.457 | V39: 475.305 | W39: 496.254 | X39: 518.414 | Y39: 541.754 | Z39: 566.478 | AA39: 592.682 | AB39: 620.525 | AC39: 650.194 | AD39: 680.584
... B73: Egypt | C73: EGY1A | D73: Energy related CO2 emissions - Other (policy) | E73: egy.mit.co2.oth.2 | F73: egy.mit.co2.oth.2_EGY1A | G73: mit | H73: emis | I73: mtco2 | J73: 2 | K73: 0.294 | L73: 0.268 | M73: 0.317 | N73: 0.417 | O73: 0.316 | P73: 0.376 | Q73: 0.398 | R73: 0.409 | S73: 0.411 | T73: 0.41 | U73: 0.409 | V73: 0.408 | W73: 0.406 | X73: 0.405 | Y73: 0.404 | Z73: 0.403 | AA73: 0.401 | AB73: 0.4 | AC73: 0.399 | AD73: 0.398
B74: Egypt | C74: EGY1A | D74: Change in CO2 emissions - (policy vs. baseline) | E74: egy.mit.co2.tot.red.pct | F74: egy.mit.co2.tot.red.pct_EGY1A | G74: mit | H74: co2red | I74: mtco2 | J74: t | K74: 0 | L74: 0 | M74: 0 | N74: 0 | O74: -0.086 | P74: -0.097 | Q74: -0.086 | R74: -0.085 | S74: -0.083 | T74: -0.085 | U74: -0.084 | V74: -0.084 | W74: -0.082 | X74: -0.08 | Y74: -0.077 | Z74: -0.074 | AA74: -0.07 | AB74: -0.066 | AC74: -0.062 | AD74: -0.058
B75: Egypt | C75: EGY1A | D75: Total GHG emissions, excl LULUCF - baseline | E75: egy.mit.ghg.tot.exc.fuel.1 | F75: egy.mit.ghg.tot.exc.fuel.1_EGY1A | G75: mit | H75: emis | I75: mtco2e | J75: 1 | K75: 400.912 | L75: 412.105 | M75: 450.924 | N75: 467.515 | O75: 473.648 | P75: 484.763 | Q75: 501.104 | R75: 518.139 | S75: 535.623 | T75: 555.043 | U75: 576.999 | V75: 601.287 | W75: 626.831 | X75: 653.747 | Y75: 682.01 | Z75: 711.827 | AA75: 743.304 | AB75: 776.605 | AC75: 811.925 | AD75: 848.157
B76: Egypt | C76: EGY1A | D76: Carbon dioxide (CO2) - baseline | E76: egy.mit.co2.tot.1 | F76: egy.mit.co2.tot.1_EGY1A | G76: mit | H76: emis | I76: mtco2 | J76: 1 | K76: 307.637 | L76: 315.625 | M76: 350.605 | N76: 364.723 | O76: 369.176 | P76: 378.155 | Q76: 391.945 | R76: 406.364 | S76: 421.246 | T76: 437.519 | U76: 455.457 | V76: 475.305 | W76: 496.254 | X76: 518.414 | Y76: 541.754 | Z76: 566.478 | AA76: 592.682 | AB76: 620.525 | AC76: 650.194 | AD76: 680.584
B77: Egypt | C77: EGY1A | D77: Methane (CH4) - baseline | E77: egy.mit.ch4.tot.1 | F77: egy.mit.ch4.tot.1_EGY1A | G77: mit | H77: emis | I77: mtco2e | J77: 1 | K77: 53.088 | L77: 55.678 | M77: 56.592 | N77: 57.34 | O77: 58.083 | P77: 59.234 | Q77: 60.428 | R77: 61.667 | S77: 62.922 | T77: 64.748 | U77: 67.185 | V77: 69.717 | W77: 72.347 | X77: 75.078 | Y77: 77.915 | Z77: 80.859 | AA77: 83.917 | AB77: 87.093 | AC77: 90.39 | AD77: 93.815
B78: Egypt | C78: EGY1A | D78: Nitrous oxide (N2O) - baseline | E78: egy.mit.nox.tot.1 | F78: egy.mit.nox.tot.1_EGY1A | G78: mit | H78: emis | I78: mtco2e | J78: 1 | K78: 28.488 | L78: 28.577 | M78: 29.32 | N78: 29.875 | O78: 30.368 | P78: 30.834 | Q78: 31.558 | R78: 32.325 | S78: 33.096 | T78: 33.832 | U78: 34.822 | V78: 36.127 | W78: 37.48 | X78: 38.883 | Y78: 40.336 | Z78: 41.842 | AA78: 43.404 | AB78: 45.023 | AC78: 46.703 | AD78: 48.438
B79: Egypt | C79: EGY1A | D79: F-gases (PFCs, HFCs, SF6, NF3) - baseline | E79: egy.mit.fga.tot.1 | F79: egy.mit.fga.tot.1_EGY1A | G79: mit | H79: emis | I79: mtco2e | J79: 1 | K79: 11.699 | L79: 12.225 | M79: 14.407 | N79: 15.576 | O79: 16.02 | P79: 16.54 | Q79: 17.172 | R79: 17.782 | S79: 18.359 | T79: 18.944 | U79: 19.535 | V79: 20.137 | W79: 20.749 | X79: 21.372 | Y79: 22.005 | Z79: 22.648 | AA79: 23.301 | AB79: 23.965 | AC79: 24.638 | AD79: 25.321
B80: Egypt | C80: EGY1A | D80: Total GHG emissions, excl LULUCF - policy | E80: egy.mit.ghg.tot.exc.fuel.2 | F80: egy.mit.ghg.tot.exc.fuel.2_EGY1A | G80: mit | H80: emis | I80: mtco2e | J80: 2 | K80: 400.912 | L80: 411.973 | M80: 450.796 | N80: 467.39 | O80: 438.859 | P80: 445.284 | Q80: 464.631 | R80: 480.832 | S80: 497.866 | T80: 515.321 | U80: 535.901 | V80: 558.702 | W80: 583.166 | X80: 609.419 | Y80: 637.527 | Z80: 667.64 | AA80: 699.662 | AB80: 733.796 | AC80: 769.927 | AD80: 807.196
B81: Egypt | C81: EGY1A | D81: Carbon dioxide (CO2) - policy | E81: egy.mit.co2.tot.2 | F81: egy.mit.co2.tot.2_EGY1A | G81: mit | H81: emis | I81: mtco2 | J81: 2 | K81: 307.637 | L81: 315.493 | M81: 350.477 | N81: 364.598 | O81: 337.551 | P81: 341.489 | Q81: 358.149 | R81: 371.706 | S81: 386.172 | T81: 400.546 | U81: 417.134 | V81: 435.499 | W81: 455.343 | X81: 476.771 | Y81: 499.839 | Z81: 524.711 | AA81: 551.295 | AB81: 579.795 | AC81: 610.079 | AD81: 641.286
B82: Egypt | C82: EGY1A | D82: Methane (CH4) - policy | E82: egy.mit.ch4.tot.2 | F82: egy.mit.ch4.tot.2_EGY1A | G82: mit | H82: emis | I82: mtco2e | J82: 2 | K82: 53.088 | L82: 55.678 | M82: 56.592 | N82: 57.34 | O82: 58.042 | P82: 59.192 | Q82: 60.398 | R82: 61.634 | S82: 62.889 | T82: 64.712 | U82: 67.151 | V82: 69.688 | W82: 72.323 | X82: 75.061 | Y82: 77.909 | Z82: 80.863 | AA82: 83.93 | AB82: 87.112 | AC82: 90.416 | AD82: 93.846
B83: Egypt | C83: EGY1A | D83: Nitrous oxide (N2O) - policy | E83: egy.mit.nox.tot.2 | F83: egy.mit.nox.tot.2_EGY1A | G83: mit | H83: emis | I83: mtco2e | J83: 2 | K83: 28.488 | L83: 28.577 | M83: 29.321 | N83: 29.876 | O83: 30.038 | P83: 30.497 | Q83: 31.253 | R83: 32.014 | S83: 32.781 | T83: 33.502 | U83: 34.487 | V83: 35.79 | W83: 37.145 | X83: 38.555 | Y83: 40.025 | Z83: 41.55 | AA83: 43.131 | AB83: 44.767 | AC83: 46.464 | AD83: 48.219
B84: Egypt | C84: EGY1A | D84: F-gases (PFCs, HFCs, SF6, NF3) - policy | E84: egy.mit.fga.tot.2 | F84: egy.mit.fga.tot.2_EGY1A | G84: mit | H84: emis | I84: mtco2e | J84: 2 | K84: 11.699 | L84: 12.225 | M84: 14.407 | N84: 15.576 | O84: 13.228 | P84: 14.108 | Q84: 14.831 | R84: 15.479 | S84: 16.023 | T84: 16.563 | U84: 17.129 | V84: 17.725 | W84: 18.354 | X84: 19.033 | Y84: 19.754 | Z84: 20.516 | AA84: 21.306 | AB84: 22.123 | AC84: 22.969 | AD84: 23.843
B85: Egypt | C85: EGY1A | D85: Total methane, incl. LULUCF (baseline) | E85: egy.mit.ghg.tot.inc.ch4.1 | F85: egy.mit.ghg.tot.inc.ch4.1_EGY1A | G85: mit | H85: emis | I85: mtco2e | J85: 1 | K85: 53.088 | L85: 55.678 | M85: 56.592 | N85: 57.34 | O85: 58.083 | P85: 59.234 | Q85: 60.428 | R85: 61.667 | S85: 62.922 | T85: 64.748 | U85: 67.185 | V85: 69.717 | W85: 72.347 | X85: 75.078 | Y85: 77.915 | Z85: 80.859 | AA85: 83.917 | AB85: 87.093 | AC85: 90.39 | AD85: 93.815
B86: Egypt | C86: EGY1A | D86: Total methane, excl. LULUCF (baseline) | E86: egy.mit.ghg.tot.exc.ch4.1 | F86: egy.mit.ghg.tot.exc.ch4.1_EGY1A | G86: mit | H86: emis | I86: mtco2e | J86: 1 | K86: 53.088 | L86: 55.678 | M86: 56.592 | N86: 57.34 | O86: 58.083 | P86: 59.234 | Q86: 60.428 | R86: 61.667 | S86: 62.922 | T86: 64.748 | U86: 67.185 | V86: 69.717 | W86: 72.347 | X86: 75.078 | Y86: 77.915 | Z86: 80.859 | AA86: 83.917 | AB86: 87.093 | AC86: 90.39 | AD86: 93.815
... B105: Egypt | C105: EGY1A | D105: Change in GHG emissions exc LULUCF - (policy vs. baseline) | E105: egy.mit.ghg.tot.inc.red.pct | F105: egy.mit.ghg.tot.inc.red.pct_EGY1A | G105: mit | H105: ghgchange | I105: pc | J105: 2 | K105: 0 | L105: 0 | M105: 0 | N105: 0 | O105: -0.073 | P105: -0.081 | Q105: -0.073 | R105: -0.072 | S105: -0.07 | T105: -0.072 | U105: -0.071 | V105: -0.071 | W105: -0.07 | X105: -0.068 | Y105: -0.065 | Z105: -0.062 | AA105: -0.059 | AB105: -0.055 | AC105: -0.052 | AD105: -0.048
B106: Egypt | C106: EGY1A | D106: NDC option | E106: egy.mit.ndc.option | F106: egy.mit.ndc.option_EGY1A | G106: mit | H106: ndcoption | I106: text | J106: 1 | K106: Latest*
B107: Egypt | D107: NDC target year | E107: egy.mit.ndc.targetyear | F107: egy.mit.ndc.targetyear_EGY1A | G107: mit | H107: ndctargetyear | I107: text | J107: 1 | K107: 1
B108: Egypt | C108: EGY1A | D108: NDC, description - long | E108: egy.mit.ndc.desc.lng | F108: egy.mit.ndc.desc.lng_EGY1A | G108: mit | H108: ndcdesclong | I108: text | J108: 1 | K108: =#VALUE! -> #VALUE!
B109: Egypt | C109: EGY1A | D109: NDC, description - short | E109: egy.mit.ndc.desc.sht | F109: egy.mit.ndc.desc.sht_EGY1A | G109: mit | H109: ndcdescshort | I109: text | J109: 1 | K109: =#VALUE! -> #VALUE!
B110: Egypt | C110: EGY1A | D110: NDC target: unconditional (2018=100) | E110: egy.mit.undc.index | F110: egy.mit.undc.index_EGY1A | G110: mit | H110: ndcunct | I110: index | J110: 1 | K110: =#VALUE! -> #VALUE! | L110: =#VALUE! -> #VALUE! | M110: =#VALUE! -> #VALUE! | N110: =#VALUE! -> #VALUE! | O110: =#VALUE! -> #VALUE! | P110: =#VALUE! -> #VALUE! | Q110: =#VALUE! -> #VALUE! | R110: =#VALUE! -> #VALUE! | ... AD110: =#VALUE! -> #VALUE!
B111: Egypt | C111: EGY1A | D111: NDC target: conditional (2018=100) | E111: egy.mit.cndc.index | F111: egy.mit.cndc.index_EGY1A | G111: mit | H111: ndccont | I111: index | J111: 1 | K111: N/A | L111: N/A | M111: N/A | N111: N/A | O111: N/A | P111: N/A | Q111: N/A | R111: N/A | S111: N/A | T111: N/A | U111: N/A | V111: N/A | W111: N/A | X111: N/A | Y111: N/A | Z111: N/A | AA111: N/A | AB111: N/A | AC111: N/A | AD111: N/A
B112: Egypt | C112: EGY1A | D112: Unconditional NDC, target level (mtCO2e) | E112: egy.mit.undc.trg.ton | F112: egy.mit.undc.trg.ton_EGY1A | G112: mit | H112: ndcunclevel | I112: ton | J112: 1 | K112: =#VALUE! -> #VALUE! | L112: =#VALUE! -> #VALUE! | M112: =#VALUE! -> #VALUE! | N112: =#VALUE! -> #VALUE! | O112: =#VALUE! -> #VALUE! | P112: =#VALUE! -> #VALUE! | Q112: =#VALUE! -> #VALUE! | R112: =#VALUE! -> #VALUE! | ... AD112: =#VALUE! -> #VALUE!
B113: Egypt | C113: EGY1A | D113: Conditional NDC, target level (mtCO2e) | E113: egy.mit.cndc.trg.ton | F113: egy.mit.cndc.trg.ton_EGY1A | G113: mit | H113: ndcconlevel | I113: ton | J113: 1 | K113: N/A | L113: N/A | M113: N/A | N113: N/A | O113: N/A | P113: N/A | Q113: N/A | R113: N/A | S113: N/A | T113: N/A | U113: N/A | V113: N/A | W113: N/A | X113: N/A | Y113: N/A | Z113: N/A | AA113: N/A | AB113: N/A | AC113: N/A | AD113: N/A
B114: Egypt | C114: EGY1A | D114: Unconditional NDC, reduction against the modelled baseline (% by 2030) | E114: egy.mit.undc.2030.pct | F114: egy.mit.undc.2030.pct_EGY1A | G114: mit | H114: undc | I114: pct | J114: 1 | K114: =#VALUE! -> #VALUE!
B115: Egypt | C115: EGY1A | D115: Conditional NDC, reduction against the modelled baseline (% by 2030) | E115: egy.mit.cndc.2030.pct | F115: egy.mit.cndc.2030.pct_EGY1A | G115: mit | H115: cndc | I115: pct | J115: 1 | K115: =#VALUE! -> #VALUE!
B116: Egypt | C116: EGY1A | D116: Average NDC, reduction against the modelled baseline (% by 2030) | E116: egy.mit.andc.2030.pct | F116: egy.mit.andc.2030.pct_EGY1A | G116: mit | H116: andc | I116: pct | J116: 1 | K116: =#VALUE! -> #VALUE!
B117: Egypt | C117: EGY1A | D117: CO2 emissions intensity of output,cement (tCO2 per $m GVA) | E117: egy.mit.emin.cem | F117: egy.mit.emin.cem_EGY1A | G117: mit | K117: 377.96 | L117: 205.55 | M117: 583.5 | N117: 0.03
B118: Egypt | C118: EGY1A | D118: CO2 emissions intensity of output, iron/steel (tCO2 per $m GVA) | E118: egy.mit.emin.irn | F118: egy.mit.emin.irn_EGY1A | G118: mit | K118: 635.9 | L118: 492.6 | M118: 1128.51 | N118: 0.01
B119: Egypt | C119: EGY1A | D119: CO2 emissions intensity of output, mining (tCO2 per $m GVA) | E119: egy.mit.emin.mch | F119: egy.mit.emin.mch_EGY1A | G119: mit | K119: 0 | L119: 54.95 | M119: 54.95 | N119: 0.03
B120: Egypt | C120: EGY1A | D120: CO2 emissions intensity of output, manufactures (tCO2 per $m GVA) | E120: egy.mit.emin.man | F120: egy.mit.emin.man_EGY1A | G120: mit | K120: 159.22 | L120: 26.04 | M120: 185.25 | N120: 0.12
B121: Egypt | C121: EGY1A | D121: CO2 emissions intensity of output, other metals (tCO2 per $m GVA) | E121: egy.mit.emin.oth | F121: egy.mit.emin.oth_EGY1A | G121: mit | K121: 0 | L121: 2.34 | M121: 2.34 | N121: 0.01
B122: Egypt | C122: EGY1A | D122: CO2 emissions intensity of output, food (tCO2 per $m GVA) | E122: egy.mit.emin.foo | F122: egy.mit.emin.foo_EGY1A | G122: mit | K122: 9.78 | L122: 21.23 | M122: 31.01 | N122: 0.26
B123: Egypt | C123: EGY1A | D123: CO2 emissions intensity of output, services (tCO2 per $m GVA) | E123: egy.mit.emin.srv | F123: egy.mit.emin.srv_EGY1A | G123: mit | K123: 0 | L123: 46.09 | M123: 46.09 | N123: 0.36
B124: Egypt | C124: EGY1A | D124: CO2 emissions intensity of output, machinery (tCO2 per $m GVA) | E124: egy.mit.emin.mac | F124: egy.mit.emin.mac_EGY1A | G124: mit | K124: 0 | L124: 48.78 | M124: 48.78 | N124: 0.05
B125: Egypt | C125: EGY1A | D125: CO2 emissions intensity of output, construction (tCO2 per $m GVA) | E125: egy.mit.emin.cst | F125: egy.mit.emin.cst_EGY1A | G125: mit | K125: 0 | L125: 0 | M125: 0 | N125: 0.06
B126: Egypt | C126: EGY1A | D126: CO2 emissions and GVA, fuel refining | E126: egy.mit.emin.ftr | F126: egy.mit.emin.ftr_EGY1A | G126: mit | K126: 0.07 | L126: 0.41 | M126: 820.06 | N126: 0.07 | O126: 0.41
B127: Egypt | C127: EGY1A | D127: CO2 emissions and GVA, food | E127: egy.mit.emin.foo | F127: egy.mit.emin.foo_EGY1A | G127: mit | K127: 0.26 | L127: 0 | M127: 31.01 | N127: 0.33 | O127: 0.41
B128: Egypt | C128: EGY1A | D128: CO2 emissions and GVA, mining | E128: egy.mit.emin.mch | F128: egy.mit.emin.mch_EGY1A | G128: mit | K128: 0.03 | L128: 0 | M128: 54.95 | N128: 0.36 | O128: 0.41
B129: Egypt | C129: EGY1A | D129: CO2 emissions and GVA, manufactures | E129: egy.mit.emin.man | F129: egy.mit.emin.man_EGY1A | G129: mit | K129: 0.12 | L129: 0.32 | M129: 185.25 | N129: 0.48 | O129: 0.73
B130: Egypt | C130: EGY1A | D130: CO2 emissions and GVA, cement | E130: egy.mit.emin.cem | F130: egy.mit.emin.cem_EGY1A | G130: mit | K130: 0.03 | L130: 0.16 | M130: 583.5 | N130: 0.51 | O130: 0.89
B131: Egypt | C131: EGY1A | D131: CO2 emissions and GVA, iron/steel | E131: egy.mit.emin.irn | F131: egy.mit.emin.irn_EGY1A | G131: mit | K131: 0.01 | L131: 0.07 | M131: 1128.51 | N131: 0.52 | O131: 0.96
B132: Egypt | C132: EGY1A | D132: CO2 emissions and GVA, construction | E132: egy.mit.emin.con | F132: egy.mit.emin.con_EGY1A | G132: mit | K132: 0.06 | L132: 0 | M132: 0 | N132: 0.58 | O132: 0.96
B133: Egypt | C133: EGY1A | D133: CO2 emissions and GVA, machinery | E133: egy.mit.emin.mac | F133: egy.mit.emin.mac_EGY1A | G133: mit | K133: 0.05 | L133: 48.78 | M133: 48.78 | N133: 0.63 | O133: 49.74
B134: Egypt | C134: EGY1A | D134: CO2 emissions and GVA, other metals | E134: egy.mit.emin.oth | F134: egy.mit.emin.oth_EGY1A | G134: mit | K134: 0.01 | L134: 0 | M134: 2.34 | N134: 0.64 | O134: 49.74
B135: Egypt | C135: EGY1A | D135: CO2 emissions and GVA, services | E135: egy.mit.emin.srv | F135: egy.mit.emin.srv_EGY1A | G135: mit | K135: 0.36 | L135: 0.04 | M135: 46.09 | N135: 1 | O135: 49.78
B136: Egypt | C136: EGY1A | D136: Electricity ($/kwh) | E136: egy.mit.rp.all.ecy.wtd.1 | F136: egy.mit.rp.all.ecy.wtd.1_EGY1A | G136: mit | H136: rp | I136: usdkwh | J136: 1 | K136: 0.063 | L136: 0.058 | M136: 0.049 | N136: 0.047 | O136: 0.049 | P136: 0.05 | Q136: 0.05 | R136: 0.05 | S136: 0.049 | T136: 0.049 | U136: 0.049 | V136: 0.049 | W136: 0.048 | X136: 0.048 | Y136: 0.048 | Z136: 0.047 | AA136: 0.047 | AB136: 0.047 | AC136: 0.047 | AD136: 0.046
B137: Egypt | C137: EGY1A | D137: Coal ($/GJ) | E137: egy.mit.rp.all.coa.wtd.1 | F137: egy.mit.rp.all.coa.wtd.1_EGY1A | G137: mit | H137: rp | I137: usdgj | J137: 1 | K137: 11.478 | L137: 8.838 | M137: 7.753 | N137: 7.06 | O137: 7.079 | P137: 7.133 | Q137: 7.107 | R137: 7.079 | S137: 7.05 | T137: 7.021 | U137: 7.021 | V137: 7.021 | W137: 7.021 | X137: 7.02 | Y137: 7.02 | Z137: 7.02 | AA137: 7.02 | AB137: 7.02 | AC137: 7.02 | AD137: 7.02
B138: Egypt | C138: EGY1A | D138: Natural gas ($/GJ) | E138: egy.mit.rp.all.nga.wtd.1 | F138: egy.mit.rp.all.nga.wtd.1_EGY1A | G138: mit | H138: rp | I138: usdgj | J138: 1 | K138: 3.534 | L138: 3.22 | M138: 3.181 | N138: 3.19 | O138: 3.217 | P138: 3.241 | Q138: 3.253 | R138: 3.261 | S138: 3.27 | T138: 3.279 | U138: 3.287 | V138: 3.293 | W138: 3.297 | X138: 3.299 | Y138: 3.3 | Z138: 3.298 | AA138: 3.294 | AB138: 3.287 | AC138: 3.278 | AD138: 3.269
B139: Egypt | C139: EGY1A | D139: Oil ($/bbl) | E139: egy.mit.rp.all.oil.wtd.1 | F139: egy.mit.rp.all.oil.wtd.1_EGY1A | G139: mit | H139: rp | I139: bbusdl | J139: 1 | K139: 33.051 | L139: 26.301 | M139: 23.176 | N139: 15 | O139: 15 | P139: 15 | Q139: 15 | R139: 15 | S139: 15 | T139: 15 | U139: 15 | V139: 15 | W139: 15 | X139: 15 | Y139: 15 | Z139: 15 | AA139: 15 | AB139: 15 | AC139: 15 | AD139: 15
B140: Egypt | C140: EGY1A | D140: Gasoline ($/liter) | E140: egy.mit.rp.all.gso.wtd.1 | F140: egy.mit.rp.all.gso.wtd.1_EGY1A | G140: mit | H140: rp | I140: usdl | J140: 1 | K140: 0.6 | L140: 0.411 | M140: 0.335 | N140: 0.335 | O140: 0.335 | P140: 0.335 | Q140: 0.335 | R140: 0.335 | S140: 0.335 | T140: 0.335 | U140: 0.335 | V140: 0.335 | W140: 0.335 | X140: 0.335 | Y140: 0.335 | Z140: 0.335 | AA140: 0.335 | AB140: 0.335 | AC140: 0.335 | AD140: 0.335
B141: Egypt | C141: EGY1A | D141: Diesel ($/liter) | E141: egy.mit.rp.all.die.wtd.1 | F141: egy.mit.rp.all.die.wtd.1_EGY1A | G141: mit | H141: rp | I141: usdl | J141: 1 | K141: 0.414 | L141: 0.281 | M141: 0.249 | N141: 0.249 | O141: 0.249 | P141: 0.249 | Q141: 0.249 | R141: 0.249 | S141: 0.249 | T141: 0.249 | U141: 0.249 | V141: 0.249 | W141: 0.249 | X141: 0.249 | Y141: 0.249 | Z141: 0.249 | AA141: 0.249 | AB141: 0.249 | AC141: 0.249 | AD141: 0.249
B142: Egypt | C142: EGY1A | D142: LPG ($/liter) | E142: egy.mit.rp.all.lpg.wtd.1 | F142: egy.mit.rp.all.lpg.wtd.1_EGY1A | G142: mit | H142: rp | I142: usdl | J142: 1 | K142: 0.175 | L142: 0.102 | M142: 0.088 | N142: 0.088 | O142: 0.088 | P142: 0.088 | Q142: 0.088 | R142: 0.088 | S142: 0.088 | T142: 0.088 | U142: 0.088 | V142: 0.088 | W142: 0.088 | X142: 0.088 | Y142: 0.088 | Z142: 0.088 | AA142: 0.088 | AB142: 0.088 | AC142: 0.088 | AD142: 0.088
B143: Egypt | C143: EGY1A | D143: Kerosene ($/liter) | E143: egy.mit.rp.all.ker.wtd.1 | F143: egy.mit.rp.all.ker.wtd.1_EGY1A | G143: mit | H143: rp | I143: usdl | J143: 1 | K143: 0.414 | L143: 0.259 | M143: 0.244 | N143: 0.244 | O143: 0.244 | P143: 0.244 | Q143: 0.244 | R143: 0.244 | S143: 0.244 | T143: 0.244 | U143: 0.244 | V143: 0.244 | W143: 0.244 | X143: 0.244 | Y143: 0.244 | Z143: 0.244 | AA143: 0.244 | AB143: 0.244 | AC143: 0.244 | AD143: 0.244
B144: Egypt | C144: EGY1A | D144: Electricity ($/kwh) | E144: egy.mit.rp.all.ecy.wtd.2 | F144: egy.mit.rp.all.ecy.wtd.2_EGY1A | G144: mit | H144: rp | I144: usdkwh | J144: 2 | K144: 0.063 | L144: 0.058 | M144: 0.049 | N144: 0.047 | O144: 0.057 | P144: 0.058 | Q144: 0.059 | R144: 0.057 | S144: 0.057 | T144: 0.056 | U144: 0.056 | V144: 0.056 | W144: 0.055 | X144: 0.055 | Y144: 0.055 | Z144: 0.055 | AA144: 0.054 | AB144: 0.054 | AC144: 0.054 | AD144: 0.053
B145: Egypt | C145: EGY1A | D145: Coal ($/GJ) | E145: egy.mit.rp.coa.wtd.2 | F145: egy.mit.rp.coa.wtd.2_EGY1A | G145: mit | H145: rp | I145: usdgj | J145: 2 | K145: 11.478 | L145: 8.838 | M145: 7.753 | N145: 7.06 | O145: 9.079 | P145: 9.134 | Q145: 9.108 | R145: 9.08 | S145: 9.05 | T145: 9.021 | U145: 9.021 | V145: 9.021 | W145: 9.021 | X145: 9.021 | Y145: 9.021 | Z145: 9.021 | AA145: 9.02 | AB145: 9.02 | AC145: 9.02 | AD145: 9.02
B146: Egypt | C146: EGY1A | D146: Natural gas ($/GJ) | E146: egy.mit.rp.nga.wtd.2 | F146: egy.mit.rp.nga.wtd.2_EGY1A | G146: mit | H146: rp | I146: usdgj | J146: 2 | K146: 3.534 | L146: 3.22 | M146: 3.181 | N146: 3.19 | O146: 4.333 | P146: 4.358 | Q146: 4.371 | R146: 4.38 | S146: 4.39 | T146: 4.399 | U146: 4.408 | V146: 4.415 | W146: 4.42 | X146: 4.423 | Y146: 4.424 | Z146: 4.422 | AA146: 4.418 | AB146: 4.411 | AC146: 4.401 | AD146: 4.392
B147: Egypt | C147: EGY1A | D147: Oil ($/bbl) | E147: egy.mit.rp.oil.wtd.2 | F147: egy.mit.rp.oil.wtd.2_EGY1A | G147: mit | H147: rp | I147: bbusdl | J147: 2 | K147: 33.051 | L147: 26.301 | M147: 23.176 | N147: 15 | O147: 23.014 | P147: 17.477 | Q147: 15.953 | R147: 15.185 | S147: 15 | T147: 15 | U147: 15 | V147: 15 | W147: 15 | X147: 15 | Y147: 15 | Z147: 15 | AA147: 15 | AB147: 15 | AC147: 15 | AD147: 15
... B159: Egypt | C159: EGY1A | D159: Kerosene (% change) | E159: egy.mit.rp.all.ker.pct.2 | F159: egy.mit.rp.all.ker.pct.2_EGY1A | G159: mit | H159: rp | I159: pc | J159: 2 | K159: 0 | L159: 0 | M159: 0 | N159: 0 | O159: 0.21 | P159: 0.21 | Q159: 0.21 | R159: 0.21 | S159: 0.21 | T159: 0.21 | U159: 0.21 | V159: 0.21 | W159: 0.21 | X159: 0.21 | Y159: 0.21 | Z159: 0.21 | AA159: 0.21 | AB159: 0.21 | AC159: 0.21 | AD159: 0.21
B160: Egypt | C160: EGY1A | D160: Implied economy-wide CO2 elasticity | E160: egy.mit.co2.ela.eco.2 | F160: egy.mit.co2.ela.eco.2_EGY1A | G160: mit | H160: co2ela | I160: unitusdless | J160: 2
B161: Egypt | C161: EGY1A | D161: Implied additional carbon price to achieve NDC (US$ per ton CO2) | E161: egy.mit.ndc.ecr.2 | F161: egy.mit.ndc.ecr.2_EGY1A | G161: mit | H161: ndcerc | I161: usdtco2 | J161: 2 | K161: =#VALUE! -> #VALUE!
B162: Egypt | C162: EGY1A | D162: Effective carbon rate - economy-wide (US$ per ton CO2) | E162: egy.mit.ecr.1 | F162: egy.mit.ecr.1_EGY1A | G162: mit | H162: ecr | I162: usdtco2 | J162: 1 | K162: -151.581 | L162: -128.294 | M162: -165.888 | N162: -154.876 | O162: -161.085 | P162: -152.54 | Q162: -147.751 | R162: -144.482 | S162: -141.161 | T162: -137.051 | U162: -133.401 | V162: -129.433 | W162: -125.136 | X162: -120.459 | Y162: -115.237 | Z162: -109.639 | AA162: -103.673 | AB162: -97.374 | AC162: -91.656 | AD162: -90.676
B163: Egypt | C163: EGY1A | D163: Effective carbon rate - economy-wide (US$ per ton CO2) | E163: egy.mit.ecr.2 | F163: egy.mit.ecr.2_EGY1A | G163: mit | H163: ecr | I163: usdtco2 | J163: 2 | K163: -151.581 | L163: -128.298 | M163: -165.919 | N163: -154.899 | O163: -141.799 | P163: -130.931 | Q163: -125.859 | R163: -122.116 | S163: -118.856 | T163: -114.679 | U163: -110.901 | V163: -106.733 | W163: -102.235 | X163: -97.389 | Y163: -92.015 | Z163: -86.305 | AA163: -80.247 | AB163: -73.883 | AC163: -68.191 | AD163: -67.623
B164: Egypt | C164: EGY1A | D164: Electricity retail price in industry, ($/kWh), baseline | E164: egy.mit.rp.ind.ecy.t.1 | F164: egy.mit.rp.ind.ecy.t.1_EGY1A | G164: mit | H164: rp | I164: usdkwh | J164: 1 | K164: 0.064 | L164: 0.062 | M164: 0.052 | N164: 0.049 | O164: 0.051 | P164: 0.053 | Q164: 0.053 | R164: 0.052 | S164: 0.052 | T164: 0.052 | U164: 0.051 | V164: 0.051 | W164: 0.051 | X164: 0.051 | Y164: 0.05 | Z164: 0.05 | AA164: 0.05 | AB164: 0.049 | AC164: 0.049 | AD164: 0.049
B165: Egypt | C165: EGY1A | D165: Electricity retail price in residential use, $/kWh (baseline) | E165: egy.mit.rp.res.ecy.t.1 | F165: egy.mit.rp.res.ecy.t.1_EGY1A | G165: mit | H165: rp | I165: usdkwh | J165: 1 | K165: 0.061 | L165: 0.052 | M165: 0.046 | N165: 0.043 | O165: 0.045 | P165: 0.046 | Q165: 0.046 | R165: 0.046 | S165: 0.046 | T165: 0.045 | U165: 0.045 | V165: 0.045 | W165: 0.045 | X165: 0.044 | Y165: 0.044 | Z165: 0.044 | AA165: 0.044 | AB165: 0.043 | AC165: 0.043 | AD165: 0.043
B166: Egypt | C166: EGY1A | D166: Coal retail price in industry, ($/GJ), baseline | E166: egy.mit.rp.ind.coa.a.1 | F166: egy.mit.rp.ind.coa.a.1_EGY1A | G166: mit | H166: rp | I166: usdgj | J166: 1 | K166: 11.466 | L166: 8.83 | M166: 7.746 | N166: 7.054 | O166: 7.072 | P166: 7.127 | Q166: 7.101 | R166: 7.073 | S166: 7.043 | T166: 7.014 | U166: 7.014 | V166: 7.014 | W166: 7.014 | X166: 7.014 | Y166: 7.014 | Z166: 7.014 | AA166: 7.014 | AB166: 7.014 | AC166: 7.014 | AD166: 7.014
B167: Egypt | C167: EGY1A | D167: Natural gas retail price in industry, ($/GJ), baseline | E167: egy.mit.rp.ind.nga.a.1 | F167: egy.mit.rp.ind.nga.a.1_EGY1A | G167: mit | H167: rp | I167: usdgj | J167: 1 | K167: 5.336 | L167: 5.01 | M167: 5.087 | N167: 5.087 | O167: 5.087 | P167: 5.087 | Q167: 5.087 | R167: 5.087 | S167: 5.087 | T167: 5.087 | U167: 5.087 | V167: 5.087 | W167: 5.087 | X167: 5.087 | Y167: 5.087 | Z167: 5.087 | AA167: 5.087 | AB167: 5.087 | AC167: 5.087 | AD167: 5.087
B168: Egypt | C168: EGY1A | D168: Coal retail price in residential use, ($/GJ), baseline | E168: egy.mit.rp.res.coa.a.1 | F168: egy.mit.rp.res.coa.a.1_EGY1A | G168: mit | H168: rp | I168: usdgj | J168: 1 | K168: 23.399 | L168: 15.864 | M168: 14.744 | N168: 13.652 | O168: 13.681 | P168: 13.768 | Q168: 13.727 | R168: 13.683 | S168: 13.636 | T168: 13.59 | U168: 13.59 | V168: 13.59 | W168: 13.59 | X168: 13.59 | Y168: 13.59 | Z168: 13.59 | AA168: 13.59 | AB168: 13.59 | AC168: 13.59 | AD168: 13.59
...
