Workbook
Name in_iso: Screen!$C$5
Name in_f1: Screen!$C$8
Name in_f2: Screen!$C$9
Name in_f3: Screen!$C$10
Name in_rebate: Screen!$C$11
Name in_cap: Screen!$C$12
Name in_tstep: Screen!$C$15
Name in_fstep: Screen!$C$16
Name in_elas: Screen!$C$19
Name in_kappa: Screen!$C$20
Name in_rise_lo: Screen!$C$21
Name in_rise_hi: Screen!$C$22
Name in_rise_miss: Screen!$C$23
Name in_gas_rep: Screen!$C$24
Name in_sw_floor: Screen!$C$25
Name in_sw_miss: Screen!$C$26
Name in_hr_coal: Screen!$C$27
Name in_hr_gas: Screen!$C$28
Name in_whole_sh: Screen!$C$29
Name in_res_sh: Screen!$C$30
Name in_q40: Screen!$C$31
Name in_phase: Screen!$C$32
Name in_pt3: Screen!$C$33
Name in_pt2: Screen!$C$34
Name in_pt1: Screen!$C$35
Name in_pt_hi: Screen!$C$36
Name in_pt_oth: Screen!$C$37
Name in_b40_li: Screen!$C$38
Name in_b40_lmi: Screen!$C$39
Name in_b40_umi: Screen!$C$40
Name in_b40_hi: Screen!$C$41
Name sel_row: Screen!$H$5

Sheet Screen
B2: Carbon tax vs feebate: feasibility screen (power sector)
B3: Most abatement each instrument gets without breaking three political limits. Yellow cells are inputs. Screening only: priors are placeholders, see notes below.
B5: Country (ISO3) | C5: ZAF | G5: Row in Countries | H5: =MATCH(in_iso,Countries!$A$1:$A$174,0)
B7: Political limits | C7: Value | D7: Note | G7: Selected country
B8: F1 max tariff rise (%) | C8: 10 | D8: First-year rise in residential tariff | G8: Country | H8: =INDEX(Countries!$B$1:$B$174,sel_row)
B9: F2 max bottom-40% burden (% of consumption) | C9: 0.5 | D9: Net of rebate | G9: Income | H9: =INDEX(Countries!$C$1:$C$174,sel_row)
B10: F3 max coal/oil generator payment (% of revenue) | C10: 15 | D10: Unpassed tax + net feebate payment | G10: Baseline power CO2 (Mt) | H10: =INDEX(Countries!$Q$1:$Q$174,sel_row)
B11: Share of tax revenue rebated to bottom 40% | C11: 0 | D11: 0-1 | G11: Average intensity (t/MWh) | H11: =INDEX(Countries!$R$1:$R$174,sel_row)
B12: Rate cap ($/tCO2) | C12: 200 | D12: Upper bound for tax and feebate rates | G12: Residential tariff ($/MWh) | H12: =INDEX(Countries!$V$1:$V$174,sel_row)
G13: Pass-through | H13: =INDEX(Countries!$W$1:$W$174,sel_row)
B14: Grid | C14: Value | D14: Note | G14: Switching price ($/t) | H14: =INDEX(Countries!$Y$1:$Y$174,sel_row)
B15: Grid: tax step ($/t) | C15: 10 | D15: Rows of the grid | G15: Max substitution share | H15: =INDEX(Countries!$X$1:$X$174,sel_row)
B16: Grid: feebate step ($/t) | C16: 20 | D16: Columns of the grid | G16: Feebate/tax abatement at $50 | H16: =INDEX(Countries!$AR$1:$AR$174,sel_row)
G17: Tariff rise from $50 tax (%) | H17: =INDEX(Countries!$AS$1:$AS$174,sel_row)
B18: Priors (assumptions: replace with country evidence or CPAT) | C18: Value | D18: Note
B19: Electricity demand elasticity | C19: -0.3 | D19: Long run | G19: Best under limits | H19: E (%) | I19: Tax $/t | J19: Feebate $/t | K19: F1 | L19: F2 | M19: F3 | N19: Binding
B20: Max share of coal+oil output displaceable by 2030 | C20: 0.4 | G20: Carbon tax / ETS | H20: =INDEX(Countries!$AJ$1:$AJ$174,sel_row) | I20: =INDEX(Countries!$AI$1:$AI$174,sel_row) | J20: =0 | K20: =INDEX(Countries!$AB$1:$AB$174,sel_row)*I20 | L20: =INDEX(Countries!$AC$1:$AC$174,sel_row)*I20 | M20: =INDEX(Countries!$AD$1:$AD$174,sel_row)*I20+INDEX(Countries!$AE$1:$AE$174,sel_row)*J20 | N20: =INDEX(Countries!$AK$1:$AK$174,sel_row)
B21: kappa multiplier at RISE score 0 | C21: 0.5 | G21: Feebate | H21: =INDEX(Countries!$AN$1:$AN$174,sel_row) | I21: =0 | J21: =INDEX(Countries!$AM$1:$AM$174,sel_row) | K21: =INDEX(Countries!$AB$1:$AB$174,sel_row)*I21 | L21: =INDEX(Countries!$AC$1:$AC$174,sel_row)*I21 | M21: =INDEX(Countries!$AD$1:$AD$174,sel_row)*I21+INDEX(Countries!$AE$1:$AE$174,sel_row)*J21 | N21: =INDEX(Countries!$AO$1:$AO$174,sel_row)
B22: kappa multiplier at RISE score 100 | C22: 1 | G22: Hybrid (tax + feebate) | H22: =INDEX(Countries!$AT$1:$AT$174,sel_row) | I22: =INDEX(Countries!$AU$1:$AU$174,sel_row) | J22: =INDEX(Countries!$AV$1:$AV$174,sel_row) | K22: =INDEX(Countries!$AB$1:$AB$174,sel_row)*I22 | L22: =INDEX(Countries!$AC$1:$AC$174,sel_row)*I22 | M22: =INDEX(Countries!$AD$1:$AD$174,sel_row)*I22+INDEX(Countries!$AE$1:$AE$174,sel_row)*J22 | N22: =INDEX(Countries!$AZ$1:$AZ$174,sel_row)
B23: RISE score when missing | C23: 35 | D23: Median
B24: Share of displaced output replaced by gas | C24: 0.3 | D24: Rest clean | G24: +1pp on F1 buys, tax only (pp E) | H24: =INDEX(Countries!$AL$1:$AL$174,sel_row)
B25: Lowest switching price ($/t) | C25: 15 | D25: Non-price barriers
B26: Switching price when no gas price ($/t) | C26: 50 | G26: Abatement E (%) by tax (rows) and feebate (columns). Green = within all three limits; bold border = best feasible cell.
B27: Coal heat rate (GJ/MWh) | C27: 10 | G27: Tax $/t \ Feebate $/t | H27: =in_fstep*0 | I27: =in_fstep*1 | J27: =in_fstep*2 | K27: =in_fstep*3 | L27: =in_fstep*4 | M27: =in_fstep*5 | N27: =in_fstep*6 | O27: =in_fstep*7 | P27: =in_fstep*8 | Q27: =in_fstep*9 | R27: =in_fstep*10
B28: Gas heat rate (GJ/MWh) | C28: 7 | D28: CCGT | G28: =in_tstep*0 | H28: =100*(1-(1-$H$44*(1-EXP(-($G28+H$27)/$I$44)))*(1-MIN(ABS(in_elas)*$J$44*$K$44*$G28/$L$44,1))) | I28: =100*(1-(1-$H$44*(1-EXP(-($G28+I$27)/$I$44)))*(1-MIN(ABS(in_elas)*$J$44*$K$44*$G28/$L$44,1))) | J28: =100*(1-(1-$H$44*(1-EXP(-($G28+J$27)/$I$44)))*(1-MIN(ABS(in_elas)*$J$44*$K$44*$G28/$L$44,1))) | K28: =100*(1-(1-$H$44*(1-EXP(-($G28+K$27)/$I$44)))*(1-MIN(ABS(in_elas)*$J$44*$K$44*$G28/$L$44,1))) | L28: =100*(1-(1-$H$44*(1-EXP(-($G28+L$27)/$I$44)))*(1-MIN(ABS(in_elas)*$J$44*$K$44*$G28/$L$44,1))) | M28: =100*(1-(1-$H$44*(1-EXP(-($G28+M$27)/$I$44)))*(1-MIN(ABS(in_elas)*$J$44*$K$44*$G28/$L$44,1))) | N28: =100*(1-(1-$H$44*(1-EXP(-($G28+N$27)/$I$44)))*(1-MIN(ABS(in_elas)*$J$44*$K$44*$G28/$L$44,1))) | O28: =100*(1-(1-$H$44*(1-EXP(-($G28+O$27)/$I$44)))*(1-MIN(ABS(in_elas)*$J$44*$K$44*$G28/$L$44,1))) | ... R28: =100*(1-(1-$H$44*(1-EXP(-($G28+R$27)/$I$44)))*(1-MIN(ABS(in_elas)*$J$44*$K$44*$G28/$L$44,1)))
B29: Wholesale price / residential tariff | C29: 0.6 | G29: =in_tstep*1 | H29: =100*(1-(1-$H$44*(1-EXP(-($G29+H$27)/$I$44)))*(1-MIN(ABS(in_elas)*$J$44*$K$44*$G29/$L$44,1))) | I29: =100*(1-(1-$H$44*(1-EXP(-($G29+I$27)/$I$44)))*(1-MIN(ABS(in_elas)*$J$44*$K$44*$G29/$L$44,1))) | J29: =100*(1-(1-$H$44*(1-EXP(-($G29+J$27)/$I$44)))*(1-MIN(ABS(in_elas)*$J$44*$K$44*$G29/$L$44,1))) | K29: =100*(1-(1-$H$44*(1-EXP(-($G29+K$27)/$I$44)))*(1-MIN(ABS(in_elas)*$J$44*$K$44*$G29/$L$44,1))) | L29: =100*(1-(1-$H$44*(1-EXP(-($G29+L$27)/$I$44)))*(1-MIN(ABS(in_elas)*$J$44*$K$44*$G29/$L$44,1))) | M29: =100*(1-(1-$H$44*(1-EXP(-($G29+M$27)/$I$44)))*(1-MIN(ABS(in_elas)*$J$44*$K$44*$G29/$L$44,1))) | N29: =100*(1-(1-$H$44*(1-EXP(-($G29+N$27)/$I$44)))*(1-MIN(ABS(in_elas)*$J$44*$K$44*$G29/$L$44,1))) | O29: =100*(1-(1-$H$44*(1-EXP(-($G29+O$27)/$I$44)))*(1-MIN(ABS(in_elas)*$J$44*$K$44*$G29/$L$44,1))) | ... R29: =100*(1-(1-$H$44*(1-EXP(-($G29+R$27)/$I$44)))*(1-MIN(ABS(in_elas)*$J$44*$K$44*$G29/$L$44,1)))
B30: Residential share of electricity sales | C30: 0.35 | G30: =in_tstep*2 | H30: =100*(1-(1-$H$44*(1-EXP(-($G30+H$27)/$I$44)))*(1-MIN(ABS(in_elas)*$J$44*$K$44*$G30/$L$44,1))) | I30: =100*(1-(1-$H$44*(1-EXP(-($G30+I$27)/$I$44)))*(1-MIN(ABS(in_elas)*$J$44*$K$44*$G30/$L$44,1))) | J30: =100*(1-(1-$H$44*(1-EXP(-($G30+J$27)/$I$44)))*(1-MIN(ABS(in_elas)*$J$44*$K$44*$G30/$L$44,1))) | K30: =100*(1-(1-$H$44*(1-EXP(-($G30+K$27)/$I$44)))*(1-MIN(ABS(in_elas)*$J$44*$K$44*$G30/$L$44,1))) | L30: =100*(1-(1-$H$44*(1-EXP(-($G30+L$27)/$I$44)))*(1-MIN(ABS(in_elas)*$J$44*$K$44*$G30/$L$44,1))) | M30: =100*(1-(1-$H$44*(1-EXP(-($G30+M$27)/$I$44)))*(1-MIN(ABS(in_elas)*$J$44*$K$44*$G30/$L$44,1))) | N30: =100*(1-(1-$H$44*(1-EXP(-($G30+N$27)/$I$44)))*(1-MIN(ABS(in_elas)*$J$44*$K$44*$G30/$L$44,1))) | O30: =100*(1-(1-$H$44*(1-EXP(-($G30+O$27)/$I$44)))*(1-MIN(ABS(in_elas)*$J$44*$K$44*$G30/$L$44,1))) | ... R30: =100*(1-(1-$H$44*(1-EXP(-($G30+R$27)/$I$44)))*(1-MIN(ABS(in_elas)*$J$44*$K$44*$G30/$L$44,1)))
B31: Bottom-40% share of residential use | C31: 0.2 | G31: =in_tstep*3 | H31: =100*(1-(1-$H$44*(1-EXP(-($G31+H$27)/$I$44)))*(1-MIN(ABS(in_elas)*$J$44*$K$44*$G31/$L$44,1))) | I31: =100*(1-(1-$H$44*(1-EXP(-($G31+I$27)/$I$44)))*(1-MIN(ABS(in_elas)*$J$44*$K$44*$G31/$L$44,1))) | J31: =100*(1-(1-$H$44*(1-EXP(-($G31+J$27)/$I$44)))*(1-MIN(ABS(in_elas)*$J$44*$K$44*$G31/$L$44,1))) | K31: =100*(1-(1-$H$44*(1-EXP(-($G31+K$27)/$I$44)))*(1-MIN(ABS(in_elas)*$J$44*$K$44*$G31/$L$44,1))) | L31: =100*(1-(1-$H$44*(1-EXP(-($G31+L$27)/$I$44)))*(1-MIN(ABS(in_elas)*$J$44*$K$44*$G31/$L$44,1))) | M31: =100*(1-(1-$H$44*(1-EXP(-($G31+M$27)/$I$44)))*(1-MIN(ABS(in_elas)*$J$44*$K$44*$G31/$L$44,1))) | N31: =100*(1-(1-$H$44*(1-EXP(-($G31+N$27)/$I$44)))*(1-MIN(ABS(in_elas)*$J$44*$K$44*$G31/$L$44,1))) | O31: =100*(1-(1-$H$44*(1-EXP(-($G31+O$27)/$I$44)))*(1-MIN(ABS(in_elas)*$J$44*$K$44*$G31/$L$44,1))) | ... R31: =100*(1-(1-$H$44*(1-EXP(-($G31+R$27)/$I$44)))*(1-MIN(ABS(in_elas)*$J$44*$K$44*$G31/$L$44,1)))
B32: Phase-in years | C32: 1 | D32: Tax reached in equal steps | G32: =in_tstep*4 | H32: =100*(1-(1-$H$44*(1-EXP(-($G32+H$27)/$I$44)))*(1-MIN(ABS(in_elas)*$J$44*$K$44*$G32/$L$44,1))) | I32: =100*(1-(1-$H$44*(1-EXP(-($G32+I$27)/$I$44)))*(1-MIN(ABS(in_elas)*$J$44*$K$44*$G32/$L$44,1))) | J32: =100*(1-(1-$H$44*(1-EXP(-($G32+J$27)/$I$44)))*(1-MIN(ABS(in_elas)*$J$44*$K$44*$G32/$L$44,1))) | K32: =100*(1-(1-$H$44*(1-EXP(-($G32+K$27)/$I$44)))*(1-MIN(ABS(in_elas)*$J$44*$K$44*$G32/$L$44,1))) | L32: =100*(1-(1-$H$44*(1-EXP(-($G32+L$27)/$I$44)))*(1-MIN(ABS(in_elas)*$J$44*$K$44*$G32/$L$44,1))) | M32: =100*(1-(1-$H$44*(1-EXP(-($G32+M$27)/$I$44)))*(1-MIN(ABS(in_elas)*$J$44*$K$44*$G32/$L$44,1))) | N32: =100*(1-(1-$H$44*(1-EXP(-($G32+N$27)/$I$44)))*(1-MIN(ABS(in_elas)*$J$44*$K$44*$G32/$L$44,1))) | O32: =100*(1-(1-$H$44*(1-EXP(-($G32+O$27)/$I$44)))*(1-MIN(ABS(in_elas)*$J$44*$K$44*$G32/$L$44,1))) | ... R32: =100*(1-(1-$H$44*(1-EXP(-($G32+R$27)/$I$44)))*(1-MIN(ABS(in_elas)*$J$44*$K$44*$G32/$L$44,1)))
B33: Pass-through: wholesale market (PSRT 3) | C33: 1 | G33: =in_tstep*5 | H33: =100*(1-(1-$H$44*(1-EXP(-($G33+H$27)/$I$44)))*(1-MIN(ABS(in_elas)*$J$44*$K$44*$G33/$L$44,1))) | I33: =100*(1-(1-$H$44*(1-EXP(-($G33+I$27)/$I$44)))*(1-MIN(ABS(in_elas)*$J$44*$K$44*$G33/$L$44,1))) | J33: =100*(1-(1-$H$44*(1-EXP(-($G33+J$27)/$I$44)))*(1-MIN(ABS(in_elas)*$J$44*$K$44*$G33/$L$44,1))) | K33: =100*(1-(1-$H$44*(1-EXP(-($G33+K$27)/$I$44)))*(1-MIN(ABS(in_elas)*$J$44*$K$44*$G33/$L$44,1))) | L33: =100*(1-(1-$H$44*(1-EXP(-($G33+L$27)/$I$44)))*(1-MIN(ABS(in_elas)*$J$44*$K$44*$G33/$L$44,1))) | M33: =100*(1-(1-$H$44*(1-EXP(-($G33+M$27)/$I$44)))*(1-MIN(ABS(in_elas)*$J$44*$K$44*$G33/$L$44,1))) | N33: =100*(1-(1-$H$44*(1-EXP(-($G33+N$27)/$I$44)))*(1-MIN(ABS(in_elas)*$J$44*$K$44*$G33/$L$44,1))) | O33: =100*(1-(1-$H$44*(1-EXP(-($G33+O$27)/$I$44)))*(1-MIN(ABS(in_elas)*$J$44*$K$44*$G33/$L$44,1))) | ... R33: =100*(1-(1-$H$44*(1-EXP(-($G33+R$27)/$I$44)))*(1-MIN(ABS(in_elas)*$J$44*$K$44*$G33/$L$44,1)))
B34: Pass-through: single buyer (PSRT 2) | C34: 0.6 | G34: =in_tstep*6 | H34: =100*(1-(1-$H$44*(1-EXP(-($G34+H$27)/$I$44)))*(1-MIN(ABS(in_elas)*$J$44*$K$44*$G34/$L$44,1))) | I34: =100*(1-(1-$H$44*(1-EXP(-($G34+I$27)/$I$44)))*(1-MIN(ABS(in_elas)*$J$44*$K$44*$G34/$L$44,1))) | J34: =100*(1-(1-$H$44*(1-EXP(-($G34+J$27)/$I$44)))*(1-MIN(ABS(in_elas)*$J$44*$K$44*$G34/$L$44,1))) | K34: =100*(1-(1-$H$44*(1-EXP(-($G34+K$27)/$I$44)))*(1-MIN(ABS(in_elas)*$J$44*$K$44*$G34/$L$44,1))) | L34: =100*(1-(1-$H$44*(1-EXP(-($G34+L$27)/$I$44)))*(1-MIN(ABS(in_elas)*$J$44*$K$44*$G34/$L$44,1))) | M34: =100*(1-(1-$H$44*(1-EXP(-($G34+M$27)/$I$44)))*(1-MIN(ABS(in_elas)*$J$44*$K$44*$G34/$L$44,1))) | N34: =100*(1-(1-$H$44*(1-EXP(-($G34+N$27)/$I$44)))*(1-MIN(ABS(in_elas)*$J$44*$K$44*$G34/$L$44,1))) | O34: =100*(1-(1-$H$44*(1-EXP(-($G34+O$27)/$I$44)))*(1-MIN(ABS(in_elas)*$J$44*$K$44*$G34/$L$44,1))) | ... R34: =100*(1-(1-$H$44*(1-EXP(-($G34+R$27)/$I$44)))*(1-MIN(ABS(in_elas)*$J$44*$K$44*$G34/$L$44,1)))
B35: Pass-through: vertically integrated (PSRT 1) | C35: 0.4 | G35: =in_tstep*7 | H35: =100*(1-(1-$H$44*(1-EXP(-($G35+H$27)/$I$44)))*(1-MIN(ABS(in_elas)*$J$44*$K$44*$G35/$L$44,1))) | I35: =100*(1-(1-$H$44*(1-EXP(-($G35+I$27)/$I$44)))*(1-MIN(ABS(in_elas)*$J$44*$K$44*$G35/$L$44,1))) | J35: =100*(1-(1-$H$44*(1-EXP(-($G35+J$27)/$I$44)))*(1-MIN(ABS(in_elas)*$J$44*$K$44*$G35/$L$44,1))) | K35: =100*(1-(1-$H$44*(1-EXP(-($G35+K$27)/$I$44)))*(1-MIN(ABS(in_elas)*$J$44*$K$44*$G35/$L$44,1))) | L35: =100*(1-(1-$H$44*(1-EXP(-($G35+L$27)/$I$44)))*(1-MIN(ABS(in_elas)*$J$44*$K$44*$G35/$L$44,1))) | M35: =100*(1-(1-$H$44*(1-EXP(-($G35+M$27)/$I$44)))*(1-MIN(ABS(in_elas)*$J$44*$K$44*$G35/$L$44,1))) | N35: =100*(1-(1-$H$44*(1-EXP(-($G35+N$27)/$I$44)))*(1-MIN(ABS(in_elas)*$J$44*$K$44*$G35/$L$44,1))) | O35: =100*(1-(1-$H$44*(1-EXP(-($G35+O$27)/$I$44)))*(1-MIN(ABS(in_elas)*$J$44*$K$44*$G35/$L$44,1))) | ... R35: =100*(1-(1-$H$44*(1-EXP(-($G35+R$27)/$I$44)))*(1-MIN(ABS(in_elas)*$J$44*$K$44*$G35/$L$44,1)))
B36: Pass-through: no PSRT data, high income | C36: 0.9 | G36: =in_tstep*8 | H36: =100*(1-(1-$H$44*(1-EXP(-($G36+H$27)/$I$44)))*(1-MIN(ABS(in_elas)*$J$44*$K$44*$G36/$L$44,1))) | I36: =100*(1-(1-$H$44*(1-EXP(-($G36+I$27)/$I$44)))*(1-MIN(ABS(in_elas)*$J$44*$K$44*$G36/$L$44,1))) | J36: =100*(1-(1-$H$44*(1-EXP(-($G36+J$27)/$I$44)))*(1-MIN(ABS(in_elas)*$J$44*$K$44*$G36/$L$44,1))) | K36: =100*(1-(1-$H$44*(1-EXP(-($G36+K$27)/$I$44)))*(1-MIN(ABS(in_elas)*$J$44*$K$44*$G36/$L$44,1))) | L36: =100*(1-(1-$H$44*(1-EXP(-($G36+L$27)/$I$44)))*(1-MIN(ABS(in_elas)*$J$44*$K$44*$G36/$L$44,1))) | M36: =100*(1-(1-$H$44*(1-EXP(-($G36+M$27)/$I$44)))*(1-MIN(ABS(in_elas)*$J$44*$K$44*$G36/$L$44,1))) | N36: =100*(1-(1-$H$44*(1-EXP(-($G36+N$27)/$I$44)))*(1-MIN(ABS(in_elas)*$J$44*$K$44*$G36/$L$44,1))) | O36: =100*(1-(1-$H$44*(1-EXP(-($G36+O$27)/$I$44)))*(1-MIN(ABS(in_elas)*$J$44*$K$44*$G36/$L$44,1))) | ... R36: =100*(1-(1-$H$44*(1-EXP(-($G36+R$27)/$I$44)))*(1-MIN(ABS(in_elas)*$J$44*$K$44*$G36/$L$44,1)))
B37: Pass-through: no PSRT data, other | C37: 0.6 | G37: =in_tstep*9 | H37: =100*(1-(1-$H$44*(1-EXP(-($G37+H$27)/$I$44)))*(1-MIN(ABS(in_elas)*$J$44*$K$44*$G37/$L$44,1))) | I37: =100*(1-(1-$H$44*(1-EXP(-($G37+I$27)/$I$44)))*(1-MIN(ABS(in_elas)*$J$44*$K$44*$G37/$L$44,1))) | J37: =100*(1-(1-$H$44*(1-EXP(-($G37+J$27)/$I$44)))*(1-MIN(ABS(in_elas)*$J$44*$K$44*$G37/$L$44,1))) | K37: =100*(1-(1-$H$44*(1-EXP(-($G37+K$27)/$I$44)))*(1-MIN(ABS(in_elas)*$J$44*$K$44*$G37/$L$44,1))) | L37: =100*(1-(1-$H$44*(1-EXP(-($G37+L$27)/$I$44)))*(1-MIN(ABS(in_elas)*$J$44*$K$44*$G37/$L$44,1))) | M37: =100*(1-(1-$H$44*(1-EXP(-($G37+M$27)/$I$44)))*(1-MIN(ABS(in_elas)*$J$44*$K$44*$G37/$L$44,1))) | N37: =100*(1-(1-$H$44*(1-EXP(-($G37+N$27)/$I$44)))*(1-MIN(ABS(in_elas)*$J$44*$K$44*$G37/$L$44,1))) | O37: =100*(1-(1-$H$44*(1-EXP(-($G37+O$27)/$I$44)))*(1-MIN(ABS(in_elas)*$J$44*$K$44*$G37/$L$44,1))) | ... R37: =100*(1-(1-$H$44*(1-EXP(-($G37+R$27)/$I$44)))*(1-MIN(ABS(in_elas)*$J$44*$K$44*$G37/$L$44,1)))
B38: Bottom-40% electricity budget share: low income | C38: 0.02 | D38: Placeholder | G38: =in_tstep*10 | H38: =100*(1-(1-$H$44*(1-EXP(-($G38+H$27)/$I$44)))*(1-MIN(ABS(in_elas)*$J$44*$K$44*$G38/$L$44,1))) | I38: =100*(1-(1-$H$44*(1-EXP(-($G38+I$27)/$I$44)))*(1-MIN(ABS(in_elas)*$J$44*$K$44*$G38/$L$44,1))) | J38: =100*(1-(1-$H$44*(1-EXP(-($G38+J$27)/$I$44)))*(1-MIN(ABS(in_elas)*$J$44*$K$44*$G38/$L$44,1))) | K38: =100*(1-(1-$H$44*(1-EXP(-($G38+K$27)/$I$44)))*(1-MIN(ABS(in_elas)*$J$44*$K$44*$G38/$L$44,1))) | L38: =100*(1-(1-$H$44*(1-EXP(-($G38+L$27)/$I$44)))*(1-MIN(ABS(in_elas)*$J$44*$K$44*$G38/$L$44,1))) | M38: =100*(1-(1-$H$44*(1-EXP(-($G38+M$27)/$I$44)))*(1-MIN(ABS(in_elas)*$J$44*$K$44*$G38/$L$44,1))) | N38: =100*(1-(1-$H$44*(1-EXP(-($G38+N$27)/$I$44)))*(1-MIN(ABS(in_elas)*$J$44*$K$44*$G38/$L$44,1))) | O38: =100*(1-(1-$H$44*(1-EXP(-($G38+O$27)/$I$44)))*(1-MIN(ABS(in_elas)*$J$44*$K$44*$G38/$L$44,1))) | ... R38: =100*(1-(1-$H$44*(1-EXP(-($G38+R$27)/$I$44)))*(1-MIN(ABS(in_elas)*$J$44*$K$44*$G38/$L$44,1)))
B39: ... lower middle income | C39: 0.035 | D39: Placeholder
B40: ... upper middle income | C40: 0.04 | D40: Placeholder
B41: ... high income | C41: 0.03 | D41: Placeholder
G42: Grid parameters (from Countries)
B43: Notes | H43: smax | I43: tsw | J43: phi | K43: eavg | L43: pres | M43: a1 | N43: a2 | O43: a3t | P43: a3f
B44: What: most power-sector CO2 cut from a carbon tax/ETS, a feebate (= output-based allocation, TPS) or a hybrid, without exceeding three political limits. | H44: =INDEX(Countries!$X$1:$X$174,sel_row) | I44: =INDEX(Countries!$Y$1:$Y$174,sel_row) | J44: =INDEX(Countries!$W$1:$W$174,sel_row) | K44: =INDEX(Countries!$R$1:$R$174,sel_row) | L44: =INDEX(Countries!$V$1:$V$174,sel_row) | M44: =INDEX(Countries!$AB$1:$AB$174,sel_row) | N44: =INDEX(Countries!$AC$1:$AC$174,sel_row) | O44: =INDEX(Countries!$AD$1:$AD$174,sel_row) | P44: =INDEX(Countries!$AE$1:$AE$174,sel_row)
B45: E = 1-(1-A_sub)(1-A_dem). A_sub = s_max(1-exp(-(tax+feebate)/switching price)): cleaner generation, driven by the marginal price. A_dem = |elasticity| x tariff rise: less use, driven by the tax only.
B46: F1 = tariff rise = pass-through x avg intensity x tax / tariff. F2 = bottom-40% budget share x F1 x (1 - rebate cover); full cover needs pass-through x residential share x q40 of revenue. | G46: Best feasible E in grid | H46: =MAX(IF(AND($M$44*$G28<=in_f1,$N$44*$G28<=in_f2,$O$44*$G28+$P$44*H$27<=in_f3),H28,0),IF(AND($M$44*$G28<=in_f1,$N$44*$G28<=in_f2,$O$44*$G28+$P$44*I$27<=in_f3),I28,0),IF(AND($M$44*$G28<=in_f1,$N$44*$G28<=in_f2,$O$44*$G28+$P$44*J$27<=in_f3),J28,0),IF(AND($M$44*$G28<=in_f1,$N$44*$G28<=in_f2,$O$44*$G28+$P$44*K$27<=in_f3),K28,0),IF(AND($M$44*$G28<=in_f1,$N$44*$G28<=in_f2,$O$44*$G28+$P$44*L$27<=in_f3),L28,0),IF(AND($M$44*$G28<=in_f1,$N$44*$G28<=in_f2,$O$44*$G28+$P$44*M$27<=in_f3),M28,0),IF(AND($M$44*$G28<=in_f1,$N$44*$G28<=in_f2,$O$44*$G28+$P$44*N$27<=in_f3),N28,0),IF(AND($M$44*$G28<=in_f1,$N$44*$G28<=in_f2,$O$44*$G28+$P$44*O$27<=in_f3),O28,0),IF(AND($M$44*$G28<=in_f1,$N$44*$G28<=in_f2,$O$44*$G28+$P$44*P$27<=in_f3),P28,0),IF(AND($M$44*$G28<=in_f1,$N$44*$G28<=in_f2,$O$44*$G28+$P$44*Q$27<=in_f3),Q28,0),IF(AND($M$44*$G28<=in_f1,$N$44*$G28<=in_f2,$O$44*$G28+$P$44*R$27<=in_f3),R28,0),IF(AND($M$44*$G29<=in_f1,$N$44*$G29<=in_f2,$O$44*$G29+$P$44*H$27<=in_f3),H29,0),IF(AND($M$44*$G29<=in_f1,$N$44*$G29<=in_f2,$O$44*$G29+$P$44*I$27<=in_f3),I29,0),IF(AND($M$44*$G29<=in_f1,$N$44*$G29<=in_f2,$O$44*$G29+$P$44*J$27<=in_f3),J29,0),IF(AND($M$44*$G29<=in_f1,$N$44*$G29<=in_f2,$O$44*$G29+$P$44*K$27<=in_f3),K29,0),IF(AND($M$44*$G29<=in_f1,$N$44*$G29<=in_f2,$O$44*$G29+$P$44*L$27<=in_f3),L29,0),IF(AND($M$44*$G29<=in_f1,$N$44*$G29<=in_f2,$O$44*$G29+$P$44*M$27<=in_f3),M29,0),IF(AND($M$44*$G29<=in_f1,$N$44*$G29<=in_f2,$O$44*$G29+$P$44*N$27<=in_f3),N29,0),IF(AND($M$44*$G29<=in_f1,$N$44*$G29<=in_f2,$O$44*$G29+$P$44*O$27<=in_f3),O29,0),IF(AND($M$44*$G29<=in_f1,$N$44*$G29<=in_f2,$O$44*$G29+$P$44*P$27<=in_f3),P29,0),IF(AND($M$44*$G29<=in_f1,$N$44*$G29<=in_f2,$O$44*$G29+$P$44*Q$27<=in_f3),Q29,0),IF(AND($M$44*$G29<=in_f1,$N$44*$G29<=in_f2,$O$44*$G29+$P$44*R$27<=in_f3),R29,0),IF(AND($M$44*$G30<=in_f1,$N$44*$G30<=in_f2,$O$44*$G30+$P$44*H$27<=in_f3),H30,0),IF(AND($M$44*$G30<=in_f1,$N$44*$G30<=in_f2,$O$44*$G30+$P$44*I$27<=in_f3),I30,0),IF(AND($M$44*$G30<=in_f1,$N$44*$G30<=in_f2,$O$44*$G30+$P$44*J$27<=in_f3),J30,0),IF(AND($M$44*$G30<=in_f1,$N$44*$G30<=in_f2,$O$44*$G30+$P$44*K$27<=in_f3),K30,0),IF(AND($M$44*$G30<=in_f1,$N$44*$G30<=in_f2,$O$44*$G30+$P$44*L$27<=in_f3),L30,0),IF(AND($M$44*$G30<=in_f1,$N$44*$G30<=in_f2,$O$44*$G30+$P$44*M$27<=in_f3),M30,0),IF(AND($M$44*$G30<=in_f1,$N$44*$G30<=in_f2,$O$44*$G30+$P$44*N$27<=in_f3),N30,0),IF(AND($M$44*$G30<=in_f1,$N$44*$G30<=in_f2,$O$44*$G30+$P$44*O$27<=in_f3),O30,0),IF(AND($M$44*$G30<=in_f1,$N$44*$G30<=in_f2,$O$44*$G30+$P$44*P$27<=in_f3),P30,0),IF(AND($M$44*$G30<=in_f1,$N$44*$G30<=in_f2,$O$44*$G30+$P$44*Q$27<=in_f3),Q30,0),IF(AND($M$44*$G30<=in_f1,$N$44*$G30<=in_f2,$O$44*$G30+$P$44*R$27<=in_f3),R30,0),IF(AND($M$44*$G31<=in_f1,$N$44*$G31<=in_f2,$O$44*$G31+$P$44*H$27<=in_f3),H31,0),IF(AND($M$44*$G31<=in_f1,$N$44*$G31<=in_f2,$O$44*$G31+$P$44*I$27<=in_f3),I31,0),IF(AND($M$44*$G31<=in_f1,$N$44*$G31<=in_f2,$O$44*$G31+$P$44*J$27<=in_f3),J31,0),IF(AND($M$44*$G31<=in_f1,$N$44*$G31<=in_f2,$O$44*$G31+$P$44*K$27<=in_f3),K31,0),IF(AND($M$44*$G31<=in_f1,$N$44*$G31<=in_f2,$O$44*$G31+$P$44*L$27<=in_f3),L31,0),IF(AND($M$44*$G31<=in_f1,$N$44*$G31<=in_f2,$O$44*$G31+$P$44*M$27<=in_f3),M31,0),IF(AND($M$44*$G31<=in_f1,$N$44*$G31<=in_f2,$O$44*$G31+$P$44*N$27<=in_f3),N31,0),IF(AND($M$44*$G31<=in_f1,$N$44*$G31<=in_f2,$O$44*$G31+$P$44*O$27<=in_f3),O31,0),IF(AND($M$44*$G31<=in_f1,$N$44*$G31<=in_f2,$O$44*$G31+$P$44*P$27<=in_f3),P31,0),IF(AND($M$44*$G31<=in_f1,$N$44*$G31<=in_f2,$O$44*$G31+$P$44*Q$27<=in_f3),Q31,0),IF(AND($M$44*$G31<=in_f1,$N$44*$G31<=in_f2,$O$44*$G31+$P$44*R$27<=in_f3),R31,0),IF(AND($M$44*$G32<=in_f1,$N$44*$G32<=in_f2,$O$44*$G32+$P$44*H$27<=in_f3),H32,0),IF(AND($M$44*$G32<=in_f1,$N$44*$G32<=in_f2,$O$44*$G32+$P$44*I$27<=in_f3),I32,0),IF(AND($M$44*$G32<=in_f1,$N$44*$G32<=in_f2,$O$44*$G32+$P$44*J$27<=in_f3),J32,0),IF(AND($M$44*$G32<=in_f1,$N$44*$G32<=in_f2,$O$44*$G32+$P$44*K$27<=in_f3),K32,0),IF(AND($M$44*$G32<=in_f1,$N$44*$G32<=in_f2,$O$44*$G32+$P$44*L$27<=in_f3),L32,0),IF(AND($M$44*$G32<=in_f1,$N$44*$G32<=in_f2,$O$44*$G32+$P$44*M$27<=in_f3),M32,0),IF(AND($M$44*$G32<=in_f1,$N$44*$G32<=in_f2,$O$44*$G32+$P$44*N$27<=in_f3),N32,0),IF(AND($M$44*$G32<=in_f1,$N$44*$G32<=in_f2,$O$44*$G32+$P$44*O$27<=in_f3),O32,0),IF(AND($M$44*$G32<=in_f1,$N$44*$G32<=in_f2,$O$44*$G32+$P$44*P$27<=in_f3),P32,0),IF(AND($M$44*$G32<=in_f1,$N$44*$G32<=in_f2,$O$44*$G32+$P$44*Q$27<=in_f3),Q32,0),IF(AND($M$44*$G32<=in_f1,$N$44*$G32<=in_f2,$O$44*$G32+$P$44*R$27<=in_f3),R32,0),IF(AND($M$44*$G33<=in_f1,$N$44*$G33<=in_f2,$O$44*$G33+$P$44*H$27<=in_f3),H33,0),IF(AND($M$44*$G33<=in_f1,$N$44*$G33<=in_f2,$O$44*$G33+$P$44*I$27<=in_f3),I33,0),IF(AND($M$44*$G33<=in_f1,$N$44*$G33<=in_f2,$O$44*$G33+$P$44*J$27<=in_f3),J33,0),IF(AND($M$44*$G33<=in_f1,$N$44*$G33<=in_f2,$O$44*$G33+$P$44*K$27<=in_f3),K33,0),IF(AND($M$44*$G33<=in_f1,$N$44*$G33<=in_f2,$O$44*$G33+$P$44*L$27<=in_f3),L33,0),IF(AND($M$44*$G33<=in_f1,$N$44*$G33<=in_f2,$O$44*$G33+$P$44*M$27<=in_f3),M33,0),IF(AND($M$44*$G33<=in_f1,$N$44*$G33<=in_f2,$O$44*$G33+$P$44*N$27<=in_f3),N33,0),IF(AND($M$44*$G33<=in_f1,$N$44*$G33<=in_f2,$O$44*$G33+$P$44*O$27<=in_f3),O33,0),IF(AND($M$44*$G33<=in_f1,$N$44*$G33<=in_f2,$O$44*$G33+$P$44*P$27<=in_f3),P33,0),IF(AND($M$44*$G33<=in_f1,$N$44*$G33<=in_f2,$O$44*$G33+$P$44*Q$27<=in_f3),Q33,0),IF(AND($M$44*$G33<=in_f1,$N$44*$G33<=in_f2,$O$44*$G33+$P$44*R$27<=in_f3),R33,0),IF(AND($M$44*$G34<=in_f1,$N$44*$G34<=in_f2,$O$44*$G34+$P$44*H$27<=in_f3),H34,0),IF(AND($M$44*$G34<=in_f1,$N$44*$G34<=in_f2,$O$44*$G34+$P$44*I$27<=in_f3),I34,0),IF(AND($M$44*$G34<=in_f1,$N$44*$G34<=in_f2,$O$44*$G34+$P$44*J$27<=in_f3),J34,0),IF(AND($M$44*$G34<=in_f1,$N$44*$G34<=in_f2,$O$44*$G34+$P$44*K$27<=in_f3),K34,0),IF(AND($M$44*$G34<=in_f1,$N$44*$G34<=in_f2,$O$44*$G34+$P$44*L$27<=in_f3),L34,0),IF(AND($M$44*$G34<=in_f1,$N$44*$G34<=in_f2,$O$44*$G34+$P$44*M$27<=in_f3),M34,0),IF(AND($M$44*$G34<=in_f1,$N$44*$G34<=in_f2,$O$44*$G34+$P$44*N$27<=in_f3),N34,0),IF(AND($M$44*$G34<=in_f1,$N$44*$G34<=in_f2,$O$44*$G34+$P$44*O$27<=in_f3),O34,0),IF(AND($M$44*$G34<=in_f1,$N$44*$G34<=in_f2,$O$44*$G34+$P$44*P$27<=in_f3),P34,0),IF(AND($M$44*$G34<=in_f1,$N$44*$G34<=in_f2,$O$44*$G34+$P$44*Q$27<=in_f3),Q34,0),IF(AND($M$44*$G34<=in_f1,$N$44*$G34<=in_f2,$O$44*$G34+$P$44*R$27<=in_f3),R34,0),IF(AND($M$44*$G35<=in_f1,$N$44*$G35<=in_f2,$O$44*$G35+$P$44*H$27<=in_f3),H35,0),IF(AND($M$44*$G35<=in_f1,$N$44*$G35<=in_f2,$O$44*$G35+$P$44*I$27<=in_f3),I35,0),IF(AND($M$44*$G35<=in_f1,$N$44*$G35<=in_f2,$O$44*$G35+$P$44*J$27<=in_f3),J35,0),IF(AND($M$44*$G35<=in_f1,$N$44*$G35<=in_f2,$O$44*$G35+$P$44*K$27<=in_f3),K35,0),IF(AND($M$44*$G35<=in_f1,$N$44*$G35<=in_f2,$O$44*$G35+$P$44*L$27<=in_f3),L35,0),IF(AND($M$44*$G35<=in_f1,$N$44*$G35<=in_f2,$O$44*$G35+$P$44*M$27<=in_f3),M35,0),IF(AND($M$44*$G35<=in_f1,$N$44*$G35<=in_f2,$O$44*$G35+$P$44*N$27<=in_f3),N35,0),IF(AND($M$44*$G35<=in_f1,$N$44*$G35<=in_f2,$O$44*$G35+$P$44*O$27<=in_f3),O35,0),IF(AND($M$44*$G35<=in_f1,$N$44*$G35<=in_f2,$O$44*$G35+$P$44*P$27<=in_f3),P35,0),IF(AND($M$44*$G35<=in_f1,$N$44*$G35<=in_f2,$O$44*$G35+$P$44*Q$27<=in_f3),Q35,0),IF(AND($M$44*$G35<=in_f1,$N$44*$G35<=in_f2,$O$44*$G35+$P$44*R$27<=in_f3),R35,0),IF(AND($M$44*$G36<=in_f1,$N$44*$G36<=in_f2,$O$44*$G36+$P$44*H$27<=in_f3),H36,0),IF(AND($M$44*$G36<=in_f1,$N$44*$G36<=in_f2,$O$44*$G36+$P$44*I$27<=in_f3),I36,0),IF(AND($M$44*$G36<=in_f1,$N$44*$G36<=in_f2,$O$44*$G36+$P$44*J$27<=in_f3),J36,0),IF(AND($M$44*$G36<=in_f1,$N$44*$G36<=in_f2,$O$44*$G36+$P$44*K$27<=in_f3),K36,0),IF(AND($M$44*$G36<=in_f1,$N$44*$G36<=in_f2,$O$44*$G36+$P$44*L$27<=in_f3),L36,0),IF(AND($M$44*$G36<=in_f1,$N$44*$G36<=in_f2,$O$44*$G36+$P$44*M$27<=in_f3),M36,0),IF(AND($M$44*$G36<=in_f1,$N$44*$G36<=in_f2,$O$44*$G36+$P$44*N$27<=in_f3),N36,0),IF(AND($M$44*$G36<=in_f1,$N$44*$G36<=in_f2,$O$44*$G36+$P$44*O$27<=in_f3),O36,0),IF(AND($M$44*$G36<=in_f1,$N$44*$G36<=in_f2,$O$44*$G36+$P$44*P$27<=in_f3),P36,0),IF(AND($M$44*$G36<=in_f1,$N$44*$G36<=in_f2,$O$44*$G36+$P$44*Q$27<=in_f3),Q36,0),IF(AND($M$44*$G36<=in_f1,$N$44*$G36<=in_f2,$O$44*$G36+$P$44*R$27<=in_f3),R36,0),IF(AND($M$44*$G37<=in_f1,$N$44*$G37<=in_f2,$O$44*$G37+$P$44*H$27<=in_f3),H37,0),IF(AND($M$44*$G37<=in_f1,$N$44*$G37<=in_f2,$O$44*$G37+$P$44*I$27<=in_f3),I37,0),IF(AND($M$44*$G37<=in_f1,$N$44*$G37<=in_f2,$O$44*$G37+$P$44*J$27<=in_f3),J37,0),IF(AND($M$44*$G37<=in_f1,$N$44*$G37<=in_f2,$O$44*$G37+$P$44*K$27<=in_f3),K37,0),IF(AND($M$44*$G37<=in_f1,$N$44*$G37<=in_f2,$O$44*$G37+$P$44*L$27<=in_f3),L37,0),IF(AND($M$44*$G37<=in_f1,$N$44*$G37<=in_f2,$O$44*$G37+$P$44*M$27<=in_f3),M37,0),IF(AND($M$44*$G37<=in_f1,$N$44*$G37<=in_f2,$O$44*$G37+$P$44*N$27<=in_f3),N37,0),IF(AND($M$44*$G37<=in_f1,$N$44*$G37<=in_f2,$O$44*$G37+$P$44*O$27<=in_f3),O37,0),IF(AND($M$44*$G37<=in_f1,$N$44*$G37<=in_f2,$O$44*$G37+$P$44*P$27<=in_f3),P37,0),IF(AND($M$44*$G37<=in_f1,$N$44*$G37<=in_f2,$O$44*$G37+$P$44*Q$27<=in_f3),Q37,0),IF(AND($M$44*$G37<=in_f1,$N$44*$G37<=in_f2,$O$44*$G37+$P$44*R$27<=in_f3),R37,0),IF(AND($M$44*$G38<=in_f1,$N$44*$G38<=in_f2,$O$44*$G38+$P$44*H$27<=in_f3),H38,0),IF(AND($M$44*$G38<=in_f1,$N$44*$G38<=in_f2,$O$44*$G38+$P$44*I$27<=in_f3),I38,0),IF(AND($M$44*$G38<=in_f1,$N$44*$G38<=in_f2,$O$44*$G38+$P$44*J$27<=in_f3),J38,0),IF(AND($M$44*$G38<=in_f1,$N$44*$G38<=in_f2,$O$44*$G38+$P$44*K$27<=in_f3),K38,0),IF(AND($M$44*$G38<=in_f1,$N$44*$G38<=in_f2,$O$44*$G38+$P$44*L$27<=in_f3),L38,0),IF(AND($M$44*$G38<=in_f1,$N$44*$G38<=in_f2,$O$44*$G38+$P$44*M$27<=in_f3),M38,0),IF(AND($M$44*$G38<=in_f1,$N$44*$G38<=in_f2,$O$44*$G38+$P$44*N$27<=in_f3),N38,0),IF(AND($M$44*$G38<=in_f1,$N$44*$G38<=in_f2,$O$44*$G38+$P$44*O$27<=in_f3),O38,0),IF(AND($M$44*$G38<=in_f1,$N$44*$G38<=in_f2,$O$44*$G38+$P$44*P$27<=in_f3),P38,0),IF(AND($M$44*$G38<=in_f1,$N$44*$G38<=in_f2,$O$44*$G38+$P$44*Q$27<=in_f3),Q38,0),IF(AND($M$44*$G38<=in_f1,$N$44*$G38<=in_f2,$O$44*$G38+$P$44*R$27<=in_f3),R38,0))
B47: F3 = [tax x coal/oil intensity x (1-pass-through) + feebate x (coal/oil intensity - average)] / wholesale price: what coal and oil generators pay.
B48: Data: same long format as the dashboard's global_data_long.csv. To refresh, paste new rows on Data (same columns); add a country by adding its ISO3 in Countries col A and copying a row down.
B49: Screening only. Priors above are placeholders. One sector, one period (~2030). Python version and method: price_feasibility.py, README.md, NOTES.md.

Sheet Countries
A1: Countries: all metrics are live formulas on the Data tab and the Screen inputs
A2: Rates in $/tCO2. E = abatement, % of baseline fossil power CO2. Hybrid: tax searched in 11 steps up to its cap; feebate fills the remaining F3 room.
A3: Country | D3: Data | Q3: Parameters | AB3: Coefficients | AF3: Tax only | AM3: Feebate only | AP3: At $50/t | AT3: Hybrid (best mix) | BB3: Hybrid search: feebate | BM3: Hybrid search: E
A4: ISO3 | B4: Country | C4: Income | D4: Coal gen TWh | E4: Gas gen TWh | F4: Oil gen TWh | G4: Total gen TWh | H4: Coal CO2 Mt | I4: Gas CO2 Mt | J4: Oil CO2 Mt | K4: Res. tariff $/kWh | L4: Coal price power $/GJ | M4: Gas price power $/GJ | N4: Gas price ind. $/GJ | O4: Market structure (PSRT) | P4: RISE RE score | Q4: Baseline CO2 Mt | R4: Avg intensity t/MWh | S4: Coal t/MWh | T4: Gas t/MWh | U4: Coal+oil t/MWh | V4: Tariff $/MWh | W4: Pass-through | X4: Max substitution share | Y4: Switching price $/t | Z4: B40 elec. budget share | AA4: Coal+oil gen share | AB4: F1 per $ tax | AC4: F2 per $ tax | AD4: F3 per $ tax | AE4: F3 per $ feebate | AF4: Tax cap from F1 | AG4: Tax cap from F2 | AH4: Tax cap from F3 | AI4: Best tax $/t | AJ4: Tax: E % | AK4: Tax: binding | AL4: Tax: +1pp F1 buys (pp E) | AM4: Best feebate $/t | AN4: Feebate: E % | AO4: Feebate: binding | AP4: E at $50 tax | AQ4: E at $50 feebate | AR4: Feebate/tax abatement ratio | AS4: F1 at $50 tax | AT4: Hybrid: E % | AU4: Hybrid: tax $/t | AV4: Hybrid: feebate $/t | AW4: Hybrid: F1 | AX4: Hybrid: F2 | AY4: Hybrid: F3 | AZ4: Hybrid: binding | BA4: Hybrid: Mt saved | BB4: Feebate at k=0 | BC4: Feebate at k=1 | BD4: Feebate at k=2 | BE4: Feebate at k=3 | BF4: Feebate at k=4 | BG4: Feebate at k=5 | BH4: Feebate at k=6 | BI4: Feebate at k=7 | BJ4: Feebate at k=8 | BK4: Feebate at k=9 | BL4: Feebate at k=10 | BM4: E at k=0 | BN4: E at k=1 | BO4: E at k=2 | BP4: E at k=3 | BQ4: E at k=4 | BR4: E at k=5 | BS4: E at k=6 | BT4: E at k=7 | BU4: E at k=8 | BV4: E at k=9 | BW4: E at k=10
A5: ABW | B5: =INDEX(Data!$B:$B,MATCH($A5,Data!$A:$A,0)) | C5: =INDEX(Data!$D:$D,MATCH($A5,Data!$A:$A,0)) | D5: =SUMIFS(Data!$G:$G,Data!$A:$A,$A5,Data!$F:$F,"gen_coal_twh") | E5: =SUMIFS(Data!$G:$G,Data!$A:$A,$A5,Data!$F:$F,"gen_gas_twh") | F5: =SUMIFS(Data!$G:$G,Data!$A:$A,$A5,Data!$F:$F,"gen_oil_twh") | G5: =SUMIFS(Data!$G:$G,Data!$A:$A,$A5,Data!$F:$F,"gen_total_twh") | H5: =SUMIFS(Data!$G:$G,Data!$A:$A,$A5,Data!$F:$F,"em_coal_mt") | I5: =SUMIFS(Data!$G:$G,Data!$A:$A,$A5,Data!$F:$F,"em_gas_mt") | J5: =SUMIFS(Data!$G:$G,Data!$A:$A,$A5,Data!$F:$F,"em_oil_mt") | K5: =IF(COUNTIFS(Data!$A:$A,$A5,Data!$F:$F,"price_electricity_residential_usd_kwh")=0,"",SUMIFS(Data!$G:$G,Data!$A:$A,$A5,Data!$F:$F,"price_electricity_residential_usd_kwh")) | L5: =IF(COUNTIFS(Data!$A:$A,$A5,Data!$F:$F,"price_coal_power_usd_gj")=0,"",SUMIFS(Data!$G:$G,Data!$A:$A,$A5,Data!$F:$F,"price_coal_power_usd_gj")) | M5: =IF(COUNTIFS(Data!$A:$A,$A5,Data!$F:$F,"price_gas_power_usd_gj")=0,"",SUMIFS(Data!$G:$G,Data!$A:$A,$A5,Data!$F:$F,"price_gas_power_usd_gj")) | N5: =IF(COUNTIFS(Data!$A:$A,$A5,Data!$F:$F,"price_gas_industry_usd_gj")=0,"",SUMIFS(Data!$G:$G,Data!$A:$A,$A5,Data!$F:$F,"price_gas_industry_usd_gj")) | O5: =IF(COUNTIFS(Data!$A:$A,$A5,Data!$F:$F,"power_market_structure")=0,"",SUMIFS(Data!$G:$G,Data!$A:$A,$A5,Data!$F:$F,"power_market_structure")) | P5: =IF(COUNTIFS(Data!$A:$A,$A5,Data!$F:$F,"rise_renewable_energy_score")=0,"",SUMIFS(Data!$G:$G,Data!$A:$A,$A5,Data!$F:$F,"rise_renewable_energy_score")) | Q5: =H5+I5+J5 | R5: =Q5/G5 | S5: =IF(D5>0,H5/D5,0.85) | T5: =IF(E5>0,I5/E5,0.4) | U5: =IF(D5+F5>0,(H5+J5)/(D5+F5),0) | V5: =K5*1000 | W5: =IF(O5=3,in_pt3,IF(O5=2,in_pt2,IF(O5=1,in_pt1,IF(C5="High income",in_pt_hi,in_pt_oth)))) | X5: =IF(Q5>0,in_kappa*(in_rise_lo+(in_rise_hi-in_rise_lo)*IF(P5="",in_rise_miss,P5)/100)*(D5+F5)*MAX(U5-in_gas_rep*T5,0)/Q5,0) | Y5: =IF(IF(M5="",N5,M5)="",MAX(in_sw_floor,in_sw_miss),MAX(in_sw_floor,(IF(M5="",N5,M5)*in_hr_gas-L5*in_hr_coal)/MAX(S5-T5,0.1))) | Z5: =IF(C5="Low income",in_b40_li,IF(C5="Lower middle income",in_b40_lmi,IF(C5="Upper middle income",in_b40_umi,IF(C5="High income",in_b40_hi,0.03)))) | AA5: =(D5+F5)/G5 | AB5: =100*W5*R5/V5/in_phase | AC5: =100*Z5*W5*R5/V5*(1-IF(W5>0,MIN(in_rebate/(W5*in_res_sh*in_q40),1),1)) | AD5: =IF(AA5>0,100*U5*(1-W5)/(in_whole_sh*V5),0) | AE5: =IF(AA5>0,100*MAX(U5-R5,0)/(in_whole_sh*V5),0) | AF5: =IF(AB5>0,in_f1/AB5,in_cap) | AG5: =IF(AC5>0,in_f2/AC5,in_cap) | AH5: =IF(AD5>0,in_f3/AD5,in_cap) | AI5: =MIN(in_cap,AF5,AG5,AH5) | AJ5: =100*(1-(1-X5*(1-EXP(-((AI5)+(0))/Y5)))*(1-MIN(ABS(in_elas)*W5*R5*(AI5)/V5,1))) | AK5: =IF(AI5>=in_cap-1E-9,"rate cap",TRIM(IF(ABS(AI5-AF5)<1E-9,"F1 ","")&IF(ABS(AI5-AG5)<1E-9,"F2 ","")&IF(ABS(AI5-AH5)<1E-9,"F3",""))) | AL5: =100*(1-(1-X5*(1-EXP(-((MIN(in_cap,IF(AB5>0,(in_f1+1)/AB5,in_cap),AG5,AH5))+(0))/Y5)))*(1-MIN(ABS(in_elas)*W5*R5*(MIN(in_cap,IF(AB5>0,(in_f1+1)/AB5,in_cap),AG5,AH5))/V5,1)))-AJ5 | AM5: =MIN(in_cap,IF(AE5>0,in_f3/AE5,in_cap)) | AN5: =100*(1-(1-X5*(1-EXP(-((0)+(AM5))/Y5)))*(1-MIN(ABS(in_elas)*W5*R5*(0)/V5,1))) | AO5: =IF(AM5>=in_cap-1E-9,"rate cap","F3") | AP5: =100*(1-(1-X5*(1-EXP(-((50)+(0))/Y5)))*(1-MIN(ABS(in_elas)*W5*R5*(50)/V5,1))) | AQ5: =100*(1-(1-X5*(1-EXP(-((0)+(50))/Y5)))*(1-MIN(ABS(in_elas)*W5*R5*(0)/V5,1))) | AR5: =IF(AP5>0,AQ5/AP5,"") | AS5: =50*AB5 | AT5: =MAX(BM5:BW5) | AU5: =AI5*(MATCH(AT5,BM5:BW5,0)-1)/10 | AV5: =INDEX(BB5:BL5,1,(MATCH(AT5,BM5:BW5,0)-1)+1) | AW5: =AB5*AU5 | AX5: =AC5*AU5 | AY5: =AD5*AU5+AE5*AV5 | AZ5: =TRIM(IF(AND(AU5>0,ABS(AU5-AF5)<1E-6),"F1 ","")&IF(AND(AU5>0,ABS(AU5-AG5)<1E-6),"F2 ","")&IF(AY5>=in_f3-1E-6,"F3 ","")&IF(AV5>=in_cap-1E-9,"rate cap","")) | BA5: =Q5*AT5/100 | BB5: =MAX(0,MIN(in_cap,IF(AE5>0,(in_f3-AD5*AI5*0/10)/AE5,in_cap))) | BC5: =MAX(0,MIN(in_cap,IF(AE5>0,(in_f3-AD5*AI5*1/10)/AE5,in_cap))) | BD5: =MAX(0,MIN(in_cap,IF(AE5>0,(in_f3-AD5*AI5*2/10)/AE5,in_cap))) | BE5: =MAX(0,MIN(in_cap,IF(AE5>0,(in_f3-AD5*AI5*3/10)/AE5,in_cap))) | BF5: =MAX(0,MIN(in_cap,IF(AE5>0,(in_f3-AD5*AI5*4/10)/AE5,in_cap))) | BG5: =MAX(0,MIN(in_cap,IF(AE5>0,(in_f3-AD5*AI5*5/10)/AE5,in_cap))) | BH5: =MAX(0,MIN(in_cap,IF(AE5>0,(in_f3-AD5*AI5*6/10)/AE5,in_cap))) | BI5: =MAX(0,MIN(in_cap,IF(AE5>0,(in_f3-AD5*AI5*7/10)/AE5,in_cap))) | BJ5: =MAX(0,MIN(in_cap,IF(AE5>0,(in_f3-AD5*AI5*8/10)/AE5,in_cap))) | BK5: =MAX(0,MIN(in_cap,IF(AE5>0,(in_f3-AD5*AI5*9/10)/AE5,in_cap))) | BL5: =MAX(0,MIN(in_cap,IF(AE5>0,(in_f3-AD5*AI5*10/10)/AE5,in_cap))) | BM5: =100*(1-(1-X5*(1-EXP(-((AI5*0/10)+(BB5))/Y5)))*(1-MIN(ABS(in_elas)*W5*R5*(AI5*0/10)/V5,1))) | BN5: =100*(1-(1-X5*(1-EXP(-((AI5*1/10)+(BC5))/Y5)))*(1-MIN(ABS(in_elas)*W5*R5*(AI5*1/10)/V5,1))) | BO5: =100*(1-(1-X5*(1-EXP(-((AI5*2/10)+(BD5))/Y5)))*(1-MIN(ABS(in_elas)*W5*R5*(AI5*2/10)/V5,1))) | BP5: =100*(1-(1-X5*(1-EXP(-((AI5*3/10)+(BE5))/Y5)))*(1-MIN(ABS(in_elas)*W5*R5*(AI5*3/10)/V5,1))) | BQ5: =100*(1-(1-X5*(1-EXP(-((AI5*4/10)+(BF5))/Y5)))*(1-MIN(ABS(in_elas)*W5*R5*(AI5*4/10)/V5,1))) | BR5: =100*(1-(1-X5*(1-EXP(-((AI5*5/10)+(BG5))/Y5)))*(1-MIN(ABS(in_elas)*W5*R5*(AI5*5/10)/V5,1))) | BS5: =100*(1-(1-X5*(1-EXP(-((AI5*6/10)+(BH5))/Y5)))*(1-MIN(ABS(in_elas)*W5*R5*(AI5*6/10)/V5,1))) | BT5: =100*(1-(1-X5*(1-EXP(-((AI5*7/10)+(BI5))/Y5)))*(1-MIN(ABS(in_elas)*W5*R5*(AI5*7/10)/V5,1))) | BU5: =100*(1-(1-X5*(1-EXP(-((AI5*8/10)+(BJ5))/Y5)))*(1-MIN(ABS(in_elas)*W5*R5*(AI5*8/10)/V5,1))) | BV5: =100*(1-(1-X5*(1-EXP(-((AI5*9/10)+(BK5))/Y5)))*(1-MIN(ABS(in_elas)*W5*R5*(AI5*9/10)/V5,1))) | BW5: =100*(1-(1-X5*(1-EXP(-((AI5*10/10)+(BL5))/Y5)))*(1-MIN(ABS(in_elas)*W5*R5*(AI5*10/10)/V5,1)))
A6: AFG | B6: =INDEX(Data!$B:$B,MATCH($A6,Data!$A:$A,0)) | C6: =INDEX(Data!$D:$D,MATCH($A6,Data!$A:$A,0)) | D6: =SUMIFS(Data!$G:$G,Data!$A:$A,$A6,Data!$F:$F,"gen_coal_twh") | E6: =SUMIFS(Data!$G:$G,Data!$A:$A,$A6,Data!$F:$F,"gen_gas_twh") | F6: =SUMIFS(Data!$G:$G,Data!$A:$A,$A6,Data!$F:$F,"gen_oil_twh") | G6: =SUMIFS(Data!$G:$G,Data!$A:$A,$A6,Data!$F:$F,"gen_total_twh") | H6: =SUMIFS(Data!$G:$G,Data!$A:$A,$A6,Data!$F:$F,"em_coal_mt") | I6: =SUMIFS(Data!$G:$G,Data!$A:$A,$A6,Data!$F:$F,"em_gas_mt") | J6: =SUMIFS(Data!$G:$G,Data!$A:$A,$A6,Data!$F:$F,"em_oil_mt") | K6: =IF(COUNTIFS(Data!$A:$A,$A6,Data!$F:$F,"price_electricity_residential_usd_kwh")=0,"",SUMIFS(Data!$G:$G,Data!$A:$A,$A6,Data!$F:$F,"price_electricity_residential_usd_kwh")) | L6: =IF(COUNTIFS(Data!$A:$A,$A6,Data!$F:$F,"price_coal_power_usd_gj")=0,"",SUMIFS(Data!$G:$G,Data!$A:$A,$A6,Data!$F:$F,"price_coal_power_usd_gj")) | M6: =IF(COUNTIFS(Data!$A:$A,$A6,Data!$F:$F,"price_gas_power_usd_gj")=0,"",SUMIFS(Data!$G:$G,Data!$A:$A,$A6,Data!$F:$F,"price_gas_power_usd_gj")) | N6: =IF(COUNTIFS(Data!$A:$A,$A6,Data!$F:$F,"price_gas_industry_usd_gj")=0,"",SUMIFS(Data!$G:$G,Data!$A:$A,$A6,Data!$F:$F,"price_gas_industry_usd_gj")) | O6: =IF(COUNTIFS(Data!$A:$A,$A6,Data!$F:$F,"power_market_structure")=0,"",SUMIFS(Data!$G:$G,Data!$A:$A,$A6,Data!$F:$F,"power_market_structure")) | P6: =IF(COUNTIFS(Data!$A:$A,$A6,Data!$F:$F,"rise_renewable_energy_score")=0,"",SUMIFS(Data!$G:$G,Data!$A:$A,$A6,Data!$F:$F,"rise_renewable_energy_score")) | Q6: =H6+I6+J6 | R6: =Q6/G6 | S6: =IF(D6>0,H6/D6,0.85) | T6: =IF(E6>0,I6/E6,0.4) | U6: =IF(D6+F6>0,(H6+J6)/(D6+F6),0) | V6: =K6*1000 | W6: =IF(O6=3,in_pt3,IF(O6=2,in_pt2,IF(O6=1,in_pt1,IF(C6="High income",in_pt_hi,in_pt_oth)))) | X6: =IF(Q6>0,in_kappa*(in_rise_lo+(in_rise_hi-in_rise_lo)*IF(P6="",in_rise_miss,P6)/100)*(D6+F6)*MAX(U6-in_gas_rep*T6,0)/Q6,0) | Y6: =IF(IF(M6="",N6,M6)="",MAX(in_sw_floor,in_sw_miss),MAX(in_sw_floor,(IF(M6="",N6,M6)*in_hr_gas-L6*in_hr_coal)/MAX(S6-T6,0.1))) | Z6: =IF(C6="Low income",in_b40_li,IF(C6="Lower middle income",in_b40_lmi,IF(C6="Upper middle income",in_b40_umi,IF(C6="High income",in_b40_hi,0.03)))) | AA6: =(D6+F6)/G6 | AB6: =100*W6*R6/V6/in_phase | AC6: =100*Z6*W6*R6/V6*(1-IF(W6>0,MIN(in_rebate/(W6*in_res_sh*in_q40),1),1)) | AD6: =IF(AA6>0,100*U6*(1-W6)/(in_whole_sh*V6),0) | AE6: =IF(AA6>0,100*MAX(U6-R6,0)/(in_whole_sh*V6),0) | AF6: =IF(AB6>0,in_f1/AB6,in_cap) | AG6: =IF(AC6>0,in_f2/AC6,in_cap) | AH6: =IF(AD6>0,in_f3/AD6,in_cap) | AI6: =MIN(in_cap,AF6,AG6,AH6) | AJ6: =100*(1-(1-X6*(1-EXP(-((AI6)+(0))/Y6)))*(1-MIN(ABS(in_elas)*W6*R6*(AI6)/V6,1))) | AK6: =IF(AI6>=in_cap-1E-9,"rate cap",TRIM(IF(ABS(AI6-AF6)<1E-9,"F1 ","")&IF(ABS(AI6-AG6)<1E-9,"F2 ","")&IF(ABS(AI6-AH6)<1E-9,"F3",""))) | AL6: =100*(1-(1-X6*(1-EXP(-((MIN(in_cap,IF(AB6>0,(in_f1+1)/AB6,in_cap),AG6,AH6))+(0))/Y6)))*(1-MIN(ABS(in_elas)*W6*R6*(MIN(in_cap,IF(AB6>0,(in_f1+1)/AB6,in_cap),AG6,AH6))/V6,1)))-AJ6 | AM6: =MIN(in_cap,IF(AE6>0,in_f3/AE6,in_cap)) | AN6: =100*(1-(1-X6*(1-EXP(-((0)+(AM6))/Y6)))*(1-MIN(ABS(in_elas)*W6*R6*(0)/V6,1))) | AO6: =IF(AM6>=in_cap-1E-9,"rate cap","F3") | AP6: =100*(1-(1-X6*(1-EXP(-((50)+(0))/Y6)))*(1-MIN(ABS(in_elas)*W6*R6*(50)/V6,1))) | AQ6: =100*(1-(1-X6*(1-EXP(-((0)+(50))/Y6)))*(1-MIN(ABS(in_elas)*W6*R6*(0)/V6,1))) | AR6: =IF(AP6>0,AQ6/AP6,"") | AS6: =50*AB6 | AT6: =MAX(BM6:BW6) | AU6: =AI6*(MATCH(AT6,BM6:BW6,0)-1)/10 | AV6: =INDEX(BB6:BL6,1,(MATCH(AT6,BM6:BW6,0)-1)+1) | AW6: =AB6*AU6 | AX6: =AC6*AU6 | AY6: =AD6*AU6+AE6*AV6 | AZ6: =TRIM(IF(AND(AU6>0,ABS(AU6-AF6)<1E-6),"F1 ","")&IF(AND(AU6>0,ABS(AU6-AG6)<1E-6),"F2 ","")&IF(AY6>=in_f3-1E-6,"F3 ","")&IF(AV6>=in_cap-1E-9,"rate cap","")) | BA6: =Q6*AT6/100 | BB6: =MAX(0,MIN(in_cap,IF(AE6>0,(in_f3-AD6*AI6*0/10)/AE6,in_cap))) | BC6: =MAX(0,MIN(in_cap,IF(AE6>0,(in_f3-AD6*AI6*1/10)/AE6,in_cap))) | BD6: =MAX(0,MIN(in_cap,IF(AE6>0,(in_f3-AD6*AI6*2/10)/AE6,in_cap))) | BE6: =MAX(0,MIN(in_cap,IF(AE6>0,(in_f3-AD6*AI6*3/10)/AE6,in_cap))) | BF6: =MAX(0,MIN(in_cap,IF(AE6>0,(in_f3-AD6*AI6*4/10)/AE6,in_cap))) | BG6: =MAX(0,MIN(in_cap,IF(AE6>0,(in_f3-AD6*AI6*5/10)/AE6,in_cap))) | BH6: =MAX(0,MIN(in_cap,IF(AE6>0,(in_f3-AD6*AI6*6/10)/AE6,in_cap))) | BI6: =MAX(0,MIN(in_cap,IF(AE6>0,(in_f3-AD6*AI6*7/10)/AE6,in_cap))) | BJ6: =MAX(0,MIN(in_cap,IF(AE6>0,(in_f3-AD6*AI6*8/10)/AE6,in_cap))) | BK6: =MAX(0,MIN(in_cap,IF(AE6>0,(in_f3-AD6*AI6*9/10)/AE6,in_cap))) | BL6: =MAX(0,MIN(in_cap,IF(AE6>0,(in_f3-AD6*AI6*10/10)/AE6,in_cap))) | BM6: =100*(1-(1-X6*(1-EXP(-((AI6*0/10)+(BB6))/Y6)))*(1-MIN(ABS(in_elas)*W6*R6*(AI6*0/10)/V6,1))) | BN6: =100*(1-(1-X6*(1-EXP(-((AI6*1/10)+(BC6))/Y6)))*(1-MIN(ABS(in_elas)*W6*R6*(AI6*1/10)/V6,1))) | BO6: =100*(1-(1-X6*(1-EXP(-((AI6*2/10)+(BD6))/Y6)))*(1-MIN(ABS(in_elas)*W6*R6*(AI6*2/10)/V6,1))) | BP6: =100*(1-(1-X6*(1-EXP(-((AI6*3/10)+(BE6))/Y6)))*(1-MIN(ABS(in_elas)*W6*R6*(AI6*3/10)/V6,1))) | BQ6: =100*(1-(1-X6*(1-EXP(-((AI6*4/10)+(BF6))/Y6)))*(1-MIN(ABS(in_elas)*W6*R6*(AI6*4/10)/V6,1))) | BR6: =100*(1-(1-X6*(1-EXP(-((AI6*5/10)+(BG6))/Y6)))*(1-MIN(ABS(in_elas)*W6*R6*(AI6*5/10)/V6,1))) | BS6: =100*(1-(1-X6*(1-EXP(-((AI6*6/10)+(BH6))/Y6)))*(1-MIN(ABS(in_elas)*W6*R6*(AI6*6/10)/V6,1))) | BT6: =100*(1-(1-X6*(1-EXP(-((AI6*7/10)+(BI6))/Y6)))*(1-MIN(ABS(in_elas)*W6*R6*(AI6*7/10)/V6,1))) | BU6: =100*(1-(1-X6*(1-EXP(-((AI6*8/10)+(BJ6))/Y6)))*(1-MIN(ABS(in_elas)*W6*R6*(AI6*8/10)/V6,1))) | BV6: =100*(1-(1-X6*(1-EXP(-((AI6*9/10)+(BK6))/Y6)))*(1-MIN(ABS(in_elas)*W6*R6*(AI6*9/10)/V6,1))) | BW6: =100*(1-(1-X6*(1-EXP(-((AI6*10/10)+(BL6))/Y6)))*(1-MIN(ABS(in_elas)*W6*R6*(AI6*10/10)/V6,1)))
A7: AGO | B7: =INDEX(Data!$B:$B,MATCH($A7,Data!$A:$A,0)) | C7: =INDEX(Data!$D:$D,MATCH($A7,Data!$A:$A,0)) | D7: =SUMIFS(Data!$G:$G,Data!$A:$A,$A7,Data!$F:$F,"gen_coal_twh") | E7: =SUMIFS(Data!$G:$G,Data!$A:$A,$A7,Data!$F:$F,"gen_gas_twh") | F7: =SUMIFS(Data!$G:$G,Data!$A:$A,$A7,Data!$F:$F,"gen_oil_twh") | G7: =SUMIFS(Data!$G:$G,Data!$A:$A,$A7,Data!$F:$F,"gen_total_twh") | H7: =SUMIFS(Data!$G:$G,Data!$A:$A,$A7,Data!$F:$F,"em_coal_mt") | I7: =SUMIFS(Data!$G:$G,Data!$A:$A,$A7,Data!$F:$F,"em_gas_mt") | J7: =SUMIFS(Data!$G:$G,Data!$A:$A,$A7,Data!$F:$F,"em_oil_mt") | K7: =IF(COUNTIFS(Data!$A:$A,$A7,Data!$F:$F,"price_electricity_residential_usd_kwh")=0,"",SUMIFS(Data!$G:$G,Data!$A:$A,$A7,Data!$F:$F,"price_electricity_residential_usd_kwh")) | L7: =IF(COUNTIFS(Data!$A:$A,$A7,Data!$F:$F,"price_coal_power_usd_gj")=0,"",SUMIFS(Data!$G:$G,Data!$A:$A,$A7,Data!$F:$F,"price_coal_power_usd_gj")) | M7: =IF(COUNTIFS(Data!$A:$A,$A7,Data!$F:$F,"price_gas_power_usd_gj")=0,"",SUMIFS(Data!$G:$G,Data!$A:$A,$A7,Data!$F:$F,"price_gas_power_usd_gj")) | N7: =IF(COUNTIFS(Data!$A:$A,$A7,Data!$F:$F,"price_gas_industry_usd_gj")=0,"",SUMIFS(Data!$G:$G,Data!$A:$A,$A7,Data!$F:$F,"price_gas_industry_usd_gj")) | O7: =IF(COUNTIFS(Data!$A:$A,$A7,Data!$F:$F,"power_market_structure")=0,"",SUMIFS(Data!$G:$G,Data!$A:$A,$A7,Data!$F:$F,"power_market_structure")) | P7: =IF(COUNTIFS(Data!$A:$A,$A7,Data!$F:$F,"rise_renewable_energy_score")=0,"",SUMIFS(Data!$G:$G,Data!$A:$A,$A7,Data!$F:$F,"rise_renewable_energy_score")) | Q7: =H7+I7+J7 | R7: =Q7/G7 | S7: =IF(D7>0,H7/D7,0.85) | T7: =IF(E7>0,I7/E7,0.4) | U7: =IF(D7+F7>0,(H7+J7)/(D7+F7),0) | V7: =K7*1000 | W7: =IF(O7=3,in_pt3,IF(O7=2,in_pt2,IF(O7=1,in_pt1,IF(C7="High income",in_pt_hi,in_pt_oth)))) | X7: =IF(Q7>0,in_kappa*(in_rise_lo+(in_rise_hi-in_rise_lo)*IF(P7="",in_rise_miss,P7)/100)*(D7+F7)*MAX(U7-in_gas_rep*T7,0)/Q7,0) | Y7: =IF(IF(M7="",N7,M7)="",MAX(in_sw_floor,in_sw_miss),MAX(in_sw_floor,(IF(M7="",N7,M7)*in_hr_gas-L7*in_hr_coal)/MAX(S7-T7,0.1))) | Z7: =IF(C7="Low income",in_b40_li,IF(C7="Lower middle income",in_b40_lmi,IF(C7="Upper middle income",in_b40_umi,IF(C7="High income",in_b40_hi,0.03)))) | AA7: =(D7+F7)/G7 | AB7: =100*W7*R7/V7/in_phase | AC7: =100*Z7*W7*R7/V7*(1-IF(W7>0,MIN(in_rebate/(W7*in_res_sh*in_q40),1),1)) | AD7: =IF(AA7>0,100*U7*(1-W7)/(in_whole_sh*V7),0) | AE7: =IF(AA7>0,100*MAX(U7-R7,0)/(in_whole_sh*V7),0) | AF7: =IF(AB7>0,in_f1/AB7,in_cap) | AG7: =IF(AC7>0,in_f2/AC7,in_cap) | AH7: =IF(AD7>0,in_f3/AD7,in_cap) | AI7: =MIN(in_cap,AF7,AG7,AH7) | AJ7: =100*(1-(1-X7*(1-EXP(-((AI7)+(0))/Y7)))*(1-MIN(ABS(in_elas)*W7*R7*(AI7)/V7,1))) | AK7: =IF(AI7>=in_cap-1E-9,"rate cap",TRIM(IF(ABS(AI7-AF7)<1E-9,"F1 ","")&IF(ABS(AI7-AG7)<1E-9,"F2 ","")&IF(ABS(AI7-AH7)<1E-9,"F3",""))) | AL7: =100*(1-(1-X7*(1-EXP(-((MIN(in_cap,IF(AB7>0,(in_f1+1)/AB7,in_cap),AG7,AH7))+(0))/Y7)))*(1-MIN(ABS(in_elas)*W7*R7*(MIN(in_cap,IF(AB7>0,(in_f1+1)/AB7,in_cap),AG7,AH7))/V7,1)))-AJ7 | AM7: =MIN(in_cap,IF(AE7>0,in_f3/AE7,in_cap)) | AN7: =100*(1-(1-X7*(1-EXP(-((0)+(AM7))/Y7)))*(1-MIN(ABS(in_elas)*W7*R7*(0)/V7,1))) | AO7: =IF(AM7>=in_cap-1E-9,"rate cap","F3") | AP7: =100*(1-(1-X7*(1-EXP(-((50)+(0))/Y7)))*(1-MIN(ABS(in_elas)*W7*R7*(50)/V7,1))) | AQ7: =100*(1-(1-X7*(1-EXP(-((0)+(50))/Y7)))*(1-MIN(ABS(in_elas)*W7*R7*(0)/V7,1))) | AR7: =IF(AP7>0,AQ7/AP7,"") | AS7: =50*AB7 | AT7: =MAX(BM7:BW7) | AU7: =AI7*(MATCH(AT7,BM7:BW7,0)-1)/10 | AV7: =INDEX(BB7:BL7,1,(MATCH(AT7,BM7:BW7,0)-1)+1) | AW7: =AB7*AU7 | AX7: =AC7*AU7 | AY7: =AD7*AU7+AE7*AV7 | AZ7: =TRIM(IF(AND(AU7>0,ABS(AU7-AF7)<1E-6),"F1 ","")&IF(AND(AU7>0,ABS(AU7-AG7)<1E-6),"F2 ","")&IF(AY7>=in_f3-1E-6,"F3 ","")&IF(AV7>=in_cap-1E-9,"rate cap","")) | BA7: =Q7*AT7/100 | BB7: =MAX(0,MIN(in_cap,IF(AE7>0,(in_f3-AD7*AI7*0/10)/AE7,in_cap))) | BC7: =MAX(0,MIN(in_cap,IF(AE7>0,(in_f3-AD7*AI7*1/10)/AE7,in_cap))) | BD7: =MAX(0,MIN(in_cap,IF(AE7>0,(in_f3-AD7*AI7*2/10)/AE7,in_cap))) | BE7: =MAX(0,MIN(in_cap,IF(AE7>0,(in_f3-AD7*AI7*3/10)/AE7,in_cap))) | BF7: =MAX(0,MIN(in_cap,IF(AE7>0,(in_f3-AD7*AI7*4/10)/AE7,in_cap))) | BG7: =MAX(0,MIN(in_cap,IF(AE7>0,(in_f3-AD7*AI7*5/10)/AE7,in_cap))) | BH7: =MAX(0,MIN(in_cap,IF(AE7>0,(in_f3-AD7*AI7*6/10)/AE7,in_cap))) | BI7: =MAX(0,MIN(in_cap,IF(AE7>0,(in_f3-AD7*AI7*7/10)/AE7,in_cap))) | BJ7: =MAX(0,MIN(in_cap,IF(AE7>0,(in_f3-AD7*AI7*8/10)/AE7,in_cap))) | BK7: =MAX(0,MIN(in_cap,IF(AE7>0,(in_f3-AD7*AI7*9/10)/AE7,in_cap))) | BL7: =MAX(0,MIN(in_cap,IF(AE7>0,(in_f3-AD7*AI7*10/10)/AE7,in_cap))) | BM7: =100*(1-(1-X7*(1-EXP(-((AI7*0/10)+(BB7))/Y7)))*(1-MIN(ABS(in_elas)*W7*R7*(AI7*0/10)/V7,1))) | BN7: =100*(1-(1-X7*(1-EXP(-((AI7*1/10)+(BC7))/Y7)))*(1-MIN(ABS(in_elas)*W7*R7*(AI7*1/10)/V7,1))) | BO7: =100*(1-(1-X7*(1-EXP(-((AI7*2/10)+(BD7))/Y7)))*(1-MIN(ABS(in_elas)*W7*R7*(AI7*2/10)/V7,1))) | BP7: =100*(1-(1-X7*(1-EXP(-((AI7*3/10)+(BE7))/Y7)))*(1-MIN(ABS(in_elas)*W7*R7*(AI7*3/10)/V7,1))) | BQ7: =100*(1-(1-X7*(1-EXP(-((AI7*4/10)+(BF7))/Y7)))*(1-MIN(ABS(in_elas)*W7*R7*(AI7*4/10)/V7,1))) | BR7: =100*(1-(1-X7*(1-EXP(-((AI7*5/10)+(BG7))/Y7)))*(1-MIN(ABS(in_elas)*W7*R7*(AI7*5/10)/V7,1))) | BS7: =100*(1-(1-X7*(1-EXP(-((AI7*6/10)+(BH7))/Y7)))*(1-MIN(ABS(in_elas)*W7*R7*(AI7*6/10)/V7,1))) | BT7: =100*(1-(1-X7*(1-EXP(-((AI7*7/10)+(BI7))/Y7)))*(1-MIN(ABS(in_elas)*W7*R7*(AI7*7/10)/V7,1))) | BU7: =100*(1-(1-X7*(1-EXP(-((AI7*8/10)+(BJ7))/Y7)))*(1-MIN(ABS(in_elas)*W7*R7*(AI7*8/10)/V7,1))) | BV7: =100*(1-(1-X7*(1-EXP(-((AI7*9/10)+(BK7))/Y7)))*(1-MIN(ABS(in_elas)*W7*R7*(AI7*9/10)/V7,1))) | BW7: =100*(1-(1-X7*(1-EXP(-((AI7*10/10)+(BL7))/Y7)))*(1-MIN(ABS(in_elas)*W7*R7*(AI7*10/10)/V7,1)))
A8: ARE | B8: =INDEX(Data!$B:$B,MATCH($A8,Data!$A:$A,0)) | C8: =INDEX(Data!$D:$D,MATCH($A8,Data!$A:$A,0)) | D8: =SUMIFS(Data!$G:$G,Data!$A:$A,$A8,Data!$F:$F,"gen_coal_twh") | E8: =SUMIFS(Data!$G:$G,Data!$A:$A,$A8,Data!$F:$F,"gen_gas_twh") | F8: =SUMIFS(Data!$G:$G,Data!$A:$A,$A8,Data!$F:$F,"gen_oil_twh") | G8: =SUMIFS(Data!$G:$G,Data!$A:$A,$A8,Data!$F:$F,"gen_total_twh") | H8: =SUMIFS(Data!$G:$G,Data!$A:$A,$A8,Data!$F:$F,"em_coal_mt") | I8: =SUMIFS(Data!$G:$G,Data!$A:$A,$A8,Data!$F:$F,"em_gas_mt") | J8: =SUMIFS(Data!$G:$G,Data!$A:$A,$A8,Data!$F:$F,"em_oil_mt") | K8: =IF(COUNTIFS(Data!$A:$A,$A8,Data!$F:$F,"price_electricity_residential_usd_kwh")=0,"",SUMIFS(Data!$G:$G,Data!$A:$A,$A8,Data!$F:$F,"price_electricity_residential_usd_kwh")) | L8: =IF(COUNTIFS(Data!$A:$A,$A8,Data!$F:$F,"price_coal_power_usd_gj")=0,"",SUMIFS(Data!$G:$G,Data!$A:$A,$A8,Data!$F:$F,"price_coal_power_usd_gj")) | M8: =IF(COUNTIFS(Data!$A:$A,$A8,Data!$F:$F,"price_gas_power_usd_gj")=0,"",SUMIFS(Data!$G:$G,Data!$A:$A,$A8,Data!$F:$F,"price_gas_power_usd_gj")) | N8: =IF(COUNTIFS(Data!$A:$A,$A8,Data!$F:$F,"price_gas_industry_usd_gj")=0,"",SUMIFS(Data!$G:$G,Data!$A:$A,$A8,Data!$F:$F,"price_gas_industry_usd_gj")) | O8: =IF(COUNTIFS(Data!$A:$A,$A8,Data!$F:$F,"power_market_structure")=0,"",SUMIFS(Data!$G:$G,Data!$A:$A,$A8,Data!$F:$F,"power_market_structure")) | P8: =IF(COUNTIFS(Data!$A:$A,$A8,Data!$F:$F,"rise_renewable_energy_score")=0,"",SUMIFS(Data!$G:$G,Data!$A:$A,$A8,Data!$F:$F,"rise_renewable_energy_score")) | Q8: =H8+I8+J8 | R8: =Q8/G8 | S8: =IF(D8>0,H8/D8,0.85) | T8: =IF(E8>0,I8/E8,0.4) | U8: =IF(D8+F8>0,(H8+J8)/(D8+F8),0) | V8: =K8*1000 | W8: =IF(O8=3,in_pt3,IF(O8=2,in_pt2,IF(O8=1,in_pt1,IF(C8="High income",in_pt_hi,in_pt_oth)))) | X8: =IF(Q8>0,in_kappa*(in_rise_lo+(in_rise_hi-in_rise_lo)*IF(P8="",in_rise_miss,P8)/100)*(D8+F8)*MAX(U8-in_gas_rep*T8,0)/Q8,0) | Y8: =IF(IF(M8="",N8,M8)="",MAX(in_sw_floor,in_sw_miss),MAX(in_sw_floor,(IF(M8="",N8,M8)*in_hr_gas-L8*in_hr_coal)/MAX(S8-T8,0.1))) | Z8: =IF(C8="Low income",in_b40_li,IF(C8="Lower middle income",in_b40_lmi,IF(C8="Upper middle income",in_b40_umi,IF(C8="High income",in_b40_hi,0.03)))) | AA8: =(D8+F8)/G8 | AB8: =100*W8*R8/V8/in_phase | AC8: =100*Z8*W8*R8/V8*(1-IF(W8>0,MIN(in_rebate/(W8*in_res_sh*in_q40),1),1)) | AD8: =IF(AA8>0,100*U8*(1-W8)/(in_whole_sh*V8),0) | AE8: =IF(AA8>0,100*MAX(U8-R8,0)/(in_whole_sh*V8),0) | AF8: =IF(AB8>0,in_f1/AB8,in_cap) | AG8: =IF(AC8>0,in_f2/AC8,in_cap) | AH8: =IF(AD8>0,in_f3/AD8,in_cap) | AI8: =MIN(in_cap,AF8,AG8,AH8) | AJ8: =100*(1-(1-X8*(1-EXP(-((AI8)+(0))/Y8)))*(1-MIN(ABS(in_elas)*W8*R8*(AI8)/V8,1))) | AK8: =IF(AI8>=in_cap-1E-9,"rate cap",TRIM(IF(ABS(AI8-AF8)<1E-9,"F1 ","")&IF(ABS(AI8-AG8)<1E-9,"F2 ","")&IF(ABS(AI8-AH8)<1E-9,"F3",""))) | AL8: =100*(1-(1-X8*(1-EXP(-((MIN(in_cap,IF(AB8>0,(in_f1+1)/AB8,in_cap),AG8,AH8))+(0))/Y8)))*(1-MIN(ABS(in_elas)*W8*R8*(MIN(in_cap,IF(AB8>0,(in_f1+1)/AB8,in_cap),AG8,AH8))/V8,1)))-AJ8 | AM8: =MIN(in_cap,IF(AE8>0,in_f3/AE8,in_cap)) | AN8: =100*(1-(1-X8*(1-EXP(-((0)+(AM8))/Y8)))*(1-MIN(ABS(in_elas)*W8*R8*(0)/V8,1))) | AO8: =IF(AM8>=in_cap-1E-9,"rate cap","F3") | AP8: =100*(1-(1-X8*(1-EXP(-((50)+(0))/Y8)))*(1-MIN(ABS(in_elas)*W8*R8*(50)/V8,1))) | AQ8: =100*(1-(1-X8*(1-EXP(-((0)+(50))/Y8)))*(1-MIN(ABS(in_elas)*W8*R8*(0)/V8,1))) | AR8: =IF(AP8>0,AQ8/AP8,"") | AS8: =50*AB8 | AT8: =MAX(BM8:BW8) | AU8: =AI8*(MATCH(AT8,BM8:BW8,0)-1)/10 | AV8: =INDEX(BB8:BL8,1,(MATCH(AT8,BM8:BW8,0)-1)+1) | AW8: =AB8*AU8 | AX8: =AC8*AU8 | AY8: =AD8*AU8+AE8*AV8 | AZ8: =TRIM(IF(AND(AU8>0,ABS(AU8-AF8)<1E-6),"F1 ","")&IF(AND(AU8>0,ABS(AU8-AG8)<1E-6),"F2 ","")&IF(AY8>=in_f3-1E-6,"F3 ","")&IF(AV8>=in_cap-1E-9,"rate cap","")) | BA8: =Q8*AT8/100 | BB8: =MAX(0,MIN(in_cap,IF(AE8>0,(in_f3-AD8*AI8*0/10)/AE8,in_cap))) | BC8: =MAX(0,MIN(in_cap,IF(AE8>0,(in_f3-AD8*AI8*1/10)/AE8,in_cap))) | BD8: =MAX(0,MIN(in_cap,IF(AE8>0,(in_f3-AD8*AI8*2/10)/AE8,in_cap))) | BE8: =MAX(0,MIN(in_cap,IF(AE8>0,(in_f3-AD8*AI8*3/10)/AE8,in_cap))) | BF8: =MAX(0,MIN(in_cap,IF(AE8>0,(in_f3-AD8*AI8*4/10)/AE8,in_cap))) | BG8: =MAX(0,MIN(in_cap,IF(AE8>0,(in_f3-AD8*AI8*5/10)/AE8,in_cap))) | BH8: =MAX(0,MIN(in_cap,IF(AE8>0,(in_f3-AD8*AI8*6/10)/AE8,in_cap))) | BI8: =MAX(0,MIN(in_cap,IF(AE8>0,(in_f3-AD8*AI8*7/10)/AE8,in_cap))) | BJ8: =MAX(0,MIN(in_cap,IF(AE8>0,(in_f3-AD8*AI8*8/10)/AE8,in_cap))) | BK8: =MAX(0,MIN(in_cap,IF(AE8>0,(in_f3-AD8*AI8*9/10)/AE8,in_cap))) | BL8: =MAX(0,MIN(in_cap,IF(AE8>0,(in_f3-AD8*AI8*10/10)/AE8,in_cap))) | BM8: =100*(1-(1-X8*(1-EXP(-((AI8*0/10)+(BB8))/Y8)))*(1-MIN(ABS(in_elas)*W8*R8*(AI8*0/10)/V8,1))) | BN8: =100*(1-(1-X8*(1-EXP(-((AI8*1/10)+(BC8))/Y8)))*(1-MIN(ABS(in_elas)*W8*R8*(AI8*1/10)/V8,1))) | BO8: =100*(1-(1-X8*(1-EXP(-((AI8*2/10)+(BD8))/Y8)))*(1-MIN(ABS(in_elas)*W8*R8*(AI8*2/10)/V8,1))) | BP8: =100*(1-(1-X8*(1-EXP(-((AI8*3/10)+(BE8))/Y8)))*(1-MIN(ABS(in_elas)*W8*R8*(AI8*3/10)/V8,1))) | BQ8: =100*(1-(1-X8*(1-EXP(-((AI8*4/10)+(BF8))/Y8)))*(1-MIN(ABS(in_elas)*W8*R8*(AI8*4/10)/V8,1))) | BR8: =100*(1-(1-X8*(1-EXP(-((AI8*5/10)+(BG8))/Y8)))*(1-MIN(ABS(in_elas)*W8*R8*(AI8*5/10)/V8,1))) | BS8: =100*(1-(1-X8*(1-EXP(-((AI8*6/10)+(BH8))/Y8)))*(1-MIN(ABS(in_elas)*W8*R8*(AI8*6/10)/V8,1))) | BT8: =100*(1-(1-X8*(1-EXP(-((AI8*7/10)+(BI8))/Y8)))*(1-MIN(ABS(in_elas)*W8*R8*(AI8*7/10)/V8,1))) | BU8: =100*(1-(1-X8*(1-EXP(-((AI8*8/10)+(BJ8))/Y8)))*(1-MIN(ABS(in_elas)*W8*R8*(AI8*8/10)/V8,1))) | BV8: =100*(1-(1-X8*(1-EXP(-((AI8*9/10)+(BK8))/Y8)))*(1-MIN(ABS(in_elas)*W8*R8*(AI8*9/10)/V8,1))) | BW8: =100*(1-(1-X8*(1-EXP(-((AI8*10/10)+(BL8))/Y8)))*(1-MIN(ABS(in_elas)*W8*R8*(AI8*10/10)/V8,1)))
A9: ARG | B9: =INDEX(Data!$B:$B,MATCH($A9,Data!$A:$A,0)) | C9: =INDEX(Data!$D:$D,MATCH($A9,Data!$A:$A,0)) | D9: =SUMIFS(Data!$G:$G,Data!$A:$A,$A9,Data!$F:$F,"gen_coal_twh") | E9: =SUMIFS(Data!$G:$G,Data!$A:$A,$A9,Data!$F:$F,"gen_gas_twh") | F9: =SUMIFS(Data!$G:$G,Data!$A:$A,$A9,Data!$F:$F,"gen_oil_twh") | G9: =SUMIFS(Data!$G:$G,Data!$A:$A,$A9,Data!$F:$F,"gen_total_twh") | H9: =SUMIFS(Data!$G:$G,Data!$A:$A,$A9,Data!$F:$F,"em_coal_mt") | I9: =SUMIFS(Data!$G:$G,Data!$A:$A,$A9,Data!$F:$F,"em_gas_mt") | J9: =SUMIFS(Data!$G:$G,Data!$A:$A,$A9,Data!$F:$F,"em_oil_mt") | K9: =IF(COUNTIFS(Data!$A:$A,$A9,Data!$F:$F,"price_electricity_residential_usd_kwh")=0,"",SUMIFS(Data!$G:$G,Data!$A:$A,$A9,Data!$F:$F,"price_electricity_residential_usd_kwh")) | L9: =IF(COUNTIFS(Data!$A:$A,$A9,Data!$F:$F,"price_coal_power_usd_gj")=0,"",SUMIFS(Data!$G:$G,Data!$A:$A,$A9,Data!$F:$F,"price_coal_power_usd_gj")) | M9: =IF(COUNTIFS(Data!$A:$A,$A9,Data!$F:$F,"price_gas_power_usd_gj")=0,"",SUMIFS(Data!$G:$G,Data!$A:$A,$A9,Data!$F:$F,"price_gas_power_usd_gj")) | N9: =IF(COUNTIFS(Data!$A:$A,$A9,Data!$F:$F,"price_gas_industry_usd_gj")=0,"",SUMIFS(Data!$G:$G,Data!$A:$A,$A9,Data!$F:$F,"price_gas_industry_usd_gj")) | O9: =IF(COUNTIFS(Data!$A:$A,$A9,Data!$F:$F,"power_market_structure")=0,"",SUMIFS(Data!$G:$G,Data!$A:$A,$A9,Data!$F:$F,"power_market_structure")) | P9: =IF(COUNTIFS(Data!$A:$A,$A9,Data!$F:$F,"rise_renewable_energy_score")=0,"",SUMIFS(Data!$G:$G,Data!$A:$A,$A9,Data!$F:$F,"rise_renewable_energy_score")) | Q9: =H9+I9+J9 | R9: =Q9/G9 | S9: =IF(D9>0,H9/D9,0.85) | T9: =IF(E9>0,I9/E9,0.4) | U9: =IF(D9+F9>0,(H9+J9)/(D9+F9),0) | V9: =K9*1000 | W9: =IF(O9=3,in_pt3,IF(O9=2,in_pt2,IF(O9=1,in_pt1,IF(C9="High income",in_pt_hi,in_pt_oth)))) | X9: =IF(Q9>0,in_kappa*(in_rise_lo+(in_rise_hi-in_rise_lo)*IF(P9="",in_rise_miss,P9)/100)*(D9+F9)*MAX(U9-in_gas_rep*T9,0)/Q9,0) | Y9: =IF(IF(M9="",N9,M9)="",MAX(in_sw_floor,in_sw_miss),MAX(in_sw_floor,(IF(M9="",N9,M9)*in_hr_gas-L9*in_hr_coal)/MAX(S9-T9,0.1))) | Z9: =IF(C9="Low income",in_b40_li,IF(C9="Lower middle income",in_b40_lmi,IF(C9="Upper middle income",in_b40_umi,IF(C9="High income",in_b40_hi,0.03)))) | AA9: =(D9+F9)/G9 | AB9: =100*W9*R9/V9/in_phase | AC9: =100*Z9*W9*R9/V9*(1-IF(W9>0,MIN(in_rebate/(W9*in_res_sh*in_q40),1),1)) | AD9: =IF(AA9>0,100*U9*(1-W9)/(in_whole_sh*V9),0) | AE9: =IF(AA9>0,100*MAX(U9-R9,0)/(in_whole_sh*V9),0) | AF9: =IF(AB9>0,in_f1/AB9,in_cap) | AG9: =IF(AC9>0,in_f2/AC9,in_cap) | AH9: =IF(AD9>0,in_f3/AD9,in_cap) | AI9: =MIN(in_cap,AF9,AG9,AH9) | AJ9: =100*(1-(1-X9*(1-EXP(-((AI9)+(0))/Y9)))*(1-MIN(ABS(in_elas)*W9*R9*(AI9)/V9,1))) | AK9: =IF(AI9>=in_cap-1E-9,"rate cap",TRIM(IF(ABS(AI9-AF9)<1E-9,"F1 ","")&IF(ABS(AI9-AG9)<1E-9,"F2 ","")&IF(ABS(AI9-AH9)<1E-9,"F3",""))) | AL9: =100*(1-(1-X9*(1-EXP(-((MIN(in_cap,IF(AB9>0,(in_f1+1)/AB9,in_cap),AG9,AH9))+(0))/Y9)))*(1-MIN(ABS(in_elas)*W9*R9*(MIN(in_cap,IF(AB9>0,(in_f1+1)/AB9,in_cap),AG9,AH9))/V9,1)))-AJ9 | AM9: =MIN(in_cap,IF(AE9>0,in_f3/AE9,in_cap)) | AN9: =100*(1-(1-X9*(1-EXP(-((0)+(AM9))/Y9)))*(1-MIN(ABS(in_elas)*W9*R9*(0)/V9,1))) | AO9: =IF(AM9>=in_cap-1E-9,"rate cap","F3") | AP9: =100*(1-(1-X9*(1-EXP(-((50)+(0))/Y9)))*(1-MIN(ABS(in_elas)*W9*R9*(50)/V9,1))) | AQ9: =100*(1-(1-X9*(1-EXP(-((0)+(50))/Y9)))*(1-MIN(ABS(in_elas)*W9*R9*(0)/V9,1))) | AR9: =IF(AP9>0,AQ9/AP9,"") | AS9: =50*AB9 | AT9: =MAX(BM9:BW9) | AU9: =AI9*(MATCH(AT9,BM9:BW9,0)-1)/10 | AV9: =INDEX(BB9:BL9,1,(MATCH(AT9,BM9:BW9,0)-1)+1) | AW9: =AB9*AU9 | AX9: =AC9*AU9 | AY9: =AD9*AU9+AE9*AV9 | AZ9: =TRIM(IF(AND(AU9>0,ABS(AU9-AF9)<1E-6),"F1 ","")&IF(AND(AU9>0,ABS(AU9-AG9)<1E-6),"F2 ","")&IF(AY9>=in_f3-1E-6,"F3 ","")&IF(AV9>=in_cap-1E-9,"rate cap","")) | BA9: =Q9*AT9/100 | BB9: =MAX(0,MIN(in_cap,IF(AE9>0,(in_f3-AD9*AI9*0/10)/AE9,in_cap))) | BC9: =MAX(0,MIN(in_cap,IF(AE9>0,(in_f3-AD9*AI9*1/10)/AE9,in_cap))) | BD9: =MAX(0,MIN(in_cap,IF(AE9>0,(in_f3-AD9*AI9*2/10)/AE9,in_cap))) | BE9: =MAX(0,MIN(in_cap,IF(AE9>0,(in_f3-AD9*AI9*3/10)/AE9,in_cap))) | BF9: =MAX(0,MIN(in_cap,IF(AE9>0,(in_f3-AD9*AI9*4/10)/AE9,in_cap))) | BG9: =MAX(0,MIN(in_cap,IF(AE9>0,(in_f3-AD9*AI9*5/10)/AE9,in_cap))) | BH9: =MAX(0,MIN(in_cap,IF(AE9>0,(in_f3-AD9*AI9*6/10)/AE9,in_cap))) | BI9: =MAX(0,MIN(in_cap,IF(AE9>0,(in_f3-AD9*AI9*7/10)/AE9,in_cap))) | BJ9: =MAX(0,MIN(in_cap,IF(AE9>0,(in_f3-AD9*AI9*8/10)/AE9,in_cap))) | BK9: =MAX(0,MIN(in_cap,IF(AE9>0,(in_f3-AD9*AI9*9/10)/AE9,in_cap))) | BL9: =MAX(0,MIN(in_cap,IF(AE9>0,(in_f3-AD9*AI9*10/10)/AE9,in_cap))) | BM9: =100*(1-(1-X9*(1-EXP(-((AI9*0/10)+(BB9))/Y9)))*(1-MIN(ABS(in_elas)*W9*R9*(AI9*0/10)/V9,1))) | BN9: =100*(1-(1-X9*(1-EXP(-((AI9*1/10)+(BC9))/Y9)))*(1-MIN(ABS(in_elas)*W9*R9*(AI9*1/10)/V9,1))) | BO9: =100*(1-(1-X9*(1-EXP(-((AI9*2/10)+(BD9))/Y9)))*(1-MIN(ABS(in_elas)*W9*R9*(AI9*2/10)/V9,1))) | BP9: =100*(1-(1-X9*(1-EXP(-((AI9*3/10)+(BE9))/Y9)))*(1-MIN(ABS(in_elas)*W9*R9*(AI9*3/10)/V9,1))) | BQ9: =100*(1-(1-X9*(1-EXP(-((AI9*4/10)+(BF9))/Y9)))*(1-MIN(ABS(in_elas)*W9*R9*(AI9*4/10)/V9,1))) | BR9: =100*(1-(1-X9*(1-EXP(-((AI9*5/10)+(BG9))/Y9)))*(1-MIN(ABS(in_elas)*W9*R9*(AI9*5/10)/V9,1))) | BS9: =100*(1-(1-X9*(1-EXP(-((AI9*6/10)+(BH9))/Y9)))*(1-MIN(ABS(in_elas)*W9*R9*(AI9*6/10)/V9,1))) | BT9: =100*(1-(1-X9*(1-EXP(-((AI9*7/10)+(BI9))/Y9)))*(1-MIN(ABS(in_elas)*W9*R9*(AI9*7/10)/V9,1))) | BU9: =100*(1-(1-X9*(1-EXP(-((AI9*8/10)+(BJ9))/Y9)))*(1-MIN(ABS(in_elas)*W9*R9*(AI9*8/10)/V9,1))) | BV9: =100*(1-(1-X9*(1-EXP(-((AI9*9/10)+(BK9))/Y9)))*(1-MIN(ABS(in_elas)*W9*R9*(AI9*9/10)/V9,1))) | BW9: =100*(1-(1-X9*(1-EXP(-((AI9*10/10)+(BL9))/Y9)))*(1-MIN(ABS(in_elas)*W9*R9*(AI9*10/10)/V9,1)))
A10: ARM | B10: =INDEX(Data!$B:$B,MATCH($A10,Data!$A:$A,0)) | C10: =INDEX(Data!$D:$D,MATCH($A10,Data!$A:$A,0)) | D10: =SUMIFS(Data!$G:$G,Data!$A:$A,$A10,Data!$F:$F,"gen_coal_twh") | E10: =SUMIFS(Data!$G:$G,Data!$A:$A,$A10,Data!$F:$F,"gen_gas_twh") | F10: =SUMIFS(Data!$G:$G,Data!$A:$A,$A10,Data!$F:$F,"gen_oil_twh") | G10: =SUMIFS(Data!$G:$G,Data!$A:$A,$A10,Data!$F:$F,"gen_total_twh") | H10: =SUMIFS(Data!$G:$G,Data!$A:$A,$A10,Data!$F:$F,"em_coal_mt") | I10: =SUMIFS(Data!$G:$G,Data!$A:$A,$A10,Data!$F:$F,"em_gas_mt") | J10: =SUMIFS(Data!$G:$G,Data!$A:$A,$A10,Data!$F:$F,"em_oil_mt") | K10: =IF(COUNTIFS(Data!$A:$A,$A10,Data!$F:$F,"price_electricity_residential_usd_kwh")=0,"",SUMIFS(Data!$G:$G,Data!$A:$A,$A10,Data!$F:$F,"price_electricity_residential_usd_kwh")) | L10: =IF(COUNTIFS(Data!$A:$A,$A10,Data!$F:$F,"price_coal_power_usd_gj")=0,"",SUMIFS(Data!$G:$G,Data!$A:$A,$A10,Data!$F:$F,"price_coal_power_usd_gj")) | M10: =IF(COUNTIFS(Data!$A:$A,$A10,Data!$F:$F,"price_gas_power_usd_gj")=0,"",SUMIFS(Data!$G:$G,Data!$A:$A,$A10,Data!$F:$F,"price_gas_power_usd_gj")) | N10: =IF(COUNTIFS(Data!$A:$A,$A10,Data!$F:$F,"price_gas_industry_usd_gj")=0,"",SUMIFS(Data!$G:$G,Data!$A:$A,$A10,Data!$F:$F,"price_gas_industry_usd_gj")) | O10: =IF(COUNTIFS(Data!$A:$A,$A10,Data!$F:$F,"power_market_structure")=0,"",SUMIFS(Data!$G:$G,Data!$A:$A,$A10,Data!$F:$F,"power_market_structure")) | P10: =IF(COUNTIFS(Data!$A:$A,$A10,Data!$F:$F,"rise_renewable_energy_score")=0,"",SUMIFS(Data!$G:$G,Data!$A:$A,$A10,Data!$F:$F,"rise_renewable_energy_score")) | Q10: =H10+I10+J10 | R10: =Q10/G10 | S10: =IF(D10>0,H10/D10,0.85) | T10: =IF(E10>0,I10/E10,0.4) | U10: =IF(D10+F10>0,(H10+J10)/(D10+F10),0) | V10: =K10*1000 | W10: =IF(O10=3,in_pt3,IF(O10=2,in_pt2,IF(O10=1,in_pt1,IF(C10="High income",in_pt_hi,in_pt_oth)))) | X10: =IF(Q10>0,in_kappa*(in_rise_lo+(in_rise_hi-in_rise_lo)*IF(P10="",in_rise_miss,P10)/100)*(D10+F10)*MAX(U10-in_gas_rep*T10,0)/Q10,0) | Y10: =IF(IF(M10="",N10,M10)="",MAX(in_sw_floor,in_sw_miss),MAX(in_sw_floor,(IF(M10="",N10,M10)*in_hr_gas-L10*in_hr_coal)/MAX(S10-T10,0.1))) | Z10: =IF(C10="Low income",in_b40_li,IF(C10="Lower middle income",in_b40_lmi,IF(C10="Upper middle income",in_b40_umi,IF(C10="High income",in_b40_hi,0.03)))) | AA10: =(D10+F10)/G10 | AB10: =100*W10*R10/V10/in_phase | AC10: =100*Z10*W10*R10/V10*(1-IF(W10>0,MIN(in_rebate/(W10*in_res_sh*in_q40),1),1)) | AD10: =IF(AA10>0,100*U10*(1-W10)/(in_whole_sh*V10),0) | AE10: =IF(AA10>0,100*MAX(U10-R10,0)/(in_whole_sh*V10),0) | AF10: =IF(AB10>0,in_f1/AB10,in_cap) | AG10: =IF(AC10>0,in_f2/AC10,in_cap) | AH10: =IF(AD10>0,in_f3/AD10,in_cap) | AI10: =MIN(in_cap,AF10,AG10,AH10) | AJ10: =100*(1-(1-X10*(1-EXP(-((AI10)+(0))/Y10)))*(1-MIN(ABS(in_elas)*W10*R10*(AI10)/V10,1))) | AK10: =IF(AI10>=in_cap-1E-9,"rate cap",TRIM(IF(ABS(AI10-AF10)<1E-9,"F1 ","")&IF(ABS(AI10-AG10)<1E-9,"F2 ","")&IF(ABS(AI10-AH10)<1E-9,"F3",""))) | AL10: =100*(1-(1-X10*(1-EXP(-((MIN(in_cap,IF(AB10>0,(in_f1+1)/AB10,in_cap),AG10,AH10))+(0))/Y10)))*(1-MIN(ABS(in_elas)*W10*R10*(MIN(in_cap,IF(AB10>0,(in_f1+1)/AB10,in_cap),AG10,AH10))/V10,1)))-AJ10 | AM10: =MIN(in_cap,IF(AE10>0,in_f3/AE10,in_cap)) | AN10: =100*(1-(1-X10*(1-EXP(-((0)+(AM10))/Y10)))*(1-MIN(ABS(in_elas)*W10*R10*(0)/V10,1))) | AO10: =IF(AM10>=in_cap-1E-9,"rate cap","F3") | AP10: =100*(1-(1-X10*(1-EXP(-((50)+(0))/Y10)))*(1-MIN(ABS(in_elas)*W10*R10*(50)/V10,1))) | AQ10: =100*(1-(1-X10*(1-EXP(-((0)+(50))/Y10)))*(1-MIN(ABS(in_elas)*W10*R10*(0)/V10,1))) | AR10: =IF(AP10>0,AQ10/AP10,"") | AS10: =50*AB10 | AT10: =MAX(BM10:BW10) | AU10: =AI10*(MATCH(AT10,BM10:BW10,0)-1)/10 | AV10: =INDEX(BB10:BL10,1,(MATCH(AT10,BM10:BW10,0)-1)+1) | AW10: =AB10*AU10 | AX10: =AC10*AU10 | AY10: =AD10*AU10+AE10*AV10 | AZ10: =TRIM(IF(AND(AU10>0,ABS(AU10-AF10)<1E-6),"F1 ","")&IF(AND(AU10>0,ABS(AU10-AG10)<1E-6),"F2 ","")&IF(AY10>=in_f3-1E-6,"F3 ","")&IF(AV10>=in_cap-1E-9,"rate cap","")) | BA10: =Q10*AT10/100 | BB10: =MAX(0,MIN(in_cap,IF(AE10>0,(in_f3-AD10*AI10*0/10)/AE10,in_cap))) | BC10: =MAX(0,MIN(in_cap,IF(AE10>0,(in_f3-AD10*AI10*1/10)/AE10,in_cap))) | BD10: =MAX(0,MIN(in_cap,IF(AE10>0,(in_f3-AD10*AI10*2/10)/AE10,in_cap))) | BE10: =MAX(0,MIN(in_cap,IF(AE10>0,(in_f3-AD10*AI10*3/10)/AE10,in_cap))) | BF10: =MAX(0,MIN(in_cap,IF(AE10>0,(in_f3-AD10*AI10*4/10)/AE10,in_cap))) | BG10: =MAX(0,MIN(in_cap,IF(AE10>0,(in_f3-AD10*AI10*5/10)/AE10,in_cap))) | BH10: =MAX(0,MIN(in_cap,IF(AE10>0,(in_f3-AD10*AI10*6/10)/AE10,in_cap))) | BI10: =MAX(0,MIN(in_cap,IF(AE10>0,(in_f3-AD10*AI10*7/10)/AE10,in_cap))) | BJ10: =MAX(0,MIN(in_cap,IF(AE10>0,(in_f3-AD10*AI10*8/10)/AE10,in_cap))) | BK10: =MAX(0,MIN(in_cap,IF(AE10>0,(in_f3-AD10*AI10*9/10)/AE10,in_cap))) | BL10: =MAX(0,MIN(in_cap,IF(AE10>0,(in_f3-AD10*AI10*10/10)/AE10,in_cap))) | BM10: =100*(1-(1-X10*(1-EXP(-((AI10*0/10)+(BB10))/Y10)))*(1-MIN(ABS(in_elas)*W10*R10*(AI10*0/10)/V10,1))) | BN10: =100*(1-(1-X10*(1-EXP(-((AI10*1/10)+(BC10))/Y10)))*(1-MIN(ABS(in_elas)*W10*R10*(AI10*1/10)/V10,1))) | BO10: =100*(1-(1-X10*(1-EXP(-((AI10*2/10)+(BD10))/Y10)))*(1-MIN(ABS(in_elas)*W10*R10*(AI10*2/10)/V10,1))) | BP10: =100*(1-(1-X10*(1-EXP(-((AI10*3/10)+(BE10))/Y10)))*(1-MIN(ABS(in_elas)*W10*R10*(AI10*3/10)/V10,1))) | BQ10: =100*(1-(1-X10*(1-EXP(-((AI10*4/10)+(BF10))/Y10)))*(1-MIN(ABS(in_elas)*W10*R10*(AI10*4/10)/V10,1))) | BR10: =100*(1-(1-X10*(1-EXP(-((AI10*5/10)+(BG10))/Y10)))*(1-MIN(ABS(in_elas)*W10*R10*(AI10*5/10)/V10,1))) | BS10: =100*(1-(1-X10*(1-EXP(-((AI10*6/10)+(BH10))/Y10)))*(1-MIN(ABS(in_elas)*W10*R10*(AI10*6/10)/V10,1))) | BT10: =100*(1-(1-X10*(1-EXP(-((AI10*7/10)+(BI10))/Y10)))*(1-MIN(ABS(in_elas)*W10*R10*(AI10*7/10)/V10,1))) | BU10: =100*(1-(1-X10*(1-EXP(-((AI10*8/10)+(BJ10))/Y10)))*(1-MIN(ABS(in_elas)*W10*R10*(AI10*8/10)/V10,1))) | BV10: =100*(1-(1-X10*(1-EXP(-((AI10*9/10)+(BK10))/Y10)))*(1-MIN(ABS(in_elas)*W10*R10*(AI10*9/10)/V10,1))) | BW10: =100*(1-(1-X10*(1-EXP(-((AI10*10/10)+(BL10))/Y10)))*(1-MIN(ABS(in_elas)*W10*R10*(AI10*10/10)/V10,1)))
A11: ATG | B11: =INDEX(Data!$B:$B,MATCH($A11,Data!$A:$A,0)) | C11: =INDEX(Data!$D:$D,MATCH($A11,Data!$A:$A,0)) | D11: =SUMIFS(Data!$G:$G,Data!$A:$A,$A11,Data!$F:$F,"gen_coal_twh") | E11: =SUMIFS(Data!$G:$G,Data!$A:$A,$A11,Data!$F:$F,"gen_gas_twh") | F11: =SUMIFS(Data!$G:$G,Data!$A:$A,$A11,Data!$F:$F,"gen_oil_twh") | G11: =SUMIFS(Data!$G:$G,Data!$A:$A,$A11,Data!$F:$F,"gen_total_twh") | H11: =SUMIFS(Data!$G:$G,Data!$A:$A,$A11,Data!$F:$F,"em_coal_mt") | I11: =SUMIFS(Data!$G:$G,Data!$A:$A,$A11,Data!$F:$F,"em_gas_mt") | J11: =SUMIFS(Data!$G:$G,Data!$A:$A,$A11,Data!$F:$F,"em_oil_mt") | K11: =IF(COUNTIFS(Data!$A:$A,$A11,Data!$F:$F,"price_electricity_residential_usd_kwh")=0,"",SUMIFS(Data!$G:$G,Data!$A:$A,$A11,Data!$F:$F,"price_electricity_residential_usd_kwh")) | L11: =IF(COUNTIFS(Data!$A:$A,$A11,Data!$F:$F,"price_coal_power_usd_gj")=0,"",SUMIFS(Data!$G:$G,Data!$A:$A,$A11,Data!$F:$F,"price_coal_power_usd_gj")) | M11: =IF(COUNTIFS(Data!$A:$A,$A11,Data!$F:$F,"price_gas_power_usd_gj")=0,"",SUMIFS(Data!$G:$G,Data!$A:$A,$A11,Data!$F:$F,"price_gas_power_usd_gj")) | N11: =IF(COUNTIFS(Data!$A:$A,$A11,Data!$F:$F,"price_gas_industry_usd_gj")=0,"",SUMIFS(Data!$G:$G,Data!$A:$A,$A11,Data!$F:$F,"price_gas_industry_usd_gj")) | O11: =IF(COUNTIFS(Data!$A:$A,$A11,Data!$F:$F,"power_market_structure")=0,"",SUMIFS(Data!$G:$G,Data!$A:$A,$A11,Data!$F:$F,"power_market_structure")) | P11: =IF(COUNTIFS(Data!$A:$A,$A11,Data!$F:$F,"rise_renewable_energy_score")=0,"",SUMIFS(Data!$G:$G,Data!$A:$A,$A11,Data!$F:$F,"rise_renewable_energy_score")) | Q11: =H11+I11+J11 | R11: =Q11/G11 | S11: =IF(D11>0,H11/D11,0.85) | T11: =IF(E11>0,I11/E11,0.4) | U11: =IF(D11+F11>0,(H11+J11)/(D11+F11),0) | V11: =K11*1000 | W11: =IF(O11=3,in_pt3,IF(O11=2,in_pt2,IF(O11=1,in_pt1,IF(C11="High income",in_pt_hi,in_pt_oth)))) | X11: =IF(Q11>0,in_kappa*(in_rise_lo+(in_rise_hi-in_rise_lo)*IF(P11="",in_rise_miss,P11)/100)*(D11+F11)*MAX(U11-in_gas_rep*T11,0)/Q11,0) | Y11: =IF(IF(M11="",N11,M11)="",MAX(in_sw_floor,in_sw_miss),MAX(in_sw_floor,(IF(M11="",N11,M11)*in_hr_gas-L11*in_hr_coal)/MAX(S11-T11,0.1))) | Z11: =IF(C11="Low income",in_b40_li,IF(C11="Lower middle income",in_b40_lmi,IF(C11="Upper middle income",in_b40_umi,IF(C11="High income",in_b40_hi,0.03)))) | AA11: =(D11+F11)/G11 | AB11: =100*W11*R11/V11/in_phase | AC11: =100*Z11*W11*R11/V11*(1-IF(W11>0,MIN(in_rebate/(W11*in_res_sh*in_q40),1),1)) | AD11: =IF(AA11>0,100*U11*(1-W11)/(in_whole_sh*V11),0) | AE11: =IF(AA11>0,100*MAX(U11-R11,0)/(in_whole_sh*V11),0) | AF11: =IF(AB11>0,in_f1/AB11,in_cap) | AG11: =IF(AC11>0,in_f2/AC11,in_cap) | AH11: =IF(AD11>0,in_f3/AD11,in_cap) | AI11: =MIN(in_cap,AF11,AG11,AH11) | AJ11: =100*(1-(1-X11*(1-EXP(-((AI11)+(0))/Y11)))*(1-MIN(ABS(in_elas)*W11*R11*(AI11)/V11,1))) | AK11: =IF(AI11>=in_cap-1E-9,"rate cap",TRIM(IF(ABS(AI11-AF11)<1E-9,"F1 ","")&IF(ABS(AI11-AG11)<1E-9,"F2 ","")&IF(ABS(AI11-AH11)<1E-9,"F3",""))) | AL11: =100*(1-(1-X11*(1-EXP(-((MIN(in_cap,IF(AB11>0,(in_f1+1)/AB11,in_cap),AG11,AH11))+(0))/Y11)))*(1-MIN(ABS(in_elas)*W11*R11*(MIN(in_cap,IF(AB11>0,(in_f1+1)/AB11,in_cap),AG11,AH11))/V11,1)))-AJ11 | AM11: =MIN(in_cap,IF(AE11>0,in_f3/AE11,in_cap)) | AN11: =100*(1-(1-X11*(1-EXP(-((0)+(AM11))/Y11)))*(1-MIN(ABS(in_elas)*W11*R11*(0)/V11,1))) | AO11: =IF(AM11>=in_cap-1E-9,"rate cap","F3") | AP11: =100*(1-(1-X11*(1-EXP(-((50)+(0))/Y11)))*(1-MIN(ABS(in_elas)*W11*R11*(50)/V11,1))) | AQ11: =100*(1-(1-X11*(1-EXP(-((0)+(50))/Y11)))*(1-MIN(ABS(in_elas)*W11*R11*(0)/V11,1))) | AR11: =IF(AP11>0,AQ11/AP11,"") | AS11: =50*AB11 | AT11: =MAX(BM11:BW11) | AU11: =AI11*(MATCH(AT11,BM11:BW11,0)-1)/10 | AV11: =INDEX(BB11:BL11,1,(MATCH(AT11,BM11:BW11,0)-1)+1) | AW11: =AB11*AU11 | AX11: =AC11*AU11 | AY11: =AD11*AU11+AE11*AV11 | AZ11: =TRIM(IF(AND(AU11>0,ABS(AU11-AF11)<1E-6),"F1 ","")&IF(AND(AU11>0,ABS(AU11-AG11)<1E-6),"F2 ","")&IF(AY11>=in_f3-1E-6,"F3 ","")&IF(AV11>=in_cap-1E-9,"rate cap","")) | BA11: =Q11*AT11/100 | BB11: =MAX(0,MIN(in_cap,IF(AE11>0,(in_f3-AD11*AI11*0/10)/AE11,in_cap))) | BC11: =MAX(0,MIN(in_cap,IF(AE11>0,(in_f3-AD11*AI11*1/10)/AE11,in_cap))) | BD11: =MAX(0,MIN(in_cap,IF(AE11>0,(in_f3-AD11*AI11*2/10)/AE11,in_cap))) | BE11: =MAX(0,MIN(in_cap,IF(AE11>0,(in_f3-AD11*AI11*3/10)/AE11,in_cap))) | BF11: =MAX(0,MIN(in_cap,IF(AE11>0,(in_f3-AD11*AI11*4/10)/AE11,in_cap))) | BG11: =MAX(0,MIN(in_cap,IF(AE11>0,(in_f3-AD11*AI11*5/10)/AE11,in_cap))) | BH11: =MAX(0,MIN(in_cap,IF(AE11>0,(in_f3-AD11*AI11*6/10)/AE11,in_cap))) | BI11: =MAX(0,MIN(in_cap,IF(AE11>0,(in_f3-AD11*AI11*7/10)/AE11,in_cap))) | BJ11: =MAX(0,MIN(in_cap,IF(AE11>0,(in_f3-AD11*AI11*8/10)/AE11,in_cap))) | BK11: =MAX(0,MIN(in_cap,IF(AE11>0,(in_f3-AD11*AI11*9/10)/AE11,in_cap))) | BL11: =MAX(0,MIN(in_cap,IF(AE11>0,(in_f3-AD11*AI11*10/10)/AE11,in_cap))) | BM11: =100*(1-(1-X11*(1-EXP(-((AI11*0/10)+(BB11))/Y11)))*(1-MIN(ABS(in_elas)*W11*R11*(AI11*0/10)/V11,1))) | BN11: =100*(1-(1-X11*(1-EXP(-((AI11*1/10)+(BC11))/Y11)))*(1-MIN(ABS(in_elas)*W11*R11*(AI11*1/10)/V11,1))) | BO11: =100*(1-(1-X11*(1-EXP(-((AI11*2/10)+(BD11))/Y11)))*(1-MIN(ABS(in_elas)*W11*R11*(AI11*2/10)/V11,1))) | BP11: =100*(1-(1-X11*(1-EXP(-((AI11*3/10)+(BE11))/Y11)))*(1-MIN(ABS(in_elas)*W11*R11*(AI11*3/10)/V11,1))) | BQ11: =100*(1-(1-X11*(1-EXP(-((AI11*4/10)+(BF11))/Y11)))*(1-MIN(ABS(in_elas)*W11*R11*(AI11*4/10)/V11,1))) | BR11: =100*(1-(1-X11*(1-EXP(-((AI11*5/10)+(BG11))/Y11)))*(1-MIN(ABS(in_elas)*W11*R11*(AI11*5/10)/V11,1))) | BS11: =100*(1-(1-X11*(1-EXP(-((AI11*6/10)+(BH11))/Y11)))*(1-MIN(ABS(in_elas)*W11*R11*(AI11*6/10)/V11,1))) | BT11: =100*(1-(1-X11*(1-EXP(-((AI11*7/10)+(BI11))/Y11)))*(1-MIN(ABS(in_elas)*W11*R11*(AI11*7/10)/V11,1))) | BU11: =100*(1-(1-X11*(1-EXP(-((AI11*8/10)+(BJ11))/Y11)))*(1-MIN(ABS(in_elas)*W11*R11*(AI11*8/10)/V11,1))) | BV11: =100*(1-(1-X11*(1-EXP(-((AI11*9/10)+(BK11))/Y11)))*(1-MIN(ABS(in_elas)*W11*R11*(AI11*9/10)/V11,1))) | BW11: =100*(1-(1-X11*(1-EXP(-((AI11*10/10)+(BL11))/Y11)))*(1-MIN(ABS(in_elas)*W11*R11*(AI11*10/10)/V11,1)))
A12: AUS | B12: =INDEX(Data!$B:$B,MATCH($A12,Data!$A:$A,0)) | C12: =INDEX(Data!$D:$D,MATCH($A12,Data!$A:$A,0)) | D12: =SUMIFS(Data!$G:$G,Data!$A:$A,$A12,Data!$F:$F,"gen_coal_twh") | E12: =SUMIFS(Data!$G:$G,Data!$A:$A,$A12,Data!$F:$F,"gen_gas_twh") | F12: =SUMIFS(Data!$G:$G,Data!$A:$A,$A12,Data!$F:$F,"gen_oil_twh") | G12: =SUMIFS(Data!$G:$G,Data!$A:$A,$A12,Data!$F:$F,"gen_total_twh") | H12: =SUMIFS(Data!$G:$G,Data!$A:$A,$A12,Data!$F:$F,"em_coal_mt") | I12: =SUMIFS(Data!$G:$G,Data!$A:$A,$A12,Data!$F:$F,"em_gas_mt") | J12: =SUMIFS(Data!$G:$G,Data!$A:$A,$A12,Data!$F:$F,"em_oil_mt") | K12: =IF(COUNTIFS(Data!$A:$A,$A12,Data!$F:$F,"price_electricity_residential_usd_kwh")=0,"",SUMIFS(Data!$G:$G,Data!$A:$A,$A12,Data!$F:$F,"price_electricity_residential_usd_kwh")) | L12: =IF(COUNTIFS(Data!$A:$A,$A12,Data!$F:$F,"price_coal_power_usd_gj")=0,"",SUMIFS(Data!$G:$G,Data!$A:$A,$A12,Data!$F:$F,"price_coal_power_usd_gj")) | M12: =IF(COUNTIFS(Data!$A:$A,$A12,Data!$F:$F,"price_gas_power_usd_gj")=0,"",SUMIFS(Data!$G:$G,Data!$A:$A,$A12,Data!$F:$F,"price_gas_power_usd_gj")) | N12: =IF(COUNTIFS(Data!$A:$A,$A12,Data!$F:$F,"price_gas_industry_usd_gj")=0,"",SUMIFS(Data!$G:$G,Data!$A:$A,$A12,Data!$F:$F,"price_gas_industry_usd_gj")) | O12: =IF(COUNTIFS(Data!$A:$A,$A12,Data!$F:$F,"power_market_structure")=0,"",SUMIFS(Data!$G:$G,Data!$A:$A,$A12,Data!$F:$F,"power_market_structure")) | P12: =IF(COUNTIFS(Data!$A:$A,$A12,Data!$F:$F,"rise_renewable_energy_score")=0,"",SUMIFS(Data!$G:$G,Data!$A:$A,$A12,Data!$F:$F,"rise_renewable_energy_score")) | Q12: =H12+I12+J12 | R12: =Q12/G12 | S12: =IF(D12>0,H12/D12,0.85) | T12: =IF(E12>0,I12/E12,0.4) | U12: =IF(D12+F12>0,(H12+J12)/(D12+F12),0) | V12: =K12*1000 | W12: =IF(O12=3,in_pt3,IF(O12=2,in_pt2,IF(O12=1,in_pt1,IF(C12="High income",in_pt_hi,in_pt_oth)))) | X12: =IF(Q12>0,in_kappa*(in_rise_lo+(in_rise_hi-in_rise_lo)*IF(P12="",in_rise_miss,P12)/100)*(D12+F12)*MAX(U12-in_gas_rep*T12,0)/Q12,0) | Y12: =IF(IF(M12="",N12,M12)="",MAX(in_sw_floor,in_sw_miss),MAX(in_sw_floor,(IF(M12="",N12,M12)*in_hr_gas-L12*in_hr_coal)/MAX(S12-T12,0.1))) | Z12: =IF(C12="Low income",in_b40_li,IF(C12="Lower middle income",in_b40_lmi,IF(C12="Upper middle income",in_b40_umi,IF(C12="High income",in_b40_hi,0.03)))) | AA12: =(D12+F12)/G12 | AB12: =100*W12*R12/V12/in_phase | AC12: =100*Z12*W12*R12/V12*(1-IF(W12>0,MIN(in_rebate/(W12*in_res_sh*in_q40),1),1)) | AD12: =IF(AA12>0,100*U12*(1-W12)/(in_whole_sh*V12),0) | AE12: =IF(AA12>0,100*MAX(U12-R12,0)/(in_whole_sh*V12),0) | AF12: =IF(AB12>0,in_f1/AB12,in_cap) | AG12: =IF(AC12>0,in_f2/AC12,in_cap) | AH12: =IF(AD12>0,in_f3/AD12,in_cap) | AI12: =MIN(in_cap,AF12,AG12,AH12) | AJ12: =100*(1-(1-X12*(1-EXP(-((AI12)+(0))/Y12)))*(1-MIN(ABS(in_elas)*W12*R12*(AI12)/V12,1))) | AK12: =IF(AI12>=in_cap-1E-9,"rate cap",TRIM(IF(ABS(AI12-AF12)<1E-9,"F1 ","")&IF(ABS(AI12-AG12)<1E-9,"F2 ","")&IF(ABS(AI12-AH12)<1E-9,"F3",""))) | AL12: =100*(1-(1-X12*(1-EXP(-((MIN(in_cap,IF(AB12>0,(in_f1+1)/AB12,in_cap),AG12,AH12))+(0))/Y12)))*(1-MIN(ABS(in_elas)*W12*R12*(MIN(in_cap,IF(AB12>0,(in_f1+1)/AB12,in_cap),AG12,AH12))/V12,1)))-AJ12 | AM12: =MIN(in_cap,IF(AE12>0,in_f3/AE12,in_cap)) | AN12: =100*(1-(1-X12*(1-EXP(-((0)+(AM12))/Y12)))*(1-MIN(ABS(in_elas)*W12*R12*(0)/V12,1))) | AO12: =IF(AM12>=in_cap-1E-9,"rate cap","F3") | AP12: =100*(1-(1-X12*(1-EXP(-((50)+(0))/Y12)))*(1-MIN(ABS(in_elas)*W12*R12*(50)/V12,1))) | AQ12: =100*(1-(1-X12*(1-EXP(-((0)+(50))/Y12)))*(1-MIN(ABS(in_elas)*W12*R12*(0)/V12,1))) | AR12: =IF(AP12>0,AQ12/AP12,"") | AS12: =50*AB12 | AT12: =MAX(BM12:BW12) | AU12: =AI12*(MATCH(AT12,BM12:BW12,0)-1)/10 | AV12: =INDEX(BB12:BL12,1,(MATCH(AT12,BM12:BW12,0)-1)+1) | AW12: =AB12*AU12 | AX12: =AC12*AU12 | AY12: =AD12*AU12+AE12*AV12 | AZ12: =TRIM(IF(AND(AU12>0,ABS(AU12-AF12)<1E-6),"F1 ","")&IF(AND(AU12>0,ABS(AU12-AG12)<1E-6),"F2 ","")&IF(AY12>=in_f3-1E-6,"F3 ","")&IF(AV12>=in_cap-1E-9,"rate cap","")) | BA12: =Q12*AT12/100 | BB12: =MAX(0,MIN(in_cap,IF(AE12>0,(in_f3-AD12*AI12*0/10)/AE12,in_cap))) | BC12: =MAX(0,MIN(in_cap,IF(AE12>0,(in_f3-AD12*AI12*1/10)/AE12,in_cap))) | BD12: =MAX(0,MIN(in_cap,IF(AE12>0,(in_f3-AD12*AI12*2/10)/AE12,in_cap))) | BE12: =MAX(0,MIN(in_cap,IF(AE12>0,(in_f3-AD12*AI12*3/10)/AE12,in_cap))) | BF12: =MAX(0,MIN(in_cap,IF(AE12>0,(in_f3-AD12*AI12*4/10)/AE12,in_cap))) | BG12: =MAX(0,MIN(in_cap,IF(AE12>0,(in_f3-AD12*AI12*5/10)/AE12,in_cap))) | BH12: =MAX(0,MIN(in_cap,IF(AE12>0,(in_f3-AD12*AI12*6/10)/AE12,in_cap))) | BI12: =MAX(0,MIN(in_cap,IF(AE12>0,(in_f3-AD12*AI12*7/10)/AE12,in_cap))) | BJ12: =MAX(0,MIN(in_cap,IF(AE12>0,(in_f3-AD12*AI12*8/10)/AE12,in_cap))) | BK12: =MAX(0,MIN(in_cap,IF(AE12>0,(in_f3-AD12*AI12*9/10)/AE12,in_cap))) | BL12: =MAX(0,MIN(in_cap,IF(AE12>0,(in_f3-AD12*AI12*10/10)/AE12,in_cap))) | BM12: =100*(1-(1-X12*(1-EXP(-((AI12*0/10)+(BB12))/Y12)))*(1-MIN(ABS(in_elas)*W12*R12*(AI12*0/10)/V12,1))) | BN12: =100*(1-(1-X12*(1-EXP(-((AI12*1/10)+(BC12))/Y12)))*(1-MIN(ABS(in_elas)*W12*R12*(AI12*1/10)/V12,1))) | BO12: =100*(1-(1-X12*(1-EXP(-((AI12*2/10)+(BD12))/Y12)))*(1-MIN(ABS(in_elas)*W12*R12*(AI12*2/10)/V12,1))) | BP12: =100*(1-(1-X12*(1-EXP(-((AI12*3/10)+(BE12))/Y12)))*(1-MIN(ABS(in_elas)*W12*R12*(AI12*3/10)/V12,1))) | BQ12: =100*(1-(1-X12*(1-EXP(-((AI12*4/10)+(BF12))/Y12)))*(1-MIN(ABS(in_elas)*W12*R12*(AI12*4/10)/V12,1))) | BR12: =100*(1-(1-X12*(1-EXP(-((AI12*5/10)+(BG12))/Y12)))*(1-MIN(ABS(in_elas)*W12*R12*(AI12*5/10)/V12,1))) | BS12: =100*(1-(1-X12*(1-EXP(-((AI12*6/10)+(BH12))/Y12)))*(1-MIN(ABS(in_elas)*W12*R12*(AI12*6/10)/V12,1))) | BT12: =100*(1-(1-X12*(1-EXP(-((AI12*7/10)+(BI12))/Y12)))*(1-MIN(ABS(in_elas)*W12*R12*(AI12*7/10)/V12,1))) | BU12: =100*(1-(1-X12*(1-EXP(-((AI12*8/10)+(BJ12))/Y12)))*(1-MIN(ABS(in_elas)*W12*R12*(AI12*8/10)/V12,1))) | BV12: =100*(1-(1-X12*(1-EXP(-((AI12*9/10)+(BK12))/Y12)))*(1-MIN(ABS(in_elas)*W12*R12*(AI12*9/10)/V12,1))) | BW12: =100*(1-(1-X12*(1-EXP(-((AI12*10/10)+(BL12))/Y12)))*(1-MIN(ABS(in_elas)*W12*R12*(AI12*10/10)/V12,1)))
A13: AUT | B13: =INDEX(Data!$B:$B,MATCH($A13,Data!$A:$A,0)) | C13: =INDEX(Data!$D:$D,MATCH($A13,Data!$A:$A,0)) | D13: =SUMIFS(Data!$G:$G,Data!$A:$A,$A13,Data!$F:$F,"gen_coal_twh") | E13: =SUMIFS(Data!$G:$G,Data!$A:$A,$A13,Data!$F:$F,"gen_gas_twh") | F13: =SUMIFS(Data!$G:$G,Data!$A:$A,$A13,Data!$F:$F,"gen_oil_twh") | G13: =SUMIFS(Data!$G:$G,Data!$A:$A,$A13,Data!$F:$F,"gen_total_twh") | H13: =SUMIFS(Data!$G:$G,Data!$A:$A,$A13,Data!$F:$F,"em_coal_mt") | I13: =SUMIFS(Data!$G:$G,Data!$A:$A,$A13,Data!$F:$F,"em_gas_mt") | J13: =SUMIFS(Data!$G:$G,Data!$A:$A,$A13,Data!$F:$F,"em_oil_mt") | K13: =IF(COUNTIFS(Data!$A:$A,$A13,Data!$F:$F,"price_electricity_residential_usd_kwh")=0,"",SUMIFS(Data!$G:$G,Data!$A:$A,$A13,Data!$F:$F,"price_electricity_residential_usd_kwh")) | L13: =IF(COUNTIFS(Data!$A:$A,$A13,Data!$F:$F,"price_coal_power_usd_gj")=0,"",SUMIFS(Data!$G:$G,Data!$A:$A,$A13,Data!$F:$F,"price_coal_power_usd_gj")) | M13: =IF(COUNTIFS(Data!$A:$A,$A13,Data!$F:$F,"price_gas_power_usd_gj")=0,"",SUMIFS(Data!$G:$G,Data!$A:$A,$A13,Data!$F:$F,"price_gas_power_usd_gj")) | N13: =IF(COUNTIFS(Data!$A:$A,$A13,Data!$F:$F,"price_gas_industry_usd_gj")=0,"",SUMIFS(Data!$G:$G,Data!$A:$A,$A13,Data!$F:$F,"price_gas_industry_usd_gj")) | O13: =IF(COUNTIFS(Data!$A:$A,$A13,Data!$F:$F,"power_market_structure")=0,"",SUMIFS(Data!$G:$G,Data!$A:$A,$A13,Data!$F:$F,"power_market_structure")) | P13: =IF(COUNTIFS(Data!$A:$A,$A13,Data!$F:$F,"rise_renewable_energy_score")=0,"",SUMIFS(Data!$G:$G,Data!$A:$A,$A13,Data!$F:$F,"rise_renewable_energy_score")) | Q13: =H13+I13+J13 | R13: =Q13/G13 | S13: =IF(D13>0,H13/D13,0.85) | T13: =IF(E13>0,I13/E13,0.4) | U13: =IF(D13+F13>0,(H13+J13)/(D13+F13),0) | V13: =K13*1000 | W13: =IF(O13=3,in_pt3,IF(O13=2,in_pt2,IF(O13=1,in_pt1,IF(C13="High income",in_pt_hi,in_pt_oth)))) | X13: =IF(Q13>0,in_kappa*(in_rise_lo+(in_rise_hi-in_rise_lo)*IF(P13="",in_rise_miss,P13)/100)*(D13+F13)*MAX(U13-in_gas_rep*T13,0)/Q13,0) | Y13: =IF(IF(M13="",N13,M13)="",MAX(in_sw_floor,in_sw_miss),MAX(in_sw_floor,(IF(M13="",N13,M13)*in_hr_gas-L13*in_hr_coal)/MAX(S13-T13,0.1))) | Z13: =IF(C13="Low income",in_b40_li,IF(C13="Lower middle income",in_b40_lmi,IF(C13="Upper middle income",in_b40_umi,IF(C13="High income",in_b40_hi,0.03)))) | AA13: =(D13+F13)/G13 | AB13: =100*W13*R13/V13/in_phase | AC13: =100*Z13*W13*R13/V13*(1-IF(W13>0,MIN(in_rebate/(W13*in_res_sh*in_q40),1),1)) | AD13: =IF(AA13>0,100*U13*(1-W13)/(in_whole_sh*V13),0) | AE13: =IF(AA13>0,100*MAX(U13-R13,0)/(in_whole_sh*V13),0) | AF13: =IF(AB13>0,in_f1/AB13,in_cap) | AG13: =IF(AC13>0,in_f2/AC13,in_cap) | AH13: =IF(AD13>0,in_f3/AD13,in_cap) | AI13: =MIN(in_cap,AF13,AG13,AH13) | AJ13: =100*(1-(1-X13*(1-EXP(-((AI13)+(0))/Y13)))*(1-MIN(ABS(in_elas)*W13*R13*(AI13)/V13,1))) | AK13: =IF(AI13>=in_cap-1E-9,"rate cap",TRIM(IF(ABS(AI13-AF13)<1E-9,"F1 ","")&IF(ABS(AI13-AG13)<1E-9,"F2 ","")&IF(ABS(AI13-AH13)<1E-9,"F3",""))) | AL13: =100*(1-(1-X13*(1-EXP(-((MIN(in_cap,IF(AB13>0,(in_f1+1)/AB13,in_cap),AG13,AH13))+(0))/Y13)))*(1-MIN(ABS(in_elas)*W13*R13*(MIN(in_cap,IF(AB13>0,(in_f1+1)/AB13,in_cap),AG13,AH13))/V13,1)))-AJ13 | AM13: =MIN(in_cap,IF(AE13>0,in_f3/AE13,in_cap)) | AN13: =100*(1-(1-X13*(1-EXP(-((0)+(AM13))/Y13)))*(1-MIN(ABS(in_elas)*W13*R13*(0)/V13,1))) | AO13: =IF(AM13>=in_cap-1E-9,"rate cap","F3") | AP13: =100*(1-(1-X13*(1-EXP(-((50)+(0))/Y13)))*(1-MIN(ABS(in_elas)*W13*R13*(50)/V13,1))) | AQ13: =100*(1-(1-X13*(1-EXP(-((0)+(50))/Y13)))*(1-MIN(ABS(in_elas)*W13*R13*(0)/V13,1))) | AR13: =IF(AP13>0,AQ13/AP13,"") | AS13: =50*AB13 | AT13: =MAX(BM13:BW13) | AU13: =AI13*(MATCH(AT13,BM13:BW13,0)-1)/10 | AV13: =INDEX(BB13:BL13,1,(MATCH(AT13,BM13:BW13,0)-1)+1) | AW13: =AB13*AU13 | AX13: =AC13*AU13 | AY13: =AD13*AU13+AE13*AV13 | AZ13: =TRIM(IF(AND(AU13>0,ABS(AU13-AF13)<1E-6),"F1 ","")&IF(AND(AU13>0,ABS(AU13-AG13)<1E-6),"F2 ","")&IF(AY13>=in_f3-1E-6,"F3 ","")&IF(AV13>=in_cap-1E-9,"rate cap","")) | BA13: =Q13*AT13/100 | BB13: =MAX(0,MIN(in_cap,IF(AE13>0,(in_f3-AD13*AI13*0/10)/AE13,in_cap))) | BC13: =MAX(0,MIN(in_cap,IF(AE13>0,(in_f3-AD13*AI13*1/10)/AE13,in_cap))) | BD13: =MAX(0,MIN(in_cap,IF(AE13>0,(in_f3-AD13*AI13*2/10)/AE13,in_cap))) | BE13: =MAX(0,MIN(in_cap,IF(AE13>0,(in_f3-AD13*AI13*3/10)/AE13,in_cap))) | BF13: =MAX(0,MIN(in_cap,IF(AE13>0,(in_f3-AD13*AI13*4/10)/AE13,in_cap))) | BG13: =MAX(0,MIN(in_cap,IF(AE13>0,(in_f3-AD13*AI13*5/10)/AE13,in_cap))) | BH13: =MAX(0,MIN(in_cap,IF(AE13>0,(in_f3-AD13*AI13*6/10)/AE13,in_cap))) | BI13: =MAX(0,MIN(in_cap,IF(AE13>0,(in_f3-AD13*AI13*7/10)/AE13,in_cap))) | BJ13: =MAX(0,MIN(in_cap,IF(AE13>0,(in_f3-AD13*AI13*8/10)/AE13,in_cap))) | BK13: =MAX(0,MIN(in_cap,IF(AE13>0,(in_f3-AD13*AI13*9/10)/AE13,in_cap))) | BL13: =MAX(0,MIN(in_cap,IF(AE13>0,(in_f3-AD13*AI13*10/10)/AE13,in_cap))) | BM13: =100*(1-(1-X13*(1-EXP(-((AI13*0/10)+(BB13))/Y13)))*(1-MIN(ABS(in_elas)*W13*R13*(AI13*0/10)/V13,1))) | BN13: =100*(1-(1-X13*(1-EXP(-((AI13*1/10)+(BC13))/Y13)))*(1-MIN(ABS(in_elas)*W13*R13*(AI13*1/10)/V13,1))) | BO13: =100*(1-(1-X13*(1-EXP(-((AI13*2/10)+(BD13))/Y13)))*(1-MIN(ABS(in_elas)*W13*R13*(AI13*2/10)/V13,1))) | BP13: =100*(1-(1-X13*(1-EXP(-((AI13*3/10)+(BE13))/Y13)))*(1-MIN(ABS(in_elas)*W13*R13*(AI13*3/10)/V13,1))) | BQ13: =100*(1-(1-X13*(1-EXP(-((AI13*4/10)+(BF13))/Y13)))*(1-MIN(ABS(in_elas)*W13*R13*(AI13*4/10)/V13,1))) | BR13: =100*(1-(1-X13*(1-EXP(-((AI13*5/10)+(BG13))/Y13)))*(1-MIN(ABS(in_elas)*W13*R13*(AI13*5/10)/V13,1))) | BS13: =100*(1-(1-X13*(1-EXP(-((AI13*6/10)+(BH13))/Y13)))*(1-MIN(ABS(in_elas)*W13*R13*(AI13*6/10)/V13,1))) | BT13: =100*(1-(1-X13*(1-EXP(-((AI13*7/10)+(BI13))/Y13)))*(1-MIN(ABS(in_elas)*W13*R13*(AI13*7/10)/V13,1))) | BU13: =100*(1-(1-X13*(1-EXP(-((AI13*8/10)+(BJ13))/Y13)))*(1-MIN(ABS(in_elas)*W13*R13*(AI13*8/10)/V13,1))) | BV13: =100*(1-(1-X13*(1-EXP(-((AI13*9/10)+(BK13))/Y13)))*(1-MIN(ABS(in_elas)*W13*R13*(AI13*9/10)/V13,1))) | BW13: =100*(1-(1-X13*(1-EXP(-((AI13*10/10)+(BL13))/Y13)))*(1-MIN(ABS(in_elas)*W13*R13*(AI13*10/10)/V13,1)))
A14: AZE | B14: =INDEX(Data!$B:$B,MATCH($A14,Data!$A:$A,0)) | C14: =INDEX(Data!$D:$D,MATCH($A14,Data!$A:$A,0)) | D14: =SUMIFS(Data!$G:$G,Data!$A:$A,$A14,Data!$F:$F,"gen_coal_twh") | E14: =SUMIFS(Data!$G:$G,Data!$A:$A,$A14,Data!$F:$F,"gen_gas_twh") | F14: =SUMIFS(Data!$G:$G,Data!$A:$A,$A14,Data!$F:$F,"gen_oil_twh") | G14: =SUMIFS(Data!$G:$G,Data!$A:$A,$A14,Data!$F:$F,"gen_total_twh") | H14: =SUMIFS(Data!$G:$G,Data!$A:$A,$A14,Data!$F:$F,"em_coal_mt") | I14: =SUMIFS(Data!$G:$G,Data!$A:$A,$A14,Data!$F:$F,"em_gas_mt") | J14: =SUMIFS(Data!$G:$G,Data!$A:$A,$A14,Data!$F:$F,"em_oil_mt") | K14: =IF(COUNTIFS(Data!$A:$A,$A14,Data!$F:$F,"price_electricity_residential_usd_kwh")=0,"",SUMIFS(Data!$G:$G,Data!$A:$A,$A14,Data!$F:$F,"price_electricity_residential_usd_kwh")) | L14: =IF(COUNTIFS(Data!$A:$A,$A14,Data!$F:$F,"price_coal_power_usd_gj")=0,"",SUMIFS(Data!$G:$G,Data!$A:$A,$A14,Data!$F:$F,"price_coal_power_usd_gj")) | M14: =IF(COUNTIFS(Data!$A:$A,$A14,Data!$F:$F,"price_gas_power_usd_gj")=0,"",SUMIFS(Data!$G:$G,Data!$A:$A,$A14,Data!$F:$F,"price_gas_power_usd_gj")) | N14: =IF(COUNTIFS(Data!$A:$A,$A14,Data!$F:$F,"price_gas_industry_usd_gj")=0,"",SUMIFS(Data!$G:$G,Data!$A:$A,$A14,Data!$F:$F,"price_gas_industry_usd_gj")) | O14: =IF(COUNTIFS(Data!$A:$A,$A14,Data!$F:$F,"power_market_structure")=0,"",SUMIFS(Data!$G:$G,Data!$A:$A,$A14,Data!$F:$F,"power_market_structure")) | P14: =IF(COUNTIFS(Data!$A:$A,$A14,Data!$F:$F,"rise_renewable_energy_score")=0,"",SUMIFS(Data!$G:$G,Data!$A:$A,$A14,Data!$F:$F,"rise_renewable_energy_score")) | Q14: =H14+I14+J14 | R14: =Q14/G14 | S14: =IF(D14>0,H14/D14,0.85) | T14: =IF(E14>0,I14/E14,0.4) | U14: =IF(D14+F14>0,(H14+J14)/(D14+F14),0) | V14: =K14*1000 | W14: =IF(O14=3,in_pt3,IF(O14=2,in_pt2,IF(O14=1,in_pt1,IF(C14="High income",in_pt_hi,in_pt_oth)))) | X14: =IF(Q14>0,in_kappa*(in_rise_lo+(in_rise_hi-in_rise_lo)*IF(P14="",in_rise_miss,P14)/100)*(D14+F14)*MAX(U14-in_gas_rep*T14,0)/Q14,0) | Y14: =IF(IF(M14="",N14,M14)="",MAX(in_sw_floor,in_sw_miss),MAX(in_sw_floor,(IF(M14="",N14,M14)*in_hr_gas-L14*in_hr_coal)/MAX(S14-T14,0.1))) | Z14: =IF(C14="Low income",in_b40_li,IF(C14="Lower middle income",in_b40_lmi,IF(C14="Upper middle income",in_b40_umi,IF(C14="High income",in_b40_hi,0.03)))) | AA14: =(D14+F14)/G14 | AB14: =100*W14*R14/V14/in_phase | AC14: =100*Z14*W14*R14/V14*(1-IF(W14>0,MIN(in_rebate/(W14*in_res_sh*in_q40),1),1)) | AD14: =IF(AA14>0,100*U14*(1-W14)/(in_whole_sh*V14),0) | AE14: =IF(AA14>0,100*MAX(U14-R14,0)/(in_whole_sh*V14),0) | AF14: =IF(AB14>0,in_f1/AB14,in_cap) | AG14: =IF(AC14>0,in_f2/AC14,in_cap) | AH14: =IF(AD14>0,in_f3/AD14,in_cap) | AI14: =MIN(in_cap,AF14,AG14,AH14) | AJ14: =100*(1-(1-X14*(1-EXP(-((AI14)+(0))/Y14)))*(1-MIN(ABS(in_elas)*W14*R14*(AI14)/V14,1))) | AK14: =IF(AI14>=in_cap-1E-9,"rate cap",TRIM(IF(ABS(AI14-AF14)<1E-9,"F1 ","")&IF(ABS(AI14-AG14)<1E-9,"F2 ","")&IF(ABS(AI14-AH14)<1E-9,"F3",""))) | AL14: =100*(1-(1-X14*(1-EXP(-((MIN(in_cap,IF(AB14>0,(in_f1+1)/AB14,in_cap),AG14,AH14))+(0))/Y14)))*(1-MIN(ABS(in_elas)*W14*R14*(MIN(in_cap,IF(AB14>0,(in_f1+1)/AB14,in_cap),AG14,AH14))/V14,1)))-AJ14 | AM14: =MIN(in_cap,IF(AE14>0,in_f3/AE14,in_cap)) | AN14: =100*(1-(1-X14*(1-EXP(-((0)+(AM14))/Y14)))*(1-MIN(ABS(in_elas)*W14*R14*(0)/V14,1))) | AO14: =IF(AM14>=in_cap-1E-9,"rate cap","F3") | AP14: =100*(1-(1-X14*(1-EXP(-((50)+(0))/Y14)))*(1-MIN(ABS(in_elas)*W14*R14*(50)/V14,1))) | AQ14: =100*(1-(1-X14*(1-EXP(-((0)+(50))/Y14)))*(1-MIN(ABS(in_elas)*W14*R14*(0)/V14,1))) | AR14: =IF(AP14>0,AQ14/AP14,"") | AS14: =50*AB14 | AT14: =MAX(BM14:BW14) | AU14: =AI14*(MATCH(AT14,BM14:BW14,0)-1)/10 | AV14: =INDEX(BB14:BL14,1,(MATCH(AT14,BM14:BW14,0)-1)+1) | AW14: =AB14*AU14 | AX14: =AC14*AU14 | AY14: =AD14*AU14+AE14*AV14 | AZ14: =TRIM(IF(AND(AU14>0,ABS(AU14-AF14)<1E-6),"F1 ","")&IF(AND(AU14>0,ABS(AU14-AG14)<1E-6),"F2 ","")&IF(AY14>=in_f3-1E-6,"F3 ","")&IF(AV14>=in_cap-1E-9,"rate cap","")) | BA14: =Q14*AT14/100 | BB14: =MAX(0,MIN(in_cap,IF(AE14>0,(in_f3-AD14*AI14*0/10)/AE14,in_cap))) | BC14: =MAX(0,MIN(in_cap,IF(AE14>0,(in_f3-AD14*AI14*1/10)/AE14,in_cap))) | BD14: =MAX(0,MIN(in_cap,IF(AE14>0,(in_f3-AD14*AI14*2/10)/AE14,in_cap))) | BE14: =MAX(0,MIN(in_cap,IF(AE14>0,(in_f3-AD14*AI14*3/10)/AE14,in_cap))) | BF14: =MAX(0,MIN(in_cap,IF(AE14>0,(in_f3-AD14*AI14*4/10)/AE14,in_cap))) | BG14: =MAX(0,MIN(in_cap,IF(AE14>0,(in_f3-AD14*AI14*5/10)/AE14,in_cap))) | BH14: =MAX(0,MIN(in_cap,IF(AE14>0,(in_f3-AD14*AI14*6/10)/AE14,in_cap))) | BI14: =MAX(0,MIN(in_cap,IF(AE14>0,(in_f3-AD14*AI14*7/10)/AE14,in_cap))) | BJ14: =MAX(0,MIN(in_cap,IF(AE14>0,(in_f3-AD14*AI14*8/10)/AE14,in_cap))) | BK14: =MAX(0,MIN(in_cap,IF(AE14>0,(in_f3-AD14*AI14*9/10)/AE14,in_cap))) | BL14: =MAX(0,MIN(in_cap,IF(AE14>0,(in_f3-AD14*AI14*10/10)/AE14,in_cap))) | BM14: =100*(1-(1-X14*(1-EXP(-((AI14*0/10)+(BB14))/Y14)))*(1-MIN(ABS(in_elas)*W14*R14*(AI14*0/10)/V14,1))) | BN14: =100*(1-(1-X14*(1-EXP(-((AI14*1/10)+(BC14))/Y14)))*(1-MIN(ABS(in_elas)*W14*R14*(AI14*1/10)/V14,1))) | BO14: =100*(1-(1-X14*(1-EXP(-((AI14*2/10)+(BD14))/Y14)))*(1-MIN(ABS(in_elas)*W14*R14*(AI14*2/10)/V14,1))) | BP14: =100*(1-(1-X14*(1-EXP(-((AI14*3/10)+(BE14))/Y14)))*(1-MIN(ABS(in_elas)*W14*R14*(AI14*3/10)/V14,1))) | BQ14: =100*(1-(1-X14*(1-EXP(-((AI14*4/10)+(BF14))/Y14)))*(1-MIN(ABS(in_elas)*W14*R14*(AI14*4/10)/V14,1))) | BR14: =100*(1-(1-X14*(1-EXP(-((AI14*5/10)+(BG14))/Y14)))*(1-MIN(ABS(in_elas)*W14*R14*(AI14*5/10)/V14,1))) | BS14: =100*(1-(1-X14*(1-EXP(-((AI14*6/10)+(BH14))/Y14)))*(1-MIN(ABS(in_elas)*W14*R14*(AI14*6/10)/V14,1))) | BT14: =100*(1-(1-X14*(1-EXP(-((AI14*7/10)+(BI14))/Y14)))*(1-MIN(ABS(in_elas)*W14*R14*(AI14*7/10)/V14,1))) | BU14: =100*(1-(1-X14*(1-EXP(-((AI14*8/10)+(BJ14))/Y14)))*(1-MIN(ABS(in_elas)*W14*R14*(AI14*8/10)/V14,1))) | BV14: =100*(1-(1-X14*(1-EXP(-((AI14*9/10)+(BK14))/Y14)))*(1-MIN(ABS(in_elas)*W14*R14*(AI14*9/10)/V14,1))) | BW14: =100*(1-(1-X14*(1-EXP(-((AI14*10/10)+(BL14))/Y14)))*(1-MIN(ABS(in_elas)*W14*R14*(AI14*10/10)/V14,1)))
A15: BDI | B15: =INDEX(Data!$B:$B,MATCH($A15,Data!$A:$A,0)) | C15: =INDEX(Data!$D:$D,MATCH($A15,Data!$A:$A,0)) | D15: =SUMIFS(Data!$G:$G,Data!$A:$A,$A15,Data!$F:$F,"gen_coal_twh") | E15: =SUMIFS(Data!$G:$G,Data!$A:$A,$A15,Data!$F:$F,"gen_gas_twh") | F15: =SUMIFS(Data!$G:$G,Data!$A:$A,$A15,Data!$F:$F,"gen_oil_twh") | G15: =SUMIFS(Data!$G:$G,Data!$A:$A,$A15,Data!$F:$F,"gen_total_twh") | H15: =SUMIFS(Data!$G:$G,Data!$A:$A,$A15,Data!$F:$F,"em_coal_mt") | I15: =SUMIFS(Data!$G:$G,Data!$A:$A,$A15,Data!$F:$F,"em_gas_mt") | J15: =SUMIFS(Data!$G:$G,Data!$A:$A,$A15,Data!$F:$F,"em_oil_mt") | K15: =IF(COUNTIFS(Data!$A:$A,$A15,Data!$F:$F,"price_electricity_residential_usd_kwh")=0,"",SUMIFS(Data!$G:$G,Data!$A:$A,$A15,Data!$F:$F,"price_electricity_residential_usd_kwh")) | L15: =IF(COUNTIFS(Data!$A:$A,$A15,Data!$F:$F,"price_coal_power_usd_gj")=0,"",SUMIFS(Data!$G:$G,Data!$A:$A,$A15,Data!$F:$F,"price_coal_power_usd_gj")) | M15: =IF(COUNTIFS(Data!$A:$A,$A15,Data!$F:$F,"price_gas_power_usd_gj")=0,"",SUMIFS(Data!$G:$G,Data!$A:$A,$A15,Data!$F:$F,"price_gas_power_usd_gj")) | N15: =IF(COUNTIFS(Data!$A:$A,$A15,Data!$F:$F,"price_gas_industry_usd_gj")=0,"",SUMIFS(Data!$G:$G,Data!$A:$A,$A15,Data!$F:$F,"price_gas_industry_usd_gj")) | O15: =IF(COUNTIFS(Data!$A:$A,$A15,Data!$F:$F,"power_market_structure")=0,"",SUMIFS(Data!$G:$G,Data!$A:$A,$A15,Data!$F:$F,"power_market_structure")) | P15: =IF(COUNTIFS(Data!$A:$A,$A15,Data!$F:$F,"rise_renewable_energy_score")=0,"",SUMIFS(Data!$G:$G,Data!$A:$A,$A15,Data!$F:$F,"rise_renewable_energy_score")) | Q15: =H15+I15+J15 | R15: =Q15/G15 | S15: =IF(D15>0,H15/D15,0.85) | T15: =IF(E15>0,I15/E15,0.4) | U15: =IF(D15+F15>0,(H15+J15)/(D15+F15),0) | V15: =K15*1000 | W15: =IF(O15=3,in_pt3,IF(O15=2,in_pt2,IF(O15=1,in_pt1,IF(C15="High income",in_pt_hi,in_pt_oth)))) | X15: =IF(Q15>0,in_kappa*(in_rise_lo+(in_rise_hi-in_rise_lo)*IF(P15="",in_rise_miss,P15)/100)*(D15+F15)*MAX(U15-in_gas_rep*T15,0)/Q15,0) | Y15: =IF(IF(M15="",N15,M15)="",MAX(in_sw_floor,in_sw_miss),MAX(in_sw_floor,(IF(M15="",N15,M15)*in_hr_gas-L15*in_hr_coal)/MAX(S15-T15,0.1))) | Z15: =IF(C15="Low income",in_b40_li,IF(C15="Lower middle income",in_b40_lmi,IF(C15="Upper middle income",in_b40_umi,IF(C15="High income",in_b40_hi,0.03)))) | AA15: =(D15+F15)/G15 | AB15: =100*W15*R15/V15/in_phase | AC15: =100*Z15*W15*R15/V15*(1-IF(W15>0,MIN(in_rebate/(W15*in_res_sh*in_q40),1),1)) | AD15: =IF(AA15>0,100*U15*(1-W15)/(in_whole_sh*V15),0) | AE15: =IF(AA15>0,100*MAX(U15-R15,0)/(in_whole_sh*V15),0) | AF15: =IF(AB15>0,in_f1/AB15,in_cap) | AG15: =IF(AC15>0,in_f2/AC15,in_cap) | AH15: =IF(AD15>0,in_f3/AD15,in_cap) | AI15: =MIN(in_cap,AF15,AG15,AH15) | AJ15: =100*(1-(1-X15*(1-EXP(-((AI15)+(0))/Y15)))*(1-MIN(ABS(in_elas)*W15*R15*(AI15)/V15,1))) | AK15: =IF(AI15>=in_cap-1E-9,"rate cap",TRIM(IF(ABS(AI15-AF15)<1E-9,"F1 ","")&IF(ABS(AI15-AG15)<1E-9,"F2 ","")&IF(ABS(AI15-AH15)<1E-9,"F3",""))) | AL15: =100*(1-(1-X15*(1-EXP(-((MIN(in_cap,IF(AB15>0,(in_f1+1)/AB15,in_cap),AG15,AH15))+(0))/Y15)))*(1-MIN(ABS(in_elas)*W15*R15*(MIN(in_cap,IF(AB15>0,(in_f1+1)/AB15,in_cap),AG15,AH15))/V15,1)))-AJ15 | AM15: =MIN(in_cap,IF(AE15>0,in_f3/AE15,in_cap)) | AN15: =100*(1-(1-X15*(1-EXP(-((0)+(AM15))/Y15)))*(1-MIN(ABS(in_elas)*W15*R15*(0)/V15,1))) | AO15: =IF(AM15>=in_cap-1E-9,"rate cap","F3") | AP15: =100*(1-(1-X15*(1-EXP(-((50)+(0))/Y15)))*(1-MIN(ABS(in_elas)*W15*R15*(50)/V15,1))) | AQ15: =100*(1-(1-X15*(1-EXP(-((0)+(50))/Y15)))*(1-MIN(ABS(in_elas)*W15*R15*(0)/V15,1))) | AR15: =IF(AP15>0,AQ15/AP15,"") | AS15: =50*AB15 | AT15: =MAX(BM15:BW15) | AU15: =AI15*(MATCH(AT15,BM15:BW15,0)-1)/10 | AV15: =INDEX(BB15:BL15,1,(MATCH(AT15,BM15:BW15,0)-1)+1) | AW15: =AB15*AU15 | AX15: =AC15*AU15 | AY15: =AD15*AU15+AE15*AV15 | AZ15: =TRIM(IF(AND(AU15>0,ABS(AU15-AF15)<1E-6),"F1 ","")&IF(AND(AU15>0,ABS(AU15-AG15)<1E-6),"F2 ","")&IF(AY15>=in_f3-1E-6,"F3 ","")&IF(AV15>=in_cap-1E-9,"rate cap","")) | BA15: =Q15*AT15/100 | BB15: =MAX(0,MIN(in_cap,IF(AE15>0,(in_f3-AD15*AI15*0/10)/AE15,in_cap))) | BC15: =MAX(0,MIN(in_cap,IF(AE15>0,(in_f3-AD15*AI15*1/10)/AE15,in_cap))) | BD15: =MAX(0,MIN(in_cap,IF(AE15>0,(in_f3-AD15*AI15*2/10)/AE15,in_cap))) | BE15: =MAX(0,MIN(in_cap,IF(AE15>0,(in_f3-AD15*AI15*3/10)/AE15,in_cap))) | BF15: =MAX(0,MIN(in_cap,IF(AE15>0,(in_f3-AD15*AI15*4/10)/AE15,in_cap))) | BG15: =MAX(0,MIN(in_cap,IF(AE15>0,(in_f3-AD15*AI15*5/10)/AE15,in_cap))) | BH15: =MAX(0,MIN(in_cap,IF(AE15>0,(in_f3-AD15*AI15*6/10)/AE15,in_cap))) | BI15: =MAX(0,MIN(in_cap,IF(AE15>0,(in_f3-AD15*AI15*7/10)/AE15,in_cap))) | BJ15: =MAX(0,MIN(in_cap,IF(AE15>0,(in_f3-AD15*AI15*8/10)/AE15,in_cap))) | BK15: =MAX(0,MIN(in_cap,IF(AE15>0,(in_f3-AD15*AI15*9/10)/AE15,in_cap))) | BL15: =MAX(0,MIN(in_cap,IF(AE15>0,(in_f3-AD15*AI15*10/10)/AE15,in_cap))) | BM15: =100*(1-(1-X15*(1-EXP(-((AI15*0/10)+(BB15))/Y15)))*(1-MIN(ABS(in_elas)*W15*R15*(AI15*0/10)/V15,1))) | BN15: =100*(1-(1-X15*(1-EXP(-((AI15*1/10)+(BC15))/Y15)))*(1-MIN(ABS(in_elas)*W15*R15*(AI15*1/10)/V15,1))) | BO15: =100*(1-(1-X15*(1-EXP(-((AI15*2/10)+(BD15))/Y15)))*(1-MIN(ABS(in_elas)*W15*R15*(AI15*2/10)/V15,1))) | BP15: =100*(1-(1-X15*(1-EXP(-((AI15*3/10)+(BE15))/Y15)))*(1-MIN(ABS(in_elas)*W15*R15*(AI15*3/10)/V15,1))) | BQ15: =100*(1-(1-X15*(1-EXP(-((AI15*4/10)+(BF15))/Y15)))*(1-MIN(ABS(in_elas)*W15*R15*(AI15*4/10)/V15,1))) | BR15: =100*(1-(1-X15*(1-EXP(-((AI15*5/10)+(BG15))/Y15)))*(1-MIN(ABS(in_elas)*W15*R15*(AI15*5/10)/V15,1))) | BS15: =100*(1-(1-X15*(1-EXP(-((AI15*6/10)+(BH15))/Y15)))*(1-MIN(ABS(in_elas)*W15*R15*(AI15*6/10)/V15,1))) | BT15: =100*(1-(1-X15*(1-EXP(-((AI15*7/10)+(BI15))/Y15)))*(1-MIN(ABS(in_elas)*W15*R15*(AI15*7/10)/V15,1))) | BU15: =100*(1-(1-X15*(1-EXP(-((AI15*8/10)+(BJ15))/Y15)))*(1-MIN(ABS(in_elas)*W15*R15*(AI15*8/10)/V15,1))) | BV15: =100*(1-(1-X15*(1-EXP(-((AI15*9/10)+(BK15))/Y15)))*(1-MIN(ABS(in_elas)*W15*R15*(AI15*9/10)/V15,1))) | BW15: =100*(1-(1-X15*(1-EXP(-((AI15*10/10)+(BL15))/Y15)))*(1-MIN(ABS(in_elas)*W15*R15*(AI15*10/10)/V15,1)))
A16: BEL | B16: =INDEX(Data!$B:$B,MATCH($A16,Data!$A:$A,0)) | C16: =INDEX(Data!$D:$D,MATCH($A16,Data!$A:$A,0)) | D16: =SUMIFS(Data!$G:$G,Data!$A:$A,$A16,Data!$F:$F,"gen_coal_twh") | E16: =SUMIFS(Data!$G:$G,Data!$A:$A,$A16,Data!$F:$F,"gen_gas_twh") | F16: =SUMIFS(Data!$G:$G,Data!$A:$A,$A16,Data!$F:$F,"gen_oil_twh") | G16: =SUMIFS(Data!$G:$G,Data!$A:$A,$A16,Data!$F:$F,"gen_total_twh") | H16: =SUMIFS(Data!$G:$G,Data!$A:$A,$A16,Data!$F:$F,"em_coal_mt") | I16: =SUMIFS(Data!$G:$G,Data!$A:$A,$A16,Data!$F:$F,"em_gas_mt") | J16: =SUMIFS(Data!$G:$G,Data!$A:$A,$A16,Data!$F:$F,"em_oil_mt") | K16: =IF(COUNTIFS(Data!$A:$A,$A16,Data!$F:$F,"price_electricity_residential_usd_kwh")=0,"",SUMIFS(Data!$G:$G,Data!$A:$A,$A16,Data!$F:$F,"price_electricity_residential_usd_kwh")) | L16: =IF(COUNTIFS(Data!$A:$A,$A16,Data!$F:$F,"price_coal_power_usd_gj")=0,"",SUMIFS(Data!$G:$G,Data!$A:$A,$A16,Data!$F:$F,"price_coal_power_usd_gj")) | M16: =IF(COUNTIFS(Data!$A:$A,$A16,Data!$F:$F,"price_gas_power_usd_gj")=0,"",SUMIFS(Data!$G:$G,Data!$A:$A,$A16,Data!$F:$F,"price_gas_power_usd_gj")) | N16: =IF(COUNTIFS(Data!$A:$A,$A16,Data!$F:$F,"price_gas_industry_usd_gj")=0,"",SUMIFS(Data!$G:$G,Data!$A:$A,$A16,Data!$F:$F,"price_gas_industry_usd_gj")) | O16: =IF(COUNTIFS(Data!$A:$A,$A16,Data!$F:$F,"power_market_structure")=0,"",SUMIFS(Data!$G:$G,Data!$A:$A,$A16,Data!$F:$F,"power_market_structure")) | P16: =IF(COUNTIFS(Data!$A:$A,$A16,Data!$F:$F,"rise_renewable_energy_score")=0,"",SUMIFS(Data!$G:$G,Data!$A:$A,$A16,Data!$F:$F,"rise_renewable_energy_score")) | Q16: =H16+I16+J16 | R16: =Q16/G16 | S16: =IF(D16>0,H16/D16,0.85) | T16: =IF(E16>0,I16/E16,0.4) | U16: =IF(D16+F16>0,(H16+J16)/(D16+F16),0) | V16: =K16*1000 | W16: =IF(O16=3,in_pt3,IF(O16=2,in_pt2,IF(O16=1,in_pt1,IF(C16="High income",in_pt_hi,in_pt_oth)))) | X16: =IF(Q16>0,in_kappa*(in_rise_lo+(in_rise_hi-in_rise_lo)*IF(P16="",in_rise_miss,P16)/100)*(D16+F16)*MAX(U16-in_gas_rep*T16,0)/Q16,0) | Y16: =IF(IF(M16="",N16,M16)="",MAX(in_sw_floor,in_sw_miss),MAX(in_sw_floor,(IF(M16="",N16,M16)*in_hr_gas-L16*in_hr_coal)/MAX(S16-T16,0.1))) | Z16: =IF(C16="Low income",in_b40_li,IF(C16="Lower middle income",in_b40_lmi,IF(C16="Upper middle income",in_b40_umi,IF(C16="High income",in_b40_hi,0.03)))) | AA16: =(D16+F16)/G16 | AB16: =100*W16*R16/V16/in_phase | AC16: =100*Z16*W16*R16/V16*(1-IF(W16>0,MIN(in_rebate/(W16*in_res_sh*in_q40),1),1)) | AD16: =IF(AA16>0,100*U16*(1-W16)/(in_whole_sh*V16),0) | AE16: =IF(AA16>0,100*MAX(U16-R16,0)/(in_whole_sh*V16),0) | AF16: =IF(AB16>0,in_f1/AB16,in_cap) | AG16: =IF(AC16>0,in_f2/AC16,in_cap) | AH16: =IF(AD16>0,in_f3/AD16,in_cap) | AI16: =MIN(in_cap,AF16,AG16,AH16) | AJ16: =100*(1-(1-X16*(1-EXP(-((AI16)+(0))/Y16)))*(1-MIN(ABS(in_elas)*W16*R16*(AI16)/V16,1))) | AK16: =IF(AI16>=in_cap-1E-9,"rate cap",TRIM(IF(ABS(AI16-AF16)<1E-9,"F1 ","")&IF(ABS(AI16-AG16)<1E-9,"F2 ","")&IF(ABS(AI16-AH16)<1E-9,"F3",""))) | AL16: =100*(1-(1-X16*(1-EXP(-((MIN(in_cap,IF(AB16>0,(in_f1+1)/AB16,in_cap),AG16,AH16))+(0))/Y16)))*(1-MIN(ABS(in_elas)*W16*R16*(MIN(in_cap,IF(AB16>0,(in_f1+1)/AB16,in_cap),AG16,AH16))/V16,1)))-AJ16 | AM16: =MIN(in_cap,IF(AE16>0,in_f3/AE16,in_cap)) | AN16: =100*(1-(1-X16*(1-EXP(-((0)+(AM16))/Y16)))*(1-MIN(ABS(in_elas)*W16*R16*(0)/V16,1))) | AO16: =IF(AM16>=in_cap-1E-9,"rate cap","F3") | AP16: =100*(1-(1-X16*(1-EXP(-((50)+(0))/Y16)))*(1-MIN(ABS(in_elas)*W16*R16*(50)/V16,1))) | AQ16: =100*(1-(1-X16*(1-EXP(-((0)+(50))/Y16)))*(1-MIN(ABS(in_elas)*W16*R16*(0)/V16,1))) | AR16: =IF(AP16>0,AQ16/AP16,"") | AS16: =50*AB16 | AT16: =MAX(BM16:BW16) | AU16: =AI16*(MATCH(AT16,BM16:BW16,0)-1)/10 | AV16: =INDEX(BB16:BL16,1,(MATCH(AT16,BM16:BW16,0)-1)+1) | AW16: =AB16*AU16 | AX16: =AC16*AU16 | AY16: =AD16*AU16+AE16*AV16 | AZ16: =TRIM(IF(AND(AU16>0,ABS(AU16-AF16)<1E-6),"F1 ","")&IF(AND(AU16>0,ABS(AU16-AG16)<1E-6),"F2 ","")&IF(AY16>=in_f3-1E-6,"F3 ","")&IF(AV16>=in_cap-1E-9,"rate cap","")) | BA16: =Q16*AT16/100 | BB16: =MAX(0,MIN(in_cap,IF(AE16>0,(in_f3-AD16*AI16*0/10)/AE16,in_cap))) | BC16: =MAX(0,MIN(in_cap,IF(AE16>0,(in_f3-AD16*AI16*1/10)/AE16,in_cap))) | BD16: =MAX(0,MIN(in_cap,IF(AE16>0,(in_f3-AD16*AI16*2/10)/AE16,in_cap))) | BE16: =MAX(0,MIN(in_cap,IF(AE16>0,(in_f3-AD16*AI16*3/10)/AE16,in_cap))) | BF16: =MAX(0,MIN(in_cap,IF(AE16>0,(in_f3-AD16*AI16*4/10)/AE16,in_cap))) | BG16: =MAX(0,MIN(in_cap,IF(AE16>0,(in_f3-AD16*AI16*5/10)/AE16,in_cap))) | BH16: =MAX(0,MIN(in_cap,IF(AE16>0,(in_f3-AD16*AI16*6/10)/AE16,in_cap))) | BI16: =MAX(0,MIN(in_cap,IF(AE16>0,(in_f3-AD16*AI16*7/10)/AE16,in_cap))) | BJ16: =MAX(0,MIN(in_cap,IF(AE16>0,(in_f3-AD16*AI16*8/10)/AE16,in_cap))) | BK16: =MAX(0,MIN(in_cap,IF(AE16>0,(in_f3-AD16*AI16*9/10)/AE16,in_cap))) | BL16: =MAX(0,MIN(in_cap,IF(AE16>0,(in_f3-AD16*AI16*10/10)/AE16,in_cap))) | BM16: =100*(1-(1-X16*(1-EXP(-((AI16*0/10)+(BB16))/Y16)))*(1-MIN(ABS(in_elas)*W16*R16*(AI16*0/10)/V16,1))) | BN16: =100*(1-(1-X16*(1-EXP(-((AI16*1/10)+(BC16))/Y16)))*(1-MIN(ABS(in_elas)*W16*R16*(AI16*1/10)/V16,1))) | BO16: =100*(1-(1-X16*(1-EXP(-((AI16*2/10)+(BD16))/Y16)))*(1-MIN(ABS(in_elas)*W16*R16*(AI16*2/10)/V16,1))) | BP16: =100*(1-(1-X16*(1-EXP(-((AI16*3/10)+(BE16))/Y16)))*(1-MIN(ABS(in_elas)*W16*R16*(AI16*3/10)/V16,1))) | BQ16: =100*(1-(1-X16*(1-EXP(-((AI16*4/10)+(BF16))/Y16)))*(1-MIN(ABS(in_elas)*W16*R16*(AI16*4/10)/V16,1))) | BR16: =100*(1-(1-X16*(1-EXP(-((AI16*5/10)+(BG16))/Y16)))*(1-MIN(ABS(in_elas)*W16*R16*(AI16*5/10)/V16,1))) | BS16: =100*(1-(1-X16*(1-EXP(-((AI16*6/10)+(BH16))/Y16)))*(1-MIN(ABS(in_elas)*W16*R16*(AI16*6/10)/V16,1))) | BT16: =100*(1-(1-X16*(1-EXP(-((AI16*7/10)+(BI16))/Y16)))*(1-MIN(ABS(in_elas)*W16*R16*(AI16*7/10)/V16,1))) | BU16: =100*(1-(1-X16*(1-EXP(-((AI16*8/10)+(BJ16))/Y16)))*(1-MIN(ABS(in_elas)*W16*R16*(AI16*8/10)/V16,1))) | BV16: =100*(1-(1-X16*(1-EXP(-((AI16*9/10)+(BK16))/Y16)))*(1-MIN(ABS(in_elas)*W16*R16*(AI16*9/10)/V16,1))) | BW16: =100*(1-(1-X16*(1-EXP(-((AI16*10/10)+(BL16))/Y16)))*(1-MIN(ABS(in_elas)*W16*R16*(AI16*10/10)/V16,1)))
... A174: ZWE | B174: =INDEX(Data!$B:$B,MATCH($A174,Data!$A:$A,0)) | C174: =INDEX(Data!$D:$D,MATCH($A174,Data!$A:$A,0)) | D174: =SUMIFS(Data!$G:$G,Data!$A:$A,$A174,Data!$F:$F,"gen_coal_twh") | E174: =SUMIFS(Data!$G:$G,Data!$A:$A,$A174,Data!$F:$F,"gen_gas_twh") | F174: =SUMIFS(Data!$G:$G,Data!$A:$A,$A174,Data!$F:$F,"gen_oil_twh") | G174: =SUMIFS(Data!$G:$G,Data!$A:$A,$A174,Data!$F:$F,"gen_total_twh") | H174: =SUMIFS(Data!$G:$G,Data!$A:$A,$A174,Data!$F:$F,"em_coal_mt") | I174: =SUMIFS(Data!$G:$G,Data!$A:$A,$A174,Data!$F:$F,"em_gas_mt") | J174: =SUMIFS(Data!$G:$G,Data!$A:$A,$A174,Data!$F:$F,"em_oil_mt") | K174: =IF(COUNTIFS(Data!$A:$A,$A174,Data!$F:$F,"price_electricity_residential_usd_kwh")=0,"",SUMIFS(Data!$G:$G,Data!$A:$A,$A174,Data!$F:$F,"price_electricity_residential_usd_kwh")) | L174: =IF(COUNTIFS(Data!$A:$A,$A174,Data!$F:$F,"price_coal_power_usd_gj")=0,"",SUMIFS(Data!$G:$G,Data!$A:$A,$A174,Data!$F:$F,"price_coal_power_usd_gj")) | M174: =IF(COUNTIFS(Data!$A:$A,$A174,Data!$F:$F,"price_gas_power_usd_gj")=0,"",SUMIFS(Data!$G:$G,Data!$A:$A,$A174,Data!$F:$F,"price_gas_power_usd_gj")) | N174: =IF(COUNTIFS(Data!$A:$A,$A174,Data!$F:$F,"price_gas_industry_usd_gj")=0,"",SUMIFS(Data!$G:$G,Data!$A:$A,$A174,Data!$F:$F,"price_gas_industry_usd_gj")) | O174: =IF(COUNTIFS(Data!$A:$A,$A174,Data!$F:$F,"power_market_structure")=0,"",SUMIFS(Data!$G:$G,Data!$A:$A,$A174,Data!$F:$F,"power_market_structure")) | P174: =IF(COUNTIFS(Data!$A:$A,$A174,Data!$F:$F,"rise_renewable_energy_score")=0,"",SUMIFS(Data!$G:$G,Data!$A:$A,$A174,Data!$F:$F,"rise_renewable_energy_score")) | Q174: =H174+I174+J174 | R174: =Q174/G174 | S174: =IF(D174>0,H174/D174,0.85) | T174: =IF(E174>0,I174/E174,0.4) | U174: =IF(D174+F174>0,(H174+J174)/(D174+F174),0) | V174: =K174*1000 | W174: =IF(O174=3,in_pt3,IF(O174=2,in_pt2,IF(O174=1,in_pt1,IF(C174="High income",in_pt_hi,in_pt_oth)))) | X174: =IF(Q174>0,in_kappa*(in_rise_lo+(in_rise_hi-in_rise_lo)*IF(P174="",in_rise_miss,P174)/100)*(D174+F174)*MAX(U174-in_gas_rep*T174,0)/Q174,0) | Y174: =IF(IF(M174="",N174,M174)="",MAX(in_sw_floor,in_sw_miss),MAX(in_sw_floor,(IF(M174="",N174,M174)*in_hr_gas-L174*in_hr_coal)/MAX(S174-T174,0.1))) | Z174: =IF(C174="Low income",in_b40_li,IF(C174="Lower middle income",in_b40_lmi,IF(C174="Upper middle income",in_b40_umi,IF(C174="High income",in_b40_hi,0.03)))) | AA174: =(D174+F174)/G174 | AB174: =100*W174*R174/V174/in_phase | AC174: =100*Z174*W174*R174/V174*(1-IF(W174>0,MIN(in_rebate/(W174*in_res_sh*in_q40),1),1)) | AD174: =IF(AA174>0,100*U174*(1-W174)/(in_whole_sh*V174),0) | AE174: =IF(AA174>0,100*MAX(U174-R174,0)/(in_whole_sh*V174),0) | AF174: =IF(AB174>0,in_f1/AB174,in_cap) | AG174: =IF(AC174>0,in_f2/AC174,in_cap) | AH174: =IF(AD174>0,in_f3/AD174,in_cap) | AI174: =MIN(in_cap,AF174,AG174,AH174) | AJ174: =100*(1-(1-X174*(1-EXP(-((AI174)+(0))/Y174)))*(1-MIN(ABS(in_elas)*W174*R174*(AI174)/V174,1))) | AK174: =IF(AI174>=in_cap-1E-9,"rate cap",TRIM(IF(ABS(AI174-AF174)<1E-9,"F1 ","")&IF(ABS(AI174-AG174)<1E-9,"F2 ","")&IF(ABS(AI174-AH174)<1E-9,"F3",""))) | AL174: =100*(1-(1-X174*(1-EXP(-((MIN(in_cap,IF(AB174>0,(in_f1+1)/AB174,in_cap),AG174,AH174))+(0))/Y174)))*(1-MIN(ABS(in_elas)*W174*R174*(MIN(in_cap,IF(AB174>0,(in_f1+1)/AB174,in_cap),AG174,AH174))/V174,1)))-AJ174 | AM174: =MIN(in_cap,IF(AE174>0,in_f3/AE174,in_cap)) | AN174: =100*(1-(1-X174*(1-EXP(-((0)+(AM174))/Y174)))*(1-MIN(ABS(in_elas)*W174*R174*(0)/V174,1))) | AO174: =IF(AM174>=in_cap-1E-9,"rate cap","F3") | AP174: =100*(1-(1-X174*(1-EXP(-((50)+(0))/Y174)))*(1-MIN(ABS(in_elas)*W174*R174*(50)/V174,1))) | AQ174: =100*(1-(1-X174*(1-EXP(-((0)+(50))/Y174)))*(1-MIN(ABS(in_elas)*W174*R174*(0)/V174,1))) | AR174: =IF(AP174>0,AQ174/AP174,"") | AS174: =50*AB174 | AT174: =MAX(BM174:BW174) | AU174: =AI174*(MATCH(AT174,BM174:BW174,0)-1)/10 | AV174: =INDEX(BB174:BL174,1,(MATCH(AT174,BM174:BW174,0)-1)+1) | AW174: =AB174*AU174 | AX174: =AC174*AU174 | AY174: =AD174*AU174+AE174*AV174 | AZ174: =TRIM(IF(AND(AU174>0,ABS(AU174-AF174)<1E-6),"F1 ","")&IF(AND(AU174>0,ABS(AU174-AG174)<1E-6),"F2 ","")&IF(AY174>=in_f3-1E-6,"F3 ","")&IF(AV174>=in_cap-1E-9,"rate cap","")) | BA174: =Q174*AT174/100 | BB174: =MAX(0,MIN(in_cap,IF(AE174>0,(in_f3-AD174*AI174*0/10)/AE174,in_cap))) | BC174: =MAX(0,MIN(in_cap,IF(AE174>0,(in_f3-AD174*AI174*1/10)/AE174,in_cap))) | BD174: =MAX(0,MIN(in_cap,IF(AE174>0,(in_f3-AD174*AI174*2/10)/AE174,in_cap))) | BE174: =MAX(0,MIN(in_cap,IF(AE174>0,(in_f3-AD174*AI174*3/10)/AE174,in_cap))) | BF174: =MAX(0,MIN(in_cap,IF(AE174>0,(in_f3-AD174*AI174*4/10)/AE174,in_cap))) | BG174: =MAX(0,MIN(in_cap,IF(AE174>0,(in_f3-AD174*AI174*5/10)/AE174,in_cap))) | BH174: =MAX(0,MIN(in_cap,IF(AE174>0,(in_f3-AD174*AI174*6/10)/AE174,in_cap))) | BI174: =MAX(0,MIN(in_cap,IF(AE174>0,(in_f3-AD174*AI174*7/10)/AE174,in_cap))) | BJ174: =MAX(0,MIN(in_cap,IF(AE174>0,(in_f3-AD174*AI174*8/10)/AE174,in_cap))) | BK174: =MAX(0,MIN(in_cap,IF(AE174>0,(in_f3-AD174*AI174*9/10)/AE174,in_cap))) | BL174: =MAX(0,MIN(in_cap,IF(AE174>0,(in_f3-AD174*AI174*10/10)/AE174,in_cap))) | BM174: =100*(1-(1-X174*(1-EXP(-((AI174*0/10)+(BB174))/Y174)))*(1-MIN(ABS(in_elas)*W174*R174*(AI174*0/10)/V174,1))) | BN174: =100*(1-(1-X174*(1-EXP(-((AI174*1/10)+(BC174))/Y174)))*(1-MIN(ABS(in_elas)*W174*R174*(AI174*1/10)/V174,1))) | BO174: =100*(1-(1-X174*(1-EXP(-((AI174*2/10)+(BD174))/Y174)))*(1-MIN(ABS(in_elas)*W174*R174*(AI174*2/10)/V174,1))) | BP174: =100*(1-(1-X174*(1-EXP(-((AI174*3/10)+(BE174))/Y174)))*(1-MIN(ABS(in_elas)*W174*R174*(AI174*3/10)/V174,1))) | BQ174: =100*(1-(1-X174*(1-EXP(-((AI174*4/10)+(BF174))/Y174)))*(1-MIN(ABS(in_elas)*W174*R174*(AI174*4/10)/V174,1))) | BR174: =100*(1-(1-X174*(1-EXP(-((AI174*5/10)+(BG174))/Y174)))*(1-MIN(ABS(in_elas)*W174*R174*(AI174*5/10)/V174,1))) | BS174: =100*(1-(1-X174*(1-EXP(-((AI174*6/10)+(BH174))/Y174)))*(1-MIN(ABS(in_elas)*W174*R174*(AI174*6/10)/V174,1))) | BT174: =100*(1-(1-X174*(1-EXP(-((AI174*7/10)+(BI174))/Y174)))*(1-MIN(ABS(in_elas)*W174*R174*(AI174*7/10)/V174,1))) | BU174: =100*(1-(1-X174*(1-EXP(-((AI174*8/10)+(BJ174))/Y174)))*(1-MIN(ABS(in_elas)*W174*R174*(AI174*8/10)/V174,1))) | BV174: =100*(1-(1-X174*(1-EXP(-((AI174*9/10)+(BK174))/Y174)))*(1-MIN(ABS(in_elas)*W174*R174*(AI174*9/10)/V174,1))) | BW174: =100*(1-(1-X174*(1-EXP(-((AI174*10/10)+(BL174))/Y174)))*(1-MIN(ABS(in_elas)*W174*R174*(AI174*10/10)/V174,1)))

Sheet Data
A1: iso3 | B1: country | C1: region | D1: income | E1: is_ccdr | F1: indicator | G1: value | H1: year | I1: source
A2: ABW | B2: Aruba | C2: Latin America & Caribbean | D2: High income | E2: FALSE | F2: coal_rents_pct_gdp | G2: 0 | H2: 2021 | I2: API_NY_GDP_COAL_RT_ZS_DS2_en_csv_v2_35370.zip
A3: ABW | B3: Aruba | C3: Latin America & Caribbean | D3: High income | E3: FALSE | F3: em_coal_mt | G3: 0 | H3: 2024 | I3: release_generation_yearly_global.csv (Ember)
A4: ABW | B4: Aruba | C4: Latin America & Caribbean | D4: High income | E4: FALSE | F4: em_gas_mt | G4: 0 | H4: 2024 | I4: release_generation_yearly_global.csv (Ember)
A5: ABW | B5: Aruba | C5: Latin America & Caribbean | D5: High income | E5: FALSE | F5: em_oil_mt | G5: 0.546 | H5: 2024 | I5: release_generation_yearly_global.csv (Ember)
A6: ABW | B6: Aruba | C6: Latin America & Caribbean | D6: High income | E6: FALSE | F6: ff_subsidy_explicit_pct_gdp | G6: 0 | H6: 2024 | I6: imffossilfuelsubsidiesdata.xlsb
A7: ABW | B7: Aruba | C7: Latin America & Caribbean | D7: High income | E7: FALSE | F7: fuel_exports_pct_merch | G7: 0.06 | H7: 2023 | I7: API_TX_VAL_FUEL_ZS_UN_DS2_en_csv_v2_33055.zip
A8: ABW | B8: Aruba | C8: Latin America & Caribbean | D8: High income | E8: FALSE | F8: gen_coal_twh | G8: 0 | H8: 2024 | I8: release_generation_yearly_global.csv (Ember)
A9: ABW | B9: Aruba | C9: Latin America & Caribbean | D9: High income | E9: FALSE | F9: gen_gas_twh | G9: 0 | H9: 2024 | I9: release_generation_yearly_global.csv (Ember)
A10: ABW | B10: Aruba | C10: Latin America & Caribbean | D10: High income | E10: FALSE | F10: gen_oil_twh | G10: 0.83 | H10: 2024 | I10: release_generation_yearly_global.csv (Ember)
A11: ABW | B11: Aruba | C11: Latin America & Caribbean | D11: High income | E11: FALSE | F11: gen_total_twh | G11: 1 | H11: 2024 | I11: release_generation_yearly_global.csv (Ember)
A12: ABW | B12: Aruba | C12: Latin America & Caribbean | D12: High income | E12: FALSE | F12: power_market_structure | G12: 1 | H12: 2013 | I12: dataverse_files.zip
A13: ABW | B13: Aruba | C13: Latin America & Caribbean | D13: High income | E13: FALSE | F13: price_coal_power_usd_gj | G13: 5.575 | H13: 2024 | I13: imffossilfuelsubsidiesdata.xlsb
A14: ABW | B14: Aruba | C14: Latin America & Caribbean | D14: High income | E14: FALSE | F14: price_electricity_residential_usd_kwh | G14: 0.275 | H14: 2024 | I14: imffossilfuelsubsidiesdata.xlsb
A15: ABW | B15: Aruba | C15: Latin America & Caribbean | D15: High income | E15: FALSE | F15: price_gas_industry_usd_gj | G15: 2.458 | H15: 2024 | I15: imffossilfuelsubsidiesdata.xlsb
A16: ABW | B16: Aruba | C16: Latin America & Caribbean | D16: High income | E16: FALSE | F16: price_gas_power_usd_gj | G16: 2.458 | H16: 2024 | I16: imffossilfuelsubsidiesdata.xlsb
A17: AFG | B17: Afghanistan | C17: Middle East & North Africa | D17: Low income | E17: FALSE | F17: coal_rents_pct_gdp | G17: 0.019 | H17: 2021 | I17: API_NY_GDP_COAL_RT_ZS_DS2_en_csv_v2_35370.zip
A18: AFG | B18: Afghanistan | C18: Middle East & North Africa | D18: Low income | E18: FALSE | F18: em_coal_mt | G18: 0.027 | H18: 2024 | I18: release_generation_yearly_global.csv (Ember)
A19: AFG | B19: Afghanistan | C19: Middle East & North Africa | D19: Low income | E19: FALSE | F19: em_gas_mt | G19: 0 | H19: 2024 | I19: release_generation_yearly_global.csv (Ember)
A20: AFG | B20: Afghanistan | C20: Middle East & North Africa | D20: Low income | E20: FALSE | F20: em_oil_mt | G20: 0.066 | H20: 2024 | I20: release_generation_yearly_global.csv (Ember)
A21: AFG | B21: Afghanistan | C21: Middle East & North Africa | D21: Low income | E21: FALSE | F21: ff_subsidy_explicit_pct_gdp | G21: 1.383 | H21: 2024 | I21: imffossilfuelsubsidiesdata.xlsb
A22: AFG | B22: Afghanistan | C22: Middle East & North Africa | D22: Low income | E22: FALSE | F22: fuel_exports_pct_merch | G22: 8.051 | H22: 2019 | I22: API_TX_VAL_FUEL_ZS_UN_DS2_en_csv_v2_33055.zip
A23: AFG | B23: Afghanistan | C23: Middle East & North Africa | D23: Low income | E23: FALSE | F23: gen_coal_twh | G23: 0.03 | H23: 2024 | I23: release_generation_yearly_global.csv (Ember)
A24: AFG | B24: Afghanistan | C24: Middle East & North Africa | D24: Low income | E24: FALSE | F24: gen_gas_twh | G24: 0 | H24: 2024 | I24: release_generation_yearly_global.csv (Ember)
A25: AFG | B25: Afghanistan | C25: Middle East & North Africa | D25: Low income | E25: FALSE | F25: gen_oil_twh | G25: 0.1 | H25: 2024 | I25: release_generation_yearly_global.csv (Ember)
A26: AFG | B26: Afghanistan | C26: Middle East & North Africa | D26: Low income | E26: FALSE | F26: gen_total_twh | G26: 0.99 | H26: 2024 | I26: release_generation_yearly_global.csv (Ember)
A27: AFG | B27: Afghanistan | C27: Middle East & North Africa | D27: Low income | E27: FALSE | F27: power_market_structure | G27: 3 | H27: 2013 | I27: dataverse_files.zip
A28: AFG | B28: Afghanistan | C28: Middle East & North Africa | D28: Low income | E28: FALSE | F28: price_coal_power_usd_gj | G28: 4.833 | H28: 2024 | I28: imffossilfuelsubsidiesdata.xlsb
A29: AFG | B29: Afghanistan | C29: Middle East & North Africa | D29: Low income | E29: FALSE | F29: price_electricity_residential_usd_kwh | G29: 0.059 | H29: 2024 | I29: imffossilfuelsubsidiesdata.xlsb
A30: AFG | B30: Afghanistan | C30: Middle East & North Africa | D30: Low income | E30: FALSE | F30: price_gas_industry_usd_gj | G30: 6.449 | H30: 2024 | I30: imffossilfuelsubsidiesdata.xlsb
A31: AFG | B31: Afghanistan | C31: Middle East & North Africa | D31: Low income | E31: FALSE | F31: price_gas_power_usd_gj | G31: 5.125 | H31: 2024 | I31: imffossilfuelsubsidiesdata.xlsb
A32: AFG | B32: Afghanistan | C32: Middle East & North Africa | D32: Low income | E32: FALSE | F32: rise_renewable_energy_score | G32: 12.116 | H32: 2023 | I32: WB_RISE_WIDEF.csv
A33: AGO | B33: Angola | C33: Sub-Saharan Africa | D33: Lower middle income | E33: TRUE | F33: coal_rents_pct_gdp | G33: 0 | H33: 2021 | I33: API_NY_GDP_COAL_RT_ZS_DS2_en_csv_v2_35370.zip
A34: AGO | B34: Angola | C34: Sub-Saharan Africa | D34: Lower middle income | E34: TRUE | F34: em_coal_mt | G34: 0 | H34: 2024 | I34: release_generation_yearly_global.csv (Ember)
A35: AGO | B35: Angola | C35: Sub-Saharan Africa | D35: Lower middle income | E35: TRUE | F35: em_gas_mt | G35: 0.815 | H35: 2024 | I35: release_generation_yearly_global.csv (Ember)
A36: AGO | B36: Angola | C36: Sub-Saharan Africa | D36: Lower middle income | E36: TRUE | F36: em_oil_mt | G36: 1.777 | H36: 2024 | I36: release_generation_yearly_global.csv (Ember)
A37: AGO | B37: Angola | C37: Sub-Saharan Africa | D37: Lower middle income | E37: TRUE | F37: ff_subsidy_explicit_pct_gdp | G37: 3.212 | H37: 2024 | I37: imffossilfuelsubsidiesdata.xlsb
A38: AGO | B38: Angola | C38: Sub-Saharan Africa | D38: Lower middle income | E38: TRUE | F38: fuel_exports_pct_merch | G38: 94.135 | H38: 2024 | I38: API_TX_VAL_FUEL_ZS_UN_DS2_en_csv_v2_33055.zip
A39: AGO | B39: Angola | C39: Sub-Saharan Africa | D39: Lower middle income | E39: TRUE | F39: gen_coal_twh | G39: 0 | H39: 2024 | I39: release_generation_yearly_global.csv (Ember)
A40: AGO | B40: Angola | C40: Sub-Saharan Africa | D40: Lower middle income | E40: TRUE | F40: gen_gas_twh | G40: 1.4 | H40: 2024 | I40: release_generation_yearly_global.csv (Ember)
A41: AGO | B41: Angola | C41: Sub-Saharan Africa | D41: Lower middle income | E41: TRUE | F41: gen_oil_twh | G41: 2.7 | H41: 2024 | I41: release_generation_yearly_global.csv (Ember)
A42: AGO | B42: Angola | C42: Sub-Saharan Africa | D42: Lower middle income | E42: TRUE | F42: gen_total_twh | G42: 15.59 | H42: 2024 | I42: release_generation_yearly_global.csv (Ember)
A43: AGO | B43: Angola | C43: Sub-Saharan Africa | D43: Lower middle income | E43: TRUE | F43: power_market_structure | G43: 1 | H43: 2013 | I43: dataverse_files.zip
A44: AGO | B44: Angola | C44: Sub-Saharan Africa | D44: Lower middle income | E44: TRUE | F44: price_coal_power_usd_gj | G44: 5.66 | H44: 2024 | I44: imffossilfuelsubsidiesdata.xlsb
A45: AGO | B45: Angola | C45: Sub-Saharan Africa | D45: Lower middle income | E45: TRUE | F45: price_electricity_residential_usd_kwh | G45: 0.012 | H45: 2024 | I45: imffossilfuelsubsidiesdata.xlsb
A46: AGO | B46: Angola | C46: Sub-Saharan Africa | D46: Lower middle income | E46: TRUE | F46: price_gas_industry_usd_gj | G46: 6.696 | H46: 2024 | I46: imffossilfuelsubsidiesdata.xlsb
A47: AGO | B47: Angola | C47: Sub-Saharan Africa | D47: Lower middle income | E47: TRUE | F47: price_gas_power_usd_gj | G47: 6.034 | H47: 2024 | I47: imffossilfuelsubsidiesdata.xlsb
A48: AGO | B48: Angola | C48: Sub-Saharan Africa | D48: Lower middle income | E48: TRUE | F48: rise_renewable_energy_score | G48: 28.259 | H48: 2023 | I48: WB_RISE_WIDEF.csv
A49: ALB | B49: Albania | C49: Europe & Central Asia | D49: Upper middle income | E49: TRUE | F49: coal_rents_pct_gdp | G49: 0.032 | H49: 2021 | I49: API_NY_GDP_COAL_RT_ZS_DS2_en_csv_v2_35370.zip
A50: ALB | B50: Albania | C50: Europe & Central Asia | D50: Upper middle income | E50: TRUE | F50: em_coal_mt | G50: 0 | H50: 2024 | I50: release_generation_yearly_global.csv (Ember)
A51: ALB | B51: Albania | C51: Europe & Central Asia | D51: Upper middle income | E51: TRUE | F51: em_gas_mt | G51: 0 | H51: 2024 | I51: release_generation_yearly_global.csv (Ember)
A52: ALB | B52: Albania | C52: Europe & Central Asia | D52: Upper middle income | E52: TRUE | F52: em_oil_mt | G52: 0 | H52: 2024 | I52: release_generation_yearly_global.csv (Ember)
A53: ALB | B53: Albania | C53: Europe & Central Asia | D53: Upper middle income | E53: TRUE | F53: ff_subsidy_explicit_pct_gdp | G53: 0 | H53: 2024 | I53: imffossilfuelsubsidiesdata.xlsb
A54: ALB | B54: Albania | C54: Europe & Central Asia | D54: Upper middle income | E54: TRUE | F54: fuel_exports_pct_merch | G54: 3.258 | H54: 2024 | I54: API_TX_VAL_FUEL_ZS_UN_DS2_en_csv_v2_33055.zip
A55: ALB | B55: Albania | C55: Europe & Central Asia | D55: Upper middle income | E55: TRUE | F55: gen_coal_twh | G55: 0 | H55: 2024 | I55: release_generation_yearly_global.csv (Ember)
A56: ALB | B56: Albania | C56: Europe & Central Asia | D56: Upper middle income | E56: TRUE | F56: gen_gas_twh | G56: 0 | H56: 2024 | I56: release_generation_yearly_global.csv (Ember)
A57: ALB | B57: Albania | C57: Europe & Central Asia | D57: Upper middle income | E57: TRUE | F57: gen_oil_twh | G57: 0 | H57: 2024 | I57: release_generation_yearly_global.csv (Ember)
A58: ALB | B58: Albania | C58: Europe & Central Asia | D58: Upper middle income | E58: TRUE | F58: gen_total_twh | G58: 8.34 | H58: 2024 | I58: release_generation_yearly_global.csv (Ember)
A59: ALB | B59: Albania | C59: Europe & Central Asia | D59: Upper middle income | E59: TRUE | F59: power_market_structure | G59: 3 | H59: 2013 | I59: dataverse_files.zip
A60: ALB | B60: Albania | C60: Europe & Central Asia | D60: Upper middle income | E60: TRUE | F60: price_coal_power_usd_gj | G60: 4.713 | H60: 2024 | I60: imffossilfuelsubsidiesdata.xlsb
A61: ALB | B61: Albania | C61: Europe & Central Asia | D61: Upper middle income | E61: TRUE | F61: price_electricity_residential_usd_kwh | G61: 0.123 | H61: 2024 | I61: imffossilfuelsubsidiesdata.xlsb
A62: ALB | B62: Albania | C62: Europe & Central Asia | D62: Upper middle income | E62: TRUE | F62: price_gas_industry_usd_gj | G62: 6.853 | H62: 2024 | I62: imffossilfuelsubsidiesdata.xlsb
A63: ALB | B63: Albania | C63: Europe & Central Asia | D63: Upper middle income | E63: TRUE | F63: price_gas_power_usd_gj | G63: 6.975 | H63: 2024 | I63: imffossilfuelsubsidiesdata.xlsb
A64: ALB | B64: Albania | C64: Europe & Central Asia | D64: Upper middle income | E64: TRUE | F64: rise_renewable_energy_score | G64: 51.011 | H64: 2023 | I64: WB_RISE_WIDEF.csv
A65: AND | B65: Andorra | C65: Europe & Central Asia | D65: High income | E65: FALSE | F65: fuel_exports_pct_merch | G65: 0.01 | H65: 2023 | I65: API_TX_VAL_FUEL_ZS_UN_DS2_en_csv_v2_33055.zip
A66: AND | B66: Andorra | C66: Europe & Central Asia | D66: High income | E66: FALSE | F66: power_market_structure | G66: 1 | H66: 2013 | I66: dataverse_files.zip
A67: ARE | B67: United Arab Emirates | C67: Middle East & North Africa | D67: High income | E67: FALSE | F67: coal_rents_pct_gdp | G67: 0 | H67: 2021 | I67: API_NY_GDP_COAL_RT_ZS_DS2_en_csv_v2_35370.zip
A68: ARE | B68: United Arab Emirates | C68: Middle East & North Africa | D68: High income | E68: FALSE | F68: em_coal_mt | G68: 0 | H68: 2024 | I68: release_generation_yearly_global.csv (Ember)
A69: ARE | B69: United Arab Emirates | C69: Middle East & North Africa | D69: High income | E69: FALSE | F69: em_gas_mt | G69: 81.892 | H69: 2024 | I69: release_generation_yearly_global.csv (Ember)
A70: ARE | B70: United Arab Emirates | C70: Middle East & North Africa | D70: High income | E70: FALSE | F70: em_oil_mt | G70: 0 | H70: 2024 | I70: release_generation_yearly_global.csv (Ember)
A71: ARE | B71: United Arab Emirates | C71: Middle East & North Africa | D71: High income | E71: FALSE | F71: ff_subsidy_explicit_pct_gdp | G71: 2.028 | H71: 2024 | I71: imffossilfuelsubsidiesdata.xlsb
A72: ARE | B72: United Arab Emirates | C72: Middle East & North Africa | D72: High income | E72: FALSE | F72: fuel_exports_pct_merch | G72: 68.203 | H72: 2023 | I72: API_TX_VAL_FUEL_ZS_UN_DS2_en_csv_v2_33055.zip
A73: ARE | B73: United Arab Emirates | C73: Middle East & North Africa | D73: High income | E73: FALSE | F73: gen_coal_twh | G73: 0 | H73: 2024 | I73: release_generation_yearly_global.csv (Ember)
A74: ARE | B74: United Arab Emirates | C74: Middle East & North Africa | D74: High income | E74: FALSE | F74: gen_gas_twh | G74: 121.01 | H74: 2024 | I74: release_generation_yearly_global.csv (Ember)
A75: ARE | B75: United Arab Emirates | C75: Middle East & North Africa | D75: High income | E75: FALSE | F75: gen_oil_twh | G75: 0 | H75: 2024 | I75: release_generation_yearly_global.csv (Ember)
A76: ARE | B76: United Arab Emirates | C76: Middle East & North Africa | D76: High income | E76: FALSE | F76: gen_total_twh | G76: 177.26 | H76: 2024 | I76: release_generation_yearly_global.csv (Ember)
A77: ARE | B77: United Arab Emirates | C77: Middle East & North Africa | D77: High income | E77: FALSE | F77: power_market_structure | G77: 3 | H77: 2013 | I77: dataverse_files.zip
A78: ARE | B78: United Arab Emirates | C78: Middle East & North Africa | D78: High income | E78: FALSE | F78: price_coal_power_usd_gj | G78: 5.787 | H78: 2024 | I78: imffossilfuelsubsidiesdata.xlsb
A79: ARE | B79: United Arab Emirates | C79: Middle East & North Africa | D79: High income | E79: FALSE | F79: price_electricity_residential_usd_kwh | G79: 0.062 | H79: 2024 | I79: imffossilfuelsubsidiesdata.xlsb
A80: ARE | B80: United Arab Emirates | C80: Middle East & North Africa | D80: High income | E80: FALSE | F80: price_gas_industry_usd_gj | G80: 2.54 | H80: 2024 | I80: imffossilfuelsubsidiesdata.xlsb
A81: ARE | B81: United Arab Emirates | C81: Middle East & North Africa | D81: High income | E81: FALSE | F81: price_gas_power_usd_gj | G81: 3.108 | H81: 2024 | I81: imffossilfuelsubsidiesdata.xlsb
A82: ARE | B82: United Arab Emirates | C82: Middle East & North Africa | D82: High income | E82: FALSE | F82: rise_renewable_energy_score | G82: 53.889 | H82: 2023 | I82: WB_RISE_WIDEF.csv
A83: ARG | B83: Argentina | C83: Latin America & Caribbean | D83: Upper middle income | E83: TRUE | F83: coal_rents_pct_gdp | G83: 0 | H83: 2021 | I83: API_NY_GDP_COAL_RT_ZS_DS2_en_csv_v2_35370.zip
A84: ARG | B84: Argentina | C84: Latin America & Caribbean | D84: Upper middle income | E84: TRUE | F84: em_coal_mt | G84: 1.142 | H84: 2024 | I84: release_generation_yearly_global.csv (Ember)
A85: ARG | B85: Argentina | C85: Latin America & Caribbean | D85: Upper middle income | E85: TRUE | F85: em_gas_mt | G85: 45.637 | H85: 2024 | I85: release_generation_yearly_global.csv (Ember)
A86: ARG | B86: Argentina | C86: Latin America & Caribbean | D86: Upper middle income | E86: TRUE | F86: em_oil_mt | G86: 4.185 | H86: 2024 | I86: release_generation_yearly_global.csv (Ember)
A87: ARG | B87: Argentina | C87: Latin America & Caribbean | D87: Upper middle income | E87: TRUE | F87: ff_subsidy_explicit_pct_gdp | G87: 2.164 | H87: 2024 | I87: imffossilfuelsubsidiesdata.xlsb
A88: ARG | B88: Argentina | C88: Latin America & Caribbean | D88: Upper middle income | E88: TRUE | F88: fuel_exports_pct_merch | G88: 8.77 | H88: 2024 | I88: API_TX_VAL_FUEL_ZS_UN_DS2_en_csv_v2_33055.zip
A89: ARG | B89: Argentina | C89: Latin America & Caribbean | D89: Upper middle income | E89: TRUE | F89: gen_coal_twh | G89: 1.31 | H89: 2024 | I89: release_generation_yearly_global.csv (Ember)
A90: ARG | B90: Argentina | C90: Latin America & Caribbean | D90: Upper middle income | E90: TRUE | F90: gen_gas_twh | G90: 81.95 | H90: 2024 | I90: release_generation_yearly_global.csv (Ember)
A91: ARG | B91: Argentina | C91: Latin America & Caribbean | D91: Upper middle income | E91: TRUE | F91: gen_oil_twh | G91: 6.36 | H91: 2024 | I91: release_generation_yearly_global.csv (Ember)
A92: ARG | B92: Argentina | C92: Latin America & Caribbean | D92: Upper middle income | E92: TRUE | F92: gen_total_twh | G92: 152.51 | H92: 2024 | I92: release_generation_yearly_global.csv (Ember)
A93: ARG | B93: Argentina | C93: Latin America & Caribbean | D93: Upper middle income | E93: TRUE | F93: power_market_structure | G93: 3 | H93: 2013 | I93: dataverse_files.zip
A94: ARG | B94: Argentina | C94: Latin America & Caribbean | D94: Upper middle income | E94: TRUE | F94: price_coal_power_usd_gj | G94: 5.767 | H94: 2024 | I94: imffossilfuelsubsidiesdata.xlsb
A95: ARG | B95: Argentina | C95: Latin America & Caribbean | D95: Upper middle income | E95: TRUE | F95: price_electricity_residential_usd_kwh | G95: 0.081 | H95: 2024 | I95: imffossilfuelsubsidiesdata.xlsb
A96: ARG | B96: Argentina | C96: Latin America & Caribbean | D96: Upper middle income | E96: TRUE | F96: price_gas_industry_usd_gj | G96: 7.576 | H96: 2024 | I96: imffossilfuelsubsidiesdata.xlsb
A97: ARG | B97: Argentina | C97: Latin America & Caribbean | D97: Upper middle income | E97: TRUE | F97: rise_renewable_energy_score | G97: 49.622 | H97: 2023 | I97: WB_RISE_WIDEF.csv
A98: ARM | B98: Armenia | C98: Europe & Central Asia | D98: Upper middle income | E98: TRUE | F98: coal_rents_pct_gdp | G98: 0 | H98: 2021 | I98: API_NY_GDP_COAL_RT_ZS_DS2_en_csv_v2_35370.zip
A99: ARM | B99: Armenia | C99: Europe & Central Asia | D99: Upper middle income | E99: TRUE | F99: em_coal_mt | G99: 0 | H99: 2024 | I99: release_generation_yearly_global.csv (Ember)
A100: ARM | B100: Armenia | C100: Europe & Central Asia | D100: Upper middle income | E100: TRUE | F100: em_gas_mt | G100: 2.066 | H100: 2024 | I100: release_generation_yearly_global.csv (Ember)
...
