Workbook
Name p_alpha: Assumptions!$B$2
Name p_delta: Assumptions!$B$3
Name p_delta_g: Assumptions!$B$4
Name p_lambda_k: Assumptions!$B$5
Name p_lambda_f: Assumptions!$B$6
Name p_lambda_f_res: Assumptions!$B$7
Name p_res_threshold: Assumptions!$B$8
Name p_eta: Assumptions!$B$9
Name p_rk: Assumptions!$B$10
Name p_amort: Assumptions!$B$11
Name p_tr_target: Assumptions!$B$12
Name p_gov_take: Assumptions!$B$13
Name p_rent_decline: Assumptions!$B$14
Name p_programme: Assumptions!$B$15
Name p_pricing: Assumptions!$B$16
Name p_sh_grant: Assumptions!$B$17
Name p_sh_conc: Assumptions!$B$18
Name p_dis_year: Assumptions!$B$19
Name p_eps_k: Assumptions!$B$20
Name p_eps_g: Assumptions!$B$21
Name p_eps_a: Assumptions!$B$22
Name p_rho_a: Assumptions!$B$23
Name dl_iso: Data_long!$A$2:$A$937
Name dl_ind: Data_long!$B$2:$B$937
Name dl_year: Data_long!$C$2:$C$937
Name dl_val: Data_long!$D$2:$D$937

Sheet README
B2: DIGNAD-R Excel
B3: Version 0.1. Proof of concept: a recursive, formula-only DIGNAD-lite / DIGNAR-lite for 12 countries, 2024-2050.
B5: What it is | C5: A simplified DIGNAD (Debt-Investment-Growth and Natural Disasters) with the DIGNAR resource block, written entirely in Excel formulas, computed for all countries at once. It answers: what does the NMIM public investment need, financed by grants, concessional and commercial debt and earmarked carbon-pricing revenue, do to GDP, public debt, transfers and the poorest households, with and without a global fall in fossil rents?
B7: How it differs from DIGNAD-lite | C7: DIGNAD-lite (Python) solves the whole path at once with forward-looking savers. Here every year follows from the previous one: private capital closes a share of the gap to its desired level each year (p_lambda_k) instead of a forward-looking investment choice, and savers' consumption is not modelled. The supply side (production with public capital and efficiency), the budget, the three kinds of financing, the debt-elastic commercial rate, the fiscal rule, the resource block and the disaster shock follow DIGNAD-lite. See the Check sheet for how close the two are.
B9: How to use it | C9: Country sheet: pick a country (yellow cell); see the two scenarios and the charts. Assumptions sheet: change any yellow cell (named p_...), e.g. p_dis_year = 2030 for a disaster, p_pricing = 0 to drop the earmarked revenue, p_sh_grant for more grant financing. Everything recalculates (F9 if not automatic).
B11: Scenarios | C11: Baseline (B): no programme; fossil rents still fall (a global transition). Programme (P): the NMIM incremental budget need (capital builds public capital; land-use and non-CO2 spending does not), financed by p_sh_grant grants, p_sh_conc concessional loans and the rest commercial, less earmarked pricing revenue. P versus B isolates the programme; P versus 2024 is the total.
B13: Inputs (dashboard norms) | C13: Data_wide: one row per country, dashboard columns (same codes as the Tax and Macro-Fiscal Dashboard) then the augmented block (shaded; income-group defaults until the data are added to the dashboard), then __year columns. Data_long: annual paths (iso3, indicator, year, value, source). Spec: every input with its block and source.
B15: Outputs (for a master tool) | C15: Outputs sheet: results in the dashboard's long form (iso3, country, indicator, year, value, source), codes dig.*. Interface sheet: the contract - what the module needs and what it passes.
B17: Sheets | C17: Country (view), Assumptions, Data_wide, Data_long, Spec, Calib (per-country calibration, formulas), Model (one row per country-year, both scenarios, formulas), Outputs, Interface, Check.
B19: Read with care | C19: Illustrative calibration; four augmented inputs are income-group defaults. No energy savings, no private investment push, no exchange rate. A proof of concept, not a forecast.

Sheet Country
B2: DIGNAD-R Excel: one country
B3: Version 0.1. Recursive DIGNAD-lite / DIGNAR-lite, all formulas. Illustrative calibration.
B5: Country (pick) | C5: Kenya | E5: =INDEX(Calib!$A$2:$A$13,MATCH(C5,Calib!$B$2:$B$13,0))
B6: First row of the country in Model | C6: =MATCH(E5,Model!$A$2:$A$325,0)+1
B8: Calibration
B9: Public investment efficiency s | C9: =INDEX(Calib!$E$1:$E$13,MATCH($E$5,Calib!$A$2:$A$13,0)+1)
B10: Return on public capital | C10: =INDEX(Calib!$F$1:$F$13,MATCH($E$5,Calib!$A$2:$A$13,0)+1)
B11: Resource block on? (1 = DIGNAR) | C11: =INDEX(Calib!$M$1:$M$13,MATCH($E$5,Calib!$A$2:$A$13,0)+1)
B12: Rents at start, share of non-resource GDP | C12: =INDEX(Calib!$N$1:$N$13,MATCH($E$5,Calib!$A$2:$A$13,0)+1)
B13: Real commercial rate | C13: =INDEX(Calib!$K$1:$K$13,MATCH($E$5,Calib!$A$2:$A$13,0)+1)
B14: Concessional share of debt | C14: =INDEX(Calib!$J$1:$J$13,MATCH($E$5,Calib!$A$2:$A$13,0)+1)
B16: Results | C16: 2030 | D16: 2050
B17: GDP, programme vs baseline (%) | C17: =INDEX(Model!$AQ$1:$AQ$325,$C$6+6)*1 | D17: =INDEX(Model!$AQ$1:$AQ$325,$C$6+26)*1
B18: GDP vs 2024, programme (%) | C18: =INDEX(Model!$AR$1:$AR$325,$C$6+6)*1 | D18: =INDEX(Model!$AR$1:$AR$325,$C$6+26)*1
B19: GDP vs 2024, baseline (%) | C19: =INDEX(Model!$AS$1:$AS$325,$C$6+6)*1 | D19: =INDEX(Model!$AS$1:$AS$325,$C$6+26)*1
B20: Public debt, programme (% GDP) | C20: =INDEX(Model!$AN$1:$AN$325,$C$6+6)*100 | D20: =INDEX(Model!$AN$1:$AN$325,$C$6+26)*100
B21: Public debt, baseline (% GDP) | C21: =INDEX(Model!$X$1:$X$325,$C$6+6)*100 | D21: =INDEX(Model!$X$1:$X$325,$C$6+26)*100
B22: Debt added by the programme (pp) | C22: =INDEX(Model!$AT$1:$AT$325,$C$6+6)*1 | D22: =INDEX(Model!$AT$1:$AT$325,$C$6+26)*1
B23: Hand-to-mouth consumption, programme vs baseline (%) | C23: =INDEX(Model!$AU$1:$AU$325,$C$6+6)*1 | D23: =INDEX(Model!$AU$1:$AU$325,$C$6+26)*1
B24: Transfers, programme vs baseline (pp GDP) | C24: =INDEX(Model!$AV$1:$AV$325,$C$6+6)*1 | D24: =INDEX(Model!$AV$1:$AV$325,$C$6+26)*1
B25: Fossil rents (% GDP) | C25: =INDEX(Model!$G$1:$G$325,$C$6+6)*100 | D25: =INDEX(Model!$G$1:$G$325,$C$6+26)*100

Sheet Data_wide
A1: iso3 | B1: country | C1: region | D1: income | E1: gross_debt_pct_gdp | F1: tax_revenue_pct_gdp | G1: pefa_pi11_pim_score | H1: ids_multilateral_share_pct | I1: ids_private_creditor_rate_pct | J1: fossil_rents_total_pct_gdp | K1: public_investment_pct_gdp | L1: return_public_capital_pct | M1: hand_to_mouth_pct | N1: grants_pct_gdp | O1: fiscal_rule_speed | P1: gross_debt_pct_gdp__year | Q1: tax_revenue_pct_gdp__year | R1: pefa_pi11_pim_score__year | S1: ids_multilateral_share_pct__year | T1: ids_private_creditor_rate_pct__year | U1: fossil_rents_total_pct_gdp__year | V1: public_investment_pct_gdp__year | W1: return_public_capital_pct__year | X1: hand_to_mouth_pct__year | Y1: grants_pct_gdp__year | Z1: fiscal_rule_speed__year
A2: KEN | B2: Kenya | C2: Sub-Saharan Africa | D2: Lower middle income | E2: 67.338 | F2: 12.937 | G2: 2.5 | H2: 56.192 | I2: 9.47 | J2: 0 | K2: 5 | L2: 17 | M2: 50 | N2: 1 | O2: 0.05 | P2: 2024 | Q2: 2024 | R2: 2023 | S2: 2024 | T2: 2024 | U2: 2021 | V2: default | W2: default | X2: default | Y2: default | Z2: 2026 run
A3: SLE | B3: Sierra Leone | C3: Sub-Saharan Africa | D3: Low income | E3: 46.667 | F3: 6.418 | G3: 1.5 | H3: 70.108 | K3: 6 | L3: 20 | M3: 60 | N3: 2 | O3: 0.05 | P3: 2024 | Q3: 2024 | R3: 2022 | S3: 2024 | V3: default | W3: default | X3: default | Y3: default | Z3: 2026 run
A4: UGA | B4: Uganda | C4: Sub-Saharan Africa | D4: Low income | E4: 51.773 | F4: 12.921 | G4: 1.5 | H4: 61.433 | I4: 7.864 | J4: 0 | K4: 6 | L4: 20 | M4: 60 | N4: 2 | O4: 0.05 | P4: 2024 | Q4: 2024 | R4: 2024 | S4: 2024 | T4: 2024 | U4: 2021 | V4: default | W4: default | X4: default | Y4: default | Z4: 2026 run
A5: LBR | B5: Liberia | C5: Sub-Saharan Africa | D5: Low income | E5: 56.368 | F5: 11.618 | G5: 1.5 | H5: 90.077 | I5: 4.02 | J5: 0 | K5: 6 | L5: 20 | M5: 60 | N5: 2 | O5: 0.2 | P5: 2024 | Q5: 2024 | R5: 2021 | S5: 2024 | T5: 2023 | U5: 2021 | V5: default | W5: default | X5: default | Y5: default | Z5: 2026 run
A6: ETH | B6: Ethiopia | C6: Sub-Saharan Africa | D6: Low income | E6: 33.382 | F6: 6.159 | G6: 1.5 | H6: 46.347 | I6: 3.996 | J6: 0 | K6: 6 | L6: 20 | M6: 60 | N6: 2 | O6: 0.05 | P6: 2024 | Q6: 2024 | R6: 2019 | S6: 2024 | T6: 2024 | U6: 2021 | V6: default | W6: default | X6: default | Y6: default | Z6: 2026 run
A7: RWA | B7: Rwanda | C7: Sub-Saharan Africa | D7: Low income | E7: 63.385 | F7: 13.805 | G7: 3.5 | H7: 66.715 | I7: 4.724 | J7: 0.051 | K7: 6 | L7: 20 | M7: 60 | N7: 2 | O7: 0.05 | P7: 2024 | Q7: 2024 | R7: 2022 | S7: 2024 | T7: 2024 | U7: 2021 | V7: default | W7: default | X7: default | Y7: default | Z7: 2026 run
A8: MOZ | B8: Mozambique | C8: Sub-Saharan Africa | D8: Low income | E8: 91.411 | F8: 20.303 | G8: 1 | H8: 48.897 | I8: 0.25 | J8: 7.426 | K8: 6 | L8: 20 | M8: 60 | N8: 2 | O8: 0.2 | P8: 2024 | Q8: 2024 | R8: 2021 | S8: 2024 | T8: 2022 | U8: 2021 | V8: default | W8: default | X8: default | Y8: default | Z8: 2026 run
A9: GHA | B9: Ghana | C9: Sub-Saharan Africa | D9: Lower middle income | E9: 70.342 | F9: 13.27 | G9: 1 | H9: 34.204 | I9: 1.665 | J9: 4.426 | K9: 5 | L9: 17 | M9: 50 | N9: 1 | O9: 0.05 | P9: 2024 | Q9: 2024 | R9: 2018 | S9: 2024 | T9: 2022 | U9: 2021 | V9: default | W9: default | X9: default | Y9: default | Z9: 2026 run
A10: SEN | B10: Senegal | C10: Sub-Saharan Africa | D10: Lower middle income | E10: 132.395 | F10: 18.197 | G10: 1.5 | H10: 37.879 | I10: 6.367 | J10: 0.003 | K10: 5 | L10: 17 | M10: 50 | N10: 1 | O10: 0.05 | P10: 2024 | Q10: 2024 | R10: 2020 | S10: 2024 | T10: 2024 | U10: 2021 | V10: default | W10: default | X10: default | Y10: default | Z10: 2026 run
A11: AGO | B11: Angola | C11: Sub-Saharan Africa | D11: Lower middle income | E11: 57.107 | F11: 5.608 | H11: 13.443 | I11: 4.681 | J11: 29.286 | K11: 5 | L11: 17 | M11: 50 | N11: 1 | O11: 0.4 | P11: 2024 | Q11: 2024 | S11: 2024 | T11: 2024 | U11: 2021 | V11: default | W11: default | X11: default | Y11: default | Z11: 2026 run
A12: COG | B12: Congo, Rep. | C12: Sub-Saharan Africa | D12: Lower middle income | E12: 98.028 | F12: 10.585 | H12: 25.083 | I12: 5.5 | J12: 34.74 | K12: 5 | L12: 17 | M12: 50 | N12: 1 | O12: 0.4 | P12: 2024 | Q12: 2024 | S12: 2024 | T12: 2024 | U12: 2021 | V12: default | W12: default | X12: default | Y12: default | Z12: 2026 run
A13: TCD | B13: Chad | C13: Sub-Saharan Africa | D13: Low income | E13: 31.427 | F13: 7.372 | G13: 1.5 | H13: 31.116 | J13: 16.765 | K13: 6 | L13: 20 | M13: 60 | N13: 2 | O13: 0.2 | P13: 2024 | Q13: 2024 | R13: 2018 | S13: 2024 | U13: 2021 | V13: default | W13: default | X13: default | Y13: default | Z13: 2026 run

Sheet Data_long
A1: iso3 | B1: indicator | C1: year | D1: value | E1: source
A2: AGO | B2: pub_cap | C2: 2025 | D2: 0.2801 | E2: NMIM v0.2 via MacroFiscalModels
A3: AGO | B3: pub_cap | C3: 2026 | D3: 0.2899 | E3: NMIM v0.2 via MacroFiscalModels
A4: AGO | B4: pub_cap | C4: 2027 | D4: 0.2967 | E4: NMIM v0.2 via MacroFiscalModels
A5: AGO | B5: pub_cap | C5: 2028 | D5: 0.3027 | E5: NMIM v0.2 via MacroFiscalModels
A6: AGO | B6: pub_cap | C6: 2029 | D6: 0.3094 | E6: NMIM v0.2 via MacroFiscalModels
A7: AGO | B7: pub_cap | C7: 2030 | D7: 0.3129 | E7: NMIM v0.2 via MacroFiscalModels
A8: AGO | B8: pub_cap | C8: 2031 | D8: 0.3135 | E8: NMIM v0.2 via MacroFiscalModels
A9: AGO | B9: pub_cap | C9: 2032 | D9: 0.311 | E9: NMIM v0.2 via MacroFiscalModels
A10: AGO | B10: pub_cap | C10: 2033 | D10: 0.3176 | E10: NMIM v0.2 via MacroFiscalModels
A11: AGO | B11: pub_cap | C11: 2034 | D11: 0.3236 | E11: NMIM v0.2 via MacroFiscalModels
A12: AGO | B12: pub_cap | C12: 2035 | D12: 0.3332 | E12: NMIM v0.2 via MacroFiscalModels
A13: AGO | B13: pub_cap | C13: 2036 | D13: 0.3443 | E13: NMIM v0.2 via MacroFiscalModels
... A937: UGA | B937: rev | C937: 2050 | D937: 0 | E937: PriceFeasibility v0.1 x NMIM power CO2

Sheet Assumptions
A1: Name | B1: Value | C1: Description | D1: Source
A2: p_alpha | B2: 0.33 | C2: Private capital share | D2: Standard
A3: p_delta | B3: 0.07 | C3: Private depreciation | D3: Standard
A4: p_delta_g | B4: 0.04 | C4: Public depreciation | D4: Standard
A5: p_lambda_k | B5: 0.3 | C5: Private capital: share of the gap to desired capital closed each year | D5: Assumption (stands in for DIGNAD's forward-looking investment)
A6: p_lambda_f | B6: 0.05 | C6: Fiscal rule: primary-balance adjustment per unit of debt ratio above its start, if Data_wide has no fiscal_rule_speed | D6: As DIGNAD-lite
A7: p_lambda_f_res | B7: 0.2 | C7: Same, resource-rich countries (rents >= threshold) | D7: As DIGNAR-lite
A8: p_res_threshold | B8: 0.1 | C8: Rents threshold for the resource block (share of GDP) | D8: As the integrated run
A9: p_eta | B9: 0.05 | C9: Commercial rate premium per unit of debt ratio above its start | D9: As DIGNAD-lite
A10: p_rk | B10: 0.01 | C10: Concessional real rate | D10: As DIGNAD-lite
A11: p_amort | B11: 0.03 | C11: Repayment rate of new concessional loans | D11: As DIGNAD-lite
A12: p_tr_target | B12: 0.02 | C12: Transfers at the start (government consumption is the residual) | D12: As calibration.py
A13: p_gov_take | B13: 0.5 | C13: Government share of resource rents | D13: Assumption
... A23: p_rho_a | B23: 0.6 | C23: Disaster: TFP loss persistence | D23: As DIGNAD-lite

Sheet Spec
A1: block | B1: code | C1: label | D1: where | E1: source
A2: Dashboard | B2: gross_debt_pct_gdp | C2: Gross debt, general govt (% GDP) | D2: Data_wide | E2: IMF WEO (via the Tax and Macro-Fiscal Dashboard panel)
A3: Dashboard | B3: tax_revenue_pct_gdp | C3: Tax revenue (% GDP) | D3: Data_wide | E3: IMF WoRLD (via the Tax and Macro-Fiscal Dashboard panel)
A4: Dashboard | B4: pefa_pi11_pim_score | C4: PEFA PI-11 public investment management (1-4) | D4: Data_wide | E4: PEFA (via the Tax and Macro-Fiscal Dashboard panel)
A5: Dashboard | B5: ids_multilateral_share_pct | C5: Multilateral share of PPG external debt (%) | D5: Data_wide | E5: World Bank IDS (via the Tax and Macro-Fiscal Dashboard panel)
A6: Dashboard | B6: ids_private_creditor_rate_pct | C6: Interest rate, private creditors (%) | D6: Data_wide | E6: World Bank IDS (via the Tax and Macro-Fiscal Dashboard panel)
A7: Dashboard | B7: fossil_rents_total_pct_gdp | C7: Fossil rents, oil + gas + coal (% GDP) | D7: Data_wide | E7: WDI (via the Tax and Macro-Fiscal Dashboard panel)
A8: Augmented | B8: public_investment_pct_gdp | C8: Public investment (% GDP) | D8: Data_wide | E8: Default by income group (IMF ICSD orders of magnitude); candidate for dashboard Appendix C
A9: Augmented | B9: return_public_capital_pct | C9: Return on public capital (%) | D9: Data_wide | E9: Default by income group (IMF literature 10-25%)
A10: Augmented | B10: hand_to_mouth_pct | C10: Hand-to-mouth households (%) | D10: Data_wide | E10: Default by income group (Findex orders of magnitude); candidate: Findex
A11: Augmented | B11: grants_pct_gdp | C11: Grants (% GDP) | D11: Data_wide | E11: Default by income group; candidate: OECD CRS / IMF GFS
A12: Augmented | B12: fiscal_rule_speed | C12: Fiscal rule speed needed to stabilise debt | D12: Data_wide | E12: MacroFiscalModels integrated run: 0.05 default, 0.2 / 0.4 where it had to tighten (DIGNAR-lite starts at 0.2)
... A15: Augmented | B15: rev | C15: Feasible power carbon-pricing revenue (% GDP) | D15: Data_long | E15: PriceFeasibility v0.1 x NMIM power CO2

Sheet Calib
A1: iso3 | B1: country | C1: income | D1: k | E1: s | F1: Rg | G1: ig | H1: tax | I1: grants0 | J1: conc | K1: rstar | L1: rr | M1: res | N1: rents0 | O1: K0 | P1: KG0 | Q1: psi | R1: A | S1: GDP0 | T1: D0 | U1: Dk0 | V1: int0 | W1: rev0 | X1: g | Y1: trbar | Z1: lam_f | AA1: ratio0
A2: =Data_wide!$A$2 | B2: =Data_wide!$B$2 | C2: =Data_wide!$D$2 | D2: =MATCH(C2,{"Low income","Lower middle income","Upper middle income","High income"},0) | E2: =1-IF(ISNUMBER(Data_wide!$G$2),0.4-(Data_wide!$G$2-1)/3*0.27,CHOOSE(D2,0.4,0.27,0.27,0.13)) | F2: =Data_wide!$L$2/100 | G2: =Data_wide!$K$2/100 | H2: =Data_wide!$F$2/100 | I2: =Data_wide!$N$2/100 | J2: =IF(ISNUMBER(Data_wide!$H$2),Data_wide!$H$2/100,CHOOSE(D2,0.7,0.45,0.15,0)) | K2: =IF(ISNUMBER(Data_wide!$I$2),MIN(MAX(Data_wide!$I$2/100-0.03,0.03),0.08),IF(D2<3,0.04,0.03)) | L2: =IF(ISNUMBER(Data_wide!$J$2),Data_wide!$J$2/100,0) | M2: =IF(L2>=p_res_threshold,1,0) | N2: =IF(M2=1,L2/(1-L2),0) | O2: =p_alpha*(1-H2)/(K2+p_delta) | P2: =E2*G2/p_delta_g | Q2: =F2*P2 | R2: =1/(P2^Q2*O2^p_alpha) | S2: =1+N2 | T2: =Data_wide!$E$2/100*S2 | U2: =J2*T2 | V2: =p_rk*U2+K2*(T2-U2) | W2: =H2+p_gov_take*N2+I2 | X2: =MAX(0.05,W2-G2-V2-p_tr_target) | Y2: =W2-X2-G2-V2 | Z2: =IF(ISNUMBER(Data_wide!$O$2),Data_wide!$O$2,IF(M2=1,p_lambda_f_res,p_lambda_f)) | AA2: =T2/S2
A3: =Data_wide!$A$3 | B3: =Data_wide!$B$3 | C3: =Data_wide!$D$3 | D3: =MATCH(C3,{"Low income","Lower middle income","Upper middle income","High income"},0) | E3: =1-IF(ISNUMBER(Data_wide!$G$3),0.4-(Data_wide!$G$3-1)/3*0.27,CHOOSE(D3,0.4,0.27,0.27,0.13)) | F3: =Data_wide!$L$3/100 | G3: =Data_wide!$K$3/100 | H3: =Data_wide!$F$3/100 | I3: =Data_wide!$N$3/100 | J3: =IF(ISNUMBER(Data_wide!$H$3),Data_wide!$H$3/100,CHOOSE(D3,0.7,0.45,0.15,0)) | K3: =IF(ISNUMBER(Data_wide!$I$3),MIN(MAX(Data_wide!$I$3/100-0.03,0.03),0.08),IF(D3<3,0.04,0.03)) | L3: =IF(ISNUMBER(Data_wide!$J$3),Data_wide!$J$3/100,0) | M3: =IF(L3>=p_res_threshold,1,0) | N3: =IF(M3=1,L3/(1-L3),0) | O3: =p_alpha*(1-H3)/(K3+p_delta) | P3: =E3*G3/p_delta_g | Q3: =F3*P3 | R3: =1/(P3^Q3*O3^p_alpha) | S3: =1+N3 | T3: =Data_wide!$E$3/100*S3 | U3: =J3*T3 | V3: =p_rk*U3+K3*(T3-U3) | W3: =H3+p_gov_take*N3+I3 | X3: =MAX(0.05,W3-G3-V3-p_tr_target) | Y3: =W3-X3-G3-V3 | Z3: =IF(ISNUMBER(Data_wide!$O$3),Data_wide!$O$3,IF(M3=1,p_lambda_f_res,p_lambda_f)) | AA3: =T3/S3
A4: =Data_wide!$A$4 | B4: =Data_wide!$B$4 | C4: =Data_wide!$D$4 | D4: =MATCH(C4,{"Low income","Lower middle income","Upper middle income","High income"},0) | E4: =1-IF(ISNUMBER(Data_wide!$G$4),0.4-(Data_wide!$G$4-1)/3*0.27,CHOOSE(D4,0.4,0.27,0.27,0.13)) | F4: =Data_wide!$L$4/100 | G4: =Data_wide!$K$4/100 | H4: =Data_wide!$F$4/100 | I4: =Data_wide!$N$4/100 | J4: =IF(ISNUMBER(Data_wide!$H$4),Data_wide!$H$4/100,CHOOSE(D4,0.7,0.45,0.15,0)) | K4: =IF(ISNUMBER(Data_wide!$I$4),MIN(MAX(Data_wide!$I$4/100-0.03,0.03),0.08),IF(D4<3,0.04,0.03)) | L4: =IF(ISNUMBER(Data_wide!$J$4),Data_wide!$J$4/100,0) | M4: =IF(L4>=p_res_threshold,1,0) | N4: =IF(M4=1,L4/(1-L4),0) | O4: =p_alpha*(1-H4)/(K4+p_delta) | P4: =E4*G4/p_delta_g | Q4: =F4*P4 | R4: =1/(P4^Q4*O4^p_alpha) | S4: =1+N4 | T4: =Data_wide!$E$4/100*S4 | U4: =J4*T4 | V4: =p_rk*U4+K4*(T4-U4) | W4: =H4+p_gov_take*N4+I4 | X4: =MAX(0.05,W4-G4-V4-p_tr_target) | Y4: =W4-X4-G4-V4 | Z4: =IF(ISNUMBER(Data_wide!$O$4),Data_wide!$O$4,IF(M4=1,p_lambda_f_res,p_lambda_f)) | AA4: =T4/S4
A5: =Data_wide!$A$5 | B5: =Data_wide!$B$5 | C5: =Data_wide!$D$5 | D5: =MATCH(C5,{"Low income","Lower middle income","Upper middle income","High income"},0) | E5: =1-IF(ISNUMBER(Data_wide!$G$5),0.4-(Data_wide!$G$5-1)/3*0.27,CHOOSE(D5,0.4,0.27,0.27,0.13)) | F5: =Data_wide!$L$5/100 | G5: =Data_wide!$K$5/100 | H5: =Data_wide!$F$5/100 | I5: =Data_wide!$N$5/100 | J5: =IF(ISNUMBER(Data_wide!$H$5),Data_wide!$H$5/100,CHOOSE(D5,0.7,0.45,0.15,0)) | K5: =IF(ISNUMBER(Data_wide!$I$5),MIN(MAX(Data_wide!$I$5/100-0.03,0.03),0.08),IF(D5<3,0.04,0.03)) | L5: =IF(ISNUMBER(Data_wide!$J$5),Data_wide!$J$5/100,0) | M5: =IF(L5>=p_res_threshold,1,0) | N5: =IF(M5=1,L5/(1-L5),0) | O5: =p_alpha*(1-H5)/(K5+p_delta) | P5: =E5*G5/p_delta_g | Q5: =F5*P5 | R5: =1/(P5^Q5*O5^p_alpha) | S5: =1+N5 | T5: =Data_wide!$E$5/100*S5 | U5: =J5*T5 | V5: =p_rk*U5+K5*(T5-U5) | W5: =H5+p_gov_take*N5+I5 | X5: =MAX(0.05,W5-G5-V5-p_tr_target) | Y5: =W5-X5-G5-V5 | Z5: =IF(ISNUMBER(Data_wide!$O$5),Data_wide!$O$5,IF(M5=1,p_lambda_f_res,p_lambda_f)) | AA5: =T5/S5
A6: =Data_wide!$A$6 | B6: =Data_wide!$B$6 | C6: =Data_wide!$D$6 | D6: =MATCH(C6,{"Low income","Lower middle income","Upper middle income","High income"},0) | E6: =1-IF(ISNUMBER(Data_wide!$G$6),0.4-(Data_wide!$G$6-1)/3*0.27,CHOOSE(D6,0.4,0.27,0.27,0.13)) | F6: =Data_wide!$L$6/100 | G6: =Data_wide!$K$6/100 | H6: =Data_wide!$F$6/100 | I6: =Data_wide!$N$6/100 | J6: =IF(ISNUMBER(Data_wide!$H$6),Data_wide!$H$6/100,CHOOSE(D6,0.7,0.45,0.15,0)) | K6: =IF(ISNUMBER(Data_wide!$I$6),MIN(MAX(Data_wide!$I$6/100-0.03,0.03),0.08),IF(D6<3,0.04,0.03)) | L6: =IF(ISNUMBER(Data_wide!$J$6),Data_wide!$J$6/100,0) | M6: =IF(L6>=p_res_threshold,1,0) | N6: =IF(M6=1,L6/(1-L6),0) | O6: =p_alpha*(1-H6)/(K6+p_delta) | P6: =E6*G6/p_delta_g | Q6: =F6*P6 | R6: =1/(P6^Q6*O6^p_alpha) | S6: =1+N6 | T6: =Data_wide!$E$6/100*S6 | U6: =J6*T6 | V6: =p_rk*U6+K6*(T6-U6) | W6: =H6+p_gov_take*N6+I6 | X6: =MAX(0.05,W6-G6-V6-p_tr_target) | Y6: =W6-X6-G6-V6 | Z6: =IF(ISNUMBER(Data_wide!$O$6),Data_wide!$O$6,IF(M6=1,p_lambda_f_res,p_lambda_f)) | AA6: =T6/S6
A7: =Data_wide!$A$7 | B7: =Data_wide!$B$7 | C7: =Data_wide!$D$7 | D7: =MATCH(C7,{"Low income","Lower middle income","Upper middle income","High income"},0) | E7: =1-IF(ISNUMBER(Data_wide!$G$7),0.4-(Data_wide!$G$7-1)/3*0.27,CHOOSE(D7,0.4,0.27,0.27,0.13)) | F7: =Data_wide!$L$7/100 | G7: =Data_wide!$K$7/100 | H7: =Data_wide!$F$7/100 | I7: =Data_wide!$N$7/100 | J7: =IF(ISNUMBER(Data_wide!$H$7),Data_wide!$H$7/100,CHOOSE(D7,0.7,0.45,0.15,0)) | K7: =IF(ISNUMBER(Data_wide!$I$7),MIN(MAX(Data_wide!$I$7/100-0.03,0.03),0.08),IF(D7<3,0.04,0.03)) | L7: =IF(ISNUMBER(Data_wide!$J$7),Data_wide!$J$7/100,0) | M7: =IF(L7>=p_res_threshold,1,0) | N7: =IF(M7=1,L7/(1-L7),0) | O7: =p_alpha*(1-H7)/(K7+p_delta) | P7: =E7*G7/p_delta_g | Q7: =F7*P7 | R7: =1/(P7^Q7*O7^p_alpha) | S7: =1+N7 | T7: =Data_wide!$E$7/100*S7 | U7: =J7*T7 | V7: =p_rk*U7+K7*(T7-U7) | W7: =H7+p_gov_take*N7+I7 | X7: =MAX(0.05,W7-G7-V7-p_tr_target) | Y7: =W7-X7-G7-V7 | Z7: =IF(ISNUMBER(Data_wide!$O$7),Data_wide!$O$7,IF(M7=1,p_lambda_f_res,p_lambda_f)) | AA7: =T7/S7
A8: =Data_wide!$A$8 | B8: =Data_wide!$B$8 | C8: =Data_wide!$D$8 | D8: =MATCH(C8,{"Low income","Lower middle income","Upper middle income","High income"},0) | E8: =1-IF(ISNUMBER(Data_wide!$G$8),0.4-(Data_wide!$G$8-1)/3*0.27,CHOOSE(D8,0.4,0.27,0.27,0.13)) | F8: =Data_wide!$L$8/100 | G8: =Data_wide!$K$8/100 | H8: =Data_wide!$F$8/100 | I8: =Data_wide!$N$8/100 | J8: =IF(ISNUMBER(Data_wide!$H$8),Data_wide!$H$8/100,CHOOSE(D8,0.7,0.45,0.15,0)) | K8: =IF(ISNUMBER(Data_wide!$I$8),MIN(MAX(Data_wide!$I$8/100-0.03,0.03),0.08),IF(D8<3,0.04,0.03)) | L8: =IF(ISNUMBER(Data_wide!$J$8),Data_wide!$J$8/100,0) | M8: =IF(L8>=p_res_threshold,1,0) | N8: =IF(M8=1,L8/(1-L8),0) | O8: =p_alpha*(1-H8)/(K8+p_delta) | P8: =E8*G8/p_delta_g | Q8: =F8*P8 | R8: =1/(P8^Q8*O8^p_alpha) | S8: =1+N8 | T8: =Data_wide!$E$8/100*S8 | U8: =J8*T8 | V8: =p_rk*U8+K8*(T8-U8) | W8: =H8+p_gov_take*N8+I8 | X8: =MAX(0.05,W8-G8-V8-p_tr_target) | Y8: =W8-X8-G8-V8 | Z8: =IF(ISNUMBER(Data_wide!$O$8),Data_wide!$O$8,IF(M8=1,p_lambda_f_res,p_lambda_f)) | AA8: =T8/S8
A9: =Data_wide!$A$9 | B9: =Data_wide!$B$9 | C9: =Data_wide!$D$9 | D9: =MATCH(C9,{"Low income","Lower middle income","Upper middle income","High income"},0) | E9: =1-IF(ISNUMBER(Data_wide!$G$9),0.4-(Data_wide!$G$9-1)/3*0.27,CHOOSE(D9,0.4,0.27,0.27,0.13)) | F9: =Data_wide!$L$9/100 | G9: =Data_wide!$K$9/100 | H9: =Data_wide!$F$9/100 | I9: =Data_wide!$N$9/100 | J9: =IF(ISNUMBER(Data_wide!$H$9),Data_wide!$H$9/100,CHOOSE(D9,0.7,0.45,0.15,0)) | K9: =IF(ISNUMBER(Data_wide!$I$9),MIN(MAX(Data_wide!$I$9/100-0.03,0.03),0.08),IF(D9<3,0.04,0.03)) | L9: =IF(ISNUMBER(Data_wide!$J$9),Data_wide!$J$9/100,0) | M9: =IF(L9>=p_res_threshold,1,0) | N9: =IF(M9=1,L9/(1-L9),0) | O9: =p_alpha*(1-H9)/(K9+p_delta) | P9: =E9*G9/p_delta_g | Q9: =F9*P9 | R9: =1/(P9^Q9*O9^p_alpha) | S9: =1+N9 | T9: =Data_wide!$E$9/100*S9 | U9: =J9*T9 | V9: =p_rk*U9+K9*(T9-U9) | W9: =H9+p_gov_take*N9+I9 | X9: =MAX(0.05,W9-G9-V9-p_tr_target) | Y9: =W9-X9-G9-V9 | Z9: =IF(ISNUMBER(Data_wide!$O$9),Data_wide!$O$9,IF(M9=1,p_lambda_f_res,p_lambda_f)) | AA9: =T9/S9
A10: =Data_wide!$A$10 | B10: =Data_wide!$B$10 | C10: =Data_wide!$D$10 | D10: =MATCH(C10,{"Low income","Lower middle income","Upper middle income","High income"},0) | E10: =1-IF(ISNUMBER(Data_wide!$G$10),0.4-(Data_wide!$G$10-1)/3*0.27,CHOOSE(D10,0.4,0.27,0.27,0.13)) | F10: =Data_wide!$L$10/100 | G10: =Data_wide!$K$10/100 | H10: =Data_wide!$F$10/100 | I10: =Data_wide!$N$10/100 | J10: =IF(ISNUMBER(Data_wide!$H$10),Data_wide!$H$10/100,CHOOSE(D10,0.7,0.45,0.15,0)) | K10: =IF(ISNUMBER(Data_wide!$I$10),MIN(MAX(Data_wide!$I$10/100-0.03,0.03),0.08),IF(D10<3,0.04,0.03)) | L10: =IF(ISNUMBER(Data_wide!$J$10),Data_wide!$J$10/100,0) | M10: =IF(L10>=p_res_threshold,1,0) | N10: =IF(M10=1,L10/(1-L10),0) | O10: =p_alpha*(1-H10)/(K10+p_delta) | P10: =E10*G10/p_delta_g | Q10: =F10*P10 | R10: =1/(P10^Q10*O10^p_alpha) | S10: =1+N10 | T10: =Data_wide!$E$10/100*S10 | U10: =J10*T10 | V10: =p_rk*U10+K10*(T10-U10) | W10: =H10+p_gov_take*N10+I10 | X10: =MAX(0.05,W10-G10-V10-p_tr_target) | Y10: =W10-X10-G10-V10 | Z10: =IF(ISNUMBER(Data_wide!$O$10),Data_wide!$O$10,IF(M10=1,p_lambda_f_res,p_lambda_f)) | AA10: =T10/S10
A11: =Data_wide!$A$11 | B11: =Data_wide!$B$11 | C11: =Data_wide!$D$11 | D11: =MATCH(C11,{"Low income","Lower middle income","Upper middle income","High income"},0) | E11: =1-IF(ISNUMBER(Data_wide!$G$11),0.4-(Data_wide!$G$11-1)/3*0.27,CHOOSE(D11,0.4,0.27,0.27,0.13)) | F11: =Data_wide!$L$11/100 | G11: =Data_wide!$K$11/100 | H11: =Data_wide!$F$11/100 | I11: =Data_wide!$N$11/100 | J11: =IF(ISNUMBER(Data_wide!$H$11),Data_wide!$H$11/100,CHOOSE(D11,0.7,0.45,0.15,0)) | K11: =IF(ISNUMBER(Data_wide!$I$11),MIN(MAX(Data_wide!$I$11/100-0.03,0.03),0.08),IF(D11<3,0.04,0.03)) | L11: =IF(ISNUMBER(Data_wide!$J$11),Data_wide!$J$11/100,0) | M11: =IF(L11>=p_res_threshold,1,0) | N11: =IF(M11=1,L11/(1-L11),0) | O11: =p_alpha*(1-H11)/(K11+p_delta) | P11: =E11*G11/p_delta_g | Q11: =F11*P11 | R11: =1/(P11^Q11*O11^p_alpha) | S11: =1+N11 | T11: =Data_wide!$E$11/100*S11 | U11: =J11*T11 | V11: =p_rk*U11+K11*(T11-U11) | W11: =H11+p_gov_take*N11+I11 | X11: =MAX(0.05,W11-G11-V11-p_tr_target) | Y11: =W11-X11-G11-V11 | Z11: =IF(ISNUMBER(Data_wide!$O$11),Data_wide!$O$11,IF(M11=1,p_lambda_f_res,p_lambda_f)) | AA11: =T11/S11
A12: =Data_wide!$A$12 | B12: =Data_wide!$B$12 | C12: =Data_wide!$D$12 | D12: =MATCH(C12,{"Low income","Lower middle income","Upper middle income","High income"},0) | E12: =1-IF(ISNUMBER(Data_wide!$G$12),0.4-(Data_wide!$G$12-1)/3*0.27,CHOOSE(D12,0.4,0.27,0.27,0.13)) | F12: =Data_wide!$L$12/100 | G12: =Data_wide!$K$12/100 | H12: =Data_wide!$F$12/100 | I12: =Data_wide!$N$12/100 | J12: =IF(ISNUMBER(Data_wide!$H$12),Data_wide!$H$12/100,CHOOSE(D12,0.7,0.45,0.15,0)) | K12: =IF(ISNUMBER(Data_wide!$I$12),MIN(MAX(Data_wide!$I$12/100-0.03,0.03),0.08),IF(D12<3,0.04,0.03)) | L12: =IF(ISNUMBER(Data_wide!$J$12),Data_wide!$J$12/100,0) | M12: =IF(L12>=p_res_threshold,1,0) | N12: =IF(M12=1,L12/(1-L12),0) | O12: =p_alpha*(1-H12)/(K12+p_delta) | P12: =E12*G12/p_delta_g | Q12: =F12*P12 | R12: =1/(P12^Q12*O12^p_alpha) | S12: =1+N12 | T12: =Data_wide!$E$12/100*S12 | U12: =J12*T12 | V12: =p_rk*U12+K12*(T12-U12) | W12: =H12+p_gov_take*N12+I12 | X12: =MAX(0.05,W12-G12-V12-p_tr_target) | Y12: =W12-X12-G12-V12 | Z12: =IF(ISNUMBER(Data_wide!$O$12),Data_wide!$O$12,IF(M12=1,p_lambda_f_res,p_lambda_f)) | AA12: =T12/S12
A13: =Data_wide!$A$13 | B13: =Data_wide!$B$13 | C13: =Data_wide!$D$13 | D13: =MATCH(C13,{"Low income","Lower middle income","Upper middle income","High income"},0) | E13: =1-IF(ISNUMBER(Data_wide!$G$13),0.4-(Data_wide!$G$13-1)/3*0.27,CHOOSE(D13,0.4,0.27,0.27,0.13)) | F13: =Data_wide!$L$13/100 | G13: =Data_wide!$K$13/100 | H13: =Data_wide!$F$13/100 | I13: =Data_wide!$N$13/100 | J13: =IF(ISNUMBER(Data_wide!$H$13),Data_wide!$H$13/100,CHOOSE(D13,0.7,0.45,0.15,0)) | K13: =IF(ISNUMBER(Data_wide!$I$13),MIN(MAX(Data_wide!$I$13/100-0.03,0.03),0.08),IF(D13<3,0.04,0.03)) | L13: =IF(ISNUMBER(Data_wide!$J$13),Data_wide!$J$13/100,0) | M13: =IF(L13>=p_res_threshold,1,0) | N13: =IF(M13=1,L13/(1-L13),0) | O13: =p_alpha*(1-H13)/(K13+p_delta) | P13: =E13*G13/p_delta_g | Q13: =F13*P13 | R13: =1/(P13^Q13*O13^p_alpha) | S13: =1+N13 | T13: =Data_wide!$E$13/100*S13 | U13: =J13*T13 | V13: =p_rk*U13+K13*(T13-U13) | W13: =H13+p_gov_take*N13+I13 | X13: =MAX(0.05,W13-G13-V13-p_tr_target) | Y13: =W13-X13-G13-V13 | Z13: =IF(ISNUMBER(Data_wide!$O$13),Data_wide!$O$13,IF(M13=1,p_lambda_f_res,p_lambda_f)) | AA13: =T13/S13

Sheet Model
A1: iso3 | B1: year | C1: t | D1: crow | E1: dis | F1: tfp | G1: rents | H1: cap | I1: spend | J1: rev | K1: B_KG | L1: B_K | M1: B_Y | N1: B_Kstar | O1: B_GDP | P1: B_P | Q1: B_grants | R1: B_revenue | S1: B_tr | T1: B_prim | U1: B_interest | V1: B_D | W1: B_Dk | X1: B_ratio | Y1: B_rc | Z1: B_chtm | AA1: P_KG | AB1: P_K | AC1: P_Y | AD1: P_Kstar | AE1: P_GDP | AF1: P_P | AG1: P_grants | AH1: P_revenue | AI1: P_tr | AJ1: P_prim | AK1: P_interest | AL1: P_D | AM1: P_Dk | AN1: P_ratio | AO1: P_rc | AP1: P_chtm | AQ1: gdp_dev_prog | AR1: gdp_vs_2024_P | AS1: gdp_vs_2024_B | AT1: debt_diff_pp | AU1: chtm_dev_prog | AV1: tr_diff
A2: KEN | B2: 2024 | C2: 0 | D2: 2 | E2: =IF(AND(p_dis_year>0,B2=p_dis_year),1,0) | F2: =IF(AND(p_dis_year>0,B2>=p_dis_year),1-p_eps_a*p_rho_a^(B2-p_dis_year),1) | G2: =INDEX(Calib!$N$1:$N$13,$D2)*(1-p_rent_decline*MIN(1,C2/26)) | H2: =IF(C2=0,0,SUMIFS(dl_val,dl_iso,$A2,dl_ind,"pub_cap",dl_year,$B2)/100) | I2: =IF(C2=0,0,SUMIFS(dl_val,dl_iso,$A2,dl_ind,"pub_spend",dl_year,$B2)/100) | J2: =IF(C2=0,0,SUMIFS(dl_val,dl_iso,$A2,dl_ind,"rev",dl_year,$B2)/100) | K2: =INDEX(Calib!$P$1:$P$13,$D2) | L2: =INDEX(Calib!$O$1:$O$13,$D2) | M2: =1 | N2: =INDEX(Calib!$O$1:$O$13,$D2) | O2: =INDEX(Calib!$S$1:$S$13,$D2) | P2: =0 | Q2: =INDEX(Calib!$I$1:$I$13,$D2) | R2: =INDEX(Calib!$W$1:$W$13,$D2) | S2: =INDEX(Calib!$Y$1:$Y$13,$D2) | T2: =-INDEX(Calib!$V$1:$V$13,$D2) | U2: =INDEX(Calib!$V$1:$V$13,$D2) | V2: =INDEX(Calib!$T$1:$T$13,$D2) | W2: =INDEX(Calib!$U$1:$U$13,$D2) | X2: =V2/O2 | Y2: =INDEX(Calib!$K$1:$K$13,$D2) | Z2: =(1-INDEX(Calib!$H$1:$H$13,$D2))*(1-p_alpha)*M2+S2 | AA2: =INDEX(Calib!$P$1:$P$13,$D2) | AB2: =INDEX(Calib!$O$1:$O$13,$D2) | AC2: =1 | AD2: =INDEX(Calib!$O$1:$O$13,$D2) | AE2: =INDEX(Calib!$S$1:$S$13,$D2) | AF2: =0 | AG2: =INDEX(Calib!$I$1:$I$13,$D2) | AH2: =INDEX(Calib!$W$1:$W$13,$D2) | AI2: =INDEX(Calib!$Y$1:$Y$13,$D2) | AJ2: =-INDEX(Calib!$V$1:$V$13,$D2) | AK2: =INDEX(Calib!$V$1:$V$13,$D2) | AL2: =INDEX(Calib!$T$1:$T$13,$D2) | AM2: =INDEX(Calib!$U$1:$U$13,$D2) | AN2: =AL2/AE2 | AO2: =INDEX(Calib!$K$1:$K$13,$D2) | AP2: =(1-INDEX(Calib!$H$1:$H$13,$D2))*(1-p_alpha)*AC2+AI2 | AQ2: =(AE2/O2-1)*100 | AR2: =(AE2/AE2-1)*100 | AS2: =(O2/O2-1)*100 | AT2: =(AN2-X2)*100 | AU2: =(AP2/Z2-1)*100 | AV2: =(AI2-S2)*100
A3: KEN | B3: 2025 | C3: 1 | D3: 2 | E3: =IF(AND(p_dis_year>0,B3=p_dis_year),1,0) | F3: =IF(AND(p_dis_year>0,B3>=p_dis_year),1-p_eps_a*p_rho_a^(B3-p_dis_year),1) | G3: =INDEX(Calib!$N$1:$N$13,$D3)*(1-p_rent_decline*MIN(1,C3/26)) | H3: =IF(C3=0,0,SUMIFS(dl_val,dl_iso,$A3,dl_ind,"pub_cap",dl_year,$B3)/100) | I3: =IF(C3=0,0,SUMIFS(dl_val,dl_iso,$A3,dl_ind,"pub_spend",dl_year,$B3)/100) | J3: =IF(C3=0,0,SUMIFS(dl_val,dl_iso,$A3,dl_ind,"rev",dl_year,$B3)/100) | K3: =(1-p_delta_g)*K2*(1-p_eps_g*$E3)+INDEX(Calib!$E$1:$E$13,$D3)*(INDEX(Calib!$G$1:$G$13,$D3)+0*$H3) | L3: =L2*(1-p_eps_k*$E3)+p_lambda_k*(N3-L2*(1-p_eps_k*$E3)) | M3: =INDEX(Calib!$R$1:$R$13,$D3)*$F3*(K2*(1-p_eps_g*$E3))^INDEX(Calib!$Q$1:$Q$13,$D3)*(L2*(1-p_eps_k*$E3))^p_alpha | N3: =p_alpha*(1-INDEX(Calib!$H$1:$H$13,$D3))*M3/(INDEX(Calib!$K$1:$K$13,$D3)+p_delta) | O3: =M3+$G3 | P3: =0*($H3+$I3) | Q3: =INDEX(Calib!$I$1:$I$13,$D3)+p_sh_grant*P3 | R3: =INDEX(Calib!$H$1:$H$13,$D3)*M3+p_gov_take*$G3+Q3+0*p_pricing*$J3 | S3: =INDEX(Calib!$Y$1:$Y$13,$D3)-INDEX(Calib!$Z$1:$Z$13,$D3)*(V2/O2-INDEX(Calib!$AA$1:$AA$13,$D3)) | T3: =INDEX(Calib!$X$1:$X$13,$D3)+INDEX(Calib!$G$1:$G$13,$D3)+P3+S3-R3 | U3: =p_rk*W2+Y2*(V2-W2) | V3: =V2+U3+T3 | W3: =INDEX(Calib!$U$1:$U$13,$D3)+(W2-INDEX(Calib!$U$1:$U$13,$D3))*(1-p_amort)+p_sh_conc*P3 | X3: =V3/O3 | Y3: =INDEX(Calib!$K$1:$K$13,$D3)+p_eta*MAX(0,X3-INDEX(Calib!$AA$1:$AA$13,$D3)) | Z3: =(1-INDEX(Calib!$H$1:$H$13,$D3))*(1-p_alpha)*M3+S3 | AA3: =(1-p_delta_g)*AA2*(1-p_eps_g*$E3)+INDEX(Calib!$E$1:$E$13,$D3)*(INDEX(Calib!$G$1:$G$13,$D3)+p_programme*$H3) | AB3: =AB2*(1-p_eps_k*$E3)+p_lambda_k*(AD3-AB2*(1-p_eps_k*$E3)) | AC3: =INDEX(Calib!$R$1:$R$13,$D3)*$F3*(AA2*(1-p_eps_g*$E3))^INDEX(Calib!$Q$1:$Q$13,$D3)*(AB2*(1-p_eps_k*$E3))^p_alpha | AD3: =p_alpha*(1-INDEX(Calib!$H$1:$H$13,$D3))*AC3/(INDEX(Calib!$K$1:$K$13,$D3)+p_delta) | AE3: =AC3+$G3 | AF3: =p_programme*($H3+$I3) | AG3: =INDEX(Calib!$I$1:$I$13,$D3)+p_sh_grant*AF3 | AH3: =INDEX(Calib!$H$1:$H$13,$D3)*AC3+p_gov_take*$G3+AG3+p_programme*p_pricing*$J3 | AI3: =INDEX(Calib!$Y$1:$Y$13,$D3)-INDEX(Calib!$Z$1:$Z$13,$D3)*(AL2/AE2-INDEX(Calib!$AA$1:$AA$13,$D3)) | AJ3: =INDEX(Calib!$X$1:$X$13,$D3)+INDEX(Calib!$G$1:$G$13,$D3)+AF3+AI3-AH3 | AK3: =p_rk*AM2+AO2*(AL2-AM2) | AL3: =AL2+AK3+AJ3 | AM3: =INDEX(Calib!$U$1:$U$13,$D3)+(AM2-INDEX(Calib!$U$1:$U$13,$D3))*(1-p_amort)+p_sh_conc*AF3 | AN3: =AL3/AE3 | AO3: =INDEX(Calib!$K$1:$K$13,$D3)+p_eta*MAX(0,AN3-INDEX(Calib!$AA$1:$AA$13,$D3)) | AP3: =(1-INDEX(Calib!$H$1:$H$13,$D3))*(1-p_alpha)*AC3+AI3 | AQ3: =(AE3/O3-1)*100 | AR3: =(AE3/AE2-1)*100 | AS3: =(O3/O2-1)*100 | AT3: =(AN3-X3)*100 | AU3: =(AP3/Z3-1)*100 | AV3: =(AI3-S3)*100
A4: KEN | B4: 2026 | C4: 2 | D4: 2 | E4: =IF(AND(p_dis_year>0,B4=p_dis_year),1,0) | F4: =IF(AND(p_dis_year>0,B4>=p_dis_year),1-p_eps_a*p_rho_a^(B4-p_dis_year),1) | G4: =INDEX(Calib!$N$1:$N$13,$D4)*(1-p_rent_decline*MIN(1,C4/26)) | H4: =IF(C4=0,0,SUMIFS(dl_val,dl_iso,$A4,dl_ind,"pub_cap",dl_year,$B4)/100) | I4: =IF(C4=0,0,SUMIFS(dl_val,dl_iso,$A4,dl_ind,"pub_spend",dl_year,$B4)/100) | J4: =IF(C4=0,0,SUMIFS(dl_val,dl_iso,$A4,dl_ind,"rev",dl_year,$B4)/100) | K4: =(1-p_delta_g)*K3*(1-p_eps_g*$E4)+INDEX(Calib!$E$1:$E$13,$D4)*(INDEX(Calib!$G$1:$G$13,$D4)+0*$H4) | L4: =L3*(1-p_eps_k*$E4)+p_lambda_k*(N4-L3*(1-p_eps_k*$E4)) | M4: =INDEX(Calib!$R$1:$R$13,$D4)*$F4*(K3*(1-p_eps_g*$E4))^INDEX(Calib!$Q$1:$Q$13,$D4)*(L3*(1-p_eps_k*$E4))^p_alpha | N4: =p_alpha*(1-INDEX(Calib!$H$1:$H$13,$D4))*M4/(INDEX(Calib!$K$1:$K$13,$D4)+p_delta) | O4: =M4+$G4 | P4: =0*($H4+$I4) | Q4: =INDEX(Calib!$I$1:$I$13,$D4)+p_sh_grant*P4 | R4: =INDEX(Calib!$H$1:$H$13,$D4)*M4+p_gov_take*$G4+Q4+0*p_pricing*$J4 | S4: =INDEX(Calib!$Y$1:$Y$13,$D4)-INDEX(Calib!$Z$1:$Z$13,$D4)*(V3/O3-INDEX(Calib!$AA$1:$AA$13,$D4)) | T4: =INDEX(Calib!$X$1:$X$13,$D4)+INDEX(Calib!$G$1:$G$13,$D4)+P4+S4-R4 | U4: =p_rk*W3+Y3*(V3-W3) | V4: =V3+U4+T4 | W4: =INDEX(Calib!$U$1:$U$13,$D4)+(W3-INDEX(Calib!$U$1:$U$13,$D4))*(1-p_amort)+p_sh_conc*P4 | X4: =V4/O4 | Y4: =INDEX(Calib!$K$1:$K$13,$D4)+p_eta*MAX(0,X4-INDEX(Calib!$AA$1:$AA$13,$D4)) | Z4: =(1-INDEX(Calib!$H$1:$H$13,$D4))*(1-p_alpha)*M4+S4 | AA4: =(1-p_delta_g)*AA3*(1-p_eps_g*$E4)+INDEX(Calib!$E$1:$E$13,$D4)*(INDEX(Calib!$G$1:$G$13,$D4)+p_programme*$H4) | AB4: =AB3*(1-p_eps_k*$E4)+p_lambda_k*(AD4-AB3*(1-p_eps_k*$E4)) | AC4: =INDEX(Calib!$R$1:$R$13,$D4)*$F4*(AA3*(1-p_eps_g*$E4))^INDEX(Calib!$Q$1:$Q$13,$D4)*(AB3*(1-p_eps_k*$E4))^p_alpha | AD4: =p_alpha*(1-INDEX(Calib!$H$1:$H$13,$D4))*AC4/(INDEX(Calib!$K$1:$K$13,$D4)+p_delta) | AE4: =AC4+$G4 | AF4: =p_programme*($H4+$I4) | AG4: =INDEX(Calib!$I$1:$I$13,$D4)+p_sh_grant*AF4 | AH4: =INDEX(Calib!$H$1:$H$13,$D4)*AC4+p_gov_take*$G4+AG4+p_programme*p_pricing*$J4 | AI4: =INDEX(Calib!$Y$1:$Y$13,$D4)-INDEX(Calib!$Z$1:$Z$13,$D4)*(AL3/AE3-INDEX(Calib!$AA$1:$AA$13,$D4)) | AJ4: =INDEX(Calib!$X$1:$X$13,$D4)+INDEX(Calib!$G$1:$G$13,$D4)+AF4+AI4-AH4 | AK4: =p_rk*AM3+AO3*(AL3-AM3) | AL4: =AL3+AK4+AJ4 | AM4: =INDEX(Calib!$U$1:$U$13,$D4)+(AM3-INDEX(Calib!$U$1:$U$13,$D4))*(1-p_amort)+p_sh_conc*AF4 | AN4: =AL4/AE4 | AO4: =INDEX(Calib!$K$1:$K$13,$D4)+p_eta*MAX(0,AN4-INDEX(Calib!$AA$1:$AA$13,$D4)) | AP4: =(1-INDEX(Calib!$H$1:$H$13,$D4))*(1-p_alpha)*AC4+AI4 | AQ4: =(AE4/O4-1)*100 | AR4: =(AE4/AE2-1)*100 | AS4: =(O4/O2-1)*100 | AT4: =(AN4-X4)*100 | AU4: =(AP4/Z4-1)*100 | AV4: =(AI4-S4)*100
A5: KEN | B5: 2027 | C5: 3 | D5: 2 | E5: =IF(AND(p_dis_year>0,B5=p_dis_year),1,0) | F5: =IF(AND(p_dis_year>0,B5>=p_dis_year),1-p_eps_a*p_rho_a^(B5-p_dis_year),1) | G5: =INDEX(Calib!$N$1:$N$13,$D5)*(1-p_rent_decline*MIN(1,C5/26)) | H5: =IF(C5=0,0,SUMIFS(dl_val,dl_iso,$A5,dl_ind,"pub_cap",dl_year,$B5)/100) | I5: =IF(C5=0,0,SUMIFS(dl_val,dl_iso,$A5,dl_ind,"pub_spend",dl_year,$B5)/100) | J5: =IF(C5=0,0,SUMIFS(dl_val,dl_iso,$A5,dl_ind,"rev",dl_year,$B5)/100) | K5: =(1-p_delta_g)*K4*(1-p_eps_g*$E5)+INDEX(Calib!$E$1:$E$13,$D5)*(INDEX(Calib!$G$1:$G$13,$D5)+0*$H5) | L5: =L4*(1-p_eps_k*$E5)+p_lambda_k*(N5-L4*(1-p_eps_k*$E5)) | M5: =INDEX(Calib!$R$1:$R$13,$D5)*$F5*(K4*(1-p_eps_g*$E5))^INDEX(Calib!$Q$1:$Q$13,$D5)*(L4*(1-p_eps_k*$E5))^p_alpha | N5: =p_alpha*(1-INDEX(Calib!$H$1:$H$13,$D5))*M5/(INDEX(Calib!$K$1:$K$13,$D5)+p_delta) | O5: =M5+$G5 | P5: =0*($H5+$I5) | Q5: =INDEX(Calib!$I$1:$I$13,$D5)+p_sh_grant*P5 | R5: =INDEX(Calib!$H$1:$H$13,$D5)*M5+p_gov_take*$G5+Q5+0*p_pricing*$J5 | S5: =INDEX(Calib!$Y$1:$Y$13,$D5)-INDEX(Calib!$Z$1:$Z$13,$D5)*(V4/O4-INDEX(Calib!$AA$1:$AA$13,$D5)) | T5: =INDEX(Calib!$X$1:$X$13,$D5)+INDEX(Calib!$G$1:$G$13,$D5)+P5+S5-R5 | U5: =p_rk*W4+Y4*(V4-W4) | V5: =V4+U5+T5 | W5: =INDEX(Calib!$U$1:$U$13,$D5)+(W4-INDEX(Calib!$U$1:$U$13,$D5))*(1-p_amort)+p_sh_conc*P5 | X5: =V5/O5 | Y5: =INDEX(Calib!$K$1:$K$13,$D5)+p_eta*MAX(0,X5-INDEX(Calib!$AA$1:$AA$13,$D5)) | Z5: =(1-INDEX(Calib!$H$1:$H$13,$D5))*(1-p_alpha)*M5+S5 | AA5: =(1-p_delta_g)*AA4*(1-p_eps_g*$E5)+INDEX(Calib!$E$1:$E$13,$D5)*(INDEX(Calib!$G$1:$G$13,$D5)+p_programme*$H5) | AB5: =AB4*(1-p_eps_k*$E5)+p_lambda_k*(AD5-AB4*(1-p_eps_k*$E5)) | AC5: =INDEX(Calib!$R$1:$R$13,$D5)*$F5*(AA4*(1-p_eps_g*$E5))^INDEX(Calib!$Q$1:$Q$13,$D5)*(AB4*(1-p_eps_k*$E5))^p_alpha | AD5: =p_alpha*(1-INDEX(Calib!$H$1:$H$13,$D5))*AC5/(INDEX(Calib!$K$1:$K$13,$D5)+p_delta) | AE5: =AC5+$G5 | AF5: =p_programme*($H5+$I5) | AG5: =INDEX(Calib!$I$1:$I$13,$D5)+p_sh_grant*AF5 | AH5: =INDEX(Calib!$H$1:$H$13,$D5)*AC5+p_gov_take*$G5+AG5+p_programme*p_pricing*$J5 | AI5: =INDEX(Calib!$Y$1:$Y$13,$D5)-INDEX(Calib!$Z$1:$Z$13,$D5)*(AL4/AE4-INDEX(Calib!$AA$1:$AA$13,$D5)) | AJ5: =INDEX(Calib!$X$1:$X$13,$D5)+INDEX(Calib!$G$1:$G$13,$D5)+AF5+AI5-AH5 | AK5: =p_rk*AM4+AO4*(AL4-AM4) | AL5: =AL4+AK5+AJ5 | AM5: =INDEX(Calib!$U$1:$U$13,$D5)+(AM4-INDEX(Calib!$U$1:$U$13,$D5))*(1-p_amort)+p_sh_conc*AF5 | AN5: =AL5/AE5 | AO5: =INDEX(Calib!$K$1:$K$13,$D5)+p_eta*MAX(0,AN5-INDEX(Calib!$AA$1:$AA$13,$D5)) | AP5: =(1-INDEX(Calib!$H$1:$H$13,$D5))*(1-p_alpha)*AC5+AI5 | AQ5: =(AE5/O5-1)*100 | AR5: =(AE5/AE2-1)*100 | AS5: =(O5/O2-1)*100 | AT5: =(AN5-X5)*100 | AU5: =(AP5/Z5-1)*100 | AV5: =(AI5-S5)*100
A6: KEN | B6: 2028 | C6: 4 | D6: 2 | E6: =IF(AND(p_dis_year>0,B6=p_dis_year),1,0) | F6: =IF(AND(p_dis_year>0,B6>=p_dis_year),1-p_eps_a*p_rho_a^(B6-p_dis_year),1) | G6: =INDEX(Calib!$N$1:$N$13,$D6)*(1-p_rent_decline*MIN(1,C6/26)) | H6: =IF(C6=0,0,SUMIFS(dl_val,dl_iso,$A6,dl_ind,"pub_cap",dl_year,$B6)/100) | I6: =IF(C6=0,0,SUMIFS(dl_val,dl_iso,$A6,dl_ind,"pub_spend",dl_year,$B6)/100) | J6: =IF(C6=0,0,SUMIFS(dl_val,dl_iso,$A6,dl_ind,"rev",dl_year,$B6)/100) | K6: =(1-p_delta_g)*K5*(1-p_eps_g*$E6)+INDEX(Calib!$E$1:$E$13,$D6)*(INDEX(Calib!$G$1:$G$13,$D6)+0*$H6) | L6: =L5*(1-p_eps_k*$E6)+p_lambda_k*(N6-L5*(1-p_eps_k*$E6)) | M6: =INDEX(Calib!$R$1:$R$13,$D6)*$F6*(K5*(1-p_eps_g*$E6))^INDEX(Calib!$Q$1:$Q$13,$D6)*(L5*(1-p_eps_k*$E6))^p_alpha | N6: =p_alpha*(1-INDEX(Calib!$H$1:$H$13,$D6))*M6/(INDEX(Calib!$K$1:$K$13,$D6)+p_delta) | O6: =M6+$G6 | P6: =0*($H6+$I6) | Q6: =INDEX(Calib!$I$1:$I$13,$D6)+p_sh_grant*P6 | R6: =INDEX(Calib!$H$1:$H$13,$D6)*M6+p_gov_take*$G6+Q6+0*p_pricing*$J6 | S6: =INDEX(Calib!$Y$1:$Y$13,$D6)-INDEX(Calib!$Z$1:$Z$13,$D6)*(V5/O5-INDEX(Calib!$AA$1:$AA$13,$D6)) | T6: =INDEX(Calib!$X$1:$X$13,$D6)+INDEX(Calib!$G$1:$G$13,$D6)+P6+S6-R6 | U6: =p_rk*W5+Y5*(V5-W5) | V6: =V5+U6+T6 | W6: =INDEX(Calib!$U$1:$U$13,$D6)+(W5-INDEX(Calib!$U$1:$U$13,$D6))*(1-p_amort)+p_sh_conc*P6 | X6: =V6/O6 | Y6: =INDEX(Calib!$K$1:$K$13,$D6)+p_eta*MAX(0,X6-INDEX(Calib!$AA$1:$AA$13,$D6)) | Z6: =(1-INDEX(Calib!$H$1:$H$13,$D6))*(1-p_alpha)*M6+S6 | AA6: =(1-p_delta_g)*AA5*(1-p_eps_g*$E6)+INDEX(Calib!$E$1:$E$13,$D6)*(INDEX(Calib!$G$1:$G$13,$D6)+p_programme*$H6) | AB6: =AB5*(1-p_eps_k*$E6)+p_lambda_k*(AD6-AB5*(1-p_eps_k*$E6)) | AC6: =INDEX(Calib!$R$1:$R$13,$D6)*$F6*(AA5*(1-p_eps_g*$E6))^INDEX(Calib!$Q$1:$Q$13,$D6)*(AB5*(1-p_eps_k*$E6))^p_alpha | AD6: =p_alpha*(1-INDEX(Calib!$H$1:$H$13,$D6))*AC6/(INDEX(Calib!$K$1:$K$13,$D6)+p_delta) | AE6: =AC6+$G6 | AF6: =p_programme*($H6+$I6) | AG6: =INDEX(Calib!$I$1:$I$13,$D6)+p_sh_grant*AF6 | AH6: =INDEX(Calib!$H$1:$H$13,$D6)*AC6+p_gov_take*$G6+AG6+p_programme*p_pricing*$J6 | AI6: =INDEX(Calib!$Y$1:$Y$13,$D6)-INDEX(Calib!$Z$1:$Z$13,$D6)*(AL5/AE5-INDEX(Calib!$AA$1:$AA$13,$D6)) | AJ6: =INDEX(Calib!$X$1:$X$13,$D6)+INDEX(Calib!$G$1:$G$13,$D6)+AF6+AI6-AH6 | AK6: =p_rk*AM5+AO5*(AL5-AM5) | AL6: =AL5+AK6+AJ6 | AM6: =INDEX(Calib!$U$1:$U$13,$D6)+(AM5-INDEX(Calib!$U$1:$U$13,$D6))*(1-p_amort)+p_sh_conc*AF6 | AN6: =AL6/AE6 | AO6: =INDEX(Calib!$K$1:$K$13,$D6)+p_eta*MAX(0,AN6-INDEX(Calib!$AA$1:$AA$13,$D6)) | AP6: =(1-INDEX(Calib!$H$1:$H$13,$D6))*(1-p_alpha)*AC6+AI6 | AQ6: =(AE6/O6-1)*100 | AR6: =(AE6/AE2-1)*100 | AS6: =(O6/O2-1)*100 | AT6: =(AN6-X6)*100 | AU6: =(AP6/Z6-1)*100 | AV6: =(AI6-S6)*100
A7: KEN | B7: 2029 | C7: 5 | D7: 2 | E7: =IF(AND(p_dis_year>0,B7=p_dis_year),1,0) | F7: =IF(AND(p_dis_year>0,B7>=p_dis_year),1-p_eps_a*p_rho_a^(B7-p_dis_year),1) | G7: =INDEX(Calib!$N$1:$N$13,$D7)*(1-p_rent_decline*MIN(1,C7/26)) | H7: =IF(C7=0,0,SUMIFS(dl_val,dl_iso,$A7,dl_ind,"pub_cap",dl_year,$B7)/100) | I7: =IF(C7=0,0,SUMIFS(dl_val,dl_iso,$A7,dl_ind,"pub_spend",dl_year,$B7)/100) | J7: =IF(C7=0,0,SUMIFS(dl_val,dl_iso,$A7,dl_ind,"rev",dl_year,$B7)/100) | K7: =(1-p_delta_g)*K6*(1-p_eps_g*$E7)+INDEX(Calib!$E$1:$E$13,$D7)*(INDEX(Calib!$G$1:$G$13,$D7)+0*$H7) | L7: =L6*(1-p_eps_k*$E7)+p_lambda_k*(N7-L6*(1-p_eps_k*$E7)) | M7: =INDEX(Calib!$R$1:$R$13,$D7)*$F7*(K6*(1-p_eps_g*$E7))^INDEX(Calib!$Q$1:$Q$13,$D7)*(L6*(1-p_eps_k*$E7))^p_alpha | N7: =p_alpha*(1-INDEX(Calib!$H$1:$H$13,$D7))*M7/(INDEX(Calib!$K$1:$K$13,$D7)+p_delta) | O7: =M7+$G7 | P7: =0*($H7+$I7) | Q7: =INDEX(Calib!$I$1:$I$13,$D7)+p_sh_grant*P7 | R7: =INDEX(Calib!$H$1:$H$13,$D7)*M7+p_gov_take*$G7+Q7+0*p_pricing*$J7 | S7: =INDEX(Calib!$Y$1:$Y$13,$D7)-INDEX(Calib!$Z$1:$Z$13,$D7)*(V6/O6-INDEX(Calib!$AA$1:$AA$13,$D7)) | T7: =INDEX(Calib!$X$1:$X$13,$D7)+INDEX(Calib!$G$1:$G$13,$D7)+P7+S7-R7 | U7: =p_rk*W6+Y6*(V6-W6) | V7: =V6+U7+T7 | W7: =INDEX(Calib!$U$1:$U$13,$D7)+(W6-INDEX(Calib!$U$1:$U$13,$D7))*(1-p_amort)+p_sh_conc*P7 | X7: =V7/O7 | Y7: =INDEX(Calib!$K$1:$K$13,$D7)+p_eta*MAX(0,X7-INDEX(Calib!$AA$1:$AA$13,$D7)) | Z7: =(1-INDEX(Calib!$H$1:$H$13,$D7))*(1-p_alpha)*M7+S7 | AA7: =(1-p_delta_g)*AA6*(1-p_eps_g*$E7)+INDEX(Calib!$E$1:$E$13,$D7)*(INDEX(Calib!$G$1:$G$13,$D7)+p_programme*$H7) | AB7: =AB6*(1-p_eps_k*$E7)+p_lambda_k*(AD7-AB6*(1-p_eps_k*$E7)) | AC7: =INDEX(Calib!$R$1:$R$13,$D7)*$F7*(AA6*(1-p_eps_g*$E7))^INDEX(Calib!$Q$1:$Q$13,$D7)*(AB6*(1-p_eps_k*$E7))^p_alpha | AD7: =p_alpha*(1-INDEX(Calib!$H$1:$H$13,$D7))*AC7/(INDEX(Calib!$K$1:$K$13,$D7)+p_delta) | AE7: =AC7+$G7 | AF7: =p_programme*($H7+$I7) | AG7: =INDEX(Calib!$I$1:$I$13,$D7)+p_sh_grant*AF7 | AH7: =INDEX(Calib!$H$1:$H$13,$D7)*AC7+p_gov_take*$G7+AG7+p_programme*p_pricing*$J7 | AI7: =INDEX(Calib!$Y$1:$Y$13,$D7)-INDEX(Calib!$Z$1:$Z$13,$D7)*(AL6/AE6-INDEX(Calib!$AA$1:$AA$13,$D7)) | AJ7: =INDEX(Calib!$X$1:$X$13,$D7)+INDEX(Calib!$G$1:$G$13,$D7)+AF7+AI7-AH7 | AK7: =p_rk*AM6+AO6*(AL6-AM6) | AL7: =AL6+AK7+AJ7 | AM7: =INDEX(Calib!$U$1:$U$13,$D7)+(AM6-INDEX(Calib!$U$1:$U$13,$D7))*(1-p_amort)+p_sh_conc*AF7 | AN7: =AL7/AE7 | AO7: =INDEX(Calib!$K$1:$K$13,$D7)+p_eta*MAX(0,AN7-INDEX(Calib!$AA$1:$AA$13,$D7)) | AP7: =(1-INDEX(Calib!$H$1:$H$13,$D7))*(1-p_alpha)*AC7+AI7 | AQ7: =(AE7/O7-1)*100 | AR7: =(AE7/AE2-1)*100 | AS7: =(O7/O2-1)*100 | AT7: =(AN7-X7)*100 | AU7: =(AP7/Z7-1)*100 | AV7: =(AI7-S7)*100
A8: KEN | B8: 2030 | C8: 6 | D8: 2 | E8: =IF(AND(p_dis_year>0,B8=p_dis_year),1,0) | F8: =IF(AND(p_dis_year>0,B8>=p_dis_year),1-p_eps_a*p_rho_a^(B8-p_dis_year),1) | G8: =INDEX(Calib!$N$1:$N$13,$D8)*(1-p_rent_decline*MIN(1,C8/26)) | H8: =IF(C8=0,0,SUMIFS(dl_val,dl_iso,$A8,dl_ind,"pub_cap",dl_year,$B8)/100) | I8: =IF(C8=0,0,SUMIFS(dl_val,dl_iso,$A8,dl_ind,"pub_spend",dl_year,$B8)/100) | J8: =IF(C8=0,0,SUMIFS(dl_val,dl_iso,$A8,dl_ind,"rev",dl_year,$B8)/100) | K8: =(1-p_delta_g)*K7*(1-p_eps_g*$E8)+INDEX(Calib!$E$1:$E$13,$D8)*(INDEX(Calib!$G$1:$G$13,$D8)+0*$H8) | L8: =L7*(1-p_eps_k*$E8)+p_lambda_k*(N8-L7*(1-p_eps_k*$E8)) | M8: =INDEX(Calib!$R$1:$R$13,$D8)*$F8*(K7*(1-p_eps_g*$E8))^INDEX(Calib!$Q$1:$Q$13,$D8)*(L7*(1-p_eps_k*$E8))^p_alpha | N8: =p_alpha*(1-INDEX(Calib!$H$1:$H$13,$D8))*M8/(INDEX(Calib!$K$1:$K$13,$D8)+p_delta) | O8: =M8+$G8 | P8: =0*($H8+$I8) | Q8: =INDEX(Calib!$I$1:$I$13,$D8)+p_sh_grant*P8 | R8: =INDEX(Calib!$H$1:$H$13,$D8)*M8+p_gov_take*$G8+Q8+0*p_pricing*$J8 | S8: =INDEX(Calib!$Y$1:$Y$13,$D8)-INDEX(Calib!$Z$1:$Z$13,$D8)*(V7/O7-INDEX(Calib!$AA$1:$AA$13,$D8)) | T8: =INDEX(Calib!$X$1:$X$13,$D8)+INDEX(Calib!$G$1:$G$13,$D8)+P8+S8-R8 | U8: =p_rk*W7+Y7*(V7-W7) | V8: =V7+U8+T8 | W8: =INDEX(Calib!$U$1:$U$13,$D8)+(W7-INDEX(Calib!$U$1:$U$13,$D8))*(1-p_amort)+p_sh_conc*P8 | X8: =V8/O8 | Y8: =INDEX(Calib!$K$1:$K$13,$D8)+p_eta*MAX(0,X8-INDEX(Calib!$AA$1:$AA$13,$D8)) | Z8: =(1-INDEX(Calib!$H$1:$H$13,$D8))*(1-p_alpha)*M8+S8 | AA8: =(1-p_delta_g)*AA7*(1-p_eps_g*$E8)+INDEX(Calib!$E$1:$E$13,$D8)*(INDEX(Calib!$G$1:$G$13,$D8)+p_programme*$H8) | AB8: =AB7*(1-p_eps_k*$E8)+p_lambda_k*(AD8-AB7*(1-p_eps_k*$E8)) | AC8: =INDEX(Calib!$R$1:$R$13,$D8)*$F8*(AA7*(1-p_eps_g*$E8))^INDEX(Calib!$Q$1:$Q$13,$D8)*(AB7*(1-p_eps_k*$E8))^p_alpha | AD8: =p_alpha*(1-INDEX(Calib!$H$1:$H$13,$D8))*AC8/(INDEX(Calib!$K$1:$K$13,$D8)+p_delta) | AE8: =AC8+$G8 | AF8: =p_programme*($H8+$I8) | AG8: =INDEX(Calib!$I$1:$I$13,$D8)+p_sh_grant*AF8 | AH8: =INDEX(Calib!$H$1:$H$13,$D8)*AC8+p_gov_take*$G8+AG8+p_programme*p_pricing*$J8 | AI8: =INDEX(Calib!$Y$1:$Y$13,$D8)-INDEX(Calib!$Z$1:$Z$13,$D8)*(AL7/AE7-INDEX(Calib!$AA$1:$AA$13,$D8)) | AJ8: =INDEX(Calib!$X$1:$X$13,$D8)+INDEX(Calib!$G$1:$G$13,$D8)+AF8+AI8-AH8 | AK8: =p_rk*AM7+AO7*(AL7-AM7) | AL8: =AL7+AK8+AJ8 | AM8: =INDEX(Calib!$U$1:$U$13,$D8)+(AM7-INDEX(Calib!$U$1:$U$13,$D8))*(1-p_amort)+p_sh_conc*AF8 | AN8: =AL8/AE8 | AO8: =INDEX(Calib!$K$1:$K$13,$D8)+p_eta*MAX(0,AN8-INDEX(Calib!$AA$1:$AA$13,$D8)) | AP8: =(1-INDEX(Calib!$H$1:$H$13,$D8))*(1-p_alpha)*AC8+AI8 | AQ8: =(AE8/O8-1)*100 | AR8: =(AE8/AE2-1)*100 | AS8: =(O8/O2-1)*100 | AT8: =(AN8-X8)*100 | AU8: =(AP8/Z8-1)*100 | AV8: =(AI8-S8)*100
A9: KEN | B9: 2031 | C9: 7 | D9: 2 | E9: =IF(AND(p_dis_year>0,B9=p_dis_year),1,0) | F9: =IF(AND(p_dis_year>0,B9>=p_dis_year),1-p_eps_a*p_rho_a^(B9-p_dis_year),1) | G9: =INDEX(Calib!$N$1:$N$13,$D9)*(1-p_rent_decline*MIN(1,C9/26)) | H9: =IF(C9=0,0,SUMIFS(dl_val,dl_iso,$A9,dl_ind,"pub_cap",dl_year,$B9)/100) | I9: =IF(C9=0,0,SUMIFS(dl_val,dl_iso,$A9,dl_ind,"pub_spend",dl_year,$B9)/100) | J9: =IF(C9=0,0,SUMIFS(dl_val,dl_iso,$A9,dl_ind,"rev",dl_year,$B9)/100) | K9: =(1-p_delta_g)*K8*(1-p_eps_g*$E9)+INDEX(Calib!$E$1:$E$13,$D9)*(INDEX(Calib!$G$1:$G$13,$D9)+0*$H9) | L9: =L8*(1-p_eps_k*$E9)+p_lambda_k*(N9-L8*(1-p_eps_k*$E9)) | M9: =INDEX(Calib!$R$1:$R$13,$D9)*$F9*(K8*(1-p_eps_g*$E9))^INDEX(Calib!$Q$1:$Q$13,$D9)*(L8*(1-p_eps_k*$E9))^p_alpha | N9: =p_alpha*(1-INDEX(Calib!$H$1:$H$13,$D9))*M9/(INDEX(Calib!$K$1:$K$13,$D9)+p_delta) | O9: =M9+$G9 | P9: =0*($H9+$I9) | Q9: =INDEX(Calib!$I$1:$I$13,$D9)+p_sh_grant*P9 | R9: =INDEX(Calib!$H$1:$H$13,$D9)*M9+p_gov_take*$G9+Q9+0*p_pricing*$J9 | S9: =INDEX(Calib!$Y$1:$Y$13,$D9)-INDEX(Calib!$Z$1:$Z$13,$D9)*(V8/O8-INDEX(Calib!$AA$1:$AA$13,$D9)) | T9: =INDEX(Calib!$X$1:$X$13,$D9)+INDEX(Calib!$G$1:$G$13,$D9)+P9+S9-R9 | U9: =p_rk*W8+Y8*(V8-W8) | V9: =V8+U9+T9 | W9: =INDEX(Calib!$U$1:$U$13,$D9)+(W8-INDEX(Calib!$U$1:$U$13,$D9))*(1-p_amort)+p_sh_conc*P9 | X9: =V9/O9 | Y9: =INDEX(Calib!$K$1:$K$13,$D9)+p_eta*MAX(0,X9-INDEX(Calib!$AA$1:$AA$13,$D9)) | Z9: =(1-INDEX(Calib!$H$1:$H$13,$D9))*(1-p_alpha)*M9+S9 | AA9: =(1-p_delta_g)*AA8*(1-p_eps_g*$E9)+INDEX(Calib!$E$1:$E$13,$D9)*(INDEX(Calib!$G$1:$G$13,$D9)+p_programme*$H9) | AB9: =AB8*(1-p_eps_k*$E9)+p_lambda_k*(AD9-AB8*(1-p_eps_k*$E9)) | AC9: =INDEX(Calib!$R$1:$R$13,$D9)*$F9*(AA8*(1-p_eps_g*$E9))^INDEX(Calib!$Q$1:$Q$13,$D9)*(AB8*(1-p_eps_k*$E9))^p_alpha | AD9: =p_alpha*(1-INDEX(Calib!$H$1:$H$13,$D9))*AC9/(INDEX(Calib!$K$1:$K$13,$D9)+p_delta) | AE9: =AC9+$G9 | AF9: =p_programme*($H9+$I9) | AG9: =INDEX(Calib!$I$1:$I$13,$D9)+p_sh_grant*AF9 | AH9: =INDEX(Calib!$H$1:$H$13,$D9)*AC9+p_gov_take*$G9+AG9+p_programme*p_pricing*$J9 | AI9: =INDEX(Calib!$Y$1:$Y$13,$D9)-INDEX(Calib!$Z$1:$Z$13,$D9)*(AL8/AE8-INDEX(Calib!$AA$1:$AA$13,$D9)) | AJ9: =INDEX(Calib!$X$1:$X$13,$D9)+INDEX(Calib!$G$1:$G$13,$D9)+AF9+AI9-AH9 | AK9: =p_rk*AM8+AO8*(AL8-AM8) | AL9: =AL8+AK9+AJ9 | AM9: =INDEX(Calib!$U$1:$U$13,$D9)+(AM8-INDEX(Calib!$U$1:$U$13,$D9))*(1-p_amort)+p_sh_conc*AF9 | AN9: =AL9/AE9 | AO9: =INDEX(Calib!$K$1:$K$13,$D9)+p_eta*MAX(0,AN9-INDEX(Calib!$AA$1:$AA$13,$D9)) | AP9: =(1-INDEX(Calib!$H$1:$H$13,$D9))*(1-p_alpha)*AC9+AI9 | AQ9: =(AE9/O9-1)*100 | AR9: =(AE9/AE2-1)*100 | AS9: =(O9/O2-1)*100 | AT9: =(AN9-X9)*100 | AU9: =(AP9/Z9-1)*100 | AV9: =(AI9-S9)*100
A10: KEN | B10: 2032 | C10: 8 | D10: 2 | E10: =IF(AND(p_dis_year>0,B10=p_dis_year),1,0) | F10: =IF(AND(p_dis_year>0,B10>=p_dis_year),1-p_eps_a*p_rho_a^(B10-p_dis_year),1) | G10: =INDEX(Calib!$N$1:$N$13,$D10)*(1-p_rent_decline*MIN(1,C10/26)) | H10: =IF(C10=0,0,SUMIFS(dl_val,dl_iso,$A10,dl_ind,"pub_cap",dl_year,$B10)/100) | I10: =IF(C10=0,0,SUMIFS(dl_val,dl_iso,$A10,dl_ind,"pub_spend",dl_year,$B10)/100) | J10: =IF(C10=0,0,SUMIFS(dl_val,dl_iso,$A10,dl_ind,"rev",dl_year,$B10)/100) | K10: =(1-p_delta_g)*K9*(1-p_eps_g*$E10)+INDEX(Calib!$E$1:$E$13,$D10)*(INDEX(Calib!$G$1:$G$13,$D10)+0*$H10) | L10: =L9*(1-p_eps_k*$E10)+p_lambda_k*(N10-L9*(1-p_eps_k*$E10)) | M10: =INDEX(Calib!$R$1:$R$13,$D10)*$F10*(K9*(1-p_eps_g*$E10))^INDEX(Calib!$Q$1:$Q$13,$D10)*(L9*(1-p_eps_k*$E10))^p_alpha | N10: =p_alpha*(1-INDEX(Calib!$H$1:$H$13,$D10))*M10/(INDEX(Calib!$K$1:$K$13,$D10)+p_delta) | O10: =M10+$G10 | P10: =0*($H10+$I10) | Q10: =INDEX(Calib!$I$1:$I$13,$D10)+p_sh_grant*P10 | R10: =INDEX(Calib!$H$1:$H$13,$D10)*M10+p_gov_take*$G10+Q10+0*p_pricing*$J10 | S10: =INDEX(Calib!$Y$1:$Y$13,$D10)-INDEX(Calib!$Z$1:$Z$13,$D10)*(V9/O9-INDEX(Calib!$AA$1:$AA$13,$D10)) | T10: =INDEX(Calib!$X$1:$X$13,$D10)+INDEX(Calib!$G$1:$G$13,$D10)+P10+S10-R10 | U10: =p_rk*W9+Y9*(V9-W9) | V10: =V9+U10+T10 | W10: =INDEX(Calib!$U$1:$U$13,$D10)+(W9-INDEX(Calib!$U$1:$U$13,$D10))*(1-p_amort)+p_sh_conc*P10 | X10: =V10/O10 | Y10: =INDEX(Calib!$K$1:$K$13,$D10)+p_eta*MAX(0,X10-INDEX(Calib!$AA$1:$AA$13,$D10)) | Z10: =(1-INDEX(Calib!$H$1:$H$13,$D10))*(1-p_alpha)*M10+S10 | AA10: =(1-p_delta_g)*AA9*(1-p_eps_g*$E10)+INDEX(Calib!$E$1:$E$13,$D10)*(INDEX(Calib!$G$1:$G$13,$D10)+p_programme*$H10) | AB10: =AB9*(1-p_eps_k*$E10)+p_lambda_k*(AD10-AB9*(1-p_eps_k*$E10)) | AC10: =INDEX(Calib!$R$1:$R$13,$D10)*$F10*(AA9*(1-p_eps_g*$E10))^INDEX(Calib!$Q$1:$Q$13,$D10)*(AB9*(1-p_eps_k*$E10))^p_alpha | AD10: =p_alpha*(1-INDEX(Calib!$H$1:$H$13,$D10))*AC10/(INDEX(Calib!$K$1:$K$13,$D10)+p_delta) | AE10: =AC10+$G10 | AF10: =p_programme*($H10+$I10) | AG10: =INDEX(Calib!$I$1:$I$13,$D10)+p_sh_grant*AF10 | AH10: =INDEX(Calib!$H$1:$H$13,$D10)*AC10+p_gov_take*$G10+AG10+p_programme*p_pricing*$J10 | AI10: =INDEX(Calib!$Y$1:$Y$13,$D10)-INDEX(Calib!$Z$1:$Z$13,$D10)*(AL9/AE9-INDEX(Calib!$AA$1:$AA$13,$D10)) | AJ10: =INDEX(Calib!$X$1:$X$13,$D10)+INDEX(Calib!$G$1:$G$13,$D10)+AF10+AI10-AH10 | AK10: =p_rk*AM9+AO9*(AL9-AM9) | AL10: =AL9+AK10+AJ10 | AM10: =INDEX(Calib!$U$1:$U$13,$D10)+(AM9-INDEX(Calib!$U$1:$U$13,$D10))*(1-p_amort)+p_sh_conc*AF10 | AN10: =AL10/AE10 | AO10: =INDEX(Calib!$K$1:$K$13,$D10)+p_eta*MAX(0,AN10-INDEX(Calib!$AA$1:$AA$13,$D10)) | AP10: =(1-INDEX(Calib!$H$1:$H$13,$D10))*(1-p_alpha)*AC10+AI10 | AQ10: =(AE10/O10-1)*100 | AR10: =(AE10/AE2-1)*100 | AS10: =(O10/O2-1)*100 | AT10: =(AN10-X10)*100 | AU10: =(AP10/Z10-1)*100 | AV10: =(AI10-S10)*100
A11: KEN | B11: 2033 | C11: 9 | D11: 2 | E11: =IF(AND(p_dis_year>0,B11=p_dis_year),1,0) | F11: =IF(AND(p_dis_year>0,B11>=p_dis_year),1-p_eps_a*p_rho_a^(B11-p_dis_year),1) | G11: =INDEX(Calib!$N$1:$N$13,$D11)*(1-p_rent_decline*MIN(1,C11/26)) | H11: =IF(C11=0,0,SUMIFS(dl_val,dl_iso,$A11,dl_ind,"pub_cap",dl_year,$B11)/100) | I11: =IF(C11=0,0,SUMIFS(dl_val,dl_iso,$A11,dl_ind,"pub_spend",dl_year,$B11)/100) | J11: =IF(C11=0,0,SUMIFS(dl_val,dl_iso,$A11,dl_ind,"rev",dl_year,$B11)/100) | K11: =(1-p_delta_g)*K10*(1-p_eps_g*$E11)+INDEX(Calib!$E$1:$E$13,$D11)*(INDEX(Calib!$G$1:$G$13,$D11)+0*$H11) | L11: =L10*(1-p_eps_k*$E11)+p_lambda_k*(N11-L10*(1-p_eps_k*$E11)) | M11: =INDEX(Calib!$R$1:$R$13,$D11)*$F11*(K10*(1-p_eps_g*$E11))^INDEX(Calib!$Q$1:$Q$13,$D11)*(L10*(1-p_eps_k*$E11))^p_alpha | N11: =p_alpha*(1-INDEX(Calib!$H$1:$H$13,$D11))*M11/(INDEX(Calib!$K$1:$K$13,$D11)+p_delta) | O11: =M11+$G11 | P11: =0*($H11+$I11) | Q11: =INDEX(Calib!$I$1:$I$13,$D11)+p_sh_grant*P11 | R11: =INDEX(Calib!$H$1:$H$13,$D11)*M11+p_gov_take*$G11+Q11+0*p_pricing*$J11 | S11: =INDEX(Calib!$Y$1:$Y$13,$D11)-INDEX(Calib!$Z$1:$Z$13,$D11)*(V10/O10-INDEX(Calib!$AA$1:$AA$13,$D11)) | T11: =INDEX(Calib!$X$1:$X$13,$D11)+INDEX(Calib!$G$1:$G$13,$D11)+P11+S11-R11 | U11: =p_rk*W10+Y10*(V10-W10) | V11: =V10+U11+T11 | W11: =INDEX(Calib!$U$1:$U$13,$D11)+(W10-INDEX(Calib!$U$1:$U$13,$D11))*(1-p_amort)+p_sh_conc*P11 | X11: =V11/O11 | Y11: =INDEX(Calib!$K$1:$K$13,$D11)+p_eta*MAX(0,X11-INDEX(Calib!$AA$1:$AA$13,$D11)) | Z11: =(1-INDEX(Calib!$H$1:$H$13,$D11))*(1-p_alpha)*M11+S11 | AA11: =(1-p_delta_g)*AA10*(1-p_eps_g*$E11)+INDEX(Calib!$E$1:$E$13,$D11)*(INDEX(Calib!$G$1:$G$13,$D11)+p_programme*$H11) | AB11: =AB10*(1-p_eps_k*$E11)+p_lambda_k*(AD11-AB10*(1-p_eps_k*$E11)) | AC11: =INDEX(Calib!$R$1:$R$13,$D11)*$F11*(AA10*(1-p_eps_g*$E11))^INDEX(Calib!$Q$1:$Q$13,$D11)*(AB10*(1-p_eps_k*$E11))^p_alpha | AD11: =p_alpha*(1-INDEX(Calib!$H$1:$H$13,$D11))*AC11/(INDEX(Calib!$K$1:$K$13,$D11)+p_delta) | AE11: =AC11+$G11 | AF11: =p_programme*($H11+$I11) | AG11: =INDEX(Calib!$I$1:$I$13,$D11)+p_sh_grant*AF11 | AH11: =INDEX(Calib!$H$1:$H$13,$D11)*AC11+p_gov_take*$G11+AG11+p_programme*p_pricing*$J11 | AI11: =INDEX(Calib!$Y$1:$Y$13,$D11)-INDEX(Calib!$Z$1:$Z$13,$D11)*(AL10/AE10-INDEX(Calib!$AA$1:$AA$13,$D11)) | AJ11: =INDEX(Calib!$X$1:$X$13,$D11)+INDEX(Calib!$G$1:$G$13,$D11)+AF11+AI11-AH11 | AK11: =p_rk*AM10+AO10*(AL10-AM10) | AL11: =AL10+AK11+AJ11 | AM11: =INDEX(Calib!$U$1:$U$13,$D11)+(AM10-INDEX(Calib!$U$1:$U$13,$D11))*(1-p_amort)+p_sh_conc*AF11 | AN11: =AL11/AE11 | AO11: =INDEX(Calib!$K$1:$K$13,$D11)+p_eta*MAX(0,AN11-INDEX(Calib!$AA$1:$AA$13,$D11)) | AP11: =(1-INDEX(Calib!$H$1:$H$13,$D11))*(1-p_alpha)*AC11+AI11 | AQ11: =(AE11/O11-1)*100 | AR11: =(AE11/AE2-1)*100 | AS11: =(O11/O2-1)*100 | AT11: =(AN11-X11)*100 | AU11: =(AP11/Z11-1)*100 | AV11: =(AI11-S11)*100
A12: KEN | B12: 2034 | C12: 10 | D12: 2 | E12: =IF(AND(p_dis_year>0,B12=p_dis_year),1,0) | F12: =IF(AND(p_dis_year>0,B12>=p_dis_year),1-p_eps_a*p_rho_a^(B12-p_dis_year),1) | G12: =INDEX(Calib!$N$1:$N$13,$D12)*(1-p_rent_decline*MIN(1,C12/26)) | H12: =IF(C12=0,0,SUMIFS(dl_val,dl_iso,$A12,dl_ind,"pub_cap",dl_year,$B12)/100) | I12: =IF(C12=0,0,SUMIFS(dl_val,dl_iso,$A12,dl_ind,"pub_spend",dl_year,$B12)/100) | J12: =IF(C12=0,0,SUMIFS(dl_val,dl_iso,$A12,dl_ind,"rev",dl_year,$B12)/100) | K12: =(1-p_delta_g)*K11*(1-p_eps_g*$E12)+INDEX(Calib!$E$1:$E$13,$D12)*(INDEX(Calib!$G$1:$G$13,$D12)+0*$H12) | L12: =L11*(1-p_eps_k*$E12)+p_lambda_k*(N12-L11*(1-p_eps_k*$E12)) | M12: =INDEX(Calib!$R$1:$R$13,$D12)*$F12*(K11*(1-p_eps_g*$E12))^INDEX(Calib!$Q$1:$Q$13,$D12)*(L11*(1-p_eps_k*$E12))^p_alpha | N12: =p_alpha*(1-INDEX(Calib!$H$1:$H$13,$D12))*M12/(INDEX(Calib!$K$1:$K$13,$D12)+p_delta) | O12: =M12+$G12 | P12: =0*($H12+$I12) | Q12: =INDEX(Calib!$I$1:$I$13,$D12)+p_sh_grant*P12 | R12: =INDEX(Calib!$H$1:$H$13,$D12)*M12+p_gov_take*$G12+Q12+0*p_pricing*$J12 | S12: =INDEX(Calib!$Y$1:$Y$13,$D12)-INDEX(Calib!$Z$1:$Z$13,$D12)*(V11/O11-INDEX(Calib!$AA$1:$AA$13,$D12)) | T12: =INDEX(Calib!$X$1:$X$13,$D12)+INDEX(Calib!$G$1:$G$13,$D12)+P12+S12-R12 | U12: =p_rk*W11+Y11*(V11-W11) | V12: =V11+U12+T12 | W12: =INDEX(Calib!$U$1:$U$13,$D12)+(W11-INDEX(Calib!$U$1:$U$13,$D12))*(1-p_amort)+p_sh_conc*P12 | X12: =V12/O12 | Y12: =INDEX(Calib!$K$1:$K$13,$D12)+p_eta*MAX(0,X12-INDEX(Calib!$AA$1:$AA$13,$D12)) | Z12: =(1-INDEX(Calib!$H$1:$H$13,$D12))*(1-p_alpha)*M12+S12 | AA12: =(1-p_delta_g)*AA11*(1-p_eps_g*$E12)+INDEX(Calib!$E$1:$E$13,$D12)*(INDEX(Calib!$G$1:$G$13,$D12)+p_programme*$H12) | AB12: =AB11*(1-p_eps_k*$E12)+p_lambda_k*(AD12-AB11*(1-p_eps_k*$E12)) | AC12: =INDEX(Calib!$R$1:$R$13,$D12)*$F12*(AA11*(1-p_eps_g*$E12))^INDEX(Calib!$Q$1:$Q$13,$D12)*(AB11*(1-p_eps_k*$E12))^p_alpha | AD12: =p_alpha*(1-INDEX(Calib!$H$1:$H$13,$D12))*AC12/(INDEX(Calib!$K$1:$K$13,$D12)+p_delta) | AE12: =AC12+$G12 | AF12: =p_programme*($H12+$I12) | AG12: =INDEX(Calib!$I$1:$I$13,$D12)+p_sh_grant*AF12 | AH12: =INDEX(Calib!$H$1:$H$13,$D12)*AC12+p_gov_take*$G12+AG12+p_programme*p_pricing*$J12 | AI12: =INDEX(Calib!$Y$1:$Y$13,$D12)-INDEX(Calib!$Z$1:$Z$13,$D12)*(AL11/AE11-INDEX(Calib!$AA$1:$AA$13,$D12)) | AJ12: =INDEX(Calib!$X$1:$X$13,$D12)+INDEX(Calib!$G$1:$G$13,$D12)+AF12+AI12-AH12 | AK12: =p_rk*AM11+AO11*(AL11-AM11) | AL12: =AL11+AK12+AJ12 | AM12: =INDEX(Calib!$U$1:$U$13,$D12)+(AM11-INDEX(Calib!$U$1:$U$13,$D12))*(1-p_amort)+p_sh_conc*AF12 | AN12: =AL12/AE12 | AO12: =INDEX(Calib!$K$1:$K$13,$D12)+p_eta*MAX(0,AN12-INDEX(Calib!$AA$1:$AA$13,$D12)) | AP12: =(1-INDEX(Calib!$H$1:$H$13,$D12))*(1-p_alpha)*AC12+AI12 | AQ12: =(AE12/O12-1)*100 | AR12: =(AE12/AE2-1)*100 | AS12: =(O12/O2-1)*100 | AT12: =(AN12-X12)*100 | AU12: =(AP12/Z12-1)*100 | AV12: =(AI12-S12)*100
A13: KEN | B13: 2035 | C13: 11 | D13: 2 | E13: =IF(AND(p_dis_year>0,B13=p_dis_year),1,0) | F13: =IF(AND(p_dis_year>0,B13>=p_dis_year),1-p_eps_a*p_rho_a^(B13-p_dis_year),1) | G13: =INDEX(Calib!$N$1:$N$13,$D13)*(1-p_rent_decline*MIN(1,C13/26)) | H13: =IF(C13=0,0,SUMIFS(dl_val,dl_iso,$A13,dl_ind,"pub_cap",dl_year,$B13)/100) | I13: =IF(C13=0,0,SUMIFS(dl_val,dl_iso,$A13,dl_ind,"pub_spend",dl_year,$B13)/100) | J13: =IF(C13=0,0,SUMIFS(dl_val,dl_iso,$A13,dl_ind,"rev",dl_year,$B13)/100) | K13: =(1-p_delta_g)*K12*(1-p_eps_g*$E13)+INDEX(Calib!$E$1:$E$13,$D13)*(INDEX(Calib!$G$1:$G$13,$D13)+0*$H13) | L13: =L12*(1-p_eps_k*$E13)+p_lambda_k*(N13-L12*(1-p_eps_k*$E13)) | M13: =INDEX(Calib!$R$1:$R$13,$D13)*$F13*(K12*(1-p_eps_g*$E13))^INDEX(Calib!$Q$1:$Q$13,$D13)*(L12*(1-p_eps_k*$E13))^p_alpha | N13: =p_alpha*(1-INDEX(Calib!$H$1:$H$13,$D13))*M13/(INDEX(Calib!$K$1:$K$13,$D13)+p_delta) | O13: =M13+$G13 | P13: =0*($H13+$I13) | Q13: =INDEX(Calib!$I$1:$I$13,$D13)+p_sh_grant*P13 | R13: =INDEX(Calib!$H$1:$H$13,$D13)*M13+p_gov_take*$G13+Q13+0*p_pricing*$J13 | S13: =INDEX(Calib!$Y$1:$Y$13,$D13)-INDEX(Calib!$Z$1:$Z$13,$D13)*(V12/O12-INDEX(Calib!$AA$1:$AA$13,$D13)) | T13: =INDEX(Calib!$X$1:$X$13,$D13)+INDEX(Calib!$G$1:$G$13,$D13)+P13+S13-R13 | U13: =p_rk*W12+Y12*(V12-W12) | V13: =V12+U13+T13 | W13: =INDEX(Calib!$U$1:$U$13,$D13)+(W12-INDEX(Calib!$U$1:$U$13,$D13))*(1-p_amort)+p_sh_conc*P13 | X13: =V13/O13 | Y13: =INDEX(Calib!$K$1:$K$13,$D13)+p_eta*MAX(0,X13-INDEX(Calib!$AA$1:$AA$13,$D13)) | Z13: =(1-INDEX(Calib!$H$1:$H$13,$D13))*(1-p_alpha)*M13+S13 | AA13: =(1-p_delta_g)*AA12*(1-p_eps_g*$E13)+INDEX(Calib!$E$1:$E$13,$D13)*(INDEX(Calib!$G$1:$G$13,$D13)+p_programme*$H13) | AB13: =AB12*(1-p_eps_k*$E13)+p_lambda_k*(AD13-AB12*(1-p_eps_k*$E13)) | AC13: =INDEX(Calib!$R$1:$R$13,$D13)*$F13*(AA12*(1-p_eps_g*$E13))^INDEX(Calib!$Q$1:$Q$13,$D13)*(AB12*(1-p_eps_k*$E13))^p_alpha | AD13: =p_alpha*(1-INDEX(Calib!$H$1:$H$13,$D13))*AC13/(INDEX(Calib!$K$1:$K$13,$D13)+p_delta) | AE13: =AC13+$G13 | AF13: =p_programme*($H13+$I13) | AG13: =INDEX(Calib!$I$1:$I$13,$D13)+p_sh_grant*AF13 | AH13: =INDEX(Calib!$H$1:$H$13,$D13)*AC13+p_gov_take*$G13+AG13+p_programme*p_pricing*$J13 | AI13: =INDEX(Calib!$Y$1:$Y$13,$D13)-INDEX(Calib!$Z$1:$Z$13,$D13)*(AL12/AE12-INDEX(Calib!$AA$1:$AA$13,$D13)) | AJ13: =INDEX(Calib!$X$1:$X$13,$D13)+INDEX(Calib!$G$1:$G$13,$D13)+AF13+AI13-AH13 | AK13: =p_rk*AM12+AO12*(AL12-AM12) | AL13: =AL12+AK13+AJ13 | AM13: =INDEX(Calib!$U$1:$U$13,$D13)+(AM12-INDEX(Calib!$U$1:$U$13,$D13))*(1-p_amort)+p_sh_conc*AF13 | AN13: =AL13/AE13 | AO13: =INDEX(Calib!$K$1:$K$13,$D13)+p_eta*MAX(0,AN13-INDEX(Calib!$AA$1:$AA$13,$D13)) | AP13: =(1-INDEX(Calib!$H$1:$H$13,$D13))*(1-p_alpha)*AC13+AI13 | AQ13: =(AE13/O13-1)*100 | AR13: =(AE13/AE2-1)*100 | AS13: =(O13/O2-1)*100 | AT13: =(AN13-X13)*100 | AU13: =(AP13/Z13-1)*100 | AV13: =(AI13-S13)*100
A14: KEN | B14: 2036 | C14: 12 | D14: 2 | E14: =IF(AND(p_dis_year>0,B14=p_dis_year),1,0) | F14: =IF(AND(p_dis_year>0,B14>=p_dis_year),1-p_eps_a*p_rho_a^(B14-p_dis_year),1) | G14: =INDEX(Calib!$N$1:$N$13,$D14)*(1-p_rent_decline*MIN(1,C14/26)) | H14: =IF(C14=0,0,SUMIFS(dl_val,dl_iso,$A14,dl_ind,"pub_cap",dl_year,$B14)/100) | I14: =IF(C14=0,0,SUMIFS(dl_val,dl_iso,$A14,dl_ind,"pub_spend",dl_year,$B14)/100) | J14: =IF(C14=0,0,SUMIFS(dl_val,dl_iso,$A14,dl_ind,"rev",dl_year,$B14)/100) | K14: =(1-p_delta_g)*K13*(1-p_eps_g*$E14)+INDEX(Calib!$E$1:$E$13,$D14)*(INDEX(Calib!$G$1:$G$13,$D14)+0*$H14) | L14: =L13*(1-p_eps_k*$E14)+p_lambda_k*(N14-L13*(1-p_eps_k*$E14)) | M14: =INDEX(Calib!$R$1:$R$13,$D14)*$F14*(K13*(1-p_eps_g*$E14))^INDEX(Calib!$Q$1:$Q$13,$D14)*(L13*(1-p_eps_k*$E14))^p_alpha | N14: =p_alpha*(1-INDEX(Calib!$H$1:$H$13,$D14))*M14/(INDEX(Calib!$K$1:$K$13,$D14)+p_delta) | O14: =M14+$G14 | P14: =0*($H14+$I14) | Q14: =INDEX(Calib!$I$1:$I$13,$D14)+p_sh_grant*P14 | R14: =INDEX(Calib!$H$1:$H$13,$D14)*M14+p_gov_take*$G14+Q14+0*p_pricing*$J14 | S14: =INDEX(Calib!$Y$1:$Y$13,$D14)-INDEX(Calib!$Z$1:$Z$13,$D14)*(V13/O13-INDEX(Calib!$AA$1:$AA$13,$D14)) | T14: =INDEX(Calib!$X$1:$X$13,$D14)+INDEX(Calib!$G$1:$G$13,$D14)+P14+S14-R14 | U14: =p_rk*W13+Y13*(V13-W13) | V14: =V13+U14+T14 | W14: =INDEX(Calib!$U$1:$U$13,$D14)+(W13-INDEX(Calib!$U$1:$U$13,$D14))*(1-p_amort)+p_sh_conc*P14 | X14: =V14/O14 | Y14: =INDEX(Calib!$K$1:$K$13,$D14)+p_eta*MAX(0,X14-INDEX(Calib!$AA$1:$AA$13,$D14)) | Z14: =(1-INDEX(Calib!$H$1:$H$13,$D14))*(1-p_alpha)*M14+S14 | AA14: =(1-p_delta_g)*AA13*(1-p_eps_g*$E14)+INDEX(Calib!$E$1:$E$13,$D14)*(INDEX(Calib!$G$1:$G$13,$D14)+p_programme*$H14) | AB14: =AB13*(1-p_eps_k*$E14)+p_lambda_k*(AD14-AB13*(1-p_eps_k*$E14)) | AC14: =INDEX(Calib!$R$1:$R$13,$D14)*$F14*(AA13*(1-p_eps_g*$E14))^INDEX(Calib!$Q$1:$Q$13,$D14)*(AB13*(1-p_eps_k*$E14))^p_alpha | AD14: =p_alpha*(1-INDEX(Calib!$H$1:$H$13,$D14))*AC14/(INDEX(Calib!$K$1:$K$13,$D14)+p_delta) | AE14: =AC14+$G14 | AF14: =p_programme*($H14+$I14) | AG14: =INDEX(Calib!$I$1:$I$13,$D14)+p_sh_grant*AF14 | AH14: =INDEX(Calib!$H$1:$H$13,$D14)*AC14+p_gov_take*$G14+AG14+p_programme*p_pricing*$J14 | AI14: =INDEX(Calib!$Y$1:$Y$13,$D14)-INDEX(Calib!$Z$1:$Z$13,$D14)*(AL13/AE13-INDEX(Calib!$AA$1:$AA$13,$D14)) | AJ14: =INDEX(Calib!$X$1:$X$13,$D14)+INDEX(Calib!$G$1:$G$13,$D14)+AF14+AI14-AH14 | AK14: =p_rk*AM13+AO13*(AL13-AM13) | AL14: =AL13+AK14+AJ14 | AM14: =INDEX(Calib!$U$1:$U$13,$D14)+(AM13-INDEX(Calib!$U$1:$U$13,$D14))*(1-p_amort)+p_sh_conc*AF14 | AN14: =AL14/AE14 | AO14: =INDEX(Calib!$K$1:$K$13,$D14)+p_eta*MAX(0,AN14-INDEX(Calib!$AA$1:$AA$13,$D14)) | AP14: =(1-INDEX(Calib!$H$1:$H$13,$D14))*(1-p_alpha)*AC14+AI14 | AQ14: =(AE14/O14-1)*100 | AR14: =(AE14/AE2-1)*100 | AS14: =(O14/O2-1)*100 | AT14: =(AN14-X14)*100 | AU14: =(AP14/Z14-1)*100 | AV14: =(AI14-S14)*100
A15: KEN | B15: 2037 | C15: 13 | D15: 2 | E15: =IF(AND(p_dis_year>0,B15=p_dis_year),1,0) | F15: =IF(AND(p_dis_year>0,B15>=p_dis_year),1-p_eps_a*p_rho_a^(B15-p_dis_year),1) | G15: =INDEX(Calib!$N$1:$N$13,$D15)*(1-p_rent_decline*MIN(1,C15/26)) | H15: =IF(C15=0,0,SUMIFS(dl_val,dl_iso,$A15,dl_ind,"pub_cap",dl_year,$B15)/100) | I15: =IF(C15=0,0,SUMIFS(dl_val,dl_iso,$A15,dl_ind,"pub_spend",dl_year,$B15)/100) | J15: =IF(C15=0,0,SUMIFS(dl_val,dl_iso,$A15,dl_ind,"rev",dl_year,$B15)/100) | K15: =(1-p_delta_g)*K14*(1-p_eps_g*$E15)+INDEX(Calib!$E$1:$E$13,$D15)*(INDEX(Calib!$G$1:$G$13,$D15)+0*$H15) | L15: =L14*(1-p_eps_k*$E15)+p_lambda_k*(N15-L14*(1-p_eps_k*$E15)) | M15: =INDEX(Calib!$R$1:$R$13,$D15)*$F15*(K14*(1-p_eps_g*$E15))^INDEX(Calib!$Q$1:$Q$13,$D15)*(L14*(1-p_eps_k*$E15))^p_alpha | N15: =p_alpha*(1-INDEX(Calib!$H$1:$H$13,$D15))*M15/(INDEX(Calib!$K$1:$K$13,$D15)+p_delta) | O15: =M15+$G15 | P15: =0*($H15+$I15) | Q15: =INDEX(Calib!$I$1:$I$13,$D15)+p_sh_grant*P15 | R15: =INDEX(Calib!$H$1:$H$13,$D15)*M15+p_gov_take*$G15+Q15+0*p_pricing*$J15 | S15: =INDEX(Calib!$Y$1:$Y$13,$D15)-INDEX(Calib!$Z$1:$Z$13,$D15)*(V14/O14-INDEX(Calib!$AA$1:$AA$13,$D15)) | T15: =INDEX(Calib!$X$1:$X$13,$D15)+INDEX(Calib!$G$1:$G$13,$D15)+P15+S15-R15 | U15: =p_rk*W14+Y14*(V14-W14) | V15: =V14+U15+T15 | W15: =INDEX(Calib!$U$1:$U$13,$D15)+(W14-INDEX(Calib!$U$1:$U$13,$D15))*(1-p_amort)+p_sh_conc*P15 | X15: =V15/O15 | Y15: =INDEX(Calib!$K$1:$K$13,$D15)+p_eta*MAX(0,X15-INDEX(Calib!$AA$1:$AA$13,$D15)) | Z15: =(1-INDEX(Calib!$H$1:$H$13,$D15))*(1-p_alpha)*M15+S15 | AA15: =(1-p_delta_g)*AA14*(1-p_eps_g*$E15)+INDEX(Calib!$E$1:$E$13,$D15)*(INDEX(Calib!$G$1:$G$13,$D15)+p_programme*$H15) | AB15: =AB14*(1-p_eps_k*$E15)+p_lambda_k*(AD15-AB14*(1-p_eps_k*$E15)) | AC15: =INDEX(Calib!$R$1:$R$13,$D15)*$F15*(AA14*(1-p_eps_g*$E15))^INDEX(Calib!$Q$1:$Q$13,$D15)*(AB14*(1-p_eps_k*$E15))^p_alpha | AD15: =p_alpha*(1-INDEX(Calib!$H$1:$H$13,$D15))*AC15/(INDEX(Calib!$K$1:$K$13,$D15)+p_delta) | AE15: =AC15+$G15 | AF15: =p_programme*($H15+$I15) | AG15: =INDEX(Calib!$I$1:$I$13,$D15)+p_sh_grant*AF15 | AH15: =INDEX(Calib!$H$1:$H$13,$D15)*AC15+p_gov_take*$G15+AG15+p_programme*p_pricing*$J15 | AI15: =INDEX(Calib!$Y$1:$Y$13,$D15)-INDEX(Calib!$Z$1:$Z$13,$D15)*(AL14/AE14-INDEX(Calib!$AA$1:$AA$13,$D15)) | AJ15: =INDEX(Calib!$X$1:$X$13,$D15)+INDEX(Calib!$G$1:$G$13,$D15)+AF15+AI15-AH15 | AK15: =p_rk*AM14+AO14*(AL14-AM14) | AL15: =AL14+AK15+AJ15 | AM15: =INDEX(Calib!$U$1:$U$13,$D15)+(AM14-INDEX(Calib!$U$1:$U$13,$D15))*(1-p_amort)+p_sh_conc*AF15 | AN15: =AL15/AE15 | AO15: =INDEX(Calib!$K$1:$K$13,$D15)+p_eta*MAX(0,AN15-INDEX(Calib!$AA$1:$AA$13,$D15)) | AP15: =(1-INDEX(Calib!$H$1:$H$13,$D15))*(1-p_alpha)*AC15+AI15 | AQ15: =(AE15/O15-1)*100 | AR15: =(AE15/AE2-1)*100 | AS15: =(O15/O2-1)*100 | AT15: =(AN15-X15)*100 | AU15: =(AP15/Z15-1)*100 | AV15: =(AI15-S15)*100
A16: KEN | B16: 2038 | C16: 14 | D16: 2 | E16: =IF(AND(p_dis_year>0,B16=p_dis_year),1,0) | F16: =IF(AND(p_dis_year>0,B16>=p_dis_year),1-p_eps_a*p_rho_a^(B16-p_dis_year),1) | G16: =INDEX(Calib!$N$1:$N$13,$D16)*(1-p_rent_decline*MIN(1,C16/26)) | H16: =IF(C16=0,0,SUMIFS(dl_val,dl_iso,$A16,dl_ind,"pub_cap",dl_year,$B16)/100) | I16: =IF(C16=0,0,SUMIFS(dl_val,dl_iso,$A16,dl_ind,"pub_spend",dl_year,$B16)/100) | J16: =IF(C16=0,0,SUMIFS(dl_val,dl_iso,$A16,dl_ind,"rev",dl_year,$B16)/100) | K16: =(1-p_delta_g)*K15*(1-p_eps_g*$E16)+INDEX(Calib!$E$1:$E$13,$D16)*(INDEX(Calib!$G$1:$G$13,$D16)+0*$H16) | L16: =L15*(1-p_eps_k*$E16)+p_lambda_k*(N16-L15*(1-p_eps_k*$E16)) | M16: =INDEX(Calib!$R$1:$R$13,$D16)*$F16*(K15*(1-p_eps_g*$E16))^INDEX(Calib!$Q$1:$Q$13,$D16)*(L15*(1-p_eps_k*$E16))^p_alpha | N16: =p_alpha*(1-INDEX(Calib!$H$1:$H$13,$D16))*M16/(INDEX(Calib!$K$1:$K$13,$D16)+p_delta) | O16: =M16+$G16 | P16: =0*($H16+$I16) | Q16: =INDEX(Calib!$I$1:$I$13,$D16)+p_sh_grant*P16 | R16: =INDEX(Calib!$H$1:$H$13,$D16)*M16+p_gov_take*$G16+Q16+0*p_pricing*$J16 | S16: =INDEX(Calib!$Y$1:$Y$13,$D16)-INDEX(Calib!$Z$1:$Z$13,$D16)*(V15/O15-INDEX(Calib!$AA$1:$AA$13,$D16)) | T16: =INDEX(Calib!$X$1:$X$13,$D16)+INDEX(Calib!$G$1:$G$13,$D16)+P16+S16-R16 | U16: =p_rk*W15+Y15*(V15-W15) | V16: =V15+U16+T16 | W16: =INDEX(Calib!$U$1:$U$13,$D16)+(W15-INDEX(Calib!$U$1:$U$13,$D16))*(1-p_amort)+p_sh_conc*P16 | X16: =V16/O16 | Y16: =INDEX(Calib!$K$1:$K$13,$D16)+p_eta*MAX(0,X16-INDEX(Calib!$AA$1:$AA$13,$D16)) | Z16: =(1-INDEX(Calib!$H$1:$H$13,$D16))*(1-p_alpha)*M16+S16 | AA16: =(1-p_delta_g)*AA15*(1-p_eps_g*$E16)+INDEX(Calib!$E$1:$E$13,$D16)*(INDEX(Calib!$G$1:$G$13,$D16)+p_programme*$H16) | AB16: =AB15*(1-p_eps_k*$E16)+p_lambda_k*(AD16-AB15*(1-p_eps_k*$E16)) | AC16: =INDEX(Calib!$R$1:$R$13,$D16)*$F16*(AA15*(1-p_eps_g*$E16))^INDEX(Calib!$Q$1:$Q$13,$D16)*(AB15*(1-p_eps_k*$E16))^p_alpha | AD16: =p_alpha*(1-INDEX(Calib!$H$1:$H$13,$D16))*AC16/(INDEX(Calib!$K$1:$K$13,$D16)+p_delta) | AE16: =AC16+$G16 | AF16: =p_programme*($H16+$I16) | AG16: =INDEX(Calib!$I$1:$I$13,$D16)+p_sh_grant*AF16 | AH16: =INDEX(Calib!$H$1:$H$13,$D16)*AC16+p_gov_take*$G16+AG16+p_programme*p_pricing*$J16 | AI16: =INDEX(Calib!$Y$1:$Y$13,$D16)-INDEX(Calib!$Z$1:$Z$13,$D16)*(AL15/AE15-INDEX(Calib!$AA$1:$AA$13,$D16)) | AJ16: =INDEX(Calib!$X$1:$X$13,$D16)+INDEX(Calib!$G$1:$G$13,$D16)+AF16+AI16-AH16 | AK16: =p_rk*AM15+AO15*(AL15-AM15) | AL16: =AL15+AK16+AJ16 | AM16: =INDEX(Calib!$U$1:$U$13,$D16)+(AM15-INDEX(Calib!$U$1:$U$13,$D16))*(1-p_amort)+p_sh_conc*AF16 | AN16: =AL16/AE16 | AO16: =INDEX(Calib!$K$1:$K$13,$D16)+p_eta*MAX(0,AN16-INDEX(Calib!$AA$1:$AA$13,$D16)) | AP16: =(1-INDEX(Calib!$H$1:$H$13,$D16))*(1-p_alpha)*AC16+AI16 | AQ16: =(AE16/O16-1)*100 | AR16: =(AE16/AE2-1)*100 | AS16: =(O16/O2-1)*100 | AT16: =(AN16-X16)*100 | AU16: =(AP16/Z16-1)*100 | AV16: =(AI16-S16)*100
A17: KEN | B17: 2039 | C17: 15 | D17: 2 | E17: =IF(AND(p_dis_year>0,B17=p_dis_year),1,0) | F17: =IF(AND(p_dis_year>0,B17>=p_dis_year),1-p_eps_a*p_rho_a^(B17-p_dis_year),1) | G17: =INDEX(Calib!$N$1:$N$13,$D17)*(1-p_rent_decline*MIN(1,C17/26)) | H17: =IF(C17=0,0,SUMIFS(dl_val,dl_iso,$A17,dl_ind,"pub_cap",dl_year,$B17)/100) | I17: =IF(C17=0,0,SUMIFS(dl_val,dl_iso,$A17,dl_ind,"pub_spend",dl_year,$B17)/100) | J17: =IF(C17=0,0,SUMIFS(dl_val,dl_iso,$A17,dl_ind,"rev",dl_year,$B17)/100) | K17: =(1-p_delta_g)*K16*(1-p_eps_g*$E17)+INDEX(Calib!$E$1:$E$13,$D17)*(INDEX(Calib!$G$1:$G$13,$D17)+0*$H17) | L17: =L16*(1-p_eps_k*$E17)+p_lambda_k*(N17-L16*(1-p_eps_k*$E17)) | M17: =INDEX(Calib!$R$1:$R$13,$D17)*$F17*(K16*(1-p_eps_g*$E17))^INDEX(Calib!$Q$1:$Q$13,$D17)*(L16*(1-p_eps_k*$E17))^p_alpha | N17: =p_alpha*(1-INDEX(Calib!$H$1:$H$13,$D17))*M17/(INDEX(Calib!$K$1:$K$13,$D17)+p_delta) | O17: =M17+$G17 | P17: =0*($H17+$I17) | Q17: =INDEX(Calib!$I$1:$I$13,$D17)+p_sh_grant*P17 | R17: =INDEX(Calib!$H$1:$H$13,$D17)*M17+p_gov_take*$G17+Q17+0*p_pricing*$J17 | S17: =INDEX(Calib!$Y$1:$Y$13,$D17)-INDEX(Calib!$Z$1:$Z$13,$D17)*(V16/O16-INDEX(Calib!$AA$1:$AA$13,$D17)) | T17: =INDEX(Calib!$X$1:$X$13,$D17)+INDEX(Calib!$G$1:$G$13,$D17)+P17+S17-R17 | U17: =p_rk*W16+Y16*(V16-W16) | V17: =V16+U17+T17 | W17: =INDEX(Calib!$U$1:$U$13,$D17)+(W16-INDEX(Calib!$U$1:$U$13,$D17))*(1-p_amort)+p_sh_conc*P17 | X17: =V17/O17 | Y17: =INDEX(Calib!$K$1:$K$13,$D17)+p_eta*MAX(0,X17-INDEX(Calib!$AA$1:$AA$13,$D17)) | Z17: =(1-INDEX(Calib!$H$1:$H$13,$D17))*(1-p_alpha)*M17+S17 | AA17: =(1-p_delta_g)*AA16*(1-p_eps_g*$E17)+INDEX(Calib!$E$1:$E$13,$D17)*(INDEX(Calib!$G$1:$G$13,$D17)+p_programme*$H17) | AB17: =AB16*(1-p_eps_k*$E17)+p_lambda_k*(AD17-AB16*(1-p_eps_k*$E17)) | AC17: =INDEX(Calib!$R$1:$R$13,$D17)*$F17*(AA16*(1-p_eps_g*$E17))^INDEX(Calib!$Q$1:$Q$13,$D17)*(AB16*(1-p_eps_k*$E17))^p_alpha | AD17: =p_alpha*(1-INDEX(Calib!$H$1:$H$13,$D17))*AC17/(INDEX(Calib!$K$1:$K$13,$D17)+p_delta) | AE17: =AC17+$G17 | AF17: =p_programme*($H17+$I17) | AG17: =INDEX(Calib!$I$1:$I$13,$D17)+p_sh_grant*AF17 | AH17: =INDEX(Calib!$H$1:$H$13,$D17)*AC17+p_gov_take*$G17+AG17+p_programme*p_pricing*$J17 | AI17: =INDEX(Calib!$Y$1:$Y$13,$D17)-INDEX(Calib!$Z$1:$Z$13,$D17)*(AL16/AE16-INDEX(Calib!$AA$1:$AA$13,$D17)) | AJ17: =INDEX(Calib!$X$1:$X$13,$D17)+INDEX(Calib!$G$1:$G$13,$D17)+AF17+AI17-AH17 | AK17: =p_rk*AM16+AO16*(AL16-AM16) | AL17: =AL16+AK17+AJ17 | AM17: =INDEX(Calib!$U$1:$U$13,$D17)+(AM16-INDEX(Calib!$U$1:$U$13,$D17))*(1-p_amort)+p_sh_conc*AF17 | AN17: =AL17/AE17 | AO17: =INDEX(Calib!$K$1:$K$13,$D17)+p_eta*MAX(0,AN17-INDEX(Calib!$AA$1:$AA$13,$D17)) | AP17: =(1-INDEX(Calib!$H$1:$H$13,$D17))*(1-p_alpha)*AC17+AI17 | AQ17: =(AE17/O17-1)*100 | AR17: =(AE17/AE2-1)*100 | AS17: =(O17/O2-1)*100 | AT17: =(AN17-X17)*100 | AU17: =(AP17/Z17-1)*100 | AV17: =(AI17-S17)*100
A18: KEN | B18: 2040 | C18: 16 | D18: 2 | E18: =IF(AND(p_dis_year>0,B18=p_dis_year),1,0) | F18: =IF(AND(p_dis_year>0,B18>=p_dis_year),1-p_eps_a*p_rho_a^(B18-p_dis_year),1) | G18: =INDEX(Calib!$N$1:$N$13,$D18)*(1-p_rent_decline*MIN(1,C18/26)) | H18: =IF(C18=0,0,SUMIFS(dl_val,dl_iso,$A18,dl_ind,"pub_cap",dl_year,$B18)/100) | I18: =IF(C18=0,0,SUMIFS(dl_val,dl_iso,$A18,dl_ind,"pub_spend",dl_year,$B18)/100) | J18: =IF(C18=0,0,SUMIFS(dl_val,dl_iso,$A18,dl_ind,"rev",dl_year,$B18)/100) | K18: =(1-p_delta_g)*K17*(1-p_eps_g*$E18)+INDEX(Calib!$E$1:$E$13,$D18)*(INDEX(Calib!$G$1:$G$13,$D18)+0*$H18) | L18: =L17*(1-p_eps_k*$E18)+p_lambda_k*(N18-L17*(1-p_eps_k*$E18)) | M18: =INDEX(Calib!$R$1:$R$13,$D18)*$F18*(K17*(1-p_eps_g*$E18))^INDEX(Calib!$Q$1:$Q$13,$D18)*(L17*(1-p_eps_k*$E18))^p_alpha | N18: =p_alpha*(1-INDEX(Calib!$H$1:$H$13,$D18))*M18/(INDEX(Calib!$K$1:$K$13,$D18)+p_delta) | O18: =M18+$G18 | P18: =0*($H18+$I18) | Q18: =INDEX(Calib!$I$1:$I$13,$D18)+p_sh_grant*P18 | R18: =INDEX(Calib!$H$1:$H$13,$D18)*M18+p_gov_take*$G18+Q18+0*p_pricing*$J18 | S18: =INDEX(Calib!$Y$1:$Y$13,$D18)-INDEX(Calib!$Z$1:$Z$13,$D18)*(V17/O17-INDEX(Calib!$AA$1:$AA$13,$D18)) | T18: =INDEX(Calib!$X$1:$X$13,$D18)+INDEX(Calib!$G$1:$G$13,$D18)+P18+S18-R18 | U18: =p_rk*W17+Y17*(V17-W17) | V18: =V17+U18+T18 | W18: =INDEX(Calib!$U$1:$U$13,$D18)+(W17-INDEX(Calib!$U$1:$U$13,$D18))*(1-p_amort)+p_sh_conc*P18 | X18: =V18/O18 | Y18: =INDEX(Calib!$K$1:$K$13,$D18)+p_eta*MAX(0,X18-INDEX(Calib!$AA$1:$AA$13,$D18)) | Z18: =(1-INDEX(Calib!$H$1:$H$13,$D18))*(1-p_alpha)*M18+S18 | AA18: =(1-p_delta_g)*AA17*(1-p_eps_g*$E18)+INDEX(Calib!$E$1:$E$13,$D18)*(INDEX(Calib!$G$1:$G$13,$D18)+p_programme*$H18) | AB18: =AB17*(1-p_eps_k*$E18)+p_lambda_k*(AD18-AB17*(1-p_eps_k*$E18)) | AC18: =INDEX(Calib!$R$1:$R$13,$D18)*$F18*(AA17*(1-p_eps_g*$E18))^INDEX(Calib!$Q$1:$Q$13,$D18)*(AB17*(1-p_eps_k*$E18))^p_alpha | AD18: =p_alpha*(1-INDEX(Calib!$H$1:$H$13,$D18))*AC18/(INDEX(Calib!$K$1:$K$13,$D18)+p_delta) | AE18: =AC18+$G18 | AF18: =p_programme*($H18+$I18) | AG18: =INDEX(Calib!$I$1:$I$13,$D18)+p_sh_grant*AF18 | AH18: =INDEX(Calib!$H$1:$H$13,$D18)*AC18+p_gov_take*$G18+AG18+p_programme*p_pricing*$J18 | AI18: =INDEX(Calib!$Y$1:$Y$13,$D18)-INDEX(Calib!$Z$1:$Z$13,$D18)*(AL17/AE17-INDEX(Calib!$AA$1:$AA$13,$D18)) | AJ18: =INDEX(Calib!$X$1:$X$13,$D18)+INDEX(Calib!$G$1:$G$13,$D18)+AF18+AI18-AH18 | AK18: =p_rk*AM17+AO17*(AL17-AM17) | AL18: =AL17+AK18+AJ18 | AM18: =INDEX(Calib!$U$1:$U$13,$D18)+(AM17-INDEX(Calib!$U$1:$U$13,$D18))*(1-p_amort)+p_sh_conc*AF18 | AN18: =AL18/AE18 | AO18: =INDEX(Calib!$K$1:$K$13,$D18)+p_eta*MAX(0,AN18-INDEX(Calib!$AA$1:$AA$13,$D18)) | AP18: =(1-INDEX(Calib!$H$1:$H$13,$D18))*(1-p_alpha)*AC18+AI18 | AQ18: =(AE18/O18-1)*100 | AR18: =(AE18/AE2-1)*100 | AS18: =(O18/O2-1)*100 | AT18: =(AN18-X18)*100 | AU18: =(AP18/Z18-1)*100 | AV18: =(AI18-S18)*100
A19: KEN | B19: 2041 | C19: 17 | D19: 2 | E19: =IF(AND(p_dis_year>0,B19=p_dis_year),1,0) | F19: =IF(AND(p_dis_year>0,B19>=p_dis_year),1-p_eps_a*p_rho_a^(B19-p_dis_year),1) | G19: =INDEX(Calib!$N$1:$N$13,$D19)*(1-p_rent_decline*MIN(1,C19/26)) | H19: =IF(C19=0,0,SUMIFS(dl_val,dl_iso,$A19,dl_ind,"pub_cap",dl_year,$B19)/100) | I19: =IF(C19=0,0,SUMIFS(dl_val,dl_iso,$A19,dl_ind,"pub_spend",dl_year,$B19)/100) | J19: =IF(C19=0,0,SUMIFS(dl_val,dl_iso,$A19,dl_ind,"rev",dl_year,$B19)/100) | K19: =(1-p_delta_g)*K18*(1-p_eps_g*$E19)+INDEX(Calib!$E$1:$E$13,$D19)*(INDEX(Calib!$G$1:$G$13,$D19)+0*$H19) | L19: =L18*(1-p_eps_k*$E19)+p_lambda_k*(N19-L18*(1-p_eps_k*$E19)) | M19: =INDEX(Calib!$R$1:$R$13,$D19)*$F19*(K18*(1-p_eps_g*$E19))^INDEX(Calib!$Q$1:$Q$13,$D19)*(L18*(1-p_eps_k*$E19))^p_alpha | N19: =p_alpha*(1-INDEX(Calib!$H$1:$H$13,$D19))*M19/(INDEX(Calib!$K$1:$K$13,$D19)+p_delta) | O19: =M19+$G19 | P19: =0*($H19+$I19) | Q19: =INDEX(Calib!$I$1:$I$13,$D19)+p_sh_grant*P19 | R19: =INDEX(Calib!$H$1:$H$13,$D19)*M19+p_gov_take*$G19+Q19+0*p_pricing*$J19 | S19: =INDEX(Calib!$Y$1:$Y$13,$D19)-INDEX(Calib!$Z$1:$Z$13,$D19)*(V18/O18-INDEX(Calib!$AA$1:$AA$13,$D19)) | T19: =INDEX(Calib!$X$1:$X$13,$D19)+INDEX(Calib!$G$1:$G$13,$D19)+P19+S19-R19 | U19: =p_rk*W18+Y18*(V18-W18) | V19: =V18+U19+T19 | W19: =INDEX(Calib!$U$1:$U$13,$D19)+(W18-INDEX(Calib!$U$1:$U$13,$D19))*(1-p_amort)+p_sh_conc*P19 | X19: =V19/O19 | Y19: =INDEX(Calib!$K$1:$K$13,$D19)+p_eta*MAX(0,X19-INDEX(Calib!$AA$1:$AA$13,$D19)) | Z19: =(1-INDEX(Calib!$H$1:$H$13,$D19))*(1-p_alpha)*M19+S19 | AA19: =(1-p_delta_g)*AA18*(1-p_eps_g*$E19)+INDEX(Calib!$E$1:$E$13,$D19)*(INDEX(Calib!$G$1:$G$13,$D19)+p_programme*$H19) | AB19: =AB18*(1-p_eps_k*$E19)+p_lambda_k*(AD19-AB18*(1-p_eps_k*$E19)) | AC19: =INDEX(Calib!$R$1:$R$13,$D19)*$F19*(AA18*(1-p_eps_g*$E19))^INDEX(Calib!$Q$1:$Q$13,$D19)*(AB18*(1-p_eps_k*$E19))^p_alpha | AD19: =p_alpha*(1-INDEX(Calib!$H$1:$H$13,$D19))*AC19/(INDEX(Calib!$K$1:$K$13,$D19)+p_delta) | AE19: =AC19+$G19 | AF19: =p_programme*($H19+$I19) | AG19: =INDEX(Calib!$I$1:$I$13,$D19)+p_sh_grant*AF19 | AH19: =INDEX(Calib!$H$1:$H$13,$D19)*AC19+p_gov_take*$G19+AG19+p_programme*p_pricing*$J19 | AI19: =INDEX(Calib!$Y$1:$Y$13,$D19)-INDEX(Calib!$Z$1:$Z$13,$D19)*(AL18/AE18-INDEX(Calib!$AA$1:$AA$13,$D19)) | AJ19: =INDEX(Calib!$X$1:$X$13,$D19)+INDEX(Calib!$G$1:$G$13,$D19)+AF19+AI19-AH19 | AK19: =p_rk*AM18+AO18*(AL18-AM18) | AL19: =AL18+AK19+AJ19 | AM19: =INDEX(Calib!$U$1:$U$13,$D19)+(AM18-INDEX(Calib!$U$1:$U$13,$D19))*(1-p_amort)+p_sh_conc*AF19 | AN19: =AL19/AE19 | AO19: =INDEX(Calib!$K$1:$K$13,$D19)+p_eta*MAX(0,AN19-INDEX(Calib!$AA$1:$AA$13,$D19)) | AP19: =(1-INDEX(Calib!$H$1:$H$13,$D19))*(1-p_alpha)*AC19+AI19 | AQ19: =(AE19/O19-1)*100 | AR19: =(AE19/AE2-1)*100 | AS19: =(O19/O2-1)*100 | AT19: =(AN19-X19)*100 | AU19: =(AP19/Z19-1)*100 | AV19: =(AI19-S19)*100
A20: KEN | B20: 2042 | C20: 18 | D20: 2 | E20: =IF(AND(p_dis_year>0,B20=p_dis_year),1,0) | F20: =IF(AND(p_dis_year>0,B20>=p_dis_year),1-p_eps_a*p_rho_a^(B20-p_dis_year),1) | G20: =INDEX(Calib!$N$1:$N$13,$D20)*(1-p_rent_decline*MIN(1,C20/26)) | H20: =IF(C20=0,0,SUMIFS(dl_val,dl_iso,$A20,dl_ind,"pub_cap",dl_year,$B20)/100) | I20: =IF(C20=0,0,SUMIFS(dl_val,dl_iso,$A20,dl_ind,"pub_spend",dl_year,$B20)/100) | J20: =IF(C20=0,0,SUMIFS(dl_val,dl_iso,$A20,dl_ind,"rev",dl_year,$B20)/100) | K20: =(1-p_delta_g)*K19*(1-p_eps_g*$E20)+INDEX(Calib!$E$1:$E$13,$D20)*(INDEX(Calib!$G$1:$G$13,$D20)+0*$H20) | L20: =L19*(1-p_eps_k*$E20)+p_lambda_k*(N20-L19*(1-p_eps_k*$E20)) | M20: =INDEX(Calib!$R$1:$R$13,$D20)*$F20*(K19*(1-p_eps_g*$E20))^INDEX(Calib!$Q$1:$Q$13,$D20)*(L19*(1-p_eps_k*$E20))^p_alpha | N20: =p_alpha*(1-INDEX(Calib!$H$1:$H$13,$D20))*M20/(INDEX(Calib!$K$1:$K$13,$D20)+p_delta) | O20: =M20+$G20 | P20: =0*($H20+$I20) | Q20: =INDEX(Calib!$I$1:$I$13,$D20)+p_sh_grant*P20 | R20: =INDEX(Calib!$H$1:$H$13,$D20)*M20+p_gov_take*$G20+Q20+0*p_pricing*$J20 | S20: =INDEX(Calib!$Y$1:$Y$13,$D20)-INDEX(Calib!$Z$1:$Z$13,$D20)*(V19/O19-INDEX(Calib!$AA$1:$AA$13,$D20)) | T20: =INDEX(Calib!$X$1:$X$13,$D20)+INDEX(Calib!$G$1:$G$13,$D20)+P20+S20-R20 | U20: =p_rk*W19+Y19*(V19-W19) | V20: =V19+U20+T20 | W20: =INDEX(Calib!$U$1:$U$13,$D20)+(W19-INDEX(Calib!$U$1:$U$13,$D20))*(1-p_amort)+p_sh_conc*P20 | X20: =V20/O20 | Y20: =INDEX(Calib!$K$1:$K$13,$D20)+p_eta*MAX(0,X20-INDEX(Calib!$AA$1:$AA$13,$D20)) | Z20: =(1-INDEX(Calib!$H$1:$H$13,$D20))*(1-p_alpha)*M20+S20 | AA20: =(1-p_delta_g)*AA19*(1-p_eps_g*$E20)+INDEX(Calib!$E$1:$E$13,$D20)*(INDEX(Calib!$G$1:$G$13,$D20)+p_programme*$H20) | AB20: =AB19*(1-p_eps_k*$E20)+p_lambda_k*(AD20-AB19*(1-p_eps_k*$E20)) | AC20: =INDEX(Calib!$R$1:$R$13,$D20)*$F20*(AA19*(1-p_eps_g*$E20))^INDEX(Calib!$Q$1:$Q$13,$D20)*(AB19*(1-p_eps_k*$E20))^p_alpha | AD20: =p_alpha*(1-INDEX(Calib!$H$1:$H$13,$D20))*AC20/(INDEX(Calib!$K$1:$K$13,$D20)+p_delta) | AE20: =AC20+$G20 | AF20: =p_programme*($H20+$I20) | AG20: =INDEX(Calib!$I$1:$I$13,$D20)+p_sh_grant*AF20 | AH20: =INDEX(Calib!$H$1:$H$13,$D20)*AC20+p_gov_take*$G20+AG20+p_programme*p_pricing*$J20 | AI20: =INDEX(Calib!$Y$1:$Y$13,$D20)-INDEX(Calib!$Z$1:$Z$13,$D20)*(AL19/AE19-INDEX(Calib!$AA$1:$AA$13,$D20)) | AJ20: =INDEX(Calib!$X$1:$X$13,$D20)+INDEX(Calib!$G$1:$G$13,$D20)+AF20+AI20-AH20 | AK20: =p_rk*AM19+AO19*(AL19-AM19) | AL20: =AL19+AK20+AJ20 | AM20: =INDEX(Calib!$U$1:$U$13,$D20)+(AM19-INDEX(Calib!$U$1:$U$13,$D20))*(1-p_amort)+p_sh_conc*AF20 | AN20: =AL20/AE20 | AO20: =INDEX(Calib!$K$1:$K$13,$D20)+p_eta*MAX(0,AN20-INDEX(Calib!$AA$1:$AA$13,$D20)) | AP20: =(1-INDEX(Calib!$H$1:$H$13,$D20))*(1-p_alpha)*AC20+AI20 | AQ20: =(AE20/O20-1)*100 | AR20: =(AE20/AE2-1)*100 | AS20: =(O20/O2-1)*100 | AT20: =(AN20-X20)*100 | AU20: =(AP20/Z20-1)*100 | AV20: =(AI20-S20)*100
A21: KEN | B21: 2043 | C21: 19 | D21: 2 | E21: =IF(AND(p_dis_year>0,B21=p_dis_year),1,0) | F21: =IF(AND(p_dis_year>0,B21>=p_dis_year),1-p_eps_a*p_rho_a^(B21-p_dis_year),1) | G21: =INDEX(Calib!$N$1:$N$13,$D21)*(1-p_rent_decline*MIN(1,C21/26)) | H21: =IF(C21=0,0,SUMIFS(dl_val,dl_iso,$A21,dl_ind,"pub_cap",dl_year,$B21)/100) | I21: =IF(C21=0,0,SUMIFS(dl_val,dl_iso,$A21,dl_ind,"pub_spend",dl_year,$B21)/100) | J21: =IF(C21=0,0,SUMIFS(dl_val,dl_iso,$A21,dl_ind,"rev",dl_year,$B21)/100) | K21: =(1-p_delta_g)*K20*(1-p_eps_g*$E21)+INDEX(Calib!$E$1:$E$13,$D21)*(INDEX(Calib!$G$1:$G$13,$D21)+0*$H21) | L21: =L20*(1-p_eps_k*$E21)+p_lambda_k*(N21-L20*(1-p_eps_k*$E21)) | M21: =INDEX(Calib!$R$1:$R$13,$D21)*$F21*(K20*(1-p_eps_g*$E21))^INDEX(Calib!$Q$1:$Q$13,$D21)*(L20*(1-p_eps_k*$E21))^p_alpha | N21: =p_alpha*(1-INDEX(Calib!$H$1:$H$13,$D21))*M21/(INDEX(Calib!$K$1:$K$13,$D21)+p_delta) | O21: =M21+$G21 | P21: =0*($H21+$I21) | Q21: =INDEX(Calib!$I$1:$I$13,$D21)+p_sh_grant*P21 | R21: =INDEX(Calib!$H$1:$H$13,$D21)*M21+p_gov_take*$G21+Q21+0*p_pricing*$J21 | S21: =INDEX(Calib!$Y$1:$Y$13,$D21)-INDEX(Calib!$Z$1:$Z$13,$D21)*(V20/O20-INDEX(Calib!$AA$1:$AA$13,$D21)) | T21: =INDEX(Calib!$X$1:$X$13,$D21)+INDEX(Calib!$G$1:$G$13,$D21)+P21+S21-R21 | U21: =p_rk*W20+Y20*(V20-W20) | V21: =V20+U21+T21 | W21: =INDEX(Calib!$U$1:$U$13,$D21)+(W20-INDEX(Calib!$U$1:$U$13,$D21))*(1-p_amort)+p_sh_conc*P21 | X21: =V21/O21 | Y21: =INDEX(Calib!$K$1:$K$13,$D21)+p_eta*MAX(0,X21-INDEX(Calib!$AA$1:$AA$13,$D21)) | Z21: =(1-INDEX(Calib!$H$1:$H$13,$D21))*(1-p_alpha)*M21+S21 | AA21: =(1-p_delta_g)*AA20*(1-p_eps_g*$E21)+INDEX(Calib!$E$1:$E$13,$D21)*(INDEX(Calib!$G$1:$G$13,$D21)+p_programme*$H21) | AB21: =AB20*(1-p_eps_k*$E21)+p_lambda_k*(AD21-AB20*(1-p_eps_k*$E21)) | AC21: =INDEX(Calib!$R$1:$R$13,$D21)*$F21*(AA20*(1-p_eps_g*$E21))^INDEX(Calib!$Q$1:$Q$13,$D21)*(AB20*(1-p_eps_k*$E21))^p_alpha | AD21: =p_alpha*(1-INDEX(Calib!$H$1:$H$13,$D21))*AC21/(INDEX(Calib!$K$1:$K$13,$D21)+p_delta) | AE21: =AC21+$G21 | AF21: =p_programme*($H21+$I21) | AG21: =INDEX(Calib!$I$1:$I$13,$D21)+p_sh_grant*AF21 | AH21: =INDEX(Calib!$H$1:$H$13,$D21)*AC21+p_gov_take*$G21+AG21+p_programme*p_pricing*$J21 | AI21: =INDEX(Calib!$Y$1:$Y$13,$D21)-INDEX(Calib!$Z$1:$Z$13,$D21)*(AL20/AE20-INDEX(Calib!$AA$1:$AA$13,$D21)) | AJ21: =INDEX(Calib!$X$1:$X$13,$D21)+INDEX(Calib!$G$1:$G$13,$D21)+AF21+AI21-AH21 | AK21: =p_rk*AM20+AO20*(AL20-AM20) | AL21: =AL20+AK21+AJ21 | AM21: =INDEX(Calib!$U$1:$U$13,$D21)+(AM20-INDEX(Calib!$U$1:$U$13,$D21))*(1-p_amort)+p_sh_conc*AF21 | AN21: =AL21/AE21 | AO21: =INDEX(Calib!$K$1:$K$13,$D21)+p_eta*MAX(0,AN21-INDEX(Calib!$AA$1:$AA$13,$D21)) | AP21: =(1-INDEX(Calib!$H$1:$H$13,$D21))*(1-p_alpha)*AC21+AI21 | AQ21: =(AE21/O21-1)*100 | AR21: =(AE21/AE2-1)*100 | AS21: =(O21/O2-1)*100 | AT21: =(AN21-X21)*100 | AU21: =(AP21/Z21-1)*100 | AV21: =(AI21-S21)*100
A22: KEN | B22: 2044 | C22: 20 | D22: 2 | E22: =IF(AND(p_dis_year>0,B22=p_dis_year),1,0) | F22: =IF(AND(p_dis_year>0,B22>=p_dis_year),1-p_eps_a*p_rho_a^(B22-p_dis_year),1) | G22: =INDEX(Calib!$N$1:$N$13,$D22)*(1-p_rent_decline*MIN(1,C22/26)) | H22: =IF(C22=0,0,SUMIFS(dl_val,dl_iso,$A22,dl_ind,"pub_cap",dl_year,$B22)/100) | I22: =IF(C22=0,0,SUMIFS(dl_val,dl_iso,$A22,dl_ind,"pub_spend",dl_year,$B22)/100) | J22: =IF(C22=0,0,SUMIFS(dl_val,dl_iso,$A22,dl_ind,"rev",dl_year,$B22)/100) | K22: =(1-p_delta_g)*K21*(1-p_eps_g*$E22)+INDEX(Calib!$E$1:$E$13,$D22)*(INDEX(Calib!$G$1:$G$13,$D22)+0*$H22) | L22: =L21*(1-p_eps_k*$E22)+p_lambda_k*(N22-L21*(1-p_eps_k*$E22)) | M22: =INDEX(Calib!$R$1:$R$13,$D22)*$F22*(K21*(1-p_eps_g*$E22))^INDEX(Calib!$Q$1:$Q$13,$D22)*(L21*(1-p_eps_k*$E22))^p_alpha | N22: =p_alpha*(1-INDEX(Calib!$H$1:$H$13,$D22))*M22/(INDEX(Calib!$K$1:$K$13,$D22)+p_delta) | O22: =M22+$G22 | P22: =0*($H22+$I22) | Q22: =INDEX(Calib!$I$1:$I$13,$D22)+p_sh_grant*P22 | R22: =INDEX(Calib!$H$1:$H$13,$D22)*M22+p_gov_take*$G22+Q22+0*p_pricing*$J22 | S22: =INDEX(Calib!$Y$1:$Y$13,$D22)-INDEX(Calib!$Z$1:$Z$13,$D22)*(V21/O21-INDEX(Calib!$AA$1:$AA$13,$D22)) | T22: =INDEX(Calib!$X$1:$X$13,$D22)+INDEX(Calib!$G$1:$G$13,$D22)+P22+S22-R22 | U22: =p_rk*W21+Y21*(V21-W21) | V22: =V21+U22+T22 | W22: =INDEX(Calib!$U$1:$U$13,$D22)+(W21-INDEX(Calib!$U$1:$U$13,$D22))*(1-p_amort)+p_sh_conc*P22 | X22: =V22/O22 | Y22: =INDEX(Calib!$K$1:$K$13,$D22)+p_eta*MAX(0,X22-INDEX(Calib!$AA$1:$AA$13,$D22)) | Z22: =(1-INDEX(Calib!$H$1:$H$13,$D22))*(1-p_alpha)*M22+S22 | AA22: =(1-p_delta_g)*AA21*(1-p_eps_g*$E22)+INDEX(Calib!$E$1:$E$13,$D22)*(INDEX(Calib!$G$1:$G$13,$D22)+p_programme*$H22) | AB22: =AB21*(1-p_eps_k*$E22)+p_lambda_k*(AD22-AB21*(1-p_eps_k*$E22)) | AC22: =INDEX(Calib!$R$1:$R$13,$D22)*$F22*(AA21*(1-p_eps_g*$E22))^INDEX(Calib!$Q$1:$Q$13,$D22)*(AB21*(1-p_eps_k*$E22))^p_alpha | AD22: =p_alpha*(1-INDEX(Calib!$H$1:$H$13,$D22))*AC22/(INDEX(Calib!$K$1:$K$13,$D22)+p_delta) | AE22: =AC22+$G22 | AF22: =p_programme*($H22+$I22) | AG22: =INDEX(Calib!$I$1:$I$13,$D22)+p_sh_grant*AF22 | AH22: =INDEX(Calib!$H$1:$H$13,$D22)*AC22+p_gov_take*$G22+AG22+p_programme*p_pricing*$J22 | AI22: =INDEX(Calib!$Y$1:$Y$13,$D22)-INDEX(Calib!$Z$1:$Z$13,$D22)*(AL21/AE21-INDEX(Calib!$AA$1:$AA$13,$D22)) | AJ22: =INDEX(Calib!$X$1:$X$13,$D22)+INDEX(Calib!$G$1:$G$13,$D22)+AF22+AI22-AH22 | AK22: =p_rk*AM21+AO21*(AL21-AM21) | AL22: =AL21+AK22+AJ22 | AM22: =INDEX(Calib!$U$1:$U$13,$D22)+(AM21-INDEX(Calib!$U$1:$U$13,$D22))*(1-p_amort)+p_sh_conc*AF22 | AN22: =AL22/AE22 | AO22: =INDEX(Calib!$K$1:$K$13,$D22)+p_eta*MAX(0,AN22-INDEX(Calib!$AA$1:$AA$13,$D22)) | AP22: =(1-INDEX(Calib!$H$1:$H$13,$D22))*(1-p_alpha)*AC22+AI22 | AQ22: =(AE22/O22-1)*100 | AR22: =(AE22/AE2-1)*100 | AS22: =(O22/O2-1)*100 | AT22: =(AN22-X22)*100 | AU22: =(AP22/Z22-1)*100 | AV22: =(AI22-S22)*100
A23: KEN | B23: 2045 | C23: 21 | D23: 2 | E23: =IF(AND(p_dis_year>0,B23=p_dis_year),1,0) | F23: =IF(AND(p_dis_year>0,B23>=p_dis_year),1-p_eps_a*p_rho_a^(B23-p_dis_year),1) | G23: =INDEX(Calib!$N$1:$N$13,$D23)*(1-p_rent_decline*MIN(1,C23/26)) | H23: =IF(C23=0,0,SUMIFS(dl_val,dl_iso,$A23,dl_ind,"pub_cap",dl_year,$B23)/100) | I23: =IF(C23=0,0,SUMIFS(dl_val,dl_iso,$A23,dl_ind,"pub_spend",dl_year,$B23)/100) | J23: =IF(C23=0,0,SUMIFS(dl_val,dl_iso,$A23,dl_ind,"rev",dl_year,$B23)/100) | K23: =(1-p_delta_g)*K22*(1-p_eps_g*$E23)+INDEX(Calib!$E$1:$E$13,$D23)*(INDEX(Calib!$G$1:$G$13,$D23)+0*$H23) | L23: =L22*(1-p_eps_k*$E23)+p_lambda_k*(N23-L22*(1-p_eps_k*$E23)) | M23: =INDEX(Calib!$R$1:$R$13,$D23)*$F23*(K22*(1-p_eps_g*$E23))^INDEX(Calib!$Q$1:$Q$13,$D23)*(L22*(1-p_eps_k*$E23))^p_alpha | N23: =p_alpha*(1-INDEX(Calib!$H$1:$H$13,$D23))*M23/(INDEX(Calib!$K$1:$K$13,$D23)+p_delta) | O23: =M23+$G23 | P23: =0*($H23+$I23) | Q23: =INDEX(Calib!$I$1:$I$13,$D23)+p_sh_grant*P23 | R23: =INDEX(Calib!$H$1:$H$13,$D23)*M23+p_gov_take*$G23+Q23+0*p_pricing*$J23 | S23: =INDEX(Calib!$Y$1:$Y$13,$D23)-INDEX(Calib!$Z$1:$Z$13,$D23)*(V22/O22-INDEX(Calib!$AA$1:$AA$13,$D23)) | T23: =INDEX(Calib!$X$1:$X$13,$D23)+INDEX(Calib!$G$1:$G$13,$D23)+P23+S23-R23 | U23: =p_rk*W22+Y22*(V22-W22) | V23: =V22+U23+T23 | W23: =INDEX(Calib!$U$1:$U$13,$D23)+(W22-INDEX(Calib!$U$1:$U$13,$D23))*(1-p_amort)+p_sh_conc*P23 | X23: =V23/O23 | Y23: =INDEX(Calib!$K$1:$K$13,$D23)+p_eta*MAX(0,X23-INDEX(Calib!$AA$1:$AA$13,$D23)) | Z23: =(1-INDEX(Calib!$H$1:$H$13,$D23))*(1-p_alpha)*M23+S23 | AA23: =(1-p_delta_g)*AA22*(1-p_eps_g*$E23)+INDEX(Calib!$E$1:$E$13,$D23)*(INDEX(Calib!$G$1:$G$13,$D23)+p_programme*$H23) | AB23: =AB22*(1-p_eps_k*$E23)+p_lambda_k*(AD23-AB22*(1-p_eps_k*$E23)) | AC23: =INDEX(Calib!$R$1:$R$13,$D23)*$F23*(AA22*(1-p_eps_g*$E23))^INDEX(Calib!$Q$1:$Q$13,$D23)*(AB22*(1-p_eps_k*$E23))^p_alpha | AD23: =p_alpha*(1-INDEX(Calib!$H$1:$H$13,$D23))*AC23/(INDEX(Calib!$K$1:$K$13,$D23)+p_delta) | AE23: =AC23+$G23 | AF23: =p_programme*($H23+$I23) | AG23: =INDEX(Calib!$I$1:$I$13,$D23)+p_sh_grant*AF23 | AH23: =INDEX(Calib!$H$1:$H$13,$D23)*AC23+p_gov_take*$G23+AG23+p_programme*p_pricing*$J23 | AI23: =INDEX(Calib!$Y$1:$Y$13,$D23)-INDEX(Calib!$Z$1:$Z$13,$D23)*(AL22/AE22-INDEX(Calib!$AA$1:$AA$13,$D23)) | AJ23: =INDEX(Calib!$X$1:$X$13,$D23)+INDEX(Calib!$G$1:$G$13,$D23)+AF23+AI23-AH23 | AK23: =p_rk*AM22+AO22*(AL22-AM22) | AL23: =AL22+AK23+AJ23 | AM23: =INDEX(Calib!$U$1:$U$13,$D23)+(AM22-INDEX(Calib!$U$1:$U$13,$D23))*(1-p_amort)+p_sh_conc*AF23 | AN23: =AL23/AE23 | AO23: =INDEX(Calib!$K$1:$K$13,$D23)+p_eta*MAX(0,AN23-INDEX(Calib!$AA$1:$AA$13,$D23)) | AP23: =(1-INDEX(Calib!$H$1:$H$13,$D23))*(1-p_alpha)*AC23+AI23 | AQ23: =(AE23/O23-1)*100 | AR23: =(AE23/AE2-1)*100 | AS23: =(O23/O2-1)*100 | AT23: =(AN23-X23)*100 | AU23: =(AP23/Z23-1)*100 | AV23: =(AI23-S23)*100
A24: KEN | B24: 2046 | C24: 22 | D24: 2 | E24: =IF(AND(p_dis_year>0,B24=p_dis_year),1,0) | F24: =IF(AND(p_dis_year>0,B24>=p_dis_year),1-p_eps_a*p_rho_a^(B24-p_dis_year),1) | G24: =INDEX(Calib!$N$1:$N$13,$D24)*(1-p_rent_decline*MIN(1,C24/26)) | H24: =IF(C24=0,0,SUMIFS(dl_val,dl_iso,$A24,dl_ind,"pub_cap",dl_year,$B24)/100) | I24: =IF(C24=0,0,SUMIFS(dl_val,dl_iso,$A24,dl_ind,"pub_spend",dl_year,$B24)/100) | J24: =IF(C24=0,0,SUMIFS(dl_val,dl_iso,$A24,dl_ind,"rev",dl_year,$B24)/100) | K24: =(1-p_delta_g)*K23*(1-p_eps_g*$E24)+INDEX(Calib!$E$1:$E$13,$D24)*(INDEX(Calib!$G$1:$G$13,$D24)+0*$H24) | L24: =L23*(1-p_eps_k*$E24)+p_lambda_k*(N24-L23*(1-p_eps_k*$E24)) | M24: =INDEX(Calib!$R$1:$R$13,$D24)*$F24*(K23*(1-p_eps_g*$E24))^INDEX(Calib!$Q$1:$Q$13,$D24)*(L23*(1-p_eps_k*$E24))^p_alpha | N24: =p_alpha*(1-INDEX(Calib!$H$1:$H$13,$D24))*M24/(INDEX(Calib!$K$1:$K$13,$D24)+p_delta) | O24: =M24+$G24 | P24: =0*($H24+$I24) | Q24: =INDEX(Calib!$I$1:$I$13,$D24)+p_sh_grant*P24 | R24: =INDEX(Calib!$H$1:$H$13,$D24)*M24+p_gov_take*$G24+Q24+0*p_pricing*$J24 | S24: =INDEX(Calib!$Y$1:$Y$13,$D24)-INDEX(Calib!$Z$1:$Z$13,$D24)*(V23/O23-INDEX(Calib!$AA$1:$AA$13,$D24)) | T24: =INDEX(Calib!$X$1:$X$13,$D24)+INDEX(Calib!$G$1:$G$13,$D24)+P24+S24-R24 | U24: =p_rk*W23+Y23*(V23-W23) | V24: =V23+U24+T24 | W24: =INDEX(Calib!$U$1:$U$13,$D24)+(W23-INDEX(Calib!$U$1:$U$13,$D24))*(1-p_amort)+p_sh_conc*P24 | X24: =V24/O24 | Y24: =INDEX(Calib!$K$1:$K$13,$D24)+p_eta*MAX(0,X24-INDEX(Calib!$AA$1:$AA$13,$D24)) | Z24: =(1-INDEX(Calib!$H$1:$H$13,$D24))*(1-p_alpha)*M24+S24 | AA24: =(1-p_delta_g)*AA23*(1-p_eps_g*$E24)+INDEX(Calib!$E$1:$E$13,$D24)*(INDEX(Calib!$G$1:$G$13,$D24)+p_programme*$H24) | AB24: =AB23*(1-p_eps_k*$E24)+p_lambda_k*(AD24-AB23*(1-p_eps_k*$E24)) | AC24: =INDEX(Calib!$R$1:$R$13,$D24)*$F24*(AA23*(1-p_eps_g*$E24))^INDEX(Calib!$Q$1:$Q$13,$D24)*(AB23*(1-p_eps_k*$E24))^p_alpha | AD24: =p_alpha*(1-INDEX(Calib!$H$1:$H$13,$D24))*AC24/(INDEX(Calib!$K$1:$K$13,$D24)+p_delta) | AE24: =AC24+$G24 | AF24: =p_programme*($H24+$I24) | AG24: =INDEX(Calib!$I$1:$I$13,$D24)+p_sh_grant*AF24 | AH24: =INDEX(Calib!$H$1:$H$13,$D24)*AC24+p_gov_take*$G24+AG24+p_programme*p_pricing*$J24 | AI24: =INDEX(Calib!$Y$1:$Y$13,$D24)-INDEX(Calib!$Z$1:$Z$13,$D24)*(AL23/AE23-INDEX(Calib!$AA$1:$AA$13,$D24)) | AJ24: =INDEX(Calib!$X$1:$X$13,$D24)+INDEX(Calib!$G$1:$G$13,$D24)+AF24+AI24-AH24 | AK24: =p_rk*AM23+AO23*(AL23-AM23) | AL24: =AL23+AK24+AJ24 | AM24: =INDEX(Calib!$U$1:$U$13,$D24)+(AM23-INDEX(Calib!$U$1:$U$13,$D24))*(1-p_amort)+p_sh_conc*AF24 | AN24: =AL24/AE24 | AO24: =INDEX(Calib!$K$1:$K$13,$D24)+p_eta*MAX(0,AN24-INDEX(Calib!$AA$1:$AA$13,$D24)) | AP24: =(1-INDEX(Calib!$H$1:$H$13,$D24))*(1-p_alpha)*AC24+AI24 | AQ24: =(AE24/O24-1)*100 | AR24: =(AE24/AE2-1)*100 | AS24: =(O24/O2-1)*100 | AT24: =(AN24-X24)*100 | AU24: =(AP24/Z24-1)*100 | AV24: =(AI24-S24)*100
A25: KEN | B25: 2047 | C25: 23 | D25: 2 | E25: =IF(AND(p_dis_year>0,B25=p_dis_year),1,0) | F25: =IF(AND(p_dis_year>0,B25>=p_dis_year),1-p_eps_a*p_rho_a^(B25-p_dis_year),1) | G25: =INDEX(Calib!$N$1:$N$13,$D25)*(1-p_rent_decline*MIN(1,C25/26)) | H25: =IF(C25=0,0,SUMIFS(dl_val,dl_iso,$A25,dl_ind,"pub_cap",dl_year,$B25)/100) | I25: =IF(C25=0,0,SUMIFS(dl_val,dl_iso,$A25,dl_ind,"pub_spend",dl_year,$B25)/100) | J25: =IF(C25=0,0,SUMIFS(dl_val,dl_iso,$A25,dl_ind,"rev",dl_year,$B25)/100) | K25: =(1-p_delta_g)*K24*(1-p_eps_g*$E25)+INDEX(Calib!$E$1:$E$13,$D25)*(INDEX(Calib!$G$1:$G$13,$D25)+0*$H25) | L25: =L24*(1-p_eps_k*$E25)+p_lambda_k*(N25-L24*(1-p_eps_k*$E25)) | M25: =INDEX(Calib!$R$1:$R$13,$D25)*$F25*(K24*(1-p_eps_g*$E25))^INDEX(Calib!$Q$1:$Q$13,$D25)*(L24*(1-p_eps_k*$E25))^p_alpha | N25: =p_alpha*(1-INDEX(Calib!$H$1:$H$13,$D25))*M25/(INDEX(Calib!$K$1:$K$13,$D25)+p_delta) | O25: =M25+$G25 | P25: =0*($H25+$I25) | Q25: =INDEX(Calib!$I$1:$I$13,$D25)+p_sh_grant*P25 | R25: =INDEX(Calib!$H$1:$H$13,$D25)*M25+p_gov_take*$G25+Q25+0*p_pricing*$J25 | S25: =INDEX(Calib!$Y$1:$Y$13,$D25)-INDEX(Calib!$Z$1:$Z$13,$D25)*(V24/O24-INDEX(Calib!$AA$1:$AA$13,$D25)) | T25: =INDEX(Calib!$X$1:$X$13,$D25)+INDEX(Calib!$G$1:$G$13,$D25)+P25+S25-R25 | U25: =p_rk*W24+Y24*(V24-W24) | V25: =V24+U25+T25 | W25: =INDEX(Calib!$U$1:$U$13,$D25)+(W24-INDEX(Calib!$U$1:$U$13,$D25))*(1-p_amort)+p_sh_conc*P25 | X25: =V25/O25 | Y25: =INDEX(Calib!$K$1:$K$13,$D25)+p_eta*MAX(0,X25-INDEX(Calib!$AA$1:$AA$13,$D25)) | Z25: =(1-INDEX(Calib!$H$1:$H$13,$D25))*(1-p_alpha)*M25+S25 | AA25: =(1-p_delta_g)*AA24*(1-p_eps_g*$E25)+INDEX(Calib!$E$1:$E$13,$D25)*(INDEX(Calib!$G$1:$G$13,$D25)+p_programme*$H25) | AB25: =AB24*(1-p_eps_k*$E25)+p_lambda_k*(AD25-AB24*(1-p_eps_k*$E25)) | AC25: =INDEX(Calib!$R$1:$R$13,$D25)*$F25*(AA24*(1-p_eps_g*$E25))^INDEX(Calib!$Q$1:$Q$13,$D25)*(AB24*(1-p_eps_k*$E25))^p_alpha | AD25: =p_alpha*(1-INDEX(Calib!$H$1:$H$13,$D25))*AC25/(INDEX(Calib!$K$1:$K$13,$D25)+p_delta) | AE25: =AC25+$G25 | AF25: =p_programme*($H25+$I25) | AG25: =INDEX(Calib!$I$1:$I$13,$D25)+p_sh_grant*AF25 | AH25: =INDEX(Calib!$H$1:$H$13,$D25)*AC25+p_gov_take*$G25+AG25+p_programme*p_pricing*$J25 | AI25: =INDEX(Calib!$Y$1:$Y$13,$D25)-INDEX(Calib!$Z$1:$Z$13,$D25)*(AL24/AE24-INDEX(Calib!$AA$1:$AA$13,$D25)) | AJ25: =INDEX(Calib!$X$1:$X$13,$D25)+INDEX(Calib!$G$1:$G$13,$D25)+AF25+AI25-AH25 | AK25: =p_rk*AM24+AO24*(AL24-AM24) | AL25: =AL24+AK25+AJ25 | AM25: =INDEX(Calib!$U$1:$U$13,$D25)+(AM24-INDEX(Calib!$U$1:$U$13,$D25))*(1-p_amort)+p_sh_conc*AF25 | AN25: =AL25/AE25 | AO25: =INDEX(Calib!$K$1:$K$13,$D25)+p_eta*MAX(0,AN25-INDEX(Calib!$AA$1:$AA$13,$D25)) | AP25: =(1-INDEX(Calib!$H$1:$H$13,$D25))*(1-p_alpha)*AC25+AI25 | AQ25: =(AE25/O25-1)*100 | AR25: =(AE25/AE2-1)*100 | AS25: =(O25/O2-1)*100 | AT25: =(AN25-X25)*100 | AU25: =(AP25/Z25-1)*100 | AV25: =(AI25-S25)*100
A26: KEN | B26: 2048 | C26: 24 | D26: 2 | E26: =IF(AND(p_dis_year>0,B26=p_dis_year),1,0) | F26: =IF(AND(p_dis_year>0,B26>=p_dis_year),1-p_eps_a*p_rho_a^(B26-p_dis_year),1) | G26: =INDEX(Calib!$N$1:$N$13,$D26)*(1-p_rent_decline*MIN(1,C26/26)) | H26: =IF(C26=0,0,SUMIFS(dl_val,dl_iso,$A26,dl_ind,"pub_cap",dl_year,$B26)/100) | I26: =IF(C26=0,0,SUMIFS(dl_val,dl_iso,$A26,dl_ind,"pub_spend",dl_year,$B26)/100) | J26: =IF(C26=0,0,SUMIFS(dl_val,dl_iso,$A26,dl_ind,"rev",dl_year,$B26)/100) | K26: =(1-p_delta_g)*K25*(1-p_eps_g*$E26)+INDEX(Calib!$E$1:$E$13,$D26)*(INDEX(Calib!$G$1:$G$13,$D26)+0*$H26) | L26: =L25*(1-p_eps_k*$E26)+p_lambda_k*(N26-L25*(1-p_eps_k*$E26)) | M26: =INDEX(Calib!$R$1:$R$13,$D26)*$F26*(K25*(1-p_eps_g*$E26))^INDEX(Calib!$Q$1:$Q$13,$D26)*(L25*(1-p_eps_k*$E26))^p_alpha | N26: =p_alpha*(1-INDEX(Calib!$H$1:$H$13,$D26))*M26/(INDEX(Calib!$K$1:$K$13,$D26)+p_delta) | O26: =M26+$G26 | P26: =0*($H26+$I26) | Q26: =INDEX(Calib!$I$1:$I$13,$D26)+p_sh_grant*P26 | R26: =INDEX(Calib!$H$1:$H$13,$D26)*M26+p_gov_take*$G26+Q26+0*p_pricing*$J26 | S26: =INDEX(Calib!$Y$1:$Y$13,$D26)-INDEX(Calib!$Z$1:$Z$13,$D26)*(V25/O25-INDEX(Calib!$AA$1:$AA$13,$D26)) | T26: =INDEX(Calib!$X$1:$X$13,$D26)+INDEX(Calib!$G$1:$G$13,$D26)+P26+S26-R26 | U26: =p_rk*W25+Y25*(V25-W25) | V26: =V25+U26+T26 | W26: =INDEX(Calib!$U$1:$U$13,$D26)+(W25-INDEX(Calib!$U$1:$U$13,$D26))*(1-p_amort)+p_sh_conc*P26 | X26: =V26/O26 | Y26: =INDEX(Calib!$K$1:$K$13,$D26)+p_eta*MAX(0,X26-INDEX(Calib!$AA$1:$AA$13,$D26)) | Z26: =(1-INDEX(Calib!$H$1:$H$13,$D26))*(1-p_alpha)*M26+S26 | AA26: =(1-p_delta_g)*AA25*(1-p_eps_g*$E26)+INDEX(Calib!$E$1:$E$13,$D26)*(INDEX(Calib!$G$1:$G$13,$D26)+p_programme*$H26) | AB26: =AB25*(1-p_eps_k*$E26)+p_lambda_k*(AD26-AB25*(1-p_eps_k*$E26)) | AC26: =INDEX(Calib!$R$1:$R$13,$D26)*$F26*(AA25*(1-p_eps_g*$E26))^INDEX(Calib!$Q$1:$Q$13,$D26)*(AB25*(1-p_eps_k*$E26))^p_alpha | AD26: =p_alpha*(1-INDEX(Calib!$H$1:$H$13,$D26))*AC26/(INDEX(Calib!$K$1:$K$13,$D26)+p_delta) | AE26: =AC26+$G26 | AF26: =p_programme*($H26+$I26) | AG26: =INDEX(Calib!$I$1:$I$13,$D26)+p_sh_grant*AF26 | AH26: =INDEX(Calib!$H$1:$H$13,$D26)*AC26+p_gov_take*$G26+AG26+p_programme*p_pricing*$J26 | AI26: =INDEX(Calib!$Y$1:$Y$13,$D26)-INDEX(Calib!$Z$1:$Z$13,$D26)*(AL25/AE25-INDEX(Calib!$AA$1:$AA$13,$D26)) | AJ26: =INDEX(Calib!$X$1:$X$13,$D26)+INDEX(Calib!$G$1:$G$13,$D26)+AF26+AI26-AH26 | AK26: =p_rk*AM25+AO25*(AL25-AM25) | AL26: =AL25+AK26+AJ26 | AM26: =INDEX(Calib!$U$1:$U$13,$D26)+(AM25-INDEX(Calib!$U$1:$U$13,$D26))*(1-p_amort)+p_sh_conc*AF26 | AN26: =AL26/AE26 | AO26: =INDEX(Calib!$K$1:$K$13,$D26)+p_eta*MAX(0,AN26-INDEX(Calib!$AA$1:$AA$13,$D26)) | AP26: =(1-INDEX(Calib!$H$1:$H$13,$D26))*(1-p_alpha)*AC26+AI26 | AQ26: =(AE26/O26-1)*100 | AR26: =(AE26/AE2-1)*100 | AS26: =(O26/O2-1)*100 | AT26: =(AN26-X26)*100 | AU26: =(AP26/Z26-1)*100 | AV26: =(AI26-S26)*100
A27: KEN | B27: 2049 | C27: 25 | D27: 2 | E27: =IF(AND(p_dis_year>0,B27=p_dis_year),1,0) | F27: =IF(AND(p_dis_year>0,B27>=p_dis_year),1-p_eps_a*p_rho_a^(B27-p_dis_year),1) | G27: =INDEX(Calib!$N$1:$N$13,$D27)*(1-p_rent_decline*MIN(1,C27/26)) | H27: =IF(C27=0,0,SUMIFS(dl_val,dl_iso,$A27,dl_ind,"pub_cap",dl_year,$B27)/100) | I27: =IF(C27=0,0,SUMIFS(dl_val,dl_iso,$A27,dl_ind,"pub_spend",dl_year,$B27)/100) | J27: =IF(C27=0,0,SUMIFS(dl_val,dl_iso,$A27,dl_ind,"rev",dl_year,$B27)/100) | K27: =(1-p_delta_g)*K26*(1-p_eps_g*$E27)+INDEX(Calib!$E$1:$E$13,$D27)*(INDEX(Calib!$G$1:$G$13,$D27)+0*$H27) | L27: =L26*(1-p_eps_k*$E27)+p_lambda_k*(N27-L26*(1-p_eps_k*$E27)) | M27: =INDEX(Calib!$R$1:$R$13,$D27)*$F27*(K26*(1-p_eps_g*$E27))^INDEX(Calib!$Q$1:$Q$13,$D27)*(L26*(1-p_eps_k*$E27))^p_alpha | N27: =p_alpha*(1-INDEX(Calib!$H$1:$H$13,$D27))*M27/(INDEX(Calib!$K$1:$K$13,$D27)+p_delta) | O27: =M27+$G27 | P27: =0*($H27+$I27) | Q27: =INDEX(Calib!$I$1:$I$13,$D27)+p_sh_grant*P27 | R27: =INDEX(Calib!$H$1:$H$13,$D27)*M27+p_gov_take*$G27+Q27+0*p_pricing*$J27 | S27: =INDEX(Calib!$Y$1:$Y$13,$D27)-INDEX(Calib!$Z$1:$Z$13,$D27)*(V26/O26-INDEX(Calib!$AA$1:$AA$13,$D27)) | T27: =INDEX(Calib!$X$1:$X$13,$D27)+INDEX(Calib!$G$1:$G$13,$D27)+P27+S27-R27 | U27: =p_rk*W26+Y26*(V26-W26) | V27: =V26+U27+T27 | W27: =INDEX(Calib!$U$1:$U$13,$D27)+(W26-INDEX(Calib!$U$1:$U$13,$D27))*(1-p_amort)+p_sh_conc*P27 | X27: =V27/O27 | Y27: =INDEX(Calib!$K$1:$K$13,$D27)+p_eta*MAX(0,X27-INDEX(Calib!$AA$1:$AA$13,$D27)) | Z27: =(1-INDEX(Calib!$H$1:$H$13,$D27))*(1-p_alpha)*M27+S27 | AA27: =(1-p_delta_g)*AA26*(1-p_eps_g*$E27)+INDEX(Calib!$E$1:$E$13,$D27)*(INDEX(Calib!$G$1:$G$13,$D27)+p_programme*$H27) | AB27: =AB26*(1-p_eps_k*$E27)+p_lambda_k*(AD27-AB26*(1-p_eps_k*$E27)) | AC27: =INDEX(Calib!$R$1:$R$13,$D27)*$F27*(AA26*(1-p_eps_g*$E27))^INDEX(Calib!$Q$1:$Q$13,$D27)*(AB26*(1-p_eps_k*$E27))^p_alpha | AD27: =p_alpha*(1-INDEX(Calib!$H$1:$H$13,$D27))*AC27/(INDEX(Calib!$K$1:$K$13,$D27)+p_delta) | AE27: =AC27+$G27 | AF27: =p_programme*($H27+$I27) | AG27: =INDEX(Calib!$I$1:$I$13,$D27)+p_sh_grant*AF27 | AH27: =INDEX(Calib!$H$1:$H$13,$D27)*AC27+p_gov_take*$G27+AG27+p_programme*p_pricing*$J27 | AI27: =INDEX(Calib!$Y$1:$Y$13,$D27)-INDEX(Calib!$Z$1:$Z$13,$D27)*(AL26/AE26-INDEX(Calib!$AA$1:$AA$13,$D27)) | AJ27: =INDEX(Calib!$X$1:$X$13,$D27)+INDEX(Calib!$G$1:$G$13,$D27)+AF27+AI27-AH27 | AK27: =p_rk*AM26+AO26*(AL26-AM26) | AL27: =AL26+AK27+AJ27 | AM27: =INDEX(Calib!$U$1:$U$13,$D27)+(AM26-INDEX(Calib!$U$1:$U$13,$D27))*(1-p_amort)+p_sh_conc*AF27 | AN27: =AL27/AE27 | AO27: =INDEX(Calib!$K$1:$K$13,$D27)+p_eta*MAX(0,AN27-INDEX(Calib!$AA$1:$AA$13,$D27)) | AP27: =(1-INDEX(Calib!$H$1:$H$13,$D27))*(1-p_alpha)*AC27+AI27 | AQ27: =(AE27/O27-1)*100 | AR27: =(AE27/AE2-1)*100 | AS27: =(O27/O2-1)*100 | AT27: =(AN27-X27)*100 | AU27: =(AP27/Z27-1)*100 | AV27: =(AI27-S27)*100
A28: KEN | B28: 2050 | C28: 26 | D28: 2 | E28: =IF(AND(p_dis_year>0,B28=p_dis_year),1,0) | F28: =IF(AND(p_dis_year>0,B28>=p_dis_year),1-p_eps_a*p_rho_a^(B28-p_dis_year),1) | G28: =INDEX(Calib!$N$1:$N$13,$D28)*(1-p_rent_decline*MIN(1,C28/26)) | H28: =IF(C28=0,0,SUMIFS(dl_val,dl_iso,$A28,dl_ind,"pub_cap",dl_year,$B28)/100) | I28: =IF(C28=0,0,SUMIFS(dl_val,dl_iso,$A28,dl_ind,"pub_spend",dl_year,$B28)/100) | J28: =IF(C28=0,0,SUMIFS(dl_val,dl_iso,$A28,dl_ind,"rev",dl_year,$B28)/100) | K28: =(1-p_delta_g)*K27*(1-p_eps_g*$E28)+INDEX(Calib!$E$1:$E$13,$D28)*(INDEX(Calib!$G$1:$G$13,$D28)+0*$H28) | L28: =L27*(1-p_eps_k*$E28)+p_lambda_k*(N28-L27*(1-p_eps_k*$E28)) | M28: =INDEX(Calib!$R$1:$R$13,$D28)*$F28*(K27*(1-p_eps_g*$E28))^INDEX(Calib!$Q$1:$Q$13,$D28)*(L27*(1-p_eps_k*$E28))^p_alpha | N28: =p_alpha*(1-INDEX(Calib!$H$1:$H$13,$D28))*M28/(INDEX(Calib!$K$1:$K$13,$D28)+p_delta) | O28: =M28+$G28 | P28: =0*($H28+$I28) | Q28: =INDEX(Calib!$I$1:$I$13,$D28)+p_sh_grant*P28 | R28: =INDEX(Calib!$H$1:$H$13,$D28)*M28+p_gov_take*$G28+Q28+0*p_pricing*$J28 | S28: =INDEX(Calib!$Y$1:$Y$13,$D28)-INDEX(Calib!$Z$1:$Z$13,$D28)*(V27/O27-INDEX(Calib!$AA$1:$AA$13,$D28)) | T28: =INDEX(Calib!$X$1:$X$13,$D28)+INDEX(Calib!$G$1:$G$13,$D28)+P28+S28-R28 | U28: =p_rk*W27+Y27*(V27-W27) | V28: =V27+U28+T28 | W28: =INDEX(Calib!$U$1:$U$13,$D28)+(W27-INDEX(Calib!$U$1:$U$13,$D28))*(1-p_amort)+p_sh_conc*P28 | X28: =V28/O28 | Y28: =INDEX(Calib!$K$1:$K$13,$D28)+p_eta*MAX(0,X28-INDEX(Calib!$AA$1:$AA$13,$D28)) | Z28: =(1-INDEX(Calib!$H$1:$H$13,$D28))*(1-p_alpha)*M28+S28 | AA28: =(1-p_delta_g)*AA27*(1-p_eps_g*$E28)+INDEX(Calib!$E$1:$E$13,$D28)*(INDEX(Calib!$G$1:$G$13,$D28)+p_programme*$H28) | AB28: =AB27*(1-p_eps_k*$E28)+p_lambda_k*(AD28-AB27*(1-p_eps_k*$E28)) | AC28: =INDEX(Calib!$R$1:$R$13,$D28)*$F28*(AA27*(1-p_eps_g*$E28))^INDEX(Calib!$Q$1:$Q$13,$D28)*(AB27*(1-p_eps_k*$E28))^p_alpha | AD28: =p_alpha*(1-INDEX(Calib!$H$1:$H$13,$D28))*AC28/(INDEX(Calib!$K$1:$K$13,$D28)+p_delta) | AE28: =AC28+$G28 | AF28: =p_programme*($H28+$I28) | AG28: =INDEX(Calib!$I$1:$I$13,$D28)+p_sh_grant*AF28 | AH28: =INDEX(Calib!$H$1:$H$13,$D28)*AC28+p_gov_take*$G28+AG28+p_programme*p_pricing*$J28 | AI28: =INDEX(Calib!$Y$1:$Y$13,$D28)-INDEX(Calib!$Z$1:$Z$13,$D28)*(AL27/AE27-INDEX(Calib!$AA$1:$AA$13,$D28)) | AJ28: =INDEX(Calib!$X$1:$X$13,$D28)+INDEX(Calib!$G$1:$G$13,$D28)+AF28+AI28-AH28 | AK28: =p_rk*AM27+AO27*(AL27-AM27) | AL28: =AL27+AK28+AJ28 | AM28: =INDEX(Calib!$U$1:$U$13,$D28)+(AM27-INDEX(Calib!$U$1:$U$13,$D28))*(1-p_amort)+p_sh_conc*AF28 | AN28: =AL28/AE28 | AO28: =INDEX(Calib!$K$1:$K$13,$D28)+p_eta*MAX(0,AN28-INDEX(Calib!$AA$1:$AA$13,$D28)) | AP28: =(1-INDEX(Calib!$H$1:$H$13,$D28))*(1-p_alpha)*AC28+AI28 | AQ28: =(AE28/O28-1)*100 | AR28: =(AE28/AE2-1)*100 | AS28: =(O28/O2-1)*100 | AT28: =(AN28-X28)*100 | AU28: =(AP28/Z28-1)*100 | AV28: =(AI28-S28)*100
A29: SLE | B29: 2024 | C29: 0 | D29: 3 | E29: =IF(AND(p_dis_year>0,B29=p_dis_year),1,0) | F29: =IF(AND(p_dis_year>0,B29>=p_dis_year),1-p_eps_a*p_rho_a^(B29-p_dis_year),1) | G29: =INDEX(Calib!$N$1:$N$13,$D29)*(1-p_rent_decline*MIN(1,C29/26)) | H29: =IF(C29=0,0,SUMIFS(dl_val,dl_iso,$A29,dl_ind,"pub_cap",dl_year,$B29)/100) | I29: =IF(C29=0,0,SUMIFS(dl_val,dl_iso,$A29,dl_ind,"pub_spend",dl_year,$B29)/100) | J29: =IF(C29=0,0,SUMIFS(dl_val,dl_iso,$A29,dl_ind,"rev",dl_year,$B29)/100) | K29: =INDEX(Calib!$P$1:$P$13,$D29) | L29: =INDEX(Calib!$O$1:$O$13,$D29) | M29: =1 | N29: =INDEX(Calib!$O$1:$O$13,$D29) | O29: =INDEX(Calib!$S$1:$S$13,$D29) | P29: =0 | Q29: =INDEX(Calib!$I$1:$I$13,$D29) | R29: =INDEX(Calib!$W$1:$W$13,$D29) | S29: =INDEX(Calib!$Y$1:$Y$13,$D29) | T29: =-INDEX(Calib!$V$1:$V$13,$D29) | U29: =INDEX(Calib!$V$1:$V$13,$D29) | V29: =INDEX(Calib!$T$1:$T$13,$D29) | W29: =INDEX(Calib!$U$1:$U$13,$D29) | X29: =V29/O29 | Y29: =INDEX(Calib!$K$1:$K$13,$D29) | Z29: =(1-INDEX(Calib!$H$1:$H$13,$D29))*(1-p_alpha)*M29+S29 | AA29: =INDEX(Calib!$P$1:$P$13,$D29) | AB29: =INDEX(Calib!$O$1:$O$13,$D29) | AC29: =1 | AD29: =INDEX(Calib!$O$1:$O$13,$D29) | AE29: =INDEX(Calib!$S$1:$S$13,$D29) | AF29: =0 | AG29: =INDEX(Calib!$I$1:$I$13,$D29) | AH29: =INDEX(Calib!$W$1:$W$13,$D29) | AI29: =INDEX(Calib!$Y$1:$Y$13,$D29) | AJ29: =-INDEX(Calib!$V$1:$V$13,$D29) | AK29: =INDEX(Calib!$V$1:$V$13,$D29) | AL29: =INDEX(Calib!$T$1:$T$13,$D29) | AM29: =INDEX(Calib!$U$1:$U$13,$D29) | AN29: =AL29/AE29 | AO29: =INDEX(Calib!$K$1:$K$13,$D29) | AP29: =(1-INDEX(Calib!$H$1:$H$13,$D29))*(1-p_alpha)*AC29+AI29 | AQ29: =(AE29/O29-1)*100 | AR29: =(AE29/AE29-1)*100 | AS29: =(O29/O29-1)*100 | AT29: =(AN29-X29)*100 | AU29: =(AP29/Z29-1)*100 | AV29: =(AI29-S29)*100
A30: SLE | B30: 2025 | C30: 1 | D30: 3 | E30: =IF(AND(p_dis_year>0,B30=p_dis_year),1,0) | F30: =IF(AND(p_dis_year>0,B30>=p_dis_year),1-p_eps_a*p_rho_a^(B30-p_dis_year),1) | G30: =INDEX(Calib!$N$1:$N$13,$D30)*(1-p_rent_decline*MIN(1,C30/26)) | H30: =IF(C30=0,0,SUMIFS(dl_val,dl_iso,$A30,dl_ind,"pub_cap",dl_year,$B30)/100) | I30: =IF(C30=0,0,SUMIFS(dl_val,dl_iso,$A30,dl_ind,"pub_spend",dl_year,$B30)/100) | J30: =IF(C30=0,0,SUMIFS(dl_val,dl_iso,$A30,dl_ind,"rev",dl_year,$B30)/100) | K30: =(1-p_delta_g)*K29*(1-p_eps_g*$E30)+INDEX(Calib!$E$1:$E$13,$D30)*(INDEX(Calib!$G$1:$G$13,$D30)+0*$H30) | L30: =L29*(1-p_eps_k*$E30)+p_lambda_k*(N30-L29*(1-p_eps_k*$E30)) | M30: =INDEX(Calib!$R$1:$R$13,$D30)*$F30*(K29*(1-p_eps_g*$E30))^INDEX(Calib!$Q$1:$Q$13,$D30)*(L29*(1-p_eps_k*$E30))^p_alpha | N30: =p_alpha*(1-INDEX(Calib!$H$1:$H$13,$D30))*M30/(INDEX(Calib!$K$1:$K$13,$D30)+p_delta) | O30: =M30+$G30 | P30: =0*($H30+$I30) | Q30: =INDEX(Calib!$I$1:$I$13,$D30)+p_sh_grant*P30 | R30: =INDEX(Calib!$H$1:$H$13,$D30)*M30+p_gov_take*$G30+Q30+0*p_pricing*$J30 | S30: =INDEX(Calib!$Y$1:$Y$13,$D30)-INDEX(Calib!$Z$1:$Z$13,$D30)*(V29/O29-INDEX(Calib!$AA$1:$AA$13,$D30)) | T30: =INDEX(Calib!$X$1:$X$13,$D30)+INDEX(Calib!$G$1:$G$13,$D30)+P30+S30-R30 | U30: =p_rk*W29+Y29*(V29-W29) | V30: =V29+U30+T30 | W30: =INDEX(Calib!$U$1:$U$13,$D30)+(W29-INDEX(Calib!$U$1:$U$13,$D30))*(1-p_amort)+p_sh_conc*P30 | X30: =V30/O30 | Y30: =INDEX(Calib!$K$1:$K$13,$D30)+p_eta*MAX(0,X30-INDEX(Calib!$AA$1:$AA$13,$D30)) | Z30: =(1-INDEX(Calib!$H$1:$H$13,$D30))*(1-p_alpha)*M30+S30 | AA30: =(1-p_delta_g)*AA29*(1-p_eps_g*$E30)+INDEX(Calib!$E$1:$E$13,$D30)*(INDEX(Calib!$G$1:$G$13,$D30)+p_programme*$H30) | AB30: =AB29*(1-p_eps_k*$E30)+p_lambda_k*(AD30-AB29*(1-p_eps_k*$E30)) | AC30: =INDEX(Calib!$R$1:$R$13,$D30)*$F30*(AA29*(1-p_eps_g*$E30))^INDEX(Calib!$Q$1:$Q$13,$D30)*(AB29*(1-p_eps_k*$E30))^p_alpha | AD30: =p_alpha*(1-INDEX(Calib!$H$1:$H$13,$D30))*AC30/(INDEX(Calib!$K$1:$K$13,$D30)+p_delta) | AE30: =AC30+$G30 | AF30: =p_programme*($H30+$I30) | AG30: =INDEX(Calib!$I$1:$I$13,$D30)+p_sh_grant*AF30 | AH30: =INDEX(Calib!$H$1:$H$13,$D30)*AC30+p_gov_take*$G30+AG30+p_programme*p_pricing*$J30 | AI30: =INDEX(Calib!$Y$1:$Y$13,$D30)-INDEX(Calib!$Z$1:$Z$13,$D30)*(AL29/AE29-INDEX(Calib!$AA$1:$AA$13,$D30)) | AJ30: =INDEX(Calib!$X$1:$X$13,$D30)+INDEX(Calib!$G$1:$G$13,$D30)+AF30+AI30-AH30 | AK30: =p_rk*AM29+AO29*(AL29-AM29) | AL30: =AL29+AK30+AJ30 | AM30: =INDEX(Calib!$U$1:$U$13,$D30)+(AM29-INDEX(Calib!$U$1:$U$13,$D30))*(1-p_amort)+p_sh_conc*AF30 | AN30: =AL30/AE30 | AO30: =INDEX(Calib!$K$1:$K$13,$D30)+p_eta*MAX(0,AN30-INDEX(Calib!$AA$1:$AA$13,$D30)) | AP30: =(1-INDEX(Calib!$H$1:$H$13,$D30))*(1-p_alpha)*AC30+AI30 | AQ30: =(AE30/O30-1)*100 | AR30: =(AE30/AE29-1)*100 | AS30: =(O30/O29-1)*100 | AT30: =(AN30-X30)*100 | AU30: =(AP30/Z30-1)*100 | AV30: =(AI30-S30)*100
A31: SLE | B31: 2026 | C31: 2 | D31: 3 | E31: =IF(AND(p_dis_year>0,B31=p_dis_year),1,0) | F31: =IF(AND(p_dis_year>0,B31>=p_dis_year),1-p_eps_a*p_rho_a^(B31-p_dis_year),1) | G31: =INDEX(Calib!$N$1:$N$13,$D31)*(1-p_rent_decline*MIN(1,C31/26)) | H31: =IF(C31=0,0,SUMIFS(dl_val,dl_iso,$A31,dl_ind,"pub_cap",dl_year,$B31)/100) | I31: =IF(C31=0,0,SUMIFS(dl_val,dl_iso,$A31,dl_ind,"pub_spend",dl_year,$B31)/100) | J31: =IF(C31=0,0,SUMIFS(dl_val,dl_iso,$A31,dl_ind,"rev",dl_year,$B31)/100) | K31: =(1-p_delta_g)*K30*(1-p_eps_g*$E31)+INDEX(Calib!$E$1:$E$13,$D31)*(INDEX(Calib!$G$1:$G$13,$D31)+0*$H31) | L31: =L30*(1-p_eps_k*$E31)+p_lambda_k*(N31-L30*(1-p_eps_k*$E31)) | M31: =INDEX(Calib!$R$1:$R$13,$D31)*$F31*(K30*(1-p_eps_g*$E31))^INDEX(Calib!$Q$1:$Q$13,$D31)*(L30*(1-p_eps_k*$E31))^p_alpha | N31: =p_alpha*(1-INDEX(Calib!$H$1:$H$13,$D31))*M31/(INDEX(Calib!$K$1:$K$13,$D31)+p_delta) | O31: =M31+$G31 | P31: =0*($H31+$I31) | Q31: =INDEX(Calib!$I$1:$I$13,$D31)+p_sh_grant*P31 | R31: =INDEX(Calib!$H$1:$H$13,$D31)*M31+p_gov_take*$G31+Q31+0*p_pricing*$J31 | S31: =INDEX(Calib!$Y$1:$Y$13,$D31)-INDEX(Calib!$Z$1:$Z$13,$D31)*(V30/O30-INDEX(Calib!$AA$1:$AA$13,$D31)) | T31: =INDEX(Calib!$X$1:$X$13,$D31)+INDEX(Calib!$G$1:$G$13,$D31)+P31+S31-R31 | U31: =p_rk*W30+Y30*(V30-W30) | V31: =V30+U31+T31 | W31: =INDEX(Calib!$U$1:$U$13,$D31)+(W30-INDEX(Calib!$U$1:$U$13,$D31))*(1-p_amort)+p_sh_conc*P31 | X31: =V31/O31 | Y31: =INDEX(Calib!$K$1:$K$13,$D31)+p_eta*MAX(0,X31-INDEX(Calib!$AA$1:$AA$13,$D31)) | Z31: =(1-INDEX(Calib!$H$1:$H$13,$D31))*(1-p_alpha)*M31+S31 | AA31: =(1-p_delta_g)*AA30*(1-p_eps_g*$E31)+INDEX(Calib!$E$1:$E$13,$D31)*(INDEX(Calib!$G$1:$G$13,$D31)+p_programme*$H31) | AB31: =AB30*(1-p_eps_k*$E31)+p_lambda_k*(AD31-AB30*(1-p_eps_k*$E31)) | AC31: =INDEX(Calib!$R$1:$R$13,$D31)*$F31*(AA30*(1-p_eps_g*$E31))^INDEX(Calib!$Q$1:$Q$13,$D31)*(AB30*(1-p_eps_k*$E31))^p_alpha | AD31: =p_alpha*(1-INDEX(Calib!$H$1:$H$13,$D31))*AC31/(INDEX(Calib!$K$1:$K$13,$D31)+p_delta) | AE31: =AC31+$G31 | AF31: =p_programme*($H31+$I31) | AG31: =INDEX(Calib!$I$1:$I$13,$D31)+p_sh_grant*AF31 | AH31: =INDEX(Calib!$H$1:$H$13,$D31)*AC31+p_gov_take*$G31+AG31+p_programme*p_pricing*$J31 | AI31: =INDEX(Calib!$Y$1:$Y$13,$D31)-INDEX(Calib!$Z$1:$Z$13,$D31)*(AL30/AE30-INDEX(Calib!$AA$1:$AA$13,$D31)) | AJ31: =INDEX(Calib!$X$1:$X$13,$D31)+INDEX(Calib!$G$1:$G$13,$D31)+AF31+AI31-AH31 | AK31: =p_rk*AM30+AO30*(AL30-AM30) | AL31: =AL30+AK31+AJ31 | AM31: =INDEX(Calib!$U$1:$U$13,$D31)+(AM30-INDEX(Calib!$U$1:$U$13,$D31))*(1-p_amort)+p_sh_conc*AF31 | AN31: =AL31/AE31 | AO31: =INDEX(Calib!$K$1:$K$13,$D31)+p_eta*MAX(0,AN31-INDEX(Calib!$AA$1:$AA$13,$D31)) | AP31: =(1-INDEX(Calib!$H$1:$H$13,$D31))*(1-p_alpha)*AC31+AI31 | AQ31: =(AE31/O31-1)*100 | AR31: =(AE31/AE29-1)*100 | AS31: =(O31/O29-1)*100 | AT31: =(AN31-X31)*100 | AU31: =(AP31/Z31-1)*100 | AV31: =(AI31-S31)*100
A32: SLE | B32: 2027 | C32: 3 | D32: 3 | E32: =IF(AND(p_dis_year>0,B32=p_dis_year),1,0) | F32: =IF(AND(p_dis_year>0,B32>=p_dis_year),1-p_eps_a*p_rho_a^(B32-p_dis_year),1) | G32: =INDEX(Calib!$N$1:$N$13,$D32)*(1-p_rent_decline*MIN(1,C32/26)) | H32: =IF(C32=0,0,SUMIFS(dl_val,dl_iso,$A32,dl_ind,"pub_cap",dl_year,$B32)/100) | I32: =IF(C32=0,0,SUMIFS(dl_val,dl_iso,$A32,dl_ind,"pub_spend",dl_year,$B32)/100) | J32: =IF(C32=0,0,SUMIFS(dl_val,dl_iso,$A32,dl_ind,"rev",dl_year,$B32)/100) | K32: =(1-p_delta_g)*K31*(1-p_eps_g*$E32)+INDEX(Calib!$E$1:$E$13,$D32)*(INDEX(Calib!$G$1:$G$13,$D32)+0*$H32) | L32: =L31*(1-p_eps_k*$E32)+p_lambda_k*(N32-L31*(1-p_eps_k*$E32)) | M32: =INDEX(Calib!$R$1:$R$13,$D32)*$F32*(K31*(1-p_eps_g*$E32))^INDEX(Calib!$Q$1:$Q$13,$D32)*(L31*(1-p_eps_k*$E32))^p_alpha | N32: =p_alpha*(1-INDEX(Calib!$H$1:$H$13,$D32))*M32/(INDEX(Calib!$K$1:$K$13,$D32)+p_delta) | O32: =M32+$G32 | P32: =0*($H32+$I32) | Q32: =INDEX(Calib!$I$1:$I$13,$D32)+p_sh_grant*P32 | R32: =INDEX(Calib!$H$1:$H$13,$D32)*M32+p_gov_take*$G32+Q32+0*p_pricing*$J32 | S32: =INDEX(Calib!$Y$1:$Y$13,$D32)-INDEX(Calib!$Z$1:$Z$13,$D32)*(V31/O31-INDEX(Calib!$AA$1:$AA$13,$D32)) | T32: =INDEX(Calib!$X$1:$X$13,$D32)+INDEX(Calib!$G$1:$G$13,$D32)+P32+S32-R32 | U32: =p_rk*W31+Y31*(V31-W31) | V32: =V31+U32+T32 | W32: =INDEX(Calib!$U$1:$U$13,$D32)+(W31-INDEX(Calib!$U$1:$U$13,$D32))*(1-p_amort)+p_sh_conc*P32 | X32: =V32/O32 | Y32: =INDEX(Calib!$K$1:$K$13,$D32)+p_eta*MAX(0,X32-INDEX(Calib!$AA$1:$AA$13,$D32)) | Z32: =(1-INDEX(Calib!$H$1:$H$13,$D32))*(1-p_alpha)*M32+S32 | AA32: =(1-p_delta_g)*AA31*(1-p_eps_g*$E32)+INDEX(Calib!$E$1:$E$13,$D32)*(INDEX(Calib!$G$1:$G$13,$D32)+p_programme*$H32) | AB32: =AB31*(1-p_eps_k*$E32)+p_lambda_k*(AD32-AB31*(1-p_eps_k*$E32)) | AC32: =INDEX(Calib!$R$1:$R$13,$D32)*$F32*(AA31*(1-p_eps_g*$E32))^INDEX(Calib!$Q$1:$Q$13,$D32)*(AB31*(1-p_eps_k*$E32))^p_alpha | AD32: =p_alpha*(1-INDEX(Calib!$H$1:$H$13,$D32))*AC32/(INDEX(Calib!$K$1:$K$13,$D32)+p_delta) | AE32: =AC32+$G32 | AF32: =p_programme*($H32+$I32) | AG32: =INDEX(Calib!$I$1:$I$13,$D32)+p_sh_grant*AF32 | AH32: =INDEX(Calib!$H$1:$H$13,$D32)*AC32+p_gov_take*$G32+AG32+p_programme*p_pricing*$J32 | AI32: =INDEX(Calib!$Y$1:$Y$13,$D32)-INDEX(Calib!$Z$1:$Z$13,$D32)*(AL31/AE31-INDEX(Calib!$AA$1:$AA$13,$D32)) | AJ32: =INDEX(Calib!$X$1:$X$13,$D32)+INDEX(Calib!$G$1:$G$13,$D32)+AF32+AI32-AH32 | AK32: =p_rk*AM31+AO31*(AL31-AM31) | AL32: =AL31+AK32+AJ32 | AM32: =INDEX(Calib!$U$1:$U$13,$D32)+(AM31-INDEX(Calib!$U$1:$U$13,$D32))*(1-p_amort)+p_sh_conc*AF32 | AN32: =AL32/AE32 | AO32: =INDEX(Calib!$K$1:$K$13,$D32)+p_eta*MAX(0,AN32-INDEX(Calib!$AA$1:$AA$13,$D32)) | AP32: =(1-INDEX(Calib!$H$1:$H$13,$D32))*(1-p_alpha)*AC32+AI32 | AQ32: =(AE32/O32-1)*100 | AR32: =(AE32/AE29-1)*100 | AS32: =(O32/O29-1)*100 | AT32: =(AN32-X32)*100 | AU32: =(AP32/Z32-1)*100 | AV32: =(AI32-S32)*100
A33: SLE | B33: 2028 | C33: 4 | D33: 3 | E33: =IF(AND(p_dis_year>0,B33=p_dis_year),1,0) | F33: =IF(AND(p_dis_year>0,B33>=p_dis_year),1-p_eps_a*p_rho_a^(B33-p_dis_year),1) | G33: =INDEX(Calib!$N$1:$N$13,$D33)*(1-p_rent_decline*MIN(1,C33/26)) | H33: =IF(C33=0,0,SUMIFS(dl_val,dl_iso,$A33,dl_ind,"pub_cap",dl_year,$B33)/100) | I33: =IF(C33=0,0,SUMIFS(dl_val,dl_iso,$A33,dl_ind,"pub_spend",dl_year,$B33)/100) | J33: =IF(C33=0,0,SUMIFS(dl_val,dl_iso,$A33,dl_ind,"rev",dl_year,$B33)/100) | K33: =(1-p_delta_g)*K32*(1-p_eps_g*$E33)+INDEX(Calib!$E$1:$E$13,$D33)*(INDEX(Calib!$G$1:$G$13,$D33)+0*$H33) | L33: =L32*(1-p_eps_k*$E33)+p_lambda_k*(N33-L32*(1-p_eps_k*$E33)) | M33: =INDEX(Calib!$R$1:$R$13,$D33)*$F33*(K32*(1-p_eps_g*$E33))^INDEX(Calib!$Q$1:$Q$13,$D33)*(L32*(1-p_eps_k*$E33))^p_alpha | N33: =p_alpha*(1-INDEX(Calib!$H$1:$H$13,$D33))*M33/(INDEX(Calib!$K$1:$K$13,$D33)+p_delta) | O33: =M33+$G33 | P33: =0*($H33+$I33) | Q33: =INDEX(Calib!$I$1:$I$13,$D33)+p_sh_grant*P33 | R33: =INDEX(Calib!$H$1:$H$13,$D33)*M33+p_gov_take*$G33+Q33+0*p_pricing*$J33 | S33: =INDEX(Calib!$Y$1:$Y$13,$D33)-INDEX(Calib!$Z$1:$Z$13,$D33)*(V32/O32-INDEX(Calib!$AA$1:$AA$13,$D33)) | T33: =INDEX(Calib!$X$1:$X$13,$D33)+INDEX(Calib!$G$1:$G$13,$D33)+P33+S33-R33 | U33: =p_rk*W32+Y32*(V32-W32) | V33: =V32+U33+T33 | W33: =INDEX(Calib!$U$1:$U$13,$D33)+(W32-INDEX(Calib!$U$1:$U$13,$D33))*(1-p_amort)+p_sh_conc*P33 | X33: =V33/O33 | Y33: =INDEX(Calib!$K$1:$K$13,$D33)+p_eta*MAX(0,X33-INDEX(Calib!$AA$1:$AA$13,$D33)) | Z33: =(1-INDEX(Calib!$H$1:$H$13,$D33))*(1-p_alpha)*M33+S33 | AA33: =(1-p_delta_g)*AA32*(1-p_eps_g*$E33)+INDEX(Calib!$E$1:$E$13,$D33)*(INDEX(Calib!$G$1:$G$13,$D33)+p_programme*$H33) | AB33: =AB32*(1-p_eps_k*$E33)+p_lambda_k*(AD33-AB32*(1-p_eps_k*$E33)) | AC33: =INDEX(Calib!$R$1:$R$13,$D33)*$F33*(AA32*(1-p_eps_g*$E33))^INDEX(Calib!$Q$1:$Q$13,$D33)*(AB32*(1-p_eps_k*$E33))^p_alpha | AD33: =p_alpha*(1-INDEX(Calib!$H$1:$H$13,$D33))*AC33/(INDEX(Calib!$K$1:$K$13,$D33)+p_delta) | AE33: =AC33+$G33 | AF33: =p_programme*($H33+$I33) | AG33: =INDEX(Calib!$I$1:$I$13,$D33)+p_sh_grant*AF33 | AH33: =INDEX(Calib!$H$1:$H$13,$D33)*AC33+p_gov_take*$G33+AG33+p_programme*p_pricing*$J33 | AI33: =INDEX(Calib!$Y$1:$Y$13,$D33)-INDEX(Calib!$Z$1:$Z$13,$D33)*(AL32/AE32-INDEX(Calib!$AA$1:$AA$13,$D33)) | AJ33: =INDEX(Calib!$X$1:$X$13,$D33)+INDEX(Calib!$G$1:$G$13,$D33)+AF33+AI33-AH33 | AK33: =p_rk*AM32+AO32*(AL32-AM32) | AL33: =AL32+AK33+AJ33 | AM33: =INDEX(Calib!$U$1:$U$13,$D33)+(AM32-INDEX(Calib!$U$1:$U$13,$D33))*(1-p_amort)+p_sh_conc*AF33 | AN33: =AL33/AE33 | AO33: =INDEX(Calib!$K$1:$K$13,$D33)+p_eta*MAX(0,AN33-INDEX(Calib!$AA$1:$AA$13,$D33)) | AP33: =(1-INDEX(Calib!$H$1:$H$13,$D33))*(1-p_alpha)*AC33+AI33 | AQ33: =(AE33/O33-1)*100 | AR33: =(AE33/AE29-1)*100 | AS33: =(O33/O29-1)*100 | AT33: =(AN33-X33)*100 | AU33: =(AP33/Z33-1)*100 | AV33: =(AI33-S33)*100
A34: SLE | B34: 2029 | C34: 5 | D34: 3 | E34: =IF(AND(p_dis_year>0,B34=p_dis_year),1,0) | F34: =IF(AND(p_dis_year>0,B34>=p_dis_year),1-p_eps_a*p_rho_a^(B34-p_dis_year),1) | G34: =INDEX(Calib!$N$1:$N$13,$D34)*(1-p_rent_decline*MIN(1,C34/26)) | H34: =IF(C34=0,0,SUMIFS(dl_val,dl_iso,$A34,dl_ind,"pub_cap",dl_year,$B34)/100) | I34: =IF(C34=0,0,SUMIFS(dl_val,dl_iso,$A34,dl_ind,"pub_spend",dl_year,$B34)/100) | J34: =IF(C34=0,0,SUMIFS(dl_val,dl_iso,$A34,dl_ind,"rev",dl_year,$B34)/100) | K34: =(1-p_delta_g)*K33*(1-p_eps_g*$E34)+INDEX(Calib!$E$1:$E$13,$D34)*(INDEX(Calib!$G$1:$G$13,$D34)+0*$H34) | L34: =L33*(1-p_eps_k*$E34)+p_lambda_k*(N34-L33*(1-p_eps_k*$E34)) | M34: =INDEX(Calib!$R$1:$R$13,$D34)*$F34*(K33*(1-p_eps_g*$E34))^INDEX(Calib!$Q$1:$Q$13,$D34)*(L33*(1-p_eps_k*$E34))^p_alpha | N34: =p_alpha*(1-INDEX(Calib!$H$1:$H$13,$D34))*M34/(INDEX(Calib!$K$1:$K$13,$D34)+p_delta) | O34: =M34+$G34 | P34: =0*($H34+$I34) | Q34: =INDEX(Calib!$I$1:$I$13,$D34)+p_sh_grant*P34 | R34: =INDEX(Calib!$H$1:$H$13,$D34)*M34+p_gov_take*$G34+Q34+0*p_pricing*$J34 | S34: =INDEX(Calib!$Y$1:$Y$13,$D34)-INDEX(Calib!$Z$1:$Z$13,$D34)*(V33/O33-INDEX(Calib!$AA$1:$AA$13,$D34)) | T34: =INDEX(Calib!$X$1:$X$13,$D34)+INDEX(Calib!$G$1:$G$13,$D34)+P34+S34-R34 | U34: =p_rk*W33+Y33*(V33-W33) | V34: =V33+U34+T34 | W34: =INDEX(Calib!$U$1:$U$13,$D34)+(W33-INDEX(Calib!$U$1:$U$13,$D34))*(1-p_amort)+p_sh_conc*P34 | X34: =V34/O34 | Y34: =INDEX(Calib!$K$1:$K$13,$D34)+p_eta*MAX(0,X34-INDEX(Calib!$AA$1:$AA$13,$D34)) | Z34: =(1-INDEX(Calib!$H$1:$H$13,$D34))*(1-p_alpha)*M34+S34 | AA34: =(1-p_delta_g)*AA33*(1-p_eps_g*$E34)+INDEX(Calib!$E$1:$E$13,$D34)*(INDEX(Calib!$G$1:$G$13,$D34)+p_programme*$H34) | AB34: =AB33*(1-p_eps_k*$E34)+p_lambda_k*(AD34-AB33*(1-p_eps_k*$E34)) | AC34: =INDEX(Calib!$R$1:$R$13,$D34)*$F34*(AA33*(1-p_eps_g*$E34))^INDEX(Calib!$Q$1:$Q$13,$D34)*(AB33*(1-p_eps_k*$E34))^p_alpha | AD34: =p_alpha*(1-INDEX(Calib!$H$1:$H$13,$D34))*AC34/(INDEX(Calib!$K$1:$K$13,$D34)+p_delta) | AE34: =AC34+$G34 | AF34: =p_programme*($H34+$I34) | AG34: =INDEX(Calib!$I$1:$I$13,$D34)+p_sh_grant*AF34 | AH34: =INDEX(Calib!$H$1:$H$13,$D34)*AC34+p_gov_take*$G34+AG34+p_programme*p_pricing*$J34 | AI34: =INDEX(Calib!$Y$1:$Y$13,$D34)-INDEX(Calib!$Z$1:$Z$13,$D34)*(AL33/AE33-INDEX(Calib!$AA$1:$AA$13,$D34)) | AJ34: =INDEX(Calib!$X$1:$X$13,$D34)+INDEX(Calib!$G$1:$G$13,$D34)+AF34+AI34-AH34 | AK34: =p_rk*AM33+AO33*(AL33-AM33) | AL34: =AL33+AK34+AJ34 | AM34: =INDEX(Calib!$U$1:$U$13,$D34)+(AM33-INDEX(Calib!$U$1:$U$13,$D34))*(1-p_amort)+p_sh_conc*AF34 | AN34: =AL34/AE34 | AO34: =INDEX(Calib!$K$1:$K$13,$D34)+p_eta*MAX(0,AN34-INDEX(Calib!$AA$1:$AA$13,$D34)) | AP34: =(1-INDEX(Calib!$H$1:$H$13,$D34))*(1-p_alpha)*AC34+AI34 | AQ34: =(AE34/O34-1)*100 | AR34: =(AE34/AE29-1)*100 | AS34: =(O34/O29-1)*100 | AT34: =(AN34-X34)*100 | AU34: =(AP34/Z34-1)*100 | AV34: =(AI34-S34)*100
A35: SLE | B35: 2030 | C35: 6 | D35: 3 | E35: =IF(AND(p_dis_year>0,B35=p_dis_year),1,0) | F35: =IF(AND(p_dis_year>0,B35>=p_dis_year),1-p_eps_a*p_rho_a^(B35-p_dis_year),1) | G35: =INDEX(Calib!$N$1:$N$13,$D35)*(1-p_rent_decline*MIN(1,C35/26)) | H35: =IF(C35=0,0,SUMIFS(dl_val,dl_iso,$A35,dl_ind,"pub_cap",dl_year,$B35)/100) | I35: =IF(C35=0,0,SUMIFS(dl_val,dl_iso,$A35,dl_ind,"pub_spend",dl_year,$B35)/100) | J35: =IF(C35=0,0,SUMIFS(dl_val,dl_iso,$A35,dl_ind,"rev",dl_year,$B35)/100) | K35: =(1-p_delta_g)*K34*(1-p_eps_g*$E35)+INDEX(Calib!$E$1:$E$13,$D35)*(INDEX(Calib!$G$1:$G$13,$D35)+0*$H35) | L35: =L34*(1-p_eps_k*$E35)+p_lambda_k*(N35-L34*(1-p_eps_k*$E35)) | M35: =INDEX(Calib!$R$1:$R$13,$D35)*$F35*(K34*(1-p_eps_g*$E35))^INDEX(Calib!$Q$1:$Q$13,$D35)*(L34*(1-p_eps_k*$E35))^p_alpha | N35: =p_alpha*(1-INDEX(Calib!$H$1:$H$13,$D35))*M35/(INDEX(Calib!$K$1:$K$13,$D35)+p_delta) | O35: =M35+$G35 | P35: =0*($H35+$I35) | Q35: =INDEX(Calib!$I$1:$I$13,$D35)+p_sh_grant*P35 | R35: =INDEX(Calib!$H$1:$H$13,$D35)*M35+p_gov_take*$G35+Q35+0*p_pricing*$J35 | S35: =INDEX(Calib!$Y$1:$Y$13,$D35)-INDEX(Calib!$Z$1:$Z$13,$D35)*(V34/O34-INDEX(Calib!$AA$1:$AA$13,$D35)) | T35: =INDEX(Calib!$X$1:$X$13,$D35)+INDEX(Calib!$G$1:$G$13,$D35)+P35+S35-R35 | U35: =p_rk*W34+Y34*(V34-W34) | V35: =V34+U35+T35 | W35: =INDEX(Calib!$U$1:$U$13,$D35)+(W34-INDEX(Calib!$U$1:$U$13,$D35))*(1-p_amort)+p_sh_conc*P35 | X35: =V35/O35 | Y35: =INDEX(Calib!$K$1:$K$13,$D35)+p_eta*MAX(0,X35-INDEX(Calib!$AA$1:$AA$13,$D35)) | Z35: =(1-INDEX(Calib!$H$1:$H$13,$D35))*(1-p_alpha)*M35+S35 | AA35: =(1-p_delta_g)*AA34*(1-p_eps_g*$E35)+INDEX(Calib!$E$1:$E$13,$D35)*(INDEX(Calib!$G$1:$G$13,$D35)+p_programme*$H35) | AB35: =AB34*(1-p_eps_k*$E35)+p_lambda_k*(AD35-AB34*(1-p_eps_k*$E35)) | AC35: =INDEX(Calib!$R$1:$R$13,$D35)*$F35*(AA34*(1-p_eps_g*$E35))^INDEX(Calib!$Q$1:$Q$13,$D35)*(AB34*(1-p_eps_k*$E35))^p_alpha | AD35: =p_alpha*(1-INDEX(Calib!$H$1:$H$13,$D35))*AC35/(INDEX(Calib!$K$1:$K$13,$D35)+p_delta) | AE35: =AC35+$G35 | AF35: =p_programme*($H35+$I35) | AG35: =INDEX(Calib!$I$1:$I$13,$D35)+p_sh_grant*AF35 | AH35: =INDEX(Calib!$H$1:$H$13,$D35)*AC35+p_gov_take*$G35+AG35+p_programme*p_pricing*$J35 | AI35: =INDEX(Calib!$Y$1:$Y$13,$D35)-INDEX(Calib!$Z$1:$Z$13,$D35)*(AL34/AE34-INDEX(Calib!$AA$1:$AA$13,$D35)) | AJ35: =INDEX(Calib!$X$1:$X$13,$D35)+INDEX(Calib!$G$1:$G$13,$D35)+AF35+AI35-AH35 | AK35: =p_rk*AM34+AO34*(AL34-AM34) | AL35: =AL34+AK35+AJ35 | AM35: =INDEX(Calib!$U$1:$U$13,$D35)+(AM34-INDEX(Calib!$U$1:$U$13,$D35))*(1-p_amort)+p_sh_conc*AF35 | AN35: =AL35/AE35 | AO35: =INDEX(Calib!$K$1:$K$13,$D35)+p_eta*MAX(0,AN35-INDEX(Calib!$AA$1:$AA$13,$D35)) | AP35: =(1-INDEX(Calib!$H$1:$H$13,$D35))*(1-p_alpha)*AC35+AI35 | AQ35: =(AE35/O35-1)*100 | AR35: =(AE35/AE29-1)*100 | AS35: =(O35/O29-1)*100 | AT35: =(AN35-X35)*100 | AU35: =(AP35/Z35-1)*100 | AV35: =(AI35-S35)*100
A36: SLE | B36: 2031 | C36: 7 | D36: 3 | E36: =IF(AND(p_dis_year>0,B36=p_dis_year),1,0) | F36: =IF(AND(p_dis_year>0,B36>=p_dis_year),1-p_eps_a*p_rho_a^(B36-p_dis_year),1) | G36: =INDEX(Calib!$N$1:$N$13,$D36)*(1-p_rent_decline*MIN(1,C36/26)) | H36: =IF(C36=0,0,SUMIFS(dl_val,dl_iso,$A36,dl_ind,"pub_cap",dl_year,$B36)/100) | I36: =IF(C36=0,0,SUMIFS(dl_val,dl_iso,$A36,dl_ind,"pub_spend",dl_year,$B36)/100) | J36: =IF(C36=0,0,SUMIFS(dl_val,dl_iso,$A36,dl_ind,"rev",dl_year,$B36)/100) | K36: =(1-p_delta_g)*K35*(1-p_eps_g*$E36)+INDEX(Calib!$E$1:$E$13,$D36)*(INDEX(Calib!$G$1:$G$13,$D36)+0*$H36) | L36: =L35*(1-p_eps_k*$E36)+p_lambda_k*(N36-L35*(1-p_eps_k*$E36)) | M36: =INDEX(Calib!$R$1:$R$13,$D36)*$F36*(K35*(1-p_eps_g*$E36))^INDEX(Calib!$Q$1:$Q$13,$D36)*(L35*(1-p_eps_k*$E36))^p_alpha | N36: =p_alpha*(1-INDEX(Calib!$H$1:$H$13,$D36))*M36/(INDEX(Calib!$K$1:$K$13,$D36)+p_delta) | O36: =M36+$G36 | P36: =0*($H36+$I36) | Q36: =INDEX(Calib!$I$1:$I$13,$D36)+p_sh_grant*P36 | R36: =INDEX(Calib!$H$1:$H$13,$D36)*M36+p_gov_take*$G36+Q36+0*p_pricing*$J36 | S36: =INDEX(Calib!$Y$1:$Y$13,$D36)-INDEX(Calib!$Z$1:$Z$13,$D36)*(V35/O35-INDEX(Calib!$AA$1:$AA$13,$D36)) | T36: =INDEX(Calib!$X$1:$X$13,$D36)+INDEX(Calib!$G$1:$G$13,$D36)+P36+S36-R36 | U36: =p_rk*W35+Y35*(V35-W35) | V36: =V35+U36+T36 | W36: =INDEX(Calib!$U$1:$U$13,$D36)+(W35-INDEX(Calib!$U$1:$U$13,$D36))*(1-p_amort)+p_sh_conc*P36 | X36: =V36/O36 | Y36: =INDEX(Calib!$K$1:$K$13,$D36)+p_eta*MAX(0,X36-INDEX(Calib!$AA$1:$AA$13,$D36)) | Z36: =(1-INDEX(Calib!$H$1:$H$13,$D36))*(1-p_alpha)*M36+S36 | AA36: =(1-p_delta_g)*AA35*(1-p_eps_g*$E36)+INDEX(Calib!$E$1:$E$13,$D36)*(INDEX(Calib!$G$1:$G$13,$D36)+p_programme*$H36) | AB36: =AB35*(1-p_eps_k*$E36)+p_lambda_k*(AD36-AB35*(1-p_eps_k*$E36)) | AC36: =INDEX(Calib!$R$1:$R$13,$D36)*$F36*(AA35*(1-p_eps_g*$E36))^INDEX(Calib!$Q$1:$Q$13,$D36)*(AB35*(1-p_eps_k*$E36))^p_alpha | AD36: =p_alpha*(1-INDEX(Calib!$H$1:$H$13,$D36))*AC36/(INDEX(Calib!$K$1:$K$13,$D36)+p_delta) | AE36: =AC36+$G36 | AF36: =p_programme*($H36+$I36) | AG36: =INDEX(Calib!$I$1:$I$13,$D36)+p_sh_grant*AF36 | AH36: =INDEX(Calib!$H$1:$H$13,$D36)*AC36+p_gov_take*$G36+AG36+p_programme*p_pricing*$J36 | AI36: =INDEX(Calib!$Y$1:$Y$13,$D36)-INDEX(Calib!$Z$1:$Z$13,$D36)*(AL35/AE35-INDEX(Calib!$AA$1:$AA$13,$D36)) | AJ36: =INDEX(Calib!$X$1:$X$13,$D36)+INDEX(Calib!$G$1:$G$13,$D36)+AF36+AI36-AH36 | AK36: =p_rk*AM35+AO35*(AL35-AM35) | AL36: =AL35+AK36+AJ36 | AM36: =INDEX(Calib!$U$1:$U$13,$D36)+(AM35-INDEX(Calib!$U$1:$U$13,$D36))*(1-p_amort)+p_sh_conc*AF36 | AN36: =AL36/AE36 | AO36: =INDEX(Calib!$K$1:$K$13,$D36)+p_eta*MAX(0,AN36-INDEX(Calib!$AA$1:$AA$13,$D36)) | AP36: =(1-INDEX(Calib!$H$1:$H$13,$D36))*(1-p_alpha)*AC36+AI36 | AQ36: =(AE36/O36-1)*100 | AR36: =(AE36/AE29-1)*100 | AS36: =(O36/O29-1)*100 | AT36: =(AN36-X36)*100 | AU36: =(AP36/Z36-1)*100 | AV36: =(AI36-S36)*100
A37: SLE | B37: 2032 | C37: 8 | D37: 3 | E37: =IF(AND(p_dis_year>0,B37=p_dis_year),1,0) | F37: =IF(AND(p_dis_year>0,B37>=p_dis_year),1-p_eps_a*p_rho_a^(B37-p_dis_year),1) | G37: =INDEX(Calib!$N$1:$N$13,$D37)*(1-p_rent_decline*MIN(1,C37/26)) | H37: =IF(C37=0,0,SUMIFS(dl_val,dl_iso,$A37,dl_ind,"pub_cap",dl_year,$B37)/100) | I37: =IF(C37=0,0,SUMIFS(dl_val,dl_iso,$A37,dl_ind,"pub_spend",dl_year,$B37)/100) | J37: =IF(C37=0,0,SUMIFS(dl_val,dl_iso,$A37,dl_ind,"rev",dl_year,$B37)/100) | K37: =(1-p_delta_g)*K36*(1-p_eps_g*$E37)+INDEX(Calib!$E$1:$E$13,$D37)*(INDEX(Calib!$G$1:$G$13,$D37)+0*$H37) | L37: =L36*(1-p_eps_k*$E37)+p_lambda_k*(N37-L36*(1-p_eps_k*$E37)) | M37: =INDEX(Calib!$R$1:$R$13,$D37)*$F37*(K36*(1-p_eps_g*$E37))^INDEX(Calib!$Q$1:$Q$13,$D37)*(L36*(1-p_eps_k*$E37))^p_alpha | N37: =p_alpha*(1-INDEX(Calib!$H$1:$H$13,$D37))*M37/(INDEX(Calib!$K$1:$K$13,$D37)+p_delta) | O37: =M37+$G37 | P37: =0*($H37+$I37) | Q37: =INDEX(Calib!$I$1:$I$13,$D37)+p_sh_grant*P37 | R37: =INDEX(Calib!$H$1:$H$13,$D37)*M37+p_gov_take*$G37+Q37+0*p_pricing*$J37 | S37: =INDEX(Calib!$Y$1:$Y$13,$D37)-INDEX(Calib!$Z$1:$Z$13,$D37)*(V36/O36-INDEX(Calib!$AA$1:$AA$13,$D37)) | T37: =INDEX(Calib!$X$1:$X$13,$D37)+INDEX(Calib!$G$1:$G$13,$D37)+P37+S37-R37 | U37: =p_rk*W36+Y36*(V36-W36) | V37: =V36+U37+T37 | W37: =INDEX(Calib!$U$1:$U$13,$D37)+(W36-INDEX(Calib!$U$1:$U$13,$D37))*(1-p_amort)+p_sh_conc*P37 | X37: =V37/O37 | Y37: =INDEX(Calib!$K$1:$K$13,$D37)+p_eta*MAX(0,X37-INDEX(Calib!$AA$1:$AA$13,$D37)) | Z37: =(1-INDEX(Calib!$H$1:$H$13,$D37))*(1-p_alpha)*M37+S37 | AA37: =(1-p_delta_g)*AA36*(1-p_eps_g*$E37)+INDEX(Calib!$E$1:$E$13,$D37)*(INDEX(Calib!$G$1:$G$13,$D37)+p_programme*$H37) | AB37: =AB36*(1-p_eps_k*$E37)+p_lambda_k*(AD37-AB36*(1-p_eps_k*$E37)) | AC37: =INDEX(Calib!$R$1:$R$13,$D37)*$F37*(AA36*(1-p_eps_g*$E37))^INDEX(Calib!$Q$1:$Q$13,$D37)*(AB36*(1-p_eps_k*$E37))^p_alpha | AD37: =p_alpha*(1-INDEX(Calib!$H$1:$H$13,$D37))*AC37/(INDEX(Calib!$K$1:$K$13,$D37)+p_delta) | AE37: =AC37+$G37 | AF37: =p_programme*($H37+$I37) | AG37: =INDEX(Calib!$I$1:$I$13,$D37)+p_sh_grant*AF37 | AH37: =INDEX(Calib!$H$1:$H$13,$D37)*AC37+p_gov_take*$G37+AG37+p_programme*p_pricing*$J37 | AI37: =INDEX(Calib!$Y$1:$Y$13,$D37)-INDEX(Calib!$Z$1:$Z$13,$D37)*(AL36/AE36-INDEX(Calib!$AA$1:$AA$13,$D37)) | AJ37: =INDEX(Calib!$X$1:$X$13,$D37)+INDEX(Calib!$G$1:$G$13,$D37)+AF37+AI37-AH37 | AK37: =p_rk*AM36+AO36*(AL36-AM36) | AL37: =AL36+AK37+AJ37 | AM37: =INDEX(Calib!$U$1:$U$13,$D37)+(AM36-INDEX(Calib!$U$1:$U$13,$D37))*(1-p_amort)+p_sh_conc*AF37 | AN37: =AL37/AE37 | AO37: =INDEX(Calib!$K$1:$K$13,$D37)+p_eta*MAX(0,AN37-INDEX(Calib!$AA$1:$AA$13,$D37)) | AP37: =(1-INDEX(Calib!$H$1:$H$13,$D37))*(1-p_alpha)*AC37+AI37 | AQ37: =(AE37/O37-1)*100 | AR37: =(AE37/AE29-1)*100 | AS37: =(O37/O29-1)*100 | AT37: =(AN37-X37)*100 | AU37: =(AP37/Z37-1)*100 | AV37: =(AI37-S37)*100
A38: SLE | B38: 2033 | C38: 9 | D38: 3 | E38: =IF(AND(p_dis_year>0,B38=p_dis_year),1,0) | F38: =IF(AND(p_dis_year>0,B38>=p_dis_year),1-p_eps_a*p_rho_a^(B38-p_dis_year),1) | G38: =INDEX(Calib!$N$1:$N$13,$D38)*(1-p_rent_decline*MIN(1,C38/26)) | H38: =IF(C38=0,0,SUMIFS(dl_val,dl_iso,$A38,dl_ind,"pub_cap",dl_year,$B38)/100) | I38: =IF(C38=0,0,SUMIFS(dl_val,dl_iso,$A38,dl_ind,"pub_spend",dl_year,$B38)/100) | J38: =IF(C38=0,0,SUMIFS(dl_val,dl_iso,$A38,dl_ind,"rev",dl_year,$B38)/100) | K38: =(1-p_delta_g)*K37*(1-p_eps_g*$E38)+INDEX(Calib!$E$1:$E$13,$D38)*(INDEX(Calib!$G$1:$G$13,$D38)+0*$H38) | L38: =L37*(1-p_eps_k*$E38)+p_lambda_k*(N38-L37*(1-p_eps_k*$E38)) | M38: =INDEX(Calib!$R$1:$R$13,$D38)*$F38*(K37*(1-p_eps_g*$E38))^INDEX(Calib!$Q$1:$Q$13,$D38)*(L37*(1-p_eps_k*$E38))^p_alpha | N38: =p_alpha*(1-INDEX(Calib!$H$1:$H$13,$D38))*M38/(INDEX(Calib!$K$1:$K$13,$D38)+p_delta) | O38: =M38+$G38 | P38: =0*($H38+$I38) | Q38: =INDEX(Calib!$I$1:$I$13,$D38)+p_sh_grant*P38 | R38: =INDEX(Calib!$H$1:$H$13,$D38)*M38+p_gov_take*$G38+Q38+0*p_pricing*$J38 | S38: =INDEX(Calib!$Y$1:$Y$13,$D38)-INDEX(Calib!$Z$1:$Z$13,$D38)*(V37/O37-INDEX(Calib!$AA$1:$AA$13,$D38)) | T38: =INDEX(Calib!$X$1:$X$13,$D38)+INDEX(Calib!$G$1:$G$13,$D38)+P38+S38-R38 | U38: =p_rk*W37+Y37*(V37-W37) | V38: =V37+U38+T38 | W38: =INDEX(Calib!$U$1:$U$13,$D38)+(W37-INDEX(Calib!$U$1:$U$13,$D38))*(1-p_amort)+p_sh_conc*P38 | X38: =V38/O38 | Y38: =INDEX(Calib!$K$1:$K$13,$D38)+p_eta*MAX(0,X38-INDEX(Calib!$AA$1:$AA$13,$D38)) | Z38: =(1-INDEX(Calib!$H$1:$H$13,$D38))*(1-p_alpha)*M38+S38 | AA38: =(1-p_delta_g)*AA37*(1-p_eps_g*$E38)+INDEX(Calib!$E$1:$E$13,$D38)*(INDEX(Calib!$G$1:$G$13,$D38)+p_programme*$H38) | AB38: =AB37*(1-p_eps_k*$E38)+p_lambda_k*(AD38-AB37*(1-p_eps_k*$E38)) | AC38: =INDEX(Calib!$R$1:$R$13,$D38)*$F38*(AA37*(1-p_eps_g*$E38))^INDEX(Calib!$Q$1:$Q$13,$D38)*(AB37*(1-p_eps_k*$E38))^p_alpha | AD38: =p_alpha*(1-INDEX(Calib!$H$1:$H$13,$D38))*AC38/(INDEX(Calib!$K$1:$K$13,$D38)+p_delta) | AE38: =AC38+$G38 | AF38: =p_programme*($H38+$I38) | AG38: =INDEX(Calib!$I$1:$I$13,$D38)+p_sh_grant*AF38 | AH38: =INDEX(Calib!$H$1:$H$13,$D38)*AC38+p_gov_take*$G38+AG38+p_programme*p_pricing*$J38 | AI38: =INDEX(Calib!$Y$1:$Y$13,$D38)-INDEX(Calib!$Z$1:$Z$13,$D38)*(AL37/AE37-INDEX(Calib!$AA$1:$AA$13,$D38)) | AJ38: =INDEX(Calib!$X$1:$X$13,$D38)+INDEX(Calib!$G$1:$G$13,$D38)+AF38+AI38-AH38 | AK38: =p_rk*AM37+AO37*(AL37-AM37) | AL38: =AL37+AK38+AJ38 | AM38: =INDEX(Calib!$U$1:$U$13,$D38)+(AM37-INDEX(Calib!$U$1:$U$13,$D38))*(1-p_amort)+p_sh_conc*AF38 | AN38: =AL38/AE38 | AO38: =INDEX(Calib!$K$1:$K$13,$D38)+p_eta*MAX(0,AN38-INDEX(Calib!$AA$1:$AA$13,$D38)) | AP38: =(1-INDEX(Calib!$H$1:$H$13,$D38))*(1-p_alpha)*AC38+AI38 | AQ38: =(AE38/O38-1)*100 | AR38: =(AE38/AE29-1)*100 | AS38: =(O38/O29-1)*100 | AT38: =(AN38-X38)*100 | AU38: =(AP38/Z38-1)*100 | AV38: =(AI38-S38)*100
A39: SLE | B39: 2034 | C39: 10 | D39: 3 | E39: =IF(AND(p_dis_year>0,B39=p_dis_year),1,0) | F39: =IF(AND(p_dis_year>0,B39>=p_dis_year),1-p_eps_a*p_rho_a^(B39-p_dis_year),1) | G39: =INDEX(Calib!$N$1:$N$13,$D39)*(1-p_rent_decline*MIN(1,C39/26)) | H39: =IF(C39=0,0,SUMIFS(dl_val,dl_iso,$A39,dl_ind,"pub_cap",dl_year,$B39)/100) | I39: =IF(C39=0,0,SUMIFS(dl_val,dl_iso,$A39,dl_ind,"pub_spend",dl_year,$B39)/100) | J39: =IF(C39=0,0,SUMIFS(dl_val,dl_iso,$A39,dl_ind,"rev",dl_year,$B39)/100) | K39: =(1-p_delta_g)*K38*(1-p_eps_g*$E39)+INDEX(Calib!$E$1:$E$13,$D39)*(INDEX(Calib!$G$1:$G$13,$D39)+0*$H39) | L39: =L38*(1-p_eps_k*$E39)+p_lambda_k*(N39-L38*(1-p_eps_k*$E39)) | M39: =INDEX(Calib!$R$1:$R$13,$D39)*$F39*(K38*(1-p_eps_g*$E39))^INDEX(Calib!$Q$1:$Q$13,$D39)*(L38*(1-p_eps_k*$E39))^p_alpha | N39: =p_alpha*(1-INDEX(Calib!$H$1:$H$13,$D39))*M39/(INDEX(Calib!$K$1:$K$13,$D39)+p_delta) | O39: =M39+$G39 | P39: =0*($H39+$I39) | Q39: =INDEX(Calib!$I$1:$I$13,$D39)+p_sh_grant*P39 | R39: =INDEX(Calib!$H$1:$H$13,$D39)*M39+p_gov_take*$G39+Q39+0*p_pricing*$J39 | S39: =INDEX(Calib!$Y$1:$Y$13,$D39)-INDEX(Calib!$Z$1:$Z$13,$D39)*(V38/O38-INDEX(Calib!$AA$1:$AA$13,$D39)) | T39: =INDEX(Calib!$X$1:$X$13,$D39)+INDEX(Calib!$G$1:$G$13,$D39)+P39+S39-R39 | U39: =p_rk*W38+Y38*(V38-W38) | V39: =V38+U39+T39 | W39: =INDEX(Calib!$U$1:$U$13,$D39)+(W38-INDEX(Calib!$U$1:$U$13,$D39))*(1-p_amort)+p_sh_conc*P39 | X39: =V39/O39 | Y39: =INDEX(Calib!$K$1:$K$13,$D39)+p_eta*MAX(0,X39-INDEX(Calib!$AA$1:$AA$13,$D39)) | Z39: =(1-INDEX(Calib!$H$1:$H$13,$D39))*(1-p_alpha)*M39+S39 | AA39: =(1-p_delta_g)*AA38*(1-p_eps_g*$E39)+INDEX(Calib!$E$1:$E$13,$D39)*(INDEX(Calib!$G$1:$G$13,$D39)+p_programme*$H39) | AB39: =AB38*(1-p_eps_k*$E39)+p_lambda_k*(AD39-AB38*(1-p_eps_k*$E39)) | AC39: =INDEX(Calib!$R$1:$R$13,$D39)*$F39*(AA38*(1-p_eps_g*$E39))^INDEX(Calib!$Q$1:$Q$13,$D39)*(AB38*(1-p_eps_k*$E39))^p_alpha | AD39: =p_alpha*(1-INDEX(Calib!$H$1:$H$13,$D39))*AC39/(INDEX(Calib!$K$1:$K$13,$D39)+p_delta) | AE39: =AC39+$G39 | AF39: =p_programme*($H39+$I39) | AG39: =INDEX(Calib!$I$1:$I$13,$D39)+p_sh_grant*AF39 | AH39: =INDEX(Calib!$H$1:$H$13,$D39)*AC39+p_gov_take*$G39+AG39+p_programme*p_pricing*$J39 | AI39: =INDEX(Calib!$Y$1:$Y$13,$D39)-INDEX(Calib!$Z$1:$Z$13,$D39)*(AL38/AE38-INDEX(Calib!$AA$1:$AA$13,$D39)) | AJ39: =INDEX(Calib!$X$1:$X$13,$D39)+INDEX(Calib!$G$1:$G$13,$D39)+AF39+AI39-AH39 | AK39: =p_rk*AM38+AO38*(AL38-AM38) | AL39: =AL38+AK39+AJ39 | AM39: =INDEX(Calib!$U$1:$U$13,$D39)+(AM38-INDEX(Calib!$U$1:$U$13,$D39))*(1-p_amort)+p_sh_conc*AF39 | AN39: =AL39/AE39 | AO39: =INDEX(Calib!$K$1:$K$13,$D39)+p_eta*MAX(0,AN39-INDEX(Calib!$AA$1:$AA$13,$D39)) | AP39: =(1-INDEX(Calib!$H$1:$H$13,$D39))*(1-p_alpha)*AC39+AI39 | AQ39: =(AE39/O39-1)*100 | AR39: =(AE39/AE29-1)*100 | AS39: =(O39/O29-1)*100 | AT39: =(AN39-X39)*100 | AU39: =(AP39/Z39-1)*100 | AV39: =(AI39-S39)*100
A40: SLE | B40: 2035 | C40: 11 | D40: 3 | E40: =IF(AND(p_dis_year>0,B40=p_dis_year),1,0) | F40: =IF(AND(p_dis_year>0,B40>=p_dis_year),1-p_eps_a*p_rho_a^(B40-p_dis_year),1) | G40: =INDEX(Calib!$N$1:$N$13,$D40)*(1-p_rent_decline*MIN(1,C40/26)) | H40: =IF(C40=0,0,SUMIFS(dl_val,dl_iso,$A40,dl_ind,"pub_cap",dl_year,$B40)/100) | I40: =IF(C40=0,0,SUMIFS(dl_val,dl_iso,$A40,dl_ind,"pub_spend",dl_year,$B40)/100) | J40: =IF(C40=0,0,SUMIFS(dl_val,dl_iso,$A40,dl_ind,"rev",dl_year,$B40)/100) | K40: =(1-p_delta_g)*K39*(1-p_eps_g*$E40)+INDEX(Calib!$E$1:$E$13,$D40)*(INDEX(Calib!$G$1:$G$13,$D40)+0*$H40) | L40: =L39*(1-p_eps_k*$E40)+p_lambda_k*(N40-L39*(1-p_eps_k*$E40)) | M40: =INDEX(Calib!$R$1:$R$13,$D40)*$F40*(K39*(1-p_eps_g*$E40))^INDEX(Calib!$Q$1:$Q$13,$D40)*(L39*(1-p_eps_k*$E40))^p_alpha | N40: =p_alpha*(1-INDEX(Calib!$H$1:$H$13,$D40))*M40/(INDEX(Calib!$K$1:$K$13,$D40)+p_delta) | O40: =M40+$G40 | P40: =0*($H40+$I40) | Q40: =INDEX(Calib!$I$1:$I$13,$D40)+p_sh_grant*P40 | R40: =INDEX(Calib!$H$1:$H$13,$D40)*M40+p_gov_take*$G40+Q40+0*p_pricing*$J40 | S40: =INDEX(Calib!$Y$1:$Y$13,$D40)-INDEX(Calib!$Z$1:$Z$13,$D40)*(V39/O39-INDEX(Calib!$AA$1:$AA$13,$D40)) | T40: =INDEX(Calib!$X$1:$X$13,$D40)+INDEX(Calib!$G$1:$G$13,$D40)+P40+S40-R40 | U40: =p_rk*W39+Y39*(V39-W39) | V40: =V39+U40+T40 | W40: =INDEX(Calib!$U$1:$U$13,$D40)+(W39-INDEX(Calib!$U$1:$U$13,$D40))*(1-p_amort)+p_sh_conc*P40 | X40: =V40/O40 | Y40: =INDEX(Calib!$K$1:$K$13,$D40)+p_eta*MAX(0,X40-INDEX(Calib!$AA$1:$AA$13,$D40)) | Z40: =(1-INDEX(Calib!$H$1:$H$13,$D40))*(1-p_alpha)*M40+S40 | AA40: =(1-p_delta_g)*AA39*(1-p_eps_g*$E40)+INDEX(Calib!$E$1:$E$13,$D40)*(INDEX(Calib!$G$1:$G$13,$D40)+p_programme*$H40) | AB40: =AB39*(1-p_eps_k*$E40)+p_lambda_k*(AD40-AB39*(1-p_eps_k*$E40)) | AC40: =INDEX(Calib!$R$1:$R$13,$D40)*$F40*(AA39*(1-p_eps_g*$E40))^INDEX(Calib!$Q$1:$Q$13,$D40)*(AB39*(1-p_eps_k*$E40))^p_alpha | AD40: =p_alpha*(1-INDEX(Calib!$H$1:$H$13,$D40))*AC40/(INDEX(Calib!$K$1:$K$13,$D40)+p_delta) | AE40: =AC40+$G40 | AF40: =p_programme*($H40+$I40) | AG40: =INDEX(Calib!$I$1:$I$13,$D40)+p_sh_grant*AF40 | AH40: =INDEX(Calib!$H$1:$H$13,$D40)*AC40+p_gov_take*$G40+AG40+p_programme*p_pricing*$J40 | AI40: =INDEX(Calib!$Y$1:$Y$13,$D40)-INDEX(Calib!$Z$1:$Z$13,$D40)*(AL39/AE39-INDEX(Calib!$AA$1:$AA$13,$D40)) | AJ40: =INDEX(Calib!$X$1:$X$13,$D40)+INDEX(Calib!$G$1:$G$13,$D40)+AF40+AI40-AH40 | AK40: =p_rk*AM39+AO39*(AL39-AM39) | AL40: =AL39+AK40+AJ40 | AM40: =INDEX(Calib!$U$1:$U$13,$D40)+(AM39-INDEX(Calib!$U$1:$U$13,$D40))*(1-p_amort)+p_sh_conc*AF40 | AN40: =AL40/AE40 | AO40: =INDEX(Calib!$K$1:$K$13,$D40)+p_eta*MAX(0,AN40-INDEX(Calib!$AA$1:$AA$13,$D40)) | AP40: =(1-INDEX(Calib!$H$1:$H$13,$D40))*(1-p_alpha)*AC40+AI40 | AQ40: =(AE40/O40-1)*100 | AR40: =(AE40/AE29-1)*100 | AS40: =(O40/O29-1)*100 | AT40: =(AN40-X40)*100 | AU40: =(AP40/Z40-1)*100 | AV40: =(AI40-S40)*100
A41: SLE | B41: 2036 | C41: 12 | D41: 3 | E41: =IF(AND(p_dis_year>0,B41=p_dis_year),1,0) | F41: =IF(AND(p_dis_year>0,B41>=p_dis_year),1-p_eps_a*p_rho_a^(B41-p_dis_year),1) | G41: =INDEX(Calib!$N$1:$N$13,$D41)*(1-p_rent_decline*MIN(1,C41/26)) | H41: =IF(C41=0,0,SUMIFS(dl_val,dl_iso,$A41,dl_ind,"pub_cap",dl_year,$B41)/100) | I41: =IF(C41=0,0,SUMIFS(dl_val,dl_iso,$A41,dl_ind,"pub_spend",dl_year,$B41)/100) | J41: =IF(C41=0,0,SUMIFS(dl_val,dl_iso,$A41,dl_ind,"rev",dl_year,$B41)/100) | K41: =(1-p_delta_g)*K40*(1-p_eps_g*$E41)+INDEX(Calib!$E$1:$E$13,$D41)*(INDEX(Calib!$G$1:$G$13,$D41)+0*$H41) | L41: =L40*(1-p_eps_k*$E41)+p_lambda_k*(N41-L40*(1-p_eps_k*$E41)) | M41: =INDEX(Calib!$R$1:$R$13,$D41)*$F41*(K40*(1-p_eps_g*$E41))^INDEX(Calib!$Q$1:$Q$13,$D41)*(L40*(1-p_eps_k*$E41))^p_alpha | N41: =p_alpha*(1-INDEX(Calib!$H$1:$H$13,$D41))*M41/(INDEX(Calib!$K$1:$K$13,$D41)+p_delta) | O41: =M41+$G41 | P41: =0*($H41+$I41) | Q41: =INDEX(Calib!$I$1:$I$13,$D41)+p_sh_grant*P41 | R41: =INDEX(Calib!$H$1:$H$13,$D41)*M41+p_gov_take*$G41+Q41+0*p_pricing*$J41 | S41: =INDEX(Calib!$Y$1:$Y$13,$D41)-INDEX(Calib!$Z$1:$Z$13,$D41)*(V40/O40-INDEX(Calib!$AA$1:$AA$13,$D41)) | T41: =INDEX(Calib!$X$1:$X$13,$D41)+INDEX(Calib!$G$1:$G$13,$D41)+P41+S41-R41 | U41: =p_rk*W40+Y40*(V40-W40) | V41: =V40+U41+T41 | W41: =INDEX(Calib!$U$1:$U$13,$D41)+(W40-INDEX(Calib!$U$1:$U$13,$D41))*(1-p_amort)+p_sh_conc*P41 | X41: =V41/O41 | Y41: =INDEX(Calib!$K$1:$K$13,$D41)+p_eta*MAX(0,X41-INDEX(Calib!$AA$1:$AA$13,$D41)) | Z41: =(1-INDEX(Calib!$H$1:$H$13,$D41))*(1-p_alpha)*M41+S41 | AA41: =(1-p_delta_g)*AA40*(1-p_eps_g*$E41)+INDEX(Calib!$E$1:$E$13,$D41)*(INDEX(Calib!$G$1:$G$13,$D41)+p_programme*$H41) | AB41: =AB40*(1-p_eps_k*$E41)+p_lambda_k*(AD41-AB40*(1-p_eps_k*$E41)) | AC41: =INDEX(Calib!$R$1:$R$13,$D41)*$F41*(AA40*(1-p_eps_g*$E41))^INDEX(Calib!$Q$1:$Q$13,$D41)*(AB40*(1-p_eps_k*$E41))^p_alpha | AD41: =p_alpha*(1-INDEX(Calib!$H$1:$H$13,$D41))*AC41/(INDEX(Calib!$K$1:$K$13,$D41)+p_delta) | AE41: =AC41+$G41 | AF41: =p_programme*($H41+$I41) | AG41: =INDEX(Calib!$I$1:$I$13,$D41)+p_sh_grant*AF41 | AH41: =INDEX(Calib!$H$1:$H$13,$D41)*AC41+p_gov_take*$G41+AG41+p_programme*p_pricing*$J41 | AI41: =INDEX(Calib!$Y$1:$Y$13,$D41)-INDEX(Calib!$Z$1:$Z$13,$D41)*(AL40/AE40-INDEX(Calib!$AA$1:$AA$13,$D41)) | AJ41: =INDEX(Calib!$X$1:$X$13,$D41)+INDEX(Calib!$G$1:$G$13,$D41)+AF41+AI41-AH41 | AK41: =p_rk*AM40+AO40*(AL40-AM40) | AL41: =AL40+AK41+AJ41 | AM41: =INDEX(Calib!$U$1:$U$13,$D41)+(AM40-INDEX(Calib!$U$1:$U$13,$D41))*(1-p_amort)+p_sh_conc*AF41 | AN41: =AL41/AE41 | AO41: =INDEX(Calib!$K$1:$K$13,$D41)+p_eta*MAX(0,AN41-INDEX(Calib!$AA$1:$AA$13,$D41)) | AP41: =(1-INDEX(Calib!$H$1:$H$13,$D41))*(1-p_alpha)*AC41+AI41 | AQ41: =(AE41/O41-1)*100 | AR41: =(AE41/AE29-1)*100 | AS41: =(O41/O29-1)*100 | AT41: =(AN41-X41)*100 | AU41: =(AP41/Z41-1)*100 | AV41: =(AI41-S41)*100
A42: SLE | B42: 2037 | C42: 13 | D42: 3 | E42: =IF(AND(p_dis_year>0,B42=p_dis_year),1,0) | F42: =IF(AND(p_dis_year>0,B42>=p_dis_year),1-p_eps_a*p_rho_a^(B42-p_dis_year),1) | G42: =INDEX(Calib!$N$1:$N$13,$D42)*(1-p_rent_decline*MIN(1,C42/26)) | H42: =IF(C42=0,0,SUMIFS(dl_val,dl_iso,$A42,dl_ind,"pub_cap",dl_year,$B42)/100) | I42: =IF(C42=0,0,SUMIFS(dl_val,dl_iso,$A42,dl_ind,"pub_spend",dl_year,$B42)/100) | J42: =IF(C42=0,0,SUMIFS(dl_val,dl_iso,$A42,dl_ind,"rev",dl_year,$B42)/100) | K42: =(1-p_delta_g)*K41*(1-p_eps_g*$E42)+INDEX(Calib!$E$1:$E$13,$D42)*(INDEX(Calib!$G$1:$G$13,$D42)+0*$H42) | L42: =L41*(1-p_eps_k*$E42)+p_lambda_k*(N42-L41*(1-p_eps_k*$E42)) | M42: =INDEX(Calib!$R$1:$R$13,$D42)*$F42*(K41*(1-p_eps_g*$E42))^INDEX(Calib!$Q$1:$Q$13,$D42)*(L41*(1-p_eps_k*$E42))^p_alpha | N42: =p_alpha*(1-INDEX(Calib!$H$1:$H$13,$D42))*M42/(INDEX(Calib!$K$1:$K$13,$D42)+p_delta) | O42: =M42+$G42 | P42: =0*($H42+$I42) | Q42: =INDEX(Calib!$I$1:$I$13,$D42)+p_sh_grant*P42 | R42: =INDEX(Calib!$H$1:$H$13,$D42)*M42+p_gov_take*$G42+Q42+0*p_pricing*$J42 | S42: =INDEX(Calib!$Y$1:$Y$13,$D42)-INDEX(Calib!$Z$1:$Z$13,$D42)*(V41/O41-INDEX(Calib!$AA$1:$AA$13,$D42)) | T42: =INDEX(Calib!$X$1:$X$13,$D42)+INDEX(Calib!$G$1:$G$13,$D42)+P42+S42-R42 | U42: =p_rk*W41+Y41*(V41-W41) | V42: =V41+U42+T42 | W42: =INDEX(Calib!$U$1:$U$13,$D42)+(W41-INDEX(Calib!$U$1:$U$13,$D42))*(1-p_amort)+p_sh_conc*P42 | X42: =V42/O42 | Y42: =INDEX(Calib!$K$1:$K$13,$D42)+p_eta*MAX(0,X42-INDEX(Calib!$AA$1:$AA$13,$D42)) | Z42: =(1-INDEX(Calib!$H$1:$H$13,$D42))*(1-p_alpha)*M42+S42 | AA42: =(1-p_delta_g)*AA41*(1-p_eps_g*$E42)+INDEX(Calib!$E$1:$E$13,$D42)*(INDEX(Calib!$G$1:$G$13,$D42)+p_programme*$H42) | AB42: =AB41*(1-p_eps_k*$E42)+p_lambda_k*(AD42-AB41*(1-p_eps_k*$E42)) | AC42: =INDEX(Calib!$R$1:$R$13,$D42)*$F42*(AA41*(1-p_eps_g*$E42))^INDEX(Calib!$Q$1:$Q$13,$D42)*(AB41*(1-p_eps_k*$E42))^p_alpha | AD42: =p_alpha*(1-INDEX(Calib!$H$1:$H$13,$D42))*AC42/(INDEX(Calib!$K$1:$K$13,$D42)+p_delta) | AE42: =AC42+$G42 | AF42: =p_programme*($H42+$I42) | AG42: =INDEX(Calib!$I$1:$I$13,$D42)+p_sh_grant*AF42 | AH42: =INDEX(Calib!$H$1:$H$13,$D42)*AC42+p_gov_take*$G42+AG42+p_programme*p_pricing*$J42 | AI42: =INDEX(Calib!$Y$1:$Y$13,$D42)-INDEX(Calib!$Z$1:$Z$13,$D42)*(AL41/AE41-INDEX(Calib!$AA$1:$AA$13,$D42)) | AJ42: =INDEX(Calib!$X$1:$X$13,$D42)+INDEX(Calib!$G$1:$G$13,$D42)+AF42+AI42-AH42 | AK42: =p_rk*AM41+AO41*(AL41-AM41) | AL42: =AL41+AK42+AJ42 | AM42: =INDEX(Calib!$U$1:$U$13,$D42)+(AM41-INDEX(Calib!$U$1:$U$13,$D42))*(1-p_amort)+p_sh_conc*AF42 | AN42: =AL42/AE42 | AO42: =INDEX(Calib!$K$1:$K$13,$D42)+p_eta*MAX(0,AN42-INDEX(Calib!$AA$1:$AA$13,$D42)) | AP42: =(1-INDEX(Calib!$H$1:$H$13,$D42))*(1-p_alpha)*AC42+AI42 | AQ42: =(AE42/O42-1)*100 | AR42: =(AE42/AE29-1)*100 | AS42: =(O42/O29-1)*100 | AT42: =(AN42-X42)*100 | AU42: =(AP42/Z42-1)*100 | AV42: =(AI42-S42)*100
A43: SLE | B43: 2038 | C43: 14 | D43: 3 | E43: =IF(AND(p_dis_year>0,B43=p_dis_year),1,0) | F43: =IF(AND(p_dis_year>0,B43>=p_dis_year),1-p_eps_a*p_rho_a^(B43-p_dis_year),1) | G43: =INDEX(Calib!$N$1:$N$13,$D43)*(1-p_rent_decline*MIN(1,C43/26)) | H43: =IF(C43=0,0,SUMIFS(dl_val,dl_iso,$A43,dl_ind,"pub_cap",dl_year,$B43)/100) | I43: =IF(C43=0,0,SUMIFS(dl_val,dl_iso,$A43,dl_ind,"pub_spend",dl_year,$B43)/100) | J43: =IF(C43=0,0,SUMIFS(dl_val,dl_iso,$A43,dl_ind,"rev",dl_year,$B43)/100) | K43: =(1-p_delta_g)*K42*(1-p_eps_g*$E43)+INDEX(Calib!$E$1:$E$13,$D43)*(INDEX(Calib!$G$1:$G$13,$D43)+0*$H43) | L43: =L42*(1-p_eps_k*$E43)+p_lambda_k*(N43-L42*(1-p_eps_k*$E43)) | M43: =INDEX(Calib!$R$1:$R$13,$D43)*$F43*(K42*(1-p_eps_g*$E43))^INDEX(Calib!$Q$1:$Q$13,$D43)*(L42*(1-p_eps_k*$E43))^p_alpha | N43: =p_alpha*(1-INDEX(Calib!$H$1:$H$13,$D43))*M43/(INDEX(Calib!$K$1:$K$13,$D43)+p_delta) | O43: =M43+$G43 | P43: =0*($H43+$I43) | Q43: =INDEX(Calib!$I$1:$I$13,$D43)+p_sh_grant*P43 | R43: =INDEX(Calib!$H$1:$H$13,$D43)*M43+p_gov_take*$G43+Q43+0*p_pricing*$J43 | S43: =INDEX(Calib!$Y$1:$Y$13,$D43)-INDEX(Calib!$Z$1:$Z$13,$D43)*(V42/O42-INDEX(Calib!$AA$1:$AA$13,$D43)) | T43: =INDEX(Calib!$X$1:$X$13,$D43)+INDEX(Calib!$G$1:$G$13,$D43)+P43+S43-R43 | U43: =p_rk*W42+Y42*(V42-W42) | V43: =V42+U43+T43 | W43: =INDEX(Calib!$U$1:$U$13,$D43)+(W42-INDEX(Calib!$U$1:$U$13,$D43))*(1-p_amort)+p_sh_conc*P43 | X43: =V43/O43 | Y43: =INDEX(Calib!$K$1:$K$13,$D43)+p_eta*MAX(0,X43-INDEX(Calib!$AA$1:$AA$13,$D43)) | Z43: =(1-INDEX(Calib!$H$1:$H$13,$D43))*(1-p_alpha)*M43+S43 | AA43: =(1-p_delta_g)*AA42*(1-p_eps_g*$E43)+INDEX(Calib!$E$1:$E$13,$D43)*(INDEX(Calib!$G$1:$G$13,$D43)+p_programme*$H43) | AB43: =AB42*(1-p_eps_k*$E43)+p_lambda_k*(AD43-AB42*(1-p_eps_k*$E43)) | AC43: =INDEX(Calib!$R$1:$R$13,$D43)*$F43*(AA42*(1-p_eps_g*$E43))^INDEX(Calib!$Q$1:$Q$13,$D43)*(AB42*(1-p_eps_k*$E43))^p_alpha | AD43: =p_alpha*(1-INDEX(Calib!$H$1:$H$13,$D43))*AC43/(INDEX(Calib!$K$1:$K$13,$D43)+p_delta) | AE43: =AC43+$G43 | AF43: =p_programme*($H43+$I43) | AG43: =INDEX(Calib!$I$1:$I$13,$D43)+p_sh_grant*AF43 | AH43: =INDEX(Calib!$H$1:$H$13,$D43)*AC43+p_gov_take*$G43+AG43+p_programme*p_pricing*$J43 | AI43: =INDEX(Calib!$Y$1:$Y$13,$D43)-INDEX(Calib!$Z$1:$Z$13,$D43)*(AL42/AE42-INDEX(Calib!$AA$1:$AA$13,$D43)) | AJ43: =INDEX(Calib!$X$1:$X$13,$D43)+INDEX(Calib!$G$1:$G$13,$D43)+AF43+AI43-AH43 | AK43: =p_rk*AM42+AO42*(AL42-AM42) | AL43: =AL42+AK43+AJ43 | AM43: =INDEX(Calib!$U$1:$U$13,$D43)+(AM42-INDEX(Calib!$U$1:$U$13,$D43))*(1-p_amort)+p_sh_conc*AF43 | AN43: =AL43/AE43 | AO43: =INDEX(Calib!$K$1:$K$13,$D43)+p_eta*MAX(0,AN43-INDEX(Calib!$AA$1:$AA$13,$D43)) | AP43: =(1-INDEX(Calib!$H$1:$H$13,$D43))*(1-p_alpha)*AC43+AI43 | AQ43: =(AE43/O43-1)*100 | AR43: =(AE43/AE29-1)*100 | AS43: =(O43/O29-1)*100 | AT43: =(AN43-X43)*100 | AU43: =(AP43/Z43-1)*100 | AV43: =(AI43-S43)*100
A44: SLE | B44: 2039 | C44: 15 | D44: 3 | E44: =IF(AND(p_dis_year>0,B44=p_dis_year),1,0) | F44: =IF(AND(p_dis_year>0,B44>=p_dis_year),1-p_eps_a*p_rho_a^(B44-p_dis_year),1) | G44: =INDEX(Calib!$N$1:$N$13,$D44)*(1-p_rent_decline*MIN(1,C44/26)) | H44: =IF(C44=0,0,SUMIFS(dl_val,dl_iso,$A44,dl_ind,"pub_cap",dl_year,$B44)/100) | I44: =IF(C44=0,0,SUMIFS(dl_val,dl_iso,$A44,dl_ind,"pub_spend",dl_year,$B44)/100) | J44: =IF(C44=0,0,SUMIFS(dl_val,dl_iso,$A44,dl_ind,"rev",dl_year,$B44)/100) | K44: =(1-p_delta_g)*K43*(1-p_eps_g*$E44)+INDEX(Calib!$E$1:$E$13,$D44)*(INDEX(Calib!$G$1:$G$13,$D44)+0*$H44) | L44: =L43*(1-p_eps_k*$E44)+p_lambda_k*(N44-L43*(1-p_eps_k*$E44)) | M44: =INDEX(Calib!$R$1:$R$13,$D44)*$F44*(K43*(1-p_eps_g*$E44))^INDEX(Calib!$Q$1:$Q$13,$D44)*(L43*(1-p_eps_k*$E44))^p_alpha | N44: =p_alpha*(1-INDEX(Calib!$H$1:$H$13,$D44))*M44/(INDEX(Calib!$K$1:$K$13,$D44)+p_delta) | O44: =M44+$G44 | P44: =0*($H44+$I44) | Q44: =INDEX(Calib!$I$1:$I$13,$D44)+p_sh_grant*P44 | R44: =INDEX(Calib!$H$1:$H$13,$D44)*M44+p_gov_take*$G44+Q44+0*p_pricing*$J44 | S44: =INDEX(Calib!$Y$1:$Y$13,$D44)-INDEX(Calib!$Z$1:$Z$13,$D44)*(V43/O43-INDEX(Calib!$AA$1:$AA$13,$D44)) | T44: =INDEX(Calib!$X$1:$X$13,$D44)+INDEX(Calib!$G$1:$G$13,$D44)+P44+S44-R44 | U44: =p_rk*W43+Y43*(V43-W43) | V44: =V43+U44+T44 | W44: =INDEX(Calib!$U$1:$U$13,$D44)+(W43-INDEX(Calib!$U$1:$U$13,$D44))*(1-p_amort)+p_sh_conc*P44 | X44: =V44/O44 | Y44: =INDEX(Calib!$K$1:$K$13,$D44)+p_eta*MAX(0,X44-INDEX(Calib!$AA$1:$AA$13,$D44)) | Z44: =(1-INDEX(Calib!$H$1:$H$13,$D44))*(1-p_alpha)*M44+S44 | AA44: =(1-p_delta_g)*AA43*(1-p_eps_g*$E44)+INDEX(Calib!$E$1:$E$13,$D44)*(INDEX(Calib!$G$1:$G$13,$D44)+p_programme*$H44) | AB44: =AB43*(1-p_eps_k*$E44)+p_lambda_k*(AD44-AB43*(1-p_eps_k*$E44)) | AC44: =INDEX(Calib!$R$1:$R$13,$D44)*$F44*(AA43*(1-p_eps_g*$E44))^INDEX(Calib!$Q$1:$Q$13,$D44)*(AB43*(1-p_eps_k*$E44))^p_alpha | AD44: =p_alpha*(1-INDEX(Calib!$H$1:$H$13,$D44))*AC44/(INDEX(Calib!$K$1:$K$13,$D44)+p_delta) | AE44: =AC44+$G44 | AF44: =p_programme*($H44+$I44) | AG44: =INDEX(Calib!$I$1:$I$13,$D44)+p_sh_grant*AF44 | AH44: =INDEX(Calib!$H$1:$H$13,$D44)*AC44+p_gov_take*$G44+AG44+p_programme*p_pricing*$J44 | AI44: =INDEX(Calib!$Y$1:$Y$13,$D44)-INDEX(Calib!$Z$1:$Z$13,$D44)*(AL43/AE43-INDEX(Calib!$AA$1:$AA$13,$D44)) | AJ44: =INDEX(Calib!$X$1:$X$13,$D44)+INDEX(Calib!$G$1:$G$13,$D44)+AF44+AI44-AH44 | AK44: =p_rk*AM43+AO43*(AL43-AM43) | AL44: =AL43+AK44+AJ44 | AM44: =INDEX(Calib!$U$1:$U$13,$D44)+(AM43-INDEX(Calib!$U$1:$U$13,$D44))*(1-p_amort)+p_sh_conc*AF44 | AN44: =AL44/AE44 | AO44: =INDEX(Calib!$K$1:$K$13,$D44)+p_eta*MAX(0,AN44-INDEX(Calib!$AA$1:$AA$13,$D44)) | AP44: =(1-INDEX(Calib!$H$1:$H$13,$D44))*(1-p_alpha)*AC44+AI44 | AQ44: =(AE44/O44-1)*100 | AR44: =(AE44/AE29-1)*100 | AS44: =(O44/O29-1)*100 | AT44: =(AN44-X44)*100 | AU44: =(AP44/Z44-1)*100 | AV44: =(AI44-S44)*100
A45: SLE | B45: 2040 | C45: 16 | D45: 3 | E45: =IF(AND(p_dis_year>0,B45=p_dis_year),1,0) | F45: =IF(AND(p_dis_year>0,B45>=p_dis_year),1-p_eps_a*p_rho_a^(B45-p_dis_year),1) | G45: =INDEX(Calib!$N$1:$N$13,$D45)*(1-p_rent_decline*MIN(1,C45/26)) | H45: =IF(C45=0,0,SUMIFS(dl_val,dl_iso,$A45,dl_ind,"pub_cap",dl_year,$B45)/100) | I45: =IF(C45=0,0,SUMIFS(dl_val,dl_iso,$A45,dl_ind,"pub_spend",dl_year,$B45)/100) | J45: =IF(C45=0,0,SUMIFS(dl_val,dl_iso,$A45,dl_ind,"rev",dl_year,$B45)/100) | K45: =(1-p_delta_g)*K44*(1-p_eps_g*$E45)+INDEX(Calib!$E$1:$E$13,$D45)*(INDEX(Calib!$G$1:$G$13,$D45)+0*$H45) | L45: =L44*(1-p_eps_k*$E45)+p_lambda_k*(N45-L44*(1-p_eps_k*$E45)) | M45: =INDEX(Calib!$R$1:$R$13,$D45)*$F45*(K44*(1-p_eps_g*$E45))^INDEX(Calib!$Q$1:$Q$13,$D45)*(L44*(1-p_eps_k*$E45))^p_alpha | N45: =p_alpha*(1-INDEX(Calib!$H$1:$H$13,$D45))*M45/(INDEX(Calib!$K$1:$K$13,$D45)+p_delta) | O45: =M45+$G45 | P45: =0*($H45+$I45) | Q45: =INDEX(Calib!$I$1:$I$13,$D45)+p_sh_grant*P45 | R45: =INDEX(Calib!$H$1:$H$13,$D45)*M45+p_gov_take*$G45+Q45+0*p_pricing*$J45 | S45: =INDEX(Calib!$Y$1:$Y$13,$D45)-INDEX(Calib!$Z$1:$Z$13,$D45)*(V44/O44-INDEX(Calib!$AA$1:$AA$13,$D45)) | T45: =INDEX(Calib!$X$1:$X$13,$D45)+INDEX(Calib!$G$1:$G$13,$D45)+P45+S45-R45 | U45: =p_rk*W44+Y44*(V44-W44) | V45: =V44+U45+T45 | W45: =INDEX(Calib!$U$1:$U$13,$D45)+(W44-INDEX(Calib!$U$1:$U$13,$D45))*(1-p_amort)+p_sh_conc*P45 | X45: =V45/O45 | Y45: =INDEX(Calib!$K$1:$K$13,$D45)+p_eta*MAX(0,X45-INDEX(Calib!$AA$1:$AA$13,$D45)) | Z45: =(1-INDEX(Calib!$H$1:$H$13,$D45))*(1-p_alpha)*M45+S45 | AA45: =(1-p_delta_g)*AA44*(1-p_eps_g*$E45)+INDEX(Calib!$E$1:$E$13,$D45)*(INDEX(Calib!$G$1:$G$13,$D45)+p_programme*$H45) | AB45: =AB44*(1-p_eps_k*$E45)+p_lambda_k*(AD45-AB44*(1-p_eps_k*$E45)) | AC45: =INDEX(Calib!$R$1:$R$13,$D45)*$F45*(AA44*(1-p_eps_g*$E45))^INDEX(Calib!$Q$1:$Q$13,$D45)*(AB44*(1-p_eps_k*$E45))^p_alpha | AD45: =p_alpha*(1-INDEX(Calib!$H$1:$H$13,$D45))*AC45/(INDEX(Calib!$K$1:$K$13,$D45)+p_delta) | AE45: =AC45+$G45 | AF45: =p_programme*($H45+$I45) | AG45: =INDEX(Calib!$I$1:$I$13,$D45)+p_sh_grant*AF45 | AH45: =INDEX(Calib!$H$1:$H$13,$D45)*AC45+p_gov_take*$G45+AG45+p_programme*p_pricing*$J45 | AI45: =INDEX(Calib!$Y$1:$Y$13,$D45)-INDEX(Calib!$Z$1:$Z$13,$D45)*(AL44/AE44-INDEX(Calib!$AA$1:$AA$13,$D45)) | AJ45: =INDEX(Calib!$X$1:$X$13,$D45)+INDEX(Calib!$G$1:$G$13,$D45)+AF45+AI45-AH45 | AK45: =p_rk*AM44+AO44*(AL44-AM44) | AL45: =AL44+AK45+AJ45 | AM45: =INDEX(Calib!$U$1:$U$13,$D45)+(AM44-INDEX(Calib!$U$1:$U$13,$D45))*(1-p_amort)+p_sh_conc*AF45 | AN45: =AL45/AE45 | AO45: =INDEX(Calib!$K$1:$K$13,$D45)+p_eta*MAX(0,AN45-INDEX(Calib!$AA$1:$AA$13,$D45)) | AP45: =(1-INDEX(Calib!$H$1:$H$13,$D45))*(1-p_alpha)*AC45+AI45 | AQ45: =(AE45/O45-1)*100 | AR45: =(AE45/AE29-1)*100 | AS45: =(O45/O29-1)*100 | AT45: =(AN45-X45)*100 | AU45: =(AP45/Z45-1)*100 | AV45: =(AI45-S45)*100
A46: SLE | B46: 2041 | C46: 17 | D46: 3 | E46: =IF(AND(p_dis_year>0,B46=p_dis_year),1,0) | F46: =IF(AND(p_dis_year>0,B46>=p_dis_year),1-p_eps_a*p_rho_a^(B46-p_dis_year),1) | G46: =INDEX(Calib!$N$1:$N$13,$D46)*(1-p_rent_decline*MIN(1,C46/26)) | H46: =IF(C46=0,0,SUMIFS(dl_val,dl_iso,$A46,dl_ind,"pub_cap",dl_year,$B46)/100) | I46: =IF(C46=0,0,SUMIFS(dl_val,dl_iso,$A46,dl_ind,"pub_spend",dl_year,$B46)/100) | J46: =IF(C46=0,0,SUMIFS(dl_val,dl_iso,$A46,dl_ind,"rev",dl_year,$B46)/100) | K46: =(1-p_delta_g)*K45*(1-p_eps_g*$E46)+INDEX(Calib!$E$1:$E$13,$D46)*(INDEX(Calib!$G$1:$G$13,$D46)+0*$H46) | L46: =L45*(1-p_eps_k*$E46)+p_lambda_k*(N46-L45*(1-p_eps_k*$E46)) | M46: =INDEX(Calib!$R$1:$R$13,$D46)*$F46*(K45*(1-p_eps_g*$E46))^INDEX(Calib!$Q$1:$Q$13,$D46)*(L45*(1-p_eps_k*$E46))^p_alpha | N46: =p_alpha*(1-INDEX(Calib!$H$1:$H$13,$D46))*M46/(INDEX(Calib!$K$1:$K$13,$D46)+p_delta) | O46: =M46+$G46 | P46: =0*($H46+$I46) | Q46: =INDEX(Calib!$I$1:$I$13,$D46)+p_sh_grant*P46 | R46: =INDEX(Calib!$H$1:$H$13,$D46)*M46+p_gov_take*$G46+Q46+0*p_pricing*$J46 | S46: =INDEX(Calib!$Y$1:$Y$13,$D46)-INDEX(Calib!$Z$1:$Z$13,$D46)*(V45/O45-INDEX(Calib!$AA$1:$AA$13,$D46)) | T46: =INDEX(Calib!$X$1:$X$13,$D46)+INDEX(Calib!$G$1:$G$13,$D46)+P46+S46-R46 | U46: =p_rk*W45+Y45*(V45-W45) | V46: =V45+U46+T46 | W46: =INDEX(Calib!$U$1:$U$13,$D46)+(W45-INDEX(Calib!$U$1:$U$13,$D46))*(1-p_amort)+p_sh_conc*P46 | X46: =V46/O46 | Y46: =INDEX(Calib!$K$1:$K$13,$D46)+p_eta*MAX(0,X46-INDEX(Calib!$AA$1:$AA$13,$D46)) | Z46: =(1-INDEX(Calib!$H$1:$H$13,$D46))*(1-p_alpha)*M46+S46 | AA46: =(1-p_delta_g)*AA45*(1-p_eps_g*$E46)+INDEX(Calib!$E$1:$E$13,$D46)*(INDEX(Calib!$G$1:$G$13,$D46)+p_programme*$H46) | AB46: =AB45*(1-p_eps_k*$E46)+p_lambda_k*(AD46-AB45*(1-p_eps_k*$E46)) | AC46: =INDEX(Calib!$R$1:$R$13,$D46)*$F46*(AA45*(1-p_eps_g*$E46))^INDEX(Calib!$Q$1:$Q$13,$D46)*(AB45*(1-p_eps_k*$E46))^p_alpha | AD46: =p_alpha*(1-INDEX(Calib!$H$1:$H$13,$D46))*AC46/(INDEX(Calib!$K$1:$K$13,$D46)+p_delta) | AE46: =AC46+$G46 | AF46: =p_programme*($H46+$I46) | AG46: =INDEX(Calib!$I$1:$I$13,$D46)+p_sh_grant*AF46 | AH46: =INDEX(Calib!$H$1:$H$13,$D46)*AC46+p_gov_take*$G46+AG46+p_programme*p_pricing*$J46 | AI46: =INDEX(Calib!$Y$1:$Y$13,$D46)-INDEX(Calib!$Z$1:$Z$13,$D46)*(AL45/AE45-INDEX(Calib!$AA$1:$AA$13,$D46)) | AJ46: =INDEX(Calib!$X$1:$X$13,$D46)+INDEX(Calib!$G$1:$G$13,$D46)+AF46+AI46-AH46 | AK46: =p_rk*AM45+AO45*(AL45-AM45) | AL46: =AL45+AK46+AJ46 | AM46: =INDEX(Calib!$U$1:$U$13,$D46)+(AM45-INDEX(Calib!$U$1:$U$13,$D46))*(1-p_amort)+p_sh_conc*AF46 | AN46: =AL46/AE46 | AO46: =INDEX(Calib!$K$1:$K$13,$D46)+p_eta*MAX(0,AN46-INDEX(Calib!$AA$1:$AA$13,$D46)) | AP46: =(1-INDEX(Calib!$H$1:$H$13,$D46))*(1-p_alpha)*AC46+AI46 | AQ46: =(AE46/O46-1)*100 | AR46: =(AE46/AE29-1)*100 | AS46: =(O46/O29-1)*100 | AT46: =(AN46-X46)*100 | AU46: =(AP46/Z46-1)*100 | AV46: =(AI46-S46)*100
A47: SLE | B47: 2042 | C47: 18 | D47: 3 | E47: =IF(AND(p_dis_year>0,B47=p_dis_year),1,0) | F47: =IF(AND(p_dis_year>0,B47>=p_dis_year),1-p_eps_a*p_rho_a^(B47-p_dis_year),1) | G47: =INDEX(Calib!$N$1:$N$13,$D47)*(1-p_rent_decline*MIN(1,C47/26)) | H47: =IF(C47=0,0,SUMIFS(dl_val,dl_iso,$A47,dl_ind,"pub_cap",dl_year,$B47)/100) | I47: =IF(C47=0,0,SUMIFS(dl_val,dl_iso,$A47,dl_ind,"pub_spend",dl_year,$B47)/100) | J47: =IF(C47=0,0,SUMIFS(dl_val,dl_iso,$A47,dl_ind,"rev",dl_year,$B47)/100) | K47: =(1-p_delta_g)*K46*(1-p_eps_g*$E47)+INDEX(Calib!$E$1:$E$13,$D47)*(INDEX(Calib!$G$1:$G$13,$D47)+0*$H47) | L47: =L46*(1-p_eps_k*$E47)+p_lambda_k*(N47-L46*(1-p_eps_k*$E47)) | M47: =INDEX(Calib!$R$1:$R$13,$D47)*$F47*(K46*(1-p_eps_g*$E47))^INDEX(Calib!$Q$1:$Q$13,$D47)*(L46*(1-p_eps_k*$E47))^p_alpha | N47: =p_alpha*(1-INDEX(Calib!$H$1:$H$13,$D47))*M47/(INDEX(Calib!$K$1:$K$13,$D47)+p_delta) | O47: =M47+$G47 | P47: =0*($H47+$I47) | Q47: =INDEX(Calib!$I$1:$I$13,$D47)+p_sh_grant*P47 | R47: =INDEX(Calib!$H$1:$H$13,$D47)*M47+p_gov_take*$G47+Q47+0*p_pricing*$J47 | S47: =INDEX(Calib!$Y$1:$Y$13,$D47)-INDEX(Calib!$Z$1:$Z$13,$D47)*(V46/O46-INDEX(Calib!$AA$1:$AA$13,$D47)) | T47: =INDEX(Calib!$X$1:$X$13,$D47)+INDEX(Calib!$G$1:$G$13,$D47)+P47+S47-R47 | U47: =p_rk*W46+Y46*(V46-W46) | V47: =V46+U47+T47 | W47: =INDEX(Calib!$U$1:$U$13,$D47)+(W46-INDEX(Calib!$U$1:$U$13,$D47))*(1-p_amort)+p_sh_conc*P47 | X47: =V47/O47 | Y47: =INDEX(Calib!$K$1:$K$13,$D47)+p_eta*MAX(0,X47-INDEX(Calib!$AA$1:$AA$13,$D47)) | Z47: =(1-INDEX(Calib!$H$1:$H$13,$D47))*(1-p_alpha)*M47+S47 | AA47: =(1-p_delta_g)*AA46*(1-p_eps_g*$E47)+INDEX(Calib!$E$1:$E$13,$D47)*(INDEX(Calib!$G$1:$G$13,$D47)+p_programme*$H47) | AB47: =AB46*(1-p_eps_k*$E47)+p_lambda_k*(AD47-AB46*(1-p_eps_k*$E47)) | AC47: =INDEX(Calib!$R$1:$R$13,$D47)*$F47*(AA46*(1-p_eps_g*$E47))^INDEX(Calib!$Q$1:$Q$13,$D47)*(AB46*(1-p_eps_k*$E47))^p_alpha | AD47: =p_alpha*(1-INDEX(Calib!$H$1:$H$13,$D47))*AC47/(INDEX(Calib!$K$1:$K$13,$D47)+p_delta) | AE47: =AC47+$G47 | AF47: =p_programme*($H47+$I47) | AG47: =INDEX(Calib!$I$1:$I$13,$D47)+p_sh_grant*AF47 | AH47: =INDEX(Calib!$H$1:$H$13,$D47)*AC47+p_gov_take*$G47+AG47+p_programme*p_pricing*$J47 | AI47: =INDEX(Calib!$Y$1:$Y$13,$D47)-INDEX(Calib!$Z$1:$Z$13,$D47)*(AL46/AE46-INDEX(Calib!$AA$1:$AA$13,$D47)) | AJ47: =INDEX(Calib!$X$1:$X$13,$D47)+INDEX(Calib!$G$1:$G$13,$D47)+AF47+AI47-AH47 | AK47: =p_rk*AM46+AO46*(AL46-AM46) | AL47: =AL46+AK47+AJ47 | AM47: =INDEX(Calib!$U$1:$U$13,$D47)+(AM46-INDEX(Calib!$U$1:$U$13,$D47))*(1-p_amort)+p_sh_conc*AF47 | AN47: =AL47/AE47 | AO47: =INDEX(Calib!$K$1:$K$13,$D47)+p_eta*MAX(0,AN47-INDEX(Calib!$AA$1:$AA$13,$D47)) | AP47: =(1-INDEX(Calib!$H$1:$H$13,$D47))*(1-p_alpha)*AC47+AI47 | AQ47: =(AE47/O47-1)*100 | AR47: =(AE47/AE29-1)*100 | AS47: =(O47/O29-1)*100 | AT47: =(AN47-X47)*100 | AU47: =(AP47/Z47-1)*100 | AV47: =(AI47-S47)*100
A48: SLE | B48: 2043 | C48: 19 | D48: 3 | E48: =IF(AND(p_dis_year>0,B48=p_dis_year),1,0) | F48: =IF(AND(p_dis_year>0,B48>=p_dis_year),1-p_eps_a*p_rho_a^(B48-p_dis_year),1) | G48: =INDEX(Calib!$N$1:$N$13,$D48)*(1-p_rent_decline*MIN(1,C48/26)) | H48: =IF(C48=0,0,SUMIFS(dl_val,dl_iso,$A48,dl_ind,"pub_cap",dl_year,$B48)/100) | I48: =IF(C48=0,0,SUMIFS(dl_val,dl_iso,$A48,dl_ind,"pub_spend",dl_year,$B48)/100) | J48: =IF(C48=0,0,SUMIFS(dl_val,dl_iso,$A48,dl_ind,"rev",dl_year,$B48)/100) | K48: =(1-p_delta_g)*K47*(1-p_eps_g*$E48)+INDEX(Calib!$E$1:$E$13,$D48)*(INDEX(Calib!$G$1:$G$13,$D48)+0*$H48) | L48: =L47*(1-p_eps_k*$E48)+p_lambda_k*(N48-L47*(1-p_eps_k*$E48)) | M48: =INDEX(Calib!$R$1:$R$13,$D48)*$F48*(K47*(1-p_eps_g*$E48))^INDEX(Calib!$Q$1:$Q$13,$D48)*(L47*(1-p_eps_k*$E48))^p_alpha | N48: =p_alpha*(1-INDEX(Calib!$H$1:$H$13,$D48))*M48/(INDEX(Calib!$K$1:$K$13,$D48)+p_delta) | O48: =M48+$G48 | P48: =0*($H48+$I48) | Q48: =INDEX(Calib!$I$1:$I$13,$D48)+p_sh_grant*P48 | R48: =INDEX(Calib!$H$1:$H$13,$D48)*M48+p_gov_take*$G48+Q48+0*p_pricing*$J48 | S48: =INDEX(Calib!$Y$1:$Y$13,$D48)-INDEX(Calib!$Z$1:$Z$13,$D48)*(V47/O47-INDEX(Calib!$AA$1:$AA$13,$D48)) | T48: =INDEX(Calib!$X$1:$X$13,$D48)+INDEX(Calib!$G$1:$G$13,$D48)+P48+S48-R48 | U48: =p_rk*W47+Y47*(V47-W47) | V48: =V47+U48+T48 | W48: =INDEX(Calib!$U$1:$U$13,$D48)+(W47-INDEX(Calib!$U$1:$U$13,$D48))*(1-p_amort)+p_sh_conc*P48 | X48: =V48/O48 | Y48: =INDEX(Calib!$K$1:$K$13,$D48)+p_eta*MAX(0,X48-INDEX(Calib!$AA$1:$AA$13,$D48)) | Z48: =(1-INDEX(Calib!$H$1:$H$13,$D48))*(1-p_alpha)*M48+S48 | AA48: =(1-p_delta_g)*AA47*(1-p_eps_g*$E48)+INDEX(Calib!$E$1:$E$13,$D48)*(INDEX(Calib!$G$1:$G$13,$D48)+p_programme*$H48) | AB48: =AB47*(1-p_eps_k*$E48)+p_lambda_k*(AD48-AB47*(1-p_eps_k*$E48)) | AC48: =INDEX(Calib!$R$1:$R$13,$D48)*$F48*(AA47*(1-p_eps_g*$E48))^INDEX(Calib!$Q$1:$Q$13,$D48)*(AB47*(1-p_eps_k*$E48))^p_alpha | AD48: =p_alpha*(1-INDEX(Calib!$H$1:$H$13,$D48))*AC48/(INDEX(Calib!$K$1:$K$13,$D48)+p_delta) | AE48: =AC48+$G48 | AF48: =p_programme*($H48+$I48) | AG48: =INDEX(Calib!$I$1:$I$13,$D48)+p_sh_grant*AF48 | AH48: =INDEX(Calib!$H$1:$H$13,$D48)*AC48+p_gov_take*$G48+AG48+p_programme*p_pricing*$J48 | AI48: =INDEX(Calib!$Y$1:$Y$13,$D48)-INDEX(Calib!$Z$1:$Z$13,$D48)*(AL47/AE47-INDEX(Calib!$AA$1:$AA$13,$D48)) | AJ48: =INDEX(Calib!$X$1:$X$13,$D48)+INDEX(Calib!$G$1:$G$13,$D48)+AF48+AI48-AH48 | AK48: =p_rk*AM47+AO47*(AL47-AM47) | AL48: =AL47+AK48+AJ48 | AM48: =INDEX(Calib!$U$1:$U$13,$D48)+(AM47-INDEX(Calib!$U$1:$U$13,$D48))*(1-p_amort)+p_sh_conc*AF48 | AN48: =AL48/AE48 | AO48: =INDEX(Calib!$K$1:$K$13,$D48)+p_eta*MAX(0,AN48-INDEX(Calib!$AA$1:$AA$13,$D48)) | AP48: =(1-INDEX(Calib!$H$1:$H$13,$D48))*(1-p_alpha)*AC48+AI48 | AQ48: =(AE48/O48-1)*100 | AR48: =(AE48/AE29-1)*100 | AS48: =(O48/O29-1)*100 | AT48: =(AN48-X48)*100 | AU48: =(AP48/Z48-1)*100 | AV48: =(AI48-S48)*100
A49: SLE | B49: 2044 | C49: 20 | D49: 3 | E49: =IF(AND(p_dis_year>0,B49=p_dis_year),1,0) | F49: =IF(AND(p_dis_year>0,B49>=p_dis_year),1-p_eps_a*p_rho_a^(B49-p_dis_year),1) | G49: =INDEX(Calib!$N$1:$N$13,$D49)*(1-p_rent_decline*MIN(1,C49/26)) | H49: =IF(C49=0,0,SUMIFS(dl_val,dl_iso,$A49,dl_ind,"pub_cap",dl_year,$B49)/100) | I49: =IF(C49=0,0,SUMIFS(dl_val,dl_iso,$A49,dl_ind,"pub_spend",dl_year,$B49)/100) | J49: =IF(C49=0,0,SUMIFS(dl_val,dl_iso,$A49,dl_ind,"rev",dl_year,$B49)/100) | K49: =(1-p_delta_g)*K48*(1-p_eps_g*$E49)+INDEX(Calib!$E$1:$E$13,$D49)*(INDEX(Calib!$G$1:$G$13,$D49)+0*$H49) | L49: =L48*(1-p_eps_k*$E49)+p_lambda_k*(N49-L48*(1-p_eps_k*$E49)) | M49: =INDEX(Calib!$R$1:$R$13,$D49)*$F49*(K48*(1-p_eps_g*$E49))^INDEX(Calib!$Q$1:$Q$13,$D49)*(L48*(1-p_eps_k*$E49))^p_alpha | N49: =p_alpha*(1-INDEX(Calib!$H$1:$H$13,$D49))*M49/(INDEX(Calib!$K$1:$K$13,$D49)+p_delta) | O49: =M49+$G49 | P49: =0*($H49+$I49) | Q49: =INDEX(Calib!$I$1:$I$13,$D49)+p_sh_grant*P49 | R49: =INDEX(Calib!$H$1:$H$13,$D49)*M49+p_gov_take*$G49+Q49+0*p_pricing*$J49 | S49: =INDEX(Calib!$Y$1:$Y$13,$D49)-INDEX(Calib!$Z$1:$Z$13,$D49)*(V48/O48-INDEX(Calib!$AA$1:$AA$13,$D49)) | T49: =INDEX(Calib!$X$1:$X$13,$D49)+INDEX(Calib!$G$1:$G$13,$D49)+P49+S49-R49 | U49: =p_rk*W48+Y48*(V48-W48) | V49: =V48+U49+T49 | W49: =INDEX(Calib!$U$1:$U$13,$D49)+(W48-INDEX(Calib!$U$1:$U$13,$D49))*(1-p_amort)+p_sh_conc*P49 | X49: =V49/O49 | Y49: =INDEX(Calib!$K$1:$K$13,$D49)+p_eta*MAX(0,X49-INDEX(Calib!$AA$1:$AA$13,$D49)) | Z49: =(1-INDEX(Calib!$H$1:$H$13,$D49))*(1-p_alpha)*M49+S49 | AA49: =(1-p_delta_g)*AA48*(1-p_eps_g*$E49)+INDEX(Calib!$E$1:$E$13,$D49)*(INDEX(Calib!$G$1:$G$13,$D49)+p_programme*$H49) | AB49: =AB48*(1-p_eps_k*$E49)+p_lambda_k*(AD49-AB48*(1-p_eps_k*$E49)) | AC49: =INDEX(Calib!$R$1:$R$13,$D49)*$F49*(AA48*(1-p_eps_g*$E49))^INDEX(Calib!$Q$1:$Q$13,$D49)*(AB48*(1-p_eps_k*$E49))^p_alpha | AD49: =p_alpha*(1-INDEX(Calib!$H$1:$H$13,$D49))*AC49/(INDEX(Calib!$K$1:$K$13,$D49)+p_delta) | AE49: =AC49+$G49 | AF49: =p_programme*($H49+$I49) | AG49: =INDEX(Calib!$I$1:$I$13,$D49)+p_sh_grant*AF49 | AH49: =INDEX(Calib!$H$1:$H$13,$D49)*AC49+p_gov_take*$G49+AG49+p_programme*p_pricing*$J49 | AI49: =INDEX(Calib!$Y$1:$Y$13,$D49)-INDEX(Calib!$Z$1:$Z$13,$D49)*(AL48/AE48-INDEX(Calib!$AA$1:$AA$13,$D49)) | AJ49: =INDEX(Calib!$X$1:$X$13,$D49)+INDEX(Calib!$G$1:$G$13,$D49)+AF49+AI49-AH49 | AK49: =p_rk*AM48+AO48*(AL48-AM48) | AL49: =AL48+AK49+AJ49 | AM49: =INDEX(Calib!$U$1:$U$13,$D49)+(AM48-INDEX(Calib!$U$1:$U$13,$D49))*(1-p_amort)+p_sh_conc*AF49 | AN49: =AL49/AE49 | AO49: =INDEX(Calib!$K$1:$K$13,$D49)+p_eta*MAX(0,AN49-INDEX(Calib!$AA$1:$AA$13,$D49)) | AP49: =(1-INDEX(Calib!$H$1:$H$13,$D49))*(1-p_alpha)*AC49+AI49 | AQ49: =(AE49/O49-1)*100 | AR49: =(AE49/AE29-1)*100 | AS49: =(O49/O29-1)*100 | AT49: =(AN49-X49)*100 | AU49: =(AP49/Z49-1)*100 | AV49: =(AI49-S49)*100
A50: SLE | B50: 2045 | C50: 21 | D50: 3 | E50: =IF(AND(p_dis_year>0,B50=p_dis_year),1,0) | F50: =IF(AND(p_dis_year>0,B50>=p_dis_year),1-p_eps_a*p_rho_a^(B50-p_dis_year),1) | G50: =INDEX(Calib!$N$1:$N$13,$D50)*(1-p_rent_decline*MIN(1,C50/26)) | H50: =IF(C50=0,0,SUMIFS(dl_val,dl_iso,$A50,dl_ind,"pub_cap",dl_year,$B50)/100) | I50: =IF(C50=0,0,SUMIFS(dl_val,dl_iso,$A50,dl_ind,"pub_spend",dl_year,$B50)/100) | J50: =IF(C50=0,0,SUMIFS(dl_val,dl_iso,$A50,dl_ind,"rev",dl_year,$B50)/100) | K50: =(1-p_delta_g)*K49*(1-p_eps_g*$E50)+INDEX(Calib!$E$1:$E$13,$D50)*(INDEX(Calib!$G$1:$G$13,$D50)+0*$H50) | L50: =L49*(1-p_eps_k*$E50)+p_lambda_k*(N50-L49*(1-p_eps_k*$E50)) | M50: =INDEX(Calib!$R$1:$R$13,$D50)*$F50*(K49*(1-p_eps_g*$E50))^INDEX(Calib!$Q$1:$Q$13,$D50)*(L49*(1-p_eps_k*$E50))^p_alpha | N50: =p_alpha*(1-INDEX(Calib!$H$1:$H$13,$D50))*M50/(INDEX(Calib!$K$1:$K$13,$D50)+p_delta) | O50: =M50+$G50 | P50: =0*($H50+$I50) | Q50: =INDEX(Calib!$I$1:$I$13,$D50)+p_sh_grant*P50 | R50: =INDEX(Calib!$H$1:$H$13,$D50)*M50+p_gov_take*$G50+Q50+0*p_pricing*$J50 | S50: =INDEX(Calib!$Y$1:$Y$13,$D50)-INDEX(Calib!$Z$1:$Z$13,$D50)*(V49/O49-INDEX(Calib!$AA$1:$AA$13,$D50)) | T50: =INDEX(Calib!$X$1:$X$13,$D50)+INDEX(Calib!$G$1:$G$13,$D50)+P50+S50-R50 | U50: =p_rk*W49+Y49*(V49-W49) | V50: =V49+U50+T50 | W50: =INDEX(Calib!$U$1:$U$13,$D50)+(W49-INDEX(Calib!$U$1:$U$13,$D50))*(1-p_amort)+p_sh_conc*P50 | X50: =V50/O50 | Y50: =INDEX(Calib!$K$1:$K$13,$D50)+p_eta*MAX(0,X50-INDEX(Calib!$AA$1:$AA$13,$D50)) | Z50: =(1-INDEX(Calib!$H$1:$H$13,$D50))*(1-p_alpha)*M50+S50 | AA50: =(1-p_delta_g)*AA49*(1-p_eps_g*$E50)+INDEX(Calib!$E$1:$E$13,$D50)*(INDEX(Calib!$G$1:$G$13,$D50)+p_programme*$H50) | AB50: =AB49*(1-p_eps_k*$E50)+p_lambda_k*(AD50-AB49*(1-p_eps_k*$E50)) | AC50: =INDEX(Calib!$R$1:$R$13,$D50)*$F50*(AA49*(1-p_eps_g*$E50))^INDEX(Calib!$Q$1:$Q$13,$D50)*(AB49*(1-p_eps_k*$E50))^p_alpha | AD50: =p_alpha*(1-INDEX(Calib!$H$1:$H$13,$D50))*AC50/(INDEX(Calib!$K$1:$K$13,$D50)+p_delta) | AE50: =AC50+$G50 | AF50: =p_programme*($H50+$I50) | AG50: =INDEX(Calib!$I$1:$I$13,$D50)+p_sh_grant*AF50 | AH50: =INDEX(Calib!$H$1:$H$13,$D50)*AC50+p_gov_take*$G50+AG50+p_programme*p_pricing*$J50 | AI50: =INDEX(Calib!$Y$1:$Y$13,$D50)-INDEX(Calib!$Z$1:$Z$13,$D50)*(AL49/AE49-INDEX(Calib!$AA$1:$AA$13,$D50)) | AJ50: =INDEX(Calib!$X$1:$X$13,$D50)+INDEX(Calib!$G$1:$G$13,$D50)+AF50+AI50-AH50 | AK50: =p_rk*AM49+AO49*(AL49-AM49) | AL50: =AL49+AK50+AJ50 | AM50: =INDEX(Calib!$U$1:$U$13,$D50)+(AM49-INDEX(Calib!$U$1:$U$13,$D50))*(1-p_amort)+p_sh_conc*AF50 | AN50: =AL50/AE50 | AO50: =INDEX(Calib!$K$1:$K$13,$D50)+p_eta*MAX(0,AN50-INDEX(Calib!$AA$1:$AA$13,$D50)) | AP50: =(1-INDEX(Calib!$H$1:$H$13,$D50))*(1-p_alpha)*AC50+AI50 | AQ50: =(AE50/O50-1)*100 | AR50: =(AE50/AE29-1)*100 | AS50: =(O50/O29-1)*100 | AT50: =(AN50-X50)*100 | AU50: =(AP50/Z50-1)*100 | AV50: =(AI50-S50)*100
A51: SLE | B51: 2046 | C51: 22 | D51: 3 | E51: =IF(AND(p_dis_year>0,B51=p_dis_year),1,0) | F51: =IF(AND(p_dis_year>0,B51>=p_dis_year),1-p_eps_a*p_rho_a^(B51-p_dis_year),1) | G51: =INDEX(Calib!$N$1:$N$13,$D51)*(1-p_rent_decline*MIN(1,C51/26)) | H51: =IF(C51=0,0,SUMIFS(dl_val,dl_iso,$A51,dl_ind,"pub_cap",dl_year,$B51)/100) | I51: =IF(C51=0,0,SUMIFS(dl_val,dl_iso,$A51,dl_ind,"pub_spend",dl_year,$B51)/100) | J51: =IF(C51=0,0,SUMIFS(dl_val,dl_iso,$A51,dl_ind,"rev",dl_year,$B51)/100) | K51: =(1-p_delta_g)*K50*(1-p_eps_g*$E51)+INDEX(Calib!$E$1:$E$13,$D51)*(INDEX(Calib!$G$1:$G$13,$D51)+0*$H51) | L51: =L50*(1-p_eps_k*$E51)+p_lambda_k*(N51-L50*(1-p_eps_k*$E51)) | M51: =INDEX(Calib!$R$1:$R$13,$D51)*$F51*(K50*(1-p_eps_g*$E51))^INDEX(Calib!$Q$1:$Q$13,$D51)*(L50*(1-p_eps_k*$E51))^p_alpha | N51: =p_alpha*(1-INDEX(Calib!$H$1:$H$13,$D51))*M51/(INDEX(Calib!$K$1:$K$13,$D51)+p_delta) | O51: =M51+$G51 | P51: =0*($H51+$I51) | Q51: =INDEX(Calib!$I$1:$I$13,$D51)+p_sh_grant*P51 | R51: =INDEX(Calib!$H$1:$H$13,$D51)*M51+p_gov_take*$G51+Q51+0*p_pricing*$J51 | S51: =INDEX(Calib!$Y$1:$Y$13,$D51)-INDEX(Calib!$Z$1:$Z$13,$D51)*(V50/O50-INDEX(Calib!$AA$1:$AA$13,$D51)) | T51: =INDEX(Calib!$X$1:$X$13,$D51)+INDEX(Calib!$G$1:$G$13,$D51)+P51+S51-R51 | U51: =p_rk*W50+Y50*(V50-W50) | V51: =V50+U51+T51 | W51: =INDEX(Calib!$U$1:$U$13,$D51)+(W50-INDEX(Calib!$U$1:$U$13,$D51))*(1-p_amort)+p_sh_conc*P51 | X51: =V51/O51 | Y51: =INDEX(Calib!$K$1:$K$13,$D51)+p_eta*MAX(0,X51-INDEX(Calib!$AA$1:$AA$13,$D51)) | Z51: =(1-INDEX(Calib!$H$1:$H$13,$D51))*(1-p_alpha)*M51+S51 | AA51: =(1-p_delta_g)*AA50*(1-p_eps_g*$E51)+INDEX(Calib!$E$1:$E$13,$D51)*(INDEX(Calib!$G$1:$G$13,$D51)+p_programme*$H51) | AB51: =AB50*(1-p_eps_k*$E51)+p_lambda_k*(AD51-AB50*(1-p_eps_k*$E51)) | AC51: =INDEX(Calib!$R$1:$R$13,$D51)*$F51*(AA50*(1-p_eps_g*$E51))^INDEX(Calib!$Q$1:$Q$13,$D51)*(AB50*(1-p_eps_k*$E51))^p_alpha | AD51: =p_alpha*(1-INDEX(Calib!$H$1:$H$13,$D51))*AC51/(INDEX(Calib!$K$1:$K$13,$D51)+p_delta) | AE51: =AC51+$G51 | AF51: =p_programme*($H51+$I51) | AG51: =INDEX(Calib!$I$1:$I$13,$D51)+p_sh_grant*AF51 | AH51: =INDEX(Calib!$H$1:$H$13,$D51)*AC51+p_gov_take*$G51+AG51+p_programme*p_pricing*$J51 | AI51: =INDEX(Calib!$Y$1:$Y$13,$D51)-INDEX(Calib!$Z$1:$Z$13,$D51)*(AL50/AE50-INDEX(Calib!$AA$1:$AA$13,$D51)) | AJ51: =INDEX(Calib!$X$1:$X$13,$D51)+INDEX(Calib!$G$1:$G$13,$D51)+AF51+AI51-AH51 | AK51: =p_rk*AM50+AO50*(AL50-AM50) | AL51: =AL50+AK51+AJ51 | AM51: =INDEX(Calib!$U$1:$U$13,$D51)+(AM50-INDEX(Calib!$U$1:$U$13,$D51))*(1-p_amort)+p_sh_conc*AF51 | AN51: =AL51/AE51 | AO51: =INDEX(Calib!$K$1:$K$13,$D51)+p_eta*MAX(0,AN51-INDEX(Calib!$AA$1:$AA$13,$D51)) | AP51: =(1-INDEX(Calib!$H$1:$H$13,$D51))*(1-p_alpha)*AC51+AI51 | AQ51: =(AE51/O51-1)*100 | AR51: =(AE51/AE29-1)*100 | AS51: =(O51/O29-1)*100 | AT51: =(AN51-X51)*100 | AU51: =(AP51/Z51-1)*100 | AV51: =(AI51-S51)*100
A52: SLE | B52: 2047 | C52: 23 | D52: 3 | E52: =IF(AND(p_dis_year>0,B52=p_dis_year),1,0) | F52: =IF(AND(p_dis_year>0,B52>=p_dis_year),1-p_eps_a*p_rho_a^(B52-p_dis_year),1) | G52: =INDEX(Calib!$N$1:$N$13,$D52)*(1-p_rent_decline*MIN(1,C52/26)) | H52: =IF(C52=0,0,SUMIFS(dl_val,dl_iso,$A52,dl_ind,"pub_cap",dl_year,$B52)/100) | I52: =IF(C52=0,0,SUMIFS(dl_val,dl_iso,$A52,dl_ind,"pub_spend",dl_year,$B52)/100) | J52: =IF(C52=0,0,SUMIFS(dl_val,dl_iso,$A52,dl_ind,"rev",dl_year,$B52)/100) | K52: =(1-p_delta_g)*K51*(1-p_eps_g*$E52)+INDEX(Calib!$E$1:$E$13,$D52)*(INDEX(Calib!$G$1:$G$13,$D52)+0*$H52) | L52: =L51*(1-p_eps_k*$E52)+p_lambda_k*(N52-L51*(1-p_eps_k*$E52)) | M52: =INDEX(Calib!$R$1:$R$13,$D52)*$F52*(K51*(1-p_eps_g*$E52))^INDEX(Calib!$Q$1:$Q$13,$D52)*(L51*(1-p_eps_k*$E52))^p_alpha | N52: =p_alpha*(1-INDEX(Calib!$H$1:$H$13,$D52))*M52/(INDEX(Calib!$K$1:$K$13,$D52)+p_delta) | O52: =M52+$G52 | P52: =0*($H52+$I52) | Q52: =INDEX(Calib!$I$1:$I$13,$D52)+p_sh_grant*P52 | R52: =INDEX(Calib!$H$1:$H$13,$D52)*M52+p_gov_take*$G52+Q52+0*p_pricing*$J52 | S52: =INDEX(Calib!$Y$1:$Y$13,$D52)-INDEX(Calib!$Z$1:$Z$13,$D52)*(V51/O51-INDEX(Calib!$AA$1:$AA$13,$D52)) | T52: =INDEX(Calib!$X$1:$X$13,$D52)+INDEX(Calib!$G$1:$G$13,$D52)+P52+S52-R52 | U52: =p_rk*W51+Y51*(V51-W51) | V52: =V51+U52+T52 | W52: =INDEX(Calib!$U$1:$U$13,$D52)+(W51-INDEX(Calib!$U$1:$U$13,$D52))*(1-p_amort)+p_sh_conc*P52 | X52: =V52/O52 | Y52: =INDEX(Calib!$K$1:$K$13,$D52)+p_eta*MAX(0,X52-INDEX(Calib!$AA$1:$AA$13,$D52)) | Z52: =(1-INDEX(Calib!$H$1:$H$13,$D52))*(1-p_alpha)*M52+S52 | AA52: =(1-p_delta_g)*AA51*(1-p_eps_g*$E52)+INDEX(Calib!$E$1:$E$13,$D52)*(INDEX(Calib!$G$1:$G$13,$D52)+p_programme*$H52) | AB52: =AB51*(1-p_eps_k*$E52)+p_lambda_k*(AD52-AB51*(1-p_eps_k*$E52)) | AC52: =INDEX(Calib!$R$1:$R$13,$D52)*$F52*(AA51*(1-p_eps_g*$E52))^INDEX(Calib!$Q$1:$Q$13,$D52)*(AB51*(1-p_eps_k*$E52))^p_alpha | AD52: =p_alpha*(1-INDEX(Calib!$H$1:$H$13,$D52))*AC52/(INDEX(Calib!$K$1:$K$13,$D52)+p_delta) | AE52: =AC52+$G52 | AF52: =p_programme*($H52+$I52) | AG52: =INDEX(Calib!$I$1:$I$13,$D52)+p_sh_grant*AF52 | AH52: =INDEX(Calib!$H$1:$H$13,$D52)*AC52+p_gov_take*$G52+AG52+p_programme*p_pricing*$J52 | AI52: =INDEX(Calib!$Y$1:$Y$13,$D52)-INDEX(Calib!$Z$1:$Z$13,$D52)*(AL51/AE51-INDEX(Calib!$AA$1:$AA$13,$D52)) | AJ52: =INDEX(Calib!$X$1:$X$13,$D52)+INDEX(Calib!$G$1:$G$13,$D52)+AF52+AI52-AH52 | AK52: =p_rk*AM51+AO51*(AL51-AM51) | AL52: =AL51+AK52+AJ52 | AM52: =INDEX(Calib!$U$1:$U$13,$D52)+(AM51-INDEX(Calib!$U$1:$U$13,$D52))*(1-p_amort)+p_sh_conc*AF52 | AN52: =AL52/AE52 | AO52: =INDEX(Calib!$K$1:$K$13,$D52)+p_eta*MAX(0,AN52-INDEX(Calib!$AA$1:$AA$13,$D52)) | AP52: =(1-INDEX(Calib!$H$1:$H$13,$D52))*(1-p_alpha)*AC52+AI52 | AQ52: =(AE52/O52-1)*100 | AR52: =(AE52/AE29-1)*100 | AS52: =(O52/O29-1)*100 | AT52: =(AN52-X52)*100 | AU52: =(AP52/Z52-1)*100 | AV52: =(AI52-S52)*100
A53: SLE | B53: 2048 | C53: 24 | D53: 3 | E53: =IF(AND(p_dis_year>0,B53=p_dis_year),1,0) | F53: =IF(AND(p_dis_year>0,B53>=p_dis_year),1-p_eps_a*p_rho_a^(B53-p_dis_year),1) | G53: =INDEX(Calib!$N$1:$N$13,$D53)*(1-p_rent_decline*MIN(1,C53/26)) | H53: =IF(C53=0,0,SUMIFS(dl_val,dl_iso,$A53,dl_ind,"pub_cap",dl_year,$B53)/100) | I53: =IF(C53=0,0,SUMIFS(dl_val,dl_iso,$A53,dl_ind,"pub_spend",dl_year,$B53)/100) | J53: =IF(C53=0,0,SUMIFS(dl_val,dl_iso,$A53,dl_ind,"rev",dl_year,$B53)/100) | K53: =(1-p_delta_g)*K52*(1-p_eps_g*$E53)+INDEX(Calib!$E$1:$E$13,$D53)*(INDEX(Calib!$G$1:$G$13,$D53)+0*$H53) | L53: =L52*(1-p_eps_k*$E53)+p_lambda_k*(N53-L52*(1-p_eps_k*$E53)) | M53: =INDEX(Calib!$R$1:$R$13,$D53)*$F53*(K52*(1-p_eps_g*$E53))^INDEX(Calib!$Q$1:$Q$13,$D53)*(L52*(1-p_eps_k*$E53))^p_alpha | N53: =p_alpha*(1-INDEX(Calib!$H$1:$H$13,$D53))*M53/(INDEX(Calib!$K$1:$K$13,$D53)+p_delta) | O53: =M53+$G53 | P53: =0*($H53+$I53) | Q53: =INDEX(Calib!$I$1:$I$13,$D53)+p_sh_grant*P53 | R53: =INDEX(Calib!$H$1:$H$13,$D53)*M53+p_gov_take*$G53+Q53+0*p_pricing*$J53 | S53: =INDEX(Calib!$Y$1:$Y$13,$D53)-INDEX(Calib!$Z$1:$Z$13,$D53)*(V52/O52-INDEX(Calib!$AA$1:$AA$13,$D53)) | T53: =INDEX(Calib!$X$1:$X$13,$D53)+INDEX(Calib!$G$1:$G$13,$D53)+P53+S53-R53 | U53: =p_rk*W52+Y52*(V52-W52) | V53: =V52+U53+T53 | W53: =INDEX(Calib!$U$1:$U$13,$D53)+(W52-INDEX(Calib!$U$1:$U$13,$D53))*(1-p_amort)+p_sh_conc*P53 | X53: =V53/O53 | Y53: =INDEX(Calib!$K$1:$K$13,$D53)+p_eta*MAX(0,X53-INDEX(Calib!$AA$1:$AA$13,$D53)) | Z53: =(1-INDEX(Calib!$H$1:$H$13,$D53))*(1-p_alpha)*M53+S53 | AA53: =(1-p_delta_g)*AA52*(1-p_eps_g*$E53)+INDEX(Calib!$E$1:$E$13,$D53)*(INDEX(Calib!$G$1:$G$13,$D53)+p_programme*$H53) | AB53: =AB52*(1-p_eps_k*$E53)+p_lambda_k*(AD53-AB52*(1-p_eps_k*$E53)) | AC53: =INDEX(Calib!$R$1:$R$13,$D53)*$F53*(AA52*(1-p_eps_g*$E53))^INDEX(Calib!$Q$1:$Q$13,$D53)*(AB52*(1-p_eps_k*$E53))^p_alpha | AD53: =p_alpha*(1-INDEX(Calib!$H$1:$H$13,$D53))*AC53/(INDEX(Calib!$K$1:$K$13,$D53)+p_delta) | AE53: =AC53+$G53 | AF53: =p_programme*($H53+$I53) | AG53: =INDEX(Calib!$I$1:$I$13,$D53)+p_sh_grant*AF53 | AH53: =INDEX(Calib!$H$1:$H$13,$D53)*AC53+p_gov_take*$G53+AG53+p_programme*p_pricing*$J53 | AI53: =INDEX(Calib!$Y$1:$Y$13,$D53)-INDEX(Calib!$Z$1:$Z$13,$D53)*(AL52/AE52-INDEX(Calib!$AA$1:$AA$13,$D53)) | AJ53: =INDEX(Calib!$X$1:$X$13,$D53)+INDEX(Calib!$G$1:$G$13,$D53)+AF53+AI53-AH53 | AK53: =p_rk*AM52+AO52*(AL52-AM52) | AL53: =AL52+AK53+AJ53 | AM53: =INDEX(Calib!$U$1:$U$13,$D53)+(AM52-INDEX(Calib!$U$1:$U$13,$D53))*(1-p_amort)+p_sh_conc*AF53 | AN53: =AL53/AE53 | AO53: =INDEX(Calib!$K$1:$K$13,$D53)+p_eta*MAX(0,AN53-INDEX(Calib!$AA$1:$AA$13,$D53)) | AP53: =(1-INDEX(Calib!$H$1:$H$13,$D53))*(1-p_alpha)*AC53+AI53 | AQ53: =(AE53/O53-1)*100 | AR53: =(AE53/AE29-1)*100 | AS53: =(O53/O29-1)*100 | AT53: =(AN53-X53)*100 | AU53: =(AP53/Z53-1)*100 | AV53: =(AI53-S53)*100
A54: SLE | B54: 2049 | C54: 25 | D54: 3 | E54: =IF(AND(p_dis_year>0,B54=p_dis_year),1,0) | F54: =IF(AND(p_dis_year>0,B54>=p_dis_year),1-p_eps_a*p_rho_a^(B54-p_dis_year),1) | G54: =INDEX(Calib!$N$1:$N$13,$D54)*(1-p_rent_decline*MIN(1,C54/26)) | H54: =IF(C54=0,0,SUMIFS(dl_val,dl_iso,$A54,dl_ind,"pub_cap",dl_year,$B54)/100) | I54: =IF(C54=0,0,SUMIFS(dl_val,dl_iso,$A54,dl_ind,"pub_spend",dl_year,$B54)/100) | J54: =IF(C54=0,0,SUMIFS(dl_val,dl_iso,$A54,dl_ind,"rev",dl_year,$B54)/100) | K54: =(1-p_delta_g)*K53*(1-p_eps_g*$E54)+INDEX(Calib!$E$1:$E$13,$D54)*(INDEX(Calib!$G$1:$G$13,$D54)+0*$H54) | L54: =L53*(1-p_eps_k*$E54)+p_lambda_k*(N54-L53*(1-p_eps_k*$E54)) | M54: =INDEX(Calib!$R$1:$R$13,$D54)*$F54*(K53*(1-p_eps_g*$E54))^INDEX(Calib!$Q$1:$Q$13,$D54)*(L53*(1-p_eps_k*$E54))^p_alpha | N54: =p_alpha*(1-INDEX(Calib!$H$1:$H$13,$D54))*M54/(INDEX(Calib!$K$1:$K$13,$D54)+p_delta) | O54: =M54+$G54 | P54: =0*($H54+$I54) | Q54: =INDEX(Calib!$I$1:$I$13,$D54)+p_sh_grant*P54 | R54: =INDEX(Calib!$H$1:$H$13,$D54)*M54+p_gov_take*$G54+Q54+0*p_pricing*$J54 | S54: =INDEX(Calib!$Y$1:$Y$13,$D54)-INDEX(Calib!$Z$1:$Z$13,$D54)*(V53/O53-INDEX(Calib!$AA$1:$AA$13,$D54)) | T54: =INDEX(Calib!$X$1:$X$13,$D54)+INDEX(Calib!$G$1:$G$13,$D54)+P54+S54-R54 | U54: =p_rk*W53+Y53*(V53-W53) | V54: =V53+U54+T54 | W54: =INDEX(Calib!$U$1:$U$13,$D54)+(W53-INDEX(Calib!$U$1:$U$13,$D54))*(1-p_amort)+p_sh_conc*P54 | X54: =V54/O54 | Y54: =INDEX(Calib!$K$1:$K$13,$D54)+p_eta*MAX(0,X54-INDEX(Calib!$AA$1:$AA$13,$D54)) | Z54: =(1-INDEX(Calib!$H$1:$H$13,$D54))*(1-p_alpha)*M54+S54 | AA54: =(1-p_delta_g)*AA53*(1-p_eps_g*$E54)+INDEX(Calib!$E$1:$E$13,$D54)*(INDEX(Calib!$G$1:$G$13,$D54)+p_programme*$H54) | AB54: =AB53*(1-p_eps_k*$E54)+p_lambda_k*(AD54-AB53*(1-p_eps_k*$E54)) | AC54: =INDEX(Calib!$R$1:$R$13,$D54)*$F54*(AA53*(1-p_eps_g*$E54))^INDEX(Calib!$Q$1:$Q$13,$D54)*(AB53*(1-p_eps_k*$E54))^p_alpha | AD54: =p_alpha*(1-INDEX(Calib!$H$1:$H$13,$D54))*AC54/(INDEX(Calib!$K$1:$K$13,$D54)+p_delta) | AE54: =AC54+$G54 | AF54: =p_programme*($H54+$I54) | AG54: =INDEX(Calib!$I$1:$I$13,$D54)+p_sh_grant*AF54 | AH54: =INDEX(Calib!$H$1:$H$13,$D54)*AC54+p_gov_take*$G54+AG54+p_programme*p_pricing*$J54 | AI54: =INDEX(Calib!$Y$1:$Y$13,$D54)-INDEX(Calib!$Z$1:$Z$13,$D54)*(AL53/AE53-INDEX(Calib!$AA$1:$AA$13,$D54)) | AJ54: =INDEX(Calib!$X$1:$X$13,$D54)+INDEX(Calib!$G$1:$G$13,$D54)+AF54+AI54-AH54 | AK54: =p_rk*AM53+AO53*(AL53-AM53) | AL54: =AL53+AK54+AJ54 | AM54: =INDEX(Calib!$U$1:$U$13,$D54)+(AM53-INDEX(Calib!$U$1:$U$13,$D54))*(1-p_amort)+p_sh_conc*AF54 | AN54: =AL54/AE54 | AO54: =INDEX(Calib!$K$1:$K$13,$D54)+p_eta*MAX(0,AN54-INDEX(Calib!$AA$1:$AA$13,$D54)) | AP54: =(1-INDEX(Calib!$H$1:$H$13,$D54))*(1-p_alpha)*AC54+AI54 | AQ54: =(AE54/O54-1)*100 | AR54: =(AE54/AE29-1)*100 | AS54: =(O54/O29-1)*100 | AT54: =(AN54-X54)*100 | AU54: =(AP54/Z54-1)*100 | AV54: =(AI54-S54)*100
A55: SLE | B55: 2050 | C55: 26 | D55: 3 | E55: =IF(AND(p_dis_year>0,B55=p_dis_year),1,0) | F55: =IF(AND(p_dis_year>0,B55>=p_dis_year),1-p_eps_a*p_rho_a^(B55-p_dis_year),1) | G55: =INDEX(Calib!$N$1:$N$13,$D55)*(1-p_rent_decline*MIN(1,C55/26)) | H55: =IF(C55=0,0,SUMIFS(dl_val,dl_iso,$A55,dl_ind,"pub_cap",dl_year,$B55)/100) | I55: =IF(C55=0,0,SUMIFS(dl_val,dl_iso,$A55,dl_ind,"pub_spend",dl_year,$B55)/100) | J55: =IF(C55=0,0,SUMIFS(dl_val,dl_iso,$A55,dl_ind,"rev",dl_year,$B55)/100) | K55: =(1-p_delta_g)*K54*(1-p_eps_g*$E55)+INDEX(Calib!$E$1:$E$13,$D55)*(INDEX(Calib!$G$1:$G$13,$D55)+0*$H55) | L55: =L54*(1-p_eps_k*$E55)+p_lambda_k*(N55-L54*(1-p_eps_k*$E55)) | M55: =INDEX(Calib!$R$1:$R$13,$D55)*$F55*(K54*(1-p_eps_g*$E55))^INDEX(Calib!$Q$1:$Q$13,$D55)*(L54*(1-p_eps_k*$E55))^p_alpha | N55: =p_alpha*(1-INDEX(Calib!$H$1:$H$13,$D55))*M55/(INDEX(Calib!$K$1:$K$13,$D55)+p_delta) | O55: =M55+$G55 | P55: =0*($H55+$I55) | Q55: =INDEX(Calib!$I$1:$I$13,$D55)+p_sh_grant*P55 | R55: =INDEX(Calib!$H$1:$H$13,$D55)*M55+p_gov_take*$G55+Q55+0*p_pricing*$J55 | S55: =INDEX(Calib!$Y$1:$Y$13,$D55)-INDEX(Calib!$Z$1:$Z$13,$D55)*(V54/O54-INDEX(Calib!$AA$1:$AA$13,$D55)) | T55: =INDEX(Calib!$X$1:$X$13,$D55)+INDEX(Calib!$G$1:$G$13,$D55)+P55+S55-R55 | U55: =p_rk*W54+Y54*(V54-W54) | V55: =V54+U55+T55 | W55: =INDEX(Calib!$U$1:$U$13,$D55)+(W54-INDEX(Calib!$U$1:$U$13,$D55))*(1-p_amort)+p_sh_conc*P55 | X55: =V55/O55 | Y55: =INDEX(Calib!$K$1:$K$13,$D55)+p_eta*MAX(0,X55-INDEX(Calib!$AA$1:$AA$13,$D55)) | Z55: =(1-INDEX(Calib!$H$1:$H$13,$D55))*(1-p_alpha)*M55+S55 | AA55: =(1-p_delta_g)*AA54*(1-p_eps_g*$E55)+INDEX(Calib!$E$1:$E$13,$D55)*(INDEX(Calib!$G$1:$G$13,$D55)+p_programme*$H55) | AB55: =AB54*(1-p_eps_k*$E55)+p_lambda_k*(AD55-AB54*(1-p_eps_k*$E55)) | AC55: =INDEX(Calib!$R$1:$R$13,$D55)*$F55*(AA54*(1-p_eps_g*$E55))^INDEX(Calib!$Q$1:$Q$13,$D55)*(AB54*(1-p_eps_k*$E55))^p_alpha | AD55: =p_alpha*(1-INDEX(Calib!$H$1:$H$13,$D55))*AC55/(INDEX(Calib!$K$1:$K$13,$D55)+p_delta) | AE55: =AC55+$G55 | AF55: =p_programme*($H55+$I55) | AG55: =INDEX(Calib!$I$1:$I$13,$D55)+p_sh_grant*AF55 | AH55: =INDEX(Calib!$H$1:$H$13,$D55)*AC55+p_gov_take*$G55+AG55+p_programme*p_pricing*$J55 | AI55: =INDEX(Calib!$Y$1:$Y$13,$D55)-INDEX(Calib!$Z$1:$Z$13,$D55)*(AL54/AE54-INDEX(Calib!$AA$1:$AA$13,$D55)) | AJ55: =INDEX(Calib!$X$1:$X$13,$D55)+INDEX(Calib!$G$1:$G$13,$D55)+AF55+AI55-AH55 | AK55: =p_rk*AM54+AO54*(AL54-AM54) | AL55: =AL54+AK55+AJ55 | AM55: =INDEX(Calib!$U$1:$U$13,$D55)+(AM54-INDEX(Calib!$U$1:$U$13,$D55))*(1-p_amort)+p_sh_conc*AF55 | AN55: =AL55/AE55 | AO55: =INDEX(Calib!$K$1:$K$13,$D55)+p_eta*MAX(0,AN55-INDEX(Calib!$AA$1:$AA$13,$D55)) | AP55: =(1-INDEX(Calib!$H$1:$H$13,$D55))*(1-p_alpha)*AC55+AI55 | AQ55: =(AE55/O55-1)*100 | AR55: =(AE55/AE29-1)*100 | AS55: =(O55/O29-1)*100 | AT55: =(AN55-X55)*100 | AU55: =(AP55/Z55-1)*100 | AV55: =(AI55-S55)*100
A56: UGA | B56: 2024 | C56: 0 | D56: 4 | E56: =IF(AND(p_dis_year>0,B56=p_dis_year),1,0) | F56: =IF(AND(p_dis_year>0,B56>=p_dis_year),1-p_eps_a*p_rho_a^(B56-p_dis_year),1) | G56: =INDEX(Calib!$N$1:$N$13,$D56)*(1-p_rent_decline*MIN(1,C56/26)) | H56: =IF(C56=0,0,SUMIFS(dl_val,dl_iso,$A56,dl_ind,"pub_cap",dl_year,$B56)/100) | I56: =IF(C56=0,0,SUMIFS(dl_val,dl_iso,$A56,dl_ind,"pub_spend",dl_year,$B56)/100) | J56: =IF(C56=0,0,SUMIFS(dl_val,dl_iso,$A56,dl_ind,"rev",dl_year,$B56)/100) | K56: =INDEX(Calib!$P$1:$P$13,$D56) | L56: =INDEX(Calib!$O$1:$O$13,$D56) | M56: =1 | N56: =INDEX(Calib!$O$1:$O$13,$D56) | O56: =INDEX(Calib!$S$1:$S$13,$D56) | P56: =0 | Q56: =INDEX(Calib!$I$1:$I$13,$D56) | R56: =INDEX(Calib!$W$1:$W$13,$D56) | S56: =INDEX(Calib!$Y$1:$Y$13,$D56) | T56: =-INDEX(Calib!$V$1:$V$13,$D56) | U56: =INDEX(Calib!$V$1:$V$13,$D56) | V56: =INDEX(Calib!$T$1:$T$13,$D56) | W56: =INDEX(Calib!$U$1:$U$13,$D56) | X56: =V56/O56 | Y56: =INDEX(Calib!$K$1:$K$13,$D56) | Z56: =(1-INDEX(Calib!$H$1:$H$13,$D56))*(1-p_alpha)*M56+S56 | AA56: =INDEX(Calib!$P$1:$P$13,$D56) | AB56: =INDEX(Calib!$O$1:$O$13,$D56) | AC56: =1 | AD56: =INDEX(Calib!$O$1:$O$13,$D56) | AE56: =INDEX(Calib!$S$1:$S$13,$D56) | AF56: =0 | AG56: =INDEX(Calib!$I$1:$I$13,$D56) | AH56: =INDEX(Calib!$W$1:$W$13,$D56) | AI56: =INDEX(Calib!$Y$1:$Y$13,$D56) | AJ56: =-INDEX(Calib!$V$1:$V$13,$D56) | AK56: =INDEX(Calib!$V$1:$V$13,$D56) | AL56: =INDEX(Calib!$T$1:$T$13,$D56) | AM56: =INDEX(Calib!$U$1:$U$13,$D56) | AN56: =AL56/AE56 | AO56: =INDEX(Calib!$K$1:$K$13,$D56) | AP56: =(1-INDEX(Calib!$H$1:$H$13,$D56))*(1-p_alpha)*AC56+AI56 | AQ56: =(AE56/O56-1)*100 | AR56: =(AE56/AE56-1)*100 | AS56: =(O56/O56-1)*100 | AT56: =(AN56-X56)*100 | AU56: =(AP56/Z56-1)*100 | AV56: =(AI56-S56)*100
A57: UGA | B57: 2025 | C57: 1 | D57: 4 | E57: =IF(AND(p_dis_year>0,B57=p_dis_year),1,0) | F57: =IF(AND(p_dis_year>0,B57>=p_dis_year),1-p_eps_a*p_rho_a^(B57-p_dis_year),1) | G57: =INDEX(Calib!$N$1:$N$13,$D57)*(1-p_rent_decline*MIN(1,C57/26)) | H57: =IF(C57=0,0,SUMIFS(dl_val,dl_iso,$A57,dl_ind,"pub_cap",dl_year,$B57)/100) | I57: =IF(C57=0,0,SUMIFS(dl_val,dl_iso,$A57,dl_ind,"pub_spend",dl_year,$B57)/100) | J57: =IF(C57=0,0,SUMIFS(dl_val,dl_iso,$A57,dl_ind,"rev",dl_year,$B57)/100) | K57: =(1-p_delta_g)*K56*(1-p_eps_g*$E57)+INDEX(Calib!$E$1:$E$13,$D57)*(INDEX(Calib!$G$1:$G$13,$D57)+0*$H57) | L57: =L56*(1-p_eps_k*$E57)+p_lambda_k*(N57-L56*(1-p_eps_k*$E57)) | M57: =INDEX(Calib!$R$1:$R$13,$D57)*$F57*(K56*(1-p_eps_g*$E57))^INDEX(Calib!$Q$1:$Q$13,$D57)*(L56*(1-p_eps_k*$E57))^p_alpha | N57: =p_alpha*(1-INDEX(Calib!$H$1:$H$13,$D57))*M57/(INDEX(Calib!$K$1:$K$13,$D57)+p_delta) | O57: =M57+$G57 | P57: =0*($H57+$I57) | Q57: =INDEX(Calib!$I$1:$I$13,$D57)+p_sh_grant*P57 | R57: =INDEX(Calib!$H$1:$H$13,$D57)*M57+p_gov_take*$G57+Q57+0*p_pricing*$J57 | S57: =INDEX(Calib!$Y$1:$Y$13,$D57)-INDEX(Calib!$Z$1:$Z$13,$D57)*(V56/O56-INDEX(Calib!$AA$1:$AA$13,$D57)) | T57: =INDEX(Calib!$X$1:$X$13,$D57)+INDEX(Calib!$G$1:$G$13,$D57)+P57+S57-R57 | U57: =p_rk*W56+Y56*(V56-W56) | V57: =V56+U57+T57 | W57: =INDEX(Calib!$U$1:$U$13,$D57)+(W56-INDEX(Calib!$U$1:$U$13,$D57))*(1-p_amort)+p_sh_conc*P57 | X57: =V57/O57 | Y57: =INDEX(Calib!$K$1:$K$13,$D57)+p_eta*MAX(0,X57-INDEX(Calib!$AA$1:$AA$13,$D57)) | Z57: =(1-INDEX(Calib!$H$1:$H$13,$D57))*(1-p_alpha)*M57+S57 | AA57: =(1-p_delta_g)*AA56*(1-p_eps_g*$E57)+INDEX(Calib!$E$1:$E$13,$D57)*(INDEX(Calib!$G$1:$G$13,$D57)+p_programme*$H57) | AB57: =AB56*(1-p_eps_k*$E57)+p_lambda_k*(AD57-AB56*(1-p_eps_k*$E57)) | AC57: =INDEX(Calib!$R$1:$R$13,$D57)*$F57*(AA56*(1-p_eps_g*$E57))^INDEX(Calib!$Q$1:$Q$13,$D57)*(AB56*(1-p_eps_k*$E57))^p_alpha | AD57: =p_alpha*(1-INDEX(Calib!$H$1:$H$13,$D57))*AC57/(INDEX(Calib!$K$1:$K$13,$D57)+p_delta) | AE57: =AC57+$G57 | AF57: =p_programme*($H57+$I57) | AG57: =INDEX(Calib!$I$1:$I$13,$D57)+p_sh_grant*AF57 | AH57: =INDEX(Calib!$H$1:$H$13,$D57)*AC57+p_gov_take*$G57+AG57+p_programme*p_pricing*$J57 | AI57: =INDEX(Calib!$Y$1:$Y$13,$D57)-INDEX(Calib!$Z$1:$Z$13,$D57)*(AL56/AE56-INDEX(Calib!$AA$1:$AA$13,$D57)) | AJ57: =INDEX(Calib!$X$1:$X$13,$D57)+INDEX(Calib!$G$1:$G$13,$D57)+AF57+AI57-AH57 | AK57: =p_rk*AM56+AO56*(AL56-AM56) | AL57: =AL56+AK57+AJ57 | AM57: =INDEX(Calib!$U$1:$U$13,$D57)+(AM56-INDEX(Calib!$U$1:$U$13,$D57))*(1-p_amort)+p_sh_conc*AF57 | AN57: =AL57/AE57 | AO57: =INDEX(Calib!$K$1:$K$13,$D57)+p_eta*MAX(0,AN57-INDEX(Calib!$AA$1:$AA$13,$D57)) | AP57: =(1-INDEX(Calib!$H$1:$H$13,$D57))*(1-p_alpha)*AC57+AI57 | AQ57: =(AE57/O57-1)*100 | AR57: =(AE57/AE56-1)*100 | AS57: =(O57/O56-1)*100 | AT57: =(AN57-X57)*100 | AU57: =(AP57/Z57-1)*100 | AV57: =(AI57-S57)*100
A58: UGA | B58: 2026 | C58: 2 | D58: 4 | E58: =IF(AND(p_dis_year>0,B58=p_dis_year),1,0) | F58: =IF(AND(p_dis_year>0,B58>=p_dis_year),1-p_eps_a*p_rho_a^(B58-p_dis_year),1) | G58: =INDEX(Calib!$N$1:$N$13,$D58)*(1-p_rent_decline*MIN(1,C58/26)) | H58: =IF(C58=0,0,SUMIFS(dl_val,dl_iso,$A58,dl_ind,"pub_cap",dl_year,$B58)/100) | I58: =IF(C58=0,0,SUMIFS(dl_val,dl_iso,$A58,dl_ind,"pub_spend",dl_year,$B58)/100) | J58: =IF(C58=0,0,SUMIFS(dl_val,dl_iso,$A58,dl_ind,"rev",dl_year,$B58)/100) | K58: =(1-p_delta_g)*K57*(1-p_eps_g*$E58)+INDEX(Calib!$E$1:$E$13,$D58)*(INDEX(Calib!$G$1:$G$13,$D58)+0*$H58) | L58: =L57*(1-p_eps_k*$E58)+p_lambda_k*(N58-L57*(1-p_eps_k*$E58)) | M58: =INDEX(Calib!$R$1:$R$13,$D58)*$F58*(K57*(1-p_eps_g*$E58))^INDEX(Calib!$Q$1:$Q$13,$D58)*(L57*(1-p_eps_k*$E58))^p_alpha | N58: =p_alpha*(1-INDEX(Calib!$H$1:$H$13,$D58))*M58/(INDEX(Calib!$K$1:$K$13,$D58)+p_delta) | O58: =M58+$G58 | P58: =0*($H58+$I58) | Q58: =INDEX(Calib!$I$1:$I$13,$D58)+p_sh_grant*P58 | R58: =INDEX(Calib!$H$1:$H$13,$D58)*M58+p_gov_take*$G58+Q58+0*p_pricing*$J58 | S58: =INDEX(Calib!$Y$1:$Y$13,$D58)-INDEX(Calib!$Z$1:$Z$13,$D58)*(V57/O57-INDEX(Calib!$AA$1:$AA$13,$D58)) | T58: =INDEX(Calib!$X$1:$X$13,$D58)+INDEX(Calib!$G$1:$G$13,$D58)+P58+S58-R58 | U58: =p_rk*W57+Y57*(V57-W57) | V58: =V57+U58+T58 | W58: =INDEX(Calib!$U$1:$U$13,$D58)+(W57-INDEX(Calib!$U$1:$U$13,$D58))*(1-p_amort)+p_sh_conc*P58 | X58: =V58/O58 | Y58: =INDEX(Calib!$K$1:$K$13,$D58)+p_eta*MAX(0,X58-INDEX(Calib!$AA$1:$AA$13,$D58)) | Z58: =(1-INDEX(Calib!$H$1:$H$13,$D58))*(1-p_alpha)*M58+S58 | AA58: =(1-p_delta_g)*AA57*(1-p_eps_g*$E58)+INDEX(Calib!$E$1:$E$13,$D58)*(INDEX(Calib!$G$1:$G$13,$D58)+p_programme*$H58) | AB58: =AB57*(1-p_eps_k*$E58)+p_lambda_k*(AD58-AB57*(1-p_eps_k*$E58)) | AC58: =INDEX(Calib!$R$1:$R$13,$D58)*$F58*(AA57*(1-p_eps_g*$E58))^INDEX(Calib!$Q$1:$Q$13,$D58)*(AB57*(1-p_eps_k*$E58))^p_alpha | AD58: =p_alpha*(1-INDEX(Calib!$H$1:$H$13,$D58))*AC58/(INDEX(Calib!$K$1:$K$13,$D58)+p_delta) | AE58: =AC58+$G58 | AF58: =p_programme*($H58+$I58) | AG58: =INDEX(Calib!$I$1:$I$13,$D58)+p_sh_grant*AF58 | AH58: =INDEX(Calib!$H$1:$H$13,$D58)*AC58+p_gov_take*$G58+AG58+p_programme*p_pricing*$J58 | AI58: =INDEX(Calib!$Y$1:$Y$13,$D58)-INDEX(Calib!$Z$1:$Z$13,$D58)*(AL57/AE57-INDEX(Calib!$AA$1:$AA$13,$D58)) | AJ58: =INDEX(Calib!$X$1:$X$13,$D58)+INDEX(Calib!$G$1:$G$13,$D58)+AF58+AI58-AH58 | AK58: =p_rk*AM57+AO57*(AL57-AM57) | AL58: =AL57+AK58+AJ58 | AM58: =INDEX(Calib!$U$1:$U$13,$D58)+(AM57-INDEX(Calib!$U$1:$U$13,$D58))*(1-p_amort)+p_sh_conc*AF58 | AN58: =AL58/AE58 | AO58: =INDEX(Calib!$K$1:$K$13,$D58)+p_eta*MAX(0,AN58-INDEX(Calib!$AA$1:$AA$13,$D58)) | AP58: =(1-INDEX(Calib!$H$1:$H$13,$D58))*(1-p_alpha)*AC58+AI58 | AQ58: =(AE58/O58-1)*100 | AR58: =(AE58/AE56-1)*100 | AS58: =(O58/O56-1)*100 | AT58: =(AN58-X58)*100 | AU58: =(AP58/Z58-1)*100 | AV58: =(AI58-S58)*100
A59: UGA | B59: 2027 | C59: 3 | D59: 4 | E59: =IF(AND(p_dis_year>0,B59=p_dis_year),1,0) | F59: =IF(AND(p_dis_year>0,B59>=p_dis_year),1-p_eps_a*p_rho_a^(B59-p_dis_year),1) | G59: =INDEX(Calib!$N$1:$N$13,$D59)*(1-p_rent_decline*MIN(1,C59/26)) | H59: =IF(C59=0,0,SUMIFS(dl_val,dl_iso,$A59,dl_ind,"pub_cap",dl_year,$B59)/100) | I59: =IF(C59=0,0,SUMIFS(dl_val,dl_iso,$A59,dl_ind,"pub_spend",dl_year,$B59)/100) | J59: =IF(C59=0,0,SUMIFS(dl_val,dl_iso,$A59,dl_ind,"rev",dl_year,$B59)/100) | K59: =(1-p_delta_g)*K58*(1-p_eps_g*$E59)+INDEX(Calib!$E$1:$E$13,$D59)*(INDEX(Calib!$G$1:$G$13,$D59)+0*$H59) | L59: =L58*(1-p_eps_k*$E59)+p_lambda_k*(N59-L58*(1-p_eps_k*$E59)) | M59: =INDEX(Calib!$R$1:$R$13,$D59)*$F59*(K58*(1-p_eps_g*$E59))^INDEX(Calib!$Q$1:$Q$13,$D59)*(L58*(1-p_eps_k*$E59))^p_alpha | N59: =p_alpha*(1-INDEX(Calib!$H$1:$H$13,$D59))*M59/(INDEX(Calib!$K$1:$K$13,$D59)+p_delta) | O59: =M59+$G59 | P59: =0*($H59+$I59) | Q59: =INDEX(Calib!$I$1:$I$13,$D59)+p_sh_grant*P59 | R59: =INDEX(Calib!$H$1:$H$13,$D59)*M59+p_gov_take*$G59+Q59+0*p_pricing*$J59 | S59: =INDEX(Calib!$Y$1:$Y$13,$D59)-INDEX(Calib!$Z$1:$Z$13,$D59)*(V58/O58-INDEX(Calib!$AA$1:$AA$13,$D59)) | T59: =INDEX(Calib!$X$1:$X$13,$D59)+INDEX(Calib!$G$1:$G$13,$D59)+P59+S59-R59 | U59: =p_rk*W58+Y58*(V58-W58) | V59: =V58+U59+T59 | W59: =INDEX(Calib!$U$1:$U$13,$D59)+(W58-INDEX(Calib!$U$1:$U$13,$D59))*(1-p_amort)+p_sh_conc*P59 | X59: =V59/O59 | Y59: =INDEX(Calib!$K$1:$K$13,$D59)+p_eta*MAX(0,X59-INDEX(Calib!$AA$1:$AA$13,$D59)) | Z59: =(1-INDEX(Calib!$H$1:$H$13,$D59))*(1-p_alpha)*M59+S59 | AA59: =(1-p_delta_g)*AA58*(1-p_eps_g*$E59)+INDEX(Calib!$E$1:$E$13,$D59)*(INDEX(Calib!$G$1:$G$13,$D59)+p_programme*$H59) | AB59: =AB58*(1-p_eps_k*$E59)+p_lambda_k*(AD59-AB58*(1-p_eps_k*$E59)) | AC59: =INDEX(Calib!$R$1:$R$13,$D59)*$F59*(AA58*(1-p_eps_g*$E59))^INDEX(Calib!$Q$1:$Q$13,$D59)*(AB58*(1-p_eps_k*$E59))^p_alpha | AD59: =p_alpha*(1-INDEX(Calib!$H$1:$H$13,$D59))*AC59/(INDEX(Calib!$K$1:$K$13,$D59)+p_delta) | AE59: =AC59+$G59 | AF59: =p_programme*($H59+$I59) | AG59: =INDEX(Calib!$I$1:$I$13,$D59)+p_sh_grant*AF59 | AH59: =INDEX(Calib!$H$1:$H$13,$D59)*AC59+p_gov_take*$G59+AG59+p_programme*p_pricing*$J59 | AI59: =INDEX(Calib!$Y$1:$Y$13,$D59)-INDEX(Calib!$Z$1:$Z$13,$D59)*(AL58/AE58-INDEX(Calib!$AA$1:$AA$13,$D59)) | AJ59: =INDEX(Calib!$X$1:$X$13,$D59)+INDEX(Calib!$G$1:$G$13,$D59)+AF59+AI59-AH59 | AK59: =p_rk*AM58+AO58*(AL58-AM58) | AL59: =AL58+AK59+AJ59 | AM59: =INDEX(Calib!$U$1:$U$13,$D59)+(AM58-INDEX(Calib!$U$1:$U$13,$D59))*(1-p_amort)+p_sh_conc*AF59 | AN59: =AL59/AE59 | AO59: =INDEX(Calib!$K$1:$K$13,$D59)+p_eta*MAX(0,AN59-INDEX(Calib!$AA$1:$AA$13,$D59)) | AP59: =(1-INDEX(Calib!$H$1:$H$13,$D59))*(1-p_alpha)*AC59+AI59 | AQ59: =(AE59/O59-1)*100 | AR59: =(AE59/AE56-1)*100 | AS59: =(O59/O56-1)*100 | AT59: =(AN59-X59)*100 | AU59: =(AP59/Z59-1)*100 | AV59: =(AI59-S59)*100
A60: UGA | B60: 2028 | C60: 4 | D60: 4 | E60: =IF(AND(p_dis_year>0,B60=p_dis_year),1,0) | F60: =IF(AND(p_dis_year>0,B60>=p_dis_year),1-p_eps_a*p_rho_a^(B60-p_dis_year),1) | G60: =INDEX(Calib!$N$1:$N$13,$D60)*(1-p_rent_decline*MIN(1,C60/26)) | H60: =IF(C60=0,0,SUMIFS(dl_val,dl_iso,$A60,dl_ind,"pub_cap",dl_year,$B60)/100) | I60: =IF(C60=0,0,SUMIFS(dl_val,dl_iso,$A60,dl_ind,"pub_spend",dl_year,$B60)/100) | J60: =IF(C60=0,0,SUMIFS(dl_val,dl_iso,$A60,dl_ind,"rev",dl_year,$B60)/100) | K60: =(1-p_delta_g)*K59*(1-p_eps_g*$E60)+INDEX(Calib!$E$1:$E$13,$D60)*(INDEX(Calib!$G$1:$G$13,$D60)+0*$H60) | L60: =L59*(1-p_eps_k*$E60)+p_lambda_k*(N60-L59*(1-p_eps_k*$E60)) | M60: =INDEX(Calib!$R$1:$R$13,$D60)*$F60*(K59*(1-p_eps_g*$E60))^INDEX(Calib!$Q$1:$Q$13,$D60)*(L59*(1-p_eps_k*$E60))^p_alpha | N60: =p_alpha*(1-INDEX(Calib!$H$1:$H$13,$D60))*M60/(INDEX(Calib!$K$1:$K$13,$D60)+p_delta) | O60: =M60+$G60 | P60: =0*($H60+$I60) | Q60: =INDEX(Calib!$I$1:$I$13,$D60)+p_sh_grant*P60 | R60: =INDEX(Calib!$H$1:$H$13,$D60)*M60+p_gov_take*$G60+Q60+0*p_pricing*$J60 | S60: =INDEX(Calib!$Y$1:$Y$13,$D60)-INDEX(Calib!$Z$1:$Z$13,$D60)*(V59/O59-INDEX(Calib!$AA$1:$AA$13,$D60)) | T60: =INDEX(Calib!$X$1:$X$13,$D60)+INDEX(Calib!$G$1:$G$13,$D60)+P60+S60-R60 | U60: =p_rk*W59+Y59*(V59-W59) | V60: =V59+U60+T60 | W60: =INDEX(Calib!$U$1:$U$13,$D60)+(W59-INDEX(Calib!$U$1:$U$13,$D60))*(1-p_amort)+p_sh_conc*P60 | X60: =V60/O60 | Y60: =INDEX(Calib!$K$1:$K$13,$D60)+p_eta*MAX(0,X60-INDEX(Calib!$AA$1:$AA$13,$D60)) | Z60: =(1-INDEX(Calib!$H$1:$H$13,$D60))*(1-p_alpha)*M60+S60 | AA60: =(1-p_delta_g)*AA59*(1-p_eps_g*$E60)+INDEX(Calib!$E$1:$E$13,$D60)*(INDEX(Calib!$G$1:$G$13,$D60)+p_programme*$H60) | AB60: =AB59*(1-p_eps_k*$E60)+p_lambda_k*(AD60-AB59*(1-p_eps_k*$E60)) | AC60: =INDEX(Calib!$R$1:$R$13,$D60)*$F60*(AA59*(1-p_eps_g*$E60))^INDEX(Calib!$Q$1:$Q$13,$D60)*(AB59*(1-p_eps_k*$E60))^p_alpha | AD60: =p_alpha*(1-INDEX(Calib!$H$1:$H$13,$D60))*AC60/(INDEX(Calib!$K$1:$K$13,$D60)+p_delta) | AE60: =AC60+$G60 | AF60: =p_programme*($H60+$I60) | AG60: =INDEX(Calib!$I$1:$I$13,$D60)+p_sh_grant*AF60 | AH60: =INDEX(Calib!$H$1:$H$13,$D60)*AC60+p_gov_take*$G60+AG60+p_programme*p_pricing*$J60 | AI60: =INDEX(Calib!$Y$1:$Y$13,$D60)-INDEX(Calib!$Z$1:$Z$13,$D60)*(AL59/AE59-INDEX(Calib!$AA$1:$AA$13,$D60)) | AJ60: =INDEX(Calib!$X$1:$X$13,$D60)+INDEX(Calib!$G$1:$G$13,$D60)+AF60+AI60-AH60 | AK60: =p_rk*AM59+AO59*(AL59-AM59) | AL60: =AL59+AK60+AJ60 | AM60: =INDEX(Calib!$U$1:$U$13,$D60)+(AM59-INDEX(Calib!$U$1:$U$13,$D60))*(1-p_amort)+p_sh_conc*AF60 | AN60: =AL60/AE60 | AO60: =INDEX(Calib!$K$1:$K$13,$D60)+p_eta*MAX(0,AN60-INDEX(Calib!$AA$1:$AA$13,$D60)) | AP60: =(1-INDEX(Calib!$H$1:$H$13,$D60))*(1-p_alpha)*AC60+AI60 | AQ60: =(AE60/O60-1)*100 | AR60: =(AE60/AE56-1)*100 | AS60: =(O60/O56-1)*100 | AT60: =(AN60-X60)*100 | AU60: =(AP60/Z60-1)*100 | AV60: =(AI60-S60)*100
A61: UGA | B61: 2029 | C61: 5 | D61: 4 | E61: =IF(AND(p_dis_year>0,B61=p_dis_year),1,0) | F61: =IF(AND(p_dis_year>0,B61>=p_dis_year),1-p_eps_a*p_rho_a^(B61-p_dis_year),1) | G61: =INDEX(Calib!$N$1:$N$13,$D61)*(1-p_rent_decline*MIN(1,C61/26)) | H61: =IF(C61=0,0,SUMIFS(dl_val,dl_iso,$A61,dl_ind,"pub_cap",dl_year,$B61)/100) | I61: =IF(C61=0,0,SUMIFS(dl_val,dl_iso,$A61,dl_ind,"pub_spend",dl_year,$B61)/100) | J61: =IF(C61=0,0,SUMIFS(dl_val,dl_iso,$A61,dl_ind,"rev",dl_year,$B61)/100) | K61: =(1-p_delta_g)*K60*(1-p_eps_g*$E61)+INDEX(Calib!$E$1:$E$13,$D61)*(INDEX(Calib!$G$1:$G$13,$D61)+0*$H61) | L61: =L60*(1-p_eps_k*$E61)+p_lambda_k*(N61-L60*(1-p_eps_k*$E61)) | M61: =INDEX(Calib!$R$1:$R$13,$D61)*$F61*(K60*(1-p_eps_g*$E61))^INDEX(Calib!$Q$1:$Q$13,$D61)*(L60*(1-p_eps_k*$E61))^p_alpha | N61: =p_alpha*(1-INDEX(Calib!$H$1:$H$13,$D61))*M61/(INDEX(Calib!$K$1:$K$13,$D61)+p_delta) | O61: =M61+$G61 | P61: =0*($H61+$I61) | Q61: =INDEX(Calib!$I$1:$I$13,$D61)+p_sh_grant*P61 | R61: =INDEX(Calib!$H$1:$H$13,$D61)*M61+p_gov_take*$G61+Q61+0*p_pricing*$J61 | S61: =INDEX(Calib!$Y$1:$Y$13,$D61)-INDEX(Calib!$Z$1:$Z$13,$D61)*(V60/O60-INDEX(Calib!$AA$1:$AA$13,$D61)) | T61: =INDEX(Calib!$X$1:$X$13,$D61)+INDEX(Calib!$G$1:$G$13,$D61)+P61+S61-R61 | U61: =p_rk*W60+Y60*(V60-W60) | V61: =V60+U61+T61 | W61: =INDEX(Calib!$U$1:$U$13,$D61)+(W60-INDEX(Calib!$U$1:$U$13,$D61))*(1-p_amort)+p_sh_conc*P61 | X61: =V61/O61 | Y61: =INDEX(Calib!$K$1:$K$13,$D61)+p_eta*MAX(0,X61-INDEX(Calib!$AA$1:$AA$13,$D61)) | Z61: =(1-INDEX(Calib!$H$1:$H$13,$D61))*(1-p_alpha)*M61+S61 | AA61: =(1-p_delta_g)*AA60*(1-p_eps_g*$E61)+INDEX(Calib!$E$1:$E$13,$D61)*(INDEX(Calib!$G$1:$G$13,$D61)+p_programme*$H61) | AB61: =AB60*(1-p_eps_k*$E61)+p_lambda_k*(AD61-AB60*(1-p_eps_k*$E61)) | AC61: =INDEX(Calib!$R$1:$R$13,$D61)*$F61*(AA60*(1-p_eps_g*$E61))^INDEX(Calib!$Q$1:$Q$13,$D61)*(AB60*(1-p_eps_k*$E61))^p_alpha | AD61: =p_alpha*(1-INDEX(Calib!$H$1:$H$13,$D61))*AC61/(INDEX(Calib!$K$1:$K$13,$D61)+p_delta) | AE61: =AC61+$G61 | AF61: =p_programme*($H61+$I61) | AG61: =INDEX(Calib!$I$1:$I$13,$D61)+p_sh_grant*AF61 | AH61: =INDEX(Calib!$H$1:$H$13,$D61)*AC61+p_gov_take*$G61+AG61+p_programme*p_pricing*$J61 | AI61: =INDEX(Calib!$Y$1:$Y$13,$D61)-INDEX(Calib!$Z$1:$Z$13,$D61)*(AL60/AE60-INDEX(Calib!$AA$1:$AA$13,$D61)) | AJ61: =INDEX(Calib!$X$1:$X$13,$D61)+INDEX(Calib!$G$1:$G$13,$D61)+AF61+AI61-AH61 | AK61: =p_rk*AM60+AO60*(AL60-AM60) | AL61: =AL60+AK61+AJ61 | AM61: =INDEX(Calib!$U$1:$U$13,$D61)+(AM60-INDEX(Calib!$U$1:$U$13,$D61))*(1-p_amort)+p_sh_conc*AF61 | AN61: =AL61/AE61 | AO61: =INDEX(Calib!$K$1:$K$13,$D61)+p_eta*MAX(0,AN61-INDEX(Calib!$AA$1:$AA$13,$D61)) | AP61: =(1-INDEX(Calib!$H$1:$H$13,$D61))*(1-p_alpha)*AC61+AI61 | AQ61: =(AE61/O61-1)*100 | AR61: =(AE61/AE56-1)*100 | AS61: =(O61/O56-1)*100 | AT61: =(AN61-X61)*100 | AU61: =(AP61/Z61-1)*100 | AV61: =(AI61-S61)*100
A62: UGA | B62: 2030 | C62: 6 | D62: 4 | E62: =IF(AND(p_dis_year>0,B62=p_dis_year),1,0) | F62: =IF(AND(p_dis_year>0,B62>=p_dis_year),1-p_eps_a*p_rho_a^(B62-p_dis_year),1) | G62: =INDEX(Calib!$N$1:$N$13,$D62)*(1-p_rent_decline*MIN(1,C62/26)) | H62: =IF(C62=0,0,SUMIFS(dl_val,dl_iso,$A62,dl_ind,"pub_cap",dl_year,$B62)/100) | I62: =IF(C62=0,0,SUMIFS(dl_val,dl_iso,$A62,dl_ind,"pub_spend",dl_year,$B62)/100) | J62: =IF(C62=0,0,SUMIFS(dl_val,dl_iso,$A62,dl_ind,"rev",dl_year,$B62)/100) | K62: =(1-p_delta_g)*K61*(1-p_eps_g*$E62)+INDEX(Calib!$E$1:$E$13,$D62)*(INDEX(Calib!$G$1:$G$13,$D62)+0*$H62) | L62: =L61*(1-p_eps_k*$E62)+p_lambda_k*(N62-L61*(1-p_eps_k*$E62)) | M62: =INDEX(Calib!$R$1:$R$13,$D62)*$F62*(K61*(1-p_eps_g*$E62))^INDEX(Calib!$Q$1:$Q$13,$D62)*(L61*(1-p_eps_k*$E62))^p_alpha | N62: =p_alpha*(1-INDEX(Calib!$H$1:$H$13,$D62))*M62/(INDEX(Calib!$K$1:$K$13,$D62)+p_delta) | O62: =M62+$G62 | P62: =0*($H62+$I62) | Q62: =INDEX(Calib!$I$1:$I$13,$D62)+p_sh_grant*P62 | R62: =INDEX(Calib!$H$1:$H$13,$D62)*M62+p_gov_take*$G62+Q62+0*p_pricing*$J62 | S62: =INDEX(Calib!$Y$1:$Y$13,$D62)-INDEX(Calib!$Z$1:$Z$13,$D62)*(V61/O61-INDEX(Calib!$AA$1:$AA$13,$D62)) | T62: =INDEX(Calib!$X$1:$X$13,$D62)+INDEX(Calib!$G$1:$G$13,$D62)+P62+S62-R62 | U62: =p_rk*W61+Y61*(V61-W61) | V62: =V61+U62+T62 | W62: =INDEX(Calib!$U$1:$U$13,$D62)+(W61-INDEX(Calib!$U$1:$U$13,$D62))*(1-p_amort)+p_sh_conc*P62 | X62: =V62/O62 | Y62: =INDEX(Calib!$K$1:$K$13,$D62)+p_eta*MAX(0,X62-INDEX(Calib!$AA$1:$AA$13,$D62)) | Z62: =(1-INDEX(Calib!$H$1:$H$13,$D62))*(1-p_alpha)*M62+S62 | AA62: =(1-p_delta_g)*AA61*(1-p_eps_g*$E62)+INDEX(Calib!$E$1:$E$13,$D62)*(INDEX(Calib!$G$1:$G$13,$D62)+p_programme*$H62) | AB62: =AB61*(1-p_eps_k*$E62)+p_lambda_k*(AD62-AB61*(1-p_eps_k*$E62)) | AC62: =INDEX(Calib!$R$1:$R$13,$D62)*$F62*(AA61*(1-p_eps_g*$E62))^INDEX(Calib!$Q$1:$Q$13,$D62)*(AB61*(1-p_eps_k*$E62))^p_alpha | AD62: =p_alpha*(1-INDEX(Calib!$H$1:$H$13,$D62))*AC62/(INDEX(Calib!$K$1:$K$13,$D62)+p_delta) | AE62: =AC62+$G62 | AF62: =p_programme*($H62+$I62) | AG62: =INDEX(Calib!$I$1:$I$13,$D62)+p_sh_grant*AF62 | AH62: =INDEX(Calib!$H$1:$H$13,$D62)*AC62+p_gov_take*$G62+AG62+p_programme*p_pricing*$J62 | AI62: =INDEX(Calib!$Y$1:$Y$13,$D62)-INDEX(Calib!$Z$1:$Z$13,$D62)*(AL61/AE61-INDEX(Calib!$AA$1:$AA$13,$D62)) | AJ62: =INDEX(Calib!$X$1:$X$13,$D62)+INDEX(Calib!$G$1:$G$13,$D62)+AF62+AI62-AH62 | AK62: =p_rk*AM61+AO61*(AL61-AM61) | AL62: =AL61+AK62+AJ62 | AM62: =INDEX(Calib!$U$1:$U$13,$D62)+(AM61-INDEX(Calib!$U$1:$U$13,$D62))*(1-p_amort)+p_sh_conc*AF62 | AN62: =AL62/AE62 | AO62: =INDEX(Calib!$K$1:$K$13,$D62)+p_eta*MAX(0,AN62-INDEX(Calib!$AA$1:$AA$13,$D62)) | AP62: =(1-INDEX(Calib!$H$1:$H$13,$D62))*(1-p_alpha)*AC62+AI62 | AQ62: =(AE62/O62-1)*100 | AR62: =(AE62/AE56-1)*100 | AS62: =(O62/O56-1)*100 | AT62: =(AN62-X62)*100 | AU62: =(AP62/Z62-1)*100 | AV62: =(AI62-S62)*100
A63: UGA | B63: 2031 | C63: 7 | D63: 4 | E63: =IF(AND(p_dis_year>0,B63=p_dis_year),1,0) | F63: =IF(AND(p_dis_year>0,B63>=p_dis_year),1-p_eps_a*p_rho_a^(B63-p_dis_year),1) | G63: =INDEX(Calib!$N$1:$N$13,$D63)*(1-p_rent_decline*MIN(1,C63/26)) | H63: =IF(C63=0,0,SUMIFS(dl_val,dl_iso,$A63,dl_ind,"pub_cap",dl_year,$B63)/100) | I63: =IF(C63=0,0,SUMIFS(dl_val,dl_iso,$A63,dl_ind,"pub_spend",dl_year,$B63)/100) | J63: =IF(C63=0,0,SUMIFS(dl_val,dl_iso,$A63,dl_ind,"rev",dl_year,$B63)/100) | K63: =(1-p_delta_g)*K62*(1-p_eps_g*$E63)+INDEX(Calib!$E$1:$E$13,$D63)*(INDEX(Calib!$G$1:$G$13,$D63)+0*$H63) | L63: =L62*(1-p_eps_k*$E63)+p_lambda_k*(N63-L62*(1-p_eps_k*$E63)) | M63: =INDEX(Calib!$R$1:$R$13,$D63)*$F63*(K62*(1-p_eps_g*$E63))^INDEX(Calib!$Q$1:$Q$13,$D63)*(L62*(1-p_eps_k*$E63))^p_alpha | N63: =p_alpha*(1-INDEX(Calib!$H$1:$H$13,$D63))*M63/(INDEX(Calib!$K$1:$K$13,$D63)+p_delta) | O63: =M63+$G63 | P63: =0*($H63+$I63) | Q63: =INDEX(Calib!$I$1:$I$13,$D63)+p_sh_grant*P63 | R63: =INDEX(Calib!$H$1:$H$13,$D63)*M63+p_gov_take*$G63+Q63+0*p_pricing*$J63 | S63: =INDEX(Calib!$Y$1:$Y$13,$D63)-INDEX(Calib!$Z$1:$Z$13,$D63)*(V62/O62-INDEX(Calib!$AA$1:$AA$13,$D63)) | T63: =INDEX(Calib!$X$1:$X$13,$D63)+INDEX(Calib!$G$1:$G$13,$D63)+P63+S63-R63 | U63: =p_rk*W62+Y62*(V62-W62) | V63: =V62+U63+T63 | W63: =INDEX(Calib!$U$1:$U$13,$D63)+(W62-INDEX(Calib!$U$1:$U$13,$D63))*(1-p_amort)+p_sh_conc*P63 | X63: =V63/O63 | Y63: =INDEX(Calib!$K$1:$K$13,$D63)+p_eta*MAX(0,X63-INDEX(Calib!$AA$1:$AA$13,$D63)) | Z63: =(1-INDEX(Calib!$H$1:$H$13,$D63))*(1-p_alpha)*M63+S63 | AA63: =(1-p_delta_g)*AA62*(1-p_eps_g*$E63)+INDEX(Calib!$E$1:$E$13,$D63)*(INDEX(Calib!$G$1:$G$13,$D63)+p_programme*$H63) | AB63: =AB62*(1-p_eps_k*$E63)+p_lambda_k*(AD63-AB62*(1-p_eps_k*$E63)) | AC63: =INDEX(Calib!$R$1:$R$13,$D63)*$F63*(AA62*(1-p_eps_g*$E63))^INDEX(Calib!$Q$1:$Q$13,$D63)*(AB62*(1-p_eps_k*$E63))^p_alpha | AD63: =p_alpha*(1-INDEX(Calib!$H$1:$H$13,$D63))*AC63/(INDEX(Calib!$K$1:$K$13,$D63)+p_delta) | AE63: =AC63+$G63 | AF63: =p_programme*($H63+$I63) | AG63: =INDEX(Calib!$I$1:$I$13,$D63)+p_sh_grant*AF63 | AH63: =INDEX(Calib!$H$1:$H$13,$D63)*AC63+p_gov_take*$G63+AG63+p_programme*p_pricing*$J63 | AI63: =INDEX(Calib!$Y$1:$Y$13,$D63)-INDEX(Calib!$Z$1:$Z$13,$D63)*(AL62/AE62-INDEX(Calib!$AA$1:$AA$13,$D63)) | AJ63: =INDEX(Calib!$X$1:$X$13,$D63)+INDEX(Calib!$G$1:$G$13,$D63)+AF63+AI63-AH63 | AK63: =p_rk*AM62+AO62*(AL62-AM62) | AL63: =AL62+AK63+AJ63 | AM63: =INDEX(Calib!$U$1:$U$13,$D63)+(AM62-INDEX(Calib!$U$1:$U$13,$D63))*(1-p_amort)+p_sh_conc*AF63 | AN63: =AL63/AE63 | AO63: =INDEX(Calib!$K$1:$K$13,$D63)+p_eta*MAX(0,AN63-INDEX(Calib!$AA$1:$AA$13,$D63)) | AP63: =(1-INDEX(Calib!$H$1:$H$13,$D63))*(1-p_alpha)*AC63+AI63 | AQ63: =(AE63/O63-1)*100 | AR63: =(AE63/AE56-1)*100 | AS63: =(O63/O56-1)*100 | AT63: =(AN63-X63)*100 | AU63: =(AP63/Z63-1)*100 | AV63: =(AI63-S63)*100
