Workbook

Sheet Cover
E2: Use these buttons to navigate to data -->
C21: Rethinking Power Sector Reform Data Repository
C23: Model status | D23: Draft final
C24: Date | D24: February 1 2019
C27: <-- Use this symbol to return to cover sheet
B34: DISCLAIMER
B35: This model has been prepared by the World Bank for its advisory services only. Although the World Bank has prepared the model with utmost care and diligence, the Bank cannot be held liable directly or indirectly for the adequacy, completeness or accuracy of the model structure, the assumptions used or results obtained from the model. Anyone using this model does so at their own risk. Model users should carry out their own due diligence and verify all assumptions, calculations and results presented in this model.

Sheet Utilities
B1: Utilities
B2: Colombia (Codensa) | C2: Private | D2: Codensa, a private distribution company, unbundled from the government-owned generation and distribution company Empresa de Energía de Bogotá (EEB), which serves 3.3 million customers in the capital and 100+ municipalities in Cundinamarca
B3: Dominican Republic (Edesur) | C3: Public | D3: Largest of three distribution companies
B4: Egypt, Arab Rep. (Alexandria) | C4: Public | D4: The Alexandria Electricity Distribution Company serves 2.6 million customers in Alexandria Governorate to K. 66 Alex/Matrouh Road.
B5: Egypt, Arab Rep. (Cairo North) | C5: Public | D5: The Cairo North Electricity Distribution Company serves 4.3 million customers in North and East Cairo Sectors, New Cairo, and El-Salam City in Cairo Governorate; and El-Obour City, Khanka, Shoubra El-kheima and El-Qanater in Qalyoubeya Governorate.
B6: Egypt, Arab Rep. (EEHC) | C6: Public | D6: Holding company
B7: India - Andhra Pradesh (APEPDCL) | C7: Public | D7: Eastern Power Distribution Company of Andhra Pradesh Ltd. (APEPDCL), a 100 percent state government-owned distribution company serving the districts of Eluru, Rajahmundry, Srikakulam, Visakhapatanam, and Vizianagaram
B8: India - Andhra Pradesh (APSPDCL) | C8: Public | D8: Southern Power Distribution Company of Andhra Pradesh Ltd. (APSPDCL), a 100 percent state government-owned distribution company with over 1.13 million customers, serving the districts of Anantapur, Chittor, Guntur, Kadapa, Krishna, Kurnool, Nellore, and Prakasam
B9: India - Odisha (CESCO) | C9: Public | D9: Central Electricity Supply Utility of Odisha (CESU) serving primarily domestic customers (90%- 69% rural and 21% urban)
B10: India - Odisha (WESCO) | C10: Public | D10: Western Electricity Supply Company of Odisha Limited (WESCO) is a public distribution company that served the entire western region of Odisha.
B11: India - Rajasthan (AVVN) | C11: Public | D11: Ajmer Vidyut Nigam Limited (AVVNL) which serves 11 districts of Rajasthan
B12: India - Rajasthan (JDVVN) | C12: Public | D12: Jodhpur Vidyut Nigam Limited (JdVVNL) which serves 10 districts
B13: India - Rajasthan (JVVN) | C13: Public | D13: Jaipur Vidyut Nigam Limited (JVVNL) which serves 12 districts
... B28: Vietnam (NPC) | C28: Public | D28: Northern Power Corporation (NPC), one of the five subsidiary distribution companies established during the sector’s reorganization in 2010, 100 percent owned by Viet Nam Electricity (EVN). NPC serves the northern region.
B30: Financial viability | D30: Large govt transfers | E30: Subsidized fuels | F30: Sustained net losses | G30: Large debt service | H30: Excessive payables | I30: Excessive receivables | J30: Sust. neg. operating CF
B31: Colombia (Codensa) | C31: Private | D31: No | E31: No | F31: No | G31: No | H31: No | I31: No | J31: Yes
B32: Dominican Republic (Edesur) | C32: Public | D32: No | E32: No | F32: Yes | G32: * | H32: * | I32: * | J32: Yes
B33: Egypt, Arab Rep. (EEHC) | C33: Public | D33: No | E33: Yes | F33: No | G33: No | H33: Yes | I33: Yes | J33: No
B34: India - Andhra Pradesh (APEPDCL) | C34: Public | D34: * | E34: No | F34: Yes | G34: No | H34: * | I34: * | J34: No
B35: India - Andhra Pradesh (APSPDCL) | C35: Public | D35: * | E35: No | F35: Yes | G35: No | H35: * | I35: * | J35: No
B36: India - Odisha (CESCO) | C36: Public | D36: * | E36: No | F36: Yes | G36: No | H36: * | I36: * | J36: No
B37: India - Odisha (WESCO) | C37: Public | D37: * | E37: No | F37: Yes | G37: No | H37: * | I37: * | J37: No
B38: India - Rajasthan (AVVN) | C38: Public | D38: * | E38: No | F38: Yes | G38: Yes | H38: No | I38: No | J38: No
B39: India - Rajasthan (JDVVN) | C39: Public | D39: * | E39: No | F39: Yes | G39: Yes | H39: No | I39: No | J39: No
B40: India - Rajasthan (JVVN) | C40: Public | D40: * | E40: No | F40: Yes | G40: Yes | H40: No | I40: No | J40: No
B41: Kenya (KPLC) | C41: Public | D41: No | E41: No | F41: No | G41: No | H41: No | I41: No | J41: Yes
B42: Morocco (ONEE) | C42: Public | D42: * | E42: * | F42: * | G42: * | H42: * | I42: * | J42: *
... B54: Vietnam (NPC) | C54: Public | D54: No | E54: No | F54: No | G54: No | H54: * | I54: * | J54: No
B56: Definitions
B57: Large government transfers: If total government transfers exceed 10% of C3 cost recovery
B58: Subsidized fuels: If utility receives fuels below market prices (qualitative information)
B59: Sustained net losses: If net losses exceed 5% of revenue (average of last three years)
B60: Large debt service: If total debt service (interest and principal payments) exceed 20% of C3 cost recovery
B61: Excessive payables: Payables exceed 50% of annual revenues
B62: Excessive receivables: Receivables exceed 50% of annual revenues
B63: Maturity mismatch: (Current liabilities / Non-current liabilities)/(Current assets / [Non-current assets + equity]) > 200%
B64: Large short-term debt: Short-term debt of more than 20% of assets
B65: Sustained negative operating CF: Negative net operating cash flow of more than 5% of revenue

Sheet Graphics
B1: Cost recovery analysis
B2: Country | D2: Operating Cost | E2: Capital Cost | F2: Cash Collected | G2: Billed tariff revenue
B3: ='Cost Recovery'!B187 -> Senegal | C3: =D3+E3 -> 0.35474683 | D3: ='Cost Recovery'!O187 -> 0.30759669 | E3: ='Cost Recovery'!O205 -> 0.047150139 | F3: ='Cost Recovery'!O259 -> 0.24547415 | G3: ='Cost Recovery'!O241 -> 0.25002728
B4: ='Cost Recovery'!B177 -> Dominican Republic | C4: =D4+E4 -> 0.30448818 | D4: ='Cost Recovery'!O177 -> 0.2974654 | E4: ='Cost Recovery'!O195 -> 0.0070227781 | F4: ='Cost Recovery'!O249 -> 0.18566127 | G4: ='Cost Recovery'!O231 -> 0.19994913 | Z4: Senegal | AA4: 1
B5: ='Cost Recovery'!B179 -> India - Andhra Pradesh | C5: =D5+E5 -> 0.2007346 | D5: ='Cost Recovery'!O179 -> 0.10155327 | E5: ='Cost Recovery'!O197 -> 0.099181326 | G5: ='Cost Recovery'!O233 -> 0.076257416 | Z5: Dominican Republic | AA5: 1
B6: ='Cost Recovery'!B182 -> Kenya | C6: =D6+E6 -> 0.19459796 | D6: ='Cost Recovery'!O182 -> 0.15014348 | E6: ='Cost Recovery'!O200 -> 0.044454477 | F6: ='Cost Recovery'!O254 -> 0.17453263 | G6: ='Cost Recovery'!O236 -> 0.17534188 | Z6: India | AA6: 1
B7: ='Cost Recovery'!B186 -> Philippines | C7: =D7+E7 -> 0.19401821 | D7: ='Cost Recovery'!O186 -> 0.17109672 | E7: ='Cost Recovery'!O204 -> 0.022921495 | F7: ='Cost Recovery'!O258 -> 0.18990399 | G7: ='Cost Recovery'!O240 -> 0.19008684 | Z7: Kenya | AA7: 1
B8: ='Cost Recovery'!B189 -> Tanzania | C8: =D8+E8 -> 0.18707758 | D8: ='Cost Recovery'!O189 -> 0.15834835 | E8: ='Cost Recovery'!O207 -> 0.028729228 | F8: ='Cost Recovery'!O261 -> 0.13044984 | G8: ='Cost Recovery'!O243 -> 0.12647004 | Z8: Philippines | AA8: 1
B9: ='Cost Recovery'!B190 -> Uganda | C9: =D9+E9 -> 0.18471029 | D9: ='Cost Recovery'!O190 -> 0.14351713 | E9: ='Cost Recovery'!O208 -> 0.041193168 | F9: ='Cost Recovery'!O262 -> 0.16700612 | G9: ='Cost Recovery'!O244 -> 0.17050627 | Z9: Tanzania | AA9: 1
B10: ='Cost Recovery'!B181 -> India - Rajasthan | C10: =D10+E10 -> 0.16574868 | D10: ='Cost Recovery'!O181 -> 0.1002091 | E10: ='Cost Recovery'!O199 -> 0.065539585 | G10: ='Cost Recovery'!O235 -> 0.073946319 | Z10: Uganda | AA10: 1
B11: ='Cost Recovery'!B183&"*" -> Morocco* | C11: =D11+E11 -> 0.14204824 | E11: ='Cost Recovery'!$O$219 -> 0.14204824 | G11: ='Cost Recovery'!O237 -> 0.11953096 | Z11: Morocco* | AA11: 1
B12: ='Cost Recovery'!B185 -> Peru | C12: =D12+E12 -> 0.13167423 | D12: ='Cost Recovery'!O185 -> 0.096827701 | E12: ='Cost Recovery'!O203 -> 0.03484653 | F12: ='Cost Recovery'!O257 -> 0.12780812 | G12: ='Cost Recovery'!O239 -> 0.12909938 | Z12: Peru | AA12: 1
B13: ='Cost Recovery'!B184 -> Pakistan | C13: =D13+E13 -> 0.1299432 | D13: ='Cost Recovery'!O184 -> 0.096981557 | E13: ='Cost Recovery'!O202 -> 0.032961639 | F13: ='Cost Recovery'!O256 -> 0.094787839 | G13: ='Cost Recovery'!O238 -> 0.10346324 | Z13: Pakistan | AA13: 1
B14: ='Cost Recovery'!B176 -> Colombia | C14: =D14+E14 -> 0.12258427 | D14: ='Cost Recovery'!O176 -> 0.084076824 | E14: ='Cost Recovery'!O194 -> 0.03850745 | F14: ='Cost Recovery'!O248 -> 0.1232462 | G14: ='Cost Recovery'!O230 -> 0.12756775 | Z14: Colombia | AA14: 1
B15: ='Cost Recovery'!B180 -> India - Odisha | C15: =D15+E15 -> 0.103407 | D15: ='Cost Recovery'!O180 -> 0.096008783 | E15: ='Cost Recovery'!O198 -> 0.0073982137 | F15: ='Cost Recovery'!O252 -> 0.086300865 | G15: ='Cost Recovery'!O234 -> 0.0945583 | Z15: Egypt, Arab Rep. | AA15: 1
B16: ='Cost Recovery'!B178 -> Egypt, Arab Rep. | C16: =D16+E16 -> 0.077737088 | D16: ='Cost Recovery'!O178 -> 0.043369216 | E16: ='Cost Recovery'!O196 -> 0.034367871 | F16: ='Cost Recovery'!O250 -> 0.03821378 | G16: ='Cost Recovery'!O232 -> 0.043142892 | Z16: Vietnam | AA16: 1
B17: ='Cost Recovery'!B192 -> Vietnam | C17: =D17+E17 -> 0.075398011 | D17: ='Cost Recovery'!O192 -> 0.06618744 | E17: ='Cost Recovery'!O210 -> 0.0092105706 | F17: ='Cost Recovery'!O264 -> 0.066735415 | G17: ='Cost Recovery'!O246 -> 0.067060325 | Z17: Ukraine | AA17: 1
B18: ='Cost Recovery'!B191 -> Ukraine | C18: =D18+E18 -> 0.059887353 | D18: ='Cost Recovery'!O191 -> 0.056252249 | E18: ='Cost Recovery'!O209 -> 0.0036351041 | G18: ='Cost Recovery'!O245 -> 0.063777527 | Z18: Tajikistan | AA18: 1
B19: ='Cost Recovery'!B188 -> Tajikistan | C19: =D19+E19 -> 0.025643252 | D19: ='Cost Recovery'!O188 -> 0.014586734 | E19: ='Cost Recovery'!O206 -> 0.011056518 | F19: ='Cost Recovery'!O260 -> 0.012815038 | G19: ='Cost Recovery'!O242 -> 0.017232131
C21: =AVERAGE(C3:C19) -> 0.15614382 | G21: =AVERAGE(G3:G19) -> 0.11929516
B26: Full-Cost Recovery (C3 or approximate)
B27: Country | C27: Unit | D27: Region | E27: Value | F27: Type
B28: ='Cost Recovery'!B24 -> India - Andhra Pradesh | C28: ='Cost Recovery'!C24 -> % | D28: ='Cost Recovery'!D24 -> SAR | E28: ='Cost Recovery'!O24 -> 0.37989174 | F28: =VLOOKUP(B28,'Cost Recovery'!B$21:E$37,4,FALSE) -> Public | S28: Row Labels | T28: Average of Value | U28: Row Labels | V28: Average of Value
B29: ='Cost Recovery'!B26 -> India - Rajasthan | C29: ='Cost Recovery'!C26 -> % | D29: ='Cost Recovery'!D26 -> SAR | E29: ='Cost Recovery'!O26 -> 0.44613519 | F29: =VLOOKUP(B29,'Cost Recovery'!B$21:E$37,4,FALSE) -> Public | S29: AFR | T29: 0.80124568 | U29: Mixed | V29: 0.94720748
B30: ='Cost Recovery'!B23 -> Egypt, Arab Rep. | C30: ='Cost Recovery'!C23 -> % | D30: ='Cost Recovery'!D23 -> MNA | E30: ='Cost Recovery'!O23 -> 0.55498467 | F30: =VLOOKUP(B30,'Cost Recovery'!B$21:E$37,4,FALSE) -> Public | S30: EAP | T30: 0.93457739 | U30: Private | V30: 0.98116387
B31: ='Cost Recovery'!B22 -> Dominican Republic | C31: ='Cost Recovery'!C22 -> % | D31: ='Cost Recovery'!D22 -> LAC | E31: ='Cost Recovery'!O22 -> 0.65667289 | F31: =VLOOKUP(B31,'Cost Recovery'!B$21:E$37,4,FALSE) -> Public | S31: ECA | T31: 0.86847648 | U31: Public | V31: 0.69426259
B32: ='Cost Recovery'!B33 -> Tajikistan | C32: ='Cost Recovery'!C33 -> % | D32: ='Cost Recovery'!D33 -> ECA | E32: ='Cost Recovery'!O33 -> 0.67199478 | F32: =VLOOKUP(B32,'Cost Recovery'!B$21:E$37,4,FALSE) -> Public | S32: LAC | T32: 0.89259054 | U32: Grand Total | V32: 0.78952956
B33: ='Cost Recovery'!B34 -> Tanzania | C33: ='Cost Recovery'!C34 -> % | D33: ='Cost Recovery'!D34 -> AFR | E33: ='Cost Recovery'!O34 -> 0.67602993 | F33: =VLOOKUP(B33,'Cost Recovery'!B$21:E$37,4,FALSE) -> Public | S33: MNA | T33: 0.69823308
B34: ='Cost Recovery'!B32 -> Senegal | C34: ='Cost Recovery'!C32 -> % | D34: ='Cost Recovery'!D32 -> AFR | E34: ='Cost Recovery'!O32 -> 0.70480485 | F34: =VLOOKUP(B34,'Cost Recovery'!B$21:E$37,4,FALSE) -> Public | S34: SAR | T34: 0.63416859
B35: ='Cost Recovery'!B29 -> Pakistan | C35: ='Cost Recovery'!C29 -> % | D35: ='Cost Recovery'!D29 -> SAR | E35: ='Cost Recovery'!O29 -> 0.79621897 | F35: =VLOOKUP(B35,'Cost Recovery'!B$21:E$37,4,FALSE) -> Mixed | S35: Grand Total | T35: 0.78952956
B36: ='Cost Recovery'!B28 -> Morocco | C36: ='Cost Recovery'!C28 -> % | D36: ='Cost Recovery'!D28 -> MNA | E36: ='Cost Recovery'!O28 -> 0.84148148 | F36: =VLOOKUP(B36,'Cost Recovery'!B$21:E$37,4,FALSE) -> Public
B37: ='Cost Recovery'!B37 -> Vietnam | C37: ='Cost Recovery'!C37 -> % | D37: ='Cost Recovery'!D37 -> EAP | E37: ='Cost Recovery'!O37 -> 0.8894177 | F37: =VLOOKUP(B37,'Cost Recovery'!B$21:E$37,4,FALSE) -> Public | S37: Row Labels | T37: Average of Value | U37: Row Labels | V37: Average of Value
B38: ='Cost Recovery'!B27 -> Kenya | C38: ='Cost Recovery'!C27 -> % | D38: ='Cost Recovery'!D27 -> AFR | E38: ='Cost Recovery'!O27 -> 0.90104686 | F38: =VLOOKUP(B38,'Cost Recovery'!B$21:E$37,4,FALSE) -> Public | S38: SAR | T38: =VLOOKUP(S38,$S$29:$T$34,2,FALSE) -> 0.63416859 | U38: Public | V38: =VLOOKUP(U38,U$29:V$31,2,FALSE) -> 0.69426259
B39: ='Cost Recovery'!B25 -> India - Odisha | C39: ='Cost Recovery'!C25 -> % | D39: ='Cost Recovery'!D25 -> SAR | E39: ='Cost Recovery'!O25 -> 0.91442845 | F39: =VLOOKUP(B39,'Cost Recovery'!B$21:E$37,4,FALSE) -> Public | S39: MNA | T39: =VLOOKUP(S39,$S$29:$T$34,2,FALSE) -> 0.69823308 | U39: Mixed | V39: =VLOOKUP(U39,U$29:V$31,2,FALSE) -> 0.94720748
B40: ='Cost Recovery'!B35 -> Uganda | C40: ='Cost Recovery'!C35 -> % | D40: ='Cost Recovery'!D35 -> AFR | E40: ='Cost Recovery'!O35 -> 0.9231011 | F40: =VLOOKUP(B40,'Cost Recovery'!B$21:E$37,4,FALSE) -> Private | S40: AFR | T40: =VLOOKUP(S40,$S$29:$T$34,2,FALSE) -> 0.80124568 | U40: Private | V40: =VLOOKUP(U40,U$29:V$31,2,FALSE) -> 0.98116387
B41: ='Cost Recovery'!B31 -> Philippines | C41: ='Cost Recovery'!C31 -> % | D41: ='Cost Recovery'!D31 -> EAP | E41: ='Cost Recovery'!O31 -> 0.97973708 | F41: =VLOOKUP(B41,'Cost Recovery'!B$21:E$37,4,FALSE) -> Private | S41: ECA | T41: =VLOOKUP(S41,$S$29:$T$34,2,FALSE) -> 0.86847648
B42: ='Cost Recovery'!B30 -> Peru | C42: ='Cost Recovery'!C30 -> % | D42: ='Cost Recovery'!D30 -> LAC | E42: ='Cost Recovery'!O30 -> 0.98044528 | F42: =VLOOKUP(B42,'Cost Recovery'!B$21:E$37,4,FALSE) -> Mixed | S42: LAC | T42: =VLOOKUP(S42,$S$29:$T$34,2,FALSE) -> 0.89259054
B43: ='Cost Recovery'!B21 -> Colombia | C43: ='Cost Recovery'!C21 -> % | D43: ='Cost Recovery'!D21 -> LAC | E43: ='Cost Recovery'!O21 -> 1.0406534 | F43: =VLOOKUP(B43,'Cost Recovery'!B$21:E$37,4,FALSE) -> Private | S43: EAP | T43: =VLOOKUP(S43,$S$29:$T$34,2,FALSE) -> 0.93457739
B44: ='Cost Recovery'!B36 -> Ukraine | C44: ='Cost Recovery'!C36 -> % | D44: ='Cost Recovery'!D36 -> ECA | E44: ='Cost Recovery'!O36 -> 1.0649582 | F44: =VLOOKUP(B44,'Cost Recovery'!B$21:E$37,4,FALSE) -> Mixed
B50: Full-Cost Recovery (C3 or approximate)- Utility level
B51: Country | C51: Unit | D51: Region | E51: Value | F51: Type
B52: ='Cost Recovery'!B348 -> India - Andhra Pradesh (APSPDCL) | C52: ='Cost Recovery'!C348 -> % | D52: ='Cost Recovery'!D348 -> SAR | E52: ='Cost Recovery'!O348 -> 0.36474951 | F52: ='Cost Recovery'!E348 -> Public
B53: ='Cost Recovery'!B352 -> India - Rajasthan (AVVN) | C53: ='Cost Recovery'!C352 -> % | D53: ='Cost Recovery'!D352 -> SAR | E53: ='Cost Recovery'!O352 -> 0.39939703 | F53: ='Cost Recovery'!E352 -> Public
B54: ='Cost Recovery'!B349 -> India - Andhra Pradesh (APEPDCL) | C54: ='Cost Recovery'!C349 -> % | D54: ='Cost Recovery'!D349 -> SAR | E54: ='Cost Recovery'!O349 -> 0.41900279 | F54: ='Cost Recovery'!E349 -> Public
B55: ='Cost Recovery'!B353 -> India - Rajasthan (JDVVN) | C55: ='Cost Recovery'!C353 -> % | D55: ='Cost Recovery'!D353 -> SAR | E55: ='Cost Recovery'!O353 -> 0.47873231 | F55: ='Cost Recovery'!E353 -> Public
B56: ='Cost Recovery'!B347 -> Egypt, Arab Rep. | C56: ='Cost Recovery'!C347 -> % | D56: ='Cost Recovery'!D347 -> MNA | E56: ='Cost Recovery'!O347 -> 0.55498467 | F56: ='Cost Recovery'!E347 -> Public
B57: ='Cost Recovery'!B354 -> India - Rajasthan (JVVN) | C57: ='Cost Recovery'!C354 -> % | D57: ='Cost Recovery'!D354 -> SAR | E57: ='Cost Recovery'!O354 -> 0.55998863 | F57: ='Cost Recovery'!E354 -> Public
B58: ='Cost Recovery'!B346 -> Dominican Republic | C58: ='Cost Recovery'!C346 -> % | D58: ='Cost Recovery'!D346 -> LAC | E58: ='Cost Recovery'!O346 -> 0.65667289 | F58: ='Cost Recovery'!E346 -> Public
B59: ='Cost Recovery'!B358 -> Pakistan (KE) | C59: ='Cost Recovery'!C358 -> % | D59: ='Cost Recovery'!D358 -> SAR | E59: ='Cost Recovery'!O358 -> 0.66303201 | F59: ='Cost Recovery'!E358 -> Private
B60: ='Cost Recovery'!B364 -> Tajikistan | C60: ='Cost Recovery'!C364 -> % | D60: ='Cost Recovery'!D364 -> ECA | E60: ='Cost Recovery'!O364 -> 0.67199478 | F60: ='Cost Recovery'!E364 -> Public
B61: ='Cost Recovery'!B363 -> Senegal | C61: ='Cost Recovery'!C363 -> % | D61: ='Cost Recovery'!D363 -> AFR | E61: ='Cost Recovery'!O363 -> 0.70480485 | F61: ='Cost Recovery'!E363 -> Public
B62: ='Cost Recovery'!B365 -> Tanzania | C62: ='Cost Recovery'!C365 -> % | D62: ='Cost Recovery'!D365 -> AFR | E62: ='Cost Recovery'!O365 -> 0.73635255 | F62: ='Cost Recovery'!E365 -> Public
B63: ='Cost Recovery'!B356 -> Morocco | C63: ='Cost Recovery'!C356 -> % | D63: ='Cost Recovery'!D356 -> MNA | E63: ='Cost Recovery'!O356 -> 0.84148148 | F63: ='Cost Recovery'!E356 -> Public
B64: ='Cost Recovery'!B357 -> Pakistan (LESCO) | C64: ='Cost Recovery'!C357 -> % | D64: ='Cost Recovery'!D357 -> SAR | E64: ='Cost Recovery'!O357 -> 0.86230805 | F64: ='Cost Recovery'!E357 -> Public
B65: ='Cost Recovery'!B360 -> Peru (Hidrandina) | C65: ='Cost Recovery'!C360 -> % | D65: ='Cost Recovery'!D360 -> LAC | E65: ='Cost Recovery'!O360 -> 0.86571634 | F65: ='Cost Recovery'!E360 -> Public
B66: ='Cost Recovery'!B351 -> India - Odisha (CESCO) | C66: ='Cost Recovery'!C351 -> % | D66: ='Cost Recovery'!D351 -> SAR | E66: ='Cost Recovery'!O351 -> 0.88573399 | F66: ='Cost Recovery'!E351 -> Public
B67: ='Cost Recovery'!B362 -> Philippines (Beneco) | C67: ='Cost Recovery'!C362 -> % | D67: ='Cost Recovery'!D362 -> EAP | E67: ='Cost Recovery'!O362 -> 0.8894008 | F67: ='Cost Recovery'!E362 -> Private
B68: ='Cost Recovery'!B368 -> Vietnam | C68: ='Cost Recovery'!C368 -> % | D68: ='Cost Recovery'!D368 -> EAP | E68: ='Cost Recovery'!O368 -> 0.8894177 | F68: ='Cost Recovery'!E368 -> Public
B69: ='Cost Recovery'!B355 -> Kenya | C69: ='Cost Recovery'!C355 -> % | D69: ='Cost Recovery'!D355 -> AFR | E69: ='Cost Recovery'!O355 -> 0.90104686 | F69: ='Cost Recovery'!E355 -> Public
B70: ='Cost Recovery'!B366 -> Uganda | C70: ='Cost Recovery'!C366 -> % | D70: ='Cost Recovery'!D366 -> AFR | E70: ='Cost Recovery'!O366 -> 0.9231011 | F70: ='Cost Recovery'!E366 -> Private
B71: ='Cost Recovery'!B350 -> India - Odisha (WESCO) | C71: ='Cost Recovery'!C350 -> % | D71: ='Cost Recovery'!D350 -> SAR | E71: ='Cost Recovery'!O350 -> 0.94553254 | F71: ='Cost Recovery'!E350 -> Public
B72: ='Cost Recovery'!B361 -> Philippines (Meralco) | C72: ='Cost Recovery'!C361 -> % | D72: ='Cost Recovery'!D361 -> EAP | E72: ='Cost Recovery'!O361 -> 0.98915675 | F72: ='Cost Recovery'!E361 -> Private
B73: ='Cost Recovery'!B359 -> Peru (Luz del Sur) | C73: ='Cost Recovery'!C359 -> % | D73: ='Cost Recovery'!D359 -> LAC | E73: ='Cost Recovery'!O359 -> 1.01787 | F73: ='Cost Recovery'!E359 -> Private
B74: ='Cost Recovery'!B345 -> Colombia | C74: ='Cost Recovery'!C345 -> % | D74: ='Cost Recovery'!D345 -> LAC | E74: ='Cost Recovery'!O345 -> 1.0406534 | F74: ='Cost Recovery'!E345 -> Private
B75: ='Cost Recovery'!B367 -> Ukraine | C75: ='Cost Recovery'!C367 -> % | D75: ='Cost Recovery'!D367 -> ECA | E75: ='Cost Recovery'!O367 -> 1.0895377 | F75: ='Cost Recovery'!E367 -> Mixed
B79: Pre-Reform Full-Cost Recovery (C3 or approximate)
B80: Country | C80: Unit | D80: Region | E80: Value | F80: Type
B81: ='Cost Recovery'!B36 -> Ukraine | C81: ='Cost Recovery'!C101 -> % | D81: ='Cost Recovery'!D36 -> ECA | E81: ='Cost Recovery'!F36 -> 0.14634146 | F81: =VLOOKUP(B81,'Cost Recovery'!B$21:E$37,4,FALSE) -> Mixed | N81: Row Labels | O81: Average of Value | P81: Row Labels | Q81: Average of Value | AD81: Full-Cost Recovery (tariff revenues)
B82: ='Cost Recovery'!B23 -> Egypt, Arab Rep. | C82: ='Cost Recovery'!C88 -> % | D82: ='Cost Recovery'!D23 -> MNA | E82: ='Cost Recovery'!F23 -> 0.21282051 | F82: =VLOOKUP(B82,'Cost Recovery'!B$21:E$37,4,FALSE) -> Public | N82: AFR | O82: 0.77443168 | P82: Mixed | Q82: 0.60408879 | AD82: Dominican Republic | AE82: -0.40097417
B83: ='Cost Recovery'!B33 -> Tajikistan | C83: ='Cost Recovery'!C98 -> % | D83: ='Cost Recovery'!D33 -> ECA | E83: ='Cost Recovery'!F33 -> 0.23809524 | F83: =VLOOKUP(B83,'Cost Recovery'!B$21:E$37,4,FALSE) -> Public | N83: EAP | O83: 0.99623781 | P83: Private | Q83: 0.71637029 | AD83: Philippines | AE83: -0.33981777
B84: ='Cost Recovery'!B35 -> Uganda | C84: ='Cost Recovery'!C100 -> % | D84: ='Cost Recovery'!D35 -> AFR | E84: ='Cost Recovery'!F35 -> 0.27918288 | F84: =VLOOKUP(B84,'Cost Recovery'!B$21:E$37,4,FALSE) -> Private | N84: ECA | O84: 0.19221835 | P84: Public | Q84: 0.69865489 | AD84: Morocco | AE84: -0.22429197
B85: ='Cost Recovery'!B24 -> India - Andhra Pradesh | C85: ='Cost Recovery'!C89 -> % | D85: ='Cost Recovery'!D24 -> SAR | E85: ='Cost Recovery'!F24 -> 0.539801 | F85: =VLOOKUP(B85,'Cost Recovery'!B$21:E$37,4,FALSE) -> Public | N85: LAC | O85: 0.78850673 | P85: Grand Total | Q85: 0.685093 | AD85: Tanzania | AE85: -0.19652484
B86: ='Cost Recovery'!B25 -> India - Odisha | C86: ='Cost Recovery'!C90 -> % | D86: ='Cost Recovery'!D25 -> SAR | E86: ='Cost Recovery'!F25 -> 0.539801 | F86: =VLOOKUP(B86,'Cost Recovery'!B$21:E$37,4,FALSE) -> Public | N86: MNA | O86: 0.63929698 | AD86: Senegal | AE86: -0.17724106
B87: ='Cost Recovery'!B26 -> India - Rajasthan | C87: ='Cost Recovery'!C91 -> % | D87: ='Cost Recovery'!D26 -> SAR | E87: ='Cost Recovery'!F26 -> 0.539801 | F87: =VLOOKUP(B87,'Cost Recovery'!B$21:E$37,4,FALSE) -> Public | N87: SAR | O87: 0.63195697 | AD87: Kenya | AE87: -0.1628963
B88: ='Cost Recovery'!B21 -> Colombia | C88: ='Cost Recovery'!C86 -> % | D88: ='Cost Recovery'!D21 -> LAC | E88: ='Cost Recovery'!F21 -> 0.55037313 | F88: =VLOOKUP(B88,'Cost Recovery'!B$21:E$37,4,FALSE) -> Private | N88: Grand Total | O88: 0.685093 | AD88: India - Andhra Pradesh | AE88: -0.15990925
B89: ='Cost Recovery'!B37 -> Vietnam | C89: ='Cost Recovery'!C102 -> % | D89: ='Cost Recovery'!D37 -> EAP | E89: ='Cost Recovery'!F37 -> 0.67292077 | F89: =VLOOKUP(B89,'Cost Recovery'!B$21:E$37,4,FALSE) -> Public | AD89: Pakistan | AE89: -0.11220594
B90: ='Cost Recovery'!B30 -> Peru | C90: ='Cost Recovery'!C95 -> % | D90: ='Cost Recovery'!D30 -> LAC | E90: ='Cost Recovery'!F30 -> 0.7575 | F90: =VLOOKUP(B90,'Cost Recovery'!B$21:E$37,4,FALSE) -> Mixed | N90: Row Labels | O90: Average of Value | AD90: India - Rajasthan | AE90: -0.09366581
B91: ='Cost Recovery'!B34 -> Tanzania | C91: ='Cost Recovery'!C99 -> % | D91: ='Cost Recovery'!D34 -> AFR | E91: ='Cost Recovery'!F34 -> 0.87255476 | F91: =VLOOKUP(B91,'Cost Recovery'!B$21:E$37,4,FALSE) -> Public | N91: ECA | O91: =VLOOKUP(N91,N$82:O$87,2,FALSE) -> 0.19221835 | Q91: Row Labels | R91: Average of Value | AD91: Vietnam | AE91: 0.21649693
B92: ='Cost Recovery'!B32 -> Senegal | C92: ='Cost Recovery'!C97 -> % | D92: ='Cost Recovery'!D32 -> AFR | E92: ='Cost Recovery'!F32 -> 0.88204591 | F92: =VLOOKUP(B92,'Cost Recovery'!B$21:E$37,4,FALSE) -> Public | N92: SAR | O92: =VLOOKUP(N92,N$82:O$87,2,FALSE) -> 0.63195697 | Q92: Private | R92: =VLOOKUP(Q92,P$82:Q$84,2,FALSE) -> 0.71637029 | AD92: Peru | AE92: 0.22294528
B93: ='Cost Recovery'!B29 -> Pakistan | C93: ='Cost Recovery'!C94 -> % | D93: ='Cost Recovery'!D29 -> SAR | E93: ='Cost Recovery'!F29 -> 0.90842491 | F93: =VLOOKUP(B93,'Cost Recovery'!B$21:E$37,4,FALSE) -> Mixed | N93: MNA | O93: =VLOOKUP(N93,N$82:O$87,2,FALSE) -> 0.63929698 | Q93: Public | R93: =VLOOKUP(Q93,P$82:Q$84,2,FALSE) -> 0.69865489 | AD93: Egypt | AE93: 0.34216416
B94: ='Cost Recovery'!B22 -> Dominican Republic | C94: ='Cost Recovery'!C87 -> % | D94: ='Cost Recovery'!D22 -> LAC | E94: ='Cost Recovery'!F22 -> 1.0576471 | F94: =VLOOKUP(B94,'Cost Recovery'!B$21:E$37,4,FALSE) -> Public | N94: AFR | O94: =VLOOKUP(N94,N$82:O$87,2,FALSE) -> 0.77443168 | Q94: Mixed | R94: =VLOOKUP(Q94,P$82:Q$84,2,FALSE) -> 0.60408879 | AD94: India - Odisha | AE94: 0.37462746
B95: ='Cost Recovery'!B27 -> Kenya | C95: ='Cost Recovery'!C92 -> 0 | D95: ='Cost Recovery'!D27 -> AFR | E95: ='Cost Recovery'!F27 -> 1.0639432 | F95: =VLOOKUP(B95,'Cost Recovery'!B$21:E$37,4,FALSE) -> Public | N95: LAC | O95: =VLOOKUP(N95,N$82:O$87,2,FALSE) -> 0.78850673 | AD95: Tajikistan | AE95: 0.43389954
B96: ='Cost Recovery'!B28 -> Morocco | C96: ='Cost Recovery'!C93 -> % | D96: ='Cost Recovery'!D28 -> MNA | E96: ='Cost Recovery'!F28 -> 1.0657734 | F96: =VLOOKUP(B96,'Cost Recovery'!B$21:E$37,4,FALSE) -> Public | N96: EAP | O96: =VLOOKUP(N96,N$82:O$87,2,FALSE) -> 0.99623781 | AD96: Colombia | AE96: 0.49028031
B97: ='Cost Recovery'!B31 -> Philippines | C97: ='Cost Recovery'!C96 -> % | D97: ='Cost Recovery'!D31 -> EAP | E97: ='Cost Recovery'!F31 -> 1.3195548 | F97: =VLOOKUP(B97,'Cost Recovery'!B$21:E$37,4,FALSE) -> Private | AD97: Uganda | AE97: 0.64391822
AD98: Ukraine | AE98: 0.91861673
D99: 0 | E99: 0
D100: 1.4 | E100: 1.4
B105: Operating cost recovery (C1 or approximate)
B106: Country | C106: Unit | D106: Region | E106: Value
B107: ='Cost Recovery'!B4 -> Dominican Republic | C107: ='Cost Recovery'!C4 -> % | D107: ='Cost Recovery'!D4 -> LAC | E107: ='Cost Recovery'!O4 -> 0.6721761
B108: ='Cost Recovery'!B8 -> India - Rajasthan | C108: ='Cost Recovery'!C8 -> % | D108: ='Cost Recovery'!D8 -> SAR | E108: ='Cost Recovery'!O8 -> 0.73792022
B109: ='Cost Recovery'!B6 -> India - Andhra Pradesh | C109: ='Cost Recovery'!C6 -> % | D109: ='Cost Recovery'!D6 -> SAR | E109: ='Cost Recovery'!O6 -> 0.75091048 | S109: Row Labels | T109: Average of Value | AA109: Row Labels | AB109: Average of Value
B110: ='Cost Recovery'!B16 -> Tanzania | C110: ='Cost Recovery'!C16 -> % | D110: ='Cost Recovery'!D16 -> AFR | E110: ='Cost Recovery'!O16 -> 0.79868241 | S110: AFR | T110: 0.99185193 | AA110: SAR | AB110: =VLOOKUP(AA110,$S$110:$T$115,2,FALSE) -> 0.88513926
B111: ='Cost Recovery'!B14 -> Senegal | C111: ='Cost Recovery'!C14 -> % | D111: ='Cost Recovery'!D14 -> AFR | E111: ='Cost Recovery'!O14 -> 0.81284127 | S111: EAP | T111: 1.0620893 | AA111: AFR | AB111: =VLOOKUP(AA111,$S$110:$T$115,2,FALSE) -> 0.99185193
B112: ='Cost Recovery'!B7 -> India - Odisha | C112: ='Cost Recovery'!C7 -> % | D112: ='Cost Recovery'!D7 -> SAR | E112: ='Cost Recovery'!O7 -> 0.98489219 | S112: ECA | T112: 1.1575669 | AA112: MNA | AB112: =VLOOKUP(AA112,$S$110:$T$115,2,FALSE) -> 0.99478145
B113: ='Cost Recovery'!B5 -> Egypt, Arab Rep. | C113: ='Cost Recovery'!C5 -> % | D113: ='Cost Recovery'!D5 -> MNA | E113: ='Cost Recovery'!O5 -> 0.99478145 | S113: LAC | T113: 1.1742473 | AA113: EAP | AB113: =VLOOKUP(AA113,$S$110:$T$115,2,FALSE) -> 1.0620893
B114: ='Cost Recovery'!B19 -> Vietnam | C114: ='Cost Recovery'!C19 -> % | D114: ='Cost Recovery'!D19 -> EAP | E114: ='Cost Recovery'!O19 -> 1.0131881 | S114: MNA | T114: 0.99478145 | AA114: ECA | AB114: =VLOOKUP(AA114,$S$110:$T$115,2,FALSE) -> 1.1575669
B115: ='Cost Recovery'!B11 -> Pakistan | C115: ='Cost Recovery'!C11 -> % | D115: ='Cost Recovery'!D11 -> SAR | E115: ='Cost Recovery'!O11 -> 1.0668342 | S115: SAR | T115: 0.88513926 | AA115: LAC | AB115: =VLOOKUP(AA115,$S$110:$T$115,2,FALSE) -> 1.1742473
B116: ='Cost Recovery'!B13 -> Philippines | C116: ='Cost Recovery'!C13 -> % | D116: ='Cost Recovery'!D13 -> EAP | E116: ='Cost Recovery'!O13 -> 1.1109905 | S116: Grand Total | T116: 1.02905
B117: ='Cost Recovery'!B18 -> Ukraine | C117: ='Cost Recovery'!C18 -> % | D117: ='Cost Recovery'!D18 -> ECA | E117: ='Cost Recovery'!O18 -> 1.1337774
...

Sheet Cost Recovery
B1: Cost recovery analysis - Country level | C1: Unit | D1: Region | E1: Type | F1: Pre-reform | G1: 2010 | H1: 2011 | I1: 2012 | J1: 2013 | K1: 2014 | L1: 2015 | M1: 2016 | N1: 2017 | O1: Average 2010-17 | P1: Change from Pre-Reform | Q1: Tariff contribution | R1: Cost contribution | S1: Min | T1: Max | U1: Coeff of Variation | X1: Source/comment
B2: Operating cost recovery (tariff revenues)
B3: Colombia | C3: % | D3: LAC | E3: Private | F3: =IFERROR(F230/F176,"n.a.") -> n.a. | G3: =IFERROR(G230/G176,"n.a.") -> 1.543569 | H3: =IFERROR(H230/H176,"n.a.") -> 1.4860379 | I3: =IFERROR(I230/I176,"n.a.") -> 1.5305283 | J3: =IFERROR(J230/J176,"n.a.") -> 1.5266911 | K3: =IFERROR(K230/K176,"n.a.") -> 1.5215409 | L3: =IFERROR(L230/L176,"n.a.") -> 1.5008171 | M3: =IFERROR(M230/M176,"n.a.") -> 1.5069675 | ... O3: =IFERROR(O230/O176,"n.a.") -> 1.517276 | X3: Tariffs/C1
B4: Dominican Republic | C4: % | D4: LAC | E4: Public | F4: =IFERROR(F231/F177,"n.a.") -> n.a. | G4: =IFERROR(G231/G177,"n.a.") -> 0.70642194 | H4: =IFERROR(H231/H177,"n.a.") -> 0.6523157 | I4: =IFERROR(I231/I177,"n.a.") -> 0.63449462 | J4: =IFERROR(J231/J177,"n.a.") -> 0.66518037 | K4: =IFERROR(K231/K177,"n.a.") -> 0.63367908 | L4: =IFERROR(L231/L177,"n.a.") -> 0.7792562 | M4: =IFERROR(M231/M177,"n.a.") -> n.a. | ... O4: =IFERROR(O231/O177,"n.a.") -> 0.6721761
B5: Egypt, Arab Rep. | C5: % | D5: MNA | E5: Public | F5: =IFERROR(F232/F178,"n.a.") -> n.a. | G5: =IFERROR(G232/G178,"n.a.") -> n.a. | H5: =IFERROR(H232/H178,"n.a.") -> 1.4603514 | I5: =IFERROR(I232/I178,"n.a.") -> 1.3554688 | J5: =IFERROR(J232/J178,"n.a.") -> 1.3995538 | K5: =IFERROR(K232/K178,"n.a.") -> 0.7276914 | L5: =IFERROR(L232/L178,"n.a.") -> 0.81326566 | M5: =IFERROR(M232/M178,"n.a.") -> 0.8127443 | ... O5: =IFERROR(O232/O178,"n.a.") -> 0.99478145
B6: India - Andhra Pradesh | C6: % | D6: SAR | E6: Public | F6: =IFERROR(F233/F179,"n.a.") -> n.a. | G6: =IFERROR(G233/G179,"n.a.") -> n.a. | H6: =IFERROR(H233/H179,"n.a.") -> 0.72486646 | I6: =IFERROR(I233/I179,"n.a.") -> 0.76088087 | J6: =IFERROR(J233/J179,"n.a.") -> 0.71445177 | K6: =IFERROR(K233/K179,"n.a.") -> 0.80237914 | L6: =IFERROR(L233/L179,"n.a.") -> 0.76140152 | M6: =IFERROR(M233/M179,"n.a.") -> n.a. | ... O6: =IFERROR(O233/O179,"n.a.") -> 0.75091048
B7: India - Odisha | C7: % | D7: SAR | E7: Public | F7: =IFERROR(F234/F180,"n.a.") -> n.a. | G7: =IFERROR(G234/G180,"n.a.") -> n.a. | H7: =IFERROR(H234/H180,"n.a.") -> 1.0176325 | I7: =IFERROR(I234/I180,"n.a.") -> 0.97872683 | J7: =IFERROR(J234/J180,"n.a.") -> 0.95638928 | K7: =IFERROR(K234/K180,"n.a.") -> 0.9831727 | L7: =IFERROR(L234/L180,"n.a.") -> 0.98939186 | M7: =IFERROR(M234/M180,"n.a.") -> n.a. | ... O7: =IFERROR(O234/O180,"n.a.") -> 0.98489219
B8: India - Rajasthan | C8: % | D8: SAR | E8: Public | F8: =IFERROR(F235/F181,"n.a.") -> n.a. | G8: =IFERROR(G235/G181,"n.a.") -> n.a. | H8: =IFERROR(H235/H181,"n.a.") -> 0.63881852 | I8: =IFERROR(I235/I181,"n.a.") -> 0.65606968 | J8: =IFERROR(J235/J181,"n.a.") -> 0.75097635 | K8: =IFERROR(K235/K181,"n.a.") -> 0.78224356 | L8: =IFERROR(L235/L181,"n.a.") -> 0.88924861 | M8: =IFERROR(M235/M181,"n.a.") -> n.a. | ... O8: =IFERROR(O235/O181,"n.a.") -> 0.73792022
B9: Kenya | C9: % | D9: AFR | E9: Public | F9: =IFERROR(F236/F182,"n.a.") -> n.a. | G9: =IFERROR(G236/G182,"n.a.") -> 1.1148206 | H9: =IFERROR(H236/H182,"n.a.") -> 1.1739996 | I9: =IFERROR(I236/I182,"n.a.") -> 1.1345275 | J9: =IFERROR(J236/J182,"n.a.") -> 1.1516351 | K9: =IFERROR(K236/K182,"n.a.") -> 1.1934046 | L9: =IFERROR(L236/L182,"n.a.") -> 1.20569 | M9: =IFERROR(M236/M182,"n.a.") -> 1.2368184 | ... O9: =IFERROR(O236/O182,"n.a.") -> 1.1678288
B10: Morocco | C10: % | D10: MNA | E10: Public | F10: =IFERROR(F237/F183,"n.a.") -> n.a. | G10: =IFERROR(G237/G183,"n.a.") -> n.a. | H10: =IFERROR(H237/H183,"n.a.") -> n.a. | I10: =IFERROR(I237/I183,"n.a.") -> n.a. | J10: =IFERROR(J237/J183,"n.a.") -> n.a. | K10: =IFERROR(K237/K183,"n.a.") -> n.a. | L10: =IFERROR(L237/L183,"n.a.") -> n.a. | M10: =IFERROR(M237/M183,"n.a.") -> n.a. | ... O10: =IFERROR(O237/O183,"n.a.") -> n.a.
B11: Pakistan | C11: % | D11: SAR | E11: Mixed | F11: =IFERROR(F238/F184,"n.a.") -> n.a. | G11: =IFERROR(G238/G184,"n.a.") -> n.a. | H11: =IFERROR(H238/H184,"n.a.") -> n.a. | I11: =IFERROR(I238/I184,"n.a.") -> n.a. | J11: =IFERROR(J238/J184,"n.a.") -> 0.84966469 | K11: =IFERROR(K238/K184,"n.a.") -> 0.97146573 | L11: =IFERROR(L238/L184,"n.a.") -> 1.1869367 | M11: =IFERROR(M238/M184,"n.a.") -> 1.3954035 | ... O11: =IFERROR(O238/O184,"n.a.") -> 1.0668342
B12: Peru | C12: % | D12: LAC | E12: Mixed | F12: =IFERROR(F239/F185,"n.a.") -> n.a. | G12: =IFERROR(G239/G185,"n.a.") -> 1.3933433 | H12: =IFERROR(H239/H185,"n.a.") -> 1.3694024 | I12: =IFERROR(I239/I185,"n.a.") -> 1.3403122 | J12: =IFERROR(J239/J185,"n.a.") -> 1.3097292 | K12: =IFERROR(K239/K185,"n.a.") -> 1.3041321 | L12: =IFERROR(L239/L185,"n.a.") -> 1.3186819 | M12: =IFERROR(M239/M185,"n.a.") -> 1.3130718 | ... O12: =IFERROR(O239/O185,"n.a.") -> 1.3332897
B13: Philippines | C13: % | D13: EAP | E13: Private | F13: =IFERROR(F240/F186,"n.a.") -> n.a. | G13: =IFERROR(G240/G186,"n.a.") -> 1.0809965 | H13: =IFERROR(H240/H186,"n.a.") -> 1.0992383 | I13: =IFERROR(I240/I186,"n.a.") -> 1.0938794 | J13: =IFERROR(J240/J186,"n.a.") -> 1.1118635 | K13: =IFERROR(K240/K186,"n.a.") -> 1.1362492 | L13: =IFERROR(L240/L186,"n.a.") -> 1.1317364 | M13: =IFERROR(M240/M186,"n.a.") -> 1.1459573 | ... O13: =IFERROR(O240/O186,"n.a.") -> 1.1109905
B14: Senegal | C14: % | D14: AFR | E14: Public | F14: =IFERROR(F241/F187,"n.a.") -> n.a. | G14: =IFERROR(G241/G187,"n.a.") -> 0.80986003 | H14: =IFERROR(H241/H187,"n.a.") -> 0.73287571 | I14: =IFERROR(I241/I187,"n.a.") -> 0.6783171 | J14: =IFERROR(J241/J187,"n.a.") -> 0.79165224 | K14: =IFERROR(K241/K187,"n.a.") -> 0.81517897 | L14: =IFERROR(L241/L187,"n.a.") -> 1.0245417 | M14: =IFERROR(M241/M187,"n.a.") -> 1.0565072 | ... O14: =IFERROR(O241/O187,"n.a.") -> 0.81284127
B15: Tajikistan | C15: % | D15: ECA | E15: Public | F15: =IFERROR(F242/F188,"n.a.") -> n.a. | G15: =IFERROR(G242/G188,"n.a.") -> n.a. | H15: =IFERROR(H242/H188,"n.a.") -> n.a. | I15: =IFERROR(I242/I188,"n.a.") -> n.a. | J15: =IFERROR(J242/J188,"n.a.") -> 1.087905 | K15: =IFERROR(K242/K188,"n.a.") -> 1.2127849 | L15: =IFERROR(L242/L188,"n.a.") -> 1.2977298 | M15: =IFERROR(M242/M188,"n.a.") -> 1.1529748 | ... O15: =IFERROR(O242/O188,"n.a.") -> 1.1813564
... B19: Vietnam | C19: % | D19: EAP | E19: Public | F19: =IFERROR(F246/F192,"n.a.") -> n.a. | G19: =IFERROR(G246/G192,"n.a.") -> 0.99921613 | H19: =IFERROR(H246/H192,"n.a.") -> 0.98310085 | I19: =IFERROR(I246/I192,"n.a.") -> 1.0377212 | J19: =IFERROR(J246/J192,"n.a.") -> 1.0223713 | K19: =IFERROR(K246/K192,"n.a.") -> 1.0130538 | L19: =IFERROR(L246/L192,"n.a.") -> 1.0201213 | M19: =IFERROR(M246/M192,"n.a.") -> 1.0125215 | ... O19: =IFERROR(O246/O192,"n.a.") -> 1.0131881
B20: Full-Cost Recovery (tariff revenues)
B21: Colombia | C21: % | D21: LAC | E21: Private | F21: =IFERROR(F230/F212,"n.a.") -> 0.55037313 | G21: =IFERROR(G230/G212,"n.a.") -> 0.93589667 | H21: =IFERROR(H230/H212,"n.a.") -> 1.0902277 | I21: =IFERROR(I230/I212,"n.a.") -> 1.1701546 | J21: =IFERROR(J230/J212,"n.a.") -> 1.0271786 | K21: =IFERROR(K230/K212,"n.a.") -> 1.0045184 | L21: =IFERROR(L230/L212,"n.a.") -> 1.052692 | M21: =IFERROR(M230/M212,"n.a.") -> 1.0244124 | ... O21: =IFERROR(O230/O212,"n.a.") -> 1.0406534 | P21: =IFERROR(O21-F21,"n.a.") -> 0.49028031 | Q21: =('Sales & Collections'!AE3-'Sales & Collections'!V3)/Costs!V95 -> 0.5528719 | R21: =('Sales & Collections'!AE3/Costs!AE95)-('Sales & Collections'!AE3/Costs!V95) -> -0.062591591 | S21: =MIN(G21:N21) -> 0.93589667 | T21: =MAX(G21:M21) -> 1.1701546 | U21: =IFERROR(STDEV(G21:N21)/GEOMEAN(G21:N21),"n.a.") -> 0.070167106 | X21: Tariffs/C3
B22: Dominican Republic | C22: % | D22: LAC | E22: Public | F22: =IFERROR(F231/F213,"n.a.") -> 1.0576471 | G22: =IFERROR(G231/G213,"n.a.") -> 0.70519218 | H22: =IFERROR(H231/H213,"n.a.") -> 0.64537084 | I22: =IFERROR(I231/I213,"n.a.") -> 0.62126843 | J22: =IFERROR(J231/J213,"n.a.") -> 0.64714685 | K22: =IFERROR(K231/K213,"n.a.") -> 0.61994635 | L22: =IFERROR(L231/L213,"n.a.") -> 0.7327526 | M22: =IFERROR(M231/M213,"n.a.") -> n.a. | ... O22: =IFERROR(O231/O213,"n.a.") -> 0.65667289 | P22: =IFERROR(O22-F22,"n.a.") -> -0.40097417 | Q22: =('Sales & Collections'!AE4-'Sales & Collections'!V4)/Costs!V96 -> 0.032779653 | R22: =('Sales & Collections'!AE4/Costs!AE96)-('Sales & Collections'!AE4/Costs!V96) -> -0.43375382 | S22: =MIN(G22:N22) -> 0.61994635 | T22: =MAX(G22:M22) -> 0.7327526 | U22: =IFERROR(STDEV(G22:N22)/GEOMEAN(G22:N22),"n.a.") -> 0.070339385
B23: Egypt, Arab Rep. | C23: % | D23: MNA | E23: Public | F23: =IFERROR(F232/F214,"n.a.") -> 0.21282051 | G23: =IFERROR(G232/G214,"n.a.") -> n.a. | H23: =IFERROR(H232/H214,"n.a.") -> 0.61743081 | I23: =IFERROR(I232/I214,"n.a.") -> 0.62214293 | J23: =IFERROR(J232/J214,"n.a.") -> 0.67704062 | K23: =IFERROR(K232/K214,"n.a.") -> 0.49802617 | L23: =IFERROR(L232/L214,"n.a.") -> 0.49020079 | M23: =IFERROR(M232/M214,"n.a.") -> 0.50356045 | ... O23: =IFERROR(O232/O214,"n.a.") -> 0.55498467 | P23: =IFERROR(O23-F23,"n.a.") -> 0.34216416 | Q23: =('Sales & Collections'!AE5-'Sales & Collections'!V5)/Costs!V97 -> 0.043575068 | R23: =('Sales & Collections'!AE5/Costs!AE97)-('Sales & Collections'!AE5/Costs!V97) -> 0.29858909 | S23: =MIN(G23:N23) -> 0.49020079 | T23: =MAX(G23:M23) -> 0.67704062 | U23: =IFERROR(STDEV(G23:N23)/GEOMEAN(G23:N23),"n.a.") -> 0.14281233
B24: India - Andhra Pradesh | C24: % | D24: SAR | E24: Public | F24: =IFERROR(F233/F215,"n.a.") -> 0.539801 | G24: =IFERROR(G233/G215,"n.a.") -> n.a. | H24: =IFERROR(H233/H215,"n.a.") -> 0.35638014 | I24: =IFERROR(I233/I215,"n.a.") -> 0.36412687 | J24: =IFERROR(J233/J215,"n.a.") -> 0.38234609 | K24: =IFERROR(K233/K215,"n.a.") -> 0.3678935 | L24: =IFERROR(L233/L215,"n.a.") -> 0.44054808 | M24: =IFERROR(M233/M215,"n.a.") -> n.a. | ... O24: =IFERROR(O233/O215,"n.a.") -> 0.37989174 | P24: =IFERROR(O24-F24,"n.a.") -> -0.15990925 | Q24: =('Sales & Collections'!AE6-'Sales & Collections'!V6)/Costs!V98 -> -0.10013597 | R24: =('Sales & Collections'!AE6/Costs!AE98)-('Sales & Collections'!AE6/Costs!V98) -> -0.059773287 | S24: =MIN(G24:N24) -> 0.35638014 | T24: =MAX(G24:M24) -> 0.44054808 | U24: =IFERROR(STDEV(G24:N24)/GEOMEAN(G24:N24),"n.a.") -> 0.089001706
B25: India - Odisha | C25: % | D25: SAR | E25: Public | F25: =IFERROR(F234/F216,"n.a.") -> 0.539801 | G25: =IFERROR(G234/G216,"n.a.") -> n.a. | H25: =IFERROR(H234/H216,"n.a.") -> 0.93758771 | I25: =IFERROR(I234/I216,"n.a.") -> 0.91515302 | J25: =IFERROR(J234/J216,"n.a.") -> 0.89531065 | K25: =IFERROR(K234/K216,"n.a.") -> 0.91668135 | L25: =IFERROR(L234/L216,"n.a.") -> 0.90692378 | M25: =IFERROR(M234/M216,"n.a.") -> n.a. | ... O25: =IFERROR(O234/O216,"n.a.") -> 0.91442845 | P25: =IFERROR(O25-F25,"n.a.") -> 0.37462746 | Q25: =('Sales & Collections'!AE7-'Sales & Collections'!V7)/Costs!V99 -> 0.0053784766 | R25: =('Sales & Collections'!AE7/Costs!AE99)-('Sales & Collections'!AE7/Costs!V99) -> 0.36924898 | S25: =MIN(G25:N25) -> 0.89531065 | T25: =MAX(G25:M25) -> 0.93758771 | U25: =IFERROR(STDEV(G25:N25)/GEOMEAN(G25:N25),"n.a.") -> 0.01697816
B26: India - Rajasthan | C26: % | D26: SAR | E26: Public | F26: =IFERROR(F235/F217,"n.a.") -> 0.539801 | G26: =IFERROR(G235/G217,"n.a.") -> n.a. | H26: =IFERROR(H235/H217,"n.a.") -> 0.38391318 | I26: =IFERROR(I235/I217,"n.a.") -> 0.41135686 | J26: =IFERROR(J235/J217,"n.a.") -> 0.47313733 | K26: =IFERROR(K235/K217,"n.a.") -> 0.428227 | L26: =IFERROR(L235/L217,"n.a.") -> 0.56686203 | M26: =IFERROR(M235/M217,"n.a.") -> n.a. | ... O26: =IFERROR(O235/O217,"n.a.") -> 0.44613519 | P26: =IFERROR(O26-F26,"n.a.") -> -0.09366581 | Q26: =('Sales & Collections'!AE8-'Sales & Collections'!V8)/Costs!V100 -> -0.11346068 | R26: =('Sales & Collections'!AE8/Costs!AE100)-('Sales & Collections'!AE8/Costs!V100) -> 0.019794873 | S26: =MIN(G26:N26) -> 0.38391318 | T26: =MAX(G26:M26) -> 0.56686203 | U26: =IFERROR(STDEV(G26:N26)/GEOMEAN(G26:N26),"n.a.") -> 0.15959813
B27: Kenya | C27: % | D27: AFR | E27: Public | F27: =IFERROR(F236/F218,"n.a.") -> 1.0639432 | G27: =IFERROR(G236/G218,"n.a.") -> 0.99283243 | H27: =IFERROR(H236/H218,"n.a.") -> 1.0053586 | I27: =IFERROR(I236/I218,"n.a.") -> 0.93871935 | J27: =IFERROR(J236/J218,"n.a.") -> 0.87485101 | K27: =IFERROR(K236/K218,"n.a.") -> 0.89240749 | L27: =IFERROR(L236/L218,"n.a.") -> 0.81330249 | M27: =IFERROR(M236/M218,"n.a.") -> 0.80030107 | ... O27: =IFERROR(O236/O218,"n.a.") -> 0.90104686 | P27: =IFERROR(O27-F27,"n.a.") -> -0.1628963 | Q27: =('Sales & Collections'!AE9-'Sales & Collections'!V9)/Costs!V101 -> 0.37974419 | R27: =('Sales & Collections'!AE9/Costs!AE101)-('Sales & Collections'!AE9/Costs!V101) -> -0.5426405 | S27: =MIN(G27:N27) -> 0.80030107 | T27: =MAX(G27:M27) -> 1.0053586 | U27: =IFERROR(STDEV(G27:N27)/GEOMEAN(G27:N27),"n.a.") -> 0.090004106
B28: Morocco | C28: % | D28: MNA | E28: Public | F28: =IFERROR(F237/F219,"n.a.") -> 1.0657734 | G28: =IFERROR(G237/G219,"n.a.") -> n.a. | H28: =IFERROR(H237/H219,"n.a.") -> n.a. | I28: =IFERROR(I237/I219,"n.a.") -> n.a. | J28: =IFERROR(J237/J219,"n.a.") -> 0.84148148 | K28: =IFERROR(K237/K219,"n.a.") -> n.a. | L28: =IFERROR(L237/L219,"n.a.") -> n.a. | M28: =IFERROR(M237/M219,"n.a.") -> n.a. | ... O28: =IFERROR(O237/O219,"n.a.") -> 0.84148148 | P28: =IFERROR(O28-F28,"n.a.") -> -0.22429197 | Q28: =('Sales & Collections'!AE10-'Sales & Collections'!V10)/Costs!V102 -> -0.3908832 | R28: =('Sales & Collections'!AE10/Costs!AE102)-('Sales & Collections'!AE10/Costs!V102) -> 0.16659124 | S28: =MIN(G28:N28) -> 0.84148148 | T28: =MAX(G28:M28) -> 0.84148148 | U28: =IFERROR(STDEV(G28:N28)/GEOMEAN(G28:N28),"n.a.") -> n.a.
B29: Pakistan | C29: % | D29: SAR | E29: Mixed | F29: =IFERROR(F238/F220,"n.a.") -> 0.90842491 | G29: =IFERROR(G238/G220,"n.a.") -> n.a. | H29: =IFERROR(H238/H220,"n.a.") -> n.a. | I29: =IFERROR(I238/I220,"n.a.") -> n.a. | J29: =IFERROR(J238/J220,"n.a.") -> 0.65705726 | K29: =IFERROR(K238/K220,"n.a.") -> 0.74903779 | L29: =IFERROR(L238/L220,"n.a.") -> 0.8677183 | M29: =IFERROR(M238/M220,"n.a.") -> 0.96846917 | ... O29: =IFERROR(O238/O220,"n.a.") -> 0.79621897 | P29: =IFERROR(O29-F29,"n.a.") -> -0.11220594 | Q29: =('Sales & Collections'!AE11-'Sales & Collections'!V11)/Costs!V103 -> -0.030031016 | R29: =('Sales & Collections'!AE11/Costs!AE103)-('Sales & Collections'!AE11/Costs!V103) -> -0.082174923 | S29: =MIN(G29:N29) -> 0.65705726 | T29: =MAX(G29:M29) -> 0.96846917 | U29: =IFERROR(STDEV(G29:N29)/GEOMEAN(G29:N29),"n.a.") -> 0.16968376
B30: Peru | C30: % | D30: LAC | E30: Mixed | F30: =IFERROR(F239/F221,"n.a.") -> 0.7575 | G30: =IFERROR(G239/G221,"n.a.") -> 1.0184226 | H30: =IFERROR(H239/H221,"n.a.") -> 1.0197177 | I30: =IFERROR(I239/I221,"n.a.") -> 1.0125604 | J30: =IFERROR(J239/J221,"n.a.") -> 0.98362552 | K30: =IFERROR(K239/K221,"n.a.") -> 0.94890369 | L30: =IFERROR(L239/L221,"n.a.") -> 0.96949243 | M30: =IFERROR(M239/M221,"n.a.") -> 0.92991165 | ... O30: =IFERROR(O239/O221,"n.a.") -> 0.98044528 | P30: =IFERROR(O30-F30,"n.a.") -> 0.22294528 | Q30: =('Sales & Collections'!AE12-'Sales & Collections'!V12)/Costs!V104 -> -0.25880066 | R30: =('Sales & Collections'!AE12/Costs!AE104)-('Sales & Collections'!AE12/Costs!V104) -> 0.48174594 | S30: =MIN(G30:N30) -> 0.92991165 | T30: =MAX(G30:M30) -> 1.0197177 | U30: =IFERROR(STDEV(G30:N30)/GEOMEAN(G30:N30),"n.a.") -> 0.036313325
B31: Philippines | C31: % | D31: EAP | E31: Private | F31: =IFERROR(F240/F222,"n.a.") -> 1.3195548 | G31: =IFERROR(G240/G222,"n.a.") -> 0.97809706 | H31: =IFERROR(H240/H222,"n.a.") -> 0.9926745 | I31: =IFERROR(I240/I222,"n.a.") -> 0.99937078 | J31: =IFERROR(J240/J222,"n.a.") -> 0.96215974 | K31: =IFERROR(K240/K222,"n.a.") -> 0.97595454 | L31: =IFERROR(L240/L222,"n.a.") -> 0.99048205 | M31: =IFERROR(M240/M222,"n.a.") -> 0.95320456 | ... O31: =IFERROR(O240/O222,"n.a.") -> 0.97973708 | P31: =IFERROR(O31-F31,"n.a.") -> -0.33981777 | Q31: =('Sales & Collections'!AE13-'Sales & Collections'!V13)/Costs!V105 -> 0.081313364 | R31: =('Sales & Collections'!AE13/Costs!AE105)-('Sales & Collections'!AE13/Costs!V105) -> -0.42113114 | S31: =MIN(G31:N31) -> 0.95320456 | T31: =MAX(G31:M31) -> 0.99937078 | U31: =IFERROR(STDEV(G31:N31)/GEOMEAN(G31:N31),"n.a.") -> 0.01716158
B32: Senegal | C32: % | D32: AFR | E32: Public | F32: =IFERROR(F241/F223,"n.a.") -> 0.88204591 | G32: =IFERROR(G241/G223,"n.a.") -> 0.7660452 | H32: =IFERROR(H241/H223,"n.a.") -> 0.67879803 | I32: =IFERROR(I241/I223,"n.a.") -> 0.54860314 | J32: =IFERROR(J241/J223,"n.a.") -> 0.65833515 | K32: =IFERROR(K241/K223,"n.a.") -> 0.71512207 | L32: =IFERROR(L241/L223,"n.a.") -> 0.85990348 | M32: =IFERROR(M241/M223,"n.a.") -> 0.87210791 | ... O32: =IFERROR(O241/O223,"n.a.") -> 0.70480485 | P32: =IFERROR(O32-F32,"n.a.") -> -0.17724106 | Q32: =('Sales & Collections'!AE14-'Sales & Collections'!V14)/Costs!V106 -> -0.33694784 | R32: =('Sales & Collections'!AE14/Costs!AE106)-('Sales & Collections'!AE14/Costs!V106) -> 0.15970678 | S32: =MIN(G32:N32) -> 0.54860314 | T32: =MAX(G32:M32) -> 0.87210791 | U32: =IFERROR(STDEV(G32:N32)/GEOMEAN(G32:N32),"n.a.") -> 0.15951332
B33: Tajikistan | C33: % | D33: ECA | E33: Public | F33: =IFERROR(F242/F224,"n.a.") -> 0.23809524 | G33: =IFERROR(G242/G224,"n.a.") -> n.a. | H33: =IFERROR(H242/H224,"n.a.") -> n.a. | I33: =IFERROR(I242/I224,"n.a.") -> n.a. | J33: =IFERROR(J242/J224,"n.a.") -> 0.52123301 | K33: =IFERROR(K242/K224,"n.a.") -> 0.72901724 | L33: =IFERROR(L242/L224,"n.a.") -> 0.82800002 | M33: =IFERROR(M242/M224,"n.a.") -> 0.70170828 | ... O33: =IFERROR(O242/O224,"n.a.") -> 0.67199478 | P33: =IFERROR(O33-F33,"n.a.") -> 0.43389954 | Q33: =('Sales & Collections'!AE15-'Sales & Collections'!V15)/Costs!V107 -> 0.37773522 | R33: =('Sales & Collections'!AE15/Costs!AE107)-('Sales & Collections'!AE15/Costs!V107) -> 0.056164325 | S33: =MIN(G33:N33) -> 0.52123301 | T33: =MAX(G33:M33) -> 0.82800002 | U33: =IFERROR(STDEV(G33:N33)/GEOMEAN(G33:N33),"n.a.") -> 0.18660774
... B37: Vietnam | C37: % | D37: EAP | E37: Public | F37: =IFERROR(F246/F228,"n.a.") -> 0.67292077 | G37: =IFERROR(G246/G228,"n.a.") -> 0.91028876 | H37: =IFERROR(H246/H228,"n.a.") -> 0.85904269 | I37: =IFERROR(I246/I228,"n.a.") -> 0.91485348 | J37: =IFERROR(J246/J228,"n.a.") -> 0.88108623 | K37: =IFERROR(K246/K228,"n.a.") -> 0.89217349 | L37: =IFERROR(L246/L228,"n.a.") -> 0.88883686 | M37: =IFERROR(M246/M228,"n.a.") -> 0.88340634 | ... O37: =IFERROR(O246/O228,"n.a.") -> 0.8894177 | P37: =IFERROR(O37-F37,"n.a.") -> 0.21649693 | Q37: =('Sales & Collections'!AE19-'Sales & Collections'!V19)/Costs!V111 -> -0.10833203 | R37: =('Sales & Collections'!AE19/Costs!AE111)-('Sales & Collections'!AE19/Costs!V111) -> 0.32482897 | S37: =MIN(G37:N37) -> 0.85904269 | T37: =MAX(G37:M37) -> 0.91485348 | U37: =IFERROR(STDEV(G37:N37)/GEOMEAN(G37:N37),"n.a.") -> 0.021108957
B38: Full Financial Cost Recovery (tariff revenues)
B39: Colombia | C39: % | D39: LAC | E39: Private | F39: =IFERROR(F230/Costs!V39,"n.a.") -> n.a. | G39: =IFERROR(G230/Costs!W39,"n.a.") -> 0.93589667 | H39: =IFERROR(H230/Costs!X39,"n.a.") -> 1.0902277 | I39: =IFERROR(I230/Costs!Y39,"n.a.") -> 1.1701546 | J39: =IFERROR(J230/Costs!Z39,"n.a.") -> 1.0271786 | K39: =IFERROR(K230/Costs!AA39,"n.a.") -> 1.0045184 | L39: =IFERROR(L230/Costs!AB39,"n.a.") -> 1.052692 | M39: =IFERROR(M230/Costs!AC39,"n.a.") -> 1.0244124 | ... O39: =IFERROR(O230/Costs!AE39,"n.a.") -> 1.0406534 | X39: Tariffs/C3
B40: Dominican Republic | C40: % | D40: LAC | E40: Public | F40: =IFERROR(F231/Costs!V40,"n.a.") -> n.a. | G40: =G22 -> 0.70519218 | H40: =H22 -> 0.64537084 | I40: =I22 -> 0.62126843 | J40: =J22 -> 0.64714685 | K40: =K22 -> 0.61994635 | L40: =L22 -> 0.7327526 | M40: =M22 -> n.a. | N40: =N22 -> n.a. | O40: =AVERAGE(G40:N40) -> 0.66194621
B41: Egypt, Arab Rep. | C41: % | D41: MNA | E41: Public | F41: =IFERROR(F232/Costs!V41,"n.a.") -> n.a. | G41: =IFERROR(G232/Costs!W41,"n.a.") -> n.a. | H41: =IFERROR(H232/Costs!X41,"n.a.") -> 0.61743081 | I41: =IFERROR(I232/Costs!Y41,"n.a.") -> 0.62214293 | J41: =IFERROR(J232/Costs!Z41,"n.a.") -> 0.67704062 | K41: =IFERROR(K232/Costs!AA41,"n.a.") -> 0.69506534 | L41: =IFERROR(L232/Costs!AB41,"n.a.") -> 0.65191951 | M41: =IFERROR(M232/Costs!AC41,"n.a.") -> 0.65565094 | ... O41: =IFERROR(O232/Costs!AE41,"n.a.") -> 0.65126463
B42: India - Andhra Pradesh | C42: % | D42: SAR | E42: Public | F42: =IFERROR(F233/Costs!V42,"n.a.") -> n.a. | G42: =IFERROR(G233/Costs!W42,"n.a.") -> n.a. | H42: =IFERROR(H233/Costs!X42,"n.a.") -> 0.39862488 | I42: =IFERROR(I233/Costs!Y42,"n.a.") -> 0.41184752 | J42: =IFERROR(J233/Costs!Z42,"n.a.") -> 0.39467739 | K42: =IFERROR(K233/Costs!AA42,"n.a.") -> 0.39290335 | L42: =IFERROR(L233/Costs!AB42,"n.a.") -> 0.47799705 | M42: =IFERROR(M233/Costs!AC42,"n.a.") -> n.a. | ... O42: =IFERROR(O233/Costs!AE42,"n.a.") -> 0.41273656
B43: India - Odisha | C43: % | D43: SAR | E43: Public | F43: =IFERROR(F234/Costs!V43,"n.a.") -> n.a. | G43: =IFERROR(G234/Costs!W43,"n.a.") -> n.a. | H43: =IFERROR(H234/Costs!X43,"n.a.") -> 0.93758771 | I43: =IFERROR(I234/Costs!Y43,"n.a.") -> 0.91515302 | J43: =IFERROR(J234/Costs!Z43,"n.a.") -> 0.89531065 | K43: =IFERROR(K234/Costs!AA43,"n.a.") -> 0.91668135 | L43: =IFERROR(L234/Costs!AB43,"n.a.") -> 0.90692378 | M43: =IFERROR(M234/Costs!AC43,"n.a.") -> n.a. | ... O43: =IFERROR(O234/Costs!AE43,"n.a.") -> 0.91442845
B44: India - Rajasthan | C44: % | D44: SAR | E44: Public | F44: =IFERROR(F235/Costs!V44,"n.a.") -> n.a. | G44: =IFERROR(G235/Costs!W44,"n.a.") -> n.a. | H44: =IFERROR(H235/Costs!X44,"n.a.") -> 0.40307895 | I44: =IFERROR(I235/Costs!Y44,"n.a.") -> 0.43949913 | J44: =IFERROR(J235/Costs!Z44,"n.a.") -> 0.50850465 | K44: =IFERROR(K235/Costs!AA44,"n.a.") -> 0.44355414 | L44: =IFERROR(L235/Costs!AB44,"n.a.") -> 0.59254638 | M44: =IFERROR(M235/Costs!AC44,"n.a.") -> n.a. | ... O44: =IFERROR(O235/Costs!AE44,"n.a.") -> 0.47005635
B45: Kenya | C45: % | D45: AFR | E45: Public | F45: =IFERROR(F236/Costs!V45,"n.a.") -> n.a. | G45: =IFERROR(G236/Costs!W45,"n.a.") -> 0.99768831 | H45: =IFERROR(H236/Costs!X45,"n.a.") -> 1.0149762 | I45: =IFERROR(I236/Costs!Y45,"n.a.") -> 0.9476729 | J45: =IFERROR(J236/Costs!Z45,"n.a.") -> 0.88446253 | K45: =IFERROR(K236/Costs!AA45,"n.a.") -> 0.90306655 | L45: =IFERROR(L236/Costs!AB45,"n.a.") -> 0.83210104 | M45: =IFERROR(M236/Costs!AC45,"n.a.") -> 0.82618325 | ... O45: =IFERROR(O236/Costs!AE45,"n.a.") -> 0.91402561
B46: Morocco | C46: % | D46: MNA | E46: Public | F46: =IFERROR(F237/Costs!V46,"n.a.") -> n.a. | G46: =G28 -> n.a. | H46: =H28 -> n.a. | I46: =I28 -> n.a. | J46: =J28 -> 0.84148148 | K46: =K28 -> n.a. | L46: =L28 -> n.a. | M46: =M28 -> n.a. | N46: =N28 -> n.a. | O46: =AVERAGE(G46:N46) -> 0.84148148
B47: Pakistan | C47: % | D47: SAR | E47: Mixed | F47: =IFERROR(F238/Costs!V47,"n.a.") -> n.a. | G47: =IFERROR(G238/Costs!W47,"n.a.") -> n.a. | H47: =IFERROR(H238/Costs!X47,"n.a.") -> n.a. | I47: =IFERROR(I238/Costs!Y47,"n.a.") -> n.a. | J47: =IFERROR(J238/Costs!Z47,"n.a.") -> 0.75542573 | K47: =IFERROR(K238/Costs!AA47,"n.a.") -> 0.88719991 | L47: =IFERROR(L238/Costs!AB47,"n.a.") -> 0.95629401 | M47: =IFERROR(M238/Costs!AC47,"n.a.") -> 1.0376751 | ... O47: =IFERROR(O238/Costs!AE47,"n.a.") -> 0.89978484
B48: Peru | C48: % | D48: LAC | E48: Mixed | F48: =IFERROR(F239/Costs!V48,"n.a.") -> n.a. | G48: =IFERROR(G239/Costs!W48,"n.a.") -> 1.0184226 | H48: =IFERROR(H239/Costs!X48,"n.a.") -> 1.0197177 | I48: =IFERROR(I239/Costs!Y48,"n.a.") -> 1.0125604 | J48: =IFERROR(J239/Costs!Z48,"n.a.") -> 0.98362552 | K48: =IFERROR(K239/Costs!AA48,"n.a.") -> 0.94890369 | L48: =IFERROR(L239/Costs!AB48,"n.a.") -> 0.96949243 | M48: =IFERROR(M239/Costs!AC48,"n.a.") -> 0.92991165 | ... O48: =IFERROR(O239/Costs!AE48,"n.a.") -> 0.98044528
B49: Philippines | C49: % | D49: EAP | E49: Private | F49: =IFERROR(F240/Costs!V49,"n.a.") -> n.a. | G49: =IFERROR(G240/Costs!W49,"n.a.") -> 0.97809706 | H49: =IFERROR(H240/Costs!X49,"n.a.") -> 0.9926745 | I49: =IFERROR(I240/Costs!Y49,"n.a.") -> 0.99937078 | J49: =IFERROR(J240/Costs!Z49,"n.a.") -> 0.96215974 | K49: =IFERROR(K240/Costs!AA49,"n.a.") -> 0.97595454 | L49: =IFERROR(L240/Costs!AB49,"n.a.") -> 0.99048205 | M49: =IFERROR(M240/Costs!AC49,"n.a.") -> 0.95320456 | ... O49: =IFERROR(O240/Costs!AE49,"n.a.") -> 0.97973708
B50: Senegal | C50: % | D50: AFR | E50: Public | F50: =IFERROR(F241/Costs!V50,"n.a.") -> n.a. | G50: =IFERROR(G241/Costs!W50,"n.a.") -> 0.84906042 | H50: =IFERROR(H241/Costs!X50,"n.a.") -> 0.97360667 | I50: =IFERROR(I241/Costs!Y50,"n.a.") -> 0.75193725 | J50: =IFERROR(J241/Costs!Z50,"n.a.") -> 0.86347972 | K50: =IFERROR(K241/Costs!AA50,"n.a.") -> 0.92652523 | L50: =IFERROR(L241/Costs!AB50,"n.a.") -> 0.96845995 | M50: =IFERROR(M241/Costs!AC50,"n.a.") -> 0.9061275 | ... O50: =IFERROR(O241/Costs!AE50,"n.a.") -> 0.88330099
B51: Tajikistan | C51: % | D51: ECA | E51: Public | F51: =IFERROR(F242/Costs!V51,"n.a.") -> n.a. | G51: =IFERROR(G242/Costs!W51,"n.a.") -> n.a. | H51: =IFERROR(H242/Costs!X51,"n.a.") -> n.a. | I51: =IFERROR(I242/Costs!Y51,"n.a.") -> n.a. | J51: =IFERROR(J242/Costs!Z51,"n.a.") -> 1.0069505 | K51: =IFERROR(K242/Costs!AA51,"n.a.") -> 1.0345733 | L51: =IFERROR(L242/Costs!AB51,"n.a.") -> 1.0753422 | M51: =IFERROR(M242/Costs!AC51,"n.a.") -> 0.93529548 | ... O51: =IFERROR(O242/Costs!AE51,"n.a.") -> 1.011713
B52: Tanzania | C52: % | D52: AFR | E52: Public | F52: =IFERROR(F243/Costs!V52,"n.a.") -> n.a. | G52: =IFERROR(G243/Costs!W52,"n.a.") -> n.a. | H52: =IFERROR(H243/Costs!X52,"n.a.") -> n.a. | I52: =IFERROR(I243/Costs!Y52,"n.a.") -> 0.72929038 | J52: =IFERROR(J243/Costs!Z52,"n.a.") -> 0.67831453 | K52: =IFERROR(K243/Costs!AA52,"n.a.") -> n.a. | L52: =IFERROR(L243/Costs!AB52,"n.a.") -> 1.0720508 | M52: =IFERROR(M243/Costs!AC52,"n.a.") -> 0.8259545 | ... O52: =IFERROR(O243/Costs!AE52,"n.a.") -> 0.80967289
B53: Uganda | C53: % | D53: AFR | E53: Private | F53: =IFERROR(F244/Costs!V53,"n.a.") -> n.a. | G53: =IFERROR(G244/Costs!W53,"n.a.") -> n.a. | H53: =IFERROR(H244/Costs!X53,"n.a.") -> n.a. | I53: =IFERROR(I244/Costs!Y53,"n.a.") -> 1.1377053 | J53: =IFERROR(J244/Costs!Z53,"n.a.") -> 1.0484666 | K53: =IFERROR(K244/Costs!AA53,"n.a.") -> 1.0024488 | L53: =IFERROR(L244/Costs!AB53,"n.a.") -> 0.93632127 | M53: =IFERROR(M244/Costs!AC53,"n.a.") -> 0.8802953 | ... O53: =IFERROR(O244/Costs!AE53,"n.a.") -> 1.0010715
B54: Ukraine | C54: % | D54: ECA | E54: Mixed | F54: =IFERROR(F245/Costs!V54,"n.a.") -> n.a. | G54: =G36 -> n.a. | H54: =IFERROR(H245/Costs!X54,"n.a.") -> n.a. | I54: =IFERROR(I245/Costs!Y54,"n.a.") -> 1.0727121 | J54: =IFERROR(J245/Costs!Z54,"n.a.") -> 1.154113 | K54: =IFERROR(K245/Costs!AA54,"n.a.") -> 1.1023189 | L54: =IFERROR(L245/Costs!AB54,"n.a.") -> 1.0489185 | M54: =IFERROR(M245/Costs!AC54,"n.a.") -> 1.0278867 | N54: =IFERROR(N245/Costs!AD54,"n.a.") -> 0.93303953 | O54: =IFERROR(O245/Costs!AE54,"n.a.") -> 1.0649582
B55: Vietnam | C55: % | D55: EAP | E55: Public | F55: =IFERROR(F246/Costs!V55,"n.a.") -> n.a. | G55: =IFERROR(G246/Costs!W55,"n.a.") -> 0.91521928 | H55: =IFERROR(H246/Costs!X55,"n.a.") -> 0.87180295 | I55: =IFERROR(I246/Costs!Y55,"n.a.") -> 0.92971634 | J55: =IFERROR(J246/Costs!Z55,"n.a.") -> 0.89463086 | K55: =IFERROR(K246/Costs!AA55,"n.a.") -> 0.90558422 | L55: =IFERROR(L246/Costs!AB55,"n.a.") -> 0.89975157 | M55: =IFERROR(M246/Costs!AC55,"n.a.") -> 0.89466178 | ... O55: =IFERROR(O246/Costs!AE55,"n.a.") -> 0.90123602
B56: Financial Operating Cost Recovery (cash collected)
B57: Colombia | C57: % | D57: LAC | E57: Private | F57: =IFERROR(F248/Costs!V57,"n.a.") -> n.a. | G57: =IFERROR(G248/Costs!W3,"n.a.") -> 1.2956465 | H57: =IFERROR(H248/Costs!X3,"n.a.") -> 1.6239247 | I57: =IFERROR(I248/Costs!Y3,"n.a.") -> 1.5223401 | J57: =IFERROR(J248/Costs!Z3,"n.a.") -> 1.4851594 | K57: =IFERROR(K248/Costs!AA3,"n.a.") -> 1.4552732 | L57: =IFERROR(L248/Costs!AB3,"n.a.") -> 1.4497486 | M57: =IFERROR(M248/Costs!AC3,"n.a.") -> 1.3941728 | N57: =IFERROR(N248/Costs!AD3,"n.a.") -> n.a. | O57: =IFERROR(O248/Costs!AE3,"n.a.") -> 1.465876 | X57: Tariffs/C3
B58: Dominican Republic | C58: % | D58: LAC | E58: Public | F58: =IFERROR(F249/Costs!V58,"n.a.") -> n.a. | G58: =IFERROR(G249/Costs!W4,"n.a.") -> 0.67291295 | H58: =IFERROR(H249/Costs!X4,"n.a.") -> 0.61635201 | I58: =IFERROR(I249/Costs!Y4,"n.a.") -> 0.57884894 | J58: =IFERROR(J249/Costs!Z4,"n.a.") -> 0.61418594 | K58: =IFERROR(K249/Costs!AA4,"n.a.") -> 0.58738934 | L58: =IFERROR(L249/Costs!AB4,"n.a.") -> 0.71246409 | M58: =IFERROR(M249/Costs!AC4,"n.a.") -> n.a. | N58: =IFERROR(N249/Costs!AD4,"n.a.") -> n.a. | O58: =IFERROR(O249/Costs!AE4,"n.a.") -> 0.6241441
B59: Egypt, Arab Rep. | C59: % | D59: MNA | E59: Public | F59: =IFERROR(F250/Costs!V59,"n.a.") -> n.a. | G59: =IFERROR(G250/Costs!W5,"n.a.") -> n.a. | H59: =IFERROR(H250/Costs!X5,"n.a.") -> 1.4297117 | I59: =IFERROR(I250/Costs!Y5,"n.a.") -> 1.2453586 | J59: =IFERROR(J250/Costs!Z5,"n.a.") -> 0.99596333 | K59: =IFERROR(K250/Costs!AA5,"n.a.") -> 1.030948 | L59: =IFERROR(L250/Costs!AB5,"n.a.") -> 1.2805745 | M59: =IFERROR(M250/Costs!AC5,"n.a.") -> 1.19381 | N59: =IFERROR(N250/Costs!AD5,"n.a.") -> n.a. | O59: =IFERROR(O250/Costs!AE5,"n.a.") -> 1.1987913
B60: India - Andhra Pradesh | C60: % | D60: SAR | E60: Public | F60: =IFERROR(F251/Costs!V60,"n.a.") -> n.a. | G60: =IFERROR(G251/Costs!W6,"n.a.") -> n.a. | H60: =IFERROR(H251/Costs!X6,"n.a.") -> n.a. | I60: =IFERROR(I251/Costs!Y6,"n.a.") -> n.a. | J60: =IFERROR(J251/Costs!Z6,"n.a.") -> n.a. | K60: =IFERROR(K251/Costs!AA6,"n.a.") -> n.a. | L60: =IFERROR(L251/Costs!AB6,"n.a.") -> n.a. | M60: =IFERROR(M251/Costs!AC6,"n.a.") -> n.a. | N60: =IFERROR(N251/Costs!AD6,"n.a.") -> n.a. | O60: =IFERROR(O251/Costs!AE6,"n.a.") -> n.a.
B61: India - Odisha | C61: % | D61: SAR | E61: Public | F61: =IFERROR(F252/Costs!V61,"n.a.") -> n.a. | G61: =IFERROR(G252/Costs!W7,"n.a.") -> n.a. | H61: =IFERROR(H252/Costs!X7,"n.a.") -> 0.88435654 | I61: =IFERROR(I252/Costs!Y7,"n.a.") -> 0.87953008 | J61: =IFERROR(J252/Costs!Z7,"n.a.") -> 0.89391254 | K61: =IFERROR(K252/Costs!AA7,"n.a.") -> 0.91684285 | L61: =IFERROR(L252/Costs!AB7,"n.a.") -> 0.92162023 | M61: =IFERROR(M252/Costs!AC7,"n.a.") -> n.a. | N61: =IFERROR(N252/Costs!AD7,"n.a.") -> n.a. | O61: =IFERROR(O252/Costs!AE7,"n.a.") -> 0.89888511
B62: India - Rajasthan | C62: % | D62: SAR | E62: Public | F62: =IFERROR(F253/Costs!V62,"n.a.") -> n.a. | G62: =IFERROR(G253/Costs!W8,"n.a.") -> n.a. | H62: =IFERROR(H253/Costs!X8,"n.a.") -> n.a. | I62: =IFERROR(I253/Costs!Y8,"n.a.") -> n.a. | J62: =IFERROR(J253/Costs!Z8,"n.a.") -> n.a. | K62: =IFERROR(K253/Costs!AA8,"n.a.") -> n.a. | L62: =IFERROR(L253/Costs!AB8,"n.a.") -> n.a. | M62: =IFERROR(M253/Costs!AC8,"n.a.") -> n.a. | N62: =IFERROR(N253/Costs!AD8,"n.a.") -> n.a. | O62: =IFERROR(O253/Costs!AE8,"n.a.") -> n.a.
B63: Kenya | C63: % | D63: AFR | E63: Public | F63: =IFERROR(F254/Costs!V63,"n.a.") -> n.a. | G63: =IFERROR(G254/Costs!W9,"n.a.") -> 1.1227273 | H63: =IFERROR(H254/Costs!X9,"n.a.") -> 1.142836 | I63: =IFERROR(I254/Costs!Y9,"n.a.") -> 1.1541527 | J63: =IFERROR(J254/Costs!Z9,"n.a.") -> 1.131406 | K63: =IFERROR(K254/Costs!AA9,"n.a.") -> 1.1537451 | L63: =IFERROR(L254/Costs!AB9,"n.a.") -> 1.2260575 | M63: =IFERROR(M254/Costs!AC9,"n.a.") -> 1.2373585 | N63: =IFERROR(N254/Costs!AD9,"n.a.") -> n.a. | O63: =IFERROR(O254/Costs!AE9,"n.a.") -> 1.1624389
B64: Morocco | C64: % | D64: MNA | E64: Public | F64: =IFERROR(F255/Costs!V64,"n.a.") -> n.a. | G64: =IFERROR(G255/Costs!W10,"n.a.") -> n.a. | H64: =IFERROR(H255/Costs!X10,"n.a.") -> n.a. | I64: =IFERROR(I255/Costs!Y10,"n.a.") -> n.a. | J64: =IFERROR(J255/Costs!Z10,"n.a.") -> n.a. | K64: =IFERROR(K255/Costs!AA10,"n.a.") -> n.a. | L64: =IFERROR(L255/Costs!AB10,"n.a.") -> n.a. | M64: =IFERROR(M255/Costs!AC10,"n.a.") -> n.a. | N64: =IFERROR(N255/Costs!AD10,"n.a.") -> n.a. | O64: =IFERROR(O255/Costs!AE10,"n.a.") -> n.a.
B65: Pakistan | C65: % | D65: SAR | E65: Mixed | F65: =IFERROR(F256/Costs!V65,"n.a.") -> n.a. | G65: =IFERROR(G256/Costs!W11,"n.a.") -> n.a. | H65: =IFERROR(H256/Costs!X11,"n.a.") -> n.a. | I65: =IFERROR(I256/Costs!Y11,"n.a.") -> n.a. | J65: =IFERROR(J256/Costs!Z11,"n.a.") -> 0.90364466 | K65: =IFERROR(K256/Costs!AA11,"n.a.") -> 1.1348062 | L65: =IFERROR(L256/Costs!AB11,"n.a.") -> 1.2412499 | M65: =IFERROR(M256/Costs!AC11,"n.a.") -> 1.4398597 | N65: =IFERROR(N256/Costs!AD11,"n.a.") -> n.a. | O65: =IFERROR(O256/Costs!AE11,"n.a.") -> 1.1555969
B66: Peru | C66: % | D66: LAC | E66: Mixed | F66: =IFERROR(F257/Costs!V66,"n.a.") -> n.a. | G66: =IFERROR(G257/Costs!W12,"n.a.") -> 1.3724514 | H66: =IFERROR(H257/Costs!X12,"n.a.") -> 1.3531774 | I66: =IFERROR(I257/Costs!Y12,"n.a.") -> 1.322645 | J66: =IFERROR(J257/Costs!Z12,"n.a.") -> 1.2894108 | K66: =IFERROR(K257/Costs!AA12,"n.a.") -> 1.3039468 | L66: =IFERROR(L257/Costs!AB12,"n.a.") -> 1.3024349 | M66: =IFERROR(M257/Costs!AC12,"n.a.") -> 1.3086533 | N66: =IFERROR(N257/Costs!AD12,"n.a.") -> n.a. | O66: =IFERROR(O257/Costs!AE12,"n.a.") -> 1.3199541
B67: Philippines | C67: % | D67: EAP | E67: Private | F67: =IFERROR(F258/Costs!V67,"n.a.") -> n.a. | G67: =IFERROR(G258/Costs!W13,"n.a.") -> 1.0808642 | H67: =IFERROR(H258/Costs!X13,"n.a.") -> 1.0734097 | I67: =IFERROR(I258/Costs!Y13,"n.a.") -> 1.0965701 | J67: =IFERROR(J258/Costs!Z13,"n.a.") -> 1.0986758 | K67: =IFERROR(K258/Costs!AA13,"n.a.") -> 1.1549283 | L67: =IFERROR(L258/Costs!AB13,"n.a.") -> 1.1462779 | M67: =IFERROR(M258/Costs!AC13,"n.a.") -> 1.1526127 | N67: =IFERROR(N258/Costs!AD13,"n.a.") -> n.a. | O67: =IFERROR(O258/Costs!AE13,"n.a.") -> 1.1099219
B68: Senegal | C68: % | D68: AFR | E68: Public | F68: =IFERROR(F259/Costs!V68,"n.a.") -> n.a. | G68: =IFERROR(G259/Costs!W14,"n.a.") -> 0.8910272 | H68: =IFERROR(H259/Costs!X14,"n.a.") -> 1.0519101 | I68: =IFERROR(I259/Costs!Y14,"n.a.") -> 0.92678235 | J68: =IFERROR(J259/Costs!Z14,"n.a.") -> 0.96636566 | K68: =IFERROR(K259/Costs!AA14,"n.a.") -> 1.0456243 | L68: =IFERROR(L259/Costs!AB14,"n.a.") -> 1.0390616 | M68: =IFERROR(M259/Costs!AC14,"n.a.") -> 1.0150705 | N68: =IFERROR(N259/Costs!AD14,"n.a.") -> n.a. | O68: =IFERROR(O259/Costs!AE14,"n.a.") -> 0.98521889
B69: Tajikistan | C69: % | D69: ECA | E69: Public | F69: =IFERROR(F260/Costs!V69,"n.a.") -> n.a. | G69: =IFERROR(G260/Costs!W15,"n.a.") -> n.a. | H69: =IFERROR(H260/Costs!X15,"n.a.") -> n.a. | I69: =IFERROR(I260/Costs!Y15,"n.a.") -> n.a. | J69: =IFERROR(J260/Costs!Z15,"n.a.") -> 0.68346291 | K69: =IFERROR(K260/Costs!AA15,"n.a.") -> 0.84259758 | L69: =IFERROR(L260/Costs!AB15,"n.a.") -> 1.0771157 | M69: =IFERROR(M260/Costs!AC15,"n.a.") -> 0.98002858 | N69: =IFERROR(N260/Costs!AD15,"n.a.") -> n.a. | O69: =IFERROR(O260/Costs!AE15,"n.a.") -> 0.8785406
... B73: Vietnam | C73: % | D73: EAP | E73: Public | F73: =IFERROR(F264/Costs!V73,"n.a.") -> n.a. | G73: =IFERROR(G264/Costs!W19,"n.a.") -> 0.98902543 | H73: =IFERROR(H264/Costs!X19,"n.a.") -> 0.97611938 | I73: =IFERROR(I264/Costs!Y19,"n.a.") -> 1.0374649 | J73: =IFERROR(J264/Costs!Z19,"n.a.") -> 1.0223713 | K73: =IFERROR(K264/Costs!AA19,"n.a.") -> 1.0067604 | L73: =IFERROR(L264/Costs!AB19,"n.a.") -> 1.0201213 | M73: =IFERROR(M264/Costs!AC19,"n.a.") -> 1.0013651 | N73: =IFERROR(N264/Costs!AD19,"n.a.") -> n.a. | O73: =IFERROR(O264/Costs!AE19,"n.a.") -> 1.0082791
B74: Operating cost recovery (cash collection)
B75: Colombia | C75: % | D75: LAC | E75: Private | F75: =IFERROR(F248/F176,"n.a.") -> n.a. | G75: =IFERROR(G248/G176,"n.a.") -> 1.2956465 | H75: =IFERROR(H248/H176,"n.a.") -> 1.6239247 | I75: =IFERROR(I248/I176,"n.a.") -> 1.5223401 | J75: =IFERROR(J248/J176,"n.a.") -> 1.4851594 | K75: =IFERROR(K248/K176,"n.a.") -> 1.4552732 | L75: =IFERROR(L248/L176,"n.a.") -> 1.4497486 | M75: =IFERROR(M248/M176,"n.a.") -> 1.3941728 | ... O75: =IFERROR(O248/O176,"n.a.") -> 1.465876 | X75: Tariffs/C1
B76: Dominican Republic | C76: % | D76: LAC | E76: Public | F76: =IFERROR(F249/F177,"n.a.") -> n.a. | G76: =IFERROR(G249/G177,"n.a.") -> 0.67291295 | H76: =IFERROR(H249/H177,"n.a.") -> 0.61635201 | I76: =IFERROR(I249/I177,"n.a.") -> 0.57884894 | J76: =IFERROR(J249/J177,"n.a.") -> 0.61418594 | K76: =IFERROR(K249/K177,"n.a.") -> 0.58738934 | L76: =IFERROR(L249/L177,"n.a.") -> 0.71246409 | M76: =IFERROR(M249/M177,"n.a.") -> n.a. | ... O76: =IFERROR(O249/O177,"n.a.") -> 0.6241441
B77: Egypt, Arab Rep. | C77: % | D77: MNA | E77: Public | F77: =IFERROR(F250/F178,"n.a.") -> n.a. | G77: =IFERROR(G250/G178,"n.a.") -> n.a. | H77: =IFERROR(H250/H178,"n.a.") -> 1.4297117 | I77: =IFERROR(I250/I178,"n.a.") -> 1.2453586 | J77: =IFERROR(J250/J178,"n.a.") -> 0.99596333 | K77: =IFERROR(K250/K178,"n.a.") -> 0.6039176 | L77: =IFERROR(L250/L178,"n.a.") -> 0.75355149 | M77: =IFERROR(M250/M178,"n.a.") -> 0.74685181 | ... O77: =IFERROR(O250/O178,"n.a.") -> 0.88112683
B78: India - Andhra Pradesh | C78: % | D78: SAR | E78: Public | F78: =IFERROR(F251/F179,"n.a.") -> n.a. | G78: =IFERROR(G251/G179,"n.a.") -> n.a. | H78: =IFERROR(H251/H179,"n.a.") -> n.a. | I78: =IFERROR(I251/I179,"n.a.") -> n.a. | J78: =IFERROR(J251/J179,"n.a.") -> n.a. | K78: =IFERROR(K251/K179,"n.a.") -> n.a. | L78: =IFERROR(L251/L179,"n.a.") -> n.a. | M78: =IFERROR(M251/M179,"n.a.") -> n.a. | ... O78: =IFERROR(O251/O179,"n.a.") -> n.a.
B79: India - Odisha | C79: % | D79: SAR | E79: Public | F79: =IFERROR(F252/F180,"n.a.") -> n.a. | G79: =IFERROR(G252/G180,"n.a.") -> n.a. | H79: =IFERROR(H252/H180,"n.a.") -> 0.88435654 | I79: =IFERROR(I252/I180,"n.a.") -> 0.87953008 | J79: =IFERROR(J252/J180,"n.a.") -> 0.89391254 | K79: =IFERROR(K252/K180,"n.a.") -> 0.91684285 | L79: =IFERROR(L252/L180,"n.a.") -> 0.92162023 | M79: =IFERROR(M252/M180,"n.a.") -> n.a. | ... O79: =IFERROR(O252/O180,"n.a.") -> 0.89888511
B80: India - Rajasthan | C80: % | D80: SAR | E80: Public | F80: =IFERROR(F253/F181,"n.a.") -> n.a. | G80: =IFERROR(G253/G181,"n.a.") -> n.a. | H80: =IFERROR(H253/H181,"n.a.") -> n.a. | I80: =IFERROR(I253/I181,"n.a.") -> n.a. | J80: =IFERROR(J253/J181,"n.a.") -> n.a. | K80: =IFERROR(K253/K181,"n.a.") -> n.a. | L80: =IFERROR(L253/L181,"n.a.") -> n.a. | M80: =IFERROR(M253/M181,"n.a.") -> n.a. | ... O80: =IFERROR(O253/O181,"n.a.") -> n.a.
B81: Kenya | C81: % | D81: AFR | E81: Public | F81: =IFERROR(F254/F182,"n.a.") -> n.a. | G81: =IFERROR(G254/G182,"n.a.") -> 1.1227273 | H81: =IFERROR(H254/H182,"n.a.") -> 1.142836 | I81: =IFERROR(I254/I182,"n.a.") -> 1.1541527 | J81: =IFERROR(J254/J182,"n.a.") -> 1.131406 | K81: =IFERROR(K254/K182,"n.a.") -> 1.1537451 | L81: =IFERROR(L254/L182,"n.a.") -> 1.2260575 | M81: =IFERROR(M254/M182,"n.a.") -> 1.2373585 | ... O81: =IFERROR(O254/O182,"n.a.") -> 1.1624389
B82: Morocco | C82: % | D82: MNA | E82: Public | F82: =IFERROR(F255/F183,"n.a.") -> n.a. | G82: =IFERROR(G255/G183,"n.a.") -> n.a. | H82: =IFERROR(H255/H183,"n.a.") -> n.a. | I82: =IFERROR(I255/I183,"n.a.") -> n.a. | J82: =IFERROR(J255/J183,"n.a.") -> n.a. | K82: =IFERROR(K255/K183,"n.a.") -> n.a. | L82: =IFERROR(L255/L183,"n.a.") -> n.a. | M82: =IFERROR(M255/M183,"n.a.") -> n.a. | ... O82: =IFERROR(O255/O183,"n.a.") -> n.a.
B83: Pakistan | C83: % | D83: SAR | E83: Mixed | F83: =IFERROR(F256/F184,"n.a.") -> n.a. | G83: =IFERROR(G256/G184,"n.a.") -> n.a. | H83: =IFERROR(H256/H184,"n.a.") -> n.a. | I83: =IFERROR(I256/I184,"n.a.") -> n.a. | J83: =IFERROR(J256/J184,"n.a.") -> 0.75148267 | K83: =IFERROR(K256/K184,"n.a.") -> 0.90560705 | L83: =IFERROR(L256/L184,"n.a.") -> 1.0839852 | M83: =IFERROR(M256/M184,"n.a.") -> 1.301498 | ... O83: =IFERROR(O256/O184,"n.a.") -> 0.97738006
B84: Peru | C84: % | D84: LAC | E84: Mixed | F84: =IFERROR(F257/F185,"n.a.") -> n.a. | G84: =IFERROR(G257/G185,"n.a.") -> 1.3724514 | H84: =IFERROR(H257/H185,"n.a.") -> 1.3531774 | I84: =IFERROR(I257/I185,"n.a.") -> 1.322645 | J84: =IFERROR(J257/J185,"n.a.") -> 1.2894108 | K84: =IFERROR(K257/K185,"n.a.") -> 1.3039468 | L84: =IFERROR(L257/L185,"n.a.") -> 1.3024349 | M84: =IFERROR(M257/M185,"n.a.") -> 1.3086533 | ... O84: =IFERROR(O257/O185,"n.a.") -> 1.3199541
B85: Philippines | C85: % | D85: EAP | E85: Private | F85: =IFERROR(F258/F186,"n.a.") -> n.a. | G85: =IFERROR(G258/G186,"n.a.") -> 1.0808642 | H85: =IFERROR(H258/H186,"n.a.") -> 1.0734097 | I85: =IFERROR(I258/I186,"n.a.") -> 1.0965701 | J85: =IFERROR(J258/J186,"n.a.") -> 1.0986758 | K85: =IFERROR(K258/K186,"n.a.") -> 1.1549283 | L85: =IFERROR(L258/L186,"n.a.") -> 1.1462779 | M85: =IFERROR(M258/M186,"n.a.") -> 1.1526127 | ... O85: =IFERROR(O258/O186,"n.a.") -> 1.1099219
B86: Senegal | C86: % | D86: AFR | E86: Public | F86: =IFERROR(F259/F187,"n.a.") -> n.a. | G86: =IFERROR(G259/G187,"n.a.") -> 0.81066989 | H86: =IFERROR(H259/H187,"n.a.") -> 0.73360858 | I86: =IFERROR(I259/I187,"n.a.") -> 0.65254105 | J86: =IFERROR(J259/J187,"n.a.") -> 0.73386163 | K86: =IFERROR(K259/K187,"n.a.") -> 0.83244378 | L86: =IFERROR(L259/L187,"n.a.") -> 0.97699906 | M86: =IFERROR(M259/M187,"n.a.") -> 1.0565072 | ... O86: =IFERROR(O259/O187,"n.a.") -> 0.79803898
B87: Tajikistan | C87: % | D87: ECA | E87: Public | F87: =IFERROR(F260/F188,"n.a.") -> n.a. | G87: =IFERROR(G260/G188,"n.a.") -> n.a. | H87: =IFERROR(H260/H188,"n.a.") -> n.a. | I87: =IFERROR(I260/I188,"n.a.") -> n.a. | J87: =IFERROR(J260/J188,"n.a.") -> 0.68346291 | K87: =IFERROR(K260/K188,"n.a.") -> 0.84259758 | L87: =IFERROR(L260/L188,"n.a.") -> 1.0771157 | M87: =IFERROR(M260/M188,"n.a.") -> 0.98002858 | ... O87: =IFERROR(O260/O188,"n.a.") -> 0.8785406
... B91: Vietnam | C91: % | D91: EAP | E91: Public | F91: =IFERROR(F264/F192,"n.a.") -> n.a. | G91: =IFERROR(G264/G192,"n.a.") -> 0.98902543 | H91: =IFERROR(H264/H192,"n.a.") -> 0.97611938 | I91: =IFERROR(I264/I192,"n.a.") -> 1.0374649 | J91: =IFERROR(J264/J192,"n.a.") -> 1.0223713 | K91: =IFERROR(K264/K192,"n.a.") -> 1.0067604 | L91: =IFERROR(L264/L192,"n.a.") -> 1.0201213 | M91: =IFERROR(M264/M192,"n.a.") -> 1.0013651 | ... O91: =IFERROR(O264/O192,"n.a.") -> 1.0082791
B92: Full-Cost Recovery (cash collection)
B93: Colombia | C93: % | D93: LAC | E93: Private | F93: =IFERROR(F248/(F176+F194),"n.a.") -> n.a. | G93: =IFERROR(G248/(G176+G194),"n.a.") -> 0.78557628 | H93: =IFERROR(H248/(H176+H194),"n.a.") -> 1.191388 | I93: =IFERROR(I248/(I176+I194),"n.a.") -> 1.1638944 | J93: =IFERROR(J248/(J176+J194),"n.a.") -> 0.9992356 | K93: =IFERROR(K248/(K176+K194),"n.a.") -> 0.96076864 | L93: =IFERROR(L248/(L176+L194),"n.a.") -> 1.0168719 | M93: =IFERROR(M248/(M176+M194),"n.a.") -> 0.94773641 | ... O93: =IFERROR(O248/(O176+O194),"n.a.") -> 1.0053997 | X93: Collection/C3
B94: Dominican Republic | C94: % | D94: LAC | E94: Public | F94: =IFERROR(F249/(F177+F195),"n.a.") -> n.a. | G94: =IFERROR(G249/(G177+G195),"n.a.") -> 0.67174153 | H94: =IFERROR(H249/(H177+H195),"n.a.") -> 0.60979003 | I94: =IFERROR(I249/(I177+I195),"n.a.") -> 0.5667827 | J94: =IFERROR(J249/(J177+J195),"n.a.") -> 0.59753492 | K94: =IFERROR(K249/(K177+K195),"n.a.") -> 0.57465977 | L94: =IFERROR(L249/(L177+L195),"n.a.") -> 0.66994643 | M94: =IFERROR(M249/(M177+M195),"n.a.") -> n.a. | ... O94: =IFERROR(O249/(O177+O195),"n.a.") -> 0.60974871
B95: Egypt, Arab Rep. | C95: % | D95: MNA | E95: Public | F95: =IFERROR(F250/(F178+F196),"n.a.") -> n.a. | G95: =IFERROR(G250/(G178+G196),"n.a.") -> n.a. | H95: =IFERROR(H250/(H178+H196),"n.a.") -> 0.60447649 | I95: =IFERROR(I250/(I178+I196),"n.a.") -> 0.57160375 | J95: =IFERROR(J250/(J178+J196),"n.a.") -> 0.48180187 | K95: =IFERROR(K250/(K178+K196),"n.a.") -> 0.41331637 | L95: =IFERROR(L250/(L178+L196),"n.a.") -> 0.45420771 | M95: =IFERROR(M250/(M178+M196),"n.a.") -> 0.46273475 | ... O95: =IFERROR(O250/(O178+O196),"n.a.") -> 0.4915772
B96: India - Andhra Pradesh | C96: % | D96: SAR | E96: Public | F96: =IFERROR(F251/(F179+F197),"n.a.") -> n.a. | G96: =IFERROR(G251/(G179+G197),"n.a.") -> n.a. | H96: =IFERROR(H251/(H179+H197),"n.a.") -> n.a. | I96: =IFERROR(I251/(I179+I197),"n.a.") -> n.a. | J96: =IFERROR(J251/(J179+J197),"n.a.") -> n.a. | K96: =IFERROR(K251/(K179+K197),"n.a.") -> n.a. | L96: =IFERROR(L251/(L179+L197),"n.a.") -> n.a. | M96: =IFERROR(M251/(M179+M197),"n.a.") -> n.a. | ... O96: =IFERROR(O251/(O179+O197),"n.a.") -> n.a.
B97: India - Odisha | C97: % | D97: SAR | E97: Public | F97: =IFERROR(F252/(F180+F198),"n.a.") -> n.a. | G97: =IFERROR(G252/(G180+G198),"n.a.") -> n.a. | H97: =IFERROR(H252/(H180+H198),"n.a.") -> 0.81479492 | I97: =IFERROR(I252/(I180+I198),"n.a.") -> 0.82239966 | J97: =IFERROR(J252/(J180+J198),"n.a.") -> 0.83682391 | K97: =IFERROR(K252/(K180+K198),"n.a.") -> 0.85483735 | L97: =IFERROR(L252/(L180+L198),"n.a.") -> 0.84480108 | M97: =IFERROR(M252/(M180+M198),"n.a.") -> n.a. | ... O97: =IFERROR(O252/(O180+O198),"n.a.") -> 0.83457472
B98: India - Rajasthan | C98: % | D98: SAR | E98: Public | F98: =IFERROR(F253/(F181+F199),"n.a.") -> n.a. | G98: =IFERROR(G253/(G181+G199),"n.a.") -> n.a. | H98: =IFERROR(H253/(H181+H199),"n.a.") -> n.a. | I98: =IFERROR(I253/(I181+I199),"n.a.") -> n.a. | J98: =IFERROR(J253/(J181+J199),"n.a.") -> n.a. | K98: =IFERROR(K253/(K181+K199),"n.a.") -> n.a. | L98: =IFERROR(L253/(L181+L199),"n.a.") -> n.a. | M98: =IFERROR(M253/(M181+M199),"n.a.") -> n.a. | ... O98: =IFERROR(O253/(O181+O199),"n.a.") -> n.a.
B99: Kenya | C99: % | D99: AFR | E99: Public | F99: =IFERROR(F254/(F182+F200),"n.a.") -> n.a. | G99: =IFERROR(G254/(G182+G200),"n.a.") -> 0.99987398 | H99: =IFERROR(H254/(H182+H200),"n.a.") -> 0.97867148 | I99: =IFERROR(I254/(I182+I200),"n.a.") -> 0.95495741 | J99: =IFERROR(J254/(J182+J200),"n.a.") -> 0.85948378 | K99: =IFERROR(K254/(K182+K200),"n.a.") -> 0.86275078 | L99: =IFERROR(L254/(L182+L200),"n.a.") -> 0.82704144 | M99: =IFERROR(M254/(M182+M200),"n.a.") -> 0.80065053 | ... O99: =IFERROR(O254/(O182+O200),"n.a.") -> 0.89688828
B100: Morocco | C100: % | D100: MNA | E100: Public | F100: =IFERROR(F255/(F183+F201),"n.a.") -> n.a. | G100: =IFERROR(G255/(G183+G201),"n.a.") -> n.a. | H100: =IFERROR(H255/(H183+H201),"n.a.") -> n.a. | I100: =IFERROR(I255/(I183+I201),"n.a.") -> n.a. | J100: =IFERROR(J255/(J183+J201),"n.a.") -> n.a. | K100: =IFERROR(K255/(K183+K201),"n.a.") -> n.a. | L100: =IFERROR(L255/(L183+L201),"n.a.") -> n.a. | M100: =IFERROR(M255/(M183+M201),"n.a.") -> n.a. | ... O100: =IFERROR(O255/(O183+O201),"n.a.") -> n.a.
B101: Pakistan | C101: % | D101: SAR | E101: Mixed | F101: =IFERROR(F256/(F184+F202),"n.a.") -> n.a. | G101: =IFERROR(G256/(G184+G202),"n.a.") -> n.a. | H101: =IFERROR(H256/(H184+H202),"n.a.") -> n.a. | I101: =IFERROR(I256/(I184+I202),"n.a.") -> n.a. | J101: =IFERROR(J256/(J184+J202),"n.a.") -> 0.58113177 | K101: =IFERROR(K256/(K184+K202),"n.a.") -> 0.69825819 | L101: =IFERROR(L256/(L184+L202),"n.a.") -> 0.79245488 | M101: =IFERROR(M256/(M184+M202),"n.a.") -> 0.90329477 | ... O101: =IFERROR(O256/(O184+O202),"n.a.") -> 0.72945597
B102: Peru | C102: % | D102: LAC | E102: Mixed | F102: =IFERROR(F257/(F185+F203),"n.a.") -> n.a. | G102: =IFERROR(G257/(G185+G203),"n.a.") -> 1.0031522 | H102: =IFERROR(H257/(H185+H203),"n.a.") -> 1.0076358 | I102: =IFERROR(I257/(I185+I203),"n.a.") -> 0.99921345 | J102: =IFERROR(J257/(J185+J203),"n.a.") -> 0.96836614 | K102: =IFERROR(K257/(K185+K203),"n.a.") -> 0.94876884 | L102: =IFERROR(L257/(L185+L203),"n.a.") -> 0.9575477 | M102: =IFERROR(M257/(M185+M203),"n.a.") -> 0.9267825 | ... O102: =IFERROR(O257/(O185+O203),"n.a.") -> 0.97063885
B103: Philippines | C103: % | D103: EAP | E103: Private | F103: =IFERROR(F258/(F186+F204),"n.a.") -> n.a. | G103: =IFERROR(G258/(G186+G204),"n.a.") -> 0.97797741 | H103: =IFERROR(H258/(H186+H204),"n.a.") -> 0.96934979 | I103: =IFERROR(I258/(I186+I204),"n.a.") -> 1.001829 | J103: =IFERROR(J258/(J186+J204),"n.a.") -> 0.95074767 | K103: =IFERROR(K258/(K186+K204),"n.a.") -> 0.99199858 | L103: =IFERROR(L258/(L186+L204),"n.a.") -> 1.0032086 | M103: =IFERROR(M258/(M186+M204),"n.a.") -> 0.95874056 | ... O103: =IFERROR(O258/(O186+O204),"n.a.") -> 0.97879466
B104: Senegal | C104: % | D104: AFR | E104: Public | F104: =IFERROR(F259/(F187+F205),"n.a.") -> n.a. | G104: =IFERROR(G259/(G187+G205),"n.a.") -> 0.76681124 | H104: =IFERROR(H259/(H187+H205),"n.a.") -> 0.67947682 | I104: =IFERROR(I259/(I187+I205),"n.a.") -> 0.52775622 | J104: =IFERROR(J259/(J187+J205),"n.a.") -> 0.61027669 | K104: =IFERROR(K259/(K187+K205),"n.a.") -> 0.73026776 | L104: =IFERROR(L259/(L187+L205),"n.a.") -> 0.82000072 | M104: =IFERROR(M259/(M187+M205),"n.a.") -> 0.87210791 | ... O104: =IFERROR(O259/(O187+O205),"n.a.") -> 0.69196996
B105: Tajikistan | C105: % | D105: ECA | E105: Public | F105: =IFERROR(F260/(F188+F206),"n.a.") -> n.a. | G105: =IFERROR(G260/(G188+G206),"n.a.") -> n.a. | H105: =IFERROR(H260/(H188+H206),"n.a.") -> n.a. | I105: =IFERROR(I260/(I188+I206),"n.a.") -> n.a. | J105: =IFERROR(J260/(J188+J206),"n.a.") -> 0.32745822 | K105: =IFERROR(K260/(K188+K206),"n.a.") -> 0.50649389 | L105: =IFERROR(L260/(L188+L206),"n.a.") -> 0.68724001 | M105: =IFERROR(M260/(M188+M206),"n.a.") -> 0.59645204 | ... O105: =IFERROR(O260/(O188+O206),"n.a.") -> 0.4997431
... B109: Vietnam | C109: % | D109: EAP | E109: Public | F109: =IFERROR(F264/(F192+F210),"n.a.") -> n.a. | G109: =IFERROR(G264/(G192+G210),"n.a.") -> 0.90100501 | H109: =IFERROR(H264/(H192+H210),"n.a.") -> 0.85294221 | I109: =IFERROR(I264/(I192+I210),"n.a.") -> 0.91462756 | J109: =IFERROR(J264/(J192+J210),"n.a.") -> 0.88108623 | K109: =IFERROR(K264/(K192+K210),"n.a.") -> 0.88663102 | L109: =IFERROR(L264/(L192+L210),"n.a.") -> 0.88883686 | M109: =IFERROR(M264/(M192+M210),"n.a.") -> 0.87367258 | ... O109: =IFERROR(O264/(O192+O210),"n.a.") -> 0.88510843
B111: Financial operating cost recovery
B112: Colombia | C112: % | D112: LAC | E112: Private | F112: =IFERROR(F248/Costs!V3,"n.a.") -> n.a. | G112: =IFERROR(G248/Costs!W3,"n.a.") -> 1.2956465 | H112: =IFERROR(H248/Costs!X3,"n.a.") -> 1.6239247 | I112: =IFERROR(I248/Costs!Y3,"n.a.") -> 1.5223401 | J112: =IFERROR(J248/Costs!Z3,"n.a.") -> 1.4851594 | K112: =IFERROR(K248/Costs!AA3,"n.a.") -> 1.4552732 | L112: =IFERROR(L248/Costs!AB3,"n.a.") -> 1.4497486 | M112: =IFERROR(M248/Costs!AC3,"n.a.") -> 1.3941728 | ... O112: =IFERROR(O248/Costs!AE3,"n.a.") -> 1.465876 | X112: Tariffs/A1
B113: Dominican Republic | C113: % | D113: LAC | E113: Public | F113: =IFERROR(F249/Costs!V4,"n.a.") -> n.a. | G113: =IFERROR(G249/Costs!W4,"n.a.") -> 0.67291295 | H113: =IFERROR(H249/Costs!X4,"n.a.") -> 0.61635201 | I113: =IFERROR(I249/Costs!Y4,"n.a.") -> 0.57884894 | J113: =IFERROR(J249/Costs!Z4,"n.a.") -> 0.61418594 | K113: =IFERROR(K249/Costs!AA4,"n.a.") -> 0.58738934 | L113: =IFERROR(L249/Costs!AB4,"n.a.") -> 0.71246409 | M113: =IFERROR(M249/Costs!AC4,"n.a.") -> n.a. | ... O113: =IFERROR(O249/Costs!AE4,"n.a.") -> 0.6241441
B114: Egypt, Arab Rep. | C114: % | D114: MNA | E114: Public | F114: =IFERROR(F250/Costs!V5,"n.a.") -> n.a. | G114: =IFERROR(G250/Costs!W5,"n.a.") -> n.a. | H114: =IFERROR(H250/Costs!X5,"n.a.") -> 1.4297117 | I114: =IFERROR(I250/Costs!Y5,"n.a.") -> 1.2453586 | J114: =IFERROR(J250/Costs!Z5,"n.a.") -> 0.99596333 | K114: =IFERROR(K250/Costs!AA5,"n.a.") -> 1.030948 | L114: =IFERROR(L250/Costs!AB5,"n.a.") -> 1.2805745 | M114: =IFERROR(M250/Costs!AC5,"n.a.") -> 1.19381 | ... O114: =IFERROR(O250/Costs!AE5,"n.a.") -> 1.1987913
B115: India - Andhra Pradesh | C115: % | D115: SAR | E115: Public | F115: =IFERROR(F251/Costs!V6,"n.a.") -> n.a. | G115: =IFERROR(G251/Costs!W6,"n.a.") -> n.a. | H115: =IFERROR(H251/Costs!X6,"n.a.") -> n.a. | I115: =IFERROR(I251/Costs!Y6,"n.a.") -> n.a. | J115: =IFERROR(J251/Costs!Z6,"n.a.") -> n.a. | K115: =IFERROR(K251/Costs!AA6,"n.a.") -> n.a. | L115: =IFERROR(L251/Costs!AB6,"n.a.") -> n.a. | M115: =IFERROR(M251/Costs!AC6,"n.a.") -> n.a. | ... O115: =IFERROR(O251/Costs!AE6,"n.a.") -> n.a.
B116: India - Odisha | C116: % | D116: SAR | E116: Public | F116: =IFERROR(F252/Costs!V7,"n.a.") -> n.a. | G116: =IFERROR(G252/Costs!W7,"n.a.") -> n.a. | H116: =IFERROR(H252/Costs!X7,"n.a.") -> 0.88435654 | I116: =IFERROR(I252/Costs!Y7,"n.a.") -> 0.87953008 | J116: =IFERROR(J252/Costs!Z7,"n.a.") -> 0.89391254 | K116: =IFERROR(K252/Costs!AA7,"n.a.") -> 0.91684285 | L116: =IFERROR(L252/Costs!AB7,"n.a.") -> 0.92162023 | M116: =IFERROR(M252/Costs!AC7,"n.a.") -> n.a. | ... O116: =IFERROR(O252/Costs!AE7,"n.a.") -> 0.89888511
...

Sheet Costs
B1: Financial cost per unit - Country level | C1: Unit | D1: Region | E1: Type | F1: Pre-reform | G1: 2010 | H1: 2011 | I1: 2012 | J1: 2013 | K1: 2014 | L1: 2015 | M1: 2016 | N1: 2017 | O1: Average | R1: Financial cost per unit | S1: Unit | T1: Region | U1: Type | V1: 1987 | W1: 2010 | X1: 2011 | Y1: 2012 | Z1: 2013 | AA1: 2014 | AB1: 2015 | AC1: 2016 | AD1: 2017 | AE1: Average | AH1: Source
B2: A1 | R2: A1
B3: Colombia | C3: Current US$/kWh | D3: LAC | E3: Private | F3: n.a. | G3: 0.079219181 | H3: 0.087507206 | I3: 0.087998657 | J3: 0.084381364 | K3: 0.082776668 | L3: 0.064528803 | M3: 0.06751134 | N3: n.a. | O3: =IFERROR(AVERAGE(G3:N3),"n.a.") -> 0.079131888 | R3: Colombia | S3: 2017 US$/kWh | T3: LAC | U3: Private | V3: n.a. | W3: =IFERROR(G3*'Inflation adjustment'!$AH$3/'Inflation adjustment'!AA$3,"n.a.") -> 0.089051515 | X3: =IFERROR(H3*'Inflation adjustment'!$AH$3/'Inflation adjustment'!AB$3,"n.a.") -> 0.095357915 | Y3: =IFERROR(I3*'Inflation adjustment'!$AH$3/'Inflation adjustment'!AC$3,"n.a.") -> 0.093949327 | Z3: =IFERROR(J3*'Inflation adjustment'!$AH$3/'Inflation adjustment'!AD$3,"n.a.") -> 0.088786847 | AA3: =IFERROR(K3*'Inflation adjustment'!$AH$3/'Inflation adjustment'!AE$3,"n.a.") -> 0.085707995 | AB3: =IFERROR(L3*'Inflation adjustment'!$AH$3/'Inflation adjustment'!AF$3,"n.a.") -> 0.066734763 | AC3: =IFERROR(M3*'Inflation adjustment'!$AH$3/'Inflation adjustment'!AG$3,"n.a.") -> 0.068949406 | AD3: =IFERROR(N3*'Inflation adjustment'!$AH$3/'Inflation adjustment'!AH$3,"n.a.") -> n.a. | AE3: =IFERROR(AVERAGE(W3:AD3),"n.a.") -> 0.084076824 | AH3: Country models
B4: Dominican Republic | C4: Current US$/kWh | D4: LAC | E4: Public | F4: n.a. | G4: =G60 -> 0.22355185 | H4: =H60 -> 0.28297225 | I4: =I60 -> 0.31661839 | J4: =J60 -> 0.31498269 | K4: =K60 -> 0.31133266 | L4: =L60 -> 0.22560835 | M4: n.a. | N4: n.a. | O4: =IFERROR(AVERAGE(G4:N4),"n.a.") -> 0.2791777 | R4: Dominican Republic | S4: 2017 US$/kWh | T4: LAC | U4: Public | V4: n.a. | W4: =IFERROR(G4*'Inflation adjustment'!$AH$3/'Inflation adjustment'!AA$3,"n.a.") -> 0.25129812 | X4: =IFERROR(H4*'Inflation adjustment'!$AH$3/'Inflation adjustment'!AB$3,"n.a.") -> 0.3083591 | Y4: =IFERROR(I4*'Inflation adjustment'!$AH$3/'Inflation adjustment'!AC$3,"n.a.") -> 0.33802885 | Z4: =IFERROR(J4*'Inflation adjustment'!$AH$3/'Inflation adjustment'!AD$3,"n.a.") -> 0.33142768 | AA4: =IFERROR(K4*'Inflation adjustment'!$AH$3/'Inflation adjustment'!AE$3,"n.a.") -> 0.32235772 | AB4: =IFERROR(L4*'Inflation adjustment'!$AH$3/'Inflation adjustment'!AF$3,"n.a.") -> 0.23332092 | AC4: =IFERROR(M4*'Inflation adjustment'!$AH$3/'Inflation adjustment'!AG$3,"n.a.") -> n.a. | AD4: =IFERROR(N4*'Inflation adjustment'!$AH$3/'Inflation adjustment'!AH$3,"n.a.") -> n.a. | AE4: =IFERROR(AVERAGE(W4:AD4),"n.a.") -> 0.2974654
B5: Egypt, Arab Rep. | C5: Current US$/kWh | D5: MNA | E5: Public | F5: n.a. | G5: n.a. | H5: 0.026510711 | I5: 0.028679552 | J5: 0.026610193 | K5: 0.029395315 | L5: 0.034056403 | M5: 0.0373025 | N5: n.a. | O5: =IFERROR(AVERAGE(G5:N5),"n.a.") -> 0.030425779 | R5: Egypt, Arab Rep. | S5: 2017 US$/kWh | T5: MNA | U5: Public | V5: n.a. | W5: =IFERROR(G5*'Inflation adjustment'!$AH$3/'Inflation adjustment'!AA$3,"n.a.") -> n.a. | X5: =IFERROR(H5*'Inflation adjustment'!$AH$3/'Inflation adjustment'!AB$3,"n.a.") -> 0.028889119 | Y5: =IFERROR(I5*'Inflation adjustment'!$AH$3/'Inflation adjustment'!AC$3,"n.a.") -> 0.030618929 | Z5: =IFERROR(J5*'Inflation adjustment'!$AH$3/'Inflation adjustment'!AD$3,"n.a.") -> 0.02799949 | AA5: =IFERROR(K5*'Inflation adjustment'!$AH$3/'Inflation adjustment'!AE$3,"n.a.") -> 0.030436276 | AB5: =IFERROR(L5*'Inflation adjustment'!$AH$3/'Inflation adjustment'!AF$3,"n.a.") -> 0.035220644 | AC5: =IFERROR(M5*'Inflation adjustment'!$AH$3/'Inflation adjustment'!AG$3,"n.a.") -> 0.038097084 | AD5: =IFERROR(N5*'Inflation adjustment'!$AH$3/'Inflation adjustment'!AH$3,"n.a.") -> n.a. | AE5: =IFERROR(AVERAGE(W5:AD5),"n.a.") -> 0.031876924
B6: India - Andhra Pradesh | C6: Current US$/kWh | D6: SAR | E6: Public | F6: n.a. | G6: n.a. | H6: 0.082120363 | I6: 0.068505675 | J6: 0.097512196 | K6: 0.079654677 | L6: 0.084504626 | M6: n.a. | N6: n.a. | O6: =IFERROR(AVERAGE(G6:N6),"n.a.") -> 0.082459507 | R6: India - Andhra Pradesh | S6: 2017 US$/kWh | T6: SAR | U6: Public | V6: n.a. | W6: =IFERROR(G6*'Inflation adjustment'!$AH$3/'Inflation adjustment'!AA$3,"n.a.") -> n.a. | X6: =IFERROR(H6*'Inflation adjustment'!$AH$3/'Inflation adjustment'!AB$3,"n.a.") -> 0.089487791 | Y6: =IFERROR(I6*'Inflation adjustment'!$AH$3/'Inflation adjustment'!AC$3,"n.a.") -> 0.073138186 | Z6: =IFERROR(J6*'Inflation adjustment'!$AH$3/'Inflation adjustment'!AD$3,"n.a.") -> 0.10260323 | AA6: =IFERROR(K6*'Inflation adjustment'!$AH$3/'Inflation adjustment'!AE$3,"n.a.") -> 0.082475447 | AB6: =IFERROR(L6*'Inflation adjustment'!$AH$3/'Inflation adjustment'!AF$3,"n.a.") -> 0.087393473 | AC6: =IFERROR(M6*'Inflation adjustment'!$AH$3/'Inflation adjustment'!AG$3,"n.a.") -> n.a. | AD6: =IFERROR(N6*'Inflation adjustment'!$AH$3/'Inflation adjustment'!AH$3,"n.a.") -> n.a. | AE6: =IFERROR(AVERAGE(W6:AD6),"n.a.") -> 0.087019625
B7: India - Odisha | C7: Current US$/kWh | D7: SAR | E7: Public | F7: n.a. | G7: n.a. | H7: 0.086981732 | I7: 0.095092819 | J7: 0.09071712 | K7: 0.093779841 | L7: 0.088167148 | M7: n.a. | N7: n.a. | O7: =IFERROR(AVERAGE(G7:N7),"n.a.") -> 0.090947732 | R7: India - Odisha | S7: 2017 US$/kWh | T7: SAR | U7: Public | V7: n.a. | W7: =IFERROR(G7*'Inflation adjustment'!$AH$3/'Inflation adjustment'!AA$3,"n.a.") -> n.a. | X7: =IFERROR(H7*'Inflation adjustment'!$AH$3/'Inflation adjustment'!AB$3,"n.a.") -> 0.094785297 | Y7: =IFERROR(I7*'Inflation adjustment'!$AH$3/'Inflation adjustment'!AC$3,"n.a.") -> 0.10152321 | Z7: =IFERROR(J7*'Inflation adjustment'!$AH$3/'Inflation adjustment'!AD$3,"n.a.") -> 0.095453387 | AA7: =IFERROR(K7*'Inflation adjustment'!$AH$3/'Inflation adjustment'!AE$3,"n.a.") -> 0.097100818 | AB7: =IFERROR(L7*'Inflation adjustment'!$AH$3/'Inflation adjustment'!AF$3,"n.a.") -> 0.0911812 | AC7: =IFERROR(M7*'Inflation adjustment'!$AH$3/'Inflation adjustment'!AG$3,"n.a.") -> n.a. | AD7: =IFERROR(N7*'Inflation adjustment'!$AH$3/'Inflation adjustment'!AH$3,"n.a.") -> n.a. | AE7: =IFERROR(AVERAGE(W7:AD7),"n.a.") -> 0.096008783
B8: India - Rajasthan | C8: Current US$/kWh | D8: SAR | E8: Public | F8: n.a. | G8: n.a. | H8: 0.095805607 | I8: 0.085011699 | J8: 0.083681958 | K8: 0.098369235 | L8: 0.080206416 | M8: n.a. | N8: n.a. | O8: =IFERROR(AVERAGE(G8:N8),"n.a.") -> 0.088614983 | R8: India - Rajasthan | S8: 2017 US$/kWh | T8: SAR | U8: Public | V8: n.a. | W8: =IFERROR(G8*'Inflation adjustment'!$AH$3/'Inflation adjustment'!AA$3,"n.a.") -> n.a. | X8: =IFERROR(H8*'Inflation adjustment'!$AH$3/'Inflation adjustment'!AB$3,"n.a.") -> 0.10440081 | Y8: =IFERROR(I8*'Inflation adjustment'!$AH$3/'Inflation adjustment'!AC$3,"n.a.") -> 0.090760384 | Z8: =IFERROR(J8*'Inflation adjustment'!$AH$3/'Inflation adjustment'!AD$3,"n.a.") -> 0.088050925 | AA8: =IFERROR(K8*'Inflation adjustment'!$AH$3/'Inflation adjustment'!AE$3,"n.a.") -> 0.10185273 | AB8: =IFERROR(L8*'Inflation adjustment'!$AH$3/'Inflation adjustment'!AF$3,"n.a.") -> 0.082948325 | AC8: =IFERROR(M8*'Inflation adjustment'!$AH$3/'Inflation adjustment'!AG$3,"n.a.") -> n.a. | AD8: =IFERROR(N8*'Inflation adjustment'!$AH$3/'Inflation adjustment'!AH$3,"n.a.") -> n.a. | AE8: =IFERROR(AVERAGE(W8:AD8),"n.a.") -> 0.093602635
B9: Kenya | C9: Current US$/kWh | D9: AFR | E9: Public | F9: n.a. | G9: 0.16159701 | H9: 0.12128442 | I9: 0.16650468 | J9: 0.14590447 | K9: 0.14878772 | L9: 0.12721034 | M9: 0.11777459 | N9: n.a. | O9: =IFERROR(AVERAGE(G9:N9),"n.a.") -> 0.14129475 | R9: Kenya | S9: 2017 US$/kWh | T9: AFR | U9: Public | V9: n.a. | W9: =IFERROR(G9*'Inflation adjustment'!$AH$3/'Inflation adjustment'!AA$3,"n.a.") -> 0.18165371 | X9: =IFERROR(H9*'Inflation adjustment'!$AH$3/'Inflation adjustment'!AB$3,"n.a.") -> 0.13216545 | Y9: =IFERROR(I9*'Inflation adjustment'!$AH$3/'Inflation adjustment'!AC$3,"n.a.") -> 0.17776411 | Z9: =IFERROR(J9*'Inflation adjustment'!$AH$3/'Inflation adjustment'!AD$3,"n.a.") -> 0.15352202 | AA9: =IFERROR(K9*'Inflation adjustment'!$AH$3/'Inflation adjustment'!AE$3,"n.a.") -> 0.15405666 | AB9: =IFERROR(L9*'Inflation adjustment'!$AH$3/'Inflation adjustment'!AF$3,"n.a.") -> 0.13155911 | AC9: =IFERROR(M9*'Inflation adjustment'!$AH$3/'Inflation adjustment'!AG$3,"n.a.") -> 0.12028332 | AD9: =IFERROR(N9*'Inflation adjustment'!$AH$3/'Inflation adjustment'!AH$3,"n.a.") -> n.a. | AE9: =IFERROR(AVERAGE(W9:AD9),"n.a.") -> 0.15014348
B10: Morocco | C10: Current US$/kWh | D10: MNA | E10: Public | F10: n.a. | G10: n.a. | H10: n.a. | I10: n.a. | J10: n.a. | K10: n.a. | L10: n.a. | M10: n.a. | N10: n.a. | O10: =IFERROR(AVERAGE(G10:N10),"n.a.") -> n.a. | R10: Morocco | S10: 2017 US$/kWh | T10: MNA | U10: Public | V10: n.a. | W10: =IFERROR(G10*'Inflation adjustment'!$AH$3/'Inflation adjustment'!AA$3,"n.a.") -> n.a. | X10: =IFERROR(H10*'Inflation adjustment'!$AH$3/'Inflation adjustment'!AB$3,"n.a.") -> n.a. | Y10: =IFERROR(I10*'Inflation adjustment'!$AH$3/'Inflation adjustment'!AC$3,"n.a.") -> n.a. | Z10: =IFERROR(J10*'Inflation adjustment'!$AH$3/'Inflation adjustment'!AD$3,"n.a.") -> n.a. | AA10: =IFERROR(K10*'Inflation adjustment'!$AH$3/'Inflation adjustment'!AE$3,"n.a.") -> n.a. | AB10: =IFERROR(L10*'Inflation adjustment'!$AH$3/'Inflation adjustment'!AF$3,"n.a.") -> n.a. | AC10: =IFERROR(M10*'Inflation adjustment'!$AH$3/'Inflation adjustment'!AG$3,"n.a.") -> n.a. | AD10: =IFERROR(N10*'Inflation adjustment'!$AH$3/'Inflation adjustment'!AH$3,"n.a.") -> n.a. | AE10: =IFERROR(AVERAGE(W10:AD10),"n.a.") -> n.a.
B11: Pakistan | C11: Current US$/kWh | D11: SAR | E11: Mixed | F11: n.a. | G11: n.a. | H11: n.a. | I11: n.a. | J11: 0.090476352 | K11: 0.083579815 | L11: 0.077019315 | M11: 0.065316791 | N11: n.a. | O11: =IFERROR(AVERAGE(G11:N11),"n.a.") -> 0.079098068 | R11: Pakistan | S11: 2017 US$/kWh | T11: SAR | U11: Mixed | V11: n.a. | W11: =IFERROR(G11*'Inflation adjustment'!$AH$3/'Inflation adjustment'!AA$3,"n.a.") -> n.a. | X11: =IFERROR(H11*'Inflation adjustment'!$AH$3/'Inflation adjustment'!AB$3,"n.a.") -> n.a. | Y11: =IFERROR(I11*'Inflation adjustment'!$AH$3/'Inflation adjustment'!AC$3,"n.a.") -> n.a. | Z11: =IFERROR(J11*'Inflation adjustment'!$AH$3/'Inflation adjustment'!AD$3,"n.a.") -> 0.095200049 | AA11: =IFERROR(K11*'Inflation adjustment'!$AH$3/'Inflation adjustment'!AE$3,"n.a.") -> 0.086539585 | AB11: =IFERROR(L11*'Inflation adjustment'!$AH$3/'Inflation adjustment'!AF$3,"n.a.") -> 0.079652272 | AC11: =IFERROR(M11*'Inflation adjustment'!$AH$3/'Inflation adjustment'!AG$3,"n.a.") -> 0.06670811 | AD11: =IFERROR(N11*'Inflation adjustment'!$AH$3/'Inflation adjustment'!AH$3,"n.a.") -> n.a. | AE11: =IFERROR(AVERAGE(W11:AD11),"n.a.") -> 0.082025004
B12: Peru | C12: Current US$/kWh | D12: LAC | E12: Mixed | F12: n.a. | G12: 0.076105924 | H12: 0.079412779 | I12: 0.090800724 | J12: 0.093564209 | K12: 0.099215619 | L12: 0.097942808 | M12: 0.10407765 | N12: n.a. | O12: =IFERROR(AVERAGE(G12:N12),"n.a.") -> 0.09158853 | R12: Peru | S12: 2017 US$/kWh | T12: LAC | U12: Mixed | V12: n.a. | W12: =IFERROR(G12*'Inflation adjustment'!$AH$3/'Inflation adjustment'!AA$3,"n.a.") -> 0.085551854 | X12: =IFERROR(H12*'Inflation adjustment'!$AH$3/'Inflation adjustment'!AB$3,"n.a.") -> 0.086537296 | Y12: =IFERROR(I12*'Inflation adjustment'!$AH$3/'Inflation adjustment'!AC$3,"n.a.") -> 0.096940877 | Z12: =IFERROR(J12*'Inflation adjustment'!$AH$3/'Inflation adjustment'!AD$3,"n.a.") -> 0.09844912 | AA12: =IFERROR(K12*'Inflation adjustment'!$AH$3/'Inflation adjustment'!AE$3,"n.a.") -> 0.10272909 | AB12: =IFERROR(L12*'Inflation adjustment'!$AH$3/'Inflation adjustment'!AF$3,"n.a.") -> 0.10129105 | AC12: =IFERROR(M12*'Inflation adjustment'!$AH$3/'Inflation adjustment'!AG$3,"n.a.") -> 0.10629462 | AD12: =IFERROR(N12*'Inflation adjustment'!$AH$3/'Inflation adjustment'!AH$3,"n.a.") -> n.a. | AE12: =IFERROR(AVERAGE(W12:AD12),"n.a.") -> 0.096827701
B13: Philippines | C13: Current US$/kWh | D13: EAP | E13: Private | F13: n.a. | G13: 0.16446181 | H13: 0.17761957 | I13: 0.18995132 | J13: 0.18742841 | K13: 0.15195116 | L13: 0.1369573 | M13: 0.11775828 | N13: n.a. | O13: =IFERROR(AVERAGE(G13:N13),"n.a.") -> 0.16087541 | R13: Philippines | S13: 2017 US$/kWh | T13: EAP | U13: Private | V13: n.a. | W13: =IFERROR(G13*'Inflation adjustment'!$AH$3/'Inflation adjustment'!AA$3,"n.a.") -> 0.18487408 | X13: =IFERROR(H13*'Inflation adjustment'!$AH$3/'Inflation adjustment'!AB$3,"n.a.") -> 0.19355471 | Y13: =IFERROR(I13*'Inflation adjustment'!$AH$3/'Inflation adjustment'!AC$3,"n.a.") -> 0.20279627 | Z13: =IFERROR(J13*'Inflation adjustment'!$AH$3/'Inflation adjustment'!AD$3,"n.a.") -> 0.19721389 | AA13: =IFERROR(K13*'Inflation adjustment'!$AH$3/'Inflation adjustment'!AE$3,"n.a.") -> 0.15733212 | AB13: =IFERROR(L13*'Inflation adjustment'!$AH$3/'Inflation adjustment'!AF$3,"n.a.") -> 0.14163928 | AC13: =IFERROR(M13*'Inflation adjustment'!$AH$3/'Inflation adjustment'!AG$3,"n.a.") -> 0.12026666 | AD13: =IFERROR(N13*'Inflation adjustment'!$AH$3/'Inflation adjustment'!AH$3,"n.a.") -> n.a. | AE13: =IFERROR(AVERAGE(W13:AD13),"n.a.") -> 0.17109672
B14: Senegal | C14: Current US$/kWh | D14: AFR | E14: Public | F14: n.a. | G14: 0.27929705 | H14: 0.24968097 | I14: 0.24859571 | J14: 0.23533313 | K14: 0.24852823 | L14: 0.1808667 | M14: 0.19646559 | N14: n.a. | O14: =IFERROR(AVERAGE(G14:N14),"n.a.") -> 0.23410962 | R14: Senegal | S14: 2017 US$/kWh | T14: AFR | U14: Public | V14: n.a. | W14: =IFERROR(G14*'Inflation adjustment'!$AH$3/'Inflation adjustment'!AA$3,"n.a.") -> 0.31396216 | X14: =IFERROR(H14*'Inflation adjustment'!$AH$3/'Inflation adjustment'!AB$3,"n.a.") -> 0.2720811 | Y14: =IFERROR(I14*'Inflation adjustment'!$AH$3/'Inflation adjustment'!AC$3,"n.a.") -> 0.26540632 | Z14: =IFERROR(J14*'Inflation adjustment'!$AH$3/'Inflation adjustment'!AD$3,"n.a.") -> 0.24761968 | AA14: =IFERROR(K14*'Inflation adjustment'!$AH$3/'Inflation adjustment'!AE$3,"n.a.") -> 0.25732924 | AB14: =IFERROR(L14*'Inflation adjustment'!$AH$3/'Inflation adjustment'!AF$3,"n.a.") -> 0.18704975 | AC14: =IFERROR(M14*'Inflation adjustment'!$AH$3/'Inflation adjustment'!AG$3,"n.a.") -> 0.20065052 | AD14: =IFERROR(N14*'Inflation adjustment'!$AH$3/'Inflation adjustment'!AH$3,"n.a.") -> n.a. | AE14: =IFERROR(AVERAGE(W14:AD14),"n.a.") -> 0.24915697
B15: Tajikistan | C15: Current US$/kWh | D15: ECA | E15: Public | F15: n.a. | G15: n.a. | H15: n.a. | I15: n.a. | J15: 0.015599243 | K15: 0.01567062 | L15: 0.011713544 | M15: 0.013310213 | N15: n.a. | O15: =IFERROR(AVERAGE(G15:N15),"n.a.") -> 0.014073405 | R15: Tajikistan | S15: 2017 US$/kWh | T15: ECA | U15: Public | V15: n.a. | W15: =IFERROR(G15*'Inflation adjustment'!$AH$3/'Inflation adjustment'!AA$3,"n.a.") -> n.a. | X15: =IFERROR(H15*'Inflation adjustment'!$AH$3/'Inflation adjustment'!AB$3,"n.a.") -> n.a. | Y15: =IFERROR(I15*'Inflation adjustment'!$AH$3/'Inflation adjustment'!AC$3,"n.a.") -> n.a. | Z15: =IFERROR(J15*'Inflation adjustment'!$AH$3/'Inflation adjustment'!AD$3,"n.a.") -> 0.016413667 | AA15: =IFERROR(K15*'Inflation adjustment'!$AH$3/'Inflation adjustment'!AE$3,"n.a.") -> 0.016225556 | AB15: =IFERROR(L15*'Inflation adjustment'!$AH$3/'Inflation adjustment'!AF$3,"n.a.") -> 0.01211398 | AC15: =IFERROR(M15*'Inflation adjustment'!$AH$3/'Inflation adjustment'!AG$3,"n.a.") -> 0.013593735 | AD15: =IFERROR(N15*'Inflation adjustment'!$AH$3/'Inflation adjustment'!AH$3,"n.a.") -> n.a. | AE15: =IFERROR(AVERAGE(W15:AD15),"n.a.") -> 0.014586734
B16: Tanzania | C16: Current US$/kWh | D16: AFR | E16: Public | F16: n.a. | G16: n.a. | H16: n.a. | I16: 0.14448677 | J16: 0.16296886 | K16: n.a. | L16: 0.1232226 | M16: 0.10440412 | N16: n.a. | O16: =IFERROR(AVERAGE(G16:N16),"n.a.") -> 0.13377059 | R16: Tanzania | S16: 2017 US$/kWh | T16: AFR | U16: Public | V16: n.a. | W16: =IFERROR(G16*'Inflation adjustment'!$AH$3/'Inflation adjustment'!AA$3,"n.a.") -> n.a. | X16: =IFERROR(H16*'Inflation adjustment'!$AH$3/'Inflation adjustment'!AB$3,"n.a.") -> n.a. | Y16: =IFERROR(I16*'Inflation adjustment'!$AH$3/'Inflation adjustment'!AC$3,"n.a.") -> 0.1542573 | Z16: =IFERROR(J16*'Inflation adjustment'!$AH$3/'Inflation adjustment'!AD$3,"n.a.") -> 0.17147733 | AA16: n.a. | AB16: 0.12758622 | AC16: 0.10797324 | AD16: =IFERROR(N16*'Inflation adjustment'!$AH$3/'Inflation adjustment'!AH$3,"n.a.") -> n.a. | AE16: =IFERROR(AVERAGE(W16:AD16),"n.a.") -> 0.14032352
B17: Uganda | C17: Current US$/kWh | D17: AFR | E17: Private | F17: n.a. | G17: n.a. | H17: n.a. | I17: 0.14253815 | J17: 0.13925368 | K17: 0.13173169 | L17: 0.12073561 | M17: 0.11421765 | N17: n.a. | O17: =IFERROR(AVERAGE(G17:N17),"n.a.") -> 0.12969536 | R17: Uganda | S17: 2017 US$/kWh | T17: AFR | U17: Private | V17: n.a. | W17: =IFERROR(G17*'Inflation adjustment'!$AH$3/'Inflation adjustment'!AA$3,"n.a.") -> n.a. | X17: =IFERROR(H17*'Inflation adjustment'!$AH$3/'Inflation adjustment'!AB$3,"n.a.") -> n.a. | Y17: =IFERROR(I17*'Inflation adjustment'!$AH$3/'Inflation adjustment'!AC$3,"n.a.") -> 0.15217691 | Z17: =IFERROR(J17*'Inflation adjustment'!$AH$3/'Inflation adjustment'!AD$3,"n.a.") -> 0.146524 | AA17: =IFERROR(K17*'Inflation adjustment'!$AH$3/'Inflation adjustment'!AE$3,"n.a.") -> 0.13639664 | AB17: =IFERROR(L17*'Inflation adjustment'!$AH$3/'Inflation adjustment'!AF$3,"n.a.") -> 0.12486304 | AC17: =IFERROR(M17*'Inflation adjustment'!$AH$3/'Inflation adjustment'!AG$3,"n.a.") -> 0.11665061 | AD17: =IFERROR(N17*'Inflation adjustment'!$AH$3/'Inflation adjustment'!AH$3,"n.a.") -> n.a. | AE17: =IFERROR(AVERAGE(W17:AD17),"n.a.") -> 0.13532224
B18: Ukraine | C18: Current US$/kWh | D18: ECA | E18: Mixed | F18: n.a. | G18: n.a. | H18: n.a. | I18: 0.073287909 | J18: 0.069842227 | K18: 0.052412946 | L18: 0.040097189 | M18: 0.043199216 | N18: 0.045924694 | O18: =IFERROR(AVERAGE(G18:N18),"n.a.") -> 0.054127363 | R18: Ukraine | S18: 2017 US$/kWh | T18: ECA | U18: Mixed | V18: n.a. | W18: =IFERROR(G18*'Inflation adjustment'!$AH$3/'Inflation adjustment'!AA$3,"n.a.") -> n.a. | X18: =IFERROR(H18*'Inflation adjustment'!$AH$3/'Inflation adjustment'!AB$3,"n.a.") -> n.a. | Y18: =IFERROR(I18*'Inflation adjustment'!$AH$3/'Inflation adjustment'!AC$3,"n.a.") -> 0.078243806 | Z18: =IFERROR(J18*'Inflation adjustment'!$AH$3/'Inflation adjustment'!AD$3,"n.a.") -> 0.073488633 | AA18: =IFERROR(K18*'Inflation adjustment'!$AH$3/'Inflation adjustment'!AE$3,"n.a.") -> 0.054269019 | AB18: =IFERROR(L18*'Inflation adjustment'!$AH$3/'Inflation adjustment'!AF$3,"n.a.") -> 0.041467938 | AC18: =IFERROR(M18*'Inflation adjustment'!$AH$3/'Inflation adjustment'!AG$3,"n.a.") -> 0.044119407 | AD18: =IFERROR(N18*'Inflation adjustment'!$AH$3/'Inflation adjustment'!AH$3,"n.a.") -> 0.045924694 | AE18: =IFERROR(AVERAGE(W18:AD18),"n.a.") -> 0.056252249
B19: Vietnam | C19: Current US$/kWh | D19: EAP | E19: Public | F19: n.a. | G19: 0.050130776 | H19: 0.055452512 | I19: 0.058694803 | J19: 0.064884385 | K19: 0.067327743 | L19: 0.0696931 | M19: 0.072269036 | N19: n.a. | O19: =IFERROR(AVERAGE(G19:N19),"n.a.") -> 0.062636051 | R19: Vietnam | S19: 2017 US$/kWh | T19: EAP | U19: Public | V19: n.a. | W19: =IFERROR(G19*'Inflation adjustment'!$AH$3/'Inflation adjustment'!AA$3,"n.a.") -> 0.056352786 | X19: =IFERROR(H19*'Inflation adjustment'!$AH$3/'Inflation adjustment'!AB$3,"n.a.") -> 0.060427434 | Y19: =IFERROR(I19*'Inflation adjustment'!$AH$3/'Inflation adjustment'!AC$3,"n.a.") -> 0.06266388 | Z19: =IFERROR(J19*'Inflation adjustment'!$AH$3/'Inflation adjustment'!AD$3,"n.a.") -> 0.068271946 | AA19: =IFERROR(K19*'Inflation adjustment'!$AH$3/'Inflation adjustment'!AE$3,"n.a.") -> 0.069711985 | AB19: =IFERROR(L19*'Inflation adjustment'!$AH$3/'Inflation adjustment'!AF$3,"n.a.") -> 0.072075605 | AC19: =IFERROR(M19*'Inflation adjustment'!$AH$3/'Inflation adjustment'!AG$3,"n.a.") -> 0.073808446 | AD19: =IFERROR(N19*'Inflation adjustment'!$AH$3/'Inflation adjustment'!AH$3,"n.a.") -> n.a. | AE19: =IFERROR(AVERAGE(W19:AD19),"n.a.") -> 0.06618744
B20: A2 | R20: A2
B21: Colombia | C21: Current US$/kWh | D21: LAC | E21: Private | F21: n.a. | G21: 0.12812138 | H21: 0.1141869 | I21: 0.10817999 | J21: 0.11683024 | K21: 0.11498493 | L21: 0.081847087 | M21: 0.086783296 | N21: n.a. | O21: =IFERROR(AVERAGE(G21:N21),"n.a.") -> 0.10727626 | R21: Colombia | S21: 2017 US$/kWh | T21: LAC | U21: Private | V21: n.a. | W21: =IFERROR(G21*'Inflation adjustment'!$AH$3/'Inflation adjustment'!AA$3,"n.a.") -> 0.14402324 | X21: =IFERROR(H21*'Inflation adjustment'!$AH$3/'Inflation adjustment'!AB$3,"n.a.") -> 0.12443117 | Y21: =IFERROR(I21*'Inflation adjustment'!$AH$3/'Inflation adjustment'!AC$3,"n.a.") -> 0.11549537 | Z21: =IFERROR(J21*'Inflation adjustment'!$AH$3/'Inflation adjustment'!AD$3,"n.a.") -> 0.12292986 | AA21: =IFERROR(K21*'Inflation adjustment'!$AH$3/'Inflation adjustment'!AE$3,"n.a.") -> 0.11905683 | AB21: =IFERROR(L21*'Inflation adjustment'!$AH$3/'Inflation adjustment'!AF$3,"n.a.") -> 0.084645084 | AC21: =IFERROR(M21*'Inflation adjustment'!$AH$3/'Inflation adjustment'!AG$3,"n.a.") -> 0.088631876 | AD21: =IFERROR(N21*'Inflation adjustment'!$AH$3/'Inflation adjustment'!AH$3,"n.a.") -> n.a. | AE21: =IFERROR(AVERAGE(W21:AD21),"n.a.") -> 0.11417335
B22: Dominican Republic | C22: Current US$/kWh | D22: LAC | E22: Public | F22: n.a. | G22: n.a. | H22: n.a. | I22: n.a. | J22: n.a. | K22: n.a. | L22: n.a. | M22: n.a. | N22: n.a. | O22: =IFERROR(AVERAGE(G22:N22),"n.a.") -> n.a. | R22: Dominican Republic | S22: 2017 US$/kWh | T22: LAC | U22: Public | V22: n.a. | W22: =IFERROR(G22*'Inflation adjustment'!$AH$3/'Inflation adjustment'!AA$3,"n.a.") -> n.a. | X22: =IFERROR(H22*'Inflation adjustment'!$AH$3/'Inflation adjustment'!AB$3,"n.a.") -> n.a. | Y22: =IFERROR(I22*'Inflation adjustment'!$AH$3/'Inflation adjustment'!AC$3,"n.a.") -> n.a. | Z22: =IFERROR(J22*'Inflation adjustment'!$AH$3/'Inflation adjustment'!AD$3,"n.a.") -> n.a. | AA22: =IFERROR(K22*'Inflation adjustment'!$AH$3/'Inflation adjustment'!AE$3,"n.a.") -> n.a. | AB22: =IFERROR(L22*'Inflation adjustment'!$AH$3/'Inflation adjustment'!AF$3,"n.a.") -> n.a. | AC22: =IFERROR(M22*'Inflation adjustment'!$AH$3/'Inflation adjustment'!AG$3,"n.a.") -> n.a. | AD22: =IFERROR(N22*'Inflation adjustment'!$AH$3/'Inflation adjustment'!AH$3,"n.a.") -> n.a. | AE22: =IFERROR(AVERAGE(W22:AD22),"n.a.") -> n.a.
B23: Egypt, Arab Rep. | C23: Current US$/kWh | D23: MNA | E23: Public | F23: n.a. | G23: n.a. | H23: 0.041184416 | I23: 0.042818544 | J23: 0.041194011 | K23: 0.043461188 | L23: 0.047468208 | M23: 0.053204766 | N23: n.a. | O23: =IFERROR(AVERAGE(G23:N23),"n.a.") -> 0.044888522 | R23: Egypt, Arab Rep. | S23: 2017 US$/kWh | T23: MNA | U23: Public | V23: n.a. | W23: =IFERROR(G23*'Inflation adjustment'!$AH$3/'Inflation adjustment'!AA$3,"n.a.") -> n.a. | X23: =IFERROR(H23*'Inflation adjustment'!$AH$3/'Inflation adjustment'!AB$3,"n.a.") -> 0.044879276 | Y23: =IFERROR(I23*'Inflation adjustment'!$AH$3/'Inflation adjustment'!AC$3,"n.a.") -> 0.045714032 | Z23: =IFERROR(J23*'Inflation adjustment'!$AH$3/'Inflation adjustment'!AD$3,"n.a.") -> 0.043344717 | AA23: =IFERROR(K23*'Inflation adjustment'!$AH$3/'Inflation adjustment'!AE$3,"n.a.") -> 0.045000256 | AB23: =IFERROR(L23*'Inflation adjustment'!$AH$3/'Inflation adjustment'!AF$3,"n.a.") -> 0.04909094 | AC23: =IFERROR(M23*'Inflation adjustment'!$AH$3/'Inflation adjustment'!AG$3,"n.a.") -> 0.054338086 | AD23: =IFERROR(N23*'Inflation adjustment'!$AH$3/'Inflation adjustment'!AH$3,"n.a.") -> n.a. | AE23: =IFERROR(AVERAGE(W23:AD23),"n.a.") -> 0.047061218
B24: India - Andhra Pradesh | C24: Current US$/kWh | D24: SAR | E24: Public | F24: n.a. | G24: n.a. | H24: 0.14855957 | I24: 0.12101661 | J24: 0.15094989 | K24: 0.15111325 | L24: 0.11793443 | M24: n.a. | N24: n.a. | O24: =IFERROR(AVERAGE(G24:N24),"n.a.") -> 0.13791475 | R24: India - Andhra Pradesh | S24: 2017 US$/kWh | T24: SAR | U24: Public | V24: n.a. | W24: =IFERROR(G24*'Inflation adjustment'!$AH$3/'Inflation adjustment'!AA$3,"n.a.") -> n.a. | X24: =IFERROR(H24*'Inflation adjustment'!$AH$3/'Inflation adjustment'!AB$3,"n.a.") -> 0.16188759 | Y24: =IFERROR(I24*'Inflation adjustment'!$AH$3/'Inflation adjustment'!AC$3,"n.a.") -> 0.12920003 | Z24: =IFERROR(J24*'Inflation adjustment'!$AH$3/'Inflation adjustment'!AD$3,"n.a.") -> 0.15883086 | AA24: =IFERROR(K24*'Inflation adjustment'!$AH$3/'Inflation adjustment'!AE$3,"n.a.") -> 0.15646455 | AB24: =IFERROR(L24*'Inflation adjustment'!$AH$3/'Inflation adjustment'!AF$3,"n.a.") -> 0.1219661 | AC24: =IFERROR(M24*'Inflation adjustment'!$AH$3/'Inflation adjustment'!AG$3,"n.a.") -> n.a. | AD24: =IFERROR(N24*'Inflation adjustment'!$AH$3/'Inflation adjustment'!AH$3,"n.a.") -> n.a. | AE24: =IFERROR(AVERAGE(W24:AD24),"n.a.") -> 0.14566983
B25: India - Odisha | C25: Current US$/kWh | D25: SAR | E25: Public | F25: n.a. | G25: n.a. | H25: 0.091087933 | I25: 0.09818035 | J25: 0.093388428 | K25: 0.096585602 | L25: 0.091024343 | M25: n.a. | N25: n.a. | O25: =IFERROR(AVERAGE(G25:N25),"n.a.") -> 0.094053331 | R25: India - Odisha | S25: 2017 US$/kWh | T25: SAR | U25: Public | V25: n.a. | W25: =IFERROR(G25*'Inflation adjustment'!$AH$3/'Inflation adjustment'!AA$3,"n.a.") -> n.a. | X25: =IFERROR(H25*'Inflation adjustment'!$AH$3/'Inflation adjustment'!AB$3,"n.a.") -> 0.099259887 | Y25: =IFERROR(I25*'Inflation adjustment'!$AH$3/'Inflation adjustment'!AC$3,"n.a.") -> 0.10481953 | Z25: =IFERROR(J25*'Inflation adjustment'!$AH$3/'Inflation adjustment'!AD$3,"n.a.") -> 0.098264162 | AA25: =IFERROR(K25*'Inflation adjustment'!$AH$3/'Inflation adjustment'!AE$3,"n.a.") -> 0.10000594 | AB25: =IFERROR(L25*'Inflation adjustment'!$AH$3/'Inflation adjustment'!AF$3,"n.a.") -> 0.09413607 | AC25: =IFERROR(M25*'Inflation adjustment'!$AH$3/'Inflation adjustment'!AG$3,"n.a.") -> n.a. | AD25: =IFERROR(N25*'Inflation adjustment'!$AH$3/'Inflation adjustment'!AH$3,"n.a.") -> n.a. | AE25: =IFERROR(AVERAGE(W25:AD25),"n.a.") -> 0.099297118
B26: India - Rajasthan | C26: Current US$/kWh | D26: SAR | E26: Public | F26: n.a. | G26: n.a. | H26: 0.15417766 | I26: 0.13000002 | J26: 0.12101956 | K26: 0.16793225 | L26: 0.11560496 | M26: n.a. | N26: n.a. | O26: =IFERROR(AVERAGE(G26:N26),"n.a.") -> 0.13774689 | R26: India - Rajasthan | S26: 2017 US$/kWh | T26: SAR | U26: Public | V26: n.a. | W26: =IFERROR(G26*'Inflation adjustment'!$AH$3/'Inflation adjustment'!AA$3,"n.a.") -> n.a. | X26: =IFERROR(H26*'Inflation adjustment'!$AH$3/'Inflation adjustment'!AB$3,"n.a.") -> 0.1680097 | Y26: =IFERROR(I26*'Inflation adjustment'!$AH$3/'Inflation adjustment'!AC$3,"n.a.") -> 0.13879092 | Z26: =IFERROR(J26*'Inflation adjustment'!$AH$3/'Inflation adjustment'!AD$3,"n.a.") -> 0.12733789 | AA26: =IFERROR(K26*'Inflation adjustment'!$AH$3/'Inflation adjustment'!AE$3,"n.a.") -> 0.17387915 | AB26: =IFERROR(L26*'Inflation adjustment'!$AH$3/'Inflation adjustment'!AF$3,"n.a.") -> 0.11955699 | AC26: =IFERROR(M26*'Inflation adjustment'!$AH$3/'Inflation adjustment'!AG$3,"n.a.") -> n.a. | AD26: =IFERROR(N26*'Inflation adjustment'!$AH$3/'Inflation adjustment'!AH$3,"n.a.") -> n.a. | AE26: =IFERROR(AVERAGE(W26:AD26),"n.a.") -> 0.14551493
B27: Kenya | C27: Current US$/kWh | D27: AFR | E27: Public | F27: n.a. | G27: 0.17223045 | H27: 0.12725827 | I27: 0.17491067 | J27: 0.15176736 | K27: 0.15723006 | L27: 0.13791254 | M27: 0.12957176 | N27: n.a. | O27: =IFERROR(AVERAGE(G27:N27),"n.a.") -> 0.15012587 | R27: Kenya | S27: 2017 US$/kWh | T27: AFR | U27: Public | V27: n.a. | W27: =IFERROR(G27*'Inflation adjustment'!$AH$3/'Inflation adjustment'!AA$3,"n.a.") -> 0.19360694 | X27: =IFERROR(H27*'Inflation adjustment'!$AH$3/'Inflation adjustment'!AB$3,"n.a.") -> 0.13867524 | Y27: =IFERROR(I27*'Inflation adjustment'!$AH$3/'Inflation adjustment'!AC$3,"n.a.") -> 0.18673853 | Z27: =IFERROR(J27*'Inflation adjustment'!$AH$3/'Inflation adjustment'!AD$3,"n.a.") -> 0.15969101 | AA27: =IFERROR(K27*'Inflation adjustment'!$AH$3/'Inflation adjustment'!AE$3,"n.a.") -> 0.16279797 | AB27: =IFERROR(L27*'Inflation adjustment'!$AH$3/'Inflation adjustment'!AF$3,"n.a.") -> 0.14262717 | AC27: =IFERROR(M27*'Inflation adjustment'!$AH$3/'Inflation adjustment'!AG$3,"n.a.") -> 0.13233178 | AD27: =IFERROR(N27*'Inflation adjustment'!$AH$3/'Inflation adjustment'!AH$3,"n.a.") -> n.a. | AE27: =IFERROR(AVERAGE(W27:AD27),"n.a.") -> 0.15949552
B28: Morocco | C28: Current US$/kWh | D28: MNA | E28: Public | F28: n.a. | G28: n.a. | H28: n.a. | I28: n.a. | J28: n.a. | K28: n.a. | L28: n.a. | M28: n.a. | N28: n.a. | O28: =IFERROR(AVERAGE(G28:N28),"n.a.") -> n.a. | R28: Morocco | S28: 2017 US$/kWh | T28: MNA | U28: Public | V28: n.a. | W28: =IFERROR(G28*'Inflation adjustment'!$AH$3/'Inflation adjustment'!AA$3,"n.a.") -> n.a. | X28: =IFERROR(H28*'Inflation adjustment'!$AH$3/'Inflation adjustment'!AB$3,"n.a.") -> n.a. | Y28: =IFERROR(I28*'Inflation adjustment'!$AH$3/'Inflation adjustment'!AC$3,"n.a.") -> n.a. | Z28: =IFERROR(J28*'Inflation adjustment'!$AH$3/'Inflation adjustment'!AD$3,"n.a.") -> n.a. | AA28: =IFERROR(K28*'Inflation adjustment'!$AH$3/'Inflation adjustment'!AE$3,"n.a.") -> n.a. | AB28: =IFERROR(L28*'Inflation adjustment'!$AH$3/'Inflation adjustment'!AF$3,"n.a.") -> n.a. | AC28: =IFERROR(M28*'Inflation adjustment'!$AH$3/'Inflation adjustment'!AG$3,"n.a.") -> n.a. | AD28: =IFERROR(N28*'Inflation adjustment'!$AH$3/'Inflation adjustment'!AH$3,"n.a.") -> n.a. | AE28: =IFERROR(AVERAGE(W28:AD28),"n.a.") -> n.a.
B29: Pakistan | C29: Current US$/kWh | D29: SAR | E29: Mixed | F29: n.a. | G29: n.a. | H29: n.a. | I29: n.a. | J29: 0.097586718 | K29: 0.091330536 | L29: 0.085173226 | M29: 0.07262007 | N29: n.a. | O29: =IFERROR(AVERAGE(G29:N29),"n.a.") -> 0.086677638 | R29: Pakistan | S29: 2017 US$/kWh | T29: SAR | U29: Mixed | V29: n.a. | W29: =IFERROR(G29*'Inflation adjustment'!$AH$3/'Inflation adjustment'!AA$3,"n.a.") -> n.a. | X29: =IFERROR(H29*'Inflation adjustment'!$AH$3/'Inflation adjustment'!AB$3,"n.a.") -> n.a. | Y29: =IFERROR(I29*'Inflation adjustment'!$AH$3/'Inflation adjustment'!AC$3,"n.a.") -> n.a. | Z29: =IFERROR(J29*'Inflation adjustment'!$AH$3/'Inflation adjustment'!AD$3,"n.a.") -> 0.10268164 | AA29: =IFERROR(K29*'Inflation adjustment'!$AH$3/'Inflation adjustment'!AE$3,"n.a.") -> 0.094564777 | AB29: =IFERROR(L29*'Inflation adjustment'!$AH$3/'Inflation adjustment'!AF$3,"n.a.") -> 0.08808493 | AC29: =IFERROR(M29*'Inflation adjustment'!$AH$3/'Inflation adjustment'!AG$3,"n.a.") -> 0.074166958 | AD29: =IFERROR(N29*'Inflation adjustment'!$AH$3/'Inflation adjustment'!AH$3,"n.a.") -> n.a. | AE29: =IFERROR(AVERAGE(W29:AD29),"n.a.") -> 0.089874576
B30: Peru | C30: Current US$/kWh | D30: LAC | E30: Mixed | F30: n.a. | G30: 0.1019539 | H30: 0.10249485 | I30: 0.11288124 | J30: 0.11438743 | K30: 0.12420886 | L30: 0.12030152 | M30: 0.13126792 | N30: n.a. | O30: =IFERROR(AVERAGE(G30:N30),"n.a.") -> 0.11535653 | R30: Peru | S30: 2017 US$/kWh | T30: LAC | U30: Mixed | V30: n.a. | W30: =IFERROR(G30*'Inflation adjustment'!$AH$3/'Inflation adjustment'!AA$3,"n.a.") -> 0.11460797 | X30: =IFERROR(H30*'Inflation adjustment'!$AH$3/'Inflation adjustment'!AB$3,"n.a.") -> 0.11169018 | Y30: =IFERROR(I30*'Inflation adjustment'!$AH$3/'Inflation adjustment'!AC$3,"n.a.") -> 0.12051453 | Z30: =IFERROR(J30*'Inflation adjustment'!$AH$3/'Inflation adjustment'!AD$3,"n.a.") -> 0.1203595 | AA30: =IFERROR(K30*'Inflation adjustment'!$AH$3/'Inflation adjustment'!AE$3,"n.a.") -> 0.12860741 | AB30: =IFERROR(L30*'Inflation adjustment'!$AH$3/'Inflation adjustment'!AF$3,"n.a.") -> 0.1244141 | AC30: =IFERROR(M30*'Inflation adjustment'!$AH$3/'Inflation adjustment'!AG$3,"n.a.") -> 0.13406407 | AD30: =IFERROR(N30*'Inflation adjustment'!$AH$3/'Inflation adjustment'!AH$3,"n.a.") -> n.a. | AE30: =IFERROR(AVERAGE(W30:AD30),"n.a.") -> 0.12203682
B31: Philippines | C31: Current US$/kWh | D31: EAP | E31: Private | F31: n.a. | G31: 0.1804066 | H31: 0.19382686 | I31: 0.20383754 | J31: 0.21146825 | K31: 0.17069967 | L31: 0.14966606 | M31: 0.13466022 | N31: n.a. | O31: =IFERROR(AVERAGE(G31:N31),"n.a.") -> 0.17779503 | R31: Philippines | S31: 2017 US$/kWh | T31: EAP | U31: Private | V31: n.a. | W31: =IFERROR(G31*'Inflation adjustment'!$AH$3/'Inflation adjustment'!AA$3,"n.a.") -> 0.20279786 | X31: =IFERROR(H31*'Inflation adjustment'!$AH$3/'Inflation adjustment'!AB$3,"n.a.") -> 0.21121604 | Y31: =IFERROR(I31*'Inflation adjustment'!$AH$3/'Inflation adjustment'!AC$3,"n.a.") -> 0.21762151 | Z31: =IFERROR(J31*'Inflation adjustment'!$AH$3/'Inflation adjustment'!AD$3,"n.a.") -> 0.22250884 | AA31: =IFERROR(K31*'Inflation adjustment'!$AH$3/'Inflation adjustment'!AE$3,"n.a.") -> 0.17674457 | AB31: =IFERROR(L31*'Inflation adjustment'!$AH$3/'Inflation adjustment'!AF$3,"n.a.") -> 0.1547825 | AC31: =IFERROR(M31*'Inflation adjustment'!$AH$3/'Inflation adjustment'!AG$3,"n.a.") -> 0.13752863 | AD31: =IFERROR(N31*'Inflation adjustment'!$AH$3/'Inflation adjustment'!AH$3,"n.a.") -> n.a. | AE31: =IFERROR(AVERAGE(W31:AD31),"n.a.") -> 0.18902856
B32: Senegal | C32: Current US$/kWh | D32: AFR | E32: Public | F32: n.a. | G32: 0.29164138 | H32: 0.26204393 | I32: 0.31066814 | J32: 0.27259251 | K32: 0.26388205 | L32: 0.19174313 | M32: 0.20568256 | N32: n.a. | O32: =IFERROR(AVERAGE(G32:N32),"n.a.") -> 0.25689338 | R32: Senegal | S32: 2017 US$/kWh | T32: AFR | U32: Public | V32: n.a. | W32: =IFERROR(G32*'Inflation adjustment'!$AH$3/'Inflation adjustment'!AA$3,"n.a.") -> 0.32783861 | X32: =IFERROR(H32*'Inflation adjustment'!$AH$3/'Inflation adjustment'!AB$3,"n.a.") -> 0.2855532 | Y32: =IFERROR(I32*'Inflation adjustment'!$AH$3/'Inflation adjustment'!AC$3,"n.a.") -> 0.33167623 | Z32: =IFERROR(J32*'Inflation adjustment'!$AH$3/'Inflation adjustment'!AD$3,"n.a.") -> 0.28682434 | AA32: =IFERROR(K32*'Inflation adjustment'!$AH$3/'Inflation adjustment'!AE$3,"n.a.") -> 0.27322677 | AB32: =IFERROR(L32*'Inflation adjustment'!$AH$3/'Inflation adjustment'!AF$3,"n.a.") -> 0.198298 | AC32: =IFERROR(M32*'Inflation adjustment'!$AH$3/'Inflation adjustment'!AG$3,"n.a.") -> 0.21006383 | AD32: =IFERROR(N32*'Inflation adjustment'!$AH$3/'Inflation adjustment'!AH$3,"n.a.") -> n.a. | AE32: =IFERROR(AVERAGE(W32:AD32),"n.a.") -> 0.27335443
B33: Tajikistan | C33: Current US$/kWh | D33: ECA | E33: Public | F33: n.a. | G33: n.a. | H33: n.a. | I33: n.a. | J33: 0.016853355 | K33: 0.017475483 | L33: 0.013906536 | M33: 0.015927787 | N33: n.a. | O33: =IFERROR(AVERAGE(G33:N33),"n.a.") -> 0.01604079 | R33: Tajikistan | S33: 2017 US$/kWh | T33: ECA | U33: Public | V33: n.a. | W33: =IFERROR(G33*'Inflation adjustment'!$AH$3/'Inflation adjustment'!AA$3,"n.a.") -> n.a. | X33: =IFERROR(H33*'Inflation adjustment'!$AH$3/'Inflation adjustment'!AB$3,"n.a.") -> n.a. | Y33: =IFERROR(I33*'Inflation adjustment'!$AH$3/'Inflation adjustment'!AC$3,"n.a.") -> n.a. | Z33: =IFERROR(J33*'Inflation adjustment'!$AH$3/'Inflation adjustment'!AD$3,"n.a.") -> 0.017733255 | AA33: =IFERROR(K33*'Inflation adjustment'!$AH$3/'Inflation adjustment'!AE$3,"n.a.") -> 0.018094334 | AB33: =IFERROR(L33*'Inflation adjustment'!$AH$3/'Inflation adjustment'!AF$3,"n.a.") -> 0.014381941 | AC33: =IFERROR(M33*'Inflation adjustment'!$AH$3/'Inflation adjustment'!AG$3,"n.a.") -> 0.016267066 | AD33: =IFERROR(N33*'Inflation adjustment'!$AH$3/'Inflation adjustment'!AH$3,"n.a.") -> n.a. | AE33: =IFERROR(AVERAGE(W33:AD33),"n.a.") -> 0.016619149
B34: Tanzania | C34: Current US$/kWh | D34: AFR | E34: Public | F34: n.a. | G34: n.a. | H34: n.a. | I34: 0.15732353 | J34: 0.17788418 | K34: n.a. | L34: 0.13245829 | M34: 0.11016069 | N34: n.a. | O34: =IFERROR(AVERAGE(G34:N34),"n.a.") -> 0.14445667 | R34: Tanzania | S34: 2017 US$/kWh | T34: AFR | U34: Public | V34: n.a. | W34: =IFERROR(G34*'Inflation adjustment'!$AH$3/'Inflation adjustment'!AA$3,"n.a.") -> n.a. | X34: =IFERROR(H34*'Inflation adjustment'!$AH$3/'Inflation adjustment'!AB$3,"n.a.") -> n.a. | Y34: =IFERROR(I34*'Inflation adjustment'!$AH$3/'Inflation adjustment'!AC$3,"n.a.") -> 0.16796211 | Z34: =IFERROR(J34*'Inflation adjustment'!$AH$3/'Inflation adjustment'!AD$3,"n.a.") -> 0.18717136 | AA34: n.a. | AB34: 0.13714897 | AC34: 0.1139266 | AD34: =IFERROR(N34*'Inflation adjustment'!$AH$3/'Inflation adjustment'!AH$3,"n.a.") -> n.a. | AE34: =IFERROR(AVERAGE(W34:AD34),"n.a.") -> 0.15155226
B35: Uganda | C35: Current US$/kWh | D35: AFR | E35: Private | F35: n.a. | G35: n.a. | H35: n.a. | I35: 0.15078137 | J35: 0.15739303 | K35: 0.13633599 | L35: 0.12752206 | M35: 0.12655075 | N35: n.a. | O35: =IFERROR(AVERAGE(G35:N35),"n.a.") -> 0.13971664 | R35: Uganda | S35: 2017 US$/kWh | T35: AFR | U35: Private | V35: n.a. | W35: =IFERROR(G35*'Inflation adjustment'!$AH$3/'Inflation adjustment'!AA$3,"n.a.") -> n.a. | X35: =IFERROR(H35*'Inflation adjustment'!$AH$3/'Inflation adjustment'!AB$3,"n.a.") -> n.a. | Y35: =IFERROR(I35*'Inflation adjustment'!$AH$3/'Inflation adjustment'!AC$3,"n.a.") -> 0.16097755 | Z35: =IFERROR(J35*'Inflation adjustment'!$AH$3/'Inflation adjustment'!AD$3,"n.a.") -> 0.16561039 | AA35: =IFERROR(K35*'Inflation adjustment'!$AH$3/'Inflation adjustment'!AE$3,"n.a.") -> 0.14116399 | AB35: =IFERROR(L35*'Inflation adjustment'!$AH$3/'Inflation adjustment'!AF$3,"n.a.") -> 0.13188149 | AC35: =IFERROR(M35*'Inflation adjustment'!$AH$3/'Inflation adjustment'!AG$3,"n.a.") -> 0.12924642 | AD35: =IFERROR(N35*'Inflation adjustment'!$AH$3/'Inflation adjustment'!AH$3,"n.a.") -> n.a. | AE35: =IFERROR(AVERAGE(W35:AD35),"n.a.") -> 0.14577597
B36: Ukraine | C36: Current US$/kWh | D36: ECA | E36: Mixed | F36: n.a. | G36: n.a. | H36: n.a. | I36: 0.074910882 | J36: 0.071820956 | K36: 0.054196673 | L36: 0.041245583 | M36: 0.044926821 | N36: 0.052790258 | O36: =IFERROR(AVERAGE(G36:N36),"n.a.") -> 0.056648529 | R36: Ukraine | S36: 2017 US$/kWh | T36: ECA | U36: Mixed | V36: n.a. | W36: =IFERROR(G36*'Inflation adjustment'!$AH$3/'Inflation adjustment'!AA$3,"n.a.") -> n.a. | X36: =IFERROR(H36*'Inflation adjustment'!$AH$3/'Inflation adjustment'!AB$3,"n.a.") -> n.a. | Y36: =IFERROR(I36*'Inflation adjustment'!$AH$3/'Inflation adjustment'!AC$3,"n.a.") -> 0.079976528 | Z36: =IFERROR(J36*'Inflation adjustment'!$AH$3/'Inflation adjustment'!AD$3,"n.a.") -> 0.07557067 | AA36: =IFERROR(K36*'Inflation adjustment'!$AH$3/'Inflation adjustment'!AE$3,"n.a.") -> 0.056115912 | AB36: =IFERROR(L36*'Inflation adjustment'!$AH$3/'Inflation adjustment'!AF$3,"n.a.") -> 0.042655591 | AC36: =IFERROR(M36*'Inflation adjustment'!$AH$3/'Inflation adjustment'!AG$3,"n.a.") -> 0.045883812 | AD36: =IFERROR(N36*'Inflation adjustment'!$AH$3/'Inflation adjustment'!AH$3,"n.a.") -> 0.052790258 | AE36: =IFERROR(AVERAGE(W36:AD36),"n.a.") -> 0.058832128
B37: Vietnam | C37: Current US$/kWh | D37: EAP | E37: Public | F37: n.a. | G37: 0.052595012 | H37: 0.059588681 | I37: 0.061245138 | J37: 0.068273742 | K37: 0.069094831 | L37: 0.072231704 | M37: 0.074046728 | N37: n.a. | O37: =IFERROR(AVERAGE(G37:N37),"n.a.") -> 0.065296548 | R37: Vietnam | S37: 2017 US$/kWh | T37: EAP | U37: Public | V37: n.a. | W37: =IFERROR(G37*'Inflation adjustment'!$AH$3/'Inflation adjustment'!AA$3,"n.a.") -> 0.059122872 | X37: =IFERROR(H37*'Inflation adjustment'!$AH$3/'Inflation adjustment'!AB$3,"n.a.") -> 0.064934679 | Y37: =IFERROR(I37*'Inflation adjustment'!$AH$3/'Inflation adjustment'!AC$3,"n.a.") -> 0.065386674 | Z37: =IFERROR(J37*'Inflation adjustment'!$AH$3/'Inflation adjustment'!AD$3,"n.a.") -> 0.071838258 | AA37: =IFERROR(K37*'Inflation adjustment'!$AH$3/'Inflation adjustment'!AE$3,"n.a.") -> 0.071541651 | AB37: =IFERROR(L37*'Inflation adjustment'!$AH$3/'Inflation adjustment'!AF$3,"n.a.") -> 0.074700993 | AC37: =IFERROR(M37*'Inflation adjustment'!$AH$3/'Inflation adjustment'!AG$3,"n.a.") -> 0.075624005 | AD37: =IFERROR(N37*'Inflation adjustment'!$AH$3/'Inflation adjustment'!AH$3,"n.a.") -> n.a. | AE37: =IFERROR(AVERAGE(W37:AD37),"n.a.") -> 0.069021305
B38: A3 | R38: A3
B39: Colombia | C39: Current US$/kWh | D39: LAC | E39: Private | F39: n.a. | G39: 0.13065574 | H39: 0.11927694 | I39: 0.11509969 | J39: 0.12541565 | K39: 0.12538156 | L39: 0.091998354 | M39: 0.099312921 | N39: n.a. | O39: =IFERROR(AVERAGE(G39:N39),"n.a.") -> 0.11530584 | R39: Colombia | S39: 2017 US$/kWh | T39: LAC | U39: Private | V39: n.a. | W39: =IFERROR(G39*'Inflation adjustment'!$AH$3/'Inflation adjustment'!AA$3,"n.a.") -> 0.14687215 | X39: =IFERROR(H39*'Inflation adjustment'!$AH$3/'Inflation adjustment'!AB$3,"n.a.") -> 0.12997787 | Y39: =IFERROR(I39*'Inflation adjustment'!$AH$3/'Inflation adjustment'!AC$3,"n.a.") -> 0.122883 | Z39: =IFERROR(J39*'Inflation adjustment'!$AH$3/'Inflation adjustment'!AD$3,"n.a.") -> 0.1319635 | AA39: =IFERROR(K39*'Inflation adjustment'!$AH$3/'Inflation adjustment'!AE$3,"n.a.") -> 0.12982163 | AB39: =IFERROR(L39*'Inflation adjustment'!$AH$3/'Inflation adjustment'!AF$3,"n.a.") -> 0.095143378 | AC39: =IFERROR(M39*'Inflation adjustment'!$AH$3/'Inflation adjustment'!AG$3,"n.a.") -> 0.1014284 | AD39: =IFERROR(N39*'Inflation adjustment'!$AH$3/'Inflation adjustment'!AH$3,"n.a.") -> n.a. | AE39: =IFERROR(AVERAGE(W39:AD39),"n.a.") -> 0.12258427
B40: Dominican Republic | C40: Current US$/kWh | D40: LAC | E40: Public | F40: n.a. | G40: =G96 -> 0.2239417 | H40: =H96 -> 0.28601733 | I40: =I96 -> 0.32335889 | J40: =J96 -> 0.32376005 | K40: =K96 -> 0.31822914 | L40: =L96 -> 0.23992642 | M40: n.a. | N40: n.a. | O40: =IFERROR(AVERAGE(G40:N40),"n.a.") -> 0.28587225 | R40: Dominican Republic | S40: 2017 US$/kWh | T40: LAC | U40: Public | V40: n.a. | W40: =IFERROR(G40*'Inflation adjustment'!$AH$3/'Inflation adjustment'!AA$3,"n.a.") -> 0.25173635 | X40: =IFERROR(H40*'Inflation adjustment'!$AH$3/'Inflation adjustment'!AB$3,"n.a.") -> 0.31167737 | Y40: =IFERROR(I40*'Inflation adjustment'!$AH$3/'Inflation adjustment'!AC$3,"n.a.") -> 0.34522516 | Z40: =IFERROR(J40*'Inflation adjustment'!$AH$3/'Inflation adjustment'!AD$3,"n.a.") -> 0.3406633 | AA40: =IFERROR(K40*'Inflation adjustment'!$AH$3/'Inflation adjustment'!AE$3,"n.a.") -> 0.32949842 | AB40: =IFERROR(L40*'Inflation adjustment'!$AH$3/'Inflation adjustment'!AF$3,"n.a.") -> 0.24812846 | AC40: =IFERROR(M40*'Inflation adjustment'!$AH$3/'Inflation adjustment'!AG$3,"n.a.") -> n.a. | AD40: =IFERROR(N40*'Inflation adjustment'!$AH$3/'Inflation adjustment'!AH$3,"n.a.") -> n.a. | AE40: =IFERROR(AVERAGE(W40:AD40),"n.a.") -> 0.30448818
B41: Egypt, Arab Rep. | C41: Current US$/kWh | D41: MNA | E41: Public | F41: n.a. | G41: n.a. | H41: 0.062703306 | I41: 0.062484414 | J41: 0.055007625 | K41: 0.052536215 | L41: 0.072198664 | M41: 0.073912855 | N41: n.a. | O41: =IFERROR(AVERAGE(G41:N41),"n.a.") -> 0.063140513 | R41: Egypt, Arab Rep. | S41: 2017 US$/kWh | T41: MNA | U41: Public | V41: n.a. | W41: =IFERROR(G41*'Inflation adjustment'!$AH$3/'Inflation adjustment'!AA$3,"n.a.") -> n.a. | X41: =IFERROR(H41*'Inflation adjustment'!$AH$3/'Inflation adjustment'!AB$3,"n.a.") -> 0.068328733 | Y41: =IFERROR(I41*'Inflation adjustment'!$AH$3/'Inflation adjustment'!AC$3,"n.a.") -> 0.066709753 | Z41: =IFERROR(J41*'Inflation adjustment'!$AH$3/'Inflation adjustment'!AD$3,"n.a.") -> 0.057879528 | AA41: =IFERROR(K41*'Inflation adjustment'!$AH$3/'Inflation adjustment'!AE$3,"n.a.") -> 0.054396653 | AB41: =IFERROR(L41*'Inflation adjustment'!$AH$3/'Inflation adjustment'!AF$3,"n.a.") -> 0.074666824 | AC41: =IFERROR(M41*'Inflation adjustment'!$AH$3/'Inflation adjustment'!AG$3,"n.a.") -> 0.07548728 | AD41: =IFERROR(N41*'Inflation adjustment'!$AH$3/'Inflation adjustment'!AH$3,"n.a.") -> n.a. | AE41: =IFERROR(AVERAGE(W41:AD41),"n.a.") -> 0.066244795
B42: India - Andhra Pradesh | C42: Current US$/kWh | D42: SAR | E42: Public | F42: n.a. | G42: n.a. | H42: 0.18664102 | I42: 0.16393905 | J42: 0.18494993 | K42: 0.18559603 | L42: 0.15337434 | M42: n.a. | N42: n.a. | O42: =IFERROR(AVERAGE(G42:N42),"n.a.") -> 0.17490008 | R42: India - Andhra Pradesh | S42: 2017 US$/kWh | T42: SAR | U42: Public | V42: n.a. | W42: =IFERROR(G42*'Inflation adjustment'!$AH$3/'Inflation adjustment'!AA$3,"n.a.") -> n.a. | X42: =IFERROR(H42*'Inflation adjustment'!$AH$3/'Inflation adjustment'!AB$3,"n.a.") -> 0.20338552 | Y42: =IFERROR(I42*'Inflation adjustment'!$AH$3/'Inflation adjustment'!AC$3,"n.a.") -> 0.17502499 | Z42: =IFERROR(J42*'Inflation adjustment'!$AH$3/'Inflation adjustment'!AD$3,"n.a.") -> 0.19460602 | AA42: =IFERROR(K42*'Inflation adjustment'!$AH$3/'Inflation adjustment'!AE$3,"n.a.") -> 0.19216845 | AB42: =IFERROR(L42*'Inflation adjustment'!$AH$3/'Inflation adjustment'!AF$3,"n.a.") -> 0.15861755 | AC42: =IFERROR(M42*'Inflation adjustment'!$AH$3/'Inflation adjustment'!AG$3,"n.a.") -> n.a. | AD42: =IFERROR(N42*'Inflation adjustment'!$AH$3/'Inflation adjustment'!AH$3,"n.a.") -> n.a. | AE42: =IFERROR(AVERAGE(W42:AD42),"n.a.") -> 0.18476051
B43: India - Odisha | C43: Current US$/kWh | D43: SAR | E43: Public | F43: n.a. | G43: n.a. | H43: 0.094407637 | I43: 0.10169872 | J43: 0.096905897 | K43: 0.10058215 | L43: 0.096184332 | M43: n.a. | N43: n.a. | O43: =IFERROR(AVERAGE(G43:N43),"n.a.") -> 0.097955747 | R43: India - Odisha | S43: 2017 US$/kWh | T43: SAR | U43: Public | V43: n.a. | W43: =IFERROR(G43*'Inflation adjustment'!$AH$3/'Inflation adjustment'!AA$3,"n.a.") -> n.a. | X43: =IFERROR(H43*'Inflation adjustment'!$AH$3/'Inflation adjustment'!AB$3,"n.a.") -> 0.10287742 | Y43: =IFERROR(I43*'Inflation adjustment'!$AH$3/'Inflation adjustment'!AC$3,"n.a.") -> 0.10857582 | Z43: =IFERROR(J43*'Inflation adjustment'!$AH$3/'Inflation adjustment'!AD$3,"n.a.") -> 0.10196528 | AA43: =IFERROR(K43*'Inflation adjustment'!$AH$3/'Inflation adjustment'!AE$3,"n.a.") -> 0.10414401 | AB43: =IFERROR(L43*'Inflation adjustment'!$AH$3/'Inflation adjustment'!AF$3,"n.a.") -> 0.099472457 | AC43: =IFERROR(M43*'Inflation adjustment'!$AH$3/'Inflation adjustment'!AG$3,"n.a.") -> n.a. | AD43: =IFERROR(N43*'Inflation adjustment'!$AH$3/'Inflation adjustment'!AH$3,"n.a.") -> n.a. | AE43: =IFERROR(AVERAGE(W43:AD43),"n.a.") -> 0.103407
B44: India - Rajasthan | C44: Current US$/kWh | D44: SAR | E44: Public | F44: n.a. | G44: n.a. | H44: 0.1632833 | I44: 0.13935148 | J44: 0.13171135 | K44: 0.18291316 | L44: 0.12752373 | M44: n.a. | N44: n.a. | O44: =IFERROR(AVERAGE(G44:N44),"n.a.") -> 0.1489566 | R44: India - Rajasthan | S44: 2017 US$/kWh | T44: SAR | U44: Public | V44: n.a. | W44: =IFERROR(G44*'Inflation adjustment'!$AH$3/'Inflation adjustment'!AA$3,"n.a.") -> n.a. | X44: =IFERROR(H44*'Inflation adjustment'!$AH$3/'Inflation adjustment'!AB$3,"n.a.") -> 0.17793226 | Y44: =IFERROR(I44*'Inflation adjustment'!$AH$3/'Inflation adjustment'!AC$3,"n.a.") -> 0.14877475 | Z44: =IFERROR(J44*'Inflation adjustment'!$AH$3/'Inflation adjustment'!AD$3,"n.a.") -> 0.13858789 | AA44: =IFERROR(K44*'Inflation adjustment'!$AH$3/'Inflation adjustment'!AE$3,"n.a.") -> 0.18939057 | AB44: =IFERROR(L44*'Inflation adjustment'!$AH$3/'Inflation adjustment'!AF$3,"n.a.") -> 0.13188321 | AC44: =IFERROR(M44*'Inflation adjustment'!$AH$3/'Inflation adjustment'!AG$3,"n.a.") -> n.a. | AD44: =IFERROR(N44*'Inflation adjustment'!$AH$3/'Inflation adjustment'!AH$3,"n.a.") -> n.a. | AE44: =IFERROR(AVERAGE(W44:AD44),"n.a.") -> 0.15731373
B45: Kenya | C45: Current US$/kWh | D45: AFR | E45: Public | F45: n.a. | G45: 0.18056909 | H45: 0.1402869 | I45: 0.19933475 | J45: 0.18997831 | K45: 0.19662334 | L45: 0.18432405 | M45: 0.17631171 | N45: n.a. | O45: =IFERROR(AVERAGE(G45:N45),"n.a.") -> 0.18106116 | R45: Kenya | S45: 2017 US$/kWh | T45: AFR | U45: Public | V45: n.a. | W45: =IFERROR(G45*'Inflation adjustment'!$AH$3/'Inflation adjustment'!AA$3,"n.a.") -> 0.20298053 | X45: =IFERROR(H45*'Inflation adjustment'!$AH$3/'Inflation adjustment'!AB$3,"n.a.") -> 0.15287274 | Y45: =IFERROR(I45*'Inflation adjustment'!$AH$3/'Inflation adjustment'!AC$3,"n.a.") -> 0.21281422 | Z45: =IFERROR(J45*'Inflation adjustment'!$AH$3/'Inflation adjustment'!AD$3,"n.a.") -> 0.19989693 | AA45: =IFERROR(K45*'Inflation adjustment'!$AH$3/'Inflation adjustment'!AE$3,"n.a.") -> 0.20358626 | AB45: =IFERROR(L45*'Inflation adjustment'!$AH$3/'Inflation adjustment'!AF$3,"n.a.") -> 0.19062529 | AC45: =IFERROR(M45*'Inflation adjustment'!$AH$3/'Inflation adjustment'!AG$3,"n.a.") -> 0.18006734 | AD45: =IFERROR(N45*'Inflation adjustment'!$AH$3/'Inflation adjustment'!AH$3,"n.a.") -> n.a. | AE45: =IFERROR(AVERAGE(W45:AD45),"n.a.") -> 0.19183476
B46: Morocco | C46: Current US$/kWh | D46: MNA | E46: Public | F46: n.a. | G46: n.a. | H46: n.a. | I46: n.a. | J46: n.a. | K46: n.a. | L46: n.a. | M46: n.a. | N46: n.a. | O46: =IFERROR(AVERAGE(G46:N46),"n.a.") -> n.a. | R46: Morocco | S46: 2017 US$/kWh | T46: MNA | U46: Public | V46: n.a. | W46: =IFERROR(G46*'Inflation adjustment'!$AH$3/'Inflation adjustment'!AA$3,"n.a.") -> n.a. | X46: =IFERROR(H46*'Inflation adjustment'!$AH$3/'Inflation adjustment'!AB$3,"n.a.") -> n.a. | Y46: =IFERROR(I46*'Inflation adjustment'!$AH$3/'Inflation adjustment'!AC$3,"n.a.") -> n.a. | Z46: =IFERROR(J46*'Inflation adjustment'!$AH$3/'Inflation adjustment'!AD$3,"n.a.") -> n.a. | AA46: =IFERROR(K46*'Inflation adjustment'!$AH$3/'Inflation adjustment'!AE$3,"n.a.") -> n.a. | AB46: =IFERROR(L46*'Inflation adjustment'!$AH$3/'Inflation adjustment'!AF$3,"n.a.") -> n.a. | AC46: =IFERROR(M46*'Inflation adjustment'!$AH$3/'Inflation adjustment'!AG$3,"n.a.") -> n.a. | AD46: =IFERROR(N46*'Inflation adjustment'!$AH$3/'Inflation adjustment'!AH$3,"n.a.") -> n.a. | AE46: =IFERROR(AVERAGE(W46:AD46),"n.a.") -> n.a.
B47: Pakistan | C47: Current US$/kWh | D47: SAR | E47: Mixed | F47: n.a. | G47: n.a. | H47: n.a. | I47: n.a. | J47: 0.12236849 | K47: 0.11468043 | L47: 0.10946408 | M47: 0.09717173 | N47: n.a. | O47: =IFERROR(AVERAGE(G47:N47),"n.a.") -> 0.11092118 | R47: Pakistan | S47: 2017 US$/kWh | T47: SAR | U47: Mixed | V47: n.a. | W47: =IFERROR(G47*'Inflation adjustment'!$AH$3/'Inflation adjustment'!AA$3,"n.a.") -> n.a. | X47: =IFERROR(H47*'Inflation adjustment'!$AH$3/'Inflation adjustment'!AB$3,"n.a.") -> n.a. | Y47: =IFERROR(I47*'Inflation adjustment'!$AH$3/'Inflation adjustment'!AC$3,"n.a.") -> n.a. | Z47: =IFERROR(J47*'Inflation adjustment'!$AH$3/'Inflation adjustment'!AD$3,"n.a.") -> 0.12875725 | AA47: =IFERROR(K47*'Inflation adjustment'!$AH$3/'Inflation adjustment'!AE$3,"n.a.") -> 0.11874154 | AB47: =IFERROR(L47*'Inflation adjustment'!$AH$3/'Inflation adjustment'!AF$3,"n.a.") -> 0.11320618 | AC47: =IFERROR(M47*'Inflation adjustment'!$AH$3/'Inflation adjustment'!AG$3,"n.a.") -> 0.099241595 | AD47: =IFERROR(N47*'Inflation adjustment'!$AH$3/'Inflation adjustment'!AH$3,"n.a.") -> n.a. | AE47: =IFERROR(AVERAGE(W47:AD47),"n.a.") -> 0.11498664
B48: Peru | C48: Current US$/kWh | D48: LAC | E48: Mixed | F48: n.a. | G48: 0.10412346 | H48: 0.10664525 | I48: 0.12019166 | J48: 0.12458377 | K48: 0.13635765 | L48: 0.13321961 | M48: 0.14696173 | N48: n.a. | O48: =IFERROR(AVERAGE(G48:N48),"n.a.") -> 0.1245833 | R48: Peru | S48: 2017 US$/kWh | T48: LAC | U48: Mixed | V48: n.a. | W48: =IFERROR(G48*'Inflation adjustment'!$AH$3/'Inflation adjustment'!AA$3,"n.a.") -> 0.1170468 | X48: =IFERROR(H48*'Inflation adjustment'!$AH$3/'Inflation adjustment'!AB$3,"n.a.") -> 0.11621293 | Y48: =IFERROR(I48*'Inflation adjustment'!$AH$3/'Inflation adjustment'!AC$3,"n.a.") -> 0.12831929 | Z48: =IFERROR(J48*'Inflation adjustment'!$AH$3/'Inflation adjustment'!AD$3,"n.a.") -> 0.13108819 | AA48: =IFERROR(K48*'Inflation adjustment'!$AH$3/'Inflation adjustment'!AE$3,"n.a.") -> 0.14118641 | AB48: =IFERROR(L48*'Inflation adjustment'!$AH$3/'Inflation adjustment'!AF$3,"n.a.") -> 0.13777381 | AC48: =IFERROR(M48*'Inflation adjustment'!$AH$3/'Inflation adjustment'!AG$3,"n.a.") -> 0.15009218 | AD48: =IFERROR(N48*'Inflation adjustment'!$AH$3/'Inflation adjustment'!AH$3,"n.a.") -> n.a. | AE48: =IFERROR(AVERAGE(W48:AD48),"n.a.") -> 0.13167423
B49: Philippines | C49: Current US$/kWh | D49: EAP | E49: Private | F49: n.a. | G49: 0.18176379 | H49: 0.19668707 | I49: 0.20791467 | J49: 0.21659064 | K49: 0.17690821 | L49: 0.15648902 | M49: 0.14157083 | N49: n.a. | O49: =IFERROR(AVERAGE(G49:N49),"n.a.") -> 0.18256061 | R49: Philippines | S49: 2017 US$/kWh | T49: EAP | U49: Private | V49: n.a. | W49: =IFERROR(G49*'Inflation adjustment'!$AH$3/'Inflation adjustment'!AA$3,"n.a.") -> 0.20432351 | X49: =IFERROR(H49*'Inflation adjustment'!$AH$3/'Inflation adjustment'!AB$3,"n.a.") -> 0.21433285 | Y49: =IFERROR(I49*'Inflation adjustment'!$AH$3/'Inflation adjustment'!AC$3,"n.a.") -> 0.22197434 | Z49: =IFERROR(J49*'Inflation adjustment'!$AH$3/'Inflation adjustment'!AD$3,"n.a.") -> 0.22789866 | AA49: =IFERROR(K49*'Inflation adjustment'!$AH$3/'Inflation adjustment'!AE$3,"n.a.") -> 0.18317297 | AB49: =IFERROR(L49*'Inflation adjustment'!$AH$3/'Inflation adjustment'!AF$3,"n.a.") -> 0.1618387 | AC49: =IFERROR(M49*'Inflation adjustment'!$AH$3/'Inflation adjustment'!AG$3,"n.a.") -> 0.14458644 | AD49: =IFERROR(N49*'Inflation adjustment'!$AH$3/'Inflation adjustment'!AH$3,"n.a.") -> n.a. | AE49: =IFERROR(AVERAGE(W49:AD49),"n.a.") -> 0.19401821
B50: Senegal | C50: Current US$/kWh | D50: AFR | E50: Public | F50: n.a. | G50: 0.29280915 | H50: 0.26949235 | I50: 0.31850386 | J50: 0.28411403 | K50: 0.27465797 | L50: 0.20349498 | M50: 0.22008649 | N50: n.a. | O50: =IFERROR(AVERAGE(G50:N50),"n.a.") -> 0.26616555 | R50: Senegal | S50: 2017 US$/kWh | T50: AFR | U50: Public | V50: n.a. | W50: =IFERROR(G50*'Inflation adjustment'!$AH$3/'Inflation adjustment'!AA$3,"n.a.") -> 0.32915132 | X50: =IFERROR(H50*'Inflation adjustment'!$AH$3/'Inflation adjustment'!AB$3,"n.a.") -> 0.29366985 | Y50: =IFERROR(I50*'Inflation adjustment'!$AH$3/'Inflation adjustment'!AC$3,"n.a.") -> 0.34004183 | Z50: =IFERROR(J50*'Inflation adjustment'!$AH$3/'Inflation adjustment'!AD$3,"n.a.") -> 0.29894739 | AA50: =IFERROR(K50*'Inflation adjustment'!$AH$3/'Inflation adjustment'!AE$3,"n.a.") -> 0.28438429 | AB50: =IFERROR(L50*'Inflation adjustment'!$AH$3/'Inflation adjustment'!AF$3,"n.a.") -> 0.21045159 | AC50: =IFERROR(M50*'Inflation adjustment'!$AH$3/'Inflation adjustment'!AG$3,"n.a.") -> 0.22477457 | AD50: =IFERROR(N50*'Inflation adjustment'!$AH$3/'Inflation adjustment'!AH$3,"n.a.") -> n.a. | AE50: =IFERROR(AVERAGE(W50:AD50),"n.a.") -> 0.28306012
B51: Tajikistan | C51: Current US$/kWh | D51: ECA | E51: Public | F51: n.a. | G51: n.a. | H51: n.a. | I51: n.a. | J51: 0.016853355 | K51: 0.018369981 | L51: 0.01413598 | M51: 0.016408013 | N51: n.a. | O51: =IFERROR(AVERAGE(G51:N51),"n.a.") -> 0.016441832 | R51: Tajikistan | S51: 2017 US$/kWh | T51: ECA | U51: Public | V51: n.a. | W51: =IFERROR(G51*'Inflation adjustment'!$AH$3/'Inflation adjustment'!AA$3,"n.a.") -> n.a. | X51: =IFERROR(H51*'Inflation adjustment'!$AH$3/'Inflation adjustment'!AB$3,"n.a.") -> n.a. | Y51: =IFERROR(I51*'Inflation adjustment'!$AH$3/'Inflation adjustment'!AC$3,"n.a.") -> n.a. | Z51: =IFERROR(J51*'Inflation adjustment'!$AH$3/'Inflation adjustment'!AD$3,"n.a.") -> 0.017733255 | AA51: =IFERROR(K51*'Inflation adjustment'!$AH$3/'Inflation adjustment'!AE$3,"n.a.") -> 0.019020507 | AB51: =IFERROR(L51*'Inflation adjustment'!$AH$3/'Inflation adjustment'!AF$3,"n.a.") -> 0.014619227 | AC51: =IFERROR(M51*'Inflation adjustment'!$AH$3/'Inflation adjustment'!AG$3,"n.a.") -> 0.016757522 | AD51: =IFERROR(N51*'Inflation adjustment'!$AH$3/'Inflation adjustment'!AH$3,"n.a.") -> n.a. | AE51: =IFERROR(AVERAGE(W51:AD51),"n.a.") -> 0.017032628
B52: Tanzania | C52: Current US$/kWh | D52: AFR | E52: Public | F52: n.a. | G52: n.a. | H52: n.a. | I52: 0.16011714 | J52: 0.18173852 | K52: n.a. | L52: 0.13572511 | M52: 0.11805685 | N52: n.a. | O52: =IFERROR(AVERAGE(G52:N52),"n.a.") -> 0.1489094 | R52: Tanzania | S52: 2017 US$/kWh | T52: AFR | U52: Public | V52: n.a. | W52: =IFERROR(G52*'Inflation adjustment'!$AH$3/'Inflation adjustment'!AA$3,"n.a.") -> n.a. | X52: =IFERROR(H52*'Inflation adjustment'!$AH$3/'Inflation adjustment'!AB$3,"n.a.") -> n.a. | Y52: =IFERROR(I52*'Inflation adjustment'!$AH$3/'Inflation adjustment'!AC$3,"n.a.") -> 0.17094462 | Z52: =IFERROR(J52*'Inflation adjustment'!$AH$3/'Inflation adjustment'!AD$3,"n.a.") -> 0.19122694 | AA52: n.a. | AB52: 0.14053147 | AC52: 0.1220927 | AD52: =IFERROR(N52*'Inflation adjustment'!$AH$3/'Inflation adjustment'!AH$3,"n.a.") -> n.a. | AE52: =IFERROR(AVERAGE(W52:AD52),"n.a.") -> 0.15619893
B53: Uganda | C53: Current US$/kWh | D53: AFR | E53: Private | F53: n.a. | G53: n.a. | H53: n.a. | I53: 0.1558214 | J53: 0.17036305 | K53: 0.16492197 | L53: 0.15580931 | M53: 0.1704736 | N53: n.a. | O53: =IFERROR(AVERAGE(G53:N53),"n.a.") -> 0.16347786 | R53: Uganda | S53: 2017 US$/kWh | T53: AFR | U53: Private | V53: n.a. | W53: =IFERROR(G53*'Inflation adjustment'!$AH$3/'Inflation adjustment'!AA$3,"n.a.") -> n.a. | X53: =IFERROR(H53*'Inflation adjustment'!$AH$3/'Inflation adjustment'!AB$3,"n.a.") -> n.a. | Y53: =IFERROR(I53*'Inflation adjustment'!$AH$3/'Inflation adjustment'!AC$3,"n.a.") -> 0.1663584 | Z53: =IFERROR(J53*'Inflation adjustment'!$AH$3/'Inflation adjustment'!AD$3,"n.a.") -> 0.17925756 | AA53: =IFERROR(K53*'Inflation adjustment'!$AH$3/'Inflation adjustment'!AE$3,"n.a.") -> 0.17076227 | AB53: =IFERROR(L53*'Inflation adjustment'!$AH$3/'Inflation adjustment'!AF$3,"n.a.") -> 0.16113575 | AC53: =IFERROR(M53*'Inflation adjustment'!$AH$3/'Inflation adjustment'!AG$3,"n.a.") -> 0.17410487 | AD53: =IFERROR(N53*'Inflation adjustment'!$AH$3/'Inflation adjustment'!AH$3,"n.a.") -> n.a. | AE53: =IFERROR(AVERAGE(W53:AD53),"n.a.") -> 0.17032377
B54: Ukraine | C54: Current US$/kWh | D54: ECA | E54: Mixed | F54: n.a. | G54: n.a. | H54: n.a. | I54: 0.074910882 | J54: 0.072662293 | K54: 0.055604645 | L54: 0.042494588 | M54: 0.046352358 | N54: 0.054030908 | O54: =IFERROR(AVERAGE(G54:N54),"n.a.") -> 0.057675946 | R54: Ukraine | S54: 2017 US$/kWh | T54: ECA | U54: Mixed | V54: n.a. | W54: =IFERROR(G54*'Inflation adjustment'!$AH$3/'Inflation adjustment'!AA$3,"n.a.") -> n.a. | X54: =IFERROR(H54*'Inflation adjustment'!$AH$3/'Inflation adjustment'!AB$3,"n.a.") -> n.a. | Y54: =IFERROR(I54*'Inflation adjustment'!$AH$3/'Inflation adjustment'!AC$3,"n.a.") -> 0.079976528 | Z54: =IFERROR(J54*'Inflation adjustment'!$AH$3/'Inflation adjustment'!AD$3,"n.a.") -> 0.076455932 | AA54: =IFERROR(K54*'Inflation adjustment'!$AH$3/'Inflation adjustment'!AE$3,"n.a.") -> 0.057573744 | AB54: =IFERROR(L54*'Inflation adjustment'!$AH$3/'Inflation adjustment'!AF$3,"n.a.") -> 0.043947294 | AC54: =IFERROR(M54*'Inflation adjustment'!$AH$3/'Inflation adjustment'!AG$3,"n.a.") -> 0.047339714 | AD54: =IFERROR(N54*'Inflation adjustment'!$AH$3/'Inflation adjustment'!AH$3,"n.a.") -> 0.054030908 | AE54: =IFERROR(AVERAGE(W54:AD54),"n.a.") -> 0.059887353
B55: Vietnam | C55: Current US$/kWh | D55: EAP | E55: Public | F55: n.a. | G55: 0.05473167 | H55: 0.062531804 | I55: 0.065513357 | J55: 0.074148942 | K55: 0.075317814 | L55: 0.07901672 | M55: 0.081789517 | N55: n.a. | O55: =IFERROR(AVERAGE(G55:N55),"n.a.") -> 0.070435689 | R55: Vietnam | S55: 2017 US$/kWh | T55: EAP | U55: Public | V55: n.a. | W55: =IFERROR(G55*'Inflation adjustment'!$AH$3/'Inflation adjustment'!AA$3,"n.a.") -> 0.061524723 | X55: =IFERROR(H55*'Inflation adjustment'!$AH$3/'Inflation adjustment'!AB$3,"n.a.") -> 0.068141845 | Y55: =IFERROR(I55*'Inflation adjustment'!$AH$3/'Inflation adjustment'!AC$3,"n.a.") -> 0.069943521 | Z55: =IFERROR(J55*'Inflation adjustment'!$AH$3/'Inflation adjustment'!AD$3,"n.a.") -> 0.078020198 | AA55: =IFERROR(K55*'Inflation adjustment'!$AH$3/'Inflation adjustment'!AE$3,"n.a.") -> 0.077985005 | AB55: =IFERROR(L55*'Inflation adjustment'!$AH$3/'Inflation adjustment'!AF$3,"n.a.") -> 0.081717959 | AC55: =IFERROR(M55*'Inflation adjustment'!$AH$3/'Inflation adjustment'!AG$3,"n.a.") -> 0.083531723 | AD55: =IFERROR(N55*'Inflation adjustment'!$AH$3/'Inflation adjustment'!AH$3,"n.a.") -> n.a. | AE55: =IFERROR(AVERAGE(W55:AD55),"n.a.") -> 0.074409282
B57: Economic cost per unit - Country level | C57: Unit | D57: Region | F57: Pre-reform | G57: 2010 | H57: 2011 | I57: 2012 | J57: 2013 | K57: 2014 | L57: 2015 | M57: 2016 | N57: 2017 | O57: Average | R57: Economic cost per unit | S57: Unit | T57: Region | V57: 1987 | W57: 2010 | X57: 2011 | Y57: 2012 | Z57: 2013 | AA57: 2014 | AB57: 2015 | AC57: 2016 | AD57: 2017 | AE57: Average | AH57: Source
B58: C1 | R58: C1
B59: Colombia | C59: Current US$/kWh | D59: LAC | E59: Private | F59: n.a. | G59: 0.079219181 | H59: 0.087507206 | I59: 0.087998657 | J59: 0.084381364 | K59: 0.082776668 | L59: 0.064528803 | M59: 0.06751134 | N59: n.a. | O59: =IFERROR(AVERAGE(G59:N59),"n.a.") -> 0.079131888 | R59: Colombia | S59: 2017 US$/kWh | T59: LAC | U59: Private | V59: n.a. | W59: =IFERROR(G59*'Inflation adjustment'!$AH$3/'Inflation adjustment'!AA$3,"n.a.") -> 0.089051515 | X59: =IFERROR(H59*'Inflation adjustment'!$AH$3/'Inflation adjustment'!AB$3,"n.a.") -> 0.095357915 | Y59: =IFERROR(I59*'Inflation adjustment'!$AH$3/'Inflation adjustment'!AC$3,"n.a.") -> 0.093949327 | Z59: =IFERROR(J59*'Inflation adjustment'!$AH$3/'Inflation adjustment'!AD$3,"n.a.") -> 0.088786847 | AA59: =IFERROR(K59*'Inflation adjustment'!$AH$3/'Inflation adjustment'!AE$3,"n.a.") -> 0.085707995 | AB59: =IFERROR(L59*'Inflation adjustment'!$AH$3/'Inflation adjustment'!AF$3,"n.a.") -> 0.066734763 | AC59: =IFERROR(M59*'Inflation adjustment'!$AH$3/'Inflation adjustment'!AG$3,"n.a.") -> 0.068949406 | AD59: =IFERROR(N59*'Inflation adjustment'!$AH$3/'Inflation adjustment'!AH$3,"n.a.") -> n.a. | AE59: =IFERROR(AVERAGE(W59:AD59),"n.a.") -> 0.084076824 | AH59: Country models
B60: Dominican Republic | C60: Current US$/kWh | D60: LAC | E60: Public | F60: n.a. | G60: 0.22355185 | H60: 0.28297225 | I60: 0.31661839 | J60: 0.31498269 | K60: 0.31133266 | L60: 0.22560835 | M60: n.a. | N60: n.a. | O60: =IFERROR(AVERAGE(G60:N60),"n.a.") -> 0.2791777 | R60: Dominican Republic | S60: 2017 US$/kWh | T60: LAC | U60: Public | V60: n.a. | W60: =IFERROR(G60*'Inflation adjustment'!$AH$3/'Inflation adjustment'!AA$3,"n.a.") -> 0.25129812 | X60: =IFERROR(H60*'Inflation adjustment'!$AH$3/'Inflation adjustment'!AB$3,"n.a.") -> 0.3083591 | Y60: =IFERROR(I60*'Inflation adjustment'!$AH$3/'Inflation adjustment'!AC$3,"n.a.") -> 0.33802885 | Z60: =IFERROR(J60*'Inflation adjustment'!$AH$3/'Inflation adjustment'!AD$3,"n.a.") -> 0.33142768 | AA60: =IFERROR(K60*'Inflation adjustment'!$AH$3/'Inflation adjustment'!AE$3,"n.a.") -> 0.32235772 | AB60: =IFERROR(L60*'Inflation adjustment'!$AH$3/'Inflation adjustment'!AF$3,"n.a.") -> 0.23332092 | AC60: =IFERROR(M60*'Inflation adjustment'!$AH$3/'Inflation adjustment'!AG$3,"n.a.") -> n.a. | AD60: =IFERROR(N60*'Inflation adjustment'!$AH$3/'Inflation adjustment'!AH$3,"n.a.") -> n.a. | AE60: =IFERROR(AVERAGE(W60:AD60),"n.a.") -> 0.2974654
B61: Egypt, Arab Rep. | C61: Current US$/kWh | D61: MNA | E61: Public | F61: n.a. | G61: n.a. | H61: 0.026510711 | I61: 0.028679552 | J61: 0.026610193 | K61: 0.050180753 | L61: 0.05787496 | M61: 0.059626419 | N61: n.a. | O61: =IFERROR(AVERAGE(G61:N61),"n.a.") -> 0.041580431 | R61: Egypt, Arab Rep. | S61: 2017 US$/kWh | T61: MNA | U61: Public | V61: n.a. | W61: =IFERROR(G61*'Inflation adjustment'!$AH$3/'Inflation adjustment'!AA$3,"n.a.") -> n.a. | X61: =IFERROR(H61*'Inflation adjustment'!$AH$3/'Inflation adjustment'!AB$3,"n.a.") -> 0.028889119 | Y61: =IFERROR(I61*'Inflation adjustment'!$AH$3/'Inflation adjustment'!AC$3,"n.a.") -> 0.030618929 | Z61: =IFERROR(J61*'Inflation adjustment'!$AH$3/'Inflation adjustment'!AD$3,"n.a.") -> 0.02799949 | AA61: =IFERROR(K61*'Inflation adjustment'!$AH$3/'Inflation adjustment'!AE$3,"n.a.") -> 0.051957778 | AB61: =IFERROR(L61*'Inflation adjustment'!$AH$3/'Inflation adjustment'!AF$3,"n.a.") -> 0.059853454 | AC61: =IFERROR(M61*'Inflation adjustment'!$AH$3/'Inflation adjustment'!AG$3,"n.a.") -> 0.060896528 | AD61: =IFERROR(N61*'Inflation adjustment'!$AH$3/'Inflation adjustment'!AH$3,"n.a.") -> n.a. | AE61: =IFERROR(AVERAGE(W61:AD61),"n.a.") -> 0.043369216
B62: India - Andhra Pradesh | C62: Current US$/kWh | D62: SAR | E62: Public | F62: n.a. | G62: n.a. | H62: 0.10263926 | I62: 0.088736483 | J62: 0.10217002 | K62: 0.090881356 | L62: 0.096286233 | M62: n.a. | N62: n.a. | O62: =IFERROR(AVERAGE(G62:N62),"n.a.") -> 0.096142671 | R62: India - Andhra Pradesh | S62: 2017 US$/kWh | T62: SAR | U62: Public | V62: n.a. | W62: =IFERROR(G62*'Inflation adjustment'!$AH$3/'Inflation adjustment'!AA$3,"n.a.") -> n.a. | X62: =IFERROR(H62*'Inflation adjustment'!$AH$3/'Inflation adjustment'!AB$3,"n.a.") -> 0.11184754 | Y62: =IFERROR(I62*'Inflation adjustment'!$AH$3/'Inflation adjustment'!AC$3,"n.a.") -> 0.094737047 | Z62: =IFERROR(J62*'Inflation adjustment'!$AH$3/'Inflation adjustment'!AD$3,"n.a.") -> 0.10750424 | AA62: =IFERROR(K62*'Inflation adjustment'!$AH$3/'Inflation adjustment'!AE$3,"n.a.") -> 0.094099691 | AB62: =IFERROR(L62*'Inflation adjustment'!$AH$3/'Inflation adjustment'!AF$3,"n.a.") -> 0.099577842 | AC62: =IFERROR(M62*'Inflation adjustment'!$AH$3/'Inflation adjustment'!AG$3,"n.a.") -> n.a. | AD62: =IFERROR(N62*'Inflation adjustment'!$AH$3/'Inflation adjustment'!AH$3,"n.a.") -> n.a. | AE62: =IFERROR(AVERAGE(W62:AD62),"n.a.") -> 0.10155327
B63: India - Odisha | C63: Current US$/kWh | D63: SAR | E63: Public | F63: n.a. | G63: n.a. | H63: 0.086981732 | I63: 0.095092819 | J63: 0.09071712 | K63: 0.093779841 | L63: 0.088167148 | M63: n.a. | N63: n.a. | O63: =IFERROR(AVERAGE(G63:N63),"n.a.") -> 0.090947732 | R63: India - Odisha | S63: 2017 US$/kWh | T63: SAR | U63: Public | V63: n.a. | W63: =IFERROR(G63*'Inflation adjustment'!$AH$3/'Inflation adjustment'!AA$3,"n.a.") -> n.a. | X63: =IFERROR(H63*'Inflation adjustment'!$AH$3/'Inflation adjustment'!AB$3,"n.a.") -> 0.094785297 | Y63: =IFERROR(I63*'Inflation adjustment'!$AH$3/'Inflation adjustment'!AC$3,"n.a.") -> 0.10152321 | Z63: =IFERROR(J63*'Inflation adjustment'!$AH$3/'Inflation adjustment'!AD$3,"n.a.") -> 0.095453387 | AA63: =IFERROR(K63*'Inflation adjustment'!$AH$3/'Inflation adjustment'!AE$3,"n.a.") -> 0.097100818 | AB63: =IFERROR(L63*'Inflation adjustment'!$AH$3/'Inflation adjustment'!AF$3,"n.a.") -> 0.0911812 | AC63: =IFERROR(M63*'Inflation adjustment'!$AH$3/'Inflation adjustment'!AG$3,"n.a.") -> n.a. | AD63: =IFERROR(N63*'Inflation adjustment'!$AH$3/'Inflation adjustment'!AH$3,"n.a.") -> n.a. | AE63: =IFERROR(AVERAGE(W63:AD63),"n.a.") -> 0.096008783
B64: India - Rajasthan | C64: Current US$/kWh | D64: SAR | E64: Public | F64: n.a. | G64: n.a. | H64: 0.10302779 | I64: 0.093351143 | J64: 0.089185009 | K64: 0.10371691 | L64: 0.084974801 | M64: n.a. | N64: n.a. | O64: =IFERROR(AVERAGE(G64:N64),"n.a.") -> 0.094851132 | R64: India - Rajasthan | S64: 2017 US$/kWh | T64: SAR | U64: Public | V64: n.a. | W64: =IFERROR(G64*'Inflation adjustment'!$AH$3/'Inflation adjustment'!AA$3,"n.a.") -> n.a. | X64: =IFERROR(H64*'Inflation adjustment'!$AH$3/'Inflation adjustment'!AB$3,"n.a.") -> 0.11227093 | Y64: =IFERROR(I64*'Inflation adjustment'!$AH$3/'Inflation adjustment'!AC$3,"n.a.") -> 0.099663761 | Z64: =IFERROR(J64*'Inflation adjustment'!$AH$3/'Inflation adjustment'!AD$3,"n.a.") -> 0.093841286 | AA64: =IFERROR(K64*'Inflation adjustment'!$AH$3/'Inflation adjustment'!AE$3,"n.a.") -> 0.10738979 | AB64: =IFERROR(L64*'Inflation adjustment'!$AH$3/'Inflation adjustment'!AF$3,"n.a.") -> 0.087879721 | AC64: =IFERROR(M64*'Inflation adjustment'!$AH$3/'Inflation adjustment'!AG$3,"n.a.") -> n.a. | AD64: =IFERROR(N64*'Inflation adjustment'!$AH$3/'Inflation adjustment'!AH$3,"n.a.") -> n.a. | AE64: =IFERROR(AVERAGE(W64:AD64),"n.a.") -> 0.1002091
B65: Kenya | C65: Current US$/kWh | D65: AFR | E65: Public | F65: n.a. | G65: 0.16159701 | H65: 0.12128442 | I65: 0.16650468 | J65: 0.14590447 | K65: 0.14878772 | L65: 0.12721034 | M65: 0.11777459 | N65: n.a. | O65: =IFERROR(AVERAGE(G65:N65),"n.a.") -> 0.14129475 | R65: Kenya | S65: 2017 US$/kWh | T65: AFR | U65: Public | V65: n.a. | W65: =IFERROR(G65*'Inflation adjustment'!$AH$3/'Inflation adjustment'!AA$3,"n.a.") -> 0.18165371 | X65: =IFERROR(H65*'Inflation adjustment'!$AH$3/'Inflation adjustment'!AB$3,"n.a.") -> 0.13216545 | Y65: =IFERROR(I65*'Inflation adjustment'!$AH$3/'Inflation adjustment'!AC$3,"n.a.") -> 0.17776411 | Z65: =IFERROR(J65*'Inflation adjustment'!$AH$3/'Inflation adjustment'!AD$3,"n.a.") -> 0.15352202 | AA65: =IFERROR(K65*'Inflation adjustment'!$AH$3/'Inflation adjustment'!AE$3,"n.a.") -> 0.15405666 | AB65: =IFERROR(L65*'Inflation adjustment'!$AH$3/'Inflation adjustment'!AF$3,"n.a.") -> 0.13155911 | AC65: =IFERROR(M65*'Inflation adjustment'!$AH$3/'Inflation adjustment'!AG$3,"n.a.") -> 0.12028332 | AD65: =IFERROR(N65*'Inflation adjustment'!$AH$3/'Inflation adjustment'!AH$3,"n.a.") -> n.a. | AE65: =IFERROR(AVERAGE(W65:AD65),"n.a.") -> 0.15014348
B66: Morocco | C66: Current US$/kWh | D66: MNA | E66: Public | F66: n.a. | G66: n.a. | H66: n.a. | I66: n.a. | J66: n.a. | K66: n.a. | L66: n.a. | M66: n.a. | N66: n.a. | O66: =IFERROR(AVERAGE(G66:N66),"n.a.") -> n.a. | R66: Morocco | S66: 2017 US$/kWh | T66: MNA | U66: Public | V66: n.a. | W66: =IFERROR(G66*'Inflation adjustment'!$AH$3/'Inflation adjustment'!AA$3,"n.a.") -> n.a. | X66: =IFERROR(H66*'Inflation adjustment'!$AH$3/'Inflation adjustment'!AB$3,"n.a.") -> n.a. | Y66: =IFERROR(I66*'Inflation adjustment'!$AH$3/'Inflation adjustment'!AC$3,"n.a.") -> n.a. | Z66: =IFERROR(J66*'Inflation adjustment'!$AH$3/'Inflation adjustment'!AD$3,"n.a.") -> n.a. | AA66: =IFERROR(K66*'Inflation adjustment'!$AH$3/'Inflation adjustment'!AE$3,"n.a.") -> n.a. | AB66: =IFERROR(L66*'Inflation adjustment'!$AH$3/'Inflation adjustment'!AF$3,"n.a.") -> n.a. | AC66: =IFERROR(M66*'Inflation adjustment'!$AH$3/'Inflation adjustment'!AG$3,"n.a.") -> n.a. | AD66: =IFERROR(N66*'Inflation adjustment'!$AH$3/'Inflation adjustment'!AH$3,"n.a.") -> n.a. | AE66: =IFERROR(AVERAGE(W66:AD66),"n.a.") -> n.a.
B67: Pakistan | C67: Current US$/kWh | D67: SAR | E67: Mixed | F67: n.a. | G67: n.a. | H67: n.a. | I67: n.a. | J67: 0.10879622 | K67: 0.10473294 | L67: 0.088193286 | M67: 0.072260591 | N67: n.a. | O67: =IFERROR(AVERAGE(G67:N67),"n.a.") -> 0.093495759 | R67: Pakistan | S67: 2017 US$/kWh | T67: SAR | U67: Mixed | V67: n.a. | W67: =IFERROR(G67*'Inflation adjustment'!$AH$3/'Inflation adjustment'!AA$3,"n.a.") -> n.a. | X67: =IFERROR(H67*'Inflation adjustment'!$AH$3/'Inflation adjustment'!AB$3,"n.a.") -> n.a. | Y67: =IFERROR(I67*'Inflation adjustment'!$AH$3/'Inflation adjustment'!AC$3,"n.a.") -> n.a. | Z67: =IFERROR(J67*'Inflation adjustment'!$AH$3/'Inflation adjustment'!AD$3,"n.a.") -> 0.11447638 | AA67: =IFERROR(K67*'Inflation adjustment'!$AH$3/'Inflation adjustment'!AE$3,"n.a.") -> 0.10844179 | AB67: =IFERROR(L67*'Inflation adjustment'!$AH$3/'Inflation adjustment'!AF$3,"n.a.") -> 0.091208232 | AC67: =IFERROR(M67*'Inflation adjustment'!$AH$3/'Inflation adjustment'!AG$3,"n.a.") -> 0.073799821 | AD67: =IFERROR(N67*'Inflation adjustment'!$AH$3/'Inflation adjustment'!AH$3,"n.a.") -> n.a. | AE67: =IFERROR(AVERAGE(W67:AD67),"n.a.") -> 0.096981557
B68: Peru | C68: Current US$/kWh | D68: LAC | E68: Mixed | F68: n.a. | G68: 0.076105924 | H68: 0.079412779 | I68: 0.090800724 | J68: 0.093564209 | K68: 0.099215619 | L68: 0.097942808 | M68: 0.10407765 | N68: n.a. | O68: =IFERROR(AVERAGE(G68:N68),"n.a.") -> 0.09158853 | R68: Peru | S68: 2017 US$/kWh | T68: LAC | U68: Mixed | V68: n.a. | W68: =IFERROR(G68*'Inflation adjustment'!$AH$3/'Inflation adjustment'!AA$3,"n.a.") -> 0.085551854 | X68: =IFERROR(H68*'Inflation adjustment'!$AH$3/'Inflation adjustment'!AB$3,"n.a.") -> 0.086537296 | Y68: =IFERROR(I68*'Inflation adjustment'!$AH$3/'Inflation adjustment'!AC$3,"n.a.") -> 0.096940877 | Z68: =IFERROR(J68*'Inflation adjustment'!$AH$3/'Inflation adjustment'!AD$3,"n.a.") -> 0.09844912 | AA68: =IFERROR(K68*'Inflation adjustment'!$AH$3/'Inflation adjustment'!AE$3,"n.a.") -> 0.10272909 | AB68: =IFERROR(L68*'Inflation adjustment'!$AH$3/'Inflation adjustment'!AF$3,"n.a.") -> 0.10129105 | AC68: =IFERROR(M68*'Inflation adjustment'!$AH$3/'Inflation adjustment'!AG$3,"n.a.") -> 0.10629462 | AD68: =IFERROR(N68*'Inflation adjustment'!$AH$3/'Inflation adjustment'!AH$3,"n.a.") -> n.a. | AE68: =IFERROR(AVERAGE(W68:AD68),"n.a.") -> 0.096827701
B69: Philippines | C69: Current US$/kWh | D69: EAP | E69: Private | F69: n.a. | G69: 0.16446181 | H69: 0.17761957 | I69: 0.18995132 | J69: 0.18742841 | K69: 0.15195116 | L69: 0.1369573 | M69: 0.11775828 | N69: n.a. | O69: =IFERROR(AVERAGE(G69:N69),"n.a.") -> 0.16087541 | R69: Philippines | S69: 2017 US$/kWh | T69: EAP | U69: Private | V69: n.a. | W69: =IFERROR(G69*'Inflation adjustment'!$AH$3/'Inflation adjustment'!AA$3,"n.a.") -> 0.18487408 | X69: =IFERROR(H69*'Inflation adjustment'!$AH$3/'Inflation adjustment'!AB$3,"n.a.") -> 0.19355471 | Y69: =IFERROR(I69*'Inflation adjustment'!$AH$3/'Inflation adjustment'!AC$3,"n.a.") -> 0.20279627 | Z69: =IFERROR(J69*'Inflation adjustment'!$AH$3/'Inflation adjustment'!AD$3,"n.a.") -> 0.19721389 | AA69: =IFERROR(K69*'Inflation adjustment'!$AH$3/'Inflation adjustment'!AE$3,"n.a.") -> 0.15733212 | AB69: =IFERROR(L69*'Inflation adjustment'!$AH$3/'Inflation adjustment'!AF$3,"n.a.") -> 0.14163928 | AC69: =IFERROR(M69*'Inflation adjustment'!$AH$3/'Inflation adjustment'!AG$3,"n.a.") -> 0.12026666 | AD69: =IFERROR(N69*'Inflation adjustment'!$AH$3/'Inflation adjustment'!AH$3,"n.a.") -> n.a. | AE69: =IFERROR(AVERAGE(W69:AD69),"n.a.") -> 0.17109672
B70: Senegal | C70: Current US$/kWh | D70: AFR | E70: Public | F70: n.a. | G70: 0.30698225 | H70: 0.3580137 | I70: 0.35307221 | J70: 0.30989201 | K70: 0.31217383 | L70: 0.192356 | M70: 0.18876011 | N70: n.a. | O70: =IFERROR(AVERAGE(G70:N70),"n.a.") -> 0.28875002 | R70: Senegal | S70: 2017 US$/kWh | T70: AFR | U70: Public | V70: n.a. | W70: =IFERROR(G70*'Inflation adjustment'!$AH$3/'Inflation adjustment'!AA$3,"n.a.") -> 0.34508353 | X70: =IFERROR(H70*'Inflation adjustment'!$AH$3/'Inflation adjustment'!AB$3,"n.a.") -> 0.3901329 | Y70: =IFERROR(I70*'Inflation adjustment'!$AH$3/'Inflation adjustment'!AC$3,"n.a.") -> 0.37694776 | Z70: =IFERROR(J70*'Inflation adjustment'!$AH$3/'Inflation adjustment'!AD$3,"n.a.") -> 0.32607122 | AA70: =IFERROR(K70*'Inflation adjustment'!$AH$3/'Inflation adjustment'!AE$3,"n.a.") -> 0.32322868 | AB70: =IFERROR(L70*'Inflation adjustment'!$AH$3/'Inflation adjustment'!AF$3,"n.a.") -> 0.19893182 | AC70: =IFERROR(M70*'Inflation adjustment'!$AH$3/'Inflation adjustment'!AG$3,"n.a.") -> 0.19278091 | AD70: =IFERROR(N70*'Inflation adjustment'!$AH$3/'Inflation adjustment'!AH$3,"n.a.") -> n.a. | AE70: =IFERROR(AVERAGE(W70:AD70),"n.a.") -> 0.30759669
B71: Tajikistan | C71: Current US$/kWh | D71: ECA | E71: Public | F71: n.a. | G71: n.a. | H71: n.a. | I71: n.a. | J71: 0.015599243 | K71: 0.01567062 | L71: 0.011713544 | M71: 0.013310213 | N71: n.a. | O71: =IFERROR(AVERAGE(G71:N71),"n.a.") -> 0.014073405 | R71: Tajikistan | S71: 2017 US$/kWh | T71: ECA | U71: Public | V71: n.a. | W71: =IFERROR(G71*'Inflation adjustment'!$AH$3/'Inflation adjustment'!AA$3,"n.a.") -> n.a. | X71: =IFERROR(H71*'Inflation adjustment'!$AH$3/'Inflation adjustment'!AB$3,"n.a.") -> n.a. | Y71: =IFERROR(I71*'Inflation adjustment'!$AH$3/'Inflation adjustment'!AC$3,"n.a.") -> n.a. | Z71: =IFERROR(J71*'Inflation adjustment'!$AH$3/'Inflation adjustment'!AD$3,"n.a.") -> 0.016413667 | AA71: =IFERROR(K71*'Inflation adjustment'!$AH$3/'Inflation adjustment'!AE$3,"n.a.") -> 0.016225556 | AB71: =IFERROR(L71*'Inflation adjustment'!$AH$3/'Inflation adjustment'!AF$3,"n.a.") -> 0.01211398 | AC71: =IFERROR(M71*'Inflation adjustment'!$AH$3/'Inflation adjustment'!AG$3,"n.a.") -> 0.013593735 | AD71: =IFERROR(N71*'Inflation adjustment'!$AH$3/'Inflation adjustment'!AH$3,"n.a.") -> n.a. | AE71: =IFERROR(AVERAGE(W71:AD71),"n.a.") -> 0.014586734
B72: Tanzania | C72: Current US$/kWh | D72: AFR | E72: Public | F72: n.a. | G72: n.a. | H72: n.a. | I72: 0.17094617 | J72: 0.1927208 | K72: n.a. | L72: 0.13485617 | M72: 0.10488746 | N72: n.a. | O72: =IFERROR(AVERAGE(G72:N72),"n.a.") -> 0.15085265 | R72: Tanzania | S72: 2017 US$/kWh | T72: AFR | U72: Public | V72: n.a. | W72: =IFERROR(G72*'Inflation adjustment'!$AH$3/'Inflation adjustment'!AA$3,"n.a.") -> n.a. | X72: =IFERROR(H72*'Inflation adjustment'!$AH$3/'Inflation adjustment'!AB$3,"n.a.") -> n.a. | Y72: =IFERROR(I72*'Inflation adjustment'!$AH$3/'Inflation adjustment'!AC$3,"n.a.") -> 0.18250594 | Z72: =IFERROR(J72*'Inflation adjustment'!$AH$3/'Inflation adjustment'!AD$3,"n.a.") -> 0.20278259 | AA72: n.a. | AB72: 0.13963176 | AC72: 0.10847311 | AD72: =IFERROR(N72*'Inflation adjustment'!$AH$3/'Inflation adjustment'!AH$3,"n.a.") -> n.a. | AE72: =IFERROR(AVERAGE(W72:AD72),"n.a.") -> 0.15834835
B73: Uganda | C73: Current US$/kWh | D73: AFR | E73: Private | F73: n.a. | G73: n.a. | H73: n.a. | I73: 0.14253815 | J73: 0.15099909 | K73: 0.14221769 | L73: 0.12978276 | M73: 0.12244444 | N73: n.a. | O73: =IFERROR(AVERAGE(G73:N73),"n.a.") -> 0.13759643 | R73: Uganda | S73: 2017 US$/kWh | T73: AFR | U73: Private | V73: n.a. | W73: =IFERROR(G73*'Inflation adjustment'!$AH$3/'Inflation adjustment'!AA$3,"n.a.") -> n.a. | X73: =IFERROR(H73*'Inflation adjustment'!$AH$3/'Inflation adjustment'!AB$3,"n.a.") -> n.a. | Y73: =IFERROR(I73*'Inflation adjustment'!$AH$3/'Inflation adjustment'!AC$3,"n.a.") -> 0.15217691 | Z73: =IFERROR(J73*'Inflation adjustment'!$AH$3/'Inflation adjustment'!AD$3,"n.a.") -> 0.15888263 | AA73: =IFERROR(K73*'Inflation adjustment'!$AH$3/'Inflation adjustment'!AE$3,"n.a.") -> 0.14725397 | AB73: =IFERROR(L73*'Inflation adjustment'!$AH$3/'Inflation adjustment'!AF$3,"n.a.") -> 0.13421947 | AC73: =IFERROR(M73*'Inflation adjustment'!$AH$3/'Inflation adjustment'!AG$3,"n.a.") -> 0.12505265 | AD73: =IFERROR(N73*'Inflation adjustment'!$AH$3/'Inflation adjustment'!AH$3,"n.a.") -> n.a. | AE73: =IFERROR(AVERAGE(W73:AD73),"n.a.") -> 0.14351713
B74: Ukraine | C74: Current US$/kWh | D74: ECA | E74: Mixed | F74: n.a. | G74: n.a. | H74: n.a. | I74: 0.073287909 | J74: 0.069842227 | K74: 0.052412946 | L74: 0.040097189 | M74: 0.043199216 | N74: 0.045924694 | O74: =IFERROR(AVERAGE(G74:N74),"n.a.") -> 0.054127363 | R74: Ukraine | S74: 2017 US$/kWh | T74: ECA | U74: Mixed | V74: n.a. | W74: =IFERROR(G74*'Inflation adjustment'!$AH$3/'Inflation adjustment'!AA$3,"n.a.") -> n.a. | X74: =IFERROR(H74*'Inflation adjustment'!$AH$3/'Inflation adjustment'!AB$3,"n.a.") -> n.a. | Y74: =IFERROR(I74*'Inflation adjustment'!$AH$3/'Inflation adjustment'!AC$3,"n.a.") -> 0.078243806 | Z74: =IFERROR(J74*'Inflation adjustment'!$AH$3/'Inflation adjustment'!AD$3,"n.a.") -> 0.073488633 | AA74: =IFERROR(K74*'Inflation adjustment'!$AH$3/'Inflation adjustment'!AE$3,"n.a.") -> 0.054269019 | AB74: =IFERROR(L74*'Inflation adjustment'!$AH$3/'Inflation adjustment'!AF$3,"n.a.") -> 0.041467938 | AC74: =IFERROR(M74*'Inflation adjustment'!$AH$3/'Inflation adjustment'!AG$3,"n.a.") -> 0.044119407 | AD74: =IFERROR(N74*'Inflation adjustment'!$AH$3/'Inflation adjustment'!AH$3,"n.a.") -> 0.045924694 | AE74: =IFERROR(AVERAGE(W74:AD74),"n.a.") -> 0.056252249
B75: Vietnam | C75: Current US$/kWh | D75: EAP | E75: Public | F75: n.a. | G75: 0.050130776 | H75: 0.055452512 | I75: 0.058694803 | J75: 0.064884385 | K75: 0.067327743 | L75: 0.0696931 | M75: 0.072269036 | N75: n.a. | O75: =IFERROR(AVERAGE(G75:N75),"n.a.") -> 0.062636051 | R75: Vietnam | S75: 2017 US$/kWh | T75: EAP | U75: Public | V75: n.a. | W75: =IFERROR(G75*'Inflation adjustment'!$AH$3/'Inflation adjustment'!AA$3,"n.a.") -> 0.056352786 | X75: =IFERROR(H75*'Inflation adjustment'!$AH$3/'Inflation adjustment'!AB$3,"n.a.") -> 0.060427434 | Y75: =IFERROR(I75*'Inflation adjustment'!$AH$3/'Inflation adjustment'!AC$3,"n.a.") -> 0.06266388 | Z75: =IFERROR(J75*'Inflation adjustment'!$AH$3/'Inflation adjustment'!AD$3,"n.a.") -> 0.068271946 | AA75: =IFERROR(K75*'Inflation adjustment'!$AH$3/'Inflation adjustment'!AE$3,"n.a.") -> 0.069711985 | AB75: =IFERROR(L75*'Inflation adjustment'!$AH$3/'Inflation adjustment'!AF$3,"n.a.") -> 0.072075605 | AC75: =IFERROR(M75*'Inflation adjustment'!$AH$3/'Inflation adjustment'!AG$3,"n.a.") -> 0.073808446 | AD75: =IFERROR(N75*'Inflation adjustment'!$AH$3/'Inflation adjustment'!AH$3,"n.a.") -> n.a. | AE75: =IFERROR(AVERAGE(W75:AD75),"n.a.") -> 0.06618744
B76: C2 | R76: C2
B77: Colombia | C77: Current US$/kWh | D77: LAC | E77: Private | F77: n.a. | G77: 0.12812138 | H77: 0.1141869 | I77: 0.10817999 | J77: 0.11683024 | K77: 0.11498493 | L77: 0.081847087 | M77: 0.086783296 | N77: n.a. | O77: =IFERROR(AVERAGE(G77:N77),"n.a.") -> 0.10727626 | R77: Colombia | S77: 2017 US$/kWh | T77: LAC | U77: Private | V77: n.a. | W77: =IFERROR(G77*'Inflation adjustment'!$AH$3/'Inflation adjustment'!AA$3,"n.a.") -> 0.14402324 | X77: =IFERROR(H77*'Inflation adjustment'!$AH$3/'Inflation adjustment'!AB$3,"n.a.") -> 0.12443117 | Y77: =IFERROR(I77*'Inflation adjustment'!$AH$3/'Inflation adjustment'!AC$3,"n.a.") -> 0.11549537 | Z77: =IFERROR(J77*'Inflation adjustment'!$AH$3/'Inflation adjustment'!AD$3,"n.a.") -> 0.12292986 | AA77: =IFERROR(K77*'Inflation adjustment'!$AH$3/'Inflation adjustment'!AE$3,"n.a.") -> 0.11905683 | AB77: =IFERROR(L77*'Inflation adjustment'!$AH$3/'Inflation adjustment'!AF$3,"n.a.") -> 0.084645084 | AC77: =IFERROR(M77*'Inflation adjustment'!$AH$3/'Inflation adjustment'!AG$3,"n.a.") -> 0.088631876 | AD77: =IFERROR(N77*'Inflation adjustment'!$AH$3/'Inflation adjustment'!AH$3,"n.a.") -> n.a. | AE77: =IFERROR(AVERAGE(W77:AD77),"n.a.") -> 0.11417335
B78: Dominican Republic | C78: Current US$/kWh | D78: LAC | E78: Public | F78: n.a. | G78: n.a. | H78: n.a. | I78: n.a. | J78: n.a. | K78: n.a. | L78: n.a. | M78: n.a. | N78: n.a. | O78: =IFERROR(AVERAGE(G78:N78),"n.a.") -> n.a. | R78: Dominican Republic | S78: 2017 US$/kWh | T78: LAC | U78: Public | V78: n.a. | W78: =IFERROR(G78*'Inflation adjustment'!$AH$3/'Inflation adjustment'!AA$3,"n.a.") -> n.a. | X78: =IFERROR(H78*'Inflation adjustment'!$AH$3/'Inflation adjustment'!AB$3,"n.a.") -> n.a. | Y78: =IFERROR(I78*'Inflation adjustment'!$AH$3/'Inflation adjustment'!AC$3,"n.a.") -> n.a. | Z78: =IFERROR(J78*'Inflation adjustment'!$AH$3/'Inflation adjustment'!AD$3,"n.a.") -> n.a. | AA78: =IFERROR(K78*'Inflation adjustment'!$AH$3/'Inflation adjustment'!AE$3,"n.a.") -> n.a. | AB78: =IFERROR(L78*'Inflation adjustment'!$AH$3/'Inflation adjustment'!AF$3,"n.a.") -> n.a. | AC78: =IFERROR(M78*'Inflation adjustment'!$AH$3/'Inflation adjustment'!AG$3,"n.a.") -> n.a. | AD78: =IFERROR(N78*'Inflation adjustment'!$AH$3/'Inflation adjustment'!AH$3,"n.a.") -> n.a. | AE78: =IFERROR(AVERAGE(W78:AD78),"n.a.") -> n.a.
B79: Egypt, Arab Rep. | C79: Current US$/kWh | D79: MNA | E79: Public | F79: n.a. | G79: n.a. | H79: 0.041184416 | I79: 0.042818544 | J79: 0.041194011 | K79: 0.064246626 | L79: 0.071286765 | M79: 0.075528685 | N79: n.a. | O79: =IFERROR(AVERAGE(G79:N79),"n.a.") -> 0.056043174 | R79: Egypt, Arab Rep. | S79: 2017 US$/kWh | T79: MNA | U79: Public | V79: n.a. | W79: =IFERROR(G79*'Inflation adjustment'!$AH$3/'Inflation adjustment'!AA$3,"n.a.") -> n.a. | X79: =IFERROR(H79*'Inflation adjustment'!$AH$3/'Inflation adjustment'!AB$3,"n.a.") -> 0.044879276 | Y79: =IFERROR(I79*'Inflation adjustment'!$AH$3/'Inflation adjustment'!AC$3,"n.a.") -> 0.045714032 | Z79: =IFERROR(J79*'Inflation adjustment'!$AH$3/'Inflation adjustment'!AD$3,"n.a.") -> 0.043344717 | AA79: =IFERROR(K79*'Inflation adjustment'!$AH$3/'Inflation adjustment'!AE$3,"n.a.") -> 0.066521758 | AB79: =IFERROR(L79*'Inflation adjustment'!$AH$3/'Inflation adjustment'!AF$3,"n.a.") -> 0.073723751 | AC79: =IFERROR(M79*'Inflation adjustment'!$AH$3/'Inflation adjustment'!AG$3,"n.a.") -> 0.077137529 | AD79: =IFERROR(N79*'Inflation adjustment'!$AH$3/'Inflation adjustment'!AH$3,"n.a.") -> n.a. | AE79: =IFERROR(AVERAGE(W79:AD79),"n.a.") -> 0.05855351
B80: India - Andhra Pradesh | C80: Current US$/kWh | D80: SAR | E80: Public | F80: n.a. | G80: n.a. | H80: 0.16907846 | I80: 0.14124741 | J80: 0.15560772 | K80: 0.16233993 | L80: 0.12971604 | M80: n.a. | N80: n.a. | O80: =IFERROR(AVERAGE(G80:N80),"n.a.") -> 0.15159791 | R80: India - Andhra Pradesh | S80: 2017 US$/kWh | T80: SAR | U80: Public | V80: n.a. | W80: =IFERROR(G80*'Inflation adjustment'!$AH$3/'Inflation adjustment'!AA$3,"n.a.") -> n.a. | X80: =IFERROR(H80*'Inflation adjustment'!$AH$3/'Inflation adjustment'!AB$3,"n.a.") -> 0.18424734 | Y80: =IFERROR(I80*'Inflation adjustment'!$AH$3/'Inflation adjustment'!AC$3,"n.a.") -> 0.15079889 | Z80: =IFERROR(J80*'Inflation adjustment'!$AH$3/'Inflation adjustment'!AD$3,"n.a.") -> 0.16373187 | AA80: =IFERROR(K80*'Inflation adjustment'!$AH$3/'Inflation adjustment'!AE$3,"n.a.") -> 0.16808879 | AB80: =IFERROR(L80*'Inflation adjustment'!$AH$3/'Inflation adjustment'!AF$3,"n.a.") -> 0.13415047 | AC80: =IFERROR(M80*'Inflation adjustment'!$AH$3/'Inflation adjustment'!AG$3,"n.a.") -> n.a. | AD80: =IFERROR(N80*'Inflation adjustment'!$AH$3/'Inflation adjustment'!AH$3,"n.a.") -> n.a. | AE80: =IFERROR(AVERAGE(W80:AD80),"n.a.") -> 0.16020347
B81: India - Odisha | C81: Current US$/kWh | D81: SAR | E81: Public | F81: n.a. | G81: n.a. | H81: 0.091087933 | I81: 0.09818035 | J81: 0.093388428 | K81: 0.096585602 | L81: 0.091024343 | M81: n.a. | N81: n.a. | O81: =IFERROR(AVERAGE(G81:N81),"n.a.") -> 0.094053331 | R81: India - Odisha | S81: 2017 US$/kWh | T81: SAR | U81: Public | V81: n.a. | W81: =IFERROR(G81*'Inflation adjustment'!$AH$3/'Inflation adjustment'!AA$3,"n.a.") -> n.a. | X81: =IFERROR(H81*'Inflation adjustment'!$AH$3/'Inflation adjustment'!AB$3,"n.a.") -> 0.099259887 | Y81: =IFERROR(I81*'Inflation adjustment'!$AH$3/'Inflation adjustment'!AC$3,"n.a.") -> 0.10481953 | Z81: =IFERROR(J81*'Inflation adjustment'!$AH$3/'Inflation adjustment'!AD$3,"n.a.") -> 0.098264162 | AA81: =IFERROR(K81*'Inflation adjustment'!$AH$3/'Inflation adjustment'!AE$3,"n.a.") -> 0.10000594 | AB81: =IFERROR(L81*'Inflation adjustment'!$AH$3/'Inflation adjustment'!AF$3,"n.a.") -> 0.09413607 | AC81: =IFERROR(M81*'Inflation adjustment'!$AH$3/'Inflation adjustment'!AG$3,"n.a.") -> n.a. | AD81: =IFERROR(N81*'Inflation adjustment'!$AH$3/'Inflation adjustment'!AH$3,"n.a.") -> n.a. | AE81: =IFERROR(AVERAGE(W81:AD81),"n.a.") -> 0.099297118
B82: India - Rajasthan | C82: Current US$/kWh | D82: SAR | E82: Public | F82: n.a. | G82: n.a. | H82: 0.16232911 | I82: 0.13953351 | J82: 0.13086507 | K82: 0.17447909 | L82: 0.12138302 | M82: n.a. | N82: n.a. | O82: =IFERROR(AVERAGE(G82:N82),"n.a.") -> 0.14571796 | R82: India - Rajasthan | S82: 2017 US$/kWh | T82: SAR | U82: Public | V82: n.a. | W82: =IFERROR(G82*'Inflation adjustment'!$AH$3/'Inflation adjustment'!AA$3,"n.a.") -> n.a. | X82: =IFERROR(H82*'Inflation adjustment'!$AH$3/'Inflation adjustment'!AB$3,"n.a.") -> 0.17689247 | Y82: =IFERROR(I82*'Inflation adjustment'!$AH$3/'Inflation adjustment'!AC$3,"n.a.") -> 0.14896908 | Z82: =IFERROR(J82*'Inflation adjustment'!$AH$3/'Inflation adjustment'!AD$3,"n.a.") -> 0.13769743 | AA82: =IFERROR(K82*'Inflation adjustment'!$AH$3/'Inflation adjustment'!AE$3,"n.a.") -> 0.18065783 | AB82: =IFERROR(L82*'Inflation adjustment'!$AH$3/'Inflation adjustment'!AF$3,"n.a.") -> 0.12553258 | AC82: =IFERROR(M82*'Inflation adjustment'!$AH$3/'Inflation adjustment'!AG$3,"n.a.") -> n.a. | AD82: =IFERROR(N82*'Inflation adjustment'!$AH$3/'Inflation adjustment'!AH$3,"n.a.") -> n.a. | AE82: =IFERROR(AVERAGE(W82:AD82),"n.a.") -> 0.15394988
B83: Kenya | C83: Current US$/kWh | D83: AFR | E83: Public | F83: n.a. | G83: 0.17300321 | H83: 0.12784954 | I83: 0.17584048 | J83: 0.15206829 | K83: 0.15810724 | L83: 0.14012942 | M83: 0.1326666 | N83: n.a. | O83: =IFERROR(AVERAGE(G83:N83),"n.a.") -> 0.15138068 | R83: Kenya | S83: 2017 US$/kWh | T83: AFR | U83: Public | V83: n.a. | W83: =IFERROR(G83*'Inflation adjustment'!$AH$3/'Inflation adjustment'!AA$3,"n.a.") -> 0.19447561 | X83: =IFERROR(H83*'Inflation adjustment'!$AH$3/'Inflation adjustment'!AB$3,"n.a.") -> 0.13931957 | Y83: =IFERROR(I83*'Inflation adjustment'!$AH$3/'Inflation adjustment'!AC$3,"n.a.") -> 0.18773122 | Z83: =IFERROR(J83*'Inflation adjustment'!$AH$3/'Inflation adjustment'!AD$3,"n.a.") -> 0.16000765 | AA83: =IFERROR(K83*'Inflation adjustment'!$AH$3/'Inflation adjustment'!AE$3,"n.a.") -> 0.16370622 | AB83: =IFERROR(L83*'Inflation adjustment'!$AH$3/'Inflation adjustment'!AF$3,"n.a.") -> 0.14491984 | AC83: =IFERROR(M83*'Inflation adjustment'!$AH$3/'Inflation adjustment'!AG$3,"n.a.") -> 0.13549254 | AD83: =IFERROR(N83*'Inflation adjustment'!$AH$3/'Inflation adjustment'!AH$3,"n.a.") -> n.a. | AE83: =IFERROR(AVERAGE(W83:AD83),"n.a.") -> 0.16080752
B84: Morocco | C84: Current US$/kWh | D84: MNA | E84: Public | F84: n.a. | G84: n.a. | H84: n.a. | I84: n.a. | J84: n.a. | K84: n.a. | L84: n.a. | M84: n.a. | N84: n.a. | O84: =IFERROR(AVERAGE(G84:N84),"n.a.") -> n.a. | R84: Morocco | S84: 2017 US$/kWh | T84: MNA | U84: Public | V84: n.a. | W84: =IFERROR(G84*'Inflation adjustment'!$AH$3/'Inflation adjustment'!AA$3,"n.a.") -> n.a. | X84: =IFERROR(H84*'Inflation adjustment'!$AH$3/'Inflation adjustment'!AB$3,"n.a.") -> n.a. | Y84: =IFERROR(I84*'Inflation adjustment'!$AH$3/'Inflation adjustment'!AC$3,"n.a.") -> n.a. | Z84: =IFERROR(J84*'Inflation adjustment'!$AH$3/'Inflation adjustment'!AD$3,"n.a.") -> n.a. | AA84: =IFERROR(K84*'Inflation adjustment'!$AH$3/'Inflation adjustment'!AE$3,"n.a.") -> n.a. | AB84: =IFERROR(L84*'Inflation adjustment'!$AH$3/'Inflation adjustment'!AF$3,"n.a.") -> n.a. | AC84: =IFERROR(M84*'Inflation adjustment'!$AH$3/'Inflation adjustment'!AG$3,"n.a.") -> n.a. | AD84: =IFERROR(N84*'Inflation adjustment'!$AH$3/'Inflation adjustment'!AH$3,"n.a.") -> n.a. | AE84: =IFERROR(AVERAGE(W84:AD84),"n.a.") -> n.a.
B85: Pakistan | C85: Current US$/kWh | D85: SAR | E85: Mixed | F85: n.a. | G85: n.a. | H85: n.a. | I85: n.a. | J85: 0.11590658 | K85: 0.11248366 | L85: 0.096347197 | M85: 0.079563871 | N85: n.a. | O85: =IFERROR(AVERAGE(G85:N85),"n.a.") -> 0.10107533 | R85: Pakistan | S85: 2017 US$/kWh | T85: SAR | U85: Mixed | V85: n.a. | W85: =IFERROR(G85*'Inflation adjustment'!$AH$3/'Inflation adjustment'!AA$3,"n.a.") -> n.a. | X85: =IFERROR(H85*'Inflation adjustment'!$AH$3/'Inflation adjustment'!AB$3,"n.a.") -> n.a. | Y85: =IFERROR(I85*'Inflation adjustment'!$AH$3/'Inflation adjustment'!AC$3,"n.a.") -> n.a. | Z85: =IFERROR(J85*'Inflation adjustment'!$AH$3/'Inflation adjustment'!AD$3,"n.a.") -> 0.12195797 | AA85: =IFERROR(K85*'Inflation adjustment'!$AH$3/'Inflation adjustment'!AE$3,"n.a.") -> 0.11646699 | AB85: =IFERROR(L85*'Inflation adjustment'!$AH$3/'Inflation adjustment'!AF$3,"n.a.") -> 0.09964089 | AC85: =IFERROR(M85*'Inflation adjustment'!$AH$3/'Inflation adjustment'!AG$3,"n.a.") -> 0.081258669 | AD85: =IFERROR(N85*'Inflation adjustment'!$AH$3/'Inflation adjustment'!AH$3,"n.a.") -> n.a. | AE85: =IFERROR(AVERAGE(W85:AD85),"n.a.") -> 0.10483113
B86: Peru | C86: Current US$/kWh | D86: LAC | E86: Mixed | F86: n.a. | G86: 0.1019539 | H86: 0.10249485 | I86: 0.11288124 | J86: 0.11438743 | K86: 0.12420886 | L86: 0.12030152 | M86: 0.13126792 | N86: n.a. | O86: =IFERROR(AVERAGE(G86:N86),"n.a.") -> 0.11535653 | R86: Peru | S86: 2017 US$/kWh | T86: LAC | U86: Mixed | V86: n.a. | W86: =IFERROR(G86*'Inflation adjustment'!$AH$3/'Inflation adjustment'!AA$3,"n.a.") -> 0.11460797 | X86: =IFERROR(H86*'Inflation adjustment'!$AH$3/'Inflation adjustment'!AB$3,"n.a.") -> 0.11169018 | Y86: =IFERROR(I86*'Inflation adjustment'!$AH$3/'Inflation adjustment'!AC$3,"n.a.") -> 0.12051453 | Z86: =IFERROR(J86*'Inflation adjustment'!$AH$3/'Inflation adjustment'!AD$3,"n.a.") -> 0.1203595 | AA86: =IFERROR(K86*'Inflation adjustment'!$AH$3/'Inflation adjustment'!AE$3,"n.a.") -> 0.12860741 | AB86: =IFERROR(L86*'Inflation adjustment'!$AH$3/'Inflation adjustment'!AF$3,"n.a.") -> 0.1244141 | AC86: =IFERROR(M86*'Inflation adjustment'!$AH$3/'Inflation adjustment'!AG$3,"n.a.") -> 0.13406407 | AD86: =IFERROR(N86*'Inflation adjustment'!$AH$3/'Inflation adjustment'!AH$3,"n.a.") -> n.a. | AE86: =IFERROR(AVERAGE(W86:AD86),"n.a.") -> 0.12203682
B87: Philippines | C87: Current US$/kWh | D87: EAP | E87: Private | F87: n.a. | G87: 0.1804066 | H87: 0.19382686 | I87: 0.20383754 | J87: 0.21146825 | K87: 0.17069967 | L87: 0.14966606 | M87: 0.13466022 | N87: n.a. | O87: =IFERROR(AVERAGE(G87:N87),"n.a.") -> 0.17779503 | R87: Philippines | S87: 2017 US$/kWh | T87: EAP | U87: Private | V87: n.a. | W87: =IFERROR(G87*'Inflation adjustment'!$AH$3/'Inflation adjustment'!AA$3,"n.a.") -> 0.20279786 | X87: =IFERROR(H87*'Inflation adjustment'!$AH$3/'Inflation adjustment'!AB$3,"n.a.") -> 0.21121604 | Y87: =IFERROR(I87*'Inflation adjustment'!$AH$3/'Inflation adjustment'!AC$3,"n.a.") -> 0.21762151 | Z87: =IFERROR(J87*'Inflation adjustment'!$AH$3/'Inflation adjustment'!AD$3,"n.a.") -> 0.22250884 | AA87: =IFERROR(K87*'Inflation adjustment'!$AH$3/'Inflation adjustment'!AE$3,"n.a.") -> 0.17674457 | AB87: =IFERROR(L87*'Inflation adjustment'!$AH$3/'Inflation adjustment'!AF$3,"n.a.") -> 0.1547825 | AC87: =IFERROR(M87*'Inflation adjustment'!$AH$3/'Inflation adjustment'!AG$3,"n.a.") -> 0.13752863 | AD87: =IFERROR(N87*'Inflation adjustment'!$AH$3/'Inflation adjustment'!AH$3,"n.a.") -> n.a. | AE87: =IFERROR(AVERAGE(W87:AD87),"n.a.") -> 0.18902856
B88: Senegal | C88: Current US$/kWh | D88: AFR | E88: Public | F88: n.a. | G88: 0.32261556 | H88: 0.37385604 | I88: 0.42014836 | J88: 0.35218231 | K88: 0.33254727 | L88: 0.20680779 | M88: 0.20224871 | N88: n.a. | O88: =IFERROR(AVERAGE(G88:N88),"n.a.") -> 0.31577229 | R88: Senegal | S88: 2017 US$/kWh | T88: AFR | U88: Public | V88: n.a. | W88: =IFERROR(G88*'Inflation adjustment'!$AH$3/'Inflation adjustment'!AA$3,"n.a.") -> 0.36265717 | X88: =IFERROR(H88*'Inflation adjustment'!$AH$3/'Inflation adjustment'!AB$3,"n.a.") -> 0.40739653 | Y88: =IFERROR(I88*'Inflation adjustment'!$AH$3/'Inflation adjustment'!AC$3,"n.a.") -> 0.44855975 | Z88: =IFERROR(J88*'Inflation adjustment'!$AH$3/'Inflation adjustment'!AD$3,"n.a.") -> 0.37056946 | AA88: =IFERROR(K88*'Inflation adjustment'!$AH$3/'Inflation adjustment'!AE$3,"n.a.") -> 0.34432359 | AB88: =IFERROR(L88*'Inflation adjustment'!$AH$3/'Inflation adjustment'!AF$3,"n.a.") -> 0.21387765 | AC88: =IFERROR(M88*'Inflation adjustment'!$AH$3/'Inflation adjustment'!AG$3,"n.a.") -> 0.20655683 | AD88: =IFERROR(N88*'Inflation adjustment'!$AH$3/'Inflation adjustment'!AH$3,"n.a.") -> n.a. | AE88: =IFERROR(AVERAGE(W88:AD88),"n.a.") -> 0.33627728
B89: Tajikistan | C89: Current US$/kWh | D89: ECA | E89: Public | F89: n.a. | G89: n.a. | H89: n.a. | I89: n.a. | J89: 0.032558364 | K89: 0.022797623 | L89: 0.018129271 | M89: 0.020563973 | N89: n.a. | O89: =IFERROR(AVERAGE(G89:N89),"n.a.") -> 0.023512308 | R89: Tajikistan | S89: 2017 US$/kWh | T89: ECA | U89: Public | V89: n.a. | W89: =IFERROR(G89*'Inflation adjustment'!$AH$3/'Inflation adjustment'!AA$3,"n.a.") -> n.a. | X89: =IFERROR(H89*'Inflation adjustment'!$AH$3/'Inflation adjustment'!AB$3,"n.a.") -> n.a. | Y89: =IFERROR(I89*'Inflation adjustment'!$AH$3/'Inflation adjustment'!AC$3,"n.a.") -> n.a. | Z89: =IFERROR(J89*'Inflation adjustment'!$AH$3/'Inflation adjustment'!AD$3,"n.a.") -> 0.03425821 | AA89: =IFERROR(K89*'Inflation adjustment'!$AH$3/'Inflation adjustment'!AE$3,"n.a.") -> 0.023604944 | AB89: =IFERROR(L89*'Inflation adjustment'!$AH$3/'Inflation adjustment'!AF$3,"n.a.") -> 0.018749032 | AC89: =IFERROR(M89*'Inflation adjustment'!$AH$3/'Inflation adjustment'!AG$3,"n.a.") -> 0.021002008 | AD89: =IFERROR(N89*'Inflation adjustment'!$AH$3/'Inflation adjustment'!AH$3,"n.a.") -> n.a. | AE89: =IFERROR(AVERAGE(W89:AD89),"n.a.") -> 0.024403548
B90: Tanzania | C90: Current US$/kWh | D90: AFR | E90: Public | F90: n.a. | G90: n.a. | H90: n.a. | I90: 0.18637518 | J90: 0.20838644 | K90: n.a. | L90: 0.14940362 | M90: 0.11356778 | N90: n.a. | O90: =IFERROR(AVERAGE(G90:N90),"n.a.") -> 0.16443325 | R90: Tanzania | S90: 2017 US$/kWh | T90: AFR | U90: Public | V90: n.a. | W90: =IFERROR(G90*'Inflation adjustment'!$AH$3/'Inflation adjustment'!AA$3,"n.a.") -> n.a. | X90: =IFERROR(H90*'Inflation adjustment'!$AH$3/'Inflation adjustment'!AB$3,"n.a.") -> n.a. | Y90: =IFERROR(I90*'Inflation adjustment'!$AH$3/'Inflation adjustment'!AC$3,"n.a.") -> 0.1989783 | Z90: =IFERROR(J90*'Inflation adjustment'!$AH$3/'Inflation adjustment'!AD$3,"n.a.") -> 0.21926613 | AA90: n.a. | AB90: 0.15469437 | AC90: 0.11745017 | AD90: =IFERROR(N90*'Inflation adjustment'!$AH$3/'Inflation adjustment'!AH$3,"n.a.") -> n.a. | AE90: =IFERROR(AVERAGE(W90:AD90),"n.a.") -> 0.17259724
B91: Uganda | C91: Current US$/kWh | D91: AFR | E91: Private | F91: n.a. | G91: n.a. | H91: n.a. | I91: 0.15396759 | J91: 0.16866168 | K91: 0.1499538 | L91: 0.13765692 | M91: 0.13957045 | N91: n.a. | O91: =IFERROR(AVERAGE(G91:N91),"n.a.") -> 0.14996209 | R91: Uganda | S91: 2017 US$/kWh | T91: AFR | U91: Private | V91: n.a. | W91: =IFERROR(G91*'Inflation adjustment'!$AH$3/'Inflation adjustment'!AA$3,"n.a.") -> n.a. | X91: =IFERROR(H91*'Inflation adjustment'!$AH$3/'Inflation adjustment'!AB$3,"n.a.") -> n.a. | Y91: =IFERROR(I91*'Inflation adjustment'!$AH$3/'Inflation adjustment'!AC$3,"n.a.") -> 0.16437923 | Z91: =IFERROR(J91*'Inflation adjustment'!$AH$3/'Inflation adjustment'!AD$3,"n.a.") -> 0.17746737 | AA91: =IFERROR(K91*'Inflation adjustment'!$AH$3/'Inflation adjustment'!AE$3,"n.a.") -> 0.15526404 | AB91: =IFERROR(L91*'Inflation adjustment'!$AH$3/'Inflation adjustment'!AF$3,"n.a.") -> 0.14236281 | AC91: =IFERROR(M91*'Inflation adjustment'!$AH$3/'Inflation adjustment'!AG$3,"n.a.") -> 0.14254345 | AD91: =IFERROR(N91*'Inflation adjustment'!$AH$3/'Inflation adjustment'!AH$3,"n.a.") -> n.a. | AE91: =IFERROR(AVERAGE(W91:AD91),"n.a.") -> 0.15640338
B92: Ukraine | C92: Current US$/kWh | D92: ECA | E92: Mixed | F92: n.a. | G92: n.a. | H92: n.a. | I92: 0.074910882 | J92: 0.071820956 | K92: 0.054196673 | L92: 0.041245583 | M92: 0.044926821 | N92: 0.052790258 | O92: =IFERROR(AVERAGE(G92:N92),"n.a.") -> 0.056648529 | R92: Ukraine | S92: 2017 US$/kWh | T92: ECA | U92: Mixed | V92: n.a. | W92: =IFERROR(G92*'Inflation adjustment'!$AH$3/'Inflation adjustment'!AA$3,"n.a.") -> n.a. | X92: =IFERROR(H92*'Inflation adjustment'!$AH$3/'Inflation adjustment'!AB$3,"n.a.") -> n.a. | Y92: =IFERROR(I92*'Inflation adjustment'!$AH$3/'Inflation adjustment'!AC$3,"n.a.") -> 0.079976528 | Z92: =IFERROR(J92*'Inflation adjustment'!$AH$3/'Inflation adjustment'!AD$3,"n.a.") -> 0.07557067 | AA92: =IFERROR(K92*'Inflation adjustment'!$AH$3/'Inflation adjustment'!AE$3,"n.a.") -> 0.056115912 | AB92: =IFERROR(L92*'Inflation adjustment'!$AH$3/'Inflation adjustment'!AF$3,"n.a.") -> 0.042655591 | AC92: =IFERROR(M92*'Inflation adjustment'!$AH$3/'Inflation adjustment'!AG$3,"n.a.") -> 0.045883812 | AD92: =IFERROR(N92*'Inflation adjustment'!$AH$3/'Inflation adjustment'!AH$3,"n.a.") -> 0.052790258 | AE92: =IFERROR(AVERAGE(W92:AD92),"n.a.") -> 0.058832128
B93: Vietnam | C93: Current US$/kWh | D93: EAP | E93: Public | F93: n.a. | G93: 0.052687627 | H93: 0.060127906 | I93: 0.061945455 | J93: 0.068937564 | K93: 0.069548856 | L93: 0.072657656 | M93: 0.074498231 | N93: n.a. | O93: =IFERROR(AVERAGE(G93:N93),"n.a.") -> 0.065771899 | R93: Vietnam | S93: 2017 US$/kWh | T93: EAP | U93: Public | V93: n.a. | W93: =IFERROR(G93*'Inflation adjustment'!$AH$3/'Inflation adjustment'!AA$3,"n.a.") -> 0.059226983 | X93: =IFERROR(H93*'Inflation adjustment'!$AH$3/'Inflation adjustment'!AB$3,"n.a.") -> 0.065522281 | Y93: =IFERROR(I93*'Inflation adjustment'!$AH$3/'Inflation adjustment'!AC$3,"n.a.") -> 0.066134348 | Z93: =IFERROR(J93*'Inflation adjustment'!$AH$3/'Inflation adjustment'!AD$3,"n.a.") -> 0.072536738 | AA93: =IFERROR(K93*'Inflation adjustment'!$AH$3/'Inflation adjustment'!AE$3,"n.a.") -> 0.072011754 | AB93: =IFERROR(L93*'Inflation adjustment'!$AH$3/'Inflation adjustment'!AF$3,"n.a.") -> 0.075141506 | AC93: =IFERROR(M93*'Inflation adjustment'!$AH$3/'Inflation adjustment'!AG$3,"n.a.") -> 0.076085125 | AD93: =IFERROR(N93*'Inflation adjustment'!$AH$3/'Inflation adjustment'!AH$3,"n.a.") -> n.a. | AE93: =IFERROR(AVERAGE(W93:AD93),"n.a.") -> 0.069522676
B94: C3 | R94: C3
B95: Colombia | C95: Current US$/kWh | D95: LAC | E95: Private | F95: 0.0536 | G95: 0.13065574 | H95: 0.11927694 | I95: 0.11509969 | J95: 0.12541565 | K95: 0.12538156 | L95: 0.091998354 | M95: 0.099312921 | N95: n.a. | O95: =IFERROR(AVERAGE(G95:N95),"n.a.") -> 0.11530584 | R95: Colombia | S95: 2017 US$/kWh | T95: LAC | U95: Private | V95: =IFERROR(F95*'Inflation adjustment'!AH$3/'Inflation adjustment'!D$3,"n.a.") -> 0.11562957 | W95: =IFERROR(G95*'Inflation adjustment'!$AH$3/'Inflation adjustment'!AA$3,"n.a.") -> 0.14687215 | X95: =IFERROR(H95*'Inflation adjustment'!$AH$3/'Inflation adjustment'!AB$3,"n.a.") -> 0.12997787 | Y95: =IFERROR(I95*'Inflation adjustment'!$AH$3/'Inflation adjustment'!AC$3,"n.a.") -> 0.122883 | Z95: =IFERROR(J95*'Inflation adjustment'!$AH$3/'Inflation adjustment'!AD$3,"n.a.") -> 0.1319635 | AA95: =IFERROR(K95*'Inflation adjustment'!$AH$3/'Inflation adjustment'!AE$3,"n.a.") -> 0.12982163 | AB95: =IFERROR(L95*'Inflation adjustment'!$AH$3/'Inflation adjustment'!AF$3,"n.a.") -> 0.095143378 | AC95: =IFERROR(M95*'Inflation adjustment'!$AH$3/'Inflation adjustment'!AG$3,"n.a.") -> 0.1014284 | AD95: =IFERROR(N95*'Inflation adjustment'!$AH$3/'Inflation adjustment'!AH$3,"n.a.") -> n.a. | AE95: =IFERROR(AVERAGE(W95:AD95),"n.a.") -> 0.12258427
B96: Dominican Republic | C96: Current US$/kWh | D96: LAC | E96: Public | F96: 0.085 | G96: 0.2239417 | H96: 0.28601733 | I96: 0.32335889 | J96: 0.32376005 | K96: 0.31822914 | L96: 0.23992642 | M96: n.a. | N96: n.a. | O96: =IFERROR(AVERAGE(G96:N96),"n.a.") -> 0.28587225 | R96: Dominican Republic | S96: 2017 US$/kWh | T96: LAC | U96: Public | V96: =IFERROR(F96*'Inflation adjustment'!AH$3/'Inflation adjustment'!D$3,"n.a.") -> 0.18336779 | W96: =IFERROR(G96*'Inflation adjustment'!$AH$3/'Inflation adjustment'!AA$3,"n.a.") -> 0.25173635 | X96: =IFERROR(H96*'Inflation adjustment'!$AH$3/'Inflation adjustment'!AB$3,"n.a.") -> 0.31167737 | Y96: =IFERROR(I96*'Inflation adjustment'!$AH$3/'Inflation adjustment'!AC$3,"n.a.") -> 0.34522516 | Z96: =IFERROR(J96*'Inflation adjustment'!$AH$3/'Inflation adjustment'!AD$3,"n.a.") -> 0.3406633 | AA96: =IFERROR(K96*'Inflation adjustment'!$AH$3/'Inflation adjustment'!AE$3,"n.a.") -> 0.32949842 | AB96: =IFERROR(L96*'Inflation adjustment'!$AH$3/'Inflation adjustment'!AF$3,"n.a.") -> 0.24812846 | AC96: =IFERROR(M96*'Inflation adjustment'!$AH$3/'Inflation adjustment'!AG$3,"n.a.") -> n.a. | AD96: =IFERROR(N96*'Inflation adjustment'!$AH$3/'Inflation adjustment'!AH$3,"n.a.") -> n.a. | AE96: =IFERROR(AVERAGE(W96:AD96),"n.a.") -> 0.30448818 | AH96: Edesur
B97: Egypt, Arab Rep. | C97: Current US$/kWh | D97: MNA | E97: Public | F97: 0.078 | G97: n.a. | H97: 0.062703306 | I97: 0.062484414 | J97: 0.055007625 | K97: 0.073321653 | L97: 0.096017221 | M97: 0.096236774 | N97: n.a. | O97: =IFERROR(AVERAGE(G97:N97),"n.a.") -> 0.074295165 | R97: Egypt, Arab Rep. | S97: 2017 US$/kWh | T97: MNA | U97: Public | V97: =IFERROR(F97*'Inflation adjustment'!AH$3/'Inflation adjustment'!D$3,"n.a.") -> 0.16826691 | W97: =IFERROR(G97*'Inflation adjustment'!$AH$3/'Inflation adjustment'!AA$3,"n.a.") -> n.a. | X97: =IFERROR(H97*'Inflation adjustment'!$AH$3/'Inflation adjustment'!AB$3,"n.a.") -> 0.068328733 | Y97: =IFERROR(I97*'Inflation adjustment'!$AH$3/'Inflation adjustment'!AC$3,"n.a.") -> 0.066709753 | Z97: =IFERROR(J97*'Inflation adjustment'!$AH$3/'Inflation adjustment'!AD$3,"n.a.") -> 0.057879528 | AA97: =IFERROR(K97*'Inflation adjustment'!$AH$3/'Inflation adjustment'!AE$3,"n.a.") -> 0.075918155 | AB97: =IFERROR(L97*'Inflation adjustment'!$AH$3/'Inflation adjustment'!AF$3,"n.a.") -> 0.099299634 | AC97: =IFERROR(M97*'Inflation adjustment'!$AH$3/'Inflation adjustment'!AG$3,"n.a.") -> 0.098286723 | AD97: =IFERROR(N97*'Inflation adjustment'!$AH$3/'Inflation adjustment'!AH$3,"n.a.") -> n.a. | AE97: =IFERROR(AVERAGE(W97:AD97),"n.a.") -> 0.077737088
B98: India - Andhra Pradesh | C98: Current US$/kWh | D98: SAR | E98: Public | F98: 0.0804 | G98: n.a. | H98: 0.20876515 | I98: 0.18542409 | J98: 0.19091488 | K98: 0.19821308 | L98: 0.166412 | M98: n.a. | N98: n.a. | O98: =IFERROR(AVERAGE(G98:N98),"n.a.") -> 0.18994584 | R98: India - Andhra Pradesh | S98: 2017 US$/kWh | T98: SAR | U98: Public | V98: =IFERROR(F98*'Inflation adjustment'!AH$3/'Inflation adjustment'!D$3,"n.a.") -> 0.17344435 | W98: =IFERROR(G98*'Inflation adjustment'!$AH$3/'Inflation adjustment'!AA$3,"n.a.") -> n.a. | X98: =IFERROR(H98*'Inflation adjustment'!$AH$3/'Inflation adjustment'!AB$3,"n.a.") -> 0.22749452 | Y98: =IFERROR(I98*'Inflation adjustment'!$AH$3/'Inflation adjustment'!AC$3,"n.a.") -> 0.19796289 | Z98: =IFERROR(J98*'Inflation adjustment'!$AH$3/'Inflation adjustment'!AD$3,"n.a.") -> 0.20088239 | AA98: =IFERROR(K98*'Inflation adjustment'!$AH$3/'Inflation adjustment'!AE$3,"n.a.") -> 0.2052323 | AB98: =IFERROR(L98*'Inflation adjustment'!$AH$3/'Inflation adjustment'!AF$3,"n.a.") -> 0.1721009 | AC98: =IFERROR(M98*'Inflation adjustment'!$AH$3/'Inflation adjustment'!AG$3,"n.a.") -> n.a. | AD98: =IFERROR(N98*'Inflation adjustment'!$AH$3/'Inflation adjustment'!AH$3,"n.a.") -> n.a. | AE98: =IFERROR(AVERAGE(W98:AD98),"n.a.") -> 0.2007346
B99: India - Odisha | C99: Current US$/kWh | D99: SAR | E99: Public | F99: 0.0804 | G99: n.a. | H99: 0.094407637 | I99: 0.10169872 | J99: 0.096905897 | K99: 0.10058215 | L99: 0.096184332 | M99: n.a. | N99: n.a. | O99: =IFERROR(AVERAGE(G99:N99),"n.a.") -> 0.097955747 | R99: India - Odisha | S99: 2017 US$/kWh | T99: SAR | U99: Public | V99: =IFERROR(F99*'Inflation adjustment'!AH$3/'Inflation adjustment'!D$3,"n.a.") -> 0.17344435 | W99: =IFERROR(G99*'Inflation adjustment'!$AH$3/'Inflation adjustment'!AA$3,"n.a.") -> n.a. | X99: =IFERROR(H99*'Inflation adjustment'!$AH$3/'Inflation adjustment'!AB$3,"n.a.") -> 0.10287742 | Y99: =IFERROR(I99*'Inflation adjustment'!$AH$3/'Inflation adjustment'!AC$3,"n.a.") -> 0.10857582 | Z99: =IFERROR(J99*'Inflation adjustment'!$AH$3/'Inflation adjustment'!AD$3,"n.a.") -> 0.10196528 | AA99: =IFERROR(K99*'Inflation adjustment'!$AH$3/'Inflation adjustment'!AE$3,"n.a.") -> 0.10414401 | AB99: =IFERROR(L99*'Inflation adjustment'!$AH$3/'Inflation adjustment'!AF$3,"n.a.") -> 0.099472457 | AC99: =IFERROR(M99*'Inflation adjustment'!$AH$3/'Inflation adjustment'!AG$3,"n.a.") -> n.a. | AD99: =IFERROR(N99*'Inflation adjustment'!$AH$3/'Inflation adjustment'!AH$3,"n.a.") -> n.a. | AE99: =IFERROR(AVERAGE(W99:AD99),"n.a.") -> 0.103407
B100: India - Rajasthan | C100: Current US$/kWh | D100: SAR | E100: Public | F100: 0.0804 | G100: n.a. | H100: 0.17143476 | I100: 0.14888497 | J100: 0.14155685 | K100: 0.18946 | L100: 0.13330179 | M100: n.a. | N100: n.a. | O100: =IFERROR(AVERAGE(G100:N100),"n.a.") -> 0.15692767 | R100: India - Rajasthan | S100: 2017 US$/kWh | T100: SAR | U100: Public | V100: =IFERROR(F100*'Inflation adjustment'!AH$3/'Inflation adjustment'!D$3,"n.a.") -> 0.17344435 | W100: =IFERROR(G100*'Inflation adjustment'!$AH$3/'Inflation adjustment'!AA$3,"n.a.") -> n.a. | X100: =IFERROR(H100*'Inflation adjustment'!$AH$3/'Inflation adjustment'!AB$3,"n.a.") -> 0.18681502 | Y100: =IFERROR(I100*'Inflation adjustment'!$AH$3/'Inflation adjustment'!AC$3,"n.a.") -> 0.15895291 | Z100: =IFERROR(J100*'Inflation adjustment'!$AH$3/'Inflation adjustment'!AD$3,"n.a.") -> 0.14894742 | AA100: =IFERROR(K100*'Inflation adjustment'!$AH$3/'Inflation adjustment'!AE$3,"n.a.") -> 0.19616925 | AB100: =IFERROR(L100*'Inflation adjustment'!$AH$3/'Inflation adjustment'!AF$3,"n.a.") -> 0.1378588 | AC100: =IFERROR(M100*'Inflation adjustment'!$AH$3/'Inflation adjustment'!AG$3,"n.a.") -> n.a. | AD100: =IFERROR(N100*'Inflation adjustment'!$AH$3/'Inflation adjustment'!AH$3,"n.a.") -> n.a. | AE100: =IFERROR(AVERAGE(W100:AD100),"n.a.") -> 0.16574868
B101: Kenya | C101: Current US$/kWh | D101: AFR | E101: Public | F101: 0.0563 | G101: 0.18145224 | H101: 0.14162893 | I101: 0.20123602 | J101: 0.1920655 | K101: 0.19897184 | L101: 0.18858449 | M101: 0.18201373 | N101: n.a. | O101: =IFERROR(AVERAGE(G101:N101),"n.a.") -> 0.18370754 | R101: Kenya | S101: 2017 US$/kWh | T101: AFR | U101: Public | V101: =IFERROR(F101*'Inflation adjustment'!AH$3/'Inflation adjustment'!D$3,"n.a.") -> 0.12145419 | W101: =IFERROR(G101*'Inflation adjustment'!$AH$3/'Inflation adjustment'!AA$3,"n.a.") -> 0.20397329 | X101: =IFERROR(H101*'Inflation adjustment'!$AH$3/'Inflation adjustment'!AB$3,"n.a.") -> 0.15433517 | Y101: =IFERROR(I101*'Inflation adjustment'!$AH$3/'Inflation adjustment'!AC$3,"n.a.") -> 0.21484406 | Z101: =IFERROR(J101*'Inflation adjustment'!$AH$3/'Inflation adjustment'!AD$3,"n.a.") -> 0.20209309 | AA101: =IFERROR(K101*'Inflation adjustment'!$AH$3/'Inflation adjustment'!AE$3,"n.a.") -> 0.20601792 | AB101: =IFERROR(L101*'Inflation adjustment'!$AH$3/'Inflation adjustment'!AF$3,"n.a.") -> 0.19503137 | AC101: =IFERROR(M101*'Inflation adjustment'!$AH$3/'Inflation adjustment'!AG$3,"n.a.") -> 0.18589082 | AD101: =IFERROR(N101*'Inflation adjustment'!$AH$3/'Inflation adjustment'!AH$3,"n.a.") -> n.a. | AE101: =IFERROR(AVERAGE(W101:AD101),"n.a.") -> 0.19459796
...

Sheet Sales & Collections
B1: Revenue/collections per unit - Country level | C1: Unit | D1: Region | E1: Type | F1: Pre-reform | G1: 2010 | H1: 2011 | I1: 2012 | J1: 2013 | K1: 2014 | L1: 2015 | M1: 2016 | N1: 2017 | O1: Average | R1: Revenue/collections per unit - Country level | S1: Unit | T1: Region | U1: Type | V1: Pre-reform | W1: 2010 | X1: 2011 | Y1: 2012 | Z1: 2013 | AA1: 2014 | AB1: 2015 | AC1: 2016 | AD1: 2017 | AE1: Average | AF1: Variance | AI1: Source
B2: Average effective revenues (from electricity sales) | R2: Average effective revenues (from electricity sales)
B3: Colombia | C3: Current US$/kWh | D3: LAC | E3: Private | F3: 0.0295 | G3: 0.12228027 | H3: 0.13003902 | I3: 0.13468444 | J3: 0.12882427 | K3: 0.12594808 | L3: 0.09684593 | M3: 0.10173739 | N3: n.a. | O3: =IFERROR(AVERAGE(G3:N3),"n.a.") -> 0.12005134 | R3: Colombia | S3: 2017 US$/kWh | T3: LAC | U3: Private | V3: =IFERROR(F3*'Inflation adjustment'!AH$3/'Inflation adjustment'!D$3,"n.a.") -> 0.063639408 | W3: =IFERROR(G3*'Inflation adjustment'!$AH$3/'Inflation adjustment'!AA$3,"n.a.") -> 0.13745716 | X3: =IFERROR(H3*'Inflation adjustment'!$AH$3/'Inflation adjustment'!AB$3,"n.a.") -> 0.14170547 | Y3: =IFERROR(I3*'Inflation adjustment'!$AH$3/'Inflation adjustment'!AC$3,"n.a.") -> 0.14379211 | Z3: =IFERROR(J3*'Inflation adjustment'!$AH$3/'Inflation adjustment'!AD$3,"n.a.") -> 0.13555008 | AA3: =IFERROR(K3*'Inflation adjustment'!$AH$3/'Inflation adjustment'!AE$3,"n.a.") -> 0.13040822 | AB3: =IFERROR(L3*'Inflation adjustment'!$AH$3/'Inflation adjustment'!AF$3,"n.a.") -> 0.10015667 | AC3: =IFERROR(M3*'Inflation adjustment'!$AH$3/'Inflation adjustment'!AG$3,"n.a.") -> 0.10390451 | AD3: =IFERROR(N3*'Inflation adjustment'!$AH$3/'Inflation adjustment'!AH$3,"n.a.") -> n.a. | AE3: =IFERROR(AVERAGE(W3:AD3),"n.a.") -> 0.12756775
B4: Dominican Republic | C4: Current US$/kWh | D4: LAC | E4: Public | F4: 0.0899 | G4: 0.15792193 | H4: 0.18458724 | I4: 0.20089267 | J4: 0.2095203 | K4: 0.19728499 | L4: 0.17580671 | M4: n.a. | N4: n.a. | O4: =IFERROR(AVERAGE(G4:N4),"n.a.") -> 0.18766897 | R4: Dominican Republic | S4: 2017 US$/kWh | T4: LAC | U4: Public | V4: =IFERROR(F4*'Inflation adjustment'!AH$3/'Inflation adjustment'!D$3,"n.a.") -> 0.1939384 | W4: =IFERROR(G4*'Inflation adjustment'!$AH$3/'Inflation adjustment'!AA$3,"n.a.") -> 0.17752251 | X4: =IFERROR(H4*'Inflation adjustment'!$AH$3/'Inflation adjustment'!AB$3,"n.a.") -> 0.20114748 | Y4: =IFERROR(I4*'Inflation adjustment'!$AH$3/'Inflation adjustment'!AC$3,"n.a.") -> 0.21447749 | Z4: =IFERROR(J4*'Inflation adjustment'!$AH$3/'Inflation adjustment'!AD$3,"n.a.") -> 0.22045919 | AA4: =IFERROR(K4*'Inflation adjustment'!$AH$3/'Inflation adjustment'!AE$3,"n.a.") -> 0.20427134 | AB4: =IFERROR(L4*'Inflation adjustment'!$AH$3/'Inflation adjustment'!AF$3,"n.a.") -> 0.18181678 | AC4: =IFERROR(M4*'Inflation adjustment'!$AH$3/'Inflation adjustment'!AG$3,"n.a.") -> n.a. | AD4: =IFERROR(N4*'Inflation adjustment'!$AH$3/'Inflation adjustment'!AH$3,"n.a.") -> n.a. | AE4: =IFERROR(AVERAGE(W4:AD4),"n.a.") -> 0.19994913 | AI4: Edesur
B5: Egypt, Arab Rep. | C5: Current US$/kWh | D5: MNA | E5: Public | F5: 0.0166 | G5: n.a. | H5: 0.038714953 | I5: 0.038874237 | J5: 0.037242396 | K5: 0.036516102 | L5: 0.047067718 | M5: 0.048461033 | N5: n.a. | O5: =IFERROR(AVERAGE(G5:N5),"n.a.") -> 0.041146073 | R5: Egypt, Arab Rep. | S5: 2017 US$/kWh | T5: MNA | U5: Public | V5: =IFERROR(F5*'Inflation adjustment'!AH$3/'Inflation adjustment'!D$3,"n.a.") -> 0.03581065 | W5: =IFERROR(G5*'Inflation adjustment'!$AH$3/'Inflation adjustment'!AA$3,"n.a.") -> n.a. | X5: =IFERROR(H5*'Inflation adjustment'!$AH$3/'Inflation adjustment'!AB$3,"n.a.") -> 0.042188265 | Y5: =IFERROR(I5*'Inflation adjustment'!$AH$3/'Inflation adjustment'!AC$3,"n.a.") -> 0.041503002 | Z5: =IFERROR(J5*'Inflation adjustment'!$AH$3/'Inflation adjustment'!AD$3,"n.a.") -> 0.039186792 | AA5: =IFERROR(K5*'Inflation adjustment'!$AH$3/'Inflation adjustment'!AE$3,"n.a.") -> 0.037809228 | AB5: =IFERROR(L5*'Inflation adjustment'!$AH$3/'Inflation adjustment'!AF$3,"n.a.") -> 0.048676759 | AC5: =IFERROR(M5*'Inflation adjustment'!$AH$3/'Inflation adjustment'!AG$3,"n.a.") -> 0.049493306 | AD5: =IFERROR(N5*'Inflation adjustment'!$AH$3/'Inflation adjustment'!AH$3,"n.a.") -> n.a. | AE5: =IFERROR(AVERAGE(W5:AD5),"n.a.") -> 0.043142892
B6: India - Andhra Pradesh | C6: Current US$/kWh | D6: SAR | E6: Public | F6: 0.0434 | G6: n.a. | H6: 0.074399755 | I6: 0.067517893 | J6: 0.072995555 | K6: 0.072921304 | L6: 0.073312484 | M6: n.a. | N6: n.a. | O6: =IFERROR(AVERAGE(G6:N6),"n.a.") -> 0.072229398 | R6: India - Andhra Pradesh | S6: 2017 US$/kWh | T6: SAR | U6: Public | V6: =IFERROR(F6*'Inflation adjustment'!AH$3/'Inflation adjustment'!D$3,"n.a.") -> 0.093625434 | W6: =IFERROR(G6*'Inflation adjustment'!$AH$3/'Inflation adjustment'!AA$3,"n.a.") -> n.a. | X6: =IFERROR(H6*'Inflation adjustment'!$AH$3/'Inflation adjustment'!AB$3,"n.a.") -> 0.081074529 | Y6: =IFERROR(I6*'Inflation adjustment'!$AH$3/'Inflation adjustment'!AC$3,"n.a.") -> 0.072083607 | Z6: =IFERROR(J6*'Inflation adjustment'!$AH$3/'Inflation adjustment'!AD$3,"n.a.") -> 0.076806594 | AA6: =IFERROR(K6*'Inflation adjustment'!$AH$3/'Inflation adjustment'!AE$3,"n.a.") -> 0.075503629 | AB6: =IFERROR(L6*'Inflation adjustment'!$AH$3/'Inflation adjustment'!AF$3,"n.a.") -> 0.07581872 | AC6: =IFERROR(M6*'Inflation adjustment'!$AH$3/'Inflation adjustment'!AG$3,"n.a.") -> n.a. | AD6: =IFERROR(N6*'Inflation adjustment'!$AH$3/'Inflation adjustment'!AH$3,"n.a.") -> n.a. | AE6: =IFERROR(AVERAGE(W6:AD6),"n.a.") -> 0.076257416
B7: India - Odisha | C7: Current US$/kWh | D7: SAR | E7: Public | F7: 0.0434 | G7: n.a. | H7: 0.08851544 | I7: 0.093069893 | J7: 0.086760881 | K7: 0.092201779 | L7: 0.087231858 | M7: n.a. | N7: n.a. | O7: =IFERROR(AVERAGE(G7:N7),"n.a.") -> 0.08955597 | R7: India - Odisha | S7: 2017 US$/kWh | T7: SAR | U7: Public | V7: =IFERROR(F7*'Inflation adjustment'!AH$3/'Inflation adjustment'!D$3,"n.a.") -> 0.093625434 | W7: =IFERROR(G7*'Inflation adjustment'!$AH$3/'Inflation adjustment'!AA$3,"n.a.") -> n.a. | X7: =IFERROR(H7*'Inflation adjustment'!$AH$3/'Inflation adjustment'!AB$3,"n.a.") -> 0.096456602 | Y7: =IFERROR(I7*'Inflation adjustment'!$AH$3/'Inflation adjustment'!AC$3,"n.a.") -> 0.099363492 | Z7: =IFERROR(J7*'Inflation adjustment'!$AH$3/'Inflation adjustment'!AD$3,"n.a.") -> 0.091290597 | AA7: =IFERROR(K7*'Inflation adjustment'!$AH$3/'Inflation adjustment'!AE$3,"n.a.") -> 0.095466874 | AB7: =IFERROR(L7*'Inflation adjustment'!$AH$3/'Inflation adjustment'!AF$3,"n.a.") -> 0.090213937 | AC7: =IFERROR(M7*'Inflation adjustment'!$AH$3/'Inflation adjustment'!AG$3,"n.a.") -> n.a. | AD7: =IFERROR(N7*'Inflation adjustment'!$AH$3/'Inflation adjustment'!AH$3,"n.a.") -> n.a. | AE7: =IFERROR(AVERAGE(W7:AD7),"n.a.") -> 0.0945583
B8: India - Rajasthan | C8: Current US$/kWh | D8: SAR | E8: Public | F8: 0.0434 | G8: n.a. | H8: 0.065816062 | I8: 0.061244854 | J8: 0.066975832 | K8: 0.081131887 | L8: 0.075563724 | M8: n.a. | N8: n.a. | O8: =IFERROR(AVERAGE(G8:N8),"n.a.") -> 0.070146472 | R8: India - Rajasthan | S8: 2017 US$/kWh | T8: SAR | U8: Public | V8: =IFERROR(F8*'Inflation adjustment'!AH$3/'Inflation adjustment'!D$3,"n.a.") -> 0.093625434 | W8: =IFERROR(G8*'Inflation adjustment'!$AH$3/'Inflation adjustment'!AA$3,"n.a.") -> n.a. | X8: =IFERROR(H8*'Inflation adjustment'!$AH$3/'Inflation adjustment'!AB$3,"n.a.") -> 0.071720749 | Y8: =IFERROR(I8*'Inflation adjustment'!$AH$3/'Inflation adjustment'!AC$3,"n.a.") -> 0.065386371 | Z8: =IFERROR(J8*'Inflation adjustment'!$AH$3/'Inflation adjustment'!AD$3,"n.a.") -> 0.070472586 | AA8: =IFERROR(K8*'Inflation adjustment'!$AH$3/'Inflation adjustment'!AE$3,"n.a.") -> 0.084004969 | AB8: =IFERROR(L8*'Inflation adjustment'!$AH$3/'Inflation adjustment'!AF$3,"n.a.") -> 0.07814692 | AC8: =IFERROR(M8*'Inflation adjustment'!$AH$3/'Inflation adjustment'!AG$3,"n.a.") -> n.a. | AD8: =IFERROR(N8*'Inflation adjustment'!$AH$3/'Inflation adjustment'!AH$3,"n.a.") -> n.a. | AE8: =IFERROR(AVERAGE(W8:AD8),"n.a.") -> 0.073946319
B9: Kenya | C9: Current US$/kWh | D9: AFR | E9: Public | F9: 0.0599 | G9: 0.18015167 | H9: 0.14238786 | I9: 0.18890414 | J9: 0.1680287 | K9: 0.17756396 | L9: 0.15337623 | M9: 0.14566578 | N9: n.a. | O9: =IFERROR(AVERAGE(G9:N9),"n.a.") -> 0.16515405 | R9: Kenya | S9: 2017 US$/kWh | T9: AFR | U9: Public | V9: =IFERROR(F9*'Inflation adjustment'!AH$3/'Inflation adjustment'!D$3,"n.a.") -> 0.12922036 | W9: =IFERROR(G9*'Inflation adjustment'!$AH$3/'Inflation adjustment'!AA$3,"n.a.") -> 0.2025113 | X9: =IFERROR(H9*'Inflation adjustment'!$AH$3/'Inflation adjustment'!AB$3,"n.a.") -> 0.15516219 | Y9: =IFERROR(I9*'Inflation adjustment'!$AH$3/'Inflation adjustment'!AC$3,"n.a.") -> 0.20167827 | Z9: =IFERROR(J9*'Inflation adjustment'!$AH$3/'Inflation adjustment'!AD$3,"n.a.") -> 0.17680134 | AA9: =IFERROR(K9*'Inflation adjustment'!$AH$3/'Inflation adjustment'!AE$3,"n.a.") -> 0.18385194 | AB9: =IFERROR(L9*'Inflation adjustment'!$AH$3/'Inflation adjustment'!AF$3,"n.a.") -> 0.1586195 | AC9: =IFERROR(M9*'Inflation adjustment'!$AH$3/'Inflation adjustment'!AG$3,"n.a.") -> 0.14876862 | AD9: =IFERROR(N9*'Inflation adjustment'!$AH$3/'Inflation adjustment'!AH$3,"n.a.") -> n.a. | AE9: =IFERROR(AVERAGE(W9:AD9),"n.a.") -> 0.17534188
B10: Morocco | C10: Current US$/kWh | D10: MNA | E10: Public | F10: 0.0875 | G10: n.a. | H10: n.a. | I10: n.a. | J10: 0.1136 | K10: n.a. | L10: n.a. | M10: n.a. | N10: n.a. | O10: =IFERROR(AVERAGE(G10:N10),"n.a.") -> 0.1136 | R10: Morocco | S10: 2017 US$/kWh | T10: MNA | U10: Public | V10: =IFERROR(F10*'Inflation adjustment'!AH$3/'Inflation adjustment'!D$3,"n.a.") -> 0.18876096 | W10: =IFERROR(G10*'Inflation adjustment'!$AH$3/'Inflation adjustment'!AA$3,"n.a.") -> n.a. | X10: =IFERROR(H10*'Inflation adjustment'!$AH$3/'Inflation adjustment'!AB$3,"n.a.") -> n.a. | Y10: =IFERROR(I10*'Inflation adjustment'!$AH$3/'Inflation adjustment'!AC$3,"n.a.") -> n.a. | Z10: =IFERROR(J10*'Inflation adjustment'!$AH$3/'Inflation adjustment'!AD$3,"n.a.") -> 0.11953096 | AA10: =IFERROR(K10*'Inflation adjustment'!$AH$3/'Inflation adjustment'!AE$3,"n.a.") -> n.a. | AB10: =IFERROR(L10*'Inflation adjustment'!$AH$3/'Inflation adjustment'!AF$3,"n.a.") -> n.a. | AC10: =IFERROR(M10*'Inflation adjustment'!$AH$3/'Inflation adjustment'!AG$3,"n.a.") -> n.a. | AD10: =IFERROR(N10*'Inflation adjustment'!$AH$3/'Inflation adjustment'!AH$3,"n.a.") -> n.a. | AE10: =IFERROR(AVERAGE(W10:AD10),"n.a.") -> 0.11953096
