Workbook

Sheet Summary
A1: Excise diagnostic: cross-country workbook (Uganda, Sierra Leone, Liberia)
A2: Data quality at a glance. All figures below are formulas over the other sheets.
A4: Indicator | B4: Sierra Leone | C4: Uganda | D4: Liberia | E4: How computed
A5: Cut-off date | B5: =Parameters!G5 -> 2026-04-27 | C5: =Parameters!G6 -> 2026-04-27 | D5: =Parameters!G7 -> 2026-09-29 | E5: Parameters
A6: Standard lines covered (of 30) | B6: =Std_Schedule!F41 -> 25 | C6: =Std_Schedule!L41 -> 26 | D6: =Std_Schedule!R41 -> 21 | E6: Std_Schedule coverage 1 + 2
A7: National rate rows (covered) | B7: =COUNTIFS(Std_Schedule_Code!$B$5:$B$191,"SLE",Std_Schedule_Code!$J$5:$J$191,">0") -> 69 | C7: =COUNTIFS(Std_Schedule_Code!$B$5:$B$191,"UGA",Std_Schedule_Code!$J$5:$J$191,">0") -> 62 | D7: =COUNTIFS(Std_Schedule_Code!$B$5:$B$191,"LBR",Std_Schedule_Code!$J$5:$J$191,">0") -> 38 | E7: Std_Schedule_Code rows with coverage 1 or 2
A8: Average DQ, schedule rows (covered) | B8: =IFERROR(AVERAGEIFS(Std_Schedule_Code!$AO$5:$AO$191,Std_Schedule_Code!$B$5:$B$191,"SLE",Std_Schedule_Code!$J$5:$J$191,">0"),"") -> 3.3188406 | C8: =IFERROR(AVERAGEIFS(Std_Schedule_Code!$AO$5:$AO$191,Std_Schedule_Code!$B$5:$B$191,"UGA",Std_Schedule_Code!$J$5:$J$191,">0"),"") -> 2 | D8: =IFERROR(AVERAGEIFS(Std_Schedule_Code!$AO$5:$AO$191,Std_Schedule_Code!$B$5:$B$191,"LBR",Std_Schedule_Code!$J$5:$J$191,">0"),"") -> 3.7105263 | E8: Mean of dq_score
A9: Share of schedule rows with DQ >= 4 | B9: =IFERROR(COUNTIFS(Std_Schedule_Code!$B$5:$B$191,"SLE",Std_Schedule_Code!$J$5:$J$191,">0",Std_Schedule_Code!$AO$5:$AO$191,">=4")/COUNTIFS(Std_Schedule_Code!$B$5:$B$191,"SLE",Std_Schedule_Code!$J$5:$J$191,">0"),"") -> 0.50724638 | C9: =IFERROR(COUNTIFS(Std_Schedule_Code!$B$5:$B$191,"UGA",Std_Schedule_Code!$J$5:$J$191,">0",Std_Schedule_Code!$AO$5:$AO$191,">=4")/COUNTIFS(Std_Schedule_Code!$B$5:$B$191,"UGA",Std_Schedule_Code!$J$5:$J$191,">0"),"") -> 0 | D9: =IFERROR(COUNTIFS(Std_Schedule_Code!$B$5:$B$191,"LBR",Std_Schedule_Code!$J$5:$J$191,">0",Std_Schedule_Code!$AO$5:$AO$191,">=4")/COUNTIFS(Std_Schedule_Code!$B$5:$B$191,"LBR",Std_Schedule_Code!$J$5:$J$191,">0"),"") -> 0.65789474 | E9: Rows verified or corrected
A10: Rows shown at last legible rate | B10: =COUNTIFS(Std_Schedule_Code!$B$5:$B$191,"SLE",Std_Schedule_Code!$O$5:$O$191,"last_legible") -> 16 | C10: =COUNTIFS(Std_Schedule_Code!$B$5:$B$191,"UGA",Std_Schedule_Code!$O$5:$O$191,"last_legible") -> 0 | D10: =COUNTIFS(Std_Schedule_Code!$B$5:$B$191,"LBR",Std_Schedule_Code!$O$5:$O$191,"last_legible") -> 0 | E10: Current rate not legible in the published law
A11: Standard lines with DQ <= 2 (incl. not-covered findings) | B11: =COUNTIF(Std_Schedule!J6:J35,"<=2") -> 16 | C11: =COUNTIF(Std_Schedule!P6:P35,"<=2") -> 30 | D11: =COUNTIF(Std_Schedule!V6:V35,"<=2") -> 3 | E11: Std_Schedule DQ columns
A12: Average DQ, country metrics | B12: =IFERROR(AVERAGE(Country_Metrics!G5:G41),"") -> 2.6857143 | C12: =IFERROR(AVERAGE(Country_Metrics!K5:K41),"") -> 1.8571429 | D12: =IFERROR(AVERAGE(Country_Metrics!O5:O41),"") -> 3.6857143 | E12: Mean of Country_Metrics DQ
A14: Sheets
A15: Country_Metrics | B15: (a) Overall metrics and the seven key questions by country, with DQ per cell.
A16: Std_Schedule | B16: (b) Human-readable standardized schedule: 30 standard lines x 3 countries, with coverage and DQ.
A17: Std_Schedule_Code | B17: (b) Code-readable schedule: one row per rate component; specific and ad valorem parts of hybrids on separate rows; USD computed by formula.
A18: Parameters | B18: Exchange rates, cut-off dates, GDP and conversion factors (inputs in blue).
A19: DQ_Scale | B19: Data-quality scale mapped from peer-review status.
A20: Sources | B20: Documents behind each country and version notes.
A22: Read before use
A23: Cut-off dates differ: Uganda and Sierra Leone at 27 April 2026 (WP v0.8); Liberia at 29 September 2026.
A24: Uganda lines are extracted but not yet peer reviewed, so they score DQ 2 throughout.
A25: Sierra Leone spirits, other fermented beverages and all SSB lines show the last legible (FA2023) rates; the FA2024 replacement rows are not legible (DQ 1).
A26: Liberia's 2026 rates read the 'Proposed' column of the December 2025 Act as in force; this is verified text with an open interpretation point (DQ 4).
A27: Mapping of HS 2206 (cider, perry, mead) to A3 differs between WP v0.8 (not mapped) and Liberia v0.3 (A3). The code sheet applies HS 2206 -> A3 for all three; the human-readable sheet keeps each report's coverage.
A28: The 'part' column groups codes into 1 Fuel, 2 Vehicles, 3 Health, 4 Other (plastics E7 placed in Other; gambling G1 in Health, following the WP's 'Health (other)' category; both placements are provisional).
A29: Editable inputs: blue cells (rate_value, conv_to_std_unit, ref_price_per_rate_unit, Parameters). To add a country, add a Parameters row and append rows to Std_Schedule_Code following the existing rows.

Sheet Country_Metrics
A1: Overall metrics and key questions by country
A2: Values as published in each diagnostic. Status column drives the DQ score (formula). Benchmarks from the process specification, section 9.
A4: Section | B4: ID | C4: Metric / question | D4: Unit | E4: SLE: Value | F4: SLE: Review status | G4: SLE: DQ | H4: SLE: Source / ref. | I4: UGA: Value | J4: UGA: Review status | K4: UGA: DQ | L4: UGA: Source / ref. | M4: LBR: Value | N4: LBR: Review status | O4: LBR: DQ | P4: LBR: Source / ref. | Q4: International reference | R4: Notes
A5: Context | B5: X1 | C5: Legal basis at cut-off | D5: text | E5: Excise Act 1982 as amended through Finance Act 2026 (eff. 1 Jan 2026) | F5: partly_verified | G5: =IF(F5="","",IFERROR(INDEX(DQ_Scale!$B$5:$B$14,MATCH(F5,DQ_Scale!$A$5:$A$14,0)),"")) -> 3 | H5: PR-01 | I5: Excise Duty Act 2014 as amended through the 2025 Amendment Acts (eff. 1 Jul 2025); 2026 Bill not assented | J5: not_reviewed | K5: =IF(J5="","",IFERROR(INDEX(DQ_Scale!$B$5:$B$14,MATCH(J5,DQ_Scale!$A$5:$A$14,0)),"")) -> 2 | L5: WP Table 13 | M5: Revenue Code Part IV, Ch. 11, as amended through the Tax Amendment Act of Dec 2025 (in force 1 Apr 2026; LRA from 1 May 2026) | N5: verified_open_point | O5: =IF(N5="","",IFERROR(INDEX(DQ_Scale!$B$5:$B$14,MATCH(N5,DQ_Scale!$A$5:$A$14,0)),"")) -> 4 | P5: PR-17, PR-01
A6: Context | B6: X2 | C6: Cut-off date | D6: date | E6: 2026-04-27 | F6: verified | G6: =IF(F6="","",IFERROR(INDEX(DQ_Scale!$B$5:$B$14,MATCH(F6,DQ_Scale!$A$5:$A$14,0)),"")) -> 5 | H6: WP s.7 | I6: 2026-04-27 | J6: verified | K6: =IF(J6="","",IFERROR(INDEX(DQ_Scale!$B$5:$B$14,MATCH(J6,DQ_Scale!$A$5:$A$14,0)),"")) -> 5 | L6: WP s.7 | M6: 2026-09-29 | N6: verified | O6: =IF(N6="","",IFERROR(INDEX(DQ_Scale!$B$5:$B$14,MATCH(N6,DQ_Scale!$A$5:$A$14,0)),"")) -> 5 | P6: v0.3 s.7
A7: Context | B7: X3 | C7: Working exchange rate | D7: LCU per USD | E7: NLe 22 (MoF 22.665-23; USD values may be ~4% high) | F7: assumption | G7: =IF(F7="","",IFERROR(INDEX(DQ_Scale!$B$5:$B$14,MATCH(F7,DQ_Scale!$A$5:$A$14,0)),"")) -> 1 | H7: PR-40 | I7: UGX 3,750 | J7: not_reviewed | K7: =IF(J7="","",IFERROR(INDEX(DQ_Scale!$B$5:$B$14,MATCH(J7,DQ_Scale!$A$5:$A$14,0)),"")) -> 2 | L7: WP Table 13 | M7: LRD 171.59 (CBL mid); excise rates printed in US$ | N7: verified | O7: =IF(N7="","",IFERROR(INDEX(DQ_Scale!$B$5:$B$14,MATCH(N7,DQ_Scale!$A$5:$A$14,0)),"")) -> 5 | P7: PR-39
A8: Context | B8: X4 | C8: Nominal GDP | D8: USD bn | E8: 7.5 (2026 working; MoF 2025 ~7.2) | F8: partly_verified | G8: =IF(F8="","",IFERROR(INDEX(DQ_Scale!$B$5:$B$14,MATCH(F8,DQ_Scale!$A$5:$A$14,0)),"")) -> 3 | H8: PR-41 | I8: 55 (WB 2024: 53.65) | J8: not_reviewed | K8: =IF(J8="","",IFERROR(INDEX(DQ_Scale!$B$5:$B$14,MATCH(J8,DQ_Scale!$A$5:$A$14,0)),"")) -> 2 | L8: WP Table 13 | M8: 5.25 (2025, WDI) | N8: verified | O8: =IF(N8="","",IFERROR(INDEX(DQ_Scale!$B$5:$B$14,MATCH(N8,DQ_Scale!$A$5:$A$14,0)),"")) -> 5 | P8: PR-41
A9: Context | B9: X5 | C9: Currency notation of rates | D9: text | E9: US$ -> 'Le' -> 'NLe'; 'Le' confirmed as new Leones | F9: verified | G9: =IF(F9="","",IFERROR(INDEX(DQ_Scale!$B$5:$B$14,MATCH(F9,DQ_Scale!$A$5:$A$14,0)),"")) -> 5 | H9: PR-07 | I9: UGX throughout | J9: not_reviewed | K9: =IF(J9="","",IFERROR(INDEX(DQ_Scale!$B$5:$B$14,MATCH(J9,DQ_Scale!$A$5:$A$14,0)),"")) -> 2 | M9: US$ / '$' (read as US$) | N9: verified | O9: =IF(N9="","",IFERROR(INDEX(DQ_Scale!$B$5:$B$14,MATCH(N9,DQ_Scale!$A$5:$A$14,0)),"")) -> 5 | P9: PR-16
A10: Context | B10: X6 | C10: Peer review (stage A5) | D10: entries | E10: 49 entries: 18 verified, 11 partly, 16 corrected, 4 not verified | G10: =IF(F10="","",IFERROR(INDEX(DQ_Scale!$B$5:$B$14,MATCH(F10,DQ_Scale!$A$5:$A$14,0)),"")) | H10: WP Annex D | I10: Not yet peer reviewed | K10: =IF(J10="","",IFERROR(INDEX(DQ_Scale!$B$5:$B$14,MATCH(J10,DQ_Scale!$A$5:$A$14,0)),"")) | L10: WP note v0.8 | M10: 49 entries: 22 verified, 11 partly, 14 corrected, 2 not verified | O10: =IF(N10="","",IFERROR(INDEX(DQ_Scale!$B$5:$B$14,MATCH(N10,DQ_Scale!$A$5:$A$14,0)),"")) | P10: v0.3 Annex B
A11: Revenue | B11: R1 | C11: Excise collected, all lines | D11: % of GDP | E11: 1.25-1.28% (2024-25) | F11: corrected | G11: =IF(F11="","",IFERROR(INDEX(DQ_Scale!$B$5:$B$14,MATCH(F11,DQ_Scale!$A$5:$A$14,0)),"")) -> 4 | H11: PR-48 | I11: n.a. (not collected for WP) | J11: data_gap | K11: =IF(J11="","",IFERROR(INDEX(DQ_Scale!$B$5:$B$14,MATCH(J11,DQ_Scale!$A$5:$A$14,0)),"")) -> 1 | M11: 0.373% (FY2024); 0.378% (FY2023) | N11: verified | O11: =IF(N11="","",IFERROR(INDEX(DQ_Scale!$B$5:$B$14,MATCH(N11,DQ_Scale!$A$5:$A$14,0)),"")) -> 5 | P11: PR-28, PR-29 | Q11: Africa avg 2.4%; low-income 2.2% (2021)
A12: Revenue | B12: R2 | C12: Excise plus excise-like levies collected | D12: % of GDP | E12: n.a. (levies not reported) | F12: data_gap | G12: =IF(F12="","",IFERROR(INDEX(DQ_Scale!$B$5:$B$14,MATCH(F12,DQ_Scale!$A$5:$A$14,0)),"")) -> 1 | I12: n.a. | J12: data_gap | K12: =IF(J12="","",IFERROR(INDEX(DQ_Scale!$B$5:$B$14,MATCH(J12,DQ_Scale!$A$5:$A$14,0)),"")) -> 1 | M12: 1.254% (FY2024: excise + Road Fund 0.665% + motor vehicle 0.215%) | N12: verified | O12: =IF(N12="","",IFERROR(INDEX(DQ_Scale!$B$5:$B$14,MATCH(N12,DQ_Scale!$A$5:$A$14,0)),"")) -> 5 | P12: PR-25, PR-38
A13: Revenue | B13: R3 | C13: Fuel excise collected | D13: % of GDP | E13: 1.12-1.15% (2024-25) | F13: corrected | G13: =IF(F13="","",IFERROR(INDEX(DQ_Scale!$B$5:$B$14,MATCH(F13,DQ_Scale!$A$5:$A$14,0)),"")) -> 4 | H13: PR-48 | I13: n.a. | J13: data_gap | K13: =IF(J13="","",IFERROR(INDEX(DQ_Scale!$B$5:$B$14,MATCH(J13,DQ_Scale!$A$5:$A$14,0)),"")) -> 1 | M13: Not in excise law. Road Fund line 0.665% (may include non-fuel receipts) | N13: partly_verified | O13: =IF(N13="","",IFERROR(INDEX(DQ_Scale!$B$5:$B$14,MATCH(N13,DQ_Scale!$A$5:$A$14,0)),"")) -> 3 | P13: PR-25, PR-48
A14: Revenue | B14: R4 | C14: Fuel excise implied at current rates | D14: % of GDP | E14: ~1.6% (1.58%, FA2026) | F14: estimate | G14: =IF(F14="","",IFERROR(INDEX(DQ_Scale!$B$5:$B$14,MATCH(F14,DQ_Scale!$A$5:$A$14,0)),"")) -> 2 | H14: WP Table 14 | I14: ~1.3% (1.29%) | J14: estimate | K14: =IF(J14="","",IFERROR(INDEX(DQ_Scale!$B$5:$B$14,MATCH(J14,DQ_Scale!$A$5:$A$14,0)),"")) -> 2 | L14: WP Table 14 | M14: 1.061% (levies; 2024 volume, 2025 GDP) | N14: estimate | O14: =IF(N14="","",IFERROR(INDEX(DQ_Scale!$B$5:$B$14,MATCH(N14,DQ_Scale!$A$5:$A$14,0)),"")) -> 2 | P14: C-11 | Q14: OECD 1.5-2.5%
A15: Revenue | B15: R5 | C15: Tobacco excise implied (upper bound) | D15: % of GDP | E15: 0.09-0.17% (5-10 cigarettes a day) | F15: estimate | G15: =IF(F15="","",IFERROR(INDEX(DQ_Scale!$B$5:$B$14,MATCH(F15,DQ_Scale!$A$5:$A$14,0)),"")) -> 2 | H15: PR-45 | I15: ~0.14% | J15: estimate | K15: =IF(J15="","",IFERROR(INDEX(DQ_Scale!$B$5:$B$14,MATCH(J15,DQ_Scale!$A$5:$A$14,0)),"")) -> 2 | L15: WP Table 14 | M15: 0.16% (8 a day) | N15: estimate | O15: =IF(N15="","",IFERROR(INDEX(DQ_Scale!$B$5:$B$14,MATCH(N15,DQ_Scale!$A$5:$A$14,0)),"")) -> 2 | P15: C-18 | Q15: South Africa ~0.4%; EU ~0.6%
A16: Revenue | B16: R6 | C16: Tobacco excise collected | D16: % of GDP / USD | E16: n.a. (within non-fuel 0.10-0.16%) | F16: data_gap | G16: =IF(F16="","",IFERROR(INDEX(DQ_Scale!$B$5:$B$14,MATCH(F16,DQ_Scale!$A$5:$A$14,0)),"")) -> 1 | I16: n.a. | J16: data_gap | K16: =IF(J16="","",IFERROR(INDEX(DQ_Scale!$B$5:$B$14,MATCH(J16,DQ_Scale!$A$5:$A$14,0)),"")) -> 1 | M16: US$0 on imported tobacco (FY2024, Q1 FY2025) | N16: verified | O16: =IF(N16="","",IFERROR(INDEX(DQ_Scale!$B$5:$B$14,MATCH(N16,DQ_Scale!$A$5:$A$14,0)),"")) -> 5 | P16: PR-28, PR-45
A17: Revenue | B17: R7 | C17: Alcohol excise implied | D17: % of GDP | E17: ~0.05% (indicative) | F17: assumption | G17: =IF(F17="","",IFERROR(INDEX(DQ_Scale!$B$5:$B$14,MATCH(F17,DQ_Scale!$A$5:$A$14,0)),"")) -> 1 | H17: WP Table 14 | I17: ~0.2% (indicative) | J17: assumption | K17: =IF(J17="","",IFERROR(INDEX(DQ_Scale!$B$5:$B$14,MATCH(J17,DQ_Scale!$A$5:$A$14,0)),"")) -> 1 | L17: WP Table 14 | M17: 0.347% at current rates (WHO recorded use, carried forward) | N17: estimate | O17: =IF(N17="","",IFERROR(INDEX(DQ_Scale!$B$5:$B$14,MATCH(N17,DQ_Scale!$A$5:$A$14,0)),"")) -> 2 | P17: C-24, PR-43 | Q17: OECD 0.4-0.6%
A18: Revenue | B18: R8 | C18: SSB excise | D18: % of GDP | E18: Not estimated (no volumes) | F18: data_gap | G18: =IF(F18="","",IFERROR(INDEX(DQ_Scale!$B$5:$B$14,MATCH(F18,DQ_Scale!$A$5:$A$14,0)),"")) -> 1 | I18: ~0.05% (indicative) | J18: assumption | K18: =IF(J18="","",IFERROR(INDEX(DQ_Scale!$B$5:$B$14,MATCH(J18,DQ_Scale!$A$5:$A$14,0)),"")) -> 1 | L18: WP Table 14 | M18: Imports collected FY2024: US$6.80m (0.142% of GDP); implied not estimated | N18: verified | O18: =IF(N18="","",IFERROR(INDEX(DQ_Scale!$B$5:$B$14,MATCH(N18,DQ_Scale!$A$5:$A$14,0)),"")) -> 5 | P18: PR-28
A19: Revenue | B19: R9 | C19: All non-fuel excise | D19: % of GDP | E19: 0.10-0.16% collected (2024-25) | F19: corrected | G19: =IF(F19="","",IFERROR(INDEX(DQ_Scale!$B$5:$B$14,MATCH(F19,DQ_Scale!$A$5:$A$14,0)),"")) -> 4 | H19: PR-48 | I19: ~0.4% implied (health lines) | J19: assumption | K19: =IF(J19="","",IFERROR(INDEX(DQ_Scale!$B$5:$B$14,MATCH(J19,DQ_Scale!$A$5:$A$14,0)),"")) -> 1 | L19: WP Table 7 | M19: 0.373% collected (all excise is non-fuel) | N19: verified | O19: =IF(N19="","",IFERROR(INDEX(DQ_Scale!$B$5:$B$14,MATCH(N19,DQ_Scale!$A$5:$A$14,0)),"")) -> 5 | P19: PR-28
A20: Rate intensity | B20: I1 | C20: Petrol: USD per liter | D20: USD/l | E20: 0.23 | F20: partly_verified | G20: =IF(F20="","",IFERROR(INDEX(DQ_Scale!$B$5:$B$14,MATCH(F20,DQ_Scale!$A$5:$A$14,0)),"")) -> 3 | H20: PR-12, PR-40 | I20: 0.41 | J20: not_reviewed | K20: =IF(J20="","",IFERROR(INDEX(DQ_Scale!$B$5:$B$14,MATCH(J20,DQ_Scale!$A$5:$A$14,0)),"")) -> 2 | M20: 0.0951 (levies only) | N20: partly_verified | O20: =IF(N20="","",IFERROR(INDEX(DQ_Scale!$B$5:$B$14,MATCH(N20,DQ_Scale!$A$5:$A$14,0)),"")) -> 3 | P20: C-12 | Q20: OECD 0.55; South Africa 0.20-0.25
A21: Rate intensity | B21: I2 | C21: Petrol: excise as % of pump price | D21: % | E21: 16% | F21: partly_verified | G21: =IF(F21="","",IFERROR(INDEX(DQ_Scale!$B$5:$B$14,MATCH(F21,DQ_Scale!$A$5:$A$14,0)),"")) -> 3 | H21: PR-42 | I21: 30% | J21: not_reviewed | K21: =IF(J21="","",IFERROR(INDEX(DQ_Scale!$B$5:$B$14,MATCH(J21,DQ_Scale!$A$5:$A$14,0)),"")) -> 2 | M21: 7.29% (June 2026 ceiling) | N21: partly_verified | O21: =IF(N21="","",IFERROR(INDEX(DQ_Scale!$B$5:$B$14,MATCH(N21,DQ_Scale!$A$5:$A$14,0)),"")) -> 3 | P21: C-13 | Q21: OECD 30-50%
A22: Rate intensity | B22: I3 | C22: Diesel: USD per liter / % of pump price | D22: USD/l; % | E22: 0.23 / 18% (pre-increase price) | F22: not_verified | G22: =IF(F22="","",IFERROR(INDEX(DQ_Scale!$B$5:$B$14,MATCH(F22,DQ_Scale!$A$5:$A$14,0)),"")) -> 2 | H22: PR-43 | I22: 0.33 / 24% | J22: not_reviewed | K22: =IF(J22="","",IFERROR(INDEX(DQ_Scale!$B$5:$B$14,MATCH(J22,DQ_Scale!$A$5:$A$14,0)),"")) -> 2 | M22: 0.0951 / 5.76% | N22: partly_verified | O22: =IF(N22="","",IFERROR(INDEX(DQ_Scale!$B$5:$B$14,MATCH(N22,DQ_Scale!$A$5:$A$14,0)),"")) -> 3 | P22: C-12, C-14
A23: Rate intensity | B23: I4 | C23: Cigarettes: USD per pack of 20 | D23: USD/pack | E23: 0.14 | F23: partly_verified | G23: =IF(F23="","",IFERROR(INDEX(DQ_Scale!$B$5:$B$14,MATCH(F23,DQ_Scale!$A$5:$A$14,0)),"")) -> 3 | H23: PR-20 | I23: 0.35-1.07 (4 tiers) | J23: not_reviewed | K23: =IF(J23="","",IFERROR(INDEX(DQ_Scale!$B$5:$B$14,MATCH(J23,DQ_Scale!$A$5:$A$14,0)),"")) -> 2 | M23: 0.50 | N23: verified_open_point | O23: =IF(N23="","",IFERROR(INDEX(DQ_Scale!$B$5:$B$14,MATCH(N23,DQ_Scale!$A$5:$A$14,0)),"")) -> 4 | P23: PR-09, PR-01
A24: Rate intensity | B24: I5 | C24: Cigarettes: excise as % of retail price | D24: % | E24: ~14% | F24: estimate | G24: =IF(F24="","",IFERROR(INDEX(DQ_Scale!$B$5:$B$14,MATCH(F24,DQ_Scale!$A$5:$A$14,0)),"")) -> 2 | H24: WP Table 14 | I24: 30-50% | J24: estimate | K24: =IF(J24="","",IFERROR(INDEX(DQ_Scale!$B$5:$B$14,MATCH(J24,DQ_Scale!$A$5:$A$14,0)),"")) -> 2 | L24: WP Table 14 | M24: 27.2% (at 2022 price) | N24: estimate | O24: =IF(N24="","",IFERROR(INDEX(DQ_Scale!$B$5:$B$14,MATCH(N24,DQ_Scale!$A$5:$A$14,0)),"")) -> 2 | P24: C-16a | Q24: WHO excise >=70%; total tax >=75%
A25: Rate intensity | B25: I6 | C25: Beer: USD per liter of pure alcohol | D25: USD/LPA | E25: 2.3-9.1 (by regime) | F25: verified | G25: =IF(F25="","",IFERROR(INDEX(DQ_Scale!$B$5:$B$14,MATCH(F25,DQ_Scale!$A$5:$A$14,0)),"")) -> 5 | H25: PR-22, PR-26 | I25: 4.8-10.9 (by local content) | J25: not_reviewed | K25: =IF(J25="","",IFERROR(INDEX(DQ_Scale!$B$5:$B$14,MATCH(J25,DQ_Scale!$A$5:$A$14,0)),"")) -> 2 | M25: 20.00 | N25: verified_open_point | O25: =IF(N25="","",IFERROR(INDEX(DQ_Scale!$B$5:$B$14,MATCH(N25,DQ_Scale!$A$5:$A$14,0)),"")) -> 4 | P25: C-19 | Q25: OECD 15-40
A26: Rate intensity | B26: I7 | C26: Spirits: USD per liter of pure alcohol | D26: USD/LPA | E26: 7.5 (FA2023; current not legible) | F26: last_legible | G26: =IF(F26="","",IFERROR(INDEX(DQ_Scale!$B$5:$B$14,MATCH(F26,DQ_Scale!$A$5:$A$14,0)),"")) -> 1 | H26: PR-27 | I26: 1.0 / 1.7 (specific floor) | J26: not_reviewed | K26: =IF(J26="","",IFERROR(INDEX(DQ_Scale!$B$5:$B$14,MATCH(J26,DQ_Scale!$A$5:$A$14,0)),"")) -> 2 | M26: 7.50 | N26: verified_open_point | O26: =IF(N26="","",IFERROR(INDEX(DQ_Scale!$B$5:$B$14,MATCH(N26,DQ_Scale!$A$5:$A$14,0)),"")) -> 4 | P26: C-19 | Q26: OECD 25-50
A27: Rate intensity | B27: I8 | C27: Soft drinks: USD per liter | D27: USD/l | E27: 0.10-0.50 by sugar (FA2023; current not legible) | F27: last_legible | G27: =IF(F27="","",IFERROR(INDEX(DQ_Scale!$B$5:$B$14,MATCH(F27,DQ_Scale!$A$5:$A$14,0)),"")) -> 1 | H27: PR-31 | I27: 0.07 | J27: not_reviewed | K27: =IF(J27="","",IFERROR(INDEX(DQ_Scale!$B$5:$B$14,MATCH(J27,DQ_Scale!$A$5:$A$14,0)),"")) -> 2 | M27: 0.45 flat | N27: verified_open_point | O27: =IF(N27="","",IFERROR(INDEX(DQ_Scale!$B$5:$B$14,MATCH(N27,DQ_Scale!$A$5:$A$14,0)),"")) -> 4 | P27: PR-11 | Q27: UK 0.23-0.30 (sugar-graduated); Mexico ~0.05 (flat)
A28: Rate intensity | B28: I9 | C28: Soft drinks: excise as % of price | D28: % | E28: n/a | F28: data_gap | G28: =IF(F28="","",IFERROR(INDEX(DQ_Scale!$B$5:$B$14,MATCH(F28,DQ_Scale!$A$5:$A$14,0)),"")) -> 1 | I28: ~6-10% | J28: estimate | K28: =IF(J28="","",IFERROR(INDEX(DQ_Scale!$B$5:$B$14,MATCH(J28,DQ_Scale!$A$5:$A$14,0)),"")) -> 2 | L28: WP Table 14 | M28: 43.7% at 2024 price, before pass-through (pre-reform 1.95%) | N28: estimate | O28: =IF(N28="","",IFERROR(INDEX(DQ_Scale!$B$5:$B$14,MATCH(N28,DQ_Scale!$A$5:$A$14,0)),"")) -> 2 | P28: C-39, PR-34
A29: Structure and base | B29: B1 | C29: Fuel use (liters per USD 1,000 of GDP) | D29: l per USD 1,000 | E29: ~69 (petrol + diesel) | F29: estimate | G29: =IF(F29="","",IFERROR(INDEX(DQ_Scale!$B$5:$B$14,MATCH(F29,DQ_Scale!$A$5:$A$14,0)),"")) -> 2 | H29: WP Table 7 | I29: ~35 (petrol + diesel) | J29: estimate | K29: =IF(J29="","",IFERROR(INDEX(DQ_Scale!$B$5:$B$14,MATCH(J29,DQ_Scale!$A$5:$A$14,0)),"")) -> 2 | L29: WP Table 7 | M29: ~122 (all petroleum, 2024) | N29: estimate | O29: =IF(N29="","",IFERROR(INDEX(DQ_Scale!$B$5:$B$14,MATCH(N29,DQ_Scale!$A$5:$A$14,0)),"")) -> 2 | P29: P-13 | R29: LBR includes all petroleum products; not comparable
A30: Structure and base | B30: B2 | C30: Standard lines covered (of 30) | D30: count | E30: =Std_Schedule!F41 -> 25 | F30: partly_verified | G30: =IF(F30="","",IFERROR(INDEX(DQ_Scale!$B$5:$B$14,MATCH(F30,DQ_Scale!$A$5:$A$14,0)),"")) -> 3 | H30: Std_Schedule | I30: =Std_Schedule!L41 -> 26 | J30: not_reviewed | K30: =IF(J30="","",IFERROR(INDEX(DQ_Scale!$B$5:$B$14,MATCH(J30,DQ_Scale!$A$5:$A$14,0)),"")) -> 2 | L30: Std_Schedule | M30: =Std_Schedule!R41 -> 21 | N30: verified_open_point | O30: =IF(N30="","",IFERROR(INDEX(DQ_Scale!$B$5:$B$14,MATCH(N30,DQ_Scale!$A$5:$A$14,0)),"")) -> 4 | P30: Std_Schedule | R30: Formula: covered (1 + 2) from Std_Schedule
A31: Structure and base | B31: B3 | C31: Specific rates indexed to inflation | D31: yes/no | E31: None | F31: partly_verified | G31: =IF(F31="","",IFERROR(INDEX(DQ_Scale!$B$5:$B$14,MATCH(F31,DQ_Scale!$A$5:$A$14,0)),"")) -> 3 | H31: WP Table 7 | I31: None | J31: not_reviewed | K31: =IF(J31="","",IFERROR(INDEX(DQ_Scale!$B$5:$B$14,MATCH(J31,DQ_Scale!$A$5:$A$14,0)),"")) -> 2 | L31: WP Table 7 | M31: Legislated from 1 Jan 2027 (s.1108(e)); first rates due 1 Dec 2026 | N31: verified | O31: =IF(N31="","",IFERROR(INDEX(DQ_Scale!$B$5:$B$14,MATCH(N31,DQ_Scale!$A$5:$A$14,0)),"")) -> 5 | P31: PR-04
A32: Structure and base | B32: B4 | C32: Differentiation by origin | D32: text | E32: Beer and wine 50-140% higher if imported; juice origin-neutral | F32: verified | G32: =IF(F32="","",IFERROR(INDEX(DQ_Scale!$B$5:$B$14,MATCH(F32,DQ_Scale!$A$5:$A$14,0)),"")) -> 5 | H32: PR-22, PR-24, PR-30 | I32: Cigarettes ~2x if imported; beer, spirits, wine by local raw material | J32: not_reviewed | K32: =IF(J32="","",IFERROR(INDEX(DQ_Scale!$B$5:$B$14,MATCH(J32,DQ_Scale!$A$5:$A$14,0)),"")) -> 2 | M32: Removed April 2026 except water (imported US$0.15/l; local nil) | N32: verified_open_point | O32: =IF(N32="","",IFERROR(INDEX(DQ_Scale!$B$5:$B$14,MATCH(N32,DQ_Scale!$A$5:$A$14,0)),"")) -> 4 | P32: PR-01, PR-11
A33: Structure and base | B33: B5 | C33: Excise-like levies outside excise law | D33: text | E33: Vehicle circulation levy; cellular surcharge (voice, data, mobile money) | F33: partly_verified | G33: =IF(F33="","",IFERROR(INDEX(DQ_Scale!$B$5:$B$14,MATCH(F33,DQ_Scale!$A$5:$A$14,0)),"")) -> 3 | H33: PR-15, PR-36, PR-37 | I33: None: telecoms and financial lines inside the Excise Duty Act | J33: not_reviewed | K33: =IF(J33="","",IFERROR(INDEX(DQ_Scale!$B$5:$B$14,MATCH(J33,DQ_Scale!$A$5:$A$14,0)),"")) -> 2 | M33: Road Fund and LPRC fuel levies; vehicle registration; telecom 5% surtax | N33: partly_verified | O33: =IF(N33="","",IFERROR(INDEX(DQ_Scale!$B$5:$B$14,MATCH(N33,DQ_Scale!$A$5:$A$14,0)),"")) -> 3 | P33: PR-23, PR-24, PR-06
A34: Key questions | B34: Q1 | C34: Coverage: what is taxed; which priority categories are absent? | D34: text | E34: 25 of 30 (21 in Excise Act, 4 levies). Absent: aviation fuel, first registration, traditional beer, sugar, luxury | F34: partly_verified | G34: =IF(F34="","",IFERROR(INDEX(DQ_Scale!$B$5:$B$14,MATCH(F34,DQ_Scale!$A$5:$A$14,0)),"")) -> 3 | H34: WP s.9.1 | I34: 26 of 30, all in the Excise Duty Act. Absent: vehicle circulation, e-cigarettes, gambling, other industrial inputs | J34: not_reviewed | K34: =IF(J34="","",IFERROR(INDEX(DQ_Scale!$B$5:$B$14,MATCH(J34,DQ_Scale!$A$5:$A$14,0)),"")) -> 2 | L34: WP s.9.1 | M34: 21 of 30 (16 in excise law incl. 2 partial; 5 levies). Fuel, plastics, mobile money, cement, edible oils outside excise law; aviation fuel exempt | N34: verified_open_point | O34: =IF(N34="","",IFERROR(INDEX(DQ_Scale!$B$5:$B$14,MATCH(N34,DQ_Scale!$A$5:$A$14,0)),"")) -> 4 | P34: v0.3 Table 9.1
A35: Key questions | B35: Q2 | C35: Structure: specific, ad valorem or hybrid; how differentiated? | D35: text | E35: Mostly specific in NLe; ad valorem local-content beer bands and industrial lines; sugar-graduated SSB design (FA2023); ABV bands | F35: partly_verified | G35: =IF(F35="","",IFERROR(INDEX(DQ_Scale!$B$5:$B$14,MATCH(F35,DQ_Scale!$A$5:$A$14,0)),"")) -> 3 | H35: WP s.9.3 | I35: 'Higher-of' hybrids for alcohol and beverages; specific fuel and cigarettes (4 tiers); ad valorem other tobacco, telecoms, finance, luxury | J35: not_reviewed | K35: =IF(J35="","",IFERROR(INDEX(DQ_Scale!$B$5:$B$14,MATCH(J35,DQ_Scale!$A$5:$A$14,0)),"")) -> 2 | L35: WP s.9.3 | M35: Specific for all beverages and tobacco, one rate for local and imported (except water); ad valorem 5-50% for luxury, sugar, gaming, pipes; fuel via levies only | N35: verified_open_point | O35: =IF(N35="","",IFERROR(INDEX(DQ_Scale!$B$5:$B$14,MATCH(N35,DQ_Scale!$A$5:$A$14,0)),"")) -> 4 | P35: v0.3 s.10
A36: Key questions | B36: Q3 | C36: Intensity: USD per unit, share of price, share of GDP | D36: text | E36: Fuel 55-69% of Uganda per liter; cigarettes 13-39% of Uganda; mainstream beer near parity; SSBs at or above peers on paper | F36: partly_verified | G36: =IF(F36="","",IFERROR(INDEX(DQ_Scale!$B$5:$B$14,MATCH(F36,DQ_Scale!$A$5:$A$14,0)),"")) -> 3 | H36: WP s.8.1 | I36: Petrol USD 0.41/l (30%); cigarettes USD 0.35-1.07/pack (30-50%); malt beer USD 10.9/LPA | J36: not_reviewed | K36: =IF(J36="","",IFERROR(INDEX(DQ_Scale!$B$5:$B$14,MATCH(J36,DQ_Scale!$A$5:$A$14,0)),"")) -> 2 | L36: WP s.8.1 | M36: Fuel levies USD 0.0951/l (7.29%); cigarettes USD 0.50/pack (27.2%); beer USD 20/LPA; spirits USD 7.5/LPA; SSBs USD 0.45/l | N36: partly_verified | O36: =IF(N36="","",IFERROR(INDEX(DQ_Scale!$B$5:$B$14,MATCH(N36,DQ_Scale!$A$5:$A$14,0)),"")) -> 3 | P36: v0.3 s.8.1
A37: Key questions | B37: Q4 | C37: Benchmarking against peers and reference levels | D37: text | E37: Below OECD on fuel, tobacco, alcohol; fuel revenue near OECD floor on a large base; total excise about half the African average | F37: partly_verified | G37: =IF(F37="","",IFERROR(INDEX(DQ_Scale!$B$5:$B$14,MATCH(F37,DQ_Scale!$A$5:$A$14,0)),"")) -> 3 | H37: WP s.8.4 | I37: Below OECD on fuel, tobacco, alcohol; cigarettes 30-50% of price vs WHO 70% | J37: not_reviewed | K37: =IF(J37="","",IFERROR(INDEX(DQ_Scale!$B$5:$B$14,MATCH(J37,DQ_Scale!$A$5:$A$14,0)),"")) -> 2 | L37: WP s.8.4 | M37: Excise 15.5% of African average; fuel 17.3% of OECD per liter; cigarettes 38.9% of WHO benchmark; beer in OECD range; spirits far below; SSBs above UK top band | N37: partly_verified | O37: =IF(N37="","",IFERROR(INDEX(DQ_Scale!$B$5:$B$14,MATCH(N37,DQ_Scale!$A$5:$A$14,0)),"")) -> 3 | P37: v0.3 s.8.4
A38: Key questions | B38: Q5 | C38: Erosion: which specific rates lose real value? | D38: text | E38: No indexation. 2024 switch from US$ to Leone rates cut beer ~70% and wine 70-90% in USD; FA2026 catch-up (fuel +79-147%, cigarettes +50%) | F38: partly_verified | G38: =IF(F38="","",IFERROR(INDEX(DQ_Scale!$B$5:$B$14,MATCH(F38,DQ_Scale!$A$5:$A$14,0)),"")) -> 3 | H38: WP Table 8 #10 | I38: No indexation. Tobacco unchanged FY2017/18-FY2024/25 then up to +100%; kerosene unchanged since 2018 | J38: not_reviewed | K38: =IF(J38="","",IFERROR(INDEX(DQ_Scale!$B$5:$B$14,MATCH(J38,DQ_Scale!$A$5:$A$14,0)),"")) -> 2 | L38: WP Table 8 #10 | M38: Rates in US$ (no LRD erosion); indexation from 1 Jan 2027. Alcohol rates swung twice in 16 months (local spirits 2.00 -> 0.50 -> 3.00) | N38: verified | O38: =IF(N38="","",IFERROR(INDEX(DQ_Scale!$B$5:$B$14,MATCH(N38,DQ_Scale!$A$5:$A$14,0)),"")) -> 5 | P38: PR-04, Table 10.3
A39: Key questions | B39: Q6 | C39: Coherence: where do differentiation devices stack into inversions or arbitrage? | D39: text | E39: Two beer regimes (1.3-4x gap by classification); wine below beer per LPA; origin gaps; kerosene 40% of diesel; three currency notations | F39: corrected | G39: =IF(F39="","",IFERROR(INDEX(DQ_Scale!$B$5:$B$14,MATCH(F39,DQ_Scale!$A$5:$A$14,0)),"")) -> 4 | H39: WP Table 8 | I39: Origin tiers on cigarettes (imported ~2x); local-content tiers on beer; kerosene 16% of diesel | J39: not_reviewed | K39: =IF(J39="","",IFERROR(INDEX(DQ_Scale!$B$5:$B$14,MATCH(J39,DQ_Scale!$A$5:$A$14,0)),"")) -> 2 | L39: WP Table 8 | M39: Spirits 0.375x beer per LPA; water excluded by s.1106(a) yet taxed; SSB flat with no sugar link; 'Current/Proposed' schedule; telecom 18% vs 15%; fuel outside law | N39: verified_open_point | O39: =IF(N39="","",IFERROR(INDEX(DQ_Scale!$B$5:$B$14,MATCH(N39,DQ_Scale!$A$5:$A$14,0)),"")) -> 4 | P39: v0.3 Table 8.3
A40: Key questions | B40: Q7 | C40: Price tracking: tax-inclusive prices vs CPI and incomes | D40: text | E40: Not answered: no retail price series | F40: data_gap | G40: =IF(F40="","",IFERROR(INDEX(DQ_Scale!$B$5:$B$14,MATCH(F40,DQ_Scale!$A$5:$A$14,0)),"")) -> 1 | I40: Not answered | J40: data_gap | K40: =IF(J40="","",IFERROR(INDEX(DQ_Scale!$B$5:$B$14,MATCH(J40,DQ_Scale!$A$5:$A$14,0)),"")) -> 1 | M40: Not answered: no retail price series | N40: data_gap | O40: =IF(N40="","",IFERROR(INDEX(DQ_Scale!$B$5:$B$14,MATCH(N40,DQ_Scale!$A$5:$A$14,0)),"")) -> 1
A41: Open items | B41: O1 | C41: Main open items | D41: text | E41: Publish legible FA2024 s.4(d)-(i) tables; confirm spirits and SSB rates; line-level NRA collections; configure import excise in ASYCUDA | G41: =IF(F41="","",IFERROR(INDEX(DQ_Scale!$B$5:$B$14,MATCH(F41,DQ_Scale!$A$5:$A$14,0)),"")) | H41: WP s.8.5 | I41: Peer review all lines (stage A5); obtain collections; track the 2026 Bill | K41: =IF(J41="","",IFERROR(INDEX(DQ_Scale!$B$5:$B$14,MATCH(J41,DQ_Scale!$A$5:$A$14,0)),"")) | L41: WP note v0.8 | M41: Confirm 'Proposed' rates in force; telecom rate; indexation formula and first rates; where tobacco excise is booked; split the Road Fund line | O41: =IF(N41="","",IFERROR(INDEX(DQ_Scale!$B$5:$B$14,MATCH(N41,DQ_Scale!$A$5:$A$14,0)),"")) | P41: v0.3 Annex B

Sheet Std_Schedule
A1: Standardized cross-country excise schedule (standard schedule v1.0): human-readable
A2: Coverage: 1 = in excise law; 2 = levy outside excise law; 0 = not covered. DQ = lowest DQ among the country's national lines on that row (formula from Std_Schedule_Code).
F4: Sierra Leone (WP v0.8; cut-off 27 Apr 2026) | L4: Uganda (WP v0.8; cut-off 27 Apr 2026; not peer reviewed) | R4: Liberia (v0.3; cut-off 29 Sep 2026)
A5: Part | B5: Typology | C5: Code | D5: Standard line | E5: Standard unit | F5: SLE: Cov. | G5: SLE: Statutory rate and structure | H5: SLE: USD per std unit | I5: SLE: % of price | J5: SLE: DQ | K5: SLE: Ref. / note | L5: UGA: Cov. | M5: UGA: Statutory rate and structure | N5: UGA: USD per std unit | O5: UGA: % of price | P5: UGA: DQ | Q5: UGA: Ref. / note | R5: LBR: Cov. | S5: LBR: Statutory rate and structure | T5: LBR: USD per std unit | U5: LBR: % of price | V5: LBR: DQ | W5: LBR: Ref. / note | X5: Cross-country note
A6: 1 Fuel | B6: energy_environment | C6: E1 | D6: Petrol | E6: per liter | F6: 1 | G6: NLe 5.00/l; specific | H6: 0.23 | I6: 16% | J6: =IF(COUNTIFS(Std_Schedule_Code!$B$5:$B$191,"SLE",Std_Schedule_Code!$G$5:$G$191,$C6)=0,"",_xlfn.MINIFS(Std_Schedule_Code!$AO$5:$AO$191,Std_Schedule_Code!$B$5:$B$191,"SLE",Std_Schedule_Code!$G$5:$G$191,$C6)) -> 3 | K6: PR-12 | L6: 1 | M6: UGX 1,550/l; specific | N6: 0.41 | O6: 30% | P6: =IF(COUNTIFS(Std_Schedule_Code!$B$5:$B$191,"UGA",Std_Schedule_Code!$G$5:$G$191,$C6)=0,"",_xlfn.MINIFS(Std_Schedule_Code!$AO$5:$AO$191,Std_Schedule_Code!$B$5:$B$191,"UGA",Std_Schedule_Code!$G$5:$G$191,$C6)) -> 2 | R6: 2 | S6: US$0.25/gal + US$0.11/gal (Levy) | T6: 0.0951 (to 0.1083) | U6: 7.29% of June 2026 ceiling | V6: =IF(COUNTIFS(Std_Schedule_Code!$B$5:$B$191,"LBR",Std_Schedule_Code!$G$5:$G$191,$C6)=0,"",_xlfn.MINIFS(Std_Schedule_Code!$AO$5:$AO$191,Std_Schedule_Code!$B$5:$B$191,"LBR",Std_Schedule_Code!$G$5:$G$191,$C6)) -> 3 | W6: PR-23, PR-24, PR-25 | X6: Liberia: fuel outside excise law; only earmarked levies.
A7: 1 Fuel | B7: energy_environment | C7: E2 | D7: Diesel, road | E7: per liter | F7: 1 | G7: NLe 5.00/l; specific; harmonized with petrol in FA2026 | H7: 0.23 | I7: 18% (pre-increase price) | J7: =IF(COUNTIFS(Std_Schedule_Code!$B$5:$B$191,"SLE",Std_Schedule_Code!$G$5:$G$191,$C7)=0,"",_xlfn.MINIFS(Std_Schedule_Code!$AO$5:$AO$191,Std_Schedule_Code!$B$5:$B$191,"SLE",Std_Schedule_Code!$G$5:$G$191,$C7)) -> 3 | K7: PR-12 | L7: 1 | M7: UGX 1,230/l; specific; nil for power generation | N7: 0.33 | O7: 24% | P7: =IF(COUNTIFS(Std_Schedule_Code!$B$5:$B$191,"UGA",Std_Schedule_Code!$G$5:$G$191,$C7)=0,"",_xlfn.MINIFS(Std_Schedule_Code!$AO$5:$AO$191,Std_Schedule_Code!$B$5:$B$191,"UGA",Std_Schedule_Code!$G$5:$G$191,$C7)) -> 2 | Q7: Diesel 21% below petrol | R7: 2 | S7: US$0.25/gal + US$0.11/gal (Levy) | T7: 0.0951 (to 0.1083) | U7: 5.76% of June 2026 ceiling | V7: =IF(COUNTIFS(Std_Schedule_Code!$B$5:$B$191,"LBR",Std_Schedule_Code!$G$5:$G$191,$C7)=0,"",_xlfn.MINIFS(Std_Schedule_Code!$AO$5:$AO$191,Std_Schedule_Code!$B$5:$B$191,"LBR",Std_Schedule_Code!$G$5:$G$191,$C7)) -> 3 | W7: PR-23, PR-24, PR-25
A8: 1 Fuel | B8: energy_environment | C8: E3 | D8: Kerosene | E8: per liter | F8: 1 | G8: NLe 2.00/l; specific | H8: 0.09 | I8: 8% | J8: =IF(COUNTIFS(Std_Schedule_Code!$B$5:$B$191,"SLE",Std_Schedule_Code!$G$5:$G$191,$C8)=0,"",_xlfn.MINIFS(Std_Schedule_Code!$AO$5:$AO$191,Std_Schedule_Code!$B$5:$B$191,"SLE",Std_Schedule_Code!$G$5:$G$191,$C8)) -> 2 | K8: PR-13 | L8: 1 | M8: UGX 200/l; specific | N8: 0.05 | O8: <5% | P8: =IF(COUNTIFS(Std_Schedule_Code!$B$5:$B$191,"UGA",Std_Schedule_Code!$G$5:$G$191,$C8)=0,"",_xlfn.MINIFS(Std_Schedule_Code!$AO$5:$AO$191,Std_Schedule_Code!$B$5:$B$191,"UGA",Std_Schedule_Code!$G$5:$G$191,$C8)) -> 2 | R8: 0 | S8: Not identified (confirm): Product scope of fuel levies not verified | T8: - | U8: - | V8: =IF(COUNTIFS(Std_Schedule_Code!$B$5:$B$191,"LBR",Std_Schedule_Code!$G$5:$G$191,$C8)=0,"",_xlfn.MINIFS(Std_Schedule_Code!$AO$5:$AO$191,Std_Schedule_Code!$B$5:$B$191,"LBR",Std_Schedule_Code!$G$5:$G$191,$C8)) -> 2 | W8: PR-24
A9: 1 Fuel | B9: energy_environment | C9: E4 | D9: Aviation fuel | E9: per liter | F9: 0 | G9: Not identified | H9: - | I9: - | J9: =IF(COUNTIFS(Std_Schedule_Code!$B$5:$B$191,"SLE",Std_Schedule_Code!$G$5:$G$191,$C9)=0,"",_xlfn.MINIFS(Std_Schedule_Code!$AO$5:$AO$191,Std_Schedule_Code!$B$5:$B$191,"SLE",Std_Schedule_Code!$G$5:$G$191,$C9)) -> 2 | L9: 1 | M9: UGX 630/l; nil for registered airlines | N9: 0.17 | O9: n/a | P9: =IF(COUNTIFS(Std_Schedule_Code!$B$5:$B$191,"UGA",Std_Schedule_Code!$G$5:$G$191,$C9)=0,"",_xlfn.MINIFS(Std_Schedule_Code!$AO$5:$AO$191,Std_Schedule_Code!$B$5:$B$191,"UGA",Std_Schedule_Code!$G$5:$G$191,$C9)) -> 2 | R9: 0 | S9: Not excisable: s.1107(a): aviation fuel exempt from excise | T9: - | U9: - | V9: =IF(COUNTIFS(Std_Schedule_Code!$B$5:$B$191,"LBR",Std_Schedule_Code!$G$5:$G$191,$C9)=0,"",_xlfn.MINIFS(Std_Schedule_Code!$AO$5:$AO$191,Std_Schedule_Code!$B$5:$B$191,"LBR",Std_Schedule_Code!$G$5:$G$191,$C9)) -> 4 | W9: PR-15
A10: 1 Fuel | B10: energy_environment | C10: E5 | D10: Heavy fuel oil / other gas oils | E10: per liter | F10: 1 | G10: NLe 7.40/l (fuel oil); specific | H10: 0.34 | I10: n/a | J10: =IF(COUNTIFS(Std_Schedule_Code!$B$5:$B$191,"SLE",Std_Schedule_Code!$G$5:$G$191,$C10)=0,"",_xlfn.MINIFS(Std_Schedule_Code!$AO$5:$AO$191,Std_Schedule_Code!$B$5:$B$191,"SLE",Std_Schedule_Code!$G$5:$G$191,$C10)) -> 2 | K10: PR-13 | L10: 1 | M10: UGX 630/l (other gas oils); specific | N10: 0.17 | O10: n/a | P10: =IF(COUNTIFS(Std_Schedule_Code!$B$5:$B$191,"UGA",Std_Schedule_Code!$G$5:$G$191,$C10)=0,"",_xlfn.MINIFS(Std_Schedule_Code!$AO$5:$AO$191,Std_Schedule_Code!$B$5:$B$191,"UGA",Std_Schedule_Code!$G$5:$G$191,$C10)) -> 2 | Q10: Definitions differ | R10: 0 | S10: Not identified (confirm): As E3 | T10: - | U10: - | V10: =IF(COUNTIFS(Std_Schedule_Code!$B$5:$B$191,"LBR",Std_Schedule_Code!$G$5:$G$191,$C10)=0,"",_xlfn.MINIFS(Std_Schedule_Code!$AO$5:$AO$191,Std_Schedule_Code!$B$5:$B$191,"LBR",Std_Schedule_Code!$G$5:$G$191,$C10)) -> 2 | W10: PR-24
A11: 1 Fuel | B11: energy_environment | C11: E6 | D11: Lubricants | E11: per liter | F11: 1 | G11: NLe 4.00/l; specific | H11: 0.18 | I11: n/a | J11: =IF(COUNTIFS(Std_Schedule_Code!$B$5:$B$191,"SLE",Std_Schedule_Code!$G$5:$G$191,$C11)=0,"",_xlfn.MINIFS(Std_Schedule_Code!$AO$5:$AO$191,Std_Schedule_Code!$B$5:$B$191,"SLE",Std_Schedule_Code!$G$5:$G$191,$C11)) -> 2 | K11: PR-13 | L11: 1 | M11: 15% ad valorem (motor vehicle, not aircraft) | N11: - | O11: 15% of value | P11: =IF(COUNTIFS(Std_Schedule_Code!$B$5:$B$191,"UGA",Std_Schedule_Code!$G$5:$G$191,$C11)=0,"",_xlfn.MINIFS(Std_Schedule_Code!$AO$5:$AO$191,Std_Schedule_Code!$B$5:$B$191,"UGA",Std_Schedule_Code!$G$5:$G$191,$C11)) -> 2 | R11: 0 | S11: Not excisable: Not in s.1106 | T11: - | U11: - | V11: =IF(COUNTIFS(Std_Schedule_Code!$B$5:$B$191,"LBR",Std_Schedule_Code!$G$5:$G$191,$C11)=0,"",_xlfn.MINIFS(Std_Schedule_Code!$AO$5:$AO$191,Std_Schedule_Code!$B$5:$B$191,"LBR",Std_Schedule_Code!$G$5:$G$191,$C11)) -> 4 | W11: PR-15
A12: 4 Other | B12: energy_environment | C12: E7 | D12: Plastic bags and packaging | E12: per kg | F12: 1 | G12: Le 16/kg: bags; bottles filled with beverages other than water | H12: 0.73 | I12: n/a | J12: =IF(COUNTIFS(Std_Schedule_Code!$B$5:$B$191,"SLE",Std_Schedule_Code!$G$5:$G$191,$C12)=0,"",_xlfn.MINIFS(Std_Schedule_Code!$AO$5:$AO$191,Std_Schedule_Code!$B$5:$B$191,"SLE",Std_Schedule_Code!$G$5:$G$191,$C12)) -> 5 | K12: PR-14 | L12: 1 | M12: UGX 10,000/kg (bags); granules 2.5% or USD 70/t | N12: 2.67 | O12: n/a | P12: =IF(COUNTIFS(Std_Schedule_Code!$B$5:$B$191,"UGA",Std_Schedule_Code!$G$5:$G$191,$C12)=0,"",_xlfn.MINIFS(Std_Schedule_Code!$AO$5:$AO$191,Std_Schedule_Code!$B$5:$B$191,"UGA",Std_Schedule_Code!$G$5:$G$191,$C12)) -> 2 | R12: 0 | S12: Not excisable: Not in s.1106 | T12: - | U12: - | V12: =IF(COUNTIFS(Std_Schedule_Code!$B$5:$B$191,"LBR",Std_Schedule_Code!$G$5:$G$191,$C12)=0,"",_xlfn.MINIFS(Std_Schedule_Code!$AO$5:$AO$191,Std_Schedule_Code!$B$5:$B$191,"LBR",Std_Schedule_Code!$G$5:$G$191,$C12)) -> 4 | W12: PR-15
A13: 2 Vehicles | B13: energy_environment | C13: E8 | D13: Vehicles: annual circulation | E13: per vehicle-year | F13: 2 | G13: NLe 500 (cars, trucks, buses); NLe 200 (motorbikes). Levy outside the Excise Act | H13: 23 / 9 | I13: n/a | J13: =IF(COUNTIFS(Std_Schedule_Code!$B$5:$B$191,"SLE",Std_Schedule_Code!$G$5:$G$191,$C13)=0,"",_xlfn.MINIFS(Std_Schedule_Code!$AO$5:$AO$191,Std_Schedule_Code!$B$5:$B$191,"SLE",Std_Schedule_Code!$G$5:$G$191,$C13)) -> 2 | K13: PR-15, PR-16 | L13: 0 | M13: Not in excise schedule | N13: - | O13: - | P13: =IF(COUNTIFS(Std_Schedule_Code!$B$5:$B$191,"UGA",Std_Schedule_Code!$G$5:$G$191,$C13)=0,"",_xlfn.MINIFS(Std_Schedule_Code!$AO$5:$AO$191,Std_Schedule_Code!$B$5:$B$191,"UGA",Std_Schedule_Code!$G$5:$G$191,$C13)) -> 2 | R13: 2 | S13: US$75 (compact car) to US$500 (heavy truck) base (Levy) | T13: 75-500 | U13: - | V13: =IF(COUNTIFS(Std_Schedule_Code!$B$5:$B$191,"LBR",Std_Schedule_Code!$G$5:$G$191,$C13)=0,"",_xlfn.MINIFS(Std_Schedule_Code!$AO$5:$AO$191,Std_Schedule_Code!$B$5:$B$191,"LBR",Std_Schedule_Code!$G$5:$G$191,$C13)) -> 2 | W13: PR-27, PR-38
A14: 2 Vehicles | B14: energy_environment | C14: E9 | D14: Vehicles: first registration / import | E14: per vehicle | F14: 0 | G14: Not in excise schedule | H14: - | I14: - | J14: =IF(COUNTIFS(Std_Schedule_Code!$B$5:$B$191,"SLE",Std_Schedule_Code!$G$5:$G$191,$C14)=0,"",_xlfn.MINIFS(Std_Schedule_Code!$AO$5:$AO$191,Std_Schedule_Code!$B$5:$B$191,"SLE",Std_Schedule_Code!$G$5:$G$191,$C14)) -> 2 | L14: 1 | M14: UGX 200,000 (motorcycles); specific | N14: 53 | O14: n/a | P14: =IF(COUNTIFS(Std_Schedule_Code!$B$5:$B$191,"UGA",Std_Schedule_Code!$G$5:$G$191,$C14)=0,"",_xlfn.MINIFS(Std_Schedule_Code!$AO$5:$AO$191,Std_Schedule_Code!$B$5:$B$191,"UGA",Std_Schedule_Code!$G$5:$G$191,$C14)) -> 2 | R14: 1 | S14: 10% (Partial: luxury only) | T14: >= 6,000 new; >= 3,000 used | U14: n/a (no price data) | V14: =IF(COUNTIFS(Std_Schedule_Code!$B$5:$B$191,"LBR",Std_Schedule_Code!$G$5:$G$191,$C14)=0,"",_xlfn.MINIFS(Std_Schedule_Code!$AO$5:$AO$191,Std_Schedule_Code!$B$5:$B$191,"LBR",Std_Schedule_Code!$G$5:$G$191,$C14)) -> 5 | W14: PR-14, PR-49
A15: 3 Health | B15: health | C15: T1 | D15: Cigarettes | E15: per pack of 20 | F15: 1 | G15: NLe 3/pack; single specific rate | H15: 0.14 | I15: ~14% | J15: =IF(COUNTIFS(Std_Schedule_Code!$B$5:$B$191,"SLE",Std_Schedule_Code!$G$5:$G$191,$C15)=0,"",_xlfn.MINIFS(Std_Schedule_Code!$AO$5:$AO$191,Std_Schedule_Code!$B$5:$B$191,"SLE",Std_Schedule_Code!$G$5:$G$191,$C15)) -> 3 | K15: PR-19, PR-20 | L15: 1 | M15: UGX 65,000-200,000 per 1,000 sticks; specific; 4 tiers by origin and pack type | N15: 0.35-1.07 | O15: 30-50% | P15: =IF(COUNTIFS(Std_Schedule_Code!$B$5:$B$191,"UGA",Std_Schedule_Code!$G$5:$G$191,$C15)=0,"",_xlfn.MINIFS(Std_Schedule_Code!$AO$5:$AO$191,Std_Schedule_Code!$B$5:$B$191,"UGA",Std_Schedule_Code!$G$5:$G$191,$C15)) -> 2 | R15: 1 | S15: $0.50 / pack of 20 sticks | T15: 0.50 | U15: 27.2% (at 2022 price) | V15: =IF(COUNTIFS(Std_Schedule_Code!$B$5:$B$191,"LBR",Std_Schedule_Code!$G$5:$G$191,$C15)=0,"",_xlfn.MINIFS(Std_Schedule_Code!$AO$5:$AO$191,Std_Schedule_Code!$B$5:$B$191,"LBR",Std_Schedule_Code!$G$5:$G$191,$C15)) -> 4 | W15: PR-09, PR-10 | X15: Uganda tiers by origin and pack; SLE and LBR single rate.
A16: 3 Health | B16: health | C16: T2 | D16: Cigars and other tobacco | E16: per pack / per kg | F16: 1 | G16: NLe 38/pack (cigars); NLe 98/kg (loose, homogenized); shisha NLe 98/kg + NLe 225/l | H16: 1.73/pack; 4.45/kg | I16: n/a | J16: =IF(COUNTIFS(Std_Schedule_Code!$B$5:$B$191,"SLE",Std_Schedule_Code!$G$5:$G$191,$C16)=0,"",_xlfn.MINIFS(Std_Schedule_Code!$AO$5:$AO$191,Std_Schedule_Code!$B$5:$B$191,"SLE",Std_Schedule_Code!$G$5:$G$191,$C16)) -> 2 | K16: PR-21 | L16: 1 | M16: 200% ad valorem | N16: - | O16: n/a | P16: =IF(COUNTIFS(Std_Schedule_Code!$B$5:$B$191,"UGA",Std_Schedule_Code!$G$5:$G$191,$C16)=0,"",_xlfn.MINIFS(Std_Schedule_Code!$AO$5:$AO$191,Std_Schedule_Code!$B$5:$B$191,"UGA",Std_Schedule_Code!$G$5:$G$191,$C16)) -> 2 | R16: 1 | S16: $0.50/pack; $0.25/stick; $25.00/Kg; 50% | T16: 0.50; 0.25/stick; 25.00/kg | U16: n/a (no price data) | V16: =IF(COUNTIFS(Std_Schedule_Code!$B$5:$B$191,"LBR",Std_Schedule_Code!$G$5:$G$191,$C16)=0,"",_xlfn.MINIFS(Std_Schedule_Code!$AO$5:$AO$191,Std_Schedule_Code!$B$5:$B$191,"LBR",Std_Schedule_Code!$G$5:$G$191,$C16)) -> 4 | W16: PR-09, PR-10
A17: 3 Health | B17: health | C17: T3 | D17: E-cigarettes and novel products | E17: per ml / per cartridge | F17: 1 | G17: NLe 0.75/ml (device); NLe 1.20/cartridge | H17: 0.03; 0.05 | I17: n/a | J17: =IF(COUNTIFS(Std_Schedule_Code!$B$5:$B$191,"SLE",Std_Schedule_Code!$G$5:$G$191,$C17)=0,"",_xlfn.MINIFS(Std_Schedule_Code!$AO$5:$AO$191,Std_Schedule_Code!$B$5:$B$191,"SLE",Std_Schedule_Code!$G$5:$G$191,$C17)) -> 2 | K17: PR-18, PR-21 | L17: 0 | M17: Not identified | N17: - | O17: - | P17: =IF(COUNTIFS(Std_Schedule_Code!$B$5:$B$191,"UGA",Std_Schedule_Code!$G$5:$G$191,$C17)=0,"",_xlfn.MINIFS(Std_Schedule_Code!$AO$5:$AO$191,Std_Schedule_Code!$B$5:$B$191,"UGA",Std_Schedule_Code!$G$5:$G$191,$C17)) -> 2 | R17: 1 | S17: $0.10 / mL; $15.00 / Kg | T17: 0.10/ml; 15.00/kg | U17: n/a (no price data) | V17: =IF(COUNTIFS(Std_Schedule_Code!$B$5:$B$191,"LBR",Std_Schedule_Code!$G$5:$G$191,$C17)=0,"",_xlfn.MINIFS(Std_Schedule_Code!$AO$5:$AO$191,Std_Schedule_Code!$B$5:$B$191,"LBR",Std_Schedule_Code!$G$5:$G$191,$C17)) -> 4 | W17: PR-09, PR-10
A18: 3 Health | B18: health | C18: A1 | D18: Beer, mainstream malt (5% ABV) | E18: per LPA | F18: 1 | G18: HS 2203: Le 10/l local; Le 15/l imported (also printed as Le 0.01 / 0.015 per cl); specific | H18: 9.1 / 13.6 | I18: 20% / 30% | J18: =IF(COUNTIFS(Std_Schedule_Code!$B$5:$B$191,"SLE",Std_Schedule_Code!$G$5:$G$191,$C18)=0,"",_xlfn.MINIFS(Std_Schedule_Code!$AO$5:$AO$191,Std_Schedule_Code!$B$5:$B$191,"SLE",Std_Schedule_Code!$G$5:$G$191,$C18)) -> 5 | K18: PR-22 | L18: 1 | M18: 60% or UGX 2,050/l; hybrid | N18: 10.9 | O18: ~29% | P18: =IF(COUNTIFS(Std_Schedule_Code!$B$5:$B$191,"UGA",Std_Schedule_Code!$G$5:$G$191,$C18)=0,"",_xlfn.MINIFS(Std_Schedule_Code!$AO$5:$AO$191,Std_Schedule_Code!$B$5:$B$191,"UGA",Std_Schedule_Code!$G$5:$G$191,$C18)) -> 2 | R18: 1 | S18: $1.00 / L | T18: 20.00 | U18: 36.7% (at 2024 price) | V18: =IF(COUNTIFS(Std_Schedule_Code!$B$5:$B$191,"LBR",Std_Schedule_Code!$G$5:$G$191,$C18)=0,"",_xlfn.MINIFS(Std_Schedule_Code!$AO$5:$AO$191,Std_Schedule_Code!$B$5:$B$191,"LBR",Std_Schedule_Code!$G$5:$G$191,$C18)) -> 4 | W18: PR-01, PR-02, PR-03
A19: 3 Health | B19: health | C19: A2 | D19: Beer, local-content concession (5% ABV) | E19: per LPA | F19: 1 | G19: Item 22.09 bands D1-D4: 5 / 8 / 12 / 15% ad valorem (<10% ABV) | H19: 2.3-6.8 | I19: 5-15% | J19: =IF(COUNTIFS(Std_Schedule_Code!$B$5:$B$191,"SLE",Std_Schedule_Code!$G$5:$G$191,$C19)=0,"",_xlfn.MINIFS(Std_Schedule_Code!$AO$5:$AO$191,Std_Schedule_Code!$B$5:$B$191,"SLE",Std_Schedule_Code!$G$5:$G$191,$C19)) -> 5 | K19: PR-25, PR-26 | L19: 1 | M19: >=75% local: 30% or UGX 900/l; Ugandan barley: 30% or UGX 950/l | N19: 4.8-5.1 | O19: ~13% | P19: =IF(COUNTIFS(Std_Schedule_Code!$B$5:$B$191,"UGA",Std_Schedule_Code!$G$5:$G$191,$C19)=0,"",_xlfn.MINIFS(Std_Schedule_Code!$AO$5:$AO$191,Std_Schedule_Code!$B$5:$B$191,"UGA",Std_Schedule_Code!$G$5:$G$191,$C19)) -> 2 | R19: 1 | S19: $1.00 / L | T19: 20.00 | U19: in A1 | V19: =IF(COUNTIFS(Std_Schedule_Code!$B$5:$B$191,"LBR",Std_Schedule_Code!$G$5:$G$191,$C19)=0,"",_xlfn.MINIFS(Std_Schedule_Code!$AO$5:$AO$191,Std_Schedule_Code!$B$5:$B$191,"LBR",Std_Schedule_Code!$G$5:$G$191,$C19)) -> 4 | W19: PR-01
A20: 3 Health | B20: health | C20: A3 | D20: Traditional / opaque beer (4% ABV) | E20: per LPA | F20: 0 | G20: Not identified (largely informal). HS 2206 cider/perry/mead line exists (FA2023, last legible); see code sheet | H20: - | I20: - | J20: =IF(COUNTIFS(Std_Schedule_Code!$B$5:$B$191,"SLE",Std_Schedule_Code!$G$5:$G$191,$C20)=0,"",_xlfn.MINIFS(Std_Schedule_Code!$AO$5:$AO$191,Std_Schedule_Code!$B$5:$B$191,"SLE",Std_Schedule_Code!$G$5:$G$191,$C20)) -> 1 | L20: 1 | M20: 12% or UGX 150/l; hybrid | N20: 1.0 | O20: ~10% | P20: =IF(COUNTIFS(Std_Schedule_Code!$B$5:$B$191,"UGA",Std_Schedule_Code!$G$5:$G$191,$C20)=0,"",_xlfn.MINIFS(Std_Schedule_Code!$AO$5:$AO$191,Std_Schedule_Code!$B$5:$B$191,"UGA",Std_Schedule_Code!$G$5:$G$191,$C20)) -> 2 | R20: 1 | S20: $1.00 / L | T20: 25.00 | U20: n/a (no price data) | V20: =IF(COUNTIFS(Std_Schedule_Code!$B$5:$B$191,"LBR",Std_Schedule_Code!$G$5:$G$191,$C20)=0,"",_xlfn.MINIFS(Std_Schedule_Code!$AO$5:$AO$191,Std_Schedule_Code!$B$5:$B$191,"LBR",Std_Schedule_Code!$G$5:$G$191,$C20)) -> 4 | W20: PR-01 | X20: Mapping of HS 2206 (cider, perry, mead; palm wine) to A3 differs between WP v0.8 and Liberia v0.3; settle in schedule v1.1.
A21: 3 Health | B21: health | C21: A4 | D21: Wine (12% ABV) | E21: per LPA | F21: 1 | G21: Le 6.30/l local; Le 12/l imported (10-20% ABV band); specific | H21: 2.4 / 4.5 | I21: n/a | J21: =IF(COUNTIFS(Std_Schedule_Code!$B$5:$B$191,"SLE",Std_Schedule_Code!$G$5:$G$191,$C21)=0,"",_xlfn.MINIFS(Std_Schedule_Code!$AO$5:$AO$191,Std_Schedule_Code!$B$5:$B$191,"SLE",Std_Schedule_Code!$G$5:$G$191,$C21)) -> 5 | K21: PR-24 | L21: 1 | M21: Local: 20% or UGX 2,000/l. Other: 80% or UGX 8,000/l | N21: 4.4 / 17.8 | O21: n/a | P21: =IF(COUNTIFS(Std_Schedule_Code!$B$5:$B$191,"UGA",Std_Schedule_Code!$G$5:$G$191,$C21)=0,"",_xlfn.MINIFS(Std_Schedule_Code!$AO$5:$AO$191,Std_Schedule_Code!$B$5:$B$191,"UGA",Std_Schedule_Code!$G$5:$G$191,$C21)) -> 2 | R21: 1 | S21: $1.00 / L | T21: 8.33 | U21: n/a (no price data) | V21: =IF(COUNTIFS(Std_Schedule_Code!$B$5:$B$191,"LBR",Std_Schedule_Code!$G$5:$G$191,$C21)=0,"",_xlfn.MINIFS(Std_Schedule_Code!$AO$5:$AO$191,Std_Schedule_Code!$B$5:$B$191,"LBR",Std_Schedule_Code!$G$5:$G$191,$C21)) -> 4 | W21: PR-01
A22: 3 Health | B22: health | C22: A5 | D22: Spirits (40% ABV) | E22: per LPA | F22: 1 | G22: HS 2208: specific. FA2023: US$3/l (>20% ABV); replaced by FA2024 s.4(e), rate not legible | H22: 7.5 (FA2023 rate) | I22: n/a | J22: =IF(COUNTIFS(Std_Schedule_Code!$B$5:$B$191,"SLE",Std_Schedule_Code!$G$5:$G$191,$C22)=0,"",_xlfn.MINIFS(Std_Schedule_Code!$AO$5:$AO$191,Std_Schedule_Code!$B$5:$B$191,"SLE",Std_Schedule_Code!$G$5:$G$191,$C22)) -> 1 | K22: PR-27 | L22: 1 | M22: Local: 60% or UGX 1,500/l. Imported: 100% or UGX 2,500/l. RTD: 80% or UGX 1,700/l | N22: 1.0 / 1.7 (specific floor) | O22: n/a | P22: =IF(COUNTIFS(Std_Schedule_Code!$B$5:$B$191,"UGA",Std_Schedule_Code!$G$5:$G$191,$C22)=0,"",_xlfn.MINIFS(Std_Schedule_Code!$AO$5:$AO$191,Std_Schedule_Code!$B$5:$B$191,"UGA",Std_Schedule_Code!$G$5:$G$191,$C22)) -> 2 | R22: 1 | S22: $3.00 / L | T22: 7.50 | U22: 73.1% (at 2024 price) | V22: =IF(COUNTIFS(Std_Schedule_Code!$B$5:$B$191,"LBR",Std_Schedule_Code!$G$5:$G$191,$C22)=0,"",_xlfn.MINIFS(Std_Schedule_Code!$AO$5:$AO$191,Std_Schedule_Code!$B$5:$B$191,"LBR",Std_Schedule_Code!$G$5:$G$191,$C22)) -> 4 | W22: PR-01, PR-03 | X22: Spirits per LPA below beer in SLE and LBR.
A23: 3 Health | B23: health | C23: S1 | D23: Carbonated and other soft drinks | E23: per liter | F23: 1 | G23: FA2023: US$0.10 / 0.30 / 0.50 per l for <15 / 15-25 / >25 g sugar per l; current rows not legible | H23: 0.10-0.50 | I23: n/a | J23: =IF(COUNTIFS(Std_Schedule_Code!$B$5:$B$191,"SLE",Std_Schedule_Code!$G$5:$G$191,$C23)=0,"",_xlfn.MINIFS(Std_Schedule_Code!$AO$5:$AO$191,Std_Schedule_Code!$B$5:$B$191,"SLE",Std_Schedule_Code!$G$5:$G$191,$C23)) -> 1 | K23: PR-31 | L23: 1 | M23: 12% or UGX 250/l; hybrid | N23: 0.07 | O23: ~6-10% | P23: =IF(COUNTIFS(Std_Schedule_Code!$B$5:$B$191,"UGA",Std_Schedule_Code!$G$5:$G$191,$C23)=0,"",_xlfn.MINIFS(Std_Schedule_Code!$AO$5:$AO$191,Std_Schedule_Code!$B$5:$B$191,"UGA",Std_Schedule_Code!$G$5:$G$191,$C23)) -> 2 | R23: 1 | S23: $0.45 / L | T23: 0.45 | U23: 43.7% (at 2024 price) | V23: =IF(COUNTIFS(Std_Schedule_Code!$B$5:$B$191,"LBR",Std_Schedule_Code!$G$5:$G$191,$C23)=0,"",_xlfn.MINIFS(Std_Schedule_Code!$AO$5:$AO$191,Std_Schedule_Code!$B$5:$B$191,"LBR",Std_Schedule_Code!$G$5:$G$191,$C23)) -> 4 | W23: PR-11, PR-12 | X23: SLE sugar-graduated (FA2023); UGA hybrid flat; LBR flat per liter.
A24: 3 Health | B24: health | C24: S2 | D24: Fruit and vegetable juice | E24: per liter | F24: 1 | G24: FA2023: US$0 (<5 g/l); 0.10 (5-15); 0.30 (15-25); 0.50 (>25) per l; origin-neutral | H24: 0-0.50 | I24: n/a | J24: =IF(COUNTIFS(Std_Schedule_Code!$B$5:$B$191,"SLE",Std_Schedule_Code!$G$5:$G$191,$C24)=0,"",_xlfn.MINIFS(Std_Schedule_Code!$AO$5:$AO$191,Std_Schedule_Code!$B$5:$B$191,"SLE",Std_Schedule_Code!$G$5:$G$191,$C24)) -> 1 | K24: PR-30 | L24: 1 | M24: 12% or UGX 250/l; concession for >=30% Ugandan pulp | N24: 0.07 | O24: ~6-10% | P24: =IF(COUNTIFS(Std_Schedule_Code!$B$5:$B$191,"UGA",Std_Schedule_Code!$G$5:$G$191,$C24)=0,"",_xlfn.MINIFS(Std_Schedule_Code!$AO$5:$AO$191,Std_Schedule_Code!$B$5:$B$191,"UGA",Std_Schedule_Code!$G$5:$G$191,$C24)) -> 2 | R24: 1 | S24: $0.45 / L | T24: 0.45 | U24: n/a (no price data) | V24: =IF(COUNTIFS(Std_Schedule_Code!$B$5:$B$191,"LBR",Std_Schedule_Code!$G$5:$G$191,$C24)=0,"",_xlfn.MINIFS(Std_Schedule_Code!$AO$5:$AO$191,Std_Schedule_Code!$B$5:$B$191,"LBR",Std_Schedule_Code!$G$5:$G$191,$C24)) -> 4 | W24: PR-11, PR-12
A25: 3 Health | B25: health | C25: S3 | D25: Energy drinks | E25: per liter | F25: 1 | G25: Within 'other non-alcoholic beverages' (as S1) | H25: 0.10-0.50 | I25: n/a | J25: =IF(COUNTIFS(Std_Schedule_Code!$B$5:$B$191,"SLE",Std_Schedule_Code!$G$5:$G$191,$C25)=0,"",_xlfn.MINIFS(Std_Schedule_Code!$AO$5:$AO$191,Std_Schedule_Code!$B$5:$B$191,"SLE",Std_Schedule_Code!$G$5:$G$191,$C25)) -> 1 | K25: PR-29 | L25: 1 | M25: Within non-alcoholic beverages: 12% or UGX 250/l | N25: 0.07 | O25: ~6-10% | P25: =IF(COUNTIFS(Std_Schedule_Code!$B$5:$B$191,"UGA",Std_Schedule_Code!$G$5:$G$191,$C25)=0,"",_xlfn.MINIFS(Std_Schedule_Code!$AO$5:$AO$191,Std_Schedule_Code!$B$5:$B$191,"UGA",Std_Schedule_Code!$G$5:$G$191,$C25)) -> 2 | R25: 1 | S25: $0.45 / L | T25: 0.45 | U25: n/a (no price data) | V25: =IF(COUNTIFS(Std_Schedule_Code!$B$5:$B$191,"LBR",Std_Schedule_Code!$G$5:$G$191,$C25)=0,"",_xlfn.MINIFS(Std_Schedule_Code!$AO$5:$AO$191,Std_Schedule_Code!$B$5:$B$191,"LBR",Std_Schedule_Code!$G$5:$G$191,$C25)) -> 4 | W25: PR-11
A26: 3 Health | B26: health | C26: S4 | D26: Bottled and processed water | E26: per liter | F26: 1 | G26: Within 'bottled or similarly packaged waters': US$0.10/l (<15 g/l) | H26: 0.10 | I26: n/a | J26: =IF(COUNTIFS(Std_Schedule_Code!$B$5:$B$191,"SLE",Std_Schedule_Code!$G$5:$G$191,$C26)=0,"",_xlfn.MINIFS(Std_Schedule_Code!$AO$5:$AO$191,Std_Schedule_Code!$B$5:$B$191,"SLE",Std_Schedule_Code!$G$5:$G$191,$C26)) -> 1 | K26: PR-29 | L26: 1 | M26: Hybrid: fixed plus ad valorem | N26: - | O26: - | P26: =IF(COUNTIFS(Std_Schedule_Code!$B$5:$B$191,"UGA",Std_Schedule_Code!$G$5:$G$191,$C26)=0,"",_xlfn.MINIFS(Std_Schedule_Code!$AO$5:$AO$191,Std_Schedule_Code!$B$5:$B$191,"UGA",Std_Schedule_Code!$G$5:$G$191,$C26)) -> 2 | R26: 1 | S26: $0.15 / L imported; NIL local | T26: 0.15 (imported) | U26: n/a (no price data) | V26: =IF(COUNTIFS(Std_Schedule_Code!$B$5:$B$191,"LBR",Std_Schedule_Code!$G$5:$G$191,$C26)=0,"",_xlfn.MINIFS(Std_Schedule_Code!$AO$5:$AO$191,Std_Schedule_Code!$B$5:$B$191,"LBR",Std_Schedule_Code!$G$5:$G$191,$C26)) -> 4 | W26: PR-11, PR-13
A27: 3 Health | B27: health | C27: G1 | D27: Gambling, betting and lotteries | E27: % of base | F27: 1 | G27: 10% of net wagered (gross gaming revenue) | H27: - | I27: - | J27: =IF(COUNTIFS(Std_Schedule_Code!$B$5:$B$191,"SLE",Std_Schedule_Code!$G$5:$G$191,$C27)=0,"",_xlfn.MINIFS(Std_Schedule_Code!$AO$5:$AO$191,Std_Schedule_Code!$B$5:$B$191,"SLE",Std_Schedule_Code!$G$5:$G$191,$C27)) -> 5 | K27: PR-32 | L27: 0 | M27: Not in excise schedule | N27: - | O27: - | P27: =IF(COUNTIFS(Std_Schedule_Code!$B$5:$B$191,"UGA",Std_Schedule_Code!$G$5:$G$191,$C27)=0,"",_xlfn.MINIFS(Std_Schedule_Code!$AO$5:$AO$191,Std_Schedule_Code!$B$5:$B$191,"UGA",Std_Schedule_Code!$G$5:$G$191,$C27)) -> 2 | R27: 1 | S27: 30% (Partial: equipment only) | T27: - | U27: - | V27: =IF(COUNTIFS(Std_Schedule_Code!$B$5:$B$191,"LBR",Std_Schedule_Code!$G$5:$G$191,$C27)=0,"",_xlfn.MINIFS(Std_Schedule_Code!$AO$5:$AO$191,Std_Schedule_Code!$B$5:$B$191,"LBR",Std_Schedule_Code!$G$5:$G$191,$C27)) -> 5 | W27: PR-14, PR-47, PR-49 | X27: Liberia taxes gaming equipment, Sierra Leone net wagered: different bases.
A28: 4 Other | B28: telecoms_digital | C28: D1 | D28: Voice and airtime | E28: per minute / % of fee | F28: 2 | G28: Cellular surcharge (FA2023 s.13): NLe 0.10 on-net; NLe 0.05 off-net; NLe 2 outgoing international | H28: 0.005 (on-net) | I28: - | J28: =IF(COUNTIFS(Std_Schedule_Code!$B$5:$B$191,"SLE",Std_Schedule_Code!$G$5:$G$191,$C28)=0,"",_xlfn.MINIFS(Std_Schedule_Code!$AO$5:$AO$191,Std_Schedule_Code!$B$5:$B$191,"SLE",Std_Schedule_Code!$G$5:$G$191,$C28)) -> 4 | K28: PR-36 | L28: 1 | M28: 12% of airtime fee; USD 0.09/min on incoming international calls (EAC partners excluded) | N28: - | O28: 12% of fee | P28: =IF(COUNTIFS(Std_Schedule_Code!$B$5:$B$191,"UGA",Std_Schedule_Code!$G$5:$G$191,$C28)=0,"",_xlfn.MINIFS(Std_Schedule_Code!$AO$5:$AO$191,Std_Schedule_Code!$B$5:$B$191,"UGA",Std_Schedule_Code!$G$5:$G$191,$C28)) -> 2 | R28: 2 | S28: 13% + 5% surtax (LRA notice: 15%) (Levy) | T28: 5-point surtax | U28: - | V28: =IF(COUNTIFS(Std_Schedule_Code!$B$5:$B$191,"LBR",Std_Schedule_Code!$G$5:$G$191,$C28)=0,"",_xlfn.MINIFS(Std_Schedule_Code!$AO$5:$AO$191,Std_Schedule_Code!$B$5:$B$191,"LBR",Std_Schedule_Code!$G$5:$G$191,$C28)) -> 3 | W28: PR-05, PR-06 | X28: Uganda inside excise law; SLE and LBR levies outside it.
A29: 4 Other | B29: telecoms_digital | C29: D2 | D29: Data and value-added services | E29: % of fee | F29: 2 | G29: Cellular surcharge: up to 5% of data recharge and bundle sales | H29: - | I29: <=5% | J29: =IF(COUNTIFS(Std_Schedule_Code!$B$5:$B$191,"SLE",Std_Schedule_Code!$G$5:$G$191,$C29)=0,"",_xlfn.MINIFS(Std_Schedule_Code!$AO$5:$AO$191,Std_Schedule_Code!$B$5:$B$191,"SLE",Std_Schedule_Code!$G$5:$G$191,$C29)) -> 5 | K29: PR-37 | L29: 1 | M29: 12% of fee (medical and education data exempt); 12% on SMS/MMS | N29: - | O29: 12% of fee | P29: =IF(COUNTIFS(Std_Schedule_Code!$B$5:$B$191,"UGA",Std_Schedule_Code!$G$5:$G$191,$C29)=0,"",_xlfn.MINIFS(Std_Schedule_Code!$AO$5:$AO$191,Std_Schedule_Code!$B$5:$B$191,"UGA",Std_Schedule_Code!$G$5:$G$191,$C29)) -> 2 | R29: 2 | S29: 13% + 5% surtax (LRA notice: 15%) (Levy) | T29: 5-point surtax | U29: - | V29: =IF(COUNTIFS(Std_Schedule_Code!$B$5:$B$191,"LBR",Std_Schedule_Code!$G$5:$G$191,$C29)=0,"",_xlfn.MINIFS(Std_Schedule_Code!$AO$5:$AO$191,Std_Schedule_Code!$B$5:$B$191,"LBR",Std_Schedule_Code!$G$5:$G$191,$C29)) -> 3 | W29: PR-06
A30: 4 Other | B30: financial_transactions | C30: F1 | D30: Mobile money and financial services | E30: % of value or fee | F30: 2 | G30: Cellular surcharge: 2% of mobile-money commissions | H30: - | I30: - | J30: =IF(COUNTIFS(Std_Schedule_Code!$B$5:$B$191,"SLE",Std_Schedule_Code!$G$5:$G$191,$C30)=0,"",_xlfn.MINIFS(Std_Schedule_Code!$AO$5:$AO$191,Std_Schedule_Code!$B$5:$B$191,"SLE",Std_Schedule_Code!$G$5:$G$191,$C30)) -> 5 | K30: PR-37 | L30: 1 | M30: 0.5% of mobile-money and agent withdrawals; 15% of bank fees | N30: - | O30: - | P30: =IF(COUNTIFS(Std_Schedule_Code!$B$5:$B$191,"UGA",Std_Schedule_Code!$G$5:$G$191,$C30)=0,"",_xlfn.MINIFS(Std_Schedule_Code!$AO$5:$AO$191,Std_Schedule_Code!$B$5:$B$191,"UGA",Std_Schedule_Code!$G$5:$G$191,$C30)) -> 2 | R30: 0 | S30: Not excisable: Not in s.1106; no levy found | T30: - | U30: - | V30: =IF(COUNTIFS(Std_Schedule_Code!$B$5:$B$191,"LBR",Std_Schedule_Code!$G$5:$G$191,$C30)=0,"",_xlfn.MINIFS(Std_Schedule_Code!$AO$5:$AO$191,Std_Schedule_Code!$B$5:$B$191,"LBR",Std_Schedule_Code!$G$5:$G$191,$C30)) -> 4 | W30: PR-15
A31: 4 Other | B31: industrial_residual | C31: I1 | D31: Cement | E31: per 50 kg bag | F31: 1 | G31: NLe 10/bag; specific (restored in FA2026) | H31: 0.45 | I31: n/a | J31: =IF(COUNTIFS(Std_Schedule_Code!$B$5:$B$191,"SLE",Std_Schedule_Code!$G$5:$G$191,$C31)=0,"",_xlfn.MINIFS(Std_Schedule_Code!$AO$5:$AO$191,Std_Schedule_Code!$B$5:$B$191,"SLE",Std_Schedule_Code!$G$5:$G$191,$C31)) -> 3 | K31: PR-33 | L31: 1 | M31: UGX 500/bag; specific | N31: 0.13 | O31: n/a | P31: =IF(COUNTIFS(Std_Schedule_Code!$B$5:$B$191,"UGA",Std_Schedule_Code!$G$5:$G$191,$C31)=0,"",_xlfn.MINIFS(Std_Schedule_Code!$AO$5:$AO$191,Std_Schedule_Code!$B$5:$B$191,"UGA",Std_Schedule_Code!$G$5:$G$191,$C31)) -> 2 | R31: 0 | S31: Not excisable: Not in s.1106 | T31: - | U31: - | V31: =IF(COUNTIFS(Std_Schedule_Code!$B$5:$B$191,"LBR",Std_Schedule_Code!$G$5:$G$191,$C31)=0,"",_xlfn.MINIFS(Std_Schedule_Code!$AO$5:$AO$191,Std_Schedule_Code!$B$5:$B$191,"LBR",Std_Schedule_Code!$G$5:$G$191,$C31)) -> 4 | W31: PR-15
A32: 4 Other | B32: industrial_residual | C32: I2 | D32: Edible oils | E32: per liter / % | F32: 1 | G32: 10% ad valorem (vegetable oils, palm olein, margarine) | H32: - | I32: - | J32: =IF(COUNTIFS(Std_Schedule_Code!$B$5:$B$191,"SLE",Std_Schedule_Code!$G$5:$G$191,$C32)=0,"",_xlfn.MINIFS(Std_Schedule_Code!$AO$5:$AO$191,Std_Schedule_Code!$B$5:$B$191,"SLE",Std_Schedule_Code!$G$5:$G$191,$C32)) -> 5 | K32: PR-35 | L32: 1 | M32: UGX 200/l (cooking oil); specific | N32: 0.05/l | O32: - | P32: =IF(COUNTIFS(Std_Schedule_Code!$B$5:$B$191,"UGA",Std_Schedule_Code!$G$5:$G$191,$C32)=0,"",_xlfn.MINIFS(Std_Schedule_Code!$AO$5:$AO$191,Std_Schedule_Code!$B$5:$B$191,"UGA",Std_Schedule_Code!$G$5:$G$191,$C32)) -> 2 | R32: 0 | S32: Not excisable: Not in s.1106 | T32: - | U32: - | V32: =IF(COUNTIFS(Std_Schedule_Code!$B$5:$B$191,"LBR",Std_Schedule_Code!$G$5:$G$191,$C32)=0,"",_xlfn.MINIFS(Std_Schedule_Code!$AO$5:$AO$191,Std_Schedule_Code!$B$5:$B$191,"LBR",Std_Schedule_Code!$G$5:$G$191,$C32)) -> 4 | W32: PR-15
A33: 4 Other | B33: industrial_residual | C33: I3 | D33: Sugar | E33: per kg | F33: 0 | G33: Not excisable | H33: - | I33: - | J33: =IF(COUNTIFS(Std_Schedule_Code!$B$5:$B$191,"SLE",Std_Schedule_Code!$G$5:$G$191,$C33)=0,"",_xlfn.MINIFS(Std_Schedule_Code!$AO$5:$AO$191,Std_Schedule_Code!$B$5:$B$191,"SLE",Std_Schedule_Code!$G$5:$G$191,$C33)) -> 2 | L33: 1 | M33: UGX 100/kg; industrial use nil | N33: 0.03 | O33: - | P33: =IF(COUNTIFS(Std_Schedule_Code!$B$5:$B$191,"UGA",Std_Schedule_Code!$G$5:$G$191,$C33)=0,"",_xlfn.MINIFS(Std_Schedule_Code!$AO$5:$AO$191,Std_Schedule_Code!$B$5:$B$191,"UGA",Std_Schedule_Code!$G$5:$G$191,$C33)) -> 2 | R33: 1 | S33: 5% | T33: - | U33: n/a (no price data) | V33: =IF(COUNTIFS(Std_Schedule_Code!$B$5:$B$191,"LBR",Std_Schedule_Code!$G$5:$G$191,$C33)=0,"",_xlfn.MINIFS(Std_Schedule_Code!$AO$5:$AO$191,Std_Schedule_Code!$B$5:$B$191,"LBR",Std_Schedule_Code!$G$5:$G$191,$C33)) -> 5 | W33: PR-14
A34: 4 Other | B34: industrial_residual | C34: I4 | D34: Other industrial inputs | E34: % | F34: 1 | G34: Soaps 20%; fatty-acid oils 20%; nails 5%; ad valorem | H34: - | I34: - | J34: =IF(COUNTIFS(Std_Schedule_Code!$B$5:$B$191,"SLE",Std_Schedule_Code!$G$5:$G$191,$C34)=0,"",_xlfn.MINIFS(Std_Schedule_Code!$AO$5:$AO$191,Std_Schedule_Code!$B$5:$B$191,"SLE",Std_Schedule_Code!$G$5:$G$191,$C34)) -> 5 | K34: PR-35 | L34: 0 | M34: Not excisable | N34: - | O34: - | P34: =IF(COUNTIFS(Std_Schedule_Code!$B$5:$B$191,"UGA",Std_Schedule_Code!$G$5:$G$191,$C34)=0,"",_xlfn.MINIFS(Std_Schedule_Code!$AO$5:$AO$191,Std_Schedule_Code!$B$5:$B$191,"UGA",Std_Schedule_Code!$G$5:$G$191,$C34)) -> 2 | R34: 0 | S34: Not excisable: Not in s.1106 | T34: - | U34: - | V34: =IF(COUNTIFS(Std_Schedule_Code!$B$5:$B$191,"LBR",Std_Schedule_Code!$G$5:$G$191,$C34)=0,"",_xlfn.MINIFS(Std_Schedule_Code!$AO$5:$AO$191,Std_Schedule_Code!$B$5:$B$191,"LBR",Std_Schedule_Code!$G$5:$G$191,$C34)) -> 4 | W34: PR-15
A35: 4 Other | B35: luxury | C35: L1 | D35: Cosmetics, furniture and other luxury | E35: % | F35: 0 | G35: Not excisable | H35: - | I35: - | J35: =IF(COUNTIFS(Std_Schedule_Code!$B$5:$B$191,"SLE",Std_Schedule_Code!$G$5:$G$191,$C35)=0,"",_xlfn.MINIFS(Std_Schedule_Code!$AO$5:$AO$191,Std_Schedule_Code!$B$5:$B$191,"SLE",Std_Schedule_Code!$G$5:$G$191,$C35)) -> 2 | L35: 1 | M35: Cosmetics 10%; furniture 20%; ad valorem | N35: - | O35: - | P35: =IF(COUNTIFS(Std_Schedule_Code!$B$5:$B$191,"UGA",Std_Schedule_Code!$G$5:$G$191,$C35)=0,"",_xlfn.MINIFS(Std_Schedule_Code!$AO$5:$AO$191,Std_Schedule_Code!$B$5:$B$191,"UGA",Std_Schedule_Code!$G$5:$G$191,$C35)) -> 2 | R35: 1 | S35: 20%; 10% | T35: - | U35: n/a (no price data) | V35: =IF(COUNTIFS(Std_Schedule_Code!$B$5:$B$191,"LBR",Std_Schedule_Code!$G$5:$G$191,$C35)=0,"",_xlfn.MINIFS(Std_Schedule_Code!$AO$5:$AO$191,Std_Schedule_Code!$B$5:$B$191,"LBR",Std_Schedule_Code!$G$5:$G$191,$C35)) -> 5 | W35: PR-14
D37: Coverage count
D38: In excise law (1) | F38: =COUNTIF(F6:F35,1) -> 21 | L38: =COUNTIF(L6:L35,1) -> 26 | R38: =COUNTIF(R6:R35,1) -> 16
D39: Levy outside excise law (2) | F39: =COUNTIF(F6:F35,2) -> 4 | L39: =COUNTIF(L6:L35,2) -> 0 | R39: =COUNTIF(R6:R35,2) -> 5
D40: Not covered (0) | F40: =COUNTIF(F6:F35,0) -> 5 | L40: =COUNTIF(L6:L35,0) -> 4 | R40: =COUNTIF(R6:R35,0) -> 9
D41: Covered (1 + 2) | F41: =F38+F39 -> 25 | L41: =L38+L39 -> 26 | R41: =R38+R39 -> 21
D43: Sources: SLE and UGA text from WP v0.8 Tables 10a-c (FX NLe 22, UGX 3,750 per USD); LBR from Liberia v0.3 Tables 9.1-9.2. USD figures here are as published; the code sheet recomputes them from Parameters.

Sheet Std_Schedule_Code
A1: Standardized schedule: code-readable (one row per rate component)
A2: Long format. A 'higher-of' hybrid has two rows (specific, ad valorem) with the same option_group. Formula columns: fx_lcu_per_usd, usd_per_rate_unit, usd_per_std_unit, share_of_ref_price, dq_score.
A4: row_id | B4: country_iso3 | C4: country | D4: cut_off | E4: part | F4: typology | G4: std_code | H4: std_line | I4: std_unit | J4: coverage_code | K4: national_item | L4: hs_code | M4: instrument | N4: effective_date | O4: record_type | P4: option_group | Q4: combination_rule | R4: rate_component | S4: rate_value | T4: rate_currency | U4: rate_per_unit | V4: ad_valorem_base | W4: text_as_printed | X4: origin | Y4: abv_min_pct | Z4: abv_max_pct | AA4: sugar_min_g_per_l | AB4: sugar_max_g_per_l | AC4: local_content_min_pct | AD4: local_content_max_pct | AE4: other_condition | AF4: fx_lcu_per_usd | AG4: usd_per_rate_unit | AH4: conv_to_std_unit | AI4: usd_per_std_unit | AJ4: ref_price_per_rate_unit | AK4: ref_price_source | AL4: share_of_ref_price | AM4: review_status | AN4: peer_review_ref | AO4: dq_score | AP4: notes
A5: SLE-001 | B5: SLE | C5: Sierra Leone | D5: 2026-04-27 | E5: 1 Fuel | F5: energy_environment | G5: E1 | H5: Petrol | I5: per liter | J5: 1 | K5: Petrol | M5: Finance Act 2026 | N5: 2026-01-01 | O5: current | Q5: single | R5: specific | S5: 5 | T5: NLe | U5: liter | W5: NLe 5.00 / liter | X5: all | AF5: =IF(T5="USD",1,IF(T5="pct","",INDEX(Parameters!$D$5:$D$7,MATCH(B5,Parameters!$A$5:$A$7,0)))) -> 22 | AG5: =IF(AND(R5="specific",ISNUMBER(S5)),S5/AF5,"") -> 0.22727273 | AH5: 1 | AI5: =IF(NOT(ISNUMBER(AH5)),"",IF(R5="specific",IF(ISNUMBER(AG5),AG5*AH5,""),IF(AND(R5="ad_valorem",ISNUMBER(AJ5)),S5*AJ5/INDEX(Parameters!$D$5:$D$7,MATCH(B5,Parameters!$A$5:$A$7,0))*AH5,""))) -> 0.22727273 | AJ5: 32 | AK5: Pump price NLe 32/l, 9 Mar 2026 (PR-42) | AL5: =IF(NOT(ISNUMBER(AJ5)),"",IF(R5="specific",S5/AJ5,IF(R5="ad_valorem",S5,""))) -> 0.15625 | AM5: partly_verified | AN5: PR-12 | AO5: =IF(AM5="","",IFERROR(INDEX(DQ_Scale!$B$5:$B$14,MATCH(AM5,DQ_Scale!$A$5:$A$14,0)),"")) -> 3
A6: SLE-002 | B6: SLE | C6: Sierra Leone | D6: 2026-04-27 | E6: 1 Fuel | F6: energy_environment | G6: E2 | H6: Diesel, road | I6: per liter | J6: 1 | K6: Diesel | M6: Finance Act 2026 | N6: 2026-01-01 | O6: current | Q6: single | R6: specific | S6: 5 | T6: NLe | U6: liter | W6: NLe 5.00 / liter | X6: all | AF6: =IF(T6="USD",1,IF(T6="pct","",INDEX(Parameters!$D$5:$D$7,MATCH(B6,Parameters!$A$5:$A$7,0)))) -> 22 | AG6: =IF(AND(R6="specific",ISNUMBER(S6)),S6/AF6,"") -> 0.22727273 | AH6: 1 | AI6: =IF(NOT(ISNUMBER(AH6)),"",IF(R6="specific",IF(ISNUMBER(AG6),AG6*AH6,""),IF(AND(R6="ad_valorem",ISNUMBER(AJ6)),S6*AJ6/INDEX(Parameters!$D$5:$D$7,MATCH(B6,Parameters!$A$5:$A$7,0))*AH6,""))) -> 0.22727273 | AJ6: 27.4 | AK6: Pump price NLe 27.4/l, mid-2025, pre-increase (PR-43) | AL6: =IF(NOT(ISNUMBER(AJ6)),"",IF(R6="specific",S6/AJ6,IF(R6="ad_valorem",S6,""))) -> 0.18248175 | AM6: partly_verified | AN6: PR-12 | AO6: =IF(AM6="","",IFERROR(INDEX(DQ_Scale!$B$5:$B$14,MATCH(AM6,DQ_Scale!$A$5:$A$14,0)),"")) -> 3 | AP6: Harmonized with petrol in FA2026
A7: SLE-003 | B7: SLE | C7: Sierra Leone | D7: 2026-04-27 | E7: 1 Fuel | F7: energy_environment | G7: E3 | H7: Kerosene | I7: per liter | J7: 1 | K7: Kerosene | M7: Finance Act 2026 | N7: 2026-01-01 | O7: current | Q7: single | R7: specific | S7: 2 | T7: NLe | U7: liter | W7: NLe 2.00 / liter | X7: all | AF7: =IF(T7="USD",1,IF(T7="pct","",INDEX(Parameters!$D$5:$D$7,MATCH(B7,Parameters!$A$5:$A$7,0)))) -> 22 | AG7: =IF(AND(R7="specific",ISNUMBER(S7)),S7/AF7,"") -> 0.090909091 | AH7: 1 | AI7: =IF(NOT(ISNUMBER(AH7)),"",IF(R7="specific",IF(ISNUMBER(AG7),AG7*AH7,""),IF(AND(R7="ad_valorem",ISNUMBER(AJ7)),S7*AJ7/INDEX(Parameters!$D$5:$D$7,MATCH(B7,Parameters!$A$5:$A$7,0))*AH7,""))) -> 0.090909091 | AJ7: 26 | AK7: Estimate NLe ~26/l | AL7: =IF(NOT(ISNUMBER(AJ7)),"",IF(R7="specific",S7/AJ7,IF(R7="ad_valorem",S7,""))) -> 0.076923077 | AM7: not_verified | AN7: PR-13 | AO7: =IF(AM7="","",IFERROR(INDEX(DQ_Scale!$B$5:$B$14,MATCH(AM7,DQ_Scale!$A$5:$A$14,0)),"")) -> 2
A8: SLE-004 | B8: SLE | C8: Sierra Leone | D8: 2026-04-27 | E8: 1 Fuel | F8: energy_environment | G8: E4 | H8: Aviation fuel | I8: per liter | J8: 0 | K8: Aviation fuel: not identified | O8: not_covered | R8: none | AF8: =IF(T8="USD",1,IF(T8="pct","",INDEX(Parameters!$D$5:$D$7,MATCH(B8,Parameters!$A$5:$A$7,0)))) -> 22 | AG8: =IF(AND(R8="specific",ISNUMBER(S8)),S8/AF8,"") | AI8: =IF(NOT(ISNUMBER(AH8)),"",IF(R8="specific",IF(ISNUMBER(AG8),AG8*AH8,""),IF(AND(R8="ad_valorem",ISNUMBER(AJ8)),S8*AJ8/INDEX(Parameters!$D$5:$D$7,MATCH(B8,Parameters!$A$5:$A$7,0))*AH8,""))) | AL8: =IF(NOT(ISNUMBER(AJ8)),"",IF(R8="specific",S8/AJ8,IF(R8="ad_valorem",S8,""))) | AM8: not_reviewed | AO8: =IF(AM8="","",IFERROR(INDEX(DQ_Scale!$B$5:$B$14,MATCH(AM8,DQ_Scale!$A$5:$A$14,0)),"")) -> 2 | AP8: WP Level 2: not identified
A9: SLE-005 | B9: SLE | C9: Sierra Leone | D9: 2026-04-27 | E9: 1 Fuel | F9: energy_environment | G9: E5 | H9: Heavy fuel oil / other gas oils | I9: per liter | J9: 1 | K9: Fuel oil | M9: Finance Act 2026 | N9: 2026-01-01 | O9: current | Q9: single | R9: specific | S9: 7.4 | T9: NLe | U9: liter | W9: NLe 7.40 / liter | X9: all | AF9: =IF(T9="USD",1,IF(T9="pct","",INDEX(Parameters!$D$5:$D$7,MATCH(B9,Parameters!$A$5:$A$7,0)))) -> 22 | AG9: =IF(AND(R9="specific",ISNUMBER(S9)),S9/AF9,"") -> 0.33636364 | AH9: 1 | AI9: =IF(NOT(ISNUMBER(AH9)),"",IF(R9="specific",IF(ISNUMBER(AG9),AG9*AH9,""),IF(AND(R9="ad_valorem",ISNUMBER(AJ9)),S9*AJ9/INDEX(Parameters!$D$5:$D$7,MATCH(B9,Parameters!$A$5:$A$7,0))*AH9,""))) -> 0.33636364 | AL9: =IF(NOT(ISNUMBER(AJ9)),"",IF(R9="specific",S9/AJ9,IF(R9="ad_valorem",S9,""))) | AM9: not_verified | AN9: PR-13 | AO9: =IF(AM9="","",IFERROR(INDEX(DQ_Scale!$B$5:$B$14,MATCH(AM9,DQ_Scale!$A$5:$A$14,0)),"")) -> 2 | AP9: Definitions differ from Uganda 'other gas oils'
A10: SLE-006 | B10: SLE | C10: Sierra Leone | D10: 2026-04-27 | E10: 1 Fuel | F10: energy_environment | G10: E6 | H10: Lubricants | I10: per liter | J10: 1 | K10: Lubricating oils | M10: Finance Act 2026 | N10: 2026-01-01 | O10: current | Q10: single | R10: specific | S10: 4 | T10: NLe | U10: liter | W10: NLe 4.00 / liter | X10: all | AF10: =IF(T10="USD",1,IF(T10="pct","",INDEX(Parameters!$D$5:$D$7,MATCH(B10,Parameters!$A$5:$A$7,0)))) -> 22 | AG10: =IF(AND(R10="specific",ISNUMBER(S10)),S10/AF10,"") -> 0.18181818 | AH10: 1 | AI10: =IF(NOT(ISNUMBER(AH10)),"",IF(R10="specific",IF(ISNUMBER(AG10),AG10*AH10,""),IF(AND(R10="ad_valorem",ISNUMBER(AJ10)),S10*AJ10/INDEX(Parameters!$D$5:$D$7,MATCH(B10,Parameters!$A$5:$A$7,0))*AH10,""))) -> 0.18181818 | AL10: =IF(NOT(ISNUMBER(AJ10)),"",IF(R10="specific",S10/AJ10,IF(R10="ad_valorem",S10,""))) | AM10: not_verified | AN10: PR-13 | AO10: =IF(AM10="","",IFERROR(INDEX(DQ_Scale!$B$5:$B$14,MATCH(AM10,DQ_Scale!$A$5:$A$14,0)),"")) -> 2
A11: SLE-007 | B11: SLE | C11: Sierra Leone | D11: 2026-04-27 | E11: 4 Other | F11: energy_environment | G11: E7 | H11: Plastic bags and packaging | I11: per kg | J11: 1 | K11: Polyethylene bags; plastic bottles filled with beverages (excl. water) | L11: 39.23 | M11: Finance Act 2024 s.4(l) | N11: 2024-01-01 | O11: current | Q11: single | R11: specific | S11: 16 | T11: NLe | U11: kg | W11: Le 16 / kg (printed 'Le' = new Leones, PR-07) | X11: all | AF11: =IF(T11="USD",1,IF(T11="pct","",INDEX(Parameters!$D$5:$D$7,MATCH(B11,Parameters!$A$5:$A$7,0)))) -> 22 | AG11: =IF(AND(R11="specific",ISNUMBER(S11)),S11/AF11,"") -> 0.72727273 | AH11: 1 | AI11: =IF(NOT(ISNUMBER(AH11)),"",IF(R11="specific",IF(ISNUMBER(AG11),AG11*AH11,""),IF(AND(R11="ad_valorem",ISNUMBER(AJ11)),S11*AJ11/INDEX(Parameters!$D$5:$D$7,MATCH(B11,Parameters!$A$5:$A$7,0))*AH11,""))) -> 0.72727273 | AL11: =IF(NOT(ISNUMBER(AJ11)),"",IF(R11="specific",S11/AJ11,IF(R11="ad_valorem",S11,""))) | AM11: verified | AN11: PR-14, PR-07 | AO11: =IF(AM11="","",IFERROR(INDEX(DQ_Scale!$B$5:$B$14,MATCH(AM11,DQ_Scale!$A$5:$A$14,0)),"")) -> 5
A12: SLE-008 | B12: SLE | C12: Sierra Leone | D12: 2026-04-27 | E12: 2 Vehicles | F12: energy_environment | G12: E8 | H12: Vehicles: annual circulation | I12: per vehicle-year | J12: 2 | K12: Vehicle annual circulation levy: cars, trucks, buses | M12: Finance Act 2026 (levy outside Excise Act) | N12: 2026-01-01 | O12: current | Q12: single | R12: specific | S12: 500 | T12: NLe | U12: vehicle-year | W12: NLe 500 / year | X12: all | AE12: vehicle class: cars, trucks, buses | AF12: =IF(T12="USD",1,IF(T12="pct","",INDEX(Parameters!$D$5:$D$7,MATCH(B12,Parameters!$A$5:$A$7,0)))) -> 22 | AG12: =IF(AND(R12="specific",ISNUMBER(S12)),S12/AF12,"") -> 22.727273 | AH12: 1 | AI12: =IF(NOT(ISNUMBER(AH12)),"",IF(R12="specific",IF(ISNUMBER(AG12),AG12*AH12,""),IF(AND(R12="ad_valorem",ISNUMBER(AJ12)),S12*AJ12/INDEX(Parameters!$D$5:$D$7,MATCH(B12,Parameters!$A$5:$A$7,0))*AH12,""))) -> 22.727273 | AL12: =IF(NOT(ISNUMBER(AJ12)),"",IF(R12="specific",S12/AJ12,IF(R12="ad_valorem",S12,""))) | AM12: partly_verified | AN12: PR-15 | AO12: =IF(AM12="","",IFERROR(INDEX(DQ_Scale!$B$5:$B$14,MATCH(AM12,DQ_Scale!$A$5:$A$14,0)),"")) -> 3
A13: SLE-009 | B13: SLE | C13: Sierra Leone | D13: 2026-04-27 | E13: 2 Vehicles | F13: energy_environment | G13: E8 | H13: Vehicles: annual circulation | I13: per vehicle-year | J13: 2 | K13: Vehicle circulation levy: motorbikes | M13: Finance Act 2026 (levy outside Excise Act) | N13: 2026-01-01 | O13: current | Q13: single | R13: specific | S13: 200 | T13: NLe | U13: vehicle-year | W13: NLe 200 / year | X13: all | AE13: vehicle class: motorbikes | AF13: =IF(T13="USD",1,IF(T13="pct","",INDEX(Parameters!$D$5:$D$7,MATCH(B13,Parameters!$A$5:$A$7,0)))) -> 22 | AG13: =IF(AND(R13="specific",ISNUMBER(S13)),S13/AF13,"") -> 9.0909091 | AH13: 1 | AI13: =IF(NOT(ISNUMBER(AH13)),"",IF(R13="specific",IF(ISNUMBER(AG13),AG13*AH13,""),IF(AND(R13="ad_valorem",ISNUMBER(AJ13)),S13*AJ13/INDEX(Parameters!$D$5:$D$7,MATCH(B13,Parameters!$A$5:$A$7,0))*AH13,""))) -> 9.0909091 | AL13: =IF(NOT(ISNUMBER(AJ13)),"",IF(R13="specific",S13/AJ13,IF(R13="ad_valorem",S13,""))) | AM13: not_verified | AN13: PR-16 | AO13: =IF(AM13="","",IFERROR(INDEX(DQ_Scale!$B$5:$B$14,MATCH(AM13,DQ_Scale!$A$5:$A$14,0)),"")) -> 2
A14: SLE-010 | B14: SLE | C14: Sierra Leone | D14: 2026-04-27 | E14: 2 Vehicles | F14: energy_environment | G14: E8 | H14: Vehicles: annual circulation | I14: per vehicle-year | J14: 2 | K14: Vehicle circulation levy: vessels up to 15 seats | M14: Finance Act 2026 (levy outside Excise Act) | N14: 2026-01-01 | O14: current | Q14: single | R14: specific | S14: 500 | T14: USD | U14: vehicle-year | W14: USD 500 / year | X14: all | AE14: vessels, <=15 seats | AF14: =IF(T14="USD",1,IF(T14="pct","",INDEX(Parameters!$D$5:$D$7,MATCH(B14,Parameters!$A$5:$A$7,0)))) -> 1 | AG14: =IF(AND(R14="specific",ISNUMBER(S14)),S14/AF14,"") -> 500 | AH14: 1 | AI14: =IF(NOT(ISNUMBER(AH14)),"",IF(R14="specific",IF(ISNUMBER(AG14),AG14*AH14,""),IF(AND(R14="ad_valorem",ISNUMBER(AJ14)),S14*AJ14/INDEX(Parameters!$D$5:$D$7,MATCH(B14,Parameters!$A$5:$A$7,0))*AH14,""))) -> 500 | AL14: =IF(NOT(ISNUMBER(AJ14)),"",IF(R14="specific",S14/AJ14,IF(R14="ad_valorem",S14,""))) | AM14: not_verified | AN14: PR-16 | AO14: =IF(AM14="","",IFERROR(INDEX(DQ_Scale!$B$5:$B$14,MATCH(AM14,DQ_Scale!$A$5:$A$14,0)),"")) -> 2
A15: SLE-011 | B15: SLE | C15: Sierra Leone | D15: 2026-04-27 | E15: 2 Vehicles | F15: energy_environment | G15: E8 | H15: Vehicles: annual circulation | I15: per vehicle-year | J15: 2 | K15: Vehicle circulation levy: vessels over 15 seats | M15: Finance Act 2026 (levy outside Excise Act) | N15: 2026-01-01 | O15: current | Q15: single | R15: specific | S15: 1000 | T15: USD | U15: vehicle-year | W15: USD 1,000 / year | X15: all | AE15: vessels, >15 seats | AF15: =IF(T15="USD",1,IF(T15="pct","",INDEX(Parameters!$D$5:$D$7,MATCH(B15,Parameters!$A$5:$A$7,0)))) -> 1 | AG15: =IF(AND(R15="specific",ISNUMBER(S15)),S15/AF15,"") -> 1000 | AH15: 1 | AI15: =IF(NOT(ISNUMBER(AH15)),"",IF(R15="specific",IF(ISNUMBER(AG15),AG15*AH15,""),IF(AND(R15="ad_valorem",ISNUMBER(AJ15)),S15*AJ15/INDEX(Parameters!$D$5:$D$7,MATCH(B15,Parameters!$A$5:$A$7,0))*AH15,""))) -> 1000 | AL15: =IF(NOT(ISNUMBER(AJ15)),"",IF(R15="specific",S15/AJ15,IF(R15="ad_valorem",S15,""))) | AM15: not_verified | AN15: PR-16 | AO15: =IF(AM15="","",IFERROR(INDEX(DQ_Scale!$B$5:$B$14,MATCH(AM15,DQ_Scale!$A$5:$A$14,0)),"")) -> 2
A16: SLE-012 | B16: SLE | C16: Sierra Leone | D16: 2026-04-27 | E16: 2 Vehicles | F16: energy_environment | G16: E9 | H16: Vehicles: first registration / import | I16: per vehicle | J16: 0 | K16: First registration: not in excise schedule | O16: not_covered | R16: none | AF16: =IF(T16="USD",1,IF(T16="pct","",INDEX(Parameters!$D$5:$D$7,MATCH(B16,Parameters!$A$5:$A$7,0)))) -> 22 | AG16: =IF(AND(R16="specific",ISNUMBER(S16)),S16/AF16,"") | AI16: =IF(NOT(ISNUMBER(AH16)),"",IF(R16="specific",IF(ISNUMBER(AG16),AG16*AH16,""),IF(AND(R16="ad_valorem",ISNUMBER(AJ16)),S16*AJ16/INDEX(Parameters!$D$5:$D$7,MATCH(B16,Parameters!$A$5:$A$7,0))*AH16,""))) | AL16: =IF(NOT(ISNUMBER(AJ16)),"",IF(R16="specific",S16/AJ16,IF(R16="ad_valorem",S16,""))) | AM16: not_reviewed | AO16: =IF(AM16="","",IFERROR(INDEX(DQ_Scale!$B$5:$B$14,MATCH(AM16,DQ_Scale!$A$5:$A$14,0)),"")) -> 2
A17: SLE-013 | B17: SLE | C17: Sierra Leone | D17: 2026-04-27 | E17: 3 Health | F17: health | G17: T1 | H17: Cigarettes | I17: per pack of 20 | J17: 1 | K17: Cigarettes | L17: 24.02 | M17: Finance Act 2026 | N17: 2026-01-01 | O17: current | Q17: single | R17: specific | S17: 3 | T17: NLe | U17: pack of 20 | W17: NLe 3 / packet of 20 | X17: all | AF17: =IF(T17="USD",1,IF(T17="pct","",INDEX(Parameters!$D$5:$D$7,MATCH(B17,Parameters!$A$5:$A$7,0)))) -> 22 | AG17: =IF(AND(R17="specific",ISNUMBER(S17)),S17/AF17,"") -> 0.13636364 | AH17: 1 | AI17: =IF(NOT(ISNUMBER(AH17)),"",IF(R17="specific",IF(ISNUMBER(AG17),AG17*AH17,""),IF(AND(R17="ad_valorem",ISNUMBER(AJ17)),S17*AJ17/INDEX(Parameters!$D$5:$D$7,MATCH(B17,Parameters!$A$5:$A$7,0))*AH17,""))) -> 0.13636364 | AJ17: 22 | AK17: Pack price NLe 22 (market estimate) | AL17: =IF(NOT(ISNUMBER(AJ17)),"",IF(R17="specific",S17/AJ17,IF(R17="ad_valorem",S17,""))) -> 0.13636364 | AM17: partly_verified | AN17: PR-20 | AO17: =IF(AM17="","",IFERROR(INDEX(DQ_Scale!$B$5:$B$14,MATCH(AM17,DQ_Scale!$A$5:$A$14,0)),"")) -> 3
A18: SLE-014 | B18: SLE | C18: Sierra Leone | D18: 2026-04-27 | E18: 3 Health | F18: health | G18: T2 | H18: Cigars and other tobacco | I18: per pack / per kg | J18: 1 | K18: Cigars, cheroots, cigarillos | L18: 24.02 | M18: Finance Act 2026 | N18: 2026-01-01 | O18: current | Q18: single | R18: specific | S18: 38 | T18: NLe | U18: packet | W18: NLe 38 / packet | X18: all | AF18: =IF(T18="USD",1,IF(T18="pct","",INDEX(Parameters!$D$5:$D$7,MATCH(B18,Parameters!$A$5:$A$7,0)))) -> 22 | AG18: =IF(AND(R18="specific",ISNUMBER(S18)),S18/AF18,"") -> 1.7272727 | AH18: 1 | AI18: =IF(NOT(ISNUMBER(AH18)),"",IF(R18="specific",IF(ISNUMBER(AG18),AG18*AH18,""),IF(AND(R18="ad_valorem",ISNUMBER(AJ18)),S18*AJ18/INDEX(Parameters!$D$5:$D$7,MATCH(B18,Parameters!$A$5:$A$7,0))*AH18,""))) -> 1.7272727 | AL18: =IF(NOT(ISNUMBER(AJ18)),"",IF(R18="specific",S18/AJ18,IF(R18="ad_valorem",S18,""))) | AM18: not_verified | AN18: PR-21 | AO18: =IF(AM18="","",IFERROR(INDEX(DQ_Scale!$B$5:$B$14,MATCH(AM18,DQ_Scale!$A$5:$A$14,0)),"")) -> 2
A19: SLE-015 | B19: SLE | C19: Sierra Leone | D19: 2026-04-27 | E19: 3 Health | F19: health | G19: T2 | H19: Cigars and other tobacco | I19: per pack / per kg | J19: 1 | K19: Unmanufactured tobacco | L19: 24.01 | M19: Finance Act 2026 | N19: 2026-01-01 | O19: current | Q19: single | R19: specific | S19: 98 | T19: NLe | U19: kg | W19: NLe 98 / kg | X19: all | AF19: =IF(T19="USD",1,IF(T19="pct","",INDEX(Parameters!$D$5:$D$7,MATCH(B19,Parameters!$A$5:$A$7,0)))) -> 22 | AG19: =IF(AND(R19="specific",ISNUMBER(S19)),S19/AF19,"") -> 4.4545455 | AH19: 1 | AI19: =IF(NOT(ISNUMBER(AH19)),"",IF(R19="specific",IF(ISNUMBER(AG19),AG19*AH19,""),IF(AND(R19="ad_valorem",ISNUMBER(AJ19)),S19*AJ19/INDEX(Parameters!$D$5:$D$7,MATCH(B19,Parameters!$A$5:$A$7,0))*AH19,""))) -> 4.4545455 | AL19: =IF(NOT(ISNUMBER(AJ19)),"",IF(R19="specific",S19/AJ19,IF(R19="ad_valorem",S19,""))) | AM19: not_verified | AN19: PR-21 | AO19: =IF(AM19="","",IFERROR(INDEX(DQ_Scale!$B$5:$B$14,MATCH(AM19,DQ_Scale!$A$5:$A$14,0)),"")) -> 2
A20: SLE-016 | B20: SLE | C20: Sierra Leone | D20: 2026-04-27 | E20: 3 Health | F20: health | G20: T2 | H20: Cigars and other tobacco | I20: per pack / per kg | J20: 1 | K20: Other manufactured or homogenized tobacco | L20: 24.03 | M20: Finance Act 2026 | N20: 2026-01-01 | O20: current | Q20: single | R20: specific | S20: 98 | T20: NLe | U20: kg | W20: NLe 98 / kg | X20: all | AF20: =IF(T20="USD",1,IF(T20="pct","",INDEX(Parameters!$D$5:$D$7,MATCH(B20,Parameters!$A$5:$A$7,0)))) -> 22 | AG20: =IF(AND(R20="specific",ISNUMBER(S20)),S20/AF20,"") -> 4.4545455 | AH20: 1 | AI20: =IF(NOT(ISNUMBER(AH20)),"",IF(R20="specific",IF(ISNUMBER(AG20),AG20*AH20,""),IF(AND(R20="ad_valorem",ISNUMBER(AJ20)),S20*AJ20/INDEX(Parameters!$D$5:$D$7,MATCH(B20,Parameters!$A$5:$A$7,0))*AH20,""))) -> 4.4545455 | AL20: =IF(NOT(ISNUMBER(AJ20)),"",IF(R20="specific",S20/AJ20,IF(R20="ad_valorem",S20,""))) | AM20: not_verified | AN20: PR-21 | AO20: =IF(AM20="","",IFERROR(INDEX(DQ_Scale!$B$5:$B$14,MATCH(AM20,DQ_Scale!$A$5:$A$14,0)),"")) -> 2
A21: SLE-017 | B21: SLE | C21: Sierra Leone | D21: 2026-04-27 | E21: 3 Health | F21: health | G21: T2 | H21: Cigars and other tobacco | I21: per pack / per kg | J21: 1 | K21: Shisha, herbal molasses: per kg component | L21: 24.03 | M21: Finance Act 2026 | N21: 2026-01-01 | O21: current | P21: SLE-shisha | Q21: compound | R21: specific | S21: 98 | T21: NLe | U21: kg | W21: NLe 98 / kg + NLe 225 / l | X21: all | AF21: =IF(T21="USD",1,IF(T21="pct","",INDEX(Parameters!$D$5:$D$7,MATCH(B21,Parameters!$A$5:$A$7,0)))) -> 22 | AG21: =IF(AND(R21="specific",ISNUMBER(S21)),S21/AF21,"") -> 4.4545455 | AH21: 1 | AI21: =IF(NOT(ISNUMBER(AH21)),"",IF(R21="specific",IF(ISNUMBER(AG21),AG21*AH21,""),IF(AND(R21="ad_valorem",ISNUMBER(AJ21)),S21*AJ21/INDEX(Parameters!$D$5:$D$7,MATCH(B21,Parameters!$A$5:$A$7,0))*AH21,""))) -> 4.4545455 | AL21: =IF(NOT(ISNUMBER(AJ21)),"",IF(R21="specific",S21/AJ21,IF(R21="ad_valorem",S21,""))) | AM21: not_verified | AN21: PR-21 | AO21: =IF(AM21="","",IFERROR(INDEX(DQ_Scale!$B$5:$B$14,MATCH(AM21,DQ_Scale!$A$5:$A$14,0)),"")) -> 2
A22: SLE-018 | B22: SLE | C22: Sierra Leone | D22: 2026-04-27 | E22: 3 Health | F22: health | G22: T2 | H22: Cigars and other tobacco | I22: per pack / per kg | J22: 1 | K22: Shisha, herbal molasses: per liter component | L22: 24.03 | M22: Finance Act 2026 | N22: 2026-01-01 | O22: current | P22: SLE-shisha | Q22: compound | R22: specific | S22: 225 | T22: NLe | U22: liter | W22: NLe 98 / kg + NLe 225 / l | X22: all | AF22: =IF(T22="USD",1,IF(T22="pct","",INDEX(Parameters!$D$5:$D$7,MATCH(B22,Parameters!$A$5:$A$7,0)))) -> 22 | AG22: =IF(AND(R22="specific",ISNUMBER(S22)),S22/AF22,"") -> 10.227273 | AI22: =IF(NOT(ISNUMBER(AH22)),"",IF(R22="specific",IF(ISNUMBER(AG22),AG22*AH22,""),IF(AND(R22="ad_valorem",ISNUMBER(AJ22)),S22*AJ22/INDEX(Parameters!$D$5:$D$7,MATCH(B22,Parameters!$A$5:$A$7,0))*AH22,""))) | AL22: =IF(NOT(ISNUMBER(AJ22)),"",IF(R22="specific",S22/AJ22,IF(R22="ad_valorem",S22,""))) | AM22: not_verified | AN22: PR-21 | AO22: =IF(AM22="","",IFERROR(INDEX(DQ_Scale!$B$5:$B$14,MATCH(AM22,DQ_Scale!$A$5:$A$14,0)),"")) -> 2
A23: SLE-019 | B23: SLE | C23: Sierra Leone | D23: 2026-04-27 | E23: 3 Health | F23: health | G23: T3 | H23: E-cigarettes and novel products | I23: per ml / per cartridge | J23: 1 | K23: E-cigarette device (incl. e-shisha, e-hookah) | L23: 24.04 | M23: Finance Act 2026 | N23: 2026-01-01 | O23: current | Q23: single | R23: specific | S23: 0.75 | T23: NLe | U23: ml | W23: NLe 0.75 / ml | X23: all | AF23: =IF(T23="USD",1,IF(T23="pct","",INDEX(Parameters!$D$5:$D$7,MATCH(B23,Parameters!$A$5:$A$7,0)))) -> 22 | AG23: =IF(AND(R23="specific",ISNUMBER(S23)),S23/AF23,"") -> 0.034090909 | AH23: 1 | AI23: =IF(NOT(ISNUMBER(AH23)),"",IF(R23="specific",IF(ISNUMBER(AG23),AG23*AH23,""),IF(AND(R23="ad_valorem",ISNUMBER(AJ23)),S23*AJ23/INDEX(Parameters!$D$5:$D$7,MATCH(B23,Parameters!$A$5:$A$7,0))*AH23,""))) -> 0.034090909 | AL23: =IF(NOT(ISNUMBER(AJ23)),"",IF(R23="specific",S23/AJ23,IF(R23="ad_valorem",S23,""))) | AM23: not_verified | AN23: PR-21 | AO23: =IF(AM23="","",IFERROR(INDEX(DQ_Scale!$B$5:$B$14,MATCH(AM23,DQ_Scale!$A$5:$A$14,0)),"")) -> 2
A24: SLE-020 | B24: SLE | C24: Sierra Leone | D24: 2026-04-27 | E24: 3 Health | F24: health | G24: T3 | H24: E-cigarettes and novel products | I24: per ml / per cartridge | J24: 1 | K24: E-cigarette cartridge | L24: 24.04 | M24: Finance Act 2026 | N24: 2026-01-01 | O24: current | Q24: single | R24: specific | S24: 1.2 | T24: NLe | U24: cartridge | W24: NLe 1.20 / unit | X24: all | AF24: =IF(T24="USD",1,IF(T24="pct","",INDEX(Parameters!$D$5:$D$7,MATCH(B24,Parameters!$A$5:$A$7,0)))) -> 22 | AG24: =IF(AND(R24="specific",ISNUMBER(S24)),S24/AF24,"") -> 0.054545455 | AH24: 1 | AI24: =IF(NOT(ISNUMBER(AH24)),"",IF(R24="specific",IF(ISNUMBER(AG24),AG24*AH24,""),IF(AND(R24="ad_valorem",ISNUMBER(AJ24)),S24*AJ24/INDEX(Parameters!$D$5:$D$7,MATCH(B24,Parameters!$A$5:$A$7,0))*AH24,""))) -> 0.054545455 | AL24: =IF(NOT(ISNUMBER(AJ24)),"",IF(R24="specific",S24/AJ24,IF(R24="ad_valorem",S24,""))) | AM24: not_verified | AN24: PR-21 | AO24: =IF(AM24="","",IFERROR(INDEX(DQ_Scale!$B$5:$B$14,MATCH(AM24,DQ_Scale!$A$5:$A$14,0)),"")) -> 2
A25: SLE-021 | B25: SLE | C25: Sierra Leone | D25: 2026-04-27 | E25: 3 Health | F25: health | G25: A1 | H25: Beer, mainstream malt (5% ABV) | I25: per LPA | J25: 1 | K25: Beer made from malt (<10% ABV), local | L25: 2203 | M25: Finance Act 2024 s.4(a) | N25: 2024-01-01 | O25: current | Q25: single | R25: specific | S25: 10 | T25: NLe | U25: liter | W25: Le 10 / l local (also printed Le 0.01 / cl) | X25: local | Z25: 10 | AF25: =IF(T25="USD",1,IF(T25="pct","",INDEX(Parameters!$D$5:$D$7,MATCH(B25,Parameters!$A$5:$A$7,0)))) -> 22 | AG25: =IF(AND(R25="specific",ISNUMBER(S25)),S25/AF25,"") -> 0.45454545 | AH25: 20 | AI25: =IF(NOT(ISNUMBER(AH25)),"",IF(R25="specific",IF(ISNUMBER(AG25),AG25*AH25,""),IF(AND(R25="ad_valorem",ISNUMBER(AJ25)),S25*AJ25/INDEX(Parameters!$D$5:$D$7,MATCH(B25,Parameters!$A$5:$A$7,0))*AH25,""))) -> 9.0909091 | AJ25: 50 | AK25: Beer NLe ~25 per 500 ml (market estimate) | AL25: =IF(NOT(ISNUMBER(AJ25)),"",IF(R25="specific",S25/AJ25,IF(R25="ad_valorem",S25,""))) -> 0.2 | AM25: verified | AN25: PR-22 | AO25: =IF(AM25="","",IFERROR(INDEX(DQ_Scale!$B$5:$B$14,MATCH(AM25,DQ_Scale!$A$5:$A$14,0)),"")) -> 5 | AP25: Per-cl figure is a tenth of the per-liter figure (Level 1 issue 2)
A26: SLE-022 | B26: SLE | C26: Sierra Leone | D26: 2026-04-27 | E26: 3 Health | F26: health | G26: A1 | H26: Beer, mainstream malt (5% ABV) | I26: per LPA | J26: 1 | K26: Beer made from malt (<10% ABV), imported | L26: 2203 | M26: Finance Act 2024 s.4(a) | N26: 2024-01-01 | O26: current | Q26: single | R26: specific | S26: 15 | T26: NLe | U26: liter | W26: Le 15 / l imported (also printed Le 0.015 / cl) | X26: imported | Z26: 10 | AF26: =IF(T26="USD",1,IF(T26="pct","",INDEX(Parameters!$D$5:$D$7,MATCH(B26,Parameters!$A$5:$A$7,0)))) -> 22 | AG26: =IF(AND(R26="specific",ISNUMBER(S26)),S26/AF26,"") -> 0.68181818 | AH26: 20 | AI26: =IF(NOT(ISNUMBER(AH26)),"",IF(R26="specific",IF(ISNUMBER(AG26),AG26*AH26,""),IF(AND(R26="ad_valorem",ISNUMBER(AJ26)),S26*AJ26/INDEX(Parameters!$D$5:$D$7,MATCH(B26,Parameters!$A$5:$A$7,0))*AH26,""))) -> 13.636364 | AJ26: 50 | AK26: Beer NLe ~25 per 500 ml (market estimate) | AL26: =IF(NOT(ISNUMBER(AJ26)),"",IF(R26="specific",S26/AJ26,IF(R26="ad_valorem",S26,""))) -> 0.3 | AM26: verified | AN26: PR-22 | AO26: =IF(AM26="","",IFERROR(INDEX(DQ_Scale!$B$5:$B$14,MATCH(AM26,DQ_Scale!$A$5:$A$14,0)),"")) -> 5
A27: SLE-023 | B27: SLE | C27: Sierra Leone | D27: 2026-04-27 | E27: 3 Health | F27: health | G27: A2 | H27: Beer, local-content concession (5% ABV) | I27: per LPA | J27: 1 | K27: Local-content beer, band D1 (80-100% local raw material) | L27: 22.09 | M27: Finance Act 2025 | N27: 2025-01-01 | O27: current | Q27: single | R27: ad_valorem | S27: 0.05 | T27: pct | U27: % of value | V27: value (legal base not observed; retail used as upper bound) | W27: 5% | X27: all | Z27: 10 | AC27: 80 | AD27: 100 | AF27: =IF(T27="USD",1,IF(T27="pct","",INDEX(Parameters!$D$5:$D$7,MATCH(B27,Parameters!$A$5:$A$7,0)))) | AG27: =IF(AND(R27="specific",ISNUMBER(S27)),S27/AF27,"") | AH27: 20 | AI27: =IF(NOT(ISNUMBER(AH27)),"",IF(R27="specific",IF(ISNUMBER(AG27),AG27*AH27,""),IF(AND(R27="ad_valorem",ISNUMBER(AJ27)),S27*AJ27/INDEX(Parameters!$D$5:$D$7,MATCH(B27,Parameters!$A$5:$A$7,0))*AH27,""))) -> 2.2727273 | AJ27: 50 | AK27: Beer NLe 50/l retail (upper bound) | AL27: =IF(NOT(ISNUMBER(AJ27)),"",IF(R27="specific",S27/AJ27,IF(R27="ad_valorem",S27,""))) -> 0.05 | AM27: verified | AN27: PR-26 | AO27: =IF(AM27="","",IFERROR(INDEX(DQ_Scale!$B$5:$B$14,MATCH(AM27,DQ_Scale!$A$5:$A$14,0)),"")) -> 5
A28: SLE-024 | B28: SLE | C28: Sierra Leone | D28: 2026-04-27 | E28: 3 Health | F28: health | G28: A2 | H28: Beer, local-content concession (5% ABV) | I28: per LPA | J28: 1 | K28: Local-content beer, band D1 (80-100% local raw material) | L28: 22.09 | M28: Finance Act 2025 | N28: 2025-01-01 | O28: current | Q28: single | R28: ad_valorem | S28: 0.08 | T28: pct | U28: % of value | V28: value (legal base not observed; retail used as upper bound) | W28: 8% | X28: all | Y28: 10 | Z28: 20 | AC28: 80 | AD28: 100 | AF28: =IF(T28="USD",1,IF(T28="pct","",INDEX(Parameters!$D$5:$D$7,MATCH(B28,Parameters!$A$5:$A$7,0)))) | AG28: =IF(AND(R28="specific",ISNUMBER(S28)),S28/AF28,"") | AI28: =IF(NOT(ISNUMBER(AH28)),"",IF(R28="specific",IF(ISNUMBER(AG28),AG28*AH28,""),IF(AND(R28="ad_valorem",ISNUMBER(AJ28)),S28*AJ28/INDEX(Parameters!$D$5:$D$7,MATCH(B28,Parameters!$A$5:$A$7,0))*AH28,""))) | AL28: =IF(NOT(ISNUMBER(AJ28)),"",IF(R28="specific",S28/AJ28,IF(R28="ad_valorem",S28,""))) | AM28: verified | AN28: PR-26 | AO28: =IF(AM28="","",IFERROR(INDEX(DQ_Scale!$B$5:$B$14,MATCH(AM28,DQ_Scale!$A$5:$A$14,0)),"")) -> 5 | AP28: Not evaluated: outside representative 5% ABV
A29: SLE-025 | B29: SLE | C29: Sierra Leone | D29: 2026-04-27 | E29: 3 Health | F29: health | G29: A2 | H29: Beer, local-content concession (5% ABV) | I29: per LPA | J29: 1 | K29: Local-content beer, band D1 (80-100% local raw material) | L29: 22.09 | M29: Finance Act 2025 | N29: 2025-01-01 | O29: current | Q29: single | R29: ad_valorem | S29: 0.12 | T29: pct | U29: % of value | V29: value (legal base not observed; retail used as upper bound) | W29: 12% | X29: all | Y29: 20 | AC29: 80 | AD29: 100 | AF29: =IF(T29="USD",1,IF(T29="pct","",INDEX(Parameters!$D$5:$D$7,MATCH(B29,Parameters!$A$5:$A$7,0)))) | AG29: =IF(AND(R29="specific",ISNUMBER(S29)),S29/AF29,"") | AI29: =IF(NOT(ISNUMBER(AH29)),"",IF(R29="specific",IF(ISNUMBER(AG29),AG29*AH29,""),IF(AND(R29="ad_valorem",ISNUMBER(AJ29)),S29*AJ29/INDEX(Parameters!$D$5:$D$7,MATCH(B29,Parameters!$A$5:$A$7,0))*AH29,""))) | AL29: =IF(NOT(ISNUMBER(AJ29)),"",IF(R29="specific",S29/AJ29,IF(R29="ad_valorem",S29,""))) | AM29: verified | AN29: PR-26 | AO29: =IF(AM29="","",IFERROR(INDEX(DQ_Scale!$B$5:$B$14,MATCH(AM29,DQ_Scale!$A$5:$A$14,0)),"")) -> 5 | AP29: Not evaluated: outside representative 5% ABV
A30: SLE-026 | B30: SLE | C30: Sierra Leone | D30: 2026-04-27 | E30: 3 Health | F30: health | G30: A2 | H30: Beer, local-content concession (5% ABV) | I30: per LPA | J30: 1 | K30: Local-content beer, band D2 (70-80% local raw material) | L30: 22.09 | M30: Finance Act 2025 | N30: 2025-01-01 | O30: current | Q30: single | R30: ad_valorem | S30: 0.08 | T30: pct | U30: % of value | V30: value (legal base not observed; retail used as upper bound) | W30: 8% | X30: all | Z30: 10 | AC30: 70 | AD30: 80 | AF30: =IF(T30="USD",1,IF(T30="pct","",INDEX(Parameters!$D$5:$D$7,MATCH(B30,Parameters!$A$5:$A$7,0)))) | AG30: =IF(AND(R30="specific",ISNUMBER(S30)),S30/AF30,"") | AH30: 20 | AI30: =IF(NOT(ISNUMBER(AH30)),"",IF(R30="specific",IF(ISNUMBER(AG30),AG30*AH30,""),IF(AND(R30="ad_valorem",ISNUMBER(AJ30)),S30*AJ30/INDEX(Parameters!$D$5:$D$7,MATCH(B30,Parameters!$A$5:$A$7,0))*AH30,""))) -> 3.6363636 | AJ30: 50 | AK30: Beer NLe 50/l retail (upper bound) | AL30: =IF(NOT(ISNUMBER(AJ30)),"",IF(R30="specific",S30/AJ30,IF(R30="ad_valorem",S30,""))) -> 0.08 | AM30: verified | AN30: PR-26 | AO30: =IF(AM30="","",IFERROR(INDEX(DQ_Scale!$B$5:$B$14,MATCH(AM30,DQ_Scale!$A$5:$A$14,0)),"")) -> 5
A31: SLE-027 | B31: SLE | C31: Sierra Leone | D31: 2026-04-27 | E31: 3 Health | F31: health | G31: A2 | H31: Beer, local-content concession (5% ABV) | I31: per LPA | J31: 1 | K31: Local-content beer, band D2 (70-80% local raw material) | L31: 22.09 | M31: Finance Act 2025 | N31: 2025-01-01 | O31: current | Q31: single | R31: ad_valorem | S31: 0.12 | T31: pct | U31: % of value | V31: value (legal base not observed; retail used as upper bound) | W31: 12% | X31: all | Y31: 10 | Z31: 20 | AC31: 70 | AD31: 80 | AF31: =IF(T31="USD",1,IF(T31="pct","",INDEX(Parameters!$D$5:$D$7,MATCH(B31,Parameters!$A$5:$A$7,0)))) | AG31: =IF(AND(R31="specific",ISNUMBER(S31)),S31/AF31,"") | AI31: =IF(NOT(ISNUMBER(AH31)),"",IF(R31="specific",IF(ISNUMBER(AG31),AG31*AH31,""),IF(AND(R31="ad_valorem",ISNUMBER(AJ31)),S31*AJ31/INDEX(Parameters!$D$5:$D$7,MATCH(B31,Parameters!$A$5:$A$7,0))*AH31,""))) | AL31: =IF(NOT(ISNUMBER(AJ31)),"",IF(R31="specific",S31/AJ31,IF(R31="ad_valorem",S31,""))) | AM31: verified | AN31: PR-26 | AO31: =IF(AM31="","",IFERROR(INDEX(DQ_Scale!$B$5:$B$14,MATCH(AM31,DQ_Scale!$A$5:$A$14,0)),"")) -> 5 | AP31: Not evaluated: outside representative 5% ABV
A32: SLE-028 | B32: SLE | C32: Sierra Leone | D32: 2026-04-27 | E32: 3 Health | F32: health | G32: A2 | H32: Beer, local-content concession (5% ABV) | I32: per LPA | J32: 1 | K32: Local-content beer, band D2 (70-80% local raw material) | L32: 22.09 | M32: Finance Act 2025 | N32: 2025-01-01 | O32: current | Q32: single | R32: ad_valorem | S32: 0.15 | T32: pct | U32: % of value | V32: value (legal base not observed; retail used as upper bound) | W32: 15% | X32: all | Y32: 20 | AC32: 70 | AD32: 80 | AF32: =IF(T32="USD",1,IF(T32="pct","",INDEX(Parameters!$D$5:$D$7,MATCH(B32,Parameters!$A$5:$A$7,0)))) | AG32: =IF(AND(R32="specific",ISNUMBER(S32)),S32/AF32,"") | AI32: =IF(NOT(ISNUMBER(AH32)),"",IF(R32="specific",IF(ISNUMBER(AG32),AG32*AH32,""),IF(AND(R32="ad_valorem",ISNUMBER(AJ32)),S32*AJ32/INDEX(Parameters!$D$5:$D$7,MATCH(B32,Parameters!$A$5:$A$7,0))*AH32,""))) | AL32: =IF(NOT(ISNUMBER(AJ32)),"",IF(R32="specific",S32/AJ32,IF(R32="ad_valorem",S32,""))) | AM32: verified | AN32: PR-26 | AO32: =IF(AM32="","",IFERROR(INDEX(DQ_Scale!$B$5:$B$14,MATCH(AM32,DQ_Scale!$A$5:$A$14,0)),"")) -> 5 | AP32: Not evaluated: outside representative 5% ABV
A33: SLE-029 | B33: SLE | C33: Sierra Leone | D33: 2026-04-27 | E33: 3 Health | F33: health | G33: A2 | H33: Beer, local-content concession (5% ABV) | I33: per LPA | J33: 1 | K33: Local-content beer, band D3 (60-70% local raw material) | L33: 22.09 | M33: Finance Act 2025 | N33: 2025-01-01 | O33: current | Q33: single | R33: ad_valorem | S33: 0.12 | T33: pct | U33: % of value | V33: value (legal base not observed; retail used as upper bound) | W33: 12% | X33: all | Z33: 10 | AC33: 60 | AD33: 70 | AF33: =IF(T33="USD",1,IF(T33="pct","",INDEX(Parameters!$D$5:$D$7,MATCH(B33,Parameters!$A$5:$A$7,0)))) | AG33: =IF(AND(R33="specific",ISNUMBER(S33)),S33/AF33,"") | AH33: 20 | AI33: =IF(NOT(ISNUMBER(AH33)),"",IF(R33="specific",IF(ISNUMBER(AG33),AG33*AH33,""),IF(AND(R33="ad_valorem",ISNUMBER(AJ33)),S33*AJ33/INDEX(Parameters!$D$5:$D$7,MATCH(B33,Parameters!$A$5:$A$7,0))*AH33,""))) -> 5.4545455 | AJ33: 50 | AK33: Beer NLe 50/l retail (upper bound) | AL33: =IF(NOT(ISNUMBER(AJ33)),"",IF(R33="specific",S33/AJ33,IF(R33="ad_valorem",S33,""))) -> 0.12 | AM33: verified | AN33: PR-26 | AO33: =IF(AM33="","",IFERROR(INDEX(DQ_Scale!$B$5:$B$14,MATCH(AM33,DQ_Scale!$A$5:$A$14,0)),"")) -> 5
A34: SLE-030 | B34: SLE | C34: Sierra Leone | D34: 2026-04-27 | E34: 3 Health | F34: health | G34: A2 | H34: Beer, local-content concession (5% ABV) | I34: per LPA | J34: 1 | K34: Local-content beer, band D3 (60-70% local raw material) | L34: 22.09 | M34: Finance Act 2025 | N34: 2025-01-01 | O34: current | Q34: single | R34: ad_valorem | S34: 0.15 | T34: pct | U34: % of value | V34: value (legal base not observed; retail used as upper bound) | W34: 15% | X34: all | Y34: 10 | Z34: 20 | AC34: 60 | AD34: 70 | AF34: =IF(T34="USD",1,IF(T34="pct","",INDEX(Parameters!$D$5:$D$7,MATCH(B34,Parameters!$A$5:$A$7,0)))) | AG34: =IF(AND(R34="specific",ISNUMBER(S34)),S34/AF34,"") | AI34: =IF(NOT(ISNUMBER(AH34)),"",IF(R34="specific",IF(ISNUMBER(AG34),AG34*AH34,""),IF(AND(R34="ad_valorem",ISNUMBER(AJ34)),S34*AJ34/INDEX(Parameters!$D$5:$D$7,MATCH(B34,Parameters!$A$5:$A$7,0))*AH34,""))) | AL34: =IF(NOT(ISNUMBER(AJ34)),"",IF(R34="specific",S34/AJ34,IF(R34="ad_valorem",S34,""))) | AM34: verified | AN34: PR-26 | AO34: =IF(AM34="","",IFERROR(INDEX(DQ_Scale!$B$5:$B$14,MATCH(AM34,DQ_Scale!$A$5:$A$14,0)),"")) -> 5 | AP34: Not evaluated: outside representative 5% ABV
A35: SLE-031 | B35: SLE | C35: Sierra Leone | D35: 2026-04-27 | E35: 3 Health | F35: health | G35: A2 | H35: Beer, local-content concession (5% ABV) | I35: per LPA | J35: 1 | K35: Local-content beer, band D3 (60-70% local raw material) | L35: 22.09 | M35: Finance Act 2025 | N35: 2025-01-01 | O35: current | Q35: single | R35: ad_valorem | S35: 0.175 | T35: pct | U35: % of value | V35: value (legal base not observed; retail used as upper bound) | W35: 17.5% | X35: all | Y35: 20 | AC35: 60 | AD35: 70 | AF35: =IF(T35="USD",1,IF(T35="pct","",INDEX(Parameters!$D$5:$D$7,MATCH(B35,Parameters!$A$5:$A$7,0)))) | AG35: =IF(AND(R35="specific",ISNUMBER(S35)),S35/AF35,"") | AI35: =IF(NOT(ISNUMBER(AH35)),"",IF(R35="specific",IF(ISNUMBER(AG35),AG35*AH35,""),IF(AND(R35="ad_valorem",ISNUMBER(AJ35)),S35*AJ35/INDEX(Parameters!$D$5:$D$7,MATCH(B35,Parameters!$A$5:$A$7,0))*AH35,""))) | AL35: =IF(NOT(ISNUMBER(AJ35)),"",IF(R35="specific",S35/AJ35,IF(R35="ad_valorem",S35,""))) | AM35: verified | AN35: PR-26 | AO35: =IF(AM35="","",IFERROR(INDEX(DQ_Scale!$B$5:$B$14,MATCH(AM35,DQ_Scale!$A$5:$A$14,0)),"")) -> 5 | AP35: Not evaluated: outside representative 5% ABV
A36: SLE-032 | B36: SLE | C36: Sierra Leone | D36: 2026-04-27 | E36: 3 Health | F36: health | G36: A2 | H36: Beer, local-content concession (5% ABV) | I36: per LPA | J36: 1 | K36: Local-content beer, band D4 (30-60% local raw material) | L36: 22.09 | M36: Finance Act 2025 | N36: 2025-01-01 | O36: current | Q36: single | R36: ad_valorem | S36: 0.15 | T36: pct | U36: % of value | V36: value (legal base not observed; retail used as upper bound) | W36: 15% | X36: all | Z36: 10 | AC36: 30 | AD36: 60 | AF36: =IF(T36="USD",1,IF(T36="pct","",INDEX(Parameters!$D$5:$D$7,MATCH(B36,Parameters!$A$5:$A$7,0)))) | AG36: =IF(AND(R36="specific",ISNUMBER(S36)),S36/AF36,"") | AH36: 20 | AI36: =IF(NOT(ISNUMBER(AH36)),"",IF(R36="specific",IF(ISNUMBER(AG36),AG36*AH36,""),IF(AND(R36="ad_valorem",ISNUMBER(AJ36)),S36*AJ36/INDEX(Parameters!$D$5:$D$7,MATCH(B36,Parameters!$A$5:$A$7,0))*AH36,""))) -> 6.8181818 | AJ36: 50 | AK36: Beer NLe 50/l retail (upper bound) | AL36: =IF(NOT(ISNUMBER(AJ36)),"",IF(R36="specific",S36/AJ36,IF(R36="ad_valorem",S36,""))) -> 0.15 | AM36: verified | AN36: PR-26 | AO36: =IF(AM36="","",IFERROR(INDEX(DQ_Scale!$B$5:$B$14,MATCH(AM36,DQ_Scale!$A$5:$A$14,0)),"")) -> 5
A37: SLE-033 | B37: SLE | C37: Sierra Leone | D37: 2026-04-27 | E37: 3 Health | F37: health | G37: A2 | H37: Beer, local-content concession (5% ABV) | I37: per LPA | J37: 1 | K37: Local-content beer, band D4 (30-60% local raw material) | L37: 22.09 | M37: Finance Act 2025 | N37: 2025-01-01 | O37: current | Q37: single | R37: ad_valorem | S37: 0.175 | T37: pct | U37: % of value | V37: value (legal base not observed; retail used as upper bound) | W37: 17.5% | X37: all | Y37: 10 | Z37: 20 | AC37: 30 | AD37: 60 | AF37: =IF(T37="USD",1,IF(T37="pct","",INDEX(Parameters!$D$5:$D$7,MATCH(B37,Parameters!$A$5:$A$7,0)))) | AG37: =IF(AND(R37="specific",ISNUMBER(S37)),S37/AF37,"") | AI37: =IF(NOT(ISNUMBER(AH37)),"",IF(R37="specific",IF(ISNUMBER(AG37),AG37*AH37,""),IF(AND(R37="ad_valorem",ISNUMBER(AJ37)),S37*AJ37/INDEX(Parameters!$D$5:$D$7,MATCH(B37,Parameters!$A$5:$A$7,0))*AH37,""))) | AL37: =IF(NOT(ISNUMBER(AJ37)),"",IF(R37="specific",S37/AJ37,IF(R37="ad_valorem",S37,""))) | AM37: verified | AN37: PR-26 | AO37: =IF(AM37="","",IFERROR(INDEX(DQ_Scale!$B$5:$B$14,MATCH(AM37,DQ_Scale!$A$5:$A$14,0)),"")) -> 5 | AP37: Not evaluated: outside representative 5% ABV
A38: SLE-034 | B38: SLE | C38: Sierra Leone | D38: 2026-04-27 | E38: 3 Health | F38: health | G38: A2 | H38: Beer, local-content concession (5% ABV) | I38: per LPA | J38: 1 | K38: Local-content beer, band D4 (30-60% local raw material) | L38: 22.09 | M38: Finance Act 2025 | N38: 2025-01-01 | O38: current | Q38: single | R38: ad_valorem | S38: 0.2 | T38: pct | U38: % of value | V38: value (legal base not observed; retail used as upper bound) | W38: 20% | X38: all | Y38: 20 | AC38: 30 | AD38: 60 | AF38: =IF(T38="USD",1,IF(T38="pct","",INDEX(Parameters!$D$5:$D$7,MATCH(B38,Parameters!$A$5:$A$7,0)))) | AG38: =IF(AND(R38="specific",ISNUMBER(S38)),S38/AF38,"") | AI38: =IF(NOT(ISNUMBER(AH38)),"",IF(R38="specific",IF(ISNUMBER(AG38),AG38*AH38,""),IF(AND(R38="ad_valorem",ISNUMBER(AJ38)),S38*AJ38/INDEX(Parameters!$D$5:$D$7,MATCH(B38,Parameters!$A$5:$A$7,0))*AH38,""))) | AL38: =IF(NOT(ISNUMBER(AJ38)),"",IF(R38="specific",S38/AJ38,IF(R38="ad_valorem",S38,""))) | AM38: verified | AN38: PR-26 | AO38: =IF(AM38="","",IFERROR(INDEX(DQ_Scale!$B$5:$B$14,MATCH(AM38,DQ_Scale!$A$5:$A$14,0)),"")) -> 5 | AP38: Not evaluated: outside representative 5% ABV
A39: SLE-035 | B39: SLE | C39: Sierra Leone | D39: 2026-04-27 | E39: 3 Health | F39: health | G39: A3 | H39: Traditional / opaque beer (4% ABV) | I39: per LPA | J39: 0 | K39: Traditional / opaque beer: not identified (largely informal) | O39: not_covered | R39: none | AF39: =IF(T39="USD",1,IF(T39="pct","",INDEX(Parameters!$D$5:$D$7,MATCH(B39,Parameters!$A$5:$A$7,0)))) -> 22 | AG39: =IF(AND(R39="specific",ISNUMBER(S39)),S39/AF39,"") | AI39: =IF(NOT(ISNUMBER(AH39)),"",IF(R39="specific",IF(ISNUMBER(AG39),AG39*AH39,""),IF(AND(R39="ad_valorem",ISNUMBER(AJ39)),S39*AJ39/INDEX(Parameters!$D$5:$D$7,MATCH(B39,Parameters!$A$5:$A$7,0))*AH39,""))) | AL39: =IF(NOT(ISNUMBER(AJ39)),"",IF(R39="specific",S39/AJ39,IF(R39="ad_valorem",S39,""))) | AM39: not_reviewed | AO39: =IF(AM39="","",IFERROR(INDEX(DQ_Scale!$B$5:$B$14,MATCH(AM39,DQ_Scale!$A$5:$A$14,0)),"")) -> 2 | AP39: WP Level 2: not identified. HS 2206 cider/perry/mead line exists (FA2023, last legible); mapped to A3 in this workbook, see rows below
A40: SLE-036 | B40: SLE | C40: Sierra Leone | D40: 2026-04-27 | E40: 3 Health | F40: health | G40: A3 | H40: Traditional / opaque beer (4% ABV) | I40: per LPA | J40: 1 | K40: Other fermented beverages: cider, perry, mead (<10% ABV) | L40: 2206 | M40: Finance Act 2023 s.3; replaced by FA2024 s.4(d), rows not legible | N40: 2023-04-01 | O40: last_legible | Q40: single | R40: specific | S40: 1.5 | T40: USD | U40: liter | W40: US$1.50 / l (FA2023) | X40: all | Z40: 10 | AF40: =IF(T40="USD",1,IF(T40="pct","",INDEX(Parameters!$D$5:$D$7,MATCH(B40,Parameters!$A$5:$A$7,0)))) -> 1 | AG40: =IF(AND(R40="specific",ISNUMBER(S40)),S40/AF40,"") -> 1.5 | AH40: 25 | AI40: =IF(NOT(ISNUMBER(AH40)),"",IF(R40="specific",IF(ISNUMBER(AG40),AG40*AH40,""),IF(AND(R40="ad_valorem",ISNUMBER(AJ40)),S40*AJ40/INDEX(Parameters!$D$5:$D$7,MATCH(B40,Parameters!$A$5:$A$7,0))*AH40,""))) -> 37.5 | AL40: =IF(NOT(ISNUMBER(AJ40)),"",IF(R40="specific",S40/AJ40,IF(R40="ad_valorem",S40,""))) | AM40: last_legible | AN40: PR-28 | AO40: =IF(AM40="","",IFERROR(INDEX(DQ_Scale!$B$5:$B$14,MATCH(AM40,DQ_Scale!$A$5:$A$14,0)),"")) -> 1 | AP40: Mapping rule: HS 2206 -> A3 (differs from WP Level 2)
A41: SLE-037 | B41: SLE | C41: Sierra Leone | D41: 2026-04-27 | E41: 3 Health | F41: health | G41: A3 | H41: Traditional / opaque beer (4% ABV) | I41: per LPA | J41: 1 | K41: Other fermented beverages: cider, perry, mead (10-20% ABV) | L41: 2206 | M41: Finance Act 2023 s.3; replaced by FA2024 s.4(d), rows not legible | N41: 2023-04-01 | O41: last_legible | Q41: single | R41: specific | S41: 2 | T41: USD | U41: liter | W41: US$2.00 / l (FA2023) | X41: all | Y41: 10 | Z41: 20 | AF41: =IF(T41="USD",1,IF(T41="pct","",INDEX(Parameters!$D$5:$D$7,MATCH(B41,Parameters!$A$5:$A$7,0)))) -> 1 | AG41: =IF(AND(R41="specific",ISNUMBER(S41)),S41/AF41,"") -> 2 | AI41: =IF(NOT(ISNUMBER(AH41)),"",IF(R41="specific",IF(ISNUMBER(AG41),AG41*AH41,""),IF(AND(R41="ad_valorem",ISNUMBER(AJ41)),S41*AJ41/INDEX(Parameters!$D$5:$D$7,MATCH(B41,Parameters!$A$5:$A$7,0))*AH41,""))) | AL41: =IF(NOT(ISNUMBER(AJ41)),"",IF(R41="specific",S41/AJ41,IF(R41="ad_valorem",S41,""))) | AM41: last_legible | AN41: PR-28 | AO41: =IF(AM41="","",IFERROR(INDEX(DQ_Scale!$B$5:$B$14,MATCH(AM41,DQ_Scale!$A$5:$A$14,0)),"")) -> 1
A42: SLE-038 | B42: SLE | C42: Sierra Leone | D42: 2026-04-27 | E42: 3 Health | F42: health | G42: A4 | H42: Wine (12% ABV) | I42: per LPA | J42: 1 | K42: Wine (HS 2204, 2205), local | L42: 2204, 2205 | M42: Finance Act 2024 s.4(b)-(c) | N42: 2024-01-01 | O42: current | Q42: single | R42: specific | S42: 4.2 | T42: NLe | U42: liter | W42: Le 4.2 / l local | X42: local | Z42: 10 | AF42: =IF(T42="USD",1,IF(T42="pct","",INDEX(Parameters!$D$5:$D$7,MATCH(B42,Parameters!$A$5:$A$7,0)))) -> 22 | AG42: =IF(AND(R42="specific",ISNUMBER(S42)),S42/AF42,"") -> 0.19090909 | AI42: =IF(NOT(ISNUMBER(AH42)),"",IF(R42="specific",IF(ISNUMBER(AG42),AG42*AH42,""),IF(AND(R42="ad_valorem",ISNUMBER(AJ42)),S42*AJ42/INDEX(Parameters!$D$5:$D$7,MATCH(B42,Parameters!$A$5:$A$7,0))*AH42,""))) | AL42: =IF(NOT(ISNUMBER(AJ42)),"",IF(R42="specific",S42/AJ42,IF(R42="ad_valorem",S42,""))) | AM42: verified | AN42: PR-24 | AO42: =IF(AM42="","",IFERROR(INDEX(DQ_Scale!$B$5:$B$14,MATCH(AM42,DQ_Scale!$A$5:$A$14,0)),"")) -> 5 | AP42: Not evaluated: outside representative 12% ABV; bands above 40% exceed any wine
A43: SLE-039 | B43: SLE | C43: Sierra Leone | D43: 2026-04-27 | E43: 3 Health | F43: health | G43: A4 | H43: Wine (12% ABV) | I43: per LPA | J43: 1 | K43: Wine (HS 2204, 2205), imported | L43: 2204, 2205 | M43: Finance Act 2024 s.4(b)-(c) | N43: 2024-01-01 | O43: current | Q43: single | R43: specific | S43: 10 | T43: NLe | U43: liter | W43: Le 10 / l imported | X43: imported | Z43: 10 | AF43: =IF(T43="USD",1,IF(T43="pct","",INDEX(Parameters!$D$5:$D$7,MATCH(B43,Parameters!$A$5:$A$7,0)))) -> 22 | AG43: =IF(AND(R43="specific",ISNUMBER(S43)),S43/AF43,"") -> 0.45454545 | AI43: =IF(NOT(ISNUMBER(AH43)),"",IF(R43="specific",IF(ISNUMBER(AG43),AG43*AH43,""),IF(AND(R43="ad_valorem",ISNUMBER(AJ43)),S43*AJ43/INDEX(Parameters!$D$5:$D$7,MATCH(B43,Parameters!$A$5:$A$7,0))*AH43,""))) | AL43: =IF(NOT(ISNUMBER(AJ43)),"",IF(R43="specific",S43/AJ43,IF(R43="ad_valorem",S43,""))) | AM43: verified | AN43: PR-24 | AO43: =IF(AM43="","",IFERROR(INDEX(DQ_Scale!$B$5:$B$14,MATCH(AM43,DQ_Scale!$A$5:$A$14,0)),"")) -> 5 | AP43: Not evaluated: outside representative 12% ABV; bands above 40% exceed any wine
A44: SLE-040 | B44: SLE | C44: Sierra Leone | D44: 2026-04-27 | E44: 3 Health | F44: health | G44: A4 | H44: Wine (12% ABV) | I44: per LPA | J44: 1 | K44: Wine (HS 2204, 2205), local | L44: 2204, 2205 | M44: Finance Act 2024 s.4(b)-(c) | N44: 2024-01-01 | O44: current | Q44: single | R44: specific | S44: 6.3 | T44: NLe | U44: liter | W44: Le 6.3 / l local | X44: local | Y44: 10 | Z44: 20 | AF44: =IF(T44="USD",1,IF(T44="pct","",INDEX(Parameters!$D$5:$D$7,MATCH(B44,Parameters!$A$5:$A$7,0)))) -> 22 | AG44: =IF(AND(R44="specific",ISNUMBER(S44)),S44/AF44,"") -> 0.28636364 | AH44: 8.3333333 | AI44: =IF(NOT(ISNUMBER(AH44)),"",IF(R44="specific",IF(ISNUMBER(AG44),AG44*AH44,""),IF(AND(R44="ad_valorem",ISNUMBER(AJ44)),S44*AJ44/INDEX(Parameters!$D$5:$D$7,MATCH(B44,Parameters!$A$5:$A$7,0))*AH44,""))) -> 2.3863636 | AL44: =IF(NOT(ISNUMBER(AJ44)),"",IF(R44="specific",S44/AJ44,IF(R44="ad_valorem",S44,""))) | AM44: verified | AN44: PR-24 | AO44: =IF(AM44="","",IFERROR(INDEX(DQ_Scale!$B$5:$B$14,MATCH(AM44,DQ_Scale!$A$5:$A$14,0)),"")) -> 5
A45: SLE-041 | B45: SLE | C45: Sierra Leone | D45: 2026-04-27 | E45: 3 Health | F45: health | G45: A4 | H45: Wine (12% ABV) | I45: per LPA | J45: 1 | K45: Wine (HS 2204, 2205), imported | L45: 2204, 2205 | M45: Finance Act 2024 s.4(b)-(c) | N45: 2024-01-01 | O45: current | Q45: single | R45: specific | S45: 12 | T45: NLe | U45: liter | W45: Le 12 / l imported | X45: imported | Y45: 10 | Z45: 20 | AF45: =IF(T45="USD",1,IF(T45="pct","",INDEX(Parameters!$D$5:$D$7,MATCH(B45,Parameters!$A$5:$A$7,0)))) -> 22 | AG45: =IF(AND(R45="specific",ISNUMBER(S45)),S45/AF45,"") -> 0.54545455 | AH45: 8.3333333 | AI45: =IF(NOT(ISNUMBER(AH45)),"",IF(R45="specific",IF(ISNUMBER(AG45),AG45*AH45,""),IF(AND(R45="ad_valorem",ISNUMBER(AJ45)),S45*AJ45/INDEX(Parameters!$D$5:$D$7,MATCH(B45,Parameters!$A$5:$A$7,0))*AH45,""))) -> 4.5454545 | AL45: =IF(NOT(ISNUMBER(AJ45)),"",IF(R45="specific",S45/AJ45,IF(R45="ad_valorem",S45,""))) | AM45: verified | AN45: PR-24 | AO45: =IF(AM45="","",IFERROR(INDEX(DQ_Scale!$B$5:$B$14,MATCH(AM45,DQ_Scale!$A$5:$A$14,0)),"")) -> 5
A46: SLE-042 | B46: SLE | C46: Sierra Leone | D46: 2026-04-27 | E46: 3 Health | F46: health | G46: A4 | H46: Wine (12% ABV) | I46: per LPA | J46: 1 | K46: Wine (HS 2204, 2205), local | L46: 2204, 2205 | M46: Finance Act 2024 s.4(b)-(c) | N46: 2024-01-01 | O46: current | Q46: single | R46: specific | S46: 8.3 | T46: NLe | U46: liter | W46: Le 8.3 / l local | X46: local | Y46: 20 | Z46: 30 | AF46: =IF(T46="USD",1,IF(T46="pct","",INDEX(Parameters!$D$5:$D$7,MATCH(B46,Parameters!$A$5:$A$7,0)))) -> 22 | AG46: =IF(AND(R46="specific",ISNUMBER(S46)),S46/AF46,"") -> 0.37727273 | AI46: =IF(NOT(ISNUMBER(AH46)),"",IF(R46="specific",IF(ISNUMBER(AG46),AG46*AH46,""),IF(AND(R46="ad_valorem",ISNUMBER(AJ46)),S46*AJ46/INDEX(Parameters!$D$5:$D$7,MATCH(B46,Parameters!$A$5:$A$7,0))*AH46,""))) | AL46: =IF(NOT(ISNUMBER(AJ46)),"",IF(R46="specific",S46/AJ46,IF(R46="ad_valorem",S46,""))) | AM46: verified | AN46: PR-24 | AO46: =IF(AM46="","",IFERROR(INDEX(DQ_Scale!$B$5:$B$14,MATCH(AM46,DQ_Scale!$A$5:$A$14,0)),"")) -> 5 | AP46: Not evaluated: outside representative 12% ABV; bands above 40% exceed any wine
A47: SLE-043 | B47: SLE | C47: Sierra Leone | D47: 2026-04-27 | E47: 3 Health | F47: health | G47: A4 | H47: Wine (12% ABV) | I47: per LPA | J47: 1 | K47: Wine (HS 2204, 2205), imported | L47: 2204, 2205 | M47: Finance Act 2024 s.4(b)-(c) | N47: 2024-01-01 | O47: current | Q47: single | R47: specific | S47: 14 | T47: NLe | U47: liter | W47: Le 14 / l imported | X47: imported | Y47: 20 | Z47: 30 | AF47: =IF(T47="USD",1,IF(T47="pct","",INDEX(Parameters!$D$5:$D$7,MATCH(B47,Parameters!$A$5:$A$7,0)))) -> 22 | AG47: =IF(AND(R47="specific",ISNUMBER(S47)),S47/AF47,"") -> 0.63636364 | AI47: =IF(NOT(ISNUMBER(AH47)),"",IF(R47="specific",IF(ISNUMBER(AG47),AG47*AH47,""),IF(AND(R47="ad_valorem",ISNUMBER(AJ47)),S47*AJ47/INDEX(Parameters!$D$5:$D$7,MATCH(B47,Parameters!$A$5:$A$7,0))*AH47,""))) | AL47: =IF(NOT(ISNUMBER(AJ47)),"",IF(R47="specific",S47/AJ47,IF(R47="ad_valorem",S47,""))) | AM47: verified | AN47: PR-24 | AO47: =IF(AM47="","",IFERROR(INDEX(DQ_Scale!$B$5:$B$14,MATCH(AM47,DQ_Scale!$A$5:$A$14,0)),"")) -> 5 | AP47: Not evaluated: outside representative 12% ABV; bands above 40% exceed any wine
A48: SLE-044 | B48: SLE | C48: Sierra Leone | D48: 2026-04-27 | E48: 3 Health | F48: health | G48: A4 | H48: Wine (12% ABV) | I48: per LPA | J48: 1 | K48: Wine (HS 2204, 2205), local | L48: 2204, 2205 | M48: Finance Act 2024 s.4(b)-(c) | N48: 2024-01-01 | O48: current | Q48: single | R48: specific | S48: 10.4 | T48: NLe | U48: liter | W48: Le 10.4 / l local | X48: local | Y48: 30 | Z48: 40 | AF48: =IF(T48="USD",1,IF(T48="pct","",INDEX(Parameters!$D$5:$D$7,MATCH(B48,Parameters!$A$5:$A$7,0)))) -> 22 | AG48: =IF(AND(R48="specific",ISNUMBER(S48)),S48/AF48,"") -> 0.47272727 | AI48: =IF(NOT(ISNUMBER(AH48)),"",IF(R48="specific",IF(ISNUMBER(AG48),AG48*AH48,""),IF(AND(R48="ad_valorem",ISNUMBER(AJ48)),S48*AJ48/INDEX(Parameters!$D$5:$D$7,MATCH(B48,Parameters!$A$5:$A$7,0))*AH48,""))) | AL48: =IF(NOT(ISNUMBER(AJ48)),"",IF(R48="specific",S48/AJ48,IF(R48="ad_valorem",S48,""))) | AM48: verified | AN48: PR-24 | AO48: =IF(AM48="","",IFERROR(INDEX(DQ_Scale!$B$5:$B$14,MATCH(AM48,DQ_Scale!$A$5:$A$14,0)),"")) -> 5 | AP48: Not evaluated: outside representative 12% ABV; bands above 40% exceed any wine
A49: SLE-045 | B49: SLE | C49: Sierra Leone | D49: 2026-04-27 | E49: 3 Health | F49: health | G49: A4 | H49: Wine (12% ABV) | I49: per LPA | J49: 1 | K49: Wine (HS 2204, 2205), imported | L49: 2204, 2205 | M49: Finance Act 2024 s.4(b)-(c) | N49: 2024-01-01 | O49: current | Q49: single | R49: specific | S49: 16 | T49: NLe | U49: liter | W49: Le 16 / l imported | X49: imported | Y49: 30 | Z49: 40 | AF49: =IF(T49="USD",1,IF(T49="pct","",INDEX(Parameters!$D$5:$D$7,MATCH(B49,Parameters!$A$5:$A$7,0)))) -> 22 | AG49: =IF(AND(R49="specific",ISNUMBER(S49)),S49/AF49,"") -> 0.72727273 | AI49: =IF(NOT(ISNUMBER(AH49)),"",IF(R49="specific",IF(ISNUMBER(AG49),AG49*AH49,""),IF(AND(R49="ad_valorem",ISNUMBER(AJ49)),S49*AJ49/INDEX(Parameters!$D$5:$D$7,MATCH(B49,Parameters!$A$5:$A$7,0))*AH49,""))) | AL49: =IF(NOT(ISNUMBER(AJ49)),"",IF(R49="specific",S49/AJ49,IF(R49="ad_valorem",S49,""))) | AM49: verified | AN49: PR-24 | AO49: =IF(AM49="","",IFERROR(INDEX(DQ_Scale!$B$5:$B$14,MATCH(AM49,DQ_Scale!$A$5:$A$14,0)),"")) -> 5 | AP49: Not evaluated: outside representative 12% ABV; bands above 40% exceed any wine
A50: SLE-046 | B50: SLE | C50: Sierra Leone | D50: 2026-04-27 | E50: 3 Health | F50: health | G50: A4 | H50: Wine (12% ABV) | I50: per LPA | J50: 1 | K50: Wine (HS 2204, 2205), local | L50: 2204, 2205 | M50: Finance Act 2024 s.4(b)-(c) | N50: 2024-01-01 | O50: current | Q50: single | R50: specific | S50: 15 | T50: NLe | U50: liter | W50: Le 15 / l local | X50: local | Y50: 40 | AF50: =IF(T50="USD",1,IF(T50="pct","",INDEX(Parameters!$D$5:$D$7,MATCH(B50,Parameters!$A$5:$A$7,0)))) -> 22 | AG50: =IF(AND(R50="specific",ISNUMBER(S50)),S50/AF50,"") -> 0.68181818 | AI50: =IF(NOT(ISNUMBER(AH50)),"",IF(R50="specific",IF(ISNUMBER(AG50),AG50*AH50,""),IF(AND(R50="ad_valorem",ISNUMBER(AJ50)),S50*AJ50/INDEX(Parameters!$D$5:$D$7,MATCH(B50,Parameters!$A$5:$A$7,0))*AH50,""))) | AL50: =IF(NOT(ISNUMBER(AJ50)),"",IF(R50="specific",S50/AJ50,IF(R50="ad_valorem",S50,""))) | AM50: verified | AN50: PR-24 | AO50: =IF(AM50="","",IFERROR(INDEX(DQ_Scale!$B$5:$B$14,MATCH(AM50,DQ_Scale!$A$5:$A$14,0)),"")) -> 5 | AP50: Not evaluated: outside representative 12% ABV; bands above 40% exceed any wine
A51: SLE-047 | B51: SLE | C51: Sierra Leone | D51: 2026-04-27 | E51: 3 Health | F51: health | G51: A4 | H51: Wine (12% ABV) | I51: per LPA | J51: 1 | K51: Wine (HS 2204, 2205), imported | L51: 2204, 2205 | M51: Finance Act 2024 s.4(b)-(c) | N51: 2024-01-01 | O51: current | Q51: single | R51: specific | S51: 22 | T51: NLe | U51: liter | W51: Le 22 / l imported | X51: imported | Y51: 40 | AF51: =IF(T51="USD",1,IF(T51="pct","",INDEX(Parameters!$D$5:$D$7,MATCH(B51,Parameters!$A$5:$A$7,0)))) -> 22 | AG51: =IF(AND(R51="specific",ISNUMBER(S51)),S51/AF51,"") -> 1 | AI51: =IF(NOT(ISNUMBER(AH51)),"",IF(R51="specific",IF(ISNUMBER(AG51),AG51*AH51,""),IF(AND(R51="ad_valorem",ISNUMBER(AJ51)),S51*AJ51/INDEX(Parameters!$D$5:$D$7,MATCH(B51,Parameters!$A$5:$A$7,0))*AH51,""))) | AL51: =IF(NOT(ISNUMBER(AJ51)),"",IF(R51="specific",S51/AJ51,IF(R51="ad_valorem",S51,""))) | AM51: verified | AN51: PR-24 | AO51: =IF(AM51="","",IFERROR(INDEX(DQ_Scale!$B$5:$B$14,MATCH(AM51,DQ_Scale!$A$5:$A$14,0)),"")) -> 5 | AP51: Not evaluated: outside representative 12% ABV; bands above 40% exceed any wine
A52: SLE-048 | B52: SLE | C52: Sierra Leone | D52: 2026-04-27 | E52: 3 Health | F52: health | G52: A5 | H52: Spirits (40% ABV) | I52: per LPA | J52: 1 | K52: Spirits: brandy, whisky, rum, gin, vodka, liqueurs (10-20% ABV) | L52: 2208 | M52: Finance Act 2023 s.3; replaced by FA2024 s.4(e), rows not legible | N52: 2023-04-01 | O52: last_legible | Q52: single | R52: specific | S52: 2 | T52: USD | U52: liter | W52: US$2.00 / l (FA2023) | X52: all | Y52: 10 | Z52: 20 | AF52: =IF(T52="USD",1,IF(T52="pct","",INDEX(Parameters!$D$5:$D$7,MATCH(B52,Parameters!$A$5:$A$7,0)))) -> 1 | AG52: =IF(AND(R52="specific",ISNUMBER(S52)),S52/AF52,"") -> 2 | AI52: =IF(NOT(ISNUMBER(AH52)),"",IF(R52="specific",IF(ISNUMBER(AG52),AG52*AH52,""),IF(AND(R52="ad_valorem",ISNUMBER(AJ52)),S52*AJ52/INDEX(Parameters!$D$5:$D$7,MATCH(B52,Parameters!$A$5:$A$7,0))*AH52,""))) | AL52: =IF(NOT(ISNUMBER(AJ52)),"",IF(R52="specific",S52/AJ52,IF(R52="ad_valorem",S52,""))) | AM52: last_legible | AN52: PR-27 | AO52: =IF(AM52="","",IFERROR(INDEX(DQ_Scale!$B$5:$B$14,MATCH(AM52,DQ_Scale!$A$5:$A$14,0)),"")) -> 1 | AP52: ABV band 10-20%: not converted to LPA (representative spirits ABV is 40%)
A53: SLE-049 | B53: SLE | C53: Sierra Leone | D53: 2026-04-27 | E53: 3 Health | F53: health | G53: A5 | H53: Spirits (40% ABV) | I53: per LPA | J53: 1 | K53: Spirits (>20% ABV) | L53: 2208 | M53: Finance Act 2023 s.3; replaced by FA2024 s.4(e), rows not legible | N53: 2023-04-01 | O53: last_legible | Q53: single | R53: specific | S53: 3 | T53: USD | U53: liter | W53: US$3.00 / l (FA2023) | X53: all | Y53: 20 | AF53: =IF(T53="USD",1,IF(T53="pct","",INDEX(Parameters!$D$5:$D$7,MATCH(B53,Parameters!$A$5:$A$7,0)))) -> 1 | AG53: =IF(AND(R53="specific",ISNUMBER(S53)),S53/AF53,"") -> 3 | AH53: 2.5 | AI53: =IF(NOT(ISNUMBER(AH53)),"",IF(R53="specific",IF(ISNUMBER(AG53),AG53*AH53,""),IF(AND(R53="ad_valorem",ISNUMBER(AJ53)),S53*AJ53/INDEX(Parameters!$D$5:$D$7,MATCH(B53,Parameters!$A$5:$A$7,0))*AH53,""))) -> 7.5 | AL53: =IF(NOT(ISNUMBER(AJ53)),"",IF(R53="specific",S53/AJ53,IF(R53="ad_valorem",S53,""))) | AM53: last_legible | AN53: PR-27 | AO53: =IF(AM53="","",IFERROR(INDEX(DQ_Scale!$B$5:$B$14,MATCH(AM53,DQ_Scale!$A$5:$A$14,0)),"")) -> 1
A54: SLE-050 | B54: SLE | C54: Sierra Leone | D54: 2026-04-27 | E54: 3 Health | F54: health | G54: A5 | H54: Spirits (40% ABV) | I54: per LPA | J54: 1 | K54: Ethyl alcohol, extra-neutral (>=95%) | L54: 2207 | M54: Finance Act 2023 s.3; replaced by FA2024 s.4(f), rows not legible | N54: 2023-04-01 | O54: last_legible | Q54: single | R54: specific | S54: 3 | T54: USD | U54: liter | W54: US$3.00 / l (FA2023) | X54: all | Y54: 95 | AF54: =IF(T54="USD",1,IF(T54="pct","",INDEX(Parameters!$D$5:$D$7,MATCH(B54,Parameters!$A$5:$A$7,0)))) -> 1 | AG54: =IF(AND(R54="specific",ISNUMBER(S54)),S54/AF54,"") -> 3 | AI54: =IF(NOT(ISNUMBER(AH54)),"",IF(R54="specific",IF(ISNUMBER(AG54),AG54*AH54,""),IF(AND(R54="ad_valorem",ISNUMBER(AJ54)),S54*AJ54/INDEX(Parameters!$D$5:$D$7,MATCH(B54,Parameters!$A$5:$A$7,0))*AH54,""))) | AL54: =IF(NOT(ISNUMBER(AJ54)),"",IF(R54="specific",S54/AJ54,IF(R54="ad_valorem",S54,""))) | AM54: last_legible | AN54: PR-28 | AO54: =IF(AM54="","",IFERROR(INDEX(DQ_Scale!$B$5:$B$14,MATCH(AM54,DQ_Scale!$A$5:$A$14,0)),"")) -> 1 | AP54: Industrial/neutral alcohol; mapped to A5
A55: SLE-051 | B55: SLE | C55: Sierra Leone | D55: 2026-04-27 | E55: 3 Health | F55: health | G55: S1 | H55: Carbonated and other soft drinks | I55: per liter | J55: 1 | K55: Other non-alcoholic beverages incl. bottled waters | L55: 20.09 | M55: Finance Act 2023 s.3(g); replaced by FA2024 s.4(h), rows not legible | N55: 2023-04-01 | O55: last_legible | Q55: single | R55: specific | S55: 0.1 | T55: USD | U55: liter | W55: US$0.10 / l (FA2023) | X55: all | AB55: 15 | AF55: =IF(T55="USD",1,IF(T55="pct","",INDEX(Parameters!$D$5:$D$7,MATCH(B55,Parameters!$A$5:$A$7,0)))) -> 1 | AG55: =IF(AND(R55="specific",ISNUMBER(S55)),S55/AF55,"") -> 0.1 | AH55: 1 | AI55: =IF(NOT(ISNUMBER(AH55)),"",IF(R55="specific",IF(ISNUMBER(AG55),AG55*AH55,""),IF(AND(R55="ad_valorem",ISNUMBER(AJ55)),S55*AJ55/INDEX(Parameters!$D$5:$D$7,MATCH(B55,Parameters!$A$5:$A$7,0))*AH55,""))) -> 0.1 | AL55: =IF(NOT(ISNUMBER(AJ55)),"",IF(R55="specific",S55/AJ55,IF(R55="ad_valorem",S55,""))) | AM55: last_legible | AN55: PR-29, PR-31 | AO55: =IF(AM55="","",IFERROR(INDEX(DQ_Scale!$B$5:$B$14,MATCH(AM55,DQ_Scale!$A$5:$A$14,0)),"")) -> 1 | AP55: Sugar-graduated, origin-neutral
A56: SLE-052 | B56: SLE | C56: Sierra Leone | D56: 2026-04-27 | E56: 3 Health | F56: health | G56: S1 | H56: Carbonated and other soft drinks | I56: per liter | J56: 1 | K56: Other non-alcoholic beverages incl. bottled waters | L56: 20.09 | M56: Finance Act 2023 s.3(g); replaced by FA2024 s.4(h), rows not legible | N56: 2023-04-01 | O56: last_legible | Q56: single | R56: specific | S56: 0.3 | T56: USD | U56: liter | W56: US$0.30 / l (FA2023) | X56: all | AA56: 15 | AB56: 25 | AF56: =IF(T56="USD",1,IF(T56="pct","",INDEX(Parameters!$D$5:$D$7,MATCH(B56,Parameters!$A$5:$A$7,0)))) -> 1 | AG56: =IF(AND(R56="specific",ISNUMBER(S56)),S56/AF56,"") -> 0.3 | AH56: 1 | AI56: =IF(NOT(ISNUMBER(AH56)),"",IF(R56="specific",IF(ISNUMBER(AG56),AG56*AH56,""),IF(AND(R56="ad_valorem",ISNUMBER(AJ56)),S56*AJ56/INDEX(Parameters!$D$5:$D$7,MATCH(B56,Parameters!$A$5:$A$7,0))*AH56,""))) -> 0.3 | AL56: =IF(NOT(ISNUMBER(AJ56)),"",IF(R56="specific",S56/AJ56,IF(R56="ad_valorem",S56,""))) | AM56: last_legible | AN56: PR-29, PR-31 | AO56: =IF(AM56="","",IFERROR(INDEX(DQ_Scale!$B$5:$B$14,MATCH(AM56,DQ_Scale!$A$5:$A$14,0)),"")) -> 1 | AP56: Sugar-graduated, origin-neutral
A57: SLE-053 | B57: SLE | C57: Sierra Leone | D57: 2026-04-27 | E57: 3 Health | F57: health | G57: S1 | H57: Carbonated and other soft drinks | I57: per liter | J57: 1 | K57: Other non-alcoholic beverages incl. bottled waters | L57: 20.09 | M57: Finance Act 2023 s.3(g); replaced by FA2024 s.4(h), rows not legible | N57: 2023-04-01 | O57: last_legible | Q57: single | R57: specific | S57: 0.5 | T57: USD | U57: liter | W57: US$0.50 / l (FA2023) | X57: all | AA57: 25 | AF57: =IF(T57="USD",1,IF(T57="pct","",INDEX(Parameters!$D$5:$D$7,MATCH(B57,Parameters!$A$5:$A$7,0)))) -> 1 | AG57: =IF(AND(R57="specific",ISNUMBER(S57)),S57/AF57,"") -> 0.5 | AH57: 1 | AI57: =IF(NOT(ISNUMBER(AH57)),"",IF(R57="specific",IF(ISNUMBER(AG57),AG57*AH57,""),IF(AND(R57="ad_valorem",ISNUMBER(AJ57)),S57*AJ57/INDEX(Parameters!$D$5:$D$7,MATCH(B57,Parameters!$A$5:$A$7,0))*AH57,""))) -> 0.5 | AL57: =IF(NOT(ISNUMBER(AJ57)),"",IF(R57="specific",S57/AJ57,IF(R57="ad_valorem",S57,""))) | AM57: last_legible | AN57: PR-29, PR-31 | AO57: =IF(AM57="","",IFERROR(INDEX(DQ_Scale!$B$5:$B$14,MATCH(AM57,DQ_Scale!$A$5:$A$14,0)),"")) -> 1 | AP57: Sugar-graduated, origin-neutral
A58: SLE-054 | B58: SLE | C58: Sierra Leone | D58: 2026-04-27 | E58: 3 Health | F58: health | G58: S2 | H58: Fruit and vegetable juice | I58: per liter | J58: 1 | K58: Fruit and vegetable juice | L58: 20.09 | M58: Finance Act 2023 s.3(g); replaced by FA2024 s.4(h), rows not legible | N58: 2023-04-01 | O58: last_legible | Q58: single | R58: specific | S58: 0 | T58: USD | U58: liter | W58: US$0.00 / l (FA2023) | X58: all | AB58: 5 | AF58: =IF(T58="USD",1,IF(T58="pct","",INDEX(Parameters!$D$5:$D$7,MATCH(B58,Parameters!$A$5:$A$7,0)))) -> 1 | AG58: =IF(AND(R58="specific",ISNUMBER(S58)),S58/AF58,"") -> 0 | AH58: 1 | AI58: =IF(NOT(ISNUMBER(AH58)),"",IF(R58="specific",IF(ISNUMBER(AG58),AG58*AH58,""),IF(AND(R58="ad_valorem",ISNUMBER(AJ58)),S58*AJ58/INDEX(Parameters!$D$5:$D$7,MATCH(B58,Parameters!$A$5:$A$7,0))*AH58,""))) -> 0 | AL58: =IF(NOT(ISNUMBER(AJ58)),"",IF(R58="specific",S58/AJ58,IF(R58="ad_valorem",S58,""))) | AM58: last_legible | AN58: PR-30 | AO58: =IF(AM58="","",IFERROR(INDEX(DQ_Scale!$B$5:$B$14,MATCH(AM58,DQ_Scale!$A$5:$A$14,0)),"")) -> 1 | AP58: Superseded FA2020 20% on imported juice
A59: SLE-055 | B59: SLE | C59: Sierra Leone | D59: 2026-04-27 | E59: 3 Health | F59: health | G59: S2 | H59: Fruit and vegetable juice | I59: per liter | J59: 1 | K59: Fruit and vegetable juice | L59: 20.09 | M59: Finance Act 2023 s.3(g); replaced by FA2024 s.4(h), rows not legible | N59: 2023-04-01 | O59: last_legible | Q59: single | R59: specific | S59: 0.1 | T59: USD | U59: liter | W59: US$0.10 / l (FA2023) | X59: all | AA59: 5 | AB59: 15 | AF59: =IF(T59="USD",1,IF(T59="pct","",INDEX(Parameters!$D$5:$D$7,MATCH(B59,Parameters!$A$5:$A$7,0)))) -> 1 | AG59: =IF(AND(R59="specific",ISNUMBER(S59)),S59/AF59,"") -> 0.1 | AH59: 1 | AI59: =IF(NOT(ISNUMBER(AH59)),"",IF(R59="specific",IF(ISNUMBER(AG59),AG59*AH59,""),IF(AND(R59="ad_valorem",ISNUMBER(AJ59)),S59*AJ59/INDEX(Parameters!$D$5:$D$7,MATCH(B59,Parameters!$A$5:$A$7,0))*AH59,""))) -> 0.1 | AL59: =IF(NOT(ISNUMBER(AJ59)),"",IF(R59="specific",S59/AJ59,IF(R59="ad_valorem",S59,""))) | AM59: last_legible | AN59: PR-30 | AO59: =IF(AM59="","",IFERROR(INDEX(DQ_Scale!$B$5:$B$14,MATCH(AM59,DQ_Scale!$A$5:$A$14,0)),"")) -> 1 | AP59: Superseded FA2020 20% on imported juice
A60: SLE-056 | B60: SLE | C60: Sierra Leone | D60: 2026-04-27 | E60: 3 Health | F60: health | G60: S2 | H60: Fruit and vegetable juice | I60: per liter | J60: 1 | K60: Fruit and vegetable juice | L60: 20.09 | M60: Finance Act 2023 s.3(g); replaced by FA2024 s.4(h), rows not legible | N60: 2023-04-01 | O60: last_legible | Q60: single | R60: specific | S60: 0.3 | T60: USD | U60: liter | W60: US$0.30 / l (FA2023) | X60: all | AA60: 15 | AB60: 25 | AF60: =IF(T60="USD",1,IF(T60="pct","",INDEX(Parameters!$D$5:$D$7,MATCH(B60,Parameters!$A$5:$A$7,0)))) -> 1 | AG60: =IF(AND(R60="specific",ISNUMBER(S60)),S60/AF60,"") -> 0.3 | AH60: 1 | AI60: =IF(NOT(ISNUMBER(AH60)),"",IF(R60="specific",IF(ISNUMBER(AG60),AG60*AH60,""),IF(AND(R60="ad_valorem",ISNUMBER(AJ60)),S60*AJ60/INDEX(Parameters!$D$5:$D$7,MATCH(B60,Parameters!$A$5:$A$7,0))*AH60,""))) -> 0.3 | AL60: =IF(NOT(ISNUMBER(AJ60)),"",IF(R60="specific",S60/AJ60,IF(R60="ad_valorem",S60,""))) | AM60: last_legible | AN60: PR-30 | AO60: =IF(AM60="","",IFERROR(INDEX(DQ_Scale!$B$5:$B$14,MATCH(AM60,DQ_Scale!$A$5:$A$14,0)),"")) -> 1 | AP60: Superseded FA2020 20% on imported juice
A61: SLE-057 | B61: SLE | C61: Sierra Leone | D61: 2026-04-27 | E61: 3 Health | F61: health | G61: S2 | H61: Fruit and vegetable juice | I61: per liter | J61: 1 | K61: Fruit and vegetable juice | L61: 20.09 | M61: Finance Act 2023 s.3(g); replaced by FA2024 s.4(h), rows not legible | N61: 2023-04-01 | O61: last_legible | Q61: single | R61: specific | S61: 0.5 | T61: USD | U61: liter | W61: US$0.50 / l (FA2023) | X61: all | AA61: 25 | AF61: =IF(T61="USD",1,IF(T61="pct","",INDEX(Parameters!$D$5:$D$7,MATCH(B61,Parameters!$A$5:$A$7,0)))) -> 1 | AG61: =IF(AND(R61="specific",ISNUMBER(S61)),S61/AF61,"") -> 0.5 | AH61: 1 | AI61: =IF(NOT(ISNUMBER(AH61)),"",IF(R61="specific",IF(ISNUMBER(AG61),AG61*AH61,""),IF(AND(R61="ad_valorem",ISNUMBER(AJ61)),S61*AJ61/INDEX(Parameters!$D$5:$D$7,MATCH(B61,Parameters!$A$5:$A$7,0))*AH61,""))) -> 0.5 | AL61: =IF(NOT(ISNUMBER(AJ61)),"",IF(R61="specific",S61/AJ61,IF(R61="ad_valorem",S61,""))) | AM61: last_legible | AN61: PR-30 | AO61: =IF(AM61="","",IFERROR(INDEX(DQ_Scale!$B$5:$B$14,MATCH(AM61,DQ_Scale!$A$5:$A$14,0)),"")) -> 1 | AP61: Superseded FA2020 20% on imported juice
A62: SLE-058 | B62: SLE | C62: Sierra Leone | D62: 2026-04-27 | E62: 3 Health | F62: health | G62: S3 | H62: Energy drinks | I62: per liter | J62: 1 | K62: Energy drinks (within other non-alcoholic beverages) | L62: 20.09 | M62: Finance Act 2023 s.3(g); replaced by FA2024 s.4(h), rows not legible | N62: 2023-04-01 | O62: last_legible | Q62: single | R62: specific | S62: 0.1 | T62: USD | U62: liter | W62: US$0.10 / l (FA2023) | X62: all | AB62: 15 | AF62: =IF(T62="USD",1,IF(T62="pct","",INDEX(Parameters!$D$5:$D$7,MATCH(B62,Parameters!$A$5:$A$7,0)))) -> 1 | AG62: =IF(AND(R62="specific",ISNUMBER(S62)),S62/AF62,"") -> 0.1 | AH62: 1 | AI62: =IF(NOT(ISNUMBER(AH62)),"",IF(R62="specific",IF(ISNUMBER(AG62),AG62*AH62,""),IF(AND(R62="ad_valorem",ISNUMBER(AJ62)),S62*AJ62/INDEX(Parameters!$D$5:$D$7,MATCH(B62,Parameters!$A$5:$A$7,0))*AH62,""))) -> 0.1 | AL62: =IF(NOT(ISNUMBER(AJ62)),"",IF(R62="specific",S62/AJ62,IF(R62="ad_valorem",S62,""))) | AM62: last_legible | AN62: PR-29, PR-31 | AO62: =IF(AM62="","",IFERROR(INDEX(DQ_Scale!$B$5:$B$14,MATCH(AM62,DQ_Scale!$A$5:$A$14,0)),"")) -> 1 | AP62: Sugar-graduated, origin-neutral
A63: SLE-059 | B63: SLE | C63: Sierra Leone | D63: 2026-04-27 | E63: 3 Health | F63: health | G63: S3 | H63: Energy drinks | I63: per liter | J63: 1 | K63: Energy drinks (within other non-alcoholic beverages) | L63: 20.09 | M63: Finance Act 2023 s.3(g); replaced by FA2024 s.4(h), rows not legible | N63: 2023-04-01 | O63: last_legible | Q63: single | R63: specific | S63: 0.3 | T63: USD | U63: liter | W63: US$0.30 / l (FA2023) | X63: all | AA63: 15 | AB63: 25 | AF63: =IF(T63="USD",1,IF(T63="pct","",INDEX(Parameters!$D$5:$D$7,MATCH(B63,Parameters!$A$5:$A$7,0)))) -> 1 | AG63: =IF(AND(R63="specific",ISNUMBER(S63)),S63/AF63,"") -> 0.3 | AH63: 1 | AI63: =IF(NOT(ISNUMBER(AH63)),"",IF(R63="specific",IF(ISNUMBER(AG63),AG63*AH63,""),IF(AND(R63="ad_valorem",ISNUMBER(AJ63)),S63*AJ63/INDEX(Parameters!$D$5:$D$7,MATCH(B63,Parameters!$A$5:$A$7,0))*AH63,""))) -> 0.3 | AL63: =IF(NOT(ISNUMBER(AJ63)),"",IF(R63="specific",S63/AJ63,IF(R63="ad_valorem",S63,""))) | AM63: last_legible | AN63: PR-29, PR-31 | AO63: =IF(AM63="","",IFERROR(INDEX(DQ_Scale!$B$5:$B$14,MATCH(AM63,DQ_Scale!$A$5:$A$14,0)),"")) -> 1 | AP63: Sugar-graduated, origin-neutral
A64: SLE-060 | B64: SLE | C64: Sierra Leone | D64: 2026-04-27 | E64: 3 Health | F64: health | G64: S3 | H64: Energy drinks | I64: per liter | J64: 1 | K64: Energy drinks (within other non-alcoholic beverages) | L64: 20.09 | M64: Finance Act 2023 s.3(g); replaced by FA2024 s.4(h), rows not legible | N64: 2023-04-01 | O64: last_legible | Q64: single | R64: specific | S64: 0.5 | T64: USD | U64: liter | W64: US$0.50 / l (FA2023) | X64: all | AA64: 25 | AF64: =IF(T64="USD",1,IF(T64="pct","",INDEX(Parameters!$D$5:$D$7,MATCH(B64,Parameters!$A$5:$A$7,0)))) -> 1 | AG64: =IF(AND(R64="specific",ISNUMBER(S64)),S64/AF64,"") -> 0.5 | AH64: 1 | AI64: =IF(NOT(ISNUMBER(AH64)),"",IF(R64="specific",IF(ISNUMBER(AG64),AG64*AH64,""),IF(AND(R64="ad_valorem",ISNUMBER(AJ64)),S64*AJ64/INDEX(Parameters!$D$5:$D$7,MATCH(B64,Parameters!$A$5:$A$7,0))*AH64,""))) -> 0.5 | AL64: =IF(NOT(ISNUMBER(AJ64)),"",IF(R64="specific",S64/AJ64,IF(R64="ad_valorem",S64,""))) | AM64: last_legible | AN64: PR-29, PR-31 | AO64: =IF(AM64="","",IFERROR(INDEX(DQ_Scale!$B$5:$B$14,MATCH(AM64,DQ_Scale!$A$5:$A$14,0)),"")) -> 1 | AP64: Sugar-graduated, origin-neutral
A65: SLE-061 | B65: SLE | C65: Sierra Leone | D65: 2026-04-27 | E65: 3 Health | F65: health | G65: S4 | H65: Bottled and processed water | I65: per liter | J65: 1 | K65: Bottled or similarly packaged waters (<15 g/l sugar) | L65: 20.09 | M65: Finance Act 2023 s.3(g); replaced by FA2024 s.4(h), rows not legible | N65: 2023-04-01 | O65: last_legible | Q65: single | R65: specific | S65: 0.1 | T65: USD | U65: liter | W65: US$0.10 / l (FA2023) | X65: all | AB65: 15 | AF65: =IF(T65="USD",1,IF(T65="pct","",INDEX(Parameters!$D$5:$D$7,MATCH(B65,Parameters!$A$5:$A$7,0)))) -> 1 | AG65: =IF(AND(R65="specific",ISNUMBER(S65)),S65/AF65,"") -> 0.1 | AH65: 1 | AI65: =IF(NOT(ISNUMBER(AH65)),"",IF(R65="specific",IF(ISNUMBER(AG65),AG65*AH65,""),IF(AND(R65="ad_valorem",ISNUMBER(AJ65)),S65*AJ65/INDEX(Parameters!$D$5:$D$7,MATCH(B65,Parameters!$A$5:$A$7,0))*AH65,""))) -> 0.1 | AL65: =IF(NOT(ISNUMBER(AJ65)),"",IF(R65="specific",S65/AJ65,IF(R65="ad_valorem",S65,""))) | AM65: last_legible | AN65: PR-29 | AO65: =IF(AM65="","",IFERROR(INDEX(DQ_Scale!$B$5:$B$14,MATCH(AM65,DQ_Scale!$A$5:$A$14,0)),"")) -> 1
A66: SLE-062 | B66: SLE | C66: Sierra Leone | D66: 2026-04-27 | E66: 3 Health | F66: health | G66: G1 | H66: Gambling, betting and lotteries | I66: % of base | J66: 1 | K66: Gambling, betting and lottery services | L66: 98.01 | M66: Finance Act 2024 s.4(m) | N66: 2024-01-01 | O66: current | Q66: single | R66: ad_valorem | S66: 0.1 | T66: pct | U66: % of base | V66: net wagered (stakes less winnings) | W66: 10% of net wagered | X66: all | AF66: =IF(T66="USD",1,IF(T66="pct","",INDEX(Parameters!$D$5:$D$7,MATCH(B66,Parameters!$A$5:$A$7,0)))) | AG66: =IF(AND(R66="specific",ISNUMBER(S66)),S66/AF66,"") | AI66: =IF(NOT(ISNUMBER(AH66)),"",IF(R66="specific",IF(ISNUMBER(AG66),AG66*AH66,""),IF(AND(R66="ad_valorem",ISNUMBER(AJ66)),S66*AJ66/INDEX(Parameters!$D$5:$D$7,MATCH(B66,Parameters!$A$5:$A$7,0))*AH66,""))) | AL66: =IF(NOT(ISNUMBER(AJ66)),"",IF(R66="specific",S66/AJ66,IF(R66="ad_valorem",S66,""))) | AM66: verified | AN66: PR-32 | AO66: =IF(AM66="","",IFERROR(INDEX(DQ_Scale!$B$5:$B$14,MATCH(AM66,DQ_Scale!$A$5:$A$14,0)),"")) -> 5
A67: SLE-063 | B67: SLE | C67: Sierra Leone | D67: 2026-04-27 | E67: 4 Other | F67: telecoms_digital | G67: D1 | H67: Voice and airtime | I67: per minute / % of fee | J67: 2 | K67: Cellular surcharge: on-net voice | M67: Finance Act 2023 s.13 (cellular surcharge) | N67: 2023-04-01 | O67: current | Q67: single | R67: specific | S67: 0.1 | T67: NLe | U67: call unit (per minute not stated) | W67: NLe 0.10 | X67: all | AF67: =IF(T67="USD",1,IF(T67="pct","",INDEX(Parameters!$D$5:$D$7,MATCH(B67,Parameters!$A$5:$A$7,0)))) -> 22 | AG67: =IF(AND(R67="specific",ISNUMBER(S67)),S67/AF67,"") -> 0.0045454545 | AH67: 1 | AI67: =IF(NOT(ISNUMBER(AH67)),"",IF(R67="specific",IF(ISNUMBER(AG67),AG67*AH67,""),IF(AND(R67="ad_valorem",ISNUMBER(AJ67)),S67*AJ67/INDEX(Parameters!$D$5:$D$7,MATCH(B67,Parameters!$A$5:$A$7,0))*AH67,""))) -> 0.0045454545 | AL67: =IF(NOT(ISNUMBER(AJ67)),"",IF(R67="specific",S67/AJ67,IF(R67="ad_valorem",S67,""))) | AM67: corrected | AN67: PR-36 | AO67: =IF(AM67="","",IFERROR(INDEX(DQ_Scale!$B$5:$B$14,MATCH(AM67,DQ_Scale!$A$5:$A$14,0)),"")) -> 4
A68: SLE-064 | B68: SLE | C68: Sierra Leone | D68: 2026-04-27 | E68: 4 Other | F68: telecoms_digital | G68: D1 | H68: Voice and airtime | I68: per minute / % of fee | J68: 2 | K68: Cellular surcharge: off-net voice | M68: Finance Act 2023 s.13 (cellular surcharge) | N68: 2023-04-01 | O68: current | Q68: single | R68: specific | S68: 0.05 | T68: NLe | U68: call unit (per minute not stated) | W68: NLe 0.05 | X68: all | AF68: =IF(T68="USD",1,IF(T68="pct","",INDEX(Parameters!$D$5:$D$7,MATCH(B68,Parameters!$A$5:$A$7,0)))) -> 22 | AG68: =IF(AND(R68="specific",ISNUMBER(S68)),S68/AF68,"") -> 0.0022727273 | AH68: 1 | AI68: =IF(NOT(ISNUMBER(AH68)),"",IF(R68="specific",IF(ISNUMBER(AG68),AG68*AH68,""),IF(AND(R68="ad_valorem",ISNUMBER(AJ68)),S68*AJ68/INDEX(Parameters!$D$5:$D$7,MATCH(B68,Parameters!$A$5:$A$7,0))*AH68,""))) -> 0.0022727273 | AL68: =IF(NOT(ISNUMBER(AJ68)),"",IF(R68="specific",S68/AJ68,IF(R68="ad_valorem",S68,""))) | AM68: corrected | AN68: PR-36 | AO68: =IF(AM68="","",IFERROR(INDEX(DQ_Scale!$B$5:$B$14,MATCH(AM68,DQ_Scale!$A$5:$A$14,0)),"")) -> 4
A69: SLE-065 | B69: SLE | C69: Sierra Leone | D69: 2026-04-27 | E69: 4 Other | F69: telecoms_digital | G69: D1 | H69: Voice and airtime | I69: per minute / % of fee | J69: 2 | K69: Cellular surcharge: outgoing international voice | M69: Finance Act 2023 s.13 (cellular surcharge) | N69: 2023-04-01 | O69: current | Q69: single | R69: specific | S69: 2 | T69: NLe | U69: call unit (per minute not stated) | W69: NLe 2 | X69: all | AF69: =IF(T69="USD",1,IF(T69="pct","",INDEX(Parameters!$D$5:$D$7,MATCH(B69,Parameters!$A$5:$A$7,0)))) -> 22 | AG69: =IF(AND(R69="specific",ISNUMBER(S69)),S69/AF69,"") -> 0.090909091 | AH69: 1 | AI69: =IF(NOT(ISNUMBER(AH69)),"",IF(R69="specific",IF(ISNUMBER(AG69),AG69*AH69,""),IF(AND(R69="ad_valorem",ISNUMBER(AJ69)),S69*AJ69/INDEX(Parameters!$D$5:$D$7,MATCH(B69,Parameters!$A$5:$A$7,0))*AH69,""))) -> 0.090909091 | AL69: =IF(NOT(ISNUMBER(AJ69)),"",IF(R69="specific",S69/AJ69,IF(R69="ad_valorem",S69,""))) | AM69: corrected | AN69: PR-36 | AO69: =IF(AM69="","",IFERROR(INDEX(DQ_Scale!$B$5:$B$14,MATCH(AM69,DQ_Scale!$A$5:$A$14,0)),"")) -> 4
A70: SLE-066 | B70: SLE | C70: Sierra Leone | D70: 2026-04-27 | E70: 4 Other | F70: telecoms_digital | G70: D2 | H70: Data and value-added services | I70: % of fee | J70: 2 | K70: Cellular surcharge: mobile data | M70: Finance Act 2023 s.13 (cellular surcharge) | N70: 2023-04-01 | O70: current | Q70: single | R70: ad_valorem | S70: 0.05 | T70: pct | U70: % of base | V70: data recharge and bundle sales (maximum) | W70: Up to 5% | X70: all | AF70: =IF(T70="USD",1,IF(T70="pct","",INDEX(Parameters!$D$5:$D$7,MATCH(B70,Parameters!$A$5:$A$7,0)))) | AG70: =IF(AND(R70="specific",ISNUMBER(S70)),S70/AF70,"") | AI70: =IF(NOT(ISNUMBER(AH70)),"",IF(R70="specific",IF(ISNUMBER(AG70),AG70*AH70,""),IF(AND(R70="ad_valorem",ISNUMBER(AJ70)),S70*AJ70/INDEX(Parameters!$D$5:$D$7,MATCH(B70,Parameters!$A$5:$A$7,0))*AH70,""))) | AL70: =IF(NOT(ISNUMBER(AJ70)),"",IF(R70="specific",S70/AJ70,IF(R70="ad_valorem",S70,""))) | AM70: verified | AN70: PR-37 | AO70: =IF(AM70="","",IFERROR(INDEX(DQ_Scale!$B$5:$B$14,MATCH(AM70,DQ_Scale!$A$5:$A$14,0)),"")) -> 5
A71: SLE-067 | B71: SLE | C71: Sierra Leone | D71: 2026-04-27 | E71: 4 Other | F71: financial_transactions | G71: F1 | H71: Mobile money and financial services | I71: % of value or fee | J71: 2 | K71: Cellular surcharge: mobile-money commissions | M71: Finance Act 2023 s.13 (cellular surcharge) | N71: 2023-04-01 | O71: current | Q71: single | R71: ad_valorem | S71: 0.02 | T71: pct | U71: % of base | V71: mobile-money commissions | W71: 2% of commissions | X71: all | AF71: =IF(T71="USD",1,IF(T71="pct","",INDEX(Parameters!$D$5:$D$7,MATCH(B71,Parameters!$A$5:$A$7,0)))) | AG71: =IF(AND(R71="specific",ISNUMBER(S71)),S71/AF71,"") | AI71: =IF(NOT(ISNUMBER(AH71)),"",IF(R71="specific",IF(ISNUMBER(AG71),AG71*AH71,""),IF(AND(R71="ad_valorem",ISNUMBER(AJ71)),S71*AJ71/INDEX(Parameters!$D$5:$D$7,MATCH(B71,Parameters!$A$5:$A$7,0))*AH71,""))) | AL71: =IF(NOT(ISNUMBER(AJ71)),"",IF(R71="specific",S71/AJ71,IF(R71="ad_valorem",S71,""))) | AM71: verified | AN71: PR-37 | AO71: =IF(AM71="","",IFERROR(INDEX(DQ_Scale!$B$5:$B$14,MATCH(AM71,DQ_Scale!$A$5:$A$14,0)),"")) -> 5
A72: SLE-068 | B72: SLE | C72: Sierra Leone | D72: 2026-04-27 | E72: 4 Other | F72: industrial_residual | G72: I1 | H72: Cement | I72: per 50 kg bag | J72: 1 | K72: Cement (Portland, slag, hydraulic) | L72: 25.23 | M72: Finance Act 2026 | N72: 2026-01-01 | O72: current | Q72: single | R72: specific | S72: 10 | T72: NLe | U72: 50 kg bag | W72: NLe 10 / 50 kg bag | X72: all | AF72: =IF(T72="USD",1,IF(T72="pct","",INDEX(Parameters!$D$5:$D$7,MATCH(B72,Parameters!$A$5:$A$7,0)))) -> 22 | AG72: =IF(AND(R72="specific",ISNUMBER(S72)),S72/AF72,"") -> 0.45454545 | AH72: 1 | AI72: =IF(NOT(ISNUMBER(AH72)),"",IF(R72="specific",IF(ISNUMBER(AG72),AG72*AH72,""),IF(AND(R72="ad_valorem",ISNUMBER(AJ72)),S72*AJ72/INDEX(Parameters!$D$5:$D$7,MATCH(B72,Parameters!$A$5:$A$7,0))*AH72,""))) -> 0.45454545 | AL72: =IF(NOT(ISNUMBER(AJ72)),"",IF(R72="specific",S72/AJ72,IF(R72="ad_valorem",S72,""))) | AM72: partly_verified | AN72: PR-33 | AO72: =IF(AM72="","",IFERROR(INDEX(DQ_Scale!$B$5:$B$14,MATCH(AM72,DQ_Scale!$A$5:$A$14,0)),"")) -> 3 | AP72: Excise restored in FA2026 (Citizens' Guide); FA2024 20% was customs duty
A73: SLE-069 | B73: SLE | C73: Sierra Leone | D73: 2026-04-27 | E73: 4 Other | F73: industrial_residual | G73: I2 | H73: Edible oils | I73: per liter / % | J73: 1 | K73: Vegetable oils, palm olein, margarine | L73: 15.11, 15.17 | M73: Finance Act 2021 | N73: 2021-01-01 | O73: current | Q73: single | R73: ad_valorem | S73: 0.1 | T73: pct | U73: % of value | V73: value | W73: 10% | X73: all | AF73: =IF(T73="USD",1,IF(T73="pct","",INDEX(Parameters!$D$5:$D$7,MATCH(B73,Parameters!$A$5:$A$7,0)))) | AG73: =IF(AND(R73="specific",ISNUMBER(S73)),S73/AF73,"") | AI73: =IF(NOT(ISNUMBER(AH73)),"",IF(R73="specific",IF(ISNUMBER(AG73),AG73*AH73,""),IF(AND(R73="ad_valorem",ISNUMBER(AJ73)),S73*AJ73/INDEX(Parameters!$D$5:$D$7,MATCH(B73,Parameters!$A$5:$A$7,0))*AH73,""))) | AL73: =IF(NOT(ISNUMBER(AJ73)),"",IF(R73="specific",S73/AJ73,IF(R73="ad_valorem",S73,""))) | AM73: verified | AN73: PR-35 | AO73: =IF(AM73="","",IFERROR(INDEX(DQ_Scale!$B$5:$B$14,MATCH(AM73,DQ_Scale!$A$5:$A$14,0)),"")) -> 5
A74: SLE-070 | B74: SLE | C74: Sierra Leone | D74: 2026-04-27 | E74: 4 Other | F74: industrial_residual | G74: I3 | H74: Sugar | I74: per kg | J74: 0 | K74: Sugar: not excisable | O74: not_covered | R74: none | AF74: =IF(T74="USD",1,IF(T74="pct","",INDEX(Parameters!$D$5:$D$7,MATCH(B74,Parameters!$A$5:$A$7,0)))) -> 22 | AG74: =IF(AND(R74="specific",ISNUMBER(S74)),S74/AF74,"") | AI74: =IF(NOT(ISNUMBER(AH74)),"",IF(R74="specific",IF(ISNUMBER(AG74),AG74*AH74,""),IF(AND(R74="ad_valorem",ISNUMBER(AJ74)),S74*AJ74/INDEX(Parameters!$D$5:$D$7,MATCH(B74,Parameters!$A$5:$A$7,0))*AH74,""))) | AL74: =IF(NOT(ISNUMBER(AJ74)),"",IF(R74="specific",S74/AJ74,IF(R74="ad_valorem",S74,""))) | AM74: not_reviewed | AO74: =IF(AM74="","",IFERROR(INDEX(DQ_Scale!$B$5:$B$14,MATCH(AM74,DQ_Scale!$A$5:$A$14,0)),"")) -> 2
A75: SLE-071 | B75: SLE | C75: Sierra Leone | D75: 2026-04-27 | E75: 4 Other | F75: industrial_residual | G75: I4 | H75: Other industrial inputs | I75: % | J75: 1 | K75: Soaps (toilet, household, laundry) | L75: 34.01 | M75: Finance Act 2021 | N75: 2021-01-01 | O75: current | Q75: single | R75: ad_valorem | S75: 0.2 | T75: pct | U75: % of value | V75: value | W75: 20% | X75: all | AF75: =IF(T75="USD",1,IF(T75="pct","",INDEX(Parameters!$D$5:$D$7,MATCH(B75,Parameters!$A$5:$A$7,0)))) | AG75: =IF(AND(R75="specific",ISNUMBER(S75)),S75/AF75,"") | AI75: =IF(NOT(ISNUMBER(AH75)),"",IF(R75="specific",IF(ISNUMBER(AG75),AG75*AH75,""),IF(AND(R75="ad_valorem",ISNUMBER(AJ75)),S75*AJ75/INDEX(Parameters!$D$5:$D$7,MATCH(B75,Parameters!$A$5:$A$7,0))*AH75,""))) | AL75: =IF(NOT(ISNUMBER(AJ75)),"",IF(R75="specific",S75/AJ75,IF(R75="ad_valorem",S75,""))) | AM75: verified | AN75: PR-35 | AO75: =IF(AM75="","",IFERROR(INDEX(DQ_Scale!$B$5:$B$14,MATCH(AM75,DQ_Scale!$A$5:$A$14,0)),"")) -> 5
A76: SLE-072 | B76: SLE | C76: Sierra Leone | D76: 2026-04-27 | E76: 4 Other | F76: industrial_residual | G76: I4 | H76: Other industrial inputs | I76: % | J76: 1 | K76: Industrial fatty-acid oils; palmitic and stearic acid | L76: 38.23 | M76: Finance Act 2021 | N76: 2021-01-01 | O76: current | Q76: single | R76: ad_valorem | S76: 0.2 | T76: pct | U76: % of value | V76: value | W76: 20% | X76: all | AF76: =IF(T76="USD",1,IF(T76="pct","",INDEX(Parameters!$D$5:$D$7,MATCH(B76,Parameters!$A$5:$A$7,0)))) | AG76: =IF(AND(R76="specific",ISNUMBER(S76)),S76/AF76,"") | AI76: =IF(NOT(ISNUMBER(AH76)),"",IF(R76="specific",IF(ISNUMBER(AG76),AG76*AH76,""),IF(AND(R76="ad_valorem",ISNUMBER(AJ76)),S76*AJ76/INDEX(Parameters!$D$5:$D$7,MATCH(B76,Parameters!$A$5:$A$7,0))*AH76,""))) | AL76: =IF(NOT(ISNUMBER(AJ76)),"",IF(R76="specific",S76/AJ76,IF(R76="ad_valorem",S76,""))) | AM76: verified | AN76: PR-35 | AO76: =IF(AM76="","",IFERROR(INDEX(DQ_Scale!$B$5:$B$14,MATCH(AM76,DQ_Scale!$A$5:$A$14,0)),"")) -> 5
A77: SLE-073 | B77: SLE | C77: Sierra Leone | D77: 2026-04-27 | E77: 4 Other | F77: industrial_residual | G77: I4 | H77: Other industrial inputs | I77: % | J77: 1 | K77: Nails | L77: 73.17 | M77: Finance Act 2021 | N77: 2021-01-01 | O77: current | Q77: single | R77: ad_valorem | S77: 0.05 | T77: pct | U77: % of value | V77: value | W77: 5% | X77: all | AF77: =IF(T77="USD",1,IF(T77="pct","",INDEX(Parameters!$D$5:$D$7,MATCH(B77,Parameters!$A$5:$A$7,0)))) | AG77: =IF(AND(R77="specific",ISNUMBER(S77)),S77/AF77,"") | AI77: =IF(NOT(ISNUMBER(AH77)),"",IF(R77="specific",IF(ISNUMBER(AG77),AG77*AH77,""),IF(AND(R77="ad_valorem",ISNUMBER(AJ77)),S77*AJ77/INDEX(Parameters!$D$5:$D$7,MATCH(B77,Parameters!$A$5:$A$7,0))*AH77,""))) | AL77: =IF(NOT(ISNUMBER(AJ77)),"",IF(R77="specific",S77/AJ77,IF(R77="ad_valorem",S77,""))) | AM77: verified | AN77: PR-35 | AO77: =IF(AM77="","",IFERROR(INDEX(DQ_Scale!$B$5:$B$14,MATCH(AM77,DQ_Scale!$A$5:$A$14,0)),"")) -> 5
A78: SLE-074 | B78: SLE | C78: Sierra Leone | D78: 2026-04-27 | E78: 4 Other | F78: luxury | G78: L1 | H78: Cosmetics, furniture and other luxury | I78: % | J78: 0 | K78: Cosmetics and furniture: not excisable | O78: not_covered | R78: none | AF78: =IF(T78="USD",1,IF(T78="pct","",INDEX(Parameters!$D$5:$D$7,MATCH(B78,Parameters!$A$5:$A$7,0)))) -> 22 | AG78: =IF(AND(R78="specific",ISNUMBER(S78)),S78/AF78,"") | AI78: =IF(NOT(ISNUMBER(AH78)),"",IF(R78="specific",IF(ISNUMBER(AG78),AG78*AH78,""),IF(AND(R78="ad_valorem",ISNUMBER(AJ78)),S78*AJ78/INDEX(Parameters!$D$5:$D$7,MATCH(B78,Parameters!$A$5:$A$7,0))*AH78,""))) | AL78: =IF(NOT(ISNUMBER(AJ78)),"",IF(R78="specific",S78/AJ78,IF(R78="ad_valorem",S78,""))) | AM78: not_reviewed | AO78: =IF(AM78="","",IFERROR(INDEX(DQ_Scale!$B$5:$B$14,MATCH(AM78,DQ_Scale!$A$5:$A$14,0)),"")) -> 2
A79: UGA-075 | B79: UGA | C79: Uganda | D79: 2026-04-27 | E79: 1 Fuel | F79: energy_environment | G79: E1 | H79: Petrol | I79: per liter | J79: 1 | K79: Petrol (motor spirit) | M79: Excise Duty Act 2014, as amended to the 2025 Amendment Acts | N79: 2025-07-01 | O79: current | Q79: single | R79: specific | S79: 1550 | T79: UGX | U79: liter | W79: UGX 1,550 / liter | X79: all | AF79: =IF(T79="USD",1,IF(T79="pct","",INDEX(Parameters!$D$5:$D$7,MATCH(B79,Parameters!$A$5:$A$7,0)))) -> 3750 | AG79: =IF(AND(R79="specific",ISNUMBER(S79)),S79/AF79,"") -> 0.41333333 | AH79: 1 | AI79: =IF(NOT(ISNUMBER(AH79)),"",IF(R79="specific",IF(ISNUMBER(AG79),AG79*AH79,""),IF(AND(R79="ad_valorem",ISNUMBER(AJ79)),S79*AJ79/INDEX(Parameters!$D$5:$D$7,MATCH(B79,Parameters!$A$5:$A$7,0))*AH79,""))) -> 0.41333333 | AJ79: 5244 | AK79: Pump price UGX 5,244/l, 20 Apr 2026 | AL79: =IF(NOT(ISNUMBER(AJ79)),"",IF(R79="specific",S79/AJ79,IF(R79="ad_valorem",S79,""))) -> 0.2955759 | AM79: not_reviewed | AO79: =IF(AM79="","",IFERROR(INDEX(DQ_Scale!$B$5:$B$14,MATCH(AM79,DQ_Scale!$A$5:$A$14,0)),"")) -> 2
A80: UGA-076 | B80: UGA | C80: Uganda | D80: 2026-04-27 | E80: 1 Fuel | F80: energy_environment | G80: E2 | H80: Diesel, road | I80: per liter | J80: 1 | K80: Diesel (gas oil, automotive) | M80: Excise Duty Act 2014, as amended to the 2025 Amendment Acts | N80: 2025-07-01 | O80: current | Q80: single | R80: specific | S80: 1230 | T80: UGX | U80: liter | W80: UGX 1,230 / liter | X80: all | AF80: =IF(T80="USD",1,IF(T80="pct","",INDEX(Parameters!$D$5:$D$7,MATCH(B80,Parameters!$A$5:$A$7,0)))) -> 3750 | AG80: =IF(AND(R80="specific",ISNUMBER(S80)),S80/AF80,"") -> 0.328 | AH80: 1 | AI80: =IF(NOT(ISNUMBER(AH80)),"",IF(R80="specific",IF(ISNUMBER(AG80),AG80*AH80,""),IF(AND(R80="ad_valorem",ISNUMBER(AJ80)),S80*AJ80/INDEX(Parameters!$D$5:$D$7,MATCH(B80,Parameters!$A$5:$A$7,0))*AH80,""))) -> 0.328 | AJ80: 5100 | AK80: Pump price UGX ~5,100/l (estimate) | AL80: =IF(NOT(ISNUMBER(AJ80)),"",IF(R80="specific",S80/AJ80,IF(R80="ad_valorem",S80,""))) -> 0.24117647 | AM80: not_reviewed | AO80: =IF(AM80="","",IFERROR(INDEX(DQ_Scale!$B$5:$B$14,MATCH(AM80,DQ_Scale!$A$5:$A$14,0)),"")) -> 2
A81: UGA-077 | B81: UGA | C81: Uganda | D81: 2026-04-27 | E81: 1 Fuel | F81: energy_environment | G81: E2 | H81: Diesel, road | I81: per liter | J81: 1 | K81: Diesel for power-grid generation | M81: Excise Duty Act 2014, as amended to the 2025 Amendment Acts | N81: 2025-07-01 | O81: current | Q81: single | R81: specific | S81: 0 | T81: UGX | U81: liter | W81: Nil | X81: all | AE81: user: power-grid generation | AF81: =IF(T81="USD",1,IF(T81="pct","",INDEX(Parameters!$D$5:$D$7,MATCH(B81,Parameters!$A$5:$A$7,0)))) -> 3750 | AG81: =IF(AND(R81="specific",ISNUMBER(S81)),S81/AF81,"") -> 0 | AH81: 1 | AI81: =IF(NOT(ISNUMBER(AH81)),"",IF(R81="specific",IF(ISNUMBER(AG81),AG81*AH81,""),IF(AND(R81="ad_valorem",ISNUMBER(AJ81)),S81*AJ81/INDEX(Parameters!$D$5:$D$7,MATCH(B81,Parameters!$A$5:$A$7,0))*AH81,""))) -> 0 | AL81: =IF(NOT(ISNUMBER(AJ81)),"",IF(R81="specific",S81/AJ81,IF(R81="ad_valorem",S81,""))) | AM81: not_reviewed | AO81: =IF(AM81="","",IFERROR(INDEX(DQ_Scale!$B$5:$B$14,MATCH(AM81,DQ_Scale!$A$5:$A$14,0)),"")) -> 2
A82: UGA-078 | B82: UGA | C82: Uganda | D82: 2026-04-27 | E82: 1 Fuel | F82: energy_environment | G82: E3 | H82: Kerosene | I82: per liter | J82: 1 | K82: Illuminating kerosene | M82: Excise Duty Act 2014, as amended to the 2025 Amendment Acts | N82: 2025-07-01 | O82: current | Q82: single | R82: specific | S82: 200 | T82: UGX | U82: liter | W82: UGX 200 / liter | X82: all | AF82: =IF(T82="USD",1,IF(T82="pct","",INDEX(Parameters!$D$5:$D$7,MATCH(B82,Parameters!$A$5:$A$7,0)))) -> 3750 | AG82: =IF(AND(R82="specific",ISNUMBER(S82)),S82/AF82,"") -> 0.053333333 | AH82: 1 | AI82: =IF(NOT(ISNUMBER(AH82)),"",IF(R82="specific",IF(ISNUMBER(AG82),AG82*AH82,""),IF(AND(R82="ad_valorem",ISNUMBER(AJ82)),S82*AJ82/INDEX(Parameters!$D$5:$D$7,MATCH(B82,Parameters!$A$5:$A$7,0))*AH82,""))) -> 0.053333333 | AJ82: 4000 | AK82: Kerosene above UGX 4,000/l (estimate; share is an upper bound) | AL82: =IF(NOT(ISNUMBER(AJ82)),"",IF(R82="specific",S82/AJ82,IF(R82="ad_valorem",S82,""))) -> 0.05 | AM82: not_reviewed | AO82: =IF(AM82="","",IFERROR(INDEX(DQ_Scale!$B$5:$B$14,MATCH(AM82,DQ_Scale!$A$5:$A$14,0)),"")) -> 2
A83: UGA-079 | B83: UGA | C83: Uganda | D83: 2026-04-27 | E83: 1 Fuel | F83: energy_environment | G83: E4 | H83: Aviation fuel | I83: per liter | J83: 1 | K83: Jet A1 / aviation fuel | M83: Excise Duty Act 2014, as amended to the 2025 Amendment Acts | N83: 2025-07-01 | O83: current | Q83: single | R83: specific | S83: 630 | T83: UGX | U83: liter | W83: UGX 630 / liter | X83: all | AF83: =IF(T83="USD",1,IF(T83="pct","",INDEX(Parameters!$D$5:$D$7,MATCH(B83,Parameters!$A$5:$A$7,0)))) -> 3750 | AG83: =IF(AND(R83="specific",ISNUMBER(S83)),S83/AF83,"") -> 0.168 | AH83: 1 | AI83: =IF(NOT(ISNUMBER(AH83)),"",IF(R83="specific",IF(ISNUMBER(AG83),AG83*AH83,""),IF(AND(R83="ad_valorem",ISNUMBER(AJ83)),S83*AJ83/INDEX(Parameters!$D$5:$D$7,MATCH(B83,Parameters!$A$5:$A$7,0))*AH83,""))) -> 0.168 | AL83: =IF(NOT(ISNUMBER(AJ83)),"",IF(R83="specific",S83/AJ83,IF(R83="ad_valorem",S83,""))) | AM83: not_reviewed | AO83: =IF(AM83="","",IFERROR(INDEX(DQ_Scale!$B$5:$B$14,MATCH(AM83,DQ_Scale!$A$5:$A$14,0)),"")) -> 2
A84: UGA-080 | B84: UGA | C84: Uganda | D84: 2026-04-27 | E84: 1 Fuel | F84: energy_environment | G84: E4 | H84: Aviation fuel | I84: per liter | J84: 1 | K84: Jet A1: registered airlines and supply contracts | M84: Excise Duty Act 2014, as amended to the 2025 Amendment Acts | N84: 2025-07-01 | O84: current | Q84: single | R84: specific | S84: 0 | T84: UGX | U84: liter | W84: Nil | X84: all | AE84: user: registered airlines | AF84: =IF(T84="USD",1,IF(T84="pct","",INDEX(Parameters!$D$5:$D$7,MATCH(B84,Parameters!$A$5:$A$7,0)))) -> 3750 | AG84: =IF(AND(R84="specific",ISNUMBER(S84)),S84/AF84,"") -> 0 | AH84: 1 | AI84: =IF(NOT(ISNUMBER(AH84)),"",IF(R84="specific",IF(ISNUMBER(AG84),AG84*AH84,""),IF(AND(R84="ad_valorem",ISNUMBER(AJ84)),S84*AJ84/INDEX(Parameters!$D$5:$D$7,MATCH(B84,Parameters!$A$5:$A$7,0))*AH84,""))) -> 0 | AL84: =IF(NOT(ISNUMBER(AJ84)),"",IF(R84="specific",S84/AJ84,IF(R84="ad_valorem",S84,""))) | AM84: not_reviewed | AO84: =IF(AM84="","",IFERROR(INDEX(DQ_Scale!$B$5:$B$14,MATCH(AM84,DQ_Scale!$A$5:$A$14,0)),"")) -> 2
A85: UGA-081 | B85: UGA | C85: Uganda | D85: 2026-04-27 | E85: 1 Fuel | F85: energy_environment | G85: E5 | H85: Heavy fuel oil / other gas oils | I85: per liter | J85: 1 | K85: Other gas oils | M85: Excise Duty Act 2014, as amended to the 2025 Amendment Acts | N85: 2025-07-01 | O85: current | Q85: single | R85: specific | S85: 630 | T85: UGX | U85: liter | W85: UGX 630 / liter | X85: all | AF85: =IF(T85="USD",1,IF(T85="pct","",INDEX(Parameters!$D$5:$D$7,MATCH(B85,Parameters!$A$5:$A$7,0)))) -> 3750 | AG85: =IF(AND(R85="specific",ISNUMBER(S85)),S85/AF85,"") -> 0.168 | AH85: 1 | AI85: =IF(NOT(ISNUMBER(AH85)),"",IF(R85="specific",IF(ISNUMBER(AG85),AG85*AH85,""),IF(AND(R85="ad_valorem",ISNUMBER(AJ85)),S85*AJ85/INDEX(Parameters!$D$5:$D$7,MATCH(B85,Parameters!$A$5:$A$7,0))*AH85,""))) -> 0.168 | AL85: =IF(NOT(ISNUMBER(AJ85)),"",IF(R85="specific",S85/AJ85,IF(R85="ad_valorem",S85,""))) | AM85: not_reviewed | AO85: =IF(AM85="","",IFERROR(INDEX(DQ_Scale!$B$5:$B$14,MATCH(AM85,DQ_Scale!$A$5:$A$14,0)),"")) -> 2
A86: UGA-082 | B86: UGA | C86: Uganda | D86: 2026-04-27 | E86: 1 Fuel | F86: energy_environment | G86: E6 | H86: Lubricants | I86: per liter | J86: 1 | K86: Lubricants (motor vehicle, not aircraft) | M86: Excise Duty Act 2014, as amended to the 2025 Amendment Acts | N86: 2025-07-01 | O86: current | Q86: single | R86: ad_valorem | S86: 0.15 | T86: pct | U86: % of value | V86: value | W86: 15% | X86: all | AE86: user: motor vehicles (not aircraft) | AF86: =IF(T86="USD",1,IF(T86="pct","",INDEX(Parameters!$D$5:$D$7,MATCH(B86,Parameters!$A$5:$A$7,0)))) | AG86: =IF(AND(R86="specific",ISNUMBER(S86)),S86/AF86,"") | AI86: =IF(NOT(ISNUMBER(AH86)),"",IF(R86="specific",IF(ISNUMBER(AG86),AG86*AH86,""),IF(AND(R86="ad_valorem",ISNUMBER(AJ86)),S86*AJ86/INDEX(Parameters!$D$5:$D$7,MATCH(B86,Parameters!$A$5:$A$7,0))*AH86,""))) | AL86: =IF(NOT(ISNUMBER(AJ86)),"",IF(R86="specific",S86/AJ86,IF(R86="ad_valorem",S86,""))) | AM86: not_reviewed | AO86: =IF(AM86="","",IFERROR(INDEX(DQ_Scale!$B$5:$B$14,MATCH(AM86,DQ_Scale!$A$5:$A$14,0)),"")) -> 2
A87: UGA-083 | B87: UGA | C87: Uganda | D87: 2026-04-27 | E87: 4 Other | F87: energy_environment | G87: E7 | H87: Plastic bags and packaging | I87: per kg | J87: 1 | K87: Plastics / plastic granules | M87: Excise Duty Act 2014, as amended to the 2025 Amendment Acts | N87: 2025-07-01 | O87: current | P87: UGA-granules | Q87: higher_of | R87: ad_valorem | S87: 0.025 | T87: pct | U87: % of value | V87: value | W87: 2.5% or USD 70 / tonne | X87: all | AF87: =IF(T87="USD",1,IF(T87="pct","",INDEX(Parameters!$D$5:$D$7,MATCH(B87,Parameters!$A$5:$A$7,0)))) | AG87: =IF(AND(R87="specific",ISNUMBER(S87)),S87/AF87,"") | AI87: =IF(NOT(ISNUMBER(AH87)),"",IF(R87="specific",IF(ISNUMBER(AG87),AG87*AH87,""),IF(AND(R87="ad_valorem",ISNUMBER(AJ87)),S87*AJ87/INDEX(Parameters!$D$5:$D$7,MATCH(B87,Parameters!$A$5:$A$7,0))*AH87,""))) | AL87: =IF(NOT(ISNUMBER(AJ87)),"",IF(R87="specific",S87/AJ87,IF(R87="ad_valorem",S87,""))) | AM87: not_reviewed | AO87: =IF(AM87="","",IFERROR(INDEX(DQ_Scale!$B$5:$B$14,MATCH(AM87,DQ_Scale!$A$5:$A$14,0)),"")) -> 2
A88: UGA-084 | B88: UGA | C88: Uganda | D88: 2026-04-27 | E88: 4 Other | F88: energy_environment | G88: E7 | H88: Plastic bags and packaging | I88: per kg | J88: 1 | K88: Plastics / plastic granules | M88: Excise Duty Act 2014, as amended to the 2025 Amendment Acts | N88: 2025-07-01 | O88: current | P88: UGA-granules | Q88: higher_of | R88: specific | S88: 70 | T88: USD | U88: tonne | W88: 2.5% or USD 70 / tonne | X88: all | AF88: =IF(T88="USD",1,IF(T88="pct","",INDEX(Parameters!$D$5:$D$7,MATCH(B88,Parameters!$A$5:$A$7,0)))) -> 1 | AG88: =IF(AND(R88="specific",ISNUMBER(S88)),S88/AF88,"") -> 70 | AH88: 0.001 | AI88: =IF(NOT(ISNUMBER(AH88)),"",IF(R88="specific",IF(ISNUMBER(AG88),AG88*AH88,""),IF(AND(R88="ad_valorem",ISNUMBER(AJ88)),S88*AJ88/INDEX(Parameters!$D$5:$D$7,MATCH(B88,Parameters!$A$5:$A$7,0))*AH88,""))) -> 0.07 | AL88: =IF(NOT(ISNUMBER(AJ88)),"",IF(R88="specific",S88/AJ88,IF(R88="ad_valorem",S88,""))) | AM88: not_reviewed | AO88: =IF(AM88="","",IFERROR(INDEX(DQ_Scale!$B$5:$B$14,MATCH(AM88,DQ_Scale!$A$5:$A$14,0)),"")) -> 2 | AP88: Converted to per kg
A89: UGA-085 | B89: UGA | C89: Uganda | D89: 2026-04-27 | E89: 4 Other | F89: energy_environment | G89: E7 | H89: Plastic bags and packaging | I89: per kg | J89: 1 | K89: Plastic bags / polyethylene sacks | M89: Excise Duty Act 2014, as amended to the 2025 Amendment Acts | N89: 2025-07-01 | O89: current | Q89: single | R89: specific | S89: 10000 | T89: UGX | U89: kg | W89: UGX 10,000 / kg | X89: all | AF89: =IF(T89="USD",1,IF(T89="pct","",INDEX(Parameters!$D$5:$D$7,MATCH(B89,Parameters!$A$5:$A$7,0)))) -> 3750 | AG89: =IF(AND(R89="specific",ISNUMBER(S89)),S89/AF89,"") -> 2.6666667 | AH89: 1 | AI89: =IF(NOT(ISNUMBER(AH89)),"",IF(R89="specific",IF(ISNUMBER(AG89),AG89*AH89,""),IF(AND(R89="ad_valorem",ISNUMBER(AJ89)),S89*AJ89/INDEX(Parameters!$D$5:$D$7,MATCH(B89,Parameters!$A$5:$A$7,0))*AH89,""))) -> 2.6666667 | AL89: =IF(NOT(ISNUMBER(AJ89)),"",IF(R89="specific",S89/AJ89,IF(R89="ad_valorem",S89,""))) | AM89: not_reviewed | AO89: =IF(AM89="","",IFERROR(INDEX(DQ_Scale!$B$5:$B$14,MATCH(AM89,DQ_Scale!$A$5:$A$14,0)),"")) -> 2 | AP89: Sanitary-pad and food/juice packaging exempt
A90: UGA-086 | B90: UGA | C90: Uganda | D90: 2026-04-27 | E90: 2 Vehicles | F90: energy_environment | G90: E8 | H90: Vehicles: annual circulation | I90: per vehicle-year | J90: 0 | K90: Annual circulation: not in excise schedule | O90: not_covered | R90: none | AF90: =IF(T90="USD",1,IF(T90="pct","",INDEX(Parameters!$D$5:$D$7,MATCH(B90,Parameters!$A$5:$A$7,0)))) -> 3750 | AG90: =IF(AND(R90="specific",ISNUMBER(S90)),S90/AF90,"") | AI90: =IF(NOT(ISNUMBER(AH90)),"",IF(R90="specific",IF(ISNUMBER(AG90),AG90*AH90,""),IF(AND(R90="ad_valorem",ISNUMBER(AJ90)),S90*AJ90/INDEX(Parameters!$D$5:$D$7,MATCH(B90,Parameters!$A$5:$A$7,0))*AH90,""))) | AL90: =IF(NOT(ISNUMBER(AJ90)),"",IF(R90="specific",S90/AJ90,IF(R90="ad_valorem",S90,""))) | AM90: not_reviewed | AO90: =IF(AM90="","",IFERROR(INDEX(DQ_Scale!$B$5:$B$14,MATCH(AM90,DQ_Scale!$A$5:$A$14,0)),"")) -> 2
A91: UGA-087 | B91: UGA | C91: Uganda | D91: 2026-04-27 | E91: 2 Vehicles | F91: energy_environment | G91: E9 | H91: Vehicles: first registration / import | I91: per vehicle | J91: 1 | K91: Motorcycles, first registration | M91: Excise Duty Act 2014, as amended to the 2025 Amendment Acts | N91: 2025-07-01 | O91: current | Q91: single | R91: specific | S91: 200000 | T91: UGX | U91: vehicle | W91: UGX 200,000 | X91: all | AF91: =IF(T91="USD",1,IF(T91="pct","",INDEX(Parameters!$D$5:$D$7,MATCH(B91,Parameters!$A$5:$A$7,0)))) -> 3750 | AG91: =IF(AND(R91="specific",ISNUMBER(S91)),S91/AF91,"") -> 53.333333 | AH91: 1 | AI91: =IF(NOT(ISNUMBER(AH91)),"",IF(R91="specific",IF(ISNUMBER(AG91),AG91*AH91,""),IF(AND(R91="ad_valorem",ISNUMBER(AJ91)),S91*AJ91/INDEX(Parameters!$D$5:$D$7,MATCH(B91,Parameters!$A$5:$A$7,0))*AH91,""))) -> 53.333333 | AL91: =IF(NOT(ISNUMBER(AJ91)),"",IF(R91="specific",S91/AJ91,IF(R91="ad_valorem",S91,""))) | AM91: not_reviewed | AO91: =IF(AM91="","",IFERROR(INDEX(DQ_Scale!$B$5:$B$14,MATCH(AM91,DQ_Scale!$A$5:$A$14,0)),"")) -> 2
A92: UGA-088 | B92: UGA | C92: Uganda | D92: 2026-04-27 | E92: 3 Health | F92: health | G92: T1 | H92: Cigarettes | I92: per pack of 20 | J92: 1 | K92: Cigarettes: soft cap, locally manufactured | M92: Excise Duty Act 2014, as amended to the 2025 Amendment Acts | N92: 2025-07-01 | O92: current | Q92: single | R92: specific | S92: 65000 | T92: UGX | U92: 1,000 sticks | W92: UGX 65,000 / 1,000 sticks | X92: local | AE92: pack type: soft cap | AF92: =IF(T92="USD",1,IF(T92="pct","",INDEX(Parameters!$D$5:$D$7,MATCH(B92,Parameters!$A$5:$A$7,0)))) -> 3750 | AG92: =IF(AND(R92="specific",ISNUMBER(S92)),S92/AF92,"") -> 17.333333 | AH92: 0.02 | AI92: =IF(NOT(ISNUMBER(AH92)),"",IF(R92="specific",IF(ISNUMBER(AG92),AG92*AH92,""),IF(AND(R92="ad_valorem",ISNUMBER(AJ92)),S92*AJ92/INDEX(Parameters!$D$5:$D$7,MATCH(B92,Parameters!$A$5:$A$7,0))*AH92,""))) -> 0.34666667 | AJ92: 215000 | AK92: Pack price UGX 4,300 (market estimate), expressed per 1,000 sticks | AL92: =IF(NOT(ISNUMBER(AJ92)),"",IF(R92="specific",S92/AJ92,IF(R92="ad_valorem",S92,""))) -> 0.30232558 | AM92: not_reviewed | AO92: =IF(AM92="","",IFERROR(INDEX(DQ_Scale!$B$5:$B$14,MATCH(AM92,DQ_Scale!$A$5:$A$14,0)),"")) -> 2
A93: UGA-089 | B93: UGA | C93: Uganda | D93: 2026-04-27 | E93: 3 Health | F93: health | G93: T1 | H93: Cigarettes | I93: per pack of 20 | J93: 1 | K93: Cigarettes: soft cap, imported | M93: Excise Duty Act 2014, as amended to the 2025 Amendment Acts | N93: 2025-07-01 | O93: current | Q93: single | R93: specific | S93: 150000 | T93: UGX | U93: 1,000 sticks | W93: UGX 150,000 / 1,000 sticks | X93: imported | AE93: pack type: soft cap | AF93: =IF(T93="USD",1,IF(T93="pct","",INDEX(Parameters!$D$5:$D$7,MATCH(B93,Parameters!$A$5:$A$7,0)))) -> 3750 | AG93: =IF(AND(R93="specific",ISNUMBER(S93)),S93/AF93,"") -> 40 | AH93: 0.02 | AI93: =IF(NOT(ISNUMBER(AH93)),"",IF(R93="specific",IF(ISNUMBER(AG93),AG93*AH93,""),IF(AND(R93="ad_valorem",ISNUMBER(AJ93)),S93*AJ93/INDEX(Parameters!$D$5:$D$7,MATCH(B93,Parameters!$A$5:$A$7,0))*AH93,""))) -> 0.8 | AJ93: 300000 | AK93: Pack price UGX 6,000 (market estimate), expressed per 1,000 sticks | AL93: =IF(NOT(ISNUMBER(AJ93)),"",IF(R93="specific",S93/AJ93,IF(R93="ad_valorem",S93,""))) -> 0.5 | AM93: not_reviewed | AO93: =IF(AM93="","",IFERROR(INDEX(DQ_Scale!$B$5:$B$14,MATCH(AM93,DQ_Scale!$A$5:$A$14,0)),"")) -> 2
A94: UGA-090 | B94: UGA | C94: Uganda | D94: 2026-04-27 | E94: 3 Health | F94: health | G94: T1 | H94: Cigarettes | I94: per pack of 20 | J94: 1 | K94: Cigarettes: hinge lid, locally manufactured | M94: Excise Duty Act 2014, as amended to the 2025 Amendment Acts | N94: 2025-07-01 | O94: current | Q94: single | R94: specific | S94: 90000 | T94: UGX | U94: 1,000 sticks | W94: UGX 90,000 / 1,000 sticks | X94: local | AE94: pack type: hinge lid | AF94: =IF(T94="USD",1,IF(T94="pct","",INDEX(Parameters!$D$5:$D$7,MATCH(B94,Parameters!$A$5:$A$7,0)))) -> 3750 | AG94: =IF(AND(R94="specific",ISNUMBER(S94)),S94/AF94,"") -> 24 | AH94: 0.02 | AI94: =IF(NOT(ISNUMBER(AH94)),"",IF(R94="specific",IF(ISNUMBER(AG94),AG94*AH94,""),IF(AND(R94="ad_valorem",ISNUMBER(AJ94)),S94*AJ94/INDEX(Parameters!$D$5:$D$7,MATCH(B94,Parameters!$A$5:$A$7,0))*AH94,""))) -> 0.48 | AL94: =IF(NOT(ISNUMBER(AJ94)),"",IF(R94="specific",S94/AJ94,IF(R94="ad_valorem",S94,""))) | AM94: not_reviewed | AO94: =IF(AM94="","",IFERROR(INDEX(DQ_Scale!$B$5:$B$14,MATCH(AM94,DQ_Scale!$A$5:$A$14,0)),"")) -> 2
A95: UGA-091 | B95: UGA | C95: Uganda | D95: 2026-04-27 | E95: 3 Health | F95: health | G95: T1 | H95: Cigarettes | I95: per pack of 20 | J95: 1 | K95: Cigarettes: hinge lid, imported | M95: Excise Duty Act 2014, as amended to the 2025 Amendment Acts | N95: 2025-07-01 | O95: current | Q95: single | R95: specific | S95: 200000 | T95: UGX | U95: 1,000 sticks | W95: UGX 200,000 / 1,000 sticks | X95: imported | AE95: pack type: hinge lid | AF95: =IF(T95="USD",1,IF(T95="pct","",INDEX(Parameters!$D$5:$D$7,MATCH(B95,Parameters!$A$5:$A$7,0)))) -> 3750 | AG95: =IF(AND(R95="specific",ISNUMBER(S95)),S95/AF95,"") -> 53.333333 | AH95: 0.02 | AI95: =IF(NOT(ISNUMBER(AH95)),"",IF(R95="specific",IF(ISNUMBER(AG95),AG95*AH95,""),IF(AND(R95="ad_valorem",ISNUMBER(AJ95)),S95*AJ95/INDEX(Parameters!$D$5:$D$7,MATCH(B95,Parameters!$A$5:$A$7,0))*AH95,""))) -> 1.0666667 | AL95: =IF(NOT(ISNUMBER(AJ95)),"",IF(R95="specific",S95/AJ95,IF(R95="ad_valorem",S95,""))) | AM95: not_reviewed | AO95: =IF(AM95="","",IFERROR(INDEX(DQ_Scale!$B$5:$B$14,MATCH(AM95,DQ_Scale!$A$5:$A$14,0)),"")) -> 2
A96: UGA-092 | B96: UGA | C96: Uganda | D96: 2026-04-27 | E96: 3 Health | F96: health | G96: T2 | H96: Cigars and other tobacco | I96: per pack / per kg | J96: 1 | K96: Cigars, cheroots, smoking and homogenized tobacco | M96: Excise Duty Act 2014, as amended to the 2025 Amendment Acts | N96: 2025-07-01 | O96: current | Q96: single | R96: ad_valorem | S96: 2 | T96: pct | U96: % of value | V96: value | W96: 200% | X96: all | AF96: =IF(T96="USD",1,IF(T96="pct","",INDEX(Parameters!$D$5:$D$7,MATCH(B96,Parameters!$A$5:$A$7,0)))) | AG96: =IF(AND(R96="specific",ISNUMBER(S96)),S96/AF96,"") | AI96: =IF(NOT(ISNUMBER(AH96)),"",IF(R96="specific",IF(ISNUMBER(AG96),AG96*AH96,""),IF(AND(R96="ad_valorem",ISNUMBER(AJ96)),S96*AJ96/INDEX(Parameters!$D$5:$D$7,MATCH(B96,Parameters!$A$5:$A$7,0))*AH96,""))) | AL96: =IF(NOT(ISNUMBER(AJ96)),"",IF(R96="specific",S96/AJ96,IF(R96="ad_valorem",S96,""))) | AM96: not_reviewed | AO96: =IF(AM96="","",IFERROR(INDEX(DQ_Scale!$B$5:$B$14,MATCH(AM96,DQ_Scale!$A$5:$A$14,0)),"")) -> 2
A97: UGA-093 | B97: UGA | C97: Uganda | D97: 2026-04-27 | E97: 3 Health | F97: health | G97: T3 | H97: E-cigarettes and novel products | I97: per ml / per cartridge | J97: 0 | K97: E-cigarettes: not identified | O97: not_covered | R97: none | AF97: =IF(T97="USD",1,IF(T97="pct","",INDEX(Parameters!$D$5:$D$7,MATCH(B97,Parameters!$A$5:$A$7,0)))) -> 3750 | AG97: =IF(AND(R97="specific",ISNUMBER(S97)),S97/AF97,"") | AI97: =IF(NOT(ISNUMBER(AH97)),"",IF(R97="specific",IF(ISNUMBER(AG97),AG97*AH97,""),IF(AND(R97="ad_valorem",ISNUMBER(AJ97)),S97*AJ97/INDEX(Parameters!$D$5:$D$7,MATCH(B97,Parameters!$A$5:$A$7,0))*AH97,""))) | AL97: =IF(NOT(ISNUMBER(AJ97)),"",IF(R97="specific",S97/AJ97,IF(R97="ad_valorem",S97,""))) | AM97: not_reviewed | AO97: =IF(AM97="","",IFERROR(INDEX(DQ_Scale!$B$5:$B$14,MATCH(AM97,DQ_Scale!$A$5:$A$14,0)),"")) -> 2
A98: UGA-094 | B98: UGA | C98: Uganda | D98: 2026-04-27 | E98: 3 Health | F98: health | G98: A1 | H98: Beer, mainstream malt (5% ABV) | I98: per LPA | J98: 1 | K98: Malt beer | M98: Excise Duty Act 2014, as amended to the 2025 Amendment Acts | N98: 2025-07-01 | O98: current | P98: UGA-maltbeer | Q98: higher_of | R98: ad_valorem | S98: 0.6 | T98: pct | U98: % of value | V98: value (ex-factory or CIF basis) | W98: 60% or UGX 2,050 / liter | X98: all | AF98: =IF(T98="USD",1,IF(T98="pct","",INDEX(Parameters!$D$5:$D$7,MATCH(B98,Parameters!$A$5:$A$7,0)))) | AG98: =IF(AND(R98="specific",ISNUMBER(S98)),S98/AF98,"") | AI98: =IF(NOT(ISNUMBER(AH98)),"",IF(R98="specific",IF(ISNUMBER(AG98),AG98*AH98,""),IF(AND(R98="ad_valorem",ISNUMBER(AJ98)),S98*AJ98/INDEX(Parameters!$D$5:$D$7,MATCH(B98,Parameters!$A$5:$A$7,0))*AH98,""))) | AL98: =IF(NOT(ISNUMBER(AJ98)),"",IF(R98="specific",S98/AJ98,IF(R98="ad_valorem",S98,""))) | AM98: not_reviewed | AO98: =IF(AM98="","",IFERROR(INDEX(DQ_Scale!$B$5:$B$14,MATCH(AM98,DQ_Scale!$A$5:$A$14,0)),"")) -> 2
A99: UGA-095 | B99: UGA | C99: Uganda | D99: 2026-04-27 | E99: 3 Health | F99: health | G99: A1 | H99: Beer, mainstream malt (5% ABV) | I99: per LPA | J99: 1 | K99: Malt beer | M99: Excise Duty Act 2014, as amended to the 2025 Amendment Acts | N99: 2025-07-01 | O99: current | P99: UGA-maltbeer | Q99: higher_of | R99: specific | S99: 2050 | T99: UGX | U99: liter | W99: 60% or UGX 2,050 / liter | X99: all | AF99: =IF(T99="USD",1,IF(T99="pct","",INDEX(Parameters!$D$5:$D$7,MATCH(B99,Parameters!$A$5:$A$7,0)))) -> 3750 | AG99: =IF(AND(R99="specific",ISNUMBER(S99)),S99/AF99,"") -> 0.54666667 | AH99: 20 | AI99: =IF(NOT(ISNUMBER(AH99)),"",IF(R99="specific",IF(ISNUMBER(AG99),AG99*AH99,""),IF(AND(R99="ad_valorem",ISNUMBER(AJ99)),S99*AJ99/INDEX(Parameters!$D$5:$D$7,MATCH(B99,Parameters!$A$5:$A$7,0))*AH99,""))) -> 10.933333 | AJ99: 7000 | AK99: Beer UGX ~3,500 per 500 ml (estimate) | AL99: =IF(NOT(ISNUMBER(AJ99)),"",IF(R99="specific",S99/AJ99,IF(R99="ad_valorem",S99,""))) -> 0.29285714 | AM99: not_reviewed | AO99: =IF(AM99="","",IFERROR(INDEX(DQ_Scale!$B$5:$B$14,MATCH(AM99,DQ_Scale!$A$5:$A$14,0)),"")) -> 2
A100: UGA-096 | B100: UGA | C100: Uganda | D100: 2026-04-27 | E100: 3 Health | F100: health | G100: A2 | H100: Beer, local-content concession (5% ABV) | I100: per LPA | J100: 1 | K100: Beer, >=75% local raw material | M100: Excise Duty Act 2014, as amended to the 2025 Amendment Acts | N100: 2025-07-01 | O100: current | P100: UGA-beer75 | Q100: higher_of | R100: ad_valorem | S100: 0.3 | T100: pct | U100: % of value | V100: value (ex-factory or CIF basis) | W100: 30% or UGX 900 / liter | X100: local | AC100: 75 | AF100: =IF(T100="USD",1,IF(T100="pct","",INDEX(Parameters!$D$5:$D$7,MATCH(B100,Parameters!$A$5:$A$7,0)))) | AG100: =IF(AND(R100="specific",ISNUMBER(S100)),S100/AF100,"") | AI100: =IF(NOT(ISNUMBER(AH100)),"",IF(R100="specific",IF(ISNUMBER(AG100),AG100*AH100,""),IF(AND(R100="ad_valorem",ISNUMBER(AJ100)),S100*AJ100/INDEX(Parameters!$D$5:$D$7,MATCH(B100,Parameters!$A$5:$A$7,0))*AH100,""))) | AL100: =IF(NOT(ISNUMBER(AJ100)),"",IF(R100="specific",S100/AJ100,IF(R100="ad_valorem",S100,""))) | AM100: not_reviewed | AO100: =IF(AM100="","",IFERROR(INDEX(DQ_Scale!$B$5:$B$14,MATCH(AM100,DQ_Scale!$A$5:$A$14,0)),"")) -> 2
A101: UGA-097 | B101: UGA | C101: Uganda | D101: 2026-04-27 | E101: 3 Health | F101: health | G101: A2 | H101: Beer, local-content concession (5% ABV) | I101: per LPA | J101: 1 | K101: Beer, >=75% local raw material | M101: Excise Duty Act 2014, as amended to the 2025 Amendment Acts | N101: 2025-07-01 | O101: current | P101: UGA-beer75 | Q101: higher_of | R101: specific | S101: 900 | T101: UGX | U101: liter | W101: 30% or UGX 900 / liter | X101: local | AC101: 75 | AF101: =IF(T101="USD",1,IF(T101="pct","",INDEX(Parameters!$D$5:$D$7,MATCH(B101,Parameters!$A$5:$A$7,0)))) -> 3750 | AG101: =IF(AND(R101="specific",ISNUMBER(S101)),S101/AF101,"") -> 0.24 | AH101: 20 | AI101: =IF(NOT(ISNUMBER(AH101)),"",IF(R101="specific",IF(ISNUMBER(AG101),AG101*AH101,""),IF(AND(R101="ad_valorem",ISNUMBER(AJ101)),S101*AJ101/INDEX(Parameters!$D$5:$D$7,MATCH(B101,Parameters!$A$5:$A$7,0))*AH101,""))) -> 4.8 | AJ101: 7000 | AK101: Beer UGX ~3,500 per 500 ml (estimate) | AL101: =IF(NOT(ISNUMBER(AJ101)),"",IF(R101="specific",S101/AJ101,IF(R101="ad_valorem",S101,""))) -> 0.12857143 | AM101: not_reviewed | AO101: =IF(AM101="","",IFERROR(INDEX(DQ_Scale!$B$5:$B$14,MATCH(AM101,DQ_Scale!$A$5:$A$14,0)),"")) -> 2
...

Sheet Parameters
A1: Parameters used by the code-readable schedule
A2: Blue = input. Change an exchange rate here and every USD column in Std_Schedule_Code updates.
A4: ISO3 | B4: Country | C4: Local currency | D4: LCU per USD | E4: FX status | F4: FX source | G4: Cut-off date | H4: Nominal GDP (USD bn) | I4: GDP source | J4: Diagnostic version
A5: SLE | B5: Sierra Leone | C5: NLe | D5: 22 | E5: assumption | F5: Working rate (WP v0.8, PR-40). MoF uses NLe 22.665 (2024) and 23 (2025): USD values may be ~4% high | G5: 2026-04-27 | H5: 7.5 | I5: Working 2026 figure (WP v0.8, PR-41); MoF 2025 prel. ~USD 7.2bn | J5: Excise Diagnostic working paper v0.8 (Sept 2026)
A6: UGA | B6: Uganda | C6: UGX | D6: 3750 | E6: not_reviewed | F6: Working mid-rate (WP v0.8, Table 13) | G6: 2026-04-27 | H6: 55 | I6: WP v0.8 estimate (World Bank 2024: USD 53.65bn) | J6: Excise Diagnostic working paper v0.8, Annex A (not peer reviewed)
A7: LBR | B7: Liberia | C7: LRD | D7: 171.592 | E7: verified | F7: CBL mid-rate, 28 Sep 2026 (buying 170.5521, selling 172.6319). Excise rates are printed in US$ | G7: 2026-09-29 | H7: 5.2459389 | I7: World Bank WDI 2025 (GDP compiled in US$) | J7: Liberia Excise Diagnostic v0.3 (29 Sep 2026)
A9: Conversions
A10: Beer, representative ABV | D10: 0.05
A11: Opaque / traditional beer, ABV | D11: 0.04
A12: Wine, ABV | D12: 0.12
A13: Spirits, ABV | D13: 0.4
A14: Cigarettes: per 1,000 sticks to per pack of 20 | D14: 0.02
A15: Liters per US gallon | D15: 3.7854118

Sheet DQ_Scale
A1: Data quality (DQ) scale
A2: DQ reflects the level of peer review (stage A5). Scores feed every DQ column by formula.
A4: Review status (code) | B4: DQ score | C4: Meaning
A5: verified | B5: 5 | C5: Checked against the primary legal text or official data, with a quote on file.
A6: verified_open_point | B6: 4 | C6: Primary text checked and matches; an interpretation point is still open (e.g. Liberia's 'Proposed' column read as in force).
A7: corrected | B7: 4 | C7: Error or omission found in peer review; corrected and now matches the source.
A8: partly_verified | B8: 3 | C8: Confirmed only in an official secondary source (budget speech, revenue authority notice, IMF report), or only part of the claim checked.
A9: not_verified | B9: 2 | C9: Looked for in peer review but no accessible source confirmed it; or press / unofficial source only.
A10: not_reviewed | B10: 2 | C10: Extracted from the legal texts but not yet peer reviewed (all Uganda lines in WP v0.8).
A11: estimate | B11: 2 | C11: Derived from published inputs with estimated volumes, prices or mixed years.
A12: last_legible | B12: 1 | C12: Current rate not legible in the published law; last legible (superseded) rate shown.
A13: assumption | B13: 1 | C13: Rests on an unsourced assumption, or an indicative figure.
A14: data_gap | B14: 1 | C14: No data; not estimated.
A16: Score | B16: Label | C16: Reading
A17: 5 | B17: High | C17: Can be cited as law or official data.
A18: 4 | B18: Good | C18: Usable; one caveat to state.
A19: 3 | B19: Moderate | C19: Usable with a source caveat; confirm before citing as law.
A20: 2 | B20: Low | C20: Indicative only; needs peer review or a better source.
A21: 1 | B21: Very low | C21: Placeholder; do not use for policy conclusions.
A23: Rules for derived figures
A24: A derived metric takes the lowest DQ of its inputs. Implied revenue from estimated or prevalence-based volumes is capped at 2 ('estimate'); indicative figures are 1 ('assumption'). On the standardized schedule, a line's DQ is the lowest DQ among the national lines mapped to it.

Sheet Sources
A1: Sources and versions
A4: Country | B4: Document | C4: Version / date | D4: Legal cut-off | E4: Peer-review status | F4: Used for
A5: SLE, UGA | B5: Excise Diagnostic working paper (World Bank, draft for discussion) | C5: v0.8, September 2026 | D5: 2026-04-27 | E5: SLE: 49 register entries (18 V, 11 PV, 16 C, 4 NV). UGA: not peer reviewed | F5: Metrics (Tables 7, 9, 13, 14); schedule (Tables 10a-c, 11, A1); statuses (Table D3)
A6: SLE | B6: Sierra Leone: An Excise Diagnostic (example) | C6: Draft, July 2026 | D6: Finance Act 2026 | E6: Pre-peer-review; superseded by WP v0.8 where they differ (e.g. SSB coverage, wine anomaly) | F6: Not used for values
A7: LBR | B7: Liberia Excise Diagnostic | C7: v0.3, 29 September 2026 | D7: 2026-09-29 | E7: 49 register entries (22 V, 11 PV, 14 C, 2 NV) | F7: Metrics (Level 1, Level 4); schedule (Tables 9.1, 10.1); statuses (Annex B)
A8: All | B8: Excise diagnostic process specification (MASTER) | C8: spec 1.0; standard schedule 1.0 | D8: - | E8: - | F8: Standard lines, coverage codes, conversions, benchmarks (section 9)
