Workbook
Name OBRSHARE: _xlfn.LAMBDA(_xlpm.benchmark,MIN(1,MAX(0,_xlpm.benchmark)))
Name COVERED: _xlfn.LAMBDA(_xlpm.emissions,_xlpm.coverage,SUMPRODUCT(_xlpm.emissions,_xlpm.coverage))
Name TAXEQUIV: _xlfn.LAMBDA(_xlpm.price,_xlpm.vadj,_xlpm.price*_xlpm.vadj)
Name REVFACTOR: _xlfn.LAMBDA(_xlpm.vadj,IF(_xlpm.vadj>0,1/_xlpm.vadj,0))
Name ETSCOVER: _xlfn.LAMBDA(_xlpm.apply,_xlpm.year,_xlpm.start_year,_xlpm.covered,IF(AND(LEFT(_xlpm.apply,3)="Yes",_xlpm.year>=_xlpm.start_year),IF(_xlpm.covered,1,0),0))
Name SHADOWSECTOR: _xlfn.LAMBDA(_xlpm.feebate,_xlpm.regulation,_xlpm.feebate+_xlpm.regulation)
Name SHADOWSHARE: _xlfn.LAMBDA(_xlpm.coverage,_xlpm.adjustment,IF(_xlpm.coverage,1,0)*_xlpm.adjustment)
Name RETAILPRICE: _xlfn.LAMBDA(_xlpm.sp,_xlpm.txo,_xlpm.vat_rate,(_xlpm.sp+_xlpm.txo)*(1+_xlpm.vat_rate))
Name VATPAY: _xlfn.LAMBDA(_xlpm.sp,_xlpm.txo,_xlpm.vat_rate,(_xlpm.sp+_xlpm.txo)*_xlpm.vat_rate)
Name TAXPART: _xlfn.LAMBDA(_xlpm.txo,MAX(_xlpm.txo,0))
Name SUBSIDYPART: _xlfn.LAMBDA(_xlpm.txo,MAX(-_xlpm.txo,0))
Name PERUNIT: _xlfn.LAMBDA(_xlpm.value_gj,_xlpm.gj_per_unit,_xlpm.value_gj*_xlpm.gj_per_unit)
Name CARBONTAX: _xlfn.LAMBDA(_xlpm.price,_xlpm.ef,_xlpm.fuel_cov,_xlpm.sector_cov,_xlpm.ets_cov,_xlpm.price*_xlpm.ef*_xlpm.fuel_cov*_xlpm.sector_cov*(1-_xlpm.ets_cov))
Name ETSCOST: _xlfn.LAMBDA(_xlpm.price,_xlpm.ef,_xlpm.ets_cov,_xlpm.obr,_xlpm.price*_xlpm.ef*_xlpm.ets_cov*(1-_xlpm.obr))
Name NEWEXCISE: _xlfn.LAMBDA(_xlpm.increase,_xlpm.gj_per_unit,_xlpm.increase/_xlpm.gj_per_unit)
Name NEWPOLICY: _xlfn.LAMBDA(_xlpm.carbon_tax,_xlpm.ets,_xlpm.excise,_xlpm.carbon_tax+_xlpm.ets+_xlpm.excise)
Name POSTTAX: _xlfn.LAMBDA(_xlpm.pre_policy_p,_xlpm.new_policy,_xlpm.vat_rate,MAX(_xlpm.pre_policy_p+_xlpm.new_policy*(1+_xlpm.vat_rate),0.01))
Name SHADOWEFF: _xlfn.LAMBDA(_xlpm.sector_price,_xlpm.share,_xlpm.ets_price,_xlpm.ets_cov,_xlpm.obr,_xlpm.ef,(_xlpm.sector_price*_xlpm.share+_xlpm.ets_price*_xlpm.ets_cov*_xlpm.obr)*_xlpm.ef)
Name REVENUE: _xlfn.LAMBDA(_xlpm.fuel_use,_xlpm.pj_per_ktoe,_xlpm.rate,_xlpm.fuel_use*_xlpm.pj_per_ktoe*_xlpm.rate)
Name EMISSIONS: _xlfn.LAMBDA(_xlpm.fuel_use,_xlpm.pj_per_ktoe,_xlpm.ef,_xlpm.fuel_use*_xlpm.pj_per_ktoe*_xlpm.ef)
Name NEWREVRATE: _xlfn.LAMBDA(_xlpm.carbon_tax,_xlpm.excise,_xlpm.ets,_xlpm.rev_factor,_xlpm.new_policy,_xlpm.vat_rate,_xlpm.carbon_tax+_xlpm.excise+_xlpm.ets*_xlpm.rev_factor+_xlpm.new_policy*_xlpm.vat_rate)

Sheet Mitigation
A1: Variable | B1: Fuel | C1: Sector | D1: Param 1 | E1: Param 2 | F1: Param 3 | G1: Param 4 | H1: Description | I1: Unit | J1: Source | K1: Scenario 1: output code | AF1: Scenario 2: output code
A2: CPAT-AI-Mitigation-MVP v1.02 - mitigation module: policies, prices, fuel use, revenues, CO2 (copy-pasteable)
A3: Scenario assumptions (one column group per scenario: code column + years; copy a whole group to add a scenario)
H4: Year | L4: =Settings!$C$7 | M4: =L4+1 | N4: =M4+1 | O4: =N4+1 | P4: =O4+1 | Q4: =P4+1 | R4: =Q4+1 | S4: =R4+1 | T4: =S4+1 | ... AD4: =AC4+1 | AG4: =Settings!$C$7 | AH4: =AG4+1 | AI4: =AH4+1 | AJ4: =AI4+1 | AK4: =AJ4+1 | AL4: =AK4+1 | AM4: =AL4+1 | AN4: =AM4+1 | AO4: =AN4+1 | ... AY4: =AX4+1
H5: Scenario number (MTInputs column) | K5: 1 | L5: =K5 | M5: =L5 | N5: =M5 | O5: =N5 | P5: =O5 | Q5: =P5 | R5: =Q5 | S5: =R5 | ... AD5: =AC5 | AF5: =K5+1 | AG5: =AF5 | AH5: =AG5 | AI5: =AH5 | AJ5: =AI5 | AK5: =AJ5 | AL5: =AK5 | AM5: =AL5 | AN5: =AM5 | ... AY5: =AX5
H6: Scenario name (from MTInputs) | L6: =INDEX(MTInputs!$J$6:$AZ$6,MATCH(L$5,MTInputs!$J$5:$AZ$5,0)) | AG6: =INDEX(MTInputs!$J$6:$AZ$6,MATCH(AG$5,MTInputs!$J$5:$AZ$5,0))
A7: gdp.pos.pct | H7: =INDEX(Variables!$B$5:$B$105,MATCH($A7,Variables!$A$5:$A$105,0))&IF($C7="",""," | "&INDEX(Mapping!$B$5:$B$26,MATCH($C7,Mapping!$A$5:$A$26,0))&" | "&INDEX(Mapping!$B$30:$B$41,MATCH($B7,Mapping!$A$30:$A$41,0))) | I7: =INDEX(Variables!$C$5:$C$105,MATCH($A7,Variables!$A$5:$A$105,0)) | J7: =INDEX(Variables!$E$5:$E$105,MATCH($A7,Variables!$A$5:$A$105,0)) | K7: =LOWER(Settings!$C$4)&".mit."&$A7&IF($C7="","","."&$C7&"."&$B7)&IF(INDEX(Variables!$D$5:$D$105,MATCH($A7,Variables!$A$5:$A$105,0))="","","."&INDEX(Variables!$D$5:$D$105,MATCH($A7,Variables!$A$5:$A$105,0)))&"."&K$5 | L7: =INDEX(WEO!$F$4:$AZ$1000,MATCH(Settings!$C$4&"|gdp_growth",WEO!$A$4:$A$1000,0),MATCH(L$4,WEO!$F$3:$AZ$3,0)) | M7: =INDEX(WEO!$F$4:$AZ$1000,MATCH(Settings!$C$4&"|gdp_growth",WEO!$A$4:$A$1000,0),MATCH(M$4,WEO!$F$3:$AZ$3,0)) | N7: =INDEX(WEO!$F$4:$AZ$1000,MATCH(Settings!$C$4&"|gdp_growth",WEO!$A$4:$A$1000,0),MATCH(N$4,WEO!$F$3:$AZ$3,0)) | O7: =INDEX(WEO!$F$4:$AZ$1000,MATCH(Settings!$C$4&"|gdp_growth",WEO!$A$4:$A$1000,0),MATCH(O$4,WEO!$F$3:$AZ$3,0)) | P7: =INDEX(WEO!$F$4:$AZ$1000,MATCH(Settings!$C$4&"|gdp_growth",WEO!$A$4:$A$1000,0),MATCH(P$4,WEO!$F$3:$AZ$3,0)) | Q7: =INDEX(WEO!$F$4:$AZ$1000,MATCH(Settings!$C$4&"|gdp_growth",WEO!$A$4:$A$1000,0),MATCH(Q$4,WEO!$F$3:$AZ$3,0)) | R7: =INDEX(WEO!$F$4:$AZ$1000,MATCH(Settings!$C$4&"|gdp_growth",WEO!$A$4:$A$1000,0),MATCH(R$4,WEO!$F$3:$AZ$3,0)) | S7: =INDEX(WEO!$F$4:$AZ$1000,MATCH(Settings!$C$4&"|gdp_growth",WEO!$A$4:$A$1000,0),MATCH(S$4,WEO!$F$3:$AZ$3,0)) | ... AD7: =INDEX(WEO!$F$4:$AZ$1000,MATCH(Settings!$C$4&"|gdp_growth",WEO!$A$4:$A$1000,0),MATCH(AD$4,WEO!$F$3:$AZ$3,0)) | AF7: =LOWER(Settings!$C$4)&".mit."&$A7&IF($C7="","","."&$C7&"."&$B7)&IF(INDEX(Variables!$D$5:$D$105,MATCH($A7,Variables!$A$5:$A$105,0))="","","."&INDEX(Variables!$D$5:$D$105,MATCH($A7,Variables!$A$5:$A$105,0)))&"."&AF$5 | AG7: =INDEX(WEO!$F$4:$AZ$1000,MATCH(Settings!$C$4&"|gdp_growth",WEO!$A$4:$A$1000,0),MATCH(AG$4,WEO!$F$3:$AZ$3,0)) | AH7: =INDEX(WEO!$F$4:$AZ$1000,MATCH(Settings!$C$4&"|gdp_growth",WEO!$A$4:$A$1000,0),MATCH(AH$4,WEO!$F$3:$AZ$3,0)) | AI7: =INDEX(WEO!$F$4:$AZ$1000,MATCH(Settings!$C$4&"|gdp_growth",WEO!$A$4:$A$1000,0),MATCH(AI$4,WEO!$F$3:$AZ$3,0)) | AJ7: =INDEX(WEO!$F$4:$AZ$1000,MATCH(Settings!$C$4&"|gdp_growth",WEO!$A$4:$A$1000,0),MATCH(AJ$4,WEO!$F$3:$AZ$3,0)) | AK7: =INDEX(WEO!$F$4:$AZ$1000,MATCH(Settings!$C$4&"|gdp_growth",WEO!$A$4:$A$1000,0),MATCH(AK$4,WEO!$F$3:$AZ$3,0)) | AL7: =INDEX(WEO!$F$4:$AZ$1000,MATCH(Settings!$C$4&"|gdp_growth",WEO!$A$4:$A$1000,0),MATCH(AL$4,WEO!$F$3:$AZ$3,0)) | AM7: =INDEX(WEO!$F$4:$AZ$1000,MATCH(Settings!$C$4&"|gdp_growth",WEO!$A$4:$A$1000,0),MATCH(AM$4,WEO!$F$3:$AZ$3,0)) | AN7: =INDEX(WEO!$F$4:$AZ$1000,MATCH(Settings!$C$4&"|gdp_growth",WEO!$A$4:$A$1000,0),MATCH(AN$4,WEO!$F$3:$AZ$3,0)) | ... AY7: =INDEX(WEO!$F$4:$AZ$1000,MATCH(Settings!$C$4&"|gdp_growth",WEO!$A$4:$A$1000,0),MATCH(AY$4,WEO!$F$3:$AZ$3,0))
A8: infl | H8: =INDEX(Variables!$B$5:$B$105,MATCH($A8,Variables!$A$5:$A$105,0))&IF($C8="",""," | "&INDEX(Mapping!$B$5:$B$26,MATCH($C8,Mapping!$A$5:$A$26,0))&" | "&INDEX(Mapping!$B$30:$B$41,MATCH($B8,Mapping!$A$30:$A$41,0))) | I8: =INDEX(Variables!$C$5:$C$105,MATCH($A8,Variables!$A$5:$A$105,0)) | J8: =INDEX(Variables!$E$5:$E$105,MATCH($A8,Variables!$A$5:$A$105,0)) | K8: =LOWER(Settings!$C$4)&".mit."&$A8&IF($C8="","","."&$C8&"."&$B8)&IF(INDEX(Variables!$D$5:$D$105,MATCH($A8,Variables!$A$5:$A$105,0))="","","."&INDEX(Variables!$D$5:$D$105,MATCH($A8,Variables!$A$5:$A$105,0)))&"."&K$5 | L8: =INDEX(WEO!$F$4:$AZ$1000,MATCH("USA|pcpi",WEO!$A$4:$A$1000,0),MATCH(Settings!$C$8,WEO!$F$3:$AZ$3,0))/INDEX(WEO!$F$4:$AZ$1000,MATCH("USA|pcpi",WEO!$A$4:$A$1000,0),MATCH(L$4,WEO!$F$3:$AZ$3,0)) | M8: =INDEX(WEO!$F$4:$AZ$1000,MATCH("USA|pcpi",WEO!$A$4:$A$1000,0),MATCH(Settings!$C$8,WEO!$F$3:$AZ$3,0))/INDEX(WEO!$F$4:$AZ$1000,MATCH("USA|pcpi",WEO!$A$4:$A$1000,0),MATCH(M$4,WEO!$F$3:$AZ$3,0)) | N8: =INDEX(WEO!$F$4:$AZ$1000,MATCH("USA|pcpi",WEO!$A$4:$A$1000,0),MATCH(Settings!$C$8,WEO!$F$3:$AZ$3,0))/INDEX(WEO!$F$4:$AZ$1000,MATCH("USA|pcpi",WEO!$A$4:$A$1000,0),MATCH(N$4,WEO!$F$3:$AZ$3,0)) | O8: =INDEX(WEO!$F$4:$AZ$1000,MATCH("USA|pcpi",WEO!$A$4:$A$1000,0),MATCH(Settings!$C$8,WEO!$F$3:$AZ$3,0))/INDEX(WEO!$F$4:$AZ$1000,MATCH("USA|pcpi",WEO!$A$4:$A$1000,0),MATCH(O$4,WEO!$F$3:$AZ$3,0)) | P8: =INDEX(WEO!$F$4:$AZ$1000,MATCH("USA|pcpi",WEO!$A$4:$A$1000,0),MATCH(Settings!$C$8,WEO!$F$3:$AZ$3,0))/INDEX(WEO!$F$4:$AZ$1000,MATCH("USA|pcpi",WEO!$A$4:$A$1000,0),MATCH(P$4,WEO!$F$3:$AZ$3,0)) | Q8: =INDEX(WEO!$F$4:$AZ$1000,MATCH("USA|pcpi",WEO!$A$4:$A$1000,0),MATCH(Settings!$C$8,WEO!$F$3:$AZ$3,0))/INDEX(WEO!$F$4:$AZ$1000,MATCH("USA|pcpi",WEO!$A$4:$A$1000,0),MATCH(Q$4,WEO!$F$3:$AZ$3,0)) | R8: =INDEX(WEO!$F$4:$AZ$1000,MATCH("USA|pcpi",WEO!$A$4:$A$1000,0),MATCH(Settings!$C$8,WEO!$F$3:$AZ$3,0))/INDEX(WEO!$F$4:$AZ$1000,MATCH("USA|pcpi",WEO!$A$4:$A$1000,0),MATCH(R$4,WEO!$F$3:$AZ$3,0)) | S8: =INDEX(WEO!$F$4:$AZ$1000,MATCH("USA|pcpi",WEO!$A$4:$A$1000,0),MATCH(Settings!$C$8,WEO!$F$3:$AZ$3,0))/INDEX(WEO!$F$4:$AZ$1000,MATCH("USA|pcpi",WEO!$A$4:$A$1000,0),MATCH(S$4,WEO!$F$3:$AZ$3,0)) | ... AD8: =INDEX(WEO!$F$4:$AZ$1000,MATCH("USA|pcpi",WEO!$A$4:$A$1000,0),MATCH(Settings!$C$8,WEO!$F$3:$AZ$3,0))/INDEX(WEO!$F$4:$AZ$1000,MATCH("USA|pcpi",WEO!$A$4:$A$1000,0),MATCH(AD$4,WEO!$F$3:$AZ$3,0)) | AF8: =LOWER(Settings!$C$4)&".mit."&$A8&IF($C8="","","."&$C8&"."&$B8)&IF(INDEX(Variables!$D$5:$D$105,MATCH($A8,Variables!$A$5:$A$105,0))="","","."&INDEX(Variables!$D$5:$D$105,MATCH($A8,Variables!$A$5:$A$105,0)))&"."&AF$5 | AG8: =INDEX(WEO!$F$4:$AZ$1000,MATCH("USA|pcpi",WEO!$A$4:$A$1000,0),MATCH(Settings!$C$8,WEO!$F$3:$AZ$3,0))/INDEX(WEO!$F$4:$AZ$1000,MATCH("USA|pcpi",WEO!$A$4:$A$1000,0),MATCH(AG$4,WEO!$F$3:$AZ$3,0)) | AH8: =INDEX(WEO!$F$4:$AZ$1000,MATCH("USA|pcpi",WEO!$A$4:$A$1000,0),MATCH(Settings!$C$8,WEO!$F$3:$AZ$3,0))/INDEX(WEO!$F$4:$AZ$1000,MATCH("USA|pcpi",WEO!$A$4:$A$1000,0),MATCH(AH$4,WEO!$F$3:$AZ$3,0)) | AI8: =INDEX(WEO!$F$4:$AZ$1000,MATCH("USA|pcpi",WEO!$A$4:$A$1000,0),MATCH(Settings!$C$8,WEO!$F$3:$AZ$3,0))/INDEX(WEO!$F$4:$AZ$1000,MATCH("USA|pcpi",WEO!$A$4:$A$1000,0),MATCH(AI$4,WEO!$F$3:$AZ$3,0)) | AJ8: =INDEX(WEO!$F$4:$AZ$1000,MATCH("USA|pcpi",WEO!$A$4:$A$1000,0),MATCH(Settings!$C$8,WEO!$F$3:$AZ$3,0))/INDEX(WEO!$F$4:$AZ$1000,MATCH("USA|pcpi",WEO!$A$4:$A$1000,0),MATCH(AJ$4,WEO!$F$3:$AZ$3,0)) | AK8: =INDEX(WEO!$F$4:$AZ$1000,MATCH("USA|pcpi",WEO!$A$4:$A$1000,0),MATCH(Settings!$C$8,WEO!$F$3:$AZ$3,0))/INDEX(WEO!$F$4:$AZ$1000,MATCH("USA|pcpi",WEO!$A$4:$A$1000,0),MATCH(AK$4,WEO!$F$3:$AZ$3,0)) | AL8: =INDEX(WEO!$F$4:$AZ$1000,MATCH("USA|pcpi",WEO!$A$4:$A$1000,0),MATCH(Settings!$C$8,WEO!$F$3:$AZ$3,0))/INDEX(WEO!$F$4:$AZ$1000,MATCH("USA|pcpi",WEO!$A$4:$A$1000,0),MATCH(AL$4,WEO!$F$3:$AZ$3,0)) | AM8: =INDEX(WEO!$F$4:$AZ$1000,MATCH("USA|pcpi",WEO!$A$4:$A$1000,0),MATCH(Settings!$C$8,WEO!$F$3:$AZ$3,0))/INDEX(WEO!$F$4:$AZ$1000,MATCH("USA|pcpi",WEO!$A$4:$A$1000,0),MATCH(AM$4,WEO!$F$3:$AZ$3,0)) | AN8: =INDEX(WEO!$F$4:$AZ$1000,MATCH("USA|pcpi",WEO!$A$4:$A$1000,0),MATCH(Settings!$C$8,WEO!$F$3:$AZ$3,0))/INDEX(WEO!$F$4:$AZ$1000,MATCH("USA|pcpi",WEO!$A$4:$A$1000,0),MATCH(AN$4,WEO!$F$3:$AZ$3,0)) | ... AY8: =INDEX(WEO!$F$4:$AZ$1000,MATCH("USA|pcpi",WEO!$A$4:$A$1000,0),MATCH(Settings!$C$8,WEO!$F$3:$AZ$3,0))/INDEX(WEO!$F$4:$AZ$1000,MATCH("USA|pcpi",WEO!$A$4:$A$1000,0),MATCH(AY$4,WEO!$F$3:$AZ$3,0))
A9: defl | H9: =INDEX(Variables!$B$5:$B$105,MATCH($A9,Variables!$A$5:$A$105,0))&IF($C9="",""," | "&INDEX(Mapping!$B$5:$B$26,MATCH($C9,Mapping!$A$5:$A$26,0))&" | "&INDEX(Mapping!$B$30:$B$41,MATCH($B9,Mapping!$A$30:$A$41,0))) | I9: =INDEX(Variables!$C$5:$C$105,MATCH($A9,Variables!$A$5:$A$105,0)) | J9: =INDEX(Variables!$E$5:$E$105,MATCH($A9,Variables!$A$5:$A$105,0)) | K9: =LOWER(Settings!$C$4)&".mit."&$A9&IF($C9="","","."&$C9&"."&$B9)&IF(INDEX(Variables!$D$5:$D$105,MATCH($A9,Variables!$A$5:$A$105,0))="","","."&INDEX(Variables!$D$5:$D$105,MATCH($A9,Variables!$A$5:$A$105,0)))&"."&K$5 | L9: =INDEX(WEO!$F$4:$AZ$1000,MATCH("USA|ngdp_d",WEO!$A$4:$A$1000,0),MATCH(Settings!$C$8,WEO!$F$3:$AZ$3,0))/INDEX(WEO!$F$4:$AZ$1000,MATCH("USA|ngdp_d",WEO!$A$4:$A$1000,0),MATCH(L$4,WEO!$F$3:$AZ$3,0)) | M9: =INDEX(WEO!$F$4:$AZ$1000,MATCH("USA|ngdp_d",WEO!$A$4:$A$1000,0),MATCH(Settings!$C$8,WEO!$F$3:$AZ$3,0))/INDEX(WEO!$F$4:$AZ$1000,MATCH("USA|ngdp_d",WEO!$A$4:$A$1000,0),MATCH(M$4,WEO!$F$3:$AZ$3,0)) | N9: =INDEX(WEO!$F$4:$AZ$1000,MATCH("USA|ngdp_d",WEO!$A$4:$A$1000,0),MATCH(Settings!$C$8,WEO!$F$3:$AZ$3,0))/INDEX(WEO!$F$4:$AZ$1000,MATCH("USA|ngdp_d",WEO!$A$4:$A$1000,0),MATCH(N$4,WEO!$F$3:$AZ$3,0)) | O9: =INDEX(WEO!$F$4:$AZ$1000,MATCH("USA|ngdp_d",WEO!$A$4:$A$1000,0),MATCH(Settings!$C$8,WEO!$F$3:$AZ$3,0))/INDEX(WEO!$F$4:$AZ$1000,MATCH("USA|ngdp_d",WEO!$A$4:$A$1000,0),MATCH(O$4,WEO!$F$3:$AZ$3,0)) | P9: =INDEX(WEO!$F$4:$AZ$1000,MATCH("USA|ngdp_d",WEO!$A$4:$A$1000,0),MATCH(Settings!$C$8,WEO!$F$3:$AZ$3,0))/INDEX(WEO!$F$4:$AZ$1000,MATCH("USA|ngdp_d",WEO!$A$4:$A$1000,0),MATCH(P$4,WEO!$F$3:$AZ$3,0)) | Q9: =INDEX(WEO!$F$4:$AZ$1000,MATCH("USA|ngdp_d",WEO!$A$4:$A$1000,0),MATCH(Settings!$C$8,WEO!$F$3:$AZ$3,0))/INDEX(WEO!$F$4:$AZ$1000,MATCH("USA|ngdp_d",WEO!$A$4:$A$1000,0),MATCH(Q$4,WEO!$F$3:$AZ$3,0)) | R9: =INDEX(WEO!$F$4:$AZ$1000,MATCH("USA|ngdp_d",WEO!$A$4:$A$1000,0),MATCH(Settings!$C$8,WEO!$F$3:$AZ$3,0))/INDEX(WEO!$F$4:$AZ$1000,MATCH("USA|ngdp_d",WEO!$A$4:$A$1000,0),MATCH(R$4,WEO!$F$3:$AZ$3,0)) | S9: =INDEX(WEO!$F$4:$AZ$1000,MATCH("USA|ngdp_d",WEO!$A$4:$A$1000,0),MATCH(Settings!$C$8,WEO!$F$3:$AZ$3,0))/INDEX(WEO!$F$4:$AZ$1000,MATCH("USA|ngdp_d",WEO!$A$4:$A$1000,0),MATCH(S$4,WEO!$F$3:$AZ$3,0)) | ... AD9: =INDEX(WEO!$F$4:$AZ$1000,MATCH("USA|ngdp_d",WEO!$A$4:$A$1000,0),MATCH(Settings!$C$8,WEO!$F$3:$AZ$3,0))/INDEX(WEO!$F$4:$AZ$1000,MATCH("USA|ngdp_d",WEO!$A$4:$A$1000,0),MATCH(AD$4,WEO!$F$3:$AZ$3,0)) | AF9: =LOWER(Settings!$C$4)&".mit."&$A9&IF($C9="","","."&$C9&"."&$B9)&IF(INDEX(Variables!$D$5:$D$105,MATCH($A9,Variables!$A$5:$A$105,0))="","","."&INDEX(Variables!$D$5:$D$105,MATCH($A9,Variables!$A$5:$A$105,0)))&"."&AF$5 | AG9: =INDEX(WEO!$F$4:$AZ$1000,MATCH("USA|ngdp_d",WEO!$A$4:$A$1000,0),MATCH(Settings!$C$8,WEO!$F$3:$AZ$3,0))/INDEX(WEO!$F$4:$AZ$1000,MATCH("USA|ngdp_d",WEO!$A$4:$A$1000,0),MATCH(AG$4,WEO!$F$3:$AZ$3,0)) | AH9: =INDEX(WEO!$F$4:$AZ$1000,MATCH("USA|ngdp_d",WEO!$A$4:$A$1000,0),MATCH(Settings!$C$8,WEO!$F$3:$AZ$3,0))/INDEX(WEO!$F$4:$AZ$1000,MATCH("USA|ngdp_d",WEO!$A$4:$A$1000,0),MATCH(AH$4,WEO!$F$3:$AZ$3,0)) | AI9: =INDEX(WEO!$F$4:$AZ$1000,MATCH("USA|ngdp_d",WEO!$A$4:$A$1000,0),MATCH(Settings!$C$8,WEO!$F$3:$AZ$3,0))/INDEX(WEO!$F$4:$AZ$1000,MATCH("USA|ngdp_d",WEO!$A$4:$A$1000,0),MATCH(AI$4,WEO!$F$3:$AZ$3,0)) | AJ9: =INDEX(WEO!$F$4:$AZ$1000,MATCH("USA|ngdp_d",WEO!$A$4:$A$1000,0),MATCH(Settings!$C$8,WEO!$F$3:$AZ$3,0))/INDEX(WEO!$F$4:$AZ$1000,MATCH("USA|ngdp_d",WEO!$A$4:$A$1000,0),MATCH(AJ$4,WEO!$F$3:$AZ$3,0)) | AK9: =INDEX(WEO!$F$4:$AZ$1000,MATCH("USA|ngdp_d",WEO!$A$4:$A$1000,0),MATCH(Settings!$C$8,WEO!$F$3:$AZ$3,0))/INDEX(WEO!$F$4:$AZ$1000,MATCH("USA|ngdp_d",WEO!$A$4:$A$1000,0),MATCH(AK$4,WEO!$F$3:$AZ$3,0)) | AL9: =INDEX(WEO!$F$4:$AZ$1000,MATCH("USA|ngdp_d",WEO!$A$4:$A$1000,0),MATCH(Settings!$C$8,WEO!$F$3:$AZ$3,0))/INDEX(WEO!$F$4:$AZ$1000,MATCH("USA|ngdp_d",WEO!$A$4:$A$1000,0),MATCH(AL$4,WEO!$F$3:$AZ$3,0)) | AM9: =INDEX(WEO!$F$4:$AZ$1000,MATCH("USA|ngdp_d",WEO!$A$4:$A$1000,0),MATCH(Settings!$C$8,WEO!$F$3:$AZ$3,0))/INDEX(WEO!$F$4:$AZ$1000,MATCH("USA|ngdp_d",WEO!$A$4:$A$1000,0),MATCH(AM$4,WEO!$F$3:$AZ$3,0)) | AN9: =INDEX(WEO!$F$4:$AZ$1000,MATCH("USA|ngdp_d",WEO!$A$4:$A$1000,0),MATCH(Settings!$C$8,WEO!$F$3:$AZ$3,0))/INDEX(WEO!$F$4:$AZ$1000,MATCH("USA|ngdp_d",WEO!$A$4:$A$1000,0),MATCH(AN$4,WEO!$F$3:$AZ$3,0)) | ... AY9: =INDEX(WEO!$F$4:$AZ$1000,MATCH("USA|ngdp_d",WEO!$A$4:$A$1000,0),MATCH(Settings!$C$8,WEO!$F$3:$AZ$3,0))/INDEX(WEO!$F$4:$AZ$1000,MATCH("USA|ngdp_d",WEO!$A$4:$A$1000,0),MATCH(AY$4,WEO!$F$3:$AZ$3,0))
A11: 1. Policies (scenario inputs from MTInputs by row and scenario number; policy paths) | D11: MTInputs row
A12: cptraj | H12: =INDEX(Variables!$B$5:$B$105,MATCH($A12,Variables!$A$5:$A$105,0))&IF($C12="",""," | "&INDEX(Mapping!$B$5:$B$26,MATCH($C12,Mapping!$A$5:$A$26,0))&" | "&INDEX(Mapping!$B$30:$B$41,MATCH($B12,Mapping!$A$30:$A$41,0))) | I12: =INDEX(Variables!$C$5:$C$105,MATCH($A12,Variables!$A$5:$A$105,0)) | J12: =INDEX(Variables!$E$5:$E$105,MATCH($A12,Variables!$A$5:$A$105,0)) | K12: =LOWER(Settings!$C$4)&".mit."&$A12&IF($C12="","","."&$C12&"."&$B12)&IF(INDEX(Variables!$D$5:$D$105,MATCH($A12,Variables!$A$5:$A$105,0))="","","."&INDEX(Variables!$D$5:$D$105,MATCH($A12,Variables!$A$5:$A$105,0)))&"."&K$5 | L12: =(IF(L$4<L$14,0,L$15+(L$16-L$15)/MAX(L$17-L$14,1)*IF(OR(L$4<=L$17,L$18="Linear*"),L$4-L$14,L$17-L$14)))*IF(LEFT(L$19,7)="Nominal",L$8,1) | M12: =(IF(M$4<M$14,0,M$15+(M$16-M$15)/MAX(M$17-M$14,1)*IF(OR(M$4<=M$17,M$18="Linear*"),M$4-M$14,M$17-M$14)))*IF(LEFT(M$19,7)="Nominal",M$8,1) | N12: =(IF(N$4<N$14,0,N$15+(N$16-N$15)/MAX(N$17-N$14,1)*IF(OR(N$4<=N$17,N$18="Linear*"),N$4-N$14,N$17-N$14)))*IF(LEFT(N$19,7)="Nominal",N$8,1) | O12: =(IF(O$4<O$14,0,O$15+(O$16-O$15)/MAX(O$17-O$14,1)*IF(OR(O$4<=O$17,O$18="Linear*"),O$4-O$14,O$17-O$14)))*IF(LEFT(O$19,7)="Nominal",O$8,1) | P12: =(IF(P$4<P$14,0,P$15+(P$16-P$15)/MAX(P$17-P$14,1)*IF(OR(P$4<=P$17,P$18="Linear*"),P$4-P$14,P$17-P$14)))*IF(LEFT(P$19,7)="Nominal",P$8,1) | Q12: =(IF(Q$4<Q$14,0,Q$15+(Q$16-Q$15)/MAX(Q$17-Q$14,1)*IF(OR(Q$4<=Q$17,Q$18="Linear*"),Q$4-Q$14,Q$17-Q$14)))*IF(LEFT(Q$19,7)="Nominal",Q$8,1) | R12: =(IF(R$4<R$14,0,R$15+(R$16-R$15)/MAX(R$17-R$14,1)*IF(OR(R$4<=R$17,R$18="Linear*"),R$4-R$14,R$17-R$14)))*IF(LEFT(R$19,7)="Nominal",R$8,1) | S12: =(IF(S$4<S$14,0,S$15+(S$16-S$15)/MAX(S$17-S$14,1)*IF(OR(S$4<=S$17,S$18="Linear*"),S$4-S$14,S$17-S$14)))*IF(LEFT(S$19,7)="Nominal",S$8,1) | ... AC12: =(IF(AC$4<AC$14,0,AC$15+(AC$16-AC$15)/MAX(AC$17-AC$14,1)*IF(OR(AC$4<=AC$17,AC$18="Linear*"),AC$4-AC$14,AC$17-AC$14)))*IF(LEFT(AC$19,7)="Nominal",AC$8,1) | AD12: =PATH(AD$4,AD$14,AD$17,AD$15,AD$16,AD$18="Linear*")*IF(LEFT(AD$19,7)="Nominal",AD$8,1) | AF12: =LOWER(Settings!$C$4)&".mit."&$A12&IF($C12="","","."&$C12&"."&$B12)&IF(INDEX(Variables!$D$5:$D$105,MATCH($A12,Variables!$A$5:$A$105,0))="","","."&INDEX(Variables!$D$5:$D$105,MATCH($A12,Variables!$A$5:$A$105,0)))&"."&AF$5 | AG12: =(IF(AG$4<AG$14,0,AG$15+(AG$16-AG$15)/MAX(AG$17-AG$14,1)*IF(OR(AG$4<=AG$17,AG$18="Linear*"),AG$4-AG$14,AG$17-AG$14)))*IF(LEFT(AG$19,7)="Nominal",AG$8,1) | AH12: =(IF(AH$4<AH$14,0,AH$15+(AH$16-AH$15)/MAX(AH$17-AH$14,1)*IF(OR(AH$4<=AH$17,AH$18="Linear*"),AH$4-AH$14,AH$17-AH$14)))*IF(LEFT(AH$19,7)="Nominal",AH$8,1) | AI12: =(IF(AI$4<AI$14,0,AI$15+(AI$16-AI$15)/MAX(AI$17-AI$14,1)*IF(OR(AI$4<=AI$17,AI$18="Linear*"),AI$4-AI$14,AI$17-AI$14)))*IF(LEFT(AI$19,7)="Nominal",AI$8,1) | AJ12: =(IF(AJ$4<AJ$14,0,AJ$15+(AJ$16-AJ$15)/MAX(AJ$17-AJ$14,1)*IF(OR(AJ$4<=AJ$17,AJ$18="Linear*"),AJ$4-AJ$14,AJ$17-AJ$14)))*IF(LEFT(AJ$19,7)="Nominal",AJ$8,1) | AK12: =(IF(AK$4<AK$14,0,AK$15+(AK$16-AK$15)/MAX(AK$17-AK$14,1)*IF(OR(AK$4<=AK$17,AK$18="Linear*"),AK$4-AK$14,AK$17-AK$14)))*IF(LEFT(AK$19,7)="Nominal",AK$8,1) | AL12: =(IF(AL$4<AL$14,0,AL$15+(AL$16-AL$15)/MAX(AL$17-AL$14,1)*IF(OR(AL$4<=AL$17,AL$18="Linear*"),AL$4-AL$14,AL$17-AL$14)))*IF(LEFT(AL$19,7)="Nominal",AL$8,1) | AM12: =(IF(AM$4<AM$14,0,AM$15+(AM$16-AM$15)/MAX(AM$17-AM$14,1)*IF(OR(AM$4<=AM$17,AM$18="Linear*"),AM$4-AM$14,AM$17-AM$14)))*IF(LEFT(AM$19,7)="Nominal",AM$8,1) | AN12: =(IF(AN$4<AN$14,0,AN$15+(AN$16-AN$15)/MAX(AN$17-AN$14,1)*IF(OR(AN$4<=AN$17,AN$18="Linear*"),AN$4-AN$14,AN$17-AN$14)))*IF(LEFT(AN$19,7)="Nominal",AN$8,1) | ... AX12: =(IF(AX$4<AX$14,0,AX$15+(AX$16-AX$15)/MAX(AX$17-AX$14,1)*IF(OR(AX$4<=AX$17,AX$18="Linear*"),AX$4-AX$14,AX$17-AX$14)))*IF(LEFT(AX$19,7)="Nominal",AX$8,1) | AY12: =PATH(AY$4,AY$14,AY$17,AY$15,AY$16,AY$18="Linear*")*IF(LEFT(AY$19,7)="Nominal",AY$8,1)
H13: Carbon tax (MTInputs rows 18-21, 265, 266)
A14: CPIntro | D14: 18 | H14: =INDEX(Variables!$B$5:$B$105,MATCH($A14,Variables!$A$5:$A$105,0))&IF($C14="",""," | "&INDEX(Mapping!$B$5:$B$26,MATCH($C14,Mapping!$A$5:$A$26,0))&" | "&INDEX(Mapping!$B$30:$B$41,MATCH($B14,Mapping!$A$30:$A$41,0))) | I14: =INDEX(Variables!$C$5:$C$105,MATCH($A14,Variables!$A$5:$A$105,0)) | J14: =INDEX(Variables!$E$5:$E$105,MATCH($A14,Variables!$A$5:$A$105,0)) | K14: =LOWER(Settings!$C$4)&".mit."&$A14&IF($C14="","","."&$C14&"."&$B14)&IF(INDEX(Variables!$D$5:$D$105,MATCH($A14,Variables!$A$5:$A$105,0))="","","."&INDEX(Variables!$D$5:$D$105,MATCH($A14,Variables!$A$5:$A$105,0)))&"."&K$5 | L14: =INDEX(MTInputs!$J$1:$AZ$415,$D14,MATCH(L$5,MTInputs!$J$5:$AZ$5,0)) | M14: =INDEX(MTInputs!$J$1:$AZ$415,$D14,MATCH(M$5,MTInputs!$J$5:$AZ$5,0)) | N14: =INDEX(MTInputs!$J$1:$AZ$415,$D14,MATCH(N$5,MTInputs!$J$5:$AZ$5,0)) | O14: =INDEX(MTInputs!$J$1:$AZ$415,$D14,MATCH(O$5,MTInputs!$J$5:$AZ$5,0)) | P14: =INDEX(MTInputs!$J$1:$AZ$415,$D14,MATCH(P$5,MTInputs!$J$5:$AZ$5,0)) | Q14: =INDEX(MTInputs!$J$1:$AZ$415,$D14,MATCH(Q$5,MTInputs!$J$5:$AZ$5,0)) | R14: =INDEX(MTInputs!$J$1:$AZ$415,$D14,MATCH(R$5,MTInputs!$J$5:$AZ$5,0)) | S14: =INDEX(MTInputs!$J$1:$AZ$415,$D14,MATCH(S$5,MTInputs!$J$5:$AZ$5,0)) | ... AD14: =INDEX(MTInputs!$J$1:$AZ$415,$D14,MATCH(AD$5,MTInputs!$J$5:$AZ$5,0)) | AF14: =LOWER(Settings!$C$4)&".mit."&$A14&IF($C14="","","."&$C14&"."&$B14)&IF(INDEX(Variables!$D$5:$D$105,MATCH($A14,Variables!$A$5:$A$105,0))="","","."&INDEX(Variables!$D$5:$D$105,MATCH($A14,Variables!$A$5:$A$105,0)))&"."&AF$5 | AG14: =INDEX(MTInputs!$J$1:$AZ$415,$D14,MATCH(AG$5,MTInputs!$J$5:$AZ$5,0)) | AH14: =INDEX(MTInputs!$J$1:$AZ$415,$D14,MATCH(AH$5,MTInputs!$J$5:$AZ$5,0)) | AI14: =INDEX(MTInputs!$J$1:$AZ$415,$D14,MATCH(AI$5,MTInputs!$J$5:$AZ$5,0)) | AJ14: =INDEX(MTInputs!$J$1:$AZ$415,$D14,MATCH(AJ$5,MTInputs!$J$5:$AZ$5,0)) | AK14: =INDEX(MTInputs!$J$1:$AZ$415,$D14,MATCH(AK$5,MTInputs!$J$5:$AZ$5,0)) | AL14: =INDEX(MTInputs!$J$1:$AZ$415,$D14,MATCH(AL$5,MTInputs!$J$5:$AZ$5,0)) | AM14: =INDEX(MTInputs!$J$1:$AZ$415,$D14,MATCH(AM$5,MTInputs!$J$5:$AZ$5,0)) | AN14: =INDEX(MTInputs!$J$1:$AZ$415,$D14,MATCH(AN$5,MTInputs!$J$5:$AZ$5,0)) | ... AY14: =INDEX(MTInputs!$J$1:$AZ$415,$D14,MATCH(AY$5,MTInputs!$J$5:$AZ$5,0))
A15: CPLevelStart | D15: 19 | H15: =INDEX(Variables!$B$5:$B$105,MATCH($A15,Variables!$A$5:$A$105,0))&IF($C15="",""," | "&INDEX(Mapping!$B$5:$B$26,MATCH($C15,Mapping!$A$5:$A$26,0))&" | "&INDEX(Mapping!$B$30:$B$41,MATCH($B15,Mapping!$A$30:$A$41,0))) | I15: =INDEX(Variables!$C$5:$C$105,MATCH($A15,Variables!$A$5:$A$105,0)) | J15: =INDEX(Variables!$E$5:$E$105,MATCH($A15,Variables!$A$5:$A$105,0)) | K15: =LOWER(Settings!$C$4)&".mit."&$A15&IF($C15="","","."&$C15&"."&$B15)&IF(INDEX(Variables!$D$5:$D$105,MATCH($A15,Variables!$A$5:$A$105,0))="","","."&INDEX(Variables!$D$5:$D$105,MATCH($A15,Variables!$A$5:$A$105,0)))&"."&K$5 | L15: =INDEX(MTInputs!$J$1:$AZ$415,$D15,MATCH(L$5,MTInputs!$J$5:$AZ$5,0)) | M15: =INDEX(MTInputs!$J$1:$AZ$415,$D15,MATCH(M$5,MTInputs!$J$5:$AZ$5,0)) | N15: =INDEX(MTInputs!$J$1:$AZ$415,$D15,MATCH(N$5,MTInputs!$J$5:$AZ$5,0)) | O15: =INDEX(MTInputs!$J$1:$AZ$415,$D15,MATCH(O$5,MTInputs!$J$5:$AZ$5,0)) | P15: =INDEX(MTInputs!$J$1:$AZ$415,$D15,MATCH(P$5,MTInputs!$J$5:$AZ$5,0)) | Q15: =INDEX(MTInputs!$J$1:$AZ$415,$D15,MATCH(Q$5,MTInputs!$J$5:$AZ$5,0)) | R15: =INDEX(MTInputs!$J$1:$AZ$415,$D15,MATCH(R$5,MTInputs!$J$5:$AZ$5,0)) | S15: =INDEX(MTInputs!$J$1:$AZ$415,$D15,MATCH(S$5,MTInputs!$J$5:$AZ$5,0)) | ... AD15: =INDEX(MTInputs!$J$1:$AZ$415,$D15,MATCH(AD$5,MTInputs!$J$5:$AZ$5,0)) | AF15: =LOWER(Settings!$C$4)&".mit."&$A15&IF($C15="","","."&$C15&"."&$B15)&IF(INDEX(Variables!$D$5:$D$105,MATCH($A15,Variables!$A$5:$A$105,0))="","","."&INDEX(Variables!$D$5:$D$105,MATCH($A15,Variables!$A$5:$A$105,0)))&"."&AF$5 | AG15: =INDEX(MTInputs!$J$1:$AZ$415,$D15,MATCH(AG$5,MTInputs!$J$5:$AZ$5,0)) | AH15: =INDEX(MTInputs!$J$1:$AZ$415,$D15,MATCH(AH$5,MTInputs!$J$5:$AZ$5,0)) | AI15: =INDEX(MTInputs!$J$1:$AZ$415,$D15,MATCH(AI$5,MTInputs!$J$5:$AZ$5,0)) | AJ15: =INDEX(MTInputs!$J$1:$AZ$415,$D15,MATCH(AJ$5,MTInputs!$J$5:$AZ$5,0)) | AK15: =INDEX(MTInputs!$J$1:$AZ$415,$D15,MATCH(AK$5,MTInputs!$J$5:$AZ$5,0)) | AL15: =INDEX(MTInputs!$J$1:$AZ$415,$D15,MATCH(AL$5,MTInputs!$J$5:$AZ$5,0)) | AM15: =INDEX(MTInputs!$J$1:$AZ$415,$D15,MATCH(AM$5,MTInputs!$J$5:$AZ$5,0)) | AN15: =INDEX(MTInputs!$J$1:$AZ$415,$D15,MATCH(AN$5,MTInputs!$J$5:$AZ$5,0)) | ... AY15: =INDEX(MTInputs!$J$1:$AZ$415,$D15,MATCH(AY$5,MTInputs!$J$5:$AZ$5,0))
A16: CPLevelTarget | D16: 20 | H16: =INDEX(Variables!$B$5:$B$105,MATCH($A16,Variables!$A$5:$A$105,0))&IF($C16="",""," | "&INDEX(Mapping!$B$5:$B$26,MATCH($C16,Mapping!$A$5:$A$26,0))&" | "&INDEX(Mapping!$B$30:$B$41,MATCH($B16,Mapping!$A$30:$A$41,0))) | I16: =INDEX(Variables!$C$5:$C$105,MATCH($A16,Variables!$A$5:$A$105,0)) | J16: =INDEX(Variables!$E$5:$E$105,MATCH($A16,Variables!$A$5:$A$105,0)) | K16: =LOWER(Settings!$C$4)&".mit."&$A16&IF($C16="","","."&$C16&"."&$B16)&IF(INDEX(Variables!$D$5:$D$105,MATCH($A16,Variables!$A$5:$A$105,0))="","","."&INDEX(Variables!$D$5:$D$105,MATCH($A16,Variables!$A$5:$A$105,0)))&"."&K$5 | L16: =INDEX(MTInputs!$J$1:$AZ$415,$D16,MATCH(L$5,MTInputs!$J$5:$AZ$5,0)) | M16: =INDEX(MTInputs!$J$1:$AZ$415,$D16,MATCH(M$5,MTInputs!$J$5:$AZ$5,0)) | N16: =INDEX(MTInputs!$J$1:$AZ$415,$D16,MATCH(N$5,MTInputs!$J$5:$AZ$5,0)) | O16: =INDEX(MTInputs!$J$1:$AZ$415,$D16,MATCH(O$5,MTInputs!$J$5:$AZ$5,0)) | P16: =INDEX(MTInputs!$J$1:$AZ$415,$D16,MATCH(P$5,MTInputs!$J$5:$AZ$5,0)) | Q16: =INDEX(MTInputs!$J$1:$AZ$415,$D16,MATCH(Q$5,MTInputs!$J$5:$AZ$5,0)) | R16: =INDEX(MTInputs!$J$1:$AZ$415,$D16,MATCH(R$5,MTInputs!$J$5:$AZ$5,0)) | S16: =INDEX(MTInputs!$J$1:$AZ$415,$D16,MATCH(S$5,MTInputs!$J$5:$AZ$5,0)) | ... AD16: =INDEX(MTInputs!$J$1:$AZ$415,$D16,MATCH(AD$5,MTInputs!$J$5:$AZ$5,0)) | AF16: =LOWER(Settings!$C$4)&".mit."&$A16&IF($C16="","","."&$C16&"."&$B16)&IF(INDEX(Variables!$D$5:$D$105,MATCH($A16,Variables!$A$5:$A$105,0))="","","."&INDEX(Variables!$D$5:$D$105,MATCH($A16,Variables!$A$5:$A$105,0)))&"."&AF$5 | AG16: =INDEX(MTInputs!$J$1:$AZ$415,$D16,MATCH(AG$5,MTInputs!$J$5:$AZ$5,0)) | AH16: =INDEX(MTInputs!$J$1:$AZ$415,$D16,MATCH(AH$5,MTInputs!$J$5:$AZ$5,0)) | AI16: =INDEX(MTInputs!$J$1:$AZ$415,$D16,MATCH(AI$5,MTInputs!$J$5:$AZ$5,0)) | AJ16: =INDEX(MTInputs!$J$1:$AZ$415,$D16,MATCH(AJ$5,MTInputs!$J$5:$AZ$5,0)) | AK16: =INDEX(MTInputs!$J$1:$AZ$415,$D16,MATCH(AK$5,MTInputs!$J$5:$AZ$5,0)) | AL16: =INDEX(MTInputs!$J$1:$AZ$415,$D16,MATCH(AL$5,MTInputs!$J$5:$AZ$5,0)) | AM16: =INDEX(MTInputs!$J$1:$AZ$415,$D16,MATCH(AM$5,MTInputs!$J$5:$AZ$5,0)) | AN16: =INDEX(MTInputs!$J$1:$AZ$415,$D16,MATCH(AN$5,MTInputs!$J$5:$AZ$5,0)) | ... AY16: =INDEX(MTInputs!$J$1:$AZ$415,$D16,MATCH(AY$5,MTInputs!$J$5:$AZ$5,0))
A17: CPOutro | D17: 21 | H17: =INDEX(Variables!$B$5:$B$105,MATCH($A17,Variables!$A$5:$A$105,0))&IF($C17="",""," | "&INDEX(Mapping!$B$5:$B$26,MATCH($C17,Mapping!$A$5:$A$26,0))&" | "&INDEX(Mapping!$B$30:$B$41,MATCH($B17,Mapping!$A$30:$A$41,0))) | I17: =INDEX(Variables!$C$5:$C$105,MATCH($A17,Variables!$A$5:$A$105,0)) | J17: =INDEX(Variables!$E$5:$E$105,MATCH($A17,Variables!$A$5:$A$105,0)) | K17: =LOWER(Settings!$C$4)&".mit."&$A17&IF($C17="","","."&$C17&"."&$B17)&IF(INDEX(Variables!$D$5:$D$105,MATCH($A17,Variables!$A$5:$A$105,0))="","","."&INDEX(Variables!$D$5:$D$105,MATCH($A17,Variables!$A$5:$A$105,0)))&"."&K$5 | L17: =INDEX(MTInputs!$J$1:$AZ$415,$D17,MATCH(L$5,MTInputs!$J$5:$AZ$5,0)) | M17: =INDEX(MTInputs!$J$1:$AZ$415,$D17,MATCH(M$5,MTInputs!$J$5:$AZ$5,0)) | N17: =INDEX(MTInputs!$J$1:$AZ$415,$D17,MATCH(N$5,MTInputs!$J$5:$AZ$5,0)) | O17: =INDEX(MTInputs!$J$1:$AZ$415,$D17,MATCH(O$5,MTInputs!$J$5:$AZ$5,0)) | P17: =INDEX(MTInputs!$J$1:$AZ$415,$D17,MATCH(P$5,MTInputs!$J$5:$AZ$5,0)) | Q17: =INDEX(MTInputs!$J$1:$AZ$415,$D17,MATCH(Q$5,MTInputs!$J$5:$AZ$5,0)) | R17: =INDEX(MTInputs!$J$1:$AZ$415,$D17,MATCH(R$5,MTInputs!$J$5:$AZ$5,0)) | S17: =INDEX(MTInputs!$J$1:$AZ$415,$D17,MATCH(S$5,MTInputs!$J$5:$AZ$5,0)) | ... AD17: =INDEX(MTInputs!$J$1:$AZ$415,$D17,MATCH(AD$5,MTInputs!$J$5:$AZ$5,0)) | AF17: =LOWER(Settings!$C$4)&".mit."&$A17&IF($C17="","","."&$C17&"."&$B17)&IF(INDEX(Variables!$D$5:$D$105,MATCH($A17,Variables!$A$5:$A$105,0))="","","."&INDEX(Variables!$D$5:$D$105,MATCH($A17,Variables!$A$5:$A$105,0)))&"."&AF$5 | AG17: =INDEX(MTInputs!$J$1:$AZ$415,$D17,MATCH(AG$5,MTInputs!$J$5:$AZ$5,0)) | AH17: =INDEX(MTInputs!$J$1:$AZ$415,$D17,MATCH(AH$5,MTInputs!$J$5:$AZ$5,0)) | AI17: =INDEX(MTInputs!$J$1:$AZ$415,$D17,MATCH(AI$5,MTInputs!$J$5:$AZ$5,0)) | AJ17: =INDEX(MTInputs!$J$1:$AZ$415,$D17,MATCH(AJ$5,MTInputs!$J$5:$AZ$5,0)) | AK17: =INDEX(MTInputs!$J$1:$AZ$415,$D17,MATCH(AK$5,MTInputs!$J$5:$AZ$5,0)) | AL17: =INDEX(MTInputs!$J$1:$AZ$415,$D17,MATCH(AL$5,MTInputs!$J$5:$AZ$5,0)) | AM17: =INDEX(MTInputs!$J$1:$AZ$415,$D17,MATCH(AM$5,MTInputs!$J$5:$AZ$5,0)) | AN17: =INDEX(MTInputs!$J$1:$AZ$415,$D17,MATCH(AN$5,MTInputs!$J$5:$AZ$5,0)) | ... AY17: =INDEX(MTInputs!$J$1:$AZ$415,$D17,MATCH(AY$5,MTInputs!$J$5:$AZ$5,0))
A18: ExtendCarbonPriceBeyondOutro | D18: 265 | H18: =INDEX(Variables!$B$5:$B$105,MATCH($A18,Variables!$A$5:$A$105,0))&IF($C18="",""," | "&INDEX(Mapping!$B$5:$B$26,MATCH($C18,Mapping!$A$5:$A$26,0))&" | "&INDEX(Mapping!$B$30:$B$41,MATCH($B18,Mapping!$A$30:$A$41,0))) | I18: =INDEX(Variables!$C$5:$C$105,MATCH($A18,Variables!$A$5:$A$105,0)) | J18: =INDEX(Variables!$E$5:$E$105,MATCH($A18,Variables!$A$5:$A$105,0)) | K18: =LOWER(Settings!$C$4)&".mit."&$A18&IF($C18="","","."&$C18&"."&$B18)&IF(INDEX(Variables!$D$5:$D$105,MATCH($A18,Variables!$A$5:$A$105,0))="","","."&INDEX(Variables!$D$5:$D$105,MATCH($A18,Variables!$A$5:$A$105,0)))&"."&K$5 | L18: =INDEX(MTInputs!$J$1:$AZ$415,$D18,MATCH(L$5,MTInputs!$J$5:$AZ$5,0)) | M18: =INDEX(MTInputs!$J$1:$AZ$415,$D18,MATCH(M$5,MTInputs!$J$5:$AZ$5,0)) | N18: =INDEX(MTInputs!$J$1:$AZ$415,$D18,MATCH(N$5,MTInputs!$J$5:$AZ$5,0)) | O18: =INDEX(MTInputs!$J$1:$AZ$415,$D18,MATCH(O$5,MTInputs!$J$5:$AZ$5,0)) | P18: =INDEX(MTInputs!$J$1:$AZ$415,$D18,MATCH(P$5,MTInputs!$J$5:$AZ$5,0)) | Q18: =INDEX(MTInputs!$J$1:$AZ$415,$D18,MATCH(Q$5,MTInputs!$J$5:$AZ$5,0)) | R18: =INDEX(MTInputs!$J$1:$AZ$415,$D18,MATCH(R$5,MTInputs!$J$5:$AZ$5,0)) | S18: =INDEX(MTInputs!$J$1:$AZ$415,$D18,MATCH(S$5,MTInputs!$J$5:$AZ$5,0)) | ... AD18: =INDEX(MTInputs!$J$1:$AZ$415,$D18,MATCH(AD$5,MTInputs!$J$5:$AZ$5,0)) | AF18: =LOWER(Settings!$C$4)&".mit."&$A18&IF($C18="","","."&$C18&"."&$B18)&IF(INDEX(Variables!$D$5:$D$105,MATCH($A18,Variables!$A$5:$A$105,0))="","","."&INDEX(Variables!$D$5:$D$105,MATCH($A18,Variables!$A$5:$A$105,0)))&"."&AF$5 | AG18: =INDEX(MTInputs!$J$1:$AZ$415,$D18,MATCH(AG$5,MTInputs!$J$5:$AZ$5,0)) | AH18: =INDEX(MTInputs!$J$1:$AZ$415,$D18,MATCH(AH$5,MTInputs!$J$5:$AZ$5,0)) | AI18: =INDEX(MTInputs!$J$1:$AZ$415,$D18,MATCH(AI$5,MTInputs!$J$5:$AZ$5,0)) | AJ18: =INDEX(MTInputs!$J$1:$AZ$415,$D18,MATCH(AJ$5,MTInputs!$J$5:$AZ$5,0)) | AK18: =INDEX(MTInputs!$J$1:$AZ$415,$D18,MATCH(AK$5,MTInputs!$J$5:$AZ$5,0)) | AL18: =INDEX(MTInputs!$J$1:$AZ$415,$D18,MATCH(AL$5,MTInputs!$J$5:$AZ$5,0)) | AM18: =INDEX(MTInputs!$J$1:$AZ$415,$D18,MATCH(AM$5,MTInputs!$J$5:$AZ$5,0)) | AN18: =INDEX(MTInputs!$J$1:$AZ$415,$D18,MATCH(AN$5,MTInputs!$J$5:$AZ$5,0)) | ... AY18: =INDEX(MTInputs!$J$1:$AZ$415,$D18,MATCH(AY$5,MTInputs!$J$5:$AZ$5,0))
A19: NomorReal | D19: 266 | H19: =INDEX(Variables!$B$5:$B$105,MATCH($A19,Variables!$A$5:$A$105,0))&IF($C19="",""," | "&INDEX(Mapping!$B$5:$B$26,MATCH($C19,Mapping!$A$5:$A$26,0))&" | "&INDEX(Mapping!$B$30:$B$41,MATCH($B19,Mapping!$A$30:$A$41,0))) | I19: =INDEX(Variables!$C$5:$C$105,MATCH($A19,Variables!$A$5:$A$105,0)) | J19: =INDEX(Variables!$E$5:$E$105,MATCH($A19,Variables!$A$5:$A$105,0)) | K19: =LOWER(Settings!$C$4)&".mit."&$A19&IF($C19="","","."&$C19&"."&$B19)&IF(INDEX(Variables!$D$5:$D$105,MATCH($A19,Variables!$A$5:$A$105,0))="","","."&INDEX(Variables!$D$5:$D$105,MATCH($A19,Variables!$A$5:$A$105,0)))&"."&K$5 | L19: =INDEX(MTInputs!$J$1:$AZ$415,$D19,MATCH(L$5,MTInputs!$J$5:$AZ$5,0)) | M19: =INDEX(MTInputs!$J$1:$AZ$415,$D19,MATCH(M$5,MTInputs!$J$5:$AZ$5,0)) | N19: =INDEX(MTInputs!$J$1:$AZ$415,$D19,MATCH(N$5,MTInputs!$J$5:$AZ$5,0)) | O19: =INDEX(MTInputs!$J$1:$AZ$415,$D19,MATCH(O$5,MTInputs!$J$5:$AZ$5,0)) | P19: =INDEX(MTInputs!$J$1:$AZ$415,$D19,MATCH(P$5,MTInputs!$J$5:$AZ$5,0)) | Q19: =INDEX(MTInputs!$J$1:$AZ$415,$D19,MATCH(Q$5,MTInputs!$J$5:$AZ$5,0)) | R19: =INDEX(MTInputs!$J$1:$AZ$415,$D19,MATCH(R$5,MTInputs!$J$5:$AZ$5,0)) | S19: =INDEX(MTInputs!$J$1:$AZ$415,$D19,MATCH(S$5,MTInputs!$J$5:$AZ$5,0)) | ... AD19: =INDEX(MTInputs!$J$1:$AZ$415,$D19,MATCH(AD$5,MTInputs!$J$5:$AZ$5,0)) | AF19: =LOWER(Settings!$C$4)&".mit."&$A19&IF($C19="","","."&$C19&"."&$B19)&IF(INDEX(Variables!$D$5:$D$105,MATCH($A19,Variables!$A$5:$A$105,0))="","","."&INDEX(Variables!$D$5:$D$105,MATCH($A19,Variables!$A$5:$A$105,0)))&"."&AF$5 | AG19: =INDEX(MTInputs!$J$1:$AZ$415,$D19,MATCH(AG$5,MTInputs!$J$5:$AZ$5,0)) | AH19: =INDEX(MTInputs!$J$1:$AZ$415,$D19,MATCH(AH$5,MTInputs!$J$5:$AZ$5,0)) | AI19: =INDEX(MTInputs!$J$1:$AZ$415,$D19,MATCH(AI$5,MTInputs!$J$5:$AZ$5,0)) | AJ19: =INDEX(MTInputs!$J$1:$AZ$415,$D19,MATCH(AJ$5,MTInputs!$J$5:$AZ$5,0)) | AK19: =INDEX(MTInputs!$J$1:$AZ$415,$D19,MATCH(AK$5,MTInputs!$J$5:$AZ$5,0)) | AL19: =INDEX(MTInputs!$J$1:$AZ$415,$D19,MATCH(AL$5,MTInputs!$J$5:$AZ$5,0)) | AM19: =INDEX(MTInputs!$J$1:$AZ$415,$D19,MATCH(AM$5,MTInputs!$J$5:$AZ$5,0)) | AN19: =INDEX(MTInputs!$J$1:$AZ$415,$D19,MATCH(AN$5,MTInputs!$J$5:$AZ$5,0)) | ... AY19: =INDEX(MTInputs!$J$1:$AZ$415,$D19,MATCH(AY$5,MTInputs!$J$5:$AZ$5,0))
H20: Carbon tax coverage: fuels (MTInputs rows 23-29)
A21: ctcov | B21: coa | C21: all | D21: 23 | H21: =INDEX(Variables!$B$5:$B$105,MATCH($A21,Variables!$A$5:$A$105,0))&IF($C21="",""," | "&INDEX(Mapping!$B$5:$B$26,MATCH($C21,Mapping!$A$5:$A$26,0))&" | "&INDEX(Mapping!$B$30:$B$41,MATCH($B21,Mapping!$A$30:$A$41,0))) | I21: =INDEX(Variables!$C$5:$C$105,MATCH($A21,Variables!$A$5:$A$105,0)) | J21: =INDEX(Variables!$E$5:$E$105,MATCH($A21,Variables!$A$5:$A$105,0)) | K21: =LOWER(Settings!$C$4)&".mit."&$A21&IF($C21="","","."&$C21&"."&$B21)&IF(INDEX(Variables!$D$5:$D$105,MATCH($A21,Variables!$A$5:$A$105,0))="","","."&INDEX(Variables!$D$5:$D$105,MATCH($A21,Variables!$A$5:$A$105,0)))&"."&K$5 | L21: =INDEX(MTInputs!$J$1:$AZ$415,$D21,MATCH(L$5,MTInputs!$J$5:$AZ$5,0)) | M21: =INDEX(MTInputs!$J$1:$AZ$415,$D21,MATCH(M$5,MTInputs!$J$5:$AZ$5,0)) | N21: =INDEX(MTInputs!$J$1:$AZ$415,$D21,MATCH(N$5,MTInputs!$J$5:$AZ$5,0)) | O21: =INDEX(MTInputs!$J$1:$AZ$415,$D21,MATCH(O$5,MTInputs!$J$5:$AZ$5,0)) | P21: =INDEX(MTInputs!$J$1:$AZ$415,$D21,MATCH(P$5,MTInputs!$J$5:$AZ$5,0)) | Q21: =INDEX(MTInputs!$J$1:$AZ$415,$D21,MATCH(Q$5,MTInputs!$J$5:$AZ$5,0)) | R21: =INDEX(MTInputs!$J$1:$AZ$415,$D21,MATCH(R$5,MTInputs!$J$5:$AZ$5,0)) | S21: =INDEX(MTInputs!$J$1:$AZ$415,$D21,MATCH(S$5,MTInputs!$J$5:$AZ$5,0)) | ... AD21: =INDEX(MTInputs!$J$1:$AZ$415,$D21,MATCH(AD$5,MTInputs!$J$5:$AZ$5,0)) | AF21: =LOWER(Settings!$C$4)&".mit."&$A21&IF($C21="","","."&$C21&"."&$B21)&IF(INDEX(Variables!$D$5:$D$105,MATCH($A21,Variables!$A$5:$A$105,0))="","","."&INDEX(Variables!$D$5:$D$105,MATCH($A21,Variables!$A$5:$A$105,0)))&"."&AF$5 | AG21: =INDEX(MTInputs!$J$1:$AZ$415,$D21,MATCH(AG$5,MTInputs!$J$5:$AZ$5,0)) | AH21: =INDEX(MTInputs!$J$1:$AZ$415,$D21,MATCH(AH$5,MTInputs!$J$5:$AZ$5,0)) | AI21: =INDEX(MTInputs!$J$1:$AZ$415,$D21,MATCH(AI$5,MTInputs!$J$5:$AZ$5,0)) | AJ21: =INDEX(MTInputs!$J$1:$AZ$415,$D21,MATCH(AJ$5,MTInputs!$J$5:$AZ$5,0)) | AK21: =INDEX(MTInputs!$J$1:$AZ$415,$D21,MATCH(AK$5,MTInputs!$J$5:$AZ$5,0)) | AL21: =INDEX(MTInputs!$J$1:$AZ$415,$D21,MATCH(AL$5,MTInputs!$J$5:$AZ$5,0)) | AM21: =INDEX(MTInputs!$J$1:$AZ$415,$D21,MATCH(AM$5,MTInputs!$J$5:$AZ$5,0)) | AN21: =INDEX(MTInputs!$J$1:$AZ$415,$D21,MATCH(AN$5,MTInputs!$J$5:$AZ$5,0)) | ... AY21: =INDEX(MTInputs!$J$1:$AZ$415,$D21,MATCH(AY$5,MTInputs!$J$5:$AZ$5,0))
A22: ctcov | B22: nga | C22: all | D22: 24 | H22: =INDEX(Variables!$B$5:$B$105,MATCH($A22,Variables!$A$5:$A$105,0))&IF($C22="",""," | "&INDEX(Mapping!$B$5:$B$26,MATCH($C22,Mapping!$A$5:$A$26,0))&" | "&INDEX(Mapping!$B$30:$B$41,MATCH($B22,Mapping!$A$30:$A$41,0))) | I22: =INDEX(Variables!$C$5:$C$105,MATCH($A22,Variables!$A$5:$A$105,0)) | J22: =INDEX(Variables!$E$5:$E$105,MATCH($A22,Variables!$A$5:$A$105,0)) | K22: =LOWER(Settings!$C$4)&".mit."&$A22&IF($C22="","","."&$C22&"."&$B22)&IF(INDEX(Variables!$D$5:$D$105,MATCH($A22,Variables!$A$5:$A$105,0))="","","."&INDEX(Variables!$D$5:$D$105,MATCH($A22,Variables!$A$5:$A$105,0)))&"."&K$5 | L22: =INDEX(MTInputs!$J$1:$AZ$415,$D22,MATCH(L$5,MTInputs!$J$5:$AZ$5,0)) | M22: =INDEX(MTInputs!$J$1:$AZ$415,$D22,MATCH(M$5,MTInputs!$J$5:$AZ$5,0)) | N22: =INDEX(MTInputs!$J$1:$AZ$415,$D22,MATCH(N$5,MTInputs!$J$5:$AZ$5,0)) | O22: =INDEX(MTInputs!$J$1:$AZ$415,$D22,MATCH(O$5,MTInputs!$J$5:$AZ$5,0)) | P22: =INDEX(MTInputs!$J$1:$AZ$415,$D22,MATCH(P$5,MTInputs!$J$5:$AZ$5,0)) | Q22: =INDEX(MTInputs!$J$1:$AZ$415,$D22,MATCH(Q$5,MTInputs!$J$5:$AZ$5,0)) | R22: =INDEX(MTInputs!$J$1:$AZ$415,$D22,MATCH(R$5,MTInputs!$J$5:$AZ$5,0)) | S22: =INDEX(MTInputs!$J$1:$AZ$415,$D22,MATCH(S$5,MTInputs!$J$5:$AZ$5,0)) | ... AD22: =INDEX(MTInputs!$J$1:$AZ$415,$D22,MATCH(AD$5,MTInputs!$J$5:$AZ$5,0)) | AF22: =LOWER(Settings!$C$4)&".mit."&$A22&IF($C22="","","."&$C22&"."&$B22)&IF(INDEX(Variables!$D$5:$D$105,MATCH($A22,Variables!$A$5:$A$105,0))="","","."&INDEX(Variables!$D$5:$D$105,MATCH($A22,Variables!$A$5:$A$105,0)))&"."&AF$5 | AG22: =INDEX(MTInputs!$J$1:$AZ$415,$D22,MATCH(AG$5,MTInputs!$J$5:$AZ$5,0)) | AH22: =INDEX(MTInputs!$J$1:$AZ$415,$D22,MATCH(AH$5,MTInputs!$J$5:$AZ$5,0)) | AI22: =INDEX(MTInputs!$J$1:$AZ$415,$D22,MATCH(AI$5,MTInputs!$J$5:$AZ$5,0)) | AJ22: =INDEX(MTInputs!$J$1:$AZ$415,$D22,MATCH(AJ$5,MTInputs!$J$5:$AZ$5,0)) | AK22: =INDEX(MTInputs!$J$1:$AZ$415,$D22,MATCH(AK$5,MTInputs!$J$5:$AZ$5,0)) | AL22: =INDEX(MTInputs!$J$1:$AZ$415,$D22,MATCH(AL$5,MTInputs!$J$5:$AZ$5,0)) | AM22: =INDEX(MTInputs!$J$1:$AZ$415,$D22,MATCH(AM$5,MTInputs!$J$5:$AZ$5,0)) | AN22: =INDEX(MTInputs!$J$1:$AZ$415,$D22,MATCH(AN$5,MTInputs!$J$5:$AZ$5,0)) | ... AY22: =INDEX(MTInputs!$J$1:$AZ$415,$D22,MATCH(AY$5,MTInputs!$J$5:$AZ$5,0))
A23: ctcov | B23: gso | C23: all | D23: 25 | H23: =INDEX(Variables!$B$5:$B$105,MATCH($A23,Variables!$A$5:$A$105,0))&IF($C23="",""," | "&INDEX(Mapping!$B$5:$B$26,MATCH($C23,Mapping!$A$5:$A$26,0))&" | "&INDEX(Mapping!$B$30:$B$41,MATCH($B23,Mapping!$A$30:$A$41,0))) | I23: =INDEX(Variables!$C$5:$C$105,MATCH($A23,Variables!$A$5:$A$105,0)) | J23: =INDEX(Variables!$E$5:$E$105,MATCH($A23,Variables!$A$5:$A$105,0)) | K23: =LOWER(Settings!$C$4)&".mit."&$A23&IF($C23="","","."&$C23&"."&$B23)&IF(INDEX(Variables!$D$5:$D$105,MATCH($A23,Variables!$A$5:$A$105,0))="","","."&INDEX(Variables!$D$5:$D$105,MATCH($A23,Variables!$A$5:$A$105,0)))&"."&K$5 | L23: =INDEX(MTInputs!$J$1:$AZ$415,$D23,MATCH(L$5,MTInputs!$J$5:$AZ$5,0)) | M23: =INDEX(MTInputs!$J$1:$AZ$415,$D23,MATCH(M$5,MTInputs!$J$5:$AZ$5,0)) | N23: =INDEX(MTInputs!$J$1:$AZ$415,$D23,MATCH(N$5,MTInputs!$J$5:$AZ$5,0)) | O23: =INDEX(MTInputs!$J$1:$AZ$415,$D23,MATCH(O$5,MTInputs!$J$5:$AZ$5,0)) | P23: =INDEX(MTInputs!$J$1:$AZ$415,$D23,MATCH(P$5,MTInputs!$J$5:$AZ$5,0)) | Q23: =INDEX(MTInputs!$J$1:$AZ$415,$D23,MATCH(Q$5,MTInputs!$J$5:$AZ$5,0)) | R23: =INDEX(MTInputs!$J$1:$AZ$415,$D23,MATCH(R$5,MTInputs!$J$5:$AZ$5,0)) | S23: =INDEX(MTInputs!$J$1:$AZ$415,$D23,MATCH(S$5,MTInputs!$J$5:$AZ$5,0)) | ... AD23: =INDEX(MTInputs!$J$1:$AZ$415,$D23,MATCH(AD$5,MTInputs!$J$5:$AZ$5,0)) | AF23: =LOWER(Settings!$C$4)&".mit."&$A23&IF($C23="","","."&$C23&"."&$B23)&IF(INDEX(Variables!$D$5:$D$105,MATCH($A23,Variables!$A$5:$A$105,0))="","","."&INDEX(Variables!$D$5:$D$105,MATCH($A23,Variables!$A$5:$A$105,0)))&"."&AF$5 | AG23: =INDEX(MTInputs!$J$1:$AZ$415,$D23,MATCH(AG$5,MTInputs!$J$5:$AZ$5,0)) | AH23: =INDEX(MTInputs!$J$1:$AZ$415,$D23,MATCH(AH$5,MTInputs!$J$5:$AZ$5,0)) | AI23: =INDEX(MTInputs!$J$1:$AZ$415,$D23,MATCH(AI$5,MTInputs!$J$5:$AZ$5,0)) | AJ23: =INDEX(MTInputs!$J$1:$AZ$415,$D23,MATCH(AJ$5,MTInputs!$J$5:$AZ$5,0)) | AK23: =INDEX(MTInputs!$J$1:$AZ$415,$D23,MATCH(AK$5,MTInputs!$J$5:$AZ$5,0)) | AL23: =INDEX(MTInputs!$J$1:$AZ$415,$D23,MATCH(AL$5,MTInputs!$J$5:$AZ$5,0)) | AM23: =INDEX(MTInputs!$J$1:$AZ$415,$D23,MATCH(AM$5,MTInputs!$J$5:$AZ$5,0)) | AN23: =INDEX(MTInputs!$J$1:$AZ$415,$D23,MATCH(AN$5,MTInputs!$J$5:$AZ$5,0)) | ... AY23: =INDEX(MTInputs!$J$1:$AZ$415,$D23,MATCH(AY$5,MTInputs!$J$5:$AZ$5,0))
A24: ctcov | B24: die | C24: all | D24: 26 | H24: =INDEX(Variables!$B$5:$B$105,MATCH($A24,Variables!$A$5:$A$105,0))&IF($C24="",""," | "&INDEX(Mapping!$B$5:$B$26,MATCH($C24,Mapping!$A$5:$A$26,0))&" | "&INDEX(Mapping!$B$30:$B$41,MATCH($B24,Mapping!$A$30:$A$41,0))) | I24: =INDEX(Variables!$C$5:$C$105,MATCH($A24,Variables!$A$5:$A$105,0)) | J24: =INDEX(Variables!$E$5:$E$105,MATCH($A24,Variables!$A$5:$A$105,0)) | K24: =LOWER(Settings!$C$4)&".mit."&$A24&IF($C24="","","."&$C24&"."&$B24)&IF(INDEX(Variables!$D$5:$D$105,MATCH($A24,Variables!$A$5:$A$105,0))="","","."&INDEX(Variables!$D$5:$D$105,MATCH($A24,Variables!$A$5:$A$105,0)))&"."&K$5 | L24: =INDEX(MTInputs!$J$1:$AZ$415,$D24,MATCH(L$5,MTInputs!$J$5:$AZ$5,0)) | M24: =INDEX(MTInputs!$J$1:$AZ$415,$D24,MATCH(M$5,MTInputs!$J$5:$AZ$5,0)) | N24: =INDEX(MTInputs!$J$1:$AZ$415,$D24,MATCH(N$5,MTInputs!$J$5:$AZ$5,0)) | O24: =INDEX(MTInputs!$J$1:$AZ$415,$D24,MATCH(O$5,MTInputs!$J$5:$AZ$5,0)) | P24: =INDEX(MTInputs!$J$1:$AZ$415,$D24,MATCH(P$5,MTInputs!$J$5:$AZ$5,0)) | Q24: =INDEX(MTInputs!$J$1:$AZ$415,$D24,MATCH(Q$5,MTInputs!$J$5:$AZ$5,0)) | R24: =INDEX(MTInputs!$J$1:$AZ$415,$D24,MATCH(R$5,MTInputs!$J$5:$AZ$5,0)) | S24: =INDEX(MTInputs!$J$1:$AZ$415,$D24,MATCH(S$5,MTInputs!$J$5:$AZ$5,0)) | ... AD24: =INDEX(MTInputs!$J$1:$AZ$415,$D24,MATCH(AD$5,MTInputs!$J$5:$AZ$5,0)) | AF24: =LOWER(Settings!$C$4)&".mit."&$A24&IF($C24="","","."&$C24&"."&$B24)&IF(INDEX(Variables!$D$5:$D$105,MATCH($A24,Variables!$A$5:$A$105,0))="","","."&INDEX(Variables!$D$5:$D$105,MATCH($A24,Variables!$A$5:$A$105,0)))&"."&AF$5 | AG24: =INDEX(MTInputs!$J$1:$AZ$415,$D24,MATCH(AG$5,MTInputs!$J$5:$AZ$5,0)) | AH24: =INDEX(MTInputs!$J$1:$AZ$415,$D24,MATCH(AH$5,MTInputs!$J$5:$AZ$5,0)) | AI24: =INDEX(MTInputs!$J$1:$AZ$415,$D24,MATCH(AI$5,MTInputs!$J$5:$AZ$5,0)) | AJ24: =INDEX(MTInputs!$J$1:$AZ$415,$D24,MATCH(AJ$5,MTInputs!$J$5:$AZ$5,0)) | AK24: =INDEX(MTInputs!$J$1:$AZ$415,$D24,MATCH(AK$5,MTInputs!$J$5:$AZ$5,0)) | AL24: =INDEX(MTInputs!$J$1:$AZ$415,$D24,MATCH(AL$5,MTInputs!$J$5:$AZ$5,0)) | AM24: =INDEX(MTInputs!$J$1:$AZ$415,$D24,MATCH(AM$5,MTInputs!$J$5:$AZ$5,0)) | AN24: =INDEX(MTInputs!$J$1:$AZ$415,$D24,MATCH(AN$5,MTInputs!$J$5:$AZ$5,0)) | ... AY24: =INDEX(MTInputs!$J$1:$AZ$415,$D24,MATCH(AY$5,MTInputs!$J$5:$AZ$5,0))
A25: ctcov | B25: lpg | C25: all | D25: 27 | H25: =INDEX(Variables!$B$5:$B$105,MATCH($A25,Variables!$A$5:$A$105,0))&IF($C25="",""," | "&INDEX(Mapping!$B$5:$B$26,MATCH($C25,Mapping!$A$5:$A$26,0))&" | "&INDEX(Mapping!$B$30:$B$41,MATCH($B25,Mapping!$A$30:$A$41,0))) | I25: =INDEX(Variables!$C$5:$C$105,MATCH($A25,Variables!$A$5:$A$105,0)) | J25: =INDEX(Variables!$E$5:$E$105,MATCH($A25,Variables!$A$5:$A$105,0)) | K25: =LOWER(Settings!$C$4)&".mit."&$A25&IF($C25="","","."&$C25&"."&$B25)&IF(INDEX(Variables!$D$5:$D$105,MATCH($A25,Variables!$A$5:$A$105,0))="","","."&INDEX(Variables!$D$5:$D$105,MATCH($A25,Variables!$A$5:$A$105,0)))&"."&K$5 | L25: =INDEX(MTInputs!$J$1:$AZ$415,$D25,MATCH(L$5,MTInputs!$J$5:$AZ$5,0)) | M25: =INDEX(MTInputs!$J$1:$AZ$415,$D25,MATCH(M$5,MTInputs!$J$5:$AZ$5,0)) | N25: =INDEX(MTInputs!$J$1:$AZ$415,$D25,MATCH(N$5,MTInputs!$J$5:$AZ$5,0)) | O25: =INDEX(MTInputs!$J$1:$AZ$415,$D25,MATCH(O$5,MTInputs!$J$5:$AZ$5,0)) | P25: =INDEX(MTInputs!$J$1:$AZ$415,$D25,MATCH(P$5,MTInputs!$J$5:$AZ$5,0)) | Q25: =INDEX(MTInputs!$J$1:$AZ$415,$D25,MATCH(Q$5,MTInputs!$J$5:$AZ$5,0)) | R25: =INDEX(MTInputs!$J$1:$AZ$415,$D25,MATCH(R$5,MTInputs!$J$5:$AZ$5,0)) | S25: =INDEX(MTInputs!$J$1:$AZ$415,$D25,MATCH(S$5,MTInputs!$J$5:$AZ$5,0)) | ... AD25: =INDEX(MTInputs!$J$1:$AZ$415,$D25,MATCH(AD$5,MTInputs!$J$5:$AZ$5,0)) | AF25: =LOWER(Settings!$C$4)&".mit."&$A25&IF($C25="","","."&$C25&"."&$B25)&IF(INDEX(Variables!$D$5:$D$105,MATCH($A25,Variables!$A$5:$A$105,0))="","","."&INDEX(Variables!$D$5:$D$105,MATCH($A25,Variables!$A$5:$A$105,0)))&"."&AF$5 | AG25: =INDEX(MTInputs!$J$1:$AZ$415,$D25,MATCH(AG$5,MTInputs!$J$5:$AZ$5,0)) | AH25: =INDEX(MTInputs!$J$1:$AZ$415,$D25,MATCH(AH$5,MTInputs!$J$5:$AZ$5,0)) | AI25: =INDEX(MTInputs!$J$1:$AZ$415,$D25,MATCH(AI$5,MTInputs!$J$5:$AZ$5,0)) | AJ25: =INDEX(MTInputs!$J$1:$AZ$415,$D25,MATCH(AJ$5,MTInputs!$J$5:$AZ$5,0)) | AK25: =INDEX(MTInputs!$J$1:$AZ$415,$D25,MATCH(AK$5,MTInputs!$J$5:$AZ$5,0)) | AL25: =INDEX(MTInputs!$J$1:$AZ$415,$D25,MATCH(AL$5,MTInputs!$J$5:$AZ$5,0)) | AM25: =INDEX(MTInputs!$J$1:$AZ$415,$D25,MATCH(AM$5,MTInputs!$J$5:$AZ$5,0)) | AN25: =INDEX(MTInputs!$J$1:$AZ$415,$D25,MATCH(AN$5,MTInputs!$J$5:$AZ$5,0)) | ... AY25: =INDEX(MTInputs!$J$1:$AZ$415,$D25,MATCH(AY$5,MTInputs!$J$5:$AZ$5,0))
A26: ctcov | B26: ker | C26: all | D26: 28 | H26: =INDEX(Variables!$B$5:$B$105,MATCH($A26,Variables!$A$5:$A$105,0))&IF($C26="",""," | "&INDEX(Mapping!$B$5:$B$26,MATCH($C26,Mapping!$A$5:$A$26,0))&" | "&INDEX(Mapping!$B$30:$B$41,MATCH($B26,Mapping!$A$30:$A$41,0))) | I26: =INDEX(Variables!$C$5:$C$105,MATCH($A26,Variables!$A$5:$A$105,0)) | J26: =INDEX(Variables!$E$5:$E$105,MATCH($A26,Variables!$A$5:$A$105,0)) | K26: =LOWER(Settings!$C$4)&".mit."&$A26&IF($C26="","","."&$C26&"."&$B26)&IF(INDEX(Variables!$D$5:$D$105,MATCH($A26,Variables!$A$5:$A$105,0))="","","."&INDEX(Variables!$D$5:$D$105,MATCH($A26,Variables!$A$5:$A$105,0)))&"."&K$5 | L26: =INDEX(MTInputs!$J$1:$AZ$415,$D26,MATCH(L$5,MTInputs!$J$5:$AZ$5,0)) | M26: =INDEX(MTInputs!$J$1:$AZ$415,$D26,MATCH(M$5,MTInputs!$J$5:$AZ$5,0)) | N26: =INDEX(MTInputs!$J$1:$AZ$415,$D26,MATCH(N$5,MTInputs!$J$5:$AZ$5,0)) | O26: =INDEX(MTInputs!$J$1:$AZ$415,$D26,MATCH(O$5,MTInputs!$J$5:$AZ$5,0)) | P26: =INDEX(MTInputs!$J$1:$AZ$415,$D26,MATCH(P$5,MTInputs!$J$5:$AZ$5,0)) | Q26: =INDEX(MTInputs!$J$1:$AZ$415,$D26,MATCH(Q$5,MTInputs!$J$5:$AZ$5,0)) | R26: =INDEX(MTInputs!$J$1:$AZ$415,$D26,MATCH(R$5,MTInputs!$J$5:$AZ$5,0)) | S26: =INDEX(MTInputs!$J$1:$AZ$415,$D26,MATCH(S$5,MTInputs!$J$5:$AZ$5,0)) | ... AD26: =INDEX(MTInputs!$J$1:$AZ$415,$D26,MATCH(AD$5,MTInputs!$J$5:$AZ$5,0)) | AF26: =LOWER(Settings!$C$4)&".mit."&$A26&IF($C26="","","."&$C26&"."&$B26)&IF(INDEX(Variables!$D$5:$D$105,MATCH($A26,Variables!$A$5:$A$105,0))="","","."&INDEX(Variables!$D$5:$D$105,MATCH($A26,Variables!$A$5:$A$105,0)))&"."&AF$5 | AG26: =INDEX(MTInputs!$J$1:$AZ$415,$D26,MATCH(AG$5,MTInputs!$J$5:$AZ$5,0)) | AH26: =INDEX(MTInputs!$J$1:$AZ$415,$D26,MATCH(AH$5,MTInputs!$J$5:$AZ$5,0)) | AI26: =INDEX(MTInputs!$J$1:$AZ$415,$D26,MATCH(AI$5,MTInputs!$J$5:$AZ$5,0)) | AJ26: =INDEX(MTInputs!$J$1:$AZ$415,$D26,MATCH(AJ$5,MTInputs!$J$5:$AZ$5,0)) | AK26: =INDEX(MTInputs!$J$1:$AZ$415,$D26,MATCH(AK$5,MTInputs!$J$5:$AZ$5,0)) | AL26: =INDEX(MTInputs!$J$1:$AZ$415,$D26,MATCH(AL$5,MTInputs!$J$5:$AZ$5,0)) | AM26: =INDEX(MTInputs!$J$1:$AZ$415,$D26,MATCH(AM$5,MTInputs!$J$5:$AZ$5,0)) | AN26: =INDEX(MTInputs!$J$1:$AZ$415,$D26,MATCH(AN$5,MTInputs!$J$5:$AZ$5,0)) | ... AY26: =INDEX(MTInputs!$J$1:$AZ$415,$D26,MATCH(AY$5,MTInputs!$J$5:$AZ$5,0))
A27: ctcov | B27: oop | C27: all | D27: 29 | H27: =INDEX(Variables!$B$5:$B$105,MATCH($A27,Variables!$A$5:$A$105,0))&IF($C27="",""," | "&INDEX(Mapping!$B$5:$B$26,MATCH($C27,Mapping!$A$5:$A$26,0))&" | "&INDEX(Mapping!$B$30:$B$41,MATCH($B27,Mapping!$A$30:$A$41,0))) | I27: =INDEX(Variables!$C$5:$C$105,MATCH($A27,Variables!$A$5:$A$105,0)) | J27: =INDEX(Variables!$E$5:$E$105,MATCH($A27,Variables!$A$5:$A$105,0)) | K27: =LOWER(Settings!$C$4)&".mit."&$A27&IF($C27="","","."&$C27&"."&$B27)&IF(INDEX(Variables!$D$5:$D$105,MATCH($A27,Variables!$A$5:$A$105,0))="","","."&INDEX(Variables!$D$5:$D$105,MATCH($A27,Variables!$A$5:$A$105,0)))&"."&K$5 | L27: =INDEX(MTInputs!$J$1:$AZ$415,$D27,MATCH(L$5,MTInputs!$J$5:$AZ$5,0)) | M27: =INDEX(MTInputs!$J$1:$AZ$415,$D27,MATCH(M$5,MTInputs!$J$5:$AZ$5,0)) | N27: =INDEX(MTInputs!$J$1:$AZ$415,$D27,MATCH(N$5,MTInputs!$J$5:$AZ$5,0)) | O27: =INDEX(MTInputs!$J$1:$AZ$415,$D27,MATCH(O$5,MTInputs!$J$5:$AZ$5,0)) | P27: =INDEX(MTInputs!$J$1:$AZ$415,$D27,MATCH(P$5,MTInputs!$J$5:$AZ$5,0)) | Q27: =INDEX(MTInputs!$J$1:$AZ$415,$D27,MATCH(Q$5,MTInputs!$J$5:$AZ$5,0)) | R27: =INDEX(MTInputs!$J$1:$AZ$415,$D27,MATCH(R$5,MTInputs!$J$5:$AZ$5,0)) | S27: =INDEX(MTInputs!$J$1:$AZ$415,$D27,MATCH(S$5,MTInputs!$J$5:$AZ$5,0)) | ... AD27: =INDEX(MTInputs!$J$1:$AZ$415,$D27,MATCH(AD$5,MTInputs!$J$5:$AZ$5,0)) | AF27: =LOWER(Settings!$C$4)&".mit."&$A27&IF($C27="","","."&$C27&"."&$B27)&IF(INDEX(Variables!$D$5:$D$105,MATCH($A27,Variables!$A$5:$A$105,0))="","","."&INDEX(Variables!$D$5:$D$105,MATCH($A27,Variables!$A$5:$A$105,0)))&"."&AF$5 | AG27: =INDEX(MTInputs!$J$1:$AZ$415,$D27,MATCH(AG$5,MTInputs!$J$5:$AZ$5,0)) | AH27: =INDEX(MTInputs!$J$1:$AZ$415,$D27,MATCH(AH$5,MTInputs!$J$5:$AZ$5,0)) | AI27: =INDEX(MTInputs!$J$1:$AZ$415,$D27,MATCH(AI$5,MTInputs!$J$5:$AZ$5,0)) | AJ27: =INDEX(MTInputs!$J$1:$AZ$415,$D27,MATCH(AJ$5,MTInputs!$J$5:$AZ$5,0)) | AK27: =INDEX(MTInputs!$J$1:$AZ$415,$D27,MATCH(AK$5,MTInputs!$J$5:$AZ$5,0)) | AL27: =INDEX(MTInputs!$J$1:$AZ$415,$D27,MATCH(AL$5,MTInputs!$J$5:$AZ$5,0)) | AM27: =INDEX(MTInputs!$J$1:$AZ$415,$D27,MATCH(AM$5,MTInputs!$J$5:$AZ$5,0)) | AN27: =INDEX(MTInputs!$J$1:$AZ$415,$D27,MATCH(AN$5,MTInputs!$J$5:$AZ$5,0)) | ... AY27: =INDEX(MTInputs!$J$1:$AZ$415,$D27,MATCH(AY$5,MTInputs!$J$5:$AZ$5,0))
A28: ctcov | B28: bio | C28: all | H28: =INDEX(Variables!$B$5:$B$105,MATCH($A28,Variables!$A$5:$A$105,0))&IF($C28="",""," | "&INDEX(Mapping!$B$5:$B$26,MATCH($C28,Mapping!$A$5:$A$26,0))&" | "&INDEX(Mapping!$B$30:$B$41,MATCH($B28,Mapping!$A$30:$A$41,0))) | I28: =INDEX(Variables!$C$5:$C$105,MATCH($A28,Variables!$A$5:$A$105,0)) | J28: =INDEX(Variables!$E$5:$E$105,MATCH($A28,Variables!$A$5:$A$105,0)) | K28: =LOWER(Settings!$C$4)&".mit."&$A28&IF($C28="","","."&$C28&"."&$B28)&IF(INDEX(Variables!$D$5:$D$105,MATCH($A28,Variables!$A$5:$A$105,0))="","","."&INDEX(Variables!$D$5:$D$105,MATCH($A28,Variables!$A$5:$A$105,0)))&"."&K$5 | L28: TRUE | M28: TRUE | N28: TRUE | O28: TRUE | P28: TRUE | Q28: TRUE | R28: TRUE | S28: TRUE | T28: TRUE | U28: TRUE | V28: TRUE | W28: TRUE | X28: TRUE | Y28: TRUE | Z28: TRUE | AA28: TRUE | AB28: TRUE | AC28: TRUE | AD28: TRUE | AF28: =LOWER(Settings!$C$4)&".mit."&$A28&IF($C28="","","."&$C28&"."&$B28)&IF(INDEX(Variables!$D$5:$D$105,MATCH($A28,Variables!$A$5:$A$105,0))="","","."&INDEX(Variables!$D$5:$D$105,MATCH($A28,Variables!$A$5:$A$105,0)))&"."&AF$5 | AG28: TRUE | AH28: TRUE | AI28: TRUE | AJ28: TRUE | AK28: TRUE | AL28: TRUE | AM28: TRUE | AN28: TRUE | AO28: TRUE | AP28: TRUE | AQ28: TRUE | AR28: TRUE | AS28: TRUE | AT28: TRUE | AU28: TRUE | AV28: TRUE | AW28: TRUE | AX28: TRUE | AY28: TRUE
H29: Carbon tax coverage: sectors (MTInputs rows 31-47)
A30: ctcov | B30: all | C30: pow | D30: 31 | H30: =INDEX(Variables!$B$5:$B$105,MATCH($A30,Variables!$A$5:$A$105,0))&IF($C30="",""," | "&INDEX(Mapping!$B$5:$B$26,MATCH($C30,Mapping!$A$5:$A$26,0))&" | "&INDEX(Mapping!$B$30:$B$41,MATCH($B30,Mapping!$A$30:$A$41,0))) | I30: =INDEX(Variables!$C$5:$C$105,MATCH($A30,Variables!$A$5:$A$105,0)) | J30: =INDEX(Variables!$E$5:$E$105,MATCH($A30,Variables!$A$5:$A$105,0)) | K30: =LOWER(Settings!$C$4)&".mit."&$A30&IF($C30="","","."&$C30&"."&$B30)&IF(INDEX(Variables!$D$5:$D$105,MATCH($A30,Variables!$A$5:$A$105,0))="","","."&INDEX(Variables!$D$5:$D$105,MATCH($A30,Variables!$A$5:$A$105,0)))&"."&K$5 | L30: =INDEX(MTInputs!$J$1:$AZ$415,$D30,MATCH(L$5,MTInputs!$J$5:$AZ$5,0)) | M30: =INDEX(MTInputs!$J$1:$AZ$415,$D30,MATCH(M$5,MTInputs!$J$5:$AZ$5,0)) | N30: =INDEX(MTInputs!$J$1:$AZ$415,$D30,MATCH(N$5,MTInputs!$J$5:$AZ$5,0)) | O30: =INDEX(MTInputs!$J$1:$AZ$415,$D30,MATCH(O$5,MTInputs!$J$5:$AZ$5,0)) | P30: =INDEX(MTInputs!$J$1:$AZ$415,$D30,MATCH(P$5,MTInputs!$J$5:$AZ$5,0)) | Q30: =INDEX(MTInputs!$J$1:$AZ$415,$D30,MATCH(Q$5,MTInputs!$J$5:$AZ$5,0)) | R30: =INDEX(MTInputs!$J$1:$AZ$415,$D30,MATCH(R$5,MTInputs!$J$5:$AZ$5,0)) | S30: =INDEX(MTInputs!$J$1:$AZ$415,$D30,MATCH(S$5,MTInputs!$J$5:$AZ$5,0)) | ... AD30: =INDEX(MTInputs!$J$1:$AZ$415,$D30,MATCH(AD$5,MTInputs!$J$5:$AZ$5,0)) | AF30: =LOWER(Settings!$C$4)&".mit."&$A30&IF($C30="","","."&$C30&"."&$B30)&IF(INDEX(Variables!$D$5:$D$105,MATCH($A30,Variables!$A$5:$A$105,0))="","","."&INDEX(Variables!$D$5:$D$105,MATCH($A30,Variables!$A$5:$A$105,0)))&"."&AF$5 | AG30: =INDEX(MTInputs!$J$1:$AZ$415,$D30,MATCH(AG$5,MTInputs!$J$5:$AZ$5,0)) | AH30: =INDEX(MTInputs!$J$1:$AZ$415,$D30,MATCH(AH$5,MTInputs!$J$5:$AZ$5,0)) | AI30: =INDEX(MTInputs!$J$1:$AZ$415,$D30,MATCH(AI$5,MTInputs!$J$5:$AZ$5,0)) | AJ30: =INDEX(MTInputs!$J$1:$AZ$415,$D30,MATCH(AJ$5,MTInputs!$J$5:$AZ$5,0)) | AK30: =INDEX(MTInputs!$J$1:$AZ$415,$D30,MATCH(AK$5,MTInputs!$J$5:$AZ$5,0)) | AL30: =INDEX(MTInputs!$J$1:$AZ$415,$D30,MATCH(AL$5,MTInputs!$J$5:$AZ$5,0)) | AM30: =INDEX(MTInputs!$J$1:$AZ$415,$D30,MATCH(AM$5,MTInputs!$J$5:$AZ$5,0)) | AN30: =INDEX(MTInputs!$J$1:$AZ$415,$D30,MATCH(AN$5,MTInputs!$J$5:$AZ$5,0)) | ... AY30: =INDEX(MTInputs!$J$1:$AZ$415,$D30,MATCH(AY$5,MTInputs!$J$5:$AZ$5,0))
A31: ctcov | B31: all | C31: rod | D31: 32 | H31: =INDEX(Variables!$B$5:$B$105,MATCH($A31,Variables!$A$5:$A$105,0))&IF($C31="",""," | "&INDEX(Mapping!$B$5:$B$26,MATCH($C31,Mapping!$A$5:$A$26,0))&" | "&INDEX(Mapping!$B$30:$B$41,MATCH($B31,Mapping!$A$30:$A$41,0))) | I31: =INDEX(Variables!$C$5:$C$105,MATCH($A31,Variables!$A$5:$A$105,0)) | J31: =INDEX(Variables!$E$5:$E$105,MATCH($A31,Variables!$A$5:$A$105,0)) | K31: =LOWER(Settings!$C$4)&".mit."&$A31&IF($C31="","","."&$C31&"."&$B31)&IF(INDEX(Variables!$D$5:$D$105,MATCH($A31,Variables!$A$5:$A$105,0))="","","."&INDEX(Variables!$D$5:$D$105,MATCH($A31,Variables!$A$5:$A$105,0)))&"."&K$5 | L31: =INDEX(MTInputs!$J$1:$AZ$415,$D31,MATCH(L$5,MTInputs!$J$5:$AZ$5,0)) | M31: =INDEX(MTInputs!$J$1:$AZ$415,$D31,MATCH(M$5,MTInputs!$J$5:$AZ$5,0)) | N31: =INDEX(MTInputs!$J$1:$AZ$415,$D31,MATCH(N$5,MTInputs!$J$5:$AZ$5,0)) | O31: =INDEX(MTInputs!$J$1:$AZ$415,$D31,MATCH(O$5,MTInputs!$J$5:$AZ$5,0)) | P31: =INDEX(MTInputs!$J$1:$AZ$415,$D31,MATCH(P$5,MTInputs!$J$5:$AZ$5,0)) | Q31: =INDEX(MTInputs!$J$1:$AZ$415,$D31,MATCH(Q$5,MTInputs!$J$5:$AZ$5,0)) | R31: =INDEX(MTInputs!$J$1:$AZ$415,$D31,MATCH(R$5,MTInputs!$J$5:$AZ$5,0)) | S31: =INDEX(MTInputs!$J$1:$AZ$415,$D31,MATCH(S$5,MTInputs!$J$5:$AZ$5,0)) | ... AD31: =INDEX(MTInputs!$J$1:$AZ$415,$D31,MATCH(AD$5,MTInputs!$J$5:$AZ$5,0)) | AF31: =LOWER(Settings!$C$4)&".mit."&$A31&IF($C31="","","."&$C31&"."&$B31)&IF(INDEX(Variables!$D$5:$D$105,MATCH($A31,Variables!$A$5:$A$105,0))="","","."&INDEX(Variables!$D$5:$D$105,MATCH($A31,Variables!$A$5:$A$105,0)))&"."&AF$5 | AG31: =INDEX(MTInputs!$J$1:$AZ$415,$D31,MATCH(AG$5,MTInputs!$J$5:$AZ$5,0)) | AH31: =INDEX(MTInputs!$J$1:$AZ$415,$D31,MATCH(AH$5,MTInputs!$J$5:$AZ$5,0)) | AI31: =INDEX(MTInputs!$J$1:$AZ$415,$D31,MATCH(AI$5,MTInputs!$J$5:$AZ$5,0)) | AJ31: =INDEX(MTInputs!$J$1:$AZ$415,$D31,MATCH(AJ$5,MTInputs!$J$5:$AZ$5,0)) | AK31: =INDEX(MTInputs!$J$1:$AZ$415,$D31,MATCH(AK$5,MTInputs!$J$5:$AZ$5,0)) | AL31: =INDEX(MTInputs!$J$1:$AZ$415,$D31,MATCH(AL$5,MTInputs!$J$5:$AZ$5,0)) | AM31: =INDEX(MTInputs!$J$1:$AZ$415,$D31,MATCH(AM$5,MTInputs!$J$5:$AZ$5,0)) | AN31: =INDEX(MTInputs!$J$1:$AZ$415,$D31,MATCH(AN$5,MTInputs!$J$5:$AZ$5,0)) | ... AY31: =INDEX(MTInputs!$J$1:$AZ$415,$D31,MATCH(AY$5,MTInputs!$J$5:$AZ$5,0))
A32: ctcov | B32: all | C32: ral | D32: 33 | H32: =INDEX(Variables!$B$5:$B$105,MATCH($A32,Variables!$A$5:$A$105,0))&IF($C32="",""," | "&INDEX(Mapping!$B$5:$B$26,MATCH($C32,Mapping!$A$5:$A$26,0))&" | "&INDEX(Mapping!$B$30:$B$41,MATCH($B32,Mapping!$A$30:$A$41,0))) | I32: =INDEX(Variables!$C$5:$C$105,MATCH($A32,Variables!$A$5:$A$105,0)) | J32: =INDEX(Variables!$E$5:$E$105,MATCH($A32,Variables!$A$5:$A$105,0)) | K32: =LOWER(Settings!$C$4)&".mit."&$A32&IF($C32="","","."&$C32&"."&$B32)&IF(INDEX(Variables!$D$5:$D$105,MATCH($A32,Variables!$A$5:$A$105,0))="","","."&INDEX(Variables!$D$5:$D$105,MATCH($A32,Variables!$A$5:$A$105,0)))&"."&K$5 | L32: =INDEX(MTInputs!$J$1:$AZ$415,$D32,MATCH(L$5,MTInputs!$J$5:$AZ$5,0)) | M32: =INDEX(MTInputs!$J$1:$AZ$415,$D32,MATCH(M$5,MTInputs!$J$5:$AZ$5,0)) | N32: =INDEX(MTInputs!$J$1:$AZ$415,$D32,MATCH(N$5,MTInputs!$J$5:$AZ$5,0)) | O32: =INDEX(MTInputs!$J$1:$AZ$415,$D32,MATCH(O$5,MTInputs!$J$5:$AZ$5,0)) | P32: =INDEX(MTInputs!$J$1:$AZ$415,$D32,MATCH(P$5,MTInputs!$J$5:$AZ$5,0)) | Q32: =INDEX(MTInputs!$J$1:$AZ$415,$D32,MATCH(Q$5,MTInputs!$J$5:$AZ$5,0)) | R32: =INDEX(MTInputs!$J$1:$AZ$415,$D32,MATCH(R$5,MTInputs!$J$5:$AZ$5,0)) | S32: =INDEX(MTInputs!$J$1:$AZ$415,$D32,MATCH(S$5,MTInputs!$J$5:$AZ$5,0)) | ... AD32: =INDEX(MTInputs!$J$1:$AZ$415,$D32,MATCH(AD$5,MTInputs!$J$5:$AZ$5,0)) | AF32: =LOWER(Settings!$C$4)&".mit."&$A32&IF($C32="","","."&$C32&"."&$B32)&IF(INDEX(Variables!$D$5:$D$105,MATCH($A32,Variables!$A$5:$A$105,0))="","","."&INDEX(Variables!$D$5:$D$105,MATCH($A32,Variables!$A$5:$A$105,0)))&"."&AF$5 | AG32: =INDEX(MTInputs!$J$1:$AZ$415,$D32,MATCH(AG$5,MTInputs!$J$5:$AZ$5,0)) | AH32: =INDEX(MTInputs!$J$1:$AZ$415,$D32,MATCH(AH$5,MTInputs!$J$5:$AZ$5,0)) | AI32: =INDEX(MTInputs!$J$1:$AZ$415,$D32,MATCH(AI$5,MTInputs!$J$5:$AZ$5,0)) | AJ32: =INDEX(MTInputs!$J$1:$AZ$415,$D32,MATCH(AJ$5,MTInputs!$J$5:$AZ$5,0)) | AK32: =INDEX(MTInputs!$J$1:$AZ$415,$D32,MATCH(AK$5,MTInputs!$J$5:$AZ$5,0)) | AL32: =INDEX(MTInputs!$J$1:$AZ$415,$D32,MATCH(AL$5,MTInputs!$J$5:$AZ$5,0)) | AM32: =INDEX(MTInputs!$J$1:$AZ$415,$D32,MATCH(AM$5,MTInputs!$J$5:$AZ$5,0)) | AN32: =INDEX(MTInputs!$J$1:$AZ$415,$D32,MATCH(AN$5,MTInputs!$J$5:$AZ$5,0)) | ... AY32: =INDEX(MTInputs!$J$1:$AZ$415,$D32,MATCH(AY$5,MTInputs!$J$5:$AZ$5,0))
A33: ctcov | B33: all | C33: avi | D33: 34 | H33: =INDEX(Variables!$B$5:$B$105,MATCH($A33,Variables!$A$5:$A$105,0))&IF($C33="",""," | "&INDEX(Mapping!$B$5:$B$26,MATCH($C33,Mapping!$A$5:$A$26,0))&" | "&INDEX(Mapping!$B$30:$B$41,MATCH($B33,Mapping!$A$30:$A$41,0))) | I33: =INDEX(Variables!$C$5:$C$105,MATCH($A33,Variables!$A$5:$A$105,0)) | J33: =INDEX(Variables!$E$5:$E$105,MATCH($A33,Variables!$A$5:$A$105,0)) | K33: =LOWER(Settings!$C$4)&".mit."&$A33&IF($C33="","","."&$C33&"."&$B33)&IF(INDEX(Variables!$D$5:$D$105,MATCH($A33,Variables!$A$5:$A$105,0))="","","."&INDEX(Variables!$D$5:$D$105,MATCH($A33,Variables!$A$5:$A$105,0)))&"."&K$5 | L33: =INDEX(MTInputs!$J$1:$AZ$415,$D33,MATCH(L$5,MTInputs!$J$5:$AZ$5,0)) | M33: =INDEX(MTInputs!$J$1:$AZ$415,$D33,MATCH(M$5,MTInputs!$J$5:$AZ$5,0)) | N33: =INDEX(MTInputs!$J$1:$AZ$415,$D33,MATCH(N$5,MTInputs!$J$5:$AZ$5,0)) | O33: =INDEX(MTInputs!$J$1:$AZ$415,$D33,MATCH(O$5,MTInputs!$J$5:$AZ$5,0)) | P33: =INDEX(MTInputs!$J$1:$AZ$415,$D33,MATCH(P$5,MTInputs!$J$5:$AZ$5,0)) | Q33: =INDEX(MTInputs!$J$1:$AZ$415,$D33,MATCH(Q$5,MTInputs!$J$5:$AZ$5,0)) | R33: =INDEX(MTInputs!$J$1:$AZ$415,$D33,MATCH(R$5,MTInputs!$J$5:$AZ$5,0)) | S33: =INDEX(MTInputs!$J$1:$AZ$415,$D33,MATCH(S$5,MTInputs!$J$5:$AZ$5,0)) | ... AD33: =INDEX(MTInputs!$J$1:$AZ$415,$D33,MATCH(AD$5,MTInputs!$J$5:$AZ$5,0)) | AF33: =LOWER(Settings!$C$4)&".mit."&$A33&IF($C33="","","."&$C33&"."&$B33)&IF(INDEX(Variables!$D$5:$D$105,MATCH($A33,Variables!$A$5:$A$105,0))="","","."&INDEX(Variables!$D$5:$D$105,MATCH($A33,Variables!$A$5:$A$105,0)))&"."&AF$5 | AG33: =INDEX(MTInputs!$J$1:$AZ$415,$D33,MATCH(AG$5,MTInputs!$J$5:$AZ$5,0)) | AH33: =INDEX(MTInputs!$J$1:$AZ$415,$D33,MATCH(AH$5,MTInputs!$J$5:$AZ$5,0)) | AI33: =INDEX(MTInputs!$J$1:$AZ$415,$D33,MATCH(AI$5,MTInputs!$J$5:$AZ$5,0)) | AJ33: =INDEX(MTInputs!$J$1:$AZ$415,$D33,MATCH(AJ$5,MTInputs!$J$5:$AZ$5,0)) | AK33: =INDEX(MTInputs!$J$1:$AZ$415,$D33,MATCH(AK$5,MTInputs!$J$5:$AZ$5,0)) | AL33: =INDEX(MTInputs!$J$1:$AZ$415,$D33,MATCH(AL$5,MTInputs!$J$5:$AZ$5,0)) | AM33: =INDEX(MTInputs!$J$1:$AZ$415,$D33,MATCH(AM$5,MTInputs!$J$5:$AZ$5,0)) | AN33: =INDEX(MTInputs!$J$1:$AZ$415,$D33,MATCH(AN$5,MTInputs!$J$5:$AZ$5,0)) | ... AY33: =INDEX(MTInputs!$J$1:$AZ$415,$D33,MATCH(AY$5,MTInputs!$J$5:$AZ$5,0))
A34: ctcov | B34: all | C34: nav | D34: 35 | H34: =INDEX(Variables!$B$5:$B$105,MATCH($A34,Variables!$A$5:$A$105,0))&IF($C34="",""," | "&INDEX(Mapping!$B$5:$B$26,MATCH($C34,Mapping!$A$5:$A$26,0))&" | "&INDEX(Mapping!$B$30:$B$41,MATCH($B34,Mapping!$A$30:$A$41,0))) | I34: =INDEX(Variables!$C$5:$C$105,MATCH($A34,Variables!$A$5:$A$105,0)) | J34: =INDEX(Variables!$E$5:$E$105,MATCH($A34,Variables!$A$5:$A$105,0)) | K34: =LOWER(Settings!$C$4)&".mit."&$A34&IF($C34="","","."&$C34&"."&$B34)&IF(INDEX(Variables!$D$5:$D$105,MATCH($A34,Variables!$A$5:$A$105,0))="","","."&INDEX(Variables!$D$5:$D$105,MATCH($A34,Variables!$A$5:$A$105,0)))&"."&K$5 | L34: =INDEX(MTInputs!$J$1:$AZ$415,$D34,MATCH(L$5,MTInputs!$J$5:$AZ$5,0)) | M34: =INDEX(MTInputs!$J$1:$AZ$415,$D34,MATCH(M$5,MTInputs!$J$5:$AZ$5,0)) | N34: =INDEX(MTInputs!$J$1:$AZ$415,$D34,MATCH(N$5,MTInputs!$J$5:$AZ$5,0)) | O34: =INDEX(MTInputs!$J$1:$AZ$415,$D34,MATCH(O$5,MTInputs!$J$5:$AZ$5,0)) | P34: =INDEX(MTInputs!$J$1:$AZ$415,$D34,MATCH(P$5,MTInputs!$J$5:$AZ$5,0)) | Q34: =INDEX(MTInputs!$J$1:$AZ$415,$D34,MATCH(Q$5,MTInputs!$J$5:$AZ$5,0)) | R34: =INDEX(MTInputs!$J$1:$AZ$415,$D34,MATCH(R$5,MTInputs!$J$5:$AZ$5,0)) | S34: =INDEX(MTInputs!$J$1:$AZ$415,$D34,MATCH(S$5,MTInputs!$J$5:$AZ$5,0)) | ... AD34: =INDEX(MTInputs!$J$1:$AZ$415,$D34,MATCH(AD$5,MTInputs!$J$5:$AZ$5,0)) | AF34: =LOWER(Settings!$C$4)&".mit."&$A34&IF($C34="","","."&$C34&"."&$B34)&IF(INDEX(Variables!$D$5:$D$105,MATCH($A34,Variables!$A$5:$A$105,0))="","","."&INDEX(Variables!$D$5:$D$105,MATCH($A34,Variables!$A$5:$A$105,0)))&"."&AF$5 | AG34: =INDEX(MTInputs!$J$1:$AZ$415,$D34,MATCH(AG$5,MTInputs!$J$5:$AZ$5,0)) | AH34: =INDEX(MTInputs!$J$1:$AZ$415,$D34,MATCH(AH$5,MTInputs!$J$5:$AZ$5,0)) | AI34: =INDEX(MTInputs!$J$1:$AZ$415,$D34,MATCH(AI$5,MTInputs!$J$5:$AZ$5,0)) | AJ34: =INDEX(MTInputs!$J$1:$AZ$415,$D34,MATCH(AJ$5,MTInputs!$J$5:$AZ$5,0)) | AK34: =INDEX(MTInputs!$J$1:$AZ$415,$D34,MATCH(AK$5,MTInputs!$J$5:$AZ$5,0)) | AL34: =INDEX(MTInputs!$J$1:$AZ$415,$D34,MATCH(AL$5,MTInputs!$J$5:$AZ$5,0)) | AM34: =INDEX(MTInputs!$J$1:$AZ$415,$D34,MATCH(AM$5,MTInputs!$J$5:$AZ$5,0)) | AN34: =INDEX(MTInputs!$J$1:$AZ$415,$D34,MATCH(AN$5,MTInputs!$J$5:$AZ$5,0)) | ... AY34: =INDEX(MTInputs!$J$1:$AZ$415,$D34,MATCH(AY$5,MTInputs!$J$5:$AZ$5,0))
A35: ctcov | B35: all | C35: res | D35: 36 | H35: =INDEX(Variables!$B$5:$B$105,MATCH($A35,Variables!$A$5:$A$105,0))&IF($C35="",""," | "&INDEX(Mapping!$B$5:$B$26,MATCH($C35,Mapping!$A$5:$A$26,0))&" | "&INDEX(Mapping!$B$30:$B$41,MATCH($B35,Mapping!$A$30:$A$41,0))) | I35: =INDEX(Variables!$C$5:$C$105,MATCH($A35,Variables!$A$5:$A$105,0)) | J35: =INDEX(Variables!$E$5:$E$105,MATCH($A35,Variables!$A$5:$A$105,0)) | K35: =LOWER(Settings!$C$4)&".mit."&$A35&IF($C35="","","."&$C35&"."&$B35)&IF(INDEX(Variables!$D$5:$D$105,MATCH($A35,Variables!$A$5:$A$105,0))="","","."&INDEX(Variables!$D$5:$D$105,MATCH($A35,Variables!$A$5:$A$105,0)))&"."&K$5 | L35: =INDEX(MTInputs!$J$1:$AZ$415,$D35,MATCH(L$5,MTInputs!$J$5:$AZ$5,0)) | M35: =INDEX(MTInputs!$J$1:$AZ$415,$D35,MATCH(M$5,MTInputs!$J$5:$AZ$5,0)) | N35: =INDEX(MTInputs!$J$1:$AZ$415,$D35,MATCH(N$5,MTInputs!$J$5:$AZ$5,0)) | O35: =INDEX(MTInputs!$J$1:$AZ$415,$D35,MATCH(O$5,MTInputs!$J$5:$AZ$5,0)) | P35: =INDEX(MTInputs!$J$1:$AZ$415,$D35,MATCH(P$5,MTInputs!$J$5:$AZ$5,0)) | Q35: =INDEX(MTInputs!$J$1:$AZ$415,$D35,MATCH(Q$5,MTInputs!$J$5:$AZ$5,0)) | R35: =INDEX(MTInputs!$J$1:$AZ$415,$D35,MATCH(R$5,MTInputs!$J$5:$AZ$5,0)) | S35: =INDEX(MTInputs!$J$1:$AZ$415,$D35,MATCH(S$5,MTInputs!$J$5:$AZ$5,0)) | ... AD35: =INDEX(MTInputs!$J$1:$AZ$415,$D35,MATCH(AD$5,MTInputs!$J$5:$AZ$5,0)) | AF35: =LOWER(Settings!$C$4)&".mit."&$A35&IF($C35="","","."&$C35&"."&$B35)&IF(INDEX(Variables!$D$5:$D$105,MATCH($A35,Variables!$A$5:$A$105,0))="","","."&INDEX(Variables!$D$5:$D$105,MATCH($A35,Variables!$A$5:$A$105,0)))&"."&AF$5 | AG35: =INDEX(MTInputs!$J$1:$AZ$415,$D35,MATCH(AG$5,MTInputs!$J$5:$AZ$5,0)) | AH35: =INDEX(MTInputs!$J$1:$AZ$415,$D35,MATCH(AH$5,MTInputs!$J$5:$AZ$5,0)) | AI35: =INDEX(MTInputs!$J$1:$AZ$415,$D35,MATCH(AI$5,MTInputs!$J$5:$AZ$5,0)) | AJ35: =INDEX(MTInputs!$J$1:$AZ$415,$D35,MATCH(AJ$5,MTInputs!$J$5:$AZ$5,0)) | AK35: =INDEX(MTInputs!$J$1:$AZ$415,$D35,MATCH(AK$5,MTInputs!$J$5:$AZ$5,0)) | AL35: =INDEX(MTInputs!$J$1:$AZ$415,$D35,MATCH(AL$5,MTInputs!$J$5:$AZ$5,0)) | AM35: =INDEX(MTInputs!$J$1:$AZ$415,$D35,MATCH(AM$5,MTInputs!$J$5:$AZ$5,0)) | AN35: =INDEX(MTInputs!$J$1:$AZ$415,$D35,MATCH(AN$5,MTInputs!$J$5:$AZ$5,0)) | ... AY35: =INDEX(MTInputs!$J$1:$AZ$415,$D35,MATCH(AY$5,MTInputs!$J$5:$AZ$5,0))
A36: ctcov | B36: all | C36: foo | D36: 37 | H36: =INDEX(Variables!$B$5:$B$105,MATCH($A36,Variables!$A$5:$A$105,0))&IF($C36="",""," | "&INDEX(Mapping!$B$5:$B$26,MATCH($C36,Mapping!$A$5:$A$26,0))&" | "&INDEX(Mapping!$B$30:$B$41,MATCH($B36,Mapping!$A$30:$A$41,0))) | I36: =INDEX(Variables!$C$5:$C$105,MATCH($A36,Variables!$A$5:$A$105,0)) | J36: =INDEX(Variables!$E$5:$E$105,MATCH($A36,Variables!$A$5:$A$105,0)) | K36: =LOWER(Settings!$C$4)&".mit."&$A36&IF($C36="","","."&$C36&"."&$B36)&IF(INDEX(Variables!$D$5:$D$105,MATCH($A36,Variables!$A$5:$A$105,0))="","","."&INDEX(Variables!$D$5:$D$105,MATCH($A36,Variables!$A$5:$A$105,0)))&"."&K$5 | L36: =INDEX(MTInputs!$J$1:$AZ$415,$D36,MATCH(L$5,MTInputs!$J$5:$AZ$5,0)) | M36: =INDEX(MTInputs!$J$1:$AZ$415,$D36,MATCH(M$5,MTInputs!$J$5:$AZ$5,0)) | N36: =INDEX(MTInputs!$J$1:$AZ$415,$D36,MATCH(N$5,MTInputs!$J$5:$AZ$5,0)) | O36: =INDEX(MTInputs!$J$1:$AZ$415,$D36,MATCH(O$5,MTInputs!$J$5:$AZ$5,0)) | P36: =INDEX(MTInputs!$J$1:$AZ$415,$D36,MATCH(P$5,MTInputs!$J$5:$AZ$5,0)) | Q36: =INDEX(MTInputs!$J$1:$AZ$415,$D36,MATCH(Q$5,MTInputs!$J$5:$AZ$5,0)) | R36: =INDEX(MTInputs!$J$1:$AZ$415,$D36,MATCH(R$5,MTInputs!$J$5:$AZ$5,0)) | S36: =INDEX(MTInputs!$J$1:$AZ$415,$D36,MATCH(S$5,MTInputs!$J$5:$AZ$5,0)) | ... AD36: =INDEX(MTInputs!$J$1:$AZ$415,$D36,MATCH(AD$5,MTInputs!$J$5:$AZ$5,0)) | AF36: =LOWER(Settings!$C$4)&".mit."&$A36&IF($C36="","","."&$C36&"."&$B36)&IF(INDEX(Variables!$D$5:$D$105,MATCH($A36,Variables!$A$5:$A$105,0))="","","."&INDEX(Variables!$D$5:$D$105,MATCH($A36,Variables!$A$5:$A$105,0)))&"."&AF$5 | AG36: =INDEX(MTInputs!$J$1:$AZ$415,$D36,MATCH(AG$5,MTInputs!$J$5:$AZ$5,0)) | AH36: =INDEX(MTInputs!$J$1:$AZ$415,$D36,MATCH(AH$5,MTInputs!$J$5:$AZ$5,0)) | AI36: =INDEX(MTInputs!$J$1:$AZ$415,$D36,MATCH(AI$5,MTInputs!$J$5:$AZ$5,0)) | AJ36: =INDEX(MTInputs!$J$1:$AZ$415,$D36,MATCH(AJ$5,MTInputs!$J$5:$AZ$5,0)) | AK36: =INDEX(MTInputs!$J$1:$AZ$415,$D36,MATCH(AK$5,MTInputs!$J$5:$AZ$5,0)) | AL36: =INDEX(MTInputs!$J$1:$AZ$415,$D36,MATCH(AL$5,MTInputs!$J$5:$AZ$5,0)) | AM36: =INDEX(MTInputs!$J$1:$AZ$415,$D36,MATCH(AM$5,MTInputs!$J$5:$AZ$5,0)) | AN36: =INDEX(MTInputs!$J$1:$AZ$415,$D36,MATCH(AN$5,MTInputs!$J$5:$AZ$5,0)) | ... AY36: =INDEX(MTInputs!$J$1:$AZ$415,$D36,MATCH(AY$5,MTInputs!$J$5:$AZ$5,0))
A37: ctcov | B37: all | C37: srv | D37: 38 | H37: =INDEX(Variables!$B$5:$B$105,MATCH($A37,Variables!$A$5:$A$105,0))&IF($C37="",""," | "&INDEX(Mapping!$B$5:$B$26,MATCH($C37,Mapping!$A$5:$A$26,0))&" | "&INDEX(Mapping!$B$30:$B$41,MATCH($B37,Mapping!$A$30:$A$41,0))) | I37: =INDEX(Variables!$C$5:$C$105,MATCH($A37,Variables!$A$5:$A$105,0)) | J37: =INDEX(Variables!$E$5:$E$105,MATCH($A37,Variables!$A$5:$A$105,0)) | K37: =LOWER(Settings!$C$4)&".mit."&$A37&IF($C37="","","."&$C37&"."&$B37)&IF(INDEX(Variables!$D$5:$D$105,MATCH($A37,Variables!$A$5:$A$105,0))="","","."&INDEX(Variables!$D$5:$D$105,MATCH($A37,Variables!$A$5:$A$105,0)))&"."&K$5 | L37: =INDEX(MTInputs!$J$1:$AZ$415,$D37,MATCH(L$5,MTInputs!$J$5:$AZ$5,0)) | M37: =INDEX(MTInputs!$J$1:$AZ$415,$D37,MATCH(M$5,MTInputs!$J$5:$AZ$5,0)) | N37: =INDEX(MTInputs!$J$1:$AZ$415,$D37,MATCH(N$5,MTInputs!$J$5:$AZ$5,0)) | O37: =INDEX(MTInputs!$J$1:$AZ$415,$D37,MATCH(O$5,MTInputs!$J$5:$AZ$5,0)) | P37: =INDEX(MTInputs!$J$1:$AZ$415,$D37,MATCH(P$5,MTInputs!$J$5:$AZ$5,0)) | Q37: =INDEX(MTInputs!$J$1:$AZ$415,$D37,MATCH(Q$5,MTInputs!$J$5:$AZ$5,0)) | R37: =INDEX(MTInputs!$J$1:$AZ$415,$D37,MATCH(R$5,MTInputs!$J$5:$AZ$5,0)) | S37: =INDEX(MTInputs!$J$1:$AZ$415,$D37,MATCH(S$5,MTInputs!$J$5:$AZ$5,0)) | ... AD37: =INDEX(MTInputs!$J$1:$AZ$415,$D37,MATCH(AD$5,MTInputs!$J$5:$AZ$5,0)) | AF37: =LOWER(Settings!$C$4)&".mit."&$A37&IF($C37="","","."&$C37&"."&$B37)&IF(INDEX(Variables!$D$5:$D$105,MATCH($A37,Variables!$A$5:$A$105,0))="","","."&INDEX(Variables!$D$5:$D$105,MATCH($A37,Variables!$A$5:$A$105,0)))&"."&AF$5 | AG37: =INDEX(MTInputs!$J$1:$AZ$415,$D37,MATCH(AG$5,MTInputs!$J$5:$AZ$5,0)) | AH37: =INDEX(MTInputs!$J$1:$AZ$415,$D37,MATCH(AH$5,MTInputs!$J$5:$AZ$5,0)) | AI37: =INDEX(MTInputs!$J$1:$AZ$415,$D37,MATCH(AI$5,MTInputs!$J$5:$AZ$5,0)) | AJ37: =INDEX(MTInputs!$J$1:$AZ$415,$D37,MATCH(AJ$5,MTInputs!$J$5:$AZ$5,0)) | AK37: =INDEX(MTInputs!$J$1:$AZ$415,$D37,MATCH(AK$5,MTInputs!$J$5:$AZ$5,0)) | AL37: =INDEX(MTInputs!$J$1:$AZ$415,$D37,MATCH(AL$5,MTInputs!$J$5:$AZ$5,0)) | AM37: =INDEX(MTInputs!$J$1:$AZ$415,$D37,MATCH(AM$5,MTInputs!$J$5:$AZ$5,0)) | AN37: =INDEX(MTInputs!$J$1:$AZ$415,$D37,MATCH(AN$5,MTInputs!$J$5:$AZ$5,0)) | ... AY37: =INDEX(MTInputs!$J$1:$AZ$415,$D37,MATCH(AY$5,MTInputs!$J$5:$AZ$5,0))
A38: ctcov | B38: all | C38: mch | D38: 39 | H38: =INDEX(Variables!$B$5:$B$105,MATCH($A38,Variables!$A$5:$A$105,0))&IF($C38="",""," | "&INDEX(Mapping!$B$5:$B$26,MATCH($C38,Mapping!$A$5:$A$26,0))&" | "&INDEX(Mapping!$B$30:$B$41,MATCH($B38,Mapping!$A$30:$A$41,0))) | I38: =INDEX(Variables!$C$5:$C$105,MATCH($A38,Variables!$A$5:$A$105,0)) | J38: =INDEX(Variables!$E$5:$E$105,MATCH($A38,Variables!$A$5:$A$105,0)) | K38: =LOWER(Settings!$C$4)&".mit."&$A38&IF($C38="","","."&$C38&"."&$B38)&IF(INDEX(Variables!$D$5:$D$105,MATCH($A38,Variables!$A$5:$A$105,0))="","","."&INDEX(Variables!$D$5:$D$105,MATCH($A38,Variables!$A$5:$A$105,0)))&"."&K$5 | L38: =INDEX(MTInputs!$J$1:$AZ$415,$D38,MATCH(L$5,MTInputs!$J$5:$AZ$5,0)) | M38: =INDEX(MTInputs!$J$1:$AZ$415,$D38,MATCH(M$5,MTInputs!$J$5:$AZ$5,0)) | N38: =INDEX(MTInputs!$J$1:$AZ$415,$D38,MATCH(N$5,MTInputs!$J$5:$AZ$5,0)) | O38: =INDEX(MTInputs!$J$1:$AZ$415,$D38,MATCH(O$5,MTInputs!$J$5:$AZ$5,0)) | P38: =INDEX(MTInputs!$J$1:$AZ$415,$D38,MATCH(P$5,MTInputs!$J$5:$AZ$5,0)) | Q38: =INDEX(MTInputs!$J$1:$AZ$415,$D38,MATCH(Q$5,MTInputs!$J$5:$AZ$5,0)) | R38: =INDEX(MTInputs!$J$1:$AZ$415,$D38,MATCH(R$5,MTInputs!$J$5:$AZ$5,0)) | S38: =INDEX(MTInputs!$J$1:$AZ$415,$D38,MATCH(S$5,MTInputs!$J$5:$AZ$5,0)) | ... AD38: =INDEX(MTInputs!$J$1:$AZ$415,$D38,MATCH(AD$5,MTInputs!$J$5:$AZ$5,0)) | AF38: =LOWER(Settings!$C$4)&".mit."&$A38&IF($C38="","","."&$C38&"."&$B38)&IF(INDEX(Variables!$D$5:$D$105,MATCH($A38,Variables!$A$5:$A$105,0))="","","."&INDEX(Variables!$D$5:$D$105,MATCH($A38,Variables!$A$5:$A$105,0)))&"."&AF$5 | AG38: =INDEX(MTInputs!$J$1:$AZ$415,$D38,MATCH(AG$5,MTInputs!$J$5:$AZ$5,0)) | AH38: =INDEX(MTInputs!$J$1:$AZ$415,$D38,MATCH(AH$5,MTInputs!$J$5:$AZ$5,0)) | AI38: =INDEX(MTInputs!$J$1:$AZ$415,$D38,MATCH(AI$5,MTInputs!$J$5:$AZ$5,0)) | AJ38: =INDEX(MTInputs!$J$1:$AZ$415,$D38,MATCH(AJ$5,MTInputs!$J$5:$AZ$5,0)) | AK38: =INDEX(MTInputs!$J$1:$AZ$415,$D38,MATCH(AK$5,MTInputs!$J$5:$AZ$5,0)) | AL38: =INDEX(MTInputs!$J$1:$AZ$415,$D38,MATCH(AL$5,MTInputs!$J$5:$AZ$5,0)) | AM38: =INDEX(MTInputs!$J$1:$AZ$415,$D38,MATCH(AM$5,MTInputs!$J$5:$AZ$5,0)) | AN38: =INDEX(MTInputs!$J$1:$AZ$415,$D38,MATCH(AN$5,MTInputs!$J$5:$AZ$5,0)) | ... AY38: =INDEX(MTInputs!$J$1:$AZ$415,$D38,MATCH(AY$5,MTInputs!$J$5:$AZ$5,0))
A39: ctcov | B39: all | C39: irn | D39: 40 | H39: =INDEX(Variables!$B$5:$B$105,MATCH($A39,Variables!$A$5:$A$105,0))&IF($C39="",""," | "&INDEX(Mapping!$B$5:$B$26,MATCH($C39,Mapping!$A$5:$A$26,0))&" | "&INDEX(Mapping!$B$30:$B$41,MATCH($B39,Mapping!$A$30:$A$41,0))) | I39: =INDEX(Variables!$C$5:$C$105,MATCH($A39,Variables!$A$5:$A$105,0)) | J39: =INDEX(Variables!$E$5:$E$105,MATCH($A39,Variables!$A$5:$A$105,0)) | K39: =LOWER(Settings!$C$4)&".mit."&$A39&IF($C39="","","."&$C39&"."&$B39)&IF(INDEX(Variables!$D$5:$D$105,MATCH($A39,Variables!$A$5:$A$105,0))="","","."&INDEX(Variables!$D$5:$D$105,MATCH($A39,Variables!$A$5:$A$105,0)))&"."&K$5 | L39: =INDEX(MTInputs!$J$1:$AZ$415,$D39,MATCH(L$5,MTInputs!$J$5:$AZ$5,0)) | M39: =INDEX(MTInputs!$J$1:$AZ$415,$D39,MATCH(M$5,MTInputs!$J$5:$AZ$5,0)) | N39: =INDEX(MTInputs!$J$1:$AZ$415,$D39,MATCH(N$5,MTInputs!$J$5:$AZ$5,0)) | O39: =INDEX(MTInputs!$J$1:$AZ$415,$D39,MATCH(O$5,MTInputs!$J$5:$AZ$5,0)) | P39: =INDEX(MTInputs!$J$1:$AZ$415,$D39,MATCH(P$5,MTInputs!$J$5:$AZ$5,0)) | Q39: =INDEX(MTInputs!$J$1:$AZ$415,$D39,MATCH(Q$5,MTInputs!$J$5:$AZ$5,0)) | R39: =INDEX(MTInputs!$J$1:$AZ$415,$D39,MATCH(R$5,MTInputs!$J$5:$AZ$5,0)) | S39: =INDEX(MTInputs!$J$1:$AZ$415,$D39,MATCH(S$5,MTInputs!$J$5:$AZ$5,0)) | ... AD39: =INDEX(MTInputs!$J$1:$AZ$415,$D39,MATCH(AD$5,MTInputs!$J$5:$AZ$5,0)) | AF39: =LOWER(Settings!$C$4)&".mit."&$A39&IF($C39="","","."&$C39&"."&$B39)&IF(INDEX(Variables!$D$5:$D$105,MATCH($A39,Variables!$A$5:$A$105,0))="","","."&INDEX(Variables!$D$5:$D$105,MATCH($A39,Variables!$A$5:$A$105,0)))&"."&AF$5 | AG39: =INDEX(MTInputs!$J$1:$AZ$415,$D39,MATCH(AG$5,MTInputs!$J$5:$AZ$5,0)) | AH39: =INDEX(MTInputs!$J$1:$AZ$415,$D39,MATCH(AH$5,MTInputs!$J$5:$AZ$5,0)) | AI39: =INDEX(MTInputs!$J$1:$AZ$415,$D39,MATCH(AI$5,MTInputs!$J$5:$AZ$5,0)) | AJ39: =INDEX(MTInputs!$J$1:$AZ$415,$D39,MATCH(AJ$5,MTInputs!$J$5:$AZ$5,0)) | AK39: =INDEX(MTInputs!$J$1:$AZ$415,$D39,MATCH(AK$5,MTInputs!$J$5:$AZ$5,0)) | AL39: =INDEX(MTInputs!$J$1:$AZ$415,$D39,MATCH(AL$5,MTInputs!$J$5:$AZ$5,0)) | AM39: =INDEX(MTInputs!$J$1:$AZ$415,$D39,MATCH(AM$5,MTInputs!$J$5:$AZ$5,0)) | AN39: =INDEX(MTInputs!$J$1:$AZ$415,$D39,MATCH(AN$5,MTInputs!$J$5:$AZ$5,0)) | ... AY39: =INDEX(MTInputs!$J$1:$AZ$415,$D39,MATCH(AY$5,MTInputs!$J$5:$AZ$5,0))
A40: ctcov | B40: all | C40: nfm | D40: 41 | H40: =INDEX(Variables!$B$5:$B$105,MATCH($A40,Variables!$A$5:$A$105,0))&IF($C40="",""," | "&INDEX(Mapping!$B$5:$B$26,MATCH($C40,Mapping!$A$5:$A$26,0))&" | "&INDEX(Mapping!$B$30:$B$41,MATCH($B40,Mapping!$A$30:$A$41,0))) | I40: =INDEX(Variables!$C$5:$C$105,MATCH($A40,Variables!$A$5:$A$105,0)) | J40: =INDEX(Variables!$E$5:$E$105,MATCH($A40,Variables!$A$5:$A$105,0)) | K40: =LOWER(Settings!$C$4)&".mit."&$A40&IF($C40="","","."&$C40&"."&$B40)&IF(INDEX(Variables!$D$5:$D$105,MATCH($A40,Variables!$A$5:$A$105,0))="","","."&INDEX(Variables!$D$5:$D$105,MATCH($A40,Variables!$A$5:$A$105,0)))&"."&K$5 | L40: =INDEX(MTInputs!$J$1:$AZ$415,$D40,MATCH(L$5,MTInputs!$J$5:$AZ$5,0)) | M40: =INDEX(MTInputs!$J$1:$AZ$415,$D40,MATCH(M$5,MTInputs!$J$5:$AZ$5,0)) | N40: =INDEX(MTInputs!$J$1:$AZ$415,$D40,MATCH(N$5,MTInputs!$J$5:$AZ$5,0)) | O40: =INDEX(MTInputs!$J$1:$AZ$415,$D40,MATCH(O$5,MTInputs!$J$5:$AZ$5,0)) | P40: =INDEX(MTInputs!$J$1:$AZ$415,$D40,MATCH(P$5,MTInputs!$J$5:$AZ$5,0)) | Q40: =INDEX(MTInputs!$J$1:$AZ$415,$D40,MATCH(Q$5,MTInputs!$J$5:$AZ$5,0)) | R40: =INDEX(MTInputs!$J$1:$AZ$415,$D40,MATCH(R$5,MTInputs!$J$5:$AZ$5,0)) | S40: =INDEX(MTInputs!$J$1:$AZ$415,$D40,MATCH(S$5,MTInputs!$J$5:$AZ$5,0)) | ... AD40: =INDEX(MTInputs!$J$1:$AZ$415,$D40,MATCH(AD$5,MTInputs!$J$5:$AZ$5,0)) | AF40: =LOWER(Settings!$C$4)&".mit."&$A40&IF($C40="","","."&$C40&"."&$B40)&IF(INDEX(Variables!$D$5:$D$105,MATCH($A40,Variables!$A$5:$A$105,0))="","","."&INDEX(Variables!$D$5:$D$105,MATCH($A40,Variables!$A$5:$A$105,0)))&"."&AF$5 | AG40: =INDEX(MTInputs!$J$1:$AZ$415,$D40,MATCH(AG$5,MTInputs!$J$5:$AZ$5,0)) | AH40: =INDEX(MTInputs!$J$1:$AZ$415,$D40,MATCH(AH$5,MTInputs!$J$5:$AZ$5,0)) | AI40: =INDEX(MTInputs!$J$1:$AZ$415,$D40,MATCH(AI$5,MTInputs!$J$5:$AZ$5,0)) | AJ40: =INDEX(MTInputs!$J$1:$AZ$415,$D40,MATCH(AJ$5,MTInputs!$J$5:$AZ$5,0)) | AK40: =INDEX(MTInputs!$J$1:$AZ$415,$D40,MATCH(AK$5,MTInputs!$J$5:$AZ$5,0)) | AL40: =INDEX(MTInputs!$J$1:$AZ$415,$D40,MATCH(AL$5,MTInputs!$J$5:$AZ$5,0)) | AM40: =INDEX(MTInputs!$J$1:$AZ$415,$D40,MATCH(AM$5,MTInputs!$J$5:$AZ$5,0)) | AN40: =INDEX(MTInputs!$J$1:$AZ$415,$D40,MATCH(AN$5,MTInputs!$J$5:$AZ$5,0)) | ... AY40: =INDEX(MTInputs!$J$1:$AZ$415,$D40,MATCH(AY$5,MTInputs!$J$5:$AZ$5,0))
A41: ctcov | B41: all | C41: mac | D41: 42 | H41: =INDEX(Variables!$B$5:$B$105,MATCH($A41,Variables!$A$5:$A$105,0))&IF($C41="",""," | "&INDEX(Mapping!$B$5:$B$26,MATCH($C41,Mapping!$A$5:$A$26,0))&" | "&INDEX(Mapping!$B$30:$B$41,MATCH($B41,Mapping!$A$30:$A$41,0))) | I41: =INDEX(Variables!$C$5:$C$105,MATCH($A41,Variables!$A$5:$A$105,0)) | J41: =INDEX(Variables!$E$5:$E$105,MATCH($A41,Variables!$A$5:$A$105,0)) | K41: =LOWER(Settings!$C$4)&".mit."&$A41&IF($C41="","","."&$C41&"."&$B41)&IF(INDEX(Variables!$D$5:$D$105,MATCH($A41,Variables!$A$5:$A$105,0))="","","."&INDEX(Variables!$D$5:$D$105,MATCH($A41,Variables!$A$5:$A$105,0)))&"."&K$5 | L41: =INDEX(MTInputs!$J$1:$AZ$415,$D41,MATCH(L$5,MTInputs!$J$5:$AZ$5,0)) | M41: =INDEX(MTInputs!$J$1:$AZ$415,$D41,MATCH(M$5,MTInputs!$J$5:$AZ$5,0)) | N41: =INDEX(MTInputs!$J$1:$AZ$415,$D41,MATCH(N$5,MTInputs!$J$5:$AZ$5,0)) | O41: =INDEX(MTInputs!$J$1:$AZ$415,$D41,MATCH(O$5,MTInputs!$J$5:$AZ$5,0)) | P41: =INDEX(MTInputs!$J$1:$AZ$415,$D41,MATCH(P$5,MTInputs!$J$5:$AZ$5,0)) | Q41: =INDEX(MTInputs!$J$1:$AZ$415,$D41,MATCH(Q$5,MTInputs!$J$5:$AZ$5,0)) | R41: =INDEX(MTInputs!$J$1:$AZ$415,$D41,MATCH(R$5,MTInputs!$J$5:$AZ$5,0)) | S41: =INDEX(MTInputs!$J$1:$AZ$415,$D41,MATCH(S$5,MTInputs!$J$5:$AZ$5,0)) | ... AD41: =INDEX(MTInputs!$J$1:$AZ$415,$D41,MATCH(AD$5,MTInputs!$J$5:$AZ$5,0)) | AF41: =LOWER(Settings!$C$4)&".mit."&$A41&IF($C41="","","."&$C41&"."&$B41)&IF(INDEX(Variables!$D$5:$D$105,MATCH($A41,Variables!$A$5:$A$105,0))="","","."&INDEX(Variables!$D$5:$D$105,MATCH($A41,Variables!$A$5:$A$105,0)))&"."&AF$5 | AG41: =INDEX(MTInputs!$J$1:$AZ$415,$D41,MATCH(AG$5,MTInputs!$J$5:$AZ$5,0)) | AH41: =INDEX(MTInputs!$J$1:$AZ$415,$D41,MATCH(AH$5,MTInputs!$J$5:$AZ$5,0)) | AI41: =INDEX(MTInputs!$J$1:$AZ$415,$D41,MATCH(AI$5,MTInputs!$J$5:$AZ$5,0)) | AJ41: =INDEX(MTInputs!$J$1:$AZ$415,$D41,MATCH(AJ$5,MTInputs!$J$5:$AZ$5,0)) | AK41: =INDEX(MTInputs!$J$1:$AZ$415,$D41,MATCH(AK$5,MTInputs!$J$5:$AZ$5,0)) | AL41: =INDEX(MTInputs!$J$1:$AZ$415,$D41,MATCH(AL$5,MTInputs!$J$5:$AZ$5,0)) | AM41: =INDEX(MTInputs!$J$1:$AZ$415,$D41,MATCH(AM$5,MTInputs!$J$5:$AZ$5,0)) | AN41: =INDEX(MTInputs!$J$1:$AZ$415,$D41,MATCH(AN$5,MTInputs!$J$5:$AZ$5,0)) | ... AY41: =INDEX(MTInputs!$J$1:$AZ$415,$D41,MATCH(AY$5,MTInputs!$J$5:$AZ$5,0))
... A46: ctcov | B46: all | C46: oen | D46: 47 | H46: =INDEX(Variables!$B$5:$B$105,MATCH($A46,Variables!$A$5:$A$105,0))&IF($C46="",""," | "&INDEX(Mapping!$B$5:$B$26,MATCH($C46,Mapping!$A$5:$A$26,0))&" | "&INDEX(Mapping!$B$30:$B$41,MATCH($B46,Mapping!$A$30:$A$41,0))) | I46: =INDEX(Variables!$C$5:$C$105,MATCH($A46,Variables!$A$5:$A$105,0)) | J46: =INDEX(Variables!$E$5:$E$105,MATCH($A46,Variables!$A$5:$A$105,0)) | K46: =LOWER(Settings!$C$4)&".mit."&$A46&IF($C46="","","."&$C46&"."&$B46)&IF(INDEX(Variables!$D$5:$D$105,MATCH($A46,Variables!$A$5:$A$105,0))="","","."&INDEX(Variables!$D$5:$D$105,MATCH($A46,Variables!$A$5:$A$105,0)))&"."&K$5 | L46: =INDEX(MTInputs!$J$1:$AZ$415,$D46,MATCH(L$5,MTInputs!$J$5:$AZ$5,0)) | M46: =INDEX(MTInputs!$J$1:$AZ$415,$D46,MATCH(M$5,MTInputs!$J$5:$AZ$5,0)) | N46: =INDEX(MTInputs!$J$1:$AZ$415,$D46,MATCH(N$5,MTInputs!$J$5:$AZ$5,0)) | O46: =INDEX(MTInputs!$J$1:$AZ$415,$D46,MATCH(O$5,MTInputs!$J$5:$AZ$5,0)) | P46: =INDEX(MTInputs!$J$1:$AZ$415,$D46,MATCH(P$5,MTInputs!$J$5:$AZ$5,0)) | Q46: =INDEX(MTInputs!$J$1:$AZ$415,$D46,MATCH(Q$5,MTInputs!$J$5:$AZ$5,0)) | R46: =INDEX(MTInputs!$J$1:$AZ$415,$D46,MATCH(R$5,MTInputs!$J$5:$AZ$5,0)) | S46: =INDEX(MTInputs!$J$1:$AZ$415,$D46,MATCH(S$5,MTInputs!$J$5:$AZ$5,0)) | ... AD46: =INDEX(MTInputs!$J$1:$AZ$415,$D46,MATCH(AD$5,MTInputs!$J$5:$AZ$5,0)) | AF46: =LOWER(Settings!$C$4)&".mit."&$A46&IF($C46="","","."&$C46&"."&$B46)&IF(INDEX(Variables!$D$5:$D$105,MATCH($A46,Variables!$A$5:$A$105,0))="","","."&INDEX(Variables!$D$5:$D$105,MATCH($A46,Variables!$A$5:$A$105,0)))&"."&AF$5 | AG46: =INDEX(MTInputs!$J$1:$AZ$415,$D46,MATCH(AG$5,MTInputs!$J$5:$AZ$5,0)) | AH46: =INDEX(MTInputs!$J$1:$AZ$415,$D46,MATCH(AH$5,MTInputs!$J$5:$AZ$5,0)) | AI46: =INDEX(MTInputs!$J$1:$AZ$415,$D46,MATCH(AI$5,MTInputs!$J$5:$AZ$5,0)) | AJ46: =INDEX(MTInputs!$J$1:$AZ$415,$D46,MATCH(AJ$5,MTInputs!$J$5:$AZ$5,0)) | AK46: =INDEX(MTInputs!$J$1:$AZ$415,$D46,MATCH(AK$5,MTInputs!$J$5:$AZ$5,0)) | AL46: =INDEX(MTInputs!$J$1:$AZ$415,$D46,MATCH(AL$5,MTInputs!$J$5:$AZ$5,0)) | AM46: =INDEX(MTInputs!$J$1:$AZ$415,$D46,MATCH(AM$5,MTInputs!$J$5:$AZ$5,0)) | AN46: =INDEX(MTInputs!$J$1:$AZ$415,$D46,MATCH(AN$5,MTInputs!$J$5:$AZ$5,0)) | ... AY46: =INDEX(MTInputs!$J$1:$AZ$415,$D46,MATCH(AY$5,MTInputs!$J$5:$AZ$5,0))
H47: Fuel price reform (MTInputs rows 140-169; increases in price units)
A48: fpr.yr0 | D48: 140 | H48: =INDEX(Variables!$B$5:$B$105,MATCH($A48,Variables!$A$5:$A$105,0))&IF($C48="",""," | "&INDEX(Mapping!$B$5:$B$26,MATCH($C48,Mapping!$A$5:$A$26,0))&" | "&INDEX(Mapping!$B$30:$B$41,MATCH($B48,Mapping!$A$30:$A$41,0))) | I48: =INDEX(Variables!$C$5:$C$105,MATCH($A48,Variables!$A$5:$A$105,0)) | J48: =INDEX(Variables!$E$5:$E$105,MATCH($A48,Variables!$A$5:$A$105,0)) | K48: =LOWER(Settings!$C$4)&".mit."&$A48&IF($C48="","","."&$C48&"."&$B48)&IF(INDEX(Variables!$D$5:$D$105,MATCH($A48,Variables!$A$5:$A$105,0))="","","."&INDEX(Variables!$D$5:$D$105,MATCH($A48,Variables!$A$5:$A$105,0)))&"."&K$5 | L48: =INDEX(MTInputs!$J$1:$AZ$415,$D48,MATCH(L$5,MTInputs!$J$5:$AZ$5,0)) | M48: =INDEX(MTInputs!$J$1:$AZ$415,$D48,MATCH(M$5,MTInputs!$J$5:$AZ$5,0)) | N48: =INDEX(MTInputs!$J$1:$AZ$415,$D48,MATCH(N$5,MTInputs!$J$5:$AZ$5,0)) | O48: =INDEX(MTInputs!$J$1:$AZ$415,$D48,MATCH(O$5,MTInputs!$J$5:$AZ$5,0)) | P48: =INDEX(MTInputs!$J$1:$AZ$415,$D48,MATCH(P$5,MTInputs!$J$5:$AZ$5,0)) | Q48: =INDEX(MTInputs!$J$1:$AZ$415,$D48,MATCH(Q$5,MTInputs!$J$5:$AZ$5,0)) | R48: =INDEX(MTInputs!$J$1:$AZ$415,$D48,MATCH(R$5,MTInputs!$J$5:$AZ$5,0)) | S48: =INDEX(MTInputs!$J$1:$AZ$415,$D48,MATCH(S$5,MTInputs!$J$5:$AZ$5,0)) | ... AD48: =INDEX(MTInputs!$J$1:$AZ$415,$D48,MATCH(AD$5,MTInputs!$J$5:$AZ$5,0)) | AF48: =LOWER(Settings!$C$4)&".mit."&$A48&IF($C48="","","."&$C48&"."&$B48)&IF(INDEX(Variables!$D$5:$D$105,MATCH($A48,Variables!$A$5:$A$105,0))="","","."&INDEX(Variables!$D$5:$D$105,MATCH($A48,Variables!$A$5:$A$105,0)))&"."&AF$5 | AG48: =INDEX(MTInputs!$J$1:$AZ$415,$D48,MATCH(AG$5,MTInputs!$J$5:$AZ$5,0)) | AH48: =INDEX(MTInputs!$J$1:$AZ$415,$D48,MATCH(AH$5,MTInputs!$J$5:$AZ$5,0)) | AI48: =INDEX(MTInputs!$J$1:$AZ$415,$D48,MATCH(AI$5,MTInputs!$J$5:$AZ$5,0)) | AJ48: =INDEX(MTInputs!$J$1:$AZ$415,$D48,MATCH(AJ$5,MTInputs!$J$5:$AZ$5,0)) | AK48: =INDEX(MTInputs!$J$1:$AZ$415,$D48,MATCH(AK$5,MTInputs!$J$5:$AZ$5,0)) | AL48: =INDEX(MTInputs!$J$1:$AZ$415,$D48,MATCH(AL$5,MTInputs!$J$5:$AZ$5,0)) | AM48: =INDEX(MTInputs!$J$1:$AZ$415,$D48,MATCH(AM$5,MTInputs!$J$5:$AZ$5,0)) | AN48: =INDEX(MTInputs!$J$1:$AZ$415,$D48,MATCH(AN$5,MTInputs!$J$5:$AZ$5,0)) | ... AY48: =INDEX(MTInputs!$J$1:$AZ$415,$D48,MATCH(AY$5,MTInputs!$J$5:$AZ$5,0))
A49: fpr.yr1 | D49: 141 | H49: =INDEX(Variables!$B$5:$B$105,MATCH($A49,Variables!$A$5:$A$105,0))&IF($C49="",""," | "&INDEX(Mapping!$B$5:$B$26,MATCH($C49,Mapping!$A$5:$A$26,0))&" | "&INDEX(Mapping!$B$30:$B$41,MATCH($B49,Mapping!$A$30:$A$41,0))) | I49: =INDEX(Variables!$C$5:$C$105,MATCH($A49,Variables!$A$5:$A$105,0)) | J49: =INDEX(Variables!$E$5:$E$105,MATCH($A49,Variables!$A$5:$A$105,0)) | K49: =LOWER(Settings!$C$4)&".mit."&$A49&IF($C49="","","."&$C49&"."&$B49)&IF(INDEX(Variables!$D$5:$D$105,MATCH($A49,Variables!$A$5:$A$105,0))="","","."&INDEX(Variables!$D$5:$D$105,MATCH($A49,Variables!$A$5:$A$105,0)))&"."&K$5 | L49: =INDEX(MTInputs!$J$1:$AZ$415,$D49,MATCH(L$5,MTInputs!$J$5:$AZ$5,0)) | M49: =INDEX(MTInputs!$J$1:$AZ$415,$D49,MATCH(M$5,MTInputs!$J$5:$AZ$5,0)) | N49: =INDEX(MTInputs!$J$1:$AZ$415,$D49,MATCH(N$5,MTInputs!$J$5:$AZ$5,0)) | O49: =INDEX(MTInputs!$J$1:$AZ$415,$D49,MATCH(O$5,MTInputs!$J$5:$AZ$5,0)) | P49: =INDEX(MTInputs!$J$1:$AZ$415,$D49,MATCH(P$5,MTInputs!$J$5:$AZ$5,0)) | Q49: =INDEX(MTInputs!$J$1:$AZ$415,$D49,MATCH(Q$5,MTInputs!$J$5:$AZ$5,0)) | R49: =INDEX(MTInputs!$J$1:$AZ$415,$D49,MATCH(R$5,MTInputs!$J$5:$AZ$5,0)) | S49: =INDEX(MTInputs!$J$1:$AZ$415,$D49,MATCH(S$5,MTInputs!$J$5:$AZ$5,0)) | ... AD49: =INDEX(MTInputs!$J$1:$AZ$415,$D49,MATCH(AD$5,MTInputs!$J$5:$AZ$5,0)) | AF49: =LOWER(Settings!$C$4)&".mit."&$A49&IF($C49="","","."&$C49&"."&$B49)&IF(INDEX(Variables!$D$5:$D$105,MATCH($A49,Variables!$A$5:$A$105,0))="","","."&INDEX(Variables!$D$5:$D$105,MATCH($A49,Variables!$A$5:$A$105,0)))&"."&AF$5 | AG49: =INDEX(MTInputs!$J$1:$AZ$415,$D49,MATCH(AG$5,MTInputs!$J$5:$AZ$5,0)) | AH49: =INDEX(MTInputs!$J$1:$AZ$415,$D49,MATCH(AH$5,MTInputs!$J$5:$AZ$5,0)) | AI49: =INDEX(MTInputs!$J$1:$AZ$415,$D49,MATCH(AI$5,MTInputs!$J$5:$AZ$5,0)) | AJ49: =INDEX(MTInputs!$J$1:$AZ$415,$D49,MATCH(AJ$5,MTInputs!$J$5:$AZ$5,0)) | AK49: =INDEX(MTInputs!$J$1:$AZ$415,$D49,MATCH(AK$5,MTInputs!$J$5:$AZ$5,0)) | AL49: =INDEX(MTInputs!$J$1:$AZ$415,$D49,MATCH(AL$5,MTInputs!$J$5:$AZ$5,0)) | AM49: =INDEX(MTInputs!$J$1:$AZ$415,$D49,MATCH(AM$5,MTInputs!$J$5:$AZ$5,0)) | AN49: =INDEX(MTInputs!$J$1:$AZ$415,$D49,MATCH(AN$5,MTInputs!$J$5:$AZ$5,0)) | ... AY49: =INDEX(MTInputs!$J$1:$AZ$415,$D49,MATCH(AY$5,MTInputs!$J$5:$AZ$5,0))
A50: fpr.s | B50: coa | C50: pow | D50: 142 | H50: =INDEX(Variables!$B$5:$B$105,MATCH($A50,Variables!$A$5:$A$105,0))&IF($C50="",""," | "&INDEX(Mapping!$B$5:$B$26,MATCH($C50,Mapping!$A$5:$A$26,0))&" | "&INDEX(Mapping!$B$30:$B$41,MATCH($B50,Mapping!$A$30:$A$41,0))) | I50: =INDEX(Variables!$C$5:$C$105,MATCH($A50,Variables!$A$5:$A$105,0)) | J50: =INDEX(Variables!$E$5:$E$105,MATCH($A50,Variables!$A$5:$A$105,0)) | K50: =LOWER(Settings!$C$4)&".mit."&$A50&IF($C50="","","."&$C50&"."&$B50)&IF(INDEX(Variables!$D$5:$D$105,MATCH($A50,Variables!$A$5:$A$105,0))="","","."&INDEX(Variables!$D$5:$D$105,MATCH($A50,Variables!$A$5:$A$105,0)))&"."&K$5 | L50: =INDEX(MTInputs!$J$1:$AZ$415,$D50,MATCH(L$5,MTInputs!$J$5:$AZ$5,0)) | M50: =INDEX(MTInputs!$J$1:$AZ$415,$D50,MATCH(M$5,MTInputs!$J$5:$AZ$5,0)) | N50: =INDEX(MTInputs!$J$1:$AZ$415,$D50,MATCH(N$5,MTInputs!$J$5:$AZ$5,0)) | O50: =INDEX(MTInputs!$J$1:$AZ$415,$D50,MATCH(O$5,MTInputs!$J$5:$AZ$5,0)) | P50: =INDEX(MTInputs!$J$1:$AZ$415,$D50,MATCH(P$5,MTInputs!$J$5:$AZ$5,0)) | Q50: =INDEX(MTInputs!$J$1:$AZ$415,$D50,MATCH(Q$5,MTInputs!$J$5:$AZ$5,0)) | R50: =INDEX(MTInputs!$J$1:$AZ$415,$D50,MATCH(R$5,MTInputs!$J$5:$AZ$5,0)) | S50: =INDEX(MTInputs!$J$1:$AZ$415,$D50,MATCH(S$5,MTInputs!$J$5:$AZ$5,0)) | ... AD50: =INDEX(MTInputs!$J$1:$AZ$415,$D50,MATCH(AD$5,MTInputs!$J$5:$AZ$5,0)) | AF50: =LOWER(Settings!$C$4)&".mit."&$A50&IF($C50="","","."&$C50&"."&$B50)&IF(INDEX(Variables!$D$5:$D$105,MATCH($A50,Variables!$A$5:$A$105,0))="","","."&INDEX(Variables!$D$5:$D$105,MATCH($A50,Variables!$A$5:$A$105,0)))&"."&AF$5 | AG50: =INDEX(MTInputs!$J$1:$AZ$415,$D50,MATCH(AG$5,MTInputs!$J$5:$AZ$5,0)) | AH50: =INDEX(MTInputs!$J$1:$AZ$415,$D50,MATCH(AH$5,MTInputs!$J$5:$AZ$5,0)) | AI50: =INDEX(MTInputs!$J$1:$AZ$415,$D50,MATCH(AI$5,MTInputs!$J$5:$AZ$5,0)) | AJ50: =INDEX(MTInputs!$J$1:$AZ$415,$D50,MATCH(AJ$5,MTInputs!$J$5:$AZ$5,0)) | AK50: =INDEX(MTInputs!$J$1:$AZ$415,$D50,MATCH(AK$5,MTInputs!$J$5:$AZ$5,0)) | AL50: =INDEX(MTInputs!$J$1:$AZ$415,$D50,MATCH(AL$5,MTInputs!$J$5:$AZ$5,0)) | AM50: =INDEX(MTInputs!$J$1:$AZ$415,$D50,MATCH(AM$5,MTInputs!$J$5:$AZ$5,0)) | AN50: =INDEX(MTInputs!$J$1:$AZ$415,$D50,MATCH(AN$5,MTInputs!$J$5:$AZ$5,0)) | ... AY50: =INDEX(MTInputs!$J$1:$AZ$415,$D50,MATCH(AY$5,MTInputs!$J$5:$AZ$5,0))
A51: fpr.s | B51: coa | C51: res | D51: 143 | H51: =INDEX(Variables!$B$5:$B$105,MATCH($A51,Variables!$A$5:$A$105,0))&IF($C51="",""," | "&INDEX(Mapping!$B$5:$B$26,MATCH($C51,Mapping!$A$5:$A$26,0))&" | "&INDEX(Mapping!$B$30:$B$41,MATCH($B51,Mapping!$A$30:$A$41,0))) | I51: =INDEX(Variables!$C$5:$C$105,MATCH($A51,Variables!$A$5:$A$105,0)) | J51: =INDEX(Variables!$E$5:$E$105,MATCH($A51,Variables!$A$5:$A$105,0)) | K51: =LOWER(Settings!$C$4)&".mit."&$A51&IF($C51="","","."&$C51&"."&$B51)&IF(INDEX(Variables!$D$5:$D$105,MATCH($A51,Variables!$A$5:$A$105,0))="","","."&INDEX(Variables!$D$5:$D$105,MATCH($A51,Variables!$A$5:$A$105,0)))&"."&K$5 | L51: =INDEX(MTInputs!$J$1:$AZ$415,$D51,MATCH(L$5,MTInputs!$J$5:$AZ$5,0)) | M51: =INDEX(MTInputs!$J$1:$AZ$415,$D51,MATCH(M$5,MTInputs!$J$5:$AZ$5,0)) | N51: =INDEX(MTInputs!$J$1:$AZ$415,$D51,MATCH(N$5,MTInputs!$J$5:$AZ$5,0)) | O51: =INDEX(MTInputs!$J$1:$AZ$415,$D51,MATCH(O$5,MTInputs!$J$5:$AZ$5,0)) | P51: =INDEX(MTInputs!$J$1:$AZ$415,$D51,MATCH(P$5,MTInputs!$J$5:$AZ$5,0)) | Q51: =INDEX(MTInputs!$J$1:$AZ$415,$D51,MATCH(Q$5,MTInputs!$J$5:$AZ$5,0)) | R51: =INDEX(MTInputs!$J$1:$AZ$415,$D51,MATCH(R$5,MTInputs!$J$5:$AZ$5,0)) | S51: =INDEX(MTInputs!$J$1:$AZ$415,$D51,MATCH(S$5,MTInputs!$J$5:$AZ$5,0)) | ... AD51: =INDEX(MTInputs!$J$1:$AZ$415,$D51,MATCH(AD$5,MTInputs!$J$5:$AZ$5,0)) | AF51: =LOWER(Settings!$C$4)&".mit."&$A51&IF($C51="","","."&$C51&"."&$B51)&IF(INDEX(Variables!$D$5:$D$105,MATCH($A51,Variables!$A$5:$A$105,0))="","","."&INDEX(Variables!$D$5:$D$105,MATCH($A51,Variables!$A$5:$A$105,0)))&"."&AF$5 | AG51: =INDEX(MTInputs!$J$1:$AZ$415,$D51,MATCH(AG$5,MTInputs!$J$5:$AZ$5,0)) | AH51: =INDEX(MTInputs!$J$1:$AZ$415,$D51,MATCH(AH$5,MTInputs!$J$5:$AZ$5,0)) | AI51: =INDEX(MTInputs!$J$1:$AZ$415,$D51,MATCH(AI$5,MTInputs!$J$5:$AZ$5,0)) | AJ51: =INDEX(MTInputs!$J$1:$AZ$415,$D51,MATCH(AJ$5,MTInputs!$J$5:$AZ$5,0)) | AK51: =INDEX(MTInputs!$J$1:$AZ$415,$D51,MATCH(AK$5,MTInputs!$J$5:$AZ$5,0)) | AL51: =INDEX(MTInputs!$J$1:$AZ$415,$D51,MATCH(AL$5,MTInputs!$J$5:$AZ$5,0)) | AM51: =INDEX(MTInputs!$J$1:$AZ$415,$D51,MATCH(AM$5,MTInputs!$J$5:$AZ$5,0)) | AN51: =INDEX(MTInputs!$J$1:$AZ$415,$D51,MATCH(AN$5,MTInputs!$J$5:$AZ$5,0)) | ... AY51: =INDEX(MTInputs!$J$1:$AZ$415,$D51,MATCH(AY$5,MTInputs!$J$5:$AZ$5,0))
A52: fpr.s | B52: coa | C52: ind | D52: 144 | H52: =INDEX(Variables!$B$5:$B$105,MATCH($A52,Variables!$A$5:$A$105,0))&IF($C52="",""," | "&INDEX(Mapping!$B$5:$B$26,MATCH($C52,Mapping!$A$5:$A$26,0))&" | "&INDEX(Mapping!$B$30:$B$41,MATCH($B52,Mapping!$A$30:$A$41,0))) | I52: =INDEX(Variables!$C$5:$C$105,MATCH($A52,Variables!$A$5:$A$105,0)) | J52: =INDEX(Variables!$E$5:$E$105,MATCH($A52,Variables!$A$5:$A$105,0)) | K52: =LOWER(Settings!$C$4)&".mit."&$A52&IF($C52="","","."&$C52&"."&$B52)&IF(INDEX(Variables!$D$5:$D$105,MATCH($A52,Variables!$A$5:$A$105,0))="","","."&INDEX(Variables!$D$5:$D$105,MATCH($A52,Variables!$A$5:$A$105,0)))&"."&K$5 | L52: =INDEX(MTInputs!$J$1:$AZ$415,$D52,MATCH(L$5,MTInputs!$J$5:$AZ$5,0)) | M52: =INDEX(MTInputs!$J$1:$AZ$415,$D52,MATCH(M$5,MTInputs!$J$5:$AZ$5,0)) | N52: =INDEX(MTInputs!$J$1:$AZ$415,$D52,MATCH(N$5,MTInputs!$J$5:$AZ$5,0)) | O52: =INDEX(MTInputs!$J$1:$AZ$415,$D52,MATCH(O$5,MTInputs!$J$5:$AZ$5,0)) | P52: =INDEX(MTInputs!$J$1:$AZ$415,$D52,MATCH(P$5,MTInputs!$J$5:$AZ$5,0)) | Q52: =INDEX(MTInputs!$J$1:$AZ$415,$D52,MATCH(Q$5,MTInputs!$J$5:$AZ$5,0)) | R52: =INDEX(MTInputs!$J$1:$AZ$415,$D52,MATCH(R$5,MTInputs!$J$5:$AZ$5,0)) | S52: =INDEX(MTInputs!$J$1:$AZ$415,$D52,MATCH(S$5,MTInputs!$J$5:$AZ$5,0)) | ... AD52: =INDEX(MTInputs!$J$1:$AZ$415,$D52,MATCH(AD$5,MTInputs!$J$5:$AZ$5,0)) | AF52: =LOWER(Settings!$C$4)&".mit."&$A52&IF($C52="","","."&$C52&"."&$B52)&IF(INDEX(Variables!$D$5:$D$105,MATCH($A52,Variables!$A$5:$A$105,0))="","","."&INDEX(Variables!$D$5:$D$105,MATCH($A52,Variables!$A$5:$A$105,0)))&"."&AF$5 | AG52: =INDEX(MTInputs!$J$1:$AZ$415,$D52,MATCH(AG$5,MTInputs!$J$5:$AZ$5,0)) | AH52: =INDEX(MTInputs!$J$1:$AZ$415,$D52,MATCH(AH$5,MTInputs!$J$5:$AZ$5,0)) | AI52: =INDEX(MTInputs!$J$1:$AZ$415,$D52,MATCH(AI$5,MTInputs!$J$5:$AZ$5,0)) | AJ52: =INDEX(MTInputs!$J$1:$AZ$415,$D52,MATCH(AJ$5,MTInputs!$J$5:$AZ$5,0)) | AK52: =INDEX(MTInputs!$J$1:$AZ$415,$D52,MATCH(AK$5,MTInputs!$J$5:$AZ$5,0)) | AL52: =INDEX(MTInputs!$J$1:$AZ$415,$D52,MATCH(AL$5,MTInputs!$J$5:$AZ$5,0)) | AM52: =INDEX(MTInputs!$J$1:$AZ$415,$D52,MATCH(AM$5,MTInputs!$J$5:$AZ$5,0)) | AN52: =INDEX(MTInputs!$J$1:$AZ$415,$D52,MATCH(AN$5,MTInputs!$J$5:$AZ$5,0)) | ... AY52: =INDEX(MTInputs!$J$1:$AZ$415,$D52,MATCH(AY$5,MTInputs!$J$5:$AZ$5,0))
A53: fpr.s | B53: nga | C53: pow | D53: 145 | H53: =INDEX(Variables!$B$5:$B$105,MATCH($A53,Variables!$A$5:$A$105,0))&IF($C53="",""," | "&INDEX(Mapping!$B$5:$B$26,MATCH($C53,Mapping!$A$5:$A$26,0))&" | "&INDEX(Mapping!$B$30:$B$41,MATCH($B53,Mapping!$A$30:$A$41,0))) | I53: =INDEX(Variables!$C$5:$C$105,MATCH($A53,Variables!$A$5:$A$105,0)) | J53: =INDEX(Variables!$E$5:$E$105,MATCH($A53,Variables!$A$5:$A$105,0)) | K53: =LOWER(Settings!$C$4)&".mit."&$A53&IF($C53="","","."&$C53&"."&$B53)&IF(INDEX(Variables!$D$5:$D$105,MATCH($A53,Variables!$A$5:$A$105,0))="","","."&INDEX(Variables!$D$5:$D$105,MATCH($A53,Variables!$A$5:$A$105,0)))&"."&K$5 | L53: =INDEX(MTInputs!$J$1:$AZ$415,$D53,MATCH(L$5,MTInputs!$J$5:$AZ$5,0)) | M53: =INDEX(MTInputs!$J$1:$AZ$415,$D53,MATCH(M$5,MTInputs!$J$5:$AZ$5,0)) | N53: =INDEX(MTInputs!$J$1:$AZ$415,$D53,MATCH(N$5,MTInputs!$J$5:$AZ$5,0)) | O53: =INDEX(MTInputs!$J$1:$AZ$415,$D53,MATCH(O$5,MTInputs!$J$5:$AZ$5,0)) | P53: =INDEX(MTInputs!$J$1:$AZ$415,$D53,MATCH(P$5,MTInputs!$J$5:$AZ$5,0)) | Q53: =INDEX(MTInputs!$J$1:$AZ$415,$D53,MATCH(Q$5,MTInputs!$J$5:$AZ$5,0)) | R53: =INDEX(MTInputs!$J$1:$AZ$415,$D53,MATCH(R$5,MTInputs!$J$5:$AZ$5,0)) | S53: =INDEX(MTInputs!$J$1:$AZ$415,$D53,MATCH(S$5,MTInputs!$J$5:$AZ$5,0)) | ... AD53: =INDEX(MTInputs!$J$1:$AZ$415,$D53,MATCH(AD$5,MTInputs!$J$5:$AZ$5,0)) | AF53: =LOWER(Settings!$C$4)&".mit."&$A53&IF($C53="","","."&$C53&"."&$B53)&IF(INDEX(Variables!$D$5:$D$105,MATCH($A53,Variables!$A$5:$A$105,0))="","","."&INDEX(Variables!$D$5:$D$105,MATCH($A53,Variables!$A$5:$A$105,0)))&"."&AF$5 | AG53: =INDEX(MTInputs!$J$1:$AZ$415,$D53,MATCH(AG$5,MTInputs!$J$5:$AZ$5,0)) | AH53: =INDEX(MTInputs!$J$1:$AZ$415,$D53,MATCH(AH$5,MTInputs!$J$5:$AZ$5,0)) | AI53: =INDEX(MTInputs!$J$1:$AZ$415,$D53,MATCH(AI$5,MTInputs!$J$5:$AZ$5,0)) | AJ53: =INDEX(MTInputs!$J$1:$AZ$415,$D53,MATCH(AJ$5,MTInputs!$J$5:$AZ$5,0)) | AK53: =INDEX(MTInputs!$J$1:$AZ$415,$D53,MATCH(AK$5,MTInputs!$J$5:$AZ$5,0)) | AL53: =INDEX(MTInputs!$J$1:$AZ$415,$D53,MATCH(AL$5,MTInputs!$J$5:$AZ$5,0)) | AM53: =INDEX(MTInputs!$J$1:$AZ$415,$D53,MATCH(AM$5,MTInputs!$J$5:$AZ$5,0)) | AN53: =INDEX(MTInputs!$J$1:$AZ$415,$D53,MATCH(AN$5,MTInputs!$J$5:$AZ$5,0)) | ... AY53: =INDEX(MTInputs!$J$1:$AZ$415,$D53,MATCH(AY$5,MTInputs!$J$5:$AZ$5,0))
A54: fpr.s | B54: nga | C54: res | D54: 146 | H54: =INDEX(Variables!$B$5:$B$105,MATCH($A54,Variables!$A$5:$A$105,0))&IF($C54="",""," | "&INDEX(Mapping!$B$5:$B$26,MATCH($C54,Mapping!$A$5:$A$26,0))&" | "&INDEX(Mapping!$B$30:$B$41,MATCH($B54,Mapping!$A$30:$A$41,0))) | I54: =INDEX(Variables!$C$5:$C$105,MATCH($A54,Variables!$A$5:$A$105,0)) | J54: =INDEX(Variables!$E$5:$E$105,MATCH($A54,Variables!$A$5:$A$105,0)) | K54: =LOWER(Settings!$C$4)&".mit."&$A54&IF($C54="","","."&$C54&"."&$B54)&IF(INDEX(Variables!$D$5:$D$105,MATCH($A54,Variables!$A$5:$A$105,0))="","","."&INDEX(Variables!$D$5:$D$105,MATCH($A54,Variables!$A$5:$A$105,0)))&"."&K$5 | L54: =INDEX(MTInputs!$J$1:$AZ$415,$D54,MATCH(L$5,MTInputs!$J$5:$AZ$5,0)) | M54: =INDEX(MTInputs!$J$1:$AZ$415,$D54,MATCH(M$5,MTInputs!$J$5:$AZ$5,0)) | N54: =INDEX(MTInputs!$J$1:$AZ$415,$D54,MATCH(N$5,MTInputs!$J$5:$AZ$5,0)) | O54: =INDEX(MTInputs!$J$1:$AZ$415,$D54,MATCH(O$5,MTInputs!$J$5:$AZ$5,0)) | P54: =INDEX(MTInputs!$J$1:$AZ$415,$D54,MATCH(P$5,MTInputs!$J$5:$AZ$5,0)) | Q54: =INDEX(MTInputs!$J$1:$AZ$415,$D54,MATCH(Q$5,MTInputs!$J$5:$AZ$5,0)) | R54: =INDEX(MTInputs!$J$1:$AZ$415,$D54,MATCH(R$5,MTInputs!$J$5:$AZ$5,0)) | S54: =INDEX(MTInputs!$J$1:$AZ$415,$D54,MATCH(S$5,MTInputs!$J$5:$AZ$5,0)) | ... AD54: =INDEX(MTInputs!$J$1:$AZ$415,$D54,MATCH(AD$5,MTInputs!$J$5:$AZ$5,0)) | AF54: =LOWER(Settings!$C$4)&".mit."&$A54&IF($C54="","","."&$C54&"."&$B54)&IF(INDEX(Variables!$D$5:$D$105,MATCH($A54,Variables!$A$5:$A$105,0))="","","."&INDEX(Variables!$D$5:$D$105,MATCH($A54,Variables!$A$5:$A$105,0)))&"."&AF$5 | AG54: =INDEX(MTInputs!$J$1:$AZ$415,$D54,MATCH(AG$5,MTInputs!$J$5:$AZ$5,0)) | AH54: =INDEX(MTInputs!$J$1:$AZ$415,$D54,MATCH(AH$5,MTInputs!$J$5:$AZ$5,0)) | AI54: =INDEX(MTInputs!$J$1:$AZ$415,$D54,MATCH(AI$5,MTInputs!$J$5:$AZ$5,0)) | AJ54: =INDEX(MTInputs!$J$1:$AZ$415,$D54,MATCH(AJ$5,MTInputs!$J$5:$AZ$5,0)) | AK54: =INDEX(MTInputs!$J$1:$AZ$415,$D54,MATCH(AK$5,MTInputs!$J$5:$AZ$5,0)) | AL54: =INDEX(MTInputs!$J$1:$AZ$415,$D54,MATCH(AL$5,MTInputs!$J$5:$AZ$5,0)) | AM54: =INDEX(MTInputs!$J$1:$AZ$415,$D54,MATCH(AM$5,MTInputs!$J$5:$AZ$5,0)) | AN54: =INDEX(MTInputs!$J$1:$AZ$415,$D54,MATCH(AN$5,MTInputs!$J$5:$AZ$5,0)) | ... AY54: =INDEX(MTInputs!$J$1:$AZ$415,$D54,MATCH(AY$5,MTInputs!$J$5:$AZ$5,0))
A55: fpr.s | B55: nga | C55: ind | D55: 147 | H55: =INDEX(Variables!$B$5:$B$105,MATCH($A55,Variables!$A$5:$A$105,0))&IF($C55="",""," | "&INDEX(Mapping!$B$5:$B$26,MATCH($C55,Mapping!$A$5:$A$26,0))&" | "&INDEX(Mapping!$B$30:$B$41,MATCH($B55,Mapping!$A$30:$A$41,0))) | I55: =INDEX(Variables!$C$5:$C$105,MATCH($A55,Variables!$A$5:$A$105,0)) | J55: =INDEX(Variables!$E$5:$E$105,MATCH($A55,Variables!$A$5:$A$105,0)) | K55: =LOWER(Settings!$C$4)&".mit."&$A55&IF($C55="","","."&$C55&"."&$B55)&IF(INDEX(Variables!$D$5:$D$105,MATCH($A55,Variables!$A$5:$A$105,0))="","","."&INDEX(Variables!$D$5:$D$105,MATCH($A55,Variables!$A$5:$A$105,0)))&"."&K$5 | L55: =INDEX(MTInputs!$J$1:$AZ$415,$D55,MATCH(L$5,MTInputs!$J$5:$AZ$5,0)) | M55: =INDEX(MTInputs!$J$1:$AZ$415,$D55,MATCH(M$5,MTInputs!$J$5:$AZ$5,0)) | N55: =INDEX(MTInputs!$J$1:$AZ$415,$D55,MATCH(N$5,MTInputs!$J$5:$AZ$5,0)) | O55: =INDEX(MTInputs!$J$1:$AZ$415,$D55,MATCH(O$5,MTInputs!$J$5:$AZ$5,0)) | P55: =INDEX(MTInputs!$J$1:$AZ$415,$D55,MATCH(P$5,MTInputs!$J$5:$AZ$5,0)) | Q55: =INDEX(MTInputs!$J$1:$AZ$415,$D55,MATCH(Q$5,MTInputs!$J$5:$AZ$5,0)) | R55: =INDEX(MTInputs!$J$1:$AZ$415,$D55,MATCH(R$5,MTInputs!$J$5:$AZ$5,0)) | S55: =INDEX(MTInputs!$J$1:$AZ$415,$D55,MATCH(S$5,MTInputs!$J$5:$AZ$5,0)) | ... AD55: =INDEX(MTInputs!$J$1:$AZ$415,$D55,MATCH(AD$5,MTInputs!$J$5:$AZ$5,0)) | AF55: =LOWER(Settings!$C$4)&".mit."&$A55&IF($C55="","","."&$C55&"."&$B55)&IF(INDEX(Variables!$D$5:$D$105,MATCH($A55,Variables!$A$5:$A$105,0))="","","."&INDEX(Variables!$D$5:$D$105,MATCH($A55,Variables!$A$5:$A$105,0)))&"."&AF$5 | AG55: =INDEX(MTInputs!$J$1:$AZ$415,$D55,MATCH(AG$5,MTInputs!$J$5:$AZ$5,0)) | AH55: =INDEX(MTInputs!$J$1:$AZ$415,$D55,MATCH(AH$5,MTInputs!$J$5:$AZ$5,0)) | AI55: =INDEX(MTInputs!$J$1:$AZ$415,$D55,MATCH(AI$5,MTInputs!$J$5:$AZ$5,0)) | AJ55: =INDEX(MTInputs!$J$1:$AZ$415,$D55,MATCH(AJ$5,MTInputs!$J$5:$AZ$5,0)) | AK55: =INDEX(MTInputs!$J$1:$AZ$415,$D55,MATCH(AK$5,MTInputs!$J$5:$AZ$5,0)) | AL55: =INDEX(MTInputs!$J$1:$AZ$415,$D55,MATCH(AL$5,MTInputs!$J$5:$AZ$5,0)) | AM55: =INDEX(MTInputs!$J$1:$AZ$415,$D55,MATCH(AM$5,MTInputs!$J$5:$AZ$5,0)) | AN55: =INDEX(MTInputs!$J$1:$AZ$415,$D55,MATCH(AN$5,MTInputs!$J$5:$AZ$5,0)) | ... AY55: =INDEX(MTInputs!$J$1:$AZ$415,$D55,MATCH(AY$5,MTInputs!$J$5:$AZ$5,0))
A56: fpr.s | B56: ecy | C56: res | D56: 148 | H56: =INDEX(Variables!$B$5:$B$105,MATCH($A56,Variables!$A$5:$A$105,0))&IF($C56="",""," | "&INDEX(Mapping!$B$5:$B$26,MATCH($C56,Mapping!$A$5:$A$26,0))&" | "&INDEX(Mapping!$B$30:$B$41,MATCH($B56,Mapping!$A$30:$A$41,0))) | I56: =INDEX(Variables!$C$5:$C$105,MATCH($A56,Variables!$A$5:$A$105,0)) | J56: =INDEX(Variables!$E$5:$E$105,MATCH($A56,Variables!$A$5:$A$105,0)) | K56: =LOWER(Settings!$C$4)&".mit."&$A56&IF($C56="","","."&$C56&"."&$B56)&IF(INDEX(Variables!$D$5:$D$105,MATCH($A56,Variables!$A$5:$A$105,0))="","","."&INDEX(Variables!$D$5:$D$105,MATCH($A56,Variables!$A$5:$A$105,0)))&"."&K$5 | L56: =INDEX(MTInputs!$J$1:$AZ$415,$D56,MATCH(L$5,MTInputs!$J$5:$AZ$5,0)) | M56: =INDEX(MTInputs!$J$1:$AZ$415,$D56,MATCH(M$5,MTInputs!$J$5:$AZ$5,0)) | N56: =INDEX(MTInputs!$J$1:$AZ$415,$D56,MATCH(N$5,MTInputs!$J$5:$AZ$5,0)) | O56: =INDEX(MTInputs!$J$1:$AZ$415,$D56,MATCH(O$5,MTInputs!$J$5:$AZ$5,0)) | P56: =INDEX(MTInputs!$J$1:$AZ$415,$D56,MATCH(P$5,MTInputs!$J$5:$AZ$5,0)) | Q56: =INDEX(MTInputs!$J$1:$AZ$415,$D56,MATCH(Q$5,MTInputs!$J$5:$AZ$5,0)) | R56: =INDEX(MTInputs!$J$1:$AZ$415,$D56,MATCH(R$5,MTInputs!$J$5:$AZ$5,0)) | S56: =INDEX(MTInputs!$J$1:$AZ$415,$D56,MATCH(S$5,MTInputs!$J$5:$AZ$5,0)) | ... AD56: =INDEX(MTInputs!$J$1:$AZ$415,$D56,MATCH(AD$5,MTInputs!$J$5:$AZ$5,0)) | AF56: =LOWER(Settings!$C$4)&".mit."&$A56&IF($C56="","","."&$C56&"."&$B56)&IF(INDEX(Variables!$D$5:$D$105,MATCH($A56,Variables!$A$5:$A$105,0))="","","."&INDEX(Variables!$D$5:$D$105,MATCH($A56,Variables!$A$5:$A$105,0)))&"."&AF$5 | AG56: =INDEX(MTInputs!$J$1:$AZ$415,$D56,MATCH(AG$5,MTInputs!$J$5:$AZ$5,0)) | AH56: =INDEX(MTInputs!$J$1:$AZ$415,$D56,MATCH(AH$5,MTInputs!$J$5:$AZ$5,0)) | AI56: =INDEX(MTInputs!$J$1:$AZ$415,$D56,MATCH(AI$5,MTInputs!$J$5:$AZ$5,0)) | AJ56: =INDEX(MTInputs!$J$1:$AZ$415,$D56,MATCH(AJ$5,MTInputs!$J$5:$AZ$5,0)) | AK56: =INDEX(MTInputs!$J$1:$AZ$415,$D56,MATCH(AK$5,MTInputs!$J$5:$AZ$5,0)) | AL56: =INDEX(MTInputs!$J$1:$AZ$415,$D56,MATCH(AL$5,MTInputs!$J$5:$AZ$5,0)) | AM56: =INDEX(MTInputs!$J$1:$AZ$415,$D56,MATCH(AM$5,MTInputs!$J$5:$AZ$5,0)) | AN56: =INDEX(MTInputs!$J$1:$AZ$415,$D56,MATCH(AN$5,MTInputs!$J$5:$AZ$5,0)) | ... AY56: =INDEX(MTInputs!$J$1:$AZ$415,$D56,MATCH(AY$5,MTInputs!$J$5:$AZ$5,0))
A57: fpr.s | B57: ecy | C57: ind | D57: 149 | H57: =INDEX(Variables!$B$5:$B$105,MATCH($A57,Variables!$A$5:$A$105,0))&IF($C57="",""," | "&INDEX(Mapping!$B$5:$B$26,MATCH($C57,Mapping!$A$5:$A$26,0))&" | "&INDEX(Mapping!$B$30:$B$41,MATCH($B57,Mapping!$A$30:$A$41,0))) | I57: =INDEX(Variables!$C$5:$C$105,MATCH($A57,Variables!$A$5:$A$105,0)) | J57: =INDEX(Variables!$E$5:$E$105,MATCH($A57,Variables!$A$5:$A$105,0)) | K57: =LOWER(Settings!$C$4)&".mit."&$A57&IF($C57="","","."&$C57&"."&$B57)&IF(INDEX(Variables!$D$5:$D$105,MATCH($A57,Variables!$A$5:$A$105,0))="","","."&INDEX(Variables!$D$5:$D$105,MATCH($A57,Variables!$A$5:$A$105,0)))&"."&K$5 | L57: =INDEX(MTInputs!$J$1:$AZ$415,$D57,MATCH(L$5,MTInputs!$J$5:$AZ$5,0)) | M57: =INDEX(MTInputs!$J$1:$AZ$415,$D57,MATCH(M$5,MTInputs!$J$5:$AZ$5,0)) | N57: =INDEX(MTInputs!$J$1:$AZ$415,$D57,MATCH(N$5,MTInputs!$J$5:$AZ$5,0)) | O57: =INDEX(MTInputs!$J$1:$AZ$415,$D57,MATCH(O$5,MTInputs!$J$5:$AZ$5,0)) | P57: =INDEX(MTInputs!$J$1:$AZ$415,$D57,MATCH(P$5,MTInputs!$J$5:$AZ$5,0)) | Q57: =INDEX(MTInputs!$J$1:$AZ$415,$D57,MATCH(Q$5,MTInputs!$J$5:$AZ$5,0)) | R57: =INDEX(MTInputs!$J$1:$AZ$415,$D57,MATCH(R$5,MTInputs!$J$5:$AZ$5,0)) | S57: =INDEX(MTInputs!$J$1:$AZ$415,$D57,MATCH(S$5,MTInputs!$J$5:$AZ$5,0)) | ... AD57: =INDEX(MTInputs!$J$1:$AZ$415,$D57,MATCH(AD$5,MTInputs!$J$5:$AZ$5,0)) | AF57: =LOWER(Settings!$C$4)&".mit."&$A57&IF($C57="","","."&$C57&"."&$B57)&IF(INDEX(Variables!$D$5:$D$105,MATCH($A57,Variables!$A$5:$A$105,0))="","","."&INDEX(Variables!$D$5:$D$105,MATCH($A57,Variables!$A$5:$A$105,0)))&"."&AF$5 | AG57: =INDEX(MTInputs!$J$1:$AZ$415,$D57,MATCH(AG$5,MTInputs!$J$5:$AZ$5,0)) | AH57: =INDEX(MTInputs!$J$1:$AZ$415,$D57,MATCH(AH$5,MTInputs!$J$5:$AZ$5,0)) | AI57: =INDEX(MTInputs!$J$1:$AZ$415,$D57,MATCH(AI$5,MTInputs!$J$5:$AZ$5,0)) | AJ57: =INDEX(MTInputs!$J$1:$AZ$415,$D57,MATCH(AJ$5,MTInputs!$J$5:$AZ$5,0)) | AK57: =INDEX(MTInputs!$J$1:$AZ$415,$D57,MATCH(AK$5,MTInputs!$J$5:$AZ$5,0)) | AL57: =INDEX(MTInputs!$J$1:$AZ$415,$D57,MATCH(AL$5,MTInputs!$J$5:$AZ$5,0)) | AM57: =INDEX(MTInputs!$J$1:$AZ$415,$D57,MATCH(AM$5,MTInputs!$J$5:$AZ$5,0)) | AN57: =INDEX(MTInputs!$J$1:$AZ$415,$D57,MATCH(AN$5,MTInputs!$J$5:$AZ$5,0)) | ... AY57: =INDEX(MTInputs!$J$1:$AZ$415,$D57,MATCH(AY$5,MTInputs!$J$5:$AZ$5,0))
A58: fpr.s | B58: gso | C58: all | D58: 150 | H58: =INDEX(Variables!$B$5:$B$105,MATCH($A58,Variables!$A$5:$A$105,0))&IF($C58="",""," | "&INDEX(Mapping!$B$5:$B$26,MATCH($C58,Mapping!$A$5:$A$26,0))&" | "&INDEX(Mapping!$B$30:$B$41,MATCH($B58,Mapping!$A$30:$A$41,0))) | I58: =INDEX(Variables!$C$5:$C$105,MATCH($A58,Variables!$A$5:$A$105,0)) | J58: =INDEX(Variables!$E$5:$E$105,MATCH($A58,Variables!$A$5:$A$105,0)) | K58: =LOWER(Settings!$C$4)&".mit."&$A58&IF($C58="","","."&$C58&"."&$B58)&IF(INDEX(Variables!$D$5:$D$105,MATCH($A58,Variables!$A$5:$A$105,0))="","","."&INDEX(Variables!$D$5:$D$105,MATCH($A58,Variables!$A$5:$A$105,0)))&"."&K$5 | L58: =INDEX(MTInputs!$J$1:$AZ$415,$D58,MATCH(L$5,MTInputs!$J$5:$AZ$5,0)) | M58: =INDEX(MTInputs!$J$1:$AZ$415,$D58,MATCH(M$5,MTInputs!$J$5:$AZ$5,0)) | N58: =INDEX(MTInputs!$J$1:$AZ$415,$D58,MATCH(N$5,MTInputs!$J$5:$AZ$5,0)) | O58: =INDEX(MTInputs!$J$1:$AZ$415,$D58,MATCH(O$5,MTInputs!$J$5:$AZ$5,0)) | P58: =INDEX(MTInputs!$J$1:$AZ$415,$D58,MATCH(P$5,MTInputs!$J$5:$AZ$5,0)) | Q58: =INDEX(MTInputs!$J$1:$AZ$415,$D58,MATCH(Q$5,MTInputs!$J$5:$AZ$5,0)) | R58: =INDEX(MTInputs!$J$1:$AZ$415,$D58,MATCH(R$5,MTInputs!$J$5:$AZ$5,0)) | S58: =INDEX(MTInputs!$J$1:$AZ$415,$D58,MATCH(S$5,MTInputs!$J$5:$AZ$5,0)) | ... AD58: =INDEX(MTInputs!$J$1:$AZ$415,$D58,MATCH(AD$5,MTInputs!$J$5:$AZ$5,0)) | AF58: =LOWER(Settings!$C$4)&".mit."&$A58&IF($C58="","","."&$C58&"."&$B58)&IF(INDEX(Variables!$D$5:$D$105,MATCH($A58,Variables!$A$5:$A$105,0))="","","."&INDEX(Variables!$D$5:$D$105,MATCH($A58,Variables!$A$5:$A$105,0)))&"."&AF$5 | AG58: =INDEX(MTInputs!$J$1:$AZ$415,$D58,MATCH(AG$5,MTInputs!$J$5:$AZ$5,0)) | AH58: =INDEX(MTInputs!$J$1:$AZ$415,$D58,MATCH(AH$5,MTInputs!$J$5:$AZ$5,0)) | AI58: =INDEX(MTInputs!$J$1:$AZ$415,$D58,MATCH(AI$5,MTInputs!$J$5:$AZ$5,0)) | AJ58: =INDEX(MTInputs!$J$1:$AZ$415,$D58,MATCH(AJ$5,MTInputs!$J$5:$AZ$5,0)) | AK58: =INDEX(MTInputs!$J$1:$AZ$415,$D58,MATCH(AK$5,MTInputs!$J$5:$AZ$5,0)) | AL58: =INDEX(MTInputs!$J$1:$AZ$415,$D58,MATCH(AL$5,MTInputs!$J$5:$AZ$5,0)) | AM58: =INDEX(MTInputs!$J$1:$AZ$415,$D58,MATCH(AM$5,MTInputs!$J$5:$AZ$5,0)) | AN58: =INDEX(MTInputs!$J$1:$AZ$415,$D58,MATCH(AN$5,MTInputs!$J$5:$AZ$5,0)) | ... AY58: =INDEX(MTInputs!$J$1:$AZ$415,$D58,MATCH(AY$5,MTInputs!$J$5:$AZ$5,0))
A59: fpr.s | B59: die | C59: all | D59: 151 | H59: =INDEX(Variables!$B$5:$B$105,MATCH($A59,Variables!$A$5:$A$105,0))&IF($C59="",""," | "&INDEX(Mapping!$B$5:$B$26,MATCH($C59,Mapping!$A$5:$A$26,0))&" | "&INDEX(Mapping!$B$30:$B$41,MATCH($B59,Mapping!$A$30:$A$41,0))) | I59: =INDEX(Variables!$C$5:$C$105,MATCH($A59,Variables!$A$5:$A$105,0)) | J59: =INDEX(Variables!$E$5:$E$105,MATCH($A59,Variables!$A$5:$A$105,0)) | K59: =LOWER(Settings!$C$4)&".mit."&$A59&IF($C59="","","."&$C59&"."&$B59)&IF(INDEX(Variables!$D$5:$D$105,MATCH($A59,Variables!$A$5:$A$105,0))="","","."&INDEX(Variables!$D$5:$D$105,MATCH($A59,Variables!$A$5:$A$105,0)))&"."&K$5 | L59: =INDEX(MTInputs!$J$1:$AZ$415,$D59,MATCH(L$5,MTInputs!$J$5:$AZ$5,0)) | M59: =INDEX(MTInputs!$J$1:$AZ$415,$D59,MATCH(M$5,MTInputs!$J$5:$AZ$5,0)) | N59: =INDEX(MTInputs!$J$1:$AZ$415,$D59,MATCH(N$5,MTInputs!$J$5:$AZ$5,0)) | O59: =INDEX(MTInputs!$J$1:$AZ$415,$D59,MATCH(O$5,MTInputs!$J$5:$AZ$5,0)) | P59: =INDEX(MTInputs!$J$1:$AZ$415,$D59,MATCH(P$5,MTInputs!$J$5:$AZ$5,0)) | Q59: =INDEX(MTInputs!$J$1:$AZ$415,$D59,MATCH(Q$5,MTInputs!$J$5:$AZ$5,0)) | R59: =INDEX(MTInputs!$J$1:$AZ$415,$D59,MATCH(R$5,MTInputs!$J$5:$AZ$5,0)) | S59: =INDEX(MTInputs!$J$1:$AZ$415,$D59,MATCH(S$5,MTInputs!$J$5:$AZ$5,0)) | ... AD59: =INDEX(MTInputs!$J$1:$AZ$415,$D59,MATCH(AD$5,MTInputs!$J$5:$AZ$5,0)) | AF59: =LOWER(Settings!$C$4)&".mit."&$A59&IF($C59="","","."&$C59&"."&$B59)&IF(INDEX(Variables!$D$5:$D$105,MATCH($A59,Variables!$A$5:$A$105,0))="","","."&INDEX(Variables!$D$5:$D$105,MATCH($A59,Variables!$A$5:$A$105,0)))&"."&AF$5 | AG59: =INDEX(MTInputs!$J$1:$AZ$415,$D59,MATCH(AG$5,MTInputs!$J$5:$AZ$5,0)) | AH59: =INDEX(MTInputs!$J$1:$AZ$415,$D59,MATCH(AH$5,MTInputs!$J$5:$AZ$5,0)) | AI59: =INDEX(MTInputs!$J$1:$AZ$415,$D59,MATCH(AI$5,MTInputs!$J$5:$AZ$5,0)) | AJ59: =INDEX(MTInputs!$J$1:$AZ$415,$D59,MATCH(AJ$5,MTInputs!$J$5:$AZ$5,0)) | AK59: =INDEX(MTInputs!$J$1:$AZ$415,$D59,MATCH(AK$5,MTInputs!$J$5:$AZ$5,0)) | AL59: =INDEX(MTInputs!$J$1:$AZ$415,$D59,MATCH(AL$5,MTInputs!$J$5:$AZ$5,0)) | AM59: =INDEX(MTInputs!$J$1:$AZ$415,$D59,MATCH(AM$5,MTInputs!$J$5:$AZ$5,0)) | AN59: =INDEX(MTInputs!$J$1:$AZ$415,$D59,MATCH(AN$5,MTInputs!$J$5:$AZ$5,0)) | ... AY59: =INDEX(MTInputs!$J$1:$AZ$415,$D59,MATCH(AY$5,MTInputs!$J$5:$AZ$5,0))
A60: fpr.s | B60: lpg | C60: all | D60: 152 | H60: =INDEX(Variables!$B$5:$B$105,MATCH($A60,Variables!$A$5:$A$105,0))&IF($C60="",""," | "&INDEX(Mapping!$B$5:$B$26,MATCH($C60,Mapping!$A$5:$A$26,0))&" | "&INDEX(Mapping!$B$30:$B$41,MATCH($B60,Mapping!$A$30:$A$41,0))) | I60: =INDEX(Variables!$C$5:$C$105,MATCH($A60,Variables!$A$5:$A$105,0)) | J60: =INDEX(Variables!$E$5:$E$105,MATCH($A60,Variables!$A$5:$A$105,0)) | K60: =LOWER(Settings!$C$4)&".mit."&$A60&IF($C60="","","."&$C60&"."&$B60)&IF(INDEX(Variables!$D$5:$D$105,MATCH($A60,Variables!$A$5:$A$105,0))="","","."&INDEX(Variables!$D$5:$D$105,MATCH($A60,Variables!$A$5:$A$105,0)))&"."&K$5 | L60: =INDEX(MTInputs!$J$1:$AZ$415,$D60,MATCH(L$5,MTInputs!$J$5:$AZ$5,0)) | M60: =INDEX(MTInputs!$J$1:$AZ$415,$D60,MATCH(M$5,MTInputs!$J$5:$AZ$5,0)) | N60: =INDEX(MTInputs!$J$1:$AZ$415,$D60,MATCH(N$5,MTInputs!$J$5:$AZ$5,0)) | O60: =INDEX(MTInputs!$J$1:$AZ$415,$D60,MATCH(O$5,MTInputs!$J$5:$AZ$5,0)) | P60: =INDEX(MTInputs!$J$1:$AZ$415,$D60,MATCH(P$5,MTInputs!$J$5:$AZ$5,0)) | Q60: =INDEX(MTInputs!$J$1:$AZ$415,$D60,MATCH(Q$5,MTInputs!$J$5:$AZ$5,0)) | R60: =INDEX(MTInputs!$J$1:$AZ$415,$D60,MATCH(R$5,MTInputs!$J$5:$AZ$5,0)) | S60: =INDEX(MTInputs!$J$1:$AZ$415,$D60,MATCH(S$5,MTInputs!$J$5:$AZ$5,0)) | ... AD60: =INDEX(MTInputs!$J$1:$AZ$415,$D60,MATCH(AD$5,MTInputs!$J$5:$AZ$5,0)) | AF60: =LOWER(Settings!$C$4)&".mit."&$A60&IF($C60="","","."&$C60&"."&$B60)&IF(INDEX(Variables!$D$5:$D$105,MATCH($A60,Variables!$A$5:$A$105,0))="","","."&INDEX(Variables!$D$5:$D$105,MATCH($A60,Variables!$A$5:$A$105,0)))&"."&AF$5 | AG60: =INDEX(MTInputs!$J$1:$AZ$415,$D60,MATCH(AG$5,MTInputs!$J$5:$AZ$5,0)) | AH60: =INDEX(MTInputs!$J$1:$AZ$415,$D60,MATCH(AH$5,MTInputs!$J$5:$AZ$5,0)) | AI60: =INDEX(MTInputs!$J$1:$AZ$415,$D60,MATCH(AI$5,MTInputs!$J$5:$AZ$5,0)) | AJ60: =INDEX(MTInputs!$J$1:$AZ$415,$D60,MATCH(AJ$5,MTInputs!$J$5:$AZ$5,0)) | AK60: =INDEX(MTInputs!$J$1:$AZ$415,$D60,MATCH(AK$5,MTInputs!$J$5:$AZ$5,0)) | AL60: =INDEX(MTInputs!$J$1:$AZ$415,$D60,MATCH(AL$5,MTInputs!$J$5:$AZ$5,0)) | AM60: =INDEX(MTInputs!$J$1:$AZ$415,$D60,MATCH(AM$5,MTInputs!$J$5:$AZ$5,0)) | AN60: =INDEX(MTInputs!$J$1:$AZ$415,$D60,MATCH(AN$5,MTInputs!$J$5:$AZ$5,0)) | ... AY60: =INDEX(MTInputs!$J$1:$AZ$415,$D60,MATCH(AY$5,MTInputs!$J$5:$AZ$5,0))
A61: fpr.s | B61: ker | C61: all | D61: 153 | H61: =INDEX(Variables!$B$5:$B$105,MATCH($A61,Variables!$A$5:$A$105,0))&IF($C61="",""," | "&INDEX(Mapping!$B$5:$B$26,MATCH($C61,Mapping!$A$5:$A$26,0))&" | "&INDEX(Mapping!$B$30:$B$41,MATCH($B61,Mapping!$A$30:$A$41,0))) | I61: =INDEX(Variables!$C$5:$C$105,MATCH($A61,Variables!$A$5:$A$105,0)) | J61: =INDEX(Variables!$E$5:$E$105,MATCH($A61,Variables!$A$5:$A$105,0)) | K61: =LOWER(Settings!$C$4)&".mit."&$A61&IF($C61="","","."&$C61&"."&$B61)&IF(INDEX(Variables!$D$5:$D$105,MATCH($A61,Variables!$A$5:$A$105,0))="","","."&INDEX(Variables!$D$5:$D$105,MATCH($A61,Variables!$A$5:$A$105,0)))&"."&K$5 | L61: =INDEX(MTInputs!$J$1:$AZ$415,$D61,MATCH(L$5,MTInputs!$J$5:$AZ$5,0)) | M61: =INDEX(MTInputs!$J$1:$AZ$415,$D61,MATCH(M$5,MTInputs!$J$5:$AZ$5,0)) | N61: =INDEX(MTInputs!$J$1:$AZ$415,$D61,MATCH(N$5,MTInputs!$J$5:$AZ$5,0)) | O61: =INDEX(MTInputs!$J$1:$AZ$415,$D61,MATCH(O$5,MTInputs!$J$5:$AZ$5,0)) | P61: =INDEX(MTInputs!$J$1:$AZ$415,$D61,MATCH(P$5,MTInputs!$J$5:$AZ$5,0)) | Q61: =INDEX(MTInputs!$J$1:$AZ$415,$D61,MATCH(Q$5,MTInputs!$J$5:$AZ$5,0)) | R61: =INDEX(MTInputs!$J$1:$AZ$415,$D61,MATCH(R$5,MTInputs!$J$5:$AZ$5,0)) | S61: =INDEX(MTInputs!$J$1:$AZ$415,$D61,MATCH(S$5,MTInputs!$J$5:$AZ$5,0)) | ... AD61: =INDEX(MTInputs!$J$1:$AZ$415,$D61,MATCH(AD$5,MTInputs!$J$5:$AZ$5,0)) | AF61: =LOWER(Settings!$C$4)&".mit."&$A61&IF($C61="","","."&$C61&"."&$B61)&IF(INDEX(Variables!$D$5:$D$105,MATCH($A61,Variables!$A$5:$A$105,0))="","","."&INDEX(Variables!$D$5:$D$105,MATCH($A61,Variables!$A$5:$A$105,0)))&"."&AF$5 | AG61: =INDEX(MTInputs!$J$1:$AZ$415,$D61,MATCH(AG$5,MTInputs!$J$5:$AZ$5,0)) | AH61: =INDEX(MTInputs!$J$1:$AZ$415,$D61,MATCH(AH$5,MTInputs!$J$5:$AZ$5,0)) | AI61: =INDEX(MTInputs!$J$1:$AZ$415,$D61,MATCH(AI$5,MTInputs!$J$5:$AZ$5,0)) | AJ61: =INDEX(MTInputs!$J$1:$AZ$415,$D61,MATCH(AJ$5,MTInputs!$J$5:$AZ$5,0)) | AK61: =INDEX(MTInputs!$J$1:$AZ$415,$D61,MATCH(AK$5,MTInputs!$J$5:$AZ$5,0)) | AL61: =INDEX(MTInputs!$J$1:$AZ$415,$D61,MATCH(AL$5,MTInputs!$J$5:$AZ$5,0)) | AM61: =INDEX(MTInputs!$J$1:$AZ$415,$D61,MATCH(AM$5,MTInputs!$J$5:$AZ$5,0)) | AN61: =INDEX(MTInputs!$J$1:$AZ$415,$D61,MATCH(AN$5,MTInputs!$J$5:$AZ$5,0)) | ... AY61: =INDEX(MTInputs!$J$1:$AZ$415,$D61,MATCH(AY$5,MTInputs!$J$5:$AZ$5,0))
... A77: fpr.f | B77: bio | C77: all | D77: 169 | H77: =INDEX(Variables!$B$5:$B$105,MATCH($A77,Variables!$A$5:$A$105,0))&IF($C77="",""," | "&INDEX(Mapping!$B$5:$B$26,MATCH($C77,Mapping!$A$5:$A$26,0))&" | "&INDEX(Mapping!$B$30:$B$41,MATCH($B77,Mapping!$A$30:$A$41,0))) | I77: =INDEX(Variables!$C$5:$C$105,MATCH($A77,Variables!$A$5:$A$105,0)) | J77: =INDEX(Variables!$E$5:$E$105,MATCH($A77,Variables!$A$5:$A$105,0)) | K77: =LOWER(Settings!$C$4)&".mit."&$A77&IF($C77="","","."&$C77&"."&$B77)&IF(INDEX(Variables!$D$5:$D$105,MATCH($A77,Variables!$A$5:$A$105,0))="","","."&INDEX(Variables!$D$5:$D$105,MATCH($A77,Variables!$A$5:$A$105,0)))&"."&K$5 | L77: =INDEX(MTInputs!$J$1:$AZ$415,$D77,MATCH(L$5,MTInputs!$J$5:$AZ$5,0)) | M77: =INDEX(MTInputs!$J$1:$AZ$415,$D77,MATCH(M$5,MTInputs!$J$5:$AZ$5,0)) | N77: =INDEX(MTInputs!$J$1:$AZ$415,$D77,MATCH(N$5,MTInputs!$J$5:$AZ$5,0)) | O77: =INDEX(MTInputs!$J$1:$AZ$415,$D77,MATCH(O$5,MTInputs!$J$5:$AZ$5,0)) | P77: =INDEX(MTInputs!$J$1:$AZ$415,$D77,MATCH(P$5,MTInputs!$J$5:$AZ$5,0)) | Q77: =INDEX(MTInputs!$J$1:$AZ$415,$D77,MATCH(Q$5,MTInputs!$J$5:$AZ$5,0)) | R77: =INDEX(MTInputs!$J$1:$AZ$415,$D77,MATCH(R$5,MTInputs!$J$5:$AZ$5,0)) | S77: =INDEX(MTInputs!$J$1:$AZ$415,$D77,MATCH(S$5,MTInputs!$J$5:$AZ$5,0)) | ... AD77: =INDEX(MTInputs!$J$1:$AZ$415,$D77,MATCH(AD$5,MTInputs!$J$5:$AZ$5,0)) | AF77: =LOWER(Settings!$C$4)&".mit."&$A77&IF($C77="","","."&$C77&"."&$B77)&IF(INDEX(Variables!$D$5:$D$105,MATCH($A77,Variables!$A$5:$A$105,0))="","","."&INDEX(Variables!$D$5:$D$105,MATCH($A77,Variables!$A$5:$A$105,0)))&"."&AF$5 | AG77: =INDEX(MTInputs!$J$1:$AZ$415,$D77,MATCH(AG$5,MTInputs!$J$5:$AZ$5,0)) | AH77: =INDEX(MTInputs!$J$1:$AZ$415,$D77,MATCH(AH$5,MTInputs!$J$5:$AZ$5,0)) | AI77: =INDEX(MTInputs!$J$1:$AZ$415,$D77,MATCH(AI$5,MTInputs!$J$5:$AZ$5,0)) | AJ77: =INDEX(MTInputs!$J$1:$AZ$415,$D77,MATCH(AJ$5,MTInputs!$J$5:$AZ$5,0)) | AK77: =INDEX(MTInputs!$J$1:$AZ$415,$D77,MATCH(AK$5,MTInputs!$J$5:$AZ$5,0)) | AL77: =INDEX(MTInputs!$J$1:$AZ$415,$D77,MATCH(AL$5,MTInputs!$J$5:$AZ$5,0)) | AM77: =INDEX(MTInputs!$J$1:$AZ$415,$D77,MATCH(AM$5,MTInputs!$J$5:$AZ$5,0)) | AN77: =INDEX(MTInputs!$J$1:$AZ$415,$D77,MATCH(AN$5,MTInputs!$J$5:$AZ$5,0)) | ... AY77: =INDEX(MTInputs!$J$1:$AZ$415,$D77,MATCH(AY$5,MTInputs!$J$5:$AZ$5,0))
A78: fpr | B78: coa | C78: pow | H78: =INDEX(Variables!$B$5:$B$105,MATCH($A78,Variables!$A$5:$A$105,0))&IF($C78="",""," | "&INDEX(Mapping!$B$5:$B$26,MATCH($C78,Mapping!$A$5:$A$26,0))&" | "&INDEX(Mapping!$B$30:$B$41,MATCH($B78,Mapping!$A$30:$A$41,0))) | I78: =INDEX(Variables!$C$5:$C$105,MATCH($A78,Variables!$A$5:$A$105,0)) | J78: =INDEX(Variables!$E$5:$E$105,MATCH($A78,Variables!$A$5:$A$105,0)) | K78: =LOWER(Settings!$C$4)&".mit."&$A78&IF($C78="","","."&$C78&"."&$B78)&IF(INDEX(Variables!$D$5:$D$105,MATCH($A78,Variables!$A$5:$A$105,0))="","","."&INDEX(Variables!$D$5:$D$105,MATCH($A78,Variables!$A$5:$A$105,0)))&"."&K$5 | L78: =IF(L$4<L$48,0,L50+(L64-L50)/MAX(L$49-L$48,1)*(L$4-L$48)) | M78: =IF(M$4<M$48,0,M50+(M64-M50)/MAX(M$49-M$48,1)*(M$4-M$48)) | N78: =IF(N$4<N$48,0,N50+(N64-N50)/MAX(N$49-N$48,1)*(N$4-N$48)) | O78: =IF(O$4<O$48,0,O50+(O64-O50)/MAX(O$49-O$48,1)*(O$4-O$48)) | P78: =IF(P$4<P$48,0,P50+(P64-P50)/MAX(P$49-P$48,1)*(P$4-P$48)) | Q78: =IF(Q$4<Q$48,0,Q50+(Q64-Q50)/MAX(Q$49-Q$48,1)*(Q$4-Q$48)) | R78: =IF(R$4<R$48,0,R50+(R64-R50)/MAX(R$49-R$48,1)*(R$4-R$48)) | S78: =IF(S$4<S$48,0,S50+(S64-S50)/MAX(S$49-S$48,1)*(S$4-S$48)) | ... AC78: =IF(AC$4<AC$48,0,AC50+(AC64-AC50)/MAX(AC$49-AC$48,1)*(AC$4-AC$48)) | AD78: =PATH(AD$4,AD$48,AD$49,AD50,AD64,TRUE) | AF78: =LOWER(Settings!$C$4)&".mit."&$A78&IF($C78="","","."&$C78&"."&$B78)&IF(INDEX(Variables!$D$5:$D$105,MATCH($A78,Variables!$A$5:$A$105,0))="","","."&INDEX(Variables!$D$5:$D$105,MATCH($A78,Variables!$A$5:$A$105,0)))&"."&AF$5 | AG78: =IF(AG$4<AG$48,0,AG50+(AG64-AG50)/MAX(AG$49-AG$48,1)*(AG$4-AG$48)) | AH78: =IF(AH$4<AH$48,0,AH50+(AH64-AH50)/MAX(AH$49-AH$48,1)*(AH$4-AH$48)) | AI78: =IF(AI$4<AI$48,0,AI50+(AI64-AI50)/MAX(AI$49-AI$48,1)*(AI$4-AI$48)) | AJ78: =IF(AJ$4<AJ$48,0,AJ50+(AJ64-AJ50)/MAX(AJ$49-AJ$48,1)*(AJ$4-AJ$48)) | AK78: =IF(AK$4<AK$48,0,AK50+(AK64-AK50)/MAX(AK$49-AK$48,1)*(AK$4-AK$48)) | AL78: =IF(AL$4<AL$48,0,AL50+(AL64-AL50)/MAX(AL$49-AL$48,1)*(AL$4-AL$48)) | AM78: =IF(AM$4<AM$48,0,AM50+(AM64-AM50)/MAX(AM$49-AM$48,1)*(AM$4-AM$48)) | AN78: =IF(AN$4<AN$48,0,AN50+(AN64-AN50)/MAX(AN$49-AN$48,1)*(AN$4-AN$48)) | ... AX78: =IF(AX$4<AX$48,0,AX50+(AX64-AX50)/MAX(AX$49-AX$48,1)*(AX$4-AX$48)) | AY78: =PATH(AY$4,AY$48,AY$49,AY50,AY64,TRUE)
A79: fpr | B79: coa | C79: res | H79: =INDEX(Variables!$B$5:$B$105,MATCH($A79,Variables!$A$5:$A$105,0))&IF($C79="",""," | "&INDEX(Mapping!$B$5:$B$26,MATCH($C79,Mapping!$A$5:$A$26,0))&" | "&INDEX(Mapping!$B$30:$B$41,MATCH($B79,Mapping!$A$30:$A$41,0))) | I79: =INDEX(Variables!$C$5:$C$105,MATCH($A79,Variables!$A$5:$A$105,0)) | J79: =INDEX(Variables!$E$5:$E$105,MATCH($A79,Variables!$A$5:$A$105,0)) | K79: =LOWER(Settings!$C$4)&".mit."&$A79&IF($C79="","","."&$C79&"."&$B79)&IF(INDEX(Variables!$D$5:$D$105,MATCH($A79,Variables!$A$5:$A$105,0))="","","."&INDEX(Variables!$D$5:$D$105,MATCH($A79,Variables!$A$5:$A$105,0)))&"."&K$5 | L79: =IF(L$4<L$48,0,L51+(L65-L51)/MAX(L$49-L$48,1)*(L$4-L$48)) | M79: =IF(M$4<M$48,0,M51+(M65-M51)/MAX(M$49-M$48,1)*(M$4-M$48)) | N79: =IF(N$4<N$48,0,N51+(N65-N51)/MAX(N$49-N$48,1)*(N$4-N$48)) | O79: =IF(O$4<O$48,0,O51+(O65-O51)/MAX(O$49-O$48,1)*(O$4-O$48)) | P79: =IF(P$4<P$48,0,P51+(P65-P51)/MAX(P$49-P$48,1)*(P$4-P$48)) | Q79: =IF(Q$4<Q$48,0,Q51+(Q65-Q51)/MAX(Q$49-Q$48,1)*(Q$4-Q$48)) | R79: =IF(R$4<R$48,0,R51+(R65-R51)/MAX(R$49-R$48,1)*(R$4-R$48)) | S79: =IF(S$4<S$48,0,S51+(S65-S51)/MAX(S$49-S$48,1)*(S$4-S$48)) | ... AC79: =IF(AC$4<AC$48,0,AC51+(AC65-AC51)/MAX(AC$49-AC$48,1)*(AC$4-AC$48)) | AD79: =PATH(AD$4,AD$48,AD$49,AD51,AD65,TRUE) | AF79: =LOWER(Settings!$C$4)&".mit."&$A79&IF($C79="","","."&$C79&"."&$B79)&IF(INDEX(Variables!$D$5:$D$105,MATCH($A79,Variables!$A$5:$A$105,0))="","","."&INDEX(Variables!$D$5:$D$105,MATCH($A79,Variables!$A$5:$A$105,0)))&"."&AF$5 | AG79: =IF(AG$4<AG$48,0,AG51+(AG65-AG51)/MAX(AG$49-AG$48,1)*(AG$4-AG$48)) | AH79: =IF(AH$4<AH$48,0,AH51+(AH65-AH51)/MAX(AH$49-AH$48,1)*(AH$4-AH$48)) | AI79: =IF(AI$4<AI$48,0,AI51+(AI65-AI51)/MAX(AI$49-AI$48,1)*(AI$4-AI$48)) | AJ79: =IF(AJ$4<AJ$48,0,AJ51+(AJ65-AJ51)/MAX(AJ$49-AJ$48,1)*(AJ$4-AJ$48)) | AK79: =IF(AK$4<AK$48,0,AK51+(AK65-AK51)/MAX(AK$49-AK$48,1)*(AK$4-AK$48)) | AL79: =IF(AL$4<AL$48,0,AL51+(AL65-AL51)/MAX(AL$49-AL$48,1)*(AL$4-AL$48)) | AM79: =IF(AM$4<AM$48,0,AM51+(AM65-AM51)/MAX(AM$49-AM$48,1)*(AM$4-AM$48)) | AN79: =IF(AN$4<AN$48,0,AN51+(AN65-AN51)/MAX(AN$49-AN$48,1)*(AN$4-AN$48)) | ... AX79: =IF(AX$4<AX$48,0,AX51+(AX65-AX51)/MAX(AX$49-AX$48,1)*(AX$4-AX$48)) | AY79: =PATH(AY$4,AY$48,AY$49,AY51,AY65,TRUE)
A80: fpr | B80: coa | C80: ind | H80: =INDEX(Variables!$B$5:$B$105,MATCH($A80,Variables!$A$5:$A$105,0))&IF($C80="",""," | "&INDEX(Mapping!$B$5:$B$26,MATCH($C80,Mapping!$A$5:$A$26,0))&" | "&INDEX(Mapping!$B$30:$B$41,MATCH($B80,Mapping!$A$30:$A$41,0))) | I80: =INDEX(Variables!$C$5:$C$105,MATCH($A80,Variables!$A$5:$A$105,0)) | J80: =INDEX(Variables!$E$5:$E$105,MATCH($A80,Variables!$A$5:$A$105,0)) | K80: =LOWER(Settings!$C$4)&".mit."&$A80&IF($C80="","","."&$C80&"."&$B80)&IF(INDEX(Variables!$D$5:$D$105,MATCH($A80,Variables!$A$5:$A$105,0))="","","."&INDEX(Variables!$D$5:$D$105,MATCH($A80,Variables!$A$5:$A$105,0)))&"."&K$5 | L80: =IF(L$4<L$48,0,L52+(L66-L52)/MAX(L$49-L$48,1)*(L$4-L$48)) | M80: =IF(M$4<M$48,0,M52+(M66-M52)/MAX(M$49-M$48,1)*(M$4-M$48)) | N80: =IF(N$4<N$48,0,N52+(N66-N52)/MAX(N$49-N$48,1)*(N$4-N$48)) | O80: =IF(O$4<O$48,0,O52+(O66-O52)/MAX(O$49-O$48,1)*(O$4-O$48)) | P80: =IF(P$4<P$48,0,P52+(P66-P52)/MAX(P$49-P$48,1)*(P$4-P$48)) | Q80: =IF(Q$4<Q$48,0,Q52+(Q66-Q52)/MAX(Q$49-Q$48,1)*(Q$4-Q$48)) | R80: =IF(R$4<R$48,0,R52+(R66-R52)/MAX(R$49-R$48,1)*(R$4-R$48)) | S80: =IF(S$4<S$48,0,S52+(S66-S52)/MAX(S$49-S$48,1)*(S$4-S$48)) | ... AC80: =IF(AC$4<AC$48,0,AC52+(AC66-AC52)/MAX(AC$49-AC$48,1)*(AC$4-AC$48)) | AD80: =PATH(AD$4,AD$48,AD$49,AD52,AD66,TRUE) | AF80: =LOWER(Settings!$C$4)&".mit."&$A80&IF($C80="","","."&$C80&"."&$B80)&IF(INDEX(Variables!$D$5:$D$105,MATCH($A80,Variables!$A$5:$A$105,0))="","","."&INDEX(Variables!$D$5:$D$105,MATCH($A80,Variables!$A$5:$A$105,0)))&"."&AF$5 | AG80: =IF(AG$4<AG$48,0,AG52+(AG66-AG52)/MAX(AG$49-AG$48,1)*(AG$4-AG$48)) | AH80: =IF(AH$4<AH$48,0,AH52+(AH66-AH52)/MAX(AH$49-AH$48,1)*(AH$4-AH$48)) | AI80: =IF(AI$4<AI$48,0,AI52+(AI66-AI52)/MAX(AI$49-AI$48,1)*(AI$4-AI$48)) | AJ80: =IF(AJ$4<AJ$48,0,AJ52+(AJ66-AJ52)/MAX(AJ$49-AJ$48,1)*(AJ$4-AJ$48)) | AK80: =IF(AK$4<AK$48,0,AK52+(AK66-AK52)/MAX(AK$49-AK$48,1)*(AK$4-AK$48)) | AL80: =IF(AL$4<AL$48,0,AL52+(AL66-AL52)/MAX(AL$49-AL$48,1)*(AL$4-AL$48)) | AM80: =IF(AM$4<AM$48,0,AM52+(AM66-AM52)/MAX(AM$49-AM$48,1)*(AM$4-AM$48)) | AN80: =IF(AN$4<AN$48,0,AN52+(AN66-AN52)/MAX(AN$49-AN$48,1)*(AN$4-AN$48)) | ... AX80: =IF(AX$4<AX$48,0,AX52+(AX66-AX52)/MAX(AX$49-AX$48,1)*(AX$4-AX$48)) | AY80: =PATH(AY$4,AY$48,AY$49,AY52,AY66,TRUE)
A81: fpr | B81: nga | C81: pow | H81: =INDEX(Variables!$B$5:$B$105,MATCH($A81,Variables!$A$5:$A$105,0))&IF($C81="",""," | "&INDEX(Mapping!$B$5:$B$26,MATCH($C81,Mapping!$A$5:$A$26,0))&" | "&INDEX(Mapping!$B$30:$B$41,MATCH($B81,Mapping!$A$30:$A$41,0))) | I81: =INDEX(Variables!$C$5:$C$105,MATCH($A81,Variables!$A$5:$A$105,0)) | J81: =INDEX(Variables!$E$5:$E$105,MATCH($A81,Variables!$A$5:$A$105,0)) | K81: =LOWER(Settings!$C$4)&".mit."&$A81&IF($C81="","","."&$C81&"."&$B81)&IF(INDEX(Variables!$D$5:$D$105,MATCH($A81,Variables!$A$5:$A$105,0))="","","."&INDEX(Variables!$D$5:$D$105,MATCH($A81,Variables!$A$5:$A$105,0)))&"."&K$5 | L81: =IF(L$4<L$48,0,L53+(L67-L53)/MAX(L$49-L$48,1)*(L$4-L$48)) | M81: =IF(M$4<M$48,0,M53+(M67-M53)/MAX(M$49-M$48,1)*(M$4-M$48)) | N81: =IF(N$4<N$48,0,N53+(N67-N53)/MAX(N$49-N$48,1)*(N$4-N$48)) | O81: =IF(O$4<O$48,0,O53+(O67-O53)/MAX(O$49-O$48,1)*(O$4-O$48)) | P81: =IF(P$4<P$48,0,P53+(P67-P53)/MAX(P$49-P$48,1)*(P$4-P$48)) | Q81: =IF(Q$4<Q$48,0,Q53+(Q67-Q53)/MAX(Q$49-Q$48,1)*(Q$4-Q$48)) | R81: =IF(R$4<R$48,0,R53+(R67-R53)/MAX(R$49-R$48,1)*(R$4-R$48)) | S81: =IF(S$4<S$48,0,S53+(S67-S53)/MAX(S$49-S$48,1)*(S$4-S$48)) | ... AC81: =IF(AC$4<AC$48,0,AC53+(AC67-AC53)/MAX(AC$49-AC$48,1)*(AC$4-AC$48)) | AD81: =PATH(AD$4,AD$48,AD$49,AD53,AD67,TRUE) | AF81: =LOWER(Settings!$C$4)&".mit."&$A81&IF($C81="","","."&$C81&"."&$B81)&IF(INDEX(Variables!$D$5:$D$105,MATCH($A81,Variables!$A$5:$A$105,0))="","","."&INDEX(Variables!$D$5:$D$105,MATCH($A81,Variables!$A$5:$A$105,0)))&"."&AF$5 | AG81: =IF(AG$4<AG$48,0,AG53+(AG67-AG53)/MAX(AG$49-AG$48,1)*(AG$4-AG$48)) | AH81: =IF(AH$4<AH$48,0,AH53+(AH67-AH53)/MAX(AH$49-AH$48,1)*(AH$4-AH$48)) | AI81: =IF(AI$4<AI$48,0,AI53+(AI67-AI53)/MAX(AI$49-AI$48,1)*(AI$4-AI$48)) | AJ81: =IF(AJ$4<AJ$48,0,AJ53+(AJ67-AJ53)/MAX(AJ$49-AJ$48,1)*(AJ$4-AJ$48)) | AK81: =IF(AK$4<AK$48,0,AK53+(AK67-AK53)/MAX(AK$49-AK$48,1)*(AK$4-AK$48)) | AL81: =IF(AL$4<AL$48,0,AL53+(AL67-AL53)/MAX(AL$49-AL$48,1)*(AL$4-AL$48)) | AM81: =IF(AM$4<AM$48,0,AM53+(AM67-AM53)/MAX(AM$49-AM$48,1)*(AM$4-AM$48)) | AN81: =IF(AN$4<AN$48,0,AN53+(AN67-AN53)/MAX(AN$49-AN$48,1)*(AN$4-AN$48)) | ... AX81: =IF(AX$4<AX$48,0,AX53+(AX67-AX53)/MAX(AX$49-AX$48,1)*(AX$4-AX$48)) | AY81: =PATH(AY$4,AY$48,AY$49,AY53,AY67,TRUE)
A82: fpr | B82: nga | C82: res | H82: =INDEX(Variables!$B$5:$B$105,MATCH($A82,Variables!$A$5:$A$105,0))&IF($C82="",""," | "&INDEX(Mapping!$B$5:$B$26,MATCH($C82,Mapping!$A$5:$A$26,0))&" | "&INDEX(Mapping!$B$30:$B$41,MATCH($B82,Mapping!$A$30:$A$41,0))) | I82: =INDEX(Variables!$C$5:$C$105,MATCH($A82,Variables!$A$5:$A$105,0)) | J82: =INDEX(Variables!$E$5:$E$105,MATCH($A82,Variables!$A$5:$A$105,0)) | K82: =LOWER(Settings!$C$4)&".mit."&$A82&IF($C82="","","."&$C82&"."&$B82)&IF(INDEX(Variables!$D$5:$D$105,MATCH($A82,Variables!$A$5:$A$105,0))="","","."&INDEX(Variables!$D$5:$D$105,MATCH($A82,Variables!$A$5:$A$105,0)))&"."&K$5 | L82: =IF(L$4<L$48,0,L54+(L68-L54)/MAX(L$49-L$48,1)*(L$4-L$48)) | M82: =IF(M$4<M$48,0,M54+(M68-M54)/MAX(M$49-M$48,1)*(M$4-M$48)) | N82: =IF(N$4<N$48,0,N54+(N68-N54)/MAX(N$49-N$48,1)*(N$4-N$48)) | O82: =IF(O$4<O$48,0,O54+(O68-O54)/MAX(O$49-O$48,1)*(O$4-O$48)) | P82: =IF(P$4<P$48,0,P54+(P68-P54)/MAX(P$49-P$48,1)*(P$4-P$48)) | Q82: =IF(Q$4<Q$48,0,Q54+(Q68-Q54)/MAX(Q$49-Q$48,1)*(Q$4-Q$48)) | R82: =IF(R$4<R$48,0,R54+(R68-R54)/MAX(R$49-R$48,1)*(R$4-R$48)) | S82: =IF(S$4<S$48,0,S54+(S68-S54)/MAX(S$49-S$48,1)*(S$4-S$48)) | ... AC82: =IF(AC$4<AC$48,0,AC54+(AC68-AC54)/MAX(AC$49-AC$48,1)*(AC$4-AC$48)) | AD82: =PATH(AD$4,AD$48,AD$49,AD54,AD68,TRUE) | AF82: =LOWER(Settings!$C$4)&".mit."&$A82&IF($C82="","","."&$C82&"."&$B82)&IF(INDEX(Variables!$D$5:$D$105,MATCH($A82,Variables!$A$5:$A$105,0))="","","."&INDEX(Variables!$D$5:$D$105,MATCH($A82,Variables!$A$5:$A$105,0)))&"."&AF$5 | AG82: =IF(AG$4<AG$48,0,AG54+(AG68-AG54)/MAX(AG$49-AG$48,1)*(AG$4-AG$48)) | AH82: =IF(AH$4<AH$48,0,AH54+(AH68-AH54)/MAX(AH$49-AH$48,1)*(AH$4-AH$48)) | AI82: =IF(AI$4<AI$48,0,AI54+(AI68-AI54)/MAX(AI$49-AI$48,1)*(AI$4-AI$48)) | AJ82: =IF(AJ$4<AJ$48,0,AJ54+(AJ68-AJ54)/MAX(AJ$49-AJ$48,1)*(AJ$4-AJ$48)) | AK82: =IF(AK$4<AK$48,0,AK54+(AK68-AK54)/MAX(AK$49-AK$48,1)*(AK$4-AK$48)) | AL82: =IF(AL$4<AL$48,0,AL54+(AL68-AL54)/MAX(AL$49-AL$48,1)*(AL$4-AL$48)) | AM82: =IF(AM$4<AM$48,0,AM54+(AM68-AM54)/MAX(AM$49-AM$48,1)*(AM$4-AM$48)) | AN82: =IF(AN$4<AN$48,0,AN54+(AN68-AN54)/MAX(AN$49-AN$48,1)*(AN$4-AN$48)) | ... AX82: =IF(AX$4<AX$48,0,AX54+(AX68-AX54)/MAX(AX$49-AX$48,1)*(AX$4-AX$48)) | AY82: =PATH(AY$4,AY$48,AY$49,AY54,AY68,TRUE)
A83: fpr | B83: nga | C83: ind | H83: =INDEX(Variables!$B$5:$B$105,MATCH($A83,Variables!$A$5:$A$105,0))&IF($C83="",""," | "&INDEX(Mapping!$B$5:$B$26,MATCH($C83,Mapping!$A$5:$A$26,0))&" | "&INDEX(Mapping!$B$30:$B$41,MATCH($B83,Mapping!$A$30:$A$41,0))) | I83: =INDEX(Variables!$C$5:$C$105,MATCH($A83,Variables!$A$5:$A$105,0)) | J83: =INDEX(Variables!$E$5:$E$105,MATCH($A83,Variables!$A$5:$A$105,0)) | K83: =LOWER(Settings!$C$4)&".mit."&$A83&IF($C83="","","."&$C83&"."&$B83)&IF(INDEX(Variables!$D$5:$D$105,MATCH($A83,Variables!$A$5:$A$105,0))="","","."&INDEX(Variables!$D$5:$D$105,MATCH($A83,Variables!$A$5:$A$105,0)))&"."&K$5 | L83: =IF(L$4<L$48,0,L55+(L69-L55)/MAX(L$49-L$48,1)*(L$4-L$48)) | M83: =IF(M$4<M$48,0,M55+(M69-M55)/MAX(M$49-M$48,1)*(M$4-M$48)) | N83: =IF(N$4<N$48,0,N55+(N69-N55)/MAX(N$49-N$48,1)*(N$4-N$48)) | O83: =IF(O$4<O$48,0,O55+(O69-O55)/MAX(O$49-O$48,1)*(O$4-O$48)) | P83: =IF(P$4<P$48,0,P55+(P69-P55)/MAX(P$49-P$48,1)*(P$4-P$48)) | Q83: =IF(Q$4<Q$48,0,Q55+(Q69-Q55)/MAX(Q$49-Q$48,1)*(Q$4-Q$48)) | R83: =IF(R$4<R$48,0,R55+(R69-R55)/MAX(R$49-R$48,1)*(R$4-R$48)) | S83: =IF(S$4<S$48,0,S55+(S69-S55)/MAX(S$49-S$48,1)*(S$4-S$48)) | ... AC83: =IF(AC$4<AC$48,0,AC55+(AC69-AC55)/MAX(AC$49-AC$48,1)*(AC$4-AC$48)) | AD83: =PATH(AD$4,AD$48,AD$49,AD55,AD69,TRUE) | AF83: =LOWER(Settings!$C$4)&".mit."&$A83&IF($C83="","","."&$C83&"."&$B83)&IF(INDEX(Variables!$D$5:$D$105,MATCH($A83,Variables!$A$5:$A$105,0))="","","."&INDEX(Variables!$D$5:$D$105,MATCH($A83,Variables!$A$5:$A$105,0)))&"."&AF$5 | AG83: =IF(AG$4<AG$48,0,AG55+(AG69-AG55)/MAX(AG$49-AG$48,1)*(AG$4-AG$48)) | AH83: =IF(AH$4<AH$48,0,AH55+(AH69-AH55)/MAX(AH$49-AH$48,1)*(AH$4-AH$48)) | AI83: =IF(AI$4<AI$48,0,AI55+(AI69-AI55)/MAX(AI$49-AI$48,1)*(AI$4-AI$48)) | AJ83: =IF(AJ$4<AJ$48,0,AJ55+(AJ69-AJ55)/MAX(AJ$49-AJ$48,1)*(AJ$4-AJ$48)) | AK83: =IF(AK$4<AK$48,0,AK55+(AK69-AK55)/MAX(AK$49-AK$48,1)*(AK$4-AK$48)) | AL83: =IF(AL$4<AL$48,0,AL55+(AL69-AL55)/MAX(AL$49-AL$48,1)*(AL$4-AL$48)) | AM83: =IF(AM$4<AM$48,0,AM55+(AM69-AM55)/MAX(AM$49-AM$48,1)*(AM$4-AM$48)) | AN83: =IF(AN$4<AN$48,0,AN55+(AN69-AN55)/MAX(AN$49-AN$48,1)*(AN$4-AN$48)) | ... AX83: =IF(AX$4<AX$48,0,AX55+(AX69-AX55)/MAX(AX$49-AX$48,1)*(AX$4-AX$48)) | AY83: =PATH(AY$4,AY$48,AY$49,AY55,AY69,TRUE)
A84: fpr | B84: ecy | C84: res | H84: =INDEX(Variables!$B$5:$B$105,MATCH($A84,Variables!$A$5:$A$105,0))&IF($C84="",""," | "&INDEX(Mapping!$B$5:$B$26,MATCH($C84,Mapping!$A$5:$A$26,0))&" | "&INDEX(Mapping!$B$30:$B$41,MATCH($B84,Mapping!$A$30:$A$41,0))) | I84: =INDEX(Variables!$C$5:$C$105,MATCH($A84,Variables!$A$5:$A$105,0)) | J84: =INDEX(Variables!$E$5:$E$105,MATCH($A84,Variables!$A$5:$A$105,0)) | K84: =LOWER(Settings!$C$4)&".mit."&$A84&IF($C84="","","."&$C84&"."&$B84)&IF(INDEX(Variables!$D$5:$D$105,MATCH($A84,Variables!$A$5:$A$105,0))="","","."&INDEX(Variables!$D$5:$D$105,MATCH($A84,Variables!$A$5:$A$105,0)))&"."&K$5 | L84: =IF(L$4<L$48,0,L56+(L70-L56)/MAX(L$49-L$48,1)*(L$4-L$48)) | M84: =IF(M$4<M$48,0,M56+(M70-M56)/MAX(M$49-M$48,1)*(M$4-M$48)) | N84: =IF(N$4<N$48,0,N56+(N70-N56)/MAX(N$49-N$48,1)*(N$4-N$48)) | O84: =IF(O$4<O$48,0,O56+(O70-O56)/MAX(O$49-O$48,1)*(O$4-O$48)) | P84: =IF(P$4<P$48,0,P56+(P70-P56)/MAX(P$49-P$48,1)*(P$4-P$48)) | Q84: =IF(Q$4<Q$48,0,Q56+(Q70-Q56)/MAX(Q$49-Q$48,1)*(Q$4-Q$48)) | R84: =IF(R$4<R$48,0,R56+(R70-R56)/MAX(R$49-R$48,1)*(R$4-R$48)) | S84: =IF(S$4<S$48,0,S56+(S70-S56)/MAX(S$49-S$48,1)*(S$4-S$48)) | ... AC84: =IF(AC$4<AC$48,0,AC56+(AC70-AC56)/MAX(AC$49-AC$48,1)*(AC$4-AC$48)) | AD84: =PATH(AD$4,AD$48,AD$49,AD56,AD70,TRUE) | AF84: =LOWER(Settings!$C$4)&".mit."&$A84&IF($C84="","","."&$C84&"."&$B84)&IF(INDEX(Variables!$D$5:$D$105,MATCH($A84,Variables!$A$5:$A$105,0))="","","."&INDEX(Variables!$D$5:$D$105,MATCH($A84,Variables!$A$5:$A$105,0)))&"."&AF$5 | AG84: =IF(AG$4<AG$48,0,AG56+(AG70-AG56)/MAX(AG$49-AG$48,1)*(AG$4-AG$48)) | AH84: =IF(AH$4<AH$48,0,AH56+(AH70-AH56)/MAX(AH$49-AH$48,1)*(AH$4-AH$48)) | AI84: =IF(AI$4<AI$48,0,AI56+(AI70-AI56)/MAX(AI$49-AI$48,1)*(AI$4-AI$48)) | AJ84: =IF(AJ$4<AJ$48,0,AJ56+(AJ70-AJ56)/MAX(AJ$49-AJ$48,1)*(AJ$4-AJ$48)) | AK84: =IF(AK$4<AK$48,0,AK56+(AK70-AK56)/MAX(AK$49-AK$48,1)*(AK$4-AK$48)) | AL84: =IF(AL$4<AL$48,0,AL56+(AL70-AL56)/MAX(AL$49-AL$48,1)*(AL$4-AL$48)) | AM84: =IF(AM$4<AM$48,0,AM56+(AM70-AM56)/MAX(AM$49-AM$48,1)*(AM$4-AM$48)) | AN84: =IF(AN$4<AN$48,0,AN56+(AN70-AN56)/MAX(AN$49-AN$48,1)*(AN$4-AN$48)) | ... AX84: =IF(AX$4<AX$48,0,AX56+(AX70-AX56)/MAX(AX$49-AX$48,1)*(AX$4-AX$48)) | AY84: =PATH(AY$4,AY$48,AY$49,AY56,AY70,TRUE)
A85: fpr | B85: ecy | C85: ind | H85: =INDEX(Variables!$B$5:$B$105,MATCH($A85,Variables!$A$5:$A$105,0))&IF($C85="",""," | "&INDEX(Mapping!$B$5:$B$26,MATCH($C85,Mapping!$A$5:$A$26,0))&" | "&INDEX(Mapping!$B$30:$B$41,MATCH($B85,Mapping!$A$30:$A$41,0))) | I85: =INDEX(Variables!$C$5:$C$105,MATCH($A85,Variables!$A$5:$A$105,0)) | J85: =INDEX(Variables!$E$5:$E$105,MATCH($A85,Variables!$A$5:$A$105,0)) | K85: =LOWER(Settings!$C$4)&".mit."&$A85&IF($C85="","","."&$C85&"."&$B85)&IF(INDEX(Variables!$D$5:$D$105,MATCH($A85,Variables!$A$5:$A$105,0))="","","."&INDEX(Variables!$D$5:$D$105,MATCH($A85,Variables!$A$5:$A$105,0)))&"."&K$5 | L85: =IF(L$4<L$48,0,L57+(L71-L57)/MAX(L$49-L$48,1)*(L$4-L$48)) | M85: =IF(M$4<M$48,0,M57+(M71-M57)/MAX(M$49-M$48,1)*(M$4-M$48)) | N85: =IF(N$4<N$48,0,N57+(N71-N57)/MAX(N$49-N$48,1)*(N$4-N$48)) | O85: =IF(O$4<O$48,0,O57+(O71-O57)/MAX(O$49-O$48,1)*(O$4-O$48)) | P85: =IF(P$4<P$48,0,P57+(P71-P57)/MAX(P$49-P$48,1)*(P$4-P$48)) | Q85: =IF(Q$4<Q$48,0,Q57+(Q71-Q57)/MAX(Q$49-Q$48,1)*(Q$4-Q$48)) | R85: =IF(R$4<R$48,0,R57+(R71-R57)/MAX(R$49-R$48,1)*(R$4-R$48)) | S85: =IF(S$4<S$48,0,S57+(S71-S57)/MAX(S$49-S$48,1)*(S$4-S$48)) | ... AC85: =IF(AC$4<AC$48,0,AC57+(AC71-AC57)/MAX(AC$49-AC$48,1)*(AC$4-AC$48)) | AD85: =PATH(AD$4,AD$48,AD$49,AD57,AD71,TRUE) | AF85: =LOWER(Settings!$C$4)&".mit."&$A85&IF($C85="","","."&$C85&"."&$B85)&IF(INDEX(Variables!$D$5:$D$105,MATCH($A85,Variables!$A$5:$A$105,0))="","","."&INDEX(Variables!$D$5:$D$105,MATCH($A85,Variables!$A$5:$A$105,0)))&"."&AF$5 | AG85: =IF(AG$4<AG$48,0,AG57+(AG71-AG57)/MAX(AG$49-AG$48,1)*(AG$4-AG$48)) | AH85: =IF(AH$4<AH$48,0,AH57+(AH71-AH57)/MAX(AH$49-AH$48,1)*(AH$4-AH$48)) | AI85: =IF(AI$4<AI$48,0,AI57+(AI71-AI57)/MAX(AI$49-AI$48,1)*(AI$4-AI$48)) | AJ85: =IF(AJ$4<AJ$48,0,AJ57+(AJ71-AJ57)/MAX(AJ$49-AJ$48,1)*(AJ$4-AJ$48)) | AK85: =IF(AK$4<AK$48,0,AK57+(AK71-AK57)/MAX(AK$49-AK$48,1)*(AK$4-AK$48)) | AL85: =IF(AL$4<AL$48,0,AL57+(AL71-AL57)/MAX(AL$49-AL$48,1)*(AL$4-AL$48)) | AM85: =IF(AM$4<AM$48,0,AM57+(AM71-AM57)/MAX(AM$49-AM$48,1)*(AM$4-AM$48)) | AN85: =IF(AN$4<AN$48,0,AN57+(AN71-AN57)/MAX(AN$49-AN$48,1)*(AN$4-AN$48)) | ... AX85: =IF(AX$4<AX$48,0,AX57+(AX71-AX57)/MAX(AX$49-AX$48,1)*(AX$4-AX$48)) | AY85: =PATH(AY$4,AY$48,AY$49,AY57,AY71,TRUE)
A86: fpr | B86: gso | C86: all | H86: =INDEX(Variables!$B$5:$B$105,MATCH($A86,Variables!$A$5:$A$105,0))&IF($C86="",""," | "&INDEX(Mapping!$B$5:$B$26,MATCH($C86,Mapping!$A$5:$A$26,0))&" | "&INDEX(Mapping!$B$30:$B$41,MATCH($B86,Mapping!$A$30:$A$41,0))) | I86: =INDEX(Variables!$C$5:$C$105,MATCH($A86,Variables!$A$5:$A$105,0)) | J86: =INDEX(Variables!$E$5:$E$105,MATCH($A86,Variables!$A$5:$A$105,0)) | K86: =LOWER(Settings!$C$4)&".mit."&$A86&IF($C86="","","."&$C86&"."&$B86)&IF(INDEX(Variables!$D$5:$D$105,MATCH($A86,Variables!$A$5:$A$105,0))="","","."&INDEX(Variables!$D$5:$D$105,MATCH($A86,Variables!$A$5:$A$105,0)))&"."&K$5 | L86: =IF(L$4<L$48,0,L58+(L72-L58)/MAX(L$49-L$48,1)*(L$4-L$48)) | M86: =IF(M$4<M$48,0,M58+(M72-M58)/MAX(M$49-M$48,1)*(M$4-M$48)) | N86: =IF(N$4<N$48,0,N58+(N72-N58)/MAX(N$49-N$48,1)*(N$4-N$48)) | O86: =IF(O$4<O$48,0,O58+(O72-O58)/MAX(O$49-O$48,1)*(O$4-O$48)) | P86: =IF(P$4<P$48,0,P58+(P72-P58)/MAX(P$49-P$48,1)*(P$4-P$48)) | Q86: =IF(Q$4<Q$48,0,Q58+(Q72-Q58)/MAX(Q$49-Q$48,1)*(Q$4-Q$48)) | R86: =IF(R$4<R$48,0,R58+(R72-R58)/MAX(R$49-R$48,1)*(R$4-R$48)) | S86: =IF(S$4<S$48,0,S58+(S72-S58)/MAX(S$49-S$48,1)*(S$4-S$48)) | ... AC86: =IF(AC$4<AC$48,0,AC58+(AC72-AC58)/MAX(AC$49-AC$48,1)*(AC$4-AC$48)) | AD86: =PATH(AD$4,AD$48,AD$49,AD58,AD72,TRUE) | AF86: =LOWER(Settings!$C$4)&".mit."&$A86&IF($C86="","","."&$C86&"."&$B86)&IF(INDEX(Variables!$D$5:$D$105,MATCH($A86,Variables!$A$5:$A$105,0))="","","."&INDEX(Variables!$D$5:$D$105,MATCH($A86,Variables!$A$5:$A$105,0)))&"."&AF$5 | AG86: =IF(AG$4<AG$48,0,AG58+(AG72-AG58)/MAX(AG$49-AG$48,1)*(AG$4-AG$48)) | AH86: =IF(AH$4<AH$48,0,AH58+(AH72-AH58)/MAX(AH$49-AH$48,1)*(AH$4-AH$48)) | AI86: =IF(AI$4<AI$48,0,AI58+(AI72-AI58)/MAX(AI$49-AI$48,1)*(AI$4-AI$48)) | AJ86: =IF(AJ$4<AJ$48,0,AJ58+(AJ72-AJ58)/MAX(AJ$49-AJ$48,1)*(AJ$4-AJ$48)) | AK86: =IF(AK$4<AK$48,0,AK58+(AK72-AK58)/MAX(AK$49-AK$48,1)*(AK$4-AK$48)) | AL86: =IF(AL$4<AL$48,0,AL58+(AL72-AL58)/MAX(AL$49-AL$48,1)*(AL$4-AL$48)) | AM86: =IF(AM$4<AM$48,0,AM58+(AM72-AM58)/MAX(AM$49-AM$48,1)*(AM$4-AM$48)) | AN86: =IF(AN$4<AN$48,0,AN58+(AN72-AN58)/MAX(AN$49-AN$48,1)*(AN$4-AN$48)) | ... AX86: =IF(AX$4<AX$48,0,AX58+(AX72-AX58)/MAX(AX$49-AX$48,1)*(AX$4-AX$48)) | AY86: =PATH(AY$4,AY$48,AY$49,AY58,AY72,TRUE)
A87: fpr | B87: die | C87: all | H87: =INDEX(Variables!$B$5:$B$105,MATCH($A87,Variables!$A$5:$A$105,0))&IF($C87="",""," | "&INDEX(Mapping!$B$5:$B$26,MATCH($C87,Mapping!$A$5:$A$26,0))&" | "&INDEX(Mapping!$B$30:$B$41,MATCH($B87,Mapping!$A$30:$A$41,0))) | I87: =INDEX(Variables!$C$5:$C$105,MATCH($A87,Variables!$A$5:$A$105,0)) | J87: =INDEX(Variables!$E$5:$E$105,MATCH($A87,Variables!$A$5:$A$105,0)) | K87: =LOWER(Settings!$C$4)&".mit."&$A87&IF($C87="","","."&$C87&"."&$B87)&IF(INDEX(Variables!$D$5:$D$105,MATCH($A87,Variables!$A$5:$A$105,0))="","","."&INDEX(Variables!$D$5:$D$105,MATCH($A87,Variables!$A$5:$A$105,0)))&"."&K$5 | L87: =IF(L$4<L$48,0,L59+(L73-L59)/MAX(L$49-L$48,1)*(L$4-L$48)) | M87: =IF(M$4<M$48,0,M59+(M73-M59)/MAX(M$49-M$48,1)*(M$4-M$48)) | N87: =IF(N$4<N$48,0,N59+(N73-N59)/MAX(N$49-N$48,1)*(N$4-N$48)) | O87: =IF(O$4<O$48,0,O59+(O73-O59)/MAX(O$49-O$48,1)*(O$4-O$48)) | P87: =IF(P$4<P$48,0,P59+(P73-P59)/MAX(P$49-P$48,1)*(P$4-P$48)) | Q87: =IF(Q$4<Q$48,0,Q59+(Q73-Q59)/MAX(Q$49-Q$48,1)*(Q$4-Q$48)) | R87: =IF(R$4<R$48,0,R59+(R73-R59)/MAX(R$49-R$48,1)*(R$4-R$48)) | S87: =IF(S$4<S$48,0,S59+(S73-S59)/MAX(S$49-S$48,1)*(S$4-S$48)) | ... AC87: =IF(AC$4<AC$48,0,AC59+(AC73-AC59)/MAX(AC$49-AC$48,1)*(AC$4-AC$48)) | AD87: =PATH(AD$4,AD$48,AD$49,AD59,AD73,TRUE) | AF87: =LOWER(Settings!$C$4)&".mit."&$A87&IF($C87="","","."&$C87&"."&$B87)&IF(INDEX(Variables!$D$5:$D$105,MATCH($A87,Variables!$A$5:$A$105,0))="","","."&INDEX(Variables!$D$5:$D$105,MATCH($A87,Variables!$A$5:$A$105,0)))&"."&AF$5 | AG87: =IF(AG$4<AG$48,0,AG59+(AG73-AG59)/MAX(AG$49-AG$48,1)*(AG$4-AG$48)) | AH87: =IF(AH$4<AH$48,0,AH59+(AH73-AH59)/MAX(AH$49-AH$48,1)*(AH$4-AH$48)) | AI87: =IF(AI$4<AI$48,0,AI59+(AI73-AI59)/MAX(AI$49-AI$48,1)*(AI$4-AI$48)) | AJ87: =IF(AJ$4<AJ$48,0,AJ59+(AJ73-AJ59)/MAX(AJ$49-AJ$48,1)*(AJ$4-AJ$48)) | AK87: =IF(AK$4<AK$48,0,AK59+(AK73-AK59)/MAX(AK$49-AK$48,1)*(AK$4-AK$48)) | AL87: =IF(AL$4<AL$48,0,AL59+(AL73-AL59)/MAX(AL$49-AL$48,1)*(AL$4-AL$48)) | AM87: =IF(AM$4<AM$48,0,AM59+(AM73-AM59)/MAX(AM$49-AM$48,1)*(AM$4-AM$48)) | AN87: =IF(AN$4<AN$48,0,AN59+(AN73-AN59)/MAX(AN$49-AN$48,1)*(AN$4-AN$48)) | ... AX87: =IF(AX$4<AX$48,0,AX59+(AX73-AX59)/MAX(AX$49-AX$48,1)*(AX$4-AX$48)) | AY87: =PATH(AY$4,AY$48,AY$49,AY59,AY73,TRUE)
A88: fpr | B88: lpg | C88: all | H88: =INDEX(Variables!$B$5:$B$105,MATCH($A88,Variables!$A$5:$A$105,0))&IF($C88="",""," | "&INDEX(Mapping!$B$5:$B$26,MATCH($C88,Mapping!$A$5:$A$26,0))&" | "&INDEX(Mapping!$B$30:$B$41,MATCH($B88,Mapping!$A$30:$A$41,0))) | I88: =INDEX(Variables!$C$5:$C$105,MATCH($A88,Variables!$A$5:$A$105,0)) | J88: =INDEX(Variables!$E$5:$E$105,MATCH($A88,Variables!$A$5:$A$105,0)) | K88: =LOWER(Settings!$C$4)&".mit."&$A88&IF($C88="","","."&$C88&"."&$B88)&IF(INDEX(Variables!$D$5:$D$105,MATCH($A88,Variables!$A$5:$A$105,0))="","","."&INDEX(Variables!$D$5:$D$105,MATCH($A88,Variables!$A$5:$A$105,0)))&"."&K$5 | L88: =IF(L$4<L$48,0,L60+(L74-L60)/MAX(L$49-L$48,1)*(L$4-L$48)) | M88: =IF(M$4<M$48,0,M60+(M74-M60)/MAX(M$49-M$48,1)*(M$4-M$48)) | N88: =IF(N$4<N$48,0,N60+(N74-N60)/MAX(N$49-N$48,1)*(N$4-N$48)) | O88: =IF(O$4<O$48,0,O60+(O74-O60)/MAX(O$49-O$48,1)*(O$4-O$48)) | P88: =IF(P$4<P$48,0,P60+(P74-P60)/MAX(P$49-P$48,1)*(P$4-P$48)) | Q88: =IF(Q$4<Q$48,0,Q60+(Q74-Q60)/MAX(Q$49-Q$48,1)*(Q$4-Q$48)) | R88: =IF(R$4<R$48,0,R60+(R74-R60)/MAX(R$49-R$48,1)*(R$4-R$48)) | S88: =IF(S$4<S$48,0,S60+(S74-S60)/MAX(S$49-S$48,1)*(S$4-S$48)) | ... AC88: =IF(AC$4<AC$48,0,AC60+(AC74-AC60)/MAX(AC$49-AC$48,1)*(AC$4-AC$48)) | AD88: =PATH(AD$4,AD$48,AD$49,AD60,AD74,TRUE) | AF88: =LOWER(Settings!$C$4)&".mit."&$A88&IF($C88="","","."&$C88&"."&$B88)&IF(INDEX(Variables!$D$5:$D$105,MATCH($A88,Variables!$A$5:$A$105,0))="","","."&INDEX(Variables!$D$5:$D$105,MATCH($A88,Variables!$A$5:$A$105,0)))&"."&AF$5 | AG88: =IF(AG$4<AG$48,0,AG60+(AG74-AG60)/MAX(AG$49-AG$48,1)*(AG$4-AG$48)) | AH88: =IF(AH$4<AH$48,0,AH60+(AH74-AH60)/MAX(AH$49-AH$48,1)*(AH$4-AH$48)) | AI88: =IF(AI$4<AI$48,0,AI60+(AI74-AI60)/MAX(AI$49-AI$48,1)*(AI$4-AI$48)) | AJ88: =IF(AJ$4<AJ$48,0,AJ60+(AJ74-AJ60)/MAX(AJ$49-AJ$48,1)*(AJ$4-AJ$48)) | AK88: =IF(AK$4<AK$48,0,AK60+(AK74-AK60)/MAX(AK$49-AK$48,1)*(AK$4-AK$48)) | AL88: =IF(AL$4<AL$48,0,AL60+(AL74-AL60)/MAX(AL$49-AL$48,1)*(AL$4-AL$48)) | AM88: =IF(AM$4<AM$48,0,AM60+(AM74-AM60)/MAX(AM$49-AM$48,1)*(AM$4-AM$48)) | AN88: =IF(AN$4<AN$48,0,AN60+(AN74-AN60)/MAX(AN$49-AN$48,1)*(AN$4-AN$48)) | ... AX88: =IF(AX$4<AX$48,0,AX60+(AX74-AX60)/MAX(AX$49-AX$48,1)*(AX$4-AX$48)) | AY88: =PATH(AY$4,AY$48,AY$49,AY60,AY74,TRUE)
A89: fpr | B89: ker | C89: all | H89: =INDEX(Variables!$B$5:$B$105,MATCH($A89,Variables!$A$5:$A$105,0))&IF($C89="",""," | "&INDEX(Mapping!$B$5:$B$26,MATCH($C89,Mapping!$A$5:$A$26,0))&" | "&INDEX(Mapping!$B$30:$B$41,MATCH($B89,Mapping!$A$30:$A$41,0))) | I89: =INDEX(Variables!$C$5:$C$105,MATCH($A89,Variables!$A$5:$A$105,0)) | J89: =INDEX(Variables!$E$5:$E$105,MATCH($A89,Variables!$A$5:$A$105,0)) | K89: =LOWER(Settings!$C$4)&".mit."&$A89&IF($C89="","","."&$C89&"."&$B89)&IF(INDEX(Variables!$D$5:$D$105,MATCH($A89,Variables!$A$5:$A$105,0))="","","."&INDEX(Variables!$D$5:$D$105,MATCH($A89,Variables!$A$5:$A$105,0)))&"."&K$5 | L89: =IF(L$4<L$48,0,L61+(L75-L61)/MAX(L$49-L$48,1)*(L$4-L$48)) | M89: =IF(M$4<M$48,0,M61+(M75-M61)/MAX(M$49-M$48,1)*(M$4-M$48)) | N89: =IF(N$4<N$48,0,N61+(N75-N61)/MAX(N$49-N$48,1)*(N$4-N$48)) | O89: =IF(O$4<O$48,0,O61+(O75-O61)/MAX(O$49-O$48,1)*(O$4-O$48)) | P89: =IF(P$4<P$48,0,P61+(P75-P61)/MAX(P$49-P$48,1)*(P$4-P$48)) | Q89: =IF(Q$4<Q$48,0,Q61+(Q75-Q61)/MAX(Q$49-Q$48,1)*(Q$4-Q$48)) | R89: =IF(R$4<R$48,0,R61+(R75-R61)/MAX(R$49-R$48,1)*(R$4-R$48)) | S89: =IF(S$4<S$48,0,S61+(S75-S61)/MAX(S$49-S$48,1)*(S$4-S$48)) | ... AC89: =IF(AC$4<AC$48,0,AC61+(AC75-AC61)/MAX(AC$49-AC$48,1)*(AC$4-AC$48)) | AD89: =PATH(AD$4,AD$48,AD$49,AD61,AD75,TRUE) | AF89: =LOWER(Settings!$C$4)&".mit."&$A89&IF($C89="","","."&$C89&"."&$B89)&IF(INDEX(Variables!$D$5:$D$105,MATCH($A89,Variables!$A$5:$A$105,0))="","","."&INDEX(Variables!$D$5:$D$105,MATCH($A89,Variables!$A$5:$A$105,0)))&"."&AF$5 | AG89: =IF(AG$4<AG$48,0,AG61+(AG75-AG61)/MAX(AG$49-AG$48,1)*(AG$4-AG$48)) | AH89: =IF(AH$4<AH$48,0,AH61+(AH75-AH61)/MAX(AH$49-AH$48,1)*(AH$4-AH$48)) | AI89: =IF(AI$4<AI$48,0,AI61+(AI75-AI61)/MAX(AI$49-AI$48,1)*(AI$4-AI$48)) | AJ89: =IF(AJ$4<AJ$48,0,AJ61+(AJ75-AJ61)/MAX(AJ$49-AJ$48,1)*(AJ$4-AJ$48)) | AK89: =IF(AK$4<AK$48,0,AK61+(AK75-AK61)/MAX(AK$49-AK$48,1)*(AK$4-AK$48)) | AL89: =IF(AL$4<AL$48,0,AL61+(AL75-AL61)/MAX(AL$49-AL$48,1)*(AL$4-AL$48)) | AM89: =IF(AM$4<AM$48,0,AM61+(AM75-AM61)/MAX(AM$49-AM$48,1)*(AM$4-AM$48)) | AN89: =IF(AN$4<AN$48,0,AN61+(AN75-AN61)/MAX(AN$49-AN$48,1)*(AN$4-AN$48)) | ... AX89: =IF(AX$4<AX$48,0,AX61+(AX75-AX61)/MAX(AX$49-AX$48,1)*(AX$4-AX$48)) | AY89: =PATH(AY$4,AY$48,AY$49,AY61,AY75,TRUE)
... A91: fpr | B91: bio | C91: all | H91: =INDEX(Variables!$B$5:$B$105,MATCH($A91,Variables!$A$5:$A$105,0))&IF($C91="",""," | "&INDEX(Mapping!$B$5:$B$26,MATCH($C91,Mapping!$A$5:$A$26,0))&" | "&INDEX(Mapping!$B$30:$B$41,MATCH($B91,Mapping!$A$30:$A$41,0))) | I91: =INDEX(Variables!$C$5:$C$105,MATCH($A91,Variables!$A$5:$A$105,0)) | J91: =INDEX(Variables!$E$5:$E$105,MATCH($A91,Variables!$A$5:$A$105,0)) | K91: =LOWER(Settings!$C$4)&".mit."&$A91&IF($C91="","","."&$C91&"."&$B91)&IF(INDEX(Variables!$D$5:$D$105,MATCH($A91,Variables!$A$5:$A$105,0))="","","."&INDEX(Variables!$D$5:$D$105,MATCH($A91,Variables!$A$5:$A$105,0)))&"."&K$5 | L91: =IF(L$4<L$48,0,L63+(L77-L63)/MAX(L$49-L$48,1)*(L$4-L$48)) | M91: =IF(M$4<M$48,0,M63+(M77-M63)/MAX(M$49-M$48,1)*(M$4-M$48)) | N91: =IF(N$4<N$48,0,N63+(N77-N63)/MAX(N$49-N$48,1)*(N$4-N$48)) | O91: =IF(O$4<O$48,0,O63+(O77-O63)/MAX(O$49-O$48,1)*(O$4-O$48)) | P91: =IF(P$4<P$48,0,P63+(P77-P63)/MAX(P$49-P$48,1)*(P$4-P$48)) | Q91: =IF(Q$4<Q$48,0,Q63+(Q77-Q63)/MAX(Q$49-Q$48,1)*(Q$4-Q$48)) | R91: =IF(R$4<R$48,0,R63+(R77-R63)/MAX(R$49-R$48,1)*(R$4-R$48)) | S91: =IF(S$4<S$48,0,S63+(S77-S63)/MAX(S$49-S$48,1)*(S$4-S$48)) | ... AC91: =IF(AC$4<AC$48,0,AC63+(AC77-AC63)/MAX(AC$49-AC$48,1)*(AC$4-AC$48)) | AD91: =PATH(AD$4,AD$48,AD$49,AD63,AD77,TRUE) | AF91: =LOWER(Settings!$C$4)&".mit."&$A91&IF($C91="","","."&$C91&"."&$B91)&IF(INDEX(Variables!$D$5:$D$105,MATCH($A91,Variables!$A$5:$A$105,0))="","","."&INDEX(Variables!$D$5:$D$105,MATCH($A91,Variables!$A$5:$A$105,0)))&"."&AF$5 | AG91: =IF(AG$4<AG$48,0,AG63+(AG77-AG63)/MAX(AG$49-AG$48,1)*(AG$4-AG$48)) | AH91: =IF(AH$4<AH$48,0,AH63+(AH77-AH63)/MAX(AH$49-AH$48,1)*(AH$4-AH$48)) | AI91: =IF(AI$4<AI$48,0,AI63+(AI77-AI63)/MAX(AI$49-AI$48,1)*(AI$4-AI$48)) | AJ91: =IF(AJ$4<AJ$48,0,AJ63+(AJ77-AJ63)/MAX(AJ$49-AJ$48,1)*(AJ$4-AJ$48)) | AK91: =IF(AK$4<AK$48,0,AK63+(AK77-AK63)/MAX(AK$49-AK$48,1)*(AK$4-AK$48)) | AL91: =IF(AL$4<AL$48,0,AL63+(AL77-AL63)/MAX(AL$49-AL$48,1)*(AL$4-AL$48)) | AM91: =IF(AM$4<AM$48,0,AM63+(AM77-AM63)/MAX(AM$49-AM$48,1)*(AM$4-AM$48)) | AN91: =IF(AN$4<AN$48,0,AN63+(AN77-AN63)/MAX(AN$49-AN$48,1)*(AN$4-AN$48)) | ... AX91: =IF(AX$4<AX$48,0,AX63+(AX77-AX63)/MAX(AX$49-AX$48,1)*(AX$4-AX$48)) | AY91: =PATH(AY$4,AY$48,AY$49,AY63,AY77,TRUE)
H92: New ETS (MTInputs rows 84-97: cap relative to baseline, years, price override, volatility; replaces the carbon tax in covered sectors)
A93: D_NewETS | D93: 84 | H93: =INDEX(Variables!$B$5:$B$105,MATCH($A93,Variables!$A$5:$A$105,0))&IF($C93="",""," | "&INDEX(Mapping!$B$5:$B$26,MATCH($C93,Mapping!$A$5:$A$26,0))&" | "&INDEX(Mapping!$B$30:$B$41,MATCH($B93,Mapping!$A$30:$A$41,0))) | I93: =INDEX(Variables!$C$5:$C$105,MATCH($A93,Variables!$A$5:$A$105,0)) | J93: =INDEX(Variables!$E$5:$E$105,MATCH($A93,Variables!$A$5:$A$105,0)) | K93: =LOWER(Settings!$C$4)&".mit."&$A93&IF($C93="","","."&$C93&"."&$B93)&IF(INDEX(Variables!$D$5:$D$105,MATCH($A93,Variables!$A$5:$A$105,0))="","","."&INDEX(Variables!$D$5:$D$105,MATCH($A93,Variables!$A$5:$A$105,0)))&"."&K$5 | L93: =INDEX(MTInputs!$J$1:$AZ$415,$D93,MATCH(L$5,MTInputs!$J$5:$AZ$5,0)) | M93: =INDEX(MTInputs!$J$1:$AZ$415,$D93,MATCH(M$5,MTInputs!$J$5:$AZ$5,0)) | N93: =INDEX(MTInputs!$J$1:$AZ$415,$D93,MATCH(N$5,MTInputs!$J$5:$AZ$5,0)) | O93: =INDEX(MTInputs!$J$1:$AZ$415,$D93,MATCH(O$5,MTInputs!$J$5:$AZ$5,0)) | P93: =INDEX(MTInputs!$J$1:$AZ$415,$D93,MATCH(P$5,MTInputs!$J$5:$AZ$5,0)) | Q93: =INDEX(MTInputs!$J$1:$AZ$415,$D93,MATCH(Q$5,MTInputs!$J$5:$AZ$5,0)) | R93: =INDEX(MTInputs!$J$1:$AZ$415,$D93,MATCH(R$5,MTInputs!$J$5:$AZ$5,0)) | S93: =INDEX(MTInputs!$J$1:$AZ$415,$D93,MATCH(S$5,MTInputs!$J$5:$AZ$5,0)) | ... AD93: =INDEX(MTInputs!$J$1:$AZ$415,$D93,MATCH(AD$5,MTInputs!$J$5:$AZ$5,0)) | AF93: =LOWER(Settings!$C$4)&".mit."&$A93&IF($C93="","","."&$C93&"."&$B93)&IF(INDEX(Variables!$D$5:$D$105,MATCH($A93,Variables!$A$5:$A$105,0))="","","."&INDEX(Variables!$D$5:$D$105,MATCH($A93,Variables!$A$5:$A$105,0)))&"."&AF$5 | AG93: =INDEX(MTInputs!$J$1:$AZ$415,$D93,MATCH(AG$5,MTInputs!$J$5:$AZ$5,0)) | AH93: =INDEX(MTInputs!$J$1:$AZ$415,$D93,MATCH(AH$5,MTInputs!$J$5:$AZ$5,0)) | AI93: =INDEX(MTInputs!$J$1:$AZ$415,$D93,MATCH(AI$5,MTInputs!$J$5:$AZ$5,0)) | AJ93: =INDEX(MTInputs!$J$1:$AZ$415,$D93,MATCH(AJ$5,MTInputs!$J$5:$AZ$5,0)) | AK93: =INDEX(MTInputs!$J$1:$AZ$415,$D93,MATCH(AK$5,MTInputs!$J$5:$AZ$5,0)) | AL93: =INDEX(MTInputs!$J$1:$AZ$415,$D93,MATCH(AL$5,MTInputs!$J$5:$AZ$5,0)) | AM93: =INDEX(MTInputs!$J$1:$AZ$415,$D93,MATCH(AM$5,MTInputs!$J$5:$AZ$5,0)) | AN93: =INDEX(MTInputs!$J$1:$AZ$415,$D93,MATCH(AN$5,MTInputs!$J$5:$AZ$5,0)) | ... AY93: =INDEX(MTInputs!$J$1:$AZ$415,$D93,MATCH(AY$5,MTInputs!$J$5:$AZ$5,0))
A94: D_ETSChangeRelStart | D94: 85 | H94: =INDEX(Variables!$B$5:$B$105,MATCH($A94,Variables!$A$5:$A$105,0))&IF($C94="",""," | "&INDEX(Mapping!$B$5:$B$26,MATCH($C94,Mapping!$A$5:$A$26,0))&" | "&INDEX(Mapping!$B$30:$B$41,MATCH($B94,Mapping!$A$30:$A$41,0))) | I94: =INDEX(Variables!$C$5:$C$105,MATCH($A94,Variables!$A$5:$A$105,0)) | J94: =INDEX(Variables!$E$5:$E$105,MATCH($A94,Variables!$A$5:$A$105,0)) | K94: =LOWER(Settings!$C$4)&".mit."&$A94&IF($C94="","","."&$C94&"."&$B94)&IF(INDEX(Variables!$D$5:$D$105,MATCH($A94,Variables!$A$5:$A$105,0))="","","."&INDEX(Variables!$D$5:$D$105,MATCH($A94,Variables!$A$5:$A$105,0)))&"."&K$5 | L94: =INDEX(MTInputs!$J$1:$AZ$415,$D94,MATCH(L$5,MTInputs!$J$5:$AZ$5,0)) | M94: =INDEX(MTInputs!$J$1:$AZ$415,$D94,MATCH(M$5,MTInputs!$J$5:$AZ$5,0)) | N94: =INDEX(MTInputs!$J$1:$AZ$415,$D94,MATCH(N$5,MTInputs!$J$5:$AZ$5,0)) | O94: =INDEX(MTInputs!$J$1:$AZ$415,$D94,MATCH(O$5,MTInputs!$J$5:$AZ$5,0)) | P94: =INDEX(MTInputs!$J$1:$AZ$415,$D94,MATCH(P$5,MTInputs!$J$5:$AZ$5,0)) | Q94: =INDEX(MTInputs!$J$1:$AZ$415,$D94,MATCH(Q$5,MTInputs!$J$5:$AZ$5,0)) | R94: =INDEX(MTInputs!$J$1:$AZ$415,$D94,MATCH(R$5,MTInputs!$J$5:$AZ$5,0)) | S94: =INDEX(MTInputs!$J$1:$AZ$415,$D94,MATCH(S$5,MTInputs!$J$5:$AZ$5,0)) | ... AD94: =INDEX(MTInputs!$J$1:$AZ$415,$D94,MATCH(AD$5,MTInputs!$J$5:$AZ$5,0)) | AF94: =LOWER(Settings!$C$4)&".mit."&$A94&IF($C94="","","."&$C94&"."&$B94)&IF(INDEX(Variables!$D$5:$D$105,MATCH($A94,Variables!$A$5:$A$105,0))="","","."&INDEX(Variables!$D$5:$D$105,MATCH($A94,Variables!$A$5:$A$105,0)))&"."&AF$5 | AG94: =INDEX(MTInputs!$J$1:$AZ$415,$D94,MATCH(AG$5,MTInputs!$J$5:$AZ$5,0)) | AH94: =INDEX(MTInputs!$J$1:$AZ$415,$D94,MATCH(AH$5,MTInputs!$J$5:$AZ$5,0)) | AI94: =INDEX(MTInputs!$J$1:$AZ$415,$D94,MATCH(AI$5,MTInputs!$J$5:$AZ$5,0)) | AJ94: =INDEX(MTInputs!$J$1:$AZ$415,$D94,MATCH(AJ$5,MTInputs!$J$5:$AZ$5,0)) | AK94: =INDEX(MTInputs!$J$1:$AZ$415,$D94,MATCH(AK$5,MTInputs!$J$5:$AZ$5,0)) | AL94: =INDEX(MTInputs!$J$1:$AZ$415,$D94,MATCH(AL$5,MTInputs!$J$5:$AZ$5,0)) | AM94: =INDEX(MTInputs!$J$1:$AZ$415,$D94,MATCH(AM$5,MTInputs!$J$5:$AZ$5,0)) | AN94: =INDEX(MTInputs!$J$1:$AZ$415,$D94,MATCH(AN$5,MTInputs!$J$5:$AZ$5,0)) | ... AY94: =INDEX(MTInputs!$J$1:$AZ$415,$D94,MATCH(AY$5,MTInputs!$J$5:$AZ$5,0))
A95: D_ETSChangeRelTarget | D95: 86 | H95: =INDEX(Variables!$B$5:$B$105,MATCH($A95,Variables!$A$5:$A$105,0))&IF($C95="",""," | "&INDEX(Mapping!$B$5:$B$26,MATCH($C95,Mapping!$A$5:$A$26,0))&" | "&INDEX(Mapping!$B$30:$B$41,MATCH($B95,Mapping!$A$30:$A$41,0))) | I95: =INDEX(Variables!$C$5:$C$105,MATCH($A95,Variables!$A$5:$A$105,0)) | J95: =INDEX(Variables!$E$5:$E$105,MATCH($A95,Variables!$A$5:$A$105,0)) | K95: =LOWER(Settings!$C$4)&".mit."&$A95&IF($C95="","","."&$C95&"."&$B95)&IF(INDEX(Variables!$D$5:$D$105,MATCH($A95,Variables!$A$5:$A$105,0))="","","."&INDEX(Variables!$D$5:$D$105,MATCH($A95,Variables!$A$5:$A$105,0)))&"."&K$5 | L95: =INDEX(MTInputs!$J$1:$AZ$415,$D95,MATCH(L$5,MTInputs!$J$5:$AZ$5,0)) | M95: =INDEX(MTInputs!$J$1:$AZ$415,$D95,MATCH(M$5,MTInputs!$J$5:$AZ$5,0)) | N95: =INDEX(MTInputs!$J$1:$AZ$415,$D95,MATCH(N$5,MTInputs!$J$5:$AZ$5,0)) | O95: =INDEX(MTInputs!$J$1:$AZ$415,$D95,MATCH(O$5,MTInputs!$J$5:$AZ$5,0)) | P95: =INDEX(MTInputs!$J$1:$AZ$415,$D95,MATCH(P$5,MTInputs!$J$5:$AZ$5,0)) | Q95: =INDEX(MTInputs!$J$1:$AZ$415,$D95,MATCH(Q$5,MTInputs!$J$5:$AZ$5,0)) | R95: =INDEX(MTInputs!$J$1:$AZ$415,$D95,MATCH(R$5,MTInputs!$J$5:$AZ$5,0)) | S95: =INDEX(MTInputs!$J$1:$AZ$415,$D95,MATCH(S$5,MTInputs!$J$5:$AZ$5,0)) | ... AD95: =INDEX(MTInputs!$J$1:$AZ$415,$D95,MATCH(AD$5,MTInputs!$J$5:$AZ$5,0)) | AF95: =LOWER(Settings!$C$4)&".mit."&$A95&IF($C95="","","."&$C95&"."&$B95)&IF(INDEX(Variables!$D$5:$D$105,MATCH($A95,Variables!$A$5:$A$105,0))="","","."&INDEX(Variables!$D$5:$D$105,MATCH($A95,Variables!$A$5:$A$105,0)))&"."&AF$5 | AG95: =INDEX(MTInputs!$J$1:$AZ$415,$D95,MATCH(AG$5,MTInputs!$J$5:$AZ$5,0)) | AH95: =INDEX(MTInputs!$J$1:$AZ$415,$D95,MATCH(AH$5,MTInputs!$J$5:$AZ$5,0)) | AI95: =INDEX(MTInputs!$J$1:$AZ$415,$D95,MATCH(AI$5,MTInputs!$J$5:$AZ$5,0)) | AJ95: =INDEX(MTInputs!$J$1:$AZ$415,$D95,MATCH(AJ$5,MTInputs!$J$5:$AZ$5,0)) | AK95: =INDEX(MTInputs!$J$1:$AZ$415,$D95,MATCH(AK$5,MTInputs!$J$5:$AZ$5,0)) | AL95: =INDEX(MTInputs!$J$1:$AZ$415,$D95,MATCH(AL$5,MTInputs!$J$5:$AZ$5,0)) | AM95: =INDEX(MTInputs!$J$1:$AZ$415,$D95,MATCH(AM$5,MTInputs!$J$5:$AZ$5,0)) | AN95: =INDEX(MTInputs!$J$1:$AZ$415,$D95,MATCH(AN$5,MTInputs!$J$5:$AZ$5,0)) | ... AY95: =INDEX(MTInputs!$J$1:$AZ$415,$D95,MATCH(AY$5,MTInputs!$J$5:$AZ$5,0))
A96: D_ETSCapCont | D96: 87 | H96: =INDEX(Variables!$B$5:$B$105,MATCH($A96,Variables!$A$5:$A$105,0))&IF($C96="",""," | "&INDEX(Mapping!$B$5:$B$26,MATCH($C96,Mapping!$A$5:$A$26,0))&" | "&INDEX(Mapping!$B$30:$B$41,MATCH($B96,Mapping!$A$30:$A$41,0))) | I96: =INDEX(Variables!$C$5:$C$105,MATCH($A96,Variables!$A$5:$A$105,0)) | J96: =INDEX(Variables!$E$5:$E$105,MATCH($A96,Variables!$A$5:$A$105,0)) | K96: =LOWER(Settings!$C$4)&".mit."&$A96&IF($C96="","","."&$C96&"."&$B96)&IF(INDEX(Variables!$D$5:$D$105,MATCH($A96,Variables!$A$5:$A$105,0))="","","."&INDEX(Variables!$D$5:$D$105,MATCH($A96,Variables!$A$5:$A$105,0)))&"."&K$5 | L96: =INDEX(MTInputs!$J$1:$AZ$415,$D96,MATCH(L$5,MTInputs!$J$5:$AZ$5,0)) | M96: =INDEX(MTInputs!$J$1:$AZ$415,$D96,MATCH(M$5,MTInputs!$J$5:$AZ$5,0)) | N96: =INDEX(MTInputs!$J$1:$AZ$415,$D96,MATCH(N$5,MTInputs!$J$5:$AZ$5,0)) | O96: =INDEX(MTInputs!$J$1:$AZ$415,$D96,MATCH(O$5,MTInputs!$J$5:$AZ$5,0)) | P96: =INDEX(MTInputs!$J$1:$AZ$415,$D96,MATCH(P$5,MTInputs!$J$5:$AZ$5,0)) | Q96: =INDEX(MTInputs!$J$1:$AZ$415,$D96,MATCH(Q$5,MTInputs!$J$5:$AZ$5,0)) | R96: =INDEX(MTInputs!$J$1:$AZ$415,$D96,MATCH(R$5,MTInputs!$J$5:$AZ$5,0)) | S96: =INDEX(MTInputs!$J$1:$AZ$415,$D96,MATCH(S$5,MTInputs!$J$5:$AZ$5,0)) | ... AD96: =INDEX(MTInputs!$J$1:$AZ$415,$D96,MATCH(AD$5,MTInputs!$J$5:$AZ$5,0)) | AF96: =LOWER(Settings!$C$4)&".mit."&$A96&IF($C96="","","."&$C96&"."&$B96)&IF(INDEX(Variables!$D$5:$D$105,MATCH($A96,Variables!$A$5:$A$105,0))="","","."&INDEX(Variables!$D$5:$D$105,MATCH($A96,Variables!$A$5:$A$105,0)))&"."&AF$5 | AG96: =INDEX(MTInputs!$J$1:$AZ$415,$D96,MATCH(AG$5,MTInputs!$J$5:$AZ$5,0)) | AH96: =INDEX(MTInputs!$J$1:$AZ$415,$D96,MATCH(AH$5,MTInputs!$J$5:$AZ$5,0)) | AI96: =INDEX(MTInputs!$J$1:$AZ$415,$D96,MATCH(AI$5,MTInputs!$J$5:$AZ$5,0)) | AJ96: =INDEX(MTInputs!$J$1:$AZ$415,$D96,MATCH(AJ$5,MTInputs!$J$5:$AZ$5,0)) | AK96: =INDEX(MTInputs!$J$1:$AZ$415,$D96,MATCH(AK$5,MTInputs!$J$5:$AZ$5,0)) | AL96: =INDEX(MTInputs!$J$1:$AZ$415,$D96,MATCH(AL$5,MTInputs!$J$5:$AZ$5,0)) | AM96: =INDEX(MTInputs!$J$1:$AZ$415,$D96,MATCH(AM$5,MTInputs!$J$5:$AZ$5,0)) | AN96: =INDEX(MTInputs!$J$1:$AZ$415,$D96,MATCH(AN$5,MTInputs!$J$5:$AZ$5,0)) | ... AY96: =INDEX(MTInputs!$J$1:$AZ$415,$D96,MATCH(AY$5,MTInputs!$J$5:$AZ$5,0))
A97: D_ETSIntro | D97: 88 | H97: =INDEX(Variables!$B$5:$B$105,MATCH($A97,Variables!$A$5:$A$105,0))&IF($C97="",""," | "&INDEX(Mapping!$B$5:$B$26,MATCH($C97,Mapping!$A$5:$A$26,0))&" | "&INDEX(Mapping!$B$30:$B$41,MATCH($B97,Mapping!$A$30:$A$41,0))) | I97: =INDEX(Variables!$C$5:$C$105,MATCH($A97,Variables!$A$5:$A$105,0)) | J97: =INDEX(Variables!$E$5:$E$105,MATCH($A97,Variables!$A$5:$A$105,0)) | K97: =LOWER(Settings!$C$4)&".mit."&$A97&IF($C97="","","."&$C97&"."&$B97)&IF(INDEX(Variables!$D$5:$D$105,MATCH($A97,Variables!$A$5:$A$105,0))="","","."&INDEX(Variables!$D$5:$D$105,MATCH($A97,Variables!$A$5:$A$105,0)))&"."&K$5 | L97: =INDEX(MTInputs!$J$1:$AZ$415,$D97,MATCH(L$5,MTInputs!$J$5:$AZ$5,0)) | M97: =INDEX(MTInputs!$J$1:$AZ$415,$D97,MATCH(M$5,MTInputs!$J$5:$AZ$5,0)) | N97: =INDEX(MTInputs!$J$1:$AZ$415,$D97,MATCH(N$5,MTInputs!$J$5:$AZ$5,0)) | O97: =INDEX(MTInputs!$J$1:$AZ$415,$D97,MATCH(O$5,MTInputs!$J$5:$AZ$5,0)) | P97: =INDEX(MTInputs!$J$1:$AZ$415,$D97,MATCH(P$5,MTInputs!$J$5:$AZ$5,0)) | Q97: =INDEX(MTInputs!$J$1:$AZ$415,$D97,MATCH(Q$5,MTInputs!$J$5:$AZ$5,0)) | R97: =INDEX(MTInputs!$J$1:$AZ$415,$D97,MATCH(R$5,MTInputs!$J$5:$AZ$5,0)) | S97: =INDEX(MTInputs!$J$1:$AZ$415,$D97,MATCH(S$5,MTInputs!$J$5:$AZ$5,0)) | ... AD97: =INDEX(MTInputs!$J$1:$AZ$415,$D97,MATCH(AD$5,MTInputs!$J$5:$AZ$5,0)) | AF97: =LOWER(Settings!$C$4)&".mit."&$A97&IF($C97="","","."&$C97&"."&$B97)&IF(INDEX(Variables!$D$5:$D$105,MATCH($A97,Variables!$A$5:$A$105,0))="","","."&INDEX(Variables!$D$5:$D$105,MATCH($A97,Variables!$A$5:$A$105,0)))&"."&AF$5 | AG97: =INDEX(MTInputs!$J$1:$AZ$415,$D97,MATCH(AG$5,MTInputs!$J$5:$AZ$5,0)) | AH97: =INDEX(MTInputs!$J$1:$AZ$415,$D97,MATCH(AH$5,MTInputs!$J$5:$AZ$5,0)) | AI97: =INDEX(MTInputs!$J$1:$AZ$415,$D97,MATCH(AI$5,MTInputs!$J$5:$AZ$5,0)) | AJ97: =INDEX(MTInputs!$J$1:$AZ$415,$D97,MATCH(AJ$5,MTInputs!$J$5:$AZ$5,0)) | AK97: =INDEX(MTInputs!$J$1:$AZ$415,$D97,MATCH(AK$5,MTInputs!$J$5:$AZ$5,0)) | AL97: =INDEX(MTInputs!$J$1:$AZ$415,$D97,MATCH(AL$5,MTInputs!$J$5:$AZ$5,0)) | AM97: =INDEX(MTInputs!$J$1:$AZ$415,$D97,MATCH(AM$5,MTInputs!$J$5:$AZ$5,0)) | AN97: =INDEX(MTInputs!$J$1:$AZ$415,$D97,MATCH(AN$5,MTInputs!$J$5:$AZ$5,0)) | ... AY97: =INDEX(MTInputs!$J$1:$AZ$415,$D97,MATCH(AY$5,MTInputs!$J$5:$AZ$5,0))
A98: D_ETSOutro | D98: 89 | H98: =INDEX(Variables!$B$5:$B$105,MATCH($A98,Variables!$A$5:$A$105,0))&IF($C98="",""," | "&INDEX(Mapping!$B$5:$B$26,MATCH($C98,Mapping!$A$5:$A$26,0))&" | "&INDEX(Mapping!$B$30:$B$41,MATCH($B98,Mapping!$A$30:$A$41,0))) | I98: =INDEX(Variables!$C$5:$C$105,MATCH($A98,Variables!$A$5:$A$105,0)) | J98: =INDEX(Variables!$E$5:$E$105,MATCH($A98,Variables!$A$5:$A$105,0)) | K98: =LOWER(Settings!$C$4)&".mit."&$A98&IF($C98="","","."&$C98&"."&$B98)&IF(INDEX(Variables!$D$5:$D$105,MATCH($A98,Variables!$A$5:$A$105,0))="","","."&INDEX(Variables!$D$5:$D$105,MATCH($A98,Variables!$A$5:$A$105,0)))&"."&K$5 | L98: =INDEX(MTInputs!$J$1:$AZ$415,$D98,MATCH(L$5,MTInputs!$J$5:$AZ$5,0)) | M98: =INDEX(MTInputs!$J$1:$AZ$415,$D98,MATCH(M$5,MTInputs!$J$5:$AZ$5,0)) | N98: =INDEX(MTInputs!$J$1:$AZ$415,$D98,MATCH(N$5,MTInputs!$J$5:$AZ$5,0)) | O98: =INDEX(MTInputs!$J$1:$AZ$415,$D98,MATCH(O$5,MTInputs!$J$5:$AZ$5,0)) | P98: =INDEX(MTInputs!$J$1:$AZ$415,$D98,MATCH(P$5,MTInputs!$J$5:$AZ$5,0)) | Q98: =INDEX(MTInputs!$J$1:$AZ$415,$D98,MATCH(Q$5,MTInputs!$J$5:$AZ$5,0)) | R98: =INDEX(MTInputs!$J$1:$AZ$415,$D98,MATCH(R$5,MTInputs!$J$5:$AZ$5,0)) | S98: =INDEX(MTInputs!$J$1:$AZ$415,$D98,MATCH(S$5,MTInputs!$J$5:$AZ$5,0)) | ... AD98: =INDEX(MTInputs!$J$1:$AZ$415,$D98,MATCH(AD$5,MTInputs!$J$5:$AZ$5,0)) | AF98: =LOWER(Settings!$C$4)&".mit."&$A98&IF($C98="","","."&$C98&"."&$B98)&IF(INDEX(Variables!$D$5:$D$105,MATCH($A98,Variables!$A$5:$A$105,0))="","","."&INDEX(Variables!$D$5:$D$105,MATCH($A98,Variables!$A$5:$A$105,0)))&"."&AF$5 | AG98: =INDEX(MTInputs!$J$1:$AZ$415,$D98,MATCH(AG$5,MTInputs!$J$5:$AZ$5,0)) | AH98: =INDEX(MTInputs!$J$1:$AZ$415,$D98,MATCH(AH$5,MTInputs!$J$5:$AZ$5,0)) | AI98: =INDEX(MTInputs!$J$1:$AZ$415,$D98,MATCH(AI$5,MTInputs!$J$5:$AZ$5,0)) | AJ98: =INDEX(MTInputs!$J$1:$AZ$415,$D98,MATCH(AJ$5,MTInputs!$J$5:$AZ$5,0)) | AK98: =INDEX(MTInputs!$J$1:$AZ$415,$D98,MATCH(AK$5,MTInputs!$J$5:$AZ$5,0)) | AL98: =INDEX(MTInputs!$J$1:$AZ$415,$D98,MATCH(AL$5,MTInputs!$J$5:$AZ$5,0)) | AM98: =INDEX(MTInputs!$J$1:$AZ$415,$D98,MATCH(AM$5,MTInputs!$J$5:$AZ$5,0)) | AN98: =INDEX(MTInputs!$J$1:$AZ$415,$D98,MATCH(AN$5,MTInputs!$J$5:$AZ$5,0)) | ... AY98: =INDEX(MTInputs!$J$1:$AZ$415,$D98,MATCH(AY$5,MTInputs!$J$5:$AZ$5,0))
A99: D_ETSPriceOverride | D99: 93 | H99: =INDEX(Variables!$B$5:$B$105,MATCH($A99,Variables!$A$5:$A$105,0))&IF($C99="",""," | "&INDEX(Mapping!$B$5:$B$26,MATCH($C99,Mapping!$A$5:$A$26,0))&" | "&INDEX(Mapping!$B$30:$B$41,MATCH($B99,Mapping!$A$30:$A$41,0))) | I99: =INDEX(Variables!$C$5:$C$105,MATCH($A99,Variables!$A$5:$A$105,0)) | J99: =INDEX(Variables!$E$5:$E$105,MATCH($A99,Variables!$A$5:$A$105,0)) | K99: =LOWER(Settings!$C$4)&".mit."&$A99&IF($C99="","","."&$C99&"."&$B99)&IF(INDEX(Variables!$D$5:$D$105,MATCH($A99,Variables!$A$5:$A$105,0))="","","."&INDEX(Variables!$D$5:$D$105,MATCH($A99,Variables!$A$5:$A$105,0)))&"."&K$5 | L99: =INDEX(MTInputs!$J$1:$AZ$415,$D99,MATCH(L$5,MTInputs!$J$5:$AZ$5,0)) | M99: =INDEX(MTInputs!$J$1:$AZ$415,$D99,MATCH(M$5,MTInputs!$J$5:$AZ$5,0)) | N99: =INDEX(MTInputs!$J$1:$AZ$415,$D99,MATCH(N$5,MTInputs!$J$5:$AZ$5,0)) | O99: =INDEX(MTInputs!$J$1:$AZ$415,$D99,MATCH(O$5,MTInputs!$J$5:$AZ$5,0)) | P99: =INDEX(MTInputs!$J$1:$AZ$415,$D99,MATCH(P$5,MTInputs!$J$5:$AZ$5,0)) | Q99: =INDEX(MTInputs!$J$1:$AZ$415,$D99,MATCH(Q$5,MTInputs!$J$5:$AZ$5,0)) | R99: =INDEX(MTInputs!$J$1:$AZ$415,$D99,MATCH(R$5,MTInputs!$J$5:$AZ$5,0)) | S99: =INDEX(MTInputs!$J$1:$AZ$415,$D99,MATCH(S$5,MTInputs!$J$5:$AZ$5,0)) | ... AD99: =INDEX(MTInputs!$J$1:$AZ$415,$D99,MATCH(AD$5,MTInputs!$J$5:$AZ$5,0)) | AF99: =LOWER(Settings!$C$4)&".mit."&$A99&IF($C99="","","."&$C99&"."&$B99)&IF(INDEX(Variables!$D$5:$D$105,MATCH($A99,Variables!$A$5:$A$105,0))="","","."&INDEX(Variables!$D$5:$D$105,MATCH($A99,Variables!$A$5:$A$105,0)))&"."&AF$5 | AG99: =INDEX(MTInputs!$J$1:$AZ$415,$D99,MATCH(AG$5,MTInputs!$J$5:$AZ$5,0)) | AH99: =INDEX(MTInputs!$J$1:$AZ$415,$D99,MATCH(AH$5,MTInputs!$J$5:$AZ$5,0)) | AI99: =INDEX(MTInputs!$J$1:$AZ$415,$D99,MATCH(AI$5,MTInputs!$J$5:$AZ$5,0)) | AJ99: =INDEX(MTInputs!$J$1:$AZ$415,$D99,MATCH(AJ$5,MTInputs!$J$5:$AZ$5,0)) | AK99: =INDEX(MTInputs!$J$1:$AZ$415,$D99,MATCH(AK$5,MTInputs!$J$5:$AZ$5,0)) | AL99: =INDEX(MTInputs!$J$1:$AZ$415,$D99,MATCH(AL$5,MTInputs!$J$5:$AZ$5,0)) | AM99: =INDEX(MTInputs!$J$1:$AZ$415,$D99,MATCH(AM$5,MTInputs!$J$5:$AZ$5,0)) | AN99: =INDEX(MTInputs!$J$1:$AZ$415,$D99,MATCH(AN$5,MTInputs!$J$5:$AZ$5,0)) | ... AY99: =INDEX(MTInputs!$J$1:$AZ$415,$D99,MATCH(AY$5,MTInputs!$J$5:$AZ$5,0))
A100: D_ETSVolatility | D100: 95 | H100: =INDEX(Variables!$B$5:$B$105,MATCH($A100,Variables!$A$5:$A$105,0))&IF($C100="",""," | "&INDEX(Mapping!$B$5:$B$26,MATCH($C100,Mapping!$A$5:$A$26,0))&" | "&INDEX(Mapping!$B$30:$B$41,MATCH($B100,Mapping!$A$30:$A$41,0))) | I100: =INDEX(Variables!$C$5:$C$105,MATCH($A100,Variables!$A$5:$A$105,0)) | J100: =INDEX(Variables!$E$5:$E$105,MATCH($A100,Variables!$A$5:$A$105,0)) | K100: =LOWER(Settings!$C$4)&".mit."&$A100&IF($C100="","","."&$C100&"."&$B100)&IF(INDEX(Variables!$D$5:$D$105,MATCH($A100,Variables!$A$5:$A$105,0))="","","."&INDEX(Variables!$D$5:$D$105,MATCH($A100,Variables!$A$5:$A$105,0)))&"."&K$5 | L100: =INDEX(MTInputs!$J$1:$AZ$415,$D100,MATCH(L$5,MTInputs!$J$5:$AZ$5,0)) | M100: =INDEX(MTInputs!$J$1:$AZ$415,$D100,MATCH(M$5,MTInputs!$J$5:$AZ$5,0)) | N100: =INDEX(MTInputs!$J$1:$AZ$415,$D100,MATCH(N$5,MTInputs!$J$5:$AZ$5,0)) | O100: =INDEX(MTInputs!$J$1:$AZ$415,$D100,MATCH(O$5,MTInputs!$J$5:$AZ$5,0)) | P100: =INDEX(MTInputs!$J$1:$AZ$415,$D100,MATCH(P$5,MTInputs!$J$5:$AZ$5,0)) | Q100: =INDEX(MTInputs!$J$1:$AZ$415,$D100,MATCH(Q$5,MTInputs!$J$5:$AZ$5,0)) | R100: =INDEX(MTInputs!$J$1:$AZ$415,$D100,MATCH(R$5,MTInputs!$J$5:$AZ$5,0)) | S100: =INDEX(MTInputs!$J$1:$AZ$415,$D100,MATCH(S$5,MTInputs!$J$5:$AZ$5,0)) | ... AD100: =INDEX(MTInputs!$J$1:$AZ$415,$D100,MATCH(AD$5,MTInputs!$J$5:$AZ$5,0)) | AF100: =LOWER(Settings!$C$4)&".mit."&$A100&IF($C100="","","."&$C100&"."&$B100)&IF(INDEX(Variables!$D$5:$D$105,MATCH($A100,Variables!$A$5:$A$105,0))="","","."&INDEX(Variables!$D$5:$D$105,MATCH($A100,Variables!$A$5:$A$105,0)))&"."&AF$5 | AG100: =INDEX(MTInputs!$J$1:$AZ$415,$D100,MATCH(AG$5,MTInputs!$J$5:$AZ$5,0)) | AH100: =INDEX(MTInputs!$J$1:$AZ$415,$D100,MATCH(AH$5,MTInputs!$J$5:$AZ$5,0)) | AI100: =INDEX(MTInputs!$J$1:$AZ$415,$D100,MATCH(AI$5,MTInputs!$J$5:$AZ$5,0)) | AJ100: =INDEX(MTInputs!$J$1:$AZ$415,$D100,MATCH(AJ$5,MTInputs!$J$5:$AZ$5,0)) | AK100: =INDEX(MTInputs!$J$1:$AZ$415,$D100,MATCH(AK$5,MTInputs!$J$5:$AZ$5,0)) | AL100: =INDEX(MTInputs!$J$1:$AZ$415,$D100,MATCH(AL$5,MTInputs!$J$5:$AZ$5,0)) | AM100: =INDEX(MTInputs!$J$1:$AZ$415,$D100,MATCH(AM$5,MTInputs!$J$5:$AZ$5,0)) | AN100: =INDEX(MTInputs!$J$1:$AZ$415,$D100,MATCH(AN$5,MTInputs!$J$5:$AZ$5,0)) | ... AY100: =INDEX(MTInputs!$J$1:$AZ$415,$D100,MATCH(AY$5,MTInputs!$J$5:$AZ$5,0))
A101: D_ETSVolImpact | D101: 96 | H101: =INDEX(Variables!$B$5:$B$105,MATCH($A101,Variables!$A$5:$A$105,0))&IF($C101="",""," | "&INDEX(Mapping!$B$5:$B$26,MATCH($C101,Mapping!$A$5:$A$26,0))&" | "&INDEX(Mapping!$B$30:$B$41,MATCH($B101,Mapping!$A$30:$A$41,0))) | I101: =INDEX(Variables!$C$5:$C$105,MATCH($A101,Variables!$A$5:$A$105,0)) | J101: =INDEX(Variables!$E$5:$E$105,MATCH($A101,Variables!$A$5:$A$105,0)) | K101: =LOWER(Settings!$C$4)&".mit."&$A101&IF($C101="","","."&$C101&"."&$B101)&IF(INDEX(Variables!$D$5:$D$105,MATCH($A101,Variables!$A$5:$A$105,0))="","","."&INDEX(Variables!$D$5:$D$105,MATCH($A101,Variables!$A$5:$A$105,0)))&"."&K$5 | L101: =INDEX(MTInputs!$J$1:$AZ$415,$D101,MATCH(L$5,MTInputs!$J$5:$AZ$5,0)) | M101: =INDEX(MTInputs!$J$1:$AZ$415,$D101,MATCH(M$5,MTInputs!$J$5:$AZ$5,0)) | N101: =INDEX(MTInputs!$J$1:$AZ$415,$D101,MATCH(N$5,MTInputs!$J$5:$AZ$5,0)) | O101: =INDEX(MTInputs!$J$1:$AZ$415,$D101,MATCH(O$5,MTInputs!$J$5:$AZ$5,0)) | P101: =INDEX(MTInputs!$J$1:$AZ$415,$D101,MATCH(P$5,MTInputs!$J$5:$AZ$5,0)) | Q101: =INDEX(MTInputs!$J$1:$AZ$415,$D101,MATCH(Q$5,MTInputs!$J$5:$AZ$5,0)) | R101: =INDEX(MTInputs!$J$1:$AZ$415,$D101,MATCH(R$5,MTInputs!$J$5:$AZ$5,0)) | S101: =INDEX(MTInputs!$J$1:$AZ$415,$D101,MATCH(S$5,MTInputs!$J$5:$AZ$5,0)) | ... AD101: =INDEX(MTInputs!$J$1:$AZ$415,$D101,MATCH(AD$5,MTInputs!$J$5:$AZ$5,0)) | AF101: =LOWER(Settings!$C$4)&".mit."&$A101&IF($C101="","","."&$C101&"."&$B101)&IF(INDEX(Variables!$D$5:$D$105,MATCH($A101,Variables!$A$5:$A$105,0))="","","."&INDEX(Variables!$D$5:$D$105,MATCH($A101,Variables!$A$5:$A$105,0)))&"."&AF$5 | AG101: =INDEX(MTInputs!$J$1:$AZ$415,$D101,MATCH(AG$5,MTInputs!$J$5:$AZ$5,0)) | AH101: =INDEX(MTInputs!$J$1:$AZ$415,$D101,MATCH(AH$5,MTInputs!$J$5:$AZ$5,0)) | AI101: =INDEX(MTInputs!$J$1:$AZ$415,$D101,MATCH(AI$5,MTInputs!$J$5:$AZ$5,0)) | AJ101: =INDEX(MTInputs!$J$1:$AZ$415,$D101,MATCH(AJ$5,MTInputs!$J$5:$AZ$5,0)) | AK101: =INDEX(MTInputs!$J$1:$AZ$415,$D101,MATCH(AK$5,MTInputs!$J$5:$AZ$5,0)) | AL101: =INDEX(MTInputs!$J$1:$AZ$415,$D101,MATCH(AL$5,MTInputs!$J$5:$AZ$5,0)) | AM101: =INDEX(MTInputs!$J$1:$AZ$415,$D101,MATCH(AM$5,MTInputs!$J$5:$AZ$5,0)) | AN101: =INDEX(MTInputs!$J$1:$AZ$415,$D101,MATCH(AN$5,MTInputs!$J$5:$AZ$5,0)) | ... AY101: =INDEX(MTInputs!$J$1:$AZ$415,$D101,MATCH(AY$5,MTInputs!$J$5:$AZ$5,0))
A102: D_ETSCTRisk | D102: 97 | H102: =INDEX(Variables!$B$5:$B$105,MATCH($A102,Variables!$A$5:$A$105,0))&IF($C102="",""," | "&INDEX(Mapping!$B$5:$B$26,MATCH($C102,Mapping!$A$5:$A$26,0))&" | "&INDEX(Mapping!$B$30:$B$41,MATCH($B102,Mapping!$A$30:$A$41,0))) | I102: =INDEX(Variables!$C$5:$C$105,MATCH($A102,Variables!$A$5:$A$105,0)) | J102: =INDEX(Variables!$E$5:$E$105,MATCH($A102,Variables!$A$5:$A$105,0)) | K102: =LOWER(Settings!$C$4)&".mit."&$A102&IF($C102="","","."&$C102&"."&$B102)&IF(INDEX(Variables!$D$5:$D$105,MATCH($A102,Variables!$A$5:$A$105,0))="","","."&INDEX(Variables!$D$5:$D$105,MATCH($A102,Variables!$A$5:$A$105,0)))&"."&K$5 | L102: =INDEX(MTInputs!$J$1:$AZ$415,$D102,MATCH(L$5,MTInputs!$J$5:$AZ$5,0)) | M102: =INDEX(MTInputs!$J$1:$AZ$415,$D102,MATCH(M$5,MTInputs!$J$5:$AZ$5,0)) | N102: =INDEX(MTInputs!$J$1:$AZ$415,$D102,MATCH(N$5,MTInputs!$J$5:$AZ$5,0)) | O102: =INDEX(MTInputs!$J$1:$AZ$415,$D102,MATCH(O$5,MTInputs!$J$5:$AZ$5,0)) | P102: =INDEX(MTInputs!$J$1:$AZ$415,$D102,MATCH(P$5,MTInputs!$J$5:$AZ$5,0)) | Q102: =INDEX(MTInputs!$J$1:$AZ$415,$D102,MATCH(Q$5,MTInputs!$J$5:$AZ$5,0)) | R102: =INDEX(MTInputs!$J$1:$AZ$415,$D102,MATCH(R$5,MTInputs!$J$5:$AZ$5,0)) | S102: =INDEX(MTInputs!$J$1:$AZ$415,$D102,MATCH(S$5,MTInputs!$J$5:$AZ$5,0)) | ... AD102: =INDEX(MTInputs!$J$1:$AZ$415,$D102,MATCH(AD$5,MTInputs!$J$5:$AZ$5,0)) | AF102: =LOWER(Settings!$C$4)&".mit."&$A102&IF($C102="","","."&$C102&"."&$B102)&IF(INDEX(Variables!$D$5:$D$105,MATCH($A102,Variables!$A$5:$A$105,0))="","","."&INDEX(Variables!$D$5:$D$105,MATCH($A102,Variables!$A$5:$A$105,0)))&"."&AF$5 | AG102: =INDEX(MTInputs!$J$1:$AZ$415,$D102,MATCH(AG$5,MTInputs!$J$5:$AZ$5,0)) | AH102: =INDEX(MTInputs!$J$1:$AZ$415,$D102,MATCH(AH$5,MTInputs!$J$5:$AZ$5,0)) | AI102: =INDEX(MTInputs!$J$1:$AZ$415,$D102,MATCH(AI$5,MTInputs!$J$5:$AZ$5,0)) | AJ102: =INDEX(MTInputs!$J$1:$AZ$415,$D102,MATCH(AJ$5,MTInputs!$J$5:$AZ$5,0)) | AK102: =INDEX(MTInputs!$J$1:$AZ$415,$D102,MATCH(AK$5,MTInputs!$J$5:$AZ$5,0)) | AL102: =INDEX(MTInputs!$J$1:$AZ$415,$D102,MATCH(AL$5,MTInputs!$J$5:$AZ$5,0)) | AM102: =INDEX(MTInputs!$J$1:$AZ$415,$D102,MATCH(AM$5,MTInputs!$J$5:$AZ$5,0)) | AN102: =INDEX(MTInputs!$J$1:$AZ$415,$D102,MATCH(AN$5,MTInputs!$J$5:$AZ$5,0)) | ... AY102: =INDEX(MTInputs!$J$1:$AZ$415,$D102,MATCH(AY$5,MTInputs!$J$5:$AZ$5,0))
H103: ETS sector coverage (MTInputs rows 99-115) and effective coverage (ETS applied and started)
A104: etscov | B104: all | C104: pow | D104: 99 | H104: =INDEX(Variables!$B$5:$B$105,MATCH($A104,Variables!$A$5:$A$105,0))&IF($C104="",""," | "&INDEX(Mapping!$B$5:$B$26,MATCH($C104,Mapping!$A$5:$A$26,0))&" | "&INDEX(Mapping!$B$30:$B$41,MATCH($B104,Mapping!$A$30:$A$41,0))) | I104: =INDEX(Variables!$C$5:$C$105,MATCH($A104,Variables!$A$5:$A$105,0)) | J104: =INDEX(Variables!$E$5:$E$105,MATCH($A104,Variables!$A$5:$A$105,0)) | K104: =LOWER(Settings!$C$4)&".mit."&$A104&IF($C104="","","."&$C104&"."&$B104)&IF(INDEX(Variables!$D$5:$D$105,MATCH($A104,Variables!$A$5:$A$105,0))="","","."&INDEX(Variables!$D$5:$D$105,MATCH($A104,Variables!$A$5:$A$105,0)))&"."&K$5 | L104: =INDEX(MTInputs!$J$1:$AZ$415,$D104,MATCH(L$5,MTInputs!$J$5:$AZ$5,0)) | M104: =INDEX(MTInputs!$J$1:$AZ$415,$D104,MATCH(M$5,MTInputs!$J$5:$AZ$5,0)) | N104: =INDEX(MTInputs!$J$1:$AZ$415,$D104,MATCH(N$5,MTInputs!$J$5:$AZ$5,0)) | O104: =INDEX(MTInputs!$J$1:$AZ$415,$D104,MATCH(O$5,MTInputs!$J$5:$AZ$5,0)) | P104: =INDEX(MTInputs!$J$1:$AZ$415,$D104,MATCH(P$5,MTInputs!$J$5:$AZ$5,0)) | Q104: =INDEX(MTInputs!$J$1:$AZ$415,$D104,MATCH(Q$5,MTInputs!$J$5:$AZ$5,0)) | R104: =INDEX(MTInputs!$J$1:$AZ$415,$D104,MATCH(R$5,MTInputs!$J$5:$AZ$5,0)) | S104: =INDEX(MTInputs!$J$1:$AZ$415,$D104,MATCH(S$5,MTInputs!$J$5:$AZ$5,0)) | ... AD104: =INDEX(MTInputs!$J$1:$AZ$415,$D104,MATCH(AD$5,MTInputs!$J$5:$AZ$5,0)) | AF104: =LOWER(Settings!$C$4)&".mit."&$A104&IF($C104="","","."&$C104&"."&$B104)&IF(INDEX(Variables!$D$5:$D$105,MATCH($A104,Variables!$A$5:$A$105,0))="","","."&INDEX(Variables!$D$5:$D$105,MATCH($A104,Variables!$A$5:$A$105,0)))&"."&AF$5 | AG104: =INDEX(MTInputs!$J$1:$AZ$415,$D104,MATCH(AG$5,MTInputs!$J$5:$AZ$5,0)) | AH104: =INDEX(MTInputs!$J$1:$AZ$415,$D104,MATCH(AH$5,MTInputs!$J$5:$AZ$5,0)) | AI104: =INDEX(MTInputs!$J$1:$AZ$415,$D104,MATCH(AI$5,MTInputs!$J$5:$AZ$5,0)) | AJ104: =INDEX(MTInputs!$J$1:$AZ$415,$D104,MATCH(AJ$5,MTInputs!$J$5:$AZ$5,0)) | AK104: =INDEX(MTInputs!$J$1:$AZ$415,$D104,MATCH(AK$5,MTInputs!$J$5:$AZ$5,0)) | AL104: =INDEX(MTInputs!$J$1:$AZ$415,$D104,MATCH(AL$5,MTInputs!$J$5:$AZ$5,0)) | AM104: =INDEX(MTInputs!$J$1:$AZ$415,$D104,MATCH(AM$5,MTInputs!$J$5:$AZ$5,0)) | AN104: =INDEX(MTInputs!$J$1:$AZ$415,$D104,MATCH(AN$5,MTInputs!$J$5:$AZ$5,0)) | ... AY104: =INDEX(MTInputs!$J$1:$AZ$415,$D104,MATCH(AY$5,MTInputs!$J$5:$AZ$5,0))
A105: etscov | B105: all | C105: rod | D105: 100 | H105: =INDEX(Variables!$B$5:$B$105,MATCH($A105,Variables!$A$5:$A$105,0))&IF($C105="",""," | "&INDEX(Mapping!$B$5:$B$26,MATCH($C105,Mapping!$A$5:$A$26,0))&" | "&INDEX(Mapping!$B$30:$B$41,MATCH($B105,Mapping!$A$30:$A$41,0))) | I105: =INDEX(Variables!$C$5:$C$105,MATCH($A105,Variables!$A$5:$A$105,0)) | J105: =INDEX(Variables!$E$5:$E$105,MATCH($A105,Variables!$A$5:$A$105,0)) | K105: =LOWER(Settings!$C$4)&".mit."&$A105&IF($C105="","","."&$C105&"."&$B105)&IF(INDEX(Variables!$D$5:$D$105,MATCH($A105,Variables!$A$5:$A$105,0))="","","."&INDEX(Variables!$D$5:$D$105,MATCH($A105,Variables!$A$5:$A$105,0)))&"."&K$5 | L105: =INDEX(MTInputs!$J$1:$AZ$415,$D105,MATCH(L$5,MTInputs!$J$5:$AZ$5,0)) | M105: =INDEX(MTInputs!$J$1:$AZ$415,$D105,MATCH(M$5,MTInputs!$J$5:$AZ$5,0)) | N105: =INDEX(MTInputs!$J$1:$AZ$415,$D105,MATCH(N$5,MTInputs!$J$5:$AZ$5,0)) | O105: =INDEX(MTInputs!$J$1:$AZ$415,$D105,MATCH(O$5,MTInputs!$J$5:$AZ$5,0)) | P105: =INDEX(MTInputs!$J$1:$AZ$415,$D105,MATCH(P$5,MTInputs!$J$5:$AZ$5,0)) | Q105: =INDEX(MTInputs!$J$1:$AZ$415,$D105,MATCH(Q$5,MTInputs!$J$5:$AZ$5,0)) | R105: =INDEX(MTInputs!$J$1:$AZ$415,$D105,MATCH(R$5,MTInputs!$J$5:$AZ$5,0)) | S105: =INDEX(MTInputs!$J$1:$AZ$415,$D105,MATCH(S$5,MTInputs!$J$5:$AZ$5,0)) | ... AD105: =INDEX(MTInputs!$J$1:$AZ$415,$D105,MATCH(AD$5,MTInputs!$J$5:$AZ$5,0)) | AF105: =LOWER(Settings!$C$4)&".mit."&$A105&IF($C105="","","."&$C105&"."&$B105)&IF(INDEX(Variables!$D$5:$D$105,MATCH($A105,Variables!$A$5:$A$105,0))="","","."&INDEX(Variables!$D$5:$D$105,MATCH($A105,Variables!$A$5:$A$105,0)))&"."&AF$5 | AG105: =INDEX(MTInputs!$J$1:$AZ$415,$D105,MATCH(AG$5,MTInputs!$J$5:$AZ$5,0)) | AH105: =INDEX(MTInputs!$J$1:$AZ$415,$D105,MATCH(AH$5,MTInputs!$J$5:$AZ$5,0)) | AI105: =INDEX(MTInputs!$J$1:$AZ$415,$D105,MATCH(AI$5,MTInputs!$J$5:$AZ$5,0)) | AJ105: =INDEX(MTInputs!$J$1:$AZ$415,$D105,MATCH(AJ$5,MTInputs!$J$5:$AZ$5,0)) | AK105: =INDEX(MTInputs!$J$1:$AZ$415,$D105,MATCH(AK$5,MTInputs!$J$5:$AZ$5,0)) | AL105: =INDEX(MTInputs!$J$1:$AZ$415,$D105,MATCH(AL$5,MTInputs!$J$5:$AZ$5,0)) | AM105: =INDEX(MTInputs!$J$1:$AZ$415,$D105,MATCH(AM$5,MTInputs!$J$5:$AZ$5,0)) | AN105: =INDEX(MTInputs!$J$1:$AZ$415,$D105,MATCH(AN$5,MTInputs!$J$5:$AZ$5,0)) | ... AY105: =INDEX(MTInputs!$J$1:$AZ$415,$D105,MATCH(AY$5,MTInputs!$J$5:$AZ$5,0))
A106: etscov | B106: all | C106: ral | D106: 101 | H106: =INDEX(Variables!$B$5:$B$105,MATCH($A106,Variables!$A$5:$A$105,0))&IF($C106="",""," | "&INDEX(Mapping!$B$5:$B$26,MATCH($C106,Mapping!$A$5:$A$26,0))&" | "&INDEX(Mapping!$B$30:$B$41,MATCH($B106,Mapping!$A$30:$A$41,0))) | I106: =INDEX(Variables!$C$5:$C$105,MATCH($A106,Variables!$A$5:$A$105,0)) | J106: =INDEX(Variables!$E$5:$E$105,MATCH($A106,Variables!$A$5:$A$105,0)) | K106: =LOWER(Settings!$C$4)&".mit."&$A106&IF($C106="","","."&$C106&"."&$B106)&IF(INDEX(Variables!$D$5:$D$105,MATCH($A106,Variables!$A$5:$A$105,0))="","","."&INDEX(Variables!$D$5:$D$105,MATCH($A106,Variables!$A$5:$A$105,0)))&"."&K$5 | L106: =INDEX(MTInputs!$J$1:$AZ$415,$D106,MATCH(L$5,MTInputs!$J$5:$AZ$5,0)) | M106: =INDEX(MTInputs!$J$1:$AZ$415,$D106,MATCH(M$5,MTInputs!$J$5:$AZ$5,0)) | N106: =INDEX(MTInputs!$J$1:$AZ$415,$D106,MATCH(N$5,MTInputs!$J$5:$AZ$5,0)) | O106: =INDEX(MTInputs!$J$1:$AZ$415,$D106,MATCH(O$5,MTInputs!$J$5:$AZ$5,0)) | P106: =INDEX(MTInputs!$J$1:$AZ$415,$D106,MATCH(P$5,MTInputs!$J$5:$AZ$5,0)) | Q106: =INDEX(MTInputs!$J$1:$AZ$415,$D106,MATCH(Q$5,MTInputs!$J$5:$AZ$5,0)) | R106: =INDEX(MTInputs!$J$1:$AZ$415,$D106,MATCH(R$5,MTInputs!$J$5:$AZ$5,0)) | S106: =INDEX(MTInputs!$J$1:$AZ$415,$D106,MATCH(S$5,MTInputs!$J$5:$AZ$5,0)) | ... AD106: =INDEX(MTInputs!$J$1:$AZ$415,$D106,MATCH(AD$5,MTInputs!$J$5:$AZ$5,0)) | AF106: =LOWER(Settings!$C$4)&".mit."&$A106&IF($C106="","","."&$C106&"."&$B106)&IF(INDEX(Variables!$D$5:$D$105,MATCH($A106,Variables!$A$5:$A$105,0))="","","."&INDEX(Variables!$D$5:$D$105,MATCH($A106,Variables!$A$5:$A$105,0)))&"."&AF$5 | AG106: =INDEX(MTInputs!$J$1:$AZ$415,$D106,MATCH(AG$5,MTInputs!$J$5:$AZ$5,0)) | AH106: =INDEX(MTInputs!$J$1:$AZ$415,$D106,MATCH(AH$5,MTInputs!$J$5:$AZ$5,0)) | AI106: =INDEX(MTInputs!$J$1:$AZ$415,$D106,MATCH(AI$5,MTInputs!$J$5:$AZ$5,0)) | AJ106: =INDEX(MTInputs!$J$1:$AZ$415,$D106,MATCH(AJ$5,MTInputs!$J$5:$AZ$5,0)) | AK106: =INDEX(MTInputs!$J$1:$AZ$415,$D106,MATCH(AK$5,MTInputs!$J$5:$AZ$5,0)) | AL106: =INDEX(MTInputs!$J$1:$AZ$415,$D106,MATCH(AL$5,MTInputs!$J$5:$AZ$5,0)) | AM106: =INDEX(MTInputs!$J$1:$AZ$415,$D106,MATCH(AM$5,MTInputs!$J$5:$AZ$5,0)) | AN106: =INDEX(MTInputs!$J$1:$AZ$415,$D106,MATCH(AN$5,MTInputs!$J$5:$AZ$5,0)) | ... AY106: =INDEX(MTInputs!$J$1:$AZ$415,$D106,MATCH(AY$5,MTInputs!$J$5:$AZ$5,0))
A107: etscov | B107: all | C107: avi | D107: 102 | H107: =INDEX(Variables!$B$5:$B$105,MATCH($A107,Variables!$A$5:$A$105,0))&IF($C107="",""," | "&INDEX(Mapping!$B$5:$B$26,MATCH($C107,Mapping!$A$5:$A$26,0))&" | "&INDEX(Mapping!$B$30:$B$41,MATCH($B107,Mapping!$A$30:$A$41,0))) | I107: =INDEX(Variables!$C$5:$C$105,MATCH($A107,Variables!$A$5:$A$105,0)) | J107: =INDEX(Variables!$E$5:$E$105,MATCH($A107,Variables!$A$5:$A$105,0)) | K107: =LOWER(Settings!$C$4)&".mit."&$A107&IF($C107="","","."&$C107&"."&$B107)&IF(INDEX(Variables!$D$5:$D$105,MATCH($A107,Variables!$A$5:$A$105,0))="","","."&INDEX(Variables!$D$5:$D$105,MATCH($A107,Variables!$A$5:$A$105,0)))&"."&K$5 | L107: =INDEX(MTInputs!$J$1:$AZ$415,$D107,MATCH(L$5,MTInputs!$J$5:$AZ$5,0)) | M107: =INDEX(MTInputs!$J$1:$AZ$415,$D107,MATCH(M$5,MTInputs!$J$5:$AZ$5,0)) | N107: =INDEX(MTInputs!$J$1:$AZ$415,$D107,MATCH(N$5,MTInputs!$J$5:$AZ$5,0)) | O107: =INDEX(MTInputs!$J$1:$AZ$415,$D107,MATCH(O$5,MTInputs!$J$5:$AZ$5,0)) | P107: =INDEX(MTInputs!$J$1:$AZ$415,$D107,MATCH(P$5,MTInputs!$J$5:$AZ$5,0)) | Q107: =INDEX(MTInputs!$J$1:$AZ$415,$D107,MATCH(Q$5,MTInputs!$J$5:$AZ$5,0)) | R107: =INDEX(MTInputs!$J$1:$AZ$415,$D107,MATCH(R$5,MTInputs!$J$5:$AZ$5,0)) | S107: =INDEX(MTInputs!$J$1:$AZ$415,$D107,MATCH(S$5,MTInputs!$J$5:$AZ$5,0)) | ... AD107: =INDEX(MTInputs!$J$1:$AZ$415,$D107,MATCH(AD$5,MTInputs!$J$5:$AZ$5,0)) | AF107: =LOWER(Settings!$C$4)&".mit."&$A107&IF($C107="","","."&$C107&"."&$B107)&IF(INDEX(Variables!$D$5:$D$105,MATCH($A107,Variables!$A$5:$A$105,0))="","","."&INDEX(Variables!$D$5:$D$105,MATCH($A107,Variables!$A$5:$A$105,0)))&"."&AF$5 | AG107: =INDEX(MTInputs!$J$1:$AZ$415,$D107,MATCH(AG$5,MTInputs!$J$5:$AZ$5,0)) | AH107: =INDEX(MTInputs!$J$1:$AZ$415,$D107,MATCH(AH$5,MTInputs!$J$5:$AZ$5,0)) | AI107: =INDEX(MTInputs!$J$1:$AZ$415,$D107,MATCH(AI$5,MTInputs!$J$5:$AZ$5,0)) | AJ107: =INDEX(MTInputs!$J$1:$AZ$415,$D107,MATCH(AJ$5,MTInputs!$J$5:$AZ$5,0)) | AK107: =INDEX(MTInputs!$J$1:$AZ$415,$D107,MATCH(AK$5,MTInputs!$J$5:$AZ$5,0)) | AL107: =INDEX(MTInputs!$J$1:$AZ$415,$D107,MATCH(AL$5,MTInputs!$J$5:$AZ$5,0)) | AM107: =INDEX(MTInputs!$J$1:$AZ$415,$D107,MATCH(AM$5,MTInputs!$J$5:$AZ$5,0)) | AN107: =INDEX(MTInputs!$J$1:$AZ$415,$D107,MATCH(AN$5,MTInputs!$J$5:$AZ$5,0)) | ... AY107: =INDEX(MTInputs!$J$1:$AZ$415,$D107,MATCH(AY$5,MTInputs!$J$5:$AZ$5,0))
A108: etscov | B108: all | C108: nav | D108: 103 | H108: =INDEX(Variables!$B$5:$B$105,MATCH($A108,Variables!$A$5:$A$105,0))&IF($C108="",""," | "&INDEX(Mapping!$B$5:$B$26,MATCH($C108,Mapping!$A$5:$A$26,0))&" | "&INDEX(Mapping!$B$30:$B$41,MATCH($B108,Mapping!$A$30:$A$41,0))) | I108: =INDEX(Variables!$C$5:$C$105,MATCH($A108,Variables!$A$5:$A$105,0)) | J108: =INDEX(Variables!$E$5:$E$105,MATCH($A108,Variables!$A$5:$A$105,0)) | K108: =LOWER(Settings!$C$4)&".mit."&$A108&IF($C108="","","."&$C108&"."&$B108)&IF(INDEX(Variables!$D$5:$D$105,MATCH($A108,Variables!$A$5:$A$105,0))="","","."&INDEX(Variables!$D$5:$D$105,MATCH($A108,Variables!$A$5:$A$105,0)))&"."&K$5 | L108: =INDEX(MTInputs!$J$1:$AZ$415,$D108,MATCH(L$5,MTInputs!$J$5:$AZ$5,0)) | M108: =INDEX(MTInputs!$J$1:$AZ$415,$D108,MATCH(M$5,MTInputs!$J$5:$AZ$5,0)) | N108: =INDEX(MTInputs!$J$1:$AZ$415,$D108,MATCH(N$5,MTInputs!$J$5:$AZ$5,0)) | O108: =INDEX(MTInputs!$J$1:$AZ$415,$D108,MATCH(O$5,MTInputs!$J$5:$AZ$5,0)) | P108: =INDEX(MTInputs!$J$1:$AZ$415,$D108,MATCH(P$5,MTInputs!$J$5:$AZ$5,0)) | Q108: =INDEX(MTInputs!$J$1:$AZ$415,$D108,MATCH(Q$5,MTInputs!$J$5:$AZ$5,0)) | R108: =INDEX(MTInputs!$J$1:$AZ$415,$D108,MATCH(R$5,MTInputs!$J$5:$AZ$5,0)) | S108: =INDEX(MTInputs!$J$1:$AZ$415,$D108,MATCH(S$5,MTInputs!$J$5:$AZ$5,0)) | ... AD108: =INDEX(MTInputs!$J$1:$AZ$415,$D108,MATCH(AD$5,MTInputs!$J$5:$AZ$5,0)) | AF108: =LOWER(Settings!$C$4)&".mit."&$A108&IF($C108="","","."&$C108&"."&$B108)&IF(INDEX(Variables!$D$5:$D$105,MATCH($A108,Variables!$A$5:$A$105,0))="","","."&INDEX(Variables!$D$5:$D$105,MATCH($A108,Variables!$A$5:$A$105,0)))&"."&AF$5 | AG108: =INDEX(MTInputs!$J$1:$AZ$415,$D108,MATCH(AG$5,MTInputs!$J$5:$AZ$5,0)) | AH108: =INDEX(MTInputs!$J$1:$AZ$415,$D108,MATCH(AH$5,MTInputs!$J$5:$AZ$5,0)) | AI108: =INDEX(MTInputs!$J$1:$AZ$415,$D108,MATCH(AI$5,MTInputs!$J$5:$AZ$5,0)) | AJ108: =INDEX(MTInputs!$J$1:$AZ$415,$D108,MATCH(AJ$5,MTInputs!$J$5:$AZ$5,0)) | AK108: =INDEX(MTInputs!$J$1:$AZ$415,$D108,MATCH(AK$5,MTInputs!$J$5:$AZ$5,0)) | AL108: =INDEX(MTInputs!$J$1:$AZ$415,$D108,MATCH(AL$5,MTInputs!$J$5:$AZ$5,0)) | AM108: =INDEX(MTInputs!$J$1:$AZ$415,$D108,MATCH(AM$5,MTInputs!$J$5:$AZ$5,0)) | AN108: =INDEX(MTInputs!$J$1:$AZ$415,$D108,MATCH(AN$5,MTInputs!$J$5:$AZ$5,0)) | ... AY108: =INDEX(MTInputs!$J$1:$AZ$415,$D108,MATCH(AY$5,MTInputs!$J$5:$AZ$5,0))
A109: etscov | B109: all | C109: res | D109: 104 | H109: =INDEX(Variables!$B$5:$B$105,MATCH($A109,Variables!$A$5:$A$105,0))&IF($C109="",""," | "&INDEX(Mapping!$B$5:$B$26,MATCH($C109,Mapping!$A$5:$A$26,0))&" | "&INDEX(Mapping!$B$30:$B$41,MATCH($B109,Mapping!$A$30:$A$41,0))) | I109: =INDEX(Variables!$C$5:$C$105,MATCH($A109,Variables!$A$5:$A$105,0)) | J109: =INDEX(Variables!$E$5:$E$105,MATCH($A109,Variables!$A$5:$A$105,0)) | K109: =LOWER(Settings!$C$4)&".mit."&$A109&IF($C109="","","."&$C109&"."&$B109)&IF(INDEX(Variables!$D$5:$D$105,MATCH($A109,Variables!$A$5:$A$105,0))="","","."&INDEX(Variables!$D$5:$D$105,MATCH($A109,Variables!$A$5:$A$105,0)))&"."&K$5 | L109: =INDEX(MTInputs!$J$1:$AZ$415,$D109,MATCH(L$5,MTInputs!$J$5:$AZ$5,0)) | M109: =INDEX(MTInputs!$J$1:$AZ$415,$D109,MATCH(M$5,MTInputs!$J$5:$AZ$5,0)) | N109: =INDEX(MTInputs!$J$1:$AZ$415,$D109,MATCH(N$5,MTInputs!$J$5:$AZ$5,0)) | O109: =INDEX(MTInputs!$J$1:$AZ$415,$D109,MATCH(O$5,MTInputs!$J$5:$AZ$5,0)) | P109: =INDEX(MTInputs!$J$1:$AZ$415,$D109,MATCH(P$5,MTInputs!$J$5:$AZ$5,0)) | Q109: =INDEX(MTInputs!$J$1:$AZ$415,$D109,MATCH(Q$5,MTInputs!$J$5:$AZ$5,0)) | R109: =INDEX(MTInputs!$J$1:$AZ$415,$D109,MATCH(R$5,MTInputs!$J$5:$AZ$5,0)) | S109: =INDEX(MTInputs!$J$1:$AZ$415,$D109,MATCH(S$5,MTInputs!$J$5:$AZ$5,0)) | ... AD109: =INDEX(MTInputs!$J$1:$AZ$415,$D109,MATCH(AD$5,MTInputs!$J$5:$AZ$5,0)) | AF109: =LOWER(Settings!$C$4)&".mit."&$A109&IF($C109="","","."&$C109&"."&$B109)&IF(INDEX(Variables!$D$5:$D$105,MATCH($A109,Variables!$A$5:$A$105,0))="","","."&INDEX(Variables!$D$5:$D$105,MATCH($A109,Variables!$A$5:$A$105,0)))&"."&AF$5 | AG109: =INDEX(MTInputs!$J$1:$AZ$415,$D109,MATCH(AG$5,MTInputs!$J$5:$AZ$5,0)) | AH109: =INDEX(MTInputs!$J$1:$AZ$415,$D109,MATCH(AH$5,MTInputs!$J$5:$AZ$5,0)) | AI109: =INDEX(MTInputs!$J$1:$AZ$415,$D109,MATCH(AI$5,MTInputs!$J$5:$AZ$5,0)) | AJ109: =INDEX(MTInputs!$J$1:$AZ$415,$D109,MATCH(AJ$5,MTInputs!$J$5:$AZ$5,0)) | AK109: =INDEX(MTInputs!$J$1:$AZ$415,$D109,MATCH(AK$5,MTInputs!$J$5:$AZ$5,0)) | AL109: =INDEX(MTInputs!$J$1:$AZ$415,$D109,MATCH(AL$5,MTInputs!$J$5:$AZ$5,0)) | AM109: =INDEX(MTInputs!$J$1:$AZ$415,$D109,MATCH(AM$5,MTInputs!$J$5:$AZ$5,0)) | AN109: =INDEX(MTInputs!$J$1:$AZ$415,$D109,MATCH(AN$5,MTInputs!$J$5:$AZ$5,0)) | ... AY109: =INDEX(MTInputs!$J$1:$AZ$415,$D109,MATCH(AY$5,MTInputs!$J$5:$AZ$5,0))
A110: etscov | B110: all | C110: foo | D110: 105 | H110: =INDEX(Variables!$B$5:$B$105,MATCH($A110,Variables!$A$5:$A$105,0))&IF($C110="",""," | "&INDEX(Mapping!$B$5:$B$26,MATCH($C110,Mapping!$A$5:$A$26,0))&" | "&INDEX(Mapping!$B$30:$B$41,MATCH($B110,Mapping!$A$30:$A$41,0))) | I110: =INDEX(Variables!$C$5:$C$105,MATCH($A110,Variables!$A$5:$A$105,0)) | J110: =INDEX(Variables!$E$5:$E$105,MATCH($A110,Variables!$A$5:$A$105,0)) | K110: =LOWER(Settings!$C$4)&".mit."&$A110&IF($C110="","","."&$C110&"."&$B110)&IF(INDEX(Variables!$D$5:$D$105,MATCH($A110,Variables!$A$5:$A$105,0))="","","."&INDEX(Variables!$D$5:$D$105,MATCH($A110,Variables!$A$5:$A$105,0)))&"."&K$5 | L110: =INDEX(MTInputs!$J$1:$AZ$415,$D110,MATCH(L$5,MTInputs!$J$5:$AZ$5,0)) | M110: =INDEX(MTInputs!$J$1:$AZ$415,$D110,MATCH(M$5,MTInputs!$J$5:$AZ$5,0)) | N110: =INDEX(MTInputs!$J$1:$AZ$415,$D110,MATCH(N$5,MTInputs!$J$5:$AZ$5,0)) | O110: =INDEX(MTInputs!$J$1:$AZ$415,$D110,MATCH(O$5,MTInputs!$J$5:$AZ$5,0)) | P110: =INDEX(MTInputs!$J$1:$AZ$415,$D110,MATCH(P$5,MTInputs!$J$5:$AZ$5,0)) | Q110: =INDEX(MTInputs!$J$1:$AZ$415,$D110,MATCH(Q$5,MTInputs!$J$5:$AZ$5,0)) | R110: =INDEX(MTInputs!$J$1:$AZ$415,$D110,MATCH(R$5,MTInputs!$J$5:$AZ$5,0)) | S110: =INDEX(MTInputs!$J$1:$AZ$415,$D110,MATCH(S$5,MTInputs!$J$5:$AZ$5,0)) | ... AD110: =INDEX(MTInputs!$J$1:$AZ$415,$D110,MATCH(AD$5,MTInputs!$J$5:$AZ$5,0)) | AF110: =LOWER(Settings!$C$4)&".mit."&$A110&IF($C110="","","."&$C110&"."&$B110)&IF(INDEX(Variables!$D$5:$D$105,MATCH($A110,Variables!$A$5:$A$105,0))="","","."&INDEX(Variables!$D$5:$D$105,MATCH($A110,Variables!$A$5:$A$105,0)))&"."&AF$5 | AG110: =INDEX(MTInputs!$J$1:$AZ$415,$D110,MATCH(AG$5,MTInputs!$J$5:$AZ$5,0)) | AH110: =INDEX(MTInputs!$J$1:$AZ$415,$D110,MATCH(AH$5,MTInputs!$J$5:$AZ$5,0)) | AI110: =INDEX(MTInputs!$J$1:$AZ$415,$D110,MATCH(AI$5,MTInputs!$J$5:$AZ$5,0)) | AJ110: =INDEX(MTInputs!$J$1:$AZ$415,$D110,MATCH(AJ$5,MTInputs!$J$5:$AZ$5,0)) | AK110: =INDEX(MTInputs!$J$1:$AZ$415,$D110,MATCH(AK$5,MTInputs!$J$5:$AZ$5,0)) | AL110: =INDEX(MTInputs!$J$1:$AZ$415,$D110,MATCH(AL$5,MTInputs!$J$5:$AZ$5,0)) | AM110: =INDEX(MTInputs!$J$1:$AZ$415,$D110,MATCH(AM$5,MTInputs!$J$5:$AZ$5,0)) | AN110: =INDEX(MTInputs!$J$1:$AZ$415,$D110,MATCH(AN$5,MTInputs!$J$5:$AZ$5,0)) | ... AY110: =INDEX(MTInputs!$J$1:$AZ$415,$D110,MATCH(AY$5,MTInputs!$J$5:$AZ$5,0))
A111: etscov | B111: all | C111: srv | D111: 106 | H111: =INDEX(Variables!$B$5:$B$105,MATCH($A111,Variables!$A$5:$A$105,0))&IF($C111="",""," | "&INDEX(Mapping!$B$5:$B$26,MATCH($C111,Mapping!$A$5:$A$26,0))&" | "&INDEX(Mapping!$B$30:$B$41,MATCH($B111,Mapping!$A$30:$A$41,0))) | I111: =INDEX(Variables!$C$5:$C$105,MATCH($A111,Variables!$A$5:$A$105,0)) | J111: =INDEX(Variables!$E$5:$E$105,MATCH($A111,Variables!$A$5:$A$105,0)) | K111: =LOWER(Settings!$C$4)&".mit."&$A111&IF($C111="","","."&$C111&"."&$B111)&IF(INDEX(Variables!$D$5:$D$105,MATCH($A111,Variables!$A$5:$A$105,0))="","","."&INDEX(Variables!$D$5:$D$105,MATCH($A111,Variables!$A$5:$A$105,0)))&"."&K$5 | L111: =INDEX(MTInputs!$J$1:$AZ$415,$D111,MATCH(L$5,MTInputs!$J$5:$AZ$5,0)) | M111: =INDEX(MTInputs!$J$1:$AZ$415,$D111,MATCH(M$5,MTInputs!$J$5:$AZ$5,0)) | N111: =INDEX(MTInputs!$J$1:$AZ$415,$D111,MATCH(N$5,MTInputs!$J$5:$AZ$5,0)) | O111: =INDEX(MTInputs!$J$1:$AZ$415,$D111,MATCH(O$5,MTInputs!$J$5:$AZ$5,0)) | P111: =INDEX(MTInputs!$J$1:$AZ$415,$D111,MATCH(P$5,MTInputs!$J$5:$AZ$5,0)) | Q111: =INDEX(MTInputs!$J$1:$AZ$415,$D111,MATCH(Q$5,MTInputs!$J$5:$AZ$5,0)) | R111: =INDEX(MTInputs!$J$1:$AZ$415,$D111,MATCH(R$5,MTInputs!$J$5:$AZ$5,0)) | S111: =INDEX(MTInputs!$J$1:$AZ$415,$D111,MATCH(S$5,MTInputs!$J$5:$AZ$5,0)) | ... AD111: =INDEX(MTInputs!$J$1:$AZ$415,$D111,MATCH(AD$5,MTInputs!$J$5:$AZ$5,0)) | AF111: =LOWER(Settings!$C$4)&".mit."&$A111&IF($C111="","","."&$C111&"."&$B111)&IF(INDEX(Variables!$D$5:$D$105,MATCH($A111,Variables!$A$5:$A$105,0))="","","."&INDEX(Variables!$D$5:$D$105,MATCH($A111,Variables!$A$5:$A$105,0)))&"."&AF$5 | AG111: =INDEX(MTInputs!$J$1:$AZ$415,$D111,MATCH(AG$5,MTInputs!$J$5:$AZ$5,0)) | AH111: =INDEX(MTInputs!$J$1:$AZ$415,$D111,MATCH(AH$5,MTInputs!$J$5:$AZ$5,0)) | AI111: =INDEX(MTInputs!$J$1:$AZ$415,$D111,MATCH(AI$5,MTInputs!$J$5:$AZ$5,0)) | AJ111: =INDEX(MTInputs!$J$1:$AZ$415,$D111,MATCH(AJ$5,MTInputs!$J$5:$AZ$5,0)) | AK111: =INDEX(MTInputs!$J$1:$AZ$415,$D111,MATCH(AK$5,MTInputs!$J$5:$AZ$5,0)) | AL111: =INDEX(MTInputs!$J$1:$AZ$415,$D111,MATCH(AL$5,MTInputs!$J$5:$AZ$5,0)) | AM111: =INDEX(MTInputs!$J$1:$AZ$415,$D111,MATCH(AM$5,MTInputs!$J$5:$AZ$5,0)) | AN111: =INDEX(MTInputs!$J$1:$AZ$415,$D111,MATCH(AN$5,MTInputs!$J$5:$AZ$5,0)) | ... AY111: =INDEX(MTInputs!$J$1:$AZ$415,$D111,MATCH(AY$5,MTInputs!$J$5:$AZ$5,0))
A112: etscov | B112: all | C112: mch | D112: 107 | H112: =INDEX(Variables!$B$5:$B$105,MATCH($A112,Variables!$A$5:$A$105,0))&IF($C112="",""," | "&INDEX(Mapping!$B$5:$B$26,MATCH($C112,Mapping!$A$5:$A$26,0))&" | "&INDEX(Mapping!$B$30:$B$41,MATCH($B112,Mapping!$A$30:$A$41,0))) | I112: =INDEX(Variables!$C$5:$C$105,MATCH($A112,Variables!$A$5:$A$105,0)) | J112: =INDEX(Variables!$E$5:$E$105,MATCH($A112,Variables!$A$5:$A$105,0)) | K112: =LOWER(Settings!$C$4)&".mit."&$A112&IF($C112="","","."&$C112&"."&$B112)&IF(INDEX(Variables!$D$5:$D$105,MATCH($A112,Variables!$A$5:$A$105,0))="","","."&INDEX(Variables!$D$5:$D$105,MATCH($A112,Variables!$A$5:$A$105,0)))&"."&K$5 | L112: =INDEX(MTInputs!$J$1:$AZ$415,$D112,MATCH(L$5,MTInputs!$J$5:$AZ$5,0)) | M112: =INDEX(MTInputs!$J$1:$AZ$415,$D112,MATCH(M$5,MTInputs!$J$5:$AZ$5,0)) | N112: =INDEX(MTInputs!$J$1:$AZ$415,$D112,MATCH(N$5,MTInputs!$J$5:$AZ$5,0)) | O112: =INDEX(MTInputs!$J$1:$AZ$415,$D112,MATCH(O$5,MTInputs!$J$5:$AZ$5,0)) | P112: =INDEX(MTInputs!$J$1:$AZ$415,$D112,MATCH(P$5,MTInputs!$J$5:$AZ$5,0)) | Q112: =INDEX(MTInputs!$J$1:$AZ$415,$D112,MATCH(Q$5,MTInputs!$J$5:$AZ$5,0)) | R112: =INDEX(MTInputs!$J$1:$AZ$415,$D112,MATCH(R$5,MTInputs!$J$5:$AZ$5,0)) | S112: =INDEX(MTInputs!$J$1:$AZ$415,$D112,MATCH(S$5,MTInputs!$J$5:$AZ$5,0)) | ... AD112: =INDEX(MTInputs!$J$1:$AZ$415,$D112,MATCH(AD$5,MTInputs!$J$5:$AZ$5,0)) | AF112: =LOWER(Settings!$C$4)&".mit."&$A112&IF($C112="","","."&$C112&"."&$B112)&IF(INDEX(Variables!$D$5:$D$105,MATCH($A112,Variables!$A$5:$A$105,0))="","","."&INDEX(Variables!$D$5:$D$105,MATCH($A112,Variables!$A$5:$A$105,0)))&"."&AF$5 | AG112: =INDEX(MTInputs!$J$1:$AZ$415,$D112,MATCH(AG$5,MTInputs!$J$5:$AZ$5,0)) | AH112: =INDEX(MTInputs!$J$1:$AZ$415,$D112,MATCH(AH$5,MTInputs!$J$5:$AZ$5,0)) | AI112: =INDEX(MTInputs!$J$1:$AZ$415,$D112,MATCH(AI$5,MTInputs!$J$5:$AZ$5,0)) | AJ112: =INDEX(MTInputs!$J$1:$AZ$415,$D112,MATCH(AJ$5,MTInputs!$J$5:$AZ$5,0)) | AK112: =INDEX(MTInputs!$J$1:$AZ$415,$D112,MATCH(AK$5,MTInputs!$J$5:$AZ$5,0)) | AL112: =INDEX(MTInputs!$J$1:$AZ$415,$D112,MATCH(AL$5,MTInputs!$J$5:$AZ$5,0)) | AM112: =INDEX(MTInputs!$J$1:$AZ$415,$D112,MATCH(AM$5,MTInputs!$J$5:$AZ$5,0)) | AN112: =INDEX(MTInputs!$J$1:$AZ$415,$D112,MATCH(AN$5,MTInputs!$J$5:$AZ$5,0)) | ... AY112: =INDEX(MTInputs!$J$1:$AZ$415,$D112,MATCH(AY$5,MTInputs!$J$5:$AZ$5,0))
A113: etscov | B113: all | C113: irn | D113: 108 | H113: =INDEX(Variables!$B$5:$B$105,MATCH($A113,Variables!$A$5:$A$105,0))&IF($C113="",""," | "&INDEX(Mapping!$B$5:$B$26,MATCH($C113,Mapping!$A$5:$A$26,0))&" | "&INDEX(Mapping!$B$30:$B$41,MATCH($B113,Mapping!$A$30:$A$41,0))) | I113: =INDEX(Variables!$C$5:$C$105,MATCH($A113,Variables!$A$5:$A$105,0)) | J113: =INDEX(Variables!$E$5:$E$105,MATCH($A113,Variables!$A$5:$A$105,0)) | K113: =LOWER(Settings!$C$4)&".mit."&$A113&IF($C113="","","."&$C113&"."&$B113)&IF(INDEX(Variables!$D$5:$D$105,MATCH($A113,Variables!$A$5:$A$105,0))="","","."&INDEX(Variables!$D$5:$D$105,MATCH($A113,Variables!$A$5:$A$105,0)))&"."&K$5 | L113: =INDEX(MTInputs!$J$1:$AZ$415,$D113,MATCH(L$5,MTInputs!$J$5:$AZ$5,0)) | M113: =INDEX(MTInputs!$J$1:$AZ$415,$D113,MATCH(M$5,MTInputs!$J$5:$AZ$5,0)) | N113: =INDEX(MTInputs!$J$1:$AZ$415,$D113,MATCH(N$5,MTInputs!$J$5:$AZ$5,0)) | O113: =INDEX(MTInputs!$J$1:$AZ$415,$D113,MATCH(O$5,MTInputs!$J$5:$AZ$5,0)) | P113: =INDEX(MTInputs!$J$1:$AZ$415,$D113,MATCH(P$5,MTInputs!$J$5:$AZ$5,0)) | Q113: =INDEX(MTInputs!$J$1:$AZ$415,$D113,MATCH(Q$5,MTInputs!$J$5:$AZ$5,0)) | R113: =INDEX(MTInputs!$J$1:$AZ$415,$D113,MATCH(R$5,MTInputs!$J$5:$AZ$5,0)) | S113: =INDEX(MTInputs!$J$1:$AZ$415,$D113,MATCH(S$5,MTInputs!$J$5:$AZ$5,0)) | ... AD113: =INDEX(MTInputs!$J$1:$AZ$415,$D113,MATCH(AD$5,MTInputs!$J$5:$AZ$5,0)) | AF113: =LOWER(Settings!$C$4)&".mit."&$A113&IF($C113="","","."&$C113&"."&$B113)&IF(INDEX(Variables!$D$5:$D$105,MATCH($A113,Variables!$A$5:$A$105,0))="","","."&INDEX(Variables!$D$5:$D$105,MATCH($A113,Variables!$A$5:$A$105,0)))&"."&AF$5 | AG113: =INDEX(MTInputs!$J$1:$AZ$415,$D113,MATCH(AG$5,MTInputs!$J$5:$AZ$5,0)) | AH113: =INDEX(MTInputs!$J$1:$AZ$415,$D113,MATCH(AH$5,MTInputs!$J$5:$AZ$5,0)) | AI113: =INDEX(MTInputs!$J$1:$AZ$415,$D113,MATCH(AI$5,MTInputs!$J$5:$AZ$5,0)) | AJ113: =INDEX(MTInputs!$J$1:$AZ$415,$D113,MATCH(AJ$5,MTInputs!$J$5:$AZ$5,0)) | AK113: =INDEX(MTInputs!$J$1:$AZ$415,$D113,MATCH(AK$5,MTInputs!$J$5:$AZ$5,0)) | AL113: =INDEX(MTInputs!$J$1:$AZ$415,$D113,MATCH(AL$5,MTInputs!$J$5:$AZ$5,0)) | AM113: =INDEX(MTInputs!$J$1:$AZ$415,$D113,MATCH(AM$5,MTInputs!$J$5:$AZ$5,0)) | AN113: =INDEX(MTInputs!$J$1:$AZ$415,$D113,MATCH(AN$5,MTInputs!$J$5:$AZ$5,0)) | ... AY113: =INDEX(MTInputs!$J$1:$AZ$415,$D113,MATCH(AY$5,MTInputs!$J$5:$AZ$5,0))
A114: etscov | B114: all | C114: nfm | D114: 109 | H114: =INDEX(Variables!$B$5:$B$105,MATCH($A114,Variables!$A$5:$A$105,0))&IF($C114="",""," | "&INDEX(Mapping!$B$5:$B$26,MATCH($C114,Mapping!$A$5:$A$26,0))&" | "&INDEX(Mapping!$B$30:$B$41,MATCH($B114,Mapping!$A$30:$A$41,0))) | I114: =INDEX(Variables!$C$5:$C$105,MATCH($A114,Variables!$A$5:$A$105,0)) | J114: =INDEX(Variables!$E$5:$E$105,MATCH($A114,Variables!$A$5:$A$105,0)) | K114: =LOWER(Settings!$C$4)&".mit."&$A114&IF($C114="","","."&$C114&"."&$B114)&IF(INDEX(Variables!$D$5:$D$105,MATCH($A114,Variables!$A$5:$A$105,0))="","","."&INDEX(Variables!$D$5:$D$105,MATCH($A114,Variables!$A$5:$A$105,0)))&"."&K$5 | L114: =INDEX(MTInputs!$J$1:$AZ$415,$D114,MATCH(L$5,MTInputs!$J$5:$AZ$5,0)) | M114: =INDEX(MTInputs!$J$1:$AZ$415,$D114,MATCH(M$5,MTInputs!$J$5:$AZ$5,0)) | N114: =INDEX(MTInputs!$J$1:$AZ$415,$D114,MATCH(N$5,MTInputs!$J$5:$AZ$5,0)) | O114: =INDEX(MTInputs!$J$1:$AZ$415,$D114,MATCH(O$5,MTInputs!$J$5:$AZ$5,0)) | P114: =INDEX(MTInputs!$J$1:$AZ$415,$D114,MATCH(P$5,MTInputs!$J$5:$AZ$5,0)) | Q114: =INDEX(MTInputs!$J$1:$AZ$415,$D114,MATCH(Q$5,MTInputs!$J$5:$AZ$5,0)) | R114: =INDEX(MTInputs!$J$1:$AZ$415,$D114,MATCH(R$5,MTInputs!$J$5:$AZ$5,0)) | S114: =INDEX(MTInputs!$J$1:$AZ$415,$D114,MATCH(S$5,MTInputs!$J$5:$AZ$5,0)) | ... AD114: =INDEX(MTInputs!$J$1:$AZ$415,$D114,MATCH(AD$5,MTInputs!$J$5:$AZ$5,0)) | AF114: =LOWER(Settings!$C$4)&".mit."&$A114&IF($C114="","","."&$C114&"."&$B114)&IF(INDEX(Variables!$D$5:$D$105,MATCH($A114,Variables!$A$5:$A$105,0))="","","."&INDEX(Variables!$D$5:$D$105,MATCH($A114,Variables!$A$5:$A$105,0)))&"."&AF$5 | AG114: =INDEX(MTInputs!$J$1:$AZ$415,$D114,MATCH(AG$5,MTInputs!$J$5:$AZ$5,0)) | AH114: =INDEX(MTInputs!$J$1:$AZ$415,$D114,MATCH(AH$5,MTInputs!$J$5:$AZ$5,0)) | AI114: =INDEX(MTInputs!$J$1:$AZ$415,$D114,MATCH(AI$5,MTInputs!$J$5:$AZ$5,0)) | AJ114: =INDEX(MTInputs!$J$1:$AZ$415,$D114,MATCH(AJ$5,MTInputs!$J$5:$AZ$5,0)) | AK114: =INDEX(MTInputs!$J$1:$AZ$415,$D114,MATCH(AK$5,MTInputs!$J$5:$AZ$5,0)) | AL114: =INDEX(MTInputs!$J$1:$AZ$415,$D114,MATCH(AL$5,MTInputs!$J$5:$AZ$5,0)) | AM114: =INDEX(MTInputs!$J$1:$AZ$415,$D114,MATCH(AM$5,MTInputs!$J$5:$AZ$5,0)) | AN114: =INDEX(MTInputs!$J$1:$AZ$415,$D114,MATCH(AN$5,MTInputs!$J$5:$AZ$5,0)) | ... AY114: =INDEX(MTInputs!$J$1:$AZ$415,$D114,MATCH(AY$5,MTInputs!$J$5:$AZ$5,0))
A115: etscov | B115: all | C115: mac | D115: 110 | H115: =INDEX(Variables!$B$5:$B$105,MATCH($A115,Variables!$A$5:$A$105,0))&IF($C115="",""," | "&INDEX(Mapping!$B$5:$B$26,MATCH($C115,Mapping!$A$5:$A$26,0))&" | "&INDEX(Mapping!$B$30:$B$41,MATCH($B115,Mapping!$A$30:$A$41,0))) | I115: =INDEX(Variables!$C$5:$C$105,MATCH($A115,Variables!$A$5:$A$105,0)) | J115: =INDEX(Variables!$E$5:$E$105,MATCH($A115,Variables!$A$5:$A$105,0)) | K115: =LOWER(Settings!$C$4)&".mit."&$A115&IF($C115="","","."&$C115&"."&$B115)&IF(INDEX(Variables!$D$5:$D$105,MATCH($A115,Variables!$A$5:$A$105,0))="","","."&INDEX(Variables!$D$5:$D$105,MATCH($A115,Variables!$A$5:$A$105,0)))&"."&K$5 | L115: =INDEX(MTInputs!$J$1:$AZ$415,$D115,MATCH(L$5,MTInputs!$J$5:$AZ$5,0)) | M115: =INDEX(MTInputs!$J$1:$AZ$415,$D115,MATCH(M$5,MTInputs!$J$5:$AZ$5,0)) | N115: =INDEX(MTInputs!$J$1:$AZ$415,$D115,MATCH(N$5,MTInputs!$J$5:$AZ$5,0)) | O115: =INDEX(MTInputs!$J$1:$AZ$415,$D115,MATCH(O$5,MTInputs!$J$5:$AZ$5,0)) | P115: =INDEX(MTInputs!$J$1:$AZ$415,$D115,MATCH(P$5,MTInputs!$J$5:$AZ$5,0)) | Q115: =INDEX(MTInputs!$J$1:$AZ$415,$D115,MATCH(Q$5,MTInputs!$J$5:$AZ$5,0)) | R115: =INDEX(MTInputs!$J$1:$AZ$415,$D115,MATCH(R$5,MTInputs!$J$5:$AZ$5,0)) | S115: =INDEX(MTInputs!$J$1:$AZ$415,$D115,MATCH(S$5,MTInputs!$J$5:$AZ$5,0)) | ... AD115: =INDEX(MTInputs!$J$1:$AZ$415,$D115,MATCH(AD$5,MTInputs!$J$5:$AZ$5,0)) | AF115: =LOWER(Settings!$C$4)&".mit."&$A115&IF($C115="","","."&$C115&"."&$B115)&IF(INDEX(Variables!$D$5:$D$105,MATCH($A115,Variables!$A$5:$A$105,0))="","","."&INDEX(Variables!$D$5:$D$105,MATCH($A115,Variables!$A$5:$A$105,0)))&"."&AF$5 | AG115: =INDEX(MTInputs!$J$1:$AZ$415,$D115,MATCH(AG$5,MTInputs!$J$5:$AZ$5,0)) | AH115: =INDEX(MTInputs!$J$1:$AZ$415,$D115,MATCH(AH$5,MTInputs!$J$5:$AZ$5,0)) | AI115: =INDEX(MTInputs!$J$1:$AZ$415,$D115,MATCH(AI$5,MTInputs!$J$5:$AZ$5,0)) | AJ115: =INDEX(MTInputs!$J$1:$AZ$415,$D115,MATCH(AJ$5,MTInputs!$J$5:$AZ$5,0)) | AK115: =INDEX(MTInputs!$J$1:$AZ$415,$D115,MATCH(AK$5,MTInputs!$J$5:$AZ$5,0)) | AL115: =INDEX(MTInputs!$J$1:$AZ$415,$D115,MATCH(AL$5,MTInputs!$J$5:$AZ$5,0)) | AM115: =INDEX(MTInputs!$J$1:$AZ$415,$D115,MATCH(AM$5,MTInputs!$J$5:$AZ$5,0)) | AN115: =INDEX(MTInputs!$J$1:$AZ$415,$D115,MATCH(AN$5,MTInputs!$J$5:$AZ$5,0)) | ... AY115: =INDEX(MTInputs!$J$1:$AZ$415,$D115,MATCH(AY$5,MTInputs!$J$5:$AZ$5,0))
... A120: etscov | B120: all | C120: oen | D120: 115 | H120: =INDEX(Variables!$B$5:$B$105,MATCH($A120,Variables!$A$5:$A$105,0))&IF($C120="",""," | "&INDEX(Mapping!$B$5:$B$26,MATCH($C120,Mapping!$A$5:$A$26,0))&" | "&INDEX(Mapping!$B$30:$B$41,MATCH($B120,Mapping!$A$30:$A$41,0))) | I120: =INDEX(Variables!$C$5:$C$105,MATCH($A120,Variables!$A$5:$A$105,0)) | J120: =INDEX(Variables!$E$5:$E$105,MATCH($A120,Variables!$A$5:$A$105,0)) | K120: =LOWER(Settings!$C$4)&".mit."&$A120&IF($C120="","","."&$C120&"."&$B120)&IF(INDEX(Variables!$D$5:$D$105,MATCH($A120,Variables!$A$5:$A$105,0))="","","."&INDEX(Variables!$D$5:$D$105,MATCH($A120,Variables!$A$5:$A$105,0)))&"."&K$5 | L120: =INDEX(MTInputs!$J$1:$AZ$415,$D120,MATCH(L$5,MTInputs!$J$5:$AZ$5,0)) | M120: =INDEX(MTInputs!$J$1:$AZ$415,$D120,MATCH(M$5,MTInputs!$J$5:$AZ$5,0)) | N120: =INDEX(MTInputs!$J$1:$AZ$415,$D120,MATCH(N$5,MTInputs!$J$5:$AZ$5,0)) | O120: =INDEX(MTInputs!$J$1:$AZ$415,$D120,MATCH(O$5,MTInputs!$J$5:$AZ$5,0)) | P120: =INDEX(MTInputs!$J$1:$AZ$415,$D120,MATCH(P$5,MTInputs!$J$5:$AZ$5,0)) | Q120: =INDEX(MTInputs!$J$1:$AZ$415,$D120,MATCH(Q$5,MTInputs!$J$5:$AZ$5,0)) | R120: =INDEX(MTInputs!$J$1:$AZ$415,$D120,MATCH(R$5,MTInputs!$J$5:$AZ$5,0)) | S120: =INDEX(MTInputs!$J$1:$AZ$415,$D120,MATCH(S$5,MTInputs!$J$5:$AZ$5,0)) | ... AD120: =INDEX(MTInputs!$J$1:$AZ$415,$D120,MATCH(AD$5,MTInputs!$J$5:$AZ$5,0)) | AF120: =LOWER(Settings!$C$4)&".mit."&$A120&IF($C120="","","."&$C120&"."&$B120)&IF(INDEX(Variables!$D$5:$D$105,MATCH($A120,Variables!$A$5:$A$105,0))="","","."&INDEX(Variables!$D$5:$D$105,MATCH($A120,Variables!$A$5:$A$105,0)))&"."&AF$5 | AG120: =INDEX(MTInputs!$J$1:$AZ$415,$D120,MATCH(AG$5,MTInputs!$J$5:$AZ$5,0)) | AH120: =INDEX(MTInputs!$J$1:$AZ$415,$D120,MATCH(AH$5,MTInputs!$J$5:$AZ$5,0)) | AI120: =INDEX(MTInputs!$J$1:$AZ$415,$D120,MATCH(AI$5,MTInputs!$J$5:$AZ$5,0)) | AJ120: =INDEX(MTInputs!$J$1:$AZ$415,$D120,MATCH(AJ$5,MTInputs!$J$5:$AZ$5,0)) | AK120: =INDEX(MTInputs!$J$1:$AZ$415,$D120,MATCH(AK$5,MTInputs!$J$5:$AZ$5,0)) | AL120: =INDEX(MTInputs!$J$1:$AZ$415,$D120,MATCH(AL$5,MTInputs!$J$5:$AZ$5,0)) | AM120: =INDEX(MTInputs!$J$1:$AZ$415,$D120,MATCH(AM$5,MTInputs!$J$5:$AZ$5,0)) | AN120: =INDEX(MTInputs!$J$1:$AZ$415,$D120,MATCH(AN$5,MTInputs!$J$5:$AZ$5,0)) | ... AY120: =INDEX(MTInputs!$J$1:$AZ$415,$D120,MATCH(AY$5,MTInputs!$J$5:$AZ$5,0))
A121: etsc | B121: all | C121: pow | H121: =INDEX(Variables!$B$5:$B$105,MATCH($A121,Variables!$A$5:$A$105,0))&IF($C121="",""," | "&INDEX(Mapping!$B$5:$B$26,MATCH($C121,Mapping!$A$5:$A$26,0))&" | "&INDEX(Mapping!$B$30:$B$41,MATCH($B121,Mapping!$A$30:$A$41,0))) | I121: =INDEX(Variables!$C$5:$C$105,MATCH($A121,Variables!$A$5:$A$105,0)) | J121: =INDEX(Variables!$E$5:$E$105,MATCH($A121,Variables!$A$5:$A$105,0)) | K121: =LOWER(Settings!$C$4)&".mit."&$A121&IF($C121="","","."&$C121&"."&$B121)&IF(INDEX(Variables!$D$5:$D$105,MATCH($A121,Variables!$A$5:$A$105,0))="","","."&INDEX(Variables!$D$5:$D$105,MATCH($A121,Variables!$A$5:$A$105,0)))&"."&K$5 | L121: =IF(AND(LEFT(L$93,3)="Yes",L$4>=L$97),IF(L104,1,0),0) | M121: =IF(AND(LEFT(M$93,3)="Yes",M$4>=M$97),IF(M104,1,0),0) | N121: =IF(AND(LEFT(N$93,3)="Yes",N$4>=N$97),IF(N104,1,0),0) | O121: =IF(AND(LEFT(O$93,3)="Yes",O$4>=O$97),IF(O104,1,0),0) | P121: =IF(AND(LEFT(P$93,3)="Yes",P$4>=P$97),IF(P104,1,0),0) | Q121: =IF(AND(LEFT(Q$93,3)="Yes",Q$4>=Q$97),IF(Q104,1,0),0) | R121: =IF(AND(LEFT(R$93,3)="Yes",R$4>=R$97),IF(R104,1,0),0) | S121: =IF(AND(LEFT(S$93,3)="Yes",S$4>=S$97),IF(S104,1,0),0) | ... AC121: =IF(AND(LEFT(AC$93,3)="Yes",AC$4>=AC$97),IF(AC104,1,0),0) | AD121: =ETSCOVER(AD$93,AD$4,AD$97,AD104) | AF121: =LOWER(Settings!$C$4)&".mit."&$A121&IF($C121="","","."&$C121&"."&$B121)&IF(INDEX(Variables!$D$5:$D$105,MATCH($A121,Variables!$A$5:$A$105,0))="","","."&INDEX(Variables!$D$5:$D$105,MATCH($A121,Variables!$A$5:$A$105,0)))&"."&AF$5 | AG121: =IF(AND(LEFT(AG$93,3)="Yes",AG$4>=AG$97),IF(AG104,1,0),0) | AH121: =IF(AND(LEFT(AH$93,3)="Yes",AH$4>=AH$97),IF(AH104,1,0),0) | AI121: =IF(AND(LEFT(AI$93,3)="Yes",AI$4>=AI$97),IF(AI104,1,0),0) | AJ121: =IF(AND(LEFT(AJ$93,3)="Yes",AJ$4>=AJ$97),IF(AJ104,1,0),0) | AK121: =IF(AND(LEFT(AK$93,3)="Yes",AK$4>=AK$97),IF(AK104,1,0),0) | AL121: =IF(AND(LEFT(AL$93,3)="Yes",AL$4>=AL$97),IF(AL104,1,0),0) | AM121: =IF(AND(LEFT(AM$93,3)="Yes",AM$4>=AM$97),IF(AM104,1,0),0) | AN121: =IF(AND(LEFT(AN$93,3)="Yes",AN$4>=AN$97),IF(AN104,1,0),0) | ... AX121: =IF(AND(LEFT(AX$93,3)="Yes",AX$4>=AX$97),IF(AX104,1,0),0) | AY121: =ETSCOVER(AY$93,AY$4,AY$97,AY104)
A122: etsc | B122: all | C122: rod | H122: =INDEX(Variables!$B$5:$B$105,MATCH($A122,Variables!$A$5:$A$105,0))&IF($C122="",""," | "&INDEX(Mapping!$B$5:$B$26,MATCH($C122,Mapping!$A$5:$A$26,0))&" | "&INDEX(Mapping!$B$30:$B$41,MATCH($B122,Mapping!$A$30:$A$41,0))) | I122: =INDEX(Variables!$C$5:$C$105,MATCH($A122,Variables!$A$5:$A$105,0)) | J122: =INDEX(Variables!$E$5:$E$105,MATCH($A122,Variables!$A$5:$A$105,0)) | K122: =LOWER(Settings!$C$4)&".mit."&$A122&IF($C122="","","."&$C122&"."&$B122)&IF(INDEX(Variables!$D$5:$D$105,MATCH($A122,Variables!$A$5:$A$105,0))="","","."&INDEX(Variables!$D$5:$D$105,MATCH($A122,Variables!$A$5:$A$105,0)))&"."&K$5 | L122: =IF(AND(LEFT(L$93,3)="Yes",L$4>=L$97),IF(L105,1,0),0) | M122: =IF(AND(LEFT(M$93,3)="Yes",M$4>=M$97),IF(M105,1,0),0) | N122: =IF(AND(LEFT(N$93,3)="Yes",N$4>=N$97),IF(N105,1,0),0) | O122: =IF(AND(LEFT(O$93,3)="Yes",O$4>=O$97),IF(O105,1,0),0) | P122: =IF(AND(LEFT(P$93,3)="Yes",P$4>=P$97),IF(P105,1,0),0) | Q122: =IF(AND(LEFT(Q$93,3)="Yes",Q$4>=Q$97),IF(Q105,1,0),0) | R122: =IF(AND(LEFT(R$93,3)="Yes",R$4>=R$97),IF(R105,1,0),0) | S122: =IF(AND(LEFT(S$93,3)="Yes",S$4>=S$97),IF(S105,1,0),0) | ... AC122: =IF(AND(LEFT(AC$93,3)="Yes",AC$4>=AC$97),IF(AC105,1,0),0) | AD122: =ETSCOVER(AD$93,AD$4,AD$97,AD105) | AF122: =LOWER(Settings!$C$4)&".mit."&$A122&IF($C122="","","."&$C122&"."&$B122)&IF(INDEX(Variables!$D$5:$D$105,MATCH($A122,Variables!$A$5:$A$105,0))="","","."&INDEX(Variables!$D$5:$D$105,MATCH($A122,Variables!$A$5:$A$105,0)))&"."&AF$5 | AG122: =IF(AND(LEFT(AG$93,3)="Yes",AG$4>=AG$97),IF(AG105,1,0),0) | AH122: =IF(AND(LEFT(AH$93,3)="Yes",AH$4>=AH$97),IF(AH105,1,0),0) | AI122: =IF(AND(LEFT(AI$93,3)="Yes",AI$4>=AI$97),IF(AI105,1,0),0) | AJ122: =IF(AND(LEFT(AJ$93,3)="Yes",AJ$4>=AJ$97),IF(AJ105,1,0),0) | AK122: =IF(AND(LEFT(AK$93,3)="Yes",AK$4>=AK$97),IF(AK105,1,0),0) | AL122: =IF(AND(LEFT(AL$93,3)="Yes",AL$4>=AL$97),IF(AL105,1,0),0) | AM122: =IF(AND(LEFT(AM$93,3)="Yes",AM$4>=AM$97),IF(AM105,1,0),0) | AN122: =IF(AND(LEFT(AN$93,3)="Yes",AN$4>=AN$97),IF(AN105,1,0),0) | ... AX122: =IF(AND(LEFT(AX$93,3)="Yes",AX$4>=AX$97),IF(AX105,1,0),0) | AY122: =ETSCOVER(AY$93,AY$4,AY$97,AY105)
