Workbook
Name PRETAX: _xlfn.LAMBDA(_xlpm.prev,_xlpm.growth,_xlpm.prev*(1+_xlpm.growth))
Name TAX: _xlfn.LAMBDA(_xlpm.base_tax,_xlpm.cp,_xlpm.ef,_xlpm.cov,_xlpm.base_tax+_xlpm.cp*_xlpm.ef*_xlpm.cov)
Name POSTTAX: _xlfn.LAMBDA(_xlpm.pre_tax_p,_xlpm.tax_p,_xlpm.pre_tax_p+_xlpm.tax_p)

Sheet ReadMe
A2: CPAT mitigation module - copy-pasteable prototype v0.6
A4: Purpose | B4: Auditable, copy-pasteable replacement of the CPAT mitigation price -> fuel-use chain. Each block has one formula across all its cells, and a whole scenario group copies to a new scenario and keeps working.
A5: Status | B5: v0.6 prototype. Price -> fuel use only (no emissions, power or revenue yet).
A6: Layout (design 2) | B6: Columns A:C variable code, fuel, subsector; D:G parameters (hidden by default - click + above column H to show); H:J description, unit, source (looked up from Variables); then one group per scenario: output-code column, base year 2022 (column L for scenario 1, as in legacy Mitigation), 2023-2035.
A7: Nesting | B7: Across: scenario (outer) > year (inner). Down: variable block (outer) > subsector > fuel (inner). 16 CPAT energy-use subsectors x 8 fuels = 128 rows per block.
A8: Blocks | B8: Pre-tax price sp (row 16), Tax (row 147), After-tax price atp (row 278), Fuel use ener (row 409), Totals (row 540).
A9: Roll-up | B9: Each block rolls up under the white summary line below its green band: click + / - at the left of that line, or the 1 / 2 outline buttons (top left) to collapse / expand all. Blocks open collapsed, totals expanded. Copying a scenario group or dragging across includes the collapsed rows.
A10: Summary lines | B10: Fuel use: total fuel use (all subsectors and fuels). Tax: the policy carbon price (repeats the scenario assumption). Prices: no total (prices are not added up).
A11: Codes | B11: Each scenario group starts with a code column: country.mit.<variable>.<subsector>.<fuel>.<suffix>.<scenario>, e.g. egy.mit.ener.rod.gso.e.1 as in legacy CPAT. The scenario number sits at the top of the code column (row 5); scenario 1 is typed, every later group = previous group + 1, so a pasted group numbers itself. Labels, units, suffixes and sources come from sheet Variables by the variable code in column A.
A12: Data step vs formulas | B12: All lookups happen in sheet Inputs (one row per fuel|subsector) and in Mitigation D:G and the base-year column, each a single INDEX/MATCH on the fuel|subsector key. Calculation cells contain no lookups.
A13: Equations | B13: Pre-tax: p(t) = p(t-1) x (1 + growth). Tax: base tax + carbon price x EF x coverage (base tax = retail - supply cost, so it includes existing excise, subsidies and VAT). After-tax = pre-tax + tax. Fuel use: F(t) = F(t-1) x (1/(1+alpha))^(1+eps_U) x (1+g)^eps_Y x (p(t)/p(t-1))^eps_U x (p(t)/p(t-1))^(eps_F(1+eps_U)) (CPAT documentation 3.3.3, without the Covid factor and shadow price).
A14: LAMBDA column | B14: 2035 (orange, dark-red text) calls named LAMBDAs with the same equations; 2023-2034 are plain formulas. Drag the 2035 cell back over the row to use the LAMBDA everywhere, or drag 2034 forward to remove it. Names (Formulas > Name Manager): PRETAX(prev, growth) = prev*(1+growth); TAX(base_tax, cp, ef, cov) = base_tax+cp*ef*cov; POSTTAX(pre_tax_p, tax_p) = pre_tax_p+tax_p; FUELUSE(f_prev, p_now, p_prev, gdp_g, eps_y, eps_u, eps_f, alpha) = f_prev*(1/(1+alpha))^(1+eps_u)*(1+gdp_g)^eps_y*(p_now/p_prev)^eps_u*(p_now/p_prev)^(eps_f*(1+eps_u)).
A15: Parameters | B15: Global, not scenario-specific: scenarios differ only in their assumption rows (row 14 carbon price). Pre-tax price growth is an input in Inputs (0 % now).
... A22: Checks | B22: Row 567 (totals by subsector and by fuel minus total fuel use) should be 0. check_v0_6.py tests formula uniformity (values, labels, codes), the LAMBDA encoding and equivalence, the scenario-copy behaviour (including auto-numbering), an independent recomputation and the regression against the previous version.

Sheet Settings
A2: Settings
B4: Country code | C4: EGY
B5: Country name | C5: =INDEX(Countries!$B$4:$B$1000,MATCH($C$4,Countries!$A$4:$A$1000,0))
B6: Income group (selects elasticities) | C6: =INDEX(Countries!$D$4:$D$1000,MATCH($C$4,Countries!$A$4:$A$1000,0))
B7: Base year | C7: 2022
B10: Version log
B11: Version | C11: Date | D11: Description | E11: Max abs regression diff
B12: 0.1 | C12: 2026-10-08 | D12: First build: design 2 price -> fuel-use prototype, Egypt base data, 2 scenarios. | E12: n/a (first version)
B13: 0.2 | C13: 2026-10-08 | D13: Inputs sheet by fuel|subsector (lookups separated from formulas); 4 hidden parameter columns D:G, global parameters; base year 2022 in column L; named LAMBDAs in 2035. | E13: 0 (all Mitigation results vs v0.1)
B14: 0.3 | C14: 2026-10-08 | D14: Variable codes in column A; description, unit and source looked up from Variables; a code column before each scenario group generates the full CPAT code with country and scenario number (auto-numbered). | E14: 0 (all Mitigation results vs v0.2)
B15: 0.4 | C15: 2026-10-08 | D15: Row outline: each block rolls up under its band row (+/- on the band; blocks collapsed by default, totals open). | E15: 0 (all Mitigation results vs v0.3)
B16: 0.5 | C16: 2026-10-08 | D16: White text in the green bands; white summary line under each band (total fuel use, policy carbon price), visible when rolled up; totals-section grand total replaced by the fuel-use summary line. | E16: 0 (all Mitigation results vs v0.4)
B17: 0.6 | C17: 2026-10-08 | D17: MTInputs sheet (legacy rows, one Used-for-calculation column per scenario); carbon price computed from the MTInputs carbon-tax parameters by scenario number. | E17: 0 (all Mitigation results vs v0.5)

Sheet MTInputs
B1: MTInputs template - row structure copied exactly from legacy CPAT MTInputs
B2: Do not insert/delete rows. Columns D:E are hidden placeholders (MT values, Dashboard values).
B3: Rows must match legacy exactly. Green (EBF1DE) = used by module; grey (F2F2F2) = unused. See NORMS.md section 4. | J3: Scenario columns (Used for calculation): number in row 5, name in row 6. Red = changed from the template value. Copy the last column one to the right to add a scenario.
C5: FALSE | D5: <-- Should normally be "FALSE"! | J5: 1 | K5: =J5+1
D6: 6 | J6: Baseline (no carbon price) | K6: Carbon price $20/tCO2 from 2027
B7: Parameters | C7: unit | D7: MT values | E7: "Dashboard" values | F7: Used for calculation | G7: Defaults | H7: NameOfParameter | J7: Used for calculation | K7: Used for calculation
B8: Country | F8: Egypt | G8: Egypt | H8: Countryname | J8: Egypt | K8: Egypt
B9: Scenario identification
B10: Scenario ID | C10: # | F10: N/A | G10: N/A | H10: MSTScenarioID | J10: =J$5 | K10: =K$5
B11: Scenario status | C11: switch | F11: N/A | G11: N/A | J11: N/A | K11: N/A
B12: Scenario name | C12: name | F12: N/A | G12: N/A | J12: =J$6 | K12: =K$6
B13: Chosen policy | C13: switch | F13: - Carbon tax | G13: - Carbon tax | H13: ScenarioSelected | J13: - Carbon tax | K13: - Carbon tax
B14: Scenario status for macro | C14: # | F14: N/A | G14: N/A | J14: N/A | K14: N/A
B15: Scenario parameters override? | C15: # | F15: N/A | G15: N/A | J15: N/A | K15: N/A
B16: CPAT-side parameters override? | C16: switch | F16: Manual* | G16: Manual* | H16: CPATDefaultsOrUserDefined | J16: Manual* | K16: Manual*
B17: Carbon pricing: main inputs
A18: X | B18: Carbon pricing start year | C18: year | F18: 2026 | G18: 2027 | H18: CPIntro | J18: 2027 | K18: 2027
A19: X | B19: Starting carbon price | C19: nom. USD/tCO2 | F19: 0 | G19: 20 | H19: CPLevelStart | J19: 0 | K19: 20
B20: Target level of carbon price | C20: nom. USD/tCO2 | F20: 50 | G20: 50 | H20: CPLevelTarget | J20: 0 | K20: 20
A21: X | B21: Year to reach target level | C21: year | F21: 2030 | G21: 2035 | H21: CPOutro | J21: 2030 | K21: 2030
B22: Carbon pricing: fuel coverage
B23: Apply tax to coal? | C23: switch | F23: TRUE | G23: TRUE | H23: MCovCoa | J23: TRUE | K23: TRUE
B24: Apply tax to natural gas? | C24: switch | F24: TRUE | G24: TRUE | H24: MCovNga | J24: TRUE | K24: TRUE
B25: Apply tax to gasoline? | C25: switch | F25: TRUE | G25: TRUE | H25: MCovGso | J25: TRUE | K25: TRUE
B26: Apply tax to diesel? | C26: switch | F26: TRUE | G26: TRUE | H26: MCovDie | J26: TRUE | K26: TRUE
B27: Apply tax to LPG? | C27: switch | F27: TRUE | G27: TRUE | H27: MCovLpg | J27: TRUE | K27: TRUE
B28: Apply tax to kerosene? | C28: switch | F28: TRUE | G28: TRUE | H28: MCovKer | J28: TRUE | K28: TRUE
B29: Apply tax to non-road oil products? | C29: switch | F29: TRUE | G29: TRUE | H29: MCovOop | J29: TRUE | K29: TRUE
B30: Carbon pricing: sector coverage
B31: Apply tax to power sector? | C31: switch | F31: TRUE | G31: TRUE | H31: MCovPow | J31: TRUE | K31: TRUE
B32: Apply tax to road transportation? | C32: switch | F32: TRUE | G32: TRUE | H32: MCovRod | J32: TRUE | K32: TRUE
B33: Apply tax to rail transportation? | C33: switch | F33: TRUE | G33: TRUE | H33: MCovRal | J33: TRUE | K33: TRUE
B34: Apply tax to domestic aviation? | C34: switch | F34: TRUE | G34: TRUE | H34: MCovAvi | J34: TRUE | K34: TRUE
B35: Apply tax to domestic shipping? | C35: switch | F35: TRUE | G35: TRUE | H35: MCovNav | J35: TRUE | K35: TRUE
B36: Apply tax to residential sector? | C36: switch | F36: TRUE | G36: TRUE | H36: MCovRes | J36: TRUE | K36: TRUE
B37: Apply tax to food & forestry? | C37: switch | F37: TRUE | G37: TRUE | H37: MCovFoo | J37: TRUE | K37: TRUE
B38: Apply tax to services (private / public)? | C38: switch | F38: TRUE | G38: TRUE | H38: MCovSrv | J38: TRUE | K38: TRUE
B39: Apply tax to mining & chemicals? | C39: switch | F39: TRUE | G39: TRUE | H39: MCovMch | J39: TRUE | K39: TRUE
B40: Apply tax to iron and steel? | C40: switch | F40: TRUE | G40: TRUE | H40: MCovIrn | J40: TRUE | K40: TRUE
B41: Apply tax to non-ferrous metals? | C41: switch | F41: TRUE | G41: TRUE | H41: MCovNfm | J41: TRUE | K41: TRUE
B42: Apply tax to machinery? | C42: switch | F42: TRUE | G42: TRUE | H42: MCovMac | J42: TRUE | K42: TRUE
... B47: Apply tax to other energy use? | C47: switch | F47: TRUE | G47: TRUE | H47: MCovOen | J47: FALSE | K47: FALSE
B48: Exemptions phaseout
B49: Apply exemption phaseout? | C49: switch | F49: FALSE | G49: FALSE | H49: ExemptPhaseout | J49: FALSE | K49: FALSE
B50: Year to start exemption phaseout (if applicable) | C50: year | F50: 2027 | G50: 2027 | H50: YearPha | J50: 2027 | K50: 2027
B51: Period to reach full exemption phaseout (if applicable) | C51: year | F51: 5 | G51: 5 | H51: ExemptPhaseoutPeriod | J51: 5 | K51: 5
B52: Feebates: Starting and End Date
B53: Start date | F53: 2027 | G53: 2027 | H53: D_FeebateIntro | J53: 2027 | K53: 2027
B54: Target date | F54: 2035 | G54: 2035 | H54: D_FeebateOutro | J54: 2035 | K54: 2035
B55: Feebates: Feebate starting rate
B56: Power sector | C56: USD/tCO2 | F56: 0 | G56: 0 | H56: D_Feb_Level_Start_Pow | J56: 0 | K56: 0
B57: Transport | C57: USD/tCO2 | F57: 0 | G57: 0 | H57: D_Feb_Level_Start_Trans | J57: 0 | K57: 0
B58: Residential | C58: USD/tCO2 | F58: 0 | G58: 0 | H58: D_Feb_Level_Start_Res | J58: 0 | K58: 0
B59: Industry | C59: USD/tCO2 | F59: 0 | G59: 0 | H59: D_Feb_Level_Start_Ind | J59: 0 | K59: 0
B60: Feebates: Feebate target rate
B61: Power sector | C61: USD/tCO2 | F61: 0 | G61: 0 | H61: D_Feb_Level_Target_Pow | J61: 0 | K61: 0
B62: Transport | C62: USD/tCO2 | F62: 0 | G62: 0 | H62: D_Feb_Level_Target_Trans | J62: 0 | K62: 0
B63: Residential | C63: USD/tCO2 | F63: 0 | G63: 0 | H63: D_Feb_Level_Target_Res | J63: 0 | K63: 0
B64: Industry | C64: USD/tCO2 | F64: 0 | G64: 0 | H64: D_Feb_Level_Target_Ind | J64: 0 | K64: 0
B65: Feebates sector coverage
B66: Apply tax to power sector? | C66: switch | F66: FALSE | G66: TRUE | J66: FALSE | K66: FALSE
B67: Apply tax to road transportation? | F67: FALSE | G67: FALSE | J67: FALSE | K67: FALSE
B68: Apply tax to rail transportation? | F68: FALSE | G68: FALSE | J68: FALSE | K68: FALSE
B69: Apply tax to domestic aviation? | F69: FALSE | G69: FALSE | J69: FALSE | K69: FALSE
B70: Apply tax to domestic shipping? | F70: FALSE | G70: FALSE | J70: FALSE | K70: FALSE
B71: Apply tax to residential sector? | C71: switch | F71: FALSE | G71: TRUE | J71: FALSE | K71: FALSE
B72: Apply tax to food & forestry? | F72: FALSE | G72: TRUE | J72: FALSE | K72: FALSE
B73: Apply tax to services (private / public)? | F73: FALSE | G73: TRUE | J73: FALSE | K73: FALSE
B74: Apply tax to mining & chemicals? | F74: TRUE | G74: TRUE | J74: TRUE | K74: TRUE
B75: Apply tax to iron and steel? | F75: FALSE | G75: TRUE | J75: FALSE | K75: FALSE
B76: Apply tax to non-ferrous metals? | F76: TRUE | G76: TRUE | J76: TRUE | K76: TRUE
B77: Apply tax to machinery? | F77: TRUE | G77: TRUE | J77: TRUE | K77: TRUE
B78: Apply tax to cement? | F78: TRUE | G78: TRUE | J78: TRUE | K78: TRUE
B79: Apply tax to other manucfacturing? | F79: TRUE | G79: TRUE | J79: TRUE | K79: TRUE
B80: Apply tax to construction? | F80: TRUE | G80: TRUE | J80: TRUE | K80: TRUE
B81: Apply tax to fuel transformation? | F81: TRUE | G81: TRUE | J81: TRUE | K81: TRUE
B82: Apply tax to other energy use? | F82: TRUE | G82: TRUE | J82: TRUE | K82: TRUE
B83: ETS Main Characteristics
B84: Apply new ETS? | F84: No | G84: No | H84: D_NewETS | J84: No | K84: No
B85: Change Relative to Baseline in Start Year | F85: 0 | G85: 0 | H85: D_ETSChangeRelStart | J85: 0 | K85: 0
B86: Change Relative to Baseline in Target Year | F86: 0 | G86: 0 | H86: D_ETSChangeRelTarget | J86: 0 | K86: 0
B87: Cap continuation after target year? | F87: Constant | G87: KeepRelativeCapConstant | H87: D_ETSCapCont | J87: Constant | K87: Constant
B88: ETS Start Year | F88: 2027 | G88: 2026 | H88: D_ETSIntro | J88: 2027 | K88: 2027
B89: ETS Target Year | F89: 2035 | G89: 2035 | H89: D_ETSOutro | J89: 2035 | K89: 2035
B90: Proportion Auctioned in Starting Year | F90: 0 | G90: 0 | H90: D_ETSAuctStart | J90: 0 | K90: 0
B91: Proportion Auctioned in Target Year | F91: 0 | G91: 1 | H91: D_ETSAuctTarget | J91: 0 | K91: 0
B92: Auction proportion continuation after target year? | F92: Constant | G92: Constant | H92: D_ETSAuctCont | J92: Constant | K92: Constant
B93: Override ETS price | F93: No | G93: No | H93: D_ETSPriceOverride | J93: No | K93: No
B94: ETS: modelling assumptions
B95: ETS Volatility | F95: Medium* | G95: Medium* | H95: D_ETSVolatility | J95: Medium* | K95: Medium*
B96: Impact of Volatility on Abatement Costs | F96: Medium* | G96: Medium* | H96: D_ETSVolImpact | J96: Medium* | K96: Medium*
B97: Carbon Tax Policy Risk | F97: 0.2 | G97: 0.2 | H97: D_ETSCTRisk | J97: 0.2 | K97: 0.2
B98: ETS: sector coverage
B99: power sector | C99: switch | F99: TRUE | G99: TRUE | J99: TRUE | K99: TRUE
B100: road transportation | F100: FALSE | G100: TRUE | J100: FALSE | K100: FALSE
B101: rail transportation | F101: FALSE | G101: TRUE | J101: FALSE | K101: FALSE
B102: domestic aviation | F102: FALSE | G102: TRUE | J102: FALSE | K102: FALSE
B103: domestic shipping | F103: FALSE | G103: TRUE | J103: FALSE | K103: FALSE
B104: residential | C104: switch | F104: FALSE | G104: TRUE | J104: FALSE | K104: FALSE
B105: food & forestry | F105: FALSE | G105: TRUE | J105: FALSE | K105: FALSE
...

Sheet Mitigation
A1: Variable | B1: Fuel | C1: Sector | D1: Param 1 | E1: Param 2 | F1: Param 3 | G1: Param 4 | H1: Description | I1: Unit | J1: Source | K1: Scenario 1: output code | Z1: Scenario 2: output code
A2: Mitigation module - price to fuel use (copy-pasteable, design 2)
A3: Scenario assumptions (one column group per scenario: code column + years; copy a whole group to add a scenario)
H4: Year | L4: =Settings!$C$7 | M4: =L4+1 | N4: =M4+1 | O4: =N4+1 | P4: =O4+1 | Q4: =P4+1 | R4: =Q4+1 | S4: =R4+1 | T4: =S4+1 | ... Y4: =X4+1 | AA4: =Settings!$C$7 | AB4: =AA4+1 | AC4: =AB4+1 | AD4: =AC4+1 | AE4: =AD4+1 | AF4: =AE4+1 | AG4: =AF4+1 | AH4: =AG4+1 | AI4: =AH4+1 | ... AN4: =AM4+1
H5: Scenario number (MTInputs column) | K5: 1 | L5: =K5 | M5: =L5 | N5: =M5 | O5: =N5 | P5: =O5 | Q5: =P5 | R5: =Q5 | S5: =R5 | ... Y5: =X5 | Z5: =K5+1 | AA5: =Z5 | AB5: =AA5 | AC5: =AB5 | AD5: =AC5 | AE5: =AD5 | AF5: =AE5 | AG5: =AF5 | AH5: =AG5 | ... AN5: =AM5
H6: Scenario name (from MTInputs) | L6: =INDEX(MTInputs!$J$6:$AZ$6,MATCH(L$5,MTInputs!$J$5:$AZ$5,0)) | AA6: =INDEX(MTInputs!$J$6:$AZ$6,MATCH(AA$5,MTInputs!$J$5:$AZ$5,0))
A7: gdp.pos.pct | H7: =INDEX(Variables!$B$5:$B$45,MATCH($A7,Variables!$A$5:$A$45,0))&IF($C7="",""," | "&INDEX(Mapping!$B$5:$B$21,MATCH($C7,Mapping!$A$5:$A$21,0))&" | "&INDEX(Mapping!$B$24:$B$32,MATCH($B7,Mapping!$A$24:$A$32,0))) | I7: =INDEX(Variables!$C$5:$C$45,MATCH($A7,Variables!$A$5:$A$45,0)) | J7: =INDEX(Variables!$E$5:$E$45,MATCH($A7,Variables!$A$5:$A$45,0)) | K7: =LOWER(Settings!$C$4)&".mit."&$A7&IF($C7="","","."&$C7&"."&$B7)&IF(INDEX(Variables!$D$5:$D$45,MATCH($A7,Variables!$A$5:$A$45,0))="","","."&INDEX(Variables!$D$5:$D$45,MATCH($A7,Variables!$A$5:$A$45,0)))&"."&K$5 | L7: =INDEX(WEO!$F$4:$AZ$1000,MATCH(Settings!$C$4&"|gdp_growth",WEO!$A$4:$A$1000,0),MATCH(L$4,WEO!$F$3:$AZ$3,0)) | M7: =INDEX(WEO!$F$4:$AZ$1000,MATCH(Settings!$C$4&"|gdp_growth",WEO!$A$4:$A$1000,0),MATCH(M$4,WEO!$F$3:$AZ$3,0)) | N7: =INDEX(WEO!$F$4:$AZ$1000,MATCH(Settings!$C$4&"|gdp_growth",WEO!$A$4:$A$1000,0),MATCH(N$4,WEO!$F$3:$AZ$3,0)) | O7: =INDEX(WEO!$F$4:$AZ$1000,MATCH(Settings!$C$4&"|gdp_growth",WEO!$A$4:$A$1000,0),MATCH(O$4,WEO!$F$3:$AZ$3,0)) | P7: =INDEX(WEO!$F$4:$AZ$1000,MATCH(Settings!$C$4&"|gdp_growth",WEO!$A$4:$A$1000,0),MATCH(P$4,WEO!$F$3:$AZ$3,0)) | Q7: =INDEX(WEO!$F$4:$AZ$1000,MATCH(Settings!$C$4&"|gdp_growth",WEO!$A$4:$A$1000,0),MATCH(Q$4,WEO!$F$3:$AZ$3,0)) | R7: =INDEX(WEO!$F$4:$AZ$1000,MATCH(Settings!$C$4&"|gdp_growth",WEO!$A$4:$A$1000,0),MATCH(R$4,WEO!$F$3:$AZ$3,0)) | S7: =INDEX(WEO!$F$4:$AZ$1000,MATCH(Settings!$C$4&"|gdp_growth",WEO!$A$4:$A$1000,0),MATCH(S$4,WEO!$F$3:$AZ$3,0)) | ... Y7: =INDEX(WEO!$F$4:$AZ$1000,MATCH(Settings!$C$4&"|gdp_growth",WEO!$A$4:$A$1000,0),MATCH(Y$4,WEO!$F$3:$AZ$3,0)) | Z7: =LOWER(Settings!$C$4)&".mit."&$A7&IF($C7="","","."&$C7&"."&$B7)&IF(INDEX(Variables!$D$5:$D$45,MATCH($A7,Variables!$A$5:$A$45,0))="","","."&INDEX(Variables!$D$5:$D$45,MATCH($A7,Variables!$A$5:$A$45,0)))&"."&Z$5 | AA7: =INDEX(WEO!$F$4:$AZ$1000,MATCH(Settings!$C$4&"|gdp_growth",WEO!$A$4:$A$1000,0),MATCH(AA$4,WEO!$F$3:$AZ$3,0)) | AB7: =INDEX(WEO!$F$4:$AZ$1000,MATCH(Settings!$C$4&"|gdp_growth",WEO!$A$4:$A$1000,0),MATCH(AB$4,WEO!$F$3:$AZ$3,0)) | AC7: =INDEX(WEO!$F$4:$AZ$1000,MATCH(Settings!$C$4&"|gdp_growth",WEO!$A$4:$A$1000,0),MATCH(AC$4,WEO!$F$3:$AZ$3,0)) | AD7: =INDEX(WEO!$F$4:$AZ$1000,MATCH(Settings!$C$4&"|gdp_growth",WEO!$A$4:$A$1000,0),MATCH(AD$4,WEO!$F$3:$AZ$3,0)) | AE7: =INDEX(WEO!$F$4:$AZ$1000,MATCH(Settings!$C$4&"|gdp_growth",WEO!$A$4:$A$1000,0),MATCH(AE$4,WEO!$F$3:$AZ$3,0)) | AF7: =INDEX(WEO!$F$4:$AZ$1000,MATCH(Settings!$C$4&"|gdp_growth",WEO!$A$4:$A$1000,0),MATCH(AF$4,WEO!$F$3:$AZ$3,0)) | AG7: =INDEX(WEO!$F$4:$AZ$1000,MATCH(Settings!$C$4&"|gdp_growth",WEO!$A$4:$A$1000,0),MATCH(AG$4,WEO!$F$3:$AZ$3,0)) | AH7: =INDEX(WEO!$F$4:$AZ$1000,MATCH(Settings!$C$4&"|gdp_growth",WEO!$A$4:$A$1000,0),MATCH(AH$4,WEO!$F$3:$AZ$3,0)) | ... AN7: =INDEX(WEO!$F$4:$AZ$1000,MATCH(Settings!$C$4&"|gdp_growth",WEO!$A$4:$A$1000,0),MATCH(AN$4,WEO!$F$3:$AZ$3,0))
A8: Policies - carbon tax (inputs looked up from MTInputs by scenario number)
A9: CPIntro | H9: =INDEX(Variables!$B$5:$B$45,MATCH($A9,Variables!$A$5:$A$45,0))&IF($C9="",""," | "&INDEX(Mapping!$B$5:$B$21,MATCH($C9,Mapping!$A$5:$A$21,0))&" | "&INDEX(Mapping!$B$24:$B$32,MATCH($B9,Mapping!$A$24:$A$32,0))) | I9: =INDEX(Variables!$C$5:$C$45,MATCH($A9,Variables!$A$5:$A$45,0)) | J9: =INDEX(Variables!$E$5:$E$45,MATCH($A9,Variables!$A$5:$A$45,0)) | K9: =LOWER(Settings!$C$4)&".mit."&$A9&IF($C9="","","."&$C9&"."&$B9)&IF(INDEX(Variables!$D$5:$D$45,MATCH($A9,Variables!$A$5:$A$45,0))="","","."&INDEX(Variables!$D$5:$D$45,MATCH($A9,Variables!$A$5:$A$45,0)))&"."&K$5 | L9: =INDEX(MTInputs!$J$8:$AZ$415,MATCH($A9,MTInputs!$H$8:$H$415,0),MATCH(L$5,MTInputs!$J$5:$AZ$5,0)) | M9: =INDEX(MTInputs!$J$8:$AZ$415,MATCH($A9,MTInputs!$H$8:$H$415,0),MATCH(M$5,MTInputs!$J$5:$AZ$5,0)) | N9: =INDEX(MTInputs!$J$8:$AZ$415,MATCH($A9,MTInputs!$H$8:$H$415,0),MATCH(N$5,MTInputs!$J$5:$AZ$5,0)) | O9: =INDEX(MTInputs!$J$8:$AZ$415,MATCH($A9,MTInputs!$H$8:$H$415,0),MATCH(O$5,MTInputs!$J$5:$AZ$5,0)) | P9: =INDEX(MTInputs!$J$8:$AZ$415,MATCH($A9,MTInputs!$H$8:$H$415,0),MATCH(P$5,MTInputs!$J$5:$AZ$5,0)) | Q9: =INDEX(MTInputs!$J$8:$AZ$415,MATCH($A9,MTInputs!$H$8:$H$415,0),MATCH(Q$5,MTInputs!$J$5:$AZ$5,0)) | R9: =INDEX(MTInputs!$J$8:$AZ$415,MATCH($A9,MTInputs!$H$8:$H$415,0),MATCH(R$5,MTInputs!$J$5:$AZ$5,0)) | S9: =INDEX(MTInputs!$J$8:$AZ$415,MATCH($A9,MTInputs!$H$8:$H$415,0),MATCH(S$5,MTInputs!$J$5:$AZ$5,0)) | ... Y9: =INDEX(MTInputs!$J$8:$AZ$415,MATCH($A9,MTInputs!$H$8:$H$415,0),MATCH(Y$5,MTInputs!$J$5:$AZ$5,0)) | Z9: =LOWER(Settings!$C$4)&".mit."&$A9&IF($C9="","","."&$C9&"."&$B9)&IF(INDEX(Variables!$D$5:$D$45,MATCH($A9,Variables!$A$5:$A$45,0))="","","."&INDEX(Variables!$D$5:$D$45,MATCH($A9,Variables!$A$5:$A$45,0)))&"."&Z$5 | AA9: =INDEX(MTInputs!$J$8:$AZ$415,MATCH($A9,MTInputs!$H$8:$H$415,0),MATCH(AA$5,MTInputs!$J$5:$AZ$5,0)) | AB9: =INDEX(MTInputs!$J$8:$AZ$415,MATCH($A9,MTInputs!$H$8:$H$415,0),MATCH(AB$5,MTInputs!$J$5:$AZ$5,0)) | AC9: =INDEX(MTInputs!$J$8:$AZ$415,MATCH($A9,MTInputs!$H$8:$H$415,0),MATCH(AC$5,MTInputs!$J$5:$AZ$5,0)) | AD9: =INDEX(MTInputs!$J$8:$AZ$415,MATCH($A9,MTInputs!$H$8:$H$415,0),MATCH(AD$5,MTInputs!$J$5:$AZ$5,0)) | AE9: =INDEX(MTInputs!$J$8:$AZ$415,MATCH($A9,MTInputs!$H$8:$H$415,0),MATCH(AE$5,MTInputs!$J$5:$AZ$5,0)) | AF9: =INDEX(MTInputs!$J$8:$AZ$415,MATCH($A9,MTInputs!$H$8:$H$415,0),MATCH(AF$5,MTInputs!$J$5:$AZ$5,0)) | AG9: =INDEX(MTInputs!$J$8:$AZ$415,MATCH($A9,MTInputs!$H$8:$H$415,0),MATCH(AG$5,MTInputs!$J$5:$AZ$5,0)) | AH9: =INDEX(MTInputs!$J$8:$AZ$415,MATCH($A9,MTInputs!$H$8:$H$415,0),MATCH(AH$5,MTInputs!$J$5:$AZ$5,0)) | ... AN9: =INDEX(MTInputs!$J$8:$AZ$415,MATCH($A9,MTInputs!$H$8:$H$415,0),MATCH(AN$5,MTInputs!$J$5:$AZ$5,0))
A10: CPLevelStart | H10: =INDEX(Variables!$B$5:$B$45,MATCH($A10,Variables!$A$5:$A$45,0))&IF($C10="",""," | "&INDEX(Mapping!$B$5:$B$21,MATCH($C10,Mapping!$A$5:$A$21,0))&" | "&INDEX(Mapping!$B$24:$B$32,MATCH($B10,Mapping!$A$24:$A$32,0))) | I10: =INDEX(Variables!$C$5:$C$45,MATCH($A10,Variables!$A$5:$A$45,0)) | J10: =INDEX(Variables!$E$5:$E$45,MATCH($A10,Variables!$A$5:$A$45,0)) | K10: =LOWER(Settings!$C$4)&".mit."&$A10&IF($C10="","","."&$C10&"."&$B10)&IF(INDEX(Variables!$D$5:$D$45,MATCH($A10,Variables!$A$5:$A$45,0))="","","."&INDEX(Variables!$D$5:$D$45,MATCH($A10,Variables!$A$5:$A$45,0)))&"."&K$5 | L10: =INDEX(MTInputs!$J$8:$AZ$415,MATCH($A10,MTInputs!$H$8:$H$415,0),MATCH(L$5,MTInputs!$J$5:$AZ$5,0)) | M10: =INDEX(MTInputs!$J$8:$AZ$415,MATCH($A10,MTInputs!$H$8:$H$415,0),MATCH(M$5,MTInputs!$J$5:$AZ$5,0)) | N10: =INDEX(MTInputs!$J$8:$AZ$415,MATCH($A10,MTInputs!$H$8:$H$415,0),MATCH(N$5,MTInputs!$J$5:$AZ$5,0)) | O10: =INDEX(MTInputs!$J$8:$AZ$415,MATCH($A10,MTInputs!$H$8:$H$415,0),MATCH(O$5,MTInputs!$J$5:$AZ$5,0)) | P10: =INDEX(MTInputs!$J$8:$AZ$415,MATCH($A10,MTInputs!$H$8:$H$415,0),MATCH(P$5,MTInputs!$J$5:$AZ$5,0)) | Q10: =INDEX(MTInputs!$J$8:$AZ$415,MATCH($A10,MTInputs!$H$8:$H$415,0),MATCH(Q$5,MTInputs!$J$5:$AZ$5,0)) | R10: =INDEX(MTInputs!$J$8:$AZ$415,MATCH($A10,MTInputs!$H$8:$H$415,0),MATCH(R$5,MTInputs!$J$5:$AZ$5,0)) | S10: =INDEX(MTInputs!$J$8:$AZ$415,MATCH($A10,MTInputs!$H$8:$H$415,0),MATCH(S$5,MTInputs!$J$5:$AZ$5,0)) | ... Y10: =INDEX(MTInputs!$J$8:$AZ$415,MATCH($A10,MTInputs!$H$8:$H$415,0),MATCH(Y$5,MTInputs!$J$5:$AZ$5,0)) | Z10: =LOWER(Settings!$C$4)&".mit."&$A10&IF($C10="","","."&$C10&"."&$B10)&IF(INDEX(Variables!$D$5:$D$45,MATCH($A10,Variables!$A$5:$A$45,0))="","","."&INDEX(Variables!$D$5:$D$45,MATCH($A10,Variables!$A$5:$A$45,0)))&"."&Z$5 | AA10: =INDEX(MTInputs!$J$8:$AZ$415,MATCH($A10,MTInputs!$H$8:$H$415,0),MATCH(AA$5,MTInputs!$J$5:$AZ$5,0)) | AB10: =INDEX(MTInputs!$J$8:$AZ$415,MATCH($A10,MTInputs!$H$8:$H$415,0),MATCH(AB$5,MTInputs!$J$5:$AZ$5,0)) | AC10: =INDEX(MTInputs!$J$8:$AZ$415,MATCH($A10,MTInputs!$H$8:$H$415,0),MATCH(AC$5,MTInputs!$J$5:$AZ$5,0)) | AD10: =INDEX(MTInputs!$J$8:$AZ$415,MATCH($A10,MTInputs!$H$8:$H$415,0),MATCH(AD$5,MTInputs!$J$5:$AZ$5,0)) | AE10: =INDEX(MTInputs!$J$8:$AZ$415,MATCH($A10,MTInputs!$H$8:$H$415,0),MATCH(AE$5,MTInputs!$J$5:$AZ$5,0)) | AF10: =INDEX(MTInputs!$J$8:$AZ$415,MATCH($A10,MTInputs!$H$8:$H$415,0),MATCH(AF$5,MTInputs!$J$5:$AZ$5,0)) | AG10: =INDEX(MTInputs!$J$8:$AZ$415,MATCH($A10,MTInputs!$H$8:$H$415,0),MATCH(AG$5,MTInputs!$J$5:$AZ$5,0)) | AH10: =INDEX(MTInputs!$J$8:$AZ$415,MATCH($A10,MTInputs!$H$8:$H$415,0),MATCH(AH$5,MTInputs!$J$5:$AZ$5,0)) | ... AN10: =INDEX(MTInputs!$J$8:$AZ$415,MATCH($A10,MTInputs!$H$8:$H$415,0),MATCH(AN$5,MTInputs!$J$5:$AZ$5,0))
A11: CPLevelTarget | H11: =INDEX(Variables!$B$5:$B$45,MATCH($A11,Variables!$A$5:$A$45,0))&IF($C11="",""," | "&INDEX(Mapping!$B$5:$B$21,MATCH($C11,Mapping!$A$5:$A$21,0))&" | "&INDEX(Mapping!$B$24:$B$32,MATCH($B11,Mapping!$A$24:$A$32,0))) | I11: =INDEX(Variables!$C$5:$C$45,MATCH($A11,Variables!$A$5:$A$45,0)) | J11: =INDEX(Variables!$E$5:$E$45,MATCH($A11,Variables!$A$5:$A$45,0)) | K11: =LOWER(Settings!$C$4)&".mit."&$A11&IF($C11="","","."&$C11&"."&$B11)&IF(INDEX(Variables!$D$5:$D$45,MATCH($A11,Variables!$A$5:$A$45,0))="","","."&INDEX(Variables!$D$5:$D$45,MATCH($A11,Variables!$A$5:$A$45,0)))&"."&K$5 | L11: =INDEX(MTInputs!$J$8:$AZ$415,MATCH($A11,MTInputs!$H$8:$H$415,0),MATCH(L$5,MTInputs!$J$5:$AZ$5,0)) | M11: =INDEX(MTInputs!$J$8:$AZ$415,MATCH($A11,MTInputs!$H$8:$H$415,0),MATCH(M$5,MTInputs!$J$5:$AZ$5,0)) | N11: =INDEX(MTInputs!$J$8:$AZ$415,MATCH($A11,MTInputs!$H$8:$H$415,0),MATCH(N$5,MTInputs!$J$5:$AZ$5,0)) | O11: =INDEX(MTInputs!$J$8:$AZ$415,MATCH($A11,MTInputs!$H$8:$H$415,0),MATCH(O$5,MTInputs!$J$5:$AZ$5,0)) | P11: =INDEX(MTInputs!$J$8:$AZ$415,MATCH($A11,MTInputs!$H$8:$H$415,0),MATCH(P$5,MTInputs!$J$5:$AZ$5,0)) | Q11: =INDEX(MTInputs!$J$8:$AZ$415,MATCH($A11,MTInputs!$H$8:$H$415,0),MATCH(Q$5,MTInputs!$J$5:$AZ$5,0)) | R11: =INDEX(MTInputs!$J$8:$AZ$415,MATCH($A11,MTInputs!$H$8:$H$415,0),MATCH(R$5,MTInputs!$J$5:$AZ$5,0)) | S11: =INDEX(MTInputs!$J$8:$AZ$415,MATCH($A11,MTInputs!$H$8:$H$415,0),MATCH(S$5,MTInputs!$J$5:$AZ$5,0)) | ... Y11: =INDEX(MTInputs!$J$8:$AZ$415,MATCH($A11,MTInputs!$H$8:$H$415,0),MATCH(Y$5,MTInputs!$J$5:$AZ$5,0)) | Z11: =LOWER(Settings!$C$4)&".mit."&$A11&IF($C11="","","."&$C11&"."&$B11)&IF(INDEX(Variables!$D$5:$D$45,MATCH($A11,Variables!$A$5:$A$45,0))="","","."&INDEX(Variables!$D$5:$D$45,MATCH($A11,Variables!$A$5:$A$45,0)))&"."&Z$5 | AA11: =INDEX(MTInputs!$J$8:$AZ$415,MATCH($A11,MTInputs!$H$8:$H$415,0),MATCH(AA$5,MTInputs!$J$5:$AZ$5,0)) | AB11: =INDEX(MTInputs!$J$8:$AZ$415,MATCH($A11,MTInputs!$H$8:$H$415,0),MATCH(AB$5,MTInputs!$J$5:$AZ$5,0)) | AC11: =INDEX(MTInputs!$J$8:$AZ$415,MATCH($A11,MTInputs!$H$8:$H$415,0),MATCH(AC$5,MTInputs!$J$5:$AZ$5,0)) | AD11: =INDEX(MTInputs!$J$8:$AZ$415,MATCH($A11,MTInputs!$H$8:$H$415,0),MATCH(AD$5,MTInputs!$J$5:$AZ$5,0)) | AE11: =INDEX(MTInputs!$J$8:$AZ$415,MATCH($A11,MTInputs!$H$8:$H$415,0),MATCH(AE$5,MTInputs!$J$5:$AZ$5,0)) | AF11: =INDEX(MTInputs!$J$8:$AZ$415,MATCH($A11,MTInputs!$H$8:$H$415,0),MATCH(AF$5,MTInputs!$J$5:$AZ$5,0)) | AG11: =INDEX(MTInputs!$J$8:$AZ$415,MATCH($A11,MTInputs!$H$8:$H$415,0),MATCH(AG$5,MTInputs!$J$5:$AZ$5,0)) | AH11: =INDEX(MTInputs!$J$8:$AZ$415,MATCH($A11,MTInputs!$H$8:$H$415,0),MATCH(AH$5,MTInputs!$J$5:$AZ$5,0)) | ... AN11: =INDEX(MTInputs!$J$8:$AZ$415,MATCH($A11,MTInputs!$H$8:$H$415,0),MATCH(AN$5,MTInputs!$J$5:$AZ$5,0))
A12: CPOutro | H12: =INDEX(Variables!$B$5:$B$45,MATCH($A12,Variables!$A$5:$A$45,0))&IF($C12="",""," | "&INDEX(Mapping!$B$5:$B$21,MATCH($C12,Mapping!$A$5:$A$21,0))&" | "&INDEX(Mapping!$B$24:$B$32,MATCH($B12,Mapping!$A$24:$A$32,0))) | I12: =INDEX(Variables!$C$5:$C$45,MATCH($A12,Variables!$A$5:$A$45,0)) | J12: =INDEX(Variables!$E$5:$E$45,MATCH($A12,Variables!$A$5:$A$45,0)) | K12: =LOWER(Settings!$C$4)&".mit."&$A12&IF($C12="","","."&$C12&"."&$B12)&IF(INDEX(Variables!$D$5:$D$45,MATCH($A12,Variables!$A$5:$A$45,0))="","","."&INDEX(Variables!$D$5:$D$45,MATCH($A12,Variables!$A$5:$A$45,0)))&"."&K$5 | L12: =INDEX(MTInputs!$J$8:$AZ$415,MATCH($A12,MTInputs!$H$8:$H$415,0),MATCH(L$5,MTInputs!$J$5:$AZ$5,0)) | M12: =INDEX(MTInputs!$J$8:$AZ$415,MATCH($A12,MTInputs!$H$8:$H$415,0),MATCH(M$5,MTInputs!$J$5:$AZ$5,0)) | N12: =INDEX(MTInputs!$J$8:$AZ$415,MATCH($A12,MTInputs!$H$8:$H$415,0),MATCH(N$5,MTInputs!$J$5:$AZ$5,0)) | O12: =INDEX(MTInputs!$J$8:$AZ$415,MATCH($A12,MTInputs!$H$8:$H$415,0),MATCH(O$5,MTInputs!$J$5:$AZ$5,0)) | P12: =INDEX(MTInputs!$J$8:$AZ$415,MATCH($A12,MTInputs!$H$8:$H$415,0),MATCH(P$5,MTInputs!$J$5:$AZ$5,0)) | Q12: =INDEX(MTInputs!$J$8:$AZ$415,MATCH($A12,MTInputs!$H$8:$H$415,0),MATCH(Q$5,MTInputs!$J$5:$AZ$5,0)) | R12: =INDEX(MTInputs!$J$8:$AZ$415,MATCH($A12,MTInputs!$H$8:$H$415,0),MATCH(R$5,MTInputs!$J$5:$AZ$5,0)) | S12: =INDEX(MTInputs!$J$8:$AZ$415,MATCH($A12,MTInputs!$H$8:$H$415,0),MATCH(S$5,MTInputs!$J$5:$AZ$5,0)) | ... Y12: =INDEX(MTInputs!$J$8:$AZ$415,MATCH($A12,MTInputs!$H$8:$H$415,0),MATCH(Y$5,MTInputs!$J$5:$AZ$5,0)) | Z12: =LOWER(Settings!$C$4)&".mit."&$A12&IF($C12="","","."&$C12&"."&$B12)&IF(INDEX(Variables!$D$5:$D$45,MATCH($A12,Variables!$A$5:$A$45,0))="","","."&INDEX(Variables!$D$5:$D$45,MATCH($A12,Variables!$A$5:$A$45,0)))&"."&Z$5 | AA12: =INDEX(MTInputs!$J$8:$AZ$415,MATCH($A12,MTInputs!$H$8:$H$415,0),MATCH(AA$5,MTInputs!$J$5:$AZ$5,0)) | AB12: =INDEX(MTInputs!$J$8:$AZ$415,MATCH($A12,MTInputs!$H$8:$H$415,0),MATCH(AB$5,MTInputs!$J$5:$AZ$5,0)) | AC12: =INDEX(MTInputs!$J$8:$AZ$415,MATCH($A12,MTInputs!$H$8:$H$415,0),MATCH(AC$5,MTInputs!$J$5:$AZ$5,0)) | AD12: =INDEX(MTInputs!$J$8:$AZ$415,MATCH($A12,MTInputs!$H$8:$H$415,0),MATCH(AD$5,MTInputs!$J$5:$AZ$5,0)) | AE12: =INDEX(MTInputs!$J$8:$AZ$415,MATCH($A12,MTInputs!$H$8:$H$415,0),MATCH(AE$5,MTInputs!$J$5:$AZ$5,0)) | AF12: =INDEX(MTInputs!$J$8:$AZ$415,MATCH($A12,MTInputs!$H$8:$H$415,0),MATCH(AF$5,MTInputs!$J$5:$AZ$5,0)) | AG12: =INDEX(MTInputs!$J$8:$AZ$415,MATCH($A12,MTInputs!$H$8:$H$415,0),MATCH(AG$5,MTInputs!$J$5:$AZ$5,0)) | AH12: =INDEX(MTInputs!$J$8:$AZ$415,MATCH($A12,MTInputs!$H$8:$H$415,0),MATCH(AH$5,MTInputs!$J$5:$AZ$5,0)) | ... AN12: =INDEX(MTInputs!$J$8:$AZ$415,MATCH($A12,MTInputs!$H$8:$H$415,0),MATCH(AN$5,MTInputs!$J$5:$AZ$5,0))
A13: ExtendCarbonPriceBeyondOutro | H13: =INDEX(Variables!$B$5:$B$45,MATCH($A13,Variables!$A$5:$A$45,0))&IF($C13="",""," | "&INDEX(Mapping!$B$5:$B$21,MATCH($C13,Mapping!$A$5:$A$21,0))&" | "&INDEX(Mapping!$B$24:$B$32,MATCH($B13,Mapping!$A$24:$A$32,0))) | I13: =INDEX(Variables!$C$5:$C$45,MATCH($A13,Variables!$A$5:$A$45,0)) | J13: =INDEX(Variables!$E$5:$E$45,MATCH($A13,Variables!$A$5:$A$45,0)) | K13: =LOWER(Settings!$C$4)&".mit."&$A13&IF($C13="","","."&$C13&"."&$B13)&IF(INDEX(Variables!$D$5:$D$45,MATCH($A13,Variables!$A$5:$A$45,0))="","","."&INDEX(Variables!$D$5:$D$45,MATCH($A13,Variables!$A$5:$A$45,0)))&"."&K$5 | L13: =INDEX(MTInputs!$J$8:$AZ$415,MATCH($A13,MTInputs!$H$8:$H$415,0),MATCH(L$5,MTInputs!$J$5:$AZ$5,0)) | M13: =INDEX(MTInputs!$J$8:$AZ$415,MATCH($A13,MTInputs!$H$8:$H$415,0),MATCH(M$5,MTInputs!$J$5:$AZ$5,0)) | N13: =INDEX(MTInputs!$J$8:$AZ$415,MATCH($A13,MTInputs!$H$8:$H$415,0),MATCH(N$5,MTInputs!$J$5:$AZ$5,0)) | O13: =INDEX(MTInputs!$J$8:$AZ$415,MATCH($A13,MTInputs!$H$8:$H$415,0),MATCH(O$5,MTInputs!$J$5:$AZ$5,0)) | P13: =INDEX(MTInputs!$J$8:$AZ$415,MATCH($A13,MTInputs!$H$8:$H$415,0),MATCH(P$5,MTInputs!$J$5:$AZ$5,0)) | Q13: =INDEX(MTInputs!$J$8:$AZ$415,MATCH($A13,MTInputs!$H$8:$H$415,0),MATCH(Q$5,MTInputs!$J$5:$AZ$5,0)) | R13: =INDEX(MTInputs!$J$8:$AZ$415,MATCH($A13,MTInputs!$H$8:$H$415,0),MATCH(R$5,MTInputs!$J$5:$AZ$5,0)) | S13: =INDEX(MTInputs!$J$8:$AZ$415,MATCH($A13,MTInputs!$H$8:$H$415,0),MATCH(S$5,MTInputs!$J$5:$AZ$5,0)) | ... Y13: =INDEX(MTInputs!$J$8:$AZ$415,MATCH($A13,MTInputs!$H$8:$H$415,0),MATCH(Y$5,MTInputs!$J$5:$AZ$5,0)) | Z13: =LOWER(Settings!$C$4)&".mit."&$A13&IF($C13="","","."&$C13&"."&$B13)&IF(INDEX(Variables!$D$5:$D$45,MATCH($A13,Variables!$A$5:$A$45,0))="","","."&INDEX(Variables!$D$5:$D$45,MATCH($A13,Variables!$A$5:$A$45,0)))&"."&Z$5 | AA13: =INDEX(MTInputs!$J$8:$AZ$415,MATCH($A13,MTInputs!$H$8:$H$415,0),MATCH(AA$5,MTInputs!$J$5:$AZ$5,0)) | AB13: =INDEX(MTInputs!$J$8:$AZ$415,MATCH($A13,MTInputs!$H$8:$H$415,0),MATCH(AB$5,MTInputs!$J$5:$AZ$5,0)) | AC13: =INDEX(MTInputs!$J$8:$AZ$415,MATCH($A13,MTInputs!$H$8:$H$415,0),MATCH(AC$5,MTInputs!$J$5:$AZ$5,0)) | AD13: =INDEX(MTInputs!$J$8:$AZ$415,MATCH($A13,MTInputs!$H$8:$H$415,0),MATCH(AD$5,MTInputs!$J$5:$AZ$5,0)) | AE13: =INDEX(MTInputs!$J$8:$AZ$415,MATCH($A13,MTInputs!$H$8:$H$415,0),MATCH(AE$5,MTInputs!$J$5:$AZ$5,0)) | AF13: =INDEX(MTInputs!$J$8:$AZ$415,MATCH($A13,MTInputs!$H$8:$H$415,0),MATCH(AF$5,MTInputs!$J$5:$AZ$5,0)) | AG13: =INDEX(MTInputs!$J$8:$AZ$415,MATCH($A13,MTInputs!$H$8:$H$415,0),MATCH(AG$5,MTInputs!$J$5:$AZ$5,0)) | AH13: =INDEX(MTInputs!$J$8:$AZ$415,MATCH($A13,MTInputs!$H$8:$H$415,0),MATCH(AH$5,MTInputs!$J$5:$AZ$5,0)) | ... AN13: =INDEX(MTInputs!$J$8:$AZ$415,MATCH($A13,MTInputs!$H$8:$H$415,0),MATCH(AN$5,MTInputs!$J$5:$AZ$5,0))
A14: cptraj | H14: =INDEX(Variables!$B$5:$B$45,MATCH($A14,Variables!$A$5:$A$45,0))&IF($C14="",""," | "&INDEX(Mapping!$B$5:$B$21,MATCH($C14,Mapping!$A$5:$A$21,0))&" | "&INDEX(Mapping!$B$24:$B$32,MATCH($B14,Mapping!$A$24:$A$32,0))) | I14: =INDEX(Variables!$C$5:$C$45,MATCH($A14,Variables!$A$5:$A$45,0)) | J14: =INDEX(Variables!$E$5:$E$45,MATCH($A14,Variables!$A$5:$A$45,0)) | K14: =LOWER(Settings!$C$4)&".mit."&$A14&IF($C14="","","."&$C14&"."&$B14)&IF(INDEX(Variables!$D$5:$D$45,MATCH($A14,Variables!$A$5:$A$45,0))="","","."&INDEX(Variables!$D$5:$D$45,MATCH($A14,Variables!$A$5:$A$45,0)))&"."&K$5 | L14: =IF(L$4<L$9,0,L$10+(L$11-L$10)/MAX(L$12-L$9,1)*IF(OR(L$4<=L$12,L$13="Linear*"),L$4-L$9,L$12-L$9)) | M14: =IF(M$4<M$9,0,M$10+(M$11-M$10)/MAX(M$12-M$9,1)*IF(OR(M$4<=M$12,M$13="Linear*"),M$4-M$9,M$12-M$9)) | N14: =IF(N$4<N$9,0,N$10+(N$11-N$10)/MAX(N$12-N$9,1)*IF(OR(N$4<=N$12,N$13="Linear*"),N$4-N$9,N$12-N$9)) | O14: =IF(O$4<O$9,0,O$10+(O$11-O$10)/MAX(O$12-O$9,1)*IF(OR(O$4<=O$12,O$13="Linear*"),O$4-O$9,O$12-O$9)) | P14: =IF(P$4<P$9,0,P$10+(P$11-P$10)/MAX(P$12-P$9,1)*IF(OR(P$4<=P$12,P$13="Linear*"),P$4-P$9,P$12-P$9)) | Q14: =IF(Q$4<Q$9,0,Q$10+(Q$11-Q$10)/MAX(Q$12-Q$9,1)*IF(OR(Q$4<=Q$12,Q$13="Linear*"),Q$4-Q$9,Q$12-Q$9)) | R14: =IF(R$4<R$9,0,R$10+(R$11-R$10)/MAX(R$12-R$9,1)*IF(OR(R$4<=R$12,R$13="Linear*"),R$4-R$9,R$12-R$9)) | S14: =IF(S$4<S$9,0,S$10+(S$11-S$10)/MAX(S$12-S$9,1)*IF(OR(S$4<=S$12,S$13="Linear*"),S$4-S$9,S$12-S$9)) | ... Y14: =IF(Y$4<Y$9,0,Y$10+(Y$11-Y$10)/MAX(Y$12-Y$9,1)*IF(OR(Y$4<=Y$12,Y$13="Linear*"),Y$4-Y$9,Y$12-Y$9)) | Z14: =LOWER(Settings!$C$4)&".mit."&$A14&IF($C14="","","."&$C14&"."&$B14)&IF(INDEX(Variables!$D$5:$D$45,MATCH($A14,Variables!$A$5:$A$45,0))="","","."&INDEX(Variables!$D$5:$D$45,MATCH($A14,Variables!$A$5:$A$45,0)))&"."&Z$5 | AA14: =IF(AA$4<AA$9,0,AA$10+(AA$11-AA$10)/MAX(AA$12-AA$9,1)*IF(OR(AA$4<=AA$12,AA$13="Linear*"),AA$4-AA$9,AA$12-AA$9)) | AB14: =IF(AB$4<AB$9,0,AB$10+(AB$11-AB$10)/MAX(AB$12-AB$9,1)*IF(OR(AB$4<=AB$12,AB$13="Linear*"),AB$4-AB$9,AB$12-AB$9)) | AC14: =IF(AC$4<AC$9,0,AC$10+(AC$11-AC$10)/MAX(AC$12-AC$9,1)*IF(OR(AC$4<=AC$12,AC$13="Linear*"),AC$4-AC$9,AC$12-AC$9)) | AD14: =IF(AD$4<AD$9,0,AD$10+(AD$11-AD$10)/MAX(AD$12-AD$9,1)*IF(OR(AD$4<=AD$12,AD$13="Linear*"),AD$4-AD$9,AD$12-AD$9)) | AE14: =IF(AE$4<AE$9,0,AE$10+(AE$11-AE$10)/MAX(AE$12-AE$9,1)*IF(OR(AE$4<=AE$12,AE$13="Linear*"),AE$4-AE$9,AE$12-AE$9)) | AF14: =IF(AF$4<AF$9,0,AF$10+(AF$11-AF$10)/MAX(AF$12-AF$9,1)*IF(OR(AF$4<=AF$12,AF$13="Linear*"),AF$4-AF$9,AF$12-AF$9)) | AG14: =IF(AG$4<AG$9,0,AG$10+(AG$11-AG$10)/MAX(AG$12-AG$9,1)*IF(OR(AG$4<=AG$12,AG$13="Linear*"),AG$4-AG$9,AG$12-AG$9)) | AH14: =IF(AH$4<AH$9,0,AH$10+(AH$11-AH$10)/MAX(AH$12-AH$9,1)*IF(OR(AH$4<=AH$12,AH$13="Linear*"),AH$4-AH$9,AH$12-AH$9)) | ... AN14: =IF(AN$4<AN$9,0,AN$10+(AN$11-AN$10)/MAX(AN$12-AN$9,1)*IF(OR(AN$4<=AN$12,AN$13="Linear*"),AN$4-AN$9,AN$12-AN$9))
A16: Pre-tax price: p(t) = p(t-1) x (1 + growth) | D16: growth
H17: No total: prices are not added up
A18: sp | B18: coa | C18: rod | D18: =INDEX(Inputs!$O$5:$O$132,MATCH($B18&"|"&$C18,Inputs!$A$5:$A$132,0)) | H18: =INDEX(Variables!$B$5:$B$45,MATCH($A18,Variables!$A$5:$A$45,0))&IF($C18="",""," | "&INDEX(Mapping!$B$5:$B$21,MATCH($C18,Mapping!$A$5:$A$21,0))&" | "&INDEX(Mapping!$B$24:$B$32,MATCH($B18,Mapping!$A$24:$A$32,0))) | I18: =INDEX(Variables!$C$5:$C$45,MATCH($A18,Variables!$A$5:$A$45,0)) | J18: =INDEX(Variables!$E$5:$E$45,MATCH($A18,Variables!$A$5:$A$45,0)) | K18: =LOWER(Settings!$C$4)&".mit."&$A18&IF($C18="","","."&$C18&"."&$B18)&IF(INDEX(Variables!$D$5:$D$45,MATCH($A18,Variables!$A$5:$A$45,0))="","","."&INDEX(Variables!$D$5:$D$45,MATCH($A18,Variables!$A$5:$A$45,0)))&"."&K$5 | L18: =INDEX(Inputs!$P$5:$P$132,MATCH($B18&"|"&$C18,Inputs!$A$5:$A$132,0)) | M18: =L18*(1+$D18) | N18: =M18*(1+$D18) | O18: =N18*(1+$D18) | P18: =O18*(1+$D18) | Q18: =P18*(1+$D18) | R18: =Q18*(1+$D18) | S18: =R18*(1+$D18) | T18: =S18*(1+$D18) | ... X18: =W18*(1+$D18) | Y18: =PRETAX(X18,$D18) | Z18: =LOWER(Settings!$C$4)&".mit."&$A18&IF($C18="","","."&$C18&"."&$B18)&IF(INDEX(Variables!$D$5:$D$45,MATCH($A18,Variables!$A$5:$A$45,0))="","","."&INDEX(Variables!$D$5:$D$45,MATCH($A18,Variables!$A$5:$A$45,0)))&"."&Z$5 | AA18: =INDEX(Inputs!$P$5:$P$132,MATCH($B18&"|"&$C18,Inputs!$A$5:$A$132,0)) | AB18: =AA18*(1+$D18) | AC18: =AB18*(1+$D18) | AD18: =AC18*(1+$D18) | AE18: =AD18*(1+$D18) | AF18: =AE18*(1+$D18) | AG18: =AF18*(1+$D18) | AH18: =AG18*(1+$D18) | AI18: =AH18*(1+$D18) | ... AM18: =AL18*(1+$D18) | AN18: =PRETAX(AM18,$D18)
A19: sp | B19: nga | C19: rod | D19: =INDEX(Inputs!$O$5:$O$132,MATCH($B19&"|"&$C19,Inputs!$A$5:$A$132,0)) | H19: =INDEX(Variables!$B$5:$B$45,MATCH($A19,Variables!$A$5:$A$45,0))&IF($C19="",""," | "&INDEX(Mapping!$B$5:$B$21,MATCH($C19,Mapping!$A$5:$A$21,0))&" | "&INDEX(Mapping!$B$24:$B$32,MATCH($B19,Mapping!$A$24:$A$32,0))) | I19: =INDEX(Variables!$C$5:$C$45,MATCH($A19,Variables!$A$5:$A$45,0)) | J19: =INDEX(Variables!$E$5:$E$45,MATCH($A19,Variables!$A$5:$A$45,0)) | K19: =LOWER(Settings!$C$4)&".mit."&$A19&IF($C19="","","."&$C19&"."&$B19)&IF(INDEX(Variables!$D$5:$D$45,MATCH($A19,Variables!$A$5:$A$45,0))="","","."&INDEX(Variables!$D$5:$D$45,MATCH($A19,Variables!$A$5:$A$45,0)))&"."&K$5 | L19: =INDEX(Inputs!$P$5:$P$132,MATCH($B19&"|"&$C19,Inputs!$A$5:$A$132,0)) | M19: =L19*(1+$D19) | N19: =M19*(1+$D19) | O19: =N19*(1+$D19) | P19: =O19*(1+$D19) | Q19: =P19*(1+$D19) | R19: =Q19*(1+$D19) | S19: =R19*(1+$D19) | T19: =S19*(1+$D19) | ... X19: =W19*(1+$D19) | Y19: =PRETAX(X19,$D19) | Z19: =LOWER(Settings!$C$4)&".mit."&$A19&IF($C19="","","."&$C19&"."&$B19)&IF(INDEX(Variables!$D$5:$D$45,MATCH($A19,Variables!$A$5:$A$45,0))="","","."&INDEX(Variables!$D$5:$D$45,MATCH($A19,Variables!$A$5:$A$45,0)))&"."&Z$5 | AA19: =INDEX(Inputs!$P$5:$P$132,MATCH($B19&"|"&$C19,Inputs!$A$5:$A$132,0)) | AB19: =AA19*(1+$D19) | AC19: =AB19*(1+$D19) | AD19: =AC19*(1+$D19) | AE19: =AD19*(1+$D19) | AF19: =AE19*(1+$D19) | AG19: =AF19*(1+$D19) | AH19: =AG19*(1+$D19) | AI19: =AH19*(1+$D19) | ... AM19: =AL19*(1+$D19) | AN19: =PRETAX(AM19,$D19)
A20: sp | B20: gso | C20: rod | D20: =INDEX(Inputs!$O$5:$O$132,MATCH($B20&"|"&$C20,Inputs!$A$5:$A$132,0)) | H20: =INDEX(Variables!$B$5:$B$45,MATCH($A20,Variables!$A$5:$A$45,0))&IF($C20="",""," | "&INDEX(Mapping!$B$5:$B$21,MATCH($C20,Mapping!$A$5:$A$21,0))&" | "&INDEX(Mapping!$B$24:$B$32,MATCH($B20,Mapping!$A$24:$A$32,0))) | I20: =INDEX(Variables!$C$5:$C$45,MATCH($A20,Variables!$A$5:$A$45,0)) | J20: =INDEX(Variables!$E$5:$E$45,MATCH($A20,Variables!$A$5:$A$45,0)) | K20: =LOWER(Settings!$C$4)&".mit."&$A20&IF($C20="","","."&$C20&"."&$B20)&IF(INDEX(Variables!$D$5:$D$45,MATCH($A20,Variables!$A$5:$A$45,0))="","","."&INDEX(Variables!$D$5:$D$45,MATCH($A20,Variables!$A$5:$A$45,0)))&"."&K$5 | L20: =INDEX(Inputs!$P$5:$P$132,MATCH($B20&"|"&$C20,Inputs!$A$5:$A$132,0)) | M20: =L20*(1+$D20) | N20: =M20*(1+$D20) | O20: =N20*(1+$D20) | P20: =O20*(1+$D20) | Q20: =P20*(1+$D20) | R20: =Q20*(1+$D20) | S20: =R20*(1+$D20) | T20: =S20*(1+$D20) | ... X20: =W20*(1+$D20) | Y20: =PRETAX(X20,$D20) | Z20: =LOWER(Settings!$C$4)&".mit."&$A20&IF($C20="","","."&$C20&"."&$B20)&IF(INDEX(Variables!$D$5:$D$45,MATCH($A20,Variables!$A$5:$A$45,0))="","","."&INDEX(Variables!$D$5:$D$45,MATCH($A20,Variables!$A$5:$A$45,0)))&"."&Z$5 | AA20: =INDEX(Inputs!$P$5:$P$132,MATCH($B20&"|"&$C20,Inputs!$A$5:$A$132,0)) | AB20: =AA20*(1+$D20) | AC20: =AB20*(1+$D20) | AD20: =AC20*(1+$D20) | AE20: =AD20*(1+$D20) | AF20: =AE20*(1+$D20) | AG20: =AF20*(1+$D20) | AH20: =AG20*(1+$D20) | AI20: =AH20*(1+$D20) | ... AM20: =AL20*(1+$D20) | AN20: =PRETAX(AM20,$D20)
A21: sp | B21: die | C21: rod | D21: =INDEX(Inputs!$O$5:$O$132,MATCH($B21&"|"&$C21,Inputs!$A$5:$A$132,0)) | H21: =INDEX(Variables!$B$5:$B$45,MATCH($A21,Variables!$A$5:$A$45,0))&IF($C21="",""," | "&INDEX(Mapping!$B$5:$B$21,MATCH($C21,Mapping!$A$5:$A$21,0))&" | "&INDEX(Mapping!$B$24:$B$32,MATCH($B21,Mapping!$A$24:$A$32,0))) | I21: =INDEX(Variables!$C$5:$C$45,MATCH($A21,Variables!$A$5:$A$45,0)) | J21: =INDEX(Variables!$E$5:$E$45,MATCH($A21,Variables!$A$5:$A$45,0)) | K21: =LOWER(Settings!$C$4)&".mit."&$A21&IF($C21="","","."&$C21&"."&$B21)&IF(INDEX(Variables!$D$5:$D$45,MATCH($A21,Variables!$A$5:$A$45,0))="","","."&INDEX(Variables!$D$5:$D$45,MATCH($A21,Variables!$A$5:$A$45,0)))&"."&K$5 | L21: =INDEX(Inputs!$P$5:$P$132,MATCH($B21&"|"&$C21,Inputs!$A$5:$A$132,0)) | M21: =L21*(1+$D21) | N21: =M21*(1+$D21) | O21: =N21*(1+$D21) | P21: =O21*(1+$D21) | Q21: =P21*(1+$D21) | R21: =Q21*(1+$D21) | S21: =R21*(1+$D21) | T21: =S21*(1+$D21) | ... X21: =W21*(1+$D21) | Y21: =PRETAX(X21,$D21) | Z21: =LOWER(Settings!$C$4)&".mit."&$A21&IF($C21="","","."&$C21&"."&$B21)&IF(INDEX(Variables!$D$5:$D$45,MATCH($A21,Variables!$A$5:$A$45,0))="","","."&INDEX(Variables!$D$5:$D$45,MATCH($A21,Variables!$A$5:$A$45,0)))&"."&Z$5 | AA21: =INDEX(Inputs!$P$5:$P$132,MATCH($B21&"|"&$C21,Inputs!$A$5:$A$132,0)) | AB21: =AA21*(1+$D21) | AC21: =AB21*(1+$D21) | AD21: =AC21*(1+$D21) | AE21: =AD21*(1+$D21) | AF21: =AE21*(1+$D21) | AG21: =AF21*(1+$D21) | AH21: =AG21*(1+$D21) | AI21: =AH21*(1+$D21) | ... AM21: =AL21*(1+$D21) | AN21: =PRETAX(AM21,$D21)
A22: sp | B22: lpg | C22: rod | D22: =INDEX(Inputs!$O$5:$O$132,MATCH($B22&"|"&$C22,Inputs!$A$5:$A$132,0)) | H22: =INDEX(Variables!$B$5:$B$45,MATCH($A22,Variables!$A$5:$A$45,0))&IF($C22="",""," | "&INDEX(Mapping!$B$5:$B$21,MATCH($C22,Mapping!$A$5:$A$21,0))&" | "&INDEX(Mapping!$B$24:$B$32,MATCH($B22,Mapping!$A$24:$A$32,0))) | I22: =INDEX(Variables!$C$5:$C$45,MATCH($A22,Variables!$A$5:$A$45,0)) | J22: =INDEX(Variables!$E$5:$E$45,MATCH($A22,Variables!$A$5:$A$45,0)) | K22: =LOWER(Settings!$C$4)&".mit."&$A22&IF($C22="","","."&$C22&"."&$B22)&IF(INDEX(Variables!$D$5:$D$45,MATCH($A22,Variables!$A$5:$A$45,0))="","","."&INDEX(Variables!$D$5:$D$45,MATCH($A22,Variables!$A$5:$A$45,0)))&"."&K$5 | L22: =INDEX(Inputs!$P$5:$P$132,MATCH($B22&"|"&$C22,Inputs!$A$5:$A$132,0)) | M22: =L22*(1+$D22) | N22: =M22*(1+$D22) | O22: =N22*(1+$D22) | P22: =O22*(1+$D22) | Q22: =P22*(1+$D22) | R22: =Q22*(1+$D22) | S22: =R22*(1+$D22) | T22: =S22*(1+$D22) | ... X22: =W22*(1+$D22) | Y22: =PRETAX(X22,$D22) | Z22: =LOWER(Settings!$C$4)&".mit."&$A22&IF($C22="","","."&$C22&"."&$B22)&IF(INDEX(Variables!$D$5:$D$45,MATCH($A22,Variables!$A$5:$A$45,0))="","","."&INDEX(Variables!$D$5:$D$45,MATCH($A22,Variables!$A$5:$A$45,0)))&"."&Z$5 | AA22: =INDEX(Inputs!$P$5:$P$132,MATCH($B22&"|"&$C22,Inputs!$A$5:$A$132,0)) | AB22: =AA22*(1+$D22) | AC22: =AB22*(1+$D22) | AD22: =AC22*(1+$D22) | AE22: =AD22*(1+$D22) | AF22: =AE22*(1+$D22) | AG22: =AF22*(1+$D22) | AH22: =AG22*(1+$D22) | AI22: =AH22*(1+$D22) | ... AM22: =AL22*(1+$D22) | AN22: =PRETAX(AM22,$D22)
A23: sp | B23: ker | C23: rod | D23: =INDEX(Inputs!$O$5:$O$132,MATCH($B23&"|"&$C23,Inputs!$A$5:$A$132,0)) | H23: =INDEX(Variables!$B$5:$B$45,MATCH($A23,Variables!$A$5:$A$45,0))&IF($C23="",""," | "&INDEX(Mapping!$B$5:$B$21,MATCH($C23,Mapping!$A$5:$A$21,0))&" | "&INDEX(Mapping!$B$24:$B$32,MATCH($B23,Mapping!$A$24:$A$32,0))) | I23: =INDEX(Variables!$C$5:$C$45,MATCH($A23,Variables!$A$5:$A$45,0)) | J23: =INDEX(Variables!$E$5:$E$45,MATCH($A23,Variables!$A$5:$A$45,0)) | K23: =LOWER(Settings!$C$4)&".mit."&$A23&IF($C23="","","."&$C23&"."&$B23)&IF(INDEX(Variables!$D$5:$D$45,MATCH($A23,Variables!$A$5:$A$45,0))="","","."&INDEX(Variables!$D$5:$D$45,MATCH($A23,Variables!$A$5:$A$45,0)))&"."&K$5 | L23: =INDEX(Inputs!$P$5:$P$132,MATCH($B23&"|"&$C23,Inputs!$A$5:$A$132,0)) | M23: =L23*(1+$D23) | N23: =M23*(1+$D23) | O23: =N23*(1+$D23) | P23: =O23*(1+$D23) | Q23: =P23*(1+$D23) | R23: =Q23*(1+$D23) | S23: =R23*(1+$D23) | T23: =S23*(1+$D23) | ... X23: =W23*(1+$D23) | Y23: =PRETAX(X23,$D23) | Z23: =LOWER(Settings!$C$4)&".mit."&$A23&IF($C23="","","."&$C23&"."&$B23)&IF(INDEX(Variables!$D$5:$D$45,MATCH($A23,Variables!$A$5:$A$45,0))="","","."&INDEX(Variables!$D$5:$D$45,MATCH($A23,Variables!$A$5:$A$45,0)))&"."&Z$5 | AA23: =INDEX(Inputs!$P$5:$P$132,MATCH($B23&"|"&$C23,Inputs!$A$5:$A$132,0)) | AB23: =AA23*(1+$D23) | AC23: =AB23*(1+$D23) | AD23: =AC23*(1+$D23) | AE23: =AD23*(1+$D23) | AF23: =AE23*(1+$D23) | AG23: =AF23*(1+$D23) | AH23: =AG23*(1+$D23) | AI23: =AH23*(1+$D23) | ... AM23: =AL23*(1+$D23) | AN23: =PRETAX(AM23,$D23)
A24: sp | B24: oop | C24: rod | D24: =INDEX(Inputs!$O$5:$O$132,MATCH($B24&"|"&$C24,Inputs!$A$5:$A$132,0)) | H24: =INDEX(Variables!$B$5:$B$45,MATCH($A24,Variables!$A$5:$A$45,0))&IF($C24="",""," | "&INDEX(Mapping!$B$5:$B$21,MATCH($C24,Mapping!$A$5:$A$21,0))&" | "&INDEX(Mapping!$B$24:$B$32,MATCH($B24,Mapping!$A$24:$A$32,0))) | I24: =INDEX(Variables!$C$5:$C$45,MATCH($A24,Variables!$A$5:$A$45,0)) | J24: =INDEX(Variables!$E$5:$E$45,MATCH($A24,Variables!$A$5:$A$45,0)) | K24: =LOWER(Settings!$C$4)&".mit."&$A24&IF($C24="","","."&$C24&"."&$B24)&IF(INDEX(Variables!$D$5:$D$45,MATCH($A24,Variables!$A$5:$A$45,0))="","","."&INDEX(Variables!$D$5:$D$45,MATCH($A24,Variables!$A$5:$A$45,0)))&"."&K$5 | L24: =INDEX(Inputs!$P$5:$P$132,MATCH($B24&"|"&$C24,Inputs!$A$5:$A$132,0)) | M24: =L24*(1+$D24) | N24: =M24*(1+$D24) | O24: =N24*(1+$D24) | P24: =O24*(1+$D24) | Q24: =P24*(1+$D24) | R24: =Q24*(1+$D24) | S24: =R24*(1+$D24) | T24: =S24*(1+$D24) | ... X24: =W24*(1+$D24) | Y24: =PRETAX(X24,$D24) | Z24: =LOWER(Settings!$C$4)&".mit."&$A24&IF($C24="","","."&$C24&"."&$B24)&IF(INDEX(Variables!$D$5:$D$45,MATCH($A24,Variables!$A$5:$A$45,0))="","","."&INDEX(Variables!$D$5:$D$45,MATCH($A24,Variables!$A$5:$A$45,0)))&"."&Z$5 | AA24: =INDEX(Inputs!$P$5:$P$132,MATCH($B24&"|"&$C24,Inputs!$A$5:$A$132,0)) | AB24: =AA24*(1+$D24) | AC24: =AB24*(1+$D24) | AD24: =AC24*(1+$D24) | AE24: =AD24*(1+$D24) | AF24: =AE24*(1+$D24) | AG24: =AF24*(1+$D24) | AH24: =AG24*(1+$D24) | AI24: =AH24*(1+$D24) | ... AM24: =AL24*(1+$D24) | AN24: =PRETAX(AM24,$D24)
A25: sp | B25: bio | C25: rod | D25: =INDEX(Inputs!$O$5:$O$132,MATCH($B25&"|"&$C25,Inputs!$A$5:$A$132,0)) | H25: =INDEX(Variables!$B$5:$B$45,MATCH($A25,Variables!$A$5:$A$45,0))&IF($C25="",""," | "&INDEX(Mapping!$B$5:$B$21,MATCH($C25,Mapping!$A$5:$A$21,0))&" | "&INDEX(Mapping!$B$24:$B$32,MATCH($B25,Mapping!$A$24:$A$32,0))) | I25: =INDEX(Variables!$C$5:$C$45,MATCH($A25,Variables!$A$5:$A$45,0)) | J25: =INDEX(Variables!$E$5:$E$45,MATCH($A25,Variables!$A$5:$A$45,0)) | K25: =LOWER(Settings!$C$4)&".mit."&$A25&IF($C25="","","."&$C25&"."&$B25)&IF(INDEX(Variables!$D$5:$D$45,MATCH($A25,Variables!$A$5:$A$45,0))="","","."&INDEX(Variables!$D$5:$D$45,MATCH($A25,Variables!$A$5:$A$45,0)))&"."&K$5 | L25: =INDEX(Inputs!$P$5:$P$132,MATCH($B25&"|"&$C25,Inputs!$A$5:$A$132,0)) | M25: =L25*(1+$D25) | N25: =M25*(1+$D25) | O25: =N25*(1+$D25) | P25: =O25*(1+$D25) | Q25: =P25*(1+$D25) | R25: =Q25*(1+$D25) | S25: =R25*(1+$D25) | T25: =S25*(1+$D25) | ... X25: =W25*(1+$D25) | Y25: =PRETAX(X25,$D25) | Z25: =LOWER(Settings!$C$4)&".mit."&$A25&IF($C25="","","."&$C25&"."&$B25)&IF(INDEX(Variables!$D$5:$D$45,MATCH($A25,Variables!$A$5:$A$45,0))="","","."&INDEX(Variables!$D$5:$D$45,MATCH($A25,Variables!$A$5:$A$45,0)))&"."&Z$5 | AA25: =INDEX(Inputs!$P$5:$P$132,MATCH($B25&"|"&$C25,Inputs!$A$5:$A$132,0)) | AB25: =AA25*(1+$D25) | AC25: =AB25*(1+$D25) | AD25: =AC25*(1+$D25) | AE25: =AD25*(1+$D25) | AF25: =AE25*(1+$D25) | AG25: =AF25*(1+$D25) | AH25: =AG25*(1+$D25) | AI25: =AH25*(1+$D25) | ... AM25: =AL25*(1+$D25) | AN25: =PRETAX(AM25,$D25)
A26: sp | B26: coa | C26: ral | D26: =INDEX(Inputs!$O$5:$O$132,MATCH($B26&"|"&$C26,Inputs!$A$5:$A$132,0)) | H26: =INDEX(Variables!$B$5:$B$45,MATCH($A26,Variables!$A$5:$A$45,0))&IF($C26="",""," | "&INDEX(Mapping!$B$5:$B$21,MATCH($C26,Mapping!$A$5:$A$21,0))&" | "&INDEX(Mapping!$B$24:$B$32,MATCH($B26,Mapping!$A$24:$A$32,0))) | I26: =INDEX(Variables!$C$5:$C$45,MATCH($A26,Variables!$A$5:$A$45,0)) | J26: =INDEX(Variables!$E$5:$E$45,MATCH($A26,Variables!$A$5:$A$45,0)) | K26: =LOWER(Settings!$C$4)&".mit."&$A26&IF($C26="","","."&$C26&"."&$B26)&IF(INDEX(Variables!$D$5:$D$45,MATCH($A26,Variables!$A$5:$A$45,0))="","","."&INDEX(Variables!$D$5:$D$45,MATCH($A26,Variables!$A$5:$A$45,0)))&"."&K$5 | L26: =INDEX(Inputs!$P$5:$P$132,MATCH($B26&"|"&$C26,Inputs!$A$5:$A$132,0)) | M26: =L26*(1+$D26) | N26: =M26*(1+$D26) | O26: =N26*(1+$D26) | P26: =O26*(1+$D26) | Q26: =P26*(1+$D26) | R26: =Q26*(1+$D26) | S26: =R26*(1+$D26) | T26: =S26*(1+$D26) | ... X26: =W26*(1+$D26) | Y26: =PRETAX(X26,$D26) | Z26: =LOWER(Settings!$C$4)&".mit."&$A26&IF($C26="","","."&$C26&"."&$B26)&IF(INDEX(Variables!$D$5:$D$45,MATCH($A26,Variables!$A$5:$A$45,0))="","","."&INDEX(Variables!$D$5:$D$45,MATCH($A26,Variables!$A$5:$A$45,0)))&"."&Z$5 | AA26: =INDEX(Inputs!$P$5:$P$132,MATCH($B26&"|"&$C26,Inputs!$A$5:$A$132,0)) | AB26: =AA26*(1+$D26) | AC26: =AB26*(1+$D26) | AD26: =AC26*(1+$D26) | AE26: =AD26*(1+$D26) | AF26: =AE26*(1+$D26) | AG26: =AF26*(1+$D26) | AH26: =AG26*(1+$D26) | AI26: =AH26*(1+$D26) | ... AM26: =AL26*(1+$D26) | AN26: =PRETAX(AM26,$D26)
A27: sp | B27: nga | C27: ral | D27: =INDEX(Inputs!$O$5:$O$132,MATCH($B27&"|"&$C27,Inputs!$A$5:$A$132,0)) | H27: =INDEX(Variables!$B$5:$B$45,MATCH($A27,Variables!$A$5:$A$45,0))&IF($C27="",""," | "&INDEX(Mapping!$B$5:$B$21,MATCH($C27,Mapping!$A$5:$A$21,0))&" | "&INDEX(Mapping!$B$24:$B$32,MATCH($B27,Mapping!$A$24:$A$32,0))) | I27: =INDEX(Variables!$C$5:$C$45,MATCH($A27,Variables!$A$5:$A$45,0)) | J27: =INDEX(Variables!$E$5:$E$45,MATCH($A27,Variables!$A$5:$A$45,0)) | K27: =LOWER(Settings!$C$4)&".mit."&$A27&IF($C27="","","."&$C27&"."&$B27)&IF(INDEX(Variables!$D$5:$D$45,MATCH($A27,Variables!$A$5:$A$45,0))="","","."&INDEX(Variables!$D$5:$D$45,MATCH($A27,Variables!$A$5:$A$45,0)))&"."&K$5 | L27: =INDEX(Inputs!$P$5:$P$132,MATCH($B27&"|"&$C27,Inputs!$A$5:$A$132,0)) | M27: =L27*(1+$D27) | N27: =M27*(1+$D27) | O27: =N27*(1+$D27) | P27: =O27*(1+$D27) | Q27: =P27*(1+$D27) | R27: =Q27*(1+$D27) | S27: =R27*(1+$D27) | T27: =S27*(1+$D27) | ... X27: =W27*(1+$D27) | Y27: =PRETAX(X27,$D27) | Z27: =LOWER(Settings!$C$4)&".mit."&$A27&IF($C27="","","."&$C27&"."&$B27)&IF(INDEX(Variables!$D$5:$D$45,MATCH($A27,Variables!$A$5:$A$45,0))="","","."&INDEX(Variables!$D$5:$D$45,MATCH($A27,Variables!$A$5:$A$45,0)))&"."&Z$5 | AA27: =INDEX(Inputs!$P$5:$P$132,MATCH($B27&"|"&$C27,Inputs!$A$5:$A$132,0)) | AB27: =AA27*(1+$D27) | AC27: =AB27*(1+$D27) | AD27: =AC27*(1+$D27) | AE27: =AD27*(1+$D27) | AF27: =AE27*(1+$D27) | AG27: =AF27*(1+$D27) | AH27: =AG27*(1+$D27) | AI27: =AH27*(1+$D27) | ... AM27: =AL27*(1+$D27) | AN27: =PRETAX(AM27,$D27)
A28: sp | B28: gso | C28: ral | D28: =INDEX(Inputs!$O$5:$O$132,MATCH($B28&"|"&$C28,Inputs!$A$5:$A$132,0)) | H28: =INDEX(Variables!$B$5:$B$45,MATCH($A28,Variables!$A$5:$A$45,0))&IF($C28="",""," | "&INDEX(Mapping!$B$5:$B$21,MATCH($C28,Mapping!$A$5:$A$21,0))&" | "&INDEX(Mapping!$B$24:$B$32,MATCH($B28,Mapping!$A$24:$A$32,0))) | I28: =INDEX(Variables!$C$5:$C$45,MATCH($A28,Variables!$A$5:$A$45,0)) | J28: =INDEX(Variables!$E$5:$E$45,MATCH($A28,Variables!$A$5:$A$45,0)) | K28: =LOWER(Settings!$C$4)&".mit."&$A28&IF($C28="","","."&$C28&"."&$B28)&IF(INDEX(Variables!$D$5:$D$45,MATCH($A28,Variables!$A$5:$A$45,0))="","","."&INDEX(Variables!$D$5:$D$45,MATCH($A28,Variables!$A$5:$A$45,0)))&"."&K$5 | L28: =INDEX(Inputs!$P$5:$P$132,MATCH($B28&"|"&$C28,Inputs!$A$5:$A$132,0)) | M28: =L28*(1+$D28) | N28: =M28*(1+$D28) | O28: =N28*(1+$D28) | P28: =O28*(1+$D28) | Q28: =P28*(1+$D28) | R28: =Q28*(1+$D28) | S28: =R28*(1+$D28) | T28: =S28*(1+$D28) | ... X28: =W28*(1+$D28) | Y28: =PRETAX(X28,$D28) | Z28: =LOWER(Settings!$C$4)&".mit."&$A28&IF($C28="","","."&$C28&"."&$B28)&IF(INDEX(Variables!$D$5:$D$45,MATCH($A28,Variables!$A$5:$A$45,0))="","","."&INDEX(Variables!$D$5:$D$45,MATCH($A28,Variables!$A$5:$A$45,0)))&"."&Z$5 | AA28: =INDEX(Inputs!$P$5:$P$132,MATCH($B28&"|"&$C28,Inputs!$A$5:$A$132,0)) | AB28: =AA28*(1+$D28) | AC28: =AB28*(1+$D28) | AD28: =AC28*(1+$D28) | AE28: =AD28*(1+$D28) | AF28: =AE28*(1+$D28) | AG28: =AF28*(1+$D28) | AH28: =AG28*(1+$D28) | AI28: =AH28*(1+$D28) | ... AM28: =AL28*(1+$D28) | AN28: =PRETAX(AM28,$D28)
A29: sp | B29: die | C29: ral | D29: =INDEX(Inputs!$O$5:$O$132,MATCH($B29&"|"&$C29,Inputs!$A$5:$A$132,0)) | H29: =INDEX(Variables!$B$5:$B$45,MATCH($A29,Variables!$A$5:$A$45,0))&IF($C29="",""," | "&INDEX(Mapping!$B$5:$B$21,MATCH($C29,Mapping!$A$5:$A$21,0))&" | "&INDEX(Mapping!$B$24:$B$32,MATCH($B29,Mapping!$A$24:$A$32,0))) | I29: =INDEX(Variables!$C$5:$C$45,MATCH($A29,Variables!$A$5:$A$45,0)) | J29: =INDEX(Variables!$E$5:$E$45,MATCH($A29,Variables!$A$5:$A$45,0)) | K29: =LOWER(Settings!$C$4)&".mit."&$A29&IF($C29="","","."&$C29&"."&$B29)&IF(INDEX(Variables!$D$5:$D$45,MATCH($A29,Variables!$A$5:$A$45,0))="","","."&INDEX(Variables!$D$5:$D$45,MATCH($A29,Variables!$A$5:$A$45,0)))&"."&K$5 | L29: =INDEX(Inputs!$P$5:$P$132,MATCH($B29&"|"&$C29,Inputs!$A$5:$A$132,0)) | M29: =L29*(1+$D29) | N29: =M29*(1+$D29) | O29: =N29*(1+$D29) | P29: =O29*(1+$D29) | Q29: =P29*(1+$D29) | R29: =Q29*(1+$D29) | S29: =R29*(1+$D29) | T29: =S29*(1+$D29) | ... X29: =W29*(1+$D29) | Y29: =PRETAX(X29,$D29) | Z29: =LOWER(Settings!$C$4)&".mit."&$A29&IF($C29="","","."&$C29&"."&$B29)&IF(INDEX(Variables!$D$5:$D$45,MATCH($A29,Variables!$A$5:$A$45,0))="","","."&INDEX(Variables!$D$5:$D$45,MATCH($A29,Variables!$A$5:$A$45,0)))&"."&Z$5 | AA29: =INDEX(Inputs!$P$5:$P$132,MATCH($B29&"|"&$C29,Inputs!$A$5:$A$132,0)) | AB29: =AA29*(1+$D29) | AC29: =AB29*(1+$D29) | AD29: =AC29*(1+$D29) | AE29: =AD29*(1+$D29) | AF29: =AE29*(1+$D29) | AG29: =AF29*(1+$D29) | AH29: =AG29*(1+$D29) | AI29: =AH29*(1+$D29) | ... AM29: =AL29*(1+$D29) | AN29: =PRETAX(AM29,$D29)
... A145: sp | B145: bio | C145: oen | D145: =INDEX(Inputs!$O$5:$O$132,MATCH($B145&"|"&$C145,Inputs!$A$5:$A$132,0)) | H145: =INDEX(Variables!$B$5:$B$45,MATCH($A145,Variables!$A$5:$A$45,0))&IF($C145="",""," | "&INDEX(Mapping!$B$5:$B$21,MATCH($C145,Mapping!$A$5:$A$21,0))&" | "&INDEX(Mapping!$B$24:$B$32,MATCH($B145,Mapping!$A$24:$A$32,0))) | I145: =INDEX(Variables!$C$5:$C$45,MATCH($A145,Variables!$A$5:$A$45,0)) | J145: =INDEX(Variables!$E$5:$E$45,MATCH($A145,Variables!$A$5:$A$45,0)) | K145: =LOWER(Settings!$C$4)&".mit."&$A145&IF($C145="","","."&$C145&"."&$B145)&IF(INDEX(Variables!$D$5:$D$45,MATCH($A145,Variables!$A$5:$A$45,0))="","","."&INDEX(Variables!$D$5:$D$45,MATCH($A145,Variables!$A$5:$A$45,0)))&"."&K$5 | L145: =INDEX(Inputs!$P$5:$P$132,MATCH($B145&"|"&$C145,Inputs!$A$5:$A$132,0)) | M145: =L145*(1+$D145) | N145: =M145*(1+$D145) | O145: =N145*(1+$D145) | P145: =O145*(1+$D145) | Q145: =P145*(1+$D145) | R145: =Q145*(1+$D145) | S145: =R145*(1+$D145) | T145: =S145*(1+$D145) | ... X145: =W145*(1+$D145) | Y145: =PRETAX(X145,$D145) | Z145: =LOWER(Settings!$C$4)&".mit."&$A145&IF($C145="","","."&$C145&"."&$B145)&IF(INDEX(Variables!$D$5:$D$45,MATCH($A145,Variables!$A$5:$A$45,0))="","","."&INDEX(Variables!$D$5:$D$45,MATCH($A145,Variables!$A$5:$A$45,0)))&"."&Z$5 | AA145: =INDEX(Inputs!$P$5:$P$132,MATCH($B145&"|"&$C145,Inputs!$A$5:$A$132,0)) | AB145: =AA145*(1+$D145) | AC145: =AB145*(1+$D145) | AD145: =AC145*(1+$D145) | AE145: =AD145*(1+$D145) | AF145: =AE145*(1+$D145) | AG145: =AF145*(1+$D145) | AH145: =AG145*(1+$D145) | AI145: =AH145*(1+$D145) | ... AM145: =AL145*(1+$D145) | AN145: =PRETAX(AM145,$D145)
A147: Tax: base tax + carbon price x EF x coverage | D147: base tax | E147: EF | F147: coverage
A148: cptraj.ref | H148: =INDEX(Variables!$B$5:$B$45,MATCH($A148,Variables!$A$5:$A$45,0))&IF($C148="",""," | "&INDEX(Mapping!$B$5:$B$21,MATCH($C148,Mapping!$A$5:$A$21,0))&" | "&INDEX(Mapping!$B$24:$B$32,MATCH($B148,Mapping!$A$24:$A$32,0))) | I148: =INDEX(Variables!$C$5:$C$45,MATCH($A148,Variables!$A$5:$A$45,0)) | J148: =INDEX(Variables!$E$5:$E$45,MATCH($A148,Variables!$A$5:$A$45,0)) | K148: =LOWER(Settings!$C$4)&".mit."&$A148&IF($C148="","","."&$C148&"."&$B148)&IF(INDEX(Variables!$D$5:$D$45,MATCH($A148,Variables!$A$5:$A$45,0))="","","."&INDEX(Variables!$D$5:$D$45,MATCH($A148,Variables!$A$5:$A$45,0)))&"."&K$5 | L148: =L$14 | M148: =M$14 | N148: =N$14 | O148: =O$14 | P148: =P$14 | Q148: =Q$14 | R148: =R$14 | S148: =S$14 | ... Y148: =Y$14 | Z148: =LOWER(Settings!$C$4)&".mit."&$A148&IF($C148="","","."&$C148&"."&$B148)&IF(INDEX(Variables!$D$5:$D$45,MATCH($A148,Variables!$A$5:$A$45,0))="","","."&INDEX(Variables!$D$5:$D$45,MATCH($A148,Variables!$A$5:$A$45,0)))&"."&Z$5 | AA148: =AA$14 | AB148: =AB$14 | AC148: =AC$14 | AD148: =AD$14 | AE148: =AE$14 | AF148: =AF$14 | AG148: =AG$14 | AH148: =AH$14 | ... AN148: =AN$14
A149: tax | B149: coa | C149: rod | D149: =INDEX(Inputs!$Q$5:$Q$132,MATCH($B149&"|"&$C149,Inputs!$A$5:$A$132,0)) | E149: =INDEX(Inputs!$R$5:$R$132,MATCH($B149&"|"&$C149,Inputs!$A$5:$A$132,0)) | F149: =INDEX(Inputs!$J$5:$J$132,MATCH($B149&"|"&$C149,Inputs!$A$5:$A$132,0)) | H149: =INDEX(Variables!$B$5:$B$45,MATCH($A149,Variables!$A$5:$A$45,0))&IF($C149="",""," | "&INDEX(Mapping!$B$5:$B$21,MATCH($C149,Mapping!$A$5:$A$21,0))&" | "&INDEX(Mapping!$B$24:$B$32,MATCH($B149,Mapping!$A$24:$A$32,0))) | I149: =INDEX(Variables!$C$5:$C$45,MATCH($A149,Variables!$A$5:$A$45,0)) | J149: =INDEX(Variables!$E$5:$E$45,MATCH($A149,Variables!$A$5:$A$45,0)) | K149: =LOWER(Settings!$C$4)&".mit."&$A149&IF($C149="","","."&$C149&"."&$B149)&IF(INDEX(Variables!$D$5:$D$45,MATCH($A149,Variables!$A$5:$A$45,0))="","","."&INDEX(Variables!$D$5:$D$45,MATCH($A149,Variables!$A$5:$A$45,0)))&"."&K$5 | L149: =$D149+L$14*$E149*$F149 | M149: =$D149+M$14*$E149*$F149 | N149: =$D149+N$14*$E149*$F149 | O149: =$D149+O$14*$E149*$F149 | P149: =$D149+P$14*$E149*$F149 | Q149: =$D149+Q$14*$E149*$F149 | R149: =$D149+R$14*$E149*$F149 | S149: =$D149+S$14*$E149*$F149 | ... X149: =$D149+X$14*$E149*$F149 | Y149: =TAX($D149,Y$14,$E149,$F149) | Z149: =LOWER(Settings!$C$4)&".mit."&$A149&IF($C149="","","."&$C149&"."&$B149)&IF(INDEX(Variables!$D$5:$D$45,MATCH($A149,Variables!$A$5:$A$45,0))="","","."&INDEX(Variables!$D$5:$D$45,MATCH($A149,Variables!$A$5:$A$45,0)))&"."&Z$5 | AA149: =$D149+AA$14*$E149*$F149 | AB149: =$D149+AB$14*$E149*$F149 | AC149: =$D149+AC$14*$E149*$F149 | AD149: =$D149+AD$14*$E149*$F149 | AE149: =$D149+AE$14*$E149*$F149 | AF149: =$D149+AF$14*$E149*$F149 | AG149: =$D149+AG$14*$E149*$F149 | AH149: =$D149+AH$14*$E149*$F149 | ... AM149: =$D149+AM$14*$E149*$F149 | AN149: =TAX($D149,AN$14,$E149,$F149)
A150: tax | B150: nga | C150: rod | D150: =INDEX(Inputs!$Q$5:$Q$132,MATCH($B150&"|"&$C150,Inputs!$A$5:$A$132,0)) | E150: =INDEX(Inputs!$R$5:$R$132,MATCH($B150&"|"&$C150,Inputs!$A$5:$A$132,0)) | F150: =INDEX(Inputs!$J$5:$J$132,MATCH($B150&"|"&$C150,Inputs!$A$5:$A$132,0)) | H150: =INDEX(Variables!$B$5:$B$45,MATCH($A150,Variables!$A$5:$A$45,0))&IF($C150="",""," | "&INDEX(Mapping!$B$5:$B$21,MATCH($C150,Mapping!$A$5:$A$21,0))&" | "&INDEX(Mapping!$B$24:$B$32,MATCH($B150,Mapping!$A$24:$A$32,0))) | I150: =INDEX(Variables!$C$5:$C$45,MATCH($A150,Variables!$A$5:$A$45,0)) | J150: =INDEX(Variables!$E$5:$E$45,MATCH($A150,Variables!$A$5:$A$45,0)) | K150: =LOWER(Settings!$C$4)&".mit."&$A150&IF($C150="","","."&$C150&"."&$B150)&IF(INDEX(Variables!$D$5:$D$45,MATCH($A150,Variables!$A$5:$A$45,0))="","","."&INDEX(Variables!$D$5:$D$45,MATCH($A150,Variables!$A$5:$A$45,0)))&"."&K$5 | L150: =$D150+L$14*$E150*$F150 | M150: =$D150+M$14*$E150*$F150 | N150: =$D150+N$14*$E150*$F150 | O150: =$D150+O$14*$E150*$F150 | P150: =$D150+P$14*$E150*$F150 | Q150: =$D150+Q$14*$E150*$F150 | R150: =$D150+R$14*$E150*$F150 | S150: =$D150+S$14*$E150*$F150 | ... X150: =$D150+X$14*$E150*$F150 | Y150: =TAX($D150,Y$14,$E150,$F150) | Z150: =LOWER(Settings!$C$4)&".mit."&$A150&IF($C150="","","."&$C150&"."&$B150)&IF(INDEX(Variables!$D$5:$D$45,MATCH($A150,Variables!$A$5:$A$45,0))="","","."&INDEX(Variables!$D$5:$D$45,MATCH($A150,Variables!$A$5:$A$45,0)))&"."&Z$5 | AA150: =$D150+AA$14*$E150*$F150 | AB150: =$D150+AB$14*$E150*$F150 | AC150: =$D150+AC$14*$E150*$F150 | AD150: =$D150+AD$14*$E150*$F150 | AE150: =$D150+AE$14*$E150*$F150 | AF150: =$D150+AF$14*$E150*$F150 | AG150: =$D150+AG$14*$E150*$F150 | AH150: =$D150+AH$14*$E150*$F150 | ... AM150: =$D150+AM$14*$E150*$F150 | AN150: =TAX($D150,AN$14,$E150,$F150)
A151: tax | B151: gso | C151: rod | D151: =INDEX(Inputs!$Q$5:$Q$132,MATCH($B151&"|"&$C151,Inputs!$A$5:$A$132,0)) | E151: =INDEX(Inputs!$R$5:$R$132,MATCH($B151&"|"&$C151,Inputs!$A$5:$A$132,0)) | F151: =INDEX(Inputs!$J$5:$J$132,MATCH($B151&"|"&$C151,Inputs!$A$5:$A$132,0)) | H151: =INDEX(Variables!$B$5:$B$45,MATCH($A151,Variables!$A$5:$A$45,0))&IF($C151="",""," | "&INDEX(Mapping!$B$5:$B$21,MATCH($C151,Mapping!$A$5:$A$21,0))&" | "&INDEX(Mapping!$B$24:$B$32,MATCH($B151,Mapping!$A$24:$A$32,0))) | I151: =INDEX(Variables!$C$5:$C$45,MATCH($A151,Variables!$A$5:$A$45,0)) | J151: =INDEX(Variables!$E$5:$E$45,MATCH($A151,Variables!$A$5:$A$45,0)) | K151: =LOWER(Settings!$C$4)&".mit."&$A151&IF($C151="","","."&$C151&"."&$B151)&IF(INDEX(Variables!$D$5:$D$45,MATCH($A151,Variables!$A$5:$A$45,0))="","","."&INDEX(Variables!$D$5:$D$45,MATCH($A151,Variables!$A$5:$A$45,0)))&"."&K$5 | L151: =$D151+L$14*$E151*$F151 | M151: =$D151+M$14*$E151*$F151 | N151: =$D151+N$14*$E151*$F151 | O151: =$D151+O$14*$E151*$F151 | P151: =$D151+P$14*$E151*$F151 | Q151: =$D151+Q$14*$E151*$F151 | R151: =$D151+R$14*$E151*$F151 | S151: =$D151+S$14*$E151*$F151 | ... X151: =$D151+X$14*$E151*$F151 | Y151: =TAX($D151,Y$14,$E151,$F151) | Z151: =LOWER(Settings!$C$4)&".mit."&$A151&IF($C151="","","."&$C151&"."&$B151)&IF(INDEX(Variables!$D$5:$D$45,MATCH($A151,Variables!$A$5:$A$45,0))="","","."&INDEX(Variables!$D$5:$D$45,MATCH($A151,Variables!$A$5:$A$45,0)))&"."&Z$5 | AA151: =$D151+AA$14*$E151*$F151 | AB151: =$D151+AB$14*$E151*$F151 | AC151: =$D151+AC$14*$E151*$F151 | AD151: =$D151+AD$14*$E151*$F151 | AE151: =$D151+AE$14*$E151*$F151 | AF151: =$D151+AF$14*$E151*$F151 | AG151: =$D151+AG$14*$E151*$F151 | AH151: =$D151+AH$14*$E151*$F151 | ... AM151: =$D151+AM$14*$E151*$F151 | AN151: =TAX($D151,AN$14,$E151,$F151)
A152: tax | B152: die | C152: rod | D152: =INDEX(Inputs!$Q$5:$Q$132,MATCH($B152&"|"&$C152,Inputs!$A$5:$A$132,0)) | E152: =INDEX(Inputs!$R$5:$R$132,MATCH($B152&"|"&$C152,Inputs!$A$5:$A$132,0)) | F152: =INDEX(Inputs!$J$5:$J$132,MATCH($B152&"|"&$C152,Inputs!$A$5:$A$132,0)) | H152: =INDEX(Variables!$B$5:$B$45,MATCH($A152,Variables!$A$5:$A$45,0))&IF($C152="",""," | "&INDEX(Mapping!$B$5:$B$21,MATCH($C152,Mapping!$A$5:$A$21,0))&" | "&INDEX(Mapping!$B$24:$B$32,MATCH($B152,Mapping!$A$24:$A$32,0))) | I152: =INDEX(Variables!$C$5:$C$45,MATCH($A152,Variables!$A$5:$A$45,0)) | J152: =INDEX(Variables!$E$5:$E$45,MATCH($A152,Variables!$A$5:$A$45,0)) | K152: =LOWER(Settings!$C$4)&".mit."&$A152&IF($C152="","","."&$C152&"."&$B152)&IF(INDEX(Variables!$D$5:$D$45,MATCH($A152,Variables!$A$5:$A$45,0))="","","."&INDEX(Variables!$D$5:$D$45,MATCH($A152,Variables!$A$5:$A$45,0)))&"."&K$5 | L152: =$D152+L$14*$E152*$F152 | M152: =$D152+M$14*$E152*$F152 | N152: =$D152+N$14*$E152*$F152 | O152: =$D152+O$14*$E152*$F152 | P152: =$D152+P$14*$E152*$F152 | Q152: =$D152+Q$14*$E152*$F152 | R152: =$D152+R$14*$E152*$F152 | S152: =$D152+S$14*$E152*$F152 | ... X152: =$D152+X$14*$E152*$F152 | Y152: =TAX($D152,Y$14,$E152,$F152) | Z152: =LOWER(Settings!$C$4)&".mit."&$A152&IF($C152="","","."&$C152&"."&$B152)&IF(INDEX(Variables!$D$5:$D$45,MATCH($A152,Variables!$A$5:$A$45,0))="","","."&INDEX(Variables!$D$5:$D$45,MATCH($A152,Variables!$A$5:$A$45,0)))&"."&Z$5 | AA152: =$D152+AA$14*$E152*$F152 | AB152: =$D152+AB$14*$E152*$F152 | AC152: =$D152+AC$14*$E152*$F152 | AD152: =$D152+AD$14*$E152*$F152 | AE152: =$D152+AE$14*$E152*$F152 | AF152: =$D152+AF$14*$E152*$F152 | AG152: =$D152+AG$14*$E152*$F152 | AH152: =$D152+AH$14*$E152*$F152 | ... AM152: =$D152+AM$14*$E152*$F152 | AN152: =TAX($D152,AN$14,$E152,$F152)
A153: tax | B153: lpg | C153: rod | D153: =INDEX(Inputs!$Q$5:$Q$132,MATCH($B153&"|"&$C153,Inputs!$A$5:$A$132,0)) | E153: =INDEX(Inputs!$R$5:$R$132,MATCH($B153&"|"&$C153,Inputs!$A$5:$A$132,0)) | F153: =INDEX(Inputs!$J$5:$J$132,MATCH($B153&"|"&$C153,Inputs!$A$5:$A$132,0)) | H153: =INDEX(Variables!$B$5:$B$45,MATCH($A153,Variables!$A$5:$A$45,0))&IF($C153="",""," | "&INDEX(Mapping!$B$5:$B$21,MATCH($C153,Mapping!$A$5:$A$21,0))&" | "&INDEX(Mapping!$B$24:$B$32,MATCH($B153,Mapping!$A$24:$A$32,0))) | I153: =INDEX(Variables!$C$5:$C$45,MATCH($A153,Variables!$A$5:$A$45,0)) | J153: =INDEX(Variables!$E$5:$E$45,MATCH($A153,Variables!$A$5:$A$45,0)) | K153: =LOWER(Settings!$C$4)&".mit."&$A153&IF($C153="","","."&$C153&"."&$B153)&IF(INDEX(Variables!$D$5:$D$45,MATCH($A153,Variables!$A$5:$A$45,0))="","","."&INDEX(Variables!$D$5:$D$45,MATCH($A153,Variables!$A$5:$A$45,0)))&"."&K$5 | L153: =$D153+L$14*$E153*$F153 | M153: =$D153+M$14*$E153*$F153 | N153: =$D153+N$14*$E153*$F153 | O153: =$D153+O$14*$E153*$F153 | P153: =$D153+P$14*$E153*$F153 | Q153: =$D153+Q$14*$E153*$F153 | R153: =$D153+R$14*$E153*$F153 | S153: =$D153+S$14*$E153*$F153 | ... X153: =$D153+X$14*$E153*$F153 | Y153: =TAX($D153,Y$14,$E153,$F153) | Z153: =LOWER(Settings!$C$4)&".mit."&$A153&IF($C153="","","."&$C153&"."&$B153)&IF(INDEX(Variables!$D$5:$D$45,MATCH($A153,Variables!$A$5:$A$45,0))="","","."&INDEX(Variables!$D$5:$D$45,MATCH($A153,Variables!$A$5:$A$45,0)))&"."&Z$5 | AA153: =$D153+AA$14*$E153*$F153 | AB153: =$D153+AB$14*$E153*$F153 | AC153: =$D153+AC$14*$E153*$F153 | AD153: =$D153+AD$14*$E153*$F153 | AE153: =$D153+AE$14*$E153*$F153 | AF153: =$D153+AF$14*$E153*$F153 | AG153: =$D153+AG$14*$E153*$F153 | AH153: =$D153+AH$14*$E153*$F153 | ... AM153: =$D153+AM$14*$E153*$F153 | AN153: =TAX($D153,AN$14,$E153,$F153)
A154: tax | B154: ker | C154: rod | D154: =INDEX(Inputs!$Q$5:$Q$132,MATCH($B154&"|"&$C154,Inputs!$A$5:$A$132,0)) | E154: =INDEX(Inputs!$R$5:$R$132,MATCH($B154&"|"&$C154,Inputs!$A$5:$A$132,0)) | F154: =INDEX(Inputs!$J$5:$J$132,MATCH($B154&"|"&$C154,Inputs!$A$5:$A$132,0)) | H154: =INDEX(Variables!$B$5:$B$45,MATCH($A154,Variables!$A$5:$A$45,0))&IF($C154="",""," | "&INDEX(Mapping!$B$5:$B$21,MATCH($C154,Mapping!$A$5:$A$21,0))&" | "&INDEX(Mapping!$B$24:$B$32,MATCH($B154,Mapping!$A$24:$A$32,0))) | I154: =INDEX(Variables!$C$5:$C$45,MATCH($A154,Variables!$A$5:$A$45,0)) | J154: =INDEX(Variables!$E$5:$E$45,MATCH($A154,Variables!$A$5:$A$45,0)) | K154: =LOWER(Settings!$C$4)&".mit."&$A154&IF($C154="","","."&$C154&"."&$B154)&IF(INDEX(Variables!$D$5:$D$45,MATCH($A154,Variables!$A$5:$A$45,0))="","","."&INDEX(Variables!$D$5:$D$45,MATCH($A154,Variables!$A$5:$A$45,0)))&"."&K$5 | L154: =$D154+L$14*$E154*$F154 | M154: =$D154+M$14*$E154*$F154 | N154: =$D154+N$14*$E154*$F154 | O154: =$D154+O$14*$E154*$F154 | P154: =$D154+P$14*$E154*$F154 | Q154: =$D154+Q$14*$E154*$F154 | R154: =$D154+R$14*$E154*$F154 | S154: =$D154+S$14*$E154*$F154 | ... X154: =$D154+X$14*$E154*$F154 | Y154: =TAX($D154,Y$14,$E154,$F154) | Z154: =LOWER(Settings!$C$4)&".mit."&$A154&IF($C154="","","."&$C154&"."&$B154)&IF(INDEX(Variables!$D$5:$D$45,MATCH($A154,Variables!$A$5:$A$45,0))="","","."&INDEX(Variables!$D$5:$D$45,MATCH($A154,Variables!$A$5:$A$45,0)))&"."&Z$5 | AA154: =$D154+AA$14*$E154*$F154 | AB154: =$D154+AB$14*$E154*$F154 | AC154: =$D154+AC$14*$E154*$F154 | AD154: =$D154+AD$14*$E154*$F154 | AE154: =$D154+AE$14*$E154*$F154 | AF154: =$D154+AF$14*$E154*$F154 | AG154: =$D154+AG$14*$E154*$F154 | AH154: =$D154+AH$14*$E154*$F154 | ... AM154: =$D154+AM$14*$E154*$F154 | AN154: =TAX($D154,AN$14,$E154,$F154)
A155: tax | B155: oop | C155: rod | D155: =INDEX(Inputs!$Q$5:$Q$132,MATCH($B155&"|"&$C155,Inputs!$A$5:$A$132,0)) | E155: =INDEX(Inputs!$R$5:$R$132,MATCH($B155&"|"&$C155,Inputs!$A$5:$A$132,0)) | F155: =INDEX(Inputs!$J$5:$J$132,MATCH($B155&"|"&$C155,Inputs!$A$5:$A$132,0)) | H155: =INDEX(Variables!$B$5:$B$45,MATCH($A155,Variables!$A$5:$A$45,0))&IF($C155="",""," | "&INDEX(Mapping!$B$5:$B$21,MATCH($C155,Mapping!$A$5:$A$21,0))&" | "&INDEX(Mapping!$B$24:$B$32,MATCH($B155,Mapping!$A$24:$A$32,0))) | I155: =INDEX(Variables!$C$5:$C$45,MATCH($A155,Variables!$A$5:$A$45,0)) | J155: =INDEX(Variables!$E$5:$E$45,MATCH($A155,Variables!$A$5:$A$45,0)) | K155: =LOWER(Settings!$C$4)&".mit."&$A155&IF($C155="","","."&$C155&"."&$B155)&IF(INDEX(Variables!$D$5:$D$45,MATCH($A155,Variables!$A$5:$A$45,0))="","","."&INDEX(Variables!$D$5:$D$45,MATCH($A155,Variables!$A$5:$A$45,0)))&"."&K$5 | L155: =$D155+L$14*$E155*$F155 | M155: =$D155+M$14*$E155*$F155 | N155: =$D155+N$14*$E155*$F155 | O155: =$D155+O$14*$E155*$F155 | P155: =$D155+P$14*$E155*$F155 | Q155: =$D155+Q$14*$E155*$F155 | R155: =$D155+R$14*$E155*$F155 | S155: =$D155+S$14*$E155*$F155 | ... X155: =$D155+X$14*$E155*$F155 | Y155: =TAX($D155,Y$14,$E155,$F155) | Z155: =LOWER(Settings!$C$4)&".mit."&$A155&IF($C155="","","."&$C155&"."&$B155)&IF(INDEX(Variables!$D$5:$D$45,MATCH($A155,Variables!$A$5:$A$45,0))="","","."&INDEX(Variables!$D$5:$D$45,MATCH($A155,Variables!$A$5:$A$45,0)))&"."&Z$5 | AA155: =$D155+AA$14*$E155*$F155 | AB155: =$D155+AB$14*$E155*$F155 | AC155: =$D155+AC$14*$E155*$F155 | AD155: =$D155+AD$14*$E155*$F155 | AE155: =$D155+AE$14*$E155*$F155 | AF155: =$D155+AF$14*$E155*$F155 | AG155: =$D155+AG$14*$E155*$F155 | AH155: =$D155+AH$14*$E155*$F155 | ... AM155: =$D155+AM$14*$E155*$F155 | AN155: =TAX($D155,AN$14,$E155,$F155)
A156: tax | B156: bio | C156: rod | D156: =INDEX(Inputs!$Q$5:$Q$132,MATCH($B156&"|"&$C156,Inputs!$A$5:$A$132,0)) | E156: =INDEX(Inputs!$R$5:$R$132,MATCH($B156&"|"&$C156,Inputs!$A$5:$A$132,0)) | F156: =INDEX(Inputs!$J$5:$J$132,MATCH($B156&"|"&$C156,Inputs!$A$5:$A$132,0)) | H156: =INDEX(Variables!$B$5:$B$45,MATCH($A156,Variables!$A$5:$A$45,0))&IF($C156="",""," | "&INDEX(Mapping!$B$5:$B$21,MATCH($C156,Mapping!$A$5:$A$21,0))&" | "&INDEX(Mapping!$B$24:$B$32,MATCH($B156,Mapping!$A$24:$A$32,0))) | I156: =INDEX(Variables!$C$5:$C$45,MATCH($A156,Variables!$A$5:$A$45,0)) | J156: =INDEX(Variables!$E$5:$E$45,MATCH($A156,Variables!$A$5:$A$45,0)) | K156: =LOWER(Settings!$C$4)&".mit."&$A156&IF($C156="","","."&$C156&"."&$B156)&IF(INDEX(Variables!$D$5:$D$45,MATCH($A156,Variables!$A$5:$A$45,0))="","","."&INDEX(Variables!$D$5:$D$45,MATCH($A156,Variables!$A$5:$A$45,0)))&"."&K$5 | L156: =$D156+L$14*$E156*$F156 | M156: =$D156+M$14*$E156*$F156 | N156: =$D156+N$14*$E156*$F156 | O156: =$D156+O$14*$E156*$F156 | P156: =$D156+P$14*$E156*$F156 | Q156: =$D156+Q$14*$E156*$F156 | R156: =$D156+R$14*$E156*$F156 | S156: =$D156+S$14*$E156*$F156 | ... X156: =$D156+X$14*$E156*$F156 | Y156: =TAX($D156,Y$14,$E156,$F156) | Z156: =LOWER(Settings!$C$4)&".mit."&$A156&IF($C156="","","."&$C156&"."&$B156)&IF(INDEX(Variables!$D$5:$D$45,MATCH($A156,Variables!$A$5:$A$45,0))="","","."&INDEX(Variables!$D$5:$D$45,MATCH($A156,Variables!$A$5:$A$45,0)))&"."&Z$5 | AA156: =$D156+AA$14*$E156*$F156 | AB156: =$D156+AB$14*$E156*$F156 | AC156: =$D156+AC$14*$E156*$F156 | AD156: =$D156+AD$14*$E156*$F156 | AE156: =$D156+AE$14*$E156*$F156 | AF156: =$D156+AF$14*$E156*$F156 | AG156: =$D156+AG$14*$E156*$F156 | AH156: =$D156+AH$14*$E156*$F156 | ... AM156: =$D156+AM$14*$E156*$F156 | AN156: =TAX($D156,AN$14,$E156,$F156)
A157: tax | B157: coa | C157: ral | D157: =INDEX(Inputs!$Q$5:$Q$132,MATCH($B157&"|"&$C157,Inputs!$A$5:$A$132,0)) | E157: =INDEX(Inputs!$R$5:$R$132,MATCH($B157&"|"&$C157,Inputs!$A$5:$A$132,0)) | F157: =INDEX(Inputs!$J$5:$J$132,MATCH($B157&"|"&$C157,Inputs!$A$5:$A$132,0)) | H157: =INDEX(Variables!$B$5:$B$45,MATCH($A157,Variables!$A$5:$A$45,0))&IF($C157="",""," | "&INDEX(Mapping!$B$5:$B$21,MATCH($C157,Mapping!$A$5:$A$21,0))&" | "&INDEX(Mapping!$B$24:$B$32,MATCH($B157,Mapping!$A$24:$A$32,0))) | I157: =INDEX(Variables!$C$5:$C$45,MATCH($A157,Variables!$A$5:$A$45,0)) | J157: =INDEX(Variables!$E$5:$E$45,MATCH($A157,Variables!$A$5:$A$45,0)) | K157: =LOWER(Settings!$C$4)&".mit."&$A157&IF($C157="","","."&$C157&"."&$B157)&IF(INDEX(Variables!$D$5:$D$45,MATCH($A157,Variables!$A$5:$A$45,0))="","","."&INDEX(Variables!$D$5:$D$45,MATCH($A157,Variables!$A$5:$A$45,0)))&"."&K$5 | L157: =$D157+L$14*$E157*$F157 | M157: =$D157+M$14*$E157*$F157 | N157: =$D157+N$14*$E157*$F157 | O157: =$D157+O$14*$E157*$F157 | P157: =$D157+P$14*$E157*$F157 | Q157: =$D157+Q$14*$E157*$F157 | R157: =$D157+R$14*$E157*$F157 | S157: =$D157+S$14*$E157*$F157 | ... X157: =$D157+X$14*$E157*$F157 | Y157: =TAX($D157,Y$14,$E157,$F157) | Z157: =LOWER(Settings!$C$4)&".mit."&$A157&IF($C157="","","."&$C157&"."&$B157)&IF(INDEX(Variables!$D$5:$D$45,MATCH($A157,Variables!$A$5:$A$45,0))="","","."&INDEX(Variables!$D$5:$D$45,MATCH($A157,Variables!$A$5:$A$45,0)))&"."&Z$5 | AA157: =$D157+AA$14*$E157*$F157 | AB157: =$D157+AB$14*$E157*$F157 | AC157: =$D157+AC$14*$E157*$F157 | AD157: =$D157+AD$14*$E157*$F157 | AE157: =$D157+AE$14*$E157*$F157 | AF157: =$D157+AF$14*$E157*$F157 | AG157: =$D157+AG$14*$E157*$F157 | AH157: =$D157+AH$14*$E157*$F157 | ... AM157: =$D157+AM$14*$E157*$F157 | AN157: =TAX($D157,AN$14,$E157,$F157)
A158: tax | B158: nga | C158: ral | D158: =INDEX(Inputs!$Q$5:$Q$132,MATCH($B158&"|"&$C158,Inputs!$A$5:$A$132,0)) | E158: =INDEX(Inputs!$R$5:$R$132,MATCH($B158&"|"&$C158,Inputs!$A$5:$A$132,0)) | F158: =INDEX(Inputs!$J$5:$J$132,MATCH($B158&"|"&$C158,Inputs!$A$5:$A$132,0)) | H158: =INDEX(Variables!$B$5:$B$45,MATCH($A158,Variables!$A$5:$A$45,0))&IF($C158="",""," | "&INDEX(Mapping!$B$5:$B$21,MATCH($C158,Mapping!$A$5:$A$21,0))&" | "&INDEX(Mapping!$B$24:$B$32,MATCH($B158,Mapping!$A$24:$A$32,0))) | I158: =INDEX(Variables!$C$5:$C$45,MATCH($A158,Variables!$A$5:$A$45,0)) | J158: =INDEX(Variables!$E$5:$E$45,MATCH($A158,Variables!$A$5:$A$45,0)) | K158: =LOWER(Settings!$C$4)&".mit."&$A158&IF($C158="","","."&$C158&"."&$B158)&IF(INDEX(Variables!$D$5:$D$45,MATCH($A158,Variables!$A$5:$A$45,0))="","","."&INDEX(Variables!$D$5:$D$45,MATCH($A158,Variables!$A$5:$A$45,0)))&"."&K$5 | L158: =$D158+L$14*$E158*$F158 | M158: =$D158+M$14*$E158*$F158 | N158: =$D158+N$14*$E158*$F158 | O158: =$D158+O$14*$E158*$F158 | P158: =$D158+P$14*$E158*$F158 | Q158: =$D158+Q$14*$E158*$F158 | R158: =$D158+R$14*$E158*$F158 | S158: =$D158+S$14*$E158*$F158 | ... X158: =$D158+X$14*$E158*$F158 | Y158: =TAX($D158,Y$14,$E158,$F158) | Z158: =LOWER(Settings!$C$4)&".mit."&$A158&IF($C158="","","."&$C158&"."&$B158)&IF(INDEX(Variables!$D$5:$D$45,MATCH($A158,Variables!$A$5:$A$45,0))="","","."&INDEX(Variables!$D$5:$D$45,MATCH($A158,Variables!$A$5:$A$45,0)))&"."&Z$5 | AA158: =$D158+AA$14*$E158*$F158 | AB158: =$D158+AB$14*$E158*$F158 | AC158: =$D158+AC$14*$E158*$F158 | AD158: =$D158+AD$14*$E158*$F158 | AE158: =$D158+AE$14*$E158*$F158 | AF158: =$D158+AF$14*$E158*$F158 | AG158: =$D158+AG$14*$E158*$F158 | AH158: =$D158+AH$14*$E158*$F158 | ... AM158: =$D158+AM$14*$E158*$F158 | AN158: =TAX($D158,AN$14,$E158,$F158)
A159: tax | B159: gso | C159: ral | D159: =INDEX(Inputs!$Q$5:$Q$132,MATCH($B159&"|"&$C159,Inputs!$A$5:$A$132,0)) | E159: =INDEX(Inputs!$R$5:$R$132,MATCH($B159&"|"&$C159,Inputs!$A$5:$A$132,0)) | F159: =INDEX(Inputs!$J$5:$J$132,MATCH($B159&"|"&$C159,Inputs!$A$5:$A$132,0)) | H159: =INDEX(Variables!$B$5:$B$45,MATCH($A159,Variables!$A$5:$A$45,0))&IF($C159="",""," | "&INDEX(Mapping!$B$5:$B$21,MATCH($C159,Mapping!$A$5:$A$21,0))&" | "&INDEX(Mapping!$B$24:$B$32,MATCH($B159,Mapping!$A$24:$A$32,0))) | I159: =INDEX(Variables!$C$5:$C$45,MATCH($A159,Variables!$A$5:$A$45,0)) | J159: =INDEX(Variables!$E$5:$E$45,MATCH($A159,Variables!$A$5:$A$45,0)) | K159: =LOWER(Settings!$C$4)&".mit."&$A159&IF($C159="","","."&$C159&"."&$B159)&IF(INDEX(Variables!$D$5:$D$45,MATCH($A159,Variables!$A$5:$A$45,0))="","","."&INDEX(Variables!$D$5:$D$45,MATCH($A159,Variables!$A$5:$A$45,0)))&"."&K$5 | L159: =$D159+L$14*$E159*$F159 | M159: =$D159+M$14*$E159*$F159 | N159: =$D159+N$14*$E159*$F159 | O159: =$D159+O$14*$E159*$F159 | P159: =$D159+P$14*$E159*$F159 | Q159: =$D159+Q$14*$E159*$F159 | R159: =$D159+R$14*$E159*$F159 | S159: =$D159+S$14*$E159*$F159 | ... X159: =$D159+X$14*$E159*$F159 | Y159: =TAX($D159,Y$14,$E159,$F159) | Z159: =LOWER(Settings!$C$4)&".mit."&$A159&IF($C159="","","."&$C159&"."&$B159)&IF(INDEX(Variables!$D$5:$D$45,MATCH($A159,Variables!$A$5:$A$45,0))="","","."&INDEX(Variables!$D$5:$D$45,MATCH($A159,Variables!$A$5:$A$45,0)))&"."&Z$5 | AA159: =$D159+AA$14*$E159*$F159 | AB159: =$D159+AB$14*$E159*$F159 | AC159: =$D159+AC$14*$E159*$F159 | AD159: =$D159+AD$14*$E159*$F159 | AE159: =$D159+AE$14*$E159*$F159 | AF159: =$D159+AF$14*$E159*$F159 | AG159: =$D159+AG$14*$E159*$F159 | AH159: =$D159+AH$14*$E159*$F159 | ... AM159: =$D159+AM$14*$E159*$F159 | AN159: =TAX($D159,AN$14,$E159,$F159)
A160: tax | B160: die | C160: ral | D160: =INDEX(Inputs!$Q$5:$Q$132,MATCH($B160&"|"&$C160,Inputs!$A$5:$A$132,0)) | E160: =INDEX(Inputs!$R$5:$R$132,MATCH($B160&"|"&$C160,Inputs!$A$5:$A$132,0)) | F160: =INDEX(Inputs!$J$5:$J$132,MATCH($B160&"|"&$C160,Inputs!$A$5:$A$132,0)) | H160: =INDEX(Variables!$B$5:$B$45,MATCH($A160,Variables!$A$5:$A$45,0))&IF($C160="",""," | "&INDEX(Mapping!$B$5:$B$21,MATCH($C160,Mapping!$A$5:$A$21,0))&" | "&INDEX(Mapping!$B$24:$B$32,MATCH($B160,Mapping!$A$24:$A$32,0))) | I160: =INDEX(Variables!$C$5:$C$45,MATCH($A160,Variables!$A$5:$A$45,0)) | J160: =INDEX(Variables!$E$5:$E$45,MATCH($A160,Variables!$A$5:$A$45,0)) | K160: =LOWER(Settings!$C$4)&".mit."&$A160&IF($C160="","","."&$C160&"."&$B160)&IF(INDEX(Variables!$D$5:$D$45,MATCH($A160,Variables!$A$5:$A$45,0))="","","."&INDEX(Variables!$D$5:$D$45,MATCH($A160,Variables!$A$5:$A$45,0)))&"."&K$5 | L160: =$D160+L$14*$E160*$F160 | M160: =$D160+M$14*$E160*$F160 | N160: =$D160+N$14*$E160*$F160 | O160: =$D160+O$14*$E160*$F160 | P160: =$D160+P$14*$E160*$F160 | Q160: =$D160+Q$14*$E160*$F160 | R160: =$D160+R$14*$E160*$F160 | S160: =$D160+S$14*$E160*$F160 | ... X160: =$D160+X$14*$E160*$F160 | Y160: =TAX($D160,Y$14,$E160,$F160) | Z160: =LOWER(Settings!$C$4)&".mit."&$A160&IF($C160="","","."&$C160&"."&$B160)&IF(INDEX(Variables!$D$5:$D$45,MATCH($A160,Variables!$A$5:$A$45,0))="","","."&INDEX(Variables!$D$5:$D$45,MATCH($A160,Variables!$A$5:$A$45,0)))&"."&Z$5 | AA160: =$D160+AA$14*$E160*$F160 | AB160: =$D160+AB$14*$E160*$F160 | AC160: =$D160+AC$14*$E160*$F160 | AD160: =$D160+AD$14*$E160*$F160 | AE160: =$D160+AE$14*$E160*$F160 | AF160: =$D160+AF$14*$E160*$F160 | AG160: =$D160+AG$14*$E160*$F160 | AH160: =$D160+AH$14*$E160*$F160 | ... AM160: =$D160+AM$14*$E160*$F160 | AN160: =TAX($D160,AN$14,$E160,$F160)
... A276: tax | B276: bio | C276: oen | D276: =INDEX(Inputs!$Q$5:$Q$132,MATCH($B276&"|"&$C276,Inputs!$A$5:$A$132,0)) | E276: =INDEX(Inputs!$R$5:$R$132,MATCH($B276&"|"&$C276,Inputs!$A$5:$A$132,0)) | F276: =INDEX(Inputs!$J$5:$J$132,MATCH($B276&"|"&$C276,Inputs!$A$5:$A$132,0)) | H276: =INDEX(Variables!$B$5:$B$45,MATCH($A276,Variables!$A$5:$A$45,0))&IF($C276="",""," | "&INDEX(Mapping!$B$5:$B$21,MATCH($C276,Mapping!$A$5:$A$21,0))&" | "&INDEX(Mapping!$B$24:$B$32,MATCH($B276,Mapping!$A$24:$A$32,0))) | I276: =INDEX(Variables!$C$5:$C$45,MATCH($A276,Variables!$A$5:$A$45,0)) | J276: =INDEX(Variables!$E$5:$E$45,MATCH($A276,Variables!$A$5:$A$45,0)) | K276: =LOWER(Settings!$C$4)&".mit."&$A276&IF($C276="","","."&$C276&"."&$B276)&IF(INDEX(Variables!$D$5:$D$45,MATCH($A276,Variables!$A$5:$A$45,0))="","","."&INDEX(Variables!$D$5:$D$45,MATCH($A276,Variables!$A$5:$A$45,0)))&"."&K$5 | L276: =$D276+L$14*$E276*$F276 | M276: =$D276+M$14*$E276*$F276 | N276: =$D276+N$14*$E276*$F276 | O276: =$D276+O$14*$E276*$F276 | P276: =$D276+P$14*$E276*$F276 | Q276: =$D276+Q$14*$E276*$F276 | R276: =$D276+R$14*$E276*$F276 | S276: =$D276+S$14*$E276*$F276 | ... X276: =$D276+X$14*$E276*$F276 | Y276: =TAX($D276,Y$14,$E276,$F276) | Z276: =LOWER(Settings!$C$4)&".mit."&$A276&IF($C276="","","."&$C276&"."&$B276)&IF(INDEX(Variables!$D$5:$D$45,MATCH($A276,Variables!$A$5:$A$45,0))="","","."&INDEX(Variables!$D$5:$D$45,MATCH($A276,Variables!$A$5:$A$45,0)))&"."&Z$5 | AA276: =$D276+AA$14*$E276*$F276 | AB276: =$D276+AB$14*$E276*$F276 | AC276: =$D276+AC$14*$E276*$F276 | AD276: =$D276+AD$14*$E276*$F276 | AE276: =$D276+AE$14*$E276*$F276 | AF276: =$D276+AF$14*$E276*$F276 | AG276: =$D276+AG$14*$E276*$F276 | AH276: =$D276+AH$14*$E276*$F276 | ... AM276: =$D276+AM$14*$E276*$F276 | AN276: =TAX($D276,AN$14,$E276,$F276)
A278: After-tax price = pre-tax price + tax
H279: No total: prices are not added up
A280: atp | B280: coa | C280: rod | H280: =INDEX(Variables!$B$5:$B$45,MATCH($A280,Variables!$A$5:$A$45,0))&IF($C280="",""," | "&INDEX(Mapping!$B$5:$B$21,MATCH($C280,Mapping!$A$5:$A$21,0))&" | "&INDEX(Mapping!$B$24:$B$32,MATCH($B280,Mapping!$A$24:$A$32,0))) | I280: =INDEX(Variables!$C$5:$C$45,MATCH($A280,Variables!$A$5:$A$45,0)) | J280: =INDEX(Variables!$E$5:$E$45,MATCH($A280,Variables!$A$5:$A$45,0)) | K280: =LOWER(Settings!$C$4)&".mit."&$A280&IF($C280="","","."&$C280&"."&$B280)&IF(INDEX(Variables!$D$5:$D$45,MATCH($A280,Variables!$A$5:$A$45,0))="","","."&INDEX(Variables!$D$5:$D$45,MATCH($A280,Variables!$A$5:$A$45,0)))&"."&K$5 | L280: =L18+L149 | M280: =M18+M149 | N280: =N18+N149 | O280: =O18+O149 | P280: =P18+P149 | Q280: =Q18+Q149 | R280: =R18+R149 | S280: =S18+S149 | ... X280: =X18+X149 | Y280: =POSTTAX(Y18,Y149) | Z280: =LOWER(Settings!$C$4)&".mit."&$A280&IF($C280="","","."&$C280&"."&$B280)&IF(INDEX(Variables!$D$5:$D$45,MATCH($A280,Variables!$A$5:$A$45,0))="","","."&INDEX(Variables!$D$5:$D$45,MATCH($A280,Variables!$A$5:$A$45,0)))&"."&Z$5 | AA280: =AA18+AA149 | AB280: =AB18+AB149 | AC280: =AC18+AC149 | AD280: =AD18+AD149 | AE280: =AE18+AE149 | AF280: =AF18+AF149 | AG280: =AG18+AG149 | AH280: =AH18+AH149 | ... AM280: =AM18+AM149 | AN280: =POSTTAX(AN18,AN149)
A281: atp | B281: nga | C281: rod | H281: =INDEX(Variables!$B$5:$B$45,MATCH($A281,Variables!$A$5:$A$45,0))&IF($C281="",""," | "&INDEX(Mapping!$B$5:$B$21,MATCH($C281,Mapping!$A$5:$A$21,0))&" | "&INDEX(Mapping!$B$24:$B$32,MATCH($B281,Mapping!$A$24:$A$32,0))) | I281: =INDEX(Variables!$C$5:$C$45,MATCH($A281,Variables!$A$5:$A$45,0)) | J281: =INDEX(Variables!$E$5:$E$45,MATCH($A281,Variables!$A$5:$A$45,0)) | K281: =LOWER(Settings!$C$4)&".mit."&$A281&IF($C281="","","."&$C281&"."&$B281)&IF(INDEX(Variables!$D$5:$D$45,MATCH($A281,Variables!$A$5:$A$45,0))="","","."&INDEX(Variables!$D$5:$D$45,MATCH($A281,Variables!$A$5:$A$45,0)))&"."&K$5 | L281: =L19+L150 | M281: =M19+M150 | N281: =N19+N150 | O281: =O19+O150 | P281: =P19+P150 | Q281: =Q19+Q150 | R281: =R19+R150 | S281: =S19+S150 | ... X281: =X19+X150 | Y281: =POSTTAX(Y19,Y150) | Z281: =LOWER(Settings!$C$4)&".mit."&$A281&IF($C281="","","."&$C281&"."&$B281)&IF(INDEX(Variables!$D$5:$D$45,MATCH($A281,Variables!$A$5:$A$45,0))="","","."&INDEX(Variables!$D$5:$D$45,MATCH($A281,Variables!$A$5:$A$45,0)))&"."&Z$5 | AA281: =AA19+AA150 | AB281: =AB19+AB150 | AC281: =AC19+AC150 | AD281: =AD19+AD150 | AE281: =AE19+AE150 | AF281: =AF19+AF150 | AG281: =AG19+AG150 | AH281: =AH19+AH150 | ... AM281: =AM19+AM150 | AN281: =POSTTAX(AN19,AN150)
A282: atp | B282: gso | C282: rod | H282: =INDEX(Variables!$B$5:$B$45,MATCH($A282,Variables!$A$5:$A$45,0))&IF($C282="",""," | "&INDEX(Mapping!$B$5:$B$21,MATCH($C282,Mapping!$A$5:$A$21,0))&" | "&INDEX(Mapping!$B$24:$B$32,MATCH($B282,Mapping!$A$24:$A$32,0))) | I282: =INDEX(Variables!$C$5:$C$45,MATCH($A282,Variables!$A$5:$A$45,0)) | J282: =INDEX(Variables!$E$5:$E$45,MATCH($A282,Variables!$A$5:$A$45,0)) | K282: =LOWER(Settings!$C$4)&".mit."&$A282&IF($C282="","","."&$C282&"."&$B282)&IF(INDEX(Variables!$D$5:$D$45,MATCH($A282,Variables!$A$5:$A$45,0))="","","."&INDEX(Variables!$D$5:$D$45,MATCH($A282,Variables!$A$5:$A$45,0)))&"."&K$5 | L282: =L20+L151 | M282: =M20+M151 | N282: =N20+N151 | O282: =O20+O151 | P282: =P20+P151 | Q282: =Q20+Q151 | R282: =R20+R151 | S282: =S20+S151 | ... X282: =X20+X151 | Y282: =POSTTAX(Y20,Y151) | Z282: =LOWER(Settings!$C$4)&".mit."&$A282&IF($C282="","","."&$C282&"."&$B282)&IF(INDEX(Variables!$D$5:$D$45,MATCH($A282,Variables!$A$5:$A$45,0))="","","."&INDEX(Variables!$D$5:$D$45,MATCH($A282,Variables!$A$5:$A$45,0)))&"."&Z$5 | AA282: =AA20+AA151 | AB282: =AB20+AB151 | AC282: =AC20+AC151 | AD282: =AD20+AD151 | AE282: =AE20+AE151 | AF282: =AF20+AF151 | AG282: =AG20+AG151 | AH282: =AH20+AH151 | ... AM282: =AM20+AM151 | AN282: =POSTTAX(AN20,AN151)
A283: atp | B283: die | C283: rod | H283: =INDEX(Variables!$B$5:$B$45,MATCH($A283,Variables!$A$5:$A$45,0))&IF($C283="",""," | "&INDEX(Mapping!$B$5:$B$21,MATCH($C283,Mapping!$A$5:$A$21,0))&" | "&INDEX(Mapping!$B$24:$B$32,MATCH($B283,Mapping!$A$24:$A$32,0))) | I283: =INDEX(Variables!$C$5:$C$45,MATCH($A283,Variables!$A$5:$A$45,0)) | J283: =INDEX(Variables!$E$5:$E$45,MATCH($A283,Variables!$A$5:$A$45,0)) | K283: =LOWER(Settings!$C$4)&".mit."&$A283&IF($C283="","","."&$C283&"."&$B283)&IF(INDEX(Variables!$D$5:$D$45,MATCH($A283,Variables!$A$5:$A$45,0))="","","."&INDEX(Variables!$D$5:$D$45,MATCH($A283,Variables!$A$5:$A$45,0)))&"."&K$5 | L283: =L21+L152 | M283: =M21+M152 | N283: =N21+N152 | O283: =O21+O152 | P283: =P21+P152 | Q283: =Q21+Q152 | R283: =R21+R152 | S283: =S21+S152 | ... X283: =X21+X152 | Y283: =POSTTAX(Y21,Y152) | Z283: =LOWER(Settings!$C$4)&".mit."&$A283&IF($C283="","","."&$C283&"."&$B283)&IF(INDEX(Variables!$D$5:$D$45,MATCH($A283,Variables!$A$5:$A$45,0))="","","."&INDEX(Variables!$D$5:$D$45,MATCH($A283,Variables!$A$5:$A$45,0)))&"."&Z$5 | AA283: =AA21+AA152 | AB283: =AB21+AB152 | AC283: =AC21+AC152 | AD283: =AD21+AD152 | AE283: =AE21+AE152 | AF283: =AF21+AF152 | AG283: =AG21+AG152 | AH283: =AH21+AH152 | ... AM283: =AM21+AM152 | AN283: =POSTTAX(AN21,AN152)
A284: atp | B284: lpg | C284: rod | H284: =INDEX(Variables!$B$5:$B$45,MATCH($A284,Variables!$A$5:$A$45,0))&IF($C284="",""," | "&INDEX(Mapping!$B$5:$B$21,MATCH($C284,Mapping!$A$5:$A$21,0))&" | "&INDEX(Mapping!$B$24:$B$32,MATCH($B284,Mapping!$A$24:$A$32,0))) | I284: =INDEX(Variables!$C$5:$C$45,MATCH($A284,Variables!$A$5:$A$45,0)) | J284: =INDEX(Variables!$E$5:$E$45,MATCH($A284,Variables!$A$5:$A$45,0)) | K284: =LOWER(Settings!$C$4)&".mit."&$A284&IF($C284="","","."&$C284&"."&$B284)&IF(INDEX(Variables!$D$5:$D$45,MATCH($A284,Variables!$A$5:$A$45,0))="","","."&INDEX(Variables!$D$5:$D$45,MATCH($A284,Variables!$A$5:$A$45,0)))&"."&K$5 | L284: =L22+L153 | M284: =M22+M153 | N284: =N22+N153 | O284: =O22+O153 | P284: =P22+P153 | Q284: =Q22+Q153 | R284: =R22+R153 | S284: =S22+S153 | ... X284: =X22+X153 | Y284: =POSTTAX(Y22,Y153) | Z284: =LOWER(Settings!$C$4)&".mit."&$A284&IF($C284="","","."&$C284&"."&$B284)&IF(INDEX(Variables!$D$5:$D$45,MATCH($A284,Variables!$A$5:$A$45,0))="","","."&INDEX(Variables!$D$5:$D$45,MATCH($A284,Variables!$A$5:$A$45,0)))&"."&Z$5 | AA284: =AA22+AA153 | AB284: =AB22+AB153 | AC284: =AC22+AC153 | AD284: =AD22+AD153 | AE284: =AE22+AE153 | AF284: =AF22+AF153 | AG284: =AG22+AG153 | AH284: =AH22+AH153 | ... AM284: =AM22+AM153 | AN284: =POSTTAX(AN22,AN153)
A285: atp | B285: ker | C285: rod | H285: =INDEX(Variables!$B$5:$B$45,MATCH($A285,Variables!$A$5:$A$45,0))&IF($C285="",""," | "&INDEX(Mapping!$B$5:$B$21,MATCH($C285,Mapping!$A$5:$A$21,0))&" | "&INDEX(Mapping!$B$24:$B$32,MATCH($B285,Mapping!$A$24:$A$32,0))) | I285: =INDEX(Variables!$C$5:$C$45,MATCH($A285,Variables!$A$5:$A$45,0)) | J285: =INDEX(Variables!$E$5:$E$45,MATCH($A285,Variables!$A$5:$A$45,0)) | K285: =LOWER(Settings!$C$4)&".mit."&$A285&IF($C285="","","."&$C285&"."&$B285)&IF(INDEX(Variables!$D$5:$D$45,MATCH($A285,Variables!$A$5:$A$45,0))="","","."&INDEX(Variables!$D$5:$D$45,MATCH($A285,Variables!$A$5:$A$45,0)))&"."&K$5 | L285: =L23+L154 | M285: =M23+M154 | N285: =N23+N154 | O285: =O23+O154 | P285: =P23+P154 | Q285: =Q23+Q154 | R285: =R23+R154 | S285: =S23+S154 | ... X285: =X23+X154 | Y285: =POSTTAX(Y23,Y154) | Z285: =LOWER(Settings!$C$4)&".mit."&$A285&IF($C285="","","."&$C285&"."&$B285)&IF(INDEX(Variables!$D$5:$D$45,MATCH($A285,Variables!$A$5:$A$45,0))="","","."&INDEX(Variables!$D$5:$D$45,MATCH($A285,Variables!$A$5:$A$45,0)))&"."&Z$5 | AA285: =AA23+AA154 | AB285: =AB23+AB154 | AC285: =AC23+AC154 | AD285: =AD23+AD154 | AE285: =AE23+AE154 | AF285: =AF23+AF154 | AG285: =AG23+AG154 | AH285: =AH23+AH154 | ... AM285: =AM23+AM154 | AN285: =POSTTAX(AN23,AN154)
A286: atp | B286: oop | C286: rod | H286: =INDEX(Variables!$B$5:$B$45,MATCH($A286,Variables!$A$5:$A$45,0))&IF($C286="",""," | "&INDEX(Mapping!$B$5:$B$21,MATCH($C286,Mapping!$A$5:$A$21,0))&" | "&INDEX(Mapping!$B$24:$B$32,MATCH($B286,Mapping!$A$24:$A$32,0))) | I286: =INDEX(Variables!$C$5:$C$45,MATCH($A286,Variables!$A$5:$A$45,0)) | J286: =INDEX(Variables!$E$5:$E$45,MATCH($A286,Variables!$A$5:$A$45,0)) | K286: =LOWER(Settings!$C$4)&".mit."&$A286&IF($C286="","","."&$C286&"."&$B286)&IF(INDEX(Variables!$D$5:$D$45,MATCH($A286,Variables!$A$5:$A$45,0))="","","."&INDEX(Variables!$D$5:$D$45,MATCH($A286,Variables!$A$5:$A$45,0)))&"."&K$5 | L286: =L24+L155 | M286: =M24+M155 | N286: =N24+N155 | O286: =O24+O155 | P286: =P24+P155 | Q286: =Q24+Q155 | R286: =R24+R155 | S286: =S24+S155 | ... X286: =X24+X155 | Y286: =POSTTAX(Y24,Y155) | Z286: =LOWER(Settings!$C$4)&".mit."&$A286&IF($C286="","","."&$C286&"."&$B286)&IF(INDEX(Variables!$D$5:$D$45,MATCH($A286,Variables!$A$5:$A$45,0))="","","."&INDEX(Variables!$D$5:$D$45,MATCH($A286,Variables!$A$5:$A$45,0)))&"."&Z$5 | AA286: =AA24+AA155 | AB286: =AB24+AB155 | AC286: =AC24+AC155 | AD286: =AD24+AD155 | AE286: =AE24+AE155 | AF286: =AF24+AF155 | AG286: =AG24+AG155 | AH286: =AH24+AH155 | ... AM286: =AM24+AM155 | AN286: =POSTTAX(AN24,AN155)
A287: atp | B287: bio | C287: rod | H287: =INDEX(Variables!$B$5:$B$45,MATCH($A287,Variables!$A$5:$A$45,0))&IF($C287="",""," | "&INDEX(Mapping!$B$5:$B$21,MATCH($C287,Mapping!$A$5:$A$21,0))&" | "&INDEX(Mapping!$B$24:$B$32,MATCH($B287,Mapping!$A$24:$A$32,0))) | I287: =INDEX(Variables!$C$5:$C$45,MATCH($A287,Variables!$A$5:$A$45,0)) | J287: =INDEX(Variables!$E$5:$E$45,MATCH($A287,Variables!$A$5:$A$45,0)) | K287: =LOWER(Settings!$C$4)&".mit."&$A287&IF($C287="","","."&$C287&"."&$B287)&IF(INDEX(Variables!$D$5:$D$45,MATCH($A287,Variables!$A$5:$A$45,0))="","","."&INDEX(Variables!$D$5:$D$45,MATCH($A287,Variables!$A$5:$A$45,0)))&"."&K$5 | L287: =L25+L156 | M287: =M25+M156 | N287: =N25+N156 | O287: =O25+O156 | P287: =P25+P156 | Q287: =Q25+Q156 | R287: =R25+R156 | S287: =S25+S156 | ... X287: =X25+X156 | Y287: =POSTTAX(Y25,Y156) | Z287: =LOWER(Settings!$C$4)&".mit."&$A287&IF($C287="","","."&$C287&"."&$B287)&IF(INDEX(Variables!$D$5:$D$45,MATCH($A287,Variables!$A$5:$A$45,0))="","","."&INDEX(Variables!$D$5:$D$45,MATCH($A287,Variables!$A$5:$A$45,0)))&"."&Z$5 | AA287: =AA25+AA156 | AB287: =AB25+AB156 | AC287: =AC25+AC156 | AD287: =AD25+AD156 | AE287: =AE25+AE156 | AF287: =AF25+AF156 | AG287: =AG25+AG156 | AH287: =AH25+AH156 | ... AM287: =AM25+AM156 | AN287: =POSTTAX(AN25,AN156)
A288: atp | B288: coa | C288: ral | H288: =INDEX(Variables!$B$5:$B$45,MATCH($A288,Variables!$A$5:$A$45,0))&IF($C288="",""," | "&INDEX(Mapping!$B$5:$B$21,MATCH($C288,Mapping!$A$5:$A$21,0))&" | "&INDEX(Mapping!$B$24:$B$32,MATCH($B288,Mapping!$A$24:$A$32,0))) | I288: =INDEX(Variables!$C$5:$C$45,MATCH($A288,Variables!$A$5:$A$45,0)) | J288: =INDEX(Variables!$E$5:$E$45,MATCH($A288,Variables!$A$5:$A$45,0)) | K288: =LOWER(Settings!$C$4)&".mit."&$A288&IF($C288="","","."&$C288&"."&$B288)&IF(INDEX(Variables!$D$5:$D$45,MATCH($A288,Variables!$A$5:$A$45,0))="","","."&INDEX(Variables!$D$5:$D$45,MATCH($A288,Variables!$A$5:$A$45,0)))&"."&K$5 | L288: =L26+L157 | M288: =M26+M157 | N288: =N26+N157 | O288: =O26+O157 | P288: =P26+P157 | Q288: =Q26+Q157 | R288: =R26+R157 | S288: =S26+S157 | ... X288: =X26+X157 | Y288: =POSTTAX(Y26,Y157) | Z288: =LOWER(Settings!$C$4)&".mit."&$A288&IF($C288="","","."&$C288&"."&$B288)&IF(INDEX(Variables!$D$5:$D$45,MATCH($A288,Variables!$A$5:$A$45,0))="","","."&INDEX(Variables!$D$5:$D$45,MATCH($A288,Variables!$A$5:$A$45,0)))&"."&Z$5 | AA288: =AA26+AA157 | AB288: =AB26+AB157 | AC288: =AC26+AC157 | AD288: =AD26+AD157 | AE288: =AE26+AE157 | AF288: =AF26+AF157 | AG288: =AG26+AG157 | AH288: =AH26+AH157 | ... AM288: =AM26+AM157 | AN288: =POSTTAX(AN26,AN157)
A289: atp | B289: nga | C289: ral | H289: =INDEX(Variables!$B$5:$B$45,MATCH($A289,Variables!$A$5:$A$45,0))&IF($C289="",""," | "&INDEX(Mapping!$B$5:$B$21,MATCH($C289,Mapping!$A$5:$A$21,0))&" | "&INDEX(Mapping!$B$24:$B$32,MATCH($B289,Mapping!$A$24:$A$32,0))) | I289: =INDEX(Variables!$C$5:$C$45,MATCH($A289,Variables!$A$5:$A$45,0)) | J289: =INDEX(Variables!$E$5:$E$45,MATCH($A289,Variables!$A$5:$A$45,0)) | K289: =LOWER(Settings!$C$4)&".mit."&$A289&IF($C289="","","."&$C289&"."&$B289)&IF(INDEX(Variables!$D$5:$D$45,MATCH($A289,Variables!$A$5:$A$45,0))="","","."&INDEX(Variables!$D$5:$D$45,MATCH($A289,Variables!$A$5:$A$45,0)))&"."&K$5 | L289: =L27+L158 | M289: =M27+M158 | N289: =N27+N158 | O289: =O27+O158 | P289: =P27+P158 | Q289: =Q27+Q158 | R289: =R27+R158 | S289: =S27+S158 | ... X289: =X27+X158 | Y289: =POSTTAX(Y27,Y158) | Z289: =LOWER(Settings!$C$4)&".mit."&$A289&IF($C289="","","."&$C289&"."&$B289)&IF(INDEX(Variables!$D$5:$D$45,MATCH($A289,Variables!$A$5:$A$45,0))="","","."&INDEX(Variables!$D$5:$D$45,MATCH($A289,Variables!$A$5:$A$45,0)))&"."&Z$5 | AA289: =AA27+AA158 | AB289: =AB27+AB158 | AC289: =AC27+AC158 | AD289: =AD27+AD158 | AE289: =AE27+AE158 | AF289: =AF27+AF158 | AG289: =AG27+AG158 | AH289: =AH27+AH158 | ... AM289: =AM27+AM158 | AN289: =POSTTAX(AN27,AN158)
A290: atp | B290: gso | C290: ral | H290: =INDEX(Variables!$B$5:$B$45,MATCH($A290,Variables!$A$5:$A$45,0))&IF($C290="",""," | "&INDEX(Mapping!$B$5:$B$21,MATCH($C290,Mapping!$A$5:$A$21,0))&" | "&INDEX(Mapping!$B$24:$B$32,MATCH($B290,Mapping!$A$24:$A$32,0))) | I290: =INDEX(Variables!$C$5:$C$45,MATCH($A290,Variables!$A$5:$A$45,0)) | J290: =INDEX(Variables!$E$5:$E$45,MATCH($A290,Variables!$A$5:$A$45,0)) | K290: =LOWER(Settings!$C$4)&".mit."&$A290&IF($C290="","","."&$C290&"."&$B290)&IF(INDEX(Variables!$D$5:$D$45,MATCH($A290,Variables!$A$5:$A$45,0))="","","."&INDEX(Variables!$D$5:$D$45,MATCH($A290,Variables!$A$5:$A$45,0)))&"."&K$5 | L290: =L28+L159 | M290: =M28+M159 | N290: =N28+N159 | O290: =O28+O159 | P290: =P28+P159 | Q290: =Q28+Q159 | R290: =R28+R159 | S290: =S28+S159 | ... X290: =X28+X159 | Y290: =POSTTAX(Y28,Y159) | Z290: =LOWER(Settings!$C$4)&".mit."&$A290&IF($C290="","","."&$C290&"."&$B290)&IF(INDEX(Variables!$D$5:$D$45,MATCH($A290,Variables!$A$5:$A$45,0))="","","."&INDEX(Variables!$D$5:$D$45,MATCH($A290,Variables!$A$5:$A$45,0)))&"."&Z$5 | AA290: =AA28+AA159 | AB290: =AB28+AB159 | AC290: =AC28+AC159 | AD290: =AD28+AD159 | AE290: =AE28+AE159 | AF290: =AF28+AF159 | AG290: =AG28+AG159 | AH290: =AH28+AH159 | ... AM290: =AM28+AM159 | AN290: =POSTTAX(AN28,AN159)
A291: atp | B291: die | C291: ral | H291: =INDEX(Variables!$B$5:$B$45,MATCH($A291,Variables!$A$5:$A$45,0))&IF($C291="",""," | "&INDEX(Mapping!$B$5:$B$21,MATCH($C291,Mapping!$A$5:$A$21,0))&" | "&INDEX(Mapping!$B$24:$B$32,MATCH($B291,Mapping!$A$24:$A$32,0))) | I291: =INDEX(Variables!$C$5:$C$45,MATCH($A291,Variables!$A$5:$A$45,0)) | J291: =INDEX(Variables!$E$5:$E$45,MATCH($A291,Variables!$A$5:$A$45,0)) | K291: =LOWER(Settings!$C$4)&".mit."&$A291&IF($C291="","","."&$C291&"."&$B291)&IF(INDEX(Variables!$D$5:$D$45,MATCH($A291,Variables!$A$5:$A$45,0))="","","."&INDEX(Variables!$D$5:$D$45,MATCH($A291,Variables!$A$5:$A$45,0)))&"."&K$5 | L291: =L29+L160 | M291: =M29+M160 | N291: =N29+N160 | O291: =O29+O160 | P291: =P29+P160 | Q291: =Q29+Q160 | R291: =R29+R160 | S291: =S29+S160 | ... X291: =X29+X160 | Y291: =POSTTAX(Y29,Y160) | Z291: =LOWER(Settings!$C$4)&".mit."&$A291&IF($C291="","","."&$C291&"."&$B291)&IF(INDEX(Variables!$D$5:$D$45,MATCH($A291,Variables!$A$5:$A$45,0))="","","."&INDEX(Variables!$D$5:$D$45,MATCH($A291,Variables!$A$5:$A$45,0)))&"."&Z$5 | AA291: =AA29+AA160 | AB291: =AB29+AB160 | AC291: =AC29+AC160 | AD291: =AD29+AD160 | AE291: =AE29+AE160 | AF291: =AF29+AF160 | AG291: =AG29+AG160 | AH291: =AH29+AH160 | ... AM291: =AM29+AM160 | AN291: =POSTTAX(AN29,AN160)
... A407: atp | B407: bio | C407: oen | H407: =INDEX(Variables!$B$5:$B$45,MATCH($A407,Variables!$A$5:$A$45,0))&IF($C407="",""," | "&INDEX(Mapping!$B$5:$B$21,MATCH($C407,Mapping!$A$5:$A$21,0))&" | "&INDEX(Mapping!$B$24:$B$32,MATCH($B407,Mapping!$A$24:$A$32,0))) | I407: =INDEX(Variables!$C$5:$C$45,MATCH($A407,Variables!$A$5:$A$45,0)) | J407: =INDEX(Variables!$E$5:$E$45,MATCH($A407,Variables!$A$5:$A$45,0)) | K407: =LOWER(Settings!$C$4)&".mit."&$A407&IF($C407="","","."&$C407&"."&$B407)&IF(INDEX(Variables!$D$5:$D$45,MATCH($A407,Variables!$A$5:$A$45,0))="","","."&INDEX(Variables!$D$5:$D$45,MATCH($A407,Variables!$A$5:$A$45,0)))&"."&K$5 | L407: =L145+L276 | M407: =M145+M276 | N407: =N145+N276 | O407: =O145+O276 | P407: =P145+P276 | Q407: =Q145+Q276 | R407: =R145+R276 | S407: =S145+S276 | ... X407: =X145+X276 | Y407: =POSTTAX(Y145,Y276) | Z407: =LOWER(Settings!$C$4)&".mit."&$A407&IF($C407="","","."&$C407&"."&$B407)&IF(INDEX(Variables!$D$5:$D$45,MATCH($A407,Variables!$A$5:$A$45,0))="","","."&INDEX(Variables!$D$5:$D$45,MATCH($A407,Variables!$A$5:$A$45,0)))&"."&Z$5 | AA407: =AA145+AA276 | AB407: =AB145+AB276 | AC407: =AC145+AC276 | AD407: =AD145+AD276 | AE407: =AE145+AE276 | AF407: =AF145+AF276 | AG407: =AG145+AG276 | AH407: =AH145+AH276 | ... AM407: =AM145+AM276 | AN407: =POSTTAX(AN145,AN276)
A409: Fuel use (CPAT documentation 3.3.3) | D409: eps_Y | E409: eps_U | F409: eps_F | G409: alpha
A410: ener | B410: all | C410: all | H410: =INDEX(Variables!$B$5:$B$45,MATCH($A410,Variables!$A$5:$A$45,0))&IF($C410="",""," | "&INDEX(Mapping!$B$5:$B$21,MATCH($C410,Mapping!$A$5:$A$21,0))&" | "&INDEX(Mapping!$B$24:$B$32,MATCH($B410,Mapping!$A$24:$A$32,0))) | I410: =INDEX(Variables!$C$5:$C$45,MATCH($A410,Variables!$A$5:$A$45,0)) | J410: =INDEX(Variables!$E$5:$E$45,MATCH($A410,Variables!$A$5:$A$45,0)) | K410: =LOWER(Settings!$C$4)&".mit."&$A410&IF($C410="","","."&$C410&"."&$B410)&IF(INDEX(Variables!$D$5:$D$45,MATCH($A410,Variables!$A$5:$A$45,0))="","","."&INDEX(Variables!$D$5:$D$45,MATCH($A410,Variables!$A$5:$A$45,0)))&"."&K$5 | L410: =SUM(L411:L538) | M410: =SUM(M411:M538) | N410: =SUM(N411:N538) | O410: =SUM(O411:O538) | P410: =SUM(P411:P538) | Q410: =SUM(Q411:Q538) | R410: =SUM(R411:R538) | S410: =SUM(S411:S538) | ... Y410: =SUM(Y411:Y538) | Z410: =LOWER(Settings!$C$4)&".mit."&$A410&IF($C410="","","."&$C410&"."&$B410)&IF(INDEX(Variables!$D$5:$D$45,MATCH($A410,Variables!$A$5:$A$45,0))="","","."&INDEX(Variables!$D$5:$D$45,MATCH($A410,Variables!$A$5:$A$45,0)))&"."&Z$5 | AA410: =SUM(AA411:AA538) | AB410: =SUM(AB411:AB538) | AC410: =SUM(AC411:AC538) | AD410: =SUM(AD411:AD538) | AE410: =SUM(AE411:AE538) | AF410: =SUM(AF411:AF538) | AG410: =SUM(AG411:AG538) | AH410: =SUM(AH411:AH538) | ... AN410: =SUM(AN411:AN538)
A411: ener | B411: coa | C411: rod | D411: =INDEX(Inputs!$K$5:$K$132,MATCH($B411&"|"&$C411,Inputs!$A$5:$A$132,0)) | E411: =INDEX(Inputs!$L$5:$L$132,MATCH($B411&"|"&$C411,Inputs!$A$5:$A$132,0)) | F411: =INDEX(Inputs!$M$5:$M$132,MATCH($B411&"|"&$C411,Inputs!$A$5:$A$132,0)) | G411: =INDEX(Inputs!$N$5:$N$132,MATCH($B411&"|"&$C411,Inputs!$A$5:$A$132,0)) | H411: =INDEX(Variables!$B$5:$B$45,MATCH($A411,Variables!$A$5:$A$45,0))&IF($C411="",""," | "&INDEX(Mapping!$B$5:$B$21,MATCH($C411,Mapping!$A$5:$A$21,0))&" | "&INDEX(Mapping!$B$24:$B$32,MATCH($B411,Mapping!$A$24:$A$32,0))) | I411: =INDEX(Variables!$C$5:$C$45,MATCH($A411,Variables!$A$5:$A$45,0)) | J411: =INDEX(Variables!$E$5:$E$45,MATCH($A411,Variables!$A$5:$A$45,0)) | K411: =LOWER(Settings!$C$4)&".mit."&$A411&IF($C411="","","."&$C411&"."&$B411)&IF(INDEX(Variables!$D$5:$D$45,MATCH($A411,Variables!$A$5:$A$45,0))="","","."&INDEX(Variables!$D$5:$D$45,MATCH($A411,Variables!$A$5:$A$45,0)))&"."&K$5 | L411: =INDEX(Inputs!$S$5:$S$132,MATCH($B411&"|"&$C411,Inputs!$A$5:$A$132,0)) | M411: =L411*(1/(1+$G411))^(1+$E411)*(1+M$7)^$D411*(M280/L280)^$E411*(M280/L280)^($F411*(1+$E411)) | N411: =M411*(1/(1+$G411))^(1+$E411)*(1+N$7)^$D411*(N280/M280)^$E411*(N280/M280)^($F411*(1+$E411)) | O411: =N411*(1/(1+$G411))^(1+$E411)*(1+O$7)^$D411*(O280/N280)^$E411*(O280/N280)^($F411*(1+$E411)) | P411: =O411*(1/(1+$G411))^(1+$E411)*(1+P$7)^$D411*(P280/O280)^$E411*(P280/O280)^($F411*(1+$E411)) | Q411: =P411*(1/(1+$G411))^(1+$E411)*(1+Q$7)^$D411*(Q280/P280)^$E411*(Q280/P280)^($F411*(1+$E411)) | R411: =Q411*(1/(1+$G411))^(1+$E411)*(1+R$7)^$D411*(R280/Q280)^$E411*(R280/Q280)^($F411*(1+$E411)) | S411: =R411*(1/(1+$G411))^(1+$E411)*(1+S$7)^$D411*(S280/R280)^$E411*(S280/R280)^($F411*(1+$E411)) | T411: =S411*(1/(1+$G411))^(1+$E411)*(1+T$7)^$D411*(T280/S280)^$E411*(T280/S280)^($F411*(1+$E411)) | ... X411: =W411*(1/(1+$G411))^(1+$E411)*(1+X$7)^$D411*(X280/W280)^$E411*(X280/W280)^($F411*(1+$E411)) | Y411: =FUELUSE(X411,Y280,X280,Y$7,$D411,$E411,$F411,$G411) | Z411: =LOWER(Settings!$C$4)&".mit."&$A411&IF($C411="","","."&$C411&"."&$B411)&IF(INDEX(Variables!$D$5:$D$45,MATCH($A411,Variables!$A$5:$A$45,0))="","","."&INDEX(Variables!$D$5:$D$45,MATCH($A411,Variables!$A$5:$A$45,0)))&"."&Z$5 | AA411: =INDEX(Inputs!$S$5:$S$132,MATCH($B411&"|"&$C411,Inputs!$A$5:$A$132,0)) | AB411: =AA411*(1/(1+$G411))^(1+$E411)*(1+AB$7)^$D411*(AB280/AA280)^$E411*(AB280/AA280)^($F411*(1+$E411)) | AC411: =AB411*(1/(1+$G411))^(1+$E411)*(1+AC$7)^$D411*(AC280/AB280)^$E411*(AC280/AB280)^($F411*(1+$E411)) | AD411: =AC411*(1/(1+$G411))^(1+$E411)*(1+AD$7)^$D411*(AD280/AC280)^$E411*(AD280/AC280)^($F411*(1+$E411)) | AE411: =AD411*(1/(1+$G411))^(1+$E411)*(1+AE$7)^$D411*(AE280/AD280)^$E411*(AE280/AD280)^($F411*(1+$E411)) | AF411: =AE411*(1/(1+$G411))^(1+$E411)*(1+AF$7)^$D411*(AF280/AE280)^$E411*(AF280/AE280)^($F411*(1+$E411)) | AG411: =AF411*(1/(1+$G411))^(1+$E411)*(1+AG$7)^$D411*(AG280/AF280)^$E411*(AG280/AF280)^($F411*(1+$E411)) | AH411: =AG411*(1/(1+$G411))^(1+$E411)*(1+AH$7)^$D411*(AH280/AG280)^$E411*(AH280/AG280)^($F411*(1+$E411)) | AI411: =AH411*(1/(1+$G411))^(1+$E411)*(1+AI$7)^$D411*(AI280/AH280)^$E411*(AI280/AH280)^($F411*(1+$E411)) | ... AM411: =AL411*(1/(1+$G411))^(1+$E411)*(1+AM$7)^$D411*(AM280/AL280)^$E411*(AM280/AL280)^($F411*(1+$E411)) | AN411: =FUELUSE(AM411,AN280,AM280,AN$7,$D411,$E411,$F411,$G411)
A412: ener | B412: nga | C412: rod | D412: =INDEX(Inputs!$K$5:$K$132,MATCH($B412&"|"&$C412,Inputs!$A$5:$A$132,0)) | E412: =INDEX(Inputs!$L$5:$L$132,MATCH($B412&"|"&$C412,Inputs!$A$5:$A$132,0)) | F412: =INDEX(Inputs!$M$5:$M$132,MATCH($B412&"|"&$C412,Inputs!$A$5:$A$132,0)) | G412: =INDEX(Inputs!$N$5:$N$132,MATCH($B412&"|"&$C412,Inputs!$A$5:$A$132,0)) | H412: =INDEX(Variables!$B$5:$B$45,MATCH($A412,Variables!$A$5:$A$45,0))&IF($C412="",""," | "&INDEX(Mapping!$B$5:$B$21,MATCH($C412,Mapping!$A$5:$A$21,0))&" | "&INDEX(Mapping!$B$24:$B$32,MATCH($B412,Mapping!$A$24:$A$32,0))) | I412: =INDEX(Variables!$C$5:$C$45,MATCH($A412,Variables!$A$5:$A$45,0)) | J412: =INDEX(Variables!$E$5:$E$45,MATCH($A412,Variables!$A$5:$A$45,0)) | K412: =LOWER(Settings!$C$4)&".mit."&$A412&IF($C412="","","."&$C412&"."&$B412)&IF(INDEX(Variables!$D$5:$D$45,MATCH($A412,Variables!$A$5:$A$45,0))="","","."&INDEX(Variables!$D$5:$D$45,MATCH($A412,Variables!$A$5:$A$45,0)))&"."&K$5 | L412: =INDEX(Inputs!$S$5:$S$132,MATCH($B412&"|"&$C412,Inputs!$A$5:$A$132,0)) | M412: =L412*(1/(1+$G412))^(1+$E412)*(1+M$7)^$D412*(M281/L281)^$E412*(M281/L281)^($F412*(1+$E412)) | N412: =M412*(1/(1+$G412))^(1+$E412)*(1+N$7)^$D412*(N281/M281)^$E412*(N281/M281)^($F412*(1+$E412)) | O412: =N412*(1/(1+$G412))^(1+$E412)*(1+O$7)^$D412*(O281/N281)^$E412*(O281/N281)^($F412*(1+$E412)) | P412: =O412*(1/(1+$G412))^(1+$E412)*(1+P$7)^$D412*(P281/O281)^$E412*(P281/O281)^($F412*(1+$E412)) | Q412: =P412*(1/(1+$G412))^(1+$E412)*(1+Q$7)^$D412*(Q281/P281)^$E412*(Q281/P281)^($F412*(1+$E412)) | R412: =Q412*(1/(1+$G412))^(1+$E412)*(1+R$7)^$D412*(R281/Q281)^$E412*(R281/Q281)^($F412*(1+$E412)) | S412: =R412*(1/(1+$G412))^(1+$E412)*(1+S$7)^$D412*(S281/R281)^$E412*(S281/R281)^($F412*(1+$E412)) | T412: =S412*(1/(1+$G412))^(1+$E412)*(1+T$7)^$D412*(T281/S281)^$E412*(T281/S281)^($F412*(1+$E412)) | ... X412: =W412*(1/(1+$G412))^(1+$E412)*(1+X$7)^$D412*(X281/W281)^$E412*(X281/W281)^($F412*(1+$E412)) | Y412: =FUELUSE(X412,Y281,X281,Y$7,$D412,$E412,$F412,$G412) | Z412: =LOWER(Settings!$C$4)&".mit."&$A412&IF($C412="","","."&$C412&"."&$B412)&IF(INDEX(Variables!$D$5:$D$45,MATCH($A412,Variables!$A$5:$A$45,0))="","","."&INDEX(Variables!$D$5:$D$45,MATCH($A412,Variables!$A$5:$A$45,0)))&"."&Z$5 | AA412: =INDEX(Inputs!$S$5:$S$132,MATCH($B412&"|"&$C412,Inputs!$A$5:$A$132,0)) | AB412: =AA412*(1/(1+$G412))^(1+$E412)*(1+AB$7)^$D412*(AB281/AA281)^$E412*(AB281/AA281)^($F412*(1+$E412)) | AC412: =AB412*(1/(1+$G412))^(1+$E412)*(1+AC$7)^$D412*(AC281/AB281)^$E412*(AC281/AB281)^($F412*(1+$E412)) | AD412: =AC412*(1/(1+$G412))^(1+$E412)*(1+AD$7)^$D412*(AD281/AC281)^$E412*(AD281/AC281)^($F412*(1+$E412)) | AE412: =AD412*(1/(1+$G412))^(1+$E412)*(1+AE$7)^$D412*(AE281/AD281)^$E412*(AE281/AD281)^($F412*(1+$E412)) | AF412: =AE412*(1/(1+$G412))^(1+$E412)*(1+AF$7)^$D412*(AF281/AE281)^$E412*(AF281/AE281)^($F412*(1+$E412)) | AG412: =AF412*(1/(1+$G412))^(1+$E412)*(1+AG$7)^$D412*(AG281/AF281)^$E412*(AG281/AF281)^($F412*(1+$E412)) | AH412: =AG412*(1/(1+$G412))^(1+$E412)*(1+AH$7)^$D412*(AH281/AG281)^$E412*(AH281/AG281)^($F412*(1+$E412)) | AI412: =AH412*(1/(1+$G412))^(1+$E412)*(1+AI$7)^$D412*(AI281/AH281)^$E412*(AI281/AH281)^($F412*(1+$E412)) | ... AM412: =AL412*(1/(1+$G412))^(1+$E412)*(1+AM$7)^$D412*(AM281/AL281)^$E412*(AM281/AL281)^($F412*(1+$E412)) | AN412: =FUELUSE(AM412,AN281,AM281,AN$7,$D412,$E412,$F412,$G412)
A413: ener | B413: gso | C413: rod | D413: =INDEX(Inputs!$K$5:$K$132,MATCH($B413&"|"&$C413,Inputs!$A$5:$A$132,0)) | E413: =INDEX(Inputs!$L$5:$L$132,MATCH($B413&"|"&$C413,Inputs!$A$5:$A$132,0)) | F413: =INDEX(Inputs!$M$5:$M$132,MATCH($B413&"|"&$C413,Inputs!$A$5:$A$132,0)) | G413: =INDEX(Inputs!$N$5:$N$132,MATCH($B413&"|"&$C413,Inputs!$A$5:$A$132,0)) | H413: =INDEX(Variables!$B$5:$B$45,MATCH($A413,Variables!$A$5:$A$45,0))&IF($C413="",""," | "&INDEX(Mapping!$B$5:$B$21,MATCH($C413,Mapping!$A$5:$A$21,0))&" | "&INDEX(Mapping!$B$24:$B$32,MATCH($B413,Mapping!$A$24:$A$32,0))) | I413: =INDEX(Variables!$C$5:$C$45,MATCH($A413,Variables!$A$5:$A$45,0)) | J413: =INDEX(Variables!$E$5:$E$45,MATCH($A413,Variables!$A$5:$A$45,0)) | K413: =LOWER(Settings!$C$4)&".mit."&$A413&IF($C413="","","."&$C413&"."&$B413)&IF(INDEX(Variables!$D$5:$D$45,MATCH($A413,Variables!$A$5:$A$45,0))="","","."&INDEX(Variables!$D$5:$D$45,MATCH($A413,Variables!$A$5:$A$45,0)))&"."&K$5 | L413: =INDEX(Inputs!$S$5:$S$132,MATCH($B413&"|"&$C413,Inputs!$A$5:$A$132,0)) | M413: =L413*(1/(1+$G413))^(1+$E413)*(1+M$7)^$D413*(M282/L282)^$E413*(M282/L282)^($F413*(1+$E413)) | N413: =M413*(1/(1+$G413))^(1+$E413)*(1+N$7)^$D413*(N282/M282)^$E413*(N282/M282)^($F413*(1+$E413)) | O413: =N413*(1/(1+$G413))^(1+$E413)*(1+O$7)^$D413*(O282/N282)^$E413*(O282/N282)^($F413*(1+$E413)) | P413: =O413*(1/(1+$G413))^(1+$E413)*(1+P$7)^$D413*(P282/O282)^$E413*(P282/O282)^($F413*(1+$E413)) | Q413: =P413*(1/(1+$G413))^(1+$E413)*(1+Q$7)^$D413*(Q282/P282)^$E413*(Q282/P282)^($F413*(1+$E413)) | R413: =Q413*(1/(1+$G413))^(1+$E413)*(1+R$7)^$D413*(R282/Q282)^$E413*(R282/Q282)^($F413*(1+$E413)) | S413: =R413*(1/(1+$G413))^(1+$E413)*(1+S$7)^$D413*(S282/R282)^$E413*(S282/R282)^($F413*(1+$E413)) | T413: =S413*(1/(1+$G413))^(1+$E413)*(1+T$7)^$D413*(T282/S282)^$E413*(T282/S282)^($F413*(1+$E413)) | ... X413: =W413*(1/(1+$G413))^(1+$E413)*(1+X$7)^$D413*(X282/W282)^$E413*(X282/W282)^($F413*(1+$E413)) | Y413: =FUELUSE(X413,Y282,X282,Y$7,$D413,$E413,$F413,$G413) | Z413: =LOWER(Settings!$C$4)&".mit."&$A413&IF($C413="","","."&$C413&"."&$B413)&IF(INDEX(Variables!$D$5:$D$45,MATCH($A413,Variables!$A$5:$A$45,0))="","","."&INDEX(Variables!$D$5:$D$45,MATCH($A413,Variables!$A$5:$A$45,0)))&"."&Z$5 | AA413: =INDEX(Inputs!$S$5:$S$132,MATCH($B413&"|"&$C413,Inputs!$A$5:$A$132,0)) | AB413: =AA413*(1/(1+$G413))^(1+$E413)*(1+AB$7)^$D413*(AB282/AA282)^$E413*(AB282/AA282)^($F413*(1+$E413)) | AC413: =AB413*(1/(1+$G413))^(1+$E413)*(1+AC$7)^$D413*(AC282/AB282)^$E413*(AC282/AB282)^($F413*(1+$E413)) | AD413: =AC413*(1/(1+$G413))^(1+$E413)*(1+AD$7)^$D413*(AD282/AC282)^$E413*(AD282/AC282)^($F413*(1+$E413)) | AE413: =AD413*(1/(1+$G413))^(1+$E413)*(1+AE$7)^$D413*(AE282/AD282)^$E413*(AE282/AD282)^($F413*(1+$E413)) | AF413: =AE413*(1/(1+$G413))^(1+$E413)*(1+AF$7)^$D413*(AF282/AE282)^$E413*(AF282/AE282)^($F413*(1+$E413)) | AG413: =AF413*(1/(1+$G413))^(1+$E413)*(1+AG$7)^$D413*(AG282/AF282)^$E413*(AG282/AF282)^($F413*(1+$E413)) | AH413: =AG413*(1/(1+$G413))^(1+$E413)*(1+AH$7)^$D413*(AH282/AG282)^$E413*(AH282/AG282)^($F413*(1+$E413)) | AI413: =AH413*(1/(1+$G413))^(1+$E413)*(1+AI$7)^$D413*(AI282/AH282)^$E413*(AI282/AH282)^($F413*(1+$E413)) | ... AM413: =AL413*(1/(1+$G413))^(1+$E413)*(1+AM$7)^$D413*(AM282/AL282)^$E413*(AM282/AL282)^($F413*(1+$E413)) | AN413: =FUELUSE(AM413,AN282,AM282,AN$7,$D413,$E413,$F413,$G413)
A414: ener | B414: die | C414: rod | D414: =INDEX(Inputs!$K$5:$K$132,MATCH($B414&"|"&$C414,Inputs!$A$5:$A$132,0)) | E414: =INDEX(Inputs!$L$5:$L$132,MATCH($B414&"|"&$C414,Inputs!$A$5:$A$132,0)) | F414: =INDEX(Inputs!$M$5:$M$132,MATCH($B414&"|"&$C414,Inputs!$A$5:$A$132,0)) | G414: =INDEX(Inputs!$N$5:$N$132,MATCH($B414&"|"&$C414,Inputs!$A$5:$A$132,0)) | H414: =INDEX(Variables!$B$5:$B$45,MATCH($A414,Variables!$A$5:$A$45,0))&IF($C414="",""," | "&INDEX(Mapping!$B$5:$B$21,MATCH($C414,Mapping!$A$5:$A$21,0))&" | "&INDEX(Mapping!$B$24:$B$32,MATCH($B414,Mapping!$A$24:$A$32,0))) | I414: =INDEX(Variables!$C$5:$C$45,MATCH($A414,Variables!$A$5:$A$45,0)) | J414: =INDEX(Variables!$E$5:$E$45,MATCH($A414,Variables!$A$5:$A$45,0)) | K414: =LOWER(Settings!$C$4)&".mit."&$A414&IF($C414="","","."&$C414&"."&$B414)&IF(INDEX(Variables!$D$5:$D$45,MATCH($A414,Variables!$A$5:$A$45,0))="","","."&INDEX(Variables!$D$5:$D$45,MATCH($A414,Variables!$A$5:$A$45,0)))&"."&K$5 | L414: =INDEX(Inputs!$S$5:$S$132,MATCH($B414&"|"&$C414,Inputs!$A$5:$A$132,0)) | M414: =L414*(1/(1+$G414))^(1+$E414)*(1+M$7)^$D414*(M283/L283)^$E414*(M283/L283)^($F414*(1+$E414)) | N414: =M414*(1/(1+$G414))^(1+$E414)*(1+N$7)^$D414*(N283/M283)^$E414*(N283/M283)^($F414*(1+$E414)) | O414: =N414*(1/(1+$G414))^(1+$E414)*(1+O$7)^$D414*(O283/N283)^$E414*(O283/N283)^($F414*(1+$E414)) | P414: =O414*(1/(1+$G414))^(1+$E414)*(1+P$7)^$D414*(P283/O283)^$E414*(P283/O283)^($F414*(1+$E414)) | Q414: =P414*(1/(1+$G414))^(1+$E414)*(1+Q$7)^$D414*(Q283/P283)^$E414*(Q283/P283)^($F414*(1+$E414)) | R414: =Q414*(1/(1+$G414))^(1+$E414)*(1+R$7)^$D414*(R283/Q283)^$E414*(R283/Q283)^($F414*(1+$E414)) | S414: =R414*(1/(1+$G414))^(1+$E414)*(1+S$7)^$D414*(S283/R283)^$E414*(S283/R283)^($F414*(1+$E414)) | T414: =S414*(1/(1+$G414))^(1+$E414)*(1+T$7)^$D414*(T283/S283)^$E414*(T283/S283)^($F414*(1+$E414)) | ... X414: =W414*(1/(1+$G414))^(1+$E414)*(1+X$7)^$D414*(X283/W283)^$E414*(X283/W283)^($F414*(1+$E414)) | Y414: =FUELUSE(X414,Y283,X283,Y$7,$D414,$E414,$F414,$G414) | Z414: =LOWER(Settings!$C$4)&".mit."&$A414&IF($C414="","","."&$C414&"."&$B414)&IF(INDEX(Variables!$D$5:$D$45,MATCH($A414,Variables!$A$5:$A$45,0))="","","."&INDEX(Variables!$D$5:$D$45,MATCH($A414,Variables!$A$5:$A$45,0)))&"."&Z$5 | AA414: =INDEX(Inputs!$S$5:$S$132,MATCH($B414&"|"&$C414,Inputs!$A$5:$A$132,0)) | AB414: =AA414*(1/(1+$G414))^(1+$E414)*(1+AB$7)^$D414*(AB283/AA283)^$E414*(AB283/AA283)^($F414*(1+$E414)) | AC414: =AB414*(1/(1+$G414))^(1+$E414)*(1+AC$7)^$D414*(AC283/AB283)^$E414*(AC283/AB283)^($F414*(1+$E414)) | AD414: =AC414*(1/(1+$G414))^(1+$E414)*(1+AD$7)^$D414*(AD283/AC283)^$E414*(AD283/AC283)^($F414*(1+$E414)) | AE414: =AD414*(1/(1+$G414))^(1+$E414)*(1+AE$7)^$D414*(AE283/AD283)^$E414*(AE283/AD283)^($F414*(1+$E414)) | AF414: =AE414*(1/(1+$G414))^(1+$E414)*(1+AF$7)^$D414*(AF283/AE283)^$E414*(AF283/AE283)^($F414*(1+$E414)) | AG414: =AF414*(1/(1+$G414))^(1+$E414)*(1+AG$7)^$D414*(AG283/AF283)^$E414*(AG283/AF283)^($F414*(1+$E414)) | AH414: =AG414*(1/(1+$G414))^(1+$E414)*(1+AH$7)^$D414*(AH283/AG283)^$E414*(AH283/AG283)^($F414*(1+$E414)) | AI414: =AH414*(1/(1+$G414))^(1+$E414)*(1+AI$7)^$D414*(AI283/AH283)^$E414*(AI283/AH283)^($F414*(1+$E414)) | ... AM414: =AL414*(1/(1+$G414))^(1+$E414)*(1+AM$7)^$D414*(AM283/AL283)^$E414*(AM283/AL283)^($F414*(1+$E414)) | AN414: =FUELUSE(AM414,AN283,AM283,AN$7,$D414,$E414,$F414,$G414)
A415: ener | B415: lpg | C415: rod | D415: =INDEX(Inputs!$K$5:$K$132,MATCH($B415&"|"&$C415,Inputs!$A$5:$A$132,0)) | E415: =INDEX(Inputs!$L$5:$L$132,MATCH($B415&"|"&$C415,Inputs!$A$5:$A$132,0)) | F415: =INDEX(Inputs!$M$5:$M$132,MATCH($B415&"|"&$C415,Inputs!$A$5:$A$132,0)) | G415: =INDEX(Inputs!$N$5:$N$132,MATCH($B415&"|"&$C415,Inputs!$A$5:$A$132,0)) | H415: =INDEX(Variables!$B$5:$B$45,MATCH($A415,Variables!$A$5:$A$45,0))&IF($C415="",""," | "&INDEX(Mapping!$B$5:$B$21,MATCH($C415,Mapping!$A$5:$A$21,0))&" | "&INDEX(Mapping!$B$24:$B$32,MATCH($B415,Mapping!$A$24:$A$32,0))) | I415: =INDEX(Variables!$C$5:$C$45,MATCH($A415,Variables!$A$5:$A$45,0)) | J415: =INDEX(Variables!$E$5:$E$45,MATCH($A415,Variables!$A$5:$A$45,0)) | K415: =LOWER(Settings!$C$4)&".mit."&$A415&IF($C415="","","."&$C415&"."&$B415)&IF(INDEX(Variables!$D$5:$D$45,MATCH($A415,Variables!$A$5:$A$45,0))="","","."&INDEX(Variables!$D$5:$D$45,MATCH($A415,Variables!$A$5:$A$45,0)))&"."&K$5 | L415: =INDEX(Inputs!$S$5:$S$132,MATCH($B415&"|"&$C415,Inputs!$A$5:$A$132,0)) | M415: =L415*(1/(1+$G415))^(1+$E415)*(1+M$7)^$D415*(M284/L284)^$E415*(M284/L284)^($F415*(1+$E415)) | N415: =M415*(1/(1+$G415))^(1+$E415)*(1+N$7)^$D415*(N284/M284)^$E415*(N284/M284)^($F415*(1+$E415)) | O415: =N415*(1/(1+$G415))^(1+$E415)*(1+O$7)^$D415*(O284/N284)^$E415*(O284/N284)^($F415*(1+$E415)) | P415: =O415*(1/(1+$G415))^(1+$E415)*(1+P$7)^$D415*(P284/O284)^$E415*(P284/O284)^($F415*(1+$E415)) | Q415: =P415*(1/(1+$G415))^(1+$E415)*(1+Q$7)^$D415*(Q284/P284)^$E415*(Q284/P284)^($F415*(1+$E415)) | R415: =Q415*(1/(1+$G415))^(1+$E415)*(1+R$7)^$D415*(R284/Q284)^$E415*(R284/Q284)^($F415*(1+$E415)) | S415: =R415*(1/(1+$G415))^(1+$E415)*(1+S$7)^$D415*(S284/R284)^$E415*(S284/R284)^($F415*(1+$E415)) | T415: =S415*(1/(1+$G415))^(1+$E415)*(1+T$7)^$D415*(T284/S284)^$E415*(T284/S284)^($F415*(1+$E415)) | ... X415: =W415*(1/(1+$G415))^(1+$E415)*(1+X$7)^$D415*(X284/W284)^$E415*(X284/W284)^($F415*(1+$E415)) | Y415: =FUELUSE(X415,Y284,X284,Y$7,$D415,$E415,$F415,$G415) | Z415: =LOWER(Settings!$C$4)&".mit."&$A415&IF($C415="","","."&$C415&"."&$B415)&IF(INDEX(Variables!$D$5:$D$45,MATCH($A415,Variables!$A$5:$A$45,0))="","","."&INDEX(Variables!$D$5:$D$45,MATCH($A415,Variables!$A$5:$A$45,0)))&"."&Z$5 | AA415: =INDEX(Inputs!$S$5:$S$132,MATCH($B415&"|"&$C415,Inputs!$A$5:$A$132,0)) | AB415: =AA415*(1/(1+$G415))^(1+$E415)*(1+AB$7)^$D415*(AB284/AA284)^$E415*(AB284/AA284)^($F415*(1+$E415)) | AC415: =AB415*(1/(1+$G415))^(1+$E415)*(1+AC$7)^$D415*(AC284/AB284)^$E415*(AC284/AB284)^($F415*(1+$E415)) | AD415: =AC415*(1/(1+$G415))^(1+$E415)*(1+AD$7)^$D415*(AD284/AC284)^$E415*(AD284/AC284)^($F415*(1+$E415)) | AE415: =AD415*(1/(1+$G415))^(1+$E415)*(1+AE$7)^$D415*(AE284/AD284)^$E415*(AE284/AD284)^($F415*(1+$E415)) | AF415: =AE415*(1/(1+$G415))^(1+$E415)*(1+AF$7)^$D415*(AF284/AE284)^$E415*(AF284/AE284)^($F415*(1+$E415)) | AG415: =AF415*(1/(1+$G415))^(1+$E415)*(1+AG$7)^$D415*(AG284/AF284)^$E415*(AG284/AF284)^($F415*(1+$E415)) | AH415: =AG415*(1/(1+$G415))^(1+$E415)*(1+AH$7)^$D415*(AH284/AG284)^$E415*(AH284/AG284)^($F415*(1+$E415)) | AI415: =AH415*(1/(1+$G415))^(1+$E415)*(1+AI$7)^$D415*(AI284/AH284)^$E415*(AI284/AH284)^($F415*(1+$E415)) | ... AM415: =AL415*(1/(1+$G415))^(1+$E415)*(1+AM$7)^$D415*(AM284/AL284)^$E415*(AM284/AL284)^($F415*(1+$E415)) | AN415: =FUELUSE(AM415,AN284,AM284,AN$7,$D415,$E415,$F415,$G415)
A416: ener | B416: ker | C416: rod | D416: =INDEX(Inputs!$K$5:$K$132,MATCH($B416&"|"&$C416,Inputs!$A$5:$A$132,0)) | E416: =INDEX(Inputs!$L$5:$L$132,MATCH($B416&"|"&$C416,Inputs!$A$5:$A$132,0)) | F416: =INDEX(Inputs!$M$5:$M$132,MATCH($B416&"|"&$C416,Inputs!$A$5:$A$132,0)) | G416: =INDEX(Inputs!$N$5:$N$132,MATCH($B416&"|"&$C416,Inputs!$A$5:$A$132,0)) | H416: =INDEX(Variables!$B$5:$B$45,MATCH($A416,Variables!$A$5:$A$45,0))&IF($C416="",""," | "&INDEX(Mapping!$B$5:$B$21,MATCH($C416,Mapping!$A$5:$A$21,0))&" | "&INDEX(Mapping!$B$24:$B$32,MATCH($B416,Mapping!$A$24:$A$32,0))) | I416: =INDEX(Variables!$C$5:$C$45,MATCH($A416,Variables!$A$5:$A$45,0)) | J416: =INDEX(Variables!$E$5:$E$45,MATCH($A416,Variables!$A$5:$A$45,0)) | K416: =LOWER(Settings!$C$4)&".mit."&$A416&IF($C416="","","."&$C416&"."&$B416)&IF(INDEX(Variables!$D$5:$D$45,MATCH($A416,Variables!$A$5:$A$45,0))="","","."&INDEX(Variables!$D$5:$D$45,MATCH($A416,Variables!$A$5:$A$45,0)))&"."&K$5 | L416: =INDEX(Inputs!$S$5:$S$132,MATCH($B416&"|"&$C416,Inputs!$A$5:$A$132,0)) | M416: =L416*(1/(1+$G416))^(1+$E416)*(1+M$7)^$D416*(M285/L285)^$E416*(M285/L285)^($F416*(1+$E416)) | N416: =M416*(1/(1+$G416))^(1+$E416)*(1+N$7)^$D416*(N285/M285)^$E416*(N285/M285)^($F416*(1+$E416)) | O416: =N416*(1/(1+$G416))^(1+$E416)*(1+O$7)^$D416*(O285/N285)^$E416*(O285/N285)^($F416*(1+$E416)) | P416: =O416*(1/(1+$G416))^(1+$E416)*(1+P$7)^$D416*(P285/O285)^$E416*(P285/O285)^($F416*(1+$E416)) | Q416: =P416*(1/(1+$G416))^(1+$E416)*(1+Q$7)^$D416*(Q285/P285)^$E416*(Q285/P285)^($F416*(1+$E416)) | R416: =Q416*(1/(1+$G416))^(1+$E416)*(1+R$7)^$D416*(R285/Q285)^$E416*(R285/Q285)^($F416*(1+$E416)) | S416: =R416*(1/(1+$G416))^(1+$E416)*(1+S$7)^$D416*(S285/R285)^$E416*(S285/R285)^($F416*(1+$E416)) | T416: =S416*(1/(1+$G416))^(1+$E416)*(1+T$7)^$D416*(T285/S285)^$E416*(T285/S285)^($F416*(1+$E416)) | ... X416: =W416*(1/(1+$G416))^(1+$E416)*(1+X$7)^$D416*(X285/W285)^$E416*(X285/W285)^($F416*(1+$E416)) | Y416: =FUELUSE(X416,Y285,X285,Y$7,$D416,$E416,$F416,$G416) | Z416: =LOWER(Settings!$C$4)&".mit."&$A416&IF($C416="","","."&$C416&"."&$B416)&IF(INDEX(Variables!$D$5:$D$45,MATCH($A416,Variables!$A$5:$A$45,0))="","","."&INDEX(Variables!$D$5:$D$45,MATCH($A416,Variables!$A$5:$A$45,0)))&"."&Z$5 | AA416: =INDEX(Inputs!$S$5:$S$132,MATCH($B416&"|"&$C416,Inputs!$A$5:$A$132,0)) | AB416: =AA416*(1/(1+$G416))^(1+$E416)*(1+AB$7)^$D416*(AB285/AA285)^$E416*(AB285/AA285)^($F416*(1+$E416)) | AC416: =AB416*(1/(1+$G416))^(1+$E416)*(1+AC$7)^$D416*(AC285/AB285)^$E416*(AC285/AB285)^($F416*(1+$E416)) | AD416: =AC416*(1/(1+$G416))^(1+$E416)*(1+AD$7)^$D416*(AD285/AC285)^$E416*(AD285/AC285)^($F416*(1+$E416)) | AE416: =AD416*(1/(1+$G416))^(1+$E416)*(1+AE$7)^$D416*(AE285/AD285)^$E416*(AE285/AD285)^($F416*(1+$E416)) | AF416: =AE416*(1/(1+$G416))^(1+$E416)*(1+AF$7)^$D416*(AF285/AE285)^$E416*(AF285/AE285)^($F416*(1+$E416)) | AG416: =AF416*(1/(1+$G416))^(1+$E416)*(1+AG$7)^$D416*(AG285/AF285)^$E416*(AG285/AF285)^($F416*(1+$E416)) | AH416: =AG416*(1/(1+$G416))^(1+$E416)*(1+AH$7)^$D416*(AH285/AG285)^$E416*(AH285/AG285)^($F416*(1+$E416)) | AI416: =AH416*(1/(1+$G416))^(1+$E416)*(1+AI$7)^$D416*(AI285/AH285)^$E416*(AI285/AH285)^($F416*(1+$E416)) | ... AM416: =AL416*(1/(1+$G416))^(1+$E416)*(1+AM$7)^$D416*(AM285/AL285)^$E416*(AM285/AL285)^($F416*(1+$E416)) | AN416: =FUELUSE(AM416,AN285,AM285,AN$7,$D416,$E416,$F416,$G416)
A417: ener | B417: oop | C417: rod | D417: =INDEX(Inputs!$K$5:$K$132,MATCH($B417&"|"&$C417,Inputs!$A$5:$A$132,0)) | E417: =INDEX(Inputs!$L$5:$L$132,MATCH($B417&"|"&$C417,Inputs!$A$5:$A$132,0)) | F417: =INDEX(Inputs!$M$5:$M$132,MATCH($B417&"|"&$C417,Inputs!$A$5:$A$132,0)) | G417: =INDEX(Inputs!$N$5:$N$132,MATCH($B417&"|"&$C417,Inputs!$A$5:$A$132,0)) | H417: =INDEX(Variables!$B$5:$B$45,MATCH($A417,Variables!$A$5:$A$45,0))&IF($C417="",""," | "&INDEX(Mapping!$B$5:$B$21,MATCH($C417,Mapping!$A$5:$A$21,0))&" | "&INDEX(Mapping!$B$24:$B$32,MATCH($B417,Mapping!$A$24:$A$32,0))) | I417: =INDEX(Variables!$C$5:$C$45,MATCH($A417,Variables!$A$5:$A$45,0)) | J417: =INDEX(Variables!$E$5:$E$45,MATCH($A417,Variables!$A$5:$A$45,0)) | K417: =LOWER(Settings!$C$4)&".mit."&$A417&IF($C417="","","."&$C417&"."&$B417)&IF(INDEX(Variables!$D$5:$D$45,MATCH($A417,Variables!$A$5:$A$45,0))="","","."&INDEX(Variables!$D$5:$D$45,MATCH($A417,Variables!$A$5:$A$45,0)))&"."&K$5 | L417: =INDEX(Inputs!$S$5:$S$132,MATCH($B417&"|"&$C417,Inputs!$A$5:$A$132,0)) | M417: =L417*(1/(1+$G417))^(1+$E417)*(1+M$7)^$D417*(M286/L286)^$E417*(M286/L286)^($F417*(1+$E417)) | N417: =M417*(1/(1+$G417))^(1+$E417)*(1+N$7)^$D417*(N286/M286)^$E417*(N286/M286)^($F417*(1+$E417)) | O417: =N417*(1/(1+$G417))^(1+$E417)*(1+O$7)^$D417*(O286/N286)^$E417*(O286/N286)^($F417*(1+$E417)) | P417: =O417*(1/(1+$G417))^(1+$E417)*(1+P$7)^$D417*(P286/O286)^$E417*(P286/O286)^($F417*(1+$E417)) | Q417: =P417*(1/(1+$G417))^(1+$E417)*(1+Q$7)^$D417*(Q286/P286)^$E417*(Q286/P286)^($F417*(1+$E417)) | R417: =Q417*(1/(1+$G417))^(1+$E417)*(1+R$7)^$D417*(R286/Q286)^$E417*(R286/Q286)^($F417*(1+$E417)) | S417: =R417*(1/(1+$G417))^(1+$E417)*(1+S$7)^$D417*(S286/R286)^$E417*(S286/R286)^($F417*(1+$E417)) | T417: =S417*(1/(1+$G417))^(1+$E417)*(1+T$7)^$D417*(T286/S286)^$E417*(T286/S286)^($F417*(1+$E417)) | ... X417: =W417*(1/(1+$G417))^(1+$E417)*(1+X$7)^$D417*(X286/W286)^$E417*(X286/W286)^($F417*(1+$E417)) | Y417: =FUELUSE(X417,Y286,X286,Y$7,$D417,$E417,$F417,$G417) | Z417: =LOWER(Settings!$C$4)&".mit."&$A417&IF($C417="","","."&$C417&"."&$B417)&IF(INDEX(Variables!$D$5:$D$45,MATCH($A417,Variables!$A$5:$A$45,0))="","","."&INDEX(Variables!$D$5:$D$45,MATCH($A417,Variables!$A$5:$A$45,0)))&"."&Z$5 | AA417: =INDEX(Inputs!$S$5:$S$132,MATCH($B417&"|"&$C417,Inputs!$A$5:$A$132,0)) | AB417: =AA417*(1/(1+$G417))^(1+$E417)*(1+AB$7)^$D417*(AB286/AA286)^$E417*(AB286/AA286)^($F417*(1+$E417)) | AC417: =AB417*(1/(1+$G417))^(1+$E417)*(1+AC$7)^$D417*(AC286/AB286)^$E417*(AC286/AB286)^($F417*(1+$E417)) | AD417: =AC417*(1/(1+$G417))^(1+$E417)*(1+AD$7)^$D417*(AD286/AC286)^$E417*(AD286/AC286)^($F417*(1+$E417)) | AE417: =AD417*(1/(1+$G417))^(1+$E417)*(1+AE$7)^$D417*(AE286/AD286)^$E417*(AE286/AD286)^($F417*(1+$E417)) | AF417: =AE417*(1/(1+$G417))^(1+$E417)*(1+AF$7)^$D417*(AF286/AE286)^$E417*(AF286/AE286)^($F417*(1+$E417)) | AG417: =AF417*(1/(1+$G417))^(1+$E417)*(1+AG$7)^$D417*(AG286/AF286)^$E417*(AG286/AF286)^($F417*(1+$E417)) | AH417: =AG417*(1/(1+$G417))^(1+$E417)*(1+AH$7)^$D417*(AH286/AG286)^$E417*(AH286/AG286)^($F417*(1+$E417)) | AI417: =AH417*(1/(1+$G417))^(1+$E417)*(1+AI$7)^$D417*(AI286/AH286)^$E417*(AI286/AH286)^($F417*(1+$E417)) | ... AM417: =AL417*(1/(1+$G417))^(1+$E417)*(1+AM$7)^$D417*(AM286/AL286)^$E417*(AM286/AL286)^($F417*(1+$E417)) | AN417: =FUELUSE(AM417,AN286,AM286,AN$7,$D417,$E417,$F417,$G417)
A418: ener | B418: bio | C418: rod | D418: =INDEX(Inputs!$K$5:$K$132,MATCH($B418&"|"&$C418,Inputs!$A$5:$A$132,0)) | E418: =INDEX(Inputs!$L$5:$L$132,MATCH($B418&"|"&$C418,Inputs!$A$5:$A$132,0)) | F418: =INDEX(Inputs!$M$5:$M$132,MATCH($B418&"|"&$C418,Inputs!$A$5:$A$132,0)) | G418: =INDEX(Inputs!$N$5:$N$132,MATCH($B418&"|"&$C418,Inputs!$A$5:$A$132,0)) | H418: =INDEX(Variables!$B$5:$B$45,MATCH($A418,Variables!$A$5:$A$45,0))&IF($C418="",""," | "&INDEX(Mapping!$B$5:$B$21,MATCH($C418,Mapping!$A$5:$A$21,0))&" | "&INDEX(Mapping!$B$24:$B$32,MATCH($B418,Mapping!$A$24:$A$32,0))) | I418: =INDEX(Variables!$C$5:$C$45,MATCH($A418,Variables!$A$5:$A$45,0)) | J418: =INDEX(Variables!$E$5:$E$45,MATCH($A418,Variables!$A$5:$A$45,0)) | K418: =LOWER(Settings!$C$4)&".mit."&$A418&IF($C418="","","."&$C418&"."&$B418)&IF(INDEX(Variables!$D$5:$D$45,MATCH($A418,Variables!$A$5:$A$45,0))="","","."&INDEX(Variables!$D$5:$D$45,MATCH($A418,Variables!$A$5:$A$45,0)))&"."&K$5 | L418: =INDEX(Inputs!$S$5:$S$132,MATCH($B418&"|"&$C418,Inputs!$A$5:$A$132,0)) | M418: =L418*(1/(1+$G418))^(1+$E418)*(1+M$7)^$D418*(M287/L287)^$E418*(M287/L287)^($F418*(1+$E418)) | N418: =M418*(1/(1+$G418))^(1+$E418)*(1+N$7)^$D418*(N287/M287)^$E418*(N287/M287)^($F418*(1+$E418)) | O418: =N418*(1/(1+$G418))^(1+$E418)*(1+O$7)^$D418*(O287/N287)^$E418*(O287/N287)^($F418*(1+$E418)) | P418: =O418*(1/(1+$G418))^(1+$E418)*(1+P$7)^$D418*(P287/O287)^$E418*(P287/O287)^($F418*(1+$E418)) | Q418: =P418*(1/(1+$G418))^(1+$E418)*(1+Q$7)^$D418*(Q287/P287)^$E418*(Q287/P287)^($F418*(1+$E418)) | R418: =Q418*(1/(1+$G418))^(1+$E418)*(1+R$7)^$D418*(R287/Q287)^$E418*(R287/Q287)^($F418*(1+$E418)) | S418: =R418*(1/(1+$G418))^(1+$E418)*(1+S$7)^$D418*(S287/R287)^$E418*(S287/R287)^($F418*(1+$E418)) | T418: =S418*(1/(1+$G418))^(1+$E418)*(1+T$7)^$D418*(T287/S287)^$E418*(T287/S287)^($F418*(1+$E418)) | ... X418: =W418*(1/(1+$G418))^(1+$E418)*(1+X$7)^$D418*(X287/W287)^$E418*(X287/W287)^($F418*(1+$E418)) | Y418: =FUELUSE(X418,Y287,X287,Y$7,$D418,$E418,$F418,$G418) | Z418: =LOWER(Settings!$C$4)&".mit."&$A418&IF($C418="","","."&$C418&"."&$B418)&IF(INDEX(Variables!$D$5:$D$45,MATCH($A418,Variables!$A$5:$A$45,0))="","","."&INDEX(Variables!$D$5:$D$45,MATCH($A418,Variables!$A$5:$A$45,0)))&"."&Z$5 | AA418: =INDEX(Inputs!$S$5:$S$132,MATCH($B418&"|"&$C418,Inputs!$A$5:$A$132,0)) | AB418: =AA418*(1/(1+$G418))^(1+$E418)*(1+AB$7)^$D418*(AB287/AA287)^$E418*(AB287/AA287)^($F418*(1+$E418)) | AC418: =AB418*(1/(1+$G418))^(1+$E418)*(1+AC$7)^$D418*(AC287/AB287)^$E418*(AC287/AB287)^($F418*(1+$E418)) | AD418: =AC418*(1/(1+$G418))^(1+$E418)*(1+AD$7)^$D418*(AD287/AC287)^$E418*(AD287/AC287)^($F418*(1+$E418)) | AE418: =AD418*(1/(1+$G418))^(1+$E418)*(1+AE$7)^$D418*(AE287/AD287)^$E418*(AE287/AD287)^($F418*(1+$E418)) | AF418: =AE418*(1/(1+$G418))^(1+$E418)*(1+AF$7)^$D418*(AF287/AE287)^$E418*(AF287/AE287)^($F418*(1+$E418)) | AG418: =AF418*(1/(1+$G418))^(1+$E418)*(1+AG$7)^$D418*(AG287/AF287)^$E418*(AG287/AF287)^($F418*(1+$E418)) | AH418: =AG418*(1/(1+$G418))^(1+$E418)*(1+AH$7)^$D418*(AH287/AG287)^$E418*(AH287/AG287)^($F418*(1+$E418)) | AI418: =AH418*(1/(1+$G418))^(1+$E418)*(1+AI$7)^$D418*(AI287/AH287)^$E418*(AI287/AH287)^($F418*(1+$E418)) | ... AM418: =AL418*(1/(1+$G418))^(1+$E418)*(1+AM$7)^$D418*(AM287/AL287)^$E418*(AM287/AL287)^($F418*(1+$E418)) | AN418: =FUELUSE(AM418,AN287,AM287,AN$7,$D418,$E418,$F418,$G418)
A419: ener | B419: coa | C419: ral | D419: =INDEX(Inputs!$K$5:$K$132,MATCH($B419&"|"&$C419,Inputs!$A$5:$A$132,0)) | E419: =INDEX(Inputs!$L$5:$L$132,MATCH($B419&"|"&$C419,Inputs!$A$5:$A$132,0)) | F419: =INDEX(Inputs!$M$5:$M$132,MATCH($B419&"|"&$C419,Inputs!$A$5:$A$132,0)) | G419: =INDEX(Inputs!$N$5:$N$132,MATCH($B419&"|"&$C419,Inputs!$A$5:$A$132,0)) | H419: =INDEX(Variables!$B$5:$B$45,MATCH($A419,Variables!$A$5:$A$45,0))&IF($C419="",""," | "&INDEX(Mapping!$B$5:$B$21,MATCH($C419,Mapping!$A$5:$A$21,0))&" | "&INDEX(Mapping!$B$24:$B$32,MATCH($B419,Mapping!$A$24:$A$32,0))) | I419: =INDEX(Variables!$C$5:$C$45,MATCH($A419,Variables!$A$5:$A$45,0)) | J419: =INDEX(Variables!$E$5:$E$45,MATCH($A419,Variables!$A$5:$A$45,0)) | K419: =LOWER(Settings!$C$4)&".mit."&$A419&IF($C419="","","."&$C419&"."&$B419)&IF(INDEX(Variables!$D$5:$D$45,MATCH($A419,Variables!$A$5:$A$45,0))="","","."&INDEX(Variables!$D$5:$D$45,MATCH($A419,Variables!$A$5:$A$45,0)))&"."&K$5 | L419: =INDEX(Inputs!$S$5:$S$132,MATCH($B419&"|"&$C419,Inputs!$A$5:$A$132,0)) | M419: =L419*(1/(1+$G419))^(1+$E419)*(1+M$7)^$D419*(M288/L288)^$E419*(M288/L288)^($F419*(1+$E419)) | N419: =M419*(1/(1+$G419))^(1+$E419)*(1+N$7)^$D419*(N288/M288)^$E419*(N288/M288)^($F419*(1+$E419)) | O419: =N419*(1/(1+$G419))^(1+$E419)*(1+O$7)^$D419*(O288/N288)^$E419*(O288/N288)^($F419*(1+$E419)) | P419: =O419*(1/(1+$G419))^(1+$E419)*(1+P$7)^$D419*(P288/O288)^$E419*(P288/O288)^($F419*(1+$E419)) | Q419: =P419*(1/(1+$G419))^(1+$E419)*(1+Q$7)^$D419*(Q288/P288)^$E419*(Q288/P288)^($F419*(1+$E419)) | R419: =Q419*(1/(1+$G419))^(1+$E419)*(1+R$7)^$D419*(R288/Q288)^$E419*(R288/Q288)^($F419*(1+$E419)) | S419: =R419*(1/(1+$G419))^(1+$E419)*(1+S$7)^$D419*(S288/R288)^$E419*(S288/R288)^($F419*(1+$E419)) | T419: =S419*(1/(1+$G419))^(1+$E419)*(1+T$7)^$D419*(T288/S288)^$E419*(T288/S288)^($F419*(1+$E419)) | ... X419: =W419*(1/(1+$G419))^(1+$E419)*(1+X$7)^$D419*(X288/W288)^$E419*(X288/W288)^($F419*(1+$E419)) | Y419: =FUELUSE(X419,Y288,X288,Y$7,$D419,$E419,$F419,$G419) | Z419: =LOWER(Settings!$C$4)&".mit."&$A419&IF($C419="","","."&$C419&"."&$B419)&IF(INDEX(Variables!$D$5:$D$45,MATCH($A419,Variables!$A$5:$A$45,0))="","","."&INDEX(Variables!$D$5:$D$45,MATCH($A419,Variables!$A$5:$A$45,0)))&"."&Z$5 | AA419: =INDEX(Inputs!$S$5:$S$132,MATCH($B419&"|"&$C419,Inputs!$A$5:$A$132,0)) | AB419: =AA419*(1/(1+$G419))^(1+$E419)*(1+AB$7)^$D419*(AB288/AA288)^$E419*(AB288/AA288)^($F419*(1+$E419)) | AC419: =AB419*(1/(1+$G419))^(1+$E419)*(1+AC$7)^$D419*(AC288/AB288)^$E419*(AC288/AB288)^($F419*(1+$E419)) | AD419: =AC419*(1/(1+$G419))^(1+$E419)*(1+AD$7)^$D419*(AD288/AC288)^$E419*(AD288/AC288)^($F419*(1+$E419)) | AE419: =AD419*(1/(1+$G419))^(1+$E419)*(1+AE$7)^$D419*(AE288/AD288)^$E419*(AE288/AD288)^($F419*(1+$E419)) | AF419: =AE419*(1/(1+$G419))^(1+$E419)*(1+AF$7)^$D419*(AF288/AE288)^$E419*(AF288/AE288)^($F419*(1+$E419)) | AG419: =AF419*(1/(1+$G419))^(1+$E419)*(1+AG$7)^$D419*(AG288/AF288)^$E419*(AG288/AF288)^($F419*(1+$E419)) | AH419: =AG419*(1/(1+$G419))^(1+$E419)*(1+AH$7)^$D419*(AH288/AG288)^$E419*(AH288/AG288)^($F419*(1+$E419)) | AI419: =AH419*(1/(1+$G419))^(1+$E419)*(1+AI$7)^$D419*(AI288/AH288)^$E419*(AI288/AH288)^($F419*(1+$E419)) | ... AM419: =AL419*(1/(1+$G419))^(1+$E419)*(1+AM$7)^$D419*(AM288/AL288)^$E419*(AM288/AL288)^($F419*(1+$E419)) | AN419: =FUELUSE(AM419,AN288,AM288,AN$7,$D419,$E419,$F419,$G419)
A420: ener | B420: nga | C420: ral | D420: =INDEX(Inputs!$K$5:$K$132,MATCH($B420&"|"&$C420,Inputs!$A$5:$A$132,0)) | E420: =INDEX(Inputs!$L$5:$L$132,MATCH($B420&"|"&$C420,Inputs!$A$5:$A$132,0)) | F420: =INDEX(Inputs!$M$5:$M$132,MATCH($B420&"|"&$C420,Inputs!$A$5:$A$132,0)) | G420: =INDEX(Inputs!$N$5:$N$132,MATCH($B420&"|"&$C420,Inputs!$A$5:$A$132,0)) | H420: =INDEX(Variables!$B$5:$B$45,MATCH($A420,Variables!$A$5:$A$45,0))&IF($C420="",""," | "&INDEX(Mapping!$B$5:$B$21,MATCH($C420,Mapping!$A$5:$A$21,0))&" | "&INDEX(Mapping!$B$24:$B$32,MATCH($B420,Mapping!$A$24:$A$32,0))) | I420: =INDEX(Variables!$C$5:$C$45,MATCH($A420,Variables!$A$5:$A$45,0)) | J420: =INDEX(Variables!$E$5:$E$45,MATCH($A420,Variables!$A$5:$A$45,0)) | K420: =LOWER(Settings!$C$4)&".mit."&$A420&IF($C420="","","."&$C420&"."&$B420)&IF(INDEX(Variables!$D$5:$D$45,MATCH($A420,Variables!$A$5:$A$45,0))="","","."&INDEX(Variables!$D$5:$D$45,MATCH($A420,Variables!$A$5:$A$45,0)))&"."&K$5 | L420: =INDEX(Inputs!$S$5:$S$132,MATCH($B420&"|"&$C420,Inputs!$A$5:$A$132,0)) | M420: =L420*(1/(1+$G420))^(1+$E420)*(1+M$7)^$D420*(M289/L289)^$E420*(M289/L289)^($F420*(1+$E420)) | N420: =M420*(1/(1+$G420))^(1+$E420)*(1+N$7)^$D420*(N289/M289)^$E420*(N289/M289)^($F420*(1+$E420)) | O420: =N420*(1/(1+$G420))^(1+$E420)*(1+O$7)^$D420*(O289/N289)^$E420*(O289/N289)^($F420*(1+$E420)) | P420: =O420*(1/(1+$G420))^(1+$E420)*(1+P$7)^$D420*(P289/O289)^$E420*(P289/O289)^($F420*(1+$E420)) | Q420: =P420*(1/(1+$G420))^(1+$E420)*(1+Q$7)^$D420*(Q289/P289)^$E420*(Q289/P289)^($F420*(1+$E420)) | R420: =Q420*(1/(1+$G420))^(1+$E420)*(1+R$7)^$D420*(R289/Q289)^$E420*(R289/Q289)^($F420*(1+$E420)) | S420: =R420*(1/(1+$G420))^(1+$E420)*(1+S$7)^$D420*(S289/R289)^$E420*(S289/R289)^($F420*(1+$E420)) | T420: =S420*(1/(1+$G420))^(1+$E420)*(1+T$7)^$D420*(T289/S289)^$E420*(T289/S289)^($F420*(1+$E420)) | ... X420: =W420*(1/(1+$G420))^(1+$E420)*(1+X$7)^$D420*(X289/W289)^$E420*(X289/W289)^($F420*(1+$E420)) | Y420: =FUELUSE(X420,Y289,X289,Y$7,$D420,$E420,$F420,$G420) | Z420: =LOWER(Settings!$C$4)&".mit."&$A420&IF($C420="","","."&$C420&"."&$B420)&IF(INDEX(Variables!$D$5:$D$45,MATCH($A420,Variables!$A$5:$A$45,0))="","","."&INDEX(Variables!$D$5:$D$45,MATCH($A420,Variables!$A$5:$A$45,0)))&"."&Z$5 | AA420: =INDEX(Inputs!$S$5:$S$132,MATCH($B420&"|"&$C420,Inputs!$A$5:$A$132,0)) | AB420: =AA420*(1/(1+$G420))^(1+$E420)*(1+AB$7)^$D420*(AB289/AA289)^$E420*(AB289/AA289)^($F420*(1+$E420)) | AC420: =AB420*(1/(1+$G420))^(1+$E420)*(1+AC$7)^$D420*(AC289/AB289)^$E420*(AC289/AB289)^($F420*(1+$E420)) | AD420: =AC420*(1/(1+$G420))^(1+$E420)*(1+AD$7)^$D420*(AD289/AC289)^$E420*(AD289/AC289)^($F420*(1+$E420)) | AE420: =AD420*(1/(1+$G420))^(1+$E420)*(1+AE$7)^$D420*(AE289/AD289)^$E420*(AE289/AD289)^($F420*(1+$E420)) | AF420: =AE420*(1/(1+$G420))^(1+$E420)*(1+AF$7)^$D420*(AF289/AE289)^$E420*(AF289/AE289)^($F420*(1+$E420)) | AG420: =AF420*(1/(1+$G420))^(1+$E420)*(1+AG$7)^$D420*(AG289/AF289)^$E420*(AG289/AF289)^($F420*(1+$E420)) | AH420: =AG420*(1/(1+$G420))^(1+$E420)*(1+AH$7)^$D420*(AH289/AG289)^$E420*(AH289/AG289)^($F420*(1+$E420)) | AI420: =AH420*(1/(1+$G420))^(1+$E420)*(1+AI$7)^$D420*(AI289/AH289)^$E420*(AI289/AH289)^($F420*(1+$E420)) | ... AM420: =AL420*(1/(1+$G420))^(1+$E420)*(1+AM$7)^$D420*(AM289/AL289)^$E420*(AM289/AL289)^($F420*(1+$E420)) | AN420: =FUELUSE(AM420,AN289,AM289,AN$7,$D420,$E420,$F420,$G420)
A421: ener | B421: gso | C421: ral | D421: =INDEX(Inputs!$K$5:$K$132,MATCH($B421&"|"&$C421,Inputs!$A$5:$A$132,0)) | E421: =INDEX(Inputs!$L$5:$L$132,MATCH($B421&"|"&$C421,Inputs!$A$5:$A$132,0)) | F421: =INDEX(Inputs!$M$5:$M$132,MATCH($B421&"|"&$C421,Inputs!$A$5:$A$132,0)) | G421: =INDEX(Inputs!$N$5:$N$132,MATCH($B421&"|"&$C421,Inputs!$A$5:$A$132,0)) | H421: =INDEX(Variables!$B$5:$B$45,MATCH($A421,Variables!$A$5:$A$45,0))&IF($C421="",""," | "&INDEX(Mapping!$B$5:$B$21,MATCH($C421,Mapping!$A$5:$A$21,0))&" | "&INDEX(Mapping!$B$24:$B$32,MATCH($B421,Mapping!$A$24:$A$32,0))) | I421: =INDEX(Variables!$C$5:$C$45,MATCH($A421,Variables!$A$5:$A$45,0)) | J421: =INDEX(Variables!$E$5:$E$45,MATCH($A421,Variables!$A$5:$A$45,0)) | K421: =LOWER(Settings!$C$4)&".mit."&$A421&IF($C421="","","."&$C421&"."&$B421)&IF(INDEX(Variables!$D$5:$D$45,MATCH($A421,Variables!$A$5:$A$45,0))="","","."&INDEX(Variables!$D$5:$D$45,MATCH($A421,Variables!$A$5:$A$45,0)))&"."&K$5 | L421: =INDEX(Inputs!$S$5:$S$132,MATCH($B421&"|"&$C421,Inputs!$A$5:$A$132,0)) | M421: =L421*(1/(1+$G421))^(1+$E421)*(1+M$7)^$D421*(M290/L290)^$E421*(M290/L290)^($F421*(1+$E421)) | N421: =M421*(1/(1+$G421))^(1+$E421)*(1+N$7)^$D421*(N290/M290)^$E421*(N290/M290)^($F421*(1+$E421)) | O421: =N421*(1/(1+$G421))^(1+$E421)*(1+O$7)^$D421*(O290/N290)^$E421*(O290/N290)^($F421*(1+$E421)) | P421: =O421*(1/(1+$G421))^(1+$E421)*(1+P$7)^$D421*(P290/O290)^$E421*(P290/O290)^($F421*(1+$E421)) | Q421: =P421*(1/(1+$G421))^(1+$E421)*(1+Q$7)^$D421*(Q290/P290)^$E421*(Q290/P290)^($F421*(1+$E421)) | R421: =Q421*(1/(1+$G421))^(1+$E421)*(1+R$7)^$D421*(R290/Q290)^$E421*(R290/Q290)^($F421*(1+$E421)) | S421: =R421*(1/(1+$G421))^(1+$E421)*(1+S$7)^$D421*(S290/R290)^$E421*(S290/R290)^($F421*(1+$E421)) | T421: =S421*(1/(1+$G421))^(1+$E421)*(1+T$7)^$D421*(T290/S290)^$E421*(T290/S290)^($F421*(1+$E421)) | ... X421: =W421*(1/(1+$G421))^(1+$E421)*(1+X$7)^$D421*(X290/W290)^$E421*(X290/W290)^($F421*(1+$E421)) | Y421: =FUELUSE(X421,Y290,X290,Y$7,$D421,$E421,$F421,$G421) | Z421: =LOWER(Settings!$C$4)&".mit."&$A421&IF($C421="","","."&$C421&"."&$B421)&IF(INDEX(Variables!$D$5:$D$45,MATCH($A421,Variables!$A$5:$A$45,0))="","","."&INDEX(Variables!$D$5:$D$45,MATCH($A421,Variables!$A$5:$A$45,0)))&"."&Z$5 | AA421: =INDEX(Inputs!$S$5:$S$132,MATCH($B421&"|"&$C421,Inputs!$A$5:$A$132,0)) | AB421: =AA421*(1/(1+$G421))^(1+$E421)*(1+AB$7)^$D421*(AB290/AA290)^$E421*(AB290/AA290)^($F421*(1+$E421)) | AC421: =AB421*(1/(1+$G421))^(1+$E421)*(1+AC$7)^$D421*(AC290/AB290)^$E421*(AC290/AB290)^($F421*(1+$E421)) | AD421: =AC421*(1/(1+$G421))^(1+$E421)*(1+AD$7)^$D421*(AD290/AC290)^$E421*(AD290/AC290)^($F421*(1+$E421)) | AE421: =AD421*(1/(1+$G421))^(1+$E421)*(1+AE$7)^$D421*(AE290/AD290)^$E421*(AE290/AD290)^($F421*(1+$E421)) | AF421: =AE421*(1/(1+$G421))^(1+$E421)*(1+AF$7)^$D421*(AF290/AE290)^$E421*(AF290/AE290)^($F421*(1+$E421)) | AG421: =AF421*(1/(1+$G421))^(1+$E421)*(1+AG$7)^$D421*(AG290/AF290)^$E421*(AG290/AF290)^($F421*(1+$E421)) | AH421: =AG421*(1/(1+$G421))^(1+$E421)*(1+AH$7)^$D421*(AH290/AG290)^$E421*(AH290/AG290)^($F421*(1+$E421)) | AI421: =AH421*(1/(1+$G421))^(1+$E421)*(1+AI$7)^$D421*(AI290/AH290)^$E421*(AI290/AH290)^($F421*(1+$E421)) | ... AM421: =AL421*(1/(1+$G421))^(1+$E421)*(1+AM$7)^$D421*(AM290/AL290)^$E421*(AM290/AL290)^($F421*(1+$E421)) | AN421: =FUELUSE(AM421,AN290,AM290,AN$7,$D421,$E421,$F421,$G421)
A422: ener | B422: die | C422: ral | D422: =INDEX(Inputs!$K$5:$K$132,MATCH($B422&"|"&$C422,Inputs!$A$5:$A$132,0)) | E422: =INDEX(Inputs!$L$5:$L$132,MATCH($B422&"|"&$C422,Inputs!$A$5:$A$132,0)) | F422: =INDEX(Inputs!$M$5:$M$132,MATCH($B422&"|"&$C422,Inputs!$A$5:$A$132,0)) | G422: =INDEX(Inputs!$N$5:$N$132,MATCH($B422&"|"&$C422,Inputs!$A$5:$A$132,0)) | H422: =INDEX(Variables!$B$5:$B$45,MATCH($A422,Variables!$A$5:$A$45,0))&IF($C422="",""," | "&INDEX(Mapping!$B$5:$B$21,MATCH($C422,Mapping!$A$5:$A$21,0))&" | "&INDEX(Mapping!$B$24:$B$32,MATCH($B422,Mapping!$A$24:$A$32,0))) | I422: =INDEX(Variables!$C$5:$C$45,MATCH($A422,Variables!$A$5:$A$45,0)) | J422: =INDEX(Variables!$E$5:$E$45,MATCH($A422,Variables!$A$5:$A$45,0)) | K422: =LOWER(Settings!$C$4)&".mit."&$A422&IF($C422="","","."&$C422&"."&$B422)&IF(INDEX(Variables!$D$5:$D$45,MATCH($A422,Variables!$A$5:$A$45,0))="","","."&INDEX(Variables!$D$5:$D$45,MATCH($A422,Variables!$A$5:$A$45,0)))&"."&K$5 | L422: =INDEX(Inputs!$S$5:$S$132,MATCH($B422&"|"&$C422,Inputs!$A$5:$A$132,0)) | M422: =L422*(1/(1+$G422))^(1+$E422)*(1+M$7)^$D422*(M291/L291)^$E422*(M291/L291)^($F422*(1+$E422)) | N422: =M422*(1/(1+$G422))^(1+$E422)*(1+N$7)^$D422*(N291/M291)^$E422*(N291/M291)^($F422*(1+$E422)) | O422: =N422*(1/(1+$G422))^(1+$E422)*(1+O$7)^$D422*(O291/N291)^$E422*(O291/N291)^($F422*(1+$E422)) | P422: =O422*(1/(1+$G422))^(1+$E422)*(1+P$7)^$D422*(P291/O291)^$E422*(P291/O291)^($F422*(1+$E422)) | Q422: =P422*(1/(1+$G422))^(1+$E422)*(1+Q$7)^$D422*(Q291/P291)^$E422*(Q291/P291)^($F422*(1+$E422)) | R422: =Q422*(1/(1+$G422))^(1+$E422)*(1+R$7)^$D422*(R291/Q291)^$E422*(R291/Q291)^($F422*(1+$E422)) | S422: =R422*(1/(1+$G422))^(1+$E422)*(1+S$7)^$D422*(S291/R291)^$E422*(S291/R291)^($F422*(1+$E422)) | T422: =S422*(1/(1+$G422))^(1+$E422)*(1+T$7)^$D422*(T291/S291)^$E422*(T291/S291)^($F422*(1+$E422)) | ... X422: =W422*(1/(1+$G422))^(1+$E422)*(1+X$7)^$D422*(X291/W291)^$E422*(X291/W291)^($F422*(1+$E422)) | Y422: =FUELUSE(X422,Y291,X291,Y$7,$D422,$E422,$F422,$G422) | Z422: =LOWER(Settings!$C$4)&".mit."&$A422&IF($C422="","","."&$C422&"."&$B422)&IF(INDEX(Variables!$D$5:$D$45,MATCH($A422,Variables!$A$5:$A$45,0))="","","."&INDEX(Variables!$D$5:$D$45,MATCH($A422,Variables!$A$5:$A$45,0)))&"."&Z$5 | AA422: =INDEX(Inputs!$S$5:$S$132,MATCH($B422&"|"&$C422,Inputs!$A$5:$A$132,0)) | AB422: =AA422*(1/(1+$G422))^(1+$E422)*(1+AB$7)^$D422*(AB291/AA291)^$E422*(AB291/AA291)^($F422*(1+$E422)) | AC422: =AB422*(1/(1+$G422))^(1+$E422)*(1+AC$7)^$D422*(AC291/AB291)^$E422*(AC291/AB291)^($F422*(1+$E422)) | AD422: =AC422*(1/(1+$G422))^(1+$E422)*(1+AD$7)^$D422*(AD291/AC291)^$E422*(AD291/AC291)^($F422*(1+$E422)) | AE422: =AD422*(1/(1+$G422))^(1+$E422)*(1+AE$7)^$D422*(AE291/AD291)^$E422*(AE291/AD291)^($F422*(1+$E422)) | AF422: =AE422*(1/(1+$G422))^(1+$E422)*(1+AF$7)^$D422*(AF291/AE291)^$E422*(AF291/AE291)^($F422*(1+$E422)) | AG422: =AF422*(1/(1+$G422))^(1+$E422)*(1+AG$7)^$D422*(AG291/AF291)^$E422*(AG291/AF291)^($F422*(1+$E422)) | AH422: =AG422*(1/(1+$G422))^(1+$E422)*(1+AH$7)^$D422*(AH291/AG291)^$E422*(AH291/AG291)^($F422*(1+$E422)) | AI422: =AH422*(1/(1+$G422))^(1+$E422)*(1+AI$7)^$D422*(AI291/AH291)^$E422*(AI291/AH291)^($F422*(1+$E422)) | ... AM422: =AL422*(1/(1+$G422))^(1+$E422)*(1+AM$7)^$D422*(AM291/AL291)^$E422*(AM291/AL291)^($F422*(1+$E422)) | AN422: =FUELUSE(AM422,AN291,AM291,AN$7,$D422,$E422,$F422,$G422)
... A538: ener | B538: bio | C538: oen | D538: =INDEX(Inputs!$K$5:$K$132,MATCH($B538&"|"&$C538,Inputs!$A$5:$A$132,0)) | E538: =INDEX(Inputs!$L$5:$L$132,MATCH($B538&"|"&$C538,Inputs!$A$5:$A$132,0)) | F538: =INDEX(Inputs!$M$5:$M$132,MATCH($B538&"|"&$C538,Inputs!$A$5:$A$132,0)) | G538: =INDEX(Inputs!$N$5:$N$132,MATCH($B538&"|"&$C538,Inputs!$A$5:$A$132,0)) | H538: =INDEX(Variables!$B$5:$B$45,MATCH($A538,Variables!$A$5:$A$45,0))&IF($C538="",""," | "&INDEX(Mapping!$B$5:$B$21,MATCH($C538,Mapping!$A$5:$A$21,0))&" | "&INDEX(Mapping!$B$24:$B$32,MATCH($B538,Mapping!$A$24:$A$32,0))) | I538: =INDEX(Variables!$C$5:$C$45,MATCH($A538,Variables!$A$5:$A$45,0)) | J538: =INDEX(Variables!$E$5:$E$45,MATCH($A538,Variables!$A$5:$A$45,0)) | K538: =LOWER(Settings!$C$4)&".mit."&$A538&IF($C538="","","."&$C538&"."&$B538)&IF(INDEX(Variables!$D$5:$D$45,MATCH($A538,Variables!$A$5:$A$45,0))="","","."&INDEX(Variables!$D$5:$D$45,MATCH($A538,Variables!$A$5:$A$45,0)))&"."&K$5 | L538: =INDEX(Inputs!$S$5:$S$132,MATCH($B538&"|"&$C538,Inputs!$A$5:$A$132,0)) | M538: =L538*(1/(1+$G538))^(1+$E538)*(1+M$7)^$D538*(M407/L407)^$E538*(M407/L407)^($F538*(1+$E538)) | N538: =M538*(1/(1+$G538))^(1+$E538)*(1+N$7)^$D538*(N407/M407)^$E538*(N407/M407)^($F538*(1+$E538)) | O538: =N538*(1/(1+$G538))^(1+$E538)*(1+O$7)^$D538*(O407/N407)^$E538*(O407/N407)^($F538*(1+$E538)) | P538: =O538*(1/(1+$G538))^(1+$E538)*(1+P$7)^$D538*(P407/O407)^$E538*(P407/O407)^($F538*(1+$E538)) | Q538: =P538*(1/(1+$G538))^(1+$E538)*(1+Q$7)^$D538*(Q407/P407)^$E538*(Q407/P407)^($F538*(1+$E538)) | R538: =Q538*(1/(1+$G538))^(1+$E538)*(1+R$7)^$D538*(R407/Q407)^$E538*(R407/Q407)^($F538*(1+$E538)) | S538: =R538*(1/(1+$G538))^(1+$E538)*(1+S$7)^$D538*(S407/R407)^$E538*(S407/R407)^($F538*(1+$E538)) | T538: =S538*(1/(1+$G538))^(1+$E538)*(1+T$7)^$D538*(T407/S407)^$E538*(T407/S407)^($F538*(1+$E538)) | ... X538: =W538*(1/(1+$G538))^(1+$E538)*(1+X$7)^$D538*(X407/W407)^$E538*(X407/W407)^($F538*(1+$E538)) | Y538: =FUELUSE(X538,Y407,X407,Y$7,$D538,$E538,$F538,$G538) | Z538: =LOWER(Settings!$C$4)&".mit."&$A538&IF($C538="","","."&$C538&"."&$B538)&IF(INDEX(Variables!$D$5:$D$45,MATCH($A538,Variables!$A$5:$A$45,0))="","","."&INDEX(Variables!$D$5:$D$45,MATCH($A538,Variables!$A$5:$A$45,0)))&"."&Z$5 | AA538: =INDEX(Inputs!$S$5:$S$132,MATCH($B538&"|"&$C538,Inputs!$A$5:$A$132,0)) | AB538: =AA538*(1/(1+$G538))^(1+$E538)*(1+AB$7)^$D538*(AB407/AA407)^$E538*(AB407/AA407)^($F538*(1+$E538)) | AC538: =AB538*(1/(1+$G538))^(1+$E538)*(1+AC$7)^$D538*(AC407/AB407)^$E538*(AC407/AB407)^($F538*(1+$E538)) | AD538: =AC538*(1/(1+$G538))^(1+$E538)*(1+AD$7)^$D538*(AD407/AC407)^$E538*(AD407/AC407)^($F538*(1+$E538)) | AE538: =AD538*(1/(1+$G538))^(1+$E538)*(1+AE$7)^$D538*(AE407/AD407)^$E538*(AE407/AD407)^($F538*(1+$E538)) | AF538: =AE538*(1/(1+$G538))^(1+$E538)*(1+AF$7)^$D538*(AF407/AE407)^$E538*(AF407/AE407)^($F538*(1+$E538)) | AG538: =AF538*(1/(1+$G538))^(1+$E538)*(1+AG$7)^$D538*(AG407/AF407)^$E538*(AG407/AF407)^($F538*(1+$E538)) | AH538: =AG538*(1/(1+$G538))^(1+$E538)*(1+AH$7)^$D538*(AH407/AG407)^$E538*(AH407/AG407)^($F538*(1+$E538)) | AI538: =AH538*(1/(1+$G538))^(1+$E538)*(1+AI$7)^$D538*(AI407/AH407)^$E538*(AI407/AH407)^($F538*(1+$E538)) | ... AM538: =AL538*(1/(1+$G538))^(1+$E538)*(1+AM$7)^$D538*(AM407/AL407)^$E538*(AM407/AL407)^($F538*(1+$E538)) | AN538: =FUELUSE(AM538,AN407,AM407,AN$7,$D538,$E538,$F538,$G538)
A540: Totals - fuel use (ktoe)
A541: ener | B541: all | C541: rod | H541: =INDEX(Variables!$B$5:$B$45,MATCH($A541,Variables!$A$5:$A$45,0))&IF($C541="",""," | "&INDEX(Mapping!$B$5:$B$21,MATCH($C541,Mapping!$A$5:$A$21,0))&" | "&INDEX(Mapping!$B$24:$B$32,MATCH($B541,Mapping!$A$24:$A$32,0))) | I541: =INDEX(Variables!$C$5:$C$45,MATCH($A541,Variables!$A$5:$A$45,0)) | J541: =INDEX(Variables!$E$5:$E$45,MATCH($A541,Variables!$A$5:$A$45,0)) | K541: =LOWER(Settings!$C$4)&".mit."&$A541&IF($C541="","","."&$C541&"."&$B541)&IF(INDEX(Variables!$D$5:$D$45,MATCH($A541,Variables!$A$5:$A$45,0))="","","."&INDEX(Variables!$D$5:$D$45,MATCH($A541,Variables!$A$5:$A$45,0)))&"."&K$5 | L541: =SUMIF($C$411:$C$538,$C541,L$411:L$538) | M541: =SUMIF($C$411:$C$538,$C541,M$411:M$538) | N541: =SUMIF($C$411:$C$538,$C541,N$411:N$538) | O541: =SUMIF($C$411:$C$538,$C541,O$411:O$538) | P541: =SUMIF($C$411:$C$538,$C541,P$411:P$538) | Q541: =SUMIF($C$411:$C$538,$C541,Q$411:Q$538) | R541: =SUMIF($C$411:$C$538,$C541,R$411:R$538) | S541: =SUMIF($C$411:$C$538,$C541,S$411:S$538) | ... Y541: =SUMIF($C$411:$C$538,$C541,Y$411:Y$538) | Z541: =LOWER(Settings!$C$4)&".mit."&$A541&IF($C541="","","."&$C541&"."&$B541)&IF(INDEX(Variables!$D$5:$D$45,MATCH($A541,Variables!$A$5:$A$45,0))="","","."&INDEX(Variables!$D$5:$D$45,MATCH($A541,Variables!$A$5:$A$45,0)))&"."&Z$5 | AA541: =SUMIF($C$411:$C$538,$C541,AA$411:AA$538) | AB541: =SUMIF($C$411:$C$538,$C541,AB$411:AB$538) | AC541: =SUMIF($C$411:$C$538,$C541,AC$411:AC$538) | AD541: =SUMIF($C$411:$C$538,$C541,AD$411:AD$538) | AE541: =SUMIF($C$411:$C$538,$C541,AE$411:AE$538) | AF541: =SUMIF($C$411:$C$538,$C541,AF$411:AF$538) | AG541: =SUMIF($C$411:$C$538,$C541,AG$411:AG$538) | AH541: =SUMIF($C$411:$C$538,$C541,AH$411:AH$538) | ... AN541: =SUMIF($C$411:$C$538,$C541,AN$411:AN$538)
A542: ener | B542: all | C542: ral | H542: =INDEX(Variables!$B$5:$B$45,MATCH($A542,Variables!$A$5:$A$45,0))&IF($C542="",""," | "&INDEX(Mapping!$B$5:$B$21,MATCH($C542,Mapping!$A$5:$A$21,0))&" | "&INDEX(Mapping!$B$24:$B$32,MATCH($B542,Mapping!$A$24:$A$32,0))) | I542: =INDEX(Variables!$C$5:$C$45,MATCH($A542,Variables!$A$5:$A$45,0)) | J542: =INDEX(Variables!$E$5:$E$45,MATCH($A542,Variables!$A$5:$A$45,0)) | K542: =LOWER(Settings!$C$4)&".mit."&$A542&IF($C542="","","."&$C542&"."&$B542)&IF(INDEX(Variables!$D$5:$D$45,MATCH($A542,Variables!$A$5:$A$45,0))="","","."&INDEX(Variables!$D$5:$D$45,MATCH($A542,Variables!$A$5:$A$45,0)))&"."&K$5 | L542: =SUMIF($C$411:$C$538,$C542,L$411:L$538) | M542: =SUMIF($C$411:$C$538,$C542,M$411:M$538) | N542: =SUMIF($C$411:$C$538,$C542,N$411:N$538) | O542: =SUMIF($C$411:$C$538,$C542,O$411:O$538) | P542: =SUMIF($C$411:$C$538,$C542,P$411:P$538) | Q542: =SUMIF($C$411:$C$538,$C542,Q$411:Q$538) | R542: =SUMIF($C$411:$C$538,$C542,R$411:R$538) | S542: =SUMIF($C$411:$C$538,$C542,S$411:S$538) | ... Y542: =SUMIF($C$411:$C$538,$C542,Y$411:Y$538) | Z542: =LOWER(Settings!$C$4)&".mit."&$A542&IF($C542="","","."&$C542&"."&$B542)&IF(INDEX(Variables!$D$5:$D$45,MATCH($A542,Variables!$A$5:$A$45,0))="","","."&INDEX(Variables!$D$5:$D$45,MATCH($A542,Variables!$A$5:$A$45,0)))&"."&Z$5 | AA542: =SUMIF($C$411:$C$538,$C542,AA$411:AA$538) | AB542: =SUMIF($C$411:$C$538,$C542,AB$411:AB$538) | AC542: =SUMIF($C$411:$C$538,$C542,AC$411:AC$538) | AD542: =SUMIF($C$411:$C$538,$C542,AD$411:AD$538) | AE542: =SUMIF($C$411:$C$538,$C542,AE$411:AE$538) | AF542: =SUMIF($C$411:$C$538,$C542,AF$411:AF$538) | AG542: =SUMIF($C$411:$C$538,$C542,AG$411:AG$538) | AH542: =SUMIF($C$411:$C$538,$C542,AH$411:AH$538) | ... AN542: =SUMIF($C$411:$C$538,$C542,AN$411:AN$538)
A543: ener | B543: all | C543: avi | H543: =INDEX(Variables!$B$5:$B$45,MATCH($A543,Variables!$A$5:$A$45,0))&IF($C543="",""," | "&INDEX(Mapping!$B$5:$B$21,MATCH($C543,Mapping!$A$5:$A$21,0))&" | "&INDEX(Mapping!$B$24:$B$32,MATCH($B543,Mapping!$A$24:$A$32,0))) | I543: =INDEX(Variables!$C$5:$C$45,MATCH($A543,Variables!$A$5:$A$45,0)) | J543: =INDEX(Variables!$E$5:$E$45,MATCH($A543,Variables!$A$5:$A$45,0)) | K543: =LOWER(Settings!$C$4)&".mit."&$A543&IF($C543="","","."&$C543&"."&$B543)&IF(INDEX(Variables!$D$5:$D$45,MATCH($A543,Variables!$A$5:$A$45,0))="","","."&INDEX(Variables!$D$5:$D$45,MATCH($A543,Variables!$A$5:$A$45,0)))&"."&K$5 | L543: =SUMIF($C$411:$C$538,$C543,L$411:L$538) | M543: =SUMIF($C$411:$C$538,$C543,M$411:M$538) | N543: =SUMIF($C$411:$C$538,$C543,N$411:N$538) | O543: =SUMIF($C$411:$C$538,$C543,O$411:O$538) | P543: =SUMIF($C$411:$C$538,$C543,P$411:P$538) | Q543: =SUMIF($C$411:$C$538,$C543,Q$411:Q$538) | R543: =SUMIF($C$411:$C$538,$C543,R$411:R$538) | S543: =SUMIF($C$411:$C$538,$C543,S$411:S$538) | ... Y543: =SUMIF($C$411:$C$538,$C543,Y$411:Y$538) | Z543: =LOWER(Settings!$C$4)&".mit."&$A543&IF($C543="","","."&$C543&"."&$B543)&IF(INDEX(Variables!$D$5:$D$45,MATCH($A543,Variables!$A$5:$A$45,0))="","","."&INDEX(Variables!$D$5:$D$45,MATCH($A543,Variables!$A$5:$A$45,0)))&"."&Z$5 | AA543: =SUMIF($C$411:$C$538,$C543,AA$411:AA$538) | AB543: =SUMIF($C$411:$C$538,$C543,AB$411:AB$538) | AC543: =SUMIF($C$411:$C$538,$C543,AC$411:AC$538) | AD543: =SUMIF($C$411:$C$538,$C543,AD$411:AD$538) | AE543: =SUMIF($C$411:$C$538,$C543,AE$411:AE$538) | AF543: =SUMIF($C$411:$C$538,$C543,AF$411:AF$538) | AG543: =SUMIF($C$411:$C$538,$C543,AG$411:AG$538) | AH543: =SUMIF($C$411:$C$538,$C543,AH$411:AH$538) | ... AN543: =SUMIF($C$411:$C$538,$C543,AN$411:AN$538)
A544: ener | B544: all | C544: nav | H544: =INDEX(Variables!$B$5:$B$45,MATCH($A544,Variables!$A$5:$A$45,0))&IF($C544="",""," | "&INDEX(Mapping!$B$5:$B$21,MATCH($C544,Mapping!$A$5:$A$21,0))&" | "&INDEX(Mapping!$B$24:$B$32,MATCH($B544,Mapping!$A$24:$A$32,0))) | I544: =INDEX(Variables!$C$5:$C$45,MATCH($A544,Variables!$A$5:$A$45,0)) | J544: =INDEX(Variables!$E$5:$E$45,MATCH($A544,Variables!$A$5:$A$45,0)) | K544: =LOWER(Settings!$C$4)&".mit."&$A544&IF($C544="","","."&$C544&"."&$B544)&IF(INDEX(Variables!$D$5:$D$45,MATCH($A544,Variables!$A$5:$A$45,0))="","","."&INDEX(Variables!$D$5:$D$45,MATCH($A544,Variables!$A$5:$A$45,0)))&"."&K$5 | L544: =SUMIF($C$411:$C$538,$C544,L$411:L$538) | M544: =SUMIF($C$411:$C$538,$C544,M$411:M$538) | N544: =SUMIF($C$411:$C$538,$C544,N$411:N$538) | O544: =SUMIF($C$411:$C$538,$C544,O$411:O$538) | P544: =SUMIF($C$411:$C$538,$C544,P$411:P$538) | Q544: =SUMIF($C$411:$C$538,$C544,Q$411:Q$538) | R544: =SUMIF($C$411:$C$538,$C544,R$411:R$538) | S544: =SUMIF($C$411:$C$538,$C544,S$411:S$538) | ... Y544: =SUMIF($C$411:$C$538,$C544,Y$411:Y$538) | Z544: =LOWER(Settings!$C$4)&".mit."&$A544&IF($C544="","","."&$C544&"."&$B544)&IF(INDEX(Variables!$D$5:$D$45,MATCH($A544,Variables!$A$5:$A$45,0))="","","."&INDEX(Variables!$D$5:$D$45,MATCH($A544,Variables!$A$5:$A$45,0)))&"."&Z$5 | AA544: =SUMIF($C$411:$C$538,$C544,AA$411:AA$538) | AB544: =SUMIF($C$411:$C$538,$C544,AB$411:AB$538) | AC544: =SUMIF($C$411:$C$538,$C544,AC$411:AC$538) | AD544: =SUMIF($C$411:$C$538,$C544,AD$411:AD$538) | AE544: =SUMIF($C$411:$C$538,$C544,AE$411:AE$538) | AF544: =SUMIF($C$411:$C$538,$C544,AF$411:AF$538) | AG544: =SUMIF($C$411:$C$538,$C544,AG$411:AG$538) | AH544: =SUMIF($C$411:$C$538,$C544,AH$411:AH$538) | ... AN544: =SUMIF($C$411:$C$538,$C544,AN$411:AN$538)
A545: ener | B545: all | C545: res | H545: =INDEX(Variables!$B$5:$B$45,MATCH($A545,Variables!$A$5:$A$45,0))&IF($C545="",""," | "&INDEX(Mapping!$B$5:$B$21,MATCH($C545,Mapping!$A$5:$A$21,0))&" | "&INDEX(Mapping!$B$24:$B$32,MATCH($B545,Mapping!$A$24:$A$32,0))) | I545: =INDEX(Variables!$C$5:$C$45,MATCH($A545,Variables!$A$5:$A$45,0)) | J545: =INDEX(Variables!$E$5:$E$45,MATCH($A545,Variables!$A$5:$A$45,0)) | K545: =LOWER(Settings!$C$4)&".mit."&$A545&IF($C545="","","."&$C545&"."&$B545)&IF(INDEX(Variables!$D$5:$D$45,MATCH($A545,Variables!$A$5:$A$45,0))="","","."&INDEX(Variables!$D$5:$D$45,MATCH($A545,Variables!$A$5:$A$45,0)))&"."&K$5 | L545: =SUMIF($C$411:$C$538,$C545,L$411:L$538) | M545: =SUMIF($C$411:$C$538,$C545,M$411:M$538) | N545: =SUMIF($C$411:$C$538,$C545,N$411:N$538) | O545: =SUMIF($C$411:$C$538,$C545,O$411:O$538) | P545: =SUMIF($C$411:$C$538,$C545,P$411:P$538) | Q545: =SUMIF($C$411:$C$538,$C545,Q$411:Q$538) | R545: =SUMIF($C$411:$C$538,$C545,R$411:R$538) | S545: =SUMIF($C$411:$C$538,$C545,S$411:S$538) | ... Y545: =SUMIF($C$411:$C$538,$C545,Y$411:Y$538) | Z545: =LOWER(Settings!$C$4)&".mit."&$A545&IF($C545="","","."&$C545&"."&$B545)&IF(INDEX(Variables!$D$5:$D$45,MATCH($A545,Variables!$A$5:$A$45,0))="","","."&INDEX(Variables!$D$5:$D$45,MATCH($A545,Variables!$A$5:$A$45,0)))&"."&Z$5 | AA545: =SUMIF($C$411:$C$538,$C545,AA$411:AA$538) | AB545: =SUMIF($C$411:$C$538,$C545,AB$411:AB$538) | AC545: =SUMIF($C$411:$C$538,$C545,AC$411:AC$538) | AD545: =SUMIF($C$411:$C$538,$C545,AD$411:AD$538) | AE545: =SUMIF($C$411:$C$538,$C545,AE$411:AE$538) | AF545: =SUMIF($C$411:$C$538,$C545,AF$411:AF$538) | AG545: =SUMIF($C$411:$C$538,$C545,AG$411:AG$538) | AH545: =SUMIF($C$411:$C$538,$C545,AH$411:AH$538) | ... AN545: =SUMIF($C$411:$C$538,$C545,AN$411:AN$538)
A546: ener | B546: all | C546: foo | H546: =INDEX(Variables!$B$5:$B$45,MATCH($A546,Variables!$A$5:$A$45,0))&IF($C546="",""," | "&INDEX(Mapping!$B$5:$B$21,MATCH($C546,Mapping!$A$5:$A$21,0))&" | "&INDEX(Mapping!$B$24:$B$32,MATCH($B546,Mapping!$A$24:$A$32,0))) | I546: =INDEX(Variables!$C$5:$C$45,MATCH($A546,Variables!$A$5:$A$45,0)) | J546: =INDEX(Variables!$E$5:$E$45,MATCH($A546,Variables!$A$5:$A$45,0)) | K546: =LOWER(Settings!$C$4)&".mit."&$A546&IF($C546="","","."&$C546&"."&$B546)&IF(INDEX(Variables!$D$5:$D$45,MATCH($A546,Variables!$A$5:$A$45,0))="","","."&INDEX(Variables!$D$5:$D$45,MATCH($A546,Variables!$A$5:$A$45,0)))&"."&K$5 | L546: =SUMIF($C$411:$C$538,$C546,L$411:L$538) | M546: =SUMIF($C$411:$C$538,$C546,M$411:M$538) | N546: =SUMIF($C$411:$C$538,$C546,N$411:N$538) | O546: =SUMIF($C$411:$C$538,$C546,O$411:O$538) | P546: =SUMIF($C$411:$C$538,$C546,P$411:P$538) | Q546: =SUMIF($C$411:$C$538,$C546,Q$411:Q$538) | R546: =SUMIF($C$411:$C$538,$C546,R$411:R$538) | S546: =SUMIF($C$411:$C$538,$C546,S$411:S$538) | ... Y546: =SUMIF($C$411:$C$538,$C546,Y$411:Y$538) | Z546: =LOWER(Settings!$C$4)&".mit."&$A546&IF($C546="","","."&$C546&"."&$B546)&IF(INDEX(Variables!$D$5:$D$45,MATCH($A546,Variables!$A$5:$A$45,0))="","","."&INDEX(Variables!$D$5:$D$45,MATCH($A546,Variables!$A$5:$A$45,0)))&"."&Z$5 | AA546: =SUMIF($C$411:$C$538,$C546,AA$411:AA$538) | AB546: =SUMIF($C$411:$C$538,$C546,AB$411:AB$538) | AC546: =SUMIF($C$411:$C$538,$C546,AC$411:AC$538) | AD546: =SUMIF($C$411:$C$538,$C546,AD$411:AD$538) | AE546: =SUMIF($C$411:$C$538,$C546,AE$411:AE$538) | AF546: =SUMIF($C$411:$C$538,$C546,AF$411:AF$538) | AG546: =SUMIF($C$411:$C$538,$C546,AG$411:AG$538) | AH546: =SUMIF($C$411:$C$538,$C546,AH$411:AH$538) | ... AN546: =SUMIF($C$411:$C$538,$C546,AN$411:AN$538)
A547: ener | B547: all | C547: srv | H547: =INDEX(Variables!$B$5:$B$45,MATCH($A547,Variables!$A$5:$A$45,0))&IF($C547="",""," | "&INDEX(Mapping!$B$5:$B$21,MATCH($C547,Mapping!$A$5:$A$21,0))&" | "&INDEX(Mapping!$B$24:$B$32,MATCH($B547,Mapping!$A$24:$A$32,0))) | I547: =INDEX(Variables!$C$5:$C$45,MATCH($A547,Variables!$A$5:$A$45,0)) | J547: =INDEX(Variables!$E$5:$E$45,MATCH($A547,Variables!$A$5:$A$45,0)) | K547: =LOWER(Settings!$C$4)&".mit."&$A547&IF($C547="","","."&$C547&"."&$B547)&IF(INDEX(Variables!$D$5:$D$45,MATCH($A547,Variables!$A$5:$A$45,0))="","","."&INDEX(Variables!$D$5:$D$45,MATCH($A547,Variables!$A$5:$A$45,0)))&"."&K$5 | L547: =SUMIF($C$411:$C$538,$C547,L$411:L$538) | M547: =SUMIF($C$411:$C$538,$C547,M$411:M$538) | N547: =SUMIF($C$411:$C$538,$C547,N$411:N$538) | O547: =SUMIF($C$411:$C$538,$C547,O$411:O$538) | P547: =SUMIF($C$411:$C$538,$C547,P$411:P$538) | Q547: =SUMIF($C$411:$C$538,$C547,Q$411:Q$538) | R547: =SUMIF($C$411:$C$538,$C547,R$411:R$538) | S547: =SUMIF($C$411:$C$538,$C547,S$411:S$538) | ... Y547: =SUMIF($C$411:$C$538,$C547,Y$411:Y$538) | Z547: =LOWER(Settings!$C$4)&".mit."&$A547&IF($C547="","","."&$C547&"."&$B547)&IF(INDEX(Variables!$D$5:$D$45,MATCH($A547,Variables!$A$5:$A$45,0))="","","."&INDEX(Variables!$D$5:$D$45,MATCH($A547,Variables!$A$5:$A$45,0)))&"."&Z$5 | AA547: =SUMIF($C$411:$C$538,$C547,AA$411:AA$538) | AB547: =SUMIF($C$411:$C$538,$C547,AB$411:AB$538) | AC547: =SUMIF($C$411:$C$538,$C547,AC$411:AC$538) | AD547: =SUMIF($C$411:$C$538,$C547,AD$411:AD$538) | AE547: =SUMIF($C$411:$C$538,$C547,AE$411:AE$538) | AF547: =SUMIF($C$411:$C$538,$C547,AF$411:AF$538) | AG547: =SUMIF($C$411:$C$538,$C547,AG$411:AG$538) | AH547: =SUMIF($C$411:$C$538,$C547,AH$411:AH$538) | ... AN547: =SUMIF($C$411:$C$538,$C547,AN$411:AN$538)
A548: ener | B548: all | C548: mch | H548: =INDEX(Variables!$B$5:$B$45,MATCH($A548,Variables!$A$5:$A$45,0))&IF($C548="",""," | "&INDEX(Mapping!$B$5:$B$21,MATCH($C548,Mapping!$A$5:$A$21,0))&" | "&INDEX(Mapping!$B$24:$B$32,MATCH($B548,Mapping!$A$24:$A$32,0))) | I548: =INDEX(Variables!$C$5:$C$45,MATCH($A548,Variables!$A$5:$A$45,0)) | J548: =INDEX(Variables!$E$5:$E$45,MATCH($A548,Variables!$A$5:$A$45,0)) | K548: =LOWER(Settings!$C$4)&".mit."&$A548&IF($C548="","","."&$C548&"."&$B548)&IF(INDEX(Variables!$D$5:$D$45,MATCH($A548,Variables!$A$5:$A$45,0))="","","."&INDEX(Variables!$D$5:$D$45,MATCH($A548,Variables!$A$5:$A$45,0)))&"."&K$5 | L548: =SUMIF($C$411:$C$538,$C548,L$411:L$538) | M548: =SUMIF($C$411:$C$538,$C548,M$411:M$538) | N548: =SUMIF($C$411:$C$538,$C548,N$411:N$538) | O548: =SUMIF($C$411:$C$538,$C548,O$411:O$538) | P548: =SUMIF($C$411:$C$538,$C548,P$411:P$538) | Q548: =SUMIF($C$411:$C$538,$C548,Q$411:Q$538) | R548: =SUMIF($C$411:$C$538,$C548,R$411:R$538) | S548: =SUMIF($C$411:$C$538,$C548,S$411:S$538) | ... Y548: =SUMIF($C$411:$C$538,$C548,Y$411:Y$538) | Z548: =LOWER(Settings!$C$4)&".mit."&$A548&IF($C548="","","."&$C548&"."&$B548)&IF(INDEX(Variables!$D$5:$D$45,MATCH($A548,Variables!$A$5:$A$45,0))="","","."&INDEX(Variables!$D$5:$D$45,MATCH($A548,Variables!$A$5:$A$45,0)))&"."&Z$5 | AA548: =SUMIF($C$411:$C$538,$C548,AA$411:AA$538) | AB548: =SUMIF($C$411:$C$538,$C548,AB$411:AB$538) | AC548: =SUMIF($C$411:$C$538,$C548,AC$411:AC$538) | AD548: =SUMIF($C$411:$C$538,$C548,AD$411:AD$538) | AE548: =SUMIF($C$411:$C$538,$C548,AE$411:AE$538) | AF548: =SUMIF($C$411:$C$538,$C548,AF$411:AF$538) | AG548: =SUMIF($C$411:$C$538,$C548,AG$411:AG$538) | AH548: =SUMIF($C$411:$C$538,$C548,AH$411:AH$538) | ... AN548: =SUMIF($C$411:$C$538,$C548,AN$411:AN$538)
A549: ener | B549: all | C549: irn | H549: =INDEX(Variables!$B$5:$B$45,MATCH($A549,Variables!$A$5:$A$45,0))&IF($C549="",""," | "&INDEX(Mapping!$B$5:$B$21,MATCH($C549,Mapping!$A$5:$A$21,0))&" | "&INDEX(Mapping!$B$24:$B$32,MATCH($B549,Mapping!$A$24:$A$32,0))) | I549: =INDEX(Variables!$C$5:$C$45,MATCH($A549,Variables!$A$5:$A$45,0)) | J549: =INDEX(Variables!$E$5:$E$45,MATCH($A549,Variables!$A$5:$A$45,0)) | K549: =LOWER(Settings!$C$4)&".mit."&$A549&IF($C549="","","."&$C549&"."&$B549)&IF(INDEX(Variables!$D$5:$D$45,MATCH($A549,Variables!$A$5:$A$45,0))="","","."&INDEX(Variables!$D$5:$D$45,MATCH($A549,Variables!$A$5:$A$45,0)))&"."&K$5 | L549: =SUMIF($C$411:$C$538,$C549,L$411:L$538) | M549: =SUMIF($C$411:$C$538,$C549,M$411:M$538) | N549: =SUMIF($C$411:$C$538,$C549,N$411:N$538) | O549: =SUMIF($C$411:$C$538,$C549,O$411:O$538) | P549: =SUMIF($C$411:$C$538,$C549,P$411:P$538) | Q549: =SUMIF($C$411:$C$538,$C549,Q$411:Q$538) | R549: =SUMIF($C$411:$C$538,$C549,R$411:R$538) | S549: =SUMIF($C$411:$C$538,$C549,S$411:S$538) | ... Y549: =SUMIF($C$411:$C$538,$C549,Y$411:Y$538) | Z549: =LOWER(Settings!$C$4)&".mit."&$A549&IF($C549="","","."&$C549&"."&$B549)&IF(INDEX(Variables!$D$5:$D$45,MATCH($A549,Variables!$A$5:$A$45,0))="","","."&INDEX(Variables!$D$5:$D$45,MATCH($A549,Variables!$A$5:$A$45,0)))&"."&Z$5 | AA549: =SUMIF($C$411:$C$538,$C549,AA$411:AA$538) | AB549: =SUMIF($C$411:$C$538,$C549,AB$411:AB$538) | AC549: =SUMIF($C$411:$C$538,$C549,AC$411:AC$538) | AD549: =SUMIF($C$411:$C$538,$C549,AD$411:AD$538) | AE549: =SUMIF($C$411:$C$538,$C549,AE$411:AE$538) | AF549: =SUMIF($C$411:$C$538,$C549,AF$411:AF$538) | AG549: =SUMIF($C$411:$C$538,$C549,AG$411:AG$538) | AH549: =SUMIF($C$411:$C$538,$C549,AH$411:AH$538) | ... AN549: =SUMIF($C$411:$C$538,$C549,AN$411:AN$538)
A550: ener | B550: all | C550: nfm | H550: =INDEX(Variables!$B$5:$B$45,MATCH($A550,Variables!$A$5:$A$45,0))&IF($C550="",""," | "&INDEX(Mapping!$B$5:$B$21,MATCH($C550,Mapping!$A$5:$A$21,0))&" | "&INDEX(Mapping!$B$24:$B$32,MATCH($B550,Mapping!$A$24:$A$32,0))) | I550: =INDEX(Variables!$C$5:$C$45,MATCH($A550,Variables!$A$5:$A$45,0)) | J550: =INDEX(Variables!$E$5:$E$45,MATCH($A550,Variables!$A$5:$A$45,0)) | K550: =LOWER(Settings!$C$4)&".mit."&$A550&IF($C550="","","."&$C550&"."&$B550)&IF(INDEX(Variables!$D$5:$D$45,MATCH($A550,Variables!$A$5:$A$45,0))="","","."&INDEX(Variables!$D$5:$D$45,MATCH($A550,Variables!$A$5:$A$45,0)))&"."&K$5 | L550: =SUMIF($C$411:$C$538,$C550,L$411:L$538) | M550: =SUMIF($C$411:$C$538,$C550,M$411:M$538) | N550: =SUMIF($C$411:$C$538,$C550,N$411:N$538) | O550: =SUMIF($C$411:$C$538,$C550,O$411:O$538) | P550: =SUMIF($C$411:$C$538,$C550,P$411:P$538) | Q550: =SUMIF($C$411:$C$538,$C550,Q$411:Q$538) | R550: =SUMIF($C$411:$C$538,$C550,R$411:R$538) | S550: =SUMIF($C$411:$C$538,$C550,S$411:S$538) | ... Y550: =SUMIF($C$411:$C$538,$C550,Y$411:Y$538) | Z550: =LOWER(Settings!$C$4)&".mit."&$A550&IF($C550="","","."&$C550&"."&$B550)&IF(INDEX(Variables!$D$5:$D$45,MATCH($A550,Variables!$A$5:$A$45,0))="","","."&INDEX(Variables!$D$5:$D$45,MATCH($A550,Variables!$A$5:$A$45,0)))&"."&Z$5 | AA550: =SUMIF($C$411:$C$538,$C550,AA$411:AA$538) | AB550: =SUMIF($C$411:$C$538,$C550,AB$411:AB$538) | AC550: =SUMIF($C$411:$C$538,$C550,AC$411:AC$538) | AD550: =SUMIF($C$411:$C$538,$C550,AD$411:AD$538) | AE550: =SUMIF($C$411:$C$538,$C550,AE$411:AE$538) | AF550: =SUMIF($C$411:$C$538,$C550,AF$411:AF$538) | AG550: =SUMIF($C$411:$C$538,$C550,AG$411:AG$538) | AH550: =SUMIF($C$411:$C$538,$C550,AH$411:AH$538) | ... AN550: =SUMIF($C$411:$C$538,$C550,AN$411:AN$538)
A551: ener | B551: all | C551: mac | H551: =INDEX(Variables!$B$5:$B$45,MATCH($A551,Variables!$A$5:$A$45,0))&IF($C551="",""," | "&INDEX(Mapping!$B$5:$B$21,MATCH($C551,Mapping!$A$5:$A$21,0))&" | "&INDEX(Mapping!$B$24:$B$32,MATCH($B551,Mapping!$A$24:$A$32,0))) | I551: =INDEX(Variables!$C$5:$C$45,MATCH($A551,Variables!$A$5:$A$45,0)) | J551: =INDEX(Variables!$E$5:$E$45,MATCH($A551,Variables!$A$5:$A$45,0)) | K551: =LOWER(Settings!$C$4)&".mit."&$A551&IF($C551="","","."&$C551&"."&$B551)&IF(INDEX(Variables!$D$5:$D$45,MATCH($A551,Variables!$A$5:$A$45,0))="","","."&INDEX(Variables!$D$5:$D$45,MATCH($A551,Variables!$A$5:$A$45,0)))&"."&K$5 | L551: =SUMIF($C$411:$C$538,$C551,L$411:L$538) | M551: =SUMIF($C$411:$C$538,$C551,M$411:M$538) | N551: =SUMIF($C$411:$C$538,$C551,N$411:N$538) | O551: =SUMIF($C$411:$C$538,$C551,O$411:O$538) | P551: =SUMIF($C$411:$C$538,$C551,P$411:P$538) | Q551: =SUMIF($C$411:$C$538,$C551,Q$411:Q$538) | R551: =SUMIF($C$411:$C$538,$C551,R$411:R$538) | S551: =SUMIF($C$411:$C$538,$C551,S$411:S$538) | ... Y551: =SUMIF($C$411:$C$538,$C551,Y$411:Y$538) | Z551: =LOWER(Settings!$C$4)&".mit."&$A551&IF($C551="","","."&$C551&"."&$B551)&IF(INDEX(Variables!$D$5:$D$45,MATCH($A551,Variables!$A$5:$A$45,0))="","","."&INDEX(Variables!$D$5:$D$45,MATCH($A551,Variables!$A$5:$A$45,0)))&"."&Z$5 | AA551: =SUMIF($C$411:$C$538,$C551,AA$411:AA$538) | AB551: =SUMIF($C$411:$C$538,$C551,AB$411:AB$538) | AC551: =SUMIF($C$411:$C$538,$C551,AC$411:AC$538) | AD551: =SUMIF($C$411:$C$538,$C551,AD$411:AD$538) | AE551: =SUMIF($C$411:$C$538,$C551,AE$411:AE$538) | AF551: =SUMIF($C$411:$C$538,$C551,AF$411:AF$538) | AG551: =SUMIF($C$411:$C$538,$C551,AG$411:AG$538) | AH551: =SUMIF($C$411:$C$538,$C551,AH$411:AH$538) | ... AN551: =SUMIF($C$411:$C$538,$C551,AN$411:AN$538)
A552: ener | B552: all | C552: cem | H552: =INDEX(Variables!$B$5:$B$45,MATCH($A552,Variables!$A$5:$A$45,0))&IF($C552="",""," | "&INDEX(Mapping!$B$5:$B$21,MATCH($C552,Mapping!$A$5:$A$21,0))&" | "&INDEX(Mapping!$B$24:$B$32,MATCH($B552,Mapping!$A$24:$A$32,0))) | I552: =INDEX(Variables!$C$5:$C$45,MATCH($A552,Variables!$A$5:$A$45,0)) | J552: =INDEX(Variables!$E$5:$E$45,MATCH($A552,Variables!$A$5:$A$45,0)) | K552: =LOWER(Settings!$C$4)&".mit."&$A552&IF($C552="","","."&$C552&"."&$B552)&IF(INDEX(Variables!$D$5:$D$45,MATCH($A552,Variables!$A$5:$A$45,0))="","","."&INDEX(Variables!$D$5:$D$45,MATCH($A552,Variables!$A$5:$A$45,0)))&"."&K$5 | L552: =SUMIF($C$411:$C$538,$C552,L$411:L$538) | M552: =SUMIF($C$411:$C$538,$C552,M$411:M$538) | N552: =SUMIF($C$411:$C$538,$C552,N$411:N$538) | O552: =SUMIF($C$411:$C$538,$C552,O$411:O$538) | P552: =SUMIF($C$411:$C$538,$C552,P$411:P$538) | Q552: =SUMIF($C$411:$C$538,$C552,Q$411:Q$538) | R552: =SUMIF($C$411:$C$538,$C552,R$411:R$538) | S552: =SUMIF($C$411:$C$538,$C552,S$411:S$538) | ... Y552: =SUMIF($C$411:$C$538,$C552,Y$411:Y$538) | Z552: =LOWER(Settings!$C$4)&".mit."&$A552&IF($C552="","","."&$C552&"."&$B552)&IF(INDEX(Variables!$D$5:$D$45,MATCH($A552,Variables!$A$5:$A$45,0))="","","."&INDEX(Variables!$D$5:$D$45,MATCH($A552,Variables!$A$5:$A$45,0)))&"."&Z$5 | AA552: =SUMIF($C$411:$C$538,$C552,AA$411:AA$538) | AB552: =SUMIF($C$411:$C$538,$C552,AB$411:AB$538) | AC552: =SUMIF($C$411:$C$538,$C552,AC$411:AC$538) | AD552: =SUMIF($C$411:$C$538,$C552,AD$411:AD$538) | AE552: =SUMIF($C$411:$C$538,$C552,AE$411:AE$538) | AF552: =SUMIF($C$411:$C$538,$C552,AF$411:AF$538) | AG552: =SUMIF($C$411:$C$538,$C552,AG$411:AG$538) | AH552: =SUMIF($C$411:$C$538,$C552,AH$411:AH$538) | ... AN552: =SUMIF($C$411:$C$538,$C552,AN$411:AN$538)
... A556: ener | B556: all | C556: oen | H556: =INDEX(Variables!$B$5:$B$45,MATCH($A556,Variables!$A$5:$A$45,0))&IF($C556="",""," | "&INDEX(Mapping!$B$5:$B$21,MATCH($C556,Mapping!$A$5:$A$21,0))&" | "&INDEX(Mapping!$B$24:$B$32,MATCH($B556,Mapping!$A$24:$A$32,0))) | I556: =INDEX(Variables!$C$5:$C$45,MATCH($A556,Variables!$A$5:$A$45,0)) | J556: =INDEX(Variables!$E$5:$E$45,MATCH($A556,Variables!$A$5:$A$45,0)) | K556: =LOWER(Settings!$C$4)&".mit."&$A556&IF($C556="","","."&$C556&"."&$B556)&IF(INDEX(Variables!$D$5:$D$45,MATCH($A556,Variables!$A$5:$A$45,0))="","","."&INDEX(Variables!$D$5:$D$45,MATCH($A556,Variables!$A$5:$A$45,0)))&"."&K$5 | L556: =SUMIF($C$411:$C$538,$C556,L$411:L$538) | M556: =SUMIF($C$411:$C$538,$C556,M$411:M$538) | N556: =SUMIF($C$411:$C$538,$C556,N$411:N$538) | O556: =SUMIF($C$411:$C$538,$C556,O$411:O$538) | P556: =SUMIF($C$411:$C$538,$C556,P$411:P$538) | Q556: =SUMIF($C$411:$C$538,$C556,Q$411:Q$538) | R556: =SUMIF($C$411:$C$538,$C556,R$411:R$538) | S556: =SUMIF($C$411:$C$538,$C556,S$411:S$538) | ... Y556: =SUMIF($C$411:$C$538,$C556,Y$411:Y$538) | Z556: =LOWER(Settings!$C$4)&".mit."&$A556&IF($C556="","","."&$C556&"."&$B556)&IF(INDEX(Variables!$D$5:$D$45,MATCH($A556,Variables!$A$5:$A$45,0))="","","."&INDEX(Variables!$D$5:$D$45,MATCH($A556,Variables!$A$5:$A$45,0)))&"."&Z$5 | AA556: =SUMIF($C$411:$C$538,$C556,AA$411:AA$538) | AB556: =SUMIF($C$411:$C$538,$C556,AB$411:AB$538) | AC556: =SUMIF($C$411:$C$538,$C556,AC$411:AC$538) | AD556: =SUMIF($C$411:$C$538,$C556,AD$411:AD$538) | AE556: =SUMIF($C$411:$C$538,$C556,AE$411:AE$538) | AF556: =SUMIF($C$411:$C$538,$C556,AF$411:AF$538) | AG556: =SUMIF($C$411:$C$538,$C556,AG$411:AG$538) | AH556: =SUMIF($C$411:$C$538,$C556,AH$411:AH$538) | ... AN556: =SUMIF($C$411:$C$538,$C556,AN$411:AN$538)
A558: ener | B558: coa | C558: all | H558: =INDEX(Variables!$B$5:$B$45,MATCH($A558,Variables!$A$5:$A$45,0))&IF($C558="",""," | "&INDEX(Mapping!$B$5:$B$21,MATCH($C558,Mapping!$A$5:$A$21,0))&" | "&INDEX(Mapping!$B$24:$B$32,MATCH($B558,Mapping!$A$24:$A$32,0))) | I558: =INDEX(Variables!$C$5:$C$45,MATCH($A558,Variables!$A$5:$A$45,0)) | J558: =INDEX(Variables!$E$5:$E$45,MATCH($A558,Variables!$A$5:$A$45,0)) | K558: =LOWER(Settings!$C$4)&".mit."&$A558&IF($C558="","","."&$C558&"."&$B558)&IF(INDEX(Variables!$D$5:$D$45,MATCH($A558,Variables!$A$5:$A$45,0))="","","."&INDEX(Variables!$D$5:$D$45,MATCH($A558,Variables!$A$5:$A$45,0)))&"."&K$5 | L558: =SUMIF($B$411:$B$538,$B558,L$411:L$538) | M558: =SUMIF($B$411:$B$538,$B558,M$411:M$538) | N558: =SUMIF($B$411:$B$538,$B558,N$411:N$538) | O558: =SUMIF($B$411:$B$538,$B558,O$411:O$538) | P558: =SUMIF($B$411:$B$538,$B558,P$411:P$538) | Q558: =SUMIF($B$411:$B$538,$B558,Q$411:Q$538) | R558: =SUMIF($B$411:$B$538,$B558,R$411:R$538) | S558: =SUMIF($B$411:$B$538,$B558,S$411:S$538) | ... Y558: =SUMIF($B$411:$B$538,$B558,Y$411:Y$538) | Z558: =LOWER(Settings!$C$4)&".mit."&$A558&IF($C558="","","."&$C558&"."&$B558)&IF(INDEX(Variables!$D$5:$D$45,MATCH($A558,Variables!$A$5:$A$45,0))="","","."&INDEX(Variables!$D$5:$D$45,MATCH($A558,Variables!$A$5:$A$45,0)))&"."&Z$5 | AA558: =SUMIF($B$411:$B$538,$B558,AA$411:AA$538) | AB558: =SUMIF($B$411:$B$538,$B558,AB$411:AB$538) | AC558: =SUMIF($B$411:$B$538,$B558,AC$411:AC$538) | AD558: =SUMIF($B$411:$B$538,$B558,AD$411:AD$538) | AE558: =SUMIF($B$411:$B$538,$B558,AE$411:AE$538) | AF558: =SUMIF($B$411:$B$538,$B558,AF$411:AF$538) | AG558: =SUMIF($B$411:$B$538,$B558,AG$411:AG$538) | AH558: =SUMIF($B$411:$B$538,$B558,AH$411:AH$538) | ... AN558: =SUMIF($B$411:$B$538,$B558,AN$411:AN$538)
A559: ener | B559: nga | C559: all | H559: =INDEX(Variables!$B$5:$B$45,MATCH($A559,Variables!$A$5:$A$45,0))&IF($C559="",""," | "&INDEX(Mapping!$B$5:$B$21,MATCH($C559,Mapping!$A$5:$A$21,0))&" | "&INDEX(Mapping!$B$24:$B$32,MATCH($B559,Mapping!$A$24:$A$32,0))) | I559: =INDEX(Variables!$C$5:$C$45,MATCH($A559,Variables!$A$5:$A$45,0)) | J559: =INDEX(Variables!$E$5:$E$45,MATCH($A559,Variables!$A$5:$A$45,0)) | K559: =LOWER(Settings!$C$4)&".mit."&$A559&IF($C559="","","."&$C559&"."&$B559)&IF(INDEX(Variables!$D$5:$D$45,MATCH($A559,Variables!$A$5:$A$45,0))="","","."&INDEX(Variables!$D$5:$D$45,MATCH($A559,Variables!$A$5:$A$45,0)))&"."&K$5 | L559: =SUMIF($B$411:$B$538,$B559,L$411:L$538) | M559: =SUMIF($B$411:$B$538,$B559,M$411:M$538) | N559: =SUMIF($B$411:$B$538,$B559,N$411:N$538) | O559: =SUMIF($B$411:$B$538,$B559,O$411:O$538) | P559: =SUMIF($B$411:$B$538,$B559,P$411:P$538) | Q559: =SUMIF($B$411:$B$538,$B559,Q$411:Q$538) | R559: =SUMIF($B$411:$B$538,$B559,R$411:R$538) | S559: =SUMIF($B$411:$B$538,$B559,S$411:S$538) | ... Y559: =SUMIF($B$411:$B$538,$B559,Y$411:Y$538) | Z559: =LOWER(Settings!$C$4)&".mit."&$A559&IF($C559="","","."&$C559&"."&$B559)&IF(INDEX(Variables!$D$5:$D$45,MATCH($A559,Variables!$A$5:$A$45,0))="","","."&INDEX(Variables!$D$5:$D$45,MATCH($A559,Variables!$A$5:$A$45,0)))&"."&Z$5 | AA559: =SUMIF($B$411:$B$538,$B559,AA$411:AA$538) | AB559: =SUMIF($B$411:$B$538,$B559,AB$411:AB$538) | AC559: =SUMIF($B$411:$B$538,$B559,AC$411:AC$538) | AD559: =SUMIF($B$411:$B$538,$B559,AD$411:AD$538) | AE559: =SUMIF($B$411:$B$538,$B559,AE$411:AE$538) | AF559: =SUMIF($B$411:$B$538,$B559,AF$411:AF$538) | AG559: =SUMIF($B$411:$B$538,$B559,AG$411:AG$538) | AH559: =SUMIF($B$411:$B$538,$B559,AH$411:AH$538) | ... AN559: =SUMIF($B$411:$B$538,$B559,AN$411:AN$538)
A560: ener | B560: gso | C560: all | H560: =INDEX(Variables!$B$5:$B$45,MATCH($A560,Variables!$A$5:$A$45,0))&IF($C560="",""," | "&INDEX(Mapping!$B$5:$B$21,MATCH($C560,Mapping!$A$5:$A$21,0))&" | "&INDEX(Mapping!$B$24:$B$32,MATCH($B560,Mapping!$A$24:$A$32,0))) | I560: =INDEX(Variables!$C$5:$C$45,MATCH($A560,Variables!$A$5:$A$45,0)) | J560: =INDEX(Variables!$E$5:$E$45,MATCH($A560,Variables!$A$5:$A$45,0)) | K560: =LOWER(Settings!$C$4)&".mit."&$A560&IF($C560="","","."&$C560&"."&$B560)&IF(INDEX(Variables!$D$5:$D$45,MATCH($A560,Variables!$A$5:$A$45,0))="","","."&INDEX(Variables!$D$5:$D$45,MATCH($A560,Variables!$A$5:$A$45,0)))&"."&K$5 | L560: =SUMIF($B$411:$B$538,$B560,L$411:L$538) | M560: =SUMIF($B$411:$B$538,$B560,M$411:M$538) | N560: =SUMIF($B$411:$B$538,$B560,N$411:N$538) | O560: =SUMIF($B$411:$B$538,$B560,O$411:O$538) | P560: =SUMIF($B$411:$B$538,$B560,P$411:P$538) | Q560: =SUMIF($B$411:$B$538,$B560,Q$411:Q$538) | R560: =SUMIF($B$411:$B$538,$B560,R$411:R$538) | S560: =SUMIF($B$411:$B$538,$B560,S$411:S$538) | ... Y560: =SUMIF($B$411:$B$538,$B560,Y$411:Y$538) | Z560: =LOWER(Settings!$C$4)&".mit."&$A560&IF($C560="","","."&$C560&"."&$B560)&IF(INDEX(Variables!$D$5:$D$45,MATCH($A560,Variables!$A$5:$A$45,0))="","","."&INDEX(Variables!$D$5:$D$45,MATCH($A560,Variables!$A$5:$A$45,0)))&"."&Z$5 | AA560: =SUMIF($B$411:$B$538,$B560,AA$411:AA$538) | AB560: =SUMIF($B$411:$B$538,$B560,AB$411:AB$538) | AC560: =SUMIF($B$411:$B$538,$B560,AC$411:AC$538) | AD560: =SUMIF($B$411:$B$538,$B560,AD$411:AD$538) | AE560: =SUMIF($B$411:$B$538,$B560,AE$411:AE$538) | AF560: =SUMIF($B$411:$B$538,$B560,AF$411:AF$538) | AG560: =SUMIF($B$411:$B$538,$B560,AG$411:AG$538) | AH560: =SUMIF($B$411:$B$538,$B560,AH$411:AH$538) | ... AN560: =SUMIF($B$411:$B$538,$B560,AN$411:AN$538)
A561: ener | B561: die | C561: all | H561: =INDEX(Variables!$B$5:$B$45,MATCH($A561,Variables!$A$5:$A$45,0))&IF($C561="",""," | "&INDEX(Mapping!$B$5:$B$21,MATCH($C561,Mapping!$A$5:$A$21,0))&" | "&INDEX(Mapping!$B$24:$B$32,MATCH($B561,Mapping!$A$24:$A$32,0))) | I561: =INDEX(Variables!$C$5:$C$45,MATCH($A561,Variables!$A$5:$A$45,0)) | J561: =INDEX(Variables!$E$5:$E$45,MATCH($A561,Variables!$A$5:$A$45,0)) | K561: =LOWER(Settings!$C$4)&".mit."&$A561&IF($C561="","","."&$C561&"."&$B561)&IF(INDEX(Variables!$D$5:$D$45,MATCH($A561,Variables!$A$5:$A$45,0))="","","."&INDEX(Variables!$D$5:$D$45,MATCH($A561,Variables!$A$5:$A$45,0)))&"."&K$5 | L561: =SUMIF($B$411:$B$538,$B561,L$411:L$538) | M561: =SUMIF($B$411:$B$538,$B561,M$411:M$538) | N561: =SUMIF($B$411:$B$538,$B561,N$411:N$538) | O561: =SUMIF($B$411:$B$538,$B561,O$411:O$538) | P561: =SUMIF($B$411:$B$538,$B561,P$411:P$538) | Q561: =SUMIF($B$411:$B$538,$B561,Q$411:Q$538) | R561: =SUMIF($B$411:$B$538,$B561,R$411:R$538) | S561: =SUMIF($B$411:$B$538,$B561,S$411:S$538) | ... Y561: =SUMIF($B$411:$B$538,$B561,Y$411:Y$538) | Z561: =LOWER(Settings!$C$4)&".mit."&$A561&IF($C561="","","."&$C561&"."&$B561)&IF(INDEX(Variables!$D$5:$D$45,MATCH($A561,Variables!$A$5:$A$45,0))="","","."&INDEX(Variables!$D$5:$D$45,MATCH($A561,Variables!$A$5:$A$45,0)))&"."&Z$5 | AA561: =SUMIF($B$411:$B$538,$B561,AA$411:AA$538) | AB561: =SUMIF($B$411:$B$538,$B561,AB$411:AB$538) | AC561: =SUMIF($B$411:$B$538,$B561,AC$411:AC$538) | AD561: =SUMIF($B$411:$B$538,$B561,AD$411:AD$538) | AE561: =SUMIF($B$411:$B$538,$B561,AE$411:AE$538) | AF561: =SUMIF($B$411:$B$538,$B561,AF$411:AF$538) | AG561: =SUMIF($B$411:$B$538,$B561,AG$411:AG$538) | AH561: =SUMIF($B$411:$B$538,$B561,AH$411:AH$538) | ... AN561: =SUMIF($B$411:$B$538,$B561,AN$411:AN$538)
A562: ener | B562: lpg | C562: all | H562: =INDEX(Variables!$B$5:$B$45,MATCH($A562,Variables!$A$5:$A$45,0))&IF($C562="",""," | "&INDEX(Mapping!$B$5:$B$21,MATCH($C562,Mapping!$A$5:$A$21,0))&" | "&INDEX(Mapping!$B$24:$B$32,MATCH($B562,Mapping!$A$24:$A$32,0))) | I562: =INDEX(Variables!$C$5:$C$45,MATCH($A562,Variables!$A$5:$A$45,0)) | J562: =INDEX(Variables!$E$5:$E$45,MATCH($A562,Variables!$A$5:$A$45,0)) | K562: =LOWER(Settings!$C$4)&".mit."&$A562&IF($C562="","","."&$C562&"."&$B562)&IF(INDEX(Variables!$D$5:$D$45,MATCH($A562,Variables!$A$5:$A$45,0))="","","."&INDEX(Variables!$D$5:$D$45,MATCH($A562,Variables!$A$5:$A$45,0)))&"."&K$5 | L562: =SUMIF($B$411:$B$538,$B562,L$411:L$538) | M562: =SUMIF($B$411:$B$538,$B562,M$411:M$538) | N562: =SUMIF($B$411:$B$538,$B562,N$411:N$538) | O562: =SUMIF($B$411:$B$538,$B562,O$411:O$538) | P562: =SUMIF($B$411:$B$538,$B562,P$411:P$538) | Q562: =SUMIF($B$411:$B$538,$B562,Q$411:Q$538) | R562: =SUMIF($B$411:$B$538,$B562,R$411:R$538) | S562: =SUMIF($B$411:$B$538,$B562,S$411:S$538) | ... Y562: =SUMIF($B$411:$B$538,$B562,Y$411:Y$538) | Z562: =LOWER(Settings!$C$4)&".mit."&$A562&IF($C562="","","."&$C562&"."&$B562)&IF(INDEX(Variables!$D$5:$D$45,MATCH($A562,Variables!$A$5:$A$45,0))="","","."&INDEX(Variables!$D$5:$D$45,MATCH($A562,Variables!$A$5:$A$45,0)))&"."&Z$5 | AA562: =SUMIF($B$411:$B$538,$B562,AA$411:AA$538) | AB562: =SUMIF($B$411:$B$538,$B562,AB$411:AB$538) | AC562: =SUMIF($B$411:$B$538,$B562,AC$411:AC$538) | AD562: =SUMIF($B$411:$B$538,$B562,AD$411:AD$538) | AE562: =SUMIF($B$411:$B$538,$B562,AE$411:AE$538) | AF562: =SUMIF($B$411:$B$538,$B562,AF$411:AF$538) | AG562: =SUMIF($B$411:$B$538,$B562,AG$411:AG$538) | AH562: =SUMIF($B$411:$B$538,$B562,AH$411:AH$538) | ... AN562: =SUMIF($B$411:$B$538,$B562,AN$411:AN$538)
A563: ener | B563: ker | C563: all | H563: =INDEX(Variables!$B$5:$B$45,MATCH($A563,Variables!$A$5:$A$45,0))&IF($C563="",""," | "&INDEX(Mapping!$B$5:$B$21,MATCH($C563,Mapping!$A$5:$A$21,0))&" | "&INDEX(Mapping!$B$24:$B$32,MATCH($B563,Mapping!$A$24:$A$32,0))) | I563: =INDEX(Variables!$C$5:$C$45,MATCH($A563,Variables!$A$5:$A$45,0)) | J563: =INDEX(Variables!$E$5:$E$45,MATCH($A563,Variables!$A$5:$A$45,0)) | K563: =LOWER(Settings!$C$4)&".mit."&$A563&IF($C563="","","."&$C563&"."&$B563)&IF(INDEX(Variables!$D$5:$D$45,MATCH($A563,Variables!$A$5:$A$45,0))="","","."&INDEX(Variables!$D$5:$D$45,MATCH($A563,Variables!$A$5:$A$45,0)))&"."&K$5 | L563: =SUMIF($B$411:$B$538,$B563,L$411:L$538) | M563: =SUMIF($B$411:$B$538,$B563,M$411:M$538) | N563: =SUMIF($B$411:$B$538,$B563,N$411:N$538) | O563: =SUMIF($B$411:$B$538,$B563,O$411:O$538) | P563: =SUMIF($B$411:$B$538,$B563,P$411:P$538) | Q563: =SUMIF($B$411:$B$538,$B563,Q$411:Q$538) | R563: =SUMIF($B$411:$B$538,$B563,R$411:R$538) | S563: =SUMIF($B$411:$B$538,$B563,S$411:S$538) | ... Y563: =SUMIF($B$411:$B$538,$B563,Y$411:Y$538) | Z563: =LOWER(Settings!$C$4)&".mit."&$A563&IF($C563="","","."&$C563&"."&$B563)&IF(INDEX(Variables!$D$5:$D$45,MATCH($A563,Variables!$A$5:$A$45,0))="","","."&INDEX(Variables!$D$5:$D$45,MATCH($A563,Variables!$A$5:$A$45,0)))&"."&Z$5 | AA563: =SUMIF($B$411:$B$538,$B563,AA$411:AA$538) | AB563: =SUMIF($B$411:$B$538,$B563,AB$411:AB$538) | AC563: =SUMIF($B$411:$B$538,$B563,AC$411:AC$538) | AD563: =SUMIF($B$411:$B$538,$B563,AD$411:AD$538) | AE563: =SUMIF($B$411:$B$538,$B563,AE$411:AE$538) | AF563: =SUMIF($B$411:$B$538,$B563,AF$411:AF$538) | AG563: =SUMIF($B$411:$B$538,$B563,AG$411:AG$538) | AH563: =SUMIF($B$411:$B$538,$B563,AH$411:AH$538) | ... AN563: =SUMIF($B$411:$B$538,$B563,AN$411:AN$538)
A564: ener | B564: oop | C564: all | H564: =INDEX(Variables!$B$5:$B$45,MATCH($A564,Variables!$A$5:$A$45,0))&IF($C564="",""," | "&INDEX(Mapping!$B$5:$B$21,MATCH($C564,Mapping!$A$5:$A$21,0))&" | "&INDEX(Mapping!$B$24:$B$32,MATCH($B564,Mapping!$A$24:$A$32,0))) | I564: =INDEX(Variables!$C$5:$C$45,MATCH($A564,Variables!$A$5:$A$45,0)) | J564: =INDEX(Variables!$E$5:$E$45,MATCH($A564,Variables!$A$5:$A$45,0)) | K564: =LOWER(Settings!$C$4)&".mit."&$A564&IF($C564="","","."&$C564&"."&$B564)&IF(INDEX(Variables!$D$5:$D$45,MATCH($A564,Variables!$A$5:$A$45,0))="","","."&INDEX(Variables!$D$5:$D$45,MATCH($A564,Variables!$A$5:$A$45,0)))&"."&K$5 | L564: =SUMIF($B$411:$B$538,$B564,L$411:L$538) | M564: =SUMIF($B$411:$B$538,$B564,M$411:M$538) | N564: =SUMIF($B$411:$B$538,$B564,N$411:N$538) | O564: =SUMIF($B$411:$B$538,$B564,O$411:O$538) | P564: =SUMIF($B$411:$B$538,$B564,P$411:P$538) | Q564: =SUMIF($B$411:$B$538,$B564,Q$411:Q$538) | R564: =SUMIF($B$411:$B$538,$B564,R$411:R$538) | S564: =SUMIF($B$411:$B$538,$B564,S$411:S$538) | ... Y564: =SUMIF($B$411:$B$538,$B564,Y$411:Y$538) | Z564: =LOWER(Settings!$C$4)&".mit."&$A564&IF($C564="","","."&$C564&"."&$B564)&IF(INDEX(Variables!$D$5:$D$45,MATCH($A564,Variables!$A$5:$A$45,0))="","","."&INDEX(Variables!$D$5:$D$45,MATCH($A564,Variables!$A$5:$A$45,0)))&"."&Z$5 | AA564: =SUMIF($B$411:$B$538,$B564,AA$411:AA$538) | AB564: =SUMIF($B$411:$B$538,$B564,AB$411:AB$538) | AC564: =SUMIF($B$411:$B$538,$B564,AC$411:AC$538) | AD564: =SUMIF($B$411:$B$538,$B564,AD$411:AD$538) | AE564: =SUMIF($B$411:$B$538,$B564,AE$411:AE$538) | AF564: =SUMIF($B$411:$B$538,$B564,AF$411:AF$538) | AG564: =SUMIF($B$411:$B$538,$B564,AG$411:AG$538) | AH564: =SUMIF($B$411:$B$538,$B564,AH$411:AH$538) | ... AN564: =SUMIF($B$411:$B$538,$B564,AN$411:AN$538)
A565: ener | B565: bio | C565: all | H565: =INDEX(Variables!$B$5:$B$45,MATCH($A565,Variables!$A$5:$A$45,0))&IF($C565="",""," | "&INDEX(Mapping!$B$5:$B$21,MATCH($C565,Mapping!$A$5:$A$21,0))&" | "&INDEX(Mapping!$B$24:$B$32,MATCH($B565,Mapping!$A$24:$A$32,0))) | I565: =INDEX(Variables!$C$5:$C$45,MATCH($A565,Variables!$A$5:$A$45,0)) | J565: =INDEX(Variables!$E$5:$E$45,MATCH($A565,Variables!$A$5:$A$45,0)) | K565: =LOWER(Settings!$C$4)&".mit."&$A565&IF($C565="","","."&$C565&"."&$B565)&IF(INDEX(Variables!$D$5:$D$45,MATCH($A565,Variables!$A$5:$A$45,0))="","","."&INDEX(Variables!$D$5:$D$45,MATCH($A565,Variables!$A$5:$A$45,0)))&"."&K$5 | L565: =SUMIF($B$411:$B$538,$B565,L$411:L$538) | M565: =SUMIF($B$411:$B$538,$B565,M$411:M$538) | N565: =SUMIF($B$411:$B$538,$B565,N$411:N$538) | O565: =SUMIF($B$411:$B$538,$B565,O$411:O$538) | P565: =SUMIF($B$411:$B$538,$B565,P$411:P$538) | Q565: =SUMIF($B$411:$B$538,$B565,Q$411:Q$538) | R565: =SUMIF($B$411:$B$538,$B565,R$411:R$538) | S565: =SUMIF($B$411:$B$538,$B565,S$411:S$538) | ... Y565: =SUMIF($B$411:$B$538,$B565,Y$411:Y$538) | Z565: =LOWER(Settings!$C$4)&".mit."&$A565&IF($C565="","","."&$C565&"."&$B565)&IF(INDEX(Variables!$D$5:$D$45,MATCH($A565,Variables!$A$5:$A$45,0))="","","."&INDEX(Variables!$D$5:$D$45,MATCH($A565,Variables!$A$5:$A$45,0)))&"."&Z$5 | AA565: =SUMIF($B$411:$B$538,$B565,AA$411:AA$538) | AB565: =SUMIF($B$411:$B$538,$B565,AB$411:AB$538) | AC565: =SUMIF($B$411:$B$538,$B565,AC$411:AC$538) | AD565: =SUMIF($B$411:$B$538,$B565,AD$411:AD$538) | AE565: =SUMIF($B$411:$B$538,$B565,AE$411:AE$538) | AF565: =SUMIF($B$411:$B$538,$B565,AF$411:AF$538) | AG565: =SUMIF($B$411:$B$538,$B565,AG$411:AG$538) | AH565: =SUMIF($B$411:$B$538,$B565,AH$411:AH$538) | ... AN565: =SUMIF($B$411:$B$538,$B565,AN$411:AN$538)
A567: ener.chk | H567: =INDEX(Variables!$B$5:$B$45,MATCH($A567,Variables!$A$5:$A$45,0))&IF($C567="",""," | "&INDEX(Mapping!$B$5:$B$21,MATCH($C567,Mapping!$A$5:$A$21,0))&" | "&INDEX(Mapping!$B$24:$B$32,MATCH($B567,Mapping!$A$24:$A$32,0))) | I567: =INDEX(Variables!$C$5:$C$45,MATCH($A567,Variables!$A$5:$A$45,0)) | J567: =INDEX(Variables!$E$5:$E$45,MATCH($A567,Variables!$A$5:$A$45,0)) | K567: =LOWER(Settings!$C$4)&".mit."&$A567&IF($C567="","","."&$C567&"."&$B567)&IF(INDEX(Variables!$D$5:$D$45,MATCH($A567,Variables!$A$5:$A$45,0))="","","."&INDEX(Variables!$D$5:$D$45,MATCH($A567,Variables!$A$5:$A$45,0)))&"."&K$5 | L567: =ABS(SUM(L541:L556)-L410)+ABS(SUM(L558:L565)-L410) | M567: =ABS(SUM(M541:M556)-M410)+ABS(SUM(M558:M565)-M410) | N567: =ABS(SUM(N541:N556)-N410)+ABS(SUM(N558:N565)-N410) | O567: =ABS(SUM(O541:O556)-O410)+ABS(SUM(O558:O565)-O410) | P567: =ABS(SUM(P541:P556)-P410)+ABS(SUM(P558:P565)-P410) | Q567: =ABS(SUM(Q541:Q556)-Q410)+ABS(SUM(Q558:Q565)-Q410) | R567: =ABS(SUM(R541:R556)-R410)+ABS(SUM(R558:R565)-R410) | S567: =ABS(SUM(S541:S556)-S410)+ABS(SUM(S558:S565)-S410) | ... Y567: =ABS(SUM(Y541:Y556)-Y410)+ABS(SUM(Y558:Y565)-Y410) | Z567: =LOWER(Settings!$C$4)&".mit."&$A567&IF($C567="","","."&$C567&"."&$B567)&IF(INDEX(Variables!$D$5:$D$45,MATCH($A567,Variables!$A$5:$A$45,0))="","","."&INDEX(Variables!$D$5:$D$45,MATCH($A567,Variables!$A$5:$A$45,0)))&"."&Z$5 | AA567: =ABS(SUM(AA541:AA556)-AA410)+ABS(SUM(AA558:AA565)-AA410) | AB567: =ABS(SUM(AB541:AB556)-AB410)+ABS(SUM(AB558:AB565)-AB410) | AC567: =ABS(SUM(AC541:AC556)-AC410)+ABS(SUM(AC558:AC565)-AC410) | AD567: =ABS(SUM(AD541:AD556)-AD410)+ABS(SUM(AD558:AD565)-AD410) | AE567: =ABS(SUM(AE541:AE556)-AE410)+ABS(SUM(AE558:AE565)-AE410) | AF567: =ABS(SUM(AF541:AF556)-AF410)+ABS(SUM(AF558:AF565)-AF410) | AG567: =ABS(SUM(AG541:AG556)-AG410)+ABS(SUM(AG558:AG565)-AG410) | AH567: =ABS(SUM(AH541:AH556)-AH410)+ABS(SUM(AH558:AH565)-AH410) | ... AN567: =ABS(SUM(AN541:AN556)-AN410)+ABS(SUM(AN558:AN565)-AN410)
A569: ener.ref | B569: all | C569: all | H569: =INDEX(Variables!$B$5:$B$45,MATCH($A569,Variables!$A$5:$A$45,0))&IF($C569="",""," | "&INDEX(Mapping!$B$5:$B$21,MATCH($C569,Mapping!$A$5:$A$21,0))&" | "&INDEX(Mapping!$B$24:$B$32,MATCH($B569,Mapping!$A$24:$A$32,0))) | I569: =INDEX(Variables!$C$5:$C$45,MATCH($A569,Variables!$A$5:$A$45,0)) | J569: =INDEX(Variables!$E$5:$E$45,MATCH($A569,Variables!$A$5:$A$45,0)) | K569: =LOWER(Settings!$C$4)&".mit."&$A569&IF($C569="","","."&$C569&"."&$B569)&IF(INDEX(Variables!$D$5:$D$45,MATCH($A569,Variables!$A$5:$A$45,0))="","","."&INDEX(Variables!$D$5:$D$45,MATCH($A569,Variables!$A$5:$A$45,0)))&"."&K$5 | L569: =INDEX($K410:$GH410,MATCH(L$4,$K$4:$GH$4,0)) | M569: =INDEX($K410:$GH410,MATCH(M$4,$K$4:$GH$4,0)) | N569: =INDEX($K410:$GH410,MATCH(N$4,$K$4:$GH$4,0)) | O569: =INDEX($K410:$GH410,MATCH(O$4,$K$4:$GH$4,0)) | P569: =INDEX($K410:$GH410,MATCH(P$4,$K$4:$GH$4,0)) | Q569: =INDEX($K410:$GH410,MATCH(Q$4,$K$4:$GH$4,0)) | R569: =INDEX($K410:$GH410,MATCH(R$4,$K$4:$GH$4,0)) | S569: =INDEX($K410:$GH410,MATCH(S$4,$K$4:$GH$4,0)) | ... Y569: =INDEX($K410:$GH410,MATCH(Y$4,$K$4:$GH$4,0)) | Z569: =LOWER(Settings!$C$4)&".mit."&$A569&IF($C569="","","."&$C569&"."&$B569)&IF(INDEX(Variables!$D$5:$D$45,MATCH($A569,Variables!$A$5:$A$45,0))="","","."&INDEX(Variables!$D$5:$D$45,MATCH($A569,Variables!$A$5:$A$45,0)))&"."&Z$5 | AA569: =INDEX($K410:$GH410,MATCH(AA$4,$K$4:$GH$4,0)) | AB569: =INDEX($K410:$GH410,MATCH(AB$4,$K$4:$GH$4,0)) | AC569: =INDEX($K410:$GH410,MATCH(AC$4,$K$4:$GH$4,0)) | AD569: =INDEX($K410:$GH410,MATCH(AD$4,$K$4:$GH$4,0)) | AE569: =INDEX($K410:$GH410,MATCH(AE$4,$K$4:$GH$4,0)) | AF569: =INDEX($K410:$GH410,MATCH(AF$4,$K$4:$GH$4,0)) | AG569: =INDEX($K410:$GH410,MATCH(AG$4,$K$4:$GH$4,0)) | AH569: =INDEX($K410:$GH410,MATCH(AH$4,$K$4:$GH$4,0)) | ... AN569: =INDEX($K410:$GH410,MATCH(AN$4,$K$4:$GH$4,0))
A570: ener.pct | B570: all | C570: all | H570: =INDEX(Variables!$B$5:$B$45,MATCH($A570,Variables!$A$5:$A$45,0))&IF($C570="",""," | "&INDEX(Mapping!$B$5:$B$21,MATCH($C570,Mapping!$A$5:$A$21,0))&" | "&INDEX(Mapping!$B$24:$B$32,MATCH($B570,Mapping!$A$24:$A$32,0))) | I570: =INDEX(Variables!$C$5:$C$45,MATCH($A570,Variables!$A$5:$A$45,0)) | J570: =INDEX(Variables!$E$5:$E$45,MATCH($A570,Variables!$A$5:$A$45,0)) | K570: =LOWER(Settings!$C$4)&".mit."&$A570&IF($C570="","","."&$C570&"."&$B570)&IF(INDEX(Variables!$D$5:$D$45,MATCH($A570,Variables!$A$5:$A$45,0))="","","."&INDEX(Variables!$D$5:$D$45,MATCH($A570,Variables!$A$5:$A$45,0)))&"."&K$5 | L570: =L410/L569-1 | M570: =M410/M569-1 | N570: =N410/N569-1 | O570: =O410/O569-1 | P570: =P410/P569-1 | Q570: =Q410/Q569-1 | R570: =R410/R569-1 | S570: =S410/S569-1 | ... Y570: =Y410/Y569-1 | Z570: =LOWER(Settings!$C$4)&".mit."&$A570&IF($C570="","","."&$C570&"."&$B570)&IF(INDEX(Variables!$D$5:$D$45,MATCH($A570,Variables!$A$5:$A$45,0))="","","."&INDEX(Variables!$D$5:$D$45,MATCH($A570,Variables!$A$5:$A$45,0)))&"."&Z$5 | AA570: =AA410/AA569-1 | AB570: =AB410/AB569-1 | AC570: =AC410/AC569-1 | AD570: =AD410/AD569-1 | AE570: =AE410/AE569-1 | AF570: =AF410/AF569-1 | AG570: =AG410/AG569-1 | AH570: =AH410/AH569-1 | ... AN570: =AN410/AN569-1

Sheet Inputs
A2: Inputs by fuel | subsector: every lookup used by Mitigation (data step, no calculations)
A3: One row per fuel | subsector (same taxonomy as Mitigation columns B:C). Mitigation reads these columns with INDEX/MATCH on the key. Green = input.
A4: Key (fuel|subsector) | B4: Fuel | C4: Subsector | D4: Elasticity sector | E4: Elasticity fuel | F4: AEEI fuel | G4: Price code | H4: EF sector | I4: GJ per price unit | J4: Coverage | K4: eps_Y GDP | L4: eps_U usage | M4: eps_F efficiency | N4: alpha AEEI | O4: Pre-tax price growth | P4: Base pre-tax price ($/GJ) | Q4: Base tax ($/GJ) | R4: EF (tCO2/GJ) | S4: Base-year fuel use (ktoe)
A5: =$B5&"|"&$C5 | B5: coa | C5: rod | D5: =INDEX(Mapping!$D$5:$D$20,MATCH($C5,Mapping!$A$5:$A$20,0)) | E5: =INDEX(Mapping!$C$24:$C$31,MATCH($B5,Mapping!$A$24:$A$31,0)) | F5: =INDEX(Mapping!$D$24:$D$31,MATCH($B5,Mapping!$A$24:$A$31,0)) | G5: =$B5&"."&IF(INDEX(Mapping!$E$24:$E$31,MATCH($B5,Mapping!$A$24:$A$31,0))="sub",INDEX(Mapping!$F$5:$F$20,MATCH($C5,Mapping!$A$5:$A$20,0)),"all") | H5: =INDEX(Mapping!$E$5:$E$20,MATCH($C5,Mapping!$A$5:$A$20,0)) | I5: =INDEX(Mapping!$G$24:$G$31,MATCH($B5,Mapping!$A$24:$A$31,0)) | J5: =INDEX(Mapping!$G$5:$G$20,MATCH($C5,Mapping!$A$5:$A$20,0)) | K5: =INDEX(Elasticities!$F$4:$I$200,MATCH("inc|"&$E5&"|"&$D5,Elasticities!$A$4:$A$200,0),MATCH(Settings!$C$6,Elasticities!$F$3:$I$3,0)) | L5: =INDEX(Elasticities!$F$4:$I$200,MATCH("usg|"&$E5&"|"&$D5,Elasticities!$A$4:$A$200,0),MATCH(Settings!$C$6,Elasticities!$F$3:$I$3,0)) | M5: =INDEX(Elasticities!$F$4:$I$200,MATCH("eff|"&$E5&"|"&$D5,Elasticities!$A$4:$A$200,0),MATCH(Settings!$C$6,Elasticities!$F$3:$I$3,0)) | N5: =INDEX(Elasticities!$F$4:$I$200,MATCH("aei|"&$F5&"|"&$D5,Elasticities!$A$4:$A$200,0),MATCH(Settings!$C$6,Elasticities!$F$3:$I$3,0)) | O5: 0 | P5: =INDEX(Prices_dom!$A$6:$CU$2000,MATCH(Settings!$C$4&Settings!$C$7,Prices_dom!$A$6:$A$2000,0),MATCH("mit.sp."&$G5,Prices_dom!$A$5:$CU$5,0))/$I5 | Q5: =(INDEX(Prices_dom!$A$6:$CU$2000,MATCH(Settings!$C$4&Settings!$C$7,Prices_dom!$A$6:$A$2000,0),MATCH("mit.rp."&$G5,Prices_dom!$A$5:$CU$5,0))-INDEX(Prices_dom!$A$6:$CU$2000,MATCH(Settings!$C$4&Settings!$C$7,Prices_dom!$A$6:$A$2000,0),MATCH("mit.sp."&$G5,Prices_dom!$A$5:$CU$5,0)))/$I5 | R5: =INDEX(EF_GHG!$E$4:$E$1000,MATCH(Settings!$C$4&"|"&$B5&"|"&$H5,EF_GHG!$A$4:$A$1000,0)) | S5: =INDEX(EnergyCons!$F$4:$F$5000,MATCH(Settings!$C$4&"|"&Settings!$C$7&"|"&$C5&"|"&$B5,EnergyCons!$A$4:$A$5000,0))
A6: =$B6&"|"&$C6 | B6: nga | C6: rod | D6: =INDEX(Mapping!$D$5:$D$20,MATCH($C6,Mapping!$A$5:$A$20,0)) | E6: =INDEX(Mapping!$C$24:$C$31,MATCH($B6,Mapping!$A$24:$A$31,0)) | F6: =INDEX(Mapping!$D$24:$D$31,MATCH($B6,Mapping!$A$24:$A$31,0)) | G6: =$B6&"."&IF(INDEX(Mapping!$E$24:$E$31,MATCH($B6,Mapping!$A$24:$A$31,0))="sub",INDEX(Mapping!$F$5:$F$20,MATCH($C6,Mapping!$A$5:$A$20,0)),"all") | H6: =INDEX(Mapping!$E$5:$E$20,MATCH($C6,Mapping!$A$5:$A$20,0)) | I6: =INDEX(Mapping!$G$24:$G$31,MATCH($B6,Mapping!$A$24:$A$31,0)) | J6: =INDEX(Mapping!$G$5:$G$20,MATCH($C6,Mapping!$A$5:$A$20,0)) | K6: =INDEX(Elasticities!$F$4:$I$200,MATCH("inc|"&$E6&"|"&$D6,Elasticities!$A$4:$A$200,0),MATCH(Settings!$C$6,Elasticities!$F$3:$I$3,0)) | L6: =INDEX(Elasticities!$F$4:$I$200,MATCH("usg|"&$E6&"|"&$D6,Elasticities!$A$4:$A$200,0),MATCH(Settings!$C$6,Elasticities!$F$3:$I$3,0)) | M6: =INDEX(Elasticities!$F$4:$I$200,MATCH("eff|"&$E6&"|"&$D6,Elasticities!$A$4:$A$200,0),MATCH(Settings!$C$6,Elasticities!$F$3:$I$3,0)) | N6: =INDEX(Elasticities!$F$4:$I$200,MATCH("aei|"&$F6&"|"&$D6,Elasticities!$A$4:$A$200,0),MATCH(Settings!$C$6,Elasticities!$F$3:$I$3,0)) | O6: 0 | P6: =INDEX(Prices_dom!$A$6:$CU$2000,MATCH(Settings!$C$4&Settings!$C$7,Prices_dom!$A$6:$A$2000,0),MATCH("mit.sp."&$G6,Prices_dom!$A$5:$CU$5,0))/$I6 | Q6: =(INDEX(Prices_dom!$A$6:$CU$2000,MATCH(Settings!$C$4&Settings!$C$7,Prices_dom!$A$6:$A$2000,0),MATCH("mit.rp."&$G6,Prices_dom!$A$5:$CU$5,0))-INDEX(Prices_dom!$A$6:$CU$2000,MATCH(Settings!$C$4&Settings!$C$7,Prices_dom!$A$6:$A$2000,0),MATCH("mit.sp."&$G6,Prices_dom!$A$5:$CU$5,0)))/$I6 | R6: =INDEX(EF_GHG!$E$4:$E$1000,MATCH(Settings!$C$4&"|"&$B6&"|"&$H6,EF_GHG!$A$4:$A$1000,0)) | S6: =INDEX(EnergyCons!$F$4:$F$5000,MATCH(Settings!$C$4&"|"&Settings!$C$7&"|"&$C6&"|"&$B6,EnergyCons!$A$4:$A$5000,0))
A7: =$B7&"|"&$C7 | B7: gso | C7: rod | D7: =INDEX(Mapping!$D$5:$D$20,MATCH($C7,Mapping!$A$5:$A$20,0)) | E7: =INDEX(Mapping!$C$24:$C$31,MATCH($B7,Mapping!$A$24:$A$31,0)) | F7: =INDEX(Mapping!$D$24:$D$31,MATCH($B7,Mapping!$A$24:$A$31,0)) | G7: =$B7&"."&IF(INDEX(Mapping!$E$24:$E$31,MATCH($B7,Mapping!$A$24:$A$31,0))="sub",INDEX(Mapping!$F$5:$F$20,MATCH($C7,Mapping!$A$5:$A$20,0)),"all") | H7: =INDEX(Mapping!$E$5:$E$20,MATCH($C7,Mapping!$A$5:$A$20,0)) | I7: =INDEX(Mapping!$G$24:$G$31,MATCH($B7,Mapping!$A$24:$A$31,0)) | J7: =INDEX(Mapping!$G$5:$G$20,MATCH($C7,Mapping!$A$5:$A$20,0)) | K7: =INDEX(Elasticities!$F$4:$I$200,MATCH("inc|"&$E7&"|"&$D7,Elasticities!$A$4:$A$200,0),MATCH(Settings!$C$6,Elasticities!$F$3:$I$3,0)) | L7: =INDEX(Elasticities!$F$4:$I$200,MATCH("usg|"&$E7&"|"&$D7,Elasticities!$A$4:$A$200,0),MATCH(Settings!$C$6,Elasticities!$F$3:$I$3,0)) | M7: =INDEX(Elasticities!$F$4:$I$200,MATCH("eff|"&$E7&"|"&$D7,Elasticities!$A$4:$A$200,0),MATCH(Settings!$C$6,Elasticities!$F$3:$I$3,0)) | N7: =INDEX(Elasticities!$F$4:$I$200,MATCH("aei|"&$F7&"|"&$D7,Elasticities!$A$4:$A$200,0),MATCH(Settings!$C$6,Elasticities!$F$3:$I$3,0)) | O7: 0 | P7: =INDEX(Prices_dom!$A$6:$CU$2000,MATCH(Settings!$C$4&Settings!$C$7,Prices_dom!$A$6:$A$2000,0),MATCH("mit.sp."&$G7,Prices_dom!$A$5:$CU$5,0))/$I7 | Q7: =(INDEX(Prices_dom!$A$6:$CU$2000,MATCH(Settings!$C$4&Settings!$C$7,Prices_dom!$A$6:$A$2000,0),MATCH("mit.rp."&$G7,Prices_dom!$A$5:$CU$5,0))-INDEX(Prices_dom!$A$6:$CU$2000,MATCH(Settings!$C$4&Settings!$C$7,Prices_dom!$A$6:$A$2000,0),MATCH("mit.sp."&$G7,Prices_dom!$A$5:$CU$5,0)))/$I7 | R7: =INDEX(EF_GHG!$E$4:$E$1000,MATCH(Settings!$C$4&"|"&$B7&"|"&$H7,EF_GHG!$A$4:$A$1000,0)) | S7: =INDEX(EnergyCons!$F$4:$F$5000,MATCH(Settings!$C$4&"|"&Settings!$C$7&"|"&$C7&"|"&$B7,EnergyCons!$A$4:$A$5000,0))
A8: =$B8&"|"&$C8 | B8: die | C8: rod | D8: =INDEX(Mapping!$D$5:$D$20,MATCH($C8,Mapping!$A$5:$A$20,0)) | E8: =INDEX(Mapping!$C$24:$C$31,MATCH($B8,Mapping!$A$24:$A$31,0)) | F8: =INDEX(Mapping!$D$24:$D$31,MATCH($B8,Mapping!$A$24:$A$31,0)) | G8: =$B8&"."&IF(INDEX(Mapping!$E$24:$E$31,MATCH($B8,Mapping!$A$24:$A$31,0))="sub",INDEX(Mapping!$F$5:$F$20,MATCH($C8,Mapping!$A$5:$A$20,0)),"all") | H8: =INDEX(Mapping!$E$5:$E$20,MATCH($C8,Mapping!$A$5:$A$20,0)) | I8: =INDEX(Mapping!$G$24:$G$31,MATCH($B8,Mapping!$A$24:$A$31,0)) | J8: =INDEX(Mapping!$G$5:$G$20,MATCH($C8,Mapping!$A$5:$A$20,0)) | K8: =INDEX(Elasticities!$F$4:$I$200,MATCH("inc|"&$E8&"|"&$D8,Elasticities!$A$4:$A$200,0),MATCH(Settings!$C$6,Elasticities!$F$3:$I$3,0)) | L8: =INDEX(Elasticities!$F$4:$I$200,MATCH("usg|"&$E8&"|"&$D8,Elasticities!$A$4:$A$200,0),MATCH(Settings!$C$6,Elasticities!$F$3:$I$3,0)) | M8: =INDEX(Elasticities!$F$4:$I$200,MATCH("eff|"&$E8&"|"&$D8,Elasticities!$A$4:$A$200,0),MATCH(Settings!$C$6,Elasticities!$F$3:$I$3,0)) | N8: =INDEX(Elasticities!$F$4:$I$200,MATCH("aei|"&$F8&"|"&$D8,Elasticities!$A$4:$A$200,0),MATCH(Settings!$C$6,Elasticities!$F$3:$I$3,0)) | O8: 0 | P8: =INDEX(Prices_dom!$A$6:$CU$2000,MATCH(Settings!$C$4&Settings!$C$7,Prices_dom!$A$6:$A$2000,0),MATCH("mit.sp."&$G8,Prices_dom!$A$5:$CU$5,0))/$I8 | Q8: =(INDEX(Prices_dom!$A$6:$CU$2000,MATCH(Settings!$C$4&Settings!$C$7,Prices_dom!$A$6:$A$2000,0),MATCH("mit.rp."&$G8,Prices_dom!$A$5:$CU$5,0))-INDEX(Prices_dom!$A$6:$CU$2000,MATCH(Settings!$C$4&Settings!$C$7,Prices_dom!$A$6:$A$2000,0),MATCH("mit.sp."&$G8,Prices_dom!$A$5:$CU$5,0)))/$I8 | R8: =INDEX(EF_GHG!$E$4:$E$1000,MATCH(Settings!$C$4&"|"&$B8&"|"&$H8,EF_GHG!$A$4:$A$1000,0)) | S8: =INDEX(EnergyCons!$F$4:$F$5000,MATCH(Settings!$C$4&"|"&Settings!$C$7&"|"&$C8&"|"&$B8,EnergyCons!$A$4:$A$5000,0))
A9: =$B9&"|"&$C9 | B9: lpg | C9: rod | D9: =INDEX(Mapping!$D$5:$D$20,MATCH($C9,Mapping!$A$5:$A$20,0)) | E9: =INDEX(Mapping!$C$24:$C$31,MATCH($B9,Mapping!$A$24:$A$31,0)) | F9: =INDEX(Mapping!$D$24:$D$31,MATCH($B9,Mapping!$A$24:$A$31,0)) | G9: =$B9&"."&IF(INDEX(Mapping!$E$24:$E$31,MATCH($B9,Mapping!$A$24:$A$31,0))="sub",INDEX(Mapping!$F$5:$F$20,MATCH($C9,Mapping!$A$5:$A$20,0)),"all") | H9: =INDEX(Mapping!$E$5:$E$20,MATCH($C9,Mapping!$A$5:$A$20,0)) | I9: =INDEX(Mapping!$G$24:$G$31,MATCH($B9,Mapping!$A$24:$A$31,0)) | J9: =INDEX(Mapping!$G$5:$G$20,MATCH($C9,Mapping!$A$5:$A$20,0)) | K9: =INDEX(Elasticities!$F$4:$I$200,MATCH("inc|"&$E9&"|"&$D9,Elasticities!$A$4:$A$200,0),MATCH(Settings!$C$6,Elasticities!$F$3:$I$3,0)) | L9: =INDEX(Elasticities!$F$4:$I$200,MATCH("usg|"&$E9&"|"&$D9,Elasticities!$A$4:$A$200,0),MATCH(Settings!$C$6,Elasticities!$F$3:$I$3,0)) | M9: =INDEX(Elasticities!$F$4:$I$200,MATCH("eff|"&$E9&"|"&$D9,Elasticities!$A$4:$A$200,0),MATCH(Settings!$C$6,Elasticities!$F$3:$I$3,0)) | N9: =INDEX(Elasticities!$F$4:$I$200,MATCH("aei|"&$F9&"|"&$D9,Elasticities!$A$4:$A$200,0),MATCH(Settings!$C$6,Elasticities!$F$3:$I$3,0)) | O9: 0 | P9: =INDEX(Prices_dom!$A$6:$CU$2000,MATCH(Settings!$C$4&Settings!$C$7,Prices_dom!$A$6:$A$2000,0),MATCH("mit.sp."&$G9,Prices_dom!$A$5:$CU$5,0))/$I9 | Q9: =(INDEX(Prices_dom!$A$6:$CU$2000,MATCH(Settings!$C$4&Settings!$C$7,Prices_dom!$A$6:$A$2000,0),MATCH("mit.rp."&$G9,Prices_dom!$A$5:$CU$5,0))-INDEX(Prices_dom!$A$6:$CU$2000,MATCH(Settings!$C$4&Settings!$C$7,Prices_dom!$A$6:$A$2000,0),MATCH("mit.sp."&$G9,Prices_dom!$A$5:$CU$5,0)))/$I9 | R9: =INDEX(EF_GHG!$E$4:$E$1000,MATCH(Settings!$C$4&"|"&$B9&"|"&$H9,EF_GHG!$A$4:$A$1000,0)) | S9: =INDEX(EnergyCons!$F$4:$F$5000,MATCH(Settings!$C$4&"|"&Settings!$C$7&"|"&$C9&"|"&$B9,EnergyCons!$A$4:$A$5000,0))
A10: =$B10&"|"&$C10 | B10: ker | C10: rod | D10: =INDEX(Mapping!$D$5:$D$20,MATCH($C10,Mapping!$A$5:$A$20,0)) | E10: =INDEX(Mapping!$C$24:$C$31,MATCH($B10,Mapping!$A$24:$A$31,0)) | F10: =INDEX(Mapping!$D$24:$D$31,MATCH($B10,Mapping!$A$24:$A$31,0)) | G10: =$B10&"."&IF(INDEX(Mapping!$E$24:$E$31,MATCH($B10,Mapping!$A$24:$A$31,0))="sub",INDEX(Mapping!$F$5:$F$20,MATCH($C10,Mapping!$A$5:$A$20,0)),"all") | H10: =INDEX(Mapping!$E$5:$E$20,MATCH($C10,Mapping!$A$5:$A$20,0)) | I10: =INDEX(Mapping!$G$24:$G$31,MATCH($B10,Mapping!$A$24:$A$31,0)) | J10: =INDEX(Mapping!$G$5:$G$20,MATCH($C10,Mapping!$A$5:$A$20,0)) | K10: =INDEX(Elasticities!$F$4:$I$200,MATCH("inc|"&$E10&"|"&$D10,Elasticities!$A$4:$A$200,0),MATCH(Settings!$C$6,Elasticities!$F$3:$I$3,0)) | L10: =INDEX(Elasticities!$F$4:$I$200,MATCH("usg|"&$E10&"|"&$D10,Elasticities!$A$4:$A$200,0),MATCH(Settings!$C$6,Elasticities!$F$3:$I$3,0)) | M10: =INDEX(Elasticities!$F$4:$I$200,MATCH("eff|"&$E10&"|"&$D10,Elasticities!$A$4:$A$200,0),MATCH(Settings!$C$6,Elasticities!$F$3:$I$3,0)) | N10: =INDEX(Elasticities!$F$4:$I$200,MATCH("aei|"&$F10&"|"&$D10,Elasticities!$A$4:$A$200,0),MATCH(Settings!$C$6,Elasticities!$F$3:$I$3,0)) | O10: 0 | P10: =INDEX(Prices_dom!$A$6:$CU$2000,MATCH(Settings!$C$4&Settings!$C$7,Prices_dom!$A$6:$A$2000,0),MATCH("mit.sp."&$G10,Prices_dom!$A$5:$CU$5,0))/$I10 | Q10: =(INDEX(Prices_dom!$A$6:$CU$2000,MATCH(Settings!$C$4&Settings!$C$7,Prices_dom!$A$6:$A$2000,0),MATCH("mit.rp."&$G10,Prices_dom!$A$5:$CU$5,0))-INDEX(Prices_dom!$A$6:$CU$2000,MATCH(Settings!$C$4&Settings!$C$7,Prices_dom!$A$6:$A$2000,0),MATCH("mit.sp."&$G10,Prices_dom!$A$5:$CU$5,0)))/$I10 | R10: =INDEX(EF_GHG!$E$4:$E$1000,MATCH(Settings!$C$4&"|"&$B10&"|"&$H10,EF_GHG!$A$4:$A$1000,0)) | S10: =INDEX(EnergyCons!$F$4:$F$5000,MATCH(Settings!$C$4&"|"&Settings!$C$7&"|"&$C10&"|"&$B10,EnergyCons!$A$4:$A$5000,0))
A11: =$B11&"|"&$C11 | B11: oop | C11: rod | D11: =INDEX(Mapping!$D$5:$D$20,MATCH($C11,Mapping!$A$5:$A$20,0)) | E11: =INDEX(Mapping!$C$24:$C$31,MATCH($B11,Mapping!$A$24:$A$31,0)) | F11: =INDEX(Mapping!$D$24:$D$31,MATCH($B11,Mapping!$A$24:$A$31,0)) | G11: =$B11&"."&IF(INDEX(Mapping!$E$24:$E$31,MATCH($B11,Mapping!$A$24:$A$31,0))="sub",INDEX(Mapping!$F$5:$F$20,MATCH($C11,Mapping!$A$5:$A$20,0)),"all") | H11: =INDEX(Mapping!$E$5:$E$20,MATCH($C11,Mapping!$A$5:$A$20,0)) | I11: =INDEX(Mapping!$G$24:$G$31,MATCH($B11,Mapping!$A$24:$A$31,0)) | J11: =INDEX(Mapping!$G$5:$G$20,MATCH($C11,Mapping!$A$5:$A$20,0)) | K11: =INDEX(Elasticities!$F$4:$I$200,MATCH("inc|"&$E11&"|"&$D11,Elasticities!$A$4:$A$200,0),MATCH(Settings!$C$6,Elasticities!$F$3:$I$3,0)) | L11: =INDEX(Elasticities!$F$4:$I$200,MATCH("usg|"&$E11&"|"&$D11,Elasticities!$A$4:$A$200,0),MATCH(Settings!$C$6,Elasticities!$F$3:$I$3,0)) | M11: =INDEX(Elasticities!$F$4:$I$200,MATCH("eff|"&$E11&"|"&$D11,Elasticities!$A$4:$A$200,0),MATCH(Settings!$C$6,Elasticities!$F$3:$I$3,0)) | N11: =INDEX(Elasticities!$F$4:$I$200,MATCH("aei|"&$F11&"|"&$D11,Elasticities!$A$4:$A$200,0),MATCH(Settings!$C$6,Elasticities!$F$3:$I$3,0)) | O11: 0 | P11: =INDEX(Prices_dom!$A$6:$CU$2000,MATCH(Settings!$C$4&Settings!$C$7,Prices_dom!$A$6:$A$2000,0),MATCH("mit.sp."&$G11,Prices_dom!$A$5:$CU$5,0))/$I11 | Q11: =(INDEX(Prices_dom!$A$6:$CU$2000,MATCH(Settings!$C$4&Settings!$C$7,Prices_dom!$A$6:$A$2000,0),MATCH("mit.rp."&$G11,Prices_dom!$A$5:$CU$5,0))-INDEX(Prices_dom!$A$6:$CU$2000,MATCH(Settings!$C$4&Settings!$C$7,Prices_dom!$A$6:$A$2000,0),MATCH("mit.sp."&$G11,Prices_dom!$A$5:$CU$5,0)))/$I11 | R11: =INDEX(EF_GHG!$E$4:$E$1000,MATCH(Settings!$C$4&"|"&$B11&"|"&$H11,EF_GHG!$A$4:$A$1000,0)) | S11: =INDEX(EnergyCons!$F$4:$F$5000,MATCH(Settings!$C$4&"|"&Settings!$C$7&"|"&$C11&"|"&$B11,EnergyCons!$A$4:$A$5000,0))
A12: =$B12&"|"&$C12 | B12: bio | C12: rod | D12: =INDEX(Mapping!$D$5:$D$20,MATCH($C12,Mapping!$A$5:$A$20,0)) | E12: =INDEX(Mapping!$C$24:$C$31,MATCH($B12,Mapping!$A$24:$A$31,0)) | F12: =INDEX(Mapping!$D$24:$D$31,MATCH($B12,Mapping!$A$24:$A$31,0)) | G12: =$B12&"."&IF(INDEX(Mapping!$E$24:$E$31,MATCH($B12,Mapping!$A$24:$A$31,0))="sub",INDEX(Mapping!$F$5:$F$20,MATCH($C12,Mapping!$A$5:$A$20,0)),"all") | H12: =INDEX(Mapping!$E$5:$E$20,MATCH($C12,Mapping!$A$5:$A$20,0)) | I12: =INDEX(Mapping!$G$24:$G$31,MATCH($B12,Mapping!$A$24:$A$31,0)) | J12: =INDEX(Mapping!$G$5:$G$20,MATCH($C12,Mapping!$A$5:$A$20,0)) | K12: =INDEX(Elasticities!$F$4:$I$200,MATCH("inc|"&$E12&"|"&$D12,Elasticities!$A$4:$A$200,0),MATCH(Settings!$C$6,Elasticities!$F$3:$I$3,0)) | L12: =INDEX(Elasticities!$F$4:$I$200,MATCH("usg|"&$E12&"|"&$D12,Elasticities!$A$4:$A$200,0),MATCH(Settings!$C$6,Elasticities!$F$3:$I$3,0)) | M12: =INDEX(Elasticities!$F$4:$I$200,MATCH("eff|"&$E12&"|"&$D12,Elasticities!$A$4:$A$200,0),MATCH(Settings!$C$6,Elasticities!$F$3:$I$3,0)) | N12: =INDEX(Elasticities!$F$4:$I$200,MATCH("aei|"&$F12&"|"&$D12,Elasticities!$A$4:$A$200,0),MATCH(Settings!$C$6,Elasticities!$F$3:$I$3,0)) | O12: 0 | P12: =INDEX(Prices_dom!$A$6:$CU$2000,MATCH(Settings!$C$4&Settings!$C$7,Prices_dom!$A$6:$A$2000,0),MATCH("mit.sp."&$G12,Prices_dom!$A$5:$CU$5,0))/$I12 | Q12: =(INDEX(Prices_dom!$A$6:$CU$2000,MATCH(Settings!$C$4&Settings!$C$7,Prices_dom!$A$6:$A$2000,0),MATCH("mit.rp."&$G12,Prices_dom!$A$5:$CU$5,0))-INDEX(Prices_dom!$A$6:$CU$2000,MATCH(Settings!$C$4&Settings!$C$7,Prices_dom!$A$6:$A$2000,0),MATCH("mit.sp."&$G12,Prices_dom!$A$5:$CU$5,0)))/$I12 | R12: =INDEX(EF_GHG!$E$4:$E$1000,MATCH(Settings!$C$4&"|"&$B12&"|"&$H12,EF_GHG!$A$4:$A$1000,0)) | S12: =INDEX(EnergyCons!$F$4:$F$5000,MATCH(Settings!$C$4&"|"&Settings!$C$7&"|"&$C12&"|"&$B12,EnergyCons!$A$4:$A$5000,0))
