Workbook
Name PRETAX: _xlfn.LAMBDA(_xlpm.prev,_xlpm.growth,_xlpm.prev*(1+_xlpm.growth))
Name TAX: _xlfn.LAMBDA(_xlpm.base_tax,_xlpm.new_policy,_xlpm.base_tax+_xlpm.new_policy)
Name POSTTAX: _xlfn.LAMBDA(_xlpm.pre_tax_p,_xlpm.tax_p,_xlpm.pre_tax_p+_xlpm.tax_p)

Sheet ReadMe
A2: CPAT mitigation module - copy-pasteable prototype v0.8
A4: Purpose | B4: Auditable, copy-pasteable replacement of the CPAT mitigation price -> fuel-use chain. Each variable has one formula across all subsectors, fuels and years, and a whole scenario group copies to a new scenario and keeps working.
A5: Status | B5: v0.8 prototype: policies (carbon tax, fuel price reform, feebate shadow price) and price -> fuel use for transport, buildings, industry and other energy use. Power, emissions, revenue and ETS not yet.
A6: Layout (as legacy CPAT) | B6: Sections: 1. Policies (row 9), 3. Power sector (row 146, placeholder), 5. Transport (row 149), 6. Buildings (row 444), 7. Industrial (row 666), 8. Other energy use (row 1253), 11. Results - energy consumption (row 1329). Numbers follow the legacy Mitigation sheet.
A7: Nesting | B7: Across: scenario (outer) > year (inner). Down: sector section > subsector > variable > fuel. Each subsector: a heading line (its total fuel use), then sp, ctxnew, ntx, nce, tax, atp, shp, ener, each over the 8 fuels with one blank row (73 rows per subsector).
A8: Variables | B8: sp pre-tax price; ctxnew new carbon tax = carbon price x EF x fuel coverage x sector coverage; ntx new excise = fuel price reform path / GJ per unit; nce total new policy = ctxnew + ntx; tax = base tax + nce; atp after-tax price = sp + tax; shp shadow price = sector shadow price x EF x share impacting efficiency; ener fuel use (CPAT eq. 3.3.3): the usage term uses atp, the efficiency term (atp + shp), as legacy CPAT.
A9: Roll-up | B9: Sector sections show their total and the subsector heading lines; click + on a heading to see its variables (outline level 2). Section 1 shows the carbon price; its inputs and paths are rolled up. Buttons 1 / 2 / 3 at the top left set all levels.
A10: Section 1 (policies) | B10: Each input row reads MTInputs by its row number (column D, hidden) and the scenario number (row 5). Paths: carbon price as legacy (0 before CPIntro, linear to CPLevelTarget by CPOutro, linear continuation if Linear*); fuel price reform and feebates: 0 before the start year, linear from the starting to the final/target value, continuing linearly afterwards (one default). Shadow prices: by sector ($/tCO2) = feebate path (later + non-auctioned ETS, regulations); share impacting efficiency = feebate coverage x adjustment (1.0).
A11: Data step vs formulas | B11: Lookups happen in Inputs (one row per fuel|subsector), in Mitigation D:G (hidden; labels per variable in Variables G:J), the base-year column and the Section-1 input rows. Calculation cells contain no searching lookups; ctxnew, ntx and shp pick a Section-1 row by position with INDEX(range, position).
A12: LAMBDA column | B12: 2035 (orange) calls named LAMBDAs for sp, tax, atp and ener; drag it back over the row to use them everywhere, or drag 2034 forward. PRETAX(prev, growth) = prev*(1+growth); TAX(base_tax, new_policy) = base_tax+new_policy; POSTTAX(pre_tax_p, tax_p) = pre_tax_p+tax_p; FUELUSE(f_prev, p_now, p_prev, shp_now, shp_prev, gdp_g, eps_y, eps_u, eps_f, alpha) = f_prev*(1/(1+alpha))^(1+eps_u)*(1+gdp_g)^eps_y*(p_now/p_prev)^eps_u*((p_now+shp_now)/(p_prev+shp_prev))^(eps_f*(1+eps_u)).
A13: Codes | B13: Code column before each scenario group: country.mit.<variable>.<subsector>.<fuel>.<suffix>.<scenario> (e.g. egy.mit.ener.rod.gso.e.1). Scenario number at the top (row 5).
A14: Add a scenario | B14: MTInputs: copy the last scenario column one column right (its number updates) and edit its inputs. Mitigation: copy columns Z:AN and paste at AO; numbers, names, codes and all policy paths follow.
A15: Example | B15: Road (heading row 151): sp rows 152-159, ener rows 215-222.
... A17: Data | B17: Countries, Elasticities, Prices_dom, EnergyCons, WEO, EF_GHG; Mapping; Variables; MTInputs. Built by build_v0_8.py; checked by check_v0_8.py.

Sheet Settings
A2: Settings
B4: Country code | C4: EGY
B5: Country name | C5: =INDEX(Countries!$B$4:$B$1000,MATCH($C$4,Countries!$A$4:$A$1000,0))
B6: Income group (selects elasticities) | C6: =INDEX(Countries!$D$4:$D$1000,MATCH($C$4,Countries!$A$4:$A$1000,0))
B7: Base year | C7: 2022
B10: Version log
B11: Version | C11: Date | D11: Description | E11: Max abs regression diff
B12: 0.1 | C12: 2026-10-08 | D12: First build: design 2 price -> fuel-use prototype, Egypt base data, 2 scenarios. | E12: n/a (first version)
B13: 0.2 | C13: 2026-10-08 | D13: Inputs sheet by fuel|subsector (lookups separated from formulas); 4 hidden parameter columns D:G, global parameters; base year 2022 in column L; named LAMBDAs in 2035. | E13: 0 (vs v0.1)
B14: 0.3 | C14: 2026-10-08 | D14: Variable codes in column A; labels from Variables; code column per scenario with full CPAT codes (auto-numbered). | E14: 0 (vs v0.2)
B15: 0.4 | C15: 2026-10-08 | D15: Row outline: blocks roll up. | E15: 0 (vs v0.3)
B16: 0.5 | C16: 2026-10-08 | D16: White band text; summary lines under bands. | E16: 0 (vs v0.4)
B17: 0.6 | C17: 2026-10-08 | D17: MTInputs sheet per scenario; carbon price from MTInputs. | E17: 0 (vs v0.5)
B18: 0.7 | C18: 2026-10-08 | D18: Legacy CPAT section layout (1 Policies, 3 Power, 5-8 sectors, 11 Results; subsector > variable > fuel); policy wedges: new carbon tax with MTInputs coverage, new excise (fuel price reform), total new policy; feebate shadow price (not yet used). | E18: 0 (common codes vs v0.6)
B19: 0.8 | C19: 2026-10-08 | D19: Shadow price on the efficiency margin of fuel use; shadow prices by sector and share impacting efficiency in section 1; all policy paths continue linearly; biomass carbon-tax coverage TRUE. | E19: 0 (common codes vs v0.7, no feebate)

Sheet MTInputs
B1: MTInputs template - row structure copied exactly from legacy CPAT MTInputs
B2: Do not insert/delete rows. Columns D:E are hidden placeholders (MT values, Dashboard values).
B3: Rows must match legacy exactly. Green (EBF1DE) = used by module; grey (F2F2F2) = unused. See NORMS.md section 4. | J3: Scenario columns (Used for calculation): number in row 5, name in row 6. Red = changed from the template value. Copy the last column one to the right to add a scenario.
C5: FALSE | D5: <-- Should normally be "FALSE"! | J5: 1 | K5: =J5+1
D6: 6 | J6: Baseline (no carbon price) | K6: Carbon price $20/tCO2 from 2027
B7: Parameters | C7: unit | D7: MT values | E7: "Dashboard" values | F7: Used for calculation | G7: Defaults | H7: NameOfParameter | J7: Used for calculation | K7: Used for calculation
B8: Country | F8: Egypt | G8: Egypt | H8: Countryname | J8: Egypt | K8: Egypt
B9: Scenario identification
B10: Scenario ID | C10: # | F10: N/A | G10: N/A | H10: MSTScenarioID | J10: =J$5 | K10: =K$5
B11: Scenario status | C11: switch | F11: N/A | G11: N/A | J11: N/A | K11: N/A
B12: Scenario name | C12: name | F12: N/A | G12: N/A | J12: =J$6 | K12: =K$6
B13: Chosen policy | C13: switch | F13: - Carbon tax | G13: - Carbon tax | H13: ScenarioSelected | J13: - Carbon tax | K13: - Carbon tax
B14: Scenario status for macro | C14: # | F14: N/A | G14: N/A | J14: N/A | K14: N/A
B15: Scenario parameters override? | C15: # | F15: N/A | G15: N/A | J15: N/A | K15: N/A
B16: CPAT-side parameters override? | C16: switch | F16: Manual* | G16: Manual* | H16: CPATDefaultsOrUserDefined | J16: Manual* | K16: Manual*
B17: Carbon pricing: main inputs
A18: X | B18: Carbon pricing start year | C18: year | F18: 2026 | G18: 2027 | H18: CPIntro | J18: 2027 | K18: 2027
A19: X | B19: Starting carbon price | C19: nom. USD/tCO2 | F19: 0 | G19: 20 | H19: CPLevelStart | J19: 0 | K19: 20
B20: Target level of carbon price | C20: nom. USD/tCO2 | F20: 50 | G20: 50 | H20: CPLevelTarget | J20: 0 | K20: 20
A21: X | B21: Year to reach target level | C21: year | F21: 2030 | G21: 2035 | H21: CPOutro | J21: 2030 | K21: 2030
B22: Carbon pricing: fuel coverage
B23: Apply tax to coal? | C23: switch | F23: TRUE | G23: TRUE | H23: MCovCoa | J23: TRUE | K23: TRUE
B24: Apply tax to natural gas? | C24: switch | F24: TRUE | G24: TRUE | H24: MCovNga | J24: TRUE | K24: TRUE
B25: Apply tax to gasoline? | C25: switch | F25: TRUE | G25: TRUE | H25: MCovGso | J25: TRUE | K25: TRUE
B26: Apply tax to diesel? | C26: switch | F26: TRUE | G26: TRUE | H26: MCovDie | J26: TRUE | K26: TRUE
B27: Apply tax to LPG? | C27: switch | F27: TRUE | G27: TRUE | H27: MCovLpg | J27: TRUE | K27: TRUE
B28: Apply tax to kerosene? | C28: switch | F28: TRUE | G28: TRUE | H28: MCovKer | J28: TRUE | K28: TRUE
B29: Apply tax to non-road oil products? | C29: switch | F29: TRUE | G29: TRUE | H29: MCovOop | J29: TRUE | K29: TRUE
B30: Carbon pricing: sector coverage
B31: Apply tax to power sector? | C31: switch | F31: TRUE | G31: TRUE | H31: MCovPow | J31: TRUE | K31: TRUE
B32: Apply tax to road transportation? | C32: switch | F32: TRUE | G32: TRUE | H32: MCovRod | J32: TRUE | K32: TRUE
B33: Apply tax to rail transportation? | C33: switch | F33: TRUE | G33: TRUE | H33: MCovRal | J33: TRUE | K33: TRUE
B34: Apply tax to domestic aviation? | C34: switch | F34: TRUE | G34: TRUE | H34: MCovAvi | J34: TRUE | K34: TRUE
B35: Apply tax to domestic shipping? | C35: switch | F35: TRUE | G35: TRUE | H35: MCovNav | J35: TRUE | K35: TRUE
B36: Apply tax to residential sector? | C36: switch | F36: TRUE | G36: TRUE | H36: MCovRes | J36: TRUE | K36: TRUE
B37: Apply tax to food & forestry? | C37: switch | F37: TRUE | G37: TRUE | H37: MCovFoo | J37: TRUE | K37: TRUE
B38: Apply tax to services (private / public)? | C38: switch | F38: TRUE | G38: TRUE | H38: MCovSrv | J38: TRUE | K38: TRUE
B39: Apply tax to mining & chemicals? | C39: switch | F39: TRUE | G39: TRUE | H39: MCovMch | J39: TRUE | K39: TRUE
B40: Apply tax to iron and steel? | C40: switch | F40: TRUE | G40: TRUE | H40: MCovIrn | J40: TRUE | K40: TRUE
B41: Apply tax to non-ferrous metals? | C41: switch | F41: TRUE | G41: TRUE | H41: MCovNfm | J41: TRUE | K41: TRUE
B42: Apply tax to machinery? | C42: switch | F42: TRUE | G42: TRUE | H42: MCovMac | J42: TRUE | K42: TRUE
... B47: Apply tax to other energy use? | C47: switch | F47: TRUE | G47: TRUE | H47: MCovOen | J47: FALSE | K47: FALSE
B48: Exemptions phaseout
B49: Apply exemption phaseout? | C49: switch | F49: FALSE | G49: FALSE | H49: ExemptPhaseout | J49: FALSE | K49: FALSE
B50: Year to start exemption phaseout (if applicable) | C50: year | F50: 2027 | G50: 2027 | H50: YearPha | J50: 2027 | K50: 2027
B51: Period to reach full exemption phaseout (if applicable) | C51: year | F51: 5 | G51: 5 | H51: ExemptPhaseoutPeriod | J51: 5 | K51: 5
B52: Feebates: Starting and End Date
B53: Start date | F53: 2027 | G53: 2027 | H53: D_FeebateIntro | J53: 2027 | K53: 2027
B54: Target date | F54: 2035 | G54: 2035 | H54: D_FeebateOutro | J54: 2035 | K54: 2035
B55: Feebates: Feebate starting rate
B56: Power sector | C56: USD/tCO2 | F56: 0 | G56: 0 | H56: D_Feb_Level_Start_Pow | J56: 0 | K56: 0
B57: Transport | C57: USD/tCO2 | F57: 0 | G57: 0 | H57: D_Feb_Level_Start_Trans | J57: 0 | K57: 0
B58: Residential | C58: USD/tCO2 | F58: 0 | G58: 0 | H58: D_Feb_Level_Start_Res | J58: 0 | K58: 0
B59: Industry | C59: USD/tCO2 | F59: 0 | G59: 0 | H59: D_Feb_Level_Start_Ind | J59: 0 | K59: 0
B60: Feebates: Feebate target rate
B61: Power sector | C61: USD/tCO2 | F61: 0 | G61: 0 | H61: D_Feb_Level_Target_Pow | J61: 0 | K61: 0
B62: Transport | C62: USD/tCO2 | F62: 0 | G62: 0 | H62: D_Feb_Level_Target_Trans | J62: 0 | K62: 0
B63: Residential | C63: USD/tCO2 | F63: 0 | G63: 0 | H63: D_Feb_Level_Target_Res | J63: 0 | K63: 0
B64: Industry | C64: USD/tCO2 | F64: 0 | G64: 0 | H64: D_Feb_Level_Target_Ind | J64: 0 | K64: 0
B65: Feebates sector coverage
B66: Apply tax to power sector? | C66: switch | F66: FALSE | G66: TRUE | J66: FALSE | K66: FALSE
B67: Apply tax to road transportation? | F67: FALSE | G67: FALSE | J67: FALSE | K67: FALSE
B68: Apply tax to rail transportation? | F68: FALSE | G68: FALSE | J68: FALSE | K68: FALSE
B69: Apply tax to domestic aviation? | F69: FALSE | G69: FALSE | J69: FALSE | K69: FALSE
B70: Apply tax to domestic shipping? | F70: FALSE | G70: FALSE | J70: FALSE | K70: FALSE
B71: Apply tax to residential sector? | C71: switch | F71: FALSE | G71: TRUE | J71: FALSE | K71: FALSE
B72: Apply tax to food & forestry? | F72: FALSE | G72: TRUE | J72: FALSE | K72: FALSE
B73: Apply tax to services (private / public)? | F73: FALSE | G73: TRUE | J73: FALSE | K73: FALSE
B74: Apply tax to mining & chemicals? | F74: TRUE | G74: TRUE | J74: TRUE | K74: TRUE
B75: Apply tax to iron and steel? | F75: FALSE | G75: TRUE | J75: FALSE | K75: FALSE
B76: Apply tax to non-ferrous metals? | F76: TRUE | G76: TRUE | J76: TRUE | K76: TRUE
B77: Apply tax to machinery? | F77: TRUE | G77: TRUE | J77: TRUE | K77: TRUE
B78: Apply tax to cement? | F78: TRUE | G78: TRUE | J78: TRUE | K78: TRUE
B79: Apply tax to other manucfacturing? | F79: TRUE | G79: TRUE | J79: TRUE | K79: TRUE
B80: Apply tax to construction? | F80: TRUE | G80: TRUE | J80: TRUE | K80: TRUE
B81: Apply tax to fuel transformation? | F81: TRUE | G81: TRUE | J81: TRUE | K81: TRUE
B82: Apply tax to other energy use? | F82: TRUE | G82: TRUE | J82: TRUE | K82: TRUE
B83: ETS Main Characteristics
B84: Apply new ETS? | F84: No | G84: No | H84: D_NewETS | J84: No | K84: No
B85: Change Relative to Baseline in Start Year | F85: 0 | G85: 0 | H85: D_ETSChangeRelStart | J85: 0 | K85: 0
B86: Change Relative to Baseline in Target Year | F86: 0 | G86: 0 | H86: D_ETSChangeRelTarget | J86: 0 | K86: 0
B87: Cap continuation after target year? | F87: Constant | G87: KeepRelativeCapConstant | H87: D_ETSCapCont | J87: Constant | K87: Constant
B88: ETS Start Year | F88: 2027 | G88: 2026 | H88: D_ETSIntro | J88: 2027 | K88: 2027
B89: ETS Target Year | F89: 2035 | G89: 2035 | H89: D_ETSOutro | J89: 2035 | K89: 2035
B90: Proportion Auctioned in Starting Year | F90: 0 | G90: 0 | H90: D_ETSAuctStart | J90: 0 | K90: 0
B91: Proportion Auctioned in Target Year | F91: 0 | G91: 1 | H91: D_ETSAuctTarget | J91: 0 | K91: 0
B92: Auction proportion continuation after target year? | F92: Constant | G92: Constant | H92: D_ETSAuctCont | J92: Constant | K92: Constant
B93: Override ETS price | F93: No | G93: No | H93: D_ETSPriceOverride | J93: No | K93: No
B94: ETS: modelling assumptions
B95: ETS Volatility | F95: Medium* | G95: Medium* | H95: D_ETSVolatility | J95: Medium* | K95: Medium*
B96: Impact of Volatility on Abatement Costs | F96: Medium* | G96: Medium* | H96: D_ETSVolImpact | J96: Medium* | K96: Medium*
B97: Carbon Tax Policy Risk | F97: 0.2 | G97: 0.2 | H97: D_ETSCTRisk | J97: 0.2 | K97: 0.2
B98: ETS: sector coverage
B99: power sector | C99: switch | F99: TRUE | G99: TRUE | J99: TRUE | K99: TRUE
B100: road transportation | F100: FALSE | G100: TRUE | J100: FALSE | K100: FALSE
B101: rail transportation | F101: FALSE | G101: TRUE | J101: FALSE | K101: FALSE
B102: domestic aviation | F102: FALSE | G102: TRUE | J102: FALSE | K102: FALSE
B103: domestic shipping | F103: FALSE | G103: TRUE | J103: FALSE | K103: FALSE
B104: residential | C104: switch | F104: FALSE | G104: TRUE | J104: FALSE | K104: FALSE
B105: food & forestry | F105: FALSE | G105: TRUE | J105: FALSE | K105: FALSE
...

Sheet Mitigation
A1: Variable | B1: Fuel | C1: Sector | D1: Param 1 | E1: Param 2 | F1: Param 3 | G1: Param 4 | H1: Description | I1: Unit | J1: Source | K1: Scenario 1: output code | Z1: Scenario 2: output code
A2: Mitigation module - price to fuel use (copy-pasteable, design 2, legacy CPAT sections)
A3: Scenario assumptions (one column group per scenario: code column + years; copy a whole group to add a scenario)
H4: Year | L4: =Settings!$C$7 | M4: =L4+1 | N4: =M4+1 | O4: =N4+1 | P4: =O4+1 | Q4: =P4+1 | R4: =Q4+1 | S4: =R4+1 | T4: =S4+1 | ... Y4: =X4+1 | AA4: =Settings!$C$7 | AB4: =AA4+1 | AC4: =AB4+1 | AD4: =AC4+1 | AE4: =AD4+1 | AF4: =AE4+1 | AG4: =AF4+1 | AH4: =AG4+1 | AI4: =AH4+1 | ... AN4: =AM4+1
H5: Scenario number (MTInputs column) | K5: 1 | L5: =K5 | M5: =L5 | N5: =M5 | O5: =N5 | P5: =O5 | Q5: =P5 | R5: =Q5 | S5: =R5 | ... Y5: =X5 | Z5: =K5+1 | AA5: =Z5 | AB5: =AA5 | AC5: =AB5 | AD5: =AC5 | AE5: =AD5 | AF5: =AE5 | AG5: =AF5 | AH5: =AG5 | ... AN5: =AM5
H6: Scenario name (from MTInputs) | L6: =INDEX(MTInputs!$J$6:$AZ$6,MATCH(L$5,MTInputs!$J$5:$AZ$5,0)) | AA6: =INDEX(MTInputs!$J$6:$AZ$6,MATCH(AA$5,MTInputs!$J$5:$AZ$5,0))
A7: gdp.pos.pct | H7: =INDEX(Variables!$B$5:$B$65,MATCH($A7,Variables!$A$5:$A$65,0))&IF($C7="",""," | "&INDEX(Mapping!$B$5:$B$25,MATCH($C7,Mapping!$A$5:$A$25,0))&" | "&INDEX(Mapping!$B$29:$B$38,MATCH($B7,Mapping!$A$29:$A$38,0))) | I7: =INDEX(Variables!$C$5:$C$65,MATCH($A7,Variables!$A$5:$A$65,0)) | J7: =INDEX(Variables!$E$5:$E$65,MATCH($A7,Variables!$A$5:$A$65,0)) | K7: =LOWER(Settings!$C$4)&".mit."&$A7&IF($C7="","","."&$C7&"."&$B7)&IF(INDEX(Variables!$D$5:$D$65,MATCH($A7,Variables!$A$5:$A$65,0))="","","."&INDEX(Variables!$D$5:$D$65,MATCH($A7,Variables!$A$5:$A$65,0)))&"."&K$5 | L7: =INDEX(WEO!$F$4:$AZ$1000,MATCH(Settings!$C$4&"|gdp_growth",WEO!$A$4:$A$1000,0),MATCH(L$4,WEO!$F$3:$AZ$3,0)) | M7: =INDEX(WEO!$F$4:$AZ$1000,MATCH(Settings!$C$4&"|gdp_growth",WEO!$A$4:$A$1000,0),MATCH(M$4,WEO!$F$3:$AZ$3,0)) | N7: =INDEX(WEO!$F$4:$AZ$1000,MATCH(Settings!$C$4&"|gdp_growth",WEO!$A$4:$A$1000,0),MATCH(N$4,WEO!$F$3:$AZ$3,0)) | O7: =INDEX(WEO!$F$4:$AZ$1000,MATCH(Settings!$C$4&"|gdp_growth",WEO!$A$4:$A$1000,0),MATCH(O$4,WEO!$F$3:$AZ$3,0)) | P7: =INDEX(WEO!$F$4:$AZ$1000,MATCH(Settings!$C$4&"|gdp_growth",WEO!$A$4:$A$1000,0),MATCH(P$4,WEO!$F$3:$AZ$3,0)) | Q7: =INDEX(WEO!$F$4:$AZ$1000,MATCH(Settings!$C$4&"|gdp_growth",WEO!$A$4:$A$1000,0),MATCH(Q$4,WEO!$F$3:$AZ$3,0)) | R7: =INDEX(WEO!$F$4:$AZ$1000,MATCH(Settings!$C$4&"|gdp_growth",WEO!$A$4:$A$1000,0),MATCH(R$4,WEO!$F$3:$AZ$3,0)) | S7: =INDEX(WEO!$F$4:$AZ$1000,MATCH(Settings!$C$4&"|gdp_growth",WEO!$A$4:$A$1000,0),MATCH(S$4,WEO!$F$3:$AZ$3,0)) | ... Y7: =INDEX(WEO!$F$4:$AZ$1000,MATCH(Settings!$C$4&"|gdp_growth",WEO!$A$4:$A$1000,0),MATCH(Y$4,WEO!$F$3:$AZ$3,0)) | Z7: =LOWER(Settings!$C$4)&".mit."&$A7&IF($C7="","","."&$C7&"."&$B7)&IF(INDEX(Variables!$D$5:$D$65,MATCH($A7,Variables!$A$5:$A$65,0))="","","."&INDEX(Variables!$D$5:$D$65,MATCH($A7,Variables!$A$5:$A$65,0)))&"."&Z$5 | AA7: =INDEX(WEO!$F$4:$AZ$1000,MATCH(Settings!$C$4&"|gdp_growth",WEO!$A$4:$A$1000,0),MATCH(AA$4,WEO!$F$3:$AZ$3,0)) | AB7: =INDEX(WEO!$F$4:$AZ$1000,MATCH(Settings!$C$4&"|gdp_growth",WEO!$A$4:$A$1000,0),MATCH(AB$4,WEO!$F$3:$AZ$3,0)) | AC7: =INDEX(WEO!$F$4:$AZ$1000,MATCH(Settings!$C$4&"|gdp_growth",WEO!$A$4:$A$1000,0),MATCH(AC$4,WEO!$F$3:$AZ$3,0)) | AD7: =INDEX(WEO!$F$4:$AZ$1000,MATCH(Settings!$C$4&"|gdp_growth",WEO!$A$4:$A$1000,0),MATCH(AD$4,WEO!$F$3:$AZ$3,0)) | AE7: =INDEX(WEO!$F$4:$AZ$1000,MATCH(Settings!$C$4&"|gdp_growth",WEO!$A$4:$A$1000,0),MATCH(AE$4,WEO!$F$3:$AZ$3,0)) | AF7: =INDEX(WEO!$F$4:$AZ$1000,MATCH(Settings!$C$4&"|gdp_growth",WEO!$A$4:$A$1000,0),MATCH(AF$4,WEO!$F$3:$AZ$3,0)) | AG7: =INDEX(WEO!$F$4:$AZ$1000,MATCH(Settings!$C$4&"|gdp_growth",WEO!$A$4:$A$1000,0),MATCH(AG$4,WEO!$F$3:$AZ$3,0)) | AH7: =INDEX(WEO!$F$4:$AZ$1000,MATCH(Settings!$C$4&"|gdp_growth",WEO!$A$4:$A$1000,0),MATCH(AH$4,WEO!$F$3:$AZ$3,0)) | ... AN7: =INDEX(WEO!$F$4:$AZ$1000,MATCH(Settings!$C$4&"|gdp_growth",WEO!$A$4:$A$1000,0),MATCH(AN$4,WEO!$F$3:$AZ$3,0))
A9: 1. Policies (scenario inputs from MTInputs by row and scenario number; policy paths) | D9: MTInputs row
A10: cptraj | H10: =INDEX(Variables!$B$5:$B$65,MATCH($A10,Variables!$A$5:$A$65,0))&IF($C10="",""," | "&INDEX(Mapping!$B$5:$B$25,MATCH($C10,Mapping!$A$5:$A$25,0))&" | "&INDEX(Mapping!$B$29:$B$38,MATCH($B10,Mapping!$A$29:$A$38,0))) | I10: =INDEX(Variables!$C$5:$C$65,MATCH($A10,Variables!$A$5:$A$65,0)) | J10: =INDEX(Variables!$E$5:$E$65,MATCH($A10,Variables!$A$5:$A$65,0)) | K10: =LOWER(Settings!$C$4)&".mit."&$A10&IF($C10="","","."&$C10&"."&$B10)&IF(INDEX(Variables!$D$5:$D$65,MATCH($A10,Variables!$A$5:$A$65,0))="","","."&INDEX(Variables!$D$5:$D$65,MATCH($A10,Variables!$A$5:$A$65,0)))&"."&K$5 | L10: =IF(L$4<L$12,0,L$13+(L$14-L$13)/MAX(L$15-L$12,1)*IF(OR(L$4<=L$15,L$16="Linear*"),L$4-L$12,L$15-L$12)) | M10: =IF(M$4<M$12,0,M$13+(M$14-M$13)/MAX(M$15-M$12,1)*IF(OR(M$4<=M$15,M$16="Linear*"),M$4-M$12,M$15-M$12)) | N10: =IF(N$4<N$12,0,N$13+(N$14-N$13)/MAX(N$15-N$12,1)*IF(OR(N$4<=N$15,N$16="Linear*"),N$4-N$12,N$15-N$12)) | O10: =IF(O$4<O$12,0,O$13+(O$14-O$13)/MAX(O$15-O$12,1)*IF(OR(O$4<=O$15,O$16="Linear*"),O$4-O$12,O$15-O$12)) | P10: =IF(P$4<P$12,0,P$13+(P$14-P$13)/MAX(P$15-P$12,1)*IF(OR(P$4<=P$15,P$16="Linear*"),P$4-P$12,P$15-P$12)) | Q10: =IF(Q$4<Q$12,0,Q$13+(Q$14-Q$13)/MAX(Q$15-Q$12,1)*IF(OR(Q$4<=Q$15,Q$16="Linear*"),Q$4-Q$12,Q$15-Q$12)) | R10: =IF(R$4<R$12,0,R$13+(R$14-R$13)/MAX(R$15-R$12,1)*IF(OR(R$4<=R$15,R$16="Linear*"),R$4-R$12,R$15-R$12)) | S10: =IF(S$4<S$12,0,S$13+(S$14-S$13)/MAX(S$15-S$12,1)*IF(OR(S$4<=S$15,S$16="Linear*"),S$4-S$12,S$15-S$12)) | ... Y10: =IF(Y$4<Y$12,0,Y$13+(Y$14-Y$13)/MAX(Y$15-Y$12,1)*IF(OR(Y$4<=Y$15,Y$16="Linear*"),Y$4-Y$12,Y$15-Y$12)) | Z10: =LOWER(Settings!$C$4)&".mit."&$A10&IF($C10="","","."&$C10&"."&$B10)&IF(INDEX(Variables!$D$5:$D$65,MATCH($A10,Variables!$A$5:$A$65,0))="","","."&INDEX(Variables!$D$5:$D$65,MATCH($A10,Variables!$A$5:$A$65,0)))&"."&Z$5 | AA10: =IF(AA$4<AA$12,0,AA$13+(AA$14-AA$13)/MAX(AA$15-AA$12,1)*IF(OR(AA$4<=AA$15,AA$16="Linear*"),AA$4-AA$12,AA$15-AA$12)) | AB10: =IF(AB$4<AB$12,0,AB$13+(AB$14-AB$13)/MAX(AB$15-AB$12,1)*IF(OR(AB$4<=AB$15,AB$16="Linear*"),AB$4-AB$12,AB$15-AB$12)) | AC10: =IF(AC$4<AC$12,0,AC$13+(AC$14-AC$13)/MAX(AC$15-AC$12,1)*IF(OR(AC$4<=AC$15,AC$16="Linear*"),AC$4-AC$12,AC$15-AC$12)) | AD10: =IF(AD$4<AD$12,0,AD$13+(AD$14-AD$13)/MAX(AD$15-AD$12,1)*IF(OR(AD$4<=AD$15,AD$16="Linear*"),AD$4-AD$12,AD$15-AD$12)) | AE10: =IF(AE$4<AE$12,0,AE$13+(AE$14-AE$13)/MAX(AE$15-AE$12,1)*IF(OR(AE$4<=AE$15,AE$16="Linear*"),AE$4-AE$12,AE$15-AE$12)) | AF10: =IF(AF$4<AF$12,0,AF$13+(AF$14-AF$13)/MAX(AF$15-AF$12,1)*IF(OR(AF$4<=AF$15,AF$16="Linear*"),AF$4-AF$12,AF$15-AF$12)) | AG10: =IF(AG$4<AG$12,0,AG$13+(AG$14-AG$13)/MAX(AG$15-AG$12,1)*IF(OR(AG$4<=AG$15,AG$16="Linear*"),AG$4-AG$12,AG$15-AG$12)) | AH10: =IF(AH$4<AH$12,0,AH$13+(AH$14-AH$13)/MAX(AH$15-AH$12,1)*IF(OR(AH$4<=AH$15,AH$16="Linear*"),AH$4-AH$12,AH$15-AH$12)) | ... AN10: =IF(AN$4<AN$12,0,AN$13+(AN$14-AN$13)/MAX(AN$15-AN$12,1)*IF(OR(AN$4<=AN$15,AN$16="Linear*"),AN$4-AN$12,AN$15-AN$12))
H11: Carbon tax (MTInputs rows 18-21, 265)
A12: CPIntro | D12: 18 | H12: =INDEX(Variables!$B$5:$B$65,MATCH($A12,Variables!$A$5:$A$65,0))&IF($C12="",""," | "&INDEX(Mapping!$B$5:$B$25,MATCH($C12,Mapping!$A$5:$A$25,0))&" | "&INDEX(Mapping!$B$29:$B$38,MATCH($B12,Mapping!$A$29:$A$38,0))) | I12: =INDEX(Variables!$C$5:$C$65,MATCH($A12,Variables!$A$5:$A$65,0)) | J12: =INDEX(Variables!$E$5:$E$65,MATCH($A12,Variables!$A$5:$A$65,0)) | K12: =LOWER(Settings!$C$4)&".mit."&$A12&IF($C12="","","."&$C12&"."&$B12)&IF(INDEX(Variables!$D$5:$D$65,MATCH($A12,Variables!$A$5:$A$65,0))="","","."&INDEX(Variables!$D$5:$D$65,MATCH($A12,Variables!$A$5:$A$65,0)))&"."&K$5 | L12: =INDEX(MTInputs!$J$1:$AZ$415,$D12,MATCH(L$5,MTInputs!$J$5:$AZ$5,0)) | M12: =INDEX(MTInputs!$J$1:$AZ$415,$D12,MATCH(M$5,MTInputs!$J$5:$AZ$5,0)) | N12: =INDEX(MTInputs!$J$1:$AZ$415,$D12,MATCH(N$5,MTInputs!$J$5:$AZ$5,0)) | O12: =INDEX(MTInputs!$J$1:$AZ$415,$D12,MATCH(O$5,MTInputs!$J$5:$AZ$5,0)) | P12: =INDEX(MTInputs!$J$1:$AZ$415,$D12,MATCH(P$5,MTInputs!$J$5:$AZ$5,0)) | Q12: =INDEX(MTInputs!$J$1:$AZ$415,$D12,MATCH(Q$5,MTInputs!$J$5:$AZ$5,0)) | R12: =INDEX(MTInputs!$J$1:$AZ$415,$D12,MATCH(R$5,MTInputs!$J$5:$AZ$5,0)) | S12: =INDEX(MTInputs!$J$1:$AZ$415,$D12,MATCH(S$5,MTInputs!$J$5:$AZ$5,0)) | ... Y12: =INDEX(MTInputs!$J$1:$AZ$415,$D12,MATCH(Y$5,MTInputs!$J$5:$AZ$5,0)) | Z12: =LOWER(Settings!$C$4)&".mit."&$A12&IF($C12="","","."&$C12&"."&$B12)&IF(INDEX(Variables!$D$5:$D$65,MATCH($A12,Variables!$A$5:$A$65,0))="","","."&INDEX(Variables!$D$5:$D$65,MATCH($A12,Variables!$A$5:$A$65,0)))&"."&Z$5 | AA12: =INDEX(MTInputs!$J$1:$AZ$415,$D12,MATCH(AA$5,MTInputs!$J$5:$AZ$5,0)) | AB12: =INDEX(MTInputs!$J$1:$AZ$415,$D12,MATCH(AB$5,MTInputs!$J$5:$AZ$5,0)) | AC12: =INDEX(MTInputs!$J$1:$AZ$415,$D12,MATCH(AC$5,MTInputs!$J$5:$AZ$5,0)) | AD12: =INDEX(MTInputs!$J$1:$AZ$415,$D12,MATCH(AD$5,MTInputs!$J$5:$AZ$5,0)) | AE12: =INDEX(MTInputs!$J$1:$AZ$415,$D12,MATCH(AE$5,MTInputs!$J$5:$AZ$5,0)) | AF12: =INDEX(MTInputs!$J$1:$AZ$415,$D12,MATCH(AF$5,MTInputs!$J$5:$AZ$5,0)) | AG12: =INDEX(MTInputs!$J$1:$AZ$415,$D12,MATCH(AG$5,MTInputs!$J$5:$AZ$5,0)) | AH12: =INDEX(MTInputs!$J$1:$AZ$415,$D12,MATCH(AH$5,MTInputs!$J$5:$AZ$5,0)) | ... AN12: =INDEX(MTInputs!$J$1:$AZ$415,$D12,MATCH(AN$5,MTInputs!$J$5:$AZ$5,0))
A13: CPLevelStart | D13: 19 | H13: =INDEX(Variables!$B$5:$B$65,MATCH($A13,Variables!$A$5:$A$65,0))&IF($C13="",""," | "&INDEX(Mapping!$B$5:$B$25,MATCH($C13,Mapping!$A$5:$A$25,0))&" | "&INDEX(Mapping!$B$29:$B$38,MATCH($B13,Mapping!$A$29:$A$38,0))) | I13: =INDEX(Variables!$C$5:$C$65,MATCH($A13,Variables!$A$5:$A$65,0)) | J13: =INDEX(Variables!$E$5:$E$65,MATCH($A13,Variables!$A$5:$A$65,0)) | K13: =LOWER(Settings!$C$4)&".mit."&$A13&IF($C13="","","."&$C13&"."&$B13)&IF(INDEX(Variables!$D$5:$D$65,MATCH($A13,Variables!$A$5:$A$65,0))="","","."&INDEX(Variables!$D$5:$D$65,MATCH($A13,Variables!$A$5:$A$65,0)))&"."&K$5 | L13: =INDEX(MTInputs!$J$1:$AZ$415,$D13,MATCH(L$5,MTInputs!$J$5:$AZ$5,0)) | M13: =INDEX(MTInputs!$J$1:$AZ$415,$D13,MATCH(M$5,MTInputs!$J$5:$AZ$5,0)) | N13: =INDEX(MTInputs!$J$1:$AZ$415,$D13,MATCH(N$5,MTInputs!$J$5:$AZ$5,0)) | O13: =INDEX(MTInputs!$J$1:$AZ$415,$D13,MATCH(O$5,MTInputs!$J$5:$AZ$5,0)) | P13: =INDEX(MTInputs!$J$1:$AZ$415,$D13,MATCH(P$5,MTInputs!$J$5:$AZ$5,0)) | Q13: =INDEX(MTInputs!$J$1:$AZ$415,$D13,MATCH(Q$5,MTInputs!$J$5:$AZ$5,0)) | R13: =INDEX(MTInputs!$J$1:$AZ$415,$D13,MATCH(R$5,MTInputs!$J$5:$AZ$5,0)) | S13: =INDEX(MTInputs!$J$1:$AZ$415,$D13,MATCH(S$5,MTInputs!$J$5:$AZ$5,0)) | ... Y13: =INDEX(MTInputs!$J$1:$AZ$415,$D13,MATCH(Y$5,MTInputs!$J$5:$AZ$5,0)) | Z13: =LOWER(Settings!$C$4)&".mit."&$A13&IF($C13="","","."&$C13&"."&$B13)&IF(INDEX(Variables!$D$5:$D$65,MATCH($A13,Variables!$A$5:$A$65,0))="","","."&INDEX(Variables!$D$5:$D$65,MATCH($A13,Variables!$A$5:$A$65,0)))&"."&Z$5 | AA13: =INDEX(MTInputs!$J$1:$AZ$415,$D13,MATCH(AA$5,MTInputs!$J$5:$AZ$5,0)) | AB13: =INDEX(MTInputs!$J$1:$AZ$415,$D13,MATCH(AB$5,MTInputs!$J$5:$AZ$5,0)) | AC13: =INDEX(MTInputs!$J$1:$AZ$415,$D13,MATCH(AC$5,MTInputs!$J$5:$AZ$5,0)) | AD13: =INDEX(MTInputs!$J$1:$AZ$415,$D13,MATCH(AD$5,MTInputs!$J$5:$AZ$5,0)) | AE13: =INDEX(MTInputs!$J$1:$AZ$415,$D13,MATCH(AE$5,MTInputs!$J$5:$AZ$5,0)) | AF13: =INDEX(MTInputs!$J$1:$AZ$415,$D13,MATCH(AF$5,MTInputs!$J$5:$AZ$5,0)) | AG13: =INDEX(MTInputs!$J$1:$AZ$415,$D13,MATCH(AG$5,MTInputs!$J$5:$AZ$5,0)) | AH13: =INDEX(MTInputs!$J$1:$AZ$415,$D13,MATCH(AH$5,MTInputs!$J$5:$AZ$5,0)) | ... AN13: =INDEX(MTInputs!$J$1:$AZ$415,$D13,MATCH(AN$5,MTInputs!$J$5:$AZ$5,0))
A14: CPLevelTarget | D14: 20 | H14: =INDEX(Variables!$B$5:$B$65,MATCH($A14,Variables!$A$5:$A$65,0))&IF($C14="",""," | "&INDEX(Mapping!$B$5:$B$25,MATCH($C14,Mapping!$A$5:$A$25,0))&" | "&INDEX(Mapping!$B$29:$B$38,MATCH($B14,Mapping!$A$29:$A$38,0))) | I14: =INDEX(Variables!$C$5:$C$65,MATCH($A14,Variables!$A$5:$A$65,0)) | J14: =INDEX(Variables!$E$5:$E$65,MATCH($A14,Variables!$A$5:$A$65,0)) | K14: =LOWER(Settings!$C$4)&".mit."&$A14&IF($C14="","","."&$C14&"."&$B14)&IF(INDEX(Variables!$D$5:$D$65,MATCH($A14,Variables!$A$5:$A$65,0))="","","."&INDEX(Variables!$D$5:$D$65,MATCH($A14,Variables!$A$5:$A$65,0)))&"."&K$5 | L14: =INDEX(MTInputs!$J$1:$AZ$415,$D14,MATCH(L$5,MTInputs!$J$5:$AZ$5,0)) | M14: =INDEX(MTInputs!$J$1:$AZ$415,$D14,MATCH(M$5,MTInputs!$J$5:$AZ$5,0)) | N14: =INDEX(MTInputs!$J$1:$AZ$415,$D14,MATCH(N$5,MTInputs!$J$5:$AZ$5,0)) | O14: =INDEX(MTInputs!$J$1:$AZ$415,$D14,MATCH(O$5,MTInputs!$J$5:$AZ$5,0)) | P14: =INDEX(MTInputs!$J$1:$AZ$415,$D14,MATCH(P$5,MTInputs!$J$5:$AZ$5,0)) | Q14: =INDEX(MTInputs!$J$1:$AZ$415,$D14,MATCH(Q$5,MTInputs!$J$5:$AZ$5,0)) | R14: =INDEX(MTInputs!$J$1:$AZ$415,$D14,MATCH(R$5,MTInputs!$J$5:$AZ$5,0)) | S14: =INDEX(MTInputs!$J$1:$AZ$415,$D14,MATCH(S$5,MTInputs!$J$5:$AZ$5,0)) | ... Y14: =INDEX(MTInputs!$J$1:$AZ$415,$D14,MATCH(Y$5,MTInputs!$J$5:$AZ$5,0)) | Z14: =LOWER(Settings!$C$4)&".mit."&$A14&IF($C14="","","."&$C14&"."&$B14)&IF(INDEX(Variables!$D$5:$D$65,MATCH($A14,Variables!$A$5:$A$65,0))="","","."&INDEX(Variables!$D$5:$D$65,MATCH($A14,Variables!$A$5:$A$65,0)))&"."&Z$5 | AA14: =INDEX(MTInputs!$J$1:$AZ$415,$D14,MATCH(AA$5,MTInputs!$J$5:$AZ$5,0)) | AB14: =INDEX(MTInputs!$J$1:$AZ$415,$D14,MATCH(AB$5,MTInputs!$J$5:$AZ$5,0)) | AC14: =INDEX(MTInputs!$J$1:$AZ$415,$D14,MATCH(AC$5,MTInputs!$J$5:$AZ$5,0)) | AD14: =INDEX(MTInputs!$J$1:$AZ$415,$D14,MATCH(AD$5,MTInputs!$J$5:$AZ$5,0)) | AE14: =INDEX(MTInputs!$J$1:$AZ$415,$D14,MATCH(AE$5,MTInputs!$J$5:$AZ$5,0)) | AF14: =INDEX(MTInputs!$J$1:$AZ$415,$D14,MATCH(AF$5,MTInputs!$J$5:$AZ$5,0)) | AG14: =INDEX(MTInputs!$J$1:$AZ$415,$D14,MATCH(AG$5,MTInputs!$J$5:$AZ$5,0)) | AH14: =INDEX(MTInputs!$J$1:$AZ$415,$D14,MATCH(AH$5,MTInputs!$J$5:$AZ$5,0)) | ... AN14: =INDEX(MTInputs!$J$1:$AZ$415,$D14,MATCH(AN$5,MTInputs!$J$5:$AZ$5,0))
A15: CPOutro | D15: 21 | H15: =INDEX(Variables!$B$5:$B$65,MATCH($A15,Variables!$A$5:$A$65,0))&IF($C15="",""," | "&INDEX(Mapping!$B$5:$B$25,MATCH($C15,Mapping!$A$5:$A$25,0))&" | "&INDEX(Mapping!$B$29:$B$38,MATCH($B15,Mapping!$A$29:$A$38,0))) | I15: =INDEX(Variables!$C$5:$C$65,MATCH($A15,Variables!$A$5:$A$65,0)) | J15: =INDEX(Variables!$E$5:$E$65,MATCH($A15,Variables!$A$5:$A$65,0)) | K15: =LOWER(Settings!$C$4)&".mit."&$A15&IF($C15="","","."&$C15&"."&$B15)&IF(INDEX(Variables!$D$5:$D$65,MATCH($A15,Variables!$A$5:$A$65,0))="","","."&INDEX(Variables!$D$5:$D$65,MATCH($A15,Variables!$A$5:$A$65,0)))&"."&K$5 | L15: =INDEX(MTInputs!$J$1:$AZ$415,$D15,MATCH(L$5,MTInputs!$J$5:$AZ$5,0)) | M15: =INDEX(MTInputs!$J$1:$AZ$415,$D15,MATCH(M$5,MTInputs!$J$5:$AZ$5,0)) | N15: =INDEX(MTInputs!$J$1:$AZ$415,$D15,MATCH(N$5,MTInputs!$J$5:$AZ$5,0)) | O15: =INDEX(MTInputs!$J$1:$AZ$415,$D15,MATCH(O$5,MTInputs!$J$5:$AZ$5,0)) | P15: =INDEX(MTInputs!$J$1:$AZ$415,$D15,MATCH(P$5,MTInputs!$J$5:$AZ$5,0)) | Q15: =INDEX(MTInputs!$J$1:$AZ$415,$D15,MATCH(Q$5,MTInputs!$J$5:$AZ$5,0)) | R15: =INDEX(MTInputs!$J$1:$AZ$415,$D15,MATCH(R$5,MTInputs!$J$5:$AZ$5,0)) | S15: =INDEX(MTInputs!$J$1:$AZ$415,$D15,MATCH(S$5,MTInputs!$J$5:$AZ$5,0)) | ... Y15: =INDEX(MTInputs!$J$1:$AZ$415,$D15,MATCH(Y$5,MTInputs!$J$5:$AZ$5,0)) | Z15: =LOWER(Settings!$C$4)&".mit."&$A15&IF($C15="","","."&$C15&"."&$B15)&IF(INDEX(Variables!$D$5:$D$65,MATCH($A15,Variables!$A$5:$A$65,0))="","","."&INDEX(Variables!$D$5:$D$65,MATCH($A15,Variables!$A$5:$A$65,0)))&"."&Z$5 | AA15: =INDEX(MTInputs!$J$1:$AZ$415,$D15,MATCH(AA$5,MTInputs!$J$5:$AZ$5,0)) | AB15: =INDEX(MTInputs!$J$1:$AZ$415,$D15,MATCH(AB$5,MTInputs!$J$5:$AZ$5,0)) | AC15: =INDEX(MTInputs!$J$1:$AZ$415,$D15,MATCH(AC$5,MTInputs!$J$5:$AZ$5,0)) | AD15: =INDEX(MTInputs!$J$1:$AZ$415,$D15,MATCH(AD$5,MTInputs!$J$5:$AZ$5,0)) | AE15: =INDEX(MTInputs!$J$1:$AZ$415,$D15,MATCH(AE$5,MTInputs!$J$5:$AZ$5,0)) | AF15: =INDEX(MTInputs!$J$1:$AZ$415,$D15,MATCH(AF$5,MTInputs!$J$5:$AZ$5,0)) | AG15: =INDEX(MTInputs!$J$1:$AZ$415,$D15,MATCH(AG$5,MTInputs!$J$5:$AZ$5,0)) | AH15: =INDEX(MTInputs!$J$1:$AZ$415,$D15,MATCH(AH$5,MTInputs!$J$5:$AZ$5,0)) | ... AN15: =INDEX(MTInputs!$J$1:$AZ$415,$D15,MATCH(AN$5,MTInputs!$J$5:$AZ$5,0))
A16: ExtendCarbonPriceBeyondOutro | D16: 265 | H16: =INDEX(Variables!$B$5:$B$65,MATCH($A16,Variables!$A$5:$A$65,0))&IF($C16="",""," | "&INDEX(Mapping!$B$5:$B$25,MATCH($C16,Mapping!$A$5:$A$25,0))&" | "&INDEX(Mapping!$B$29:$B$38,MATCH($B16,Mapping!$A$29:$A$38,0))) | I16: =INDEX(Variables!$C$5:$C$65,MATCH($A16,Variables!$A$5:$A$65,0)) | J16: =INDEX(Variables!$E$5:$E$65,MATCH($A16,Variables!$A$5:$A$65,0)) | K16: =LOWER(Settings!$C$4)&".mit."&$A16&IF($C16="","","."&$C16&"."&$B16)&IF(INDEX(Variables!$D$5:$D$65,MATCH($A16,Variables!$A$5:$A$65,0))="","","."&INDEX(Variables!$D$5:$D$65,MATCH($A16,Variables!$A$5:$A$65,0)))&"."&K$5 | L16: =INDEX(MTInputs!$J$1:$AZ$415,$D16,MATCH(L$5,MTInputs!$J$5:$AZ$5,0)) | M16: =INDEX(MTInputs!$J$1:$AZ$415,$D16,MATCH(M$5,MTInputs!$J$5:$AZ$5,0)) | N16: =INDEX(MTInputs!$J$1:$AZ$415,$D16,MATCH(N$5,MTInputs!$J$5:$AZ$5,0)) | O16: =INDEX(MTInputs!$J$1:$AZ$415,$D16,MATCH(O$5,MTInputs!$J$5:$AZ$5,0)) | P16: =INDEX(MTInputs!$J$1:$AZ$415,$D16,MATCH(P$5,MTInputs!$J$5:$AZ$5,0)) | Q16: =INDEX(MTInputs!$J$1:$AZ$415,$D16,MATCH(Q$5,MTInputs!$J$5:$AZ$5,0)) | R16: =INDEX(MTInputs!$J$1:$AZ$415,$D16,MATCH(R$5,MTInputs!$J$5:$AZ$5,0)) | S16: =INDEX(MTInputs!$J$1:$AZ$415,$D16,MATCH(S$5,MTInputs!$J$5:$AZ$5,0)) | ... Y16: =INDEX(MTInputs!$J$1:$AZ$415,$D16,MATCH(Y$5,MTInputs!$J$5:$AZ$5,0)) | Z16: =LOWER(Settings!$C$4)&".mit."&$A16&IF($C16="","","."&$C16&"."&$B16)&IF(INDEX(Variables!$D$5:$D$65,MATCH($A16,Variables!$A$5:$A$65,0))="","","."&INDEX(Variables!$D$5:$D$65,MATCH($A16,Variables!$A$5:$A$65,0)))&"."&Z$5 | AA16: =INDEX(MTInputs!$J$1:$AZ$415,$D16,MATCH(AA$5,MTInputs!$J$5:$AZ$5,0)) | AB16: =INDEX(MTInputs!$J$1:$AZ$415,$D16,MATCH(AB$5,MTInputs!$J$5:$AZ$5,0)) | AC16: =INDEX(MTInputs!$J$1:$AZ$415,$D16,MATCH(AC$5,MTInputs!$J$5:$AZ$5,0)) | AD16: =INDEX(MTInputs!$J$1:$AZ$415,$D16,MATCH(AD$5,MTInputs!$J$5:$AZ$5,0)) | AE16: =INDEX(MTInputs!$J$1:$AZ$415,$D16,MATCH(AE$5,MTInputs!$J$5:$AZ$5,0)) | AF16: =INDEX(MTInputs!$J$1:$AZ$415,$D16,MATCH(AF$5,MTInputs!$J$5:$AZ$5,0)) | AG16: =INDEX(MTInputs!$J$1:$AZ$415,$D16,MATCH(AG$5,MTInputs!$J$5:$AZ$5,0)) | AH16: =INDEX(MTInputs!$J$1:$AZ$415,$D16,MATCH(AH$5,MTInputs!$J$5:$AZ$5,0)) | ... AN16: =INDEX(MTInputs!$J$1:$AZ$415,$D16,MATCH(AN$5,MTInputs!$J$5:$AZ$5,0))
H17: Carbon tax coverage: fuels (MTInputs rows 23-29)
A18: ctcov | B18: coa | C18: all | D18: 23 | H18: =INDEX(Variables!$B$5:$B$65,MATCH($A18,Variables!$A$5:$A$65,0))&IF($C18="",""," | "&INDEX(Mapping!$B$5:$B$25,MATCH($C18,Mapping!$A$5:$A$25,0))&" | "&INDEX(Mapping!$B$29:$B$38,MATCH($B18,Mapping!$A$29:$A$38,0))) | I18: =INDEX(Variables!$C$5:$C$65,MATCH($A18,Variables!$A$5:$A$65,0)) | J18: =INDEX(Variables!$E$5:$E$65,MATCH($A18,Variables!$A$5:$A$65,0)) | K18: =LOWER(Settings!$C$4)&".mit."&$A18&IF($C18="","","."&$C18&"."&$B18)&IF(INDEX(Variables!$D$5:$D$65,MATCH($A18,Variables!$A$5:$A$65,0))="","","."&INDEX(Variables!$D$5:$D$65,MATCH($A18,Variables!$A$5:$A$65,0)))&"."&K$5 | L18: =INDEX(MTInputs!$J$1:$AZ$415,$D18,MATCH(L$5,MTInputs!$J$5:$AZ$5,0)) | M18: =INDEX(MTInputs!$J$1:$AZ$415,$D18,MATCH(M$5,MTInputs!$J$5:$AZ$5,0)) | N18: =INDEX(MTInputs!$J$1:$AZ$415,$D18,MATCH(N$5,MTInputs!$J$5:$AZ$5,0)) | O18: =INDEX(MTInputs!$J$1:$AZ$415,$D18,MATCH(O$5,MTInputs!$J$5:$AZ$5,0)) | P18: =INDEX(MTInputs!$J$1:$AZ$415,$D18,MATCH(P$5,MTInputs!$J$5:$AZ$5,0)) | Q18: =INDEX(MTInputs!$J$1:$AZ$415,$D18,MATCH(Q$5,MTInputs!$J$5:$AZ$5,0)) | R18: =INDEX(MTInputs!$J$1:$AZ$415,$D18,MATCH(R$5,MTInputs!$J$5:$AZ$5,0)) | S18: =INDEX(MTInputs!$J$1:$AZ$415,$D18,MATCH(S$5,MTInputs!$J$5:$AZ$5,0)) | ... Y18: =INDEX(MTInputs!$J$1:$AZ$415,$D18,MATCH(Y$5,MTInputs!$J$5:$AZ$5,0)) | Z18: =LOWER(Settings!$C$4)&".mit."&$A18&IF($C18="","","."&$C18&"."&$B18)&IF(INDEX(Variables!$D$5:$D$65,MATCH($A18,Variables!$A$5:$A$65,0))="","","."&INDEX(Variables!$D$5:$D$65,MATCH($A18,Variables!$A$5:$A$65,0)))&"."&Z$5 | AA18: =INDEX(MTInputs!$J$1:$AZ$415,$D18,MATCH(AA$5,MTInputs!$J$5:$AZ$5,0)) | AB18: =INDEX(MTInputs!$J$1:$AZ$415,$D18,MATCH(AB$5,MTInputs!$J$5:$AZ$5,0)) | AC18: =INDEX(MTInputs!$J$1:$AZ$415,$D18,MATCH(AC$5,MTInputs!$J$5:$AZ$5,0)) | AD18: =INDEX(MTInputs!$J$1:$AZ$415,$D18,MATCH(AD$5,MTInputs!$J$5:$AZ$5,0)) | AE18: =INDEX(MTInputs!$J$1:$AZ$415,$D18,MATCH(AE$5,MTInputs!$J$5:$AZ$5,0)) | AF18: =INDEX(MTInputs!$J$1:$AZ$415,$D18,MATCH(AF$5,MTInputs!$J$5:$AZ$5,0)) | AG18: =INDEX(MTInputs!$J$1:$AZ$415,$D18,MATCH(AG$5,MTInputs!$J$5:$AZ$5,0)) | AH18: =INDEX(MTInputs!$J$1:$AZ$415,$D18,MATCH(AH$5,MTInputs!$J$5:$AZ$5,0)) | ... AN18: =INDEX(MTInputs!$J$1:$AZ$415,$D18,MATCH(AN$5,MTInputs!$J$5:$AZ$5,0))
A19: ctcov | B19: nga | C19: all | D19: 24 | H19: =INDEX(Variables!$B$5:$B$65,MATCH($A19,Variables!$A$5:$A$65,0))&IF($C19="",""," | "&INDEX(Mapping!$B$5:$B$25,MATCH($C19,Mapping!$A$5:$A$25,0))&" | "&INDEX(Mapping!$B$29:$B$38,MATCH($B19,Mapping!$A$29:$A$38,0))) | I19: =INDEX(Variables!$C$5:$C$65,MATCH($A19,Variables!$A$5:$A$65,0)) | J19: =INDEX(Variables!$E$5:$E$65,MATCH($A19,Variables!$A$5:$A$65,0)) | K19: =LOWER(Settings!$C$4)&".mit."&$A19&IF($C19="","","."&$C19&"."&$B19)&IF(INDEX(Variables!$D$5:$D$65,MATCH($A19,Variables!$A$5:$A$65,0))="","","."&INDEX(Variables!$D$5:$D$65,MATCH($A19,Variables!$A$5:$A$65,0)))&"."&K$5 | L19: =INDEX(MTInputs!$J$1:$AZ$415,$D19,MATCH(L$5,MTInputs!$J$5:$AZ$5,0)) | M19: =INDEX(MTInputs!$J$1:$AZ$415,$D19,MATCH(M$5,MTInputs!$J$5:$AZ$5,0)) | N19: =INDEX(MTInputs!$J$1:$AZ$415,$D19,MATCH(N$5,MTInputs!$J$5:$AZ$5,0)) | O19: =INDEX(MTInputs!$J$1:$AZ$415,$D19,MATCH(O$5,MTInputs!$J$5:$AZ$5,0)) | P19: =INDEX(MTInputs!$J$1:$AZ$415,$D19,MATCH(P$5,MTInputs!$J$5:$AZ$5,0)) | Q19: =INDEX(MTInputs!$J$1:$AZ$415,$D19,MATCH(Q$5,MTInputs!$J$5:$AZ$5,0)) | R19: =INDEX(MTInputs!$J$1:$AZ$415,$D19,MATCH(R$5,MTInputs!$J$5:$AZ$5,0)) | S19: =INDEX(MTInputs!$J$1:$AZ$415,$D19,MATCH(S$5,MTInputs!$J$5:$AZ$5,0)) | ... Y19: =INDEX(MTInputs!$J$1:$AZ$415,$D19,MATCH(Y$5,MTInputs!$J$5:$AZ$5,0)) | Z19: =LOWER(Settings!$C$4)&".mit."&$A19&IF($C19="","","."&$C19&"."&$B19)&IF(INDEX(Variables!$D$5:$D$65,MATCH($A19,Variables!$A$5:$A$65,0))="","","."&INDEX(Variables!$D$5:$D$65,MATCH($A19,Variables!$A$5:$A$65,0)))&"."&Z$5 | AA19: =INDEX(MTInputs!$J$1:$AZ$415,$D19,MATCH(AA$5,MTInputs!$J$5:$AZ$5,0)) | AB19: =INDEX(MTInputs!$J$1:$AZ$415,$D19,MATCH(AB$5,MTInputs!$J$5:$AZ$5,0)) | AC19: =INDEX(MTInputs!$J$1:$AZ$415,$D19,MATCH(AC$5,MTInputs!$J$5:$AZ$5,0)) | AD19: =INDEX(MTInputs!$J$1:$AZ$415,$D19,MATCH(AD$5,MTInputs!$J$5:$AZ$5,0)) | AE19: =INDEX(MTInputs!$J$1:$AZ$415,$D19,MATCH(AE$5,MTInputs!$J$5:$AZ$5,0)) | AF19: =INDEX(MTInputs!$J$1:$AZ$415,$D19,MATCH(AF$5,MTInputs!$J$5:$AZ$5,0)) | AG19: =INDEX(MTInputs!$J$1:$AZ$415,$D19,MATCH(AG$5,MTInputs!$J$5:$AZ$5,0)) | AH19: =INDEX(MTInputs!$J$1:$AZ$415,$D19,MATCH(AH$5,MTInputs!$J$5:$AZ$5,0)) | ... AN19: =INDEX(MTInputs!$J$1:$AZ$415,$D19,MATCH(AN$5,MTInputs!$J$5:$AZ$5,0))
A20: ctcov | B20: gso | C20: all | D20: 25 | H20: =INDEX(Variables!$B$5:$B$65,MATCH($A20,Variables!$A$5:$A$65,0))&IF($C20="",""," | "&INDEX(Mapping!$B$5:$B$25,MATCH($C20,Mapping!$A$5:$A$25,0))&" | "&INDEX(Mapping!$B$29:$B$38,MATCH($B20,Mapping!$A$29:$A$38,0))) | I20: =INDEX(Variables!$C$5:$C$65,MATCH($A20,Variables!$A$5:$A$65,0)) | J20: =INDEX(Variables!$E$5:$E$65,MATCH($A20,Variables!$A$5:$A$65,0)) | K20: =LOWER(Settings!$C$4)&".mit."&$A20&IF($C20="","","."&$C20&"."&$B20)&IF(INDEX(Variables!$D$5:$D$65,MATCH($A20,Variables!$A$5:$A$65,0))="","","."&INDEX(Variables!$D$5:$D$65,MATCH($A20,Variables!$A$5:$A$65,0)))&"."&K$5 | L20: =INDEX(MTInputs!$J$1:$AZ$415,$D20,MATCH(L$5,MTInputs!$J$5:$AZ$5,0)) | M20: =INDEX(MTInputs!$J$1:$AZ$415,$D20,MATCH(M$5,MTInputs!$J$5:$AZ$5,0)) | N20: =INDEX(MTInputs!$J$1:$AZ$415,$D20,MATCH(N$5,MTInputs!$J$5:$AZ$5,0)) | O20: =INDEX(MTInputs!$J$1:$AZ$415,$D20,MATCH(O$5,MTInputs!$J$5:$AZ$5,0)) | P20: =INDEX(MTInputs!$J$1:$AZ$415,$D20,MATCH(P$5,MTInputs!$J$5:$AZ$5,0)) | Q20: =INDEX(MTInputs!$J$1:$AZ$415,$D20,MATCH(Q$5,MTInputs!$J$5:$AZ$5,0)) | R20: =INDEX(MTInputs!$J$1:$AZ$415,$D20,MATCH(R$5,MTInputs!$J$5:$AZ$5,0)) | S20: =INDEX(MTInputs!$J$1:$AZ$415,$D20,MATCH(S$5,MTInputs!$J$5:$AZ$5,0)) | ... Y20: =INDEX(MTInputs!$J$1:$AZ$415,$D20,MATCH(Y$5,MTInputs!$J$5:$AZ$5,0)) | Z20: =LOWER(Settings!$C$4)&".mit."&$A20&IF($C20="","","."&$C20&"."&$B20)&IF(INDEX(Variables!$D$5:$D$65,MATCH($A20,Variables!$A$5:$A$65,0))="","","."&INDEX(Variables!$D$5:$D$65,MATCH($A20,Variables!$A$5:$A$65,0)))&"."&Z$5 | AA20: =INDEX(MTInputs!$J$1:$AZ$415,$D20,MATCH(AA$5,MTInputs!$J$5:$AZ$5,0)) | AB20: =INDEX(MTInputs!$J$1:$AZ$415,$D20,MATCH(AB$5,MTInputs!$J$5:$AZ$5,0)) | AC20: =INDEX(MTInputs!$J$1:$AZ$415,$D20,MATCH(AC$5,MTInputs!$J$5:$AZ$5,0)) | AD20: =INDEX(MTInputs!$J$1:$AZ$415,$D20,MATCH(AD$5,MTInputs!$J$5:$AZ$5,0)) | AE20: =INDEX(MTInputs!$J$1:$AZ$415,$D20,MATCH(AE$5,MTInputs!$J$5:$AZ$5,0)) | AF20: =INDEX(MTInputs!$J$1:$AZ$415,$D20,MATCH(AF$5,MTInputs!$J$5:$AZ$5,0)) | AG20: =INDEX(MTInputs!$J$1:$AZ$415,$D20,MATCH(AG$5,MTInputs!$J$5:$AZ$5,0)) | AH20: =INDEX(MTInputs!$J$1:$AZ$415,$D20,MATCH(AH$5,MTInputs!$J$5:$AZ$5,0)) | ... AN20: =INDEX(MTInputs!$J$1:$AZ$415,$D20,MATCH(AN$5,MTInputs!$J$5:$AZ$5,0))
A21: ctcov | B21: die | C21: all | D21: 26 | H21: =INDEX(Variables!$B$5:$B$65,MATCH($A21,Variables!$A$5:$A$65,0))&IF($C21="",""," | "&INDEX(Mapping!$B$5:$B$25,MATCH($C21,Mapping!$A$5:$A$25,0))&" | "&INDEX(Mapping!$B$29:$B$38,MATCH($B21,Mapping!$A$29:$A$38,0))) | I21: =INDEX(Variables!$C$5:$C$65,MATCH($A21,Variables!$A$5:$A$65,0)) | J21: =INDEX(Variables!$E$5:$E$65,MATCH($A21,Variables!$A$5:$A$65,0)) | K21: =LOWER(Settings!$C$4)&".mit."&$A21&IF($C21="","","."&$C21&"."&$B21)&IF(INDEX(Variables!$D$5:$D$65,MATCH($A21,Variables!$A$5:$A$65,0))="","","."&INDEX(Variables!$D$5:$D$65,MATCH($A21,Variables!$A$5:$A$65,0)))&"."&K$5 | L21: =INDEX(MTInputs!$J$1:$AZ$415,$D21,MATCH(L$5,MTInputs!$J$5:$AZ$5,0)) | M21: =INDEX(MTInputs!$J$1:$AZ$415,$D21,MATCH(M$5,MTInputs!$J$5:$AZ$5,0)) | N21: =INDEX(MTInputs!$J$1:$AZ$415,$D21,MATCH(N$5,MTInputs!$J$5:$AZ$5,0)) | O21: =INDEX(MTInputs!$J$1:$AZ$415,$D21,MATCH(O$5,MTInputs!$J$5:$AZ$5,0)) | P21: =INDEX(MTInputs!$J$1:$AZ$415,$D21,MATCH(P$5,MTInputs!$J$5:$AZ$5,0)) | Q21: =INDEX(MTInputs!$J$1:$AZ$415,$D21,MATCH(Q$5,MTInputs!$J$5:$AZ$5,0)) | R21: =INDEX(MTInputs!$J$1:$AZ$415,$D21,MATCH(R$5,MTInputs!$J$5:$AZ$5,0)) | S21: =INDEX(MTInputs!$J$1:$AZ$415,$D21,MATCH(S$5,MTInputs!$J$5:$AZ$5,0)) | ... Y21: =INDEX(MTInputs!$J$1:$AZ$415,$D21,MATCH(Y$5,MTInputs!$J$5:$AZ$5,0)) | Z21: =LOWER(Settings!$C$4)&".mit."&$A21&IF($C21="","","."&$C21&"."&$B21)&IF(INDEX(Variables!$D$5:$D$65,MATCH($A21,Variables!$A$5:$A$65,0))="","","."&INDEX(Variables!$D$5:$D$65,MATCH($A21,Variables!$A$5:$A$65,0)))&"."&Z$5 | AA21: =INDEX(MTInputs!$J$1:$AZ$415,$D21,MATCH(AA$5,MTInputs!$J$5:$AZ$5,0)) | AB21: =INDEX(MTInputs!$J$1:$AZ$415,$D21,MATCH(AB$5,MTInputs!$J$5:$AZ$5,0)) | AC21: =INDEX(MTInputs!$J$1:$AZ$415,$D21,MATCH(AC$5,MTInputs!$J$5:$AZ$5,0)) | AD21: =INDEX(MTInputs!$J$1:$AZ$415,$D21,MATCH(AD$5,MTInputs!$J$5:$AZ$5,0)) | AE21: =INDEX(MTInputs!$J$1:$AZ$415,$D21,MATCH(AE$5,MTInputs!$J$5:$AZ$5,0)) | AF21: =INDEX(MTInputs!$J$1:$AZ$415,$D21,MATCH(AF$5,MTInputs!$J$5:$AZ$5,0)) | AG21: =INDEX(MTInputs!$J$1:$AZ$415,$D21,MATCH(AG$5,MTInputs!$J$5:$AZ$5,0)) | AH21: =INDEX(MTInputs!$J$1:$AZ$415,$D21,MATCH(AH$5,MTInputs!$J$5:$AZ$5,0)) | ... AN21: =INDEX(MTInputs!$J$1:$AZ$415,$D21,MATCH(AN$5,MTInputs!$J$5:$AZ$5,0))
A22: ctcov | B22: lpg | C22: all | D22: 27 | H22: =INDEX(Variables!$B$5:$B$65,MATCH($A22,Variables!$A$5:$A$65,0))&IF($C22="",""," | "&INDEX(Mapping!$B$5:$B$25,MATCH($C22,Mapping!$A$5:$A$25,0))&" | "&INDEX(Mapping!$B$29:$B$38,MATCH($B22,Mapping!$A$29:$A$38,0))) | I22: =INDEX(Variables!$C$5:$C$65,MATCH($A22,Variables!$A$5:$A$65,0)) | J22: =INDEX(Variables!$E$5:$E$65,MATCH($A22,Variables!$A$5:$A$65,0)) | K22: =LOWER(Settings!$C$4)&".mit."&$A22&IF($C22="","","."&$C22&"."&$B22)&IF(INDEX(Variables!$D$5:$D$65,MATCH($A22,Variables!$A$5:$A$65,0))="","","."&INDEX(Variables!$D$5:$D$65,MATCH($A22,Variables!$A$5:$A$65,0)))&"."&K$5 | L22: =INDEX(MTInputs!$J$1:$AZ$415,$D22,MATCH(L$5,MTInputs!$J$5:$AZ$5,0)) | M22: =INDEX(MTInputs!$J$1:$AZ$415,$D22,MATCH(M$5,MTInputs!$J$5:$AZ$5,0)) | N22: =INDEX(MTInputs!$J$1:$AZ$415,$D22,MATCH(N$5,MTInputs!$J$5:$AZ$5,0)) | O22: =INDEX(MTInputs!$J$1:$AZ$415,$D22,MATCH(O$5,MTInputs!$J$5:$AZ$5,0)) | P22: =INDEX(MTInputs!$J$1:$AZ$415,$D22,MATCH(P$5,MTInputs!$J$5:$AZ$5,0)) | Q22: =INDEX(MTInputs!$J$1:$AZ$415,$D22,MATCH(Q$5,MTInputs!$J$5:$AZ$5,0)) | R22: =INDEX(MTInputs!$J$1:$AZ$415,$D22,MATCH(R$5,MTInputs!$J$5:$AZ$5,0)) | S22: =INDEX(MTInputs!$J$1:$AZ$415,$D22,MATCH(S$5,MTInputs!$J$5:$AZ$5,0)) | ... Y22: =INDEX(MTInputs!$J$1:$AZ$415,$D22,MATCH(Y$5,MTInputs!$J$5:$AZ$5,0)) | Z22: =LOWER(Settings!$C$4)&".mit."&$A22&IF($C22="","","."&$C22&"."&$B22)&IF(INDEX(Variables!$D$5:$D$65,MATCH($A22,Variables!$A$5:$A$65,0))="","","."&INDEX(Variables!$D$5:$D$65,MATCH($A22,Variables!$A$5:$A$65,0)))&"."&Z$5 | AA22: =INDEX(MTInputs!$J$1:$AZ$415,$D22,MATCH(AA$5,MTInputs!$J$5:$AZ$5,0)) | AB22: =INDEX(MTInputs!$J$1:$AZ$415,$D22,MATCH(AB$5,MTInputs!$J$5:$AZ$5,0)) | AC22: =INDEX(MTInputs!$J$1:$AZ$415,$D22,MATCH(AC$5,MTInputs!$J$5:$AZ$5,0)) | AD22: =INDEX(MTInputs!$J$1:$AZ$415,$D22,MATCH(AD$5,MTInputs!$J$5:$AZ$5,0)) | AE22: =INDEX(MTInputs!$J$1:$AZ$415,$D22,MATCH(AE$5,MTInputs!$J$5:$AZ$5,0)) | AF22: =INDEX(MTInputs!$J$1:$AZ$415,$D22,MATCH(AF$5,MTInputs!$J$5:$AZ$5,0)) | AG22: =INDEX(MTInputs!$J$1:$AZ$415,$D22,MATCH(AG$5,MTInputs!$J$5:$AZ$5,0)) | AH22: =INDEX(MTInputs!$J$1:$AZ$415,$D22,MATCH(AH$5,MTInputs!$J$5:$AZ$5,0)) | ... AN22: =INDEX(MTInputs!$J$1:$AZ$415,$D22,MATCH(AN$5,MTInputs!$J$5:$AZ$5,0))
A23: ctcov | B23: ker | C23: all | D23: 28 | H23: =INDEX(Variables!$B$5:$B$65,MATCH($A23,Variables!$A$5:$A$65,0))&IF($C23="",""," | "&INDEX(Mapping!$B$5:$B$25,MATCH($C23,Mapping!$A$5:$A$25,0))&" | "&INDEX(Mapping!$B$29:$B$38,MATCH($B23,Mapping!$A$29:$A$38,0))) | I23: =INDEX(Variables!$C$5:$C$65,MATCH($A23,Variables!$A$5:$A$65,0)) | J23: =INDEX(Variables!$E$5:$E$65,MATCH($A23,Variables!$A$5:$A$65,0)) | K23: =LOWER(Settings!$C$4)&".mit."&$A23&IF($C23="","","."&$C23&"."&$B23)&IF(INDEX(Variables!$D$5:$D$65,MATCH($A23,Variables!$A$5:$A$65,0))="","","."&INDEX(Variables!$D$5:$D$65,MATCH($A23,Variables!$A$5:$A$65,0)))&"."&K$5 | L23: =INDEX(MTInputs!$J$1:$AZ$415,$D23,MATCH(L$5,MTInputs!$J$5:$AZ$5,0)) | M23: =INDEX(MTInputs!$J$1:$AZ$415,$D23,MATCH(M$5,MTInputs!$J$5:$AZ$5,0)) | N23: =INDEX(MTInputs!$J$1:$AZ$415,$D23,MATCH(N$5,MTInputs!$J$5:$AZ$5,0)) | O23: =INDEX(MTInputs!$J$1:$AZ$415,$D23,MATCH(O$5,MTInputs!$J$5:$AZ$5,0)) | P23: =INDEX(MTInputs!$J$1:$AZ$415,$D23,MATCH(P$5,MTInputs!$J$5:$AZ$5,0)) | Q23: =INDEX(MTInputs!$J$1:$AZ$415,$D23,MATCH(Q$5,MTInputs!$J$5:$AZ$5,0)) | R23: =INDEX(MTInputs!$J$1:$AZ$415,$D23,MATCH(R$5,MTInputs!$J$5:$AZ$5,0)) | S23: =INDEX(MTInputs!$J$1:$AZ$415,$D23,MATCH(S$5,MTInputs!$J$5:$AZ$5,0)) | ... Y23: =INDEX(MTInputs!$J$1:$AZ$415,$D23,MATCH(Y$5,MTInputs!$J$5:$AZ$5,0)) | Z23: =LOWER(Settings!$C$4)&".mit."&$A23&IF($C23="","","."&$C23&"."&$B23)&IF(INDEX(Variables!$D$5:$D$65,MATCH($A23,Variables!$A$5:$A$65,0))="","","."&INDEX(Variables!$D$5:$D$65,MATCH($A23,Variables!$A$5:$A$65,0)))&"."&Z$5 | AA23: =INDEX(MTInputs!$J$1:$AZ$415,$D23,MATCH(AA$5,MTInputs!$J$5:$AZ$5,0)) | AB23: =INDEX(MTInputs!$J$1:$AZ$415,$D23,MATCH(AB$5,MTInputs!$J$5:$AZ$5,0)) | AC23: =INDEX(MTInputs!$J$1:$AZ$415,$D23,MATCH(AC$5,MTInputs!$J$5:$AZ$5,0)) | AD23: =INDEX(MTInputs!$J$1:$AZ$415,$D23,MATCH(AD$5,MTInputs!$J$5:$AZ$5,0)) | AE23: =INDEX(MTInputs!$J$1:$AZ$415,$D23,MATCH(AE$5,MTInputs!$J$5:$AZ$5,0)) | AF23: =INDEX(MTInputs!$J$1:$AZ$415,$D23,MATCH(AF$5,MTInputs!$J$5:$AZ$5,0)) | AG23: =INDEX(MTInputs!$J$1:$AZ$415,$D23,MATCH(AG$5,MTInputs!$J$5:$AZ$5,0)) | AH23: =INDEX(MTInputs!$J$1:$AZ$415,$D23,MATCH(AH$5,MTInputs!$J$5:$AZ$5,0)) | ... AN23: =INDEX(MTInputs!$J$1:$AZ$415,$D23,MATCH(AN$5,MTInputs!$J$5:$AZ$5,0))
A24: ctcov | B24: oop | C24: all | D24: 29 | H24: =INDEX(Variables!$B$5:$B$65,MATCH($A24,Variables!$A$5:$A$65,0))&IF($C24="",""," | "&INDEX(Mapping!$B$5:$B$25,MATCH($C24,Mapping!$A$5:$A$25,0))&" | "&INDEX(Mapping!$B$29:$B$38,MATCH($B24,Mapping!$A$29:$A$38,0))) | I24: =INDEX(Variables!$C$5:$C$65,MATCH($A24,Variables!$A$5:$A$65,0)) | J24: =INDEX(Variables!$E$5:$E$65,MATCH($A24,Variables!$A$5:$A$65,0)) | K24: =LOWER(Settings!$C$4)&".mit."&$A24&IF($C24="","","."&$C24&"."&$B24)&IF(INDEX(Variables!$D$5:$D$65,MATCH($A24,Variables!$A$5:$A$65,0))="","","."&INDEX(Variables!$D$5:$D$65,MATCH($A24,Variables!$A$5:$A$65,0)))&"."&K$5 | L24: =INDEX(MTInputs!$J$1:$AZ$415,$D24,MATCH(L$5,MTInputs!$J$5:$AZ$5,0)) | M24: =INDEX(MTInputs!$J$1:$AZ$415,$D24,MATCH(M$5,MTInputs!$J$5:$AZ$5,0)) | N24: =INDEX(MTInputs!$J$1:$AZ$415,$D24,MATCH(N$5,MTInputs!$J$5:$AZ$5,0)) | O24: =INDEX(MTInputs!$J$1:$AZ$415,$D24,MATCH(O$5,MTInputs!$J$5:$AZ$5,0)) | P24: =INDEX(MTInputs!$J$1:$AZ$415,$D24,MATCH(P$5,MTInputs!$J$5:$AZ$5,0)) | Q24: =INDEX(MTInputs!$J$1:$AZ$415,$D24,MATCH(Q$5,MTInputs!$J$5:$AZ$5,0)) | R24: =INDEX(MTInputs!$J$1:$AZ$415,$D24,MATCH(R$5,MTInputs!$J$5:$AZ$5,0)) | S24: =INDEX(MTInputs!$J$1:$AZ$415,$D24,MATCH(S$5,MTInputs!$J$5:$AZ$5,0)) | ... Y24: =INDEX(MTInputs!$J$1:$AZ$415,$D24,MATCH(Y$5,MTInputs!$J$5:$AZ$5,0)) | Z24: =LOWER(Settings!$C$4)&".mit."&$A24&IF($C24="","","."&$C24&"."&$B24)&IF(INDEX(Variables!$D$5:$D$65,MATCH($A24,Variables!$A$5:$A$65,0))="","","."&INDEX(Variables!$D$5:$D$65,MATCH($A24,Variables!$A$5:$A$65,0)))&"."&Z$5 | AA24: =INDEX(MTInputs!$J$1:$AZ$415,$D24,MATCH(AA$5,MTInputs!$J$5:$AZ$5,0)) | AB24: =INDEX(MTInputs!$J$1:$AZ$415,$D24,MATCH(AB$5,MTInputs!$J$5:$AZ$5,0)) | AC24: =INDEX(MTInputs!$J$1:$AZ$415,$D24,MATCH(AC$5,MTInputs!$J$5:$AZ$5,0)) | AD24: =INDEX(MTInputs!$J$1:$AZ$415,$D24,MATCH(AD$5,MTInputs!$J$5:$AZ$5,0)) | AE24: =INDEX(MTInputs!$J$1:$AZ$415,$D24,MATCH(AE$5,MTInputs!$J$5:$AZ$5,0)) | AF24: =INDEX(MTInputs!$J$1:$AZ$415,$D24,MATCH(AF$5,MTInputs!$J$5:$AZ$5,0)) | AG24: =INDEX(MTInputs!$J$1:$AZ$415,$D24,MATCH(AG$5,MTInputs!$J$5:$AZ$5,0)) | AH24: =INDEX(MTInputs!$J$1:$AZ$415,$D24,MATCH(AH$5,MTInputs!$J$5:$AZ$5,0)) | ... AN24: =INDEX(MTInputs!$J$1:$AZ$415,$D24,MATCH(AN$5,MTInputs!$J$5:$AZ$5,0))
A25: ctcov | B25: bio | C25: all | H25: =INDEX(Variables!$B$5:$B$65,MATCH($A25,Variables!$A$5:$A$65,0))&IF($C25="",""," | "&INDEX(Mapping!$B$5:$B$25,MATCH($C25,Mapping!$A$5:$A$25,0))&" | "&INDEX(Mapping!$B$29:$B$38,MATCH($B25,Mapping!$A$29:$A$38,0))) | I25: =INDEX(Variables!$C$5:$C$65,MATCH($A25,Variables!$A$5:$A$65,0)) | J25: =INDEX(Variables!$E$5:$E$65,MATCH($A25,Variables!$A$5:$A$65,0)) | K25: =LOWER(Settings!$C$4)&".mit."&$A25&IF($C25="","","."&$C25&"."&$B25)&IF(INDEX(Variables!$D$5:$D$65,MATCH($A25,Variables!$A$5:$A$65,0))="","","."&INDEX(Variables!$D$5:$D$65,MATCH($A25,Variables!$A$5:$A$65,0)))&"."&K$5 | L25: TRUE | M25: TRUE | N25: TRUE | O25: TRUE | P25: TRUE | Q25: TRUE | R25: TRUE | S25: TRUE | T25: TRUE | U25: TRUE | V25: TRUE | W25: TRUE | X25: TRUE | Y25: TRUE | Z25: =LOWER(Settings!$C$4)&".mit."&$A25&IF($C25="","","."&$C25&"."&$B25)&IF(INDEX(Variables!$D$5:$D$65,MATCH($A25,Variables!$A$5:$A$65,0))="","","."&INDEX(Variables!$D$5:$D$65,MATCH($A25,Variables!$A$5:$A$65,0)))&"."&Z$5 | AA25: TRUE | AB25: TRUE | AC25: TRUE | AD25: TRUE | AE25: TRUE | AF25: TRUE | AG25: TRUE | AH25: TRUE | AI25: TRUE | AJ25: TRUE | AK25: TRUE | AL25: TRUE | AM25: TRUE | AN25: TRUE
H26: Carbon tax coverage: sectors (MTInputs rows 31-47)
A27: ctcov | B27: all | C27: pow | D27: 31 | H27: =INDEX(Variables!$B$5:$B$65,MATCH($A27,Variables!$A$5:$A$65,0))&IF($C27="",""," | "&INDEX(Mapping!$B$5:$B$25,MATCH($C27,Mapping!$A$5:$A$25,0))&" | "&INDEX(Mapping!$B$29:$B$38,MATCH($B27,Mapping!$A$29:$A$38,0))) | I27: =INDEX(Variables!$C$5:$C$65,MATCH($A27,Variables!$A$5:$A$65,0)) | J27: =INDEX(Variables!$E$5:$E$65,MATCH($A27,Variables!$A$5:$A$65,0)) | K27: =LOWER(Settings!$C$4)&".mit."&$A27&IF($C27="","","."&$C27&"."&$B27)&IF(INDEX(Variables!$D$5:$D$65,MATCH($A27,Variables!$A$5:$A$65,0))="","","."&INDEX(Variables!$D$5:$D$65,MATCH($A27,Variables!$A$5:$A$65,0)))&"."&K$5 | L27: =INDEX(MTInputs!$J$1:$AZ$415,$D27,MATCH(L$5,MTInputs!$J$5:$AZ$5,0)) | M27: =INDEX(MTInputs!$J$1:$AZ$415,$D27,MATCH(M$5,MTInputs!$J$5:$AZ$5,0)) | N27: =INDEX(MTInputs!$J$1:$AZ$415,$D27,MATCH(N$5,MTInputs!$J$5:$AZ$5,0)) | O27: =INDEX(MTInputs!$J$1:$AZ$415,$D27,MATCH(O$5,MTInputs!$J$5:$AZ$5,0)) | P27: =INDEX(MTInputs!$J$1:$AZ$415,$D27,MATCH(P$5,MTInputs!$J$5:$AZ$5,0)) | Q27: =INDEX(MTInputs!$J$1:$AZ$415,$D27,MATCH(Q$5,MTInputs!$J$5:$AZ$5,0)) | R27: =INDEX(MTInputs!$J$1:$AZ$415,$D27,MATCH(R$5,MTInputs!$J$5:$AZ$5,0)) | S27: =INDEX(MTInputs!$J$1:$AZ$415,$D27,MATCH(S$5,MTInputs!$J$5:$AZ$5,0)) | ... Y27: =INDEX(MTInputs!$J$1:$AZ$415,$D27,MATCH(Y$5,MTInputs!$J$5:$AZ$5,0)) | Z27: =LOWER(Settings!$C$4)&".mit."&$A27&IF($C27="","","."&$C27&"."&$B27)&IF(INDEX(Variables!$D$5:$D$65,MATCH($A27,Variables!$A$5:$A$65,0))="","","."&INDEX(Variables!$D$5:$D$65,MATCH($A27,Variables!$A$5:$A$65,0)))&"."&Z$5 | AA27: =INDEX(MTInputs!$J$1:$AZ$415,$D27,MATCH(AA$5,MTInputs!$J$5:$AZ$5,0)) | AB27: =INDEX(MTInputs!$J$1:$AZ$415,$D27,MATCH(AB$5,MTInputs!$J$5:$AZ$5,0)) | AC27: =INDEX(MTInputs!$J$1:$AZ$415,$D27,MATCH(AC$5,MTInputs!$J$5:$AZ$5,0)) | AD27: =INDEX(MTInputs!$J$1:$AZ$415,$D27,MATCH(AD$5,MTInputs!$J$5:$AZ$5,0)) | AE27: =INDEX(MTInputs!$J$1:$AZ$415,$D27,MATCH(AE$5,MTInputs!$J$5:$AZ$5,0)) | AF27: =INDEX(MTInputs!$J$1:$AZ$415,$D27,MATCH(AF$5,MTInputs!$J$5:$AZ$5,0)) | AG27: =INDEX(MTInputs!$J$1:$AZ$415,$D27,MATCH(AG$5,MTInputs!$J$5:$AZ$5,0)) | AH27: =INDEX(MTInputs!$J$1:$AZ$415,$D27,MATCH(AH$5,MTInputs!$J$5:$AZ$5,0)) | ... AN27: =INDEX(MTInputs!$J$1:$AZ$415,$D27,MATCH(AN$5,MTInputs!$J$5:$AZ$5,0))
A28: ctcov | B28: all | C28: rod | D28: 32 | H28: =INDEX(Variables!$B$5:$B$65,MATCH($A28,Variables!$A$5:$A$65,0))&IF($C28="",""," | "&INDEX(Mapping!$B$5:$B$25,MATCH($C28,Mapping!$A$5:$A$25,0))&" | "&INDEX(Mapping!$B$29:$B$38,MATCH($B28,Mapping!$A$29:$A$38,0))) | I28: =INDEX(Variables!$C$5:$C$65,MATCH($A28,Variables!$A$5:$A$65,0)) | J28: =INDEX(Variables!$E$5:$E$65,MATCH($A28,Variables!$A$5:$A$65,0)) | K28: =LOWER(Settings!$C$4)&".mit."&$A28&IF($C28="","","."&$C28&"."&$B28)&IF(INDEX(Variables!$D$5:$D$65,MATCH($A28,Variables!$A$5:$A$65,0))="","","."&INDEX(Variables!$D$5:$D$65,MATCH($A28,Variables!$A$5:$A$65,0)))&"."&K$5 | L28: =INDEX(MTInputs!$J$1:$AZ$415,$D28,MATCH(L$5,MTInputs!$J$5:$AZ$5,0)) | M28: =INDEX(MTInputs!$J$1:$AZ$415,$D28,MATCH(M$5,MTInputs!$J$5:$AZ$5,0)) | N28: =INDEX(MTInputs!$J$1:$AZ$415,$D28,MATCH(N$5,MTInputs!$J$5:$AZ$5,0)) | O28: =INDEX(MTInputs!$J$1:$AZ$415,$D28,MATCH(O$5,MTInputs!$J$5:$AZ$5,0)) | P28: =INDEX(MTInputs!$J$1:$AZ$415,$D28,MATCH(P$5,MTInputs!$J$5:$AZ$5,0)) | Q28: =INDEX(MTInputs!$J$1:$AZ$415,$D28,MATCH(Q$5,MTInputs!$J$5:$AZ$5,0)) | R28: =INDEX(MTInputs!$J$1:$AZ$415,$D28,MATCH(R$5,MTInputs!$J$5:$AZ$5,0)) | S28: =INDEX(MTInputs!$J$1:$AZ$415,$D28,MATCH(S$5,MTInputs!$J$5:$AZ$5,0)) | ... Y28: =INDEX(MTInputs!$J$1:$AZ$415,$D28,MATCH(Y$5,MTInputs!$J$5:$AZ$5,0)) | Z28: =LOWER(Settings!$C$4)&".mit."&$A28&IF($C28="","","."&$C28&"."&$B28)&IF(INDEX(Variables!$D$5:$D$65,MATCH($A28,Variables!$A$5:$A$65,0))="","","."&INDEX(Variables!$D$5:$D$65,MATCH($A28,Variables!$A$5:$A$65,0)))&"."&Z$5 | AA28: =INDEX(MTInputs!$J$1:$AZ$415,$D28,MATCH(AA$5,MTInputs!$J$5:$AZ$5,0)) | AB28: =INDEX(MTInputs!$J$1:$AZ$415,$D28,MATCH(AB$5,MTInputs!$J$5:$AZ$5,0)) | AC28: =INDEX(MTInputs!$J$1:$AZ$415,$D28,MATCH(AC$5,MTInputs!$J$5:$AZ$5,0)) | AD28: =INDEX(MTInputs!$J$1:$AZ$415,$D28,MATCH(AD$5,MTInputs!$J$5:$AZ$5,0)) | AE28: =INDEX(MTInputs!$J$1:$AZ$415,$D28,MATCH(AE$5,MTInputs!$J$5:$AZ$5,0)) | AF28: =INDEX(MTInputs!$J$1:$AZ$415,$D28,MATCH(AF$5,MTInputs!$J$5:$AZ$5,0)) | AG28: =INDEX(MTInputs!$J$1:$AZ$415,$D28,MATCH(AG$5,MTInputs!$J$5:$AZ$5,0)) | AH28: =INDEX(MTInputs!$J$1:$AZ$415,$D28,MATCH(AH$5,MTInputs!$J$5:$AZ$5,0)) | ... AN28: =INDEX(MTInputs!$J$1:$AZ$415,$D28,MATCH(AN$5,MTInputs!$J$5:$AZ$5,0))
A29: ctcov | B29: all | C29: ral | D29: 33 | H29: =INDEX(Variables!$B$5:$B$65,MATCH($A29,Variables!$A$5:$A$65,0))&IF($C29="",""," | "&INDEX(Mapping!$B$5:$B$25,MATCH($C29,Mapping!$A$5:$A$25,0))&" | "&INDEX(Mapping!$B$29:$B$38,MATCH($B29,Mapping!$A$29:$A$38,0))) | I29: =INDEX(Variables!$C$5:$C$65,MATCH($A29,Variables!$A$5:$A$65,0)) | J29: =INDEX(Variables!$E$5:$E$65,MATCH($A29,Variables!$A$5:$A$65,0)) | K29: =LOWER(Settings!$C$4)&".mit."&$A29&IF($C29="","","."&$C29&"."&$B29)&IF(INDEX(Variables!$D$5:$D$65,MATCH($A29,Variables!$A$5:$A$65,0))="","","."&INDEX(Variables!$D$5:$D$65,MATCH($A29,Variables!$A$5:$A$65,0)))&"."&K$5 | L29: =INDEX(MTInputs!$J$1:$AZ$415,$D29,MATCH(L$5,MTInputs!$J$5:$AZ$5,0)) | M29: =INDEX(MTInputs!$J$1:$AZ$415,$D29,MATCH(M$5,MTInputs!$J$5:$AZ$5,0)) | N29: =INDEX(MTInputs!$J$1:$AZ$415,$D29,MATCH(N$5,MTInputs!$J$5:$AZ$5,0)) | O29: =INDEX(MTInputs!$J$1:$AZ$415,$D29,MATCH(O$5,MTInputs!$J$5:$AZ$5,0)) | P29: =INDEX(MTInputs!$J$1:$AZ$415,$D29,MATCH(P$5,MTInputs!$J$5:$AZ$5,0)) | Q29: =INDEX(MTInputs!$J$1:$AZ$415,$D29,MATCH(Q$5,MTInputs!$J$5:$AZ$5,0)) | R29: =INDEX(MTInputs!$J$1:$AZ$415,$D29,MATCH(R$5,MTInputs!$J$5:$AZ$5,0)) | S29: =INDEX(MTInputs!$J$1:$AZ$415,$D29,MATCH(S$5,MTInputs!$J$5:$AZ$5,0)) | ... Y29: =INDEX(MTInputs!$J$1:$AZ$415,$D29,MATCH(Y$5,MTInputs!$J$5:$AZ$5,0)) | Z29: =LOWER(Settings!$C$4)&".mit."&$A29&IF($C29="","","."&$C29&"."&$B29)&IF(INDEX(Variables!$D$5:$D$65,MATCH($A29,Variables!$A$5:$A$65,0))="","","."&INDEX(Variables!$D$5:$D$65,MATCH($A29,Variables!$A$5:$A$65,0)))&"."&Z$5 | AA29: =INDEX(MTInputs!$J$1:$AZ$415,$D29,MATCH(AA$5,MTInputs!$J$5:$AZ$5,0)) | AB29: =INDEX(MTInputs!$J$1:$AZ$415,$D29,MATCH(AB$5,MTInputs!$J$5:$AZ$5,0)) | AC29: =INDEX(MTInputs!$J$1:$AZ$415,$D29,MATCH(AC$5,MTInputs!$J$5:$AZ$5,0)) | AD29: =INDEX(MTInputs!$J$1:$AZ$415,$D29,MATCH(AD$5,MTInputs!$J$5:$AZ$5,0)) | AE29: =INDEX(MTInputs!$J$1:$AZ$415,$D29,MATCH(AE$5,MTInputs!$J$5:$AZ$5,0)) | AF29: =INDEX(MTInputs!$J$1:$AZ$415,$D29,MATCH(AF$5,MTInputs!$J$5:$AZ$5,0)) | AG29: =INDEX(MTInputs!$J$1:$AZ$415,$D29,MATCH(AG$5,MTInputs!$J$5:$AZ$5,0)) | AH29: =INDEX(MTInputs!$J$1:$AZ$415,$D29,MATCH(AH$5,MTInputs!$J$5:$AZ$5,0)) | ... AN29: =INDEX(MTInputs!$J$1:$AZ$415,$D29,MATCH(AN$5,MTInputs!$J$5:$AZ$5,0))
A30: ctcov | B30: all | C30: avi | D30: 34 | H30: =INDEX(Variables!$B$5:$B$65,MATCH($A30,Variables!$A$5:$A$65,0))&IF($C30="",""," | "&INDEX(Mapping!$B$5:$B$25,MATCH($C30,Mapping!$A$5:$A$25,0))&" | "&INDEX(Mapping!$B$29:$B$38,MATCH($B30,Mapping!$A$29:$A$38,0))) | I30: =INDEX(Variables!$C$5:$C$65,MATCH($A30,Variables!$A$5:$A$65,0)) | J30: =INDEX(Variables!$E$5:$E$65,MATCH($A30,Variables!$A$5:$A$65,0)) | K30: =LOWER(Settings!$C$4)&".mit."&$A30&IF($C30="","","."&$C30&"."&$B30)&IF(INDEX(Variables!$D$5:$D$65,MATCH($A30,Variables!$A$5:$A$65,0))="","","."&INDEX(Variables!$D$5:$D$65,MATCH($A30,Variables!$A$5:$A$65,0)))&"."&K$5 | L30: =INDEX(MTInputs!$J$1:$AZ$415,$D30,MATCH(L$5,MTInputs!$J$5:$AZ$5,0)) | M30: =INDEX(MTInputs!$J$1:$AZ$415,$D30,MATCH(M$5,MTInputs!$J$5:$AZ$5,0)) | N30: =INDEX(MTInputs!$J$1:$AZ$415,$D30,MATCH(N$5,MTInputs!$J$5:$AZ$5,0)) | O30: =INDEX(MTInputs!$J$1:$AZ$415,$D30,MATCH(O$5,MTInputs!$J$5:$AZ$5,0)) | P30: =INDEX(MTInputs!$J$1:$AZ$415,$D30,MATCH(P$5,MTInputs!$J$5:$AZ$5,0)) | Q30: =INDEX(MTInputs!$J$1:$AZ$415,$D30,MATCH(Q$5,MTInputs!$J$5:$AZ$5,0)) | R30: =INDEX(MTInputs!$J$1:$AZ$415,$D30,MATCH(R$5,MTInputs!$J$5:$AZ$5,0)) | S30: =INDEX(MTInputs!$J$1:$AZ$415,$D30,MATCH(S$5,MTInputs!$J$5:$AZ$5,0)) | ... Y30: =INDEX(MTInputs!$J$1:$AZ$415,$D30,MATCH(Y$5,MTInputs!$J$5:$AZ$5,0)) | Z30: =LOWER(Settings!$C$4)&".mit."&$A30&IF($C30="","","."&$C30&"."&$B30)&IF(INDEX(Variables!$D$5:$D$65,MATCH($A30,Variables!$A$5:$A$65,0))="","","."&INDEX(Variables!$D$5:$D$65,MATCH($A30,Variables!$A$5:$A$65,0)))&"."&Z$5 | AA30: =INDEX(MTInputs!$J$1:$AZ$415,$D30,MATCH(AA$5,MTInputs!$J$5:$AZ$5,0)) | AB30: =INDEX(MTInputs!$J$1:$AZ$415,$D30,MATCH(AB$5,MTInputs!$J$5:$AZ$5,0)) | AC30: =INDEX(MTInputs!$J$1:$AZ$415,$D30,MATCH(AC$5,MTInputs!$J$5:$AZ$5,0)) | AD30: =INDEX(MTInputs!$J$1:$AZ$415,$D30,MATCH(AD$5,MTInputs!$J$5:$AZ$5,0)) | AE30: =INDEX(MTInputs!$J$1:$AZ$415,$D30,MATCH(AE$5,MTInputs!$J$5:$AZ$5,0)) | AF30: =INDEX(MTInputs!$J$1:$AZ$415,$D30,MATCH(AF$5,MTInputs!$J$5:$AZ$5,0)) | AG30: =INDEX(MTInputs!$J$1:$AZ$415,$D30,MATCH(AG$5,MTInputs!$J$5:$AZ$5,0)) | AH30: =INDEX(MTInputs!$J$1:$AZ$415,$D30,MATCH(AH$5,MTInputs!$J$5:$AZ$5,0)) | ... AN30: =INDEX(MTInputs!$J$1:$AZ$415,$D30,MATCH(AN$5,MTInputs!$J$5:$AZ$5,0))
A31: ctcov | B31: all | C31: nav | D31: 35 | H31: =INDEX(Variables!$B$5:$B$65,MATCH($A31,Variables!$A$5:$A$65,0))&IF($C31="",""," | "&INDEX(Mapping!$B$5:$B$25,MATCH($C31,Mapping!$A$5:$A$25,0))&" | "&INDEX(Mapping!$B$29:$B$38,MATCH($B31,Mapping!$A$29:$A$38,0))) | I31: =INDEX(Variables!$C$5:$C$65,MATCH($A31,Variables!$A$5:$A$65,0)) | J31: =INDEX(Variables!$E$5:$E$65,MATCH($A31,Variables!$A$5:$A$65,0)) | K31: =LOWER(Settings!$C$4)&".mit."&$A31&IF($C31="","","."&$C31&"."&$B31)&IF(INDEX(Variables!$D$5:$D$65,MATCH($A31,Variables!$A$5:$A$65,0))="","","."&INDEX(Variables!$D$5:$D$65,MATCH($A31,Variables!$A$5:$A$65,0)))&"."&K$5 | L31: =INDEX(MTInputs!$J$1:$AZ$415,$D31,MATCH(L$5,MTInputs!$J$5:$AZ$5,0)) | M31: =INDEX(MTInputs!$J$1:$AZ$415,$D31,MATCH(M$5,MTInputs!$J$5:$AZ$5,0)) | N31: =INDEX(MTInputs!$J$1:$AZ$415,$D31,MATCH(N$5,MTInputs!$J$5:$AZ$5,0)) | O31: =INDEX(MTInputs!$J$1:$AZ$415,$D31,MATCH(O$5,MTInputs!$J$5:$AZ$5,0)) | P31: =INDEX(MTInputs!$J$1:$AZ$415,$D31,MATCH(P$5,MTInputs!$J$5:$AZ$5,0)) | Q31: =INDEX(MTInputs!$J$1:$AZ$415,$D31,MATCH(Q$5,MTInputs!$J$5:$AZ$5,0)) | R31: =INDEX(MTInputs!$J$1:$AZ$415,$D31,MATCH(R$5,MTInputs!$J$5:$AZ$5,0)) | S31: =INDEX(MTInputs!$J$1:$AZ$415,$D31,MATCH(S$5,MTInputs!$J$5:$AZ$5,0)) | ... Y31: =INDEX(MTInputs!$J$1:$AZ$415,$D31,MATCH(Y$5,MTInputs!$J$5:$AZ$5,0)) | Z31: =LOWER(Settings!$C$4)&".mit."&$A31&IF($C31="","","."&$C31&"."&$B31)&IF(INDEX(Variables!$D$5:$D$65,MATCH($A31,Variables!$A$5:$A$65,0))="","","."&INDEX(Variables!$D$5:$D$65,MATCH($A31,Variables!$A$5:$A$65,0)))&"."&Z$5 | AA31: =INDEX(MTInputs!$J$1:$AZ$415,$D31,MATCH(AA$5,MTInputs!$J$5:$AZ$5,0)) | AB31: =INDEX(MTInputs!$J$1:$AZ$415,$D31,MATCH(AB$5,MTInputs!$J$5:$AZ$5,0)) | AC31: =INDEX(MTInputs!$J$1:$AZ$415,$D31,MATCH(AC$5,MTInputs!$J$5:$AZ$5,0)) | AD31: =INDEX(MTInputs!$J$1:$AZ$415,$D31,MATCH(AD$5,MTInputs!$J$5:$AZ$5,0)) | AE31: =INDEX(MTInputs!$J$1:$AZ$415,$D31,MATCH(AE$5,MTInputs!$J$5:$AZ$5,0)) | AF31: =INDEX(MTInputs!$J$1:$AZ$415,$D31,MATCH(AF$5,MTInputs!$J$5:$AZ$5,0)) | AG31: =INDEX(MTInputs!$J$1:$AZ$415,$D31,MATCH(AG$5,MTInputs!$J$5:$AZ$5,0)) | AH31: =INDEX(MTInputs!$J$1:$AZ$415,$D31,MATCH(AH$5,MTInputs!$J$5:$AZ$5,0)) | ... AN31: =INDEX(MTInputs!$J$1:$AZ$415,$D31,MATCH(AN$5,MTInputs!$J$5:$AZ$5,0))
A32: ctcov | B32: all | C32: res | D32: 36 | H32: =INDEX(Variables!$B$5:$B$65,MATCH($A32,Variables!$A$5:$A$65,0))&IF($C32="",""," | "&INDEX(Mapping!$B$5:$B$25,MATCH($C32,Mapping!$A$5:$A$25,0))&" | "&INDEX(Mapping!$B$29:$B$38,MATCH($B32,Mapping!$A$29:$A$38,0))) | I32: =INDEX(Variables!$C$5:$C$65,MATCH($A32,Variables!$A$5:$A$65,0)) | J32: =INDEX(Variables!$E$5:$E$65,MATCH($A32,Variables!$A$5:$A$65,0)) | K32: =LOWER(Settings!$C$4)&".mit."&$A32&IF($C32="","","."&$C32&"."&$B32)&IF(INDEX(Variables!$D$5:$D$65,MATCH($A32,Variables!$A$5:$A$65,0))="","","."&INDEX(Variables!$D$5:$D$65,MATCH($A32,Variables!$A$5:$A$65,0)))&"."&K$5 | L32: =INDEX(MTInputs!$J$1:$AZ$415,$D32,MATCH(L$5,MTInputs!$J$5:$AZ$5,0)) | M32: =INDEX(MTInputs!$J$1:$AZ$415,$D32,MATCH(M$5,MTInputs!$J$5:$AZ$5,0)) | N32: =INDEX(MTInputs!$J$1:$AZ$415,$D32,MATCH(N$5,MTInputs!$J$5:$AZ$5,0)) | O32: =INDEX(MTInputs!$J$1:$AZ$415,$D32,MATCH(O$5,MTInputs!$J$5:$AZ$5,0)) | P32: =INDEX(MTInputs!$J$1:$AZ$415,$D32,MATCH(P$5,MTInputs!$J$5:$AZ$5,0)) | Q32: =INDEX(MTInputs!$J$1:$AZ$415,$D32,MATCH(Q$5,MTInputs!$J$5:$AZ$5,0)) | R32: =INDEX(MTInputs!$J$1:$AZ$415,$D32,MATCH(R$5,MTInputs!$J$5:$AZ$5,0)) | S32: =INDEX(MTInputs!$J$1:$AZ$415,$D32,MATCH(S$5,MTInputs!$J$5:$AZ$5,0)) | ... Y32: =INDEX(MTInputs!$J$1:$AZ$415,$D32,MATCH(Y$5,MTInputs!$J$5:$AZ$5,0)) | Z32: =LOWER(Settings!$C$4)&".mit."&$A32&IF($C32="","","."&$C32&"."&$B32)&IF(INDEX(Variables!$D$5:$D$65,MATCH($A32,Variables!$A$5:$A$65,0))="","","."&INDEX(Variables!$D$5:$D$65,MATCH($A32,Variables!$A$5:$A$65,0)))&"."&Z$5 | AA32: =INDEX(MTInputs!$J$1:$AZ$415,$D32,MATCH(AA$5,MTInputs!$J$5:$AZ$5,0)) | AB32: =INDEX(MTInputs!$J$1:$AZ$415,$D32,MATCH(AB$5,MTInputs!$J$5:$AZ$5,0)) | AC32: =INDEX(MTInputs!$J$1:$AZ$415,$D32,MATCH(AC$5,MTInputs!$J$5:$AZ$5,0)) | AD32: =INDEX(MTInputs!$J$1:$AZ$415,$D32,MATCH(AD$5,MTInputs!$J$5:$AZ$5,0)) | AE32: =INDEX(MTInputs!$J$1:$AZ$415,$D32,MATCH(AE$5,MTInputs!$J$5:$AZ$5,0)) | AF32: =INDEX(MTInputs!$J$1:$AZ$415,$D32,MATCH(AF$5,MTInputs!$J$5:$AZ$5,0)) | AG32: =INDEX(MTInputs!$J$1:$AZ$415,$D32,MATCH(AG$5,MTInputs!$J$5:$AZ$5,0)) | AH32: =INDEX(MTInputs!$J$1:$AZ$415,$D32,MATCH(AH$5,MTInputs!$J$5:$AZ$5,0)) | ... AN32: =INDEX(MTInputs!$J$1:$AZ$415,$D32,MATCH(AN$5,MTInputs!$J$5:$AZ$5,0))
A33: ctcov | B33: all | C33: foo | D33: 37 | H33: =INDEX(Variables!$B$5:$B$65,MATCH($A33,Variables!$A$5:$A$65,0))&IF($C33="",""," | "&INDEX(Mapping!$B$5:$B$25,MATCH($C33,Mapping!$A$5:$A$25,0))&" | "&INDEX(Mapping!$B$29:$B$38,MATCH($B33,Mapping!$A$29:$A$38,0))) | I33: =INDEX(Variables!$C$5:$C$65,MATCH($A33,Variables!$A$5:$A$65,0)) | J33: =INDEX(Variables!$E$5:$E$65,MATCH($A33,Variables!$A$5:$A$65,0)) | K33: =LOWER(Settings!$C$4)&".mit."&$A33&IF($C33="","","."&$C33&"."&$B33)&IF(INDEX(Variables!$D$5:$D$65,MATCH($A33,Variables!$A$5:$A$65,0))="","","."&INDEX(Variables!$D$5:$D$65,MATCH($A33,Variables!$A$5:$A$65,0)))&"."&K$5 | L33: =INDEX(MTInputs!$J$1:$AZ$415,$D33,MATCH(L$5,MTInputs!$J$5:$AZ$5,0)) | M33: =INDEX(MTInputs!$J$1:$AZ$415,$D33,MATCH(M$5,MTInputs!$J$5:$AZ$5,0)) | N33: =INDEX(MTInputs!$J$1:$AZ$415,$D33,MATCH(N$5,MTInputs!$J$5:$AZ$5,0)) | O33: =INDEX(MTInputs!$J$1:$AZ$415,$D33,MATCH(O$5,MTInputs!$J$5:$AZ$5,0)) | P33: =INDEX(MTInputs!$J$1:$AZ$415,$D33,MATCH(P$5,MTInputs!$J$5:$AZ$5,0)) | Q33: =INDEX(MTInputs!$J$1:$AZ$415,$D33,MATCH(Q$5,MTInputs!$J$5:$AZ$5,0)) | R33: =INDEX(MTInputs!$J$1:$AZ$415,$D33,MATCH(R$5,MTInputs!$J$5:$AZ$5,0)) | S33: =INDEX(MTInputs!$J$1:$AZ$415,$D33,MATCH(S$5,MTInputs!$J$5:$AZ$5,0)) | ... Y33: =INDEX(MTInputs!$J$1:$AZ$415,$D33,MATCH(Y$5,MTInputs!$J$5:$AZ$5,0)) | Z33: =LOWER(Settings!$C$4)&".mit."&$A33&IF($C33="","","."&$C33&"."&$B33)&IF(INDEX(Variables!$D$5:$D$65,MATCH($A33,Variables!$A$5:$A$65,0))="","","."&INDEX(Variables!$D$5:$D$65,MATCH($A33,Variables!$A$5:$A$65,0)))&"."&Z$5 | AA33: =INDEX(MTInputs!$J$1:$AZ$415,$D33,MATCH(AA$5,MTInputs!$J$5:$AZ$5,0)) | AB33: =INDEX(MTInputs!$J$1:$AZ$415,$D33,MATCH(AB$5,MTInputs!$J$5:$AZ$5,0)) | AC33: =INDEX(MTInputs!$J$1:$AZ$415,$D33,MATCH(AC$5,MTInputs!$J$5:$AZ$5,0)) | AD33: =INDEX(MTInputs!$J$1:$AZ$415,$D33,MATCH(AD$5,MTInputs!$J$5:$AZ$5,0)) | AE33: =INDEX(MTInputs!$J$1:$AZ$415,$D33,MATCH(AE$5,MTInputs!$J$5:$AZ$5,0)) | AF33: =INDEX(MTInputs!$J$1:$AZ$415,$D33,MATCH(AF$5,MTInputs!$J$5:$AZ$5,0)) | AG33: =INDEX(MTInputs!$J$1:$AZ$415,$D33,MATCH(AG$5,MTInputs!$J$5:$AZ$5,0)) | AH33: =INDEX(MTInputs!$J$1:$AZ$415,$D33,MATCH(AH$5,MTInputs!$J$5:$AZ$5,0)) | ... AN33: =INDEX(MTInputs!$J$1:$AZ$415,$D33,MATCH(AN$5,MTInputs!$J$5:$AZ$5,0))
A34: ctcov | B34: all | C34: srv | D34: 38 | H34: =INDEX(Variables!$B$5:$B$65,MATCH($A34,Variables!$A$5:$A$65,0))&IF($C34="",""," | "&INDEX(Mapping!$B$5:$B$25,MATCH($C34,Mapping!$A$5:$A$25,0))&" | "&INDEX(Mapping!$B$29:$B$38,MATCH($B34,Mapping!$A$29:$A$38,0))) | I34: =INDEX(Variables!$C$5:$C$65,MATCH($A34,Variables!$A$5:$A$65,0)) | J34: =INDEX(Variables!$E$5:$E$65,MATCH($A34,Variables!$A$5:$A$65,0)) | K34: =LOWER(Settings!$C$4)&".mit."&$A34&IF($C34="","","."&$C34&"."&$B34)&IF(INDEX(Variables!$D$5:$D$65,MATCH($A34,Variables!$A$5:$A$65,0))="","","."&INDEX(Variables!$D$5:$D$65,MATCH($A34,Variables!$A$5:$A$65,0)))&"."&K$5 | L34: =INDEX(MTInputs!$J$1:$AZ$415,$D34,MATCH(L$5,MTInputs!$J$5:$AZ$5,0)) | M34: =INDEX(MTInputs!$J$1:$AZ$415,$D34,MATCH(M$5,MTInputs!$J$5:$AZ$5,0)) | N34: =INDEX(MTInputs!$J$1:$AZ$415,$D34,MATCH(N$5,MTInputs!$J$5:$AZ$5,0)) | O34: =INDEX(MTInputs!$J$1:$AZ$415,$D34,MATCH(O$5,MTInputs!$J$5:$AZ$5,0)) | P34: =INDEX(MTInputs!$J$1:$AZ$415,$D34,MATCH(P$5,MTInputs!$J$5:$AZ$5,0)) | Q34: =INDEX(MTInputs!$J$1:$AZ$415,$D34,MATCH(Q$5,MTInputs!$J$5:$AZ$5,0)) | R34: =INDEX(MTInputs!$J$1:$AZ$415,$D34,MATCH(R$5,MTInputs!$J$5:$AZ$5,0)) | S34: =INDEX(MTInputs!$J$1:$AZ$415,$D34,MATCH(S$5,MTInputs!$J$5:$AZ$5,0)) | ... Y34: =INDEX(MTInputs!$J$1:$AZ$415,$D34,MATCH(Y$5,MTInputs!$J$5:$AZ$5,0)) | Z34: =LOWER(Settings!$C$4)&".mit."&$A34&IF($C34="","","."&$C34&"."&$B34)&IF(INDEX(Variables!$D$5:$D$65,MATCH($A34,Variables!$A$5:$A$65,0))="","","."&INDEX(Variables!$D$5:$D$65,MATCH($A34,Variables!$A$5:$A$65,0)))&"."&Z$5 | AA34: =INDEX(MTInputs!$J$1:$AZ$415,$D34,MATCH(AA$5,MTInputs!$J$5:$AZ$5,0)) | AB34: =INDEX(MTInputs!$J$1:$AZ$415,$D34,MATCH(AB$5,MTInputs!$J$5:$AZ$5,0)) | AC34: =INDEX(MTInputs!$J$1:$AZ$415,$D34,MATCH(AC$5,MTInputs!$J$5:$AZ$5,0)) | AD34: =INDEX(MTInputs!$J$1:$AZ$415,$D34,MATCH(AD$5,MTInputs!$J$5:$AZ$5,0)) | AE34: =INDEX(MTInputs!$J$1:$AZ$415,$D34,MATCH(AE$5,MTInputs!$J$5:$AZ$5,0)) | AF34: =INDEX(MTInputs!$J$1:$AZ$415,$D34,MATCH(AF$5,MTInputs!$J$5:$AZ$5,0)) | AG34: =INDEX(MTInputs!$J$1:$AZ$415,$D34,MATCH(AG$5,MTInputs!$J$5:$AZ$5,0)) | AH34: =INDEX(MTInputs!$J$1:$AZ$415,$D34,MATCH(AH$5,MTInputs!$J$5:$AZ$5,0)) | ... AN34: =INDEX(MTInputs!$J$1:$AZ$415,$D34,MATCH(AN$5,MTInputs!$J$5:$AZ$5,0))
A35: ctcov | B35: all | C35: mch | D35: 39 | H35: =INDEX(Variables!$B$5:$B$65,MATCH($A35,Variables!$A$5:$A$65,0))&IF($C35="",""," | "&INDEX(Mapping!$B$5:$B$25,MATCH($C35,Mapping!$A$5:$A$25,0))&" | "&INDEX(Mapping!$B$29:$B$38,MATCH($B35,Mapping!$A$29:$A$38,0))) | I35: =INDEX(Variables!$C$5:$C$65,MATCH($A35,Variables!$A$5:$A$65,0)) | J35: =INDEX(Variables!$E$5:$E$65,MATCH($A35,Variables!$A$5:$A$65,0)) | K35: =LOWER(Settings!$C$4)&".mit."&$A35&IF($C35="","","."&$C35&"."&$B35)&IF(INDEX(Variables!$D$5:$D$65,MATCH($A35,Variables!$A$5:$A$65,0))="","","."&INDEX(Variables!$D$5:$D$65,MATCH($A35,Variables!$A$5:$A$65,0)))&"."&K$5 | L35: =INDEX(MTInputs!$J$1:$AZ$415,$D35,MATCH(L$5,MTInputs!$J$5:$AZ$5,0)) | M35: =INDEX(MTInputs!$J$1:$AZ$415,$D35,MATCH(M$5,MTInputs!$J$5:$AZ$5,0)) | N35: =INDEX(MTInputs!$J$1:$AZ$415,$D35,MATCH(N$5,MTInputs!$J$5:$AZ$5,0)) | O35: =INDEX(MTInputs!$J$1:$AZ$415,$D35,MATCH(O$5,MTInputs!$J$5:$AZ$5,0)) | P35: =INDEX(MTInputs!$J$1:$AZ$415,$D35,MATCH(P$5,MTInputs!$J$5:$AZ$5,0)) | Q35: =INDEX(MTInputs!$J$1:$AZ$415,$D35,MATCH(Q$5,MTInputs!$J$5:$AZ$5,0)) | R35: =INDEX(MTInputs!$J$1:$AZ$415,$D35,MATCH(R$5,MTInputs!$J$5:$AZ$5,0)) | S35: =INDEX(MTInputs!$J$1:$AZ$415,$D35,MATCH(S$5,MTInputs!$J$5:$AZ$5,0)) | ... Y35: =INDEX(MTInputs!$J$1:$AZ$415,$D35,MATCH(Y$5,MTInputs!$J$5:$AZ$5,0)) | Z35: =LOWER(Settings!$C$4)&".mit."&$A35&IF($C35="","","."&$C35&"."&$B35)&IF(INDEX(Variables!$D$5:$D$65,MATCH($A35,Variables!$A$5:$A$65,0))="","","."&INDEX(Variables!$D$5:$D$65,MATCH($A35,Variables!$A$5:$A$65,0)))&"."&Z$5 | AA35: =INDEX(MTInputs!$J$1:$AZ$415,$D35,MATCH(AA$5,MTInputs!$J$5:$AZ$5,0)) | AB35: =INDEX(MTInputs!$J$1:$AZ$415,$D35,MATCH(AB$5,MTInputs!$J$5:$AZ$5,0)) | AC35: =INDEX(MTInputs!$J$1:$AZ$415,$D35,MATCH(AC$5,MTInputs!$J$5:$AZ$5,0)) | AD35: =INDEX(MTInputs!$J$1:$AZ$415,$D35,MATCH(AD$5,MTInputs!$J$5:$AZ$5,0)) | AE35: =INDEX(MTInputs!$J$1:$AZ$415,$D35,MATCH(AE$5,MTInputs!$J$5:$AZ$5,0)) | AF35: =INDEX(MTInputs!$J$1:$AZ$415,$D35,MATCH(AF$5,MTInputs!$J$5:$AZ$5,0)) | AG35: =INDEX(MTInputs!$J$1:$AZ$415,$D35,MATCH(AG$5,MTInputs!$J$5:$AZ$5,0)) | AH35: =INDEX(MTInputs!$J$1:$AZ$415,$D35,MATCH(AH$5,MTInputs!$J$5:$AZ$5,0)) | ... AN35: =INDEX(MTInputs!$J$1:$AZ$415,$D35,MATCH(AN$5,MTInputs!$J$5:$AZ$5,0))
A36: ctcov | B36: all | C36: irn | D36: 40 | H36: =INDEX(Variables!$B$5:$B$65,MATCH($A36,Variables!$A$5:$A$65,0))&IF($C36="",""," | "&INDEX(Mapping!$B$5:$B$25,MATCH($C36,Mapping!$A$5:$A$25,0))&" | "&INDEX(Mapping!$B$29:$B$38,MATCH($B36,Mapping!$A$29:$A$38,0))) | I36: =INDEX(Variables!$C$5:$C$65,MATCH($A36,Variables!$A$5:$A$65,0)) | J36: =INDEX(Variables!$E$5:$E$65,MATCH($A36,Variables!$A$5:$A$65,0)) | K36: =LOWER(Settings!$C$4)&".mit."&$A36&IF($C36="","","."&$C36&"."&$B36)&IF(INDEX(Variables!$D$5:$D$65,MATCH($A36,Variables!$A$5:$A$65,0))="","","."&INDEX(Variables!$D$5:$D$65,MATCH($A36,Variables!$A$5:$A$65,0)))&"."&K$5 | L36: =INDEX(MTInputs!$J$1:$AZ$415,$D36,MATCH(L$5,MTInputs!$J$5:$AZ$5,0)) | M36: =INDEX(MTInputs!$J$1:$AZ$415,$D36,MATCH(M$5,MTInputs!$J$5:$AZ$5,0)) | N36: =INDEX(MTInputs!$J$1:$AZ$415,$D36,MATCH(N$5,MTInputs!$J$5:$AZ$5,0)) | O36: =INDEX(MTInputs!$J$1:$AZ$415,$D36,MATCH(O$5,MTInputs!$J$5:$AZ$5,0)) | P36: =INDEX(MTInputs!$J$1:$AZ$415,$D36,MATCH(P$5,MTInputs!$J$5:$AZ$5,0)) | Q36: =INDEX(MTInputs!$J$1:$AZ$415,$D36,MATCH(Q$5,MTInputs!$J$5:$AZ$5,0)) | R36: =INDEX(MTInputs!$J$1:$AZ$415,$D36,MATCH(R$5,MTInputs!$J$5:$AZ$5,0)) | S36: =INDEX(MTInputs!$J$1:$AZ$415,$D36,MATCH(S$5,MTInputs!$J$5:$AZ$5,0)) | ... Y36: =INDEX(MTInputs!$J$1:$AZ$415,$D36,MATCH(Y$5,MTInputs!$J$5:$AZ$5,0)) | Z36: =LOWER(Settings!$C$4)&".mit."&$A36&IF($C36="","","."&$C36&"."&$B36)&IF(INDEX(Variables!$D$5:$D$65,MATCH($A36,Variables!$A$5:$A$65,0))="","","."&INDEX(Variables!$D$5:$D$65,MATCH($A36,Variables!$A$5:$A$65,0)))&"."&Z$5 | AA36: =INDEX(MTInputs!$J$1:$AZ$415,$D36,MATCH(AA$5,MTInputs!$J$5:$AZ$5,0)) | AB36: =INDEX(MTInputs!$J$1:$AZ$415,$D36,MATCH(AB$5,MTInputs!$J$5:$AZ$5,0)) | AC36: =INDEX(MTInputs!$J$1:$AZ$415,$D36,MATCH(AC$5,MTInputs!$J$5:$AZ$5,0)) | AD36: =INDEX(MTInputs!$J$1:$AZ$415,$D36,MATCH(AD$5,MTInputs!$J$5:$AZ$5,0)) | AE36: =INDEX(MTInputs!$J$1:$AZ$415,$D36,MATCH(AE$5,MTInputs!$J$5:$AZ$5,0)) | AF36: =INDEX(MTInputs!$J$1:$AZ$415,$D36,MATCH(AF$5,MTInputs!$J$5:$AZ$5,0)) | AG36: =INDEX(MTInputs!$J$1:$AZ$415,$D36,MATCH(AG$5,MTInputs!$J$5:$AZ$5,0)) | AH36: =INDEX(MTInputs!$J$1:$AZ$415,$D36,MATCH(AH$5,MTInputs!$J$5:$AZ$5,0)) | ... AN36: =INDEX(MTInputs!$J$1:$AZ$415,$D36,MATCH(AN$5,MTInputs!$J$5:$AZ$5,0))
A37: ctcov | B37: all | C37: nfm | D37: 41 | H37: =INDEX(Variables!$B$5:$B$65,MATCH($A37,Variables!$A$5:$A$65,0))&IF($C37="",""," | "&INDEX(Mapping!$B$5:$B$25,MATCH($C37,Mapping!$A$5:$A$25,0))&" | "&INDEX(Mapping!$B$29:$B$38,MATCH($B37,Mapping!$A$29:$A$38,0))) | I37: =INDEX(Variables!$C$5:$C$65,MATCH($A37,Variables!$A$5:$A$65,0)) | J37: =INDEX(Variables!$E$5:$E$65,MATCH($A37,Variables!$A$5:$A$65,0)) | K37: =LOWER(Settings!$C$4)&".mit."&$A37&IF($C37="","","."&$C37&"."&$B37)&IF(INDEX(Variables!$D$5:$D$65,MATCH($A37,Variables!$A$5:$A$65,0))="","","."&INDEX(Variables!$D$5:$D$65,MATCH($A37,Variables!$A$5:$A$65,0)))&"."&K$5 | L37: =INDEX(MTInputs!$J$1:$AZ$415,$D37,MATCH(L$5,MTInputs!$J$5:$AZ$5,0)) | M37: =INDEX(MTInputs!$J$1:$AZ$415,$D37,MATCH(M$5,MTInputs!$J$5:$AZ$5,0)) | N37: =INDEX(MTInputs!$J$1:$AZ$415,$D37,MATCH(N$5,MTInputs!$J$5:$AZ$5,0)) | O37: =INDEX(MTInputs!$J$1:$AZ$415,$D37,MATCH(O$5,MTInputs!$J$5:$AZ$5,0)) | P37: =INDEX(MTInputs!$J$1:$AZ$415,$D37,MATCH(P$5,MTInputs!$J$5:$AZ$5,0)) | Q37: =INDEX(MTInputs!$J$1:$AZ$415,$D37,MATCH(Q$5,MTInputs!$J$5:$AZ$5,0)) | R37: =INDEX(MTInputs!$J$1:$AZ$415,$D37,MATCH(R$5,MTInputs!$J$5:$AZ$5,0)) | S37: =INDEX(MTInputs!$J$1:$AZ$415,$D37,MATCH(S$5,MTInputs!$J$5:$AZ$5,0)) | ... Y37: =INDEX(MTInputs!$J$1:$AZ$415,$D37,MATCH(Y$5,MTInputs!$J$5:$AZ$5,0)) | Z37: =LOWER(Settings!$C$4)&".mit."&$A37&IF($C37="","","."&$C37&"."&$B37)&IF(INDEX(Variables!$D$5:$D$65,MATCH($A37,Variables!$A$5:$A$65,0))="","","."&INDEX(Variables!$D$5:$D$65,MATCH($A37,Variables!$A$5:$A$65,0)))&"."&Z$5 | AA37: =INDEX(MTInputs!$J$1:$AZ$415,$D37,MATCH(AA$5,MTInputs!$J$5:$AZ$5,0)) | AB37: =INDEX(MTInputs!$J$1:$AZ$415,$D37,MATCH(AB$5,MTInputs!$J$5:$AZ$5,0)) | AC37: =INDEX(MTInputs!$J$1:$AZ$415,$D37,MATCH(AC$5,MTInputs!$J$5:$AZ$5,0)) | AD37: =INDEX(MTInputs!$J$1:$AZ$415,$D37,MATCH(AD$5,MTInputs!$J$5:$AZ$5,0)) | AE37: =INDEX(MTInputs!$J$1:$AZ$415,$D37,MATCH(AE$5,MTInputs!$J$5:$AZ$5,0)) | AF37: =INDEX(MTInputs!$J$1:$AZ$415,$D37,MATCH(AF$5,MTInputs!$J$5:$AZ$5,0)) | AG37: =INDEX(MTInputs!$J$1:$AZ$415,$D37,MATCH(AG$5,MTInputs!$J$5:$AZ$5,0)) | AH37: =INDEX(MTInputs!$J$1:$AZ$415,$D37,MATCH(AH$5,MTInputs!$J$5:$AZ$5,0)) | ... AN37: =INDEX(MTInputs!$J$1:$AZ$415,$D37,MATCH(AN$5,MTInputs!$J$5:$AZ$5,0))
A38: ctcov | B38: all | C38: mac | D38: 42 | H38: =INDEX(Variables!$B$5:$B$65,MATCH($A38,Variables!$A$5:$A$65,0))&IF($C38="",""," | "&INDEX(Mapping!$B$5:$B$25,MATCH($C38,Mapping!$A$5:$A$25,0))&" | "&INDEX(Mapping!$B$29:$B$38,MATCH($B38,Mapping!$A$29:$A$38,0))) | I38: =INDEX(Variables!$C$5:$C$65,MATCH($A38,Variables!$A$5:$A$65,0)) | J38: =INDEX(Variables!$E$5:$E$65,MATCH($A38,Variables!$A$5:$A$65,0)) | K38: =LOWER(Settings!$C$4)&".mit."&$A38&IF($C38="","","."&$C38&"."&$B38)&IF(INDEX(Variables!$D$5:$D$65,MATCH($A38,Variables!$A$5:$A$65,0))="","","."&INDEX(Variables!$D$5:$D$65,MATCH($A38,Variables!$A$5:$A$65,0)))&"."&K$5 | L38: =INDEX(MTInputs!$J$1:$AZ$415,$D38,MATCH(L$5,MTInputs!$J$5:$AZ$5,0)) | M38: =INDEX(MTInputs!$J$1:$AZ$415,$D38,MATCH(M$5,MTInputs!$J$5:$AZ$5,0)) | N38: =INDEX(MTInputs!$J$1:$AZ$415,$D38,MATCH(N$5,MTInputs!$J$5:$AZ$5,0)) | O38: =INDEX(MTInputs!$J$1:$AZ$415,$D38,MATCH(O$5,MTInputs!$J$5:$AZ$5,0)) | P38: =INDEX(MTInputs!$J$1:$AZ$415,$D38,MATCH(P$5,MTInputs!$J$5:$AZ$5,0)) | Q38: =INDEX(MTInputs!$J$1:$AZ$415,$D38,MATCH(Q$5,MTInputs!$J$5:$AZ$5,0)) | R38: =INDEX(MTInputs!$J$1:$AZ$415,$D38,MATCH(R$5,MTInputs!$J$5:$AZ$5,0)) | S38: =INDEX(MTInputs!$J$1:$AZ$415,$D38,MATCH(S$5,MTInputs!$J$5:$AZ$5,0)) | ... Y38: =INDEX(MTInputs!$J$1:$AZ$415,$D38,MATCH(Y$5,MTInputs!$J$5:$AZ$5,0)) | Z38: =LOWER(Settings!$C$4)&".mit."&$A38&IF($C38="","","."&$C38&"."&$B38)&IF(INDEX(Variables!$D$5:$D$65,MATCH($A38,Variables!$A$5:$A$65,0))="","","."&INDEX(Variables!$D$5:$D$65,MATCH($A38,Variables!$A$5:$A$65,0)))&"."&Z$5 | AA38: =INDEX(MTInputs!$J$1:$AZ$415,$D38,MATCH(AA$5,MTInputs!$J$5:$AZ$5,0)) | AB38: =INDEX(MTInputs!$J$1:$AZ$415,$D38,MATCH(AB$5,MTInputs!$J$5:$AZ$5,0)) | AC38: =INDEX(MTInputs!$J$1:$AZ$415,$D38,MATCH(AC$5,MTInputs!$J$5:$AZ$5,0)) | AD38: =INDEX(MTInputs!$J$1:$AZ$415,$D38,MATCH(AD$5,MTInputs!$J$5:$AZ$5,0)) | AE38: =INDEX(MTInputs!$J$1:$AZ$415,$D38,MATCH(AE$5,MTInputs!$J$5:$AZ$5,0)) | AF38: =INDEX(MTInputs!$J$1:$AZ$415,$D38,MATCH(AF$5,MTInputs!$J$5:$AZ$5,0)) | AG38: =INDEX(MTInputs!$J$1:$AZ$415,$D38,MATCH(AG$5,MTInputs!$J$5:$AZ$5,0)) | AH38: =INDEX(MTInputs!$J$1:$AZ$415,$D38,MATCH(AH$5,MTInputs!$J$5:$AZ$5,0)) | ... AN38: =INDEX(MTInputs!$J$1:$AZ$415,$D38,MATCH(AN$5,MTInputs!$J$5:$AZ$5,0))
... A43: ctcov | B43: all | C43: oen | D43: 47 | H43: =INDEX(Variables!$B$5:$B$65,MATCH($A43,Variables!$A$5:$A$65,0))&IF($C43="",""," | "&INDEX(Mapping!$B$5:$B$25,MATCH($C43,Mapping!$A$5:$A$25,0))&" | "&INDEX(Mapping!$B$29:$B$38,MATCH($B43,Mapping!$A$29:$A$38,0))) | I43: =INDEX(Variables!$C$5:$C$65,MATCH($A43,Variables!$A$5:$A$65,0)) | J43: =INDEX(Variables!$E$5:$E$65,MATCH($A43,Variables!$A$5:$A$65,0)) | K43: =LOWER(Settings!$C$4)&".mit."&$A43&IF($C43="","","."&$C43&"."&$B43)&IF(INDEX(Variables!$D$5:$D$65,MATCH($A43,Variables!$A$5:$A$65,0))="","","."&INDEX(Variables!$D$5:$D$65,MATCH($A43,Variables!$A$5:$A$65,0)))&"."&K$5 | L43: =INDEX(MTInputs!$J$1:$AZ$415,$D43,MATCH(L$5,MTInputs!$J$5:$AZ$5,0)) | M43: =INDEX(MTInputs!$J$1:$AZ$415,$D43,MATCH(M$5,MTInputs!$J$5:$AZ$5,0)) | N43: =INDEX(MTInputs!$J$1:$AZ$415,$D43,MATCH(N$5,MTInputs!$J$5:$AZ$5,0)) | O43: =INDEX(MTInputs!$J$1:$AZ$415,$D43,MATCH(O$5,MTInputs!$J$5:$AZ$5,0)) | P43: =INDEX(MTInputs!$J$1:$AZ$415,$D43,MATCH(P$5,MTInputs!$J$5:$AZ$5,0)) | Q43: =INDEX(MTInputs!$J$1:$AZ$415,$D43,MATCH(Q$5,MTInputs!$J$5:$AZ$5,0)) | R43: =INDEX(MTInputs!$J$1:$AZ$415,$D43,MATCH(R$5,MTInputs!$J$5:$AZ$5,0)) | S43: =INDEX(MTInputs!$J$1:$AZ$415,$D43,MATCH(S$5,MTInputs!$J$5:$AZ$5,0)) | ... Y43: =INDEX(MTInputs!$J$1:$AZ$415,$D43,MATCH(Y$5,MTInputs!$J$5:$AZ$5,0)) | Z43: =LOWER(Settings!$C$4)&".mit."&$A43&IF($C43="","","."&$C43&"."&$B43)&IF(INDEX(Variables!$D$5:$D$65,MATCH($A43,Variables!$A$5:$A$65,0))="","","."&INDEX(Variables!$D$5:$D$65,MATCH($A43,Variables!$A$5:$A$65,0)))&"."&Z$5 | AA43: =INDEX(MTInputs!$J$1:$AZ$415,$D43,MATCH(AA$5,MTInputs!$J$5:$AZ$5,0)) | AB43: =INDEX(MTInputs!$J$1:$AZ$415,$D43,MATCH(AB$5,MTInputs!$J$5:$AZ$5,0)) | AC43: =INDEX(MTInputs!$J$1:$AZ$415,$D43,MATCH(AC$5,MTInputs!$J$5:$AZ$5,0)) | AD43: =INDEX(MTInputs!$J$1:$AZ$415,$D43,MATCH(AD$5,MTInputs!$J$5:$AZ$5,0)) | AE43: =INDEX(MTInputs!$J$1:$AZ$415,$D43,MATCH(AE$5,MTInputs!$J$5:$AZ$5,0)) | AF43: =INDEX(MTInputs!$J$1:$AZ$415,$D43,MATCH(AF$5,MTInputs!$J$5:$AZ$5,0)) | AG43: =INDEX(MTInputs!$J$1:$AZ$415,$D43,MATCH(AG$5,MTInputs!$J$5:$AZ$5,0)) | AH43: =INDEX(MTInputs!$J$1:$AZ$415,$D43,MATCH(AH$5,MTInputs!$J$5:$AZ$5,0)) | ... AN43: =INDEX(MTInputs!$J$1:$AZ$415,$D43,MATCH(AN$5,MTInputs!$J$5:$AZ$5,0))
H44: Fuel price reform (MTInputs rows 140-169; increases in price units)
A45: fpr.yr0 | D45: 140 | H45: =INDEX(Variables!$B$5:$B$65,MATCH($A45,Variables!$A$5:$A$65,0))&IF($C45="",""," | "&INDEX(Mapping!$B$5:$B$25,MATCH($C45,Mapping!$A$5:$A$25,0))&" | "&INDEX(Mapping!$B$29:$B$38,MATCH($B45,Mapping!$A$29:$A$38,0))) | I45: =INDEX(Variables!$C$5:$C$65,MATCH($A45,Variables!$A$5:$A$65,0)) | J45: =INDEX(Variables!$E$5:$E$65,MATCH($A45,Variables!$A$5:$A$65,0)) | K45: =LOWER(Settings!$C$4)&".mit."&$A45&IF($C45="","","."&$C45&"."&$B45)&IF(INDEX(Variables!$D$5:$D$65,MATCH($A45,Variables!$A$5:$A$65,0))="","","."&INDEX(Variables!$D$5:$D$65,MATCH($A45,Variables!$A$5:$A$65,0)))&"."&K$5 | L45: =INDEX(MTInputs!$J$1:$AZ$415,$D45,MATCH(L$5,MTInputs!$J$5:$AZ$5,0)) | M45: =INDEX(MTInputs!$J$1:$AZ$415,$D45,MATCH(M$5,MTInputs!$J$5:$AZ$5,0)) | N45: =INDEX(MTInputs!$J$1:$AZ$415,$D45,MATCH(N$5,MTInputs!$J$5:$AZ$5,0)) | O45: =INDEX(MTInputs!$J$1:$AZ$415,$D45,MATCH(O$5,MTInputs!$J$5:$AZ$5,0)) | P45: =INDEX(MTInputs!$J$1:$AZ$415,$D45,MATCH(P$5,MTInputs!$J$5:$AZ$5,0)) | Q45: =INDEX(MTInputs!$J$1:$AZ$415,$D45,MATCH(Q$5,MTInputs!$J$5:$AZ$5,0)) | R45: =INDEX(MTInputs!$J$1:$AZ$415,$D45,MATCH(R$5,MTInputs!$J$5:$AZ$5,0)) | S45: =INDEX(MTInputs!$J$1:$AZ$415,$D45,MATCH(S$5,MTInputs!$J$5:$AZ$5,0)) | ... Y45: =INDEX(MTInputs!$J$1:$AZ$415,$D45,MATCH(Y$5,MTInputs!$J$5:$AZ$5,0)) | Z45: =LOWER(Settings!$C$4)&".mit."&$A45&IF($C45="","","."&$C45&"."&$B45)&IF(INDEX(Variables!$D$5:$D$65,MATCH($A45,Variables!$A$5:$A$65,0))="","","."&INDEX(Variables!$D$5:$D$65,MATCH($A45,Variables!$A$5:$A$65,0)))&"."&Z$5 | AA45: =INDEX(MTInputs!$J$1:$AZ$415,$D45,MATCH(AA$5,MTInputs!$J$5:$AZ$5,0)) | AB45: =INDEX(MTInputs!$J$1:$AZ$415,$D45,MATCH(AB$5,MTInputs!$J$5:$AZ$5,0)) | AC45: =INDEX(MTInputs!$J$1:$AZ$415,$D45,MATCH(AC$5,MTInputs!$J$5:$AZ$5,0)) | AD45: =INDEX(MTInputs!$J$1:$AZ$415,$D45,MATCH(AD$5,MTInputs!$J$5:$AZ$5,0)) | AE45: =INDEX(MTInputs!$J$1:$AZ$415,$D45,MATCH(AE$5,MTInputs!$J$5:$AZ$5,0)) | AF45: =INDEX(MTInputs!$J$1:$AZ$415,$D45,MATCH(AF$5,MTInputs!$J$5:$AZ$5,0)) | AG45: =INDEX(MTInputs!$J$1:$AZ$415,$D45,MATCH(AG$5,MTInputs!$J$5:$AZ$5,0)) | AH45: =INDEX(MTInputs!$J$1:$AZ$415,$D45,MATCH(AH$5,MTInputs!$J$5:$AZ$5,0)) | ... AN45: =INDEX(MTInputs!$J$1:$AZ$415,$D45,MATCH(AN$5,MTInputs!$J$5:$AZ$5,0))
A46: fpr.yr1 | D46: 141 | H46: =INDEX(Variables!$B$5:$B$65,MATCH($A46,Variables!$A$5:$A$65,0))&IF($C46="",""," | "&INDEX(Mapping!$B$5:$B$25,MATCH($C46,Mapping!$A$5:$A$25,0))&" | "&INDEX(Mapping!$B$29:$B$38,MATCH($B46,Mapping!$A$29:$A$38,0))) | I46: =INDEX(Variables!$C$5:$C$65,MATCH($A46,Variables!$A$5:$A$65,0)) | J46: =INDEX(Variables!$E$5:$E$65,MATCH($A46,Variables!$A$5:$A$65,0)) | K46: =LOWER(Settings!$C$4)&".mit."&$A46&IF($C46="","","."&$C46&"."&$B46)&IF(INDEX(Variables!$D$5:$D$65,MATCH($A46,Variables!$A$5:$A$65,0))="","","."&INDEX(Variables!$D$5:$D$65,MATCH($A46,Variables!$A$5:$A$65,0)))&"."&K$5 | L46: =INDEX(MTInputs!$J$1:$AZ$415,$D46,MATCH(L$5,MTInputs!$J$5:$AZ$5,0)) | M46: =INDEX(MTInputs!$J$1:$AZ$415,$D46,MATCH(M$5,MTInputs!$J$5:$AZ$5,0)) | N46: =INDEX(MTInputs!$J$1:$AZ$415,$D46,MATCH(N$5,MTInputs!$J$5:$AZ$5,0)) | O46: =INDEX(MTInputs!$J$1:$AZ$415,$D46,MATCH(O$5,MTInputs!$J$5:$AZ$5,0)) | P46: =INDEX(MTInputs!$J$1:$AZ$415,$D46,MATCH(P$5,MTInputs!$J$5:$AZ$5,0)) | Q46: =INDEX(MTInputs!$J$1:$AZ$415,$D46,MATCH(Q$5,MTInputs!$J$5:$AZ$5,0)) | R46: =INDEX(MTInputs!$J$1:$AZ$415,$D46,MATCH(R$5,MTInputs!$J$5:$AZ$5,0)) | S46: =INDEX(MTInputs!$J$1:$AZ$415,$D46,MATCH(S$5,MTInputs!$J$5:$AZ$5,0)) | ... Y46: =INDEX(MTInputs!$J$1:$AZ$415,$D46,MATCH(Y$5,MTInputs!$J$5:$AZ$5,0)) | Z46: =LOWER(Settings!$C$4)&".mit."&$A46&IF($C46="","","."&$C46&"."&$B46)&IF(INDEX(Variables!$D$5:$D$65,MATCH($A46,Variables!$A$5:$A$65,0))="","","."&INDEX(Variables!$D$5:$D$65,MATCH($A46,Variables!$A$5:$A$65,0)))&"."&Z$5 | AA46: =INDEX(MTInputs!$J$1:$AZ$415,$D46,MATCH(AA$5,MTInputs!$J$5:$AZ$5,0)) | AB46: =INDEX(MTInputs!$J$1:$AZ$415,$D46,MATCH(AB$5,MTInputs!$J$5:$AZ$5,0)) | AC46: =INDEX(MTInputs!$J$1:$AZ$415,$D46,MATCH(AC$5,MTInputs!$J$5:$AZ$5,0)) | AD46: =INDEX(MTInputs!$J$1:$AZ$415,$D46,MATCH(AD$5,MTInputs!$J$5:$AZ$5,0)) | AE46: =INDEX(MTInputs!$J$1:$AZ$415,$D46,MATCH(AE$5,MTInputs!$J$5:$AZ$5,0)) | AF46: =INDEX(MTInputs!$J$1:$AZ$415,$D46,MATCH(AF$5,MTInputs!$J$5:$AZ$5,0)) | AG46: =INDEX(MTInputs!$J$1:$AZ$415,$D46,MATCH(AG$5,MTInputs!$J$5:$AZ$5,0)) | AH46: =INDEX(MTInputs!$J$1:$AZ$415,$D46,MATCH(AH$5,MTInputs!$J$5:$AZ$5,0)) | ... AN46: =INDEX(MTInputs!$J$1:$AZ$415,$D46,MATCH(AN$5,MTInputs!$J$5:$AZ$5,0))
A47: fpr.s | B47: coa | C47: pow | D47: 142 | H47: =INDEX(Variables!$B$5:$B$65,MATCH($A47,Variables!$A$5:$A$65,0))&IF($C47="",""," | "&INDEX(Mapping!$B$5:$B$25,MATCH($C47,Mapping!$A$5:$A$25,0))&" | "&INDEX(Mapping!$B$29:$B$38,MATCH($B47,Mapping!$A$29:$A$38,0))) | I47: =INDEX(Variables!$C$5:$C$65,MATCH($A47,Variables!$A$5:$A$65,0)) | J47: =INDEX(Variables!$E$5:$E$65,MATCH($A47,Variables!$A$5:$A$65,0)) | K47: =LOWER(Settings!$C$4)&".mit."&$A47&IF($C47="","","."&$C47&"."&$B47)&IF(INDEX(Variables!$D$5:$D$65,MATCH($A47,Variables!$A$5:$A$65,0))="","","."&INDEX(Variables!$D$5:$D$65,MATCH($A47,Variables!$A$5:$A$65,0)))&"."&K$5 | L47: =INDEX(MTInputs!$J$1:$AZ$415,$D47,MATCH(L$5,MTInputs!$J$5:$AZ$5,0)) | M47: =INDEX(MTInputs!$J$1:$AZ$415,$D47,MATCH(M$5,MTInputs!$J$5:$AZ$5,0)) | N47: =INDEX(MTInputs!$J$1:$AZ$415,$D47,MATCH(N$5,MTInputs!$J$5:$AZ$5,0)) | O47: =INDEX(MTInputs!$J$1:$AZ$415,$D47,MATCH(O$5,MTInputs!$J$5:$AZ$5,0)) | P47: =INDEX(MTInputs!$J$1:$AZ$415,$D47,MATCH(P$5,MTInputs!$J$5:$AZ$5,0)) | Q47: =INDEX(MTInputs!$J$1:$AZ$415,$D47,MATCH(Q$5,MTInputs!$J$5:$AZ$5,0)) | R47: =INDEX(MTInputs!$J$1:$AZ$415,$D47,MATCH(R$5,MTInputs!$J$5:$AZ$5,0)) | S47: =INDEX(MTInputs!$J$1:$AZ$415,$D47,MATCH(S$5,MTInputs!$J$5:$AZ$5,0)) | ... Y47: =INDEX(MTInputs!$J$1:$AZ$415,$D47,MATCH(Y$5,MTInputs!$J$5:$AZ$5,0)) | Z47: =LOWER(Settings!$C$4)&".mit."&$A47&IF($C47="","","."&$C47&"."&$B47)&IF(INDEX(Variables!$D$5:$D$65,MATCH($A47,Variables!$A$5:$A$65,0))="","","."&INDEX(Variables!$D$5:$D$65,MATCH($A47,Variables!$A$5:$A$65,0)))&"."&Z$5 | AA47: =INDEX(MTInputs!$J$1:$AZ$415,$D47,MATCH(AA$5,MTInputs!$J$5:$AZ$5,0)) | AB47: =INDEX(MTInputs!$J$1:$AZ$415,$D47,MATCH(AB$5,MTInputs!$J$5:$AZ$5,0)) | AC47: =INDEX(MTInputs!$J$1:$AZ$415,$D47,MATCH(AC$5,MTInputs!$J$5:$AZ$5,0)) | AD47: =INDEX(MTInputs!$J$1:$AZ$415,$D47,MATCH(AD$5,MTInputs!$J$5:$AZ$5,0)) | AE47: =INDEX(MTInputs!$J$1:$AZ$415,$D47,MATCH(AE$5,MTInputs!$J$5:$AZ$5,0)) | AF47: =INDEX(MTInputs!$J$1:$AZ$415,$D47,MATCH(AF$5,MTInputs!$J$5:$AZ$5,0)) | AG47: =INDEX(MTInputs!$J$1:$AZ$415,$D47,MATCH(AG$5,MTInputs!$J$5:$AZ$5,0)) | AH47: =INDEX(MTInputs!$J$1:$AZ$415,$D47,MATCH(AH$5,MTInputs!$J$5:$AZ$5,0)) | ... AN47: =INDEX(MTInputs!$J$1:$AZ$415,$D47,MATCH(AN$5,MTInputs!$J$5:$AZ$5,0))
A48: fpr.s | B48: coa | C48: res | D48: 143 | H48: =INDEX(Variables!$B$5:$B$65,MATCH($A48,Variables!$A$5:$A$65,0))&IF($C48="",""," | "&INDEX(Mapping!$B$5:$B$25,MATCH($C48,Mapping!$A$5:$A$25,0))&" | "&INDEX(Mapping!$B$29:$B$38,MATCH($B48,Mapping!$A$29:$A$38,0))) | I48: =INDEX(Variables!$C$5:$C$65,MATCH($A48,Variables!$A$5:$A$65,0)) | J48: =INDEX(Variables!$E$5:$E$65,MATCH($A48,Variables!$A$5:$A$65,0)) | K48: =LOWER(Settings!$C$4)&".mit."&$A48&IF($C48="","","."&$C48&"."&$B48)&IF(INDEX(Variables!$D$5:$D$65,MATCH($A48,Variables!$A$5:$A$65,0))="","","."&INDEX(Variables!$D$5:$D$65,MATCH($A48,Variables!$A$5:$A$65,0)))&"."&K$5 | L48: =INDEX(MTInputs!$J$1:$AZ$415,$D48,MATCH(L$5,MTInputs!$J$5:$AZ$5,0)) | M48: =INDEX(MTInputs!$J$1:$AZ$415,$D48,MATCH(M$5,MTInputs!$J$5:$AZ$5,0)) | N48: =INDEX(MTInputs!$J$1:$AZ$415,$D48,MATCH(N$5,MTInputs!$J$5:$AZ$5,0)) | O48: =INDEX(MTInputs!$J$1:$AZ$415,$D48,MATCH(O$5,MTInputs!$J$5:$AZ$5,0)) | P48: =INDEX(MTInputs!$J$1:$AZ$415,$D48,MATCH(P$5,MTInputs!$J$5:$AZ$5,0)) | Q48: =INDEX(MTInputs!$J$1:$AZ$415,$D48,MATCH(Q$5,MTInputs!$J$5:$AZ$5,0)) | R48: =INDEX(MTInputs!$J$1:$AZ$415,$D48,MATCH(R$5,MTInputs!$J$5:$AZ$5,0)) | S48: =INDEX(MTInputs!$J$1:$AZ$415,$D48,MATCH(S$5,MTInputs!$J$5:$AZ$5,0)) | ... Y48: =INDEX(MTInputs!$J$1:$AZ$415,$D48,MATCH(Y$5,MTInputs!$J$5:$AZ$5,0)) | Z48: =LOWER(Settings!$C$4)&".mit."&$A48&IF($C48="","","."&$C48&"."&$B48)&IF(INDEX(Variables!$D$5:$D$65,MATCH($A48,Variables!$A$5:$A$65,0))="","","."&INDEX(Variables!$D$5:$D$65,MATCH($A48,Variables!$A$5:$A$65,0)))&"."&Z$5 | AA48: =INDEX(MTInputs!$J$1:$AZ$415,$D48,MATCH(AA$5,MTInputs!$J$5:$AZ$5,0)) | AB48: =INDEX(MTInputs!$J$1:$AZ$415,$D48,MATCH(AB$5,MTInputs!$J$5:$AZ$5,0)) | AC48: =INDEX(MTInputs!$J$1:$AZ$415,$D48,MATCH(AC$5,MTInputs!$J$5:$AZ$5,0)) | AD48: =INDEX(MTInputs!$J$1:$AZ$415,$D48,MATCH(AD$5,MTInputs!$J$5:$AZ$5,0)) | AE48: =INDEX(MTInputs!$J$1:$AZ$415,$D48,MATCH(AE$5,MTInputs!$J$5:$AZ$5,0)) | AF48: =INDEX(MTInputs!$J$1:$AZ$415,$D48,MATCH(AF$5,MTInputs!$J$5:$AZ$5,0)) | AG48: =INDEX(MTInputs!$J$1:$AZ$415,$D48,MATCH(AG$5,MTInputs!$J$5:$AZ$5,0)) | AH48: =INDEX(MTInputs!$J$1:$AZ$415,$D48,MATCH(AH$5,MTInputs!$J$5:$AZ$5,0)) | ... AN48: =INDEX(MTInputs!$J$1:$AZ$415,$D48,MATCH(AN$5,MTInputs!$J$5:$AZ$5,0))
A49: fpr.s | B49: coa | C49: ind | D49: 144 | H49: =INDEX(Variables!$B$5:$B$65,MATCH($A49,Variables!$A$5:$A$65,0))&IF($C49="",""," | "&INDEX(Mapping!$B$5:$B$25,MATCH($C49,Mapping!$A$5:$A$25,0))&" | "&INDEX(Mapping!$B$29:$B$38,MATCH($B49,Mapping!$A$29:$A$38,0))) | I49: =INDEX(Variables!$C$5:$C$65,MATCH($A49,Variables!$A$5:$A$65,0)) | J49: =INDEX(Variables!$E$5:$E$65,MATCH($A49,Variables!$A$5:$A$65,0)) | K49: =LOWER(Settings!$C$4)&".mit."&$A49&IF($C49="","","."&$C49&"."&$B49)&IF(INDEX(Variables!$D$5:$D$65,MATCH($A49,Variables!$A$5:$A$65,0))="","","."&INDEX(Variables!$D$5:$D$65,MATCH($A49,Variables!$A$5:$A$65,0)))&"."&K$5 | L49: =INDEX(MTInputs!$J$1:$AZ$415,$D49,MATCH(L$5,MTInputs!$J$5:$AZ$5,0)) | M49: =INDEX(MTInputs!$J$1:$AZ$415,$D49,MATCH(M$5,MTInputs!$J$5:$AZ$5,0)) | N49: =INDEX(MTInputs!$J$1:$AZ$415,$D49,MATCH(N$5,MTInputs!$J$5:$AZ$5,0)) | O49: =INDEX(MTInputs!$J$1:$AZ$415,$D49,MATCH(O$5,MTInputs!$J$5:$AZ$5,0)) | P49: =INDEX(MTInputs!$J$1:$AZ$415,$D49,MATCH(P$5,MTInputs!$J$5:$AZ$5,0)) | Q49: =INDEX(MTInputs!$J$1:$AZ$415,$D49,MATCH(Q$5,MTInputs!$J$5:$AZ$5,0)) | R49: =INDEX(MTInputs!$J$1:$AZ$415,$D49,MATCH(R$5,MTInputs!$J$5:$AZ$5,0)) | S49: =INDEX(MTInputs!$J$1:$AZ$415,$D49,MATCH(S$5,MTInputs!$J$5:$AZ$5,0)) | ... Y49: =INDEX(MTInputs!$J$1:$AZ$415,$D49,MATCH(Y$5,MTInputs!$J$5:$AZ$5,0)) | Z49: =LOWER(Settings!$C$4)&".mit."&$A49&IF($C49="","","."&$C49&"."&$B49)&IF(INDEX(Variables!$D$5:$D$65,MATCH($A49,Variables!$A$5:$A$65,0))="","","."&INDEX(Variables!$D$5:$D$65,MATCH($A49,Variables!$A$5:$A$65,0)))&"."&Z$5 | AA49: =INDEX(MTInputs!$J$1:$AZ$415,$D49,MATCH(AA$5,MTInputs!$J$5:$AZ$5,0)) | AB49: =INDEX(MTInputs!$J$1:$AZ$415,$D49,MATCH(AB$5,MTInputs!$J$5:$AZ$5,0)) | AC49: =INDEX(MTInputs!$J$1:$AZ$415,$D49,MATCH(AC$5,MTInputs!$J$5:$AZ$5,0)) | AD49: =INDEX(MTInputs!$J$1:$AZ$415,$D49,MATCH(AD$5,MTInputs!$J$5:$AZ$5,0)) | AE49: =INDEX(MTInputs!$J$1:$AZ$415,$D49,MATCH(AE$5,MTInputs!$J$5:$AZ$5,0)) | AF49: =INDEX(MTInputs!$J$1:$AZ$415,$D49,MATCH(AF$5,MTInputs!$J$5:$AZ$5,0)) | AG49: =INDEX(MTInputs!$J$1:$AZ$415,$D49,MATCH(AG$5,MTInputs!$J$5:$AZ$5,0)) | AH49: =INDEX(MTInputs!$J$1:$AZ$415,$D49,MATCH(AH$5,MTInputs!$J$5:$AZ$5,0)) | ... AN49: =INDEX(MTInputs!$J$1:$AZ$415,$D49,MATCH(AN$5,MTInputs!$J$5:$AZ$5,0))
A50: fpr.s | B50: nga | C50: pow | D50: 145 | H50: =INDEX(Variables!$B$5:$B$65,MATCH($A50,Variables!$A$5:$A$65,0))&IF($C50="",""," | "&INDEX(Mapping!$B$5:$B$25,MATCH($C50,Mapping!$A$5:$A$25,0))&" | "&INDEX(Mapping!$B$29:$B$38,MATCH($B50,Mapping!$A$29:$A$38,0))) | I50: =INDEX(Variables!$C$5:$C$65,MATCH($A50,Variables!$A$5:$A$65,0)) | J50: =INDEX(Variables!$E$5:$E$65,MATCH($A50,Variables!$A$5:$A$65,0)) | K50: =LOWER(Settings!$C$4)&".mit."&$A50&IF($C50="","","."&$C50&"."&$B50)&IF(INDEX(Variables!$D$5:$D$65,MATCH($A50,Variables!$A$5:$A$65,0))="","","."&INDEX(Variables!$D$5:$D$65,MATCH($A50,Variables!$A$5:$A$65,0)))&"."&K$5 | L50: =INDEX(MTInputs!$J$1:$AZ$415,$D50,MATCH(L$5,MTInputs!$J$5:$AZ$5,0)) | M50: =INDEX(MTInputs!$J$1:$AZ$415,$D50,MATCH(M$5,MTInputs!$J$5:$AZ$5,0)) | N50: =INDEX(MTInputs!$J$1:$AZ$415,$D50,MATCH(N$5,MTInputs!$J$5:$AZ$5,0)) | O50: =INDEX(MTInputs!$J$1:$AZ$415,$D50,MATCH(O$5,MTInputs!$J$5:$AZ$5,0)) | P50: =INDEX(MTInputs!$J$1:$AZ$415,$D50,MATCH(P$5,MTInputs!$J$5:$AZ$5,0)) | Q50: =INDEX(MTInputs!$J$1:$AZ$415,$D50,MATCH(Q$5,MTInputs!$J$5:$AZ$5,0)) | R50: =INDEX(MTInputs!$J$1:$AZ$415,$D50,MATCH(R$5,MTInputs!$J$5:$AZ$5,0)) | S50: =INDEX(MTInputs!$J$1:$AZ$415,$D50,MATCH(S$5,MTInputs!$J$5:$AZ$5,0)) | ... Y50: =INDEX(MTInputs!$J$1:$AZ$415,$D50,MATCH(Y$5,MTInputs!$J$5:$AZ$5,0)) | Z50: =LOWER(Settings!$C$4)&".mit."&$A50&IF($C50="","","."&$C50&"."&$B50)&IF(INDEX(Variables!$D$5:$D$65,MATCH($A50,Variables!$A$5:$A$65,0))="","","."&INDEX(Variables!$D$5:$D$65,MATCH($A50,Variables!$A$5:$A$65,0)))&"."&Z$5 | AA50: =INDEX(MTInputs!$J$1:$AZ$415,$D50,MATCH(AA$5,MTInputs!$J$5:$AZ$5,0)) | AB50: =INDEX(MTInputs!$J$1:$AZ$415,$D50,MATCH(AB$5,MTInputs!$J$5:$AZ$5,0)) | AC50: =INDEX(MTInputs!$J$1:$AZ$415,$D50,MATCH(AC$5,MTInputs!$J$5:$AZ$5,0)) | AD50: =INDEX(MTInputs!$J$1:$AZ$415,$D50,MATCH(AD$5,MTInputs!$J$5:$AZ$5,0)) | AE50: =INDEX(MTInputs!$J$1:$AZ$415,$D50,MATCH(AE$5,MTInputs!$J$5:$AZ$5,0)) | AF50: =INDEX(MTInputs!$J$1:$AZ$415,$D50,MATCH(AF$5,MTInputs!$J$5:$AZ$5,0)) | AG50: =INDEX(MTInputs!$J$1:$AZ$415,$D50,MATCH(AG$5,MTInputs!$J$5:$AZ$5,0)) | AH50: =INDEX(MTInputs!$J$1:$AZ$415,$D50,MATCH(AH$5,MTInputs!$J$5:$AZ$5,0)) | ... AN50: =INDEX(MTInputs!$J$1:$AZ$415,$D50,MATCH(AN$5,MTInputs!$J$5:$AZ$5,0))
A51: fpr.s | B51: nga | C51: res | D51: 146 | H51: =INDEX(Variables!$B$5:$B$65,MATCH($A51,Variables!$A$5:$A$65,0))&IF($C51="",""," | "&INDEX(Mapping!$B$5:$B$25,MATCH($C51,Mapping!$A$5:$A$25,0))&" | "&INDEX(Mapping!$B$29:$B$38,MATCH($B51,Mapping!$A$29:$A$38,0))) | I51: =INDEX(Variables!$C$5:$C$65,MATCH($A51,Variables!$A$5:$A$65,0)) | J51: =INDEX(Variables!$E$5:$E$65,MATCH($A51,Variables!$A$5:$A$65,0)) | K51: =LOWER(Settings!$C$4)&".mit."&$A51&IF($C51="","","."&$C51&"."&$B51)&IF(INDEX(Variables!$D$5:$D$65,MATCH($A51,Variables!$A$5:$A$65,0))="","","."&INDEX(Variables!$D$5:$D$65,MATCH($A51,Variables!$A$5:$A$65,0)))&"."&K$5 | L51: =INDEX(MTInputs!$J$1:$AZ$415,$D51,MATCH(L$5,MTInputs!$J$5:$AZ$5,0)) | M51: =INDEX(MTInputs!$J$1:$AZ$415,$D51,MATCH(M$5,MTInputs!$J$5:$AZ$5,0)) | N51: =INDEX(MTInputs!$J$1:$AZ$415,$D51,MATCH(N$5,MTInputs!$J$5:$AZ$5,0)) | O51: =INDEX(MTInputs!$J$1:$AZ$415,$D51,MATCH(O$5,MTInputs!$J$5:$AZ$5,0)) | P51: =INDEX(MTInputs!$J$1:$AZ$415,$D51,MATCH(P$5,MTInputs!$J$5:$AZ$5,0)) | Q51: =INDEX(MTInputs!$J$1:$AZ$415,$D51,MATCH(Q$5,MTInputs!$J$5:$AZ$5,0)) | R51: =INDEX(MTInputs!$J$1:$AZ$415,$D51,MATCH(R$5,MTInputs!$J$5:$AZ$5,0)) | S51: =INDEX(MTInputs!$J$1:$AZ$415,$D51,MATCH(S$5,MTInputs!$J$5:$AZ$5,0)) | ... Y51: =INDEX(MTInputs!$J$1:$AZ$415,$D51,MATCH(Y$5,MTInputs!$J$5:$AZ$5,0)) | Z51: =LOWER(Settings!$C$4)&".mit."&$A51&IF($C51="","","."&$C51&"."&$B51)&IF(INDEX(Variables!$D$5:$D$65,MATCH($A51,Variables!$A$5:$A$65,0))="","","."&INDEX(Variables!$D$5:$D$65,MATCH($A51,Variables!$A$5:$A$65,0)))&"."&Z$5 | AA51: =INDEX(MTInputs!$J$1:$AZ$415,$D51,MATCH(AA$5,MTInputs!$J$5:$AZ$5,0)) | AB51: =INDEX(MTInputs!$J$1:$AZ$415,$D51,MATCH(AB$5,MTInputs!$J$5:$AZ$5,0)) | AC51: =INDEX(MTInputs!$J$1:$AZ$415,$D51,MATCH(AC$5,MTInputs!$J$5:$AZ$5,0)) | AD51: =INDEX(MTInputs!$J$1:$AZ$415,$D51,MATCH(AD$5,MTInputs!$J$5:$AZ$5,0)) | AE51: =INDEX(MTInputs!$J$1:$AZ$415,$D51,MATCH(AE$5,MTInputs!$J$5:$AZ$5,0)) | AF51: =INDEX(MTInputs!$J$1:$AZ$415,$D51,MATCH(AF$5,MTInputs!$J$5:$AZ$5,0)) | AG51: =INDEX(MTInputs!$J$1:$AZ$415,$D51,MATCH(AG$5,MTInputs!$J$5:$AZ$5,0)) | AH51: =INDEX(MTInputs!$J$1:$AZ$415,$D51,MATCH(AH$5,MTInputs!$J$5:$AZ$5,0)) | ... AN51: =INDEX(MTInputs!$J$1:$AZ$415,$D51,MATCH(AN$5,MTInputs!$J$5:$AZ$5,0))
A52: fpr.s | B52: nga | C52: ind | D52: 147 | H52: =INDEX(Variables!$B$5:$B$65,MATCH($A52,Variables!$A$5:$A$65,0))&IF($C52="",""," | "&INDEX(Mapping!$B$5:$B$25,MATCH($C52,Mapping!$A$5:$A$25,0))&" | "&INDEX(Mapping!$B$29:$B$38,MATCH($B52,Mapping!$A$29:$A$38,0))) | I52: =INDEX(Variables!$C$5:$C$65,MATCH($A52,Variables!$A$5:$A$65,0)) | J52: =INDEX(Variables!$E$5:$E$65,MATCH($A52,Variables!$A$5:$A$65,0)) | K52: =LOWER(Settings!$C$4)&".mit."&$A52&IF($C52="","","."&$C52&"."&$B52)&IF(INDEX(Variables!$D$5:$D$65,MATCH($A52,Variables!$A$5:$A$65,0))="","","."&INDEX(Variables!$D$5:$D$65,MATCH($A52,Variables!$A$5:$A$65,0)))&"."&K$5 | L52: =INDEX(MTInputs!$J$1:$AZ$415,$D52,MATCH(L$5,MTInputs!$J$5:$AZ$5,0)) | M52: =INDEX(MTInputs!$J$1:$AZ$415,$D52,MATCH(M$5,MTInputs!$J$5:$AZ$5,0)) | N52: =INDEX(MTInputs!$J$1:$AZ$415,$D52,MATCH(N$5,MTInputs!$J$5:$AZ$5,0)) | O52: =INDEX(MTInputs!$J$1:$AZ$415,$D52,MATCH(O$5,MTInputs!$J$5:$AZ$5,0)) | P52: =INDEX(MTInputs!$J$1:$AZ$415,$D52,MATCH(P$5,MTInputs!$J$5:$AZ$5,0)) | Q52: =INDEX(MTInputs!$J$1:$AZ$415,$D52,MATCH(Q$5,MTInputs!$J$5:$AZ$5,0)) | R52: =INDEX(MTInputs!$J$1:$AZ$415,$D52,MATCH(R$5,MTInputs!$J$5:$AZ$5,0)) | S52: =INDEX(MTInputs!$J$1:$AZ$415,$D52,MATCH(S$5,MTInputs!$J$5:$AZ$5,0)) | ... Y52: =INDEX(MTInputs!$J$1:$AZ$415,$D52,MATCH(Y$5,MTInputs!$J$5:$AZ$5,0)) | Z52: =LOWER(Settings!$C$4)&".mit."&$A52&IF($C52="","","."&$C52&"."&$B52)&IF(INDEX(Variables!$D$5:$D$65,MATCH($A52,Variables!$A$5:$A$65,0))="","","."&INDEX(Variables!$D$5:$D$65,MATCH($A52,Variables!$A$5:$A$65,0)))&"."&Z$5 | AA52: =INDEX(MTInputs!$J$1:$AZ$415,$D52,MATCH(AA$5,MTInputs!$J$5:$AZ$5,0)) | AB52: =INDEX(MTInputs!$J$1:$AZ$415,$D52,MATCH(AB$5,MTInputs!$J$5:$AZ$5,0)) | AC52: =INDEX(MTInputs!$J$1:$AZ$415,$D52,MATCH(AC$5,MTInputs!$J$5:$AZ$5,0)) | AD52: =INDEX(MTInputs!$J$1:$AZ$415,$D52,MATCH(AD$5,MTInputs!$J$5:$AZ$5,0)) | AE52: =INDEX(MTInputs!$J$1:$AZ$415,$D52,MATCH(AE$5,MTInputs!$J$5:$AZ$5,0)) | AF52: =INDEX(MTInputs!$J$1:$AZ$415,$D52,MATCH(AF$5,MTInputs!$J$5:$AZ$5,0)) | AG52: =INDEX(MTInputs!$J$1:$AZ$415,$D52,MATCH(AG$5,MTInputs!$J$5:$AZ$5,0)) | AH52: =INDEX(MTInputs!$J$1:$AZ$415,$D52,MATCH(AH$5,MTInputs!$J$5:$AZ$5,0)) | ... AN52: =INDEX(MTInputs!$J$1:$AZ$415,$D52,MATCH(AN$5,MTInputs!$J$5:$AZ$5,0))
A53: fpr.s | B53: ecy | C53: res | D53: 148 | H53: =INDEX(Variables!$B$5:$B$65,MATCH($A53,Variables!$A$5:$A$65,0))&IF($C53="",""," | "&INDEX(Mapping!$B$5:$B$25,MATCH($C53,Mapping!$A$5:$A$25,0))&" | "&INDEX(Mapping!$B$29:$B$38,MATCH($B53,Mapping!$A$29:$A$38,0))) | I53: =INDEX(Variables!$C$5:$C$65,MATCH($A53,Variables!$A$5:$A$65,0)) | J53: =INDEX(Variables!$E$5:$E$65,MATCH($A53,Variables!$A$5:$A$65,0)) | K53: =LOWER(Settings!$C$4)&".mit."&$A53&IF($C53="","","."&$C53&"."&$B53)&IF(INDEX(Variables!$D$5:$D$65,MATCH($A53,Variables!$A$5:$A$65,0))="","","."&INDEX(Variables!$D$5:$D$65,MATCH($A53,Variables!$A$5:$A$65,0)))&"."&K$5 | L53: =INDEX(MTInputs!$J$1:$AZ$415,$D53,MATCH(L$5,MTInputs!$J$5:$AZ$5,0)) | M53: =INDEX(MTInputs!$J$1:$AZ$415,$D53,MATCH(M$5,MTInputs!$J$5:$AZ$5,0)) | N53: =INDEX(MTInputs!$J$1:$AZ$415,$D53,MATCH(N$5,MTInputs!$J$5:$AZ$5,0)) | O53: =INDEX(MTInputs!$J$1:$AZ$415,$D53,MATCH(O$5,MTInputs!$J$5:$AZ$5,0)) | P53: =INDEX(MTInputs!$J$1:$AZ$415,$D53,MATCH(P$5,MTInputs!$J$5:$AZ$5,0)) | Q53: =INDEX(MTInputs!$J$1:$AZ$415,$D53,MATCH(Q$5,MTInputs!$J$5:$AZ$5,0)) | R53: =INDEX(MTInputs!$J$1:$AZ$415,$D53,MATCH(R$5,MTInputs!$J$5:$AZ$5,0)) | S53: =INDEX(MTInputs!$J$1:$AZ$415,$D53,MATCH(S$5,MTInputs!$J$5:$AZ$5,0)) | ... Y53: =INDEX(MTInputs!$J$1:$AZ$415,$D53,MATCH(Y$5,MTInputs!$J$5:$AZ$5,0)) | Z53: =LOWER(Settings!$C$4)&".mit."&$A53&IF($C53="","","."&$C53&"."&$B53)&IF(INDEX(Variables!$D$5:$D$65,MATCH($A53,Variables!$A$5:$A$65,0))="","","."&INDEX(Variables!$D$5:$D$65,MATCH($A53,Variables!$A$5:$A$65,0)))&"."&Z$5 | AA53: =INDEX(MTInputs!$J$1:$AZ$415,$D53,MATCH(AA$5,MTInputs!$J$5:$AZ$5,0)) | AB53: =INDEX(MTInputs!$J$1:$AZ$415,$D53,MATCH(AB$5,MTInputs!$J$5:$AZ$5,0)) | AC53: =INDEX(MTInputs!$J$1:$AZ$415,$D53,MATCH(AC$5,MTInputs!$J$5:$AZ$5,0)) | AD53: =INDEX(MTInputs!$J$1:$AZ$415,$D53,MATCH(AD$5,MTInputs!$J$5:$AZ$5,0)) | AE53: =INDEX(MTInputs!$J$1:$AZ$415,$D53,MATCH(AE$5,MTInputs!$J$5:$AZ$5,0)) | AF53: =INDEX(MTInputs!$J$1:$AZ$415,$D53,MATCH(AF$5,MTInputs!$J$5:$AZ$5,0)) | AG53: =INDEX(MTInputs!$J$1:$AZ$415,$D53,MATCH(AG$5,MTInputs!$J$5:$AZ$5,0)) | AH53: =INDEX(MTInputs!$J$1:$AZ$415,$D53,MATCH(AH$5,MTInputs!$J$5:$AZ$5,0)) | ... AN53: =INDEX(MTInputs!$J$1:$AZ$415,$D53,MATCH(AN$5,MTInputs!$J$5:$AZ$5,0))
A54: fpr.s | B54: ecy | C54: ind | D54: 149 | H54: =INDEX(Variables!$B$5:$B$65,MATCH($A54,Variables!$A$5:$A$65,0))&IF($C54="",""," | "&INDEX(Mapping!$B$5:$B$25,MATCH($C54,Mapping!$A$5:$A$25,0))&" | "&INDEX(Mapping!$B$29:$B$38,MATCH($B54,Mapping!$A$29:$A$38,0))) | I54: =INDEX(Variables!$C$5:$C$65,MATCH($A54,Variables!$A$5:$A$65,0)) | J54: =INDEX(Variables!$E$5:$E$65,MATCH($A54,Variables!$A$5:$A$65,0)) | K54: =LOWER(Settings!$C$4)&".mit."&$A54&IF($C54="","","."&$C54&"."&$B54)&IF(INDEX(Variables!$D$5:$D$65,MATCH($A54,Variables!$A$5:$A$65,0))="","","."&INDEX(Variables!$D$5:$D$65,MATCH($A54,Variables!$A$5:$A$65,0)))&"."&K$5 | L54: =INDEX(MTInputs!$J$1:$AZ$415,$D54,MATCH(L$5,MTInputs!$J$5:$AZ$5,0)) | M54: =INDEX(MTInputs!$J$1:$AZ$415,$D54,MATCH(M$5,MTInputs!$J$5:$AZ$5,0)) | N54: =INDEX(MTInputs!$J$1:$AZ$415,$D54,MATCH(N$5,MTInputs!$J$5:$AZ$5,0)) | O54: =INDEX(MTInputs!$J$1:$AZ$415,$D54,MATCH(O$5,MTInputs!$J$5:$AZ$5,0)) | P54: =INDEX(MTInputs!$J$1:$AZ$415,$D54,MATCH(P$5,MTInputs!$J$5:$AZ$5,0)) | Q54: =INDEX(MTInputs!$J$1:$AZ$415,$D54,MATCH(Q$5,MTInputs!$J$5:$AZ$5,0)) | R54: =INDEX(MTInputs!$J$1:$AZ$415,$D54,MATCH(R$5,MTInputs!$J$5:$AZ$5,0)) | S54: =INDEX(MTInputs!$J$1:$AZ$415,$D54,MATCH(S$5,MTInputs!$J$5:$AZ$5,0)) | ... Y54: =INDEX(MTInputs!$J$1:$AZ$415,$D54,MATCH(Y$5,MTInputs!$J$5:$AZ$5,0)) | Z54: =LOWER(Settings!$C$4)&".mit."&$A54&IF($C54="","","."&$C54&"."&$B54)&IF(INDEX(Variables!$D$5:$D$65,MATCH($A54,Variables!$A$5:$A$65,0))="","","."&INDEX(Variables!$D$5:$D$65,MATCH($A54,Variables!$A$5:$A$65,0)))&"."&Z$5 | AA54: =INDEX(MTInputs!$J$1:$AZ$415,$D54,MATCH(AA$5,MTInputs!$J$5:$AZ$5,0)) | AB54: =INDEX(MTInputs!$J$1:$AZ$415,$D54,MATCH(AB$5,MTInputs!$J$5:$AZ$5,0)) | AC54: =INDEX(MTInputs!$J$1:$AZ$415,$D54,MATCH(AC$5,MTInputs!$J$5:$AZ$5,0)) | AD54: =INDEX(MTInputs!$J$1:$AZ$415,$D54,MATCH(AD$5,MTInputs!$J$5:$AZ$5,0)) | AE54: =INDEX(MTInputs!$J$1:$AZ$415,$D54,MATCH(AE$5,MTInputs!$J$5:$AZ$5,0)) | AF54: =INDEX(MTInputs!$J$1:$AZ$415,$D54,MATCH(AF$5,MTInputs!$J$5:$AZ$5,0)) | AG54: =INDEX(MTInputs!$J$1:$AZ$415,$D54,MATCH(AG$5,MTInputs!$J$5:$AZ$5,0)) | AH54: =INDEX(MTInputs!$J$1:$AZ$415,$D54,MATCH(AH$5,MTInputs!$J$5:$AZ$5,0)) | ... AN54: =INDEX(MTInputs!$J$1:$AZ$415,$D54,MATCH(AN$5,MTInputs!$J$5:$AZ$5,0))
A55: fpr.s | B55: gso | C55: all | D55: 150 | H55: =INDEX(Variables!$B$5:$B$65,MATCH($A55,Variables!$A$5:$A$65,0))&IF($C55="",""," | "&INDEX(Mapping!$B$5:$B$25,MATCH($C55,Mapping!$A$5:$A$25,0))&" | "&INDEX(Mapping!$B$29:$B$38,MATCH($B55,Mapping!$A$29:$A$38,0))) | I55: =INDEX(Variables!$C$5:$C$65,MATCH($A55,Variables!$A$5:$A$65,0)) | J55: =INDEX(Variables!$E$5:$E$65,MATCH($A55,Variables!$A$5:$A$65,0)) | K55: =LOWER(Settings!$C$4)&".mit."&$A55&IF($C55="","","."&$C55&"."&$B55)&IF(INDEX(Variables!$D$5:$D$65,MATCH($A55,Variables!$A$5:$A$65,0))="","","."&INDEX(Variables!$D$5:$D$65,MATCH($A55,Variables!$A$5:$A$65,0)))&"."&K$5 | L55: =INDEX(MTInputs!$J$1:$AZ$415,$D55,MATCH(L$5,MTInputs!$J$5:$AZ$5,0)) | M55: =INDEX(MTInputs!$J$1:$AZ$415,$D55,MATCH(M$5,MTInputs!$J$5:$AZ$5,0)) | N55: =INDEX(MTInputs!$J$1:$AZ$415,$D55,MATCH(N$5,MTInputs!$J$5:$AZ$5,0)) | O55: =INDEX(MTInputs!$J$1:$AZ$415,$D55,MATCH(O$5,MTInputs!$J$5:$AZ$5,0)) | P55: =INDEX(MTInputs!$J$1:$AZ$415,$D55,MATCH(P$5,MTInputs!$J$5:$AZ$5,0)) | Q55: =INDEX(MTInputs!$J$1:$AZ$415,$D55,MATCH(Q$5,MTInputs!$J$5:$AZ$5,0)) | R55: =INDEX(MTInputs!$J$1:$AZ$415,$D55,MATCH(R$5,MTInputs!$J$5:$AZ$5,0)) | S55: =INDEX(MTInputs!$J$1:$AZ$415,$D55,MATCH(S$5,MTInputs!$J$5:$AZ$5,0)) | ... Y55: =INDEX(MTInputs!$J$1:$AZ$415,$D55,MATCH(Y$5,MTInputs!$J$5:$AZ$5,0)) | Z55: =LOWER(Settings!$C$4)&".mit."&$A55&IF($C55="","","."&$C55&"."&$B55)&IF(INDEX(Variables!$D$5:$D$65,MATCH($A55,Variables!$A$5:$A$65,0))="","","."&INDEX(Variables!$D$5:$D$65,MATCH($A55,Variables!$A$5:$A$65,0)))&"."&Z$5 | AA55: =INDEX(MTInputs!$J$1:$AZ$415,$D55,MATCH(AA$5,MTInputs!$J$5:$AZ$5,0)) | AB55: =INDEX(MTInputs!$J$1:$AZ$415,$D55,MATCH(AB$5,MTInputs!$J$5:$AZ$5,0)) | AC55: =INDEX(MTInputs!$J$1:$AZ$415,$D55,MATCH(AC$5,MTInputs!$J$5:$AZ$5,0)) | AD55: =INDEX(MTInputs!$J$1:$AZ$415,$D55,MATCH(AD$5,MTInputs!$J$5:$AZ$5,0)) | AE55: =INDEX(MTInputs!$J$1:$AZ$415,$D55,MATCH(AE$5,MTInputs!$J$5:$AZ$5,0)) | AF55: =INDEX(MTInputs!$J$1:$AZ$415,$D55,MATCH(AF$5,MTInputs!$J$5:$AZ$5,0)) | AG55: =INDEX(MTInputs!$J$1:$AZ$415,$D55,MATCH(AG$5,MTInputs!$J$5:$AZ$5,0)) | AH55: =INDEX(MTInputs!$J$1:$AZ$415,$D55,MATCH(AH$5,MTInputs!$J$5:$AZ$5,0)) | ... AN55: =INDEX(MTInputs!$J$1:$AZ$415,$D55,MATCH(AN$5,MTInputs!$J$5:$AZ$5,0))
A56: fpr.s | B56: die | C56: all | D56: 151 | H56: =INDEX(Variables!$B$5:$B$65,MATCH($A56,Variables!$A$5:$A$65,0))&IF($C56="",""," | "&INDEX(Mapping!$B$5:$B$25,MATCH($C56,Mapping!$A$5:$A$25,0))&" | "&INDEX(Mapping!$B$29:$B$38,MATCH($B56,Mapping!$A$29:$A$38,0))) | I56: =INDEX(Variables!$C$5:$C$65,MATCH($A56,Variables!$A$5:$A$65,0)) | J56: =INDEX(Variables!$E$5:$E$65,MATCH($A56,Variables!$A$5:$A$65,0)) | K56: =LOWER(Settings!$C$4)&".mit."&$A56&IF($C56="","","."&$C56&"."&$B56)&IF(INDEX(Variables!$D$5:$D$65,MATCH($A56,Variables!$A$5:$A$65,0))="","","."&INDEX(Variables!$D$5:$D$65,MATCH($A56,Variables!$A$5:$A$65,0)))&"."&K$5 | L56: =INDEX(MTInputs!$J$1:$AZ$415,$D56,MATCH(L$5,MTInputs!$J$5:$AZ$5,0)) | M56: =INDEX(MTInputs!$J$1:$AZ$415,$D56,MATCH(M$5,MTInputs!$J$5:$AZ$5,0)) | N56: =INDEX(MTInputs!$J$1:$AZ$415,$D56,MATCH(N$5,MTInputs!$J$5:$AZ$5,0)) | O56: =INDEX(MTInputs!$J$1:$AZ$415,$D56,MATCH(O$5,MTInputs!$J$5:$AZ$5,0)) | P56: =INDEX(MTInputs!$J$1:$AZ$415,$D56,MATCH(P$5,MTInputs!$J$5:$AZ$5,0)) | Q56: =INDEX(MTInputs!$J$1:$AZ$415,$D56,MATCH(Q$5,MTInputs!$J$5:$AZ$5,0)) | R56: =INDEX(MTInputs!$J$1:$AZ$415,$D56,MATCH(R$5,MTInputs!$J$5:$AZ$5,0)) | S56: =INDEX(MTInputs!$J$1:$AZ$415,$D56,MATCH(S$5,MTInputs!$J$5:$AZ$5,0)) | ... Y56: =INDEX(MTInputs!$J$1:$AZ$415,$D56,MATCH(Y$5,MTInputs!$J$5:$AZ$5,0)) | Z56: =LOWER(Settings!$C$4)&".mit."&$A56&IF($C56="","","."&$C56&"."&$B56)&IF(INDEX(Variables!$D$5:$D$65,MATCH($A56,Variables!$A$5:$A$65,0))="","","."&INDEX(Variables!$D$5:$D$65,MATCH($A56,Variables!$A$5:$A$65,0)))&"."&Z$5 | AA56: =INDEX(MTInputs!$J$1:$AZ$415,$D56,MATCH(AA$5,MTInputs!$J$5:$AZ$5,0)) | AB56: =INDEX(MTInputs!$J$1:$AZ$415,$D56,MATCH(AB$5,MTInputs!$J$5:$AZ$5,0)) | AC56: =INDEX(MTInputs!$J$1:$AZ$415,$D56,MATCH(AC$5,MTInputs!$J$5:$AZ$5,0)) | AD56: =INDEX(MTInputs!$J$1:$AZ$415,$D56,MATCH(AD$5,MTInputs!$J$5:$AZ$5,0)) | AE56: =INDEX(MTInputs!$J$1:$AZ$415,$D56,MATCH(AE$5,MTInputs!$J$5:$AZ$5,0)) | AF56: =INDEX(MTInputs!$J$1:$AZ$415,$D56,MATCH(AF$5,MTInputs!$J$5:$AZ$5,0)) | AG56: =INDEX(MTInputs!$J$1:$AZ$415,$D56,MATCH(AG$5,MTInputs!$J$5:$AZ$5,0)) | AH56: =INDEX(MTInputs!$J$1:$AZ$415,$D56,MATCH(AH$5,MTInputs!$J$5:$AZ$5,0)) | ... AN56: =INDEX(MTInputs!$J$1:$AZ$415,$D56,MATCH(AN$5,MTInputs!$J$5:$AZ$5,0))
A57: fpr.s | B57: lpg | C57: all | D57: 152 | H57: =INDEX(Variables!$B$5:$B$65,MATCH($A57,Variables!$A$5:$A$65,0))&IF($C57="",""," | "&INDEX(Mapping!$B$5:$B$25,MATCH($C57,Mapping!$A$5:$A$25,0))&" | "&INDEX(Mapping!$B$29:$B$38,MATCH($B57,Mapping!$A$29:$A$38,0))) | I57: =INDEX(Variables!$C$5:$C$65,MATCH($A57,Variables!$A$5:$A$65,0)) | J57: =INDEX(Variables!$E$5:$E$65,MATCH($A57,Variables!$A$5:$A$65,0)) | K57: =LOWER(Settings!$C$4)&".mit."&$A57&IF($C57="","","."&$C57&"."&$B57)&IF(INDEX(Variables!$D$5:$D$65,MATCH($A57,Variables!$A$5:$A$65,0))="","","."&INDEX(Variables!$D$5:$D$65,MATCH($A57,Variables!$A$5:$A$65,0)))&"."&K$5 | L57: =INDEX(MTInputs!$J$1:$AZ$415,$D57,MATCH(L$5,MTInputs!$J$5:$AZ$5,0)) | M57: =INDEX(MTInputs!$J$1:$AZ$415,$D57,MATCH(M$5,MTInputs!$J$5:$AZ$5,0)) | N57: =INDEX(MTInputs!$J$1:$AZ$415,$D57,MATCH(N$5,MTInputs!$J$5:$AZ$5,0)) | O57: =INDEX(MTInputs!$J$1:$AZ$415,$D57,MATCH(O$5,MTInputs!$J$5:$AZ$5,0)) | P57: =INDEX(MTInputs!$J$1:$AZ$415,$D57,MATCH(P$5,MTInputs!$J$5:$AZ$5,0)) | Q57: =INDEX(MTInputs!$J$1:$AZ$415,$D57,MATCH(Q$5,MTInputs!$J$5:$AZ$5,0)) | R57: =INDEX(MTInputs!$J$1:$AZ$415,$D57,MATCH(R$5,MTInputs!$J$5:$AZ$5,0)) | S57: =INDEX(MTInputs!$J$1:$AZ$415,$D57,MATCH(S$5,MTInputs!$J$5:$AZ$5,0)) | ... Y57: =INDEX(MTInputs!$J$1:$AZ$415,$D57,MATCH(Y$5,MTInputs!$J$5:$AZ$5,0)) | Z57: =LOWER(Settings!$C$4)&".mit."&$A57&IF($C57="","","."&$C57&"."&$B57)&IF(INDEX(Variables!$D$5:$D$65,MATCH($A57,Variables!$A$5:$A$65,0))="","","."&INDEX(Variables!$D$5:$D$65,MATCH($A57,Variables!$A$5:$A$65,0)))&"."&Z$5 | AA57: =INDEX(MTInputs!$J$1:$AZ$415,$D57,MATCH(AA$5,MTInputs!$J$5:$AZ$5,0)) | AB57: =INDEX(MTInputs!$J$1:$AZ$415,$D57,MATCH(AB$5,MTInputs!$J$5:$AZ$5,0)) | AC57: =INDEX(MTInputs!$J$1:$AZ$415,$D57,MATCH(AC$5,MTInputs!$J$5:$AZ$5,0)) | AD57: =INDEX(MTInputs!$J$1:$AZ$415,$D57,MATCH(AD$5,MTInputs!$J$5:$AZ$5,0)) | AE57: =INDEX(MTInputs!$J$1:$AZ$415,$D57,MATCH(AE$5,MTInputs!$J$5:$AZ$5,0)) | AF57: =INDEX(MTInputs!$J$1:$AZ$415,$D57,MATCH(AF$5,MTInputs!$J$5:$AZ$5,0)) | AG57: =INDEX(MTInputs!$J$1:$AZ$415,$D57,MATCH(AG$5,MTInputs!$J$5:$AZ$5,0)) | AH57: =INDEX(MTInputs!$J$1:$AZ$415,$D57,MATCH(AH$5,MTInputs!$J$5:$AZ$5,0)) | ... AN57: =INDEX(MTInputs!$J$1:$AZ$415,$D57,MATCH(AN$5,MTInputs!$J$5:$AZ$5,0))
A58: fpr.s | B58: ker | C58: all | D58: 153 | H58: =INDEX(Variables!$B$5:$B$65,MATCH($A58,Variables!$A$5:$A$65,0))&IF($C58="",""," | "&INDEX(Mapping!$B$5:$B$25,MATCH($C58,Mapping!$A$5:$A$25,0))&" | "&INDEX(Mapping!$B$29:$B$38,MATCH($B58,Mapping!$A$29:$A$38,0))) | I58: =INDEX(Variables!$C$5:$C$65,MATCH($A58,Variables!$A$5:$A$65,0)) | J58: =INDEX(Variables!$E$5:$E$65,MATCH($A58,Variables!$A$5:$A$65,0)) | K58: =LOWER(Settings!$C$4)&".mit."&$A58&IF($C58="","","."&$C58&"."&$B58)&IF(INDEX(Variables!$D$5:$D$65,MATCH($A58,Variables!$A$5:$A$65,0))="","","."&INDEX(Variables!$D$5:$D$65,MATCH($A58,Variables!$A$5:$A$65,0)))&"."&K$5 | L58: =INDEX(MTInputs!$J$1:$AZ$415,$D58,MATCH(L$5,MTInputs!$J$5:$AZ$5,0)) | M58: =INDEX(MTInputs!$J$1:$AZ$415,$D58,MATCH(M$5,MTInputs!$J$5:$AZ$5,0)) | N58: =INDEX(MTInputs!$J$1:$AZ$415,$D58,MATCH(N$5,MTInputs!$J$5:$AZ$5,0)) | O58: =INDEX(MTInputs!$J$1:$AZ$415,$D58,MATCH(O$5,MTInputs!$J$5:$AZ$5,0)) | P58: =INDEX(MTInputs!$J$1:$AZ$415,$D58,MATCH(P$5,MTInputs!$J$5:$AZ$5,0)) | Q58: =INDEX(MTInputs!$J$1:$AZ$415,$D58,MATCH(Q$5,MTInputs!$J$5:$AZ$5,0)) | R58: =INDEX(MTInputs!$J$1:$AZ$415,$D58,MATCH(R$5,MTInputs!$J$5:$AZ$5,0)) | S58: =INDEX(MTInputs!$J$1:$AZ$415,$D58,MATCH(S$5,MTInputs!$J$5:$AZ$5,0)) | ... Y58: =INDEX(MTInputs!$J$1:$AZ$415,$D58,MATCH(Y$5,MTInputs!$J$5:$AZ$5,0)) | Z58: =LOWER(Settings!$C$4)&".mit."&$A58&IF($C58="","","."&$C58&"."&$B58)&IF(INDEX(Variables!$D$5:$D$65,MATCH($A58,Variables!$A$5:$A$65,0))="","","."&INDEX(Variables!$D$5:$D$65,MATCH($A58,Variables!$A$5:$A$65,0)))&"."&Z$5 | AA58: =INDEX(MTInputs!$J$1:$AZ$415,$D58,MATCH(AA$5,MTInputs!$J$5:$AZ$5,0)) | AB58: =INDEX(MTInputs!$J$1:$AZ$415,$D58,MATCH(AB$5,MTInputs!$J$5:$AZ$5,0)) | AC58: =INDEX(MTInputs!$J$1:$AZ$415,$D58,MATCH(AC$5,MTInputs!$J$5:$AZ$5,0)) | AD58: =INDEX(MTInputs!$J$1:$AZ$415,$D58,MATCH(AD$5,MTInputs!$J$5:$AZ$5,0)) | AE58: =INDEX(MTInputs!$J$1:$AZ$415,$D58,MATCH(AE$5,MTInputs!$J$5:$AZ$5,0)) | AF58: =INDEX(MTInputs!$J$1:$AZ$415,$D58,MATCH(AF$5,MTInputs!$J$5:$AZ$5,0)) | AG58: =INDEX(MTInputs!$J$1:$AZ$415,$D58,MATCH(AG$5,MTInputs!$J$5:$AZ$5,0)) | AH58: =INDEX(MTInputs!$J$1:$AZ$415,$D58,MATCH(AH$5,MTInputs!$J$5:$AZ$5,0)) | ... AN58: =INDEX(MTInputs!$J$1:$AZ$415,$D58,MATCH(AN$5,MTInputs!$J$5:$AZ$5,0))
... A74: fpr.f | B74: bio | C74: all | D74: 169 | H74: =INDEX(Variables!$B$5:$B$65,MATCH($A74,Variables!$A$5:$A$65,0))&IF($C74="",""," | "&INDEX(Mapping!$B$5:$B$25,MATCH($C74,Mapping!$A$5:$A$25,0))&" | "&INDEX(Mapping!$B$29:$B$38,MATCH($B74,Mapping!$A$29:$A$38,0))) | I74: =INDEX(Variables!$C$5:$C$65,MATCH($A74,Variables!$A$5:$A$65,0)) | J74: =INDEX(Variables!$E$5:$E$65,MATCH($A74,Variables!$A$5:$A$65,0)) | K74: =LOWER(Settings!$C$4)&".mit."&$A74&IF($C74="","","."&$C74&"."&$B74)&IF(INDEX(Variables!$D$5:$D$65,MATCH($A74,Variables!$A$5:$A$65,0))="","","."&INDEX(Variables!$D$5:$D$65,MATCH($A74,Variables!$A$5:$A$65,0)))&"."&K$5 | L74: =INDEX(MTInputs!$J$1:$AZ$415,$D74,MATCH(L$5,MTInputs!$J$5:$AZ$5,0)) | M74: =INDEX(MTInputs!$J$1:$AZ$415,$D74,MATCH(M$5,MTInputs!$J$5:$AZ$5,0)) | N74: =INDEX(MTInputs!$J$1:$AZ$415,$D74,MATCH(N$5,MTInputs!$J$5:$AZ$5,0)) | O74: =INDEX(MTInputs!$J$1:$AZ$415,$D74,MATCH(O$5,MTInputs!$J$5:$AZ$5,0)) | P74: =INDEX(MTInputs!$J$1:$AZ$415,$D74,MATCH(P$5,MTInputs!$J$5:$AZ$5,0)) | Q74: =INDEX(MTInputs!$J$1:$AZ$415,$D74,MATCH(Q$5,MTInputs!$J$5:$AZ$5,0)) | R74: =INDEX(MTInputs!$J$1:$AZ$415,$D74,MATCH(R$5,MTInputs!$J$5:$AZ$5,0)) | S74: =INDEX(MTInputs!$J$1:$AZ$415,$D74,MATCH(S$5,MTInputs!$J$5:$AZ$5,0)) | ... Y74: =INDEX(MTInputs!$J$1:$AZ$415,$D74,MATCH(Y$5,MTInputs!$J$5:$AZ$5,0)) | Z74: =LOWER(Settings!$C$4)&".mit."&$A74&IF($C74="","","."&$C74&"."&$B74)&IF(INDEX(Variables!$D$5:$D$65,MATCH($A74,Variables!$A$5:$A$65,0))="","","."&INDEX(Variables!$D$5:$D$65,MATCH($A74,Variables!$A$5:$A$65,0)))&"."&Z$5 | AA74: =INDEX(MTInputs!$J$1:$AZ$415,$D74,MATCH(AA$5,MTInputs!$J$5:$AZ$5,0)) | AB74: =INDEX(MTInputs!$J$1:$AZ$415,$D74,MATCH(AB$5,MTInputs!$J$5:$AZ$5,0)) | AC74: =INDEX(MTInputs!$J$1:$AZ$415,$D74,MATCH(AC$5,MTInputs!$J$5:$AZ$5,0)) | AD74: =INDEX(MTInputs!$J$1:$AZ$415,$D74,MATCH(AD$5,MTInputs!$J$5:$AZ$5,0)) | AE74: =INDEX(MTInputs!$J$1:$AZ$415,$D74,MATCH(AE$5,MTInputs!$J$5:$AZ$5,0)) | AF74: =INDEX(MTInputs!$J$1:$AZ$415,$D74,MATCH(AF$5,MTInputs!$J$5:$AZ$5,0)) | AG74: =INDEX(MTInputs!$J$1:$AZ$415,$D74,MATCH(AG$5,MTInputs!$J$5:$AZ$5,0)) | AH74: =INDEX(MTInputs!$J$1:$AZ$415,$D74,MATCH(AH$5,MTInputs!$J$5:$AZ$5,0)) | ... AN74: =INDEX(MTInputs!$J$1:$AZ$415,$D74,MATCH(AN$5,MTInputs!$J$5:$AZ$5,0))
A75: fpr | B75: coa | C75: pow | H75: =INDEX(Variables!$B$5:$B$65,MATCH($A75,Variables!$A$5:$A$65,0))&IF($C75="",""," | "&INDEX(Mapping!$B$5:$B$25,MATCH($C75,Mapping!$A$5:$A$25,0))&" | "&INDEX(Mapping!$B$29:$B$38,MATCH($B75,Mapping!$A$29:$A$38,0))) | I75: =INDEX(Variables!$C$5:$C$65,MATCH($A75,Variables!$A$5:$A$65,0)) | J75: =INDEX(Variables!$E$5:$E$65,MATCH($A75,Variables!$A$5:$A$65,0)) | K75: =LOWER(Settings!$C$4)&".mit."&$A75&IF($C75="","","."&$C75&"."&$B75)&IF(INDEX(Variables!$D$5:$D$65,MATCH($A75,Variables!$A$5:$A$65,0))="","","."&INDEX(Variables!$D$5:$D$65,MATCH($A75,Variables!$A$5:$A$65,0)))&"."&K$5 | L75: =IF(L$4<L$45,0,L47+(L61-L47)/MAX(L$46-L$45,1)*(L$4-L$45)) | M75: =IF(M$4<M$45,0,M47+(M61-M47)/MAX(M$46-M$45,1)*(M$4-M$45)) | N75: =IF(N$4<N$45,0,N47+(N61-N47)/MAX(N$46-N$45,1)*(N$4-N$45)) | O75: =IF(O$4<O$45,0,O47+(O61-O47)/MAX(O$46-O$45,1)*(O$4-O$45)) | P75: =IF(P$4<P$45,0,P47+(P61-P47)/MAX(P$46-P$45,1)*(P$4-P$45)) | Q75: =IF(Q$4<Q$45,0,Q47+(Q61-Q47)/MAX(Q$46-Q$45,1)*(Q$4-Q$45)) | R75: =IF(R$4<R$45,0,R47+(R61-R47)/MAX(R$46-R$45,1)*(R$4-R$45)) | S75: =IF(S$4<S$45,0,S47+(S61-S47)/MAX(S$46-S$45,1)*(S$4-S$45)) | ... Y75: =IF(Y$4<Y$45,0,Y47+(Y61-Y47)/MAX(Y$46-Y$45,1)*(Y$4-Y$45)) | Z75: =LOWER(Settings!$C$4)&".mit."&$A75&IF($C75="","","."&$C75&"."&$B75)&IF(INDEX(Variables!$D$5:$D$65,MATCH($A75,Variables!$A$5:$A$65,0))="","","."&INDEX(Variables!$D$5:$D$65,MATCH($A75,Variables!$A$5:$A$65,0)))&"."&Z$5 | AA75: =IF(AA$4<AA$45,0,AA47+(AA61-AA47)/MAX(AA$46-AA$45,1)*(AA$4-AA$45)) | AB75: =IF(AB$4<AB$45,0,AB47+(AB61-AB47)/MAX(AB$46-AB$45,1)*(AB$4-AB$45)) | AC75: =IF(AC$4<AC$45,0,AC47+(AC61-AC47)/MAX(AC$46-AC$45,1)*(AC$4-AC$45)) | AD75: =IF(AD$4<AD$45,0,AD47+(AD61-AD47)/MAX(AD$46-AD$45,1)*(AD$4-AD$45)) | AE75: =IF(AE$4<AE$45,0,AE47+(AE61-AE47)/MAX(AE$46-AE$45,1)*(AE$4-AE$45)) | AF75: =IF(AF$4<AF$45,0,AF47+(AF61-AF47)/MAX(AF$46-AF$45,1)*(AF$4-AF$45)) | AG75: =IF(AG$4<AG$45,0,AG47+(AG61-AG47)/MAX(AG$46-AG$45,1)*(AG$4-AG$45)) | AH75: =IF(AH$4<AH$45,0,AH47+(AH61-AH47)/MAX(AH$46-AH$45,1)*(AH$4-AH$45)) | ... AN75: =IF(AN$4<AN$45,0,AN47+(AN61-AN47)/MAX(AN$46-AN$45,1)*(AN$4-AN$45))
A76: fpr | B76: coa | C76: res | H76: =INDEX(Variables!$B$5:$B$65,MATCH($A76,Variables!$A$5:$A$65,0))&IF($C76="",""," | "&INDEX(Mapping!$B$5:$B$25,MATCH($C76,Mapping!$A$5:$A$25,0))&" | "&INDEX(Mapping!$B$29:$B$38,MATCH($B76,Mapping!$A$29:$A$38,0))) | I76: =INDEX(Variables!$C$5:$C$65,MATCH($A76,Variables!$A$5:$A$65,0)) | J76: =INDEX(Variables!$E$5:$E$65,MATCH($A76,Variables!$A$5:$A$65,0)) | K76: =LOWER(Settings!$C$4)&".mit."&$A76&IF($C76="","","."&$C76&"."&$B76)&IF(INDEX(Variables!$D$5:$D$65,MATCH($A76,Variables!$A$5:$A$65,0))="","","."&INDEX(Variables!$D$5:$D$65,MATCH($A76,Variables!$A$5:$A$65,0)))&"."&K$5 | L76: =IF(L$4<L$45,0,L48+(L62-L48)/MAX(L$46-L$45,1)*(L$4-L$45)) | M76: =IF(M$4<M$45,0,M48+(M62-M48)/MAX(M$46-M$45,1)*(M$4-M$45)) | N76: =IF(N$4<N$45,0,N48+(N62-N48)/MAX(N$46-N$45,1)*(N$4-N$45)) | O76: =IF(O$4<O$45,0,O48+(O62-O48)/MAX(O$46-O$45,1)*(O$4-O$45)) | P76: =IF(P$4<P$45,0,P48+(P62-P48)/MAX(P$46-P$45,1)*(P$4-P$45)) | Q76: =IF(Q$4<Q$45,0,Q48+(Q62-Q48)/MAX(Q$46-Q$45,1)*(Q$4-Q$45)) | R76: =IF(R$4<R$45,0,R48+(R62-R48)/MAX(R$46-R$45,1)*(R$4-R$45)) | S76: =IF(S$4<S$45,0,S48+(S62-S48)/MAX(S$46-S$45,1)*(S$4-S$45)) | ... Y76: =IF(Y$4<Y$45,0,Y48+(Y62-Y48)/MAX(Y$46-Y$45,1)*(Y$4-Y$45)) | Z76: =LOWER(Settings!$C$4)&".mit."&$A76&IF($C76="","","."&$C76&"."&$B76)&IF(INDEX(Variables!$D$5:$D$65,MATCH($A76,Variables!$A$5:$A$65,0))="","","."&INDEX(Variables!$D$5:$D$65,MATCH($A76,Variables!$A$5:$A$65,0)))&"."&Z$5 | AA76: =IF(AA$4<AA$45,0,AA48+(AA62-AA48)/MAX(AA$46-AA$45,1)*(AA$4-AA$45)) | AB76: =IF(AB$4<AB$45,0,AB48+(AB62-AB48)/MAX(AB$46-AB$45,1)*(AB$4-AB$45)) | AC76: =IF(AC$4<AC$45,0,AC48+(AC62-AC48)/MAX(AC$46-AC$45,1)*(AC$4-AC$45)) | AD76: =IF(AD$4<AD$45,0,AD48+(AD62-AD48)/MAX(AD$46-AD$45,1)*(AD$4-AD$45)) | AE76: =IF(AE$4<AE$45,0,AE48+(AE62-AE48)/MAX(AE$46-AE$45,1)*(AE$4-AE$45)) | AF76: =IF(AF$4<AF$45,0,AF48+(AF62-AF48)/MAX(AF$46-AF$45,1)*(AF$4-AF$45)) | AG76: =IF(AG$4<AG$45,0,AG48+(AG62-AG48)/MAX(AG$46-AG$45,1)*(AG$4-AG$45)) | AH76: =IF(AH$4<AH$45,0,AH48+(AH62-AH48)/MAX(AH$46-AH$45,1)*(AH$4-AH$45)) | ... AN76: =IF(AN$4<AN$45,0,AN48+(AN62-AN48)/MAX(AN$46-AN$45,1)*(AN$4-AN$45))
A77: fpr | B77: coa | C77: ind | H77: =INDEX(Variables!$B$5:$B$65,MATCH($A77,Variables!$A$5:$A$65,0))&IF($C77="",""," | "&INDEX(Mapping!$B$5:$B$25,MATCH($C77,Mapping!$A$5:$A$25,0))&" | "&INDEX(Mapping!$B$29:$B$38,MATCH($B77,Mapping!$A$29:$A$38,0))) | I77: =INDEX(Variables!$C$5:$C$65,MATCH($A77,Variables!$A$5:$A$65,0)) | J77: =INDEX(Variables!$E$5:$E$65,MATCH($A77,Variables!$A$5:$A$65,0)) | K77: =LOWER(Settings!$C$4)&".mit."&$A77&IF($C77="","","."&$C77&"."&$B77)&IF(INDEX(Variables!$D$5:$D$65,MATCH($A77,Variables!$A$5:$A$65,0))="","","."&INDEX(Variables!$D$5:$D$65,MATCH($A77,Variables!$A$5:$A$65,0)))&"."&K$5 | L77: =IF(L$4<L$45,0,L49+(L63-L49)/MAX(L$46-L$45,1)*(L$4-L$45)) | M77: =IF(M$4<M$45,0,M49+(M63-M49)/MAX(M$46-M$45,1)*(M$4-M$45)) | N77: =IF(N$4<N$45,0,N49+(N63-N49)/MAX(N$46-N$45,1)*(N$4-N$45)) | O77: =IF(O$4<O$45,0,O49+(O63-O49)/MAX(O$46-O$45,1)*(O$4-O$45)) | P77: =IF(P$4<P$45,0,P49+(P63-P49)/MAX(P$46-P$45,1)*(P$4-P$45)) | Q77: =IF(Q$4<Q$45,0,Q49+(Q63-Q49)/MAX(Q$46-Q$45,1)*(Q$4-Q$45)) | R77: =IF(R$4<R$45,0,R49+(R63-R49)/MAX(R$46-R$45,1)*(R$4-R$45)) | S77: =IF(S$4<S$45,0,S49+(S63-S49)/MAX(S$46-S$45,1)*(S$4-S$45)) | ... Y77: =IF(Y$4<Y$45,0,Y49+(Y63-Y49)/MAX(Y$46-Y$45,1)*(Y$4-Y$45)) | Z77: =LOWER(Settings!$C$4)&".mit."&$A77&IF($C77="","","."&$C77&"."&$B77)&IF(INDEX(Variables!$D$5:$D$65,MATCH($A77,Variables!$A$5:$A$65,0))="","","."&INDEX(Variables!$D$5:$D$65,MATCH($A77,Variables!$A$5:$A$65,0)))&"."&Z$5 | AA77: =IF(AA$4<AA$45,0,AA49+(AA63-AA49)/MAX(AA$46-AA$45,1)*(AA$4-AA$45)) | AB77: =IF(AB$4<AB$45,0,AB49+(AB63-AB49)/MAX(AB$46-AB$45,1)*(AB$4-AB$45)) | AC77: =IF(AC$4<AC$45,0,AC49+(AC63-AC49)/MAX(AC$46-AC$45,1)*(AC$4-AC$45)) | AD77: =IF(AD$4<AD$45,0,AD49+(AD63-AD49)/MAX(AD$46-AD$45,1)*(AD$4-AD$45)) | AE77: =IF(AE$4<AE$45,0,AE49+(AE63-AE49)/MAX(AE$46-AE$45,1)*(AE$4-AE$45)) | AF77: =IF(AF$4<AF$45,0,AF49+(AF63-AF49)/MAX(AF$46-AF$45,1)*(AF$4-AF$45)) | AG77: =IF(AG$4<AG$45,0,AG49+(AG63-AG49)/MAX(AG$46-AG$45,1)*(AG$4-AG$45)) | AH77: =IF(AH$4<AH$45,0,AH49+(AH63-AH49)/MAX(AH$46-AH$45,1)*(AH$4-AH$45)) | ... AN77: =IF(AN$4<AN$45,0,AN49+(AN63-AN49)/MAX(AN$46-AN$45,1)*(AN$4-AN$45))
A78: fpr | B78: nga | C78: pow | H78: =INDEX(Variables!$B$5:$B$65,MATCH($A78,Variables!$A$5:$A$65,0))&IF($C78="",""," | "&INDEX(Mapping!$B$5:$B$25,MATCH($C78,Mapping!$A$5:$A$25,0))&" | "&INDEX(Mapping!$B$29:$B$38,MATCH($B78,Mapping!$A$29:$A$38,0))) | I78: =INDEX(Variables!$C$5:$C$65,MATCH($A78,Variables!$A$5:$A$65,0)) | J78: =INDEX(Variables!$E$5:$E$65,MATCH($A78,Variables!$A$5:$A$65,0)) | K78: =LOWER(Settings!$C$4)&".mit."&$A78&IF($C78="","","."&$C78&"."&$B78)&IF(INDEX(Variables!$D$5:$D$65,MATCH($A78,Variables!$A$5:$A$65,0))="","","."&INDEX(Variables!$D$5:$D$65,MATCH($A78,Variables!$A$5:$A$65,0)))&"."&K$5 | L78: =IF(L$4<L$45,0,L50+(L64-L50)/MAX(L$46-L$45,1)*(L$4-L$45)) | M78: =IF(M$4<M$45,0,M50+(M64-M50)/MAX(M$46-M$45,1)*(M$4-M$45)) | N78: =IF(N$4<N$45,0,N50+(N64-N50)/MAX(N$46-N$45,1)*(N$4-N$45)) | O78: =IF(O$4<O$45,0,O50+(O64-O50)/MAX(O$46-O$45,1)*(O$4-O$45)) | P78: =IF(P$4<P$45,0,P50+(P64-P50)/MAX(P$46-P$45,1)*(P$4-P$45)) | Q78: =IF(Q$4<Q$45,0,Q50+(Q64-Q50)/MAX(Q$46-Q$45,1)*(Q$4-Q$45)) | R78: =IF(R$4<R$45,0,R50+(R64-R50)/MAX(R$46-R$45,1)*(R$4-R$45)) | S78: =IF(S$4<S$45,0,S50+(S64-S50)/MAX(S$46-S$45,1)*(S$4-S$45)) | ... Y78: =IF(Y$4<Y$45,0,Y50+(Y64-Y50)/MAX(Y$46-Y$45,1)*(Y$4-Y$45)) | Z78: =LOWER(Settings!$C$4)&".mit."&$A78&IF($C78="","","."&$C78&"."&$B78)&IF(INDEX(Variables!$D$5:$D$65,MATCH($A78,Variables!$A$5:$A$65,0))="","","."&INDEX(Variables!$D$5:$D$65,MATCH($A78,Variables!$A$5:$A$65,0)))&"."&Z$5 | AA78: =IF(AA$4<AA$45,0,AA50+(AA64-AA50)/MAX(AA$46-AA$45,1)*(AA$4-AA$45)) | AB78: =IF(AB$4<AB$45,0,AB50+(AB64-AB50)/MAX(AB$46-AB$45,1)*(AB$4-AB$45)) | AC78: =IF(AC$4<AC$45,0,AC50+(AC64-AC50)/MAX(AC$46-AC$45,1)*(AC$4-AC$45)) | AD78: =IF(AD$4<AD$45,0,AD50+(AD64-AD50)/MAX(AD$46-AD$45,1)*(AD$4-AD$45)) | AE78: =IF(AE$4<AE$45,0,AE50+(AE64-AE50)/MAX(AE$46-AE$45,1)*(AE$4-AE$45)) | AF78: =IF(AF$4<AF$45,0,AF50+(AF64-AF50)/MAX(AF$46-AF$45,1)*(AF$4-AF$45)) | AG78: =IF(AG$4<AG$45,0,AG50+(AG64-AG50)/MAX(AG$46-AG$45,1)*(AG$4-AG$45)) | AH78: =IF(AH$4<AH$45,0,AH50+(AH64-AH50)/MAX(AH$46-AH$45,1)*(AH$4-AH$45)) | ... AN78: =IF(AN$4<AN$45,0,AN50+(AN64-AN50)/MAX(AN$46-AN$45,1)*(AN$4-AN$45))
A79: fpr | B79: nga | C79: res | H79: =INDEX(Variables!$B$5:$B$65,MATCH($A79,Variables!$A$5:$A$65,0))&IF($C79="",""," | "&INDEX(Mapping!$B$5:$B$25,MATCH($C79,Mapping!$A$5:$A$25,0))&" | "&INDEX(Mapping!$B$29:$B$38,MATCH($B79,Mapping!$A$29:$A$38,0))) | I79: =INDEX(Variables!$C$5:$C$65,MATCH($A79,Variables!$A$5:$A$65,0)) | J79: =INDEX(Variables!$E$5:$E$65,MATCH($A79,Variables!$A$5:$A$65,0)) | K79: =LOWER(Settings!$C$4)&".mit."&$A79&IF($C79="","","."&$C79&"."&$B79)&IF(INDEX(Variables!$D$5:$D$65,MATCH($A79,Variables!$A$5:$A$65,0))="","","."&INDEX(Variables!$D$5:$D$65,MATCH($A79,Variables!$A$5:$A$65,0)))&"."&K$5 | L79: =IF(L$4<L$45,0,L51+(L65-L51)/MAX(L$46-L$45,1)*(L$4-L$45)) | M79: =IF(M$4<M$45,0,M51+(M65-M51)/MAX(M$46-M$45,1)*(M$4-M$45)) | N79: =IF(N$4<N$45,0,N51+(N65-N51)/MAX(N$46-N$45,1)*(N$4-N$45)) | O79: =IF(O$4<O$45,0,O51+(O65-O51)/MAX(O$46-O$45,1)*(O$4-O$45)) | P79: =IF(P$4<P$45,0,P51+(P65-P51)/MAX(P$46-P$45,1)*(P$4-P$45)) | Q79: =IF(Q$4<Q$45,0,Q51+(Q65-Q51)/MAX(Q$46-Q$45,1)*(Q$4-Q$45)) | R79: =IF(R$4<R$45,0,R51+(R65-R51)/MAX(R$46-R$45,1)*(R$4-R$45)) | S79: =IF(S$4<S$45,0,S51+(S65-S51)/MAX(S$46-S$45,1)*(S$4-S$45)) | ... Y79: =IF(Y$4<Y$45,0,Y51+(Y65-Y51)/MAX(Y$46-Y$45,1)*(Y$4-Y$45)) | Z79: =LOWER(Settings!$C$4)&".mit."&$A79&IF($C79="","","."&$C79&"."&$B79)&IF(INDEX(Variables!$D$5:$D$65,MATCH($A79,Variables!$A$5:$A$65,0))="","","."&INDEX(Variables!$D$5:$D$65,MATCH($A79,Variables!$A$5:$A$65,0)))&"."&Z$5 | AA79: =IF(AA$4<AA$45,0,AA51+(AA65-AA51)/MAX(AA$46-AA$45,1)*(AA$4-AA$45)) | AB79: =IF(AB$4<AB$45,0,AB51+(AB65-AB51)/MAX(AB$46-AB$45,1)*(AB$4-AB$45)) | AC79: =IF(AC$4<AC$45,0,AC51+(AC65-AC51)/MAX(AC$46-AC$45,1)*(AC$4-AC$45)) | AD79: =IF(AD$4<AD$45,0,AD51+(AD65-AD51)/MAX(AD$46-AD$45,1)*(AD$4-AD$45)) | AE79: =IF(AE$4<AE$45,0,AE51+(AE65-AE51)/MAX(AE$46-AE$45,1)*(AE$4-AE$45)) | AF79: =IF(AF$4<AF$45,0,AF51+(AF65-AF51)/MAX(AF$46-AF$45,1)*(AF$4-AF$45)) | AG79: =IF(AG$4<AG$45,0,AG51+(AG65-AG51)/MAX(AG$46-AG$45,1)*(AG$4-AG$45)) | AH79: =IF(AH$4<AH$45,0,AH51+(AH65-AH51)/MAX(AH$46-AH$45,1)*(AH$4-AH$45)) | ... AN79: =IF(AN$4<AN$45,0,AN51+(AN65-AN51)/MAX(AN$46-AN$45,1)*(AN$4-AN$45))
A80: fpr | B80: nga | C80: ind | H80: =INDEX(Variables!$B$5:$B$65,MATCH($A80,Variables!$A$5:$A$65,0))&IF($C80="",""," | "&INDEX(Mapping!$B$5:$B$25,MATCH($C80,Mapping!$A$5:$A$25,0))&" | "&INDEX(Mapping!$B$29:$B$38,MATCH($B80,Mapping!$A$29:$A$38,0))) | I80: =INDEX(Variables!$C$5:$C$65,MATCH($A80,Variables!$A$5:$A$65,0)) | J80: =INDEX(Variables!$E$5:$E$65,MATCH($A80,Variables!$A$5:$A$65,0)) | K80: =LOWER(Settings!$C$4)&".mit."&$A80&IF($C80="","","."&$C80&"."&$B80)&IF(INDEX(Variables!$D$5:$D$65,MATCH($A80,Variables!$A$5:$A$65,0))="","","."&INDEX(Variables!$D$5:$D$65,MATCH($A80,Variables!$A$5:$A$65,0)))&"."&K$5 | L80: =IF(L$4<L$45,0,L52+(L66-L52)/MAX(L$46-L$45,1)*(L$4-L$45)) | M80: =IF(M$4<M$45,0,M52+(M66-M52)/MAX(M$46-M$45,1)*(M$4-M$45)) | N80: =IF(N$4<N$45,0,N52+(N66-N52)/MAX(N$46-N$45,1)*(N$4-N$45)) | O80: =IF(O$4<O$45,0,O52+(O66-O52)/MAX(O$46-O$45,1)*(O$4-O$45)) | P80: =IF(P$4<P$45,0,P52+(P66-P52)/MAX(P$46-P$45,1)*(P$4-P$45)) | Q80: =IF(Q$4<Q$45,0,Q52+(Q66-Q52)/MAX(Q$46-Q$45,1)*(Q$4-Q$45)) | R80: =IF(R$4<R$45,0,R52+(R66-R52)/MAX(R$46-R$45,1)*(R$4-R$45)) | S80: =IF(S$4<S$45,0,S52+(S66-S52)/MAX(S$46-S$45,1)*(S$4-S$45)) | ... Y80: =IF(Y$4<Y$45,0,Y52+(Y66-Y52)/MAX(Y$46-Y$45,1)*(Y$4-Y$45)) | Z80: =LOWER(Settings!$C$4)&".mit."&$A80&IF($C80="","","."&$C80&"."&$B80)&IF(INDEX(Variables!$D$5:$D$65,MATCH($A80,Variables!$A$5:$A$65,0))="","","."&INDEX(Variables!$D$5:$D$65,MATCH($A80,Variables!$A$5:$A$65,0)))&"."&Z$5 | AA80: =IF(AA$4<AA$45,0,AA52+(AA66-AA52)/MAX(AA$46-AA$45,1)*(AA$4-AA$45)) | AB80: =IF(AB$4<AB$45,0,AB52+(AB66-AB52)/MAX(AB$46-AB$45,1)*(AB$4-AB$45)) | AC80: =IF(AC$4<AC$45,0,AC52+(AC66-AC52)/MAX(AC$46-AC$45,1)*(AC$4-AC$45)) | AD80: =IF(AD$4<AD$45,0,AD52+(AD66-AD52)/MAX(AD$46-AD$45,1)*(AD$4-AD$45)) | AE80: =IF(AE$4<AE$45,0,AE52+(AE66-AE52)/MAX(AE$46-AE$45,1)*(AE$4-AE$45)) | AF80: =IF(AF$4<AF$45,0,AF52+(AF66-AF52)/MAX(AF$46-AF$45,1)*(AF$4-AF$45)) | AG80: =IF(AG$4<AG$45,0,AG52+(AG66-AG52)/MAX(AG$46-AG$45,1)*(AG$4-AG$45)) | AH80: =IF(AH$4<AH$45,0,AH52+(AH66-AH52)/MAX(AH$46-AH$45,1)*(AH$4-AH$45)) | ... AN80: =IF(AN$4<AN$45,0,AN52+(AN66-AN52)/MAX(AN$46-AN$45,1)*(AN$4-AN$45))
A81: fpr | B81: ecy | C81: res | H81: =INDEX(Variables!$B$5:$B$65,MATCH($A81,Variables!$A$5:$A$65,0))&IF($C81="",""," | "&INDEX(Mapping!$B$5:$B$25,MATCH($C81,Mapping!$A$5:$A$25,0))&" | "&INDEX(Mapping!$B$29:$B$38,MATCH($B81,Mapping!$A$29:$A$38,0))) | I81: =INDEX(Variables!$C$5:$C$65,MATCH($A81,Variables!$A$5:$A$65,0)) | J81: =INDEX(Variables!$E$5:$E$65,MATCH($A81,Variables!$A$5:$A$65,0)) | K81: =LOWER(Settings!$C$4)&".mit."&$A81&IF($C81="","","."&$C81&"."&$B81)&IF(INDEX(Variables!$D$5:$D$65,MATCH($A81,Variables!$A$5:$A$65,0))="","","."&INDEX(Variables!$D$5:$D$65,MATCH($A81,Variables!$A$5:$A$65,0)))&"."&K$5 | L81: =IF(L$4<L$45,0,L53+(L67-L53)/MAX(L$46-L$45,1)*(L$4-L$45)) | M81: =IF(M$4<M$45,0,M53+(M67-M53)/MAX(M$46-M$45,1)*(M$4-M$45)) | N81: =IF(N$4<N$45,0,N53+(N67-N53)/MAX(N$46-N$45,1)*(N$4-N$45)) | O81: =IF(O$4<O$45,0,O53+(O67-O53)/MAX(O$46-O$45,1)*(O$4-O$45)) | P81: =IF(P$4<P$45,0,P53+(P67-P53)/MAX(P$46-P$45,1)*(P$4-P$45)) | Q81: =IF(Q$4<Q$45,0,Q53+(Q67-Q53)/MAX(Q$46-Q$45,1)*(Q$4-Q$45)) | R81: =IF(R$4<R$45,0,R53+(R67-R53)/MAX(R$46-R$45,1)*(R$4-R$45)) | S81: =IF(S$4<S$45,0,S53+(S67-S53)/MAX(S$46-S$45,1)*(S$4-S$45)) | ... Y81: =IF(Y$4<Y$45,0,Y53+(Y67-Y53)/MAX(Y$46-Y$45,1)*(Y$4-Y$45)) | Z81: =LOWER(Settings!$C$4)&".mit."&$A81&IF($C81="","","."&$C81&"."&$B81)&IF(INDEX(Variables!$D$5:$D$65,MATCH($A81,Variables!$A$5:$A$65,0))="","","."&INDEX(Variables!$D$5:$D$65,MATCH($A81,Variables!$A$5:$A$65,0)))&"."&Z$5 | AA81: =IF(AA$4<AA$45,0,AA53+(AA67-AA53)/MAX(AA$46-AA$45,1)*(AA$4-AA$45)) | AB81: =IF(AB$4<AB$45,0,AB53+(AB67-AB53)/MAX(AB$46-AB$45,1)*(AB$4-AB$45)) | AC81: =IF(AC$4<AC$45,0,AC53+(AC67-AC53)/MAX(AC$46-AC$45,1)*(AC$4-AC$45)) | AD81: =IF(AD$4<AD$45,0,AD53+(AD67-AD53)/MAX(AD$46-AD$45,1)*(AD$4-AD$45)) | AE81: =IF(AE$4<AE$45,0,AE53+(AE67-AE53)/MAX(AE$46-AE$45,1)*(AE$4-AE$45)) | AF81: =IF(AF$4<AF$45,0,AF53+(AF67-AF53)/MAX(AF$46-AF$45,1)*(AF$4-AF$45)) | AG81: =IF(AG$4<AG$45,0,AG53+(AG67-AG53)/MAX(AG$46-AG$45,1)*(AG$4-AG$45)) | AH81: =IF(AH$4<AH$45,0,AH53+(AH67-AH53)/MAX(AH$46-AH$45,1)*(AH$4-AH$45)) | ... AN81: =IF(AN$4<AN$45,0,AN53+(AN67-AN53)/MAX(AN$46-AN$45,1)*(AN$4-AN$45))
A82: fpr | B82: ecy | C82: ind | H82: =INDEX(Variables!$B$5:$B$65,MATCH($A82,Variables!$A$5:$A$65,0))&IF($C82="",""," | "&INDEX(Mapping!$B$5:$B$25,MATCH($C82,Mapping!$A$5:$A$25,0))&" | "&INDEX(Mapping!$B$29:$B$38,MATCH($B82,Mapping!$A$29:$A$38,0))) | I82: =INDEX(Variables!$C$5:$C$65,MATCH($A82,Variables!$A$5:$A$65,0)) | J82: =INDEX(Variables!$E$5:$E$65,MATCH($A82,Variables!$A$5:$A$65,0)) | K82: =LOWER(Settings!$C$4)&".mit."&$A82&IF($C82="","","."&$C82&"."&$B82)&IF(INDEX(Variables!$D$5:$D$65,MATCH($A82,Variables!$A$5:$A$65,0))="","","."&INDEX(Variables!$D$5:$D$65,MATCH($A82,Variables!$A$5:$A$65,0)))&"."&K$5 | L82: =IF(L$4<L$45,0,L54+(L68-L54)/MAX(L$46-L$45,1)*(L$4-L$45)) | M82: =IF(M$4<M$45,0,M54+(M68-M54)/MAX(M$46-M$45,1)*(M$4-M$45)) | N82: =IF(N$4<N$45,0,N54+(N68-N54)/MAX(N$46-N$45,1)*(N$4-N$45)) | O82: =IF(O$4<O$45,0,O54+(O68-O54)/MAX(O$46-O$45,1)*(O$4-O$45)) | P82: =IF(P$4<P$45,0,P54+(P68-P54)/MAX(P$46-P$45,1)*(P$4-P$45)) | Q82: =IF(Q$4<Q$45,0,Q54+(Q68-Q54)/MAX(Q$46-Q$45,1)*(Q$4-Q$45)) | R82: =IF(R$4<R$45,0,R54+(R68-R54)/MAX(R$46-R$45,1)*(R$4-R$45)) | S82: =IF(S$4<S$45,0,S54+(S68-S54)/MAX(S$46-S$45,1)*(S$4-S$45)) | ... Y82: =IF(Y$4<Y$45,0,Y54+(Y68-Y54)/MAX(Y$46-Y$45,1)*(Y$4-Y$45)) | Z82: =LOWER(Settings!$C$4)&".mit."&$A82&IF($C82="","","."&$C82&"."&$B82)&IF(INDEX(Variables!$D$5:$D$65,MATCH($A82,Variables!$A$5:$A$65,0))="","","."&INDEX(Variables!$D$5:$D$65,MATCH($A82,Variables!$A$5:$A$65,0)))&"."&Z$5 | AA82: =IF(AA$4<AA$45,0,AA54+(AA68-AA54)/MAX(AA$46-AA$45,1)*(AA$4-AA$45)) | AB82: =IF(AB$4<AB$45,0,AB54+(AB68-AB54)/MAX(AB$46-AB$45,1)*(AB$4-AB$45)) | AC82: =IF(AC$4<AC$45,0,AC54+(AC68-AC54)/MAX(AC$46-AC$45,1)*(AC$4-AC$45)) | AD82: =IF(AD$4<AD$45,0,AD54+(AD68-AD54)/MAX(AD$46-AD$45,1)*(AD$4-AD$45)) | AE82: =IF(AE$4<AE$45,0,AE54+(AE68-AE54)/MAX(AE$46-AE$45,1)*(AE$4-AE$45)) | AF82: =IF(AF$4<AF$45,0,AF54+(AF68-AF54)/MAX(AF$46-AF$45,1)*(AF$4-AF$45)) | AG82: =IF(AG$4<AG$45,0,AG54+(AG68-AG54)/MAX(AG$46-AG$45,1)*(AG$4-AG$45)) | AH82: =IF(AH$4<AH$45,0,AH54+(AH68-AH54)/MAX(AH$46-AH$45,1)*(AH$4-AH$45)) | ... AN82: =IF(AN$4<AN$45,0,AN54+(AN68-AN54)/MAX(AN$46-AN$45,1)*(AN$4-AN$45))
A83: fpr | B83: gso | C83: all | H83: =INDEX(Variables!$B$5:$B$65,MATCH($A83,Variables!$A$5:$A$65,0))&IF($C83="",""," | "&INDEX(Mapping!$B$5:$B$25,MATCH($C83,Mapping!$A$5:$A$25,0))&" | "&INDEX(Mapping!$B$29:$B$38,MATCH($B83,Mapping!$A$29:$A$38,0))) | I83: =INDEX(Variables!$C$5:$C$65,MATCH($A83,Variables!$A$5:$A$65,0)) | J83: =INDEX(Variables!$E$5:$E$65,MATCH($A83,Variables!$A$5:$A$65,0)) | K83: =LOWER(Settings!$C$4)&".mit."&$A83&IF($C83="","","."&$C83&"."&$B83)&IF(INDEX(Variables!$D$5:$D$65,MATCH($A83,Variables!$A$5:$A$65,0))="","","."&INDEX(Variables!$D$5:$D$65,MATCH($A83,Variables!$A$5:$A$65,0)))&"."&K$5 | L83: =IF(L$4<L$45,0,L55+(L69-L55)/MAX(L$46-L$45,1)*(L$4-L$45)) | M83: =IF(M$4<M$45,0,M55+(M69-M55)/MAX(M$46-M$45,1)*(M$4-M$45)) | N83: =IF(N$4<N$45,0,N55+(N69-N55)/MAX(N$46-N$45,1)*(N$4-N$45)) | O83: =IF(O$4<O$45,0,O55+(O69-O55)/MAX(O$46-O$45,1)*(O$4-O$45)) | P83: =IF(P$4<P$45,0,P55+(P69-P55)/MAX(P$46-P$45,1)*(P$4-P$45)) | Q83: =IF(Q$4<Q$45,0,Q55+(Q69-Q55)/MAX(Q$46-Q$45,1)*(Q$4-Q$45)) | R83: =IF(R$4<R$45,0,R55+(R69-R55)/MAX(R$46-R$45,1)*(R$4-R$45)) | S83: =IF(S$4<S$45,0,S55+(S69-S55)/MAX(S$46-S$45,1)*(S$4-S$45)) | ... Y83: =IF(Y$4<Y$45,0,Y55+(Y69-Y55)/MAX(Y$46-Y$45,1)*(Y$4-Y$45)) | Z83: =LOWER(Settings!$C$4)&".mit."&$A83&IF($C83="","","."&$C83&"."&$B83)&IF(INDEX(Variables!$D$5:$D$65,MATCH($A83,Variables!$A$5:$A$65,0))="","","."&INDEX(Variables!$D$5:$D$65,MATCH($A83,Variables!$A$5:$A$65,0)))&"."&Z$5 | AA83: =IF(AA$4<AA$45,0,AA55+(AA69-AA55)/MAX(AA$46-AA$45,1)*(AA$4-AA$45)) | AB83: =IF(AB$4<AB$45,0,AB55+(AB69-AB55)/MAX(AB$46-AB$45,1)*(AB$4-AB$45)) | AC83: =IF(AC$4<AC$45,0,AC55+(AC69-AC55)/MAX(AC$46-AC$45,1)*(AC$4-AC$45)) | AD83: =IF(AD$4<AD$45,0,AD55+(AD69-AD55)/MAX(AD$46-AD$45,1)*(AD$4-AD$45)) | AE83: =IF(AE$4<AE$45,0,AE55+(AE69-AE55)/MAX(AE$46-AE$45,1)*(AE$4-AE$45)) | AF83: =IF(AF$4<AF$45,0,AF55+(AF69-AF55)/MAX(AF$46-AF$45,1)*(AF$4-AF$45)) | AG83: =IF(AG$4<AG$45,0,AG55+(AG69-AG55)/MAX(AG$46-AG$45,1)*(AG$4-AG$45)) | AH83: =IF(AH$4<AH$45,0,AH55+(AH69-AH55)/MAX(AH$46-AH$45,1)*(AH$4-AH$45)) | ... AN83: =IF(AN$4<AN$45,0,AN55+(AN69-AN55)/MAX(AN$46-AN$45,1)*(AN$4-AN$45))
A84: fpr | B84: die | C84: all | H84: =INDEX(Variables!$B$5:$B$65,MATCH($A84,Variables!$A$5:$A$65,0))&IF($C84="",""," | "&INDEX(Mapping!$B$5:$B$25,MATCH($C84,Mapping!$A$5:$A$25,0))&" | "&INDEX(Mapping!$B$29:$B$38,MATCH($B84,Mapping!$A$29:$A$38,0))) | I84: =INDEX(Variables!$C$5:$C$65,MATCH($A84,Variables!$A$5:$A$65,0)) | J84: =INDEX(Variables!$E$5:$E$65,MATCH($A84,Variables!$A$5:$A$65,0)) | K84: =LOWER(Settings!$C$4)&".mit."&$A84&IF($C84="","","."&$C84&"."&$B84)&IF(INDEX(Variables!$D$5:$D$65,MATCH($A84,Variables!$A$5:$A$65,0))="","","."&INDEX(Variables!$D$5:$D$65,MATCH($A84,Variables!$A$5:$A$65,0)))&"."&K$5 | L84: =IF(L$4<L$45,0,L56+(L70-L56)/MAX(L$46-L$45,1)*(L$4-L$45)) | M84: =IF(M$4<M$45,0,M56+(M70-M56)/MAX(M$46-M$45,1)*(M$4-M$45)) | N84: =IF(N$4<N$45,0,N56+(N70-N56)/MAX(N$46-N$45,1)*(N$4-N$45)) | O84: =IF(O$4<O$45,0,O56+(O70-O56)/MAX(O$46-O$45,1)*(O$4-O$45)) | P84: =IF(P$4<P$45,0,P56+(P70-P56)/MAX(P$46-P$45,1)*(P$4-P$45)) | Q84: =IF(Q$4<Q$45,0,Q56+(Q70-Q56)/MAX(Q$46-Q$45,1)*(Q$4-Q$45)) | R84: =IF(R$4<R$45,0,R56+(R70-R56)/MAX(R$46-R$45,1)*(R$4-R$45)) | S84: =IF(S$4<S$45,0,S56+(S70-S56)/MAX(S$46-S$45,1)*(S$4-S$45)) | ... Y84: =IF(Y$4<Y$45,0,Y56+(Y70-Y56)/MAX(Y$46-Y$45,1)*(Y$4-Y$45)) | Z84: =LOWER(Settings!$C$4)&".mit."&$A84&IF($C84="","","."&$C84&"."&$B84)&IF(INDEX(Variables!$D$5:$D$65,MATCH($A84,Variables!$A$5:$A$65,0))="","","."&INDEX(Variables!$D$5:$D$65,MATCH($A84,Variables!$A$5:$A$65,0)))&"."&Z$5 | AA84: =IF(AA$4<AA$45,0,AA56+(AA70-AA56)/MAX(AA$46-AA$45,1)*(AA$4-AA$45)) | AB84: =IF(AB$4<AB$45,0,AB56+(AB70-AB56)/MAX(AB$46-AB$45,1)*(AB$4-AB$45)) | AC84: =IF(AC$4<AC$45,0,AC56+(AC70-AC56)/MAX(AC$46-AC$45,1)*(AC$4-AC$45)) | AD84: =IF(AD$4<AD$45,0,AD56+(AD70-AD56)/MAX(AD$46-AD$45,1)*(AD$4-AD$45)) | AE84: =IF(AE$4<AE$45,0,AE56+(AE70-AE56)/MAX(AE$46-AE$45,1)*(AE$4-AE$45)) | AF84: =IF(AF$4<AF$45,0,AF56+(AF70-AF56)/MAX(AF$46-AF$45,1)*(AF$4-AF$45)) | AG84: =IF(AG$4<AG$45,0,AG56+(AG70-AG56)/MAX(AG$46-AG$45,1)*(AG$4-AG$45)) | AH84: =IF(AH$4<AH$45,0,AH56+(AH70-AH56)/MAX(AH$46-AH$45,1)*(AH$4-AH$45)) | ... AN84: =IF(AN$4<AN$45,0,AN56+(AN70-AN56)/MAX(AN$46-AN$45,1)*(AN$4-AN$45))
A85: fpr | B85: lpg | C85: all | H85: =INDEX(Variables!$B$5:$B$65,MATCH($A85,Variables!$A$5:$A$65,0))&IF($C85="",""," | "&INDEX(Mapping!$B$5:$B$25,MATCH($C85,Mapping!$A$5:$A$25,0))&" | "&INDEX(Mapping!$B$29:$B$38,MATCH($B85,Mapping!$A$29:$A$38,0))) | I85: =INDEX(Variables!$C$5:$C$65,MATCH($A85,Variables!$A$5:$A$65,0)) | J85: =INDEX(Variables!$E$5:$E$65,MATCH($A85,Variables!$A$5:$A$65,0)) | K85: =LOWER(Settings!$C$4)&".mit."&$A85&IF($C85="","","."&$C85&"."&$B85)&IF(INDEX(Variables!$D$5:$D$65,MATCH($A85,Variables!$A$5:$A$65,0))="","","."&INDEX(Variables!$D$5:$D$65,MATCH($A85,Variables!$A$5:$A$65,0)))&"."&K$5 | L85: =IF(L$4<L$45,0,L57+(L71-L57)/MAX(L$46-L$45,1)*(L$4-L$45)) | M85: =IF(M$4<M$45,0,M57+(M71-M57)/MAX(M$46-M$45,1)*(M$4-M$45)) | N85: =IF(N$4<N$45,0,N57+(N71-N57)/MAX(N$46-N$45,1)*(N$4-N$45)) | O85: =IF(O$4<O$45,0,O57+(O71-O57)/MAX(O$46-O$45,1)*(O$4-O$45)) | P85: =IF(P$4<P$45,0,P57+(P71-P57)/MAX(P$46-P$45,1)*(P$4-P$45)) | Q85: =IF(Q$4<Q$45,0,Q57+(Q71-Q57)/MAX(Q$46-Q$45,1)*(Q$4-Q$45)) | R85: =IF(R$4<R$45,0,R57+(R71-R57)/MAX(R$46-R$45,1)*(R$4-R$45)) | S85: =IF(S$4<S$45,0,S57+(S71-S57)/MAX(S$46-S$45,1)*(S$4-S$45)) | ... Y85: =IF(Y$4<Y$45,0,Y57+(Y71-Y57)/MAX(Y$46-Y$45,1)*(Y$4-Y$45)) | Z85: =LOWER(Settings!$C$4)&".mit."&$A85&IF($C85="","","."&$C85&"."&$B85)&IF(INDEX(Variables!$D$5:$D$65,MATCH($A85,Variables!$A$5:$A$65,0))="","","."&INDEX(Variables!$D$5:$D$65,MATCH($A85,Variables!$A$5:$A$65,0)))&"."&Z$5 | AA85: =IF(AA$4<AA$45,0,AA57+(AA71-AA57)/MAX(AA$46-AA$45,1)*(AA$4-AA$45)) | AB85: =IF(AB$4<AB$45,0,AB57+(AB71-AB57)/MAX(AB$46-AB$45,1)*(AB$4-AB$45)) | AC85: =IF(AC$4<AC$45,0,AC57+(AC71-AC57)/MAX(AC$46-AC$45,1)*(AC$4-AC$45)) | AD85: =IF(AD$4<AD$45,0,AD57+(AD71-AD57)/MAX(AD$46-AD$45,1)*(AD$4-AD$45)) | AE85: =IF(AE$4<AE$45,0,AE57+(AE71-AE57)/MAX(AE$46-AE$45,1)*(AE$4-AE$45)) | AF85: =IF(AF$4<AF$45,0,AF57+(AF71-AF57)/MAX(AF$46-AF$45,1)*(AF$4-AF$45)) | AG85: =IF(AG$4<AG$45,0,AG57+(AG71-AG57)/MAX(AG$46-AG$45,1)*(AG$4-AG$45)) | AH85: =IF(AH$4<AH$45,0,AH57+(AH71-AH57)/MAX(AH$46-AH$45,1)*(AH$4-AH$45)) | ... AN85: =IF(AN$4<AN$45,0,AN57+(AN71-AN57)/MAX(AN$46-AN$45,1)*(AN$4-AN$45))
A86: fpr | B86: ker | C86: all | H86: =INDEX(Variables!$B$5:$B$65,MATCH($A86,Variables!$A$5:$A$65,0))&IF($C86="",""," | "&INDEX(Mapping!$B$5:$B$25,MATCH($C86,Mapping!$A$5:$A$25,0))&" | "&INDEX(Mapping!$B$29:$B$38,MATCH($B86,Mapping!$A$29:$A$38,0))) | I86: =INDEX(Variables!$C$5:$C$65,MATCH($A86,Variables!$A$5:$A$65,0)) | J86: =INDEX(Variables!$E$5:$E$65,MATCH($A86,Variables!$A$5:$A$65,0)) | K86: =LOWER(Settings!$C$4)&".mit."&$A86&IF($C86="","","."&$C86&"."&$B86)&IF(INDEX(Variables!$D$5:$D$65,MATCH($A86,Variables!$A$5:$A$65,0))="","","."&INDEX(Variables!$D$5:$D$65,MATCH($A86,Variables!$A$5:$A$65,0)))&"."&K$5 | L86: =IF(L$4<L$45,0,L58+(L72-L58)/MAX(L$46-L$45,1)*(L$4-L$45)) | M86: =IF(M$4<M$45,0,M58+(M72-M58)/MAX(M$46-M$45,1)*(M$4-M$45)) | N86: =IF(N$4<N$45,0,N58+(N72-N58)/MAX(N$46-N$45,1)*(N$4-N$45)) | O86: =IF(O$4<O$45,0,O58+(O72-O58)/MAX(O$46-O$45,1)*(O$4-O$45)) | P86: =IF(P$4<P$45,0,P58+(P72-P58)/MAX(P$46-P$45,1)*(P$4-P$45)) | Q86: =IF(Q$4<Q$45,0,Q58+(Q72-Q58)/MAX(Q$46-Q$45,1)*(Q$4-Q$45)) | R86: =IF(R$4<R$45,0,R58+(R72-R58)/MAX(R$46-R$45,1)*(R$4-R$45)) | S86: =IF(S$4<S$45,0,S58+(S72-S58)/MAX(S$46-S$45,1)*(S$4-S$45)) | ... Y86: =IF(Y$4<Y$45,0,Y58+(Y72-Y58)/MAX(Y$46-Y$45,1)*(Y$4-Y$45)) | Z86: =LOWER(Settings!$C$4)&".mit."&$A86&IF($C86="","","."&$C86&"."&$B86)&IF(INDEX(Variables!$D$5:$D$65,MATCH($A86,Variables!$A$5:$A$65,0))="","","."&INDEX(Variables!$D$5:$D$65,MATCH($A86,Variables!$A$5:$A$65,0)))&"."&Z$5 | AA86: =IF(AA$4<AA$45,0,AA58+(AA72-AA58)/MAX(AA$46-AA$45,1)*(AA$4-AA$45)) | AB86: =IF(AB$4<AB$45,0,AB58+(AB72-AB58)/MAX(AB$46-AB$45,1)*(AB$4-AB$45)) | AC86: =IF(AC$4<AC$45,0,AC58+(AC72-AC58)/MAX(AC$46-AC$45,1)*(AC$4-AC$45)) | AD86: =IF(AD$4<AD$45,0,AD58+(AD72-AD58)/MAX(AD$46-AD$45,1)*(AD$4-AD$45)) | AE86: =IF(AE$4<AE$45,0,AE58+(AE72-AE58)/MAX(AE$46-AE$45,1)*(AE$4-AE$45)) | AF86: =IF(AF$4<AF$45,0,AF58+(AF72-AF58)/MAX(AF$46-AF$45,1)*(AF$4-AF$45)) | AG86: =IF(AG$4<AG$45,0,AG58+(AG72-AG58)/MAX(AG$46-AG$45,1)*(AG$4-AG$45)) | AH86: =IF(AH$4<AH$45,0,AH58+(AH72-AH58)/MAX(AH$46-AH$45,1)*(AH$4-AH$45)) | ... AN86: =IF(AN$4<AN$45,0,AN58+(AN72-AN58)/MAX(AN$46-AN$45,1)*(AN$4-AN$45))
... A88: fpr | B88: bio | C88: all | H88: =INDEX(Variables!$B$5:$B$65,MATCH($A88,Variables!$A$5:$A$65,0))&IF($C88="",""," | "&INDEX(Mapping!$B$5:$B$25,MATCH($C88,Mapping!$A$5:$A$25,0))&" | "&INDEX(Mapping!$B$29:$B$38,MATCH($B88,Mapping!$A$29:$A$38,0))) | I88: =INDEX(Variables!$C$5:$C$65,MATCH($A88,Variables!$A$5:$A$65,0)) | J88: =INDEX(Variables!$E$5:$E$65,MATCH($A88,Variables!$A$5:$A$65,0)) | K88: =LOWER(Settings!$C$4)&".mit."&$A88&IF($C88="","","."&$C88&"."&$B88)&IF(INDEX(Variables!$D$5:$D$65,MATCH($A88,Variables!$A$5:$A$65,0))="","","."&INDEX(Variables!$D$5:$D$65,MATCH($A88,Variables!$A$5:$A$65,0)))&"."&K$5 | L88: =IF(L$4<L$45,0,L60+(L74-L60)/MAX(L$46-L$45,1)*(L$4-L$45)) | M88: =IF(M$4<M$45,0,M60+(M74-M60)/MAX(M$46-M$45,1)*(M$4-M$45)) | N88: =IF(N$4<N$45,0,N60+(N74-N60)/MAX(N$46-N$45,1)*(N$4-N$45)) | O88: =IF(O$4<O$45,0,O60+(O74-O60)/MAX(O$46-O$45,1)*(O$4-O$45)) | P88: =IF(P$4<P$45,0,P60+(P74-P60)/MAX(P$46-P$45,1)*(P$4-P$45)) | Q88: =IF(Q$4<Q$45,0,Q60+(Q74-Q60)/MAX(Q$46-Q$45,1)*(Q$4-Q$45)) | R88: =IF(R$4<R$45,0,R60+(R74-R60)/MAX(R$46-R$45,1)*(R$4-R$45)) | S88: =IF(S$4<S$45,0,S60+(S74-S60)/MAX(S$46-S$45,1)*(S$4-S$45)) | ... Y88: =IF(Y$4<Y$45,0,Y60+(Y74-Y60)/MAX(Y$46-Y$45,1)*(Y$4-Y$45)) | Z88: =LOWER(Settings!$C$4)&".mit."&$A88&IF($C88="","","."&$C88&"."&$B88)&IF(INDEX(Variables!$D$5:$D$65,MATCH($A88,Variables!$A$5:$A$65,0))="","","."&INDEX(Variables!$D$5:$D$65,MATCH($A88,Variables!$A$5:$A$65,0)))&"."&Z$5 | AA88: =IF(AA$4<AA$45,0,AA60+(AA74-AA60)/MAX(AA$46-AA$45,1)*(AA$4-AA$45)) | AB88: =IF(AB$4<AB$45,0,AB60+(AB74-AB60)/MAX(AB$46-AB$45,1)*(AB$4-AB$45)) | AC88: =IF(AC$4<AC$45,0,AC60+(AC74-AC60)/MAX(AC$46-AC$45,1)*(AC$4-AC$45)) | AD88: =IF(AD$4<AD$45,0,AD60+(AD74-AD60)/MAX(AD$46-AD$45,1)*(AD$4-AD$45)) | AE88: =IF(AE$4<AE$45,0,AE60+(AE74-AE60)/MAX(AE$46-AE$45,1)*(AE$4-AE$45)) | AF88: =IF(AF$4<AF$45,0,AF60+(AF74-AF60)/MAX(AF$46-AF$45,1)*(AF$4-AF$45)) | AG88: =IF(AG$4<AG$45,0,AG60+(AG74-AG60)/MAX(AG$46-AG$45,1)*(AG$4-AG$45)) | AH88: =IF(AH$4<AH$45,0,AH60+(AH74-AH60)/MAX(AH$46-AH$45,1)*(AH$4-AH$45)) | ... AN88: =IF(AN$4<AN$45,0,AN60+(AN74-AN60)/MAX(AN$46-AN$45,1)*(AN$4-AN$45))
H89: Feebates (MTInputs rows 53-64; rates in USD/tCO2)
A90: fb.yr0 | D90: 53 | H90: =INDEX(Variables!$B$5:$B$65,MATCH($A90,Variables!$A$5:$A$65,0))&IF($C90="",""," | "&INDEX(Mapping!$B$5:$B$25,MATCH($C90,Mapping!$A$5:$A$25,0))&" | "&INDEX(Mapping!$B$29:$B$38,MATCH($B90,Mapping!$A$29:$A$38,0))) | I90: =INDEX(Variables!$C$5:$C$65,MATCH($A90,Variables!$A$5:$A$65,0)) | J90: =INDEX(Variables!$E$5:$E$65,MATCH($A90,Variables!$A$5:$A$65,0)) | K90: =LOWER(Settings!$C$4)&".mit."&$A90&IF($C90="","","."&$C90&"."&$B90)&IF(INDEX(Variables!$D$5:$D$65,MATCH($A90,Variables!$A$5:$A$65,0))="","","."&INDEX(Variables!$D$5:$D$65,MATCH($A90,Variables!$A$5:$A$65,0)))&"."&K$5 | L90: =INDEX(MTInputs!$J$1:$AZ$415,$D90,MATCH(L$5,MTInputs!$J$5:$AZ$5,0)) | M90: =INDEX(MTInputs!$J$1:$AZ$415,$D90,MATCH(M$5,MTInputs!$J$5:$AZ$5,0)) | N90: =INDEX(MTInputs!$J$1:$AZ$415,$D90,MATCH(N$5,MTInputs!$J$5:$AZ$5,0)) | O90: =INDEX(MTInputs!$J$1:$AZ$415,$D90,MATCH(O$5,MTInputs!$J$5:$AZ$5,0)) | P90: =INDEX(MTInputs!$J$1:$AZ$415,$D90,MATCH(P$5,MTInputs!$J$5:$AZ$5,0)) | Q90: =INDEX(MTInputs!$J$1:$AZ$415,$D90,MATCH(Q$5,MTInputs!$J$5:$AZ$5,0)) | R90: =INDEX(MTInputs!$J$1:$AZ$415,$D90,MATCH(R$5,MTInputs!$J$5:$AZ$5,0)) | S90: =INDEX(MTInputs!$J$1:$AZ$415,$D90,MATCH(S$5,MTInputs!$J$5:$AZ$5,0)) | ... Y90: =INDEX(MTInputs!$J$1:$AZ$415,$D90,MATCH(Y$5,MTInputs!$J$5:$AZ$5,0)) | Z90: =LOWER(Settings!$C$4)&".mit."&$A90&IF($C90="","","."&$C90&"."&$B90)&IF(INDEX(Variables!$D$5:$D$65,MATCH($A90,Variables!$A$5:$A$65,0))="","","."&INDEX(Variables!$D$5:$D$65,MATCH($A90,Variables!$A$5:$A$65,0)))&"."&Z$5 | AA90: =INDEX(MTInputs!$J$1:$AZ$415,$D90,MATCH(AA$5,MTInputs!$J$5:$AZ$5,0)) | AB90: =INDEX(MTInputs!$J$1:$AZ$415,$D90,MATCH(AB$5,MTInputs!$J$5:$AZ$5,0)) | AC90: =INDEX(MTInputs!$J$1:$AZ$415,$D90,MATCH(AC$5,MTInputs!$J$5:$AZ$5,0)) | AD90: =INDEX(MTInputs!$J$1:$AZ$415,$D90,MATCH(AD$5,MTInputs!$J$5:$AZ$5,0)) | AE90: =INDEX(MTInputs!$J$1:$AZ$415,$D90,MATCH(AE$5,MTInputs!$J$5:$AZ$5,0)) | AF90: =INDEX(MTInputs!$J$1:$AZ$415,$D90,MATCH(AF$5,MTInputs!$J$5:$AZ$5,0)) | AG90: =INDEX(MTInputs!$J$1:$AZ$415,$D90,MATCH(AG$5,MTInputs!$J$5:$AZ$5,0)) | AH90: =INDEX(MTInputs!$J$1:$AZ$415,$D90,MATCH(AH$5,MTInputs!$J$5:$AZ$5,0)) | ... AN90: =INDEX(MTInputs!$J$1:$AZ$415,$D90,MATCH(AN$5,MTInputs!$J$5:$AZ$5,0))
A91: fb.yr1 | D91: 54 | H91: =INDEX(Variables!$B$5:$B$65,MATCH($A91,Variables!$A$5:$A$65,0))&IF($C91="",""," | "&INDEX(Mapping!$B$5:$B$25,MATCH($C91,Mapping!$A$5:$A$25,0))&" | "&INDEX(Mapping!$B$29:$B$38,MATCH($B91,Mapping!$A$29:$A$38,0))) | I91: =INDEX(Variables!$C$5:$C$65,MATCH($A91,Variables!$A$5:$A$65,0)) | J91: =INDEX(Variables!$E$5:$E$65,MATCH($A91,Variables!$A$5:$A$65,0)) | K91: =LOWER(Settings!$C$4)&".mit."&$A91&IF($C91="","","."&$C91&"."&$B91)&IF(INDEX(Variables!$D$5:$D$65,MATCH($A91,Variables!$A$5:$A$65,0))="","","."&INDEX(Variables!$D$5:$D$65,MATCH($A91,Variables!$A$5:$A$65,0)))&"."&K$5 | L91: =INDEX(MTInputs!$J$1:$AZ$415,$D91,MATCH(L$5,MTInputs!$J$5:$AZ$5,0)) | M91: =INDEX(MTInputs!$J$1:$AZ$415,$D91,MATCH(M$5,MTInputs!$J$5:$AZ$5,0)) | N91: =INDEX(MTInputs!$J$1:$AZ$415,$D91,MATCH(N$5,MTInputs!$J$5:$AZ$5,0)) | O91: =INDEX(MTInputs!$J$1:$AZ$415,$D91,MATCH(O$5,MTInputs!$J$5:$AZ$5,0)) | P91: =INDEX(MTInputs!$J$1:$AZ$415,$D91,MATCH(P$5,MTInputs!$J$5:$AZ$5,0)) | Q91: =INDEX(MTInputs!$J$1:$AZ$415,$D91,MATCH(Q$5,MTInputs!$J$5:$AZ$5,0)) | R91: =INDEX(MTInputs!$J$1:$AZ$415,$D91,MATCH(R$5,MTInputs!$J$5:$AZ$5,0)) | S91: =INDEX(MTInputs!$J$1:$AZ$415,$D91,MATCH(S$5,MTInputs!$J$5:$AZ$5,0)) | ... Y91: =INDEX(MTInputs!$J$1:$AZ$415,$D91,MATCH(Y$5,MTInputs!$J$5:$AZ$5,0)) | Z91: =LOWER(Settings!$C$4)&".mit."&$A91&IF($C91="","","."&$C91&"."&$B91)&IF(INDEX(Variables!$D$5:$D$65,MATCH($A91,Variables!$A$5:$A$65,0))="","","."&INDEX(Variables!$D$5:$D$65,MATCH($A91,Variables!$A$5:$A$65,0)))&"."&Z$5 | AA91: =INDEX(MTInputs!$J$1:$AZ$415,$D91,MATCH(AA$5,MTInputs!$J$5:$AZ$5,0)) | AB91: =INDEX(MTInputs!$J$1:$AZ$415,$D91,MATCH(AB$5,MTInputs!$J$5:$AZ$5,0)) | AC91: =INDEX(MTInputs!$J$1:$AZ$415,$D91,MATCH(AC$5,MTInputs!$J$5:$AZ$5,0)) | AD91: =INDEX(MTInputs!$J$1:$AZ$415,$D91,MATCH(AD$5,MTInputs!$J$5:$AZ$5,0)) | AE91: =INDEX(MTInputs!$J$1:$AZ$415,$D91,MATCH(AE$5,MTInputs!$J$5:$AZ$5,0)) | AF91: =INDEX(MTInputs!$J$1:$AZ$415,$D91,MATCH(AF$5,MTInputs!$J$5:$AZ$5,0)) | AG91: =INDEX(MTInputs!$J$1:$AZ$415,$D91,MATCH(AG$5,MTInputs!$J$5:$AZ$5,0)) | AH91: =INDEX(MTInputs!$J$1:$AZ$415,$D91,MATCH(AH$5,MTInputs!$J$5:$AZ$5,0)) | ... AN91: =INDEX(MTInputs!$J$1:$AZ$415,$D91,MATCH(AN$5,MTInputs!$J$5:$AZ$5,0))
A92: fb.s | B92: all | C92: pow | D92: 56 | H92: =INDEX(Variables!$B$5:$B$65,MATCH($A92,Variables!$A$5:$A$65,0))&IF($C92="",""," | "&INDEX(Mapping!$B$5:$B$25,MATCH($C92,Mapping!$A$5:$A$25,0))&" | "&INDEX(Mapping!$B$29:$B$38,MATCH($B92,Mapping!$A$29:$A$38,0))) | I92: =INDEX(Variables!$C$5:$C$65,MATCH($A92,Variables!$A$5:$A$65,0)) | J92: =INDEX(Variables!$E$5:$E$65,MATCH($A92,Variables!$A$5:$A$65,0)) | K92: =LOWER(Settings!$C$4)&".mit."&$A92&IF($C92="","","."&$C92&"."&$B92)&IF(INDEX(Variables!$D$5:$D$65,MATCH($A92,Variables!$A$5:$A$65,0))="","","."&INDEX(Variables!$D$5:$D$65,MATCH($A92,Variables!$A$5:$A$65,0)))&"."&K$5 | L92: =INDEX(MTInputs!$J$1:$AZ$415,$D92,MATCH(L$5,MTInputs!$J$5:$AZ$5,0)) | M92: =INDEX(MTInputs!$J$1:$AZ$415,$D92,MATCH(M$5,MTInputs!$J$5:$AZ$5,0)) | N92: =INDEX(MTInputs!$J$1:$AZ$415,$D92,MATCH(N$5,MTInputs!$J$5:$AZ$5,0)) | O92: =INDEX(MTInputs!$J$1:$AZ$415,$D92,MATCH(O$5,MTInputs!$J$5:$AZ$5,0)) | P92: =INDEX(MTInputs!$J$1:$AZ$415,$D92,MATCH(P$5,MTInputs!$J$5:$AZ$5,0)) | Q92: =INDEX(MTInputs!$J$1:$AZ$415,$D92,MATCH(Q$5,MTInputs!$J$5:$AZ$5,0)) | R92: =INDEX(MTInputs!$J$1:$AZ$415,$D92,MATCH(R$5,MTInputs!$J$5:$AZ$5,0)) | S92: =INDEX(MTInputs!$J$1:$AZ$415,$D92,MATCH(S$5,MTInputs!$J$5:$AZ$5,0)) | ... Y92: =INDEX(MTInputs!$J$1:$AZ$415,$D92,MATCH(Y$5,MTInputs!$J$5:$AZ$5,0)) | Z92: =LOWER(Settings!$C$4)&".mit."&$A92&IF($C92="","","."&$C92&"."&$B92)&IF(INDEX(Variables!$D$5:$D$65,MATCH($A92,Variables!$A$5:$A$65,0))="","","."&INDEX(Variables!$D$5:$D$65,MATCH($A92,Variables!$A$5:$A$65,0)))&"."&Z$5 | AA92: =INDEX(MTInputs!$J$1:$AZ$415,$D92,MATCH(AA$5,MTInputs!$J$5:$AZ$5,0)) | AB92: =INDEX(MTInputs!$J$1:$AZ$415,$D92,MATCH(AB$5,MTInputs!$J$5:$AZ$5,0)) | AC92: =INDEX(MTInputs!$J$1:$AZ$415,$D92,MATCH(AC$5,MTInputs!$J$5:$AZ$5,0)) | AD92: =INDEX(MTInputs!$J$1:$AZ$415,$D92,MATCH(AD$5,MTInputs!$J$5:$AZ$5,0)) | AE92: =INDEX(MTInputs!$J$1:$AZ$415,$D92,MATCH(AE$5,MTInputs!$J$5:$AZ$5,0)) | AF92: =INDEX(MTInputs!$J$1:$AZ$415,$D92,MATCH(AF$5,MTInputs!$J$5:$AZ$5,0)) | AG92: =INDEX(MTInputs!$J$1:$AZ$415,$D92,MATCH(AG$5,MTInputs!$J$5:$AZ$5,0)) | AH92: =INDEX(MTInputs!$J$1:$AZ$415,$D92,MATCH(AH$5,MTInputs!$J$5:$AZ$5,0)) | ... AN92: =INDEX(MTInputs!$J$1:$AZ$415,$D92,MATCH(AN$5,MTInputs!$J$5:$AZ$5,0))
A93: fb.s | B93: all | C93: tra | D93: 57 | H93: =INDEX(Variables!$B$5:$B$65,MATCH($A93,Variables!$A$5:$A$65,0))&IF($C93="",""," | "&INDEX(Mapping!$B$5:$B$25,MATCH($C93,Mapping!$A$5:$A$25,0))&" | "&INDEX(Mapping!$B$29:$B$38,MATCH($B93,Mapping!$A$29:$A$38,0))) | I93: =INDEX(Variables!$C$5:$C$65,MATCH($A93,Variables!$A$5:$A$65,0)) | J93: =INDEX(Variables!$E$5:$E$65,MATCH($A93,Variables!$A$5:$A$65,0)) | K93: =LOWER(Settings!$C$4)&".mit."&$A93&IF($C93="","","."&$C93&"."&$B93)&IF(INDEX(Variables!$D$5:$D$65,MATCH($A93,Variables!$A$5:$A$65,0))="","","."&INDEX(Variables!$D$5:$D$65,MATCH($A93,Variables!$A$5:$A$65,0)))&"."&K$5 | L93: =INDEX(MTInputs!$J$1:$AZ$415,$D93,MATCH(L$5,MTInputs!$J$5:$AZ$5,0)) | M93: =INDEX(MTInputs!$J$1:$AZ$415,$D93,MATCH(M$5,MTInputs!$J$5:$AZ$5,0)) | N93: =INDEX(MTInputs!$J$1:$AZ$415,$D93,MATCH(N$5,MTInputs!$J$5:$AZ$5,0)) | O93: =INDEX(MTInputs!$J$1:$AZ$415,$D93,MATCH(O$5,MTInputs!$J$5:$AZ$5,0)) | P93: =INDEX(MTInputs!$J$1:$AZ$415,$D93,MATCH(P$5,MTInputs!$J$5:$AZ$5,0)) | Q93: =INDEX(MTInputs!$J$1:$AZ$415,$D93,MATCH(Q$5,MTInputs!$J$5:$AZ$5,0)) | R93: =INDEX(MTInputs!$J$1:$AZ$415,$D93,MATCH(R$5,MTInputs!$J$5:$AZ$5,0)) | S93: =INDEX(MTInputs!$J$1:$AZ$415,$D93,MATCH(S$5,MTInputs!$J$5:$AZ$5,0)) | ... Y93: =INDEX(MTInputs!$J$1:$AZ$415,$D93,MATCH(Y$5,MTInputs!$J$5:$AZ$5,0)) | Z93: =LOWER(Settings!$C$4)&".mit."&$A93&IF($C93="","","."&$C93&"."&$B93)&IF(INDEX(Variables!$D$5:$D$65,MATCH($A93,Variables!$A$5:$A$65,0))="","","."&INDEX(Variables!$D$5:$D$65,MATCH($A93,Variables!$A$5:$A$65,0)))&"."&Z$5 | AA93: =INDEX(MTInputs!$J$1:$AZ$415,$D93,MATCH(AA$5,MTInputs!$J$5:$AZ$5,0)) | AB93: =INDEX(MTInputs!$J$1:$AZ$415,$D93,MATCH(AB$5,MTInputs!$J$5:$AZ$5,0)) | AC93: =INDEX(MTInputs!$J$1:$AZ$415,$D93,MATCH(AC$5,MTInputs!$J$5:$AZ$5,0)) | AD93: =INDEX(MTInputs!$J$1:$AZ$415,$D93,MATCH(AD$5,MTInputs!$J$5:$AZ$5,0)) | AE93: =INDEX(MTInputs!$J$1:$AZ$415,$D93,MATCH(AE$5,MTInputs!$J$5:$AZ$5,0)) | AF93: =INDEX(MTInputs!$J$1:$AZ$415,$D93,MATCH(AF$5,MTInputs!$J$5:$AZ$5,0)) | AG93: =INDEX(MTInputs!$J$1:$AZ$415,$D93,MATCH(AG$5,MTInputs!$J$5:$AZ$5,0)) | AH93: =INDEX(MTInputs!$J$1:$AZ$415,$D93,MATCH(AH$5,MTInputs!$J$5:$AZ$5,0)) | ... AN93: =INDEX(MTInputs!$J$1:$AZ$415,$D93,MATCH(AN$5,MTInputs!$J$5:$AZ$5,0))
A94: fb.s | B94: all | C94: res | D94: 58 | H94: =INDEX(Variables!$B$5:$B$65,MATCH($A94,Variables!$A$5:$A$65,0))&IF($C94="",""," | "&INDEX(Mapping!$B$5:$B$25,MATCH($C94,Mapping!$A$5:$A$25,0))&" | "&INDEX(Mapping!$B$29:$B$38,MATCH($B94,Mapping!$A$29:$A$38,0))) | I94: =INDEX(Variables!$C$5:$C$65,MATCH($A94,Variables!$A$5:$A$65,0)) | J94: =INDEX(Variables!$E$5:$E$65,MATCH($A94,Variables!$A$5:$A$65,0)) | K94: =LOWER(Settings!$C$4)&".mit."&$A94&IF($C94="","","."&$C94&"."&$B94)&IF(INDEX(Variables!$D$5:$D$65,MATCH($A94,Variables!$A$5:$A$65,0))="","","."&INDEX(Variables!$D$5:$D$65,MATCH($A94,Variables!$A$5:$A$65,0)))&"."&K$5 | L94: =INDEX(MTInputs!$J$1:$AZ$415,$D94,MATCH(L$5,MTInputs!$J$5:$AZ$5,0)) | M94: =INDEX(MTInputs!$J$1:$AZ$415,$D94,MATCH(M$5,MTInputs!$J$5:$AZ$5,0)) | N94: =INDEX(MTInputs!$J$1:$AZ$415,$D94,MATCH(N$5,MTInputs!$J$5:$AZ$5,0)) | O94: =INDEX(MTInputs!$J$1:$AZ$415,$D94,MATCH(O$5,MTInputs!$J$5:$AZ$5,0)) | P94: =INDEX(MTInputs!$J$1:$AZ$415,$D94,MATCH(P$5,MTInputs!$J$5:$AZ$5,0)) | Q94: =INDEX(MTInputs!$J$1:$AZ$415,$D94,MATCH(Q$5,MTInputs!$J$5:$AZ$5,0)) | R94: =INDEX(MTInputs!$J$1:$AZ$415,$D94,MATCH(R$5,MTInputs!$J$5:$AZ$5,0)) | S94: =INDEX(MTInputs!$J$1:$AZ$415,$D94,MATCH(S$5,MTInputs!$J$5:$AZ$5,0)) | ... Y94: =INDEX(MTInputs!$J$1:$AZ$415,$D94,MATCH(Y$5,MTInputs!$J$5:$AZ$5,0)) | Z94: =LOWER(Settings!$C$4)&".mit."&$A94&IF($C94="","","."&$C94&"."&$B94)&IF(INDEX(Variables!$D$5:$D$65,MATCH($A94,Variables!$A$5:$A$65,0))="","","."&INDEX(Variables!$D$5:$D$65,MATCH($A94,Variables!$A$5:$A$65,0)))&"."&Z$5 | AA94: =INDEX(MTInputs!$J$1:$AZ$415,$D94,MATCH(AA$5,MTInputs!$J$5:$AZ$5,0)) | AB94: =INDEX(MTInputs!$J$1:$AZ$415,$D94,MATCH(AB$5,MTInputs!$J$5:$AZ$5,0)) | AC94: =INDEX(MTInputs!$J$1:$AZ$415,$D94,MATCH(AC$5,MTInputs!$J$5:$AZ$5,0)) | AD94: =INDEX(MTInputs!$J$1:$AZ$415,$D94,MATCH(AD$5,MTInputs!$J$5:$AZ$5,0)) | AE94: =INDEX(MTInputs!$J$1:$AZ$415,$D94,MATCH(AE$5,MTInputs!$J$5:$AZ$5,0)) | AF94: =INDEX(MTInputs!$J$1:$AZ$415,$D94,MATCH(AF$5,MTInputs!$J$5:$AZ$5,0)) | AG94: =INDEX(MTInputs!$J$1:$AZ$415,$D94,MATCH(AG$5,MTInputs!$J$5:$AZ$5,0)) | AH94: =INDEX(MTInputs!$J$1:$AZ$415,$D94,MATCH(AH$5,MTInputs!$J$5:$AZ$5,0)) | ... AN94: =INDEX(MTInputs!$J$1:$AZ$415,$D94,MATCH(AN$5,MTInputs!$J$5:$AZ$5,0))
A95: fb.s | B95: all | C95: ind | D95: 59 | H95: =INDEX(Variables!$B$5:$B$65,MATCH($A95,Variables!$A$5:$A$65,0))&IF($C95="",""," | "&INDEX(Mapping!$B$5:$B$25,MATCH($C95,Mapping!$A$5:$A$25,0))&" | "&INDEX(Mapping!$B$29:$B$38,MATCH($B95,Mapping!$A$29:$A$38,0))) | I95: =INDEX(Variables!$C$5:$C$65,MATCH($A95,Variables!$A$5:$A$65,0)) | J95: =INDEX(Variables!$E$5:$E$65,MATCH($A95,Variables!$A$5:$A$65,0)) | K95: =LOWER(Settings!$C$4)&".mit."&$A95&IF($C95="","","."&$C95&"."&$B95)&IF(INDEX(Variables!$D$5:$D$65,MATCH($A95,Variables!$A$5:$A$65,0))="","","."&INDEX(Variables!$D$5:$D$65,MATCH($A95,Variables!$A$5:$A$65,0)))&"."&K$5 | L95: =INDEX(MTInputs!$J$1:$AZ$415,$D95,MATCH(L$5,MTInputs!$J$5:$AZ$5,0)) | M95: =INDEX(MTInputs!$J$1:$AZ$415,$D95,MATCH(M$5,MTInputs!$J$5:$AZ$5,0)) | N95: =INDEX(MTInputs!$J$1:$AZ$415,$D95,MATCH(N$5,MTInputs!$J$5:$AZ$5,0)) | O95: =INDEX(MTInputs!$J$1:$AZ$415,$D95,MATCH(O$5,MTInputs!$J$5:$AZ$5,0)) | P95: =INDEX(MTInputs!$J$1:$AZ$415,$D95,MATCH(P$5,MTInputs!$J$5:$AZ$5,0)) | Q95: =INDEX(MTInputs!$J$1:$AZ$415,$D95,MATCH(Q$5,MTInputs!$J$5:$AZ$5,0)) | R95: =INDEX(MTInputs!$J$1:$AZ$415,$D95,MATCH(R$5,MTInputs!$J$5:$AZ$5,0)) | S95: =INDEX(MTInputs!$J$1:$AZ$415,$D95,MATCH(S$5,MTInputs!$J$5:$AZ$5,0)) | ... Y95: =INDEX(MTInputs!$J$1:$AZ$415,$D95,MATCH(Y$5,MTInputs!$J$5:$AZ$5,0)) | Z95: =LOWER(Settings!$C$4)&".mit."&$A95&IF($C95="","","."&$C95&"."&$B95)&IF(INDEX(Variables!$D$5:$D$65,MATCH($A95,Variables!$A$5:$A$65,0))="","","."&INDEX(Variables!$D$5:$D$65,MATCH($A95,Variables!$A$5:$A$65,0)))&"."&Z$5 | AA95: =INDEX(MTInputs!$J$1:$AZ$415,$D95,MATCH(AA$5,MTInputs!$J$5:$AZ$5,0)) | AB95: =INDEX(MTInputs!$J$1:$AZ$415,$D95,MATCH(AB$5,MTInputs!$J$5:$AZ$5,0)) | AC95: =INDEX(MTInputs!$J$1:$AZ$415,$D95,MATCH(AC$5,MTInputs!$J$5:$AZ$5,0)) | AD95: =INDEX(MTInputs!$J$1:$AZ$415,$D95,MATCH(AD$5,MTInputs!$J$5:$AZ$5,0)) | AE95: =INDEX(MTInputs!$J$1:$AZ$415,$D95,MATCH(AE$5,MTInputs!$J$5:$AZ$5,0)) | AF95: =INDEX(MTInputs!$J$1:$AZ$415,$D95,MATCH(AF$5,MTInputs!$J$5:$AZ$5,0)) | AG95: =INDEX(MTInputs!$J$1:$AZ$415,$D95,MATCH(AG$5,MTInputs!$J$5:$AZ$5,0)) | AH95: =INDEX(MTInputs!$J$1:$AZ$415,$D95,MATCH(AH$5,MTInputs!$J$5:$AZ$5,0)) | ... AN95: =INDEX(MTInputs!$J$1:$AZ$415,$D95,MATCH(AN$5,MTInputs!$J$5:$AZ$5,0))
A96: fb.t | B96: all | C96: pow | D96: 61 | H96: =INDEX(Variables!$B$5:$B$65,MATCH($A96,Variables!$A$5:$A$65,0))&IF($C96="",""," | "&INDEX(Mapping!$B$5:$B$25,MATCH($C96,Mapping!$A$5:$A$25,0))&" | "&INDEX(Mapping!$B$29:$B$38,MATCH($B96,Mapping!$A$29:$A$38,0))) | I96: =INDEX(Variables!$C$5:$C$65,MATCH($A96,Variables!$A$5:$A$65,0)) | J96: =INDEX(Variables!$E$5:$E$65,MATCH($A96,Variables!$A$5:$A$65,0)) | K96: =LOWER(Settings!$C$4)&".mit."&$A96&IF($C96="","","."&$C96&"."&$B96)&IF(INDEX(Variables!$D$5:$D$65,MATCH($A96,Variables!$A$5:$A$65,0))="","","."&INDEX(Variables!$D$5:$D$65,MATCH($A96,Variables!$A$5:$A$65,0)))&"."&K$5 | L96: =INDEX(MTInputs!$J$1:$AZ$415,$D96,MATCH(L$5,MTInputs!$J$5:$AZ$5,0)) | M96: =INDEX(MTInputs!$J$1:$AZ$415,$D96,MATCH(M$5,MTInputs!$J$5:$AZ$5,0)) | N96: =INDEX(MTInputs!$J$1:$AZ$415,$D96,MATCH(N$5,MTInputs!$J$5:$AZ$5,0)) | O96: =INDEX(MTInputs!$J$1:$AZ$415,$D96,MATCH(O$5,MTInputs!$J$5:$AZ$5,0)) | P96: =INDEX(MTInputs!$J$1:$AZ$415,$D96,MATCH(P$5,MTInputs!$J$5:$AZ$5,0)) | Q96: =INDEX(MTInputs!$J$1:$AZ$415,$D96,MATCH(Q$5,MTInputs!$J$5:$AZ$5,0)) | R96: =INDEX(MTInputs!$J$1:$AZ$415,$D96,MATCH(R$5,MTInputs!$J$5:$AZ$5,0)) | S96: =INDEX(MTInputs!$J$1:$AZ$415,$D96,MATCH(S$5,MTInputs!$J$5:$AZ$5,0)) | ... Y96: =INDEX(MTInputs!$J$1:$AZ$415,$D96,MATCH(Y$5,MTInputs!$J$5:$AZ$5,0)) | Z96: =LOWER(Settings!$C$4)&".mit."&$A96&IF($C96="","","."&$C96&"."&$B96)&IF(INDEX(Variables!$D$5:$D$65,MATCH($A96,Variables!$A$5:$A$65,0))="","","."&INDEX(Variables!$D$5:$D$65,MATCH($A96,Variables!$A$5:$A$65,0)))&"."&Z$5 | AA96: =INDEX(MTInputs!$J$1:$AZ$415,$D96,MATCH(AA$5,MTInputs!$J$5:$AZ$5,0)) | AB96: =INDEX(MTInputs!$J$1:$AZ$415,$D96,MATCH(AB$5,MTInputs!$J$5:$AZ$5,0)) | AC96: =INDEX(MTInputs!$J$1:$AZ$415,$D96,MATCH(AC$5,MTInputs!$J$5:$AZ$5,0)) | AD96: =INDEX(MTInputs!$J$1:$AZ$415,$D96,MATCH(AD$5,MTInputs!$J$5:$AZ$5,0)) | AE96: =INDEX(MTInputs!$J$1:$AZ$415,$D96,MATCH(AE$5,MTInputs!$J$5:$AZ$5,0)) | AF96: =INDEX(MTInputs!$J$1:$AZ$415,$D96,MATCH(AF$5,MTInputs!$J$5:$AZ$5,0)) | AG96: =INDEX(MTInputs!$J$1:$AZ$415,$D96,MATCH(AG$5,MTInputs!$J$5:$AZ$5,0)) | AH96: =INDEX(MTInputs!$J$1:$AZ$415,$D96,MATCH(AH$5,MTInputs!$J$5:$AZ$5,0)) | ... AN96: =INDEX(MTInputs!$J$1:$AZ$415,$D96,MATCH(AN$5,MTInputs!$J$5:$AZ$5,0))
A97: fb.t | B97: all | C97: tra | D97: 62 | H97: =INDEX(Variables!$B$5:$B$65,MATCH($A97,Variables!$A$5:$A$65,0))&IF($C97="",""," | "&INDEX(Mapping!$B$5:$B$25,MATCH($C97,Mapping!$A$5:$A$25,0))&" | "&INDEX(Mapping!$B$29:$B$38,MATCH($B97,Mapping!$A$29:$A$38,0))) | I97: =INDEX(Variables!$C$5:$C$65,MATCH($A97,Variables!$A$5:$A$65,0)) | J97: =INDEX(Variables!$E$5:$E$65,MATCH($A97,Variables!$A$5:$A$65,0)) | K97: =LOWER(Settings!$C$4)&".mit."&$A97&IF($C97="","","."&$C97&"."&$B97)&IF(INDEX(Variables!$D$5:$D$65,MATCH($A97,Variables!$A$5:$A$65,0))="","","."&INDEX(Variables!$D$5:$D$65,MATCH($A97,Variables!$A$5:$A$65,0)))&"."&K$5 | L97: =INDEX(MTInputs!$J$1:$AZ$415,$D97,MATCH(L$5,MTInputs!$J$5:$AZ$5,0)) | M97: =INDEX(MTInputs!$J$1:$AZ$415,$D97,MATCH(M$5,MTInputs!$J$5:$AZ$5,0)) | N97: =INDEX(MTInputs!$J$1:$AZ$415,$D97,MATCH(N$5,MTInputs!$J$5:$AZ$5,0)) | O97: =INDEX(MTInputs!$J$1:$AZ$415,$D97,MATCH(O$5,MTInputs!$J$5:$AZ$5,0)) | P97: =INDEX(MTInputs!$J$1:$AZ$415,$D97,MATCH(P$5,MTInputs!$J$5:$AZ$5,0)) | Q97: =INDEX(MTInputs!$J$1:$AZ$415,$D97,MATCH(Q$5,MTInputs!$J$5:$AZ$5,0)) | R97: =INDEX(MTInputs!$J$1:$AZ$415,$D97,MATCH(R$5,MTInputs!$J$5:$AZ$5,0)) | S97: =INDEX(MTInputs!$J$1:$AZ$415,$D97,MATCH(S$5,MTInputs!$J$5:$AZ$5,0)) | ... Y97: =INDEX(MTInputs!$J$1:$AZ$415,$D97,MATCH(Y$5,MTInputs!$J$5:$AZ$5,0)) | Z97: =LOWER(Settings!$C$4)&".mit."&$A97&IF($C97="","","."&$C97&"."&$B97)&IF(INDEX(Variables!$D$5:$D$65,MATCH($A97,Variables!$A$5:$A$65,0))="","","."&INDEX(Variables!$D$5:$D$65,MATCH($A97,Variables!$A$5:$A$65,0)))&"."&Z$5 | AA97: =INDEX(MTInputs!$J$1:$AZ$415,$D97,MATCH(AA$5,MTInputs!$J$5:$AZ$5,0)) | AB97: =INDEX(MTInputs!$J$1:$AZ$415,$D97,MATCH(AB$5,MTInputs!$J$5:$AZ$5,0)) | AC97: =INDEX(MTInputs!$J$1:$AZ$415,$D97,MATCH(AC$5,MTInputs!$J$5:$AZ$5,0)) | AD97: =INDEX(MTInputs!$J$1:$AZ$415,$D97,MATCH(AD$5,MTInputs!$J$5:$AZ$5,0)) | AE97: =INDEX(MTInputs!$J$1:$AZ$415,$D97,MATCH(AE$5,MTInputs!$J$5:$AZ$5,0)) | AF97: =INDEX(MTInputs!$J$1:$AZ$415,$D97,MATCH(AF$5,MTInputs!$J$5:$AZ$5,0)) | AG97: =INDEX(MTInputs!$J$1:$AZ$415,$D97,MATCH(AG$5,MTInputs!$J$5:$AZ$5,0)) | AH97: =INDEX(MTInputs!$J$1:$AZ$415,$D97,MATCH(AH$5,MTInputs!$J$5:$AZ$5,0)) | ... AN97: =INDEX(MTInputs!$J$1:$AZ$415,$D97,MATCH(AN$5,MTInputs!$J$5:$AZ$5,0))
A98: fb.t | B98: all | C98: res | D98: 63 | H98: =INDEX(Variables!$B$5:$B$65,MATCH($A98,Variables!$A$5:$A$65,0))&IF($C98="",""," | "&INDEX(Mapping!$B$5:$B$25,MATCH($C98,Mapping!$A$5:$A$25,0))&" | "&INDEX(Mapping!$B$29:$B$38,MATCH($B98,Mapping!$A$29:$A$38,0))) | I98: =INDEX(Variables!$C$5:$C$65,MATCH($A98,Variables!$A$5:$A$65,0)) | J98: =INDEX(Variables!$E$5:$E$65,MATCH($A98,Variables!$A$5:$A$65,0)) | K98: =LOWER(Settings!$C$4)&".mit."&$A98&IF($C98="","","."&$C98&"."&$B98)&IF(INDEX(Variables!$D$5:$D$65,MATCH($A98,Variables!$A$5:$A$65,0))="","","."&INDEX(Variables!$D$5:$D$65,MATCH($A98,Variables!$A$5:$A$65,0)))&"."&K$5 | L98: =INDEX(MTInputs!$J$1:$AZ$415,$D98,MATCH(L$5,MTInputs!$J$5:$AZ$5,0)) | M98: =INDEX(MTInputs!$J$1:$AZ$415,$D98,MATCH(M$5,MTInputs!$J$5:$AZ$5,0)) | N98: =INDEX(MTInputs!$J$1:$AZ$415,$D98,MATCH(N$5,MTInputs!$J$5:$AZ$5,0)) | O98: =INDEX(MTInputs!$J$1:$AZ$415,$D98,MATCH(O$5,MTInputs!$J$5:$AZ$5,0)) | P98: =INDEX(MTInputs!$J$1:$AZ$415,$D98,MATCH(P$5,MTInputs!$J$5:$AZ$5,0)) | Q98: =INDEX(MTInputs!$J$1:$AZ$415,$D98,MATCH(Q$5,MTInputs!$J$5:$AZ$5,0)) | R98: =INDEX(MTInputs!$J$1:$AZ$415,$D98,MATCH(R$5,MTInputs!$J$5:$AZ$5,0)) | S98: =INDEX(MTInputs!$J$1:$AZ$415,$D98,MATCH(S$5,MTInputs!$J$5:$AZ$5,0)) | ... Y98: =INDEX(MTInputs!$J$1:$AZ$415,$D98,MATCH(Y$5,MTInputs!$J$5:$AZ$5,0)) | Z98: =LOWER(Settings!$C$4)&".mit."&$A98&IF($C98="","","."&$C98&"."&$B98)&IF(INDEX(Variables!$D$5:$D$65,MATCH($A98,Variables!$A$5:$A$65,0))="","","."&INDEX(Variables!$D$5:$D$65,MATCH($A98,Variables!$A$5:$A$65,0)))&"."&Z$5 | AA98: =INDEX(MTInputs!$J$1:$AZ$415,$D98,MATCH(AA$5,MTInputs!$J$5:$AZ$5,0)) | AB98: =INDEX(MTInputs!$J$1:$AZ$415,$D98,MATCH(AB$5,MTInputs!$J$5:$AZ$5,0)) | AC98: =INDEX(MTInputs!$J$1:$AZ$415,$D98,MATCH(AC$5,MTInputs!$J$5:$AZ$5,0)) | AD98: =INDEX(MTInputs!$J$1:$AZ$415,$D98,MATCH(AD$5,MTInputs!$J$5:$AZ$5,0)) | AE98: =INDEX(MTInputs!$J$1:$AZ$415,$D98,MATCH(AE$5,MTInputs!$J$5:$AZ$5,0)) | AF98: =INDEX(MTInputs!$J$1:$AZ$415,$D98,MATCH(AF$5,MTInputs!$J$5:$AZ$5,0)) | AG98: =INDEX(MTInputs!$J$1:$AZ$415,$D98,MATCH(AG$5,MTInputs!$J$5:$AZ$5,0)) | AH98: =INDEX(MTInputs!$J$1:$AZ$415,$D98,MATCH(AH$5,MTInputs!$J$5:$AZ$5,0)) | ... AN98: =INDEX(MTInputs!$J$1:$AZ$415,$D98,MATCH(AN$5,MTInputs!$J$5:$AZ$5,0))
A99: fb.t | B99: all | C99: ind | D99: 64 | H99: =INDEX(Variables!$B$5:$B$65,MATCH($A99,Variables!$A$5:$A$65,0))&IF($C99="",""," | "&INDEX(Mapping!$B$5:$B$25,MATCH($C99,Mapping!$A$5:$A$25,0))&" | "&INDEX(Mapping!$B$29:$B$38,MATCH($B99,Mapping!$A$29:$A$38,0))) | I99: =INDEX(Variables!$C$5:$C$65,MATCH($A99,Variables!$A$5:$A$65,0)) | J99: =INDEX(Variables!$E$5:$E$65,MATCH($A99,Variables!$A$5:$A$65,0)) | K99: =LOWER(Settings!$C$4)&".mit."&$A99&IF($C99="","","."&$C99&"."&$B99)&IF(INDEX(Variables!$D$5:$D$65,MATCH($A99,Variables!$A$5:$A$65,0))="","","."&INDEX(Variables!$D$5:$D$65,MATCH($A99,Variables!$A$5:$A$65,0)))&"."&K$5 | L99: =INDEX(MTInputs!$J$1:$AZ$415,$D99,MATCH(L$5,MTInputs!$J$5:$AZ$5,0)) | M99: =INDEX(MTInputs!$J$1:$AZ$415,$D99,MATCH(M$5,MTInputs!$J$5:$AZ$5,0)) | N99: =INDEX(MTInputs!$J$1:$AZ$415,$D99,MATCH(N$5,MTInputs!$J$5:$AZ$5,0)) | O99: =INDEX(MTInputs!$J$1:$AZ$415,$D99,MATCH(O$5,MTInputs!$J$5:$AZ$5,0)) | P99: =INDEX(MTInputs!$J$1:$AZ$415,$D99,MATCH(P$5,MTInputs!$J$5:$AZ$5,0)) | Q99: =INDEX(MTInputs!$J$1:$AZ$415,$D99,MATCH(Q$5,MTInputs!$J$5:$AZ$5,0)) | R99: =INDEX(MTInputs!$J$1:$AZ$415,$D99,MATCH(R$5,MTInputs!$J$5:$AZ$5,0)) | S99: =INDEX(MTInputs!$J$1:$AZ$415,$D99,MATCH(S$5,MTInputs!$J$5:$AZ$5,0)) | ... Y99: =INDEX(MTInputs!$J$1:$AZ$415,$D99,MATCH(Y$5,MTInputs!$J$5:$AZ$5,0)) | Z99: =LOWER(Settings!$C$4)&".mit."&$A99&IF($C99="","","."&$C99&"."&$B99)&IF(INDEX(Variables!$D$5:$D$65,MATCH($A99,Variables!$A$5:$A$65,0))="","","."&INDEX(Variables!$D$5:$D$65,MATCH($A99,Variables!$A$5:$A$65,0)))&"."&Z$5 | AA99: =INDEX(MTInputs!$J$1:$AZ$415,$D99,MATCH(AA$5,MTInputs!$J$5:$AZ$5,0)) | AB99: =INDEX(MTInputs!$J$1:$AZ$415,$D99,MATCH(AB$5,MTInputs!$J$5:$AZ$5,0)) | AC99: =INDEX(MTInputs!$J$1:$AZ$415,$D99,MATCH(AC$5,MTInputs!$J$5:$AZ$5,0)) | AD99: =INDEX(MTInputs!$J$1:$AZ$415,$D99,MATCH(AD$5,MTInputs!$J$5:$AZ$5,0)) | AE99: =INDEX(MTInputs!$J$1:$AZ$415,$D99,MATCH(AE$5,MTInputs!$J$5:$AZ$5,0)) | AF99: =INDEX(MTInputs!$J$1:$AZ$415,$D99,MATCH(AF$5,MTInputs!$J$5:$AZ$5,0)) | AG99: =INDEX(MTInputs!$J$1:$AZ$415,$D99,MATCH(AG$5,MTInputs!$J$5:$AZ$5,0)) | AH99: =INDEX(MTInputs!$J$1:$AZ$415,$D99,MATCH(AH$5,MTInputs!$J$5:$AZ$5,0)) | ... AN99: =INDEX(MTInputs!$J$1:$AZ$415,$D99,MATCH(AN$5,MTInputs!$J$5:$AZ$5,0))
A100: fb | B100: all | C100: pow | H100: =INDEX(Variables!$B$5:$B$65,MATCH($A100,Variables!$A$5:$A$65,0))&IF($C100="",""," | "&INDEX(Mapping!$B$5:$B$25,MATCH($C100,Mapping!$A$5:$A$25,0))&" | "&INDEX(Mapping!$B$29:$B$38,MATCH($B100,Mapping!$A$29:$A$38,0))) | I100: =INDEX(Variables!$C$5:$C$65,MATCH($A100,Variables!$A$5:$A$65,0)) | J100: =INDEX(Variables!$E$5:$E$65,MATCH($A100,Variables!$A$5:$A$65,0)) | K100: =LOWER(Settings!$C$4)&".mit."&$A100&IF($C100="","","."&$C100&"."&$B100)&IF(INDEX(Variables!$D$5:$D$65,MATCH($A100,Variables!$A$5:$A$65,0))="","","."&INDEX(Variables!$D$5:$D$65,MATCH($A100,Variables!$A$5:$A$65,0)))&"."&K$5 | L100: =IF(L$4<L$90,0,L92+(L96-L92)/MAX(L$91-L$90,1)*(L$4-L$90)) | M100: =IF(M$4<M$90,0,M92+(M96-M92)/MAX(M$91-M$90,1)*(M$4-M$90)) | N100: =IF(N$4<N$90,0,N92+(N96-N92)/MAX(N$91-N$90,1)*(N$4-N$90)) | O100: =IF(O$4<O$90,0,O92+(O96-O92)/MAX(O$91-O$90,1)*(O$4-O$90)) | P100: =IF(P$4<P$90,0,P92+(P96-P92)/MAX(P$91-P$90,1)*(P$4-P$90)) | Q100: =IF(Q$4<Q$90,0,Q92+(Q96-Q92)/MAX(Q$91-Q$90,1)*(Q$4-Q$90)) | R100: =IF(R$4<R$90,0,R92+(R96-R92)/MAX(R$91-R$90,1)*(R$4-R$90)) | S100: =IF(S$4<S$90,0,S92+(S96-S92)/MAX(S$91-S$90,1)*(S$4-S$90)) | ... Y100: =IF(Y$4<Y$90,0,Y92+(Y96-Y92)/MAX(Y$91-Y$90,1)*(Y$4-Y$90)) | Z100: =LOWER(Settings!$C$4)&".mit."&$A100&IF($C100="","","."&$C100&"."&$B100)&IF(INDEX(Variables!$D$5:$D$65,MATCH($A100,Variables!$A$5:$A$65,0))="","","."&INDEX(Variables!$D$5:$D$65,MATCH($A100,Variables!$A$5:$A$65,0)))&"."&Z$5 | AA100: =IF(AA$4<AA$90,0,AA92+(AA96-AA92)/MAX(AA$91-AA$90,1)*(AA$4-AA$90)) | AB100: =IF(AB$4<AB$90,0,AB92+(AB96-AB92)/MAX(AB$91-AB$90,1)*(AB$4-AB$90)) | AC100: =IF(AC$4<AC$90,0,AC92+(AC96-AC92)/MAX(AC$91-AC$90,1)*(AC$4-AC$90)) | AD100: =IF(AD$4<AD$90,0,AD92+(AD96-AD92)/MAX(AD$91-AD$90,1)*(AD$4-AD$90)) | AE100: =IF(AE$4<AE$90,0,AE92+(AE96-AE92)/MAX(AE$91-AE$90,1)*(AE$4-AE$90)) | AF100: =IF(AF$4<AF$90,0,AF92+(AF96-AF92)/MAX(AF$91-AF$90,1)*(AF$4-AF$90)) | AG100: =IF(AG$4<AG$90,0,AG92+(AG96-AG92)/MAX(AG$91-AG$90,1)*(AG$4-AG$90)) | AH100: =IF(AH$4<AH$90,0,AH92+(AH96-AH92)/MAX(AH$91-AH$90,1)*(AH$4-AH$90)) | ... AN100: =IF(AN$4<AN$90,0,AN92+(AN96-AN92)/MAX(AN$91-AN$90,1)*(AN$4-AN$90))
A101: fb | B101: all | C101: tra | H101: =INDEX(Variables!$B$5:$B$65,MATCH($A101,Variables!$A$5:$A$65,0))&IF($C101="",""," | "&INDEX(Mapping!$B$5:$B$25,MATCH($C101,Mapping!$A$5:$A$25,0))&" | "&INDEX(Mapping!$B$29:$B$38,MATCH($B101,Mapping!$A$29:$A$38,0))) | I101: =INDEX(Variables!$C$5:$C$65,MATCH($A101,Variables!$A$5:$A$65,0)) | J101: =INDEX(Variables!$E$5:$E$65,MATCH($A101,Variables!$A$5:$A$65,0)) | K101: =LOWER(Settings!$C$4)&".mit."&$A101&IF($C101="","","."&$C101&"."&$B101)&IF(INDEX(Variables!$D$5:$D$65,MATCH($A101,Variables!$A$5:$A$65,0))="","","."&INDEX(Variables!$D$5:$D$65,MATCH($A101,Variables!$A$5:$A$65,0)))&"."&K$5 | L101: =IF(L$4<L$90,0,L93+(L97-L93)/MAX(L$91-L$90,1)*(L$4-L$90)) | M101: =IF(M$4<M$90,0,M93+(M97-M93)/MAX(M$91-M$90,1)*(M$4-M$90)) | N101: =IF(N$4<N$90,0,N93+(N97-N93)/MAX(N$91-N$90,1)*(N$4-N$90)) | O101: =IF(O$4<O$90,0,O93+(O97-O93)/MAX(O$91-O$90,1)*(O$4-O$90)) | P101: =IF(P$4<P$90,0,P93+(P97-P93)/MAX(P$91-P$90,1)*(P$4-P$90)) | Q101: =IF(Q$4<Q$90,0,Q93+(Q97-Q93)/MAX(Q$91-Q$90,1)*(Q$4-Q$90)) | R101: =IF(R$4<R$90,0,R93+(R97-R93)/MAX(R$91-R$90,1)*(R$4-R$90)) | S101: =IF(S$4<S$90,0,S93+(S97-S93)/MAX(S$91-S$90,1)*(S$4-S$90)) | ... Y101: =IF(Y$4<Y$90,0,Y93+(Y97-Y93)/MAX(Y$91-Y$90,1)*(Y$4-Y$90)) | Z101: =LOWER(Settings!$C$4)&".mit."&$A101&IF($C101="","","."&$C101&"."&$B101)&IF(INDEX(Variables!$D$5:$D$65,MATCH($A101,Variables!$A$5:$A$65,0))="","","."&INDEX(Variables!$D$5:$D$65,MATCH($A101,Variables!$A$5:$A$65,0)))&"."&Z$5 | AA101: =IF(AA$4<AA$90,0,AA93+(AA97-AA93)/MAX(AA$91-AA$90,1)*(AA$4-AA$90)) | AB101: =IF(AB$4<AB$90,0,AB93+(AB97-AB93)/MAX(AB$91-AB$90,1)*(AB$4-AB$90)) | AC101: =IF(AC$4<AC$90,0,AC93+(AC97-AC93)/MAX(AC$91-AC$90,1)*(AC$4-AC$90)) | AD101: =IF(AD$4<AD$90,0,AD93+(AD97-AD93)/MAX(AD$91-AD$90,1)*(AD$4-AD$90)) | AE101: =IF(AE$4<AE$90,0,AE93+(AE97-AE93)/MAX(AE$91-AE$90,1)*(AE$4-AE$90)) | AF101: =IF(AF$4<AF$90,0,AF93+(AF97-AF93)/MAX(AF$91-AF$90,1)*(AF$4-AF$90)) | AG101: =IF(AG$4<AG$90,0,AG93+(AG97-AG93)/MAX(AG$91-AG$90,1)*(AG$4-AG$90)) | AH101: =IF(AH$4<AH$90,0,AH93+(AH97-AH93)/MAX(AH$91-AH$90,1)*(AH$4-AH$90)) | ... AN101: =IF(AN$4<AN$90,0,AN93+(AN97-AN93)/MAX(AN$91-AN$90,1)*(AN$4-AN$90))
A102: fb | B102: all | C102: res | H102: =INDEX(Variables!$B$5:$B$65,MATCH($A102,Variables!$A$5:$A$65,0))&IF($C102="",""," | "&INDEX(Mapping!$B$5:$B$25,MATCH($C102,Mapping!$A$5:$A$25,0))&" | "&INDEX(Mapping!$B$29:$B$38,MATCH($B102,Mapping!$A$29:$A$38,0))) | I102: =INDEX(Variables!$C$5:$C$65,MATCH($A102,Variables!$A$5:$A$65,0)) | J102: =INDEX(Variables!$E$5:$E$65,MATCH($A102,Variables!$A$5:$A$65,0)) | K102: =LOWER(Settings!$C$4)&".mit."&$A102&IF($C102="","","."&$C102&"."&$B102)&IF(INDEX(Variables!$D$5:$D$65,MATCH($A102,Variables!$A$5:$A$65,0))="","","."&INDEX(Variables!$D$5:$D$65,MATCH($A102,Variables!$A$5:$A$65,0)))&"."&K$5 | L102: =IF(L$4<L$90,0,L94+(L98-L94)/MAX(L$91-L$90,1)*(L$4-L$90)) | M102: =IF(M$4<M$90,0,M94+(M98-M94)/MAX(M$91-M$90,1)*(M$4-M$90)) | N102: =IF(N$4<N$90,0,N94+(N98-N94)/MAX(N$91-N$90,1)*(N$4-N$90)) | O102: =IF(O$4<O$90,0,O94+(O98-O94)/MAX(O$91-O$90,1)*(O$4-O$90)) | P102: =IF(P$4<P$90,0,P94+(P98-P94)/MAX(P$91-P$90,1)*(P$4-P$90)) | Q102: =IF(Q$4<Q$90,0,Q94+(Q98-Q94)/MAX(Q$91-Q$90,1)*(Q$4-Q$90)) | R102: =IF(R$4<R$90,0,R94+(R98-R94)/MAX(R$91-R$90,1)*(R$4-R$90)) | S102: =IF(S$4<S$90,0,S94+(S98-S94)/MAX(S$91-S$90,1)*(S$4-S$90)) | ... Y102: =IF(Y$4<Y$90,0,Y94+(Y98-Y94)/MAX(Y$91-Y$90,1)*(Y$4-Y$90)) | Z102: =LOWER(Settings!$C$4)&".mit."&$A102&IF($C102="","","."&$C102&"."&$B102)&IF(INDEX(Variables!$D$5:$D$65,MATCH($A102,Variables!$A$5:$A$65,0))="","","."&INDEX(Variables!$D$5:$D$65,MATCH($A102,Variables!$A$5:$A$65,0)))&"."&Z$5 | AA102: =IF(AA$4<AA$90,0,AA94+(AA98-AA94)/MAX(AA$91-AA$90,1)*(AA$4-AA$90)) | AB102: =IF(AB$4<AB$90,0,AB94+(AB98-AB94)/MAX(AB$91-AB$90,1)*(AB$4-AB$90)) | AC102: =IF(AC$4<AC$90,0,AC94+(AC98-AC94)/MAX(AC$91-AC$90,1)*(AC$4-AC$90)) | AD102: =IF(AD$4<AD$90,0,AD94+(AD98-AD94)/MAX(AD$91-AD$90,1)*(AD$4-AD$90)) | AE102: =IF(AE$4<AE$90,0,AE94+(AE98-AE94)/MAX(AE$91-AE$90,1)*(AE$4-AE$90)) | AF102: =IF(AF$4<AF$90,0,AF94+(AF98-AF94)/MAX(AF$91-AF$90,1)*(AF$4-AF$90)) | AG102: =IF(AG$4<AG$90,0,AG94+(AG98-AG94)/MAX(AG$91-AG$90,1)*(AG$4-AG$90)) | AH102: =IF(AH$4<AH$90,0,AH94+(AH98-AH94)/MAX(AH$91-AH$90,1)*(AH$4-AH$90)) | ... AN102: =IF(AN$4<AN$90,0,AN94+(AN98-AN94)/MAX(AN$91-AN$90,1)*(AN$4-AN$90))
A103: fb | B103: all | C103: ind | H103: =INDEX(Variables!$B$5:$B$65,MATCH($A103,Variables!$A$5:$A$65,0))&IF($C103="",""," | "&INDEX(Mapping!$B$5:$B$25,MATCH($C103,Mapping!$A$5:$A$25,0))&" | "&INDEX(Mapping!$B$29:$B$38,MATCH($B103,Mapping!$A$29:$A$38,0))) | I103: =INDEX(Variables!$C$5:$C$65,MATCH($A103,Variables!$A$5:$A$65,0)) | J103: =INDEX(Variables!$E$5:$E$65,MATCH($A103,Variables!$A$5:$A$65,0)) | K103: =LOWER(Settings!$C$4)&".mit."&$A103&IF($C103="","","."&$C103&"."&$B103)&IF(INDEX(Variables!$D$5:$D$65,MATCH($A103,Variables!$A$5:$A$65,0))="","","."&INDEX(Variables!$D$5:$D$65,MATCH($A103,Variables!$A$5:$A$65,0)))&"."&K$5 | L103: =IF(L$4<L$90,0,L95+(L99-L95)/MAX(L$91-L$90,1)*(L$4-L$90)) | M103: =IF(M$4<M$90,0,M95+(M99-M95)/MAX(M$91-M$90,1)*(M$4-M$90)) | N103: =IF(N$4<N$90,0,N95+(N99-N95)/MAX(N$91-N$90,1)*(N$4-N$90)) | O103: =IF(O$4<O$90,0,O95+(O99-O95)/MAX(O$91-O$90,1)*(O$4-O$90)) | P103: =IF(P$4<P$90,0,P95+(P99-P95)/MAX(P$91-P$90,1)*(P$4-P$90)) | Q103: =IF(Q$4<Q$90,0,Q95+(Q99-Q95)/MAX(Q$91-Q$90,1)*(Q$4-Q$90)) | R103: =IF(R$4<R$90,0,R95+(R99-R95)/MAX(R$91-R$90,1)*(R$4-R$90)) | S103: =IF(S$4<S$90,0,S95+(S99-S95)/MAX(S$91-S$90,1)*(S$4-S$90)) | ... Y103: =IF(Y$4<Y$90,0,Y95+(Y99-Y95)/MAX(Y$91-Y$90,1)*(Y$4-Y$90)) | Z103: =LOWER(Settings!$C$4)&".mit."&$A103&IF($C103="","","."&$C103&"."&$B103)&IF(INDEX(Variables!$D$5:$D$65,MATCH($A103,Variables!$A$5:$A$65,0))="","","."&INDEX(Variables!$D$5:$D$65,MATCH($A103,Variables!$A$5:$A$65,0)))&"."&Z$5 | AA103: =IF(AA$4<AA$90,0,AA95+(AA99-AA95)/MAX(AA$91-AA$90,1)*(AA$4-AA$90)) | AB103: =IF(AB$4<AB$90,0,AB95+(AB99-AB95)/MAX(AB$91-AB$90,1)*(AB$4-AB$90)) | AC103: =IF(AC$4<AC$90,0,AC95+(AC99-AC95)/MAX(AC$91-AC$90,1)*(AC$4-AC$90)) | AD103: =IF(AD$4<AD$90,0,AD95+(AD99-AD95)/MAX(AD$91-AD$90,1)*(AD$4-AD$90)) | AE103: =IF(AE$4<AE$90,0,AE95+(AE99-AE95)/MAX(AE$91-AE$90,1)*(AE$4-AE$90)) | AF103: =IF(AF$4<AF$90,0,AF95+(AF99-AF95)/MAX(AF$91-AF$90,1)*(AF$4-AF$90)) | AG103: =IF(AG$4<AG$90,0,AG95+(AG99-AG95)/MAX(AG$91-AG$90,1)*(AG$4-AG$90)) | AH103: =IF(AH$4<AH$90,0,AH95+(AH99-AH95)/MAX(AH$91-AH$90,1)*(AH$4-AH$90)) | ... AN103: =IF(AN$4<AN$90,0,AN95+(AN99-AN95)/MAX(AN$91-AN$90,1)*(AN$4-AN$90))
H104: Feebates sector coverage (MTInputs rows 66-82)
A105: fbcov | B105: all | C105: pow | D105: 66 | H105: =INDEX(Variables!$B$5:$B$65,MATCH($A105,Variables!$A$5:$A$65,0))&IF($C105="",""," | "&INDEX(Mapping!$B$5:$B$25,MATCH($C105,Mapping!$A$5:$A$25,0))&" | "&INDEX(Mapping!$B$29:$B$38,MATCH($B105,Mapping!$A$29:$A$38,0))) | I105: =INDEX(Variables!$C$5:$C$65,MATCH($A105,Variables!$A$5:$A$65,0)) | J105: =INDEX(Variables!$E$5:$E$65,MATCH($A105,Variables!$A$5:$A$65,0)) | K105: =LOWER(Settings!$C$4)&".mit."&$A105&IF($C105="","","."&$C105&"."&$B105)&IF(INDEX(Variables!$D$5:$D$65,MATCH($A105,Variables!$A$5:$A$65,0))="","","."&INDEX(Variables!$D$5:$D$65,MATCH($A105,Variables!$A$5:$A$65,0)))&"."&K$5 | L105: =INDEX(MTInputs!$J$1:$AZ$415,$D105,MATCH(L$5,MTInputs!$J$5:$AZ$5,0)) | M105: =INDEX(MTInputs!$J$1:$AZ$415,$D105,MATCH(M$5,MTInputs!$J$5:$AZ$5,0)) | N105: =INDEX(MTInputs!$J$1:$AZ$415,$D105,MATCH(N$5,MTInputs!$J$5:$AZ$5,0)) | O105: =INDEX(MTInputs!$J$1:$AZ$415,$D105,MATCH(O$5,MTInputs!$J$5:$AZ$5,0)) | P105: =INDEX(MTInputs!$J$1:$AZ$415,$D105,MATCH(P$5,MTInputs!$J$5:$AZ$5,0)) | Q105: =INDEX(MTInputs!$J$1:$AZ$415,$D105,MATCH(Q$5,MTInputs!$J$5:$AZ$5,0)) | R105: =INDEX(MTInputs!$J$1:$AZ$415,$D105,MATCH(R$5,MTInputs!$J$5:$AZ$5,0)) | S105: =INDEX(MTInputs!$J$1:$AZ$415,$D105,MATCH(S$5,MTInputs!$J$5:$AZ$5,0)) | ... Y105: =INDEX(MTInputs!$J$1:$AZ$415,$D105,MATCH(Y$5,MTInputs!$J$5:$AZ$5,0)) | Z105: =LOWER(Settings!$C$4)&".mit."&$A105&IF($C105="","","."&$C105&"."&$B105)&IF(INDEX(Variables!$D$5:$D$65,MATCH($A105,Variables!$A$5:$A$65,0))="","","."&INDEX(Variables!$D$5:$D$65,MATCH($A105,Variables!$A$5:$A$65,0)))&"."&Z$5 | AA105: =INDEX(MTInputs!$J$1:$AZ$415,$D105,MATCH(AA$5,MTInputs!$J$5:$AZ$5,0)) | AB105: =INDEX(MTInputs!$J$1:$AZ$415,$D105,MATCH(AB$5,MTInputs!$J$5:$AZ$5,0)) | AC105: =INDEX(MTInputs!$J$1:$AZ$415,$D105,MATCH(AC$5,MTInputs!$J$5:$AZ$5,0)) | AD105: =INDEX(MTInputs!$J$1:$AZ$415,$D105,MATCH(AD$5,MTInputs!$J$5:$AZ$5,0)) | AE105: =INDEX(MTInputs!$J$1:$AZ$415,$D105,MATCH(AE$5,MTInputs!$J$5:$AZ$5,0)) | AF105: =INDEX(MTInputs!$J$1:$AZ$415,$D105,MATCH(AF$5,MTInputs!$J$5:$AZ$5,0)) | AG105: =INDEX(MTInputs!$J$1:$AZ$415,$D105,MATCH(AG$5,MTInputs!$J$5:$AZ$5,0)) | AH105: =INDEX(MTInputs!$J$1:$AZ$415,$D105,MATCH(AH$5,MTInputs!$J$5:$AZ$5,0)) | ... AN105: =INDEX(MTInputs!$J$1:$AZ$415,$D105,MATCH(AN$5,MTInputs!$J$5:$AZ$5,0))
A106: fbcov | B106: all | C106: rod | D106: 67 | H106: =INDEX(Variables!$B$5:$B$65,MATCH($A106,Variables!$A$5:$A$65,0))&IF($C106="",""," | "&INDEX(Mapping!$B$5:$B$25,MATCH($C106,Mapping!$A$5:$A$25,0))&" | "&INDEX(Mapping!$B$29:$B$38,MATCH($B106,Mapping!$A$29:$A$38,0))) | I106: =INDEX(Variables!$C$5:$C$65,MATCH($A106,Variables!$A$5:$A$65,0)) | J106: =INDEX(Variables!$E$5:$E$65,MATCH($A106,Variables!$A$5:$A$65,0)) | K106: =LOWER(Settings!$C$4)&".mit."&$A106&IF($C106="","","."&$C106&"."&$B106)&IF(INDEX(Variables!$D$5:$D$65,MATCH($A106,Variables!$A$5:$A$65,0))="","","."&INDEX(Variables!$D$5:$D$65,MATCH($A106,Variables!$A$5:$A$65,0)))&"."&K$5 | L106: =INDEX(MTInputs!$J$1:$AZ$415,$D106,MATCH(L$5,MTInputs!$J$5:$AZ$5,0)) | M106: =INDEX(MTInputs!$J$1:$AZ$415,$D106,MATCH(M$5,MTInputs!$J$5:$AZ$5,0)) | N106: =INDEX(MTInputs!$J$1:$AZ$415,$D106,MATCH(N$5,MTInputs!$J$5:$AZ$5,0)) | O106: =INDEX(MTInputs!$J$1:$AZ$415,$D106,MATCH(O$5,MTInputs!$J$5:$AZ$5,0)) | P106: =INDEX(MTInputs!$J$1:$AZ$415,$D106,MATCH(P$5,MTInputs!$J$5:$AZ$5,0)) | Q106: =INDEX(MTInputs!$J$1:$AZ$415,$D106,MATCH(Q$5,MTInputs!$J$5:$AZ$5,0)) | R106: =INDEX(MTInputs!$J$1:$AZ$415,$D106,MATCH(R$5,MTInputs!$J$5:$AZ$5,0)) | S106: =INDEX(MTInputs!$J$1:$AZ$415,$D106,MATCH(S$5,MTInputs!$J$5:$AZ$5,0)) | ... Y106: =INDEX(MTInputs!$J$1:$AZ$415,$D106,MATCH(Y$5,MTInputs!$J$5:$AZ$5,0)) | Z106: =LOWER(Settings!$C$4)&".mit."&$A106&IF($C106="","","."&$C106&"."&$B106)&IF(INDEX(Variables!$D$5:$D$65,MATCH($A106,Variables!$A$5:$A$65,0))="","","."&INDEX(Variables!$D$5:$D$65,MATCH($A106,Variables!$A$5:$A$65,0)))&"."&Z$5 | AA106: =INDEX(MTInputs!$J$1:$AZ$415,$D106,MATCH(AA$5,MTInputs!$J$5:$AZ$5,0)) | AB106: =INDEX(MTInputs!$J$1:$AZ$415,$D106,MATCH(AB$5,MTInputs!$J$5:$AZ$5,0)) | AC106: =INDEX(MTInputs!$J$1:$AZ$415,$D106,MATCH(AC$5,MTInputs!$J$5:$AZ$5,0)) | AD106: =INDEX(MTInputs!$J$1:$AZ$415,$D106,MATCH(AD$5,MTInputs!$J$5:$AZ$5,0)) | AE106: =INDEX(MTInputs!$J$1:$AZ$415,$D106,MATCH(AE$5,MTInputs!$J$5:$AZ$5,0)) | AF106: =INDEX(MTInputs!$J$1:$AZ$415,$D106,MATCH(AF$5,MTInputs!$J$5:$AZ$5,0)) | AG106: =INDEX(MTInputs!$J$1:$AZ$415,$D106,MATCH(AG$5,MTInputs!$J$5:$AZ$5,0)) | AH106: =INDEX(MTInputs!$J$1:$AZ$415,$D106,MATCH(AH$5,MTInputs!$J$5:$AZ$5,0)) | ... AN106: =INDEX(MTInputs!$J$1:$AZ$415,$D106,MATCH(AN$5,MTInputs!$J$5:$AZ$5,0))
A107: fbcov | B107: all | C107: ral | D107: 68 | H107: =INDEX(Variables!$B$5:$B$65,MATCH($A107,Variables!$A$5:$A$65,0))&IF($C107="",""," | "&INDEX(Mapping!$B$5:$B$25,MATCH($C107,Mapping!$A$5:$A$25,0))&" | "&INDEX(Mapping!$B$29:$B$38,MATCH($B107,Mapping!$A$29:$A$38,0))) | I107: =INDEX(Variables!$C$5:$C$65,MATCH($A107,Variables!$A$5:$A$65,0)) | J107: =INDEX(Variables!$E$5:$E$65,MATCH($A107,Variables!$A$5:$A$65,0)) | K107: =LOWER(Settings!$C$4)&".mit."&$A107&IF($C107="","","."&$C107&"."&$B107)&IF(INDEX(Variables!$D$5:$D$65,MATCH($A107,Variables!$A$5:$A$65,0))="","","."&INDEX(Variables!$D$5:$D$65,MATCH($A107,Variables!$A$5:$A$65,0)))&"."&K$5 | L107: =INDEX(MTInputs!$J$1:$AZ$415,$D107,MATCH(L$5,MTInputs!$J$5:$AZ$5,0)) | M107: =INDEX(MTInputs!$J$1:$AZ$415,$D107,MATCH(M$5,MTInputs!$J$5:$AZ$5,0)) | N107: =INDEX(MTInputs!$J$1:$AZ$415,$D107,MATCH(N$5,MTInputs!$J$5:$AZ$5,0)) | O107: =INDEX(MTInputs!$J$1:$AZ$415,$D107,MATCH(O$5,MTInputs!$J$5:$AZ$5,0)) | P107: =INDEX(MTInputs!$J$1:$AZ$415,$D107,MATCH(P$5,MTInputs!$J$5:$AZ$5,0)) | Q107: =INDEX(MTInputs!$J$1:$AZ$415,$D107,MATCH(Q$5,MTInputs!$J$5:$AZ$5,0)) | R107: =INDEX(MTInputs!$J$1:$AZ$415,$D107,MATCH(R$5,MTInputs!$J$5:$AZ$5,0)) | S107: =INDEX(MTInputs!$J$1:$AZ$415,$D107,MATCH(S$5,MTInputs!$J$5:$AZ$5,0)) | ... Y107: =INDEX(MTInputs!$J$1:$AZ$415,$D107,MATCH(Y$5,MTInputs!$J$5:$AZ$5,0)) | Z107: =LOWER(Settings!$C$4)&".mit."&$A107&IF($C107="","","."&$C107&"."&$B107)&IF(INDEX(Variables!$D$5:$D$65,MATCH($A107,Variables!$A$5:$A$65,0))="","","."&INDEX(Variables!$D$5:$D$65,MATCH($A107,Variables!$A$5:$A$65,0)))&"."&Z$5 | AA107: =INDEX(MTInputs!$J$1:$AZ$415,$D107,MATCH(AA$5,MTInputs!$J$5:$AZ$5,0)) | AB107: =INDEX(MTInputs!$J$1:$AZ$415,$D107,MATCH(AB$5,MTInputs!$J$5:$AZ$5,0)) | AC107: =INDEX(MTInputs!$J$1:$AZ$415,$D107,MATCH(AC$5,MTInputs!$J$5:$AZ$5,0)) | AD107: =INDEX(MTInputs!$J$1:$AZ$415,$D107,MATCH(AD$5,MTInputs!$J$5:$AZ$5,0)) | AE107: =INDEX(MTInputs!$J$1:$AZ$415,$D107,MATCH(AE$5,MTInputs!$J$5:$AZ$5,0)) | AF107: =INDEX(MTInputs!$J$1:$AZ$415,$D107,MATCH(AF$5,MTInputs!$J$5:$AZ$5,0)) | AG107: =INDEX(MTInputs!$J$1:$AZ$415,$D107,MATCH(AG$5,MTInputs!$J$5:$AZ$5,0)) | AH107: =INDEX(MTInputs!$J$1:$AZ$415,$D107,MATCH(AH$5,MTInputs!$J$5:$AZ$5,0)) | ... AN107: =INDEX(MTInputs!$J$1:$AZ$415,$D107,MATCH(AN$5,MTInputs!$J$5:$AZ$5,0))
A108: fbcov | B108: all | C108: avi | D108: 69 | H108: =INDEX(Variables!$B$5:$B$65,MATCH($A108,Variables!$A$5:$A$65,0))&IF($C108="",""," | "&INDEX(Mapping!$B$5:$B$25,MATCH($C108,Mapping!$A$5:$A$25,0))&" | "&INDEX(Mapping!$B$29:$B$38,MATCH($B108,Mapping!$A$29:$A$38,0))) | I108: =INDEX(Variables!$C$5:$C$65,MATCH($A108,Variables!$A$5:$A$65,0)) | J108: =INDEX(Variables!$E$5:$E$65,MATCH($A108,Variables!$A$5:$A$65,0)) | K108: =LOWER(Settings!$C$4)&".mit."&$A108&IF($C108="","","."&$C108&"."&$B108)&IF(INDEX(Variables!$D$5:$D$65,MATCH($A108,Variables!$A$5:$A$65,0))="","","."&INDEX(Variables!$D$5:$D$65,MATCH($A108,Variables!$A$5:$A$65,0)))&"."&K$5 | L108: =INDEX(MTInputs!$J$1:$AZ$415,$D108,MATCH(L$5,MTInputs!$J$5:$AZ$5,0)) | M108: =INDEX(MTInputs!$J$1:$AZ$415,$D108,MATCH(M$5,MTInputs!$J$5:$AZ$5,0)) | N108: =INDEX(MTInputs!$J$1:$AZ$415,$D108,MATCH(N$5,MTInputs!$J$5:$AZ$5,0)) | O108: =INDEX(MTInputs!$J$1:$AZ$415,$D108,MATCH(O$5,MTInputs!$J$5:$AZ$5,0)) | P108: =INDEX(MTInputs!$J$1:$AZ$415,$D108,MATCH(P$5,MTInputs!$J$5:$AZ$5,0)) | Q108: =INDEX(MTInputs!$J$1:$AZ$415,$D108,MATCH(Q$5,MTInputs!$J$5:$AZ$5,0)) | R108: =INDEX(MTInputs!$J$1:$AZ$415,$D108,MATCH(R$5,MTInputs!$J$5:$AZ$5,0)) | S108: =INDEX(MTInputs!$J$1:$AZ$415,$D108,MATCH(S$5,MTInputs!$J$5:$AZ$5,0)) | ... Y108: =INDEX(MTInputs!$J$1:$AZ$415,$D108,MATCH(Y$5,MTInputs!$J$5:$AZ$5,0)) | Z108: =LOWER(Settings!$C$4)&".mit."&$A108&IF($C108="","","."&$C108&"."&$B108)&IF(INDEX(Variables!$D$5:$D$65,MATCH($A108,Variables!$A$5:$A$65,0))="","","."&INDEX(Variables!$D$5:$D$65,MATCH($A108,Variables!$A$5:$A$65,0)))&"."&Z$5 | AA108: =INDEX(MTInputs!$J$1:$AZ$415,$D108,MATCH(AA$5,MTInputs!$J$5:$AZ$5,0)) | AB108: =INDEX(MTInputs!$J$1:$AZ$415,$D108,MATCH(AB$5,MTInputs!$J$5:$AZ$5,0)) | AC108: =INDEX(MTInputs!$J$1:$AZ$415,$D108,MATCH(AC$5,MTInputs!$J$5:$AZ$5,0)) | AD108: =INDEX(MTInputs!$J$1:$AZ$415,$D108,MATCH(AD$5,MTInputs!$J$5:$AZ$5,0)) | AE108: =INDEX(MTInputs!$J$1:$AZ$415,$D108,MATCH(AE$5,MTInputs!$J$5:$AZ$5,0)) | AF108: =INDEX(MTInputs!$J$1:$AZ$415,$D108,MATCH(AF$5,MTInputs!$J$5:$AZ$5,0)) | AG108: =INDEX(MTInputs!$J$1:$AZ$415,$D108,MATCH(AG$5,MTInputs!$J$5:$AZ$5,0)) | AH108: =INDEX(MTInputs!$J$1:$AZ$415,$D108,MATCH(AH$5,MTInputs!$J$5:$AZ$5,0)) | ... AN108: =INDEX(MTInputs!$J$1:$AZ$415,$D108,MATCH(AN$5,MTInputs!$J$5:$AZ$5,0))
A109: fbcov | B109: all | C109: nav | D109: 70 | H109: =INDEX(Variables!$B$5:$B$65,MATCH($A109,Variables!$A$5:$A$65,0))&IF($C109="",""," | "&INDEX(Mapping!$B$5:$B$25,MATCH($C109,Mapping!$A$5:$A$25,0))&" | "&INDEX(Mapping!$B$29:$B$38,MATCH($B109,Mapping!$A$29:$A$38,0))) | I109: =INDEX(Variables!$C$5:$C$65,MATCH($A109,Variables!$A$5:$A$65,0)) | J109: =INDEX(Variables!$E$5:$E$65,MATCH($A109,Variables!$A$5:$A$65,0)) | K109: =LOWER(Settings!$C$4)&".mit."&$A109&IF($C109="","","."&$C109&"."&$B109)&IF(INDEX(Variables!$D$5:$D$65,MATCH($A109,Variables!$A$5:$A$65,0))="","","."&INDEX(Variables!$D$5:$D$65,MATCH($A109,Variables!$A$5:$A$65,0)))&"."&K$5 | L109: =INDEX(MTInputs!$J$1:$AZ$415,$D109,MATCH(L$5,MTInputs!$J$5:$AZ$5,0)) | M109: =INDEX(MTInputs!$J$1:$AZ$415,$D109,MATCH(M$5,MTInputs!$J$5:$AZ$5,0)) | N109: =INDEX(MTInputs!$J$1:$AZ$415,$D109,MATCH(N$5,MTInputs!$J$5:$AZ$5,0)) | O109: =INDEX(MTInputs!$J$1:$AZ$415,$D109,MATCH(O$5,MTInputs!$J$5:$AZ$5,0)) | P109: =INDEX(MTInputs!$J$1:$AZ$415,$D109,MATCH(P$5,MTInputs!$J$5:$AZ$5,0)) | Q109: =INDEX(MTInputs!$J$1:$AZ$415,$D109,MATCH(Q$5,MTInputs!$J$5:$AZ$5,0)) | R109: =INDEX(MTInputs!$J$1:$AZ$415,$D109,MATCH(R$5,MTInputs!$J$5:$AZ$5,0)) | S109: =INDEX(MTInputs!$J$1:$AZ$415,$D109,MATCH(S$5,MTInputs!$J$5:$AZ$5,0)) | ... Y109: =INDEX(MTInputs!$J$1:$AZ$415,$D109,MATCH(Y$5,MTInputs!$J$5:$AZ$5,0)) | Z109: =LOWER(Settings!$C$4)&".mit."&$A109&IF($C109="","","."&$C109&"."&$B109)&IF(INDEX(Variables!$D$5:$D$65,MATCH($A109,Variables!$A$5:$A$65,0))="","","."&INDEX(Variables!$D$5:$D$65,MATCH($A109,Variables!$A$5:$A$65,0)))&"."&Z$5 | AA109: =INDEX(MTInputs!$J$1:$AZ$415,$D109,MATCH(AA$5,MTInputs!$J$5:$AZ$5,0)) | AB109: =INDEX(MTInputs!$J$1:$AZ$415,$D109,MATCH(AB$5,MTInputs!$J$5:$AZ$5,0)) | AC109: =INDEX(MTInputs!$J$1:$AZ$415,$D109,MATCH(AC$5,MTInputs!$J$5:$AZ$5,0)) | AD109: =INDEX(MTInputs!$J$1:$AZ$415,$D109,MATCH(AD$5,MTInputs!$J$5:$AZ$5,0)) | AE109: =INDEX(MTInputs!$J$1:$AZ$415,$D109,MATCH(AE$5,MTInputs!$J$5:$AZ$5,0)) | AF109: =INDEX(MTInputs!$J$1:$AZ$415,$D109,MATCH(AF$5,MTInputs!$J$5:$AZ$5,0)) | AG109: =INDEX(MTInputs!$J$1:$AZ$415,$D109,MATCH(AG$5,MTInputs!$J$5:$AZ$5,0)) | AH109: =INDEX(MTInputs!$J$1:$AZ$415,$D109,MATCH(AH$5,MTInputs!$J$5:$AZ$5,0)) | ... AN109: =INDEX(MTInputs!$J$1:$AZ$415,$D109,MATCH(AN$5,MTInputs!$J$5:$AZ$5,0))
A110: fbcov | B110: all | C110: res | D110: 71 | H110: =INDEX(Variables!$B$5:$B$65,MATCH($A110,Variables!$A$5:$A$65,0))&IF($C110="",""," | "&INDEX(Mapping!$B$5:$B$25,MATCH($C110,Mapping!$A$5:$A$25,0))&" | "&INDEX(Mapping!$B$29:$B$38,MATCH($B110,Mapping!$A$29:$A$38,0))) | I110: =INDEX(Variables!$C$5:$C$65,MATCH($A110,Variables!$A$5:$A$65,0)) | J110: =INDEX(Variables!$E$5:$E$65,MATCH($A110,Variables!$A$5:$A$65,0)) | K110: =LOWER(Settings!$C$4)&".mit."&$A110&IF($C110="","","."&$C110&"."&$B110)&IF(INDEX(Variables!$D$5:$D$65,MATCH($A110,Variables!$A$5:$A$65,0))="","","."&INDEX(Variables!$D$5:$D$65,MATCH($A110,Variables!$A$5:$A$65,0)))&"."&K$5 | L110: =INDEX(MTInputs!$J$1:$AZ$415,$D110,MATCH(L$5,MTInputs!$J$5:$AZ$5,0)) | M110: =INDEX(MTInputs!$J$1:$AZ$415,$D110,MATCH(M$5,MTInputs!$J$5:$AZ$5,0)) | N110: =INDEX(MTInputs!$J$1:$AZ$415,$D110,MATCH(N$5,MTInputs!$J$5:$AZ$5,0)) | O110: =INDEX(MTInputs!$J$1:$AZ$415,$D110,MATCH(O$5,MTInputs!$J$5:$AZ$5,0)) | P110: =INDEX(MTInputs!$J$1:$AZ$415,$D110,MATCH(P$5,MTInputs!$J$5:$AZ$5,0)) | Q110: =INDEX(MTInputs!$J$1:$AZ$415,$D110,MATCH(Q$5,MTInputs!$J$5:$AZ$5,0)) | R110: =INDEX(MTInputs!$J$1:$AZ$415,$D110,MATCH(R$5,MTInputs!$J$5:$AZ$5,0)) | S110: =INDEX(MTInputs!$J$1:$AZ$415,$D110,MATCH(S$5,MTInputs!$J$5:$AZ$5,0)) | ... Y110: =INDEX(MTInputs!$J$1:$AZ$415,$D110,MATCH(Y$5,MTInputs!$J$5:$AZ$5,0)) | Z110: =LOWER(Settings!$C$4)&".mit."&$A110&IF($C110="","","."&$C110&"."&$B110)&IF(INDEX(Variables!$D$5:$D$65,MATCH($A110,Variables!$A$5:$A$65,0))="","","."&INDEX(Variables!$D$5:$D$65,MATCH($A110,Variables!$A$5:$A$65,0)))&"."&Z$5 | AA110: =INDEX(MTInputs!$J$1:$AZ$415,$D110,MATCH(AA$5,MTInputs!$J$5:$AZ$5,0)) | AB110: =INDEX(MTInputs!$J$1:$AZ$415,$D110,MATCH(AB$5,MTInputs!$J$5:$AZ$5,0)) | AC110: =INDEX(MTInputs!$J$1:$AZ$415,$D110,MATCH(AC$5,MTInputs!$J$5:$AZ$5,0)) | AD110: =INDEX(MTInputs!$J$1:$AZ$415,$D110,MATCH(AD$5,MTInputs!$J$5:$AZ$5,0)) | AE110: =INDEX(MTInputs!$J$1:$AZ$415,$D110,MATCH(AE$5,MTInputs!$J$5:$AZ$5,0)) | AF110: =INDEX(MTInputs!$J$1:$AZ$415,$D110,MATCH(AF$5,MTInputs!$J$5:$AZ$5,0)) | AG110: =INDEX(MTInputs!$J$1:$AZ$415,$D110,MATCH(AG$5,MTInputs!$J$5:$AZ$5,0)) | AH110: =INDEX(MTInputs!$J$1:$AZ$415,$D110,MATCH(AH$5,MTInputs!$J$5:$AZ$5,0)) | ... AN110: =INDEX(MTInputs!$J$1:$AZ$415,$D110,MATCH(AN$5,MTInputs!$J$5:$AZ$5,0))
A111: fbcov | B111: all | C111: foo | D111: 72 | H111: =INDEX(Variables!$B$5:$B$65,MATCH($A111,Variables!$A$5:$A$65,0))&IF($C111="",""," | "&INDEX(Mapping!$B$5:$B$25,MATCH($C111,Mapping!$A$5:$A$25,0))&" | "&INDEX(Mapping!$B$29:$B$38,MATCH($B111,Mapping!$A$29:$A$38,0))) | I111: =INDEX(Variables!$C$5:$C$65,MATCH($A111,Variables!$A$5:$A$65,0)) | J111: =INDEX(Variables!$E$5:$E$65,MATCH($A111,Variables!$A$5:$A$65,0)) | K111: =LOWER(Settings!$C$4)&".mit."&$A111&IF($C111="","","."&$C111&"."&$B111)&IF(INDEX(Variables!$D$5:$D$65,MATCH($A111,Variables!$A$5:$A$65,0))="","","."&INDEX(Variables!$D$5:$D$65,MATCH($A111,Variables!$A$5:$A$65,0)))&"."&K$5 | L111: =INDEX(MTInputs!$J$1:$AZ$415,$D111,MATCH(L$5,MTInputs!$J$5:$AZ$5,0)) | M111: =INDEX(MTInputs!$J$1:$AZ$415,$D111,MATCH(M$5,MTInputs!$J$5:$AZ$5,0)) | N111: =INDEX(MTInputs!$J$1:$AZ$415,$D111,MATCH(N$5,MTInputs!$J$5:$AZ$5,0)) | O111: =INDEX(MTInputs!$J$1:$AZ$415,$D111,MATCH(O$5,MTInputs!$J$5:$AZ$5,0)) | P111: =INDEX(MTInputs!$J$1:$AZ$415,$D111,MATCH(P$5,MTInputs!$J$5:$AZ$5,0)) | Q111: =INDEX(MTInputs!$J$1:$AZ$415,$D111,MATCH(Q$5,MTInputs!$J$5:$AZ$5,0)) | R111: =INDEX(MTInputs!$J$1:$AZ$415,$D111,MATCH(R$5,MTInputs!$J$5:$AZ$5,0)) | S111: =INDEX(MTInputs!$J$1:$AZ$415,$D111,MATCH(S$5,MTInputs!$J$5:$AZ$5,0)) | ... Y111: =INDEX(MTInputs!$J$1:$AZ$415,$D111,MATCH(Y$5,MTInputs!$J$5:$AZ$5,0)) | Z111: =LOWER(Settings!$C$4)&".mit."&$A111&IF($C111="","","."&$C111&"."&$B111)&IF(INDEX(Variables!$D$5:$D$65,MATCH($A111,Variables!$A$5:$A$65,0))="","","."&INDEX(Variables!$D$5:$D$65,MATCH($A111,Variables!$A$5:$A$65,0)))&"."&Z$5 | AA111: =INDEX(MTInputs!$J$1:$AZ$415,$D111,MATCH(AA$5,MTInputs!$J$5:$AZ$5,0)) | AB111: =INDEX(MTInputs!$J$1:$AZ$415,$D111,MATCH(AB$5,MTInputs!$J$5:$AZ$5,0)) | AC111: =INDEX(MTInputs!$J$1:$AZ$415,$D111,MATCH(AC$5,MTInputs!$J$5:$AZ$5,0)) | AD111: =INDEX(MTInputs!$J$1:$AZ$415,$D111,MATCH(AD$5,MTInputs!$J$5:$AZ$5,0)) | AE111: =INDEX(MTInputs!$J$1:$AZ$415,$D111,MATCH(AE$5,MTInputs!$J$5:$AZ$5,0)) | AF111: =INDEX(MTInputs!$J$1:$AZ$415,$D111,MATCH(AF$5,MTInputs!$J$5:$AZ$5,0)) | AG111: =INDEX(MTInputs!$J$1:$AZ$415,$D111,MATCH(AG$5,MTInputs!$J$5:$AZ$5,0)) | AH111: =INDEX(MTInputs!$J$1:$AZ$415,$D111,MATCH(AH$5,MTInputs!$J$5:$AZ$5,0)) | ... AN111: =INDEX(MTInputs!$J$1:$AZ$415,$D111,MATCH(AN$5,MTInputs!$J$5:$AZ$5,0))
A112: fbcov | B112: all | C112: srv | D112: 73 | H112: =INDEX(Variables!$B$5:$B$65,MATCH($A112,Variables!$A$5:$A$65,0))&IF($C112="",""," | "&INDEX(Mapping!$B$5:$B$25,MATCH($C112,Mapping!$A$5:$A$25,0))&" | "&INDEX(Mapping!$B$29:$B$38,MATCH($B112,Mapping!$A$29:$A$38,0))) | I112: =INDEX(Variables!$C$5:$C$65,MATCH($A112,Variables!$A$5:$A$65,0)) | J112: =INDEX(Variables!$E$5:$E$65,MATCH($A112,Variables!$A$5:$A$65,0)) | K112: =LOWER(Settings!$C$4)&".mit."&$A112&IF($C112="","","."&$C112&"."&$B112)&IF(INDEX(Variables!$D$5:$D$65,MATCH($A112,Variables!$A$5:$A$65,0))="","","."&INDEX(Variables!$D$5:$D$65,MATCH($A112,Variables!$A$5:$A$65,0)))&"."&K$5 | L112: =INDEX(MTInputs!$J$1:$AZ$415,$D112,MATCH(L$5,MTInputs!$J$5:$AZ$5,0)) | M112: =INDEX(MTInputs!$J$1:$AZ$415,$D112,MATCH(M$5,MTInputs!$J$5:$AZ$5,0)) | N112: =INDEX(MTInputs!$J$1:$AZ$415,$D112,MATCH(N$5,MTInputs!$J$5:$AZ$5,0)) | O112: =INDEX(MTInputs!$J$1:$AZ$415,$D112,MATCH(O$5,MTInputs!$J$5:$AZ$5,0)) | P112: =INDEX(MTInputs!$J$1:$AZ$415,$D112,MATCH(P$5,MTInputs!$J$5:$AZ$5,0)) | Q112: =INDEX(MTInputs!$J$1:$AZ$415,$D112,MATCH(Q$5,MTInputs!$J$5:$AZ$5,0)) | R112: =INDEX(MTInputs!$J$1:$AZ$415,$D112,MATCH(R$5,MTInputs!$J$5:$AZ$5,0)) | S112: =INDEX(MTInputs!$J$1:$AZ$415,$D112,MATCH(S$5,MTInputs!$J$5:$AZ$5,0)) | ... Y112: =INDEX(MTInputs!$J$1:$AZ$415,$D112,MATCH(Y$5,MTInputs!$J$5:$AZ$5,0)) | Z112: =LOWER(Settings!$C$4)&".mit."&$A112&IF($C112="","","."&$C112&"."&$B112)&IF(INDEX(Variables!$D$5:$D$65,MATCH($A112,Variables!$A$5:$A$65,0))="","","."&INDEX(Variables!$D$5:$D$65,MATCH($A112,Variables!$A$5:$A$65,0)))&"."&Z$5 | AA112: =INDEX(MTInputs!$J$1:$AZ$415,$D112,MATCH(AA$5,MTInputs!$J$5:$AZ$5,0)) | AB112: =INDEX(MTInputs!$J$1:$AZ$415,$D112,MATCH(AB$5,MTInputs!$J$5:$AZ$5,0)) | AC112: =INDEX(MTInputs!$J$1:$AZ$415,$D112,MATCH(AC$5,MTInputs!$J$5:$AZ$5,0)) | AD112: =INDEX(MTInputs!$J$1:$AZ$415,$D112,MATCH(AD$5,MTInputs!$J$5:$AZ$5,0)) | AE112: =INDEX(MTInputs!$J$1:$AZ$415,$D112,MATCH(AE$5,MTInputs!$J$5:$AZ$5,0)) | AF112: =INDEX(MTInputs!$J$1:$AZ$415,$D112,MATCH(AF$5,MTInputs!$J$5:$AZ$5,0)) | AG112: =INDEX(MTInputs!$J$1:$AZ$415,$D112,MATCH(AG$5,MTInputs!$J$5:$AZ$5,0)) | AH112: =INDEX(MTInputs!$J$1:$AZ$415,$D112,MATCH(AH$5,MTInputs!$J$5:$AZ$5,0)) | ... AN112: =INDEX(MTInputs!$J$1:$AZ$415,$D112,MATCH(AN$5,MTInputs!$J$5:$AZ$5,0))
A113: fbcov | B113: all | C113: mch | D113: 74 | H113: =INDEX(Variables!$B$5:$B$65,MATCH($A113,Variables!$A$5:$A$65,0))&IF($C113="",""," | "&INDEX(Mapping!$B$5:$B$25,MATCH($C113,Mapping!$A$5:$A$25,0))&" | "&INDEX(Mapping!$B$29:$B$38,MATCH($B113,Mapping!$A$29:$A$38,0))) | I113: =INDEX(Variables!$C$5:$C$65,MATCH($A113,Variables!$A$5:$A$65,0)) | J113: =INDEX(Variables!$E$5:$E$65,MATCH($A113,Variables!$A$5:$A$65,0)) | K113: =LOWER(Settings!$C$4)&".mit."&$A113&IF($C113="","","."&$C113&"."&$B113)&IF(INDEX(Variables!$D$5:$D$65,MATCH($A113,Variables!$A$5:$A$65,0))="","","."&INDEX(Variables!$D$5:$D$65,MATCH($A113,Variables!$A$5:$A$65,0)))&"."&K$5 | L113: =INDEX(MTInputs!$J$1:$AZ$415,$D113,MATCH(L$5,MTInputs!$J$5:$AZ$5,0)) | M113: =INDEX(MTInputs!$J$1:$AZ$415,$D113,MATCH(M$5,MTInputs!$J$5:$AZ$5,0)) | N113: =INDEX(MTInputs!$J$1:$AZ$415,$D113,MATCH(N$5,MTInputs!$J$5:$AZ$5,0)) | O113: =INDEX(MTInputs!$J$1:$AZ$415,$D113,MATCH(O$5,MTInputs!$J$5:$AZ$5,0)) | P113: =INDEX(MTInputs!$J$1:$AZ$415,$D113,MATCH(P$5,MTInputs!$J$5:$AZ$5,0)) | Q113: =INDEX(MTInputs!$J$1:$AZ$415,$D113,MATCH(Q$5,MTInputs!$J$5:$AZ$5,0)) | R113: =INDEX(MTInputs!$J$1:$AZ$415,$D113,MATCH(R$5,MTInputs!$J$5:$AZ$5,0)) | S113: =INDEX(MTInputs!$J$1:$AZ$415,$D113,MATCH(S$5,MTInputs!$J$5:$AZ$5,0)) | ... Y113: =INDEX(MTInputs!$J$1:$AZ$415,$D113,MATCH(Y$5,MTInputs!$J$5:$AZ$5,0)) | Z113: =LOWER(Settings!$C$4)&".mit."&$A113&IF($C113="","","."&$C113&"."&$B113)&IF(INDEX(Variables!$D$5:$D$65,MATCH($A113,Variables!$A$5:$A$65,0))="","","."&INDEX(Variables!$D$5:$D$65,MATCH($A113,Variables!$A$5:$A$65,0)))&"."&Z$5 | AA113: =INDEX(MTInputs!$J$1:$AZ$415,$D113,MATCH(AA$5,MTInputs!$J$5:$AZ$5,0)) | AB113: =INDEX(MTInputs!$J$1:$AZ$415,$D113,MATCH(AB$5,MTInputs!$J$5:$AZ$5,0)) | AC113: =INDEX(MTInputs!$J$1:$AZ$415,$D113,MATCH(AC$5,MTInputs!$J$5:$AZ$5,0)) | AD113: =INDEX(MTInputs!$J$1:$AZ$415,$D113,MATCH(AD$5,MTInputs!$J$5:$AZ$5,0)) | AE113: =INDEX(MTInputs!$J$1:$AZ$415,$D113,MATCH(AE$5,MTInputs!$J$5:$AZ$5,0)) | AF113: =INDEX(MTInputs!$J$1:$AZ$415,$D113,MATCH(AF$5,MTInputs!$J$5:$AZ$5,0)) | AG113: =INDEX(MTInputs!$J$1:$AZ$415,$D113,MATCH(AG$5,MTInputs!$J$5:$AZ$5,0)) | AH113: =INDEX(MTInputs!$J$1:$AZ$415,$D113,MATCH(AH$5,MTInputs!$J$5:$AZ$5,0)) | ... AN113: =INDEX(MTInputs!$J$1:$AZ$415,$D113,MATCH(AN$5,MTInputs!$J$5:$AZ$5,0))
A114: fbcov | B114: all | C114: irn | D114: 75 | H114: =INDEX(Variables!$B$5:$B$65,MATCH($A114,Variables!$A$5:$A$65,0))&IF($C114="",""," | "&INDEX(Mapping!$B$5:$B$25,MATCH($C114,Mapping!$A$5:$A$25,0))&" | "&INDEX(Mapping!$B$29:$B$38,MATCH($B114,Mapping!$A$29:$A$38,0))) | I114: =INDEX(Variables!$C$5:$C$65,MATCH($A114,Variables!$A$5:$A$65,0)) | J114: =INDEX(Variables!$E$5:$E$65,MATCH($A114,Variables!$A$5:$A$65,0)) | K114: =LOWER(Settings!$C$4)&".mit."&$A114&IF($C114="","","."&$C114&"."&$B114)&IF(INDEX(Variables!$D$5:$D$65,MATCH($A114,Variables!$A$5:$A$65,0))="","","."&INDEX(Variables!$D$5:$D$65,MATCH($A114,Variables!$A$5:$A$65,0)))&"."&K$5 | L114: =INDEX(MTInputs!$J$1:$AZ$415,$D114,MATCH(L$5,MTInputs!$J$5:$AZ$5,0)) | M114: =INDEX(MTInputs!$J$1:$AZ$415,$D114,MATCH(M$5,MTInputs!$J$5:$AZ$5,0)) | N114: =INDEX(MTInputs!$J$1:$AZ$415,$D114,MATCH(N$5,MTInputs!$J$5:$AZ$5,0)) | O114: =INDEX(MTInputs!$J$1:$AZ$415,$D114,MATCH(O$5,MTInputs!$J$5:$AZ$5,0)) | P114: =INDEX(MTInputs!$J$1:$AZ$415,$D114,MATCH(P$5,MTInputs!$J$5:$AZ$5,0)) | Q114: =INDEX(MTInputs!$J$1:$AZ$415,$D114,MATCH(Q$5,MTInputs!$J$5:$AZ$5,0)) | R114: =INDEX(MTInputs!$J$1:$AZ$415,$D114,MATCH(R$5,MTInputs!$J$5:$AZ$5,0)) | S114: =INDEX(MTInputs!$J$1:$AZ$415,$D114,MATCH(S$5,MTInputs!$J$5:$AZ$5,0)) | ... Y114: =INDEX(MTInputs!$J$1:$AZ$415,$D114,MATCH(Y$5,MTInputs!$J$5:$AZ$5,0)) | Z114: =LOWER(Settings!$C$4)&".mit."&$A114&IF($C114="","","."&$C114&"."&$B114)&IF(INDEX(Variables!$D$5:$D$65,MATCH($A114,Variables!$A$5:$A$65,0))="","","."&INDEX(Variables!$D$5:$D$65,MATCH($A114,Variables!$A$5:$A$65,0)))&"."&Z$5 | AA114: =INDEX(MTInputs!$J$1:$AZ$415,$D114,MATCH(AA$5,MTInputs!$J$5:$AZ$5,0)) | AB114: =INDEX(MTInputs!$J$1:$AZ$415,$D114,MATCH(AB$5,MTInputs!$J$5:$AZ$5,0)) | AC114: =INDEX(MTInputs!$J$1:$AZ$415,$D114,MATCH(AC$5,MTInputs!$J$5:$AZ$5,0)) | AD114: =INDEX(MTInputs!$J$1:$AZ$415,$D114,MATCH(AD$5,MTInputs!$J$5:$AZ$5,0)) | AE114: =INDEX(MTInputs!$J$1:$AZ$415,$D114,MATCH(AE$5,MTInputs!$J$5:$AZ$5,0)) | AF114: =INDEX(MTInputs!$J$1:$AZ$415,$D114,MATCH(AF$5,MTInputs!$J$5:$AZ$5,0)) | AG114: =INDEX(MTInputs!$J$1:$AZ$415,$D114,MATCH(AG$5,MTInputs!$J$5:$AZ$5,0)) | AH114: =INDEX(MTInputs!$J$1:$AZ$415,$D114,MATCH(AH$5,MTInputs!$J$5:$AZ$5,0)) | ... AN114: =INDEX(MTInputs!$J$1:$AZ$415,$D114,MATCH(AN$5,MTInputs!$J$5:$AZ$5,0))
A115: fbcov | B115: all | C115: nfm | D115: 76 | H115: =INDEX(Variables!$B$5:$B$65,MATCH($A115,Variables!$A$5:$A$65,0))&IF($C115="",""," | "&INDEX(Mapping!$B$5:$B$25,MATCH($C115,Mapping!$A$5:$A$25,0))&" | "&INDEX(Mapping!$B$29:$B$38,MATCH($B115,Mapping!$A$29:$A$38,0))) | I115: =INDEX(Variables!$C$5:$C$65,MATCH($A115,Variables!$A$5:$A$65,0)) | J115: =INDEX(Variables!$E$5:$E$65,MATCH($A115,Variables!$A$5:$A$65,0)) | K115: =LOWER(Settings!$C$4)&".mit."&$A115&IF($C115="","","."&$C115&"."&$B115)&IF(INDEX(Variables!$D$5:$D$65,MATCH($A115,Variables!$A$5:$A$65,0))="","","."&INDEX(Variables!$D$5:$D$65,MATCH($A115,Variables!$A$5:$A$65,0)))&"."&K$5 | L115: =INDEX(MTInputs!$J$1:$AZ$415,$D115,MATCH(L$5,MTInputs!$J$5:$AZ$5,0)) | M115: =INDEX(MTInputs!$J$1:$AZ$415,$D115,MATCH(M$5,MTInputs!$J$5:$AZ$5,0)) | N115: =INDEX(MTInputs!$J$1:$AZ$415,$D115,MATCH(N$5,MTInputs!$J$5:$AZ$5,0)) | O115: =INDEX(MTInputs!$J$1:$AZ$415,$D115,MATCH(O$5,MTInputs!$J$5:$AZ$5,0)) | P115: =INDEX(MTInputs!$J$1:$AZ$415,$D115,MATCH(P$5,MTInputs!$J$5:$AZ$5,0)) | Q115: =INDEX(MTInputs!$J$1:$AZ$415,$D115,MATCH(Q$5,MTInputs!$J$5:$AZ$5,0)) | R115: =INDEX(MTInputs!$J$1:$AZ$415,$D115,MATCH(R$5,MTInputs!$J$5:$AZ$5,0)) | S115: =INDEX(MTInputs!$J$1:$AZ$415,$D115,MATCH(S$5,MTInputs!$J$5:$AZ$5,0)) | ... Y115: =INDEX(MTInputs!$J$1:$AZ$415,$D115,MATCH(Y$5,MTInputs!$J$5:$AZ$5,0)) | Z115: =LOWER(Settings!$C$4)&".mit."&$A115&IF($C115="","","."&$C115&"."&$B115)&IF(INDEX(Variables!$D$5:$D$65,MATCH($A115,Variables!$A$5:$A$65,0))="","","."&INDEX(Variables!$D$5:$D$65,MATCH($A115,Variables!$A$5:$A$65,0)))&"."&Z$5 | AA115: =INDEX(MTInputs!$J$1:$AZ$415,$D115,MATCH(AA$5,MTInputs!$J$5:$AZ$5,0)) | AB115: =INDEX(MTInputs!$J$1:$AZ$415,$D115,MATCH(AB$5,MTInputs!$J$5:$AZ$5,0)) | AC115: =INDEX(MTInputs!$J$1:$AZ$415,$D115,MATCH(AC$5,MTInputs!$J$5:$AZ$5,0)) | AD115: =INDEX(MTInputs!$J$1:$AZ$415,$D115,MATCH(AD$5,MTInputs!$J$5:$AZ$5,0)) | AE115: =INDEX(MTInputs!$J$1:$AZ$415,$D115,MATCH(AE$5,MTInputs!$J$5:$AZ$5,0)) | AF115: =INDEX(MTInputs!$J$1:$AZ$415,$D115,MATCH(AF$5,MTInputs!$J$5:$AZ$5,0)) | AG115: =INDEX(MTInputs!$J$1:$AZ$415,$D115,MATCH(AG$5,MTInputs!$J$5:$AZ$5,0)) | AH115: =INDEX(MTInputs!$J$1:$AZ$415,$D115,MATCH(AH$5,MTInputs!$J$5:$AZ$5,0)) | ... AN115: =INDEX(MTInputs!$J$1:$AZ$415,$D115,MATCH(AN$5,MTInputs!$J$5:$AZ$5,0))
A116: fbcov | B116: all | C116: mac | D116: 77 | H116: =INDEX(Variables!$B$5:$B$65,MATCH($A116,Variables!$A$5:$A$65,0))&IF($C116="",""," | "&INDEX(Mapping!$B$5:$B$25,MATCH($C116,Mapping!$A$5:$A$25,0))&" | "&INDEX(Mapping!$B$29:$B$38,MATCH($B116,Mapping!$A$29:$A$38,0))) | I116: =INDEX(Variables!$C$5:$C$65,MATCH($A116,Variables!$A$5:$A$65,0)) | J116: =INDEX(Variables!$E$5:$E$65,MATCH($A116,Variables!$A$5:$A$65,0)) | K116: =LOWER(Settings!$C$4)&".mit."&$A116&IF($C116="","","."&$C116&"."&$B116)&IF(INDEX(Variables!$D$5:$D$65,MATCH($A116,Variables!$A$5:$A$65,0))="","","."&INDEX(Variables!$D$5:$D$65,MATCH($A116,Variables!$A$5:$A$65,0)))&"."&K$5 | L116: =INDEX(MTInputs!$J$1:$AZ$415,$D116,MATCH(L$5,MTInputs!$J$5:$AZ$5,0)) | M116: =INDEX(MTInputs!$J$1:$AZ$415,$D116,MATCH(M$5,MTInputs!$J$5:$AZ$5,0)) | N116: =INDEX(MTInputs!$J$1:$AZ$415,$D116,MATCH(N$5,MTInputs!$J$5:$AZ$5,0)) | O116: =INDEX(MTInputs!$J$1:$AZ$415,$D116,MATCH(O$5,MTInputs!$J$5:$AZ$5,0)) | P116: =INDEX(MTInputs!$J$1:$AZ$415,$D116,MATCH(P$5,MTInputs!$J$5:$AZ$5,0)) | Q116: =INDEX(MTInputs!$J$1:$AZ$415,$D116,MATCH(Q$5,MTInputs!$J$5:$AZ$5,0)) | R116: =INDEX(MTInputs!$J$1:$AZ$415,$D116,MATCH(R$5,MTInputs!$J$5:$AZ$5,0)) | S116: =INDEX(MTInputs!$J$1:$AZ$415,$D116,MATCH(S$5,MTInputs!$J$5:$AZ$5,0)) | ... Y116: =INDEX(MTInputs!$J$1:$AZ$415,$D116,MATCH(Y$5,MTInputs!$J$5:$AZ$5,0)) | Z116: =LOWER(Settings!$C$4)&".mit."&$A116&IF($C116="","","."&$C116&"."&$B116)&IF(INDEX(Variables!$D$5:$D$65,MATCH($A116,Variables!$A$5:$A$65,0))="","","."&INDEX(Variables!$D$5:$D$65,MATCH($A116,Variables!$A$5:$A$65,0)))&"."&Z$5 | AA116: =INDEX(MTInputs!$J$1:$AZ$415,$D116,MATCH(AA$5,MTInputs!$J$5:$AZ$5,0)) | AB116: =INDEX(MTInputs!$J$1:$AZ$415,$D116,MATCH(AB$5,MTInputs!$J$5:$AZ$5,0)) | AC116: =INDEX(MTInputs!$J$1:$AZ$415,$D116,MATCH(AC$5,MTInputs!$J$5:$AZ$5,0)) | AD116: =INDEX(MTInputs!$J$1:$AZ$415,$D116,MATCH(AD$5,MTInputs!$J$5:$AZ$5,0)) | AE116: =INDEX(MTInputs!$J$1:$AZ$415,$D116,MATCH(AE$5,MTInputs!$J$5:$AZ$5,0)) | AF116: =INDEX(MTInputs!$J$1:$AZ$415,$D116,MATCH(AF$5,MTInputs!$J$5:$AZ$5,0)) | AG116: =INDEX(MTInputs!$J$1:$AZ$415,$D116,MATCH(AG$5,MTInputs!$J$5:$AZ$5,0)) | AH116: =INDEX(MTInputs!$J$1:$AZ$415,$D116,MATCH(AH$5,MTInputs!$J$5:$AZ$5,0)) | ... AN116: =INDEX(MTInputs!$J$1:$AZ$415,$D116,MATCH(AN$5,MTInputs!$J$5:$AZ$5,0))
