Workbook

Sheet Settings
A1: CPAT industry kernel - Egypt prototype v0.9
A3: Country code | B3: egy | C3: First component of every code; CPAT convention (egy.mit.<var>.<sector>.<fuel>.<type>.<scenario>)
A4: Price group for industry sectors | B4: ind | C4: C2 retail-price group the four sectors read (pow / res / ind / tra)
A5: Elasticity column | B5: Industries | C5: Column of the master elasticity table (Transport / Residential / Industries / Services)
A6: Base year | B6: 2022 | C6: MTInputs FirstYearCalculations; energy in the base year is read from Data_Energy, later years from the kernel
A7: Additional policy-induced efficiency (alpha+) | B7: =INDEX(MTInputs!$F$8:$F$415,MATCH("AdditionalEfficiencyIndustrial",MTInputs!$H$8:$H$415,0)) -> 0 | C7: Read from the MTInputs column by NameOfParameter; this is the only MTInputs dependency of the kernel rows
A8: Carbon price start year (info) | B8: =INDEX(MTInputs!$F$8:$F$415,MATCH("CPIntro",MTInputs!$H$8:$H$415,0)) -> 2026 | C8: For reference: the policy scenario new-policy wedge (nce) starts here
A9: Carbon price target (info) | B9: =INDEX(MTInputs!$F$8:$F$415,MATCH("CPLevelTarget",MTInputs!$H$8:$H$415,0)) -> 50 | C9: $/tCO2
A10: Policy bundle for scenario 2 (EGY) | B10: LEGACY | C10: Bundle run as policy scenario 2 (Scenarios section 2). LEGACY = CPAT default (regression vs v0.3/legacy). Check-sheet legacy comparisons are valid for LEGACY only.
A12: Kernel (every energy cell, year t >= 2023):
A13: F(t) = F(t-1) * (1+g)^(eY*delta) * (1+psi) * (p(t)/p(t-1))^eU * [ (s(t)/s(t-1))^eF / (1 + a + a+) ]^(1+eU)
A14: p = post-tax price (atp), s = shadow price (shp) = atp + sigma*ssc, g = post-policy GDP growth, delta = income-elasticity discount, psi = exogenous shock
A16: Sheets
A17: Manual inputs | C17: Legacy 'Manual inputs' Process Emissions section (rows 18-47, same positions): CBAM process coverage switches, product emission factors, half-elasticities.
A18: Scenarios | C18: EGY: carbon price paths, policy bundles 1A-3C (+LEGACY), active-bundle series mirrored into Data_Prices by code, pass-through factors, interface contract between work streams.
A19: Mitigation_Industry | C19: Kernel sheet in the CPAT Mitigation layout (columns A-AI, years K-AI): 4 CBAM sectors x 2 scenarios, each scenario followed by the 156-row CBAM goods block (legacy Mitigation 5881-6036 / 12198-12353). All formulas; codes built from components.
A20: MTInputs | C20: The 415-row CPAT parameter column, copied unchanged (columns A-I of the MTInputs sheet).
A21: Data_Energy | C21: Base-year energy matrix, fuel x sector, ktoe (Mitigation B4 rows 583-602).
A22: Data_Prices | C22: Pre-tax price before new policies (pbc), new-policy wedge (nce), shadow price (shp), sector coverage (tcf), share of shadow price on efficiency (ssc); both scenarios. Plus carbon price (cptraj) and auctioned ETS price (etstraj) trajectories for the CBAM block. v0.4: scenario-2 cptraj/etstraj/nce read Scenarios; interface rows pptraj, encov, obrsh, obrrb, fundsh, fundsp.
A23: Data_Macro | C23: GDP growth, income-elasticity discount factor, exogenous shock; both scenarios.
A24: Data_Elast | C24: Master elasticity table (income, usage, efficiency, AEEI) by fuel group x sector group, plus the fuel-group map.
A25: Check | C25: Kernel output against the values stored in CPAT_1_0pre_456 for the same rows; max absolute and relative differences. v0.3: plus CBAM block rows vs legacy (rows from 583). v0.4: plus Scenarios regression section. v0.5: Task A identity section (row 1429). v0.6: Task B section (row 1443). v0.7: Task C section (row 1455). v0.8: Task K section (row 1464). v0.9: Task D section (row 1476).
A27: Version log
A28: v0.1 | C28: Initial kernel (egypt+mitigation).
A29: v0.2 | C29: Conformed to NORMS.md: MTInputs used/unused colouring, hidden MT/Dashboard placeholder columns, CPAT colours, title band. No formula changes.
A30: v0.3 | C30: TASK-1: CBAM goods / process emissions block (legacy Mitigation 12198-12353, 156 rows, cols A-AI) added after each scenario; 'Manual inputs' rows 18-47; cptraj/etstraj in Data_Prices; MTInputs F117:F121 linked to Manual inputs row 22. Carbon Tax/ETS rows now read the scenario trajectories (legacy: hard zeros, broken K refs). Legacy WIP bugs fixed: fuel emissions by sector M..AE hard-coded; aluminium fuel-ER relative ref; missing post-policy process total; product-price year header. Kernel rows unchanged (regression diff 0).
A31: v0.4 | B31: 2026-10-02 | C31: Task E: Scenarios sheet (price paths LEGACY/ZERO/FLAT20_2028/RAMP_EG3/RAMP50_2034; bundles LEGACY,1A,2A,2B,3A,3B,3C; selector Settings!B10). Scenario-2 cptraj/etstraj/nce now = active-bundle series (nce = cptraj x encov x factor). New interface rows pptraj/encov/obrsh/obrrb/fundsh/fundsp (both scenarios). CBAM block o4 = fundsp, o5 = fundsh x o155, o6 = obrrb; Additional ER rows o107-o114 read o4 instead of o5. Manual inputs E21 = bundle process flag. LEGACY: regression diff vs v0.3 ~1e-15 (floating point of cptraj x factor).
A32: v0.5 | B32: 2026-10-02 | C32: Task A: CBAM block output codes unique (cpef/cpep, emisf/emisp, emrf/emrp; combined emis/emr in spare rows o135/o136). Revenues fixed: o147-o154 = post-policy fuel CO2 x fuel inclusion + post-policy process x process inclusion (legacy: pre-policy process x fuel inclusion, no fuel revenue); split revf/revp in o137/o138, o155 = sum. Changed by design: scenario-2 revenue rows (LEGACY o155 2030: 1697.5 -> fuel only, process not covered); all other values identical to v0.4.
A33: v0.6 | B33: 2026-10-02 | C33: Task B: 4-way EF split (fc, fp, np, no) with coverage switches per bundle (Scenarios M:P, all 1; block o28). Price rows use covered EFs (fuel group fc+fp, process group np+no); process ER and revenues act on the covered share (o85-o92 I:J). Full process EF floored per category. Post-policy emissions by category in o13-o16 (emisfc/emisfp/emisnp/emisno.cbam.tot). All values identical to v0.5 with switches = 1.
A34: v0.7 | B34: 2026-10-02 | C34: Task C: CBAM process emissions (np + no) priced at pptraj (new block row o63) in the process price rows, process ER, revp, product revenues and np/no emissions; fuel CO2 stays on cptraj (o2). All values identical to v0.6 (every bundle uses the same energy and process path).
A35: v0.8 | B35: 2026-10-02 | C35: Task K: CBAM metrics in block spare rows: cbcov (o39), cbint (o40), cbintch (o41), EU-export-weighted cbintchx (o51) and cbcovx (o52). New rows only; no existing value changes.
A36: v0.9 | B36: 2026-10-02 | C36: Task D: IPCC-inferred process semi-elasticities by product and category (np, no) with technical potential ERmax (Manual inputs rows 53-60); block o118-o125 apply them per category. Selector Manual inputs E50 (IPCC default; ADHOC reproduces v0.8). Anchors are placeholders equal to the ad hoc values (results unchanged) pending the IPCC research report.

Sheet Manual inputs
B1: CPAT Manual inputs
B2: Replicates the legacy 'Manual inputs' tab at the same row/column positions. Only the Process Emissions section (rows 18-47, used by the CBAM block) is ported; other rows are left blank so legacy references port 1:1.
B3: Change only green cells. Row 22 feeds MTInputs F117:F121 (as in legacy).
A18: . | B18: Process Emissions
B19: Non-Fuel Process Emissions Coverage (CBAM goods only) for ETS and Carbon Tax
H20: mining & chemicals | I20: iron and steel | J20: non-ferrous metals | K20: machinery | L20: cement
D21: Include non-fuel process emissions in ETS/CT? (legacy Dashboard!G20; v0.4: set by the active bundle, Scenarios) | E21: =Scenarios!$G$27=1 -> FALSE | H21: TRUE | I21: TRUE | J21: TRUE | L21: TRUE
H22: =AND($E$21,'Manual inputs'!H21) -> FALSE | I22: =AND($E$21,'Manual inputs'!I21) -> FALSE | J22: =AND($E$21,'Manual inputs'!J21) -> FALSE | K22: FALSE | L22: =AND($E$21,'Manual inputs'!L21) -> FALSE
B28: Emission Factors | H28: SCOPE 1 (tCO₂e/t, NH₃ integrated) | O28: SCOPE 2 + TOTALS | S28: EF INPUTS | W28: LATEST MAY 2026 EU DEFAULTS + BENCHMARKS | AD28: CONFIDENCE
D29: Product | E29: Unit | F29: CN codes | G29: Route | H29: S1.fc | I29: S1.fp | J29: S1.np | K29: S1.no | L29: S1 own | M29: Embed NH₃ | N29: S1 incl NH₃ | O29: S2 | P29: S2 in CBAM scope? | Q29: S1+S2 total | R29: CBAM- equiv | S29: fc GJ/t | T29: fc EF | U29: fp GJ/t | V29: fp EF | W29: EU def base | X29: mark up | Y29: EU def 2026 | Z29: EU bench | AA29: Gap vs def | AB29: Gap vs bench | AC29: Latest EU regulatory note (May 2026) | AD29: S1.fc / S1.fp confidence | AE29: S1.np / S1.no confidence
D30: DRI-EAF steel | E30: t crude steel | F30: 7207 10 (D); 7207 12 (D); 7208/7209 flat (partial); 7214 rebar | G30: Midrex NG shaft furnace + EAF | H30: 0.12903 | I30: 0.561 | J30: 0.04 | K30: 0 | L30: =SUM(H30:K30) -> 0.73003 | M30: 0 | N30: =L30+M30 -> 0.73003 | O30: 0.25 | P30: 0 | Q30: =N30+O30 -> 0.98003 | R30: =N30+O30*P30 -> 0.73003 | S30: 5 | T30: 56.1 | U30: 24 | V30: 56.1 | W30: 1.82 | X30: 0.1 | Y30: =W30*(1+X30) -> 2.002 | Z30: 0.481 | AA30: =R30-Y30 -> -1.27197 | AB30: =R30-Z30 -> 0.24903 | AC30: DRI-EAF. Default base 1.820 ×1.10 markup = 2.002 (2026). Benchmark 0.481 (final IR 2025/2620). CAUTION: CBAM default matrix for HRC CN 7208 may assign only BF-BOF route (4.454) — 'DRI default vacancy' risk for flat products. | AD30: S1.fc: Est: Midrex heat:reductant ratio 5:24 GJ/t NG. Total EF Auth (WSA 2023 / S1.fp: Est: Midrex standard ratio; IPCC 2006 Vol2 2C1; WSA 2023. Total Auth; | AE30: S1.np: Auth: IPCC 2006 2C1 — DRI process CO2 = 0 / S1.no: Auth: IPCC 2006 2C1
D31: Scrap-EAF steel | E31: t crude steel | F31: 7206 10; 7207 10 (E); 7214 rebar; 7208 HRC (E-route); 7216 sections | G31: Scrap-EAF | H31: 0.14025 | I31: 0 | J31: 0.015 | K31: 0 | L31: =SUM(H31:K31) -> 0.15525 | M31: 0 | N31: =L31+M31 -> 0.15525 | O31: 0.25 | P31: 0 | Q31: =N31+O31 -> 0.40525 | R31: =N31+O31*P31 -> 0.15525 | S31: 2.5 | T31: 56.1 | U31: 0 | V31: 0 | W31: 0.72 | X31: 0.1 | Y31: =W31*(1+X31) -> 0.792 | Z31: 0.072 | AA31: =R31-Y31 -> -0.63675 | AB31: =R31-Z31 -> 0.08325 | AC31: Scrap-EAF. Default base 0.720 ×1.10 = 0.792 (2026). Benchmark 0.072 (final, scrap route). | AD31: S1.fc: Est: IEA Egypt sector average; WSA 2023 scrap-EAF range 2-3 GJ/t. Tota / S1.fp: Auth: no reductant in scrap melting process | AE31: S1.np: Est: IPCC 2006 Vol2 2C1 default 0.01-0.02 tCO2/t for scrap-EAF / S1.no: Auth: IPCC 2006 2C1
D32: BF-BOF steel (reference) | E32: t crude steel | F32: 7206 10 (C); 7207 10 (C); 7209 CR (C-route); 7208 HRC (C-route) | G32: BF-BOF coal/coke | H32: 0.3844 | I32: 1.5376 | J32: 0.25 | K32: 0 | L32: =SUM(H32:K32) -> 2.172 | M32: 0 | N32: =L32+M32 -> 2.172 | O32: 0.1875 | P32: 0 | Q32: =N32+O32 -> 2.3595 | R32: =N32+O32*P32 -> 2.172 | S32: 4 | T32: 96.1 | U32: 16 | V32: 96.1 | W32: 2.8 | X32: 0.1 | Y32: =W32*(1+X32) -> 3.08 | Z32: 1.37 | AA32: =R32-Y32 -> -0.908 | AB32: =R32-Z32 -> 0.802 | AC32: BF-BOF reference. Default base 2.800 ×1.10 = 3.080 (2026). Benchmark 1.370 (final IR 2025/2620). | AD32: S1.fc: Prox: WSA 2023 global BF-BOF average. No Egypt-specific data (no produ / S1.fp: Prox: WSA 2023 BF standard; IPCC 2006 Vol2 2C1. Split Est within proxy | AE32: S1.np: Auth: IPCC 2006 Vol2 2C1 default 0.22-0.28 tCO2/t crude steel / S1.no: Auth: IPCC 2006 2C1
D33: Grey clinker (dry-process) | E33: t clinker | F33: 2523 10 (clinker); 2523 21; 2523 29 Portland cement | G33: Dry rotary kiln | H33: 0.2883 | I33: 0 | J33: 0.526 | K33: 0 | L33: =SUM(H33:K33) -> 0.8143 | M33: 0 | N33: =L33+M33 -> 0.8143 | O33: 0.05625 | P33: 1 | Q33: =N33+O33 -> 0.87055 | R33: =N33+O33*P33 -> 0.87055 | S33: 3 | T33: 96.1 | U33: 0 | V33: 0 | W33: 1.58 | X33: 0.1 | Y33: =W33*(1+X33) -> 1.738 | Z33: 0.666 | AA33: =R33-Y33 -> -0.86745 | AB33: =R33-Z33 -> 0.20455 | AC33: Cement clinker. Default base 1.580 ×1.10 = 1.738 (2026). Benchmark 0.666 (col B). S2 IN CBAM scope. | AD33: S1.fc: Est: IEA Egypt cement sector; CSI/GCCA GNR Egypt 2022. Total AukCoa / S1.fp: Auth: cement production has no chemical reductant fuel | AE33: S1.np: Auth: IPCC 2006 2A1 stoichiometric constant (44/100 × fraction CaCO3 i / S1.no: Auth
D34: Ammonia (net merchant) | E34: t NH3 | F34: 2814 10 (anhydrous ammonia) | G34: Steam methane reforming (SMR) + Haber-Bosch synthesis | H34: 0.3927 | I34: 1.4586 | J34: 0 | K34: 0 | L34: =SUM(H34:K34) -> 1.8513 | M34: 0 | N34: =L34+M34 -> 1.8513 | O34: 0.0375 | P34: 1 | Q34: =N34+O34 -> 1.8888 | R34: =N34+O34*P34 -> 1.8888 | S34: 7 | T34: 56.1 | U34: 26 | V34: 56.1 | W34: 2.05 | X34: 0.01 | Y34: =W34*(1+X34) -> 2.0705 | Z34: 1.484 | AA34: =R34-Y34 -> -0.1817 | AB34: =R34-Z34 -> 0.4048 | AC34: Egypt ammonia 2026 default = 2.07 tCO2e/t (incl 1% fertiliser markup; Argus 17 Dec 2025). Benchmark 1.522 → 1.484 after 2.5% reduction in 2026. S2 IN CBAM scope. | AD34: S1.fc: Est: IFA/EFMA BAT Vol.1; combustion ~6-8 GJ/t NH3. Total Auth (IFA sta / S1.fp: Est: IFA/EFMA BAT Vol.1 standard SMR ~24-28 GJ/t NH3. Total Auth; comb | AE34: S1.np: Auth: NH3 synthesis has no carbon process emissions / S1.no: Auth
D35: Urea | E35: t urea | F35: 3102 10 (urea >= 45% N) | G35: Urea synthesis from captured CO2 + NH3 feedstock | H35: 0.1122 | I35: 0 | J35: -0.733 | K35: 0 | L35: =SUM(H35:K35) -> -0.6208 | M35: 1.0709496 | N35: =L35+M35 -> 0.4501496 | O35: 0.0375 | P35: 1 | Q35: =N35+O35 -> 0.4876496 | R35: =N35+O35*P35 -> 0.4876496 | S35: 2 | T35: 56.1 | U35: 0 | V35: 0 | W35: 1.39 | X35: 0.01 | Y35: =W35*(1+X35) -> 1.4039 | Z35: 0.902 | AA35: =R35-Y35 -> -0.9162504 | AB35: =R35-Z35 -> -0.4143504 | AC35: NH₃ INTEGRATED in headline. Egypt urea 2026 default = 1.404 tCO2e/t (incl 1% markup; Sandbag Feb 2026). Benchmark col B 0.902 (col A 0.053 for actual-data pathway). SEFA chain uses ammonia benchmark 1.522. S2 IN CBAM scope. | AD35: S1.fc: Est: IFA/EFMA; small relative to NH3 chain. ~1.5-2.5 GJ/t urea typical / S1.fp: Auth: no additional reductant/feedstock in urea synthesis itself | AE35: S1.np: Auth: IPCC 2006 Vol2 3G stoichiometric constant. 44/60 = 0.733 tCO2 ab / S1.no: Auth
D36: Ammonium nitrate | E36: t AN | F36: 3102 30 (AN >= 28% N); 3102 40 (CAN) | G36: Ostwald process (NH3 → HNO3) + neutralisation (HNO3 + NH3 → NH4NO3) | H36: 0.1122 | I36: 0 | J36: 0 | K36: 0.97 | L36: =SUM(H36:K36) -> 1.0822 | M36: 0.40137 | N36: =L36+M36 -> 1.48357 | O36: 0.04375 | P36: 1 | Q36: =N36+O36 -> 1.52732 | R36: =N36+O36*P36 -> 1.52732 | S36: 2 | T36: 56.1 | U36: 0 | V36: 0 | W36: 2.64 | X36: 0.01 | Y36: =W36*(1+X36) -> 2.6664 | Z36: 0.302 | AA36: =R36-Y36 -> -1.13908 | AB36: =R36-Z36 -> 1.22532 | AC36: NH₃ INTEGRATED in headline. AN/CAN. Default base ~2.64 ×1.01 = 2.666 (2026, N2O-driven). Benchmark 0.302. S2 IN CBAM scope. Default value highly sensitive to assumed N2O abatement. | AD36: S1.fc: Est: IFA/EFMA BAT Vol.3; 1.5-2.5 GJ/t AN typical. Total direct EF less / S1.fp: Auth: HNO3 and neutralisation have no reductant | AE36: S1.np: Auth: AN chemistry (NH4NO3) contains no carbon / S1.no: Est: IPCC 2006 2B2; GWP AR6 AII.1.2. CRITICAL: range 0.21 (with high-e
D37: Primary aluminium | E37: t Al | F37: 7601 10 (unwrought primary); 7601 20 (alloys, semi-finished); 7604 (bars/rods); 7606 (sheet/plate) | G37: Hall-Héroult electrolysis + carbon anode prebaking | H37: 0.156 | I37: 0 | J37: 1.5 | K37: 0.85 | L37: =SUM(H37:K37) -> 2.506 | M37: 0 | N37: =L37+M37 -> 2.506 | O37: 6.75 | P37: 0 | Q37: =N37+O37 -> 9.256 | R37: =N37+O37*P37 -> 2.506 | S37: 2 | T37: 78 | U37: 0 | V37: 0 | W37: 2.06 | X37: 0.1 | Y37: =W37*(1+X37) -> 2.266 | Z37: 1.423 | AA37: =R37-Y37 -> 0.24 | AB37: =R37-Z37 -> 1.083 | AC37: Primary aluminium. Default base 2.060 ×1.10 = 2.266 (2026). Benchmark 1.423. S2 NOT in CBAM scope (direct emissions only). | AD37: S1.fc: Est: IAI 2023 smelter profile; 1.5-2.5 GJ/t range. Weighted EF 78 kgCO / S1.fp: Auth: Hall-Héroult is electrolytic; reduction is electrical not fuel-d | AE37: S1.np: Auth: IPCC 2006 Vol2 2C3 default 1.5 tCO2/t Al for prebaked anodes. Ra / S1.no: Est: IAI 2023 Egypt country profile. Global prebaked average 0.38 tCO2
B38: Legacy ad hoc semi-elasticities (AdHocCalculations; one beta for np + no; no documented source). Used only when E50 = ADHOC, and by the fund placeholder (block o107-o114)
D39: Process | E39: Half Elasticity | F39: ER at $100 (%)
D40: DRI-EAF steel | E40: 0.0010536052 | F40: 0.1
D41: Scrap-EAF steel | E41: 0.00020202707 | F41: 0.02
D42: BF-BOF steel reference | E42: 0.00051293294 | F42: 0.05
D43: Grey clinker dry-process | E43: 0.00083381609 | F43: 0.08
D44: Ammonia net | E44: 0.0019845094 | F44: 0.18
D45: Urea | E45: 0 | F45: 0
D46: AN | E46: 0.010498221 | F46: 0.65
D47: Primary aluminium | E47: 0.00083381609 | F47: 0.08
B49: Process-emission semi-elasticities (Task D, v0.9): inferred from IPCC; used by CBAM block rows o118-o125
D50: Semi-elasticity set used by the block (IPCC / ADHOC) | E50: IPCC | F50: ADHOC = rows 40-47 with ERmax = 1 (reproduces v0.8)
D51: ER(P) = ERmax x (1 - exp(-beta x P)); beta = -ln(1 - ER*/ERmax)/P* from the anchor (P*, ER*); semi-elasticity at P = 0 = ERmax x beta. np = non-fuel process CO2, no = non-CO2 process (Manual inputs J, K). ERmax = technical potential by ~2035 with commercial technology; CCS and process change are excluded (no Egyptian CO2 storage or H2-DRI before 2035).
D52: Product | E52: np ERmax | F52: np anchor P* ($/t) | G52: np ER at P* | H52: np beta (1/$) | I52: no ERmax | J52: no anchor P* ($/t) | K52: no ER at P* | L52: no beta (1/$) | M52: np semi-el. at P=0 (%/$) | N52: no semi-el. at P=0 (%/$) | O52: np ER at $20 | P52: no ER at $20 | Q52: np lever and source | R52: no lever and source | S52: Confidence | T52: beta.np used | U52: ERmax.np used | V52: beta.no used | W52: ERmax.no used
D53: DRI-EAF steel | E53: 1 | F53: 100 | G53: 0.1 | H53: =IF(OR(E53=0,G53=0),0,-LN(1-G53/E53)/F53) -> 0.0010536052 | I53: 1 | J53: 100 | K53: 0.1 | L53: =IF(OR(I53=0,K53=0),0,-LN(1-K53/I53)/J53) -> 0.0010536052 | M53: =E53*H53 -> 0.0010536052 | N53: =I53*L53 -> 0.0010536052 | O53: =E53*(1-EXP(-H53*20)) -> 0.020851638 | P53: =I53*(1-EXP(-L53*20)) -> 0.020851638 | Q53: PLACEHOLDER (ad hoc ER at $100); replace from IPCC research report. Lever: biocarbon for charge/injection carbon; electrode efficiency | R53: PLACEHOLDER (ad hoc ER at $100); replace from IPCC research report. Lever: n/a (no = 0) | S53: placeholder | T53: =IF($E$50="ADHOC",$E$40,H53) -> 0.0010536052 | U53: =IF($E$50="ADHOC",1,E53) -> 1 | V53: =IF($E$50="ADHOC",$E$40,L53) -> 0.0010536052 | W53: =IF($E$50="ADHOC",1,I53) -> 1
D54: Scrap-EAF steel | E54: 1 | F54: 100 | G54: 0.02 | H54: =IF(OR(E54=0,G54=0),0,-LN(1-G54/E54)/F54) -> 0.00020202707 | I54: 1 | J54: 100 | K54: 0.02 | L54: =IF(OR(I54=0,K54=0),0,-LN(1-K54/I54)/J54) -> 0.00020202707 | M54: =E54*H54 -> 0.00020202707 | N54: =I54*L54 -> 0.00020202707 | O54: =E54*(1-EXP(-H54*20)) -> 0.0040323895 | P54: =I54*(1-EXP(-L54*20)) -> 0.0040323895 | Q54: PLACEHOLDER (ad hoc ER at $100); replace from IPCC research report. Lever: biocarbon for charge/injection carbon; electrode efficiency | R54: PLACEHOLDER (ad hoc ER at $100); replace from IPCC research report. Lever: n/a (no = 0) | S54: placeholder | T54: =IF($E$50="ADHOC",$E$41,H54) -> 0.00020202707 | U54: =IF($E$50="ADHOC",1,E54) -> 1 | V54: =IF($E$50="ADHOC",$E$41,L54) -> 0.00020202707 | W54: =IF($E$50="ADHOC",1,I54) -> 1
D55: BF-BOF steel (reference) | E55: 1 | F55: 100 | G55: 0.05 | H55: =IF(OR(E55=0,G55=0),0,-LN(1-G55/E55)/F55) -> 0.00051293294 | I55: 1 | J55: 100 | K55: 0.05 | L55: =IF(OR(I55=0,K55=0),0,-LN(1-K55/I55)/J55) -> 0.00051293294 | M55: =E55*H55 -> 0.00051293294 | N55: =I55*L55 -> 0.00051293294 | O55: =E55*(1-EXP(-H55*20)) -> 0.010206218 | P55: =I55*(1-EXP(-L55*20)) -> 0.010206218 | Q55: PLACEHOLDER (ad hoc ER at $100); replace from IPCC research report. Lever: flux (carbonate) reduction; deep options are process change/CCS | R55: PLACEHOLDER (ad hoc ER at $100); replace from IPCC research report. Lever: n/a (no = 0) | S55: placeholder | T55: =IF($E$50="ADHOC",$E$42,H55) -> 0.00051293294 | U55: =IF($E$50="ADHOC",1,E55) -> 1 | V55: =IF($E$50="ADHOC",$E$42,L55) -> 0.00051293294 | W55: =IF($E$50="ADHOC",1,I55) -> 1
D56: Grey clinker (dry-process) | E56: 1 | F56: 100 | G56: 0.08 | H56: =IF(OR(E56=0,G56=0),0,-LN(1-G56/E56)/F56) -> 0.00083381609 | I56: 1 | J56: 100 | K56: 0.08 | L56: =IF(OR(I56=0,K56=0),0,-LN(1-K56/I56)/J56) -> 0.00083381609 | M56: =E56*H56 -> 0.00083381609 | N56: =I56*L56 -> 0.00083381609 | O56: =E56*(1-EXP(-H56*20)) -> 0.016538042 | P56: =I56*(1-EXP(-L56*20)) -> 0.016538042 | Q56: PLACEHOLDER (ad hoc ER at $100); replace from IPCC research report. Lever: decarbonated raw materials; CCS excluded before 2035 | R56: PLACEHOLDER (ad hoc ER at $100); replace from IPCC research report. Lever: n/a (no = 0) | S56: placeholder | T56: =IF($E$50="ADHOC",$E$43,H56) -> 0.00083381609 | U56: =IF($E$50="ADHOC",1,E56) -> 1 | V56: =IF($E$50="ADHOC",$E$43,L56) -> 0.00083381609 | W56: =IF($E$50="ADHOC",1,I56) -> 1
D57: Ammonia (net merchant) | E57: 1 | F57: 100 | G57: 0.18 | H57: =IF(OR(E57=0,G57=0),0,-LN(1-G57/E57)/F57) -> 0.0019845094 | I57: 1 | J57: 100 | K57: 0.18 | L57: =IF(OR(I57=0,K57=0),0,-LN(1-K57/I57)/J57) -> 0.0019845094 | M57: =E57*H57 -> 0.0019845094 | N57: =I57*L57 -> 0.0019845094 | O57: =E57*(1-EXP(-H57*20)) -> 0.03891285 | P57: =I57*(1-EXP(-L57*20)) -> 0.03891285 | Q57: PLACEHOLDER (ad hoc ER at $100); replace from IPCC research report. Lever: n/a (np = 0; SMR CO2 is fp) | R57: PLACEHOLDER (ad hoc ER at $100); replace from IPCC research report. Lever: n/a (no = 0) | S57: placeholder | T57: =IF($E$50="ADHOC",$E$44,H57) -> 0.0019845094 | U57: =IF($E$50="ADHOC",1,E57) -> 1 | V57: =IF($E$50="ADHOC",$E$44,L57) -> 0.0019845094 | W57: =IF($E$50="ADHOC",1,I57) -> 1
D58: Urea | E58: 1 | F58: 100 | G58: 0 | H58: =IF(OR(E58=0,G58=0),0,-LN(1-G58/E58)/F58) -> 0 | I58: 1 | J58: 100 | K58: 0 | L58: =IF(OR(I58=0,K58=0),0,-LN(1-K58/I58)/J58) -> 0 | M58: =E58*H58 -> 0 | N58: =I58*L58 -> 0 | O58: =E58*(1-EXP(-H58*20)) -> 0 | P58: =I58*(1-EXP(-L58*20)) -> 0 | Q58: PLACEHOLDER (ad hoc ER at $100); replace from IPCC research report. Lever: n/a (np < 0, captured CO2) | R58: PLACEHOLDER (ad hoc ER at $100); replace from IPCC research report. Lever: n/a (no = 0) | S58: placeholder | T58: =IF($E$50="ADHOC",$E$45,H58) -> 0 | U58: =IF($E$50="ADHOC",1,E58) -> 1 | V58: =IF($E$50="ADHOC",$E$45,L58) -> 0 | W58: =IF($E$50="ADHOC",1,I58) -> 1
D59: Ammonium nitrate | E59: 1 | F59: 100 | G59: 0.65 | H59: =IF(OR(E59=0,G59=0),0,-LN(1-G59/E59)/F59) -> 0.010498221 | I59: 1 | J59: 100 | K59: 0.65 | L59: =IF(OR(I59=0,K59=0),0,-LN(1-K59/I59)/J59) -> 0.010498221 | M59: =E59*H59 -> 0.010498221 | N59: =I59*L59 -> 0.010498221 | O59: =E59*(1-EXP(-H59*20)) -> 0.18938692 | P59: =I59*(1-EXP(-L59*20)) -> 0.18938692 | Q59: PLACEHOLDER (ad hoc ER at $100); replace from IPCC research report. Lever: n/a (np = 0) | R59: PLACEHOLDER (ad hoc ER at $100); replace from IPCC research report. Lever: nitric-acid N2O: secondary/tertiary catalysts, NSCR | S59: placeholder | T59: =IF($E$50="ADHOC",$E$46,H59) -> 0.010498221 | U59: =IF($E$50="ADHOC",1,E59) -> 1 | V59: =IF($E$50="ADHOC",$E$46,L59) -> 0.010498221 | W59: =IF($E$50="ADHOC",1,I59) -> 1
D60: Primary aluminium | E60: 1 | F60: 100 | G60: 0.08 | H60: =IF(OR(E60=0,G60=0),0,-LN(1-G60/E60)/F60) -> 0.00083381609 | I60: 1 | J60: 100 | K60: 0.08 | L60: =IF(OR(I60=0,K60=0),0,-LN(1-K60/I60)/J60) -> 0.00083381609 | M60: =E60*H60 -> 0.00083381609 | N60: =I60*L60 -> 0.00083381609 | O60: =E60*(1-EXP(-H60*20)) -> 0.016538042 | P60: =I60*(1-EXP(-L60*20)) -> 0.016538042 | Q60: PLACEHOLDER (ad hoc ER at $100); replace from IPCC research report. Lever: anode carbon consumption; inert anodes not commercial before 2035 | R60: PLACEHOLDER (ad hoc ER at $100); replace from IPCC research report. Lever: PFC: anode-effect management, point feeders | S60: placeholder | T60: =IF($E$50="ADHOC",$E$47,H60) -> 0.00083381609 | U60: =IF($E$50="ADHOC",1,E60) -> 1 | V60: =IF($E$50="ADHOC",$E$47,L60) -> 0.00083381609 | W60: =IF($E$50="ADHOC",1,I60) -> 1

Sheet Scenarios
B1: Scenarios (EGY): carbon price paths, policy bundles, active-bundle series
B2: Policy scenario 2 runs the bundle selected in Settings!B10 (one at a time). Section 4 is mirrored into Data_Prices by code. LEGACY reproduces v0.3 / CPAT default values exactly.
B3: Change only green cells. Bundles from EgyptResultsInitial.docx Table 1/2.
A5: 1 | B5: Carbon price paths ($/ton CO2 real)
B6: Path | C6: Description | D6: Source | I6: Unit | J6: Scenario | K6: 2021 | L6: 2022 | M6: 2023 | N6: 2024 | O6: 2025 | P6: 2026 | Q6: 2027 | R6: 2028 | S6: 2029 | T6: 2030 | U6: 2031 | V6: 2032 | W6: 2033 | X6: 2034 | Y6: 2035 | Z6: 2036 | AA6: 2037 | AB6: 2038 | AC6: 2039 | AD6: 2040 | AE6: 2041 | AF6: 2042 | AG6: 2043 | AH6: 2044 | AI6: 2045
B7: LEGACY_CP | C7: CPAT default carbon tax path in the legacy file | D7: CPAT 1.0pre_456 Mitigation row 8582 (cptraj.2) | I7: $/ton CO2 real | J7: EGY | L7: 0 | M7: 0 | N7: 0 | O7: 0 | P7: 0 | Q7: 12.5 | R7: 25 | S7: 37.5 | T7: 50 | U7: 62.5 | V7: 75 | W7: 87.5 | X7: 100 | Y7: 112.5 | Z7: 125 | AA7: 137.5 | AB7: 150 | AC7: 162.5 | AD7: 175 | AE7: 187.5
B8: LEGACY_ETS | C8: CPAT default auctioned ETS path in the legacy file | D8: CPAT 1.0pre_456 Mitigation row 8583 (etstraj.2) | I8: $/ton CO2 real | J8: EGY | L8: 0 | M8: 0 | N8: 0 | O8: 0 | P8: 0 | Q8: 0 | R8: 0 | S8: 0 | T8: 0 | U8: 0 | V8: 0 | W8: 0 | X8: 0 | Y8: 0 | Z8: 0 | AA8: 0 | AB8: 0 | AC8: 0 | AD8: 0 | AE8: 0
B9: ZERO | C9: No price | D9: - | I9: $/ton CO2 real | J9: EGY | K9: 0 | L9: 0 | M9: 0 | N9: 0 | O9: 0 | P9: 0 | Q9: 0 | R9: 0 | S9: 0 | T9: 0 | U9: 0 | V9: 0 | W9: 0 | X9: 0 | Y9: 0 | Z9: 0 | AA9: 0 | AB9: 0 | AC9: 0 | AD9: 0 | AE9: 0 | AF9: 0 | AG9: 0 | AH9: 0 | AI9: 0
B10: FLAT20_2028 | C10: USD20/tCO2 flat from 2028 | D10: EgyptResultsInitial 1A/2A/2B; CPAT runs EG1/EG2 | I10: $/ton CO2 real | J10: EGY | K10: 0 | L10: 0 | M10: 0 | N10: 0 | O10: 0 | P10: 0 | Q10: 0 | R10: 20 | S10: 20 | T10: 20 | U10: 20 | V10: 20 | W10: 20 | X10: 20 | Y10: 20 | Z10: 20 | AA10: 20 | AB10: 20 | AC10: 20 | AD10: 20 | AE10: 20 | AF10: 20 | AG10: 20 | AH10: 20 | AI10: 20
B11: RAMP_EG3 | C11: USD5 in 2028, +7.5/yr (USD20 in 2030, USD50 in 2034, keeps rising) | D11: CPAT run EG3 (Outputs), behind the reported 3A-3C numbers | I11: $/ton CO2 real | J11: EGY | K11: 0 | L11: 0 | M11: 0 | N11: 0 | O11: 0 | P11: 0 | Q11: 0 | R11: 5 | S11: 12.5 | T11: 20 | U11: 27.5 | V11: 35 | W11: 42.5 | X11: 50 | Y11: 57.5 | Z11: 65 | AA11: 72.5 | AB11: 80 | AC11: 87.5 | AD11: 95 | AE11: 102.5 | AF11: 110 | AG11: 117.5 | AH11: 125 | AI11: 132.5
B12: RAMP50_2034 | C12: USD5 in 2028, +7.5/yr to USD50 in 2034, flat after | D12: EgyptResultsInitial text ('USD5 to USD50 by 2034') | I12: $/ton CO2 real | J12: EGY | K12: 0 | L12: 0 | M12: 0 | N12: 0 | O12: 0 | P12: 0 | Q12: 0 | R12: 5 | S12: 12.5 | T12: 20 | U12: 27.5 | V12: 35 | W12: 42.5 | X12: 50 | Y12: 50 | Z12: 50 | AA12: 50 | AB12: 50 | AC12: 50 | AD12: 50 | AE12: 50 | AF12: 50 | AG12: 50 | AH12: 50 | AI12: 50
B13: Kernel and Data_Prices use 2022-2041 (L..AE), the CPAT data horizon. Reported EgyptResultsInitial metrics refer to 2030, when every non-legacy bundle prices USD20/tCO2. RAMP_EG3 (3A-3C default) and RAMP50_2034 differ only after 2034.
A15: 2 | B15: Policy bundles (one row per bundle)
B16: Bundle | C16: Name | D16: Energy CO2 price path | E16: ETS path | F16: Industry energy covered (share) | G16: Process emissions covered (0/1) | H16: Process price path | I16: OBR share (theta) | J16: Fund share (phi) | K16: Revenue use | L16: Energy scope in main CPAT (Task M) | M16: fc covered (0/1) | N16: fp covered (0/1) | O16: np covered (0/1) | P16: no covered (0/1)
B17: LEGACY | C17: CPAT default policy scenario (regression) | D17: LEGACY_CP | E17: LEGACY_ETS | F17: 1 | G17: 0 | H17: LEGACY_CP | I17: 0 | J17: 0 | K17: CPAT default | L17: All sectors | M17: 1 | N17: 1 | O17: 1 | P17: 1
B18: 1A | C18: Comprehensive levy + CBAM process fee | D18: FLAT20_2028 | E18: ZERO | F18: 1 | G18: 1 | H18: FLAT20_2028 | I18: 0 | J18: 0 | K18: Public investment (non-green) | L18: All sectors | M18: 1 | N18: 1 | O18: 1 | P18: 1
B19: 2A | C19: Upstream levy, public investment | D19: FLAT20_2028 | E19: ZERO | F19: 1 | G19: 0 | H19: FLAT20_2028 | I19: 0 | J19: 0 | K19: Public investment (non-green) | L19: All sectors | M19: 1 | N19: 1 | O19: 1 | P19: 1
B20: 2B | C20: Upstream levy, households | D20: FLAT20_2028 | E20: ZERO | F20: 1 | G20: 0 | H20: FLAT20_2028 | I20: 0 | J20: 0 | K20: Households (per capita) | L20: All sectors | M20: 1 | N20: 1 | O20: 1 | P20: 1
B21: 3A | C21: Downstream heavy industry, households | D21: RAMP_EG3 | E21: ZERO | F21: 1 | G21: 1 | H21: RAMP_EG3 | I21: 0 | J21: 0 | K21: Households (per capita) | L21: Industry only | M21: 1 | N21: 1 | O21: 1 | P21: 1
B22: 3B | C22: Downstream heavy industry, free allocation (benchmark) | D22: RAMP_EG3 | E22: ZERO | F22: 1 | G22: 1 | H22: RAMP_EG3 | I22: 1 | J22: 0 | K22: Firms: output-based free allocation | L22: Industry only | M22: 1 | N22: 1 | O22: 1 | P22: 1
B23: 3C | C23: Downstream heavy industry, abatement rebate | D23: RAMP_EG3 | E23: ZERO | F23: 1 | G23: 1 | H23: RAMP_EG3 | I23: 0 | J23: 1 | K23: Firms: abatement rebate fund | L23: Industry only | M23: 1 | N23: 1 | O23: 1 | P23: 1
A25: 3 | B25: Active bundle (policy scenario 2) and carbon price pass-through factors
B26: Bundle | C26: Name | D26: Energy CO2 price path | E26: ETS path | F26: Industry energy covered (share) | G26: Process emissions covered (0/1) | H26: Process price path | I26: OBR share (theta) | J26: Fund share (phi) | K26: Revenue use | L26: Energy scope in main CPAT (Task M) | M26: fc covered (0/1) | N26: fp covered (0/1) | O26: np covered (0/1) | P26: no covered (0/1)
B27: =Settings!$B$10 -> LEGACY | C27: =INDEX(C$17:C$23,MATCH($B$27,$B$17:$B$23,0)) -> CPAT default policy scenario (regression) | D27: =INDEX(D$17:D$23,MATCH($B$27,$B$17:$B$23,0)) -> LEGACY_CP | E27: =INDEX(E$17:E$23,MATCH($B$27,$B$17:$B$23,0)) -> LEGACY_ETS | F27: =INDEX(F$17:F$23,MATCH($B$27,$B$17:$B$23,0)) -> 1 | G27: =INDEX(G$17:G$23,MATCH($B$27,$B$17:$B$23,0)) -> 0 | H27: =INDEX(H$17:H$23,MATCH($B$27,$B$17:$B$23,0)) -> LEGACY_CP | I27: =INDEX(I$17:I$23,MATCH($B$27,$B$17:$B$23,0)) -> 0 | J27: =INDEX(J$17:J$23,MATCH($B$27,$B$17:$B$23,0)) -> 0 | ... P27: =INDEX(P$17:P$23,MATCH($B$27,$B$17:$B$23,0)) -> 1
B29: Fuel | C29: Pass-through factor: price units per $/ton CO2 | E29: Factor | I29: Unit | J29: Source
B30: coa | C30: CO2 content per native unit (tCO2/unit) | E30: 0.1 | I30: $/GJ per $/tCO2 | J30: Implied by CPAT: legacy nce.2 / cptraj.2 (exactly proportional)
B31: nga | C31: CO2 content per native unit (tCO2/unit) | E31: 0.0558 | I31: $/GJ per $/tCO2 | J31: Implied by CPAT: legacy nce.2 / cptraj.2 (exactly proportional)
B32: gso | C32: CO2 content per native unit (tCO2/unit) | E32: 0.0023142275 | I32: $/liter per $/tCO2 | J32: Implied by CPAT: legacy nce.2 / cptraj.2 (exactly proportional)
B33: die | C33: CO2 content per native unit (tCO2/unit) | E33: 0.0026408351 | I33: $/liter per $/tCO2 | J33: Implied by CPAT: legacy nce.2 / cptraj.2 (exactly proportional)
B34: lpg | C34: CO2 content per native unit (tCO2/unit) | E34: 0.0017684866 | I34: $/liter per $/tCO2 | J34: Implied by CPAT: legacy nce.2 / cptraj.2 (exactly proportional)
B35: ker | C35: CO2 content per native unit (tCO2/unit) | E35: 0.0025591064 | I35: $/liter per $/tCO2 | J35: Implied by CPAT: legacy nce.2 / cptraj.2 (exactly proportional)
B36: oop | C36: CO2 content per native unit (tCO2/unit) | E36: 0.469404 | I36: $/bbl per $/tCO2 | J36: Implied by CPAT: legacy nce.2 / cptraj.2 (exactly proportional)
B37: bio | C37: CO2 content per native unit (tCO2/unit) | E37: 0 | I37: $/GJ per $/tCO2 | J37: Implied by CPAT: legacy nce.2 / cptraj.2 (exactly proportional)
B38: ren | C38: CO2 content per native unit (tCO2/unit) | E38: 0 | I38: $/kwh per $/tCO2 | J38: Implied by CPAT: legacy nce.2 / cptraj.2 (exactly proportional)
A40: 4 | B40: Active-bundle series for scenario 2 (read by Data_Prices via code in column G)
B41: Variable | C41: Description | D41: Written by | E41: Unit | F41: Source | G41: Input Code | H41: Read by | J41: Scenario | K41: 2021 | L41: 2022 | M41: 2023 | N41: 2024 | O41: 2025 | P41: 2026 | Q41: 2027 | R41: 2028 | S41: 2029 | T41: 2030 | U41: 2031 | V41: 2032 | W41: 2033 | X41: 2034 | Y41: 2035 | Z41: 2036 | AA41: 2037 | AB41: 2038 | AC41: 2039 | AD41: 2040 | AE41: 2041 | AF41: 2042 | AG41: 2043 | AH41: 2044 | AI41: 2045
B42: cptraj | C42: Carbon price on energy CO2 (active bundle) | D42: Stream 2 (E) | E42: $/ton CO2 real | F42: Scenarios | G42: egy.mit.cptraj.2 | H42: kernel via nce; CBAM block o2 (fuel CO2 only from v0.7) | J42: EGY | K42: =INDEX(K$7:K$12,MATCH($D$27,$B$7:$B$12,0)) -> 0 | L42: =INDEX(L$7:L$12,MATCH($D$27,$B$7:$B$12,0)) -> 0 | M42: =INDEX(M$7:M$12,MATCH($D$27,$B$7:$B$12,0)) -> 0 | N42: =INDEX(N$7:N$12,MATCH($D$27,$B$7:$B$12,0)) -> 0 | O42: =INDEX(O$7:O$12,MATCH($D$27,$B$7:$B$12,0)) -> 0 | P42: =INDEX(P$7:P$12,MATCH($D$27,$B$7:$B$12,0)) -> 0 | Q42: =INDEX(Q$7:Q$12,MATCH($D$27,$B$7:$B$12,0)) -> 12.5 | R42: =INDEX(R$7:R$12,MATCH($D$27,$B$7:$B$12,0)) -> 25 | ... AI42: =INDEX(AI$7:AI$12,MATCH($D$27,$B$7:$B$12,0)) -> 0
B43: etstraj | C43: Auctioned ETS price (active bundle) | D43: Stream 2 (E) | E43: $/ton CO2 real | F43: Scenarios | G43: egy.mit.etstraj.2 | H43: CBAM block o3 | J43: EGY | K43: =INDEX(K$7:K$12,MATCH($E$27,$B$7:$B$12,0)) -> 0 | L43: =INDEX(L$7:L$12,MATCH($E$27,$B$7:$B$12,0)) -> 0 | M43: =INDEX(M$7:M$12,MATCH($E$27,$B$7:$B$12,0)) -> 0 | N43: =INDEX(N$7:N$12,MATCH($E$27,$B$7:$B$12,0)) -> 0 | O43: =INDEX(O$7:O$12,MATCH($E$27,$B$7:$B$12,0)) -> 0 | P43: =INDEX(P$7:P$12,MATCH($E$27,$B$7:$B$12,0)) -> 0 | Q43: =INDEX(Q$7:Q$12,MATCH($E$27,$B$7:$B$12,0)) -> 0 | R43: =INDEX(R$7:R$12,MATCH($E$27,$B$7:$B$12,0)) -> 0 | ... AI43: =INDEX(AI$7:AI$12,MATCH($E$27,$B$7:$B$12,0)) -> 0
B44: pptraj | C44: Carbon price on CBAM process emissions = process path x process flag | D44: Stream 2 (E) | E44: $/ton CO2 real | F44: Scenarios | G44: egy.mit.pptraj.2 | H44: CBAM block o63 (Task C, process price); Stream 1 L: CBAM obligations | J44: EGY | K44: =INDEX(K$7:K$12,MATCH($H$27,$B$7:$B$12,0))*$G$27 -> 0 | L44: =INDEX(L$7:L$12,MATCH($H$27,$B$7:$B$12,0))*$G$27 -> 0 | M44: =INDEX(M$7:M$12,MATCH($H$27,$B$7:$B$12,0))*$G$27 -> 0 | N44: =INDEX(N$7:N$12,MATCH($H$27,$B$7:$B$12,0))*$G$27 -> 0 | O44: =INDEX(O$7:O$12,MATCH($H$27,$B$7:$B$12,0))*$G$27 -> 0 | P44: =INDEX(P$7:P$12,MATCH($H$27,$B$7:$B$12,0))*$G$27 -> 0 | Q44: =INDEX(Q$7:Q$12,MATCH($H$27,$B$7:$B$12,0))*$G$27 -> 0 | R44: =INDEX(R$7:R$12,MATCH($H$27,$B$7:$B$12,0))*$G$27 -> 0 | ... AI44: =INDEX(AI$7:AI$12,MATCH($H$27,$B$7:$B$12,0))*$G$27 -> 0
B45: encov | C45: Share of industry energy CO2 covered by the energy price | D45: Stream 2 (E) | E45: share | F45: Scenarios | G45: egy.mit.encov.2 | H45: nce (this sheet) | J45: EGY | K45: =$F$27 -> 1 | L45: =$F$27 -> 1 | M45: =$F$27 -> 1 | N45: =$F$27 -> 1 | O45: =$F$27 -> 1 | P45: =$F$27 -> 1 | Q45: =$F$27 -> 1 | R45: =$F$27 -> 1 | ... AI45: =$F$27 -> 1
B46: obrsh | C46: Output-based rebate share theta (free allocation / benchmark) | D46: Stream 2 (E, I) | E46: share | F46: Scenarios | G46: egy.mit.obrsh.2 | H46: Stream 1 (H: output response; L: CBAM price deduction) | J46: EGY | K46: =$I$27 -> 0 | L46: =$I$27 -> 0 | M46: =$I$27 -> 0 | N46: =$I$27 -> 0 | O46: =$I$27 -> 0 | P46: =$I$27 -> 0 | Q46: =$I$27 -> 0 | R46: =$I$27 -> 0 | ... AI46: =$I$27 -> 0
B47: obrrb | C47: Output-based rebate = theta x cptraj (value returned per t at benchmark) | D47: Stream 2 (E, I) | E47: $/ton CO2 real | F47: Scenarios | G47: egy.mit.obrrb.2 | H47: CBAM block o6; Stream 1 (H, L) | J47: EGY | K47: =K46*K42 -> 0 | L47: =L46*L42 -> 0 | M47: =M46*M42 -> 0 | N47: =N46*N42 -> 0 | O47: =O46*O42 -> 0 | P47: =P46*P42 -> 0 | Q47: =Q46*Q42 -> 0 | R47: =R46*R42 -> 0 | ... AI47: =AI46*AI42 -> 0
B48: fundsh | C48: Share of revenue recycled to the industrial abatement fund phi | D48: Stream 2 (E, J) | E48: share | F48: Scenarios | G48: egy.mit.fundsh.2 | H48: CBAM block o5 | J48: EGY | K48: =$J$27 -> 0 | L48: =$J$27 -> 0 | M48: =$J$27 -> 0 | N48: =$J$27 -> 0 | O48: =$J$27 -> 0 | P48: =$J$27 -> 0 | Q48: =$J$27 -> 0 | R48: =$J$27 -> 0 | ... AI48: =$J$27 -> 0
B49: fundsp | C49: Shadow price of fund-financed abatement (acts on intensity only). Placeholder 0 until Task J | D49: Stream 2 (J) | E49: $/ton CO2 real | F49: Scenarios | G49: egy.mit.fundsp.2 | H49: CBAM block o4 -> Additional ER rows o107-o114 | J49: EGY | K49: 0 | L49: 0 | M49: 0 | N49: 0 | O49: 0 | P49: 0 | Q49: 0 | R49: 0 | S49: 0 | T49: 0 | U49: 0 | V49: 0 | W49: 0 | X49: 0 | Y49: 0 | Z49: 0 | AA49: 0 | AB49: 0 | AC49: 0 | AD49: 0 | AE49: 0 | AF49: 0 | AG49: 0 | AH49: 0 | AI49: 0
B50: nce | C50: New-policy wedge, coa = cptraj x encov x factor | D50: Stream 2 (E) | E50: $/GJ | F50: Scenarios | G50: egy.mit.nce.ind.coa.a.2 | H50: kernel atp rows | J50: EGY | K50: =K42*K45*$E$30 -> 0 | L50: =L42*L45*$E$30 -> 0 | M50: =M42*M45*$E$30 -> 0 | N50: =N42*N45*$E$30 -> 0 | O50: =O42*O45*$E$30 -> 0 | P50: =P42*P45*$E$30 -> 0 | Q50: =Q42*Q45*$E$30 -> 1.25 | R50: =R42*R45*$E$30 -> 2.5 | ... AI50: =AI42*AI45*$E$30 -> 0
B51: nce | C51: New-policy wedge, nga = cptraj x encov x factor | D51: Stream 2 (E) | E51: $/GJ | F51: Scenarios | G51: egy.mit.nce.ind.nga.a.2 | H51: kernel atp rows | J51: EGY | K51: =K42*K45*$E$31 -> 0 | L51: =L42*L45*$E$31 -> 0 | M51: =M42*M45*$E$31 -> 0 | N51: =N42*N45*$E$31 -> 0 | O51: =O42*O45*$E$31 -> 0 | P51: =P42*P45*$E$31 -> 0 | Q51: =Q42*Q45*$E$31 -> 0.6975 | R51: =R42*R45*$E$31 -> 1.395 | ... AI51: =AI42*AI45*$E$31 -> 0
B52: nce | C52: New-policy wedge, gso = cptraj x encov x factor | D52: Stream 2 (E) | E52: $/liter | F52: Scenarios | G52: egy.mit.nce.ind.gso.a.2 | H52: kernel atp rows | J52: EGY | K52: =K42*K45*$E$32 -> 0 | L52: =L42*L45*$E$32 -> 0 | M52: =M42*M45*$E$32 -> 0 | N52: =N42*N45*$E$32 -> 0 | O52: =O42*O45*$E$32 -> 0 | P52: =P42*P45*$E$32 -> 0 | Q52: =Q42*Q45*$E$32 -> 0.028927843 | R52: =R42*R45*$E$32 -> 0.057855686 | ... AI52: =AI42*AI45*$E$32 -> 0
B53: nce | C53: New-policy wedge, die = cptraj x encov x factor | D53: Stream 2 (E) | E53: $/liter | F53: Scenarios | G53: egy.mit.nce.ind.die.a.2 | H53: kernel atp rows | J53: EGY | K53: =K42*K45*$E$33 -> 0 | L53: =L42*L45*$E$33 -> 0 | M53: =M42*M45*$E$33 -> 0 | N53: =N42*N45*$E$33 -> 0 | O53: =O42*O45*$E$33 -> 0 | P53: =P42*P45*$E$33 -> 0 | Q53: =Q42*Q45*$E$33 -> 0.033010439 | R53: =R42*R45*$E$33 -> 0.066020878 | ... AI53: =AI42*AI45*$E$33 -> 0
B54: nce | C54: New-policy wedge, lpg = cptraj x encov x factor | D54: Stream 2 (E) | E54: $/liter | F54: Scenarios | G54: egy.mit.nce.ind.lpg.a.2 | H54: kernel atp rows | J54: EGY | K54: =K42*K45*$E$34 -> 0 | L54: =L42*L45*$E$34 -> 0 | M54: =M42*M45*$E$34 -> 0 | N54: =N42*N45*$E$34 -> 0 | O54: =O42*O45*$E$34 -> 0 | P54: =P42*P45*$E$34 -> 0 | Q54: =Q42*Q45*$E$34 -> 0.022106083 | R54: =R42*R45*$E$34 -> 0.044212166 | ... AI54: =AI42*AI45*$E$34 -> 0
B55: nce | C55: New-policy wedge, ker = cptraj x encov x factor | D55: Stream 2 (E) | E55: $/liter | F55: Scenarios | G55: egy.mit.nce.ind.ker.a.2 | H55: kernel atp rows | J55: EGY | K55: =K42*K45*$E$35 -> 0 | L55: =L42*L45*$E$35 -> 0 | M55: =M42*M45*$E$35 -> 0 | N55: =N42*N45*$E$35 -> 0 | O55: =O42*O45*$E$35 -> 0 | P55: =P42*P45*$E$35 -> 0 | Q55: =Q42*Q45*$E$35 -> 0.03198883 | R55: =R42*R45*$E$35 -> 0.06397766 | ... AI55: =AI42*AI45*$E$35 -> 0
B56: nce | C56: New-policy wedge, oop = cptraj x encov x factor | D56: Stream 2 (E) | E56: $/bbl | F56: Scenarios | G56: egy.mit.nce.ind.oop.a.2 | H56: kernel atp rows | J56: EGY | K56: =K42*K45*$E$36 -> 0 | L56: =L42*L45*$E$36 -> 0 | M56: =M42*M45*$E$36 -> 0 | N56: =N42*N45*$E$36 -> 0 | O56: =O42*O45*$E$36 -> 0 | P56: =P42*P45*$E$36 -> 0 | Q56: =Q42*Q45*$E$36 -> 5.86755 | R56: =R42*R45*$E$36 -> 11.7351 | ... AI56: =AI42*AI45*$E$36 -> 0
B57: nce | C57: New-policy wedge, bio = cptraj x encov x factor | D57: Stream 2 (E) | E57: $/GJ | F57: Scenarios | G57: egy.mit.nce.ind.bio.a.2 | H57: kernel atp rows | J57: EGY | K57: =K42*K45*$E$37 -> 0 | L57: =L42*L45*$E$37 -> 0 | M57: =M42*M45*$E$37 -> 0 | N57: =N42*N45*$E$37 -> 0 | O57: =O42*O45*$E$37 -> 0 | P57: =P42*P45*$E$37 -> 0 | Q57: =Q42*Q45*$E$37 -> 0 | R57: =R42*R45*$E$37 -> 0 | ... AI57: =AI42*AI45*$E$37 -> 0
B58: nce | C58: New-policy wedge, ren = cptraj x encov x factor | D58: Stream 2 (E) | E58: $/kwh | F58: Scenarios | G58: egy.mit.nce.ind.ren.a.2 | H58: kernel atp rows | J58: EGY | K58: =K42*K45*$E$38 -> 0 | L58: =L42*L45*$E$38 -> 0 | M58: =M42*M45*$E$38 -> 0 | N58: =N42*N45*$E$38 -> 0 | O58: =O42*O45*$E$38 -> 0 | P58: =P42*P45*$E$38 -> 0 | Q58: =Q42*Q45*$E$38 -> 0 | R58: =R42*R45*$E$38 -> 0 | ... AI58: =AI42*AI45*$E$38 -> 0
A60: 5 | B60: Interface contract between work streams (merge rules)
B61: Stream 1 = product/CBAM side (tasks A, B, C, D, H, K, L): owns Manual inputs rows 18-47 and CBAM block rows o7-o155.
B62: Stream 2 = energy/policy side (tasks E, F, I, J): owns Scenarios, Data_Prices policy rows, kernel sector blocks, block rows o2-o6.
B63: Interface = the codes in section 4 (Data_Prices egy.mit.<var>.<s>) plus block rows o2-o6. Stream 2 writes, stream 1 reads.
B64: o2 Carbon Tax = cptraj; o3 ETS = etstraj; o4 Total Shadow Price = fundsp ($/tCO2, intensity only); o5 Revenues Fund = fundsh x Total Revenues (o155); o6 Output-based rebate = obrrb.
B65: Price seen by: efficiency / intensity (fuel and process ER) = full price (+ o4); output / usage = price - obrrb (Task H, I).
B66: Process emissions price = pptraj (Task C switches block process rows from o2 to pptraj; equal for all current bundles).
B67: Manual inputs E21 (process emissions priced) = active bundle 'Process emissions covered'; per-sector detail stays in Manual inputs (Task C).
B68: Rules: find rows by code/label, never by row number; never insert rows in the other stream's area; each stream adds its own Check section; merge = run both stream build scripts on v0.4.
B69: Stream 1 output codes (Task A, CBAM block column H, suffix = scenario): cpef / cpep.ind.<sec> (post-policy fuel / process emissions by sector); emisf / emisp / emis.cbam.tot; emrf / emrp / emr.cbam.tot; revf / revp / rev.cbam.tot (o137 / o138 / o155). o5 fund base = o155 = fuel + process revenue; main CPAT adds only revp (fuel CO2 already in nce).
B70: Task B (stream 1): EF category coverage switches M:P (c.fc, c.fp, c.np, c.no; 1 in every bundle: the report treats fc + fp as the fuel-combustion share covered by energy CO2 pricing and np + no as all process emissions). fc, fp are priced with the energy CO2 flags, np, no with the process flags (E21). Set c.fp = 0 to exclude reductant/feedstock fuel, c.no = 0 to exclude non-CO2. Outputs emisfc / emisfp / emisnp / emisno.cbam.tot (block o13-o16); fuel switches affect only CBAM-block memo revenue, not the kernel energy wedge (nce).
B71: Task C (stream 1, v0.7): CBAM process emissions (np + no) are priced at pptraj (block o63), fuel CO2 (fc + fp) at cptraj (o2); ETS (o3) applies to both via the sector ETS flags. To give process emissions their own path, set the bundle's 'Process price path' (column H); 'Process emissions covered' (G) switches it off. Reporting convention: all bundles price 20 $/t in 2030 (checked).
B72: Task K (stream 1, v0.8): CBAM metric codes (block column H, G = cbam.tot): cbcov (o39, priced share of CBAM-sector emissions), cbint (o40, tCO2e/t), cbintch (o41, intensity change vs pre-policy), cbintchx (o51, EU-export-weighted intensity change), cbcovx (o52, EU-export-weighted coverage). Fuel/process split of the change: emisfc..emisno (o13-o16) vs pre-policy o85-o103.
B73: Task D (stream 1, v0.9): process-emission semi-elasticities by product and category (np, no) in Manual inputs rows 53-60 (selector E50: IPCC default, ADHOC = v0.8). Stream 2 (fund, Task G/J) should apply its own shadow price through the same parameters, not rows 40-47.

Sheet Mitigation_Industry
B1: Fuel | C1: Sector | D1: Description | E1: Unit | F1: Source | G1: Input Code | H1: Output Code | I1: Note | J1: Helper | K1: 2021 | L1: 2022 | M1: 2023 | N1: 2024 | O1: 2025 | P1: 2026 | Q1: 2027 | R1: 2028 | S1: 2029 | T1: 2030 | U1: 2031 | V1: 2032 | W1: 2033 | X1: 2034 | Y1: 2035 | Z1: 2036 | AA1: 2037 | AB1: 2038 | AC1: 2039 | AD1: 2040 | AE1: 2041 | AF1: 2042 | AG1: 2043 | AH1: 2044 | AI1: 2045
B2: Mitigation Module - Egypt: Industry kernel
A3: 7 | B3: Industrial sector - Baseline (CBAM sectors: iron and steel, cement, non-ferrous metals, mining & chemicals)
B5: Iron and steel | C5: irn | D5: Fuel Type | E5: Unit | F5: Variable Code | G5: Input Code (data-table key) | H5: Output Code | I5: Scenario | J5: 1 | K5: 2021 | L5: 2022 | M5: 2023 | N5: 2024 | O5: 2025 | P5: 2026 | Q5: 2027 | R5: 2028 | S5: 2029 | T5: 2030 | U5: 2031 | V5: 2032 | W5: 2033 | X5: 2034 | Y5: 2035 | Z5: 2036 | AA5: 2037 | AB5: 2038 | AC5: 2039 | AD5: 2040 | AE5: 2041 | AF5: 2042 | AG5: 2043 | AH5: 2044 | AI5: 2045
B6: Pre-tax price: price before any new policy (supply cost + VAT + existing excise, subsidies and carbon prices)
B7: coa | C7: =$C$5 -> irn | D7: Coal | E7: $/GJ | F7: ptp | G7: =Settings!$B$3&".mit.pbc."&Settings!$B$4&"."&$B7&".a."&$J$5 -> egy.mit.pbc.ind.coa.a.1 | H7: =Settings!$B$3&".mit.ptp."&$C$5&"."&$B7&".e."&$J$5 -> egy.mit.ptp.irn.coa.e.1 | K7: =INDEX(Data_Prices!K:K,MATCH($G7,Data_Prices!$A:$A,0)) -> 11.182902 | L7: =INDEX(Data_Prices!L:L,MATCH($G7,Data_Prices!$A:$A,0)) -> 10.523361 | M7: =INDEX(Data_Prices!M:M,MATCH($G7,Data_Prices!$A:$A,0)) -> 10.299561 | N7: =INDEX(Data_Prices!N:N,MATCH($G7,Data_Prices!$A:$A,0)) -> 9.5775284 | O7: =INDEX(Data_Prices!O:O,MATCH($G7,Data_Prices!$A:$A,0)) -> 8.4854783 | P7: =INDEX(Data_Prices!P:P,MATCH($G7,Data_Prices!$A:$A,0)) -> 9.0871922 | Q7: =INDEX(Data_Prices!Q:Q,MATCH($G7,Data_Prices!$A:$A,0)) -> 9.2229237 | R7: =INDEX(Data_Prices!R:R,MATCH($G7,Data_Prices!$A:$A,0)) -> 9.158565 | S7: =INDEX(Data_Prices!S:S,MATCH($G7,Data_Prices!$A:$A,0)) -> 9.0895479 | T7: =INDEX(Data_Prices!T:T,MATCH($G7,Data_Prices!$A:$A,0)) -> 9.0156817 | U7: =INDEX(Data_Prices!U:U,MATCH($G7,Data_Prices!$A:$A,0)) -> 8.9443978 | V7: =INDEX(Data_Prices!V:V,MATCH($G7,Data_Prices!$A:$A,0)) -> 8.9443978 | W7: =INDEX(Data_Prices!W:W,MATCH($G7,Data_Prices!$A:$A,0)) -> 8.9443978 | X7: =INDEX(Data_Prices!X:X,MATCH($G7,Data_Prices!$A:$A,0)) -> 8.9443978 | Y7: =INDEX(Data_Prices!Y:Y,MATCH($G7,Data_Prices!$A:$A,0)) -> 8.9443978 | Z7: =INDEX(Data_Prices!Z:Z,MATCH($G7,Data_Prices!$A:$A,0)) -> 8.9443978 | AA7: =INDEX(Data_Prices!AA:AA,MATCH($G7,Data_Prices!$A:$A,0)) -> 8.9443978 | AB7: =INDEX(Data_Prices!AB:AB,MATCH($G7,Data_Prices!$A:$A,0)) -> 8.9443978 | AC7: =INDEX(Data_Prices!AC:AC,MATCH($G7,Data_Prices!$A:$A,0)) -> 8.9443978 | AD7: =INDEX(Data_Prices!AD:AD,MATCH($G7,Data_Prices!$A:$A,0)) -> 8.9443978 | AE7: =INDEX(Data_Prices!AE:AE,MATCH($G7,Data_Prices!$A:$A,0)) -> 8.9443978
B8: nga | C8: =$C$5 -> irn | D8: Natural gas | E8: $/GJ | F8: ptp | G8: =Settings!$B$3&".mit.pbc."&Settings!$B$4&"."&$B8&".a."&$J$5 -> egy.mit.pbc.ind.nga.a.1 | H8: =Settings!$B$3&".mit.ptp."&$C$5&"."&$B8&".e."&$J$5 -> egy.mit.ptp.irn.nga.e.1 | K8: =INDEX(Data_Prices!K:K,MATCH($G8,Data_Prices!$A:$A,0)) -> 6.0634636 | L8: =INDEX(Data_Prices!L:L,MATCH($G8,Data_Prices!$A:$A,0)) -> 5.4510151 | M8: =INDEX(Data_Prices!M:M,MATCH($G8,Data_Prices!$A:$A,0)) -> 5.1193563 | N8: =INDEX(Data_Prices!N:N,MATCH($G8,Data_Prices!$A:$A,0)) -> 5.0821846 | O8: =INDEX(Data_Prices!O:O,MATCH($G8,Data_Prices!$A:$A,0)) -> 5.0821846 | P8: =INDEX(Data_Prices!P:P,MATCH($G8,Data_Prices!$A:$A,0)) -> 5.0821846 | Q8: =INDEX(Data_Prices!Q:Q,MATCH($G8,Data_Prices!$A:$A,0)) -> 5.0821846 | R8: =INDEX(Data_Prices!R:R,MATCH($G8,Data_Prices!$A:$A,0)) -> 5.0821846 | S8: =INDEX(Data_Prices!S:S,MATCH($G8,Data_Prices!$A:$A,0)) -> 5.0821846 | T8: =INDEX(Data_Prices!T:T,MATCH($G8,Data_Prices!$A:$A,0)) -> 5.0821846 | U8: =INDEX(Data_Prices!U:U,MATCH($G8,Data_Prices!$A:$A,0)) -> 5.0821846 | V8: =INDEX(Data_Prices!V:V,MATCH($G8,Data_Prices!$A:$A,0)) -> 5.0821846 | W8: =INDEX(Data_Prices!W:W,MATCH($G8,Data_Prices!$A:$A,0)) -> 5.0821846 | X8: =INDEX(Data_Prices!X:X,MATCH($G8,Data_Prices!$A:$A,0)) -> 5.0821846 | Y8: =INDEX(Data_Prices!Y:Y,MATCH($G8,Data_Prices!$A:$A,0)) -> 5.0821846 | Z8: =INDEX(Data_Prices!Z:Z,MATCH($G8,Data_Prices!$A:$A,0)) -> 5.0821846 | AA8: =INDEX(Data_Prices!AA:AA,MATCH($G8,Data_Prices!$A:$A,0)) -> 5.0821846 | AB8: =INDEX(Data_Prices!AB:AB,MATCH($G8,Data_Prices!$A:$A,0)) -> 5.0821846 | AC8: =INDEX(Data_Prices!AC:AC,MATCH($G8,Data_Prices!$A:$A,0)) -> 5.0821846 | AD8: =INDEX(Data_Prices!AD:AD,MATCH($G8,Data_Prices!$A:$A,0)) -> 5.0821846 | AE8: =INDEX(Data_Prices!AE:AE,MATCH($G8,Data_Prices!$A:$A,0)) -> 5.0821846
B9: gso | C9: =$C$5 -> irn | D9: Gasoline | E9: $/liter | F9: ptp | G9: =Settings!$B$3&".mit.pbc."&Settings!$B$4&"."&$B9&".a."&$J$5 -> egy.mit.pbc.ind.gso.a.1 | H9: =Settings!$B$3&".mit.ptp."&$C$5&"."&$B9&".e."&$J$5 -> egy.mit.ptp.irn.gso.e.1 | K9: =INDEX(Data_Prices!K:K,MATCH($G9,Data_Prices!$A:$A,0)) -> 0.67114653 | L9: =INDEX(Data_Prices!L:L,MATCH($G9,Data_Prices!$A:$A,0)) -> 0.61197798 | M9: =INDEX(Data_Prices!M:M,MATCH($G9,Data_Prices!$A:$A,0)) -> 0.61180975 | N9: =INDEX(Data_Prices!N:N,MATCH($G9,Data_Prices!$A:$A,0)) -> 0.6035831 | O9: =INDEX(Data_Prices!O:O,MATCH($G9,Data_Prices!$A:$A,0)) -> 0.6035831 | P9: =INDEX(Data_Prices!P:P,MATCH($G9,Data_Prices!$A:$A,0)) -> 0.6035831 | Q9: =INDEX(Data_Prices!Q:Q,MATCH($G9,Data_Prices!$A:$A,0)) -> 0.6035831 | R9: =INDEX(Data_Prices!R:R,MATCH($G9,Data_Prices!$A:$A,0)) -> 0.6035831 | S9: =INDEX(Data_Prices!S:S,MATCH($G9,Data_Prices!$A:$A,0)) -> 0.6035831 | T9: =INDEX(Data_Prices!T:T,MATCH($G9,Data_Prices!$A:$A,0)) -> 0.6035831 | U9: =INDEX(Data_Prices!U:U,MATCH($G9,Data_Prices!$A:$A,0)) -> 0.6035831 | V9: =INDEX(Data_Prices!V:V,MATCH($G9,Data_Prices!$A:$A,0)) -> 0.6035831 | W9: =INDEX(Data_Prices!W:W,MATCH($G9,Data_Prices!$A:$A,0)) -> 0.6035831 | X9: =INDEX(Data_Prices!X:X,MATCH($G9,Data_Prices!$A:$A,0)) -> 0.6035831 | Y9: =INDEX(Data_Prices!Y:Y,MATCH($G9,Data_Prices!$A:$A,0)) -> 0.6035831 | Z9: =INDEX(Data_Prices!Z:Z,MATCH($G9,Data_Prices!$A:$A,0)) -> 0.6035831 | AA9: =INDEX(Data_Prices!AA:AA,MATCH($G9,Data_Prices!$A:$A,0)) -> 0.6035831 | AB9: =INDEX(Data_Prices!AB:AB,MATCH($G9,Data_Prices!$A:$A,0)) -> 0.6035831 | AC9: =INDEX(Data_Prices!AC:AC,MATCH($G9,Data_Prices!$A:$A,0)) -> 0.6035831 | AD9: =INDEX(Data_Prices!AD:AD,MATCH($G9,Data_Prices!$A:$A,0)) -> 0.6035831 | AE9: =INDEX(Data_Prices!AE:AE,MATCH($G9,Data_Prices!$A:$A,0)) -> 0.6035831
B10: die | C10: =$C$5 -> irn | D10: Diesel | E10: $/liter | F10: ptp | G10: =Settings!$B$3&".mit.pbc."&Settings!$B$4&"."&$B10&".a."&$J$5 -> egy.mit.pbc.ind.die.a.1 | H10: =Settings!$B$3&".mit.ptp."&$C$5&"."&$B10&".e."&$J$5 -> egy.mit.ptp.irn.die.e.1 | K10: =INDEX(Data_Prices!K:K,MATCH($G10,Data_Prices!$A:$A,0)) -> 0.55971121 | L10: =INDEX(Data_Prices!L:L,MATCH($G10,Data_Prices!$A:$A,0)) -> 0.49458873 | M10: =INDEX(Data_Prices!M:M,MATCH($G10,Data_Prices!$A:$A,0)) -> 0.50778655 | N10: =INDEX(Data_Prices!N:N,MATCH($G10,Data_Prices!$A:$A,0)) -> 0.47043643 | O10: =INDEX(Data_Prices!O:O,MATCH($G10,Data_Prices!$A:$A,0)) -> 0.47043643 | P10: =INDEX(Data_Prices!P:P,MATCH($G10,Data_Prices!$A:$A,0)) -> 0.47043643 | Q10: =INDEX(Data_Prices!Q:Q,MATCH($G10,Data_Prices!$A:$A,0)) -> 0.47043643 | R10: =INDEX(Data_Prices!R:R,MATCH($G10,Data_Prices!$A:$A,0)) -> 0.47043643 | S10: =INDEX(Data_Prices!S:S,MATCH($G10,Data_Prices!$A:$A,0)) -> 0.47043643 | T10: =INDEX(Data_Prices!T:T,MATCH($G10,Data_Prices!$A:$A,0)) -> 0.47043643 | U10: =INDEX(Data_Prices!U:U,MATCH($G10,Data_Prices!$A:$A,0)) -> 0.47043643 | V10: =INDEX(Data_Prices!V:V,MATCH($G10,Data_Prices!$A:$A,0)) -> 0.47043643 | W10: =INDEX(Data_Prices!W:W,MATCH($G10,Data_Prices!$A:$A,0)) -> 0.47043643 | X10: =INDEX(Data_Prices!X:X,MATCH($G10,Data_Prices!$A:$A,0)) -> 0.47043643 | Y10: =INDEX(Data_Prices!Y:Y,MATCH($G10,Data_Prices!$A:$A,0)) -> 0.47043643 | Z10: =INDEX(Data_Prices!Z:Z,MATCH($G10,Data_Prices!$A:$A,0)) -> 0.47043643 | AA10: =INDEX(Data_Prices!AA:AA,MATCH($G10,Data_Prices!$A:$A,0)) -> 0.47043643 | AB10: =INDEX(Data_Prices!AB:AB,MATCH($G10,Data_Prices!$A:$A,0)) -> 0.47043643 | AC10: =INDEX(Data_Prices!AC:AC,MATCH($G10,Data_Prices!$A:$A,0)) -> 0.47043643 | AD10: =INDEX(Data_Prices!AD:AD,MATCH($G10,Data_Prices!$A:$A,0)) -> 0.47043643 | AE10: =INDEX(Data_Prices!AE:AE,MATCH($G10,Data_Prices!$A:$A,0)) -> 0.47043643
B11: lpg | C11: =$C$5 -> irn | D11: LPG | E11: $/liter | F11: ptp | G11: =Settings!$B$3&".mit.pbc."&Settings!$B$4&"."&$B11&".a."&$J$5 -> egy.mit.pbc.ind.lpg.a.1 | H11: =Settings!$B$3&".mit.ptp."&$C$5&"."&$B11&".e."&$J$5 -> egy.mit.ptp.irn.lpg.e.1 | K11: =INDEX(Data_Prices!K:K,MATCH($G11,Data_Prices!$A:$A,0)) -> 0.20036669 | L11: =INDEX(Data_Prices!L:L,MATCH($G11,Data_Prices!$A:$A,0)) -> 0.15734474 | M11: =INDEX(Data_Prices!M:M,MATCH($G11,Data_Prices!$A:$A,0)) -> 0.16448404 | N11: =INDEX(Data_Prices!N:N,MATCH($G11,Data_Prices!$A:$A,0)) -> 0.15070908 | O11: =INDEX(Data_Prices!O:O,MATCH($G11,Data_Prices!$A:$A,0)) -> 0.15070908 | P11: =INDEX(Data_Prices!P:P,MATCH($G11,Data_Prices!$A:$A,0)) -> 0.15070908 | Q11: =INDEX(Data_Prices!Q:Q,MATCH($G11,Data_Prices!$A:$A,0)) -> 0.15070908 | R11: =INDEX(Data_Prices!R:R,MATCH($G11,Data_Prices!$A:$A,0)) -> 0.15070908 | S11: =INDEX(Data_Prices!S:S,MATCH($G11,Data_Prices!$A:$A,0)) -> 0.15070908 | T11: =INDEX(Data_Prices!T:T,MATCH($G11,Data_Prices!$A:$A,0)) -> 0.15070908 | U11: =INDEX(Data_Prices!U:U,MATCH($G11,Data_Prices!$A:$A,0)) -> 0.15070908 | V11: =INDEX(Data_Prices!V:V,MATCH($G11,Data_Prices!$A:$A,0)) -> 0.15070908 | W11: =INDEX(Data_Prices!W:W,MATCH($G11,Data_Prices!$A:$A,0)) -> 0.15070908 | X11: =INDEX(Data_Prices!X:X,MATCH($G11,Data_Prices!$A:$A,0)) -> 0.15070908 | Y11: =INDEX(Data_Prices!Y:Y,MATCH($G11,Data_Prices!$A:$A,0)) -> 0.15070908 | Z11: =INDEX(Data_Prices!Z:Z,MATCH($G11,Data_Prices!$A:$A,0)) -> 0.15070908 | AA11: =INDEX(Data_Prices!AA:AA,MATCH($G11,Data_Prices!$A:$A,0)) -> 0.15070908 | AB11: =INDEX(Data_Prices!AB:AB,MATCH($G11,Data_Prices!$A:$A,0)) -> 0.15070908 | AC11: =INDEX(Data_Prices!AC:AC,MATCH($G11,Data_Prices!$A:$A,0)) -> 0.15070908 | AD11: =INDEX(Data_Prices!AD:AD,MATCH($G11,Data_Prices!$A:$A,0)) -> 0.15070908 | AE11: =INDEX(Data_Prices!AE:AE,MATCH($G11,Data_Prices!$A:$A,0)) -> 0.15070908
B12: ker | C12: =$C$5 -> irn | D12: Kerosene | E12: $/liter | F12: ptp | G12: =Settings!$B$3&".mit.pbc."&Settings!$B$4&"."&$B12&".a."&$J$5 -> egy.mit.pbc.ind.ker.a.1 | H12: =Settings!$B$3&".mit.ptp."&$C$5&"."&$B12&".e."&$J$5 -> egy.mit.ptp.irn.ker.e.1 | K12: =INDEX(Data_Prices!K:K,MATCH($G12,Data_Prices!$A:$A,0)) -> 0.48429424 | L12: =INDEX(Data_Prices!L:L,MATCH($G12,Data_Prices!$A:$A,0)) -> 0.45642817 | M12: =INDEX(Data_Prices!M:M,MATCH($G12,Data_Prices!$A:$A,0)) -> 0.4316892 | N12: =INDEX(Data_Prices!N:N,MATCH($G12,Data_Prices!$A:$A,0)) -> 0.42507558 | O12: =INDEX(Data_Prices!O:O,MATCH($G12,Data_Prices!$A:$A,0)) -> 0.42507558 | P12: =INDEX(Data_Prices!P:P,MATCH($G12,Data_Prices!$A:$A,0)) -> 0.42507558 | Q12: =INDEX(Data_Prices!Q:Q,MATCH($G12,Data_Prices!$A:$A,0)) -> 0.42507558 | R12: =INDEX(Data_Prices!R:R,MATCH($G12,Data_Prices!$A:$A,0)) -> 0.42507558 | S12: =INDEX(Data_Prices!S:S,MATCH($G12,Data_Prices!$A:$A,0)) -> 0.42507558 | T12: =INDEX(Data_Prices!T:T,MATCH($G12,Data_Prices!$A:$A,0)) -> 0.42507558 | U12: =INDEX(Data_Prices!U:U,MATCH($G12,Data_Prices!$A:$A,0)) -> 0.42507558 | V12: =INDEX(Data_Prices!V:V,MATCH($G12,Data_Prices!$A:$A,0)) -> 0.42507558 | W12: =INDEX(Data_Prices!W:W,MATCH($G12,Data_Prices!$A:$A,0)) -> 0.42507558 | X12: =INDEX(Data_Prices!X:X,MATCH($G12,Data_Prices!$A:$A,0)) -> 0.42507558 | Y12: =INDEX(Data_Prices!Y:Y,MATCH($G12,Data_Prices!$A:$A,0)) -> 0.42507558 | Z12: =INDEX(Data_Prices!Z:Z,MATCH($G12,Data_Prices!$A:$A,0)) -> 0.42507558 | AA12: =INDEX(Data_Prices!AA:AA,MATCH($G12,Data_Prices!$A:$A,0)) -> 0.42507558 | AB12: =INDEX(Data_Prices!AB:AB,MATCH($G12,Data_Prices!$A:$A,0)) -> 0.42507558 | AC12: =INDEX(Data_Prices!AC:AC,MATCH($G12,Data_Prices!$A:$A,0)) -> 0.42507558 | AD12: =INDEX(Data_Prices!AD:AD,MATCH($G12,Data_Prices!$A:$A,0)) -> 0.42507558 | AE12: =INDEX(Data_Prices!AE:AE,MATCH($G12,Data_Prices!$A:$A,0)) -> 0.42507558
B13: oop | C13: =$C$5 -> irn | D13: Other oil products | E13: $/bbl | F13: ptp | G13: =Settings!$B$3&".mit.pbc."&Settings!$B$4&"."&$B13&".a."&$J$5 -> egy.mit.pbc.ind.oop.a.1 | H13: =Settings!$B$3&".mit.ptp."&$C$5&"."&$B13&".e."&$J$5 -> egy.mit.ptp.irn.oop.e.1 | K13: =INDEX(Data_Prices!K:K,MATCH($G13,Data_Prices!$A:$A,0)) -> 41.500338 | L13: =INDEX(Data_Prices!L:L,MATCH($G13,Data_Prices!$A:$A,0)) -> 34.41537 | M13: =INDEX(Data_Prices!M:M,MATCH($G13,Data_Prices!$A:$A,0)) -> 37.368961 | N13: =INDEX(Data_Prices!N:N,MATCH($G13,Data_Prices!$A:$A,0)) -> 28.982761 | O13: =INDEX(Data_Prices!O:O,MATCH($G13,Data_Prices!$A:$A,0)) -> 15 | P13: =INDEX(Data_Prices!P:P,MATCH($G13,Data_Prices!$A:$A,0)) -> 24.25863 | Q13: =INDEX(Data_Prices!Q:Q,MATCH($G13,Data_Prices!$A:$A,0)) -> 15 | R13: =INDEX(Data_Prices!R:R,MATCH($G13,Data_Prices!$A:$A,0)) -> 15 | S13: =INDEX(Data_Prices!S:S,MATCH($G13,Data_Prices!$A:$A,0)) -> 15 | T13: =INDEX(Data_Prices!T:T,MATCH($G13,Data_Prices!$A:$A,0)) -> 15 | U13: =INDEX(Data_Prices!U:U,MATCH($G13,Data_Prices!$A:$A,0)) -> 15 | V13: =INDEX(Data_Prices!V:V,MATCH($G13,Data_Prices!$A:$A,0)) -> 15 | W13: =INDEX(Data_Prices!W:W,MATCH($G13,Data_Prices!$A:$A,0)) -> 15 | X13: =INDEX(Data_Prices!X:X,MATCH($G13,Data_Prices!$A:$A,0)) -> 15 | Y13: =INDEX(Data_Prices!Y:Y,MATCH($G13,Data_Prices!$A:$A,0)) -> 15 | Z13: =INDEX(Data_Prices!Z:Z,MATCH($G13,Data_Prices!$A:$A,0)) -> 15 | AA13: =INDEX(Data_Prices!AA:AA,MATCH($G13,Data_Prices!$A:$A,0)) -> 15 | AB13: =INDEX(Data_Prices!AB:AB,MATCH($G13,Data_Prices!$A:$A,0)) -> 15 | AC13: =INDEX(Data_Prices!AC:AC,MATCH($G13,Data_Prices!$A:$A,0)) -> 15 | AD13: =INDEX(Data_Prices!AD:AD,MATCH($G13,Data_Prices!$A:$A,0)) -> 15 | AE13: =INDEX(Data_Prices!AE:AE,MATCH($G13,Data_Prices!$A:$A,0)) -> 15
B14: bio | C14: =$C$5 -> irn | D14: Biomass | E14: $/GJ | F14: ptp | G14: =Settings!$B$3&".mit.pbc."&Settings!$B$4&"."&$B14&".a."&$J$5 -> egy.mit.pbc.ind.bio.a.1 | H14: =Settings!$B$3&".mit.ptp."&$C$5&"."&$B14&".e."&$J$5 -> egy.mit.ptp.irn.bio.e.1 | K14: =INDEX(Data_Prices!K:K,MATCH($G14,Data_Prices!$A:$A,0)) -> 15.334551 | L14: =INDEX(Data_Prices!L:L,MATCH($G14,Data_Prices!$A:$A,0)) -> 14.199528 | M14: =INDEX(Data_Prices!M:M,MATCH($G14,Data_Prices!$A:$A,0)) -> 13.840442 | N14: =INDEX(Data_Prices!N:N,MATCH($G14,Data_Prices!$A:$A,0)) -> 13.567727 | O14: =INDEX(Data_Prices!O:O,MATCH($G14,Data_Prices!$A:$A,0)) -> 13.567727 | P14: =INDEX(Data_Prices!P:P,MATCH($G14,Data_Prices!$A:$A,0)) -> 13.567727 | Q14: =INDEX(Data_Prices!Q:Q,MATCH($G14,Data_Prices!$A:$A,0)) -> 13.567727 | R14: =INDEX(Data_Prices!R:R,MATCH($G14,Data_Prices!$A:$A,0)) -> 13.567727 | S14: =INDEX(Data_Prices!S:S,MATCH($G14,Data_Prices!$A:$A,0)) -> 13.567727 | T14: =INDEX(Data_Prices!T:T,MATCH($G14,Data_Prices!$A:$A,0)) -> 13.567727 | U14: =INDEX(Data_Prices!U:U,MATCH($G14,Data_Prices!$A:$A,0)) -> 13.567727 | V14: =INDEX(Data_Prices!V:V,MATCH($G14,Data_Prices!$A:$A,0)) -> 13.567727 | W14: =INDEX(Data_Prices!W:W,MATCH($G14,Data_Prices!$A:$A,0)) -> 13.567727 | X14: =INDEX(Data_Prices!X:X,MATCH($G14,Data_Prices!$A:$A,0)) -> 13.567727 | Y14: =INDEX(Data_Prices!Y:Y,MATCH($G14,Data_Prices!$A:$A,0)) -> 13.567727 | Z14: =INDEX(Data_Prices!Z:Z,MATCH($G14,Data_Prices!$A:$A,0)) -> 13.567727 | AA14: =INDEX(Data_Prices!AA:AA,MATCH($G14,Data_Prices!$A:$A,0)) -> 13.567727 | AB14: =INDEX(Data_Prices!AB:AB,MATCH($G14,Data_Prices!$A:$A,0)) -> 13.567727 | AC14: =INDEX(Data_Prices!AC:AC,MATCH($G14,Data_Prices!$A:$A,0)) -> 13.567727 | AD14: =INDEX(Data_Prices!AD:AD,MATCH($G14,Data_Prices!$A:$A,0)) -> 13.567727 | AE14: =INDEX(Data_Prices!AE:AE,MATCH($G14,Data_Prices!$A:$A,0)) -> 13.567727
B15: ren | C15: =$C$5 -> irn | D15: Self-generated renewables | E15: $/kwh | F15: ptp | G15: =Settings!$B$3&".mit.pbc."&Settings!$B$4&"."&$B15&".a."&$J$5 -> egy.mit.pbc.ind.ren.a.1 | H15: =Settings!$B$3&".mit.ptp."&$C$5&"."&$B15&".e."&$J$5 -> egy.mit.ptp.irn.ren.e.1 | K15: =INDEX(Data_Prices!K:K,MATCH($G15,Data_Prices!$A:$A,0)) -> 0 | L15: =INDEX(Data_Prices!L:L,MATCH($G15,Data_Prices!$A:$A,0)) -> 0.14404499 | M15: =INDEX(Data_Prices!M:M,MATCH($G15,Data_Prices!$A:$A,0)) -> 0.14102041 | N15: =INDEX(Data_Prices!N:N,MATCH($G15,Data_Prices!$A:$A,0)) -> 0.13511636 | O15: =INDEX(Data_Prices!O:O,MATCH($G15,Data_Prices!$A:$A,0)) -> 0.13098826 | P15: =INDEX(Data_Prices!P:P,MATCH($G15,Data_Prices!$A:$A,0)) -> 0.12790842 | Q15: =INDEX(Data_Prices!Q:Q,MATCH($G15,Data_Prices!$A:$A,0)) -> 0.12481431 | R15: =INDEX(Data_Prices!R:R,MATCH($G15,Data_Prices!$A:$A,0)) -> 0.12146026 | S15: =INDEX(Data_Prices!S:S,MATCH($G15,Data_Prices!$A:$A,0)) -> 0.11795074 | T15: =INDEX(Data_Prices!T:T,MATCH($G15,Data_Prices!$A:$A,0)) -> 0.11419916 | U15: =INDEX(Data_Prices!U:U,MATCH($G15,Data_Prices!$A:$A,0)) -> 0.1136651 | V15: =INDEX(Data_Prices!V:V,MATCH($G15,Data_Prices!$A:$A,0)) -> 0.11301693 | W15: =INDEX(Data_Prices!W:W,MATCH($G15,Data_Prices!$A:$A,0)) -> 0.11231407 | X15: =INDEX(Data_Prices!X:X,MATCH($G15,Data_Prices!$A:$A,0)) -> 0.11142204 | Y15: =INDEX(Data_Prices!Y:Y,MATCH($G15,Data_Prices!$A:$A,0)) -> 0.11043412 | Z15: =INDEX(Data_Prices!Z:Z,MATCH($G15,Data_Prices!$A:$A,0)) -> 0.10948397 | AA15: =INDEX(Data_Prices!AA:AA,MATCH($G15,Data_Prices!$A:$A,0)) -> 0.10839192 | AB15: =INDEX(Data_Prices!AB:AB,MATCH($G15,Data_Prices!$A:$A,0)) -> 0.10735443 | AC15: =INDEX(Data_Prices!AC:AC,MATCH($G15,Data_Prices!$A:$A,0)) -> 0.10516868 | AD15: =INDEX(Data_Prices!AD:AD,MATCH($G15,Data_Prices!$A:$A,0)) -> 0.10305798 | AE15: =INDEX(Data_Prices!AE:AE,MATCH($G15,Data_Prices!$A:$A,0)) -> 0.10093184
B16: Post-tax price: pre-tax + new-policy wedge x sector coverage factor (= CPAT atp row)
B17: coa | C17: =$C$5 -> irn | D17: Coal | E17: $/GJ | F17: atp | G17: =Settings!$B$3&".mit.nce."&Settings!$B$4&"."&$B17&".a."&$J$5 -> egy.mit.nce.ind.coa.a.1 | H17: =Settings!$B$3&".mit.atp."&$C$5&"."&$B17&".e."&$J$5 -> egy.mit.atp.irn.coa.e.1 | K17: =K7+INDEX(Data_Prices!K:K,MATCH($G17,Data_Prices!$A:$A,0))*K$37 -> 11.182902 | L17: =L7+INDEX(Data_Prices!L:L,MATCH($G17,Data_Prices!$A:$A,0))*L$37 -> 10.523361 | M17: =M7+INDEX(Data_Prices!M:M,MATCH($G17,Data_Prices!$A:$A,0))*M$37 -> 10.299561 | N17: =N7+INDEX(Data_Prices!N:N,MATCH($G17,Data_Prices!$A:$A,0))*N$37 -> 9.5775284 | O17: =O7+INDEX(Data_Prices!O:O,MATCH($G17,Data_Prices!$A:$A,0))*O$37 -> 8.4854783 | P17: =P7+INDEX(Data_Prices!P:P,MATCH($G17,Data_Prices!$A:$A,0))*P$37 -> 9.0871922 | Q17: =Q7+INDEX(Data_Prices!Q:Q,MATCH($G17,Data_Prices!$A:$A,0))*Q$37 -> 9.2229237 | R17: =R7+INDEX(Data_Prices!R:R,MATCH($G17,Data_Prices!$A:$A,0))*R$37 -> 9.158565 | S17: =S7+INDEX(Data_Prices!S:S,MATCH($G17,Data_Prices!$A:$A,0))*S$37 -> 9.0895479 | T17: =T7+INDEX(Data_Prices!T:T,MATCH($G17,Data_Prices!$A:$A,0))*T$37 -> 9.0156817 | U17: =U7+INDEX(Data_Prices!U:U,MATCH($G17,Data_Prices!$A:$A,0))*U$37 -> 8.9443978 | V17: =V7+INDEX(Data_Prices!V:V,MATCH($G17,Data_Prices!$A:$A,0))*V$37 -> 8.9443978 | W17: =W7+INDEX(Data_Prices!W:W,MATCH($G17,Data_Prices!$A:$A,0))*W$37 -> 8.9443978 | X17: =X7+INDEX(Data_Prices!X:X,MATCH($G17,Data_Prices!$A:$A,0))*X$37 -> 8.9443978 | Y17: =Y7+INDEX(Data_Prices!Y:Y,MATCH($G17,Data_Prices!$A:$A,0))*Y$37 -> 8.9443978 | Z17: =Z7+INDEX(Data_Prices!Z:Z,MATCH($G17,Data_Prices!$A:$A,0))*Z$37 -> 8.9443978 | AA17: =AA7+INDEX(Data_Prices!AA:AA,MATCH($G17,Data_Prices!$A:$A,0))*AA$37 -> 8.9443978 | AB17: =AB7+INDEX(Data_Prices!AB:AB,MATCH($G17,Data_Prices!$A:$A,0))*AB$37 -> 8.9443978 | AC17: =AC7+INDEX(Data_Prices!AC:AC,MATCH($G17,Data_Prices!$A:$A,0))*AC$37 -> 8.9443978 | AD17: =AD7+INDEX(Data_Prices!AD:AD,MATCH($G17,Data_Prices!$A:$A,0))*AD$37 -> 8.9443978 | AE17: =AE7+INDEX(Data_Prices!AE:AE,MATCH($G17,Data_Prices!$A:$A,0))*AE$37 -> 8.9443978
B18: nga | C18: =$C$5 -> irn | D18: Natural gas | E18: $/GJ | F18: atp | G18: =Settings!$B$3&".mit.nce."&Settings!$B$4&"."&$B18&".a."&$J$5 -> egy.mit.nce.ind.nga.a.1 | H18: =Settings!$B$3&".mit.atp."&$C$5&"."&$B18&".e."&$J$5 -> egy.mit.atp.irn.nga.e.1 | K18: =K8+INDEX(Data_Prices!K:K,MATCH($G18,Data_Prices!$A:$A,0))*K$37 -> 6.0634636 | L18: =L8+INDEX(Data_Prices!L:L,MATCH($G18,Data_Prices!$A:$A,0))*L$37 -> 5.4510151 | M18: =M8+INDEX(Data_Prices!M:M,MATCH($G18,Data_Prices!$A:$A,0))*M$37 -> 5.1193563 | N18: =N8+INDEX(Data_Prices!N:N,MATCH($G18,Data_Prices!$A:$A,0))*N$37 -> 5.0821846 | O18: =O8+INDEX(Data_Prices!O:O,MATCH($G18,Data_Prices!$A:$A,0))*O$37 -> 5.0821846 | P18: =P8+INDEX(Data_Prices!P:P,MATCH($G18,Data_Prices!$A:$A,0))*P$37 -> 5.0821846 | Q18: =Q8+INDEX(Data_Prices!Q:Q,MATCH($G18,Data_Prices!$A:$A,0))*Q$37 -> 5.0821846 | R18: =R8+INDEX(Data_Prices!R:R,MATCH($G18,Data_Prices!$A:$A,0))*R$37 -> 5.0821846 | S18: =S8+INDEX(Data_Prices!S:S,MATCH($G18,Data_Prices!$A:$A,0))*S$37 -> 5.0821846 | T18: =T8+INDEX(Data_Prices!T:T,MATCH($G18,Data_Prices!$A:$A,0))*T$37 -> 5.0821846 | U18: =U8+INDEX(Data_Prices!U:U,MATCH($G18,Data_Prices!$A:$A,0))*U$37 -> 5.0821846 | V18: =V8+INDEX(Data_Prices!V:V,MATCH($G18,Data_Prices!$A:$A,0))*V$37 -> 5.0821846 | W18: =W8+INDEX(Data_Prices!W:W,MATCH($G18,Data_Prices!$A:$A,0))*W$37 -> 5.0821846 | X18: =X8+INDEX(Data_Prices!X:X,MATCH($G18,Data_Prices!$A:$A,0))*X$37 -> 5.0821846 | Y18: =Y8+INDEX(Data_Prices!Y:Y,MATCH($G18,Data_Prices!$A:$A,0))*Y$37 -> 5.0821846 | Z18: =Z8+INDEX(Data_Prices!Z:Z,MATCH($G18,Data_Prices!$A:$A,0))*Z$37 -> 5.0821846 | AA18: =AA8+INDEX(Data_Prices!AA:AA,MATCH($G18,Data_Prices!$A:$A,0))*AA$37 -> 5.0821846 | AB18: =AB8+INDEX(Data_Prices!AB:AB,MATCH($G18,Data_Prices!$A:$A,0))*AB$37 -> 5.0821846 | AC18: =AC8+INDEX(Data_Prices!AC:AC,MATCH($G18,Data_Prices!$A:$A,0))*AC$37 -> 5.0821846 | AD18: =AD8+INDEX(Data_Prices!AD:AD,MATCH($G18,Data_Prices!$A:$A,0))*AD$37 -> 5.0821846 | AE18: =AE8+INDEX(Data_Prices!AE:AE,MATCH($G18,Data_Prices!$A:$A,0))*AE$37 -> 5.0821846
B19: gso | C19: =$C$5 -> irn | D19: Gasoline | E19: $/liter | F19: atp | G19: =Settings!$B$3&".mit.nce."&Settings!$B$4&"."&$B19&".a."&$J$5 -> egy.mit.nce.ind.gso.a.1 | H19: =Settings!$B$3&".mit.atp."&$C$5&"."&$B19&".e."&$J$5 -> egy.mit.atp.irn.gso.e.1 | K19: =K9+INDEX(Data_Prices!K:K,MATCH($G19,Data_Prices!$A:$A,0))*K$37 -> 0.67114653 | L19: =L9+INDEX(Data_Prices!L:L,MATCH($G19,Data_Prices!$A:$A,0))*L$37 -> 0.61197798 | M19: =M9+INDEX(Data_Prices!M:M,MATCH($G19,Data_Prices!$A:$A,0))*M$37 -> 0.61180975 | N19: =N9+INDEX(Data_Prices!N:N,MATCH($G19,Data_Prices!$A:$A,0))*N$37 -> 0.6035831 | O19: =O9+INDEX(Data_Prices!O:O,MATCH($G19,Data_Prices!$A:$A,0))*O$37 -> 0.6035831 | P19: =P9+INDEX(Data_Prices!P:P,MATCH($G19,Data_Prices!$A:$A,0))*P$37 -> 0.6035831 | Q19: =Q9+INDEX(Data_Prices!Q:Q,MATCH($G19,Data_Prices!$A:$A,0))*Q$37 -> 0.6035831 | R19: =R9+INDEX(Data_Prices!R:R,MATCH($G19,Data_Prices!$A:$A,0))*R$37 -> 0.6035831 | S19: =S9+INDEX(Data_Prices!S:S,MATCH($G19,Data_Prices!$A:$A,0))*S$37 -> 0.6035831 | T19: =T9+INDEX(Data_Prices!T:T,MATCH($G19,Data_Prices!$A:$A,0))*T$37 -> 0.6035831 | U19: =U9+INDEX(Data_Prices!U:U,MATCH($G19,Data_Prices!$A:$A,0))*U$37 -> 0.6035831 | V19: =V9+INDEX(Data_Prices!V:V,MATCH($G19,Data_Prices!$A:$A,0))*V$37 -> 0.6035831 | W19: =W9+INDEX(Data_Prices!W:W,MATCH($G19,Data_Prices!$A:$A,0))*W$37 -> 0.6035831 | X19: =X9+INDEX(Data_Prices!X:X,MATCH($G19,Data_Prices!$A:$A,0))*X$37 -> 0.6035831 | Y19: =Y9+INDEX(Data_Prices!Y:Y,MATCH($G19,Data_Prices!$A:$A,0))*Y$37 -> 0.6035831 | Z19: =Z9+INDEX(Data_Prices!Z:Z,MATCH($G19,Data_Prices!$A:$A,0))*Z$37 -> 0.6035831 | AA19: =AA9+INDEX(Data_Prices!AA:AA,MATCH($G19,Data_Prices!$A:$A,0))*AA$37 -> 0.6035831 | AB19: =AB9+INDEX(Data_Prices!AB:AB,MATCH($G19,Data_Prices!$A:$A,0))*AB$37 -> 0.6035831 | AC19: =AC9+INDEX(Data_Prices!AC:AC,MATCH($G19,Data_Prices!$A:$A,0))*AC$37 -> 0.6035831 | AD19: =AD9+INDEX(Data_Prices!AD:AD,MATCH($G19,Data_Prices!$A:$A,0))*AD$37 -> 0.6035831 | AE19: =AE9+INDEX(Data_Prices!AE:AE,MATCH($G19,Data_Prices!$A:$A,0))*AE$37 -> 0.6035831
B20: die | C20: =$C$5 -> irn | D20: Diesel | E20: $/liter | F20: atp | G20: =Settings!$B$3&".mit.nce."&Settings!$B$4&"."&$B20&".a."&$J$5 -> egy.mit.nce.ind.die.a.1 | H20: =Settings!$B$3&".mit.atp."&$C$5&"."&$B20&".e."&$J$5 -> egy.mit.atp.irn.die.e.1 | K20: =K10+INDEX(Data_Prices!K:K,MATCH($G20,Data_Prices!$A:$A,0))*K$37 -> 0.55971121 | L20: =L10+INDEX(Data_Prices!L:L,MATCH($G20,Data_Prices!$A:$A,0))*L$37 -> 0.49458873 | M20: =M10+INDEX(Data_Prices!M:M,MATCH($G20,Data_Prices!$A:$A,0))*M$37 -> 0.50778655 | N20: =N10+INDEX(Data_Prices!N:N,MATCH($G20,Data_Prices!$A:$A,0))*N$37 -> 0.47043643 | O20: =O10+INDEX(Data_Prices!O:O,MATCH($G20,Data_Prices!$A:$A,0))*O$37 -> 0.47043643 | P20: =P10+INDEX(Data_Prices!P:P,MATCH($G20,Data_Prices!$A:$A,0))*P$37 -> 0.47043643 | Q20: =Q10+INDEX(Data_Prices!Q:Q,MATCH($G20,Data_Prices!$A:$A,0))*Q$37 -> 0.47043643 | R20: =R10+INDEX(Data_Prices!R:R,MATCH($G20,Data_Prices!$A:$A,0))*R$37 -> 0.47043643 | S20: =S10+INDEX(Data_Prices!S:S,MATCH($G20,Data_Prices!$A:$A,0))*S$37 -> 0.47043643 | T20: =T10+INDEX(Data_Prices!T:T,MATCH($G20,Data_Prices!$A:$A,0))*T$37 -> 0.47043643 | U20: =U10+INDEX(Data_Prices!U:U,MATCH($G20,Data_Prices!$A:$A,0))*U$37 -> 0.47043643 | V20: =V10+INDEX(Data_Prices!V:V,MATCH($G20,Data_Prices!$A:$A,0))*V$37 -> 0.47043643 | W20: =W10+INDEX(Data_Prices!W:W,MATCH($G20,Data_Prices!$A:$A,0))*W$37 -> 0.47043643 | X20: =X10+INDEX(Data_Prices!X:X,MATCH($G20,Data_Prices!$A:$A,0))*X$37 -> 0.47043643 | Y20: =Y10+INDEX(Data_Prices!Y:Y,MATCH($G20,Data_Prices!$A:$A,0))*Y$37 -> 0.47043643 | Z20: =Z10+INDEX(Data_Prices!Z:Z,MATCH($G20,Data_Prices!$A:$A,0))*Z$37 -> 0.47043643 | AA20: =AA10+INDEX(Data_Prices!AA:AA,MATCH($G20,Data_Prices!$A:$A,0))*AA$37 -> 0.47043643 | AB20: =AB10+INDEX(Data_Prices!AB:AB,MATCH($G20,Data_Prices!$A:$A,0))*AB$37 -> 0.47043643 | AC20: =AC10+INDEX(Data_Prices!AC:AC,MATCH($G20,Data_Prices!$A:$A,0))*AC$37 -> 0.47043643 | AD20: =AD10+INDEX(Data_Prices!AD:AD,MATCH($G20,Data_Prices!$A:$A,0))*AD$37 -> 0.47043643 | AE20: =AE10+INDEX(Data_Prices!AE:AE,MATCH($G20,Data_Prices!$A:$A,0))*AE$37 -> 0.47043643
B21: lpg | C21: =$C$5 -> irn | D21: LPG | E21: $/liter | F21: atp | G21: =Settings!$B$3&".mit.nce."&Settings!$B$4&"."&$B21&".a."&$J$5 -> egy.mit.nce.ind.lpg.a.1 | H21: =Settings!$B$3&".mit.atp."&$C$5&"."&$B21&".e."&$J$5 -> egy.mit.atp.irn.lpg.e.1 | K21: =K11+INDEX(Data_Prices!K:K,MATCH($G21,Data_Prices!$A:$A,0))*K$37 -> 0.20036669 | L21: =L11+INDEX(Data_Prices!L:L,MATCH($G21,Data_Prices!$A:$A,0))*L$37 -> 0.15734474 | M21: =M11+INDEX(Data_Prices!M:M,MATCH($G21,Data_Prices!$A:$A,0))*M$37 -> 0.16448404 | N21: =N11+INDEX(Data_Prices!N:N,MATCH($G21,Data_Prices!$A:$A,0))*N$37 -> 0.15070908 | O21: =O11+INDEX(Data_Prices!O:O,MATCH($G21,Data_Prices!$A:$A,0))*O$37 -> 0.15070908 | P21: =P11+INDEX(Data_Prices!P:P,MATCH($G21,Data_Prices!$A:$A,0))*P$37 -> 0.15070908 | Q21: =Q11+INDEX(Data_Prices!Q:Q,MATCH($G21,Data_Prices!$A:$A,0))*Q$37 -> 0.15070908 | R21: =R11+INDEX(Data_Prices!R:R,MATCH($G21,Data_Prices!$A:$A,0))*R$37 -> 0.15070908 | S21: =S11+INDEX(Data_Prices!S:S,MATCH($G21,Data_Prices!$A:$A,0))*S$37 -> 0.15070908 | T21: =T11+INDEX(Data_Prices!T:T,MATCH($G21,Data_Prices!$A:$A,0))*T$37 -> 0.15070908 | U21: =U11+INDEX(Data_Prices!U:U,MATCH($G21,Data_Prices!$A:$A,0))*U$37 -> 0.15070908 | V21: =V11+INDEX(Data_Prices!V:V,MATCH($G21,Data_Prices!$A:$A,0))*V$37 -> 0.15070908 | W21: =W11+INDEX(Data_Prices!W:W,MATCH($G21,Data_Prices!$A:$A,0))*W$37 -> 0.15070908 | X21: =X11+INDEX(Data_Prices!X:X,MATCH($G21,Data_Prices!$A:$A,0))*X$37 -> 0.15070908 | Y21: =Y11+INDEX(Data_Prices!Y:Y,MATCH($G21,Data_Prices!$A:$A,0))*Y$37 -> 0.15070908 | Z21: =Z11+INDEX(Data_Prices!Z:Z,MATCH($G21,Data_Prices!$A:$A,0))*Z$37 -> 0.15070908 | AA21: =AA11+INDEX(Data_Prices!AA:AA,MATCH($G21,Data_Prices!$A:$A,0))*AA$37 -> 0.15070908 | AB21: =AB11+INDEX(Data_Prices!AB:AB,MATCH($G21,Data_Prices!$A:$A,0))*AB$37 -> 0.15070908 | AC21: =AC11+INDEX(Data_Prices!AC:AC,MATCH($G21,Data_Prices!$A:$A,0))*AC$37 -> 0.15070908 | AD21: =AD11+INDEX(Data_Prices!AD:AD,MATCH($G21,Data_Prices!$A:$A,0))*AD$37 -> 0.15070908 | AE21: =AE11+INDEX(Data_Prices!AE:AE,MATCH($G21,Data_Prices!$A:$A,0))*AE$37 -> 0.15070908
B22: ker | C22: =$C$5 -> irn | D22: Kerosene | E22: $/liter | F22: atp | G22: =Settings!$B$3&".mit.nce."&Settings!$B$4&"."&$B22&".a."&$J$5 -> egy.mit.nce.ind.ker.a.1 | H22: =Settings!$B$3&".mit.atp."&$C$5&"."&$B22&".e."&$J$5 -> egy.mit.atp.irn.ker.e.1 | K22: =K12+INDEX(Data_Prices!K:K,MATCH($G22,Data_Prices!$A:$A,0))*K$37 -> 0.48429424 | L22: =L12+INDEX(Data_Prices!L:L,MATCH($G22,Data_Prices!$A:$A,0))*L$37 -> 0.45642817 | M22: =M12+INDEX(Data_Prices!M:M,MATCH($G22,Data_Prices!$A:$A,0))*M$37 -> 0.4316892 | N22: =N12+INDEX(Data_Prices!N:N,MATCH($G22,Data_Prices!$A:$A,0))*N$37 -> 0.42507558 | O22: =O12+INDEX(Data_Prices!O:O,MATCH($G22,Data_Prices!$A:$A,0))*O$37 -> 0.42507558 | P22: =P12+INDEX(Data_Prices!P:P,MATCH($G22,Data_Prices!$A:$A,0))*P$37 -> 0.42507558 | Q22: =Q12+INDEX(Data_Prices!Q:Q,MATCH($G22,Data_Prices!$A:$A,0))*Q$37 -> 0.42507558 | R22: =R12+INDEX(Data_Prices!R:R,MATCH($G22,Data_Prices!$A:$A,0))*R$37 -> 0.42507558 | S22: =S12+INDEX(Data_Prices!S:S,MATCH($G22,Data_Prices!$A:$A,0))*S$37 -> 0.42507558 | T22: =T12+INDEX(Data_Prices!T:T,MATCH($G22,Data_Prices!$A:$A,0))*T$37 -> 0.42507558 | U22: =U12+INDEX(Data_Prices!U:U,MATCH($G22,Data_Prices!$A:$A,0))*U$37 -> 0.42507558 | V22: =V12+INDEX(Data_Prices!V:V,MATCH($G22,Data_Prices!$A:$A,0))*V$37 -> 0.42507558 | W22: =W12+INDEX(Data_Prices!W:W,MATCH($G22,Data_Prices!$A:$A,0))*W$37 -> 0.42507558 | X22: =X12+INDEX(Data_Prices!X:X,MATCH($G22,Data_Prices!$A:$A,0))*X$37 -> 0.42507558 | Y22: =Y12+INDEX(Data_Prices!Y:Y,MATCH($G22,Data_Prices!$A:$A,0))*Y$37 -> 0.42507558 | Z22: =Z12+INDEX(Data_Prices!Z:Z,MATCH($G22,Data_Prices!$A:$A,0))*Z$37 -> 0.42507558 | AA22: =AA12+INDEX(Data_Prices!AA:AA,MATCH($G22,Data_Prices!$A:$A,0))*AA$37 -> 0.42507558 | AB22: =AB12+INDEX(Data_Prices!AB:AB,MATCH($G22,Data_Prices!$A:$A,0))*AB$37 -> 0.42507558 | AC22: =AC12+INDEX(Data_Prices!AC:AC,MATCH($G22,Data_Prices!$A:$A,0))*AC$37 -> 0.42507558 | AD22: =AD12+INDEX(Data_Prices!AD:AD,MATCH($G22,Data_Prices!$A:$A,0))*AD$37 -> 0.42507558 | AE22: =AE12+INDEX(Data_Prices!AE:AE,MATCH($G22,Data_Prices!$A:$A,0))*AE$37 -> 0.42507558
B23: oop | C23: =$C$5 -> irn | D23: Other oil products | E23: $/bbl | F23: atp | G23: =Settings!$B$3&".mit.nce."&Settings!$B$4&"."&$B23&".a."&$J$5 -> egy.mit.nce.ind.oop.a.1 | H23: =Settings!$B$3&".mit.atp."&$C$5&"."&$B23&".e."&$J$5 -> egy.mit.atp.irn.oop.e.1 | K23: =K13+INDEX(Data_Prices!K:K,MATCH($G23,Data_Prices!$A:$A,0))*K$37 -> 41.500338 | L23: =L13+INDEX(Data_Prices!L:L,MATCH($G23,Data_Prices!$A:$A,0))*L$37 -> 34.41537 | M23: =M13+INDEX(Data_Prices!M:M,MATCH($G23,Data_Prices!$A:$A,0))*M$37 -> 37.368961 | N23: =N13+INDEX(Data_Prices!N:N,MATCH($G23,Data_Prices!$A:$A,0))*N$37 -> 28.982761 | O23: =O13+INDEX(Data_Prices!O:O,MATCH($G23,Data_Prices!$A:$A,0))*O$37 -> 15 | P23: =P13+INDEX(Data_Prices!P:P,MATCH($G23,Data_Prices!$A:$A,0))*P$37 -> 24.25863 | Q23: =Q13+INDEX(Data_Prices!Q:Q,MATCH($G23,Data_Prices!$A:$A,0))*Q$37 -> 15 | R23: =R13+INDEX(Data_Prices!R:R,MATCH($G23,Data_Prices!$A:$A,0))*R$37 -> 15 | S23: =S13+INDEX(Data_Prices!S:S,MATCH($G23,Data_Prices!$A:$A,0))*S$37 -> 15 | T23: =T13+INDEX(Data_Prices!T:T,MATCH($G23,Data_Prices!$A:$A,0))*T$37 -> 15 | U23: =U13+INDEX(Data_Prices!U:U,MATCH($G23,Data_Prices!$A:$A,0))*U$37 -> 15 | V23: =V13+INDEX(Data_Prices!V:V,MATCH($G23,Data_Prices!$A:$A,0))*V$37 -> 15 | W23: =W13+INDEX(Data_Prices!W:W,MATCH($G23,Data_Prices!$A:$A,0))*W$37 -> 15 | X23: =X13+INDEX(Data_Prices!X:X,MATCH($G23,Data_Prices!$A:$A,0))*X$37 -> 15 | Y23: =Y13+INDEX(Data_Prices!Y:Y,MATCH($G23,Data_Prices!$A:$A,0))*Y$37 -> 15 | Z23: =Z13+INDEX(Data_Prices!Z:Z,MATCH($G23,Data_Prices!$A:$A,0))*Z$37 -> 15 | AA23: =AA13+INDEX(Data_Prices!AA:AA,MATCH($G23,Data_Prices!$A:$A,0))*AA$37 -> 15 | AB23: =AB13+INDEX(Data_Prices!AB:AB,MATCH($G23,Data_Prices!$A:$A,0))*AB$37 -> 15 | AC23: =AC13+INDEX(Data_Prices!AC:AC,MATCH($G23,Data_Prices!$A:$A,0))*AC$37 -> 15 | AD23: =AD13+INDEX(Data_Prices!AD:AD,MATCH($G23,Data_Prices!$A:$A,0))*AD$37 -> 15 | AE23: =AE13+INDEX(Data_Prices!AE:AE,MATCH($G23,Data_Prices!$A:$A,0))*AE$37 -> 15
B24: bio | C24: =$C$5 -> irn | D24: Biomass | E24: $/GJ | F24: atp | G24: =Settings!$B$3&".mit.nce."&Settings!$B$4&"."&$B24&".a."&$J$5 -> egy.mit.nce.ind.bio.a.1 | H24: =Settings!$B$3&".mit.atp."&$C$5&"."&$B24&".e."&$J$5 -> egy.mit.atp.irn.bio.e.1 | K24: =K14+INDEX(Data_Prices!K:K,MATCH($G24,Data_Prices!$A:$A,0))*K$37 -> 15.334551 | L24: =L14+INDEX(Data_Prices!L:L,MATCH($G24,Data_Prices!$A:$A,0))*L$37 -> 14.199528 | M24: =M14+INDEX(Data_Prices!M:M,MATCH($G24,Data_Prices!$A:$A,0))*M$37 -> 13.840442 | N24: =N14+INDEX(Data_Prices!N:N,MATCH($G24,Data_Prices!$A:$A,0))*N$37 -> 13.567727 | O24: =O14+INDEX(Data_Prices!O:O,MATCH($G24,Data_Prices!$A:$A,0))*O$37 -> 13.567727 | P24: =P14+INDEX(Data_Prices!P:P,MATCH($G24,Data_Prices!$A:$A,0))*P$37 -> 13.567727 | Q24: =Q14+INDEX(Data_Prices!Q:Q,MATCH($G24,Data_Prices!$A:$A,0))*Q$37 -> 13.567727 | R24: =R14+INDEX(Data_Prices!R:R,MATCH($G24,Data_Prices!$A:$A,0))*R$37 -> 13.567727 | S24: =S14+INDEX(Data_Prices!S:S,MATCH($G24,Data_Prices!$A:$A,0))*S$37 -> 13.567727 | T24: =T14+INDEX(Data_Prices!T:T,MATCH($G24,Data_Prices!$A:$A,0))*T$37 -> 13.567727 | U24: =U14+INDEX(Data_Prices!U:U,MATCH($G24,Data_Prices!$A:$A,0))*U$37 -> 13.567727 | V24: =V14+INDEX(Data_Prices!V:V,MATCH($G24,Data_Prices!$A:$A,0))*V$37 -> 13.567727 | W24: =W14+INDEX(Data_Prices!W:W,MATCH($G24,Data_Prices!$A:$A,0))*W$37 -> 13.567727 | X24: =X14+INDEX(Data_Prices!X:X,MATCH($G24,Data_Prices!$A:$A,0))*X$37 -> 13.567727 | Y24: =Y14+INDEX(Data_Prices!Y:Y,MATCH($G24,Data_Prices!$A:$A,0))*Y$37 -> 13.567727 | Z24: =Z14+INDEX(Data_Prices!Z:Z,MATCH($G24,Data_Prices!$A:$A,0))*Z$37 -> 13.567727 | AA24: =AA14+INDEX(Data_Prices!AA:AA,MATCH($G24,Data_Prices!$A:$A,0))*AA$37 -> 13.567727 | AB24: =AB14+INDEX(Data_Prices!AB:AB,MATCH($G24,Data_Prices!$A:$A,0))*AB$37 -> 13.567727 | AC24: =AC14+INDEX(Data_Prices!AC:AC,MATCH($G24,Data_Prices!$A:$A,0))*AC$37 -> 13.567727 | AD24: =AD14+INDEX(Data_Prices!AD:AD,MATCH($G24,Data_Prices!$A:$A,0))*AD$37 -> 13.567727 | AE24: =AE14+INDEX(Data_Prices!AE:AE,MATCH($G24,Data_Prices!$A:$A,0))*AE$37 -> 13.567727
B25: ren | C25: =$C$5 -> irn | D25: Self-generated renewables | E25: $/kwh | F25: atp | G25: =Settings!$B$3&".mit.nce."&Settings!$B$4&"."&$B25&".a."&$J$5 -> egy.mit.nce.ind.ren.a.1 | H25: =Settings!$B$3&".mit.atp."&$C$5&"."&$B25&".e."&$J$5 -> egy.mit.atp.irn.ren.e.1 | K25: =K15+INDEX(Data_Prices!K:K,MATCH($G25,Data_Prices!$A:$A,0))*K$37 -> 0 | L25: =L15+INDEX(Data_Prices!L:L,MATCH($G25,Data_Prices!$A:$A,0))*L$37 -> 0.14404499 | M25: =M15+INDEX(Data_Prices!M:M,MATCH($G25,Data_Prices!$A:$A,0))*M$37 -> 0.14102041 | N25: =N15+INDEX(Data_Prices!N:N,MATCH($G25,Data_Prices!$A:$A,0))*N$37 -> 0.13511636 | O25: =O15+INDEX(Data_Prices!O:O,MATCH($G25,Data_Prices!$A:$A,0))*O$37 -> 0.13098826 | P25: =P15+INDEX(Data_Prices!P:P,MATCH($G25,Data_Prices!$A:$A,0))*P$37 -> 0.12790842 | Q25: =Q15+INDEX(Data_Prices!Q:Q,MATCH($G25,Data_Prices!$A:$A,0))*Q$37 -> 0.12481431 | R25: =R15+INDEX(Data_Prices!R:R,MATCH($G25,Data_Prices!$A:$A,0))*R$37 -> 0.12146026 | S25: =S15+INDEX(Data_Prices!S:S,MATCH($G25,Data_Prices!$A:$A,0))*S$37 -> 0.11795074 | T25: =T15+INDEX(Data_Prices!T:T,MATCH($G25,Data_Prices!$A:$A,0))*T$37 -> 0.11419916 | U25: =U15+INDEX(Data_Prices!U:U,MATCH($G25,Data_Prices!$A:$A,0))*U$37 -> 0.1136651 | V25: =V15+INDEX(Data_Prices!V:V,MATCH($G25,Data_Prices!$A:$A,0))*V$37 -> 0.11301693 | W25: =W15+INDEX(Data_Prices!W:W,MATCH($G25,Data_Prices!$A:$A,0))*W$37 -> 0.11231407 | X25: =X15+INDEX(Data_Prices!X:X,MATCH($G25,Data_Prices!$A:$A,0))*X$37 -> 0.11142204 | Y25: =Y15+INDEX(Data_Prices!Y:Y,MATCH($G25,Data_Prices!$A:$A,0))*Y$37 -> 0.11043412 | Z25: =Z15+INDEX(Data_Prices!Z:Z,MATCH($G25,Data_Prices!$A:$A,0))*Z$37 -> 0.10948397 | AA25: =AA15+INDEX(Data_Prices!AA:AA,MATCH($G25,Data_Prices!$A:$A,0))*AA$37 -> 0.10839192 | AB25: =AB15+INDEX(Data_Prices!AB:AB,MATCH($G25,Data_Prices!$A:$A,0))*AB$37 -> 0.10735443 | AC25: =AC15+INDEX(Data_Prices!AC:AC,MATCH($G25,Data_Prices!$A:$A,0))*AC$37 -> 0.10516868 | AD25: =AD15+INDEX(Data_Prices!AD:AD,MATCH($G25,Data_Prices!$A:$A,0))*AD$37 -> 0.10305798 | AE25: =AE15+INDEX(Data_Prices!AE:AE,MATCH($G25,Data_Prices!$A:$A,0))*AE$37 -> 0.10093184
B26: Shadow price: post-tax + shadow price of non-price policies x share acting on efficiency
B27: coa | C27: =$C$5 -> irn | D27: Coal | E27: $/GJ | F27: shp | G27: =Settings!$B$3&".mit.shp."&$B27&"."&Settings!$B$4&"."&$J$5 -> egy.mit.shp.coa.ind.1 | H27: =Settings!$B$3&".mit.shp."&$C$5&"."&$B27&".e."&$J$5 -> egy.mit.shp.irn.coa.e.1 | K27: =K17+INDEX(Data_Prices!K:K,MATCH($G27,Data_Prices!$A:$A,0))*K$38 -> 11.182902 | L27: =L17+INDEX(Data_Prices!L:L,MATCH($G27,Data_Prices!$A:$A,0))*L$38 -> 10.523361 | M27: =M17+INDEX(Data_Prices!M:M,MATCH($G27,Data_Prices!$A:$A,0))*M$38 -> 10.299561 | N27: =N17+INDEX(Data_Prices!N:N,MATCH($G27,Data_Prices!$A:$A,0))*N$38 -> 9.5775284 | O27: =O17+INDEX(Data_Prices!O:O,MATCH($G27,Data_Prices!$A:$A,0))*O$38 -> 8.4854783 | P27: =P17+INDEX(Data_Prices!P:P,MATCH($G27,Data_Prices!$A:$A,0))*P$38 -> 9.0871922 | Q27: =Q17+INDEX(Data_Prices!Q:Q,MATCH($G27,Data_Prices!$A:$A,0))*Q$38 -> 9.2229237 | R27: =R17+INDEX(Data_Prices!R:R,MATCH($G27,Data_Prices!$A:$A,0))*R$38 -> 9.158565 | S27: =S17+INDEX(Data_Prices!S:S,MATCH($G27,Data_Prices!$A:$A,0))*S$38 -> 9.0895479 | T27: =T17+INDEX(Data_Prices!T:T,MATCH($G27,Data_Prices!$A:$A,0))*T$38 -> 9.0156817 | U27: =U17+INDEX(Data_Prices!U:U,MATCH($G27,Data_Prices!$A:$A,0))*U$38 -> 8.9443978 | V27: =V17+INDEX(Data_Prices!V:V,MATCH($G27,Data_Prices!$A:$A,0))*V$38 -> 8.9443978 | W27: =W17+INDEX(Data_Prices!W:W,MATCH($G27,Data_Prices!$A:$A,0))*W$38 -> 8.9443978 | X27: =X17+INDEX(Data_Prices!X:X,MATCH($G27,Data_Prices!$A:$A,0))*X$38 -> 8.9443978 | Y27: =Y17+INDEX(Data_Prices!Y:Y,MATCH($G27,Data_Prices!$A:$A,0))*Y$38 -> 8.9443978 | Z27: =Z17+INDEX(Data_Prices!Z:Z,MATCH($G27,Data_Prices!$A:$A,0))*Z$38 -> 8.9443978 | AA27: =AA17+INDEX(Data_Prices!AA:AA,MATCH($G27,Data_Prices!$A:$A,0))*AA$38 -> 8.9443978 | AB27: =AB17+INDEX(Data_Prices!AB:AB,MATCH($G27,Data_Prices!$A:$A,0))*AB$38 -> 8.9443978 | AC27: =AC17+INDEX(Data_Prices!AC:AC,MATCH($G27,Data_Prices!$A:$A,0))*AC$38 -> 8.9443978 | AD27: =AD17+INDEX(Data_Prices!AD:AD,MATCH($G27,Data_Prices!$A:$A,0))*AD$38 -> 8.9443978 | AE27: =AE17+INDEX(Data_Prices!AE:AE,MATCH($G27,Data_Prices!$A:$A,0))*AE$38 -> 8.9443978
B28: nga | C28: =$C$5 -> irn | D28: Natural gas | E28: $/GJ | F28: shp | G28: =Settings!$B$3&".mit.shp."&$B28&"."&Settings!$B$4&"."&$J$5 -> egy.mit.shp.nga.ind.1 | H28: =Settings!$B$3&".mit.shp."&$C$5&"."&$B28&".e."&$J$5 -> egy.mit.shp.irn.nga.e.1 | K28: =K18+INDEX(Data_Prices!K:K,MATCH($G28,Data_Prices!$A:$A,0))*K$38 -> 6.0634636 | L28: =L18+INDEX(Data_Prices!L:L,MATCH($G28,Data_Prices!$A:$A,0))*L$38 -> 5.4510151 | M28: =M18+INDEX(Data_Prices!M:M,MATCH($G28,Data_Prices!$A:$A,0))*M$38 -> 5.1193563 | N28: =N18+INDEX(Data_Prices!N:N,MATCH($G28,Data_Prices!$A:$A,0))*N$38 -> 5.0821846 | O28: =O18+INDEX(Data_Prices!O:O,MATCH($G28,Data_Prices!$A:$A,0))*O$38 -> 5.0821846 | P28: =P18+INDEX(Data_Prices!P:P,MATCH($G28,Data_Prices!$A:$A,0))*P$38 -> 5.0821846 | Q28: =Q18+INDEX(Data_Prices!Q:Q,MATCH($G28,Data_Prices!$A:$A,0))*Q$38 -> 5.0821846 | R28: =R18+INDEX(Data_Prices!R:R,MATCH($G28,Data_Prices!$A:$A,0))*R$38 -> 5.0821846 | S28: =S18+INDEX(Data_Prices!S:S,MATCH($G28,Data_Prices!$A:$A,0))*S$38 -> 5.0821846 | T28: =T18+INDEX(Data_Prices!T:T,MATCH($G28,Data_Prices!$A:$A,0))*T$38 -> 5.0821846 | U28: =U18+INDEX(Data_Prices!U:U,MATCH($G28,Data_Prices!$A:$A,0))*U$38 -> 5.0821846 | V28: =V18+INDEX(Data_Prices!V:V,MATCH($G28,Data_Prices!$A:$A,0))*V$38 -> 5.0821846 | W28: =W18+INDEX(Data_Prices!W:W,MATCH($G28,Data_Prices!$A:$A,0))*W$38 -> 5.0821846 | X28: =X18+INDEX(Data_Prices!X:X,MATCH($G28,Data_Prices!$A:$A,0))*X$38 -> 5.0821846 | Y28: =Y18+INDEX(Data_Prices!Y:Y,MATCH($G28,Data_Prices!$A:$A,0))*Y$38 -> 5.0821846 | Z28: =Z18+INDEX(Data_Prices!Z:Z,MATCH($G28,Data_Prices!$A:$A,0))*Z$38 -> 5.0821846 | AA28: =AA18+INDEX(Data_Prices!AA:AA,MATCH($G28,Data_Prices!$A:$A,0))*AA$38 -> 5.0821846 | AB28: =AB18+INDEX(Data_Prices!AB:AB,MATCH($G28,Data_Prices!$A:$A,0))*AB$38 -> 5.0821846 | AC28: =AC18+INDEX(Data_Prices!AC:AC,MATCH($G28,Data_Prices!$A:$A,0))*AC$38 -> 5.0821846 | AD28: =AD18+INDEX(Data_Prices!AD:AD,MATCH($G28,Data_Prices!$A:$A,0))*AD$38 -> 5.0821846 | AE28: =AE18+INDEX(Data_Prices!AE:AE,MATCH($G28,Data_Prices!$A:$A,0))*AE$38 -> 5.0821846
B29: gso | C29: =$C$5 -> irn | D29: Gasoline | E29: $/liter | F29: shp | G29: =Settings!$B$3&".mit.shp."&$B29&"."&Settings!$B$4&"."&$J$5 -> egy.mit.shp.gso.ind.1 | H29: =Settings!$B$3&".mit.shp."&$C$5&"."&$B29&".e."&$J$5 -> egy.mit.shp.irn.gso.e.1 | K29: =K19+INDEX(Data_Prices!K:K,MATCH($G29,Data_Prices!$A:$A,0))*K$38 -> 0.67114653 | L29: =L19+INDEX(Data_Prices!L:L,MATCH($G29,Data_Prices!$A:$A,0))*L$38 -> 0.61197798 | M29: =M19+INDEX(Data_Prices!M:M,MATCH($G29,Data_Prices!$A:$A,0))*M$38 -> 0.61180975 | N29: =N19+INDEX(Data_Prices!N:N,MATCH($G29,Data_Prices!$A:$A,0))*N$38 -> 0.6035831 | O29: =O19+INDEX(Data_Prices!O:O,MATCH($G29,Data_Prices!$A:$A,0))*O$38 -> 0.6035831 | P29: =P19+INDEX(Data_Prices!P:P,MATCH($G29,Data_Prices!$A:$A,0))*P$38 -> 0.6035831 | Q29: =Q19+INDEX(Data_Prices!Q:Q,MATCH($G29,Data_Prices!$A:$A,0))*Q$38 -> 0.6035831 | R29: =R19+INDEX(Data_Prices!R:R,MATCH($G29,Data_Prices!$A:$A,0))*R$38 -> 0.6035831 | S29: =S19+INDEX(Data_Prices!S:S,MATCH($G29,Data_Prices!$A:$A,0))*S$38 -> 0.6035831 | T29: =T19+INDEX(Data_Prices!T:T,MATCH($G29,Data_Prices!$A:$A,0))*T$38 -> 0.6035831 | U29: =U19+INDEX(Data_Prices!U:U,MATCH($G29,Data_Prices!$A:$A,0))*U$38 -> 0.6035831 | V29: =V19+INDEX(Data_Prices!V:V,MATCH($G29,Data_Prices!$A:$A,0))*V$38 -> 0.6035831 | W29: =W19+INDEX(Data_Prices!W:W,MATCH($G29,Data_Prices!$A:$A,0))*W$38 -> 0.6035831 | X29: =X19+INDEX(Data_Prices!X:X,MATCH($G29,Data_Prices!$A:$A,0))*X$38 -> 0.6035831 | Y29: =Y19+INDEX(Data_Prices!Y:Y,MATCH($G29,Data_Prices!$A:$A,0))*Y$38 -> 0.6035831 | Z29: =Z19+INDEX(Data_Prices!Z:Z,MATCH($G29,Data_Prices!$A:$A,0))*Z$38 -> 0.6035831 | AA29: =AA19+INDEX(Data_Prices!AA:AA,MATCH($G29,Data_Prices!$A:$A,0))*AA$38 -> 0.6035831 | AB29: =AB19+INDEX(Data_Prices!AB:AB,MATCH($G29,Data_Prices!$A:$A,0))*AB$38 -> 0.6035831 | AC29: =AC19+INDEX(Data_Prices!AC:AC,MATCH($G29,Data_Prices!$A:$A,0))*AC$38 -> 0.6035831 | AD29: =AD19+INDEX(Data_Prices!AD:AD,MATCH($G29,Data_Prices!$A:$A,0))*AD$38 -> 0.6035831 | AE29: =AE19+INDEX(Data_Prices!AE:AE,MATCH($G29,Data_Prices!$A:$A,0))*AE$38 -> 0.6035831
B30: die | C30: =$C$5 -> irn | D30: Diesel | E30: $/liter | F30: shp | G30: =Settings!$B$3&".mit.shp."&$B30&"."&Settings!$B$4&"."&$J$5 -> egy.mit.shp.die.ind.1 | H30: =Settings!$B$3&".mit.shp."&$C$5&"."&$B30&".e."&$J$5 -> egy.mit.shp.irn.die.e.1 | K30: =K20+INDEX(Data_Prices!K:K,MATCH($G30,Data_Prices!$A:$A,0))*K$38 -> 0.55971121 | L30: =L20+INDEX(Data_Prices!L:L,MATCH($G30,Data_Prices!$A:$A,0))*L$38 -> 0.49458873 | M30: =M20+INDEX(Data_Prices!M:M,MATCH($G30,Data_Prices!$A:$A,0))*M$38 -> 0.50778655 | N30: =N20+INDEX(Data_Prices!N:N,MATCH($G30,Data_Prices!$A:$A,0))*N$38 -> 0.47043643 | O30: =O20+INDEX(Data_Prices!O:O,MATCH($G30,Data_Prices!$A:$A,0))*O$38 -> 0.47043643 | P30: =P20+INDEX(Data_Prices!P:P,MATCH($G30,Data_Prices!$A:$A,0))*P$38 -> 0.47043643 | Q30: =Q20+INDEX(Data_Prices!Q:Q,MATCH($G30,Data_Prices!$A:$A,0))*Q$38 -> 0.47043643 | R30: =R20+INDEX(Data_Prices!R:R,MATCH($G30,Data_Prices!$A:$A,0))*R$38 -> 0.47043643 | S30: =S20+INDEX(Data_Prices!S:S,MATCH($G30,Data_Prices!$A:$A,0))*S$38 -> 0.47043643 | T30: =T20+INDEX(Data_Prices!T:T,MATCH($G30,Data_Prices!$A:$A,0))*T$38 -> 0.47043643 | U30: =U20+INDEX(Data_Prices!U:U,MATCH($G30,Data_Prices!$A:$A,0))*U$38 -> 0.47043643 | V30: =V20+INDEX(Data_Prices!V:V,MATCH($G30,Data_Prices!$A:$A,0))*V$38 -> 0.47043643 | W30: =W20+INDEX(Data_Prices!W:W,MATCH($G30,Data_Prices!$A:$A,0))*W$38 -> 0.47043643 | X30: =X20+INDEX(Data_Prices!X:X,MATCH($G30,Data_Prices!$A:$A,0))*X$38 -> 0.47043643 | Y30: =Y20+INDEX(Data_Prices!Y:Y,MATCH($G30,Data_Prices!$A:$A,0))*Y$38 -> 0.47043643 | Z30: =Z20+INDEX(Data_Prices!Z:Z,MATCH($G30,Data_Prices!$A:$A,0))*Z$38 -> 0.47043643 | AA30: =AA20+INDEX(Data_Prices!AA:AA,MATCH($G30,Data_Prices!$A:$A,0))*AA$38 -> 0.47043643 | AB30: =AB20+INDEX(Data_Prices!AB:AB,MATCH($G30,Data_Prices!$A:$A,0))*AB$38 -> 0.47043643 | AC30: =AC20+INDEX(Data_Prices!AC:AC,MATCH($G30,Data_Prices!$A:$A,0))*AC$38 -> 0.47043643 | AD30: =AD20+INDEX(Data_Prices!AD:AD,MATCH($G30,Data_Prices!$A:$A,0))*AD$38 -> 0.47043643 | AE30: =AE20+INDEX(Data_Prices!AE:AE,MATCH($G30,Data_Prices!$A:$A,0))*AE$38 -> 0.47043643
B31: lpg | C31: =$C$5 -> irn | D31: LPG | E31: $/liter | F31: shp | G31: =Settings!$B$3&".mit.shp."&$B31&"."&Settings!$B$4&"."&$J$5 -> egy.mit.shp.lpg.ind.1 | H31: =Settings!$B$3&".mit.shp."&$C$5&"."&$B31&".e."&$J$5 -> egy.mit.shp.irn.lpg.e.1 | K31: =K21+INDEX(Data_Prices!K:K,MATCH($G31,Data_Prices!$A:$A,0))*K$38 -> 0.20036669 | L31: =L21+INDEX(Data_Prices!L:L,MATCH($G31,Data_Prices!$A:$A,0))*L$38 -> 0.15734474 | M31: =M21+INDEX(Data_Prices!M:M,MATCH($G31,Data_Prices!$A:$A,0))*M$38 -> 0.16448404 | N31: =N21+INDEX(Data_Prices!N:N,MATCH($G31,Data_Prices!$A:$A,0))*N$38 -> 0.15070908 | O31: =O21+INDEX(Data_Prices!O:O,MATCH($G31,Data_Prices!$A:$A,0))*O$38 -> 0.15070908 | P31: =P21+INDEX(Data_Prices!P:P,MATCH($G31,Data_Prices!$A:$A,0))*P$38 -> 0.15070908 | Q31: =Q21+INDEX(Data_Prices!Q:Q,MATCH($G31,Data_Prices!$A:$A,0))*Q$38 -> 0.15070908 | R31: =R21+INDEX(Data_Prices!R:R,MATCH($G31,Data_Prices!$A:$A,0))*R$38 -> 0.15070908 | S31: =S21+INDEX(Data_Prices!S:S,MATCH($G31,Data_Prices!$A:$A,0))*S$38 -> 0.15070908 | T31: =T21+INDEX(Data_Prices!T:T,MATCH($G31,Data_Prices!$A:$A,0))*T$38 -> 0.15070908 | U31: =U21+INDEX(Data_Prices!U:U,MATCH($G31,Data_Prices!$A:$A,0))*U$38 -> 0.15070908 | V31: =V21+INDEX(Data_Prices!V:V,MATCH($G31,Data_Prices!$A:$A,0))*V$38 -> 0.15070908 | W31: =W21+INDEX(Data_Prices!W:W,MATCH($G31,Data_Prices!$A:$A,0))*W$38 -> 0.15070908 | X31: =X21+INDEX(Data_Prices!X:X,MATCH($G31,Data_Prices!$A:$A,0))*X$38 -> 0.15070908 | Y31: =Y21+INDEX(Data_Prices!Y:Y,MATCH($G31,Data_Prices!$A:$A,0))*Y$38 -> 0.15070908 | Z31: =Z21+INDEX(Data_Prices!Z:Z,MATCH($G31,Data_Prices!$A:$A,0))*Z$38 -> 0.15070908 | AA31: =AA21+INDEX(Data_Prices!AA:AA,MATCH($G31,Data_Prices!$A:$A,0))*AA$38 -> 0.15070908 | AB31: =AB21+INDEX(Data_Prices!AB:AB,MATCH($G31,Data_Prices!$A:$A,0))*AB$38 -> 0.15070908 | AC31: =AC21+INDEX(Data_Prices!AC:AC,MATCH($G31,Data_Prices!$A:$A,0))*AC$38 -> 0.15070908 | AD31: =AD21+INDEX(Data_Prices!AD:AD,MATCH($G31,Data_Prices!$A:$A,0))*AD$38 -> 0.15070908 | AE31: =AE21+INDEX(Data_Prices!AE:AE,MATCH($G31,Data_Prices!$A:$A,0))*AE$38 -> 0.15070908
B32: ker | C32: =$C$5 -> irn | D32: Kerosene | E32: $/liter | F32: shp | G32: =Settings!$B$3&".mit.shp."&$B32&"."&Settings!$B$4&"."&$J$5 -> egy.mit.shp.ker.ind.1 | H32: =Settings!$B$3&".mit.shp."&$C$5&"."&$B32&".e."&$J$5 -> egy.mit.shp.irn.ker.e.1 | K32: =K22+INDEX(Data_Prices!K:K,MATCH($G32,Data_Prices!$A:$A,0))*K$38 -> 0.48429424 | L32: =L22+INDEX(Data_Prices!L:L,MATCH($G32,Data_Prices!$A:$A,0))*L$38 -> 0.45642817 | M32: =M22+INDEX(Data_Prices!M:M,MATCH($G32,Data_Prices!$A:$A,0))*M$38 -> 0.4316892 | N32: =N22+INDEX(Data_Prices!N:N,MATCH($G32,Data_Prices!$A:$A,0))*N$38 -> 0.42507558 | O32: =O22+INDEX(Data_Prices!O:O,MATCH($G32,Data_Prices!$A:$A,0))*O$38 -> 0.42507558 | P32: =P22+INDEX(Data_Prices!P:P,MATCH($G32,Data_Prices!$A:$A,0))*P$38 -> 0.42507558 | Q32: =Q22+INDEX(Data_Prices!Q:Q,MATCH($G32,Data_Prices!$A:$A,0))*Q$38 -> 0.42507558 | R32: =R22+INDEX(Data_Prices!R:R,MATCH($G32,Data_Prices!$A:$A,0))*R$38 -> 0.42507558 | S32: =S22+INDEX(Data_Prices!S:S,MATCH($G32,Data_Prices!$A:$A,0))*S$38 -> 0.42507558 | T32: =T22+INDEX(Data_Prices!T:T,MATCH($G32,Data_Prices!$A:$A,0))*T$38 -> 0.42507558 | U32: =U22+INDEX(Data_Prices!U:U,MATCH($G32,Data_Prices!$A:$A,0))*U$38 -> 0.42507558 | V32: =V22+INDEX(Data_Prices!V:V,MATCH($G32,Data_Prices!$A:$A,0))*V$38 -> 0.42507558 | W32: =W22+INDEX(Data_Prices!W:W,MATCH($G32,Data_Prices!$A:$A,0))*W$38 -> 0.42507558 | X32: =X22+INDEX(Data_Prices!X:X,MATCH($G32,Data_Prices!$A:$A,0))*X$38 -> 0.42507558 | Y32: =Y22+INDEX(Data_Prices!Y:Y,MATCH($G32,Data_Prices!$A:$A,0))*Y$38 -> 0.42507558 | Z32: =Z22+INDEX(Data_Prices!Z:Z,MATCH($G32,Data_Prices!$A:$A,0))*Z$38 -> 0.42507558 | AA32: =AA22+INDEX(Data_Prices!AA:AA,MATCH($G32,Data_Prices!$A:$A,0))*AA$38 -> 0.42507558 | AB32: =AB22+INDEX(Data_Prices!AB:AB,MATCH($G32,Data_Prices!$A:$A,0))*AB$38 -> 0.42507558 | AC32: =AC22+INDEX(Data_Prices!AC:AC,MATCH($G32,Data_Prices!$A:$A,0))*AC$38 -> 0.42507558 | AD32: =AD22+INDEX(Data_Prices!AD:AD,MATCH($G32,Data_Prices!$A:$A,0))*AD$38 -> 0.42507558 | AE32: =AE22+INDEX(Data_Prices!AE:AE,MATCH($G32,Data_Prices!$A:$A,0))*AE$38 -> 0.42507558
B33: oop | C33: =$C$5 -> irn | D33: Other oil products | E33: $/bbl | F33: shp | G33: =Settings!$B$3&".mit.shp."&$B33&"."&Settings!$B$4&"."&$J$5 -> egy.mit.shp.oop.ind.1 | H33: =Settings!$B$3&".mit.shp."&$C$5&"."&$B33&".e."&$J$5 -> egy.mit.shp.irn.oop.e.1 | K33: =K23+INDEX(Data_Prices!K:K,MATCH($G33,Data_Prices!$A:$A,0))*K$38 -> 41.500338 | L33: =L23+INDEX(Data_Prices!L:L,MATCH($G33,Data_Prices!$A:$A,0))*L$38 -> 34.41537 | M33: =M23+INDEX(Data_Prices!M:M,MATCH($G33,Data_Prices!$A:$A,0))*M$38 -> 37.368961 | N33: =N23+INDEX(Data_Prices!N:N,MATCH($G33,Data_Prices!$A:$A,0))*N$38 -> 28.982761 | O33: =O23+INDEX(Data_Prices!O:O,MATCH($G33,Data_Prices!$A:$A,0))*O$38 -> 15 | P33: =P23+INDEX(Data_Prices!P:P,MATCH($G33,Data_Prices!$A:$A,0))*P$38 -> 24.25863 | Q33: =Q23+INDEX(Data_Prices!Q:Q,MATCH($G33,Data_Prices!$A:$A,0))*Q$38 -> 15 | R33: =R23+INDEX(Data_Prices!R:R,MATCH($G33,Data_Prices!$A:$A,0))*R$38 -> 15 | S33: =S23+INDEX(Data_Prices!S:S,MATCH($G33,Data_Prices!$A:$A,0))*S$38 -> 15 | T33: =T23+INDEX(Data_Prices!T:T,MATCH($G33,Data_Prices!$A:$A,0))*T$38 -> 15 | U33: =U23+INDEX(Data_Prices!U:U,MATCH($G33,Data_Prices!$A:$A,0))*U$38 -> 15 | V33: =V23+INDEX(Data_Prices!V:V,MATCH($G33,Data_Prices!$A:$A,0))*V$38 -> 15 | W33: =W23+INDEX(Data_Prices!W:W,MATCH($G33,Data_Prices!$A:$A,0))*W$38 -> 15 | X33: =X23+INDEX(Data_Prices!X:X,MATCH($G33,Data_Prices!$A:$A,0))*X$38 -> 15 | Y33: =Y23+INDEX(Data_Prices!Y:Y,MATCH($G33,Data_Prices!$A:$A,0))*Y$38 -> 15 | Z33: =Z23+INDEX(Data_Prices!Z:Z,MATCH($G33,Data_Prices!$A:$A,0))*Z$38 -> 15 | AA33: =AA23+INDEX(Data_Prices!AA:AA,MATCH($G33,Data_Prices!$A:$A,0))*AA$38 -> 15 | AB33: =AB23+INDEX(Data_Prices!AB:AB,MATCH($G33,Data_Prices!$A:$A,0))*AB$38 -> 15 | AC33: =AC23+INDEX(Data_Prices!AC:AC,MATCH($G33,Data_Prices!$A:$A,0))*AC$38 -> 15 | AD33: =AD23+INDEX(Data_Prices!AD:AD,MATCH($G33,Data_Prices!$A:$A,0))*AD$38 -> 15 | AE33: =AE23+INDEX(Data_Prices!AE:AE,MATCH($G33,Data_Prices!$A:$A,0))*AE$38 -> 15
B34: bio | C34: =$C$5 -> irn | D34: Biomass | E34: $/GJ | F34: shp | G34: =Settings!$B$3&".mit.shp."&$B34&"."&Settings!$B$4&"."&$J$5 -> egy.mit.shp.bio.ind.1 | H34: =Settings!$B$3&".mit.shp."&$C$5&"."&$B34&".e."&$J$5 -> egy.mit.shp.irn.bio.e.1 | K34: =K24+INDEX(Data_Prices!K:K,MATCH($G34,Data_Prices!$A:$A,0))*K$38 -> 15.334551 | L34: =L24+INDEX(Data_Prices!L:L,MATCH($G34,Data_Prices!$A:$A,0))*L$38 -> 14.199528 | M34: =M24+INDEX(Data_Prices!M:M,MATCH($G34,Data_Prices!$A:$A,0))*M$38 -> 13.840442 | N34: =N24+INDEX(Data_Prices!N:N,MATCH($G34,Data_Prices!$A:$A,0))*N$38 -> 13.567727 | O34: =O24+INDEX(Data_Prices!O:O,MATCH($G34,Data_Prices!$A:$A,0))*O$38 -> 13.567727 | P34: =P24+INDEX(Data_Prices!P:P,MATCH($G34,Data_Prices!$A:$A,0))*P$38 -> 13.567727 | Q34: =Q24+INDEX(Data_Prices!Q:Q,MATCH($G34,Data_Prices!$A:$A,0))*Q$38 -> 13.567727 | R34: =R24+INDEX(Data_Prices!R:R,MATCH($G34,Data_Prices!$A:$A,0))*R$38 -> 13.567727 | S34: =S24+INDEX(Data_Prices!S:S,MATCH($G34,Data_Prices!$A:$A,0))*S$38 -> 13.567727 | T34: =T24+INDEX(Data_Prices!T:T,MATCH($G34,Data_Prices!$A:$A,0))*T$38 -> 13.567727 | U34: =U24+INDEX(Data_Prices!U:U,MATCH($G34,Data_Prices!$A:$A,0))*U$38 -> 13.567727 | V34: =V24+INDEX(Data_Prices!V:V,MATCH($G34,Data_Prices!$A:$A,0))*V$38 -> 13.567727 | W34: =W24+INDEX(Data_Prices!W:W,MATCH($G34,Data_Prices!$A:$A,0))*W$38 -> 13.567727 | X34: =X24+INDEX(Data_Prices!X:X,MATCH($G34,Data_Prices!$A:$A,0))*X$38 -> 13.567727 | Y34: =Y24+INDEX(Data_Prices!Y:Y,MATCH($G34,Data_Prices!$A:$A,0))*Y$38 -> 13.567727 | Z34: =Z24+INDEX(Data_Prices!Z:Z,MATCH($G34,Data_Prices!$A:$A,0))*Z$38 -> 13.567727 | AA34: =AA24+INDEX(Data_Prices!AA:AA,MATCH($G34,Data_Prices!$A:$A,0))*AA$38 -> 13.567727 | AB34: =AB24+INDEX(Data_Prices!AB:AB,MATCH($G34,Data_Prices!$A:$A,0))*AB$38 -> 13.567727 | AC34: =AC24+INDEX(Data_Prices!AC:AC,MATCH($G34,Data_Prices!$A:$A,0))*AC$38 -> 13.567727 | AD34: =AD24+INDEX(Data_Prices!AD:AD,MATCH($G34,Data_Prices!$A:$A,0))*AD$38 -> 13.567727 | AE34: =AE24+INDEX(Data_Prices!AE:AE,MATCH($G34,Data_Prices!$A:$A,0))*AE$38 -> 13.567727
B35: ren | C35: =$C$5 -> irn | D35: Self-generated renewables | E35: $/kwh | F35: shp | G35: =Settings!$B$3&".mit.shp."&$B35&"."&Settings!$B$4&"."&$J$5 -> egy.mit.shp.ren.ind.1 | H35: =Settings!$B$3&".mit.shp."&$C$5&"."&$B35&".e."&$J$5 -> egy.mit.shp.irn.ren.e.1 | K35: =K25+INDEX(Data_Prices!K:K,MATCH($G35,Data_Prices!$A:$A,0))*K$38 -> 0 | L35: =L25+INDEX(Data_Prices!L:L,MATCH($G35,Data_Prices!$A:$A,0))*L$38 -> 0.14404499 | M35: =M25+INDEX(Data_Prices!M:M,MATCH($G35,Data_Prices!$A:$A,0))*M$38 -> 0.14102041 | N35: =N25+INDEX(Data_Prices!N:N,MATCH($G35,Data_Prices!$A:$A,0))*N$38 -> 0.13511636 | O35: =O25+INDEX(Data_Prices!O:O,MATCH($G35,Data_Prices!$A:$A,0))*O$38 -> 0.13098826 | P35: =P25+INDEX(Data_Prices!P:P,MATCH($G35,Data_Prices!$A:$A,0))*P$38 -> 0.12790842 | Q35: =Q25+INDEX(Data_Prices!Q:Q,MATCH($G35,Data_Prices!$A:$A,0))*Q$38 -> 0.12481431 | R35: =R25+INDEX(Data_Prices!R:R,MATCH($G35,Data_Prices!$A:$A,0))*R$38 -> 0.12146026 | S35: =S25+INDEX(Data_Prices!S:S,MATCH($G35,Data_Prices!$A:$A,0))*S$38 -> 0.11795074 | T35: =T25+INDEX(Data_Prices!T:T,MATCH($G35,Data_Prices!$A:$A,0))*T$38 -> 0.11419916 | U35: =U25+INDEX(Data_Prices!U:U,MATCH($G35,Data_Prices!$A:$A,0))*U$38 -> 0.1136651 | V35: =V25+INDEX(Data_Prices!V:V,MATCH($G35,Data_Prices!$A:$A,0))*V$38 -> 0.11301693 | W35: =W25+INDEX(Data_Prices!W:W,MATCH($G35,Data_Prices!$A:$A,0))*W$38 -> 0.11231407 | X35: =X25+INDEX(Data_Prices!X:X,MATCH($G35,Data_Prices!$A:$A,0))*X$38 -> 0.11142204 | Y35: =Y25+INDEX(Data_Prices!Y:Y,MATCH($G35,Data_Prices!$A:$A,0))*Y$38 -> 0.11043412 | Z35: =Z25+INDEX(Data_Prices!Z:Z,MATCH($G35,Data_Prices!$A:$A,0))*Z$38 -> 0.10948397 | AA35: =AA25+INDEX(Data_Prices!AA:AA,MATCH($G35,Data_Prices!$A:$A,0))*AA$38 -> 0.10839192 | AB35: =AB25+INDEX(Data_Prices!AB:AB,MATCH($G35,Data_Prices!$A:$A,0))*AB$38 -> 0.10735443 | AC35: =AC25+INDEX(Data_Prices!AC:AC,MATCH($G35,Data_Prices!$A:$A,0))*AC$38 -> 0.10516868 | AD35: =AD25+INDEX(Data_Prices!AD:AD,MATCH($G35,Data_Prices!$A:$A,0))*AD$38 -> 0.10305798 | AE35: =AE25+INDEX(Data_Prices!AE:AE,MATCH($G35,Data_Prices!$A:$A,0))*AE$38 -> 0.10093184
B36: Sector policy and macro drivers
B37: - | C37: =$C$5 -> irn | D37: Sector coverage factor of the new-policy wedge | E37: share | F37: tcf | G37: =Settings!$B$3&".mit.tcf."&$C$5&"."&$J$5 -> egy.mit.tcf.irn.1 | K37: =INDEX(Data_Prices!K:K,MATCH($G37,Data_Prices!$A:$A,0)) -> 0 | L37: =INDEX(Data_Prices!L:L,MATCH($G37,Data_Prices!$A:$A,0)) -> 0 | M37: =INDEX(Data_Prices!M:M,MATCH($G37,Data_Prices!$A:$A,0)) -> 0 | N37: =INDEX(Data_Prices!N:N,MATCH($G37,Data_Prices!$A:$A,0)) -> 0 | O37: =INDEX(Data_Prices!O:O,MATCH($G37,Data_Prices!$A:$A,0)) -> 0 | P37: =INDEX(Data_Prices!P:P,MATCH($G37,Data_Prices!$A:$A,0)) -> 0 | Q37: =INDEX(Data_Prices!Q:Q,MATCH($G37,Data_Prices!$A:$A,0)) -> 0 | R37: =INDEX(Data_Prices!R:R,MATCH($G37,Data_Prices!$A:$A,0)) -> 0 | S37: =INDEX(Data_Prices!S:S,MATCH($G37,Data_Prices!$A:$A,0)) -> 0 | T37: =INDEX(Data_Prices!T:T,MATCH($G37,Data_Prices!$A:$A,0)) -> 0 | U37: =INDEX(Data_Prices!U:U,MATCH($G37,Data_Prices!$A:$A,0)) -> 0 | V37: =INDEX(Data_Prices!V:V,MATCH($G37,Data_Prices!$A:$A,0)) -> 0 | W37: =INDEX(Data_Prices!W:W,MATCH($G37,Data_Prices!$A:$A,0)) -> 0 | X37: =INDEX(Data_Prices!X:X,MATCH($G37,Data_Prices!$A:$A,0)) -> 0 | Y37: =INDEX(Data_Prices!Y:Y,MATCH($G37,Data_Prices!$A:$A,0)) -> 0 | Z37: =INDEX(Data_Prices!Z:Z,MATCH($G37,Data_Prices!$A:$A,0)) -> 0 | AA37: =INDEX(Data_Prices!AA:AA,MATCH($G37,Data_Prices!$A:$A,0)) -> 0 | AB37: =INDEX(Data_Prices!AB:AB,MATCH($G37,Data_Prices!$A:$A,0)) -> 0 | AC37: =INDEX(Data_Prices!AC:AC,MATCH($G37,Data_Prices!$A:$A,0)) -> 0 | AD37: =INDEX(Data_Prices!AD:AD,MATCH($G37,Data_Prices!$A:$A,0)) -> 0 | AE37: =INDEX(Data_Prices!AE:AE,MATCH($G37,Data_Prices!$A:$A,0)) -> 0
B38: - | C38: =$C$5 -> irn | D38: Share of shadow price acting on efficiency | E38: share | F38: ssc | G38: =Settings!$B$3&".mit.ssc."&$C$5&"."&$J$5 -> egy.mit.ssc.irn.1 | K38: =INDEX(Data_Prices!K:K,MATCH($G38,Data_Prices!$A:$A,0)) -> 0 | L38: =INDEX(Data_Prices!L:L,MATCH($G38,Data_Prices!$A:$A,0)) -> 0 | M38: =INDEX(Data_Prices!M:M,MATCH($G38,Data_Prices!$A:$A,0)) -> 0 | N38: =INDEX(Data_Prices!N:N,MATCH($G38,Data_Prices!$A:$A,0)) -> 0 | O38: =INDEX(Data_Prices!O:O,MATCH($G38,Data_Prices!$A:$A,0)) -> 0 | P38: =INDEX(Data_Prices!P:P,MATCH($G38,Data_Prices!$A:$A,0)) -> 0 | Q38: =INDEX(Data_Prices!Q:Q,MATCH($G38,Data_Prices!$A:$A,0)) -> 0 | R38: =INDEX(Data_Prices!R:R,MATCH($G38,Data_Prices!$A:$A,0)) -> 0 | S38: =INDEX(Data_Prices!S:S,MATCH($G38,Data_Prices!$A:$A,0)) -> 0 | T38: =INDEX(Data_Prices!T:T,MATCH($G38,Data_Prices!$A:$A,0)) -> 0 | U38: =INDEX(Data_Prices!U:U,MATCH($G38,Data_Prices!$A:$A,0)) -> 0 | V38: =INDEX(Data_Prices!V:V,MATCH($G38,Data_Prices!$A:$A,0)) -> 0 | W38: =INDEX(Data_Prices!W:W,MATCH($G38,Data_Prices!$A:$A,0)) -> 0 | X38: =INDEX(Data_Prices!X:X,MATCH($G38,Data_Prices!$A:$A,0)) -> 0 | Y38: =INDEX(Data_Prices!Y:Y,MATCH($G38,Data_Prices!$A:$A,0)) -> 0 | Z38: =INDEX(Data_Prices!Z:Z,MATCH($G38,Data_Prices!$A:$A,0)) -> 0 | AA38: =INDEX(Data_Prices!AA:AA,MATCH($G38,Data_Prices!$A:$A,0)) -> 0 | AB38: =INDEX(Data_Prices!AB:AB,MATCH($G38,Data_Prices!$A:$A,0)) -> 0 | AC38: =INDEX(Data_Prices!AC:AC,MATCH($G38,Data_Prices!$A:$A,0)) -> 0 | AD38: =INDEX(Data_Prices!AD:AD,MATCH($G38,Data_Prices!$A:$A,0)) -> 0 | AE38: =INDEX(Data_Prices!AE:AE,MATCH($G38,Data_Prices!$A:$A,0)) -> 0
B39: - | C39: =$C$5 -> irn | D39: Post-policy real GDP growth | E39: % | F39: g | G39: =Settings!$B$3&".mit.gdp.pos.pct."&$J$5 -> egy.mit.gdp.pos.pct.1 | K39: =INDEX(Data_Macro!K:K,MATCH($G39,Data_Macro!$A:$A,0)) -> 0 | L39: =INDEX(Data_Macro!L:L,MATCH($G39,Data_Macro!$A:$A,0)) -> 0.06651345 | M39: =INDEX(Data_Macro!M:M,MATCH($G39,Data_Macro!$A:$A,0)) -> 0.03760281 | N39: =INDEX(Data_Macro!N:N,MATCH($G39,Data_Macro!$A:$A,0)) -> 0.02398801 | O39: =INDEX(Data_Macro!O:O,MATCH($G39,Data_Macro!$A:$A,0)) -> 0.04392387 | P39: =INDEX(Data_Macro!P:P,MATCH($G39,Data_Macro!$A:$A,0)) -> 0.04239706 | Q39: =INDEX(Data_Macro!Q:Q,MATCH($G39,Data_Macro!$A:$A,0)) -> 0.04829218 | R39: =INDEX(Data_Macro!R:R,MATCH($G39,Data_Macro!$A:$A,0)) -> 0.05535316 | S39: =INDEX(Data_Macro!S:S,MATCH($G39,Data_Macro!$A:$A,0)) -> 0.05226606 | T39: =INDEX(Data_Macro!T:T,MATCH($G39,Data_Macro!$A:$A,0)) -> 0.04841877 | U39: =INDEX(Data_Macro!U:U,MATCH($G39,Data_Macro!$A:$A,0)) -> 0.04788736 | V39: =INDEX(Data_Macro!V:V,MATCH($G39,Data_Macro!$A:$A,0)) -> 0.04735595 | W39: =INDEX(Data_Macro!W:W,MATCH($G39,Data_Macro!$A:$A,0)) -> 0.04682454 | X39: =INDEX(Data_Macro!X:X,MATCH($G39,Data_Macro!$A:$A,0)) -> 0.04629313 | Y39: =INDEX(Data_Macro!Y:Y,MATCH($G39,Data_Macro!$A:$A,0)) -> 0.04576172 | Z39: =INDEX(Data_Macro!Z:Z,MATCH($G39,Data_Macro!$A:$A,0)) -> 0.04523031 | AA39: =INDEX(Data_Macro!AA:AA,MATCH($G39,Data_Macro!$A:$A,0)) -> 0.0446989 | AB39: =INDEX(Data_Macro!AB:AB,MATCH($G39,Data_Macro!$A:$A,0)) -> 0.04416749 | AC39: =INDEX(Data_Macro!AC:AC,MATCH($G39,Data_Macro!$A:$A,0)) -> 0.04363608 | AD39: =INDEX(Data_Macro!AD:AD,MATCH($G39,Data_Macro!$A:$A,0)) -> 0.04310467 | AE39: =INDEX(Data_Macro!AE:AE,MATCH($G39,Data_Macro!$A:$A,0)) -> 0.04257326
B40: - | C40: =$C$5 -> irn | D40: Income-elasticity discount factor | E40: ratio | F40: delta | G40: =Settings!$B$3&".mit.inc.ela.adj."&$J$5 -> egy.mit.inc.ela.adj.1 | K40: =INDEX(Data_Macro!K:K,MATCH($G40,Data_Macro!$A:$A,0)) -> 0 | L40: =INDEX(Data_Macro!L:L,MATCH($G40,Data_Macro!$A:$A,0)) -> 1.0271517 | M40: =INDEX(Data_Macro!M:M,MATCH($G40,Data_Macro!$A:$A,0)) -> 1.0271517 | N40: =INDEX(Data_Macro!N:N,MATCH($G40,Data_Macro!$A:$A,0)) -> 1.0205698 | O40: =INDEX(Data_Macro!O:O,MATCH($G40,Data_Macro!$A:$A,0)) -> 1.0173344 | P40: =INDEX(Data_Macro!P:P,MATCH($G40,Data_Macro!$A:$A,0)) -> 1.0076683 | Q40: =INDEX(Data_Macro!Q:Q,MATCH($G40,Data_Macro!$A:$A,0)) -> 1.0007443 | R40: =INDEX(Data_Macro!R:R,MATCH($G40,Data_Macro!$A:$A,0)) -> 0.99188649 | S40: =INDEX(Data_Macro!S:S,MATCH($G40,Data_Macro!$A:$A,0)) -> 0.9806554 | T40: =INDEX(Data_Macro!T:T,MATCH($G40,Data_Macro!$A:$A,0)) -> 0.9702094 | U40: =INDEX(Data_Macro!U:U,MATCH($G40,Data_Macro!$A:$A,0)) -> 0.96419266 | V40: =INDEX(Data_Macro!V:V,MATCH($G40,Data_Macro!$A:$A,0)) -> 0.96161287 | W40: =INDEX(Data_Macro!W:W,MATCH($G40,Data_Macro!$A:$A,0)) -> 0.95919845 | X40: =INDEX(Data_Macro!X:X,MATCH($G40,Data_Macro!$A:$A,0)) -> 0.95695125 | Y40: =INDEX(Data_Macro!Y:Y,MATCH($G40,Data_Macro!$A:$A,0)) -> 0.95487298 | Z40: =INDEX(Data_Macro!Z:Z,MATCH($G40,Data_Macro!$A:$A,0)) -> 0.95296514 | AA40: =INDEX(Data_Macro!AA:AA,MATCH($G40,Data_Macro!$A:$A,0)) -> 0.9512291 | AB40: =INDEX(Data_Macro!AB:AB,MATCH($G40,Data_Macro!$A:$A,0)) -> 0.94966609 | AC40: =INDEX(Data_Macro!AC:AC,MATCH($G40,Data_Macro!$A:$A,0)) -> 0.94827716 | AD40: =INDEX(Data_Macro!AD:AD,MATCH($G40,Data_Macro!$A:$A,0)) -> 0.94706328 | AE40: =INDEX(Data_Macro!AE:AE,MATCH($G40,Data_Macro!$A:$A,0)) -> 0.94602527
B41: - | C41: =$C$5 -> irn | D41: Exogenous shock on energy consumption | E41: ratio | F41: psi | G41: =Settings!$B$3&".mit.shock."&$J$5 -> egy.mit.shock.1 | K41: =INDEX(Data_Macro!K:K,MATCH($G41,Data_Macro!$A:$A,0)) -> 0 | L41: =INDEX(Data_Macro!L:L,MATCH($G41,Data_Macro!$A:$A,0)) -> 0 | M41: =INDEX(Data_Macro!M:M,MATCH($G41,Data_Macro!$A:$A,0)) -> -0.20813308 | N41: =INDEX(Data_Macro!N:N,MATCH($G41,Data_Macro!$A:$A,0)) -> 0.092371429 | O41: =INDEX(Data_Macro!O:O,MATCH($G41,Data_Macro!$A:$A,0)) -> 0 | P41: =INDEX(Data_Macro!P:P,MATCH($G41,Data_Macro!$A:$A,0)) -> 0 | Q41: =INDEX(Data_Macro!Q:Q,MATCH($G41,Data_Macro!$A:$A,0)) -> 0 | R41: =INDEX(Data_Macro!R:R,MATCH($G41,Data_Macro!$A:$A,0)) -> 0 | S41: =INDEX(Data_Macro!S:S,MATCH($G41,Data_Macro!$A:$A,0)) -> 0 | T41: =INDEX(Data_Macro!T:T,MATCH($G41,Data_Macro!$A:$A,0)) -> 0 | U41: =INDEX(Data_Macro!U:U,MATCH($G41,Data_Macro!$A:$A,0)) -> 0 | V41: =INDEX(Data_Macro!V:V,MATCH($G41,Data_Macro!$A:$A,0)) -> 0 | W41: =INDEX(Data_Macro!W:W,MATCH($G41,Data_Macro!$A:$A,0)) -> 0 | X41: =INDEX(Data_Macro!X:X,MATCH($G41,Data_Macro!$A:$A,0)) -> 0 | Y41: =INDEX(Data_Macro!Y:Y,MATCH($G41,Data_Macro!$A:$A,0)) -> 0 | Z41: =INDEX(Data_Macro!Z:Z,MATCH($G41,Data_Macro!$A:$A,0)) -> 0 | AA41: =INDEX(Data_Macro!AA:AA,MATCH($G41,Data_Macro!$A:$A,0)) -> 0 | AB41: =INDEX(Data_Macro!AB:AB,MATCH($G41,Data_Macro!$A:$A,0)) -> 0 | AC41: =INDEX(Data_Macro!AC:AC,MATCH($G41,Data_Macro!$A:$A,0)) -> 0 | AD41: =INDEX(Data_Macro!AD:AD,MATCH($G41,Data_Macro!$A:$A,0)) -> 0 | AE41: =INDEX(Data_Macro!AE:AE,MATCH($G41,Data_Macro!$A:$A,0)) -> 0
B42: Kernel parameters (looked up from Data_Elast; column = Settings elasticity group)
B43: Fuel | C43: Sector | D43: Description | E43: Income el. (eY) | F43: Usage el. (eU) | G43: Efficiency el. (eF) | H43: AEEI (a) | I43: Add. efficiency (a+) | J43: Elasticity fuel group
B44: coa | C44: =$C$5 -> irn | D44: Parameters: Coal | E44: =INDEX(Data_Elast!$D:$G,MATCH("el_inc_"&INDEX(Data_Elast!$J:$J,MATCH($B44,Data_Elast!$I:$I,0)),Data_Elast!$A:$A,0),MATCH(Settings!$B$5,Data_Elast!$D$1:$G$1,0)) -> 0.5 | F44: =INDEX(Data_Elast!$D:$G,MATCH("el_dem_"&INDEX(Data_Elast!$J:$J,MATCH($B44,Data_Elast!$I:$I,0)),Data_Elast!$A:$A,0),MATCH(Settings!$B$5,Data_Elast!$D$1:$G$1,0)) -> -0.3 | G44: =INDEX(Data_Elast!$D:$G,MATCH("el_eff_"&INDEX(Data_Elast!$J:$J,MATCH($B44,Data_Elast!$I:$I,0)),Data_Elast!$A:$A,0),MATCH(Settings!$B$5,Data_Elast!$D$1:$G$1,0)) -> -0.4 | H44: =INDEX(Data_Elast!$D:$G,MATCH("eff_imp_"&INDEX(Data_Elast!$K:$K,MATCH($B44,Data_Elast!$I:$I,0)),Data_Elast!$A:$A,0),MATCH(Settings!$B$5,Data_Elast!$D$1:$G$1,0)) -> 0.005 | I44: =Settings!$B$7 -> 0 | J44: =INDEX(Data_Elast!$J:$J,MATCH($B44,Data_Elast!$I:$I,0)) -> coa
B45: nga | C45: =$C$5 -> irn | D45: Parameters: Natural gas | E45: =INDEX(Data_Elast!$D:$G,MATCH("el_inc_"&INDEX(Data_Elast!$J:$J,MATCH($B45,Data_Elast!$I:$I,0)),Data_Elast!$A:$A,0),MATCH(Settings!$B$5,Data_Elast!$D$1:$G$1,0)) -> 1 | F45: =INDEX(Data_Elast!$D:$G,MATCH("el_dem_"&INDEX(Data_Elast!$J:$J,MATCH($B45,Data_Elast!$I:$I,0)),Data_Elast!$A:$A,0),MATCH(Settings!$B$5,Data_Elast!$D$1:$G$1,0)) -> -0.5 | G45: =INDEX(Data_Elast!$D:$G,MATCH("el_eff_"&INDEX(Data_Elast!$J:$J,MATCH($B45,Data_Elast!$I:$I,0)),Data_Elast!$A:$A,0),MATCH(Settings!$B$5,Data_Elast!$D$1:$G$1,0)) -> -0.5 | H45: =INDEX(Data_Elast!$D:$G,MATCH("eff_imp_"&INDEX(Data_Elast!$K:$K,MATCH($B45,Data_Elast!$I:$I,0)),Data_Elast!$A:$A,0),MATCH(Settings!$B$5,Data_Elast!$D$1:$G$1,0)) -> 0.01 | I45: =Settings!$B$7 -> 0 | J45: =INDEX(Data_Elast!$J:$J,MATCH($B45,Data_Elast!$I:$I,0)) -> nga
B46: gso | C46: =$C$5 -> irn | D46: Parameters: Gasoline | E46: =INDEX(Data_Elast!$D:$G,MATCH("el_inc_"&INDEX(Data_Elast!$J:$J,MATCH($B46,Data_Elast!$I:$I,0)),Data_Elast!$A:$A,0),MATCH(Settings!$B$5,Data_Elast!$D$1:$G$1,0)) -> 0.5 | F46: =INDEX(Data_Elast!$D:$G,MATCH("el_dem_"&INDEX(Data_Elast!$J:$J,MATCH($B46,Data_Elast!$I:$I,0)),Data_Elast!$A:$A,0),MATCH(Settings!$B$5,Data_Elast!$D$1:$G$1,0)) -> -0.4 | G46: =INDEX(Data_Elast!$D:$G,MATCH("el_eff_"&INDEX(Data_Elast!$J:$J,MATCH($B46,Data_Elast!$I:$I,0)),Data_Elast!$A:$A,0),MATCH(Settings!$B$5,Data_Elast!$D$1:$G$1,0)) -> -0.7 | H46: =INDEX(Data_Elast!$D:$G,MATCH("eff_imp_"&INDEX(Data_Elast!$K:$K,MATCH($B46,Data_Elast!$I:$I,0)),Data_Elast!$A:$A,0),MATCH(Settings!$B$5,Data_Elast!$D$1:$G$1,0)) -> 0.005 | I46: =Settings!$B$7 -> 0 | J46: =INDEX(Data_Elast!$J:$J,MATCH($B46,Data_Elast!$I:$I,0)) -> gso
B47: die | C47: =$C$5 -> irn | D47: Parameters: Diesel | E47: =INDEX(Data_Elast!$D:$G,MATCH("el_inc_"&INDEX(Data_Elast!$J:$J,MATCH($B47,Data_Elast!$I:$I,0)),Data_Elast!$A:$A,0),MATCH(Settings!$B$5,Data_Elast!$D$1:$G$1,0)) -> 0.5 | F47: =INDEX(Data_Elast!$D:$G,MATCH("el_dem_"&INDEX(Data_Elast!$J:$J,MATCH($B47,Data_Elast!$I:$I,0)),Data_Elast!$A:$A,0),MATCH(Settings!$B$5,Data_Elast!$D$1:$G$1,0)) -> -0.7 | G47: =INDEX(Data_Elast!$D:$G,MATCH("el_eff_"&INDEX(Data_Elast!$J:$J,MATCH($B47,Data_Elast!$I:$I,0)),Data_Elast!$A:$A,0),MATCH(Settings!$B$5,Data_Elast!$D$1:$G$1,0)) -> -1.2 | H47: =INDEX(Data_Elast!$D:$G,MATCH("eff_imp_"&INDEX(Data_Elast!$K:$K,MATCH($B47,Data_Elast!$I:$I,0)),Data_Elast!$A:$A,0),MATCH(Settings!$B$5,Data_Elast!$D$1:$G$1,0)) -> 0.005 | I47: =Settings!$B$7 -> 0 | J47: =INDEX(Data_Elast!$J:$J,MATCH($B47,Data_Elast!$I:$I,0)) -> die
B48: lpg | C48: =$C$5 -> irn | D48: Parameters: LPG | E48: =INDEX(Data_Elast!$D:$G,MATCH("el_inc_"&INDEX(Data_Elast!$J:$J,MATCH($B48,Data_Elast!$I:$I,0)),Data_Elast!$A:$A,0),MATCH(Settings!$B$5,Data_Elast!$D$1:$G$1,0)) -> 0.8 | F48: =INDEX(Data_Elast!$D:$G,MATCH("el_dem_"&INDEX(Data_Elast!$J:$J,MATCH($B48,Data_Elast!$I:$I,0)),Data_Elast!$A:$A,0),MATCH(Settings!$B$5,Data_Elast!$D$1:$G$1,0)) -> -0.4 | G48: =INDEX(Data_Elast!$D:$G,MATCH("el_eff_"&INDEX(Data_Elast!$J:$J,MATCH($B48,Data_Elast!$I:$I,0)),Data_Elast!$A:$A,0),MATCH(Settings!$B$5,Data_Elast!$D$1:$G$1,0)) -> -0.4 | H48: =INDEX(Data_Elast!$D:$G,MATCH("eff_imp_"&INDEX(Data_Elast!$K:$K,MATCH($B48,Data_Elast!$I:$I,0)),Data_Elast!$A:$A,0),MATCH(Settings!$B$5,Data_Elast!$D$1:$G$1,0)) -> 0.005 | I48: =Settings!$B$7 -> 0 | J48: =INDEX(Data_Elast!$J:$J,MATCH($B48,Data_Elast!$I:$I,0)) -> oil
B49: ker | C49: =$C$5 -> irn | D49: Parameters: Kerosene | E49: =INDEX(Data_Elast!$D:$G,MATCH("el_inc_"&INDEX(Data_Elast!$J:$J,MATCH($B49,Data_Elast!$I:$I,0)),Data_Elast!$A:$A,0),MATCH(Settings!$B$5,Data_Elast!$D$1:$G$1,0)) -> 0.8 | F49: =INDEX(Data_Elast!$D:$G,MATCH("el_dem_"&INDEX(Data_Elast!$J:$J,MATCH($B49,Data_Elast!$I:$I,0)),Data_Elast!$A:$A,0),MATCH(Settings!$B$5,Data_Elast!$D$1:$G$1,0)) -> -0.4 | G49: =INDEX(Data_Elast!$D:$G,MATCH("el_eff_"&INDEX(Data_Elast!$J:$J,MATCH($B49,Data_Elast!$I:$I,0)),Data_Elast!$A:$A,0),MATCH(Settings!$B$5,Data_Elast!$D$1:$G$1,0)) -> -0.4 | H49: =INDEX(Data_Elast!$D:$G,MATCH("eff_imp_"&INDEX(Data_Elast!$K:$K,MATCH($B49,Data_Elast!$I:$I,0)),Data_Elast!$A:$A,0),MATCH(Settings!$B$5,Data_Elast!$D$1:$G$1,0)) -> 0.005 | I49: =Settings!$B$7 -> 0 | J49: =INDEX(Data_Elast!$J:$J,MATCH($B49,Data_Elast!$I:$I,0)) -> oil
B50: oop | C50: =$C$5 -> irn | D50: Parameters: Other oil products | E50: =INDEX(Data_Elast!$D:$G,MATCH("el_inc_"&INDEX(Data_Elast!$J:$J,MATCH($B50,Data_Elast!$I:$I,0)),Data_Elast!$A:$A,0),MATCH(Settings!$B$5,Data_Elast!$D$1:$G$1,0)) -> 0.8 | F50: =INDEX(Data_Elast!$D:$G,MATCH("el_dem_"&INDEX(Data_Elast!$J:$J,MATCH($B50,Data_Elast!$I:$I,0)),Data_Elast!$A:$A,0),MATCH(Settings!$B$5,Data_Elast!$D$1:$G$1,0)) -> -0.4 | G50: =INDEX(Data_Elast!$D:$G,MATCH("el_eff_"&INDEX(Data_Elast!$J:$J,MATCH($B50,Data_Elast!$I:$I,0)),Data_Elast!$A:$A,0),MATCH(Settings!$B$5,Data_Elast!$D$1:$G$1,0)) -> -0.4 | H50: =INDEX(Data_Elast!$D:$G,MATCH("eff_imp_"&INDEX(Data_Elast!$K:$K,MATCH($B50,Data_Elast!$I:$I,0)),Data_Elast!$A:$A,0),MATCH(Settings!$B$5,Data_Elast!$D$1:$G$1,0)) -> 0.005 | I50: =Settings!$B$7 -> 0 | J50: =INDEX(Data_Elast!$J:$J,MATCH($B50,Data_Elast!$I:$I,0)) -> oil
B51: bio | C51: =$C$5 -> irn | D51: Parameters: Biomass | E51: =INDEX(Data_Elast!$D:$G,MATCH("el_inc_"&INDEX(Data_Elast!$J:$J,MATCH($B51,Data_Elast!$I:$I,0)),Data_Elast!$A:$A,0),MATCH(Settings!$B$5,Data_Elast!$D$1:$G$1,0)) -> 0.1 | F51: =INDEX(Data_Elast!$D:$G,MATCH("el_dem_"&INDEX(Data_Elast!$J:$J,MATCH($B51,Data_Elast!$I:$I,0)),Data_Elast!$A:$A,0),MATCH(Settings!$B$5,Data_Elast!$D$1:$G$1,0)) -> -0.3 | G51: =INDEX(Data_Elast!$D:$G,MATCH("el_eff_"&INDEX(Data_Elast!$J:$J,MATCH($B51,Data_Elast!$I:$I,0)),Data_Elast!$A:$A,0),MATCH(Settings!$B$5,Data_Elast!$D$1:$G$1,0)) -> -0.2 | H51: =INDEX(Data_Elast!$D:$G,MATCH("eff_imp_"&INDEX(Data_Elast!$K:$K,MATCH($B51,Data_Elast!$I:$I,0)),Data_Elast!$A:$A,0),MATCH(Settings!$B$5,Data_Elast!$D$1:$G$1,0)) -> 0.005 | I51: =Settings!$B$7 -> 0 | J51: =INDEX(Data_Elast!$J:$J,MATCH($B51,Data_Elast!$I:$I,0)) -> bio
B52: ren | C52: =$C$5 -> irn | D52: Parameters: Self-generated renewables | E52: =INDEX(Data_Elast!$D:$G,MATCH("el_inc_"&INDEX(Data_Elast!$J:$J,MATCH($B52,Data_Elast!$I:$I,0)),Data_Elast!$A:$A,0),MATCH(Settings!$B$5,Data_Elast!$D$1:$G$1,0)) -> 0.8 | F52: =INDEX(Data_Elast!$D:$G,MATCH("el_dem_"&INDEX(Data_Elast!$J:$J,MATCH($B52,Data_Elast!$I:$I,0)),Data_Elast!$A:$A,0),MATCH(Settings!$B$5,Data_Elast!$D$1:$G$1,0)) -> -0.5 | G52: =INDEX(Data_Elast!$D:$G,MATCH("el_eff_"&INDEX(Data_Elast!$J:$J,MATCH($B52,Data_Elast!$I:$I,0)),Data_Elast!$A:$A,0),MATCH(Settings!$B$5,Data_Elast!$D$1:$G$1,0)) -> -0.4 | H52: =INDEX(Data_Elast!$D:$G,MATCH("eff_imp_"&INDEX(Data_Elast!$K:$K,MATCH($B52,Data_Elast!$I:$I,0)),Data_Elast!$A:$A,0),MATCH(Settings!$B$5,Data_Elast!$D$1:$G$1,0)) -> 0.005 | I52: =Settings!$B$7 -> 0 | J52: =INDEX(Data_Elast!$J:$J,MATCH($B52,Data_Elast!$I:$I,0)) -> ren
B53: Energy use: base year from Data_Energy, later years from the kernel (= CPAT ener rows)
B54: coa | C54: =$C$5 -> irn | D54: Coal | E54: ktoe | F54: ener | G54: =Settings!$B$3&".mit.enc."&$B54 -> egy.mit.enc.coa | H54: =Settings!$B$3&".mit.ener."&$C$5&"."&$B54&".e."&$J$5 -> egy.mit.ener.irn.coa.e.1 | L54: =INDEX(Data_Energy!$D$3:$U$22,MATCH($B54,Data_Energy!$C$3:$C$22,0),MATCH($C54,Data_Energy!$D$2:$U$2,0)) -> 232.65735 | M54: =L54*(1+M$39)^($E44*M$40)*(1+M$41)*IF(L17<=0,1,M17/L17)^$F44*(IF(L27<=0,1,M27/L27)^$G44/(1+$H44+$I44))^(1+$F44) -> 189.45266 | N54: =M54*(1+N$39)^($E44*N$40)*(1+N$41)*IF(M17<=0,1,N17/M17)^$F44*(IF(M27<=0,1,N27/M27)^$G44/(1+$H44+$I44))^(1+$F44) -> 217.72884 | O54: =N54*(1+O$39)^($E44*O$40)*(1+O$41)*IF(N17<=0,1,O17/N17)^$F44*(IF(N27<=0,1,O27/N27)^$G44/(1+$H44+$I44))^(1+$F44) -> 237.89793 | P54: =O54*(1+P$39)^($E44*P$40)*(1+P$41)*IF(O17<=0,1,P17/O17)^$F44*(IF(O27<=0,1,P27/O27)^$G44/(1+$H44+$I44))^(1+$F44) -> 232.65007 | Q54: =P54*(1+Q$39)^($E44*Q$40)*(1+Q$41)*IF(P17<=0,1,Q17/P17)^$F44*(IF(P27<=0,1,Q27/P27)^$G44/(1+$H44+$I44))^(1+$F44) -> 235.34294 | R54: =Q54*(1+R$39)^($E44*R$40)*(1+R$41)*IF(Q17<=0,1,R17/Q17)^$F44*(IF(Q27<=0,1,R27/Q27)^$G44/(1+$H44+$I44))^(1+$F44) -> 241.85374 | S54: =R54*(1+S$39)^($E44*S$40)*(1+S$41)*IF(R17<=0,1,S17/R17)^$F44*(IF(R27<=0,1,S27/R27)^$G44/(1+$H44+$I44))^(1+$F44) -> 248.19369 | T54: =S54*(1+T$39)^($E44*T$40)*(1+T$41)*IF(S17<=0,1,T17/S17)^$F44*(IF(S27<=0,1,T27/S27)^$G44/(1+$H44+$I44))^(1+$F44) -> 254.2678 | ... AE54: =AD54*(1+AE$39)^($E44*AE$40)*(1+AE$41)*IF(AD17<=0,1,AE17/AD17)^$F44*(IF(AD27<=0,1,AE27/AD27)^$G44/(1+$H44+$I44))^(1+$F44) -> 310.04019
B55: nga | C55: =$C$5 -> irn | D55: Natural gas | E55: ktoe | F55: ener | G55: =Settings!$B$3&".mit.enc."&$B55 -> egy.mit.enc.nga | H55: =Settings!$B$3&".mit.ener."&$C$5&"."&$B55&".e."&$J$5 -> egy.mit.ener.irn.nga.e.1 | L55: =INDEX(Data_Energy!$D$3:$U$22,MATCH($B55,Data_Energy!$C$3:$C$22,0),MATCH($C55,Data_Energy!$D$2:$U$2,0)) -> 1669.0567 | M55: =L55*(1+M$39)^($E45*M$40)*(1+M$41)*IF(L18<=0,1,M18/L18)^$F45*(IF(L28<=0,1,M28/L28)^$G45/(1+$H45+$I45))^(1+$F45) -> 1431.7775 | N55: =M55*(1+N$39)^($E45*N$40)*(1+N$41)*IF(M18<=0,1,N18/M18)^$F45*(IF(M28<=0,1,N28/M28)^$G45/(1+$H45+$I45))^(1+$F45) -> 1603.1181 | O55: =N55*(1+O$39)^($E45*O$40)*(1+O$41)*IF(N18<=0,1,O18/N18)^$F45*(IF(N28<=0,1,O28/N28)^$G45/(1+$H45+$I45))^(1+$F45) -> 1666.4691 | P55: =O55*(1+P$39)^($E45*P$40)*(1+P$41)*IF(O18<=0,1,P18/O18)^$F45*(IF(O28<=0,1,P28/O28)^$G45/(1+$H45+$I45))^(1+$F45) -> 1729.052 | Q55: =P55*(1+Q$39)^($E45*Q$40)*(1+Q$41)*IF(P18<=0,1,Q18/P18)^$F45*(IF(P28<=0,1,Q28/P28)^$G45/(1+$H45+$I45))^(1+$F45) -> 1803.6196 | R55: =Q55*(1+R$39)^($E45*R$40)*(1+R$41)*IF(Q18<=0,1,R18/Q18)^$F45*(IF(Q28<=0,1,R28/Q28)^$G45/(1+$H45+$I45))^(1+$F45) -> 1893.1814 | S55: =R55*(1+S$39)^($E45*S$40)*(1+S$41)*IF(R18<=0,1,S18/R18)^$F45*(IF(R28<=0,1,S28/R28)^$G45/(1+$H45+$I45))^(1+$F45) -> 1980.2914 | T55: =S55*(1+T$39)^($E45*T$40)*(1+T$41)*IF(S18<=0,1,T18/S18)^$F45*(IF(S28<=0,1,T28/S28)^$G45/(1+$H45+$I45))^(1+$F45) -> 2062.9631 | ... AE55: =AD55*(1+AE$39)^($E45*AE$40)*(1+AE$41)*IF(AD18<=0,1,AE18/AD18)^$F45*(IF(AD28<=0,1,AE28/AD28)^$G45/(1+$H45+$I45))^(1+$F45) -> 3106.9586
B56: gso | C56: =$C$5 -> irn | D56: Gasoline | E56: ktoe | F56: ener | G56: =Settings!$B$3&".mit.enc."&$B56 -> egy.mit.enc.gso | H56: =Settings!$B$3&".mit.ener."&$C$5&"."&$B56&".e."&$J$5 -> egy.mit.ener.irn.gso.e.1 | L56: =INDEX(Data_Energy!$D$3:$U$22,MATCH($B56,Data_Energy!$C$3:$C$22,0),MATCH($C56,Data_Energy!$D$2:$U$2,0)) -> 0 | M56: =L56*(1+M$39)^($E46*M$40)*(1+M$41)*IF(L19<=0,1,M19/L19)^$F46*(IF(L29<=0,1,M29/L29)^$G46/(1+$H46+$I46))^(1+$F46) -> 0 | N56: =M56*(1+N$39)^($E46*N$40)*(1+N$41)*IF(M19<=0,1,N19/M19)^$F46*(IF(M29<=0,1,N29/M29)^$G46/(1+$H46+$I46))^(1+$F46) -> 0 | O56: =N56*(1+O$39)^($E46*O$40)*(1+O$41)*IF(N19<=0,1,O19/N19)^$F46*(IF(N29<=0,1,O29/N29)^$G46/(1+$H46+$I46))^(1+$F46) -> 0 | P56: =O56*(1+P$39)^($E46*P$40)*(1+P$41)*IF(O19<=0,1,P19/O19)^$F46*(IF(O29<=0,1,P29/O29)^$G46/(1+$H46+$I46))^(1+$F46) -> 0 | Q56: =P56*(1+Q$39)^($E46*Q$40)*(1+Q$41)*IF(P19<=0,1,Q19/P19)^$F46*(IF(P29<=0,1,Q29/P29)^$G46/(1+$H46+$I46))^(1+$F46) -> 0 | R56: =Q56*(1+R$39)^($E46*R$40)*(1+R$41)*IF(Q19<=0,1,R19/Q19)^$F46*(IF(Q29<=0,1,R29/Q29)^$G46/(1+$H46+$I46))^(1+$F46) -> 0 | S56: =R56*(1+S$39)^($E46*S$40)*(1+S$41)*IF(R19<=0,1,S19/R19)^$F46*(IF(R29<=0,1,S29/R29)^$G46/(1+$H46+$I46))^(1+$F46) -> 0 | T56: =S56*(1+T$39)^($E46*T$40)*(1+T$41)*IF(S19<=0,1,T19/S19)^$F46*(IF(S29<=0,1,T29/S29)^$G46/(1+$H46+$I46))^(1+$F46) -> 0 | ... AE56: =AD56*(1+AE$39)^($E46*AE$40)*(1+AE$41)*IF(AD19<=0,1,AE19/AD19)^$F46*(IF(AD29<=0,1,AE29/AD29)^$G46/(1+$H46+$I46))^(1+$F46) -> 0
B57: die | C57: =$C$5 -> irn | D57: Diesel | E57: ktoe | F57: ener | G57: =Settings!$B$3&".mit.enc."&$B57 -> egy.mit.enc.die | H57: =Settings!$B$3&".mit.ener."&$C$5&"."&$B57&".e."&$J$5 -> egy.mit.ener.irn.die.e.1 | L57: =INDEX(Data_Energy!$D$3:$U$22,MATCH($B57,Data_Energy!$C$3:$C$22,0),MATCH($C57,Data_Energy!$D$2:$U$2,0)) -> 0 | M57: =L57*(1+M$39)^($E47*M$40)*(1+M$41)*IF(L20<=0,1,M20/L20)^$F47*(IF(L30<=0,1,M30/L30)^$G47/(1+$H47+$I47))^(1+$F47) -> 0 | N57: =M57*(1+N$39)^($E47*N$40)*(1+N$41)*IF(M20<=0,1,N20/M20)^$F47*(IF(M30<=0,1,N30/M30)^$G47/(1+$H47+$I47))^(1+$F47) -> 0 | O57: =N57*(1+O$39)^($E47*O$40)*(1+O$41)*IF(N20<=0,1,O20/N20)^$F47*(IF(N30<=0,1,O30/N30)^$G47/(1+$H47+$I47))^(1+$F47) -> 0 | P57: =O57*(1+P$39)^($E47*P$40)*(1+P$41)*IF(O20<=0,1,P20/O20)^$F47*(IF(O30<=0,1,P30/O30)^$G47/(1+$H47+$I47))^(1+$F47) -> 0 | Q57: =P57*(1+Q$39)^($E47*Q$40)*(1+Q$41)*IF(P20<=0,1,Q20/P20)^$F47*(IF(P30<=0,1,Q30/P30)^$G47/(1+$H47+$I47))^(1+$F47) -> 0 | R57: =Q57*(1+R$39)^($E47*R$40)*(1+R$41)*IF(Q20<=0,1,R20/Q20)^$F47*(IF(Q30<=0,1,R30/Q30)^$G47/(1+$H47+$I47))^(1+$F47) -> 0 | S57: =R57*(1+S$39)^($E47*S$40)*(1+S$41)*IF(R20<=0,1,S20/R20)^$F47*(IF(R30<=0,1,S30/R30)^$G47/(1+$H47+$I47))^(1+$F47) -> 0 | T57: =S57*(1+T$39)^($E47*T$40)*(1+T$41)*IF(S20<=0,1,T20/S20)^$F47*(IF(S30<=0,1,T30/S30)^$G47/(1+$H47+$I47))^(1+$F47) -> 0 | ... AE57: =AD57*(1+AE$39)^($E47*AE$40)*(1+AE$41)*IF(AD20<=0,1,AE20/AD20)^$F47*(IF(AD30<=0,1,AE30/AD30)^$G47/(1+$H47+$I47))^(1+$F47) -> 0
B58: lpg | C58: =$C$5 -> irn | D58: LPG | E58: ktoe | F58: ener | G58: =Settings!$B$3&".mit.enc."&$B58 -> egy.mit.enc.lpg | H58: =Settings!$B$3&".mit.ener."&$C$5&"."&$B58&".e."&$J$5 -> egy.mit.ener.irn.lpg.e.1 | L58: =INDEX(Data_Energy!$D$3:$U$22,MATCH($B58,Data_Energy!$C$3:$C$22,0),MATCH($C58,Data_Energy!$D$2:$U$2,0)) -> 0 | M58: =L58*(1+M$39)^($E48*M$40)*(1+M$41)*IF(L21<=0,1,M21/L21)^$F48*(IF(L31<=0,1,M31/L31)^$G48/(1+$H48+$I48))^(1+$F48) -> 0 | N58: =M58*(1+N$39)^($E48*N$40)*(1+N$41)*IF(M21<=0,1,N21/M21)^$F48*(IF(M31<=0,1,N31/M31)^$G48/(1+$H48+$I48))^(1+$F48) -> 0 | O58: =N58*(1+O$39)^($E48*O$40)*(1+O$41)*IF(N21<=0,1,O21/N21)^$F48*(IF(N31<=0,1,O31/N31)^$G48/(1+$H48+$I48))^(1+$F48) -> 0 | P58: =O58*(1+P$39)^($E48*P$40)*(1+P$41)*IF(O21<=0,1,P21/O21)^$F48*(IF(O31<=0,1,P31/O31)^$G48/(1+$H48+$I48))^(1+$F48) -> 0 | Q58: =P58*(1+Q$39)^($E48*Q$40)*(1+Q$41)*IF(P21<=0,1,Q21/P21)^$F48*(IF(P31<=0,1,Q31/P31)^$G48/(1+$H48+$I48))^(1+$F48) -> 0 | R58: =Q58*(1+R$39)^($E48*R$40)*(1+R$41)*IF(Q21<=0,1,R21/Q21)^$F48*(IF(Q31<=0,1,R31/Q31)^$G48/(1+$H48+$I48))^(1+$F48) -> 0 | S58: =R58*(1+S$39)^($E48*S$40)*(1+S$41)*IF(R21<=0,1,S21/R21)^$F48*(IF(R31<=0,1,S31/R31)^$G48/(1+$H48+$I48))^(1+$F48) -> 0 | T58: =S58*(1+T$39)^($E48*T$40)*(1+T$41)*IF(S21<=0,1,T21/S21)^$F48*(IF(S31<=0,1,T31/S31)^$G48/(1+$H48+$I48))^(1+$F48) -> 0 | ... AE58: =AD58*(1+AE$39)^($E48*AE$40)*(1+AE$41)*IF(AD21<=0,1,AE21/AD21)^$F48*(IF(AD31<=0,1,AE31/AD31)^$G48/(1+$H48+$I48))^(1+$F48) -> 0
B59: ker | C59: =$C$5 -> irn | D59: Kerosene | E59: ktoe | F59: ener | G59: =Settings!$B$3&".mit.enc."&$B59 -> egy.mit.enc.ker | H59: =Settings!$B$3&".mit.ener."&$C$5&"."&$B59&".e."&$J$5 -> egy.mit.ener.irn.ker.e.1 | L59: =INDEX(Data_Energy!$D$3:$U$22,MATCH($B59,Data_Energy!$C$3:$C$22,0),MATCH($C59,Data_Energy!$D$2:$U$2,0)) -> 0 | M59: =L59*(1+M$39)^($E49*M$40)*(1+M$41)*IF(L22<=0,1,M22/L22)^$F49*(IF(L32<=0,1,M32/L32)^$G49/(1+$H49+$I49))^(1+$F49) -> 0 | N59: =M59*(1+N$39)^($E49*N$40)*(1+N$41)*IF(M22<=0,1,N22/M22)^$F49*(IF(M32<=0,1,N32/M32)^$G49/(1+$H49+$I49))^(1+$F49) -> 0 | O59: =N59*(1+O$39)^($E49*O$40)*(1+O$41)*IF(N22<=0,1,O22/N22)^$F49*(IF(N32<=0,1,O32/N32)^$G49/(1+$H49+$I49))^(1+$F49) -> 0 | P59: =O59*(1+P$39)^($E49*P$40)*(1+P$41)*IF(O22<=0,1,P22/O22)^$F49*(IF(O32<=0,1,P32/O32)^$G49/(1+$H49+$I49))^(1+$F49) -> 0 | Q59: =P59*(1+Q$39)^($E49*Q$40)*(1+Q$41)*IF(P22<=0,1,Q22/P22)^$F49*(IF(P32<=0,1,Q32/P32)^$G49/(1+$H49+$I49))^(1+$F49) -> 0 | R59: =Q59*(1+R$39)^($E49*R$40)*(1+R$41)*IF(Q22<=0,1,R22/Q22)^$F49*(IF(Q32<=0,1,R32/Q32)^$G49/(1+$H49+$I49))^(1+$F49) -> 0 | S59: =R59*(1+S$39)^($E49*S$40)*(1+S$41)*IF(R22<=0,1,S22/R22)^$F49*(IF(R32<=0,1,S32/R32)^$G49/(1+$H49+$I49))^(1+$F49) -> 0 | T59: =S59*(1+T$39)^($E49*T$40)*(1+T$41)*IF(S22<=0,1,T22/S22)^$F49*(IF(S32<=0,1,T32/S32)^$G49/(1+$H49+$I49))^(1+$F49) -> 0 | ... AE59: =AD59*(1+AE$39)^($E49*AE$40)*(1+AE$41)*IF(AD22<=0,1,AE22/AD22)^$F49*(IF(AD32<=0,1,AE32/AD32)^$G49/(1+$H49+$I49))^(1+$F49) -> 0
B60: oop | C60: =$C$5 -> irn | D60: Other oil products | E60: ktoe | F60: ener | G60: =Settings!$B$3&".mit.enc."&$B60 -> egy.mit.enc.oop | H60: =Settings!$B$3&".mit.ener."&$C$5&"."&$B60&".e."&$J$5 -> egy.mit.ener.irn.oop.e.1 | L60: =INDEX(Data_Energy!$D$3:$U$22,MATCH($B60,Data_Energy!$C$3:$C$22,0),MATCH($C60,Data_Energy!$D$2:$U$2,0)) -> 0 | M60: =L60*(1+M$39)^($E50*M$40)*(1+M$41)*IF(L23<=0,1,M23/L23)^$F50*(IF(L33<=0,1,M33/L33)^$G50/(1+$H50+$I50))^(1+$F50) -> 0 | N60: =M60*(1+N$39)^($E50*N$40)*(1+N$41)*IF(M23<=0,1,N23/M23)^$F50*(IF(M33<=0,1,N33/M33)^$G50/(1+$H50+$I50))^(1+$F50) -> 0 | O60: =N60*(1+O$39)^($E50*O$40)*(1+O$41)*IF(N23<=0,1,O23/N23)^$F50*(IF(N33<=0,1,O33/N33)^$G50/(1+$H50+$I50))^(1+$F50) -> 0 | P60: =O60*(1+P$39)^($E50*P$40)*(1+P$41)*IF(O23<=0,1,P23/O23)^$F50*(IF(O33<=0,1,P33/O33)^$G50/(1+$H50+$I50))^(1+$F50) -> 0 | Q60: =P60*(1+Q$39)^($E50*Q$40)*(1+Q$41)*IF(P23<=0,1,Q23/P23)^$F50*(IF(P33<=0,1,Q33/P33)^$G50/(1+$H50+$I50))^(1+$F50) -> 0 | R60: =Q60*(1+R$39)^($E50*R$40)*(1+R$41)*IF(Q23<=0,1,R23/Q23)^$F50*(IF(Q33<=0,1,R33/Q33)^$G50/(1+$H50+$I50))^(1+$F50) -> 0 | S60: =R60*(1+S$39)^($E50*S$40)*(1+S$41)*IF(R23<=0,1,S23/R23)^$F50*(IF(R33<=0,1,S33/R33)^$G50/(1+$H50+$I50))^(1+$F50) -> 0 | T60: =S60*(1+T$39)^($E50*T$40)*(1+T$41)*IF(S23<=0,1,T23/S23)^$F50*(IF(S33<=0,1,T33/S33)^$G50/(1+$H50+$I50))^(1+$F50) -> 0 | ... AE60: =AD60*(1+AE$39)^($E50*AE$40)*(1+AE$41)*IF(AD23<=0,1,AE23/AD23)^$F50*(IF(AD33<=0,1,AE33/AD33)^$G50/(1+$H50+$I50))^(1+$F50) -> 0
B61: bio | C61: =$C$5 -> irn | D61: Biomass | E61: ktoe | F61: ener | G61: =Settings!$B$3&".mit.enc."&$B61 -> egy.mit.enc.bio | H61: =Settings!$B$3&".mit.ener."&$C$5&"."&$B61&".e."&$J$5 -> egy.mit.ener.irn.bio.e.1 | L61: =INDEX(Data_Energy!$D$3:$U$22,MATCH($B61,Data_Energy!$C$3:$C$22,0),MATCH($C61,Data_Energy!$D$2:$U$2,0)) -> 0 | M61: =L61*(1+M$39)^($E51*M$40)*(1+M$41)*IF(L24<=0,1,M24/L24)^$F51*(IF(L34<=0,1,M34/L34)^$G51/(1+$H51+$I51))^(1+$F51) -> 0 | N61: =M61*(1+N$39)^($E51*N$40)*(1+N$41)*IF(M24<=0,1,N24/M24)^$F51*(IF(M34<=0,1,N34/M34)^$G51/(1+$H51+$I51))^(1+$F51) -> 0 | O61: =N61*(1+O$39)^($E51*O$40)*(1+O$41)*IF(N24<=0,1,O24/N24)^$F51*(IF(N34<=0,1,O34/N34)^$G51/(1+$H51+$I51))^(1+$F51) -> 0 | P61: =O61*(1+P$39)^($E51*P$40)*(1+P$41)*IF(O24<=0,1,P24/O24)^$F51*(IF(O34<=0,1,P34/O34)^$G51/(1+$H51+$I51))^(1+$F51) -> 0 | Q61: =P61*(1+Q$39)^($E51*Q$40)*(1+Q$41)*IF(P24<=0,1,Q24/P24)^$F51*(IF(P34<=0,1,Q34/P34)^$G51/(1+$H51+$I51))^(1+$F51) -> 0 | R61: =Q61*(1+R$39)^($E51*R$40)*(1+R$41)*IF(Q24<=0,1,R24/Q24)^$F51*(IF(Q34<=0,1,R34/Q34)^$G51/(1+$H51+$I51))^(1+$F51) -> 0 | S61: =R61*(1+S$39)^($E51*S$40)*(1+S$41)*IF(R24<=0,1,S24/R24)^$F51*(IF(R34<=0,1,S34/R34)^$G51/(1+$H51+$I51))^(1+$F51) -> 0 | T61: =S61*(1+T$39)^($E51*T$40)*(1+T$41)*IF(S24<=0,1,T24/S24)^$F51*(IF(S34<=0,1,T34/S34)^$G51/(1+$H51+$I51))^(1+$F51) -> 0 | ... AE61: =AD61*(1+AE$39)^($E51*AE$40)*(1+AE$41)*IF(AD24<=0,1,AE24/AD24)^$F51*(IF(AD34<=0,1,AE34/AD34)^$G51/(1+$H51+$I51))^(1+$F51) -> 0
B62: ren | C62: =$C$5 -> irn | D62: Self-generated renewables | E62: ktoe | F62: ener | G62: =Settings!$B$3&".mit.enc."&$B62 -> egy.mit.enc.ren | H62: =Settings!$B$3&".mit.ener."&$C$5&"."&$B62&".e."&$J$5 -> egy.mit.ener.irn.ren.e.1 | L62: =INDEX(Data_Energy!$D$3:$U$22,MATCH($B62,Data_Energy!$C$3:$C$22,0),MATCH($C62,Data_Energy!$D$2:$U$2,0)) -> 0 | M62: =L62*(1+M$39)^($E52*M$40)*(1+M$41)*IF(L25<=0,1,M25/L25)^$F52*(IF(L35<=0,1,M35/L35)^$G52/(1+$H52+$I52))^(1+$F52) -> 0 | N62: =M62*(1+N$39)^($E52*N$40)*(1+N$41)*IF(M25<=0,1,N25/M25)^$F52*(IF(M35<=0,1,N35/M35)^$G52/(1+$H52+$I52))^(1+$F52) -> 0 | O62: =N62*(1+O$39)^($E52*O$40)*(1+O$41)*IF(N25<=0,1,O25/N25)^$F52*(IF(N35<=0,1,O35/N35)^$G52/(1+$H52+$I52))^(1+$F52) -> 0 | P62: =O62*(1+P$39)^($E52*P$40)*(1+P$41)*IF(O25<=0,1,P25/O25)^$F52*(IF(O35<=0,1,P35/O35)^$G52/(1+$H52+$I52))^(1+$F52) -> 0 | Q62: =P62*(1+Q$39)^($E52*Q$40)*(1+Q$41)*IF(P25<=0,1,Q25/P25)^$F52*(IF(P35<=0,1,Q35/P35)^$G52/(1+$H52+$I52))^(1+$F52) -> 0 | R62: =Q62*(1+R$39)^($E52*R$40)*(1+R$41)*IF(Q25<=0,1,R25/Q25)^$F52*(IF(Q35<=0,1,R35/Q35)^$G52/(1+$H52+$I52))^(1+$F52) -> 0 | S62: =R62*(1+S$39)^($E52*S$40)*(1+S$41)*IF(R25<=0,1,S25/R25)^$F52*(IF(R35<=0,1,S35/R35)^$G52/(1+$H52+$I52))^(1+$F52) -> 0 | T62: =S62*(1+T$39)^($E52*T$40)*(1+T$41)*IF(S25<=0,1,T25/S25)^$F52*(IF(S35<=0,1,T35/S35)^$G52/(1+$H52+$I52))^(1+$F52) -> 0 | ... AE62: =AD62*(1+AE$39)^($E52*AE$40)*(1+AE$41)*IF(AD25<=0,1,AE25/AD25)^$F52*(IF(AD35<=0,1,AE35/AD35)^$G52/(1+$H52+$I52))^(1+$F52) -> 0
B63: tot | C63: =$C$5 -> irn | D63: Total | E63: ktoe | F63: ener | H63: =Settings!$B$3&".mit.ener."&$C$5&".tot.e."&$J$5 -> egy.mit.ener.irn.tot.e.1 | L63: =SUM(L54:L62) -> 1901.7141 | M63: =SUM(M54:M62) -> 1621.2302 | N63: =SUM(N54:N62) -> 1820.8469 | O63: =SUM(O54:O62) -> 1904.367 | P63: =SUM(P54:P62) -> 1961.702 | Q63: =SUM(Q54:Q62) -> 2038.9625 | R63: =SUM(R54:R62) -> 2135.0352 | S63: =SUM(S54:S62) -> 2228.4851 | ... AE63: =SUM(AE54:AE62) -> 3416.9988
B65: Cement | C65: cem | D65: Fuel Type | E65: Unit | F65: Variable Code | G65: Input Code (data-table key) | H65: Output Code | I65: Scenario | J65: 1 | K65: 2021 | L65: 2022 | M65: 2023 | N65: 2024 | O65: 2025 | P65: 2026 | Q65: 2027 | R65: 2028 | S65: 2029 | T65: 2030 | U65: 2031 | V65: 2032 | W65: 2033 | X65: 2034 | Y65: 2035 | Z65: 2036 | AA65: 2037 | AB65: 2038 | AC65: 2039 | AD65: 2040 | AE65: 2041 | AF65: 2042 | AG65: 2043 | AH65: 2044 | AI65: 2045
B66: Pre-tax price: price before any new policy (supply cost + VAT + existing excise, subsidies and carbon prices)
B67: coa | C67: =$C$65 -> cem | D67: Coal | E67: $/GJ | F67: ptp | G67: =Settings!$B$3&".mit.pbc."&Settings!$B$4&"."&$B67&".a."&$J$65 -> egy.mit.pbc.ind.coa.a.1 | H67: =Settings!$B$3&".mit.ptp."&$C$65&"."&$B67&".e."&$J$65 -> egy.mit.ptp.cem.coa.e.1 | K67: =INDEX(Data_Prices!K:K,MATCH($G67,Data_Prices!$A:$A,0)) -> 11.182902 | L67: =INDEX(Data_Prices!L:L,MATCH($G67,Data_Prices!$A:$A,0)) -> 10.523361 | M67: =INDEX(Data_Prices!M:M,MATCH($G67,Data_Prices!$A:$A,0)) -> 10.299561 | N67: =INDEX(Data_Prices!N:N,MATCH($G67,Data_Prices!$A:$A,0)) -> 9.5775284 | O67: =INDEX(Data_Prices!O:O,MATCH($G67,Data_Prices!$A:$A,0)) -> 8.4854783 | P67: =INDEX(Data_Prices!P:P,MATCH($G67,Data_Prices!$A:$A,0)) -> 9.0871922 | Q67: =INDEX(Data_Prices!Q:Q,MATCH($G67,Data_Prices!$A:$A,0)) -> 9.2229237 | R67: =INDEX(Data_Prices!R:R,MATCH($G67,Data_Prices!$A:$A,0)) -> 9.158565 | S67: =INDEX(Data_Prices!S:S,MATCH($G67,Data_Prices!$A:$A,0)) -> 9.0895479 | T67: =INDEX(Data_Prices!T:T,MATCH($G67,Data_Prices!$A:$A,0)) -> 9.0156817 | U67: =INDEX(Data_Prices!U:U,MATCH($G67,Data_Prices!$A:$A,0)) -> 8.9443978 | V67: =INDEX(Data_Prices!V:V,MATCH($G67,Data_Prices!$A:$A,0)) -> 8.9443978 | W67: =INDEX(Data_Prices!W:W,MATCH($G67,Data_Prices!$A:$A,0)) -> 8.9443978 | X67: =INDEX(Data_Prices!X:X,MATCH($G67,Data_Prices!$A:$A,0)) -> 8.9443978 | Y67: =INDEX(Data_Prices!Y:Y,MATCH($G67,Data_Prices!$A:$A,0)) -> 8.9443978 | Z67: =INDEX(Data_Prices!Z:Z,MATCH($G67,Data_Prices!$A:$A,0)) -> 8.9443978 | AA67: =INDEX(Data_Prices!AA:AA,MATCH($G67,Data_Prices!$A:$A,0)) -> 8.9443978 | AB67: =INDEX(Data_Prices!AB:AB,MATCH($G67,Data_Prices!$A:$A,0)) -> 8.9443978 | AC67: =INDEX(Data_Prices!AC:AC,MATCH($G67,Data_Prices!$A:$A,0)) -> 8.9443978 | AD67: =INDEX(Data_Prices!AD:AD,MATCH($G67,Data_Prices!$A:$A,0)) -> 8.9443978 | AE67: =INDEX(Data_Prices!AE:AE,MATCH($G67,Data_Prices!$A:$A,0)) -> 8.9443978
B68: nga | C68: =$C$65 -> cem | D68: Natural gas | E68: $/GJ | F68: ptp | G68: =Settings!$B$3&".mit.pbc."&Settings!$B$4&"."&$B68&".a."&$J$65 -> egy.mit.pbc.ind.nga.a.1 | H68: =Settings!$B$3&".mit.ptp."&$C$65&"."&$B68&".e."&$J$65 -> egy.mit.ptp.cem.nga.e.1 | K68: =INDEX(Data_Prices!K:K,MATCH($G68,Data_Prices!$A:$A,0)) -> 6.0634636 | L68: =INDEX(Data_Prices!L:L,MATCH($G68,Data_Prices!$A:$A,0)) -> 5.4510151 | M68: =INDEX(Data_Prices!M:M,MATCH($G68,Data_Prices!$A:$A,0)) -> 5.1193563 | N68: =INDEX(Data_Prices!N:N,MATCH($G68,Data_Prices!$A:$A,0)) -> 5.0821846 | O68: =INDEX(Data_Prices!O:O,MATCH($G68,Data_Prices!$A:$A,0)) -> 5.0821846 | P68: =INDEX(Data_Prices!P:P,MATCH($G68,Data_Prices!$A:$A,0)) -> 5.0821846 | Q68: =INDEX(Data_Prices!Q:Q,MATCH($G68,Data_Prices!$A:$A,0)) -> 5.0821846 | R68: =INDEX(Data_Prices!R:R,MATCH($G68,Data_Prices!$A:$A,0)) -> 5.0821846 | S68: =INDEX(Data_Prices!S:S,MATCH($G68,Data_Prices!$A:$A,0)) -> 5.0821846 | T68: =INDEX(Data_Prices!T:T,MATCH($G68,Data_Prices!$A:$A,0)) -> 5.0821846 | U68: =INDEX(Data_Prices!U:U,MATCH($G68,Data_Prices!$A:$A,0)) -> 5.0821846 | V68: =INDEX(Data_Prices!V:V,MATCH($G68,Data_Prices!$A:$A,0)) -> 5.0821846 | W68: =INDEX(Data_Prices!W:W,MATCH($G68,Data_Prices!$A:$A,0)) -> 5.0821846 | X68: =INDEX(Data_Prices!X:X,MATCH($G68,Data_Prices!$A:$A,0)) -> 5.0821846 | Y68: =INDEX(Data_Prices!Y:Y,MATCH($G68,Data_Prices!$A:$A,0)) -> 5.0821846 | Z68: =INDEX(Data_Prices!Z:Z,MATCH($G68,Data_Prices!$A:$A,0)) -> 5.0821846 | AA68: =INDEX(Data_Prices!AA:AA,MATCH($G68,Data_Prices!$A:$A,0)) -> 5.0821846 | AB68: =INDEX(Data_Prices!AB:AB,MATCH($G68,Data_Prices!$A:$A,0)) -> 5.0821846 | AC68: =INDEX(Data_Prices!AC:AC,MATCH($G68,Data_Prices!$A:$A,0)) -> 5.0821846 | AD68: =INDEX(Data_Prices!AD:AD,MATCH($G68,Data_Prices!$A:$A,0)) -> 5.0821846 | AE68: =INDEX(Data_Prices!AE:AE,MATCH($G68,Data_Prices!$A:$A,0)) -> 5.0821846
B69: gso | C69: =$C$65 -> cem | D69: Gasoline | E69: $/liter | F69: ptp | G69: =Settings!$B$3&".mit.pbc."&Settings!$B$4&"."&$B69&".a."&$J$65 -> egy.mit.pbc.ind.gso.a.1 | H69: =Settings!$B$3&".mit.ptp."&$C$65&"."&$B69&".e."&$J$65 -> egy.mit.ptp.cem.gso.e.1 | K69: =INDEX(Data_Prices!K:K,MATCH($G69,Data_Prices!$A:$A,0)) -> 0.67114653 | L69: =INDEX(Data_Prices!L:L,MATCH($G69,Data_Prices!$A:$A,0)) -> 0.61197798 | M69: =INDEX(Data_Prices!M:M,MATCH($G69,Data_Prices!$A:$A,0)) -> 0.61180975 | N69: =INDEX(Data_Prices!N:N,MATCH($G69,Data_Prices!$A:$A,0)) -> 0.6035831 | O69: =INDEX(Data_Prices!O:O,MATCH($G69,Data_Prices!$A:$A,0)) -> 0.6035831 | P69: =INDEX(Data_Prices!P:P,MATCH($G69,Data_Prices!$A:$A,0)) -> 0.6035831 | Q69: =INDEX(Data_Prices!Q:Q,MATCH($G69,Data_Prices!$A:$A,0)) -> 0.6035831 | R69: =INDEX(Data_Prices!R:R,MATCH($G69,Data_Prices!$A:$A,0)) -> 0.6035831 | S69: =INDEX(Data_Prices!S:S,MATCH($G69,Data_Prices!$A:$A,0)) -> 0.6035831 | T69: =INDEX(Data_Prices!T:T,MATCH($G69,Data_Prices!$A:$A,0)) -> 0.6035831 | U69: =INDEX(Data_Prices!U:U,MATCH($G69,Data_Prices!$A:$A,0)) -> 0.6035831 | V69: =INDEX(Data_Prices!V:V,MATCH($G69,Data_Prices!$A:$A,0)) -> 0.6035831 | W69: =INDEX(Data_Prices!W:W,MATCH($G69,Data_Prices!$A:$A,0)) -> 0.6035831 | X69: =INDEX(Data_Prices!X:X,MATCH($G69,Data_Prices!$A:$A,0)) -> 0.6035831 | Y69: =INDEX(Data_Prices!Y:Y,MATCH($G69,Data_Prices!$A:$A,0)) -> 0.6035831 | Z69: =INDEX(Data_Prices!Z:Z,MATCH($G69,Data_Prices!$A:$A,0)) -> 0.6035831 | AA69: =INDEX(Data_Prices!AA:AA,MATCH($G69,Data_Prices!$A:$A,0)) -> 0.6035831 | AB69: =INDEX(Data_Prices!AB:AB,MATCH($G69,Data_Prices!$A:$A,0)) -> 0.6035831 | AC69: =INDEX(Data_Prices!AC:AC,MATCH($G69,Data_Prices!$A:$A,0)) -> 0.6035831 | AD69: =INDEX(Data_Prices!AD:AD,MATCH($G69,Data_Prices!$A:$A,0)) -> 0.6035831 | AE69: =INDEX(Data_Prices!AE:AE,MATCH($G69,Data_Prices!$A:$A,0)) -> 0.6035831
B70: die | C70: =$C$65 -> cem | D70: Diesel | E70: $/liter | F70: ptp | G70: =Settings!$B$3&".mit.pbc."&Settings!$B$4&"."&$B70&".a."&$J$65 -> egy.mit.pbc.ind.die.a.1 | H70: =Settings!$B$3&".mit.ptp."&$C$65&"."&$B70&".e."&$J$65 -> egy.mit.ptp.cem.die.e.1 | K70: =INDEX(Data_Prices!K:K,MATCH($G70,Data_Prices!$A:$A,0)) -> 0.55971121 | L70: =INDEX(Data_Prices!L:L,MATCH($G70,Data_Prices!$A:$A,0)) -> 0.49458873 | M70: =INDEX(Data_Prices!M:M,MATCH($G70,Data_Prices!$A:$A,0)) -> 0.50778655 | N70: =INDEX(Data_Prices!N:N,MATCH($G70,Data_Prices!$A:$A,0)) -> 0.47043643 | O70: =INDEX(Data_Prices!O:O,MATCH($G70,Data_Prices!$A:$A,0)) -> 0.47043643 | P70: =INDEX(Data_Prices!P:P,MATCH($G70,Data_Prices!$A:$A,0)) -> 0.47043643 | Q70: =INDEX(Data_Prices!Q:Q,MATCH($G70,Data_Prices!$A:$A,0)) -> 0.47043643 | R70: =INDEX(Data_Prices!R:R,MATCH($G70,Data_Prices!$A:$A,0)) -> 0.47043643 | S70: =INDEX(Data_Prices!S:S,MATCH($G70,Data_Prices!$A:$A,0)) -> 0.47043643 | T70: =INDEX(Data_Prices!T:T,MATCH($G70,Data_Prices!$A:$A,0)) -> 0.47043643 | U70: =INDEX(Data_Prices!U:U,MATCH($G70,Data_Prices!$A:$A,0)) -> 0.47043643 | V70: =INDEX(Data_Prices!V:V,MATCH($G70,Data_Prices!$A:$A,0)) -> 0.47043643 | W70: =INDEX(Data_Prices!W:W,MATCH($G70,Data_Prices!$A:$A,0)) -> 0.47043643 | X70: =INDEX(Data_Prices!X:X,MATCH($G70,Data_Prices!$A:$A,0)) -> 0.47043643 | Y70: =INDEX(Data_Prices!Y:Y,MATCH($G70,Data_Prices!$A:$A,0)) -> 0.47043643 | Z70: =INDEX(Data_Prices!Z:Z,MATCH($G70,Data_Prices!$A:$A,0)) -> 0.47043643 | AA70: =INDEX(Data_Prices!AA:AA,MATCH($G70,Data_Prices!$A:$A,0)) -> 0.47043643 | AB70: =INDEX(Data_Prices!AB:AB,MATCH($G70,Data_Prices!$A:$A,0)) -> 0.47043643 | AC70: =INDEX(Data_Prices!AC:AC,MATCH($G70,Data_Prices!$A:$A,0)) -> 0.47043643 | AD70: =INDEX(Data_Prices!AD:AD,MATCH($G70,Data_Prices!$A:$A,0)) -> 0.47043643 | AE70: =INDEX(Data_Prices!AE:AE,MATCH($G70,Data_Prices!$A:$A,0)) -> 0.47043643
B71: lpg | C71: =$C$65 -> cem | D71: LPG | E71: $/liter | F71: ptp | G71: =Settings!$B$3&".mit.pbc."&Settings!$B$4&"."&$B71&".a."&$J$65 -> egy.mit.pbc.ind.lpg.a.1 | H71: =Settings!$B$3&".mit.ptp."&$C$65&"."&$B71&".e."&$J$65 -> egy.mit.ptp.cem.lpg.e.1 | K71: =INDEX(Data_Prices!K:K,MATCH($G71,Data_Prices!$A:$A,0)) -> 0.20036669 | L71: =INDEX(Data_Prices!L:L,MATCH($G71,Data_Prices!$A:$A,0)) -> 0.15734474 | M71: =INDEX(Data_Prices!M:M,MATCH($G71,Data_Prices!$A:$A,0)) -> 0.16448404 | N71: =INDEX(Data_Prices!N:N,MATCH($G71,Data_Prices!$A:$A,0)) -> 0.15070908 | O71: =INDEX(Data_Prices!O:O,MATCH($G71,Data_Prices!$A:$A,0)) -> 0.15070908 | P71: =INDEX(Data_Prices!P:P,MATCH($G71,Data_Prices!$A:$A,0)) -> 0.15070908 | Q71: =INDEX(Data_Prices!Q:Q,MATCH($G71,Data_Prices!$A:$A,0)) -> 0.15070908 | R71: =INDEX(Data_Prices!R:R,MATCH($G71,Data_Prices!$A:$A,0)) -> 0.15070908 | S71: =INDEX(Data_Prices!S:S,MATCH($G71,Data_Prices!$A:$A,0)) -> 0.15070908 | T71: =INDEX(Data_Prices!T:T,MATCH($G71,Data_Prices!$A:$A,0)) -> 0.15070908 | U71: =INDEX(Data_Prices!U:U,MATCH($G71,Data_Prices!$A:$A,0)) -> 0.15070908 | V71: =INDEX(Data_Prices!V:V,MATCH($G71,Data_Prices!$A:$A,0)) -> 0.15070908 | W71: =INDEX(Data_Prices!W:W,MATCH($G71,Data_Prices!$A:$A,0)) -> 0.15070908 | X71: =INDEX(Data_Prices!X:X,MATCH($G71,Data_Prices!$A:$A,0)) -> 0.15070908 | Y71: =INDEX(Data_Prices!Y:Y,MATCH($G71,Data_Prices!$A:$A,0)) -> 0.15070908 | Z71: =INDEX(Data_Prices!Z:Z,MATCH($G71,Data_Prices!$A:$A,0)) -> 0.15070908 | AA71: =INDEX(Data_Prices!AA:AA,MATCH($G71,Data_Prices!$A:$A,0)) -> 0.15070908 | AB71: =INDEX(Data_Prices!AB:AB,MATCH($G71,Data_Prices!$A:$A,0)) -> 0.15070908 | AC71: =INDEX(Data_Prices!AC:AC,MATCH($G71,Data_Prices!$A:$A,0)) -> 0.15070908 | AD71: =INDEX(Data_Prices!AD:AD,MATCH($G71,Data_Prices!$A:$A,0)) -> 0.15070908 | AE71: =INDEX(Data_Prices!AE:AE,MATCH($G71,Data_Prices!$A:$A,0)) -> 0.15070908
B72: ker | C72: =$C$65 -> cem | D72: Kerosene | E72: $/liter | F72: ptp | G72: =Settings!$B$3&".mit.pbc."&Settings!$B$4&"."&$B72&".a."&$J$65 -> egy.mit.pbc.ind.ker.a.1 | H72: =Settings!$B$3&".mit.ptp."&$C$65&"."&$B72&".e."&$J$65 -> egy.mit.ptp.cem.ker.e.1 | K72: =INDEX(Data_Prices!K:K,MATCH($G72,Data_Prices!$A:$A,0)) -> 0.48429424 | L72: =INDEX(Data_Prices!L:L,MATCH($G72,Data_Prices!$A:$A,0)) -> 0.45642817 | M72: =INDEX(Data_Prices!M:M,MATCH($G72,Data_Prices!$A:$A,0)) -> 0.4316892 | N72: =INDEX(Data_Prices!N:N,MATCH($G72,Data_Prices!$A:$A,0)) -> 0.42507558 | O72: =INDEX(Data_Prices!O:O,MATCH($G72,Data_Prices!$A:$A,0)) -> 0.42507558 | P72: =INDEX(Data_Prices!P:P,MATCH($G72,Data_Prices!$A:$A,0)) -> 0.42507558 | Q72: =INDEX(Data_Prices!Q:Q,MATCH($G72,Data_Prices!$A:$A,0)) -> 0.42507558 | R72: =INDEX(Data_Prices!R:R,MATCH($G72,Data_Prices!$A:$A,0)) -> 0.42507558 | S72: =INDEX(Data_Prices!S:S,MATCH($G72,Data_Prices!$A:$A,0)) -> 0.42507558 | T72: =INDEX(Data_Prices!T:T,MATCH($G72,Data_Prices!$A:$A,0)) -> 0.42507558 | U72: =INDEX(Data_Prices!U:U,MATCH($G72,Data_Prices!$A:$A,0)) -> 0.42507558 | V72: =INDEX(Data_Prices!V:V,MATCH($G72,Data_Prices!$A:$A,0)) -> 0.42507558 | W72: =INDEX(Data_Prices!W:W,MATCH($G72,Data_Prices!$A:$A,0)) -> 0.42507558 | X72: =INDEX(Data_Prices!X:X,MATCH($G72,Data_Prices!$A:$A,0)) -> 0.42507558 | Y72: =INDEX(Data_Prices!Y:Y,MATCH($G72,Data_Prices!$A:$A,0)) -> 0.42507558 | Z72: =INDEX(Data_Prices!Z:Z,MATCH($G72,Data_Prices!$A:$A,0)) -> 0.42507558 | AA72: =INDEX(Data_Prices!AA:AA,MATCH($G72,Data_Prices!$A:$A,0)) -> 0.42507558 | AB72: =INDEX(Data_Prices!AB:AB,MATCH($G72,Data_Prices!$A:$A,0)) -> 0.42507558 | AC72: =INDEX(Data_Prices!AC:AC,MATCH($G72,Data_Prices!$A:$A,0)) -> 0.42507558 | AD72: =INDEX(Data_Prices!AD:AD,MATCH($G72,Data_Prices!$A:$A,0)) -> 0.42507558 | AE72: =INDEX(Data_Prices!AE:AE,MATCH($G72,Data_Prices!$A:$A,0)) -> 0.42507558
B73: oop | C73: =$C$65 -> cem | D73: Other oil products | E73: $/bbl | F73: ptp | G73: =Settings!$B$3&".mit.pbc."&Settings!$B$4&"."&$B73&".a."&$J$65 -> egy.mit.pbc.ind.oop.a.1 | H73: =Settings!$B$3&".mit.ptp."&$C$65&"."&$B73&".e."&$J$65 -> egy.mit.ptp.cem.oop.e.1 | K73: =INDEX(Data_Prices!K:K,MATCH($G73,Data_Prices!$A:$A,0)) -> 41.500338 | L73: =INDEX(Data_Prices!L:L,MATCH($G73,Data_Prices!$A:$A,0)) -> 34.41537 | M73: =INDEX(Data_Prices!M:M,MATCH($G73,Data_Prices!$A:$A,0)) -> 37.368961 | N73: =INDEX(Data_Prices!N:N,MATCH($G73,Data_Prices!$A:$A,0)) -> 28.982761 | O73: =INDEX(Data_Prices!O:O,MATCH($G73,Data_Prices!$A:$A,0)) -> 15 | P73: =INDEX(Data_Prices!P:P,MATCH($G73,Data_Prices!$A:$A,0)) -> 24.25863 | Q73: =INDEX(Data_Prices!Q:Q,MATCH($G73,Data_Prices!$A:$A,0)) -> 15 | R73: =INDEX(Data_Prices!R:R,MATCH($G73,Data_Prices!$A:$A,0)) -> 15 | S73: =INDEX(Data_Prices!S:S,MATCH($G73,Data_Prices!$A:$A,0)) -> 15 | T73: =INDEX(Data_Prices!T:T,MATCH($G73,Data_Prices!$A:$A,0)) -> 15 | U73: =INDEX(Data_Prices!U:U,MATCH($G73,Data_Prices!$A:$A,0)) -> 15 | V73: =INDEX(Data_Prices!V:V,MATCH($G73,Data_Prices!$A:$A,0)) -> 15 | W73: =INDEX(Data_Prices!W:W,MATCH($G73,Data_Prices!$A:$A,0)) -> 15 | X73: =INDEX(Data_Prices!X:X,MATCH($G73,Data_Prices!$A:$A,0)) -> 15 | Y73: =INDEX(Data_Prices!Y:Y,MATCH($G73,Data_Prices!$A:$A,0)) -> 15 | Z73: =INDEX(Data_Prices!Z:Z,MATCH($G73,Data_Prices!$A:$A,0)) -> 15 | AA73: =INDEX(Data_Prices!AA:AA,MATCH($G73,Data_Prices!$A:$A,0)) -> 15 | AB73: =INDEX(Data_Prices!AB:AB,MATCH($G73,Data_Prices!$A:$A,0)) -> 15 | AC73: =INDEX(Data_Prices!AC:AC,MATCH($G73,Data_Prices!$A:$A,0)) -> 15 | AD73: =INDEX(Data_Prices!AD:AD,MATCH($G73,Data_Prices!$A:$A,0)) -> 15 | AE73: =INDEX(Data_Prices!AE:AE,MATCH($G73,Data_Prices!$A:$A,0)) -> 15
B74: bio | C74: =$C$65 -> cem | D74: Biomass | E74: $/GJ | F74: ptp | G74: =Settings!$B$3&".mit.pbc."&Settings!$B$4&"."&$B74&".a."&$J$65 -> egy.mit.pbc.ind.bio.a.1 | H74: =Settings!$B$3&".mit.ptp."&$C$65&"."&$B74&".e."&$J$65 -> egy.mit.ptp.cem.bio.e.1 | K74: =INDEX(Data_Prices!K:K,MATCH($G74,Data_Prices!$A:$A,0)) -> 15.334551 | L74: =INDEX(Data_Prices!L:L,MATCH($G74,Data_Prices!$A:$A,0)) -> 14.199528 | M74: =INDEX(Data_Prices!M:M,MATCH($G74,Data_Prices!$A:$A,0)) -> 13.840442 | N74: =INDEX(Data_Prices!N:N,MATCH($G74,Data_Prices!$A:$A,0)) -> 13.567727 | O74: =INDEX(Data_Prices!O:O,MATCH($G74,Data_Prices!$A:$A,0)) -> 13.567727 | P74: =INDEX(Data_Prices!P:P,MATCH($G74,Data_Prices!$A:$A,0)) -> 13.567727 | Q74: =INDEX(Data_Prices!Q:Q,MATCH($G74,Data_Prices!$A:$A,0)) -> 13.567727 | R74: =INDEX(Data_Prices!R:R,MATCH($G74,Data_Prices!$A:$A,0)) -> 13.567727 | S74: =INDEX(Data_Prices!S:S,MATCH($G74,Data_Prices!$A:$A,0)) -> 13.567727 | T74: =INDEX(Data_Prices!T:T,MATCH($G74,Data_Prices!$A:$A,0)) -> 13.567727 | U74: =INDEX(Data_Prices!U:U,MATCH($G74,Data_Prices!$A:$A,0)) -> 13.567727 | V74: =INDEX(Data_Prices!V:V,MATCH($G74,Data_Prices!$A:$A,0)) -> 13.567727 | W74: =INDEX(Data_Prices!W:W,MATCH($G74,Data_Prices!$A:$A,0)) -> 13.567727 | X74: =INDEX(Data_Prices!X:X,MATCH($G74,Data_Prices!$A:$A,0)) -> 13.567727 | Y74: =INDEX(Data_Prices!Y:Y,MATCH($G74,Data_Prices!$A:$A,0)) -> 13.567727 | Z74: =INDEX(Data_Prices!Z:Z,MATCH($G74,Data_Prices!$A:$A,0)) -> 13.567727 | AA74: =INDEX(Data_Prices!AA:AA,MATCH($G74,Data_Prices!$A:$A,0)) -> 13.567727 | AB74: =INDEX(Data_Prices!AB:AB,MATCH($G74,Data_Prices!$A:$A,0)) -> 13.567727 | AC74: =INDEX(Data_Prices!AC:AC,MATCH($G74,Data_Prices!$A:$A,0)) -> 13.567727 | AD74: =INDEX(Data_Prices!AD:AD,MATCH($G74,Data_Prices!$A:$A,0)) -> 13.567727 | AE74: =INDEX(Data_Prices!AE:AE,MATCH($G74,Data_Prices!$A:$A,0)) -> 13.567727
B75: ren | C75: =$C$65 -> cem | D75: Self-generated renewables | E75: $/kwh | F75: ptp | G75: =Settings!$B$3&".mit.pbc."&Settings!$B$4&"."&$B75&".a."&$J$65 -> egy.mit.pbc.ind.ren.a.1 | H75: =Settings!$B$3&".mit.ptp."&$C$65&"."&$B75&".e."&$J$65 -> egy.mit.ptp.cem.ren.e.1 | K75: =INDEX(Data_Prices!K:K,MATCH($G75,Data_Prices!$A:$A,0)) -> 0 | L75: =INDEX(Data_Prices!L:L,MATCH($G75,Data_Prices!$A:$A,0)) -> 0.14404499 | M75: =INDEX(Data_Prices!M:M,MATCH($G75,Data_Prices!$A:$A,0)) -> 0.14102041 | N75: =INDEX(Data_Prices!N:N,MATCH($G75,Data_Prices!$A:$A,0)) -> 0.13511636 | O75: =INDEX(Data_Prices!O:O,MATCH($G75,Data_Prices!$A:$A,0)) -> 0.13098826 | P75: =INDEX(Data_Prices!P:P,MATCH($G75,Data_Prices!$A:$A,0)) -> 0.12790842 | Q75: =INDEX(Data_Prices!Q:Q,MATCH($G75,Data_Prices!$A:$A,0)) -> 0.12481431 | R75: =INDEX(Data_Prices!R:R,MATCH($G75,Data_Prices!$A:$A,0)) -> 0.12146026 | S75: =INDEX(Data_Prices!S:S,MATCH($G75,Data_Prices!$A:$A,0)) -> 0.11795074 | T75: =INDEX(Data_Prices!T:T,MATCH($G75,Data_Prices!$A:$A,0)) -> 0.11419916 | U75: =INDEX(Data_Prices!U:U,MATCH($G75,Data_Prices!$A:$A,0)) -> 0.1136651 | V75: =INDEX(Data_Prices!V:V,MATCH($G75,Data_Prices!$A:$A,0)) -> 0.11301693 | W75: =INDEX(Data_Prices!W:W,MATCH($G75,Data_Prices!$A:$A,0)) -> 0.11231407 | X75: =INDEX(Data_Prices!X:X,MATCH($G75,Data_Prices!$A:$A,0)) -> 0.11142204 | Y75: =INDEX(Data_Prices!Y:Y,MATCH($G75,Data_Prices!$A:$A,0)) -> 0.11043412 | Z75: =INDEX(Data_Prices!Z:Z,MATCH($G75,Data_Prices!$A:$A,0)) -> 0.10948397 | AA75: =INDEX(Data_Prices!AA:AA,MATCH($G75,Data_Prices!$A:$A,0)) -> 0.10839192 | AB75: =INDEX(Data_Prices!AB:AB,MATCH($G75,Data_Prices!$A:$A,0)) -> 0.10735443 | AC75: =INDEX(Data_Prices!AC:AC,MATCH($G75,Data_Prices!$A:$A,0)) -> 0.10516868 | AD75: =INDEX(Data_Prices!AD:AD,MATCH($G75,Data_Prices!$A:$A,0)) -> 0.10305798 | AE75: =INDEX(Data_Prices!AE:AE,MATCH($G75,Data_Prices!$A:$A,0)) -> 0.10093184
B76: Post-tax price: pre-tax + new-policy wedge x sector coverage factor (= CPAT atp row)
B77: coa | C77: =$C$65 -> cem | D77: Coal | E77: $/GJ | F77: atp | G77: =Settings!$B$3&".mit.nce."&Settings!$B$4&"."&$B77&".a."&$J$65 -> egy.mit.nce.ind.coa.a.1 | H77: =Settings!$B$3&".mit.atp."&$C$65&"."&$B77&".e."&$J$65 -> egy.mit.atp.cem.coa.e.1 | K77: =K67+INDEX(Data_Prices!K:K,MATCH($G77,Data_Prices!$A:$A,0))*K$97 -> 11.182902 | L77: =L67+INDEX(Data_Prices!L:L,MATCH($G77,Data_Prices!$A:$A,0))*L$97 -> 10.523361 | M77: =M67+INDEX(Data_Prices!M:M,MATCH($G77,Data_Prices!$A:$A,0))*M$97 -> 10.299561 | N77: =N67+INDEX(Data_Prices!N:N,MATCH($G77,Data_Prices!$A:$A,0))*N$97 -> 9.5775284 | O77: =O67+INDEX(Data_Prices!O:O,MATCH($G77,Data_Prices!$A:$A,0))*O$97 -> 8.4854783 | P77: =P67+INDEX(Data_Prices!P:P,MATCH($G77,Data_Prices!$A:$A,0))*P$97 -> 9.0871922 | Q77: =Q67+INDEX(Data_Prices!Q:Q,MATCH($G77,Data_Prices!$A:$A,0))*Q$97 -> 9.2229237 | R77: =R67+INDEX(Data_Prices!R:R,MATCH($G77,Data_Prices!$A:$A,0))*R$97 -> 9.158565 | S77: =S67+INDEX(Data_Prices!S:S,MATCH($G77,Data_Prices!$A:$A,0))*S$97 -> 9.0895479 | T77: =T67+INDEX(Data_Prices!T:T,MATCH($G77,Data_Prices!$A:$A,0))*T$97 -> 9.0156817 | U77: =U67+INDEX(Data_Prices!U:U,MATCH($G77,Data_Prices!$A:$A,0))*U$97 -> 8.9443978 | V77: =V67+INDEX(Data_Prices!V:V,MATCH($G77,Data_Prices!$A:$A,0))*V$97 -> 8.9443978 | W77: =W67+INDEX(Data_Prices!W:W,MATCH($G77,Data_Prices!$A:$A,0))*W$97 -> 8.9443978 | X77: =X67+INDEX(Data_Prices!X:X,MATCH($G77,Data_Prices!$A:$A,0))*X$97 -> 8.9443978 | Y77: =Y67+INDEX(Data_Prices!Y:Y,MATCH($G77,Data_Prices!$A:$A,0))*Y$97 -> 8.9443978 | Z77: =Z67+INDEX(Data_Prices!Z:Z,MATCH($G77,Data_Prices!$A:$A,0))*Z$97 -> 8.9443978 | AA77: =AA67+INDEX(Data_Prices!AA:AA,MATCH($G77,Data_Prices!$A:$A,0))*AA$97 -> 8.9443978 | AB77: =AB67+INDEX(Data_Prices!AB:AB,MATCH($G77,Data_Prices!$A:$A,0))*AB$97 -> 8.9443978 | AC77: =AC67+INDEX(Data_Prices!AC:AC,MATCH($G77,Data_Prices!$A:$A,0))*AC$97 -> 8.9443978 | AD77: =AD67+INDEX(Data_Prices!AD:AD,MATCH($G77,Data_Prices!$A:$A,0))*AD$97 -> 8.9443978 | AE77: =AE67+INDEX(Data_Prices!AE:AE,MATCH($G77,Data_Prices!$A:$A,0))*AE$97 -> 8.9443978
B78: nga | C78: =$C$65 -> cem | D78: Natural gas | E78: $/GJ | F78: atp | G78: =Settings!$B$3&".mit.nce."&Settings!$B$4&"."&$B78&".a."&$J$65 -> egy.mit.nce.ind.nga.a.1 | H78: =Settings!$B$3&".mit.atp."&$C$65&"."&$B78&".e."&$J$65 -> egy.mit.atp.cem.nga.e.1 | K78: =K68+INDEX(Data_Prices!K:K,MATCH($G78,Data_Prices!$A:$A,0))*K$97 -> 6.0634636 | L78: =L68+INDEX(Data_Prices!L:L,MATCH($G78,Data_Prices!$A:$A,0))*L$97 -> 5.4510151 | M78: =M68+INDEX(Data_Prices!M:M,MATCH($G78,Data_Prices!$A:$A,0))*M$97 -> 5.1193563 | N78: =N68+INDEX(Data_Prices!N:N,MATCH($G78,Data_Prices!$A:$A,0))*N$97 -> 5.0821846 | O78: =O68+INDEX(Data_Prices!O:O,MATCH($G78,Data_Prices!$A:$A,0))*O$97 -> 5.0821846 | P78: =P68+INDEX(Data_Prices!P:P,MATCH($G78,Data_Prices!$A:$A,0))*P$97 -> 5.0821846 | Q78: =Q68+INDEX(Data_Prices!Q:Q,MATCH($G78,Data_Prices!$A:$A,0))*Q$97 -> 5.0821846 | R78: =R68+INDEX(Data_Prices!R:R,MATCH($G78,Data_Prices!$A:$A,0))*R$97 -> 5.0821846 | S78: =S68+INDEX(Data_Prices!S:S,MATCH($G78,Data_Prices!$A:$A,0))*S$97 -> 5.0821846 | T78: =T68+INDEX(Data_Prices!T:T,MATCH($G78,Data_Prices!$A:$A,0))*T$97 -> 5.0821846 | U78: =U68+INDEX(Data_Prices!U:U,MATCH($G78,Data_Prices!$A:$A,0))*U$97 -> 5.0821846 | V78: =V68+INDEX(Data_Prices!V:V,MATCH($G78,Data_Prices!$A:$A,0))*V$97 -> 5.0821846 | W78: =W68+INDEX(Data_Prices!W:W,MATCH($G78,Data_Prices!$A:$A,0))*W$97 -> 5.0821846 | X78: =X68+INDEX(Data_Prices!X:X,MATCH($G78,Data_Prices!$A:$A,0))*X$97 -> 5.0821846 | Y78: =Y68+INDEX(Data_Prices!Y:Y,MATCH($G78,Data_Prices!$A:$A,0))*Y$97 -> 5.0821846 | Z78: =Z68+INDEX(Data_Prices!Z:Z,MATCH($G78,Data_Prices!$A:$A,0))*Z$97 -> 5.0821846 | AA78: =AA68+INDEX(Data_Prices!AA:AA,MATCH($G78,Data_Prices!$A:$A,0))*AA$97 -> 5.0821846 | AB78: =AB68+INDEX(Data_Prices!AB:AB,MATCH($G78,Data_Prices!$A:$A,0))*AB$97 -> 5.0821846 | AC78: =AC68+INDEX(Data_Prices!AC:AC,MATCH($G78,Data_Prices!$A:$A,0))*AC$97 -> 5.0821846 | AD78: =AD68+INDEX(Data_Prices!AD:AD,MATCH($G78,Data_Prices!$A:$A,0))*AD$97 -> 5.0821846 | AE78: =AE68+INDEX(Data_Prices!AE:AE,MATCH($G78,Data_Prices!$A:$A,0))*AE$97 -> 5.0821846
B79: gso | C79: =$C$65 -> cem | D79: Gasoline | E79: $/liter | F79: atp | G79: =Settings!$B$3&".mit.nce."&Settings!$B$4&"."&$B79&".a."&$J$65 -> egy.mit.nce.ind.gso.a.1 | H79: =Settings!$B$3&".mit.atp."&$C$65&"."&$B79&".e."&$J$65 -> egy.mit.atp.cem.gso.e.1 | K79: =K69+INDEX(Data_Prices!K:K,MATCH($G79,Data_Prices!$A:$A,0))*K$97 -> 0.67114653 | L79: =L69+INDEX(Data_Prices!L:L,MATCH($G79,Data_Prices!$A:$A,0))*L$97 -> 0.61197798 | M79: =M69+INDEX(Data_Prices!M:M,MATCH($G79,Data_Prices!$A:$A,0))*M$97 -> 0.61180975 | N79: =N69+INDEX(Data_Prices!N:N,MATCH($G79,Data_Prices!$A:$A,0))*N$97 -> 0.6035831 | O79: =O69+INDEX(Data_Prices!O:O,MATCH($G79,Data_Prices!$A:$A,0))*O$97 -> 0.6035831 | P79: =P69+INDEX(Data_Prices!P:P,MATCH($G79,Data_Prices!$A:$A,0))*P$97 -> 0.6035831 | Q79: =Q69+INDEX(Data_Prices!Q:Q,MATCH($G79,Data_Prices!$A:$A,0))*Q$97 -> 0.6035831 | R79: =R69+INDEX(Data_Prices!R:R,MATCH($G79,Data_Prices!$A:$A,0))*R$97 -> 0.6035831 | S79: =S69+INDEX(Data_Prices!S:S,MATCH($G79,Data_Prices!$A:$A,0))*S$97 -> 0.6035831 | T79: =T69+INDEX(Data_Prices!T:T,MATCH($G79,Data_Prices!$A:$A,0))*T$97 -> 0.6035831 | U79: =U69+INDEX(Data_Prices!U:U,MATCH($G79,Data_Prices!$A:$A,0))*U$97 -> 0.6035831 | V79: =V69+INDEX(Data_Prices!V:V,MATCH($G79,Data_Prices!$A:$A,0))*V$97 -> 0.6035831 | W79: =W69+INDEX(Data_Prices!W:W,MATCH($G79,Data_Prices!$A:$A,0))*W$97 -> 0.6035831 | X79: =X69+INDEX(Data_Prices!X:X,MATCH($G79,Data_Prices!$A:$A,0))*X$97 -> 0.6035831 | Y79: =Y69+INDEX(Data_Prices!Y:Y,MATCH($G79,Data_Prices!$A:$A,0))*Y$97 -> 0.6035831 | Z79: =Z69+INDEX(Data_Prices!Z:Z,MATCH($G79,Data_Prices!$A:$A,0))*Z$97 -> 0.6035831 | AA79: =AA69+INDEX(Data_Prices!AA:AA,MATCH($G79,Data_Prices!$A:$A,0))*AA$97 -> 0.6035831 | AB79: =AB69+INDEX(Data_Prices!AB:AB,MATCH($G79,Data_Prices!$A:$A,0))*AB$97 -> 0.6035831 | AC79: =AC69+INDEX(Data_Prices!AC:AC,MATCH($G79,Data_Prices!$A:$A,0))*AC$97 -> 0.6035831 | AD79: =AD69+INDEX(Data_Prices!AD:AD,MATCH($G79,Data_Prices!$A:$A,0))*AD$97 -> 0.6035831 | AE79: =AE69+INDEX(Data_Prices!AE:AE,MATCH($G79,Data_Prices!$A:$A,0))*AE$97 -> 0.6035831
B80: die | C80: =$C$65 -> cem | D80: Diesel | E80: $/liter | F80: atp | G80: =Settings!$B$3&".mit.nce."&Settings!$B$4&"."&$B80&".a."&$J$65 -> egy.mit.nce.ind.die.a.1 | H80: =Settings!$B$3&".mit.atp."&$C$65&"."&$B80&".e."&$J$65 -> egy.mit.atp.cem.die.e.1 | K80: =K70+INDEX(Data_Prices!K:K,MATCH($G80,Data_Prices!$A:$A,0))*K$97 -> 0.55971121 | L80: =L70+INDEX(Data_Prices!L:L,MATCH($G80,Data_Prices!$A:$A,0))*L$97 -> 0.49458873 | M80: =M70+INDEX(Data_Prices!M:M,MATCH($G80,Data_Prices!$A:$A,0))*M$97 -> 0.50778655 | N80: =N70+INDEX(Data_Prices!N:N,MATCH($G80,Data_Prices!$A:$A,0))*N$97 -> 0.47043643 | O80: =O70+INDEX(Data_Prices!O:O,MATCH($G80,Data_Prices!$A:$A,0))*O$97 -> 0.47043643 | P80: =P70+INDEX(Data_Prices!P:P,MATCH($G80,Data_Prices!$A:$A,0))*P$97 -> 0.47043643 | Q80: =Q70+INDEX(Data_Prices!Q:Q,MATCH($G80,Data_Prices!$A:$A,0))*Q$97 -> 0.47043643 | R80: =R70+INDEX(Data_Prices!R:R,MATCH($G80,Data_Prices!$A:$A,0))*R$97 -> 0.47043643 | S80: =S70+INDEX(Data_Prices!S:S,MATCH($G80,Data_Prices!$A:$A,0))*S$97 -> 0.47043643 | T80: =T70+INDEX(Data_Prices!T:T,MATCH($G80,Data_Prices!$A:$A,0))*T$97 -> 0.47043643 | U80: =U70+INDEX(Data_Prices!U:U,MATCH($G80,Data_Prices!$A:$A,0))*U$97 -> 0.47043643 | V80: =V70+INDEX(Data_Prices!V:V,MATCH($G80,Data_Prices!$A:$A,0))*V$97 -> 0.47043643 | W80: =W70+INDEX(Data_Prices!W:W,MATCH($G80,Data_Prices!$A:$A,0))*W$97 -> 0.47043643 | X80: =X70+INDEX(Data_Prices!X:X,MATCH($G80,Data_Prices!$A:$A,0))*X$97 -> 0.47043643 | Y80: =Y70+INDEX(Data_Prices!Y:Y,MATCH($G80,Data_Prices!$A:$A,0))*Y$97 -> 0.47043643 | Z80: =Z70+INDEX(Data_Prices!Z:Z,MATCH($G80,Data_Prices!$A:$A,0))*Z$97 -> 0.47043643 | AA80: =AA70+INDEX(Data_Prices!AA:AA,MATCH($G80,Data_Prices!$A:$A,0))*AA$97 -> 0.47043643 | AB80: =AB70+INDEX(Data_Prices!AB:AB,MATCH($G80,Data_Prices!$A:$A,0))*AB$97 -> 0.47043643 | AC80: =AC70+INDEX(Data_Prices!AC:AC,MATCH($G80,Data_Prices!$A:$A,0))*AC$97 -> 0.47043643 | AD80: =AD70+INDEX(Data_Prices!AD:AD,MATCH($G80,Data_Prices!$A:$A,0))*AD$97 -> 0.47043643 | AE80: =AE70+INDEX(Data_Prices!AE:AE,MATCH($G80,Data_Prices!$A:$A,0))*AE$97 -> 0.47043643
B81: lpg | C81: =$C$65 -> cem | D81: LPG | E81: $/liter | F81: atp | G81: =Settings!$B$3&".mit.nce."&Settings!$B$4&"."&$B81&".a."&$J$65 -> egy.mit.nce.ind.lpg.a.1 | H81: =Settings!$B$3&".mit.atp."&$C$65&"."&$B81&".e."&$J$65 -> egy.mit.atp.cem.lpg.e.1 | K81: =K71+INDEX(Data_Prices!K:K,MATCH($G81,Data_Prices!$A:$A,0))*K$97 -> 0.20036669 | L81: =L71+INDEX(Data_Prices!L:L,MATCH($G81,Data_Prices!$A:$A,0))*L$97 -> 0.15734474 | M81: =M71+INDEX(Data_Prices!M:M,MATCH($G81,Data_Prices!$A:$A,0))*M$97 -> 0.16448404 | N81: =N71+INDEX(Data_Prices!N:N,MATCH($G81,Data_Prices!$A:$A,0))*N$97 -> 0.15070908 | O81: =O71+INDEX(Data_Prices!O:O,MATCH($G81,Data_Prices!$A:$A,0))*O$97 -> 0.15070908 | P81: =P71+INDEX(Data_Prices!P:P,MATCH($G81,Data_Prices!$A:$A,0))*P$97 -> 0.15070908 | Q81: =Q71+INDEX(Data_Prices!Q:Q,MATCH($G81,Data_Prices!$A:$A,0))*Q$97 -> 0.15070908 | R81: =R71+INDEX(Data_Prices!R:R,MATCH($G81,Data_Prices!$A:$A,0))*R$97 -> 0.15070908 | S81: =S71+INDEX(Data_Prices!S:S,MATCH($G81,Data_Prices!$A:$A,0))*S$97 -> 0.15070908 | T81: =T71+INDEX(Data_Prices!T:T,MATCH($G81,Data_Prices!$A:$A,0))*T$97 -> 0.15070908 | U81: =U71+INDEX(Data_Prices!U:U,MATCH($G81,Data_Prices!$A:$A,0))*U$97 -> 0.15070908 | V81: =V71+INDEX(Data_Prices!V:V,MATCH($G81,Data_Prices!$A:$A,0))*V$97 -> 0.15070908 | W81: =W71+INDEX(Data_Prices!W:W,MATCH($G81,Data_Prices!$A:$A,0))*W$97 -> 0.15070908 | X81: =X71+INDEX(Data_Prices!X:X,MATCH($G81,Data_Prices!$A:$A,0))*X$97 -> 0.15070908 | Y81: =Y71+INDEX(Data_Prices!Y:Y,MATCH($G81,Data_Prices!$A:$A,0))*Y$97 -> 0.15070908 | Z81: =Z71+INDEX(Data_Prices!Z:Z,MATCH($G81,Data_Prices!$A:$A,0))*Z$97 -> 0.15070908 | AA81: =AA71+INDEX(Data_Prices!AA:AA,MATCH($G81,Data_Prices!$A:$A,0))*AA$97 -> 0.15070908 | AB81: =AB71+INDEX(Data_Prices!AB:AB,MATCH($G81,Data_Prices!$A:$A,0))*AB$97 -> 0.15070908 | AC81: =AC71+INDEX(Data_Prices!AC:AC,MATCH($G81,Data_Prices!$A:$A,0))*AC$97 -> 0.15070908 | AD81: =AD71+INDEX(Data_Prices!AD:AD,MATCH($G81,Data_Prices!$A:$A,0))*AD$97 -> 0.15070908 | AE81: =AE71+INDEX(Data_Prices!AE:AE,MATCH($G81,Data_Prices!$A:$A,0))*AE$97 -> 0.15070908
B82: ker | C82: =$C$65 -> cem | D82: Kerosene | E82: $/liter | F82: atp | G82: =Settings!$B$3&".mit.nce."&Settings!$B$4&"."&$B82&".a."&$J$65 -> egy.mit.nce.ind.ker.a.1 | H82: =Settings!$B$3&".mit.atp."&$C$65&"."&$B82&".e."&$J$65 -> egy.mit.atp.cem.ker.e.1 | K82: =K72+INDEX(Data_Prices!K:K,MATCH($G82,Data_Prices!$A:$A,0))*K$97 -> 0.48429424 | L82: =L72+INDEX(Data_Prices!L:L,MATCH($G82,Data_Prices!$A:$A,0))*L$97 -> 0.45642817 | M82: =M72+INDEX(Data_Prices!M:M,MATCH($G82,Data_Prices!$A:$A,0))*M$97 -> 0.4316892 | N82: =N72+INDEX(Data_Prices!N:N,MATCH($G82,Data_Prices!$A:$A,0))*N$97 -> 0.42507558 | O82: =O72+INDEX(Data_Prices!O:O,MATCH($G82,Data_Prices!$A:$A,0))*O$97 -> 0.42507558 | P82: =P72+INDEX(Data_Prices!P:P,MATCH($G82,Data_Prices!$A:$A,0))*P$97 -> 0.42507558 | Q82: =Q72+INDEX(Data_Prices!Q:Q,MATCH($G82,Data_Prices!$A:$A,0))*Q$97 -> 0.42507558 | R82: =R72+INDEX(Data_Prices!R:R,MATCH($G82,Data_Prices!$A:$A,0))*R$97 -> 0.42507558 | S82: =S72+INDEX(Data_Prices!S:S,MATCH($G82,Data_Prices!$A:$A,0))*S$97 -> 0.42507558 | T82: =T72+INDEX(Data_Prices!T:T,MATCH($G82,Data_Prices!$A:$A,0))*T$97 -> 0.42507558 | U82: =U72+INDEX(Data_Prices!U:U,MATCH($G82,Data_Prices!$A:$A,0))*U$97 -> 0.42507558 | V82: =V72+INDEX(Data_Prices!V:V,MATCH($G82,Data_Prices!$A:$A,0))*V$97 -> 0.42507558 | W82: =W72+INDEX(Data_Prices!W:W,MATCH($G82,Data_Prices!$A:$A,0))*W$97 -> 0.42507558 | X82: =X72+INDEX(Data_Prices!X:X,MATCH($G82,Data_Prices!$A:$A,0))*X$97 -> 0.42507558 | Y82: =Y72+INDEX(Data_Prices!Y:Y,MATCH($G82,Data_Prices!$A:$A,0))*Y$97 -> 0.42507558 | Z82: =Z72+INDEX(Data_Prices!Z:Z,MATCH($G82,Data_Prices!$A:$A,0))*Z$97 -> 0.42507558 | AA82: =AA72+INDEX(Data_Prices!AA:AA,MATCH($G82,Data_Prices!$A:$A,0))*AA$97 -> 0.42507558 | AB82: =AB72+INDEX(Data_Prices!AB:AB,MATCH($G82,Data_Prices!$A:$A,0))*AB$97 -> 0.42507558 | AC82: =AC72+INDEX(Data_Prices!AC:AC,MATCH($G82,Data_Prices!$A:$A,0))*AC$97 -> 0.42507558 | AD82: =AD72+INDEX(Data_Prices!AD:AD,MATCH($G82,Data_Prices!$A:$A,0))*AD$97 -> 0.42507558 | AE82: =AE72+INDEX(Data_Prices!AE:AE,MATCH($G82,Data_Prices!$A:$A,0))*AE$97 -> 0.42507558
B83: oop | C83: =$C$65 -> cem | D83: Other oil products | E83: $/bbl | F83: atp | G83: =Settings!$B$3&".mit.nce."&Settings!$B$4&"."&$B83&".a."&$J$65 -> egy.mit.nce.ind.oop.a.1 | H83: =Settings!$B$3&".mit.atp."&$C$65&"."&$B83&".e."&$J$65 -> egy.mit.atp.cem.oop.e.1 | K83: =K73+INDEX(Data_Prices!K:K,MATCH($G83,Data_Prices!$A:$A,0))*K$97 -> 41.500338 | L83: =L73+INDEX(Data_Prices!L:L,MATCH($G83,Data_Prices!$A:$A,0))*L$97 -> 34.41537 | M83: =M73+INDEX(Data_Prices!M:M,MATCH($G83,Data_Prices!$A:$A,0))*M$97 -> 37.368961 | N83: =N73+INDEX(Data_Prices!N:N,MATCH($G83,Data_Prices!$A:$A,0))*N$97 -> 28.982761 | O83: =O73+INDEX(Data_Prices!O:O,MATCH($G83,Data_Prices!$A:$A,0))*O$97 -> 15 | P83: =P73+INDEX(Data_Prices!P:P,MATCH($G83,Data_Prices!$A:$A,0))*P$97 -> 24.25863 | Q83: =Q73+INDEX(Data_Prices!Q:Q,MATCH($G83,Data_Prices!$A:$A,0))*Q$97 -> 15 | R83: =R73+INDEX(Data_Prices!R:R,MATCH($G83,Data_Prices!$A:$A,0))*R$97 -> 15 | S83: =S73+INDEX(Data_Prices!S:S,MATCH($G83,Data_Prices!$A:$A,0))*S$97 -> 15 | T83: =T73+INDEX(Data_Prices!T:T,MATCH($G83,Data_Prices!$A:$A,0))*T$97 -> 15 | U83: =U73+INDEX(Data_Prices!U:U,MATCH($G83,Data_Prices!$A:$A,0))*U$97 -> 15 | V83: =V73+INDEX(Data_Prices!V:V,MATCH($G83,Data_Prices!$A:$A,0))*V$97 -> 15 | W83: =W73+INDEX(Data_Prices!W:W,MATCH($G83,Data_Prices!$A:$A,0))*W$97 -> 15 | X83: =X73+INDEX(Data_Prices!X:X,MATCH($G83,Data_Prices!$A:$A,0))*X$97 -> 15 | Y83: =Y73+INDEX(Data_Prices!Y:Y,MATCH($G83,Data_Prices!$A:$A,0))*Y$97 -> 15 | Z83: =Z73+INDEX(Data_Prices!Z:Z,MATCH($G83,Data_Prices!$A:$A,0))*Z$97 -> 15 | AA83: =AA73+INDEX(Data_Prices!AA:AA,MATCH($G83,Data_Prices!$A:$A,0))*AA$97 -> 15 | AB83: =AB73+INDEX(Data_Prices!AB:AB,MATCH($G83,Data_Prices!$A:$A,0))*AB$97 -> 15 | AC83: =AC73+INDEX(Data_Prices!AC:AC,MATCH($G83,Data_Prices!$A:$A,0))*AC$97 -> 15 | AD83: =AD73+INDEX(Data_Prices!AD:AD,MATCH($G83,Data_Prices!$A:$A,0))*AD$97 -> 15 | AE83: =AE73+INDEX(Data_Prices!AE:AE,MATCH($G83,Data_Prices!$A:$A,0))*AE$97 -> 15
B84: bio | C84: =$C$65 -> cem | D84: Biomass | E84: $/GJ | F84: atp | G84: =Settings!$B$3&".mit.nce."&Settings!$B$4&"."&$B84&".a."&$J$65 -> egy.mit.nce.ind.bio.a.1 | H84: =Settings!$B$3&".mit.atp."&$C$65&"."&$B84&".e."&$J$65 -> egy.mit.atp.cem.bio.e.1 | K84: =K74+INDEX(Data_Prices!K:K,MATCH($G84,Data_Prices!$A:$A,0))*K$97 -> 15.334551 | L84: =L74+INDEX(Data_Prices!L:L,MATCH($G84,Data_Prices!$A:$A,0))*L$97 -> 14.199528 | M84: =M74+INDEX(Data_Prices!M:M,MATCH($G84,Data_Prices!$A:$A,0))*M$97 -> 13.840442 | N84: =N74+INDEX(Data_Prices!N:N,MATCH($G84,Data_Prices!$A:$A,0))*N$97 -> 13.567727 | O84: =O74+INDEX(Data_Prices!O:O,MATCH($G84,Data_Prices!$A:$A,0))*O$97 -> 13.567727 | P84: =P74+INDEX(Data_Prices!P:P,MATCH($G84,Data_Prices!$A:$A,0))*P$97 -> 13.567727 | Q84: =Q74+INDEX(Data_Prices!Q:Q,MATCH($G84,Data_Prices!$A:$A,0))*Q$97 -> 13.567727 | R84: =R74+INDEX(Data_Prices!R:R,MATCH($G84,Data_Prices!$A:$A,0))*R$97 -> 13.567727 | S84: =S74+INDEX(Data_Prices!S:S,MATCH($G84,Data_Prices!$A:$A,0))*S$97 -> 13.567727 | T84: =T74+INDEX(Data_Prices!T:T,MATCH($G84,Data_Prices!$A:$A,0))*T$97 -> 13.567727 | U84: =U74+INDEX(Data_Prices!U:U,MATCH($G84,Data_Prices!$A:$A,0))*U$97 -> 13.567727 | V84: =V74+INDEX(Data_Prices!V:V,MATCH($G84,Data_Prices!$A:$A,0))*V$97 -> 13.567727 | W84: =W74+INDEX(Data_Prices!W:W,MATCH($G84,Data_Prices!$A:$A,0))*W$97 -> 13.567727 | X84: =X74+INDEX(Data_Prices!X:X,MATCH($G84,Data_Prices!$A:$A,0))*X$97 -> 13.567727 | Y84: =Y74+INDEX(Data_Prices!Y:Y,MATCH($G84,Data_Prices!$A:$A,0))*Y$97 -> 13.567727 | Z84: =Z74+INDEX(Data_Prices!Z:Z,MATCH($G84,Data_Prices!$A:$A,0))*Z$97 -> 13.567727 | AA84: =AA74+INDEX(Data_Prices!AA:AA,MATCH($G84,Data_Prices!$A:$A,0))*AA$97 -> 13.567727 | AB84: =AB74+INDEX(Data_Prices!AB:AB,MATCH($G84,Data_Prices!$A:$A,0))*AB$97 -> 13.567727 | AC84: =AC74+INDEX(Data_Prices!AC:AC,MATCH($G84,Data_Prices!$A:$A,0))*AC$97 -> 13.567727 | AD84: =AD74+INDEX(Data_Prices!AD:AD,MATCH($G84,Data_Prices!$A:$A,0))*AD$97 -> 13.567727 | AE84: =AE74+INDEX(Data_Prices!AE:AE,MATCH($G84,Data_Prices!$A:$A,0))*AE$97 -> 13.567727
B85: ren | C85: =$C$65 -> cem | D85: Self-generated renewables | E85: $/kwh | F85: atp | G85: =Settings!$B$3&".mit.nce."&Settings!$B$4&"."&$B85&".a."&$J$65 -> egy.mit.nce.ind.ren.a.1 | H85: =Settings!$B$3&".mit.atp."&$C$65&"."&$B85&".e."&$J$65 -> egy.mit.atp.cem.ren.e.1 | K85: =K75+INDEX(Data_Prices!K:K,MATCH($G85,Data_Prices!$A:$A,0))*K$97 -> 0 | L85: =L75+INDEX(Data_Prices!L:L,MATCH($G85,Data_Prices!$A:$A,0))*L$97 -> 0.14404499 | M85: =M75+INDEX(Data_Prices!M:M,MATCH($G85,Data_Prices!$A:$A,0))*M$97 -> 0.14102041 | N85: =N75+INDEX(Data_Prices!N:N,MATCH($G85,Data_Prices!$A:$A,0))*N$97 -> 0.13511636 | O85: =O75+INDEX(Data_Prices!O:O,MATCH($G85,Data_Prices!$A:$A,0))*O$97 -> 0.13098826 | P85: =P75+INDEX(Data_Prices!P:P,MATCH($G85,Data_Prices!$A:$A,0))*P$97 -> 0.12790842 | Q85: =Q75+INDEX(Data_Prices!Q:Q,MATCH($G85,Data_Prices!$A:$A,0))*Q$97 -> 0.12481431 | R85: =R75+INDEX(Data_Prices!R:R,MATCH($G85,Data_Prices!$A:$A,0))*R$97 -> 0.12146026 | S85: =S75+INDEX(Data_Prices!S:S,MATCH($G85,Data_Prices!$A:$A,0))*S$97 -> 0.11795074 | T85: =T75+INDEX(Data_Prices!T:T,MATCH($G85,Data_Prices!$A:$A,0))*T$97 -> 0.11419916 | U85: =U75+INDEX(Data_Prices!U:U,MATCH($G85,Data_Prices!$A:$A,0))*U$97 -> 0.1136651 | V85: =V75+INDEX(Data_Prices!V:V,MATCH($G85,Data_Prices!$A:$A,0))*V$97 -> 0.11301693 | W85: =W75+INDEX(Data_Prices!W:W,MATCH($G85,Data_Prices!$A:$A,0))*W$97 -> 0.11231407 | X85: =X75+INDEX(Data_Prices!X:X,MATCH($G85,Data_Prices!$A:$A,0))*X$97 -> 0.11142204 | Y85: =Y75+INDEX(Data_Prices!Y:Y,MATCH($G85,Data_Prices!$A:$A,0))*Y$97 -> 0.11043412 | Z85: =Z75+INDEX(Data_Prices!Z:Z,MATCH($G85,Data_Prices!$A:$A,0))*Z$97 -> 0.10948397 | AA85: =AA75+INDEX(Data_Prices!AA:AA,MATCH($G85,Data_Prices!$A:$A,0))*AA$97 -> 0.10839192 | AB85: =AB75+INDEX(Data_Prices!AB:AB,MATCH($G85,Data_Prices!$A:$A,0))*AB$97 -> 0.10735443 | AC85: =AC75+INDEX(Data_Prices!AC:AC,MATCH($G85,Data_Prices!$A:$A,0))*AC$97 -> 0.10516868 | AD85: =AD75+INDEX(Data_Prices!AD:AD,MATCH($G85,Data_Prices!$A:$A,0))*AD$97 -> 0.10305798 | AE85: =AE75+INDEX(Data_Prices!AE:AE,MATCH($G85,Data_Prices!$A:$A,0))*AE$97 -> 0.10093184
B86: Shadow price: post-tax + shadow price of non-price policies x share acting on efficiency
B87: coa | C87: =$C$65 -> cem | D87: Coal | E87: $/GJ | F87: shp | G87: =Settings!$B$3&".mit.shp."&$B87&"."&Settings!$B$4&"."&$J$65 -> egy.mit.shp.coa.ind.1 | H87: =Settings!$B$3&".mit.shp."&$C$65&"."&$B87&".e."&$J$65 -> egy.mit.shp.cem.coa.e.1 | K87: =K77+INDEX(Data_Prices!K:K,MATCH($G87,Data_Prices!$A:$A,0))*K$98 -> 11.182902 | L87: =L77+INDEX(Data_Prices!L:L,MATCH($G87,Data_Prices!$A:$A,0))*L$98 -> 10.523361 | M87: =M77+INDEX(Data_Prices!M:M,MATCH($G87,Data_Prices!$A:$A,0))*M$98 -> 10.299561 | N87: =N77+INDEX(Data_Prices!N:N,MATCH($G87,Data_Prices!$A:$A,0))*N$98 -> 9.5775284 | O87: =O77+INDEX(Data_Prices!O:O,MATCH($G87,Data_Prices!$A:$A,0))*O$98 -> 8.4854783 | P87: =P77+INDEX(Data_Prices!P:P,MATCH($G87,Data_Prices!$A:$A,0))*P$98 -> 9.0871922 | Q87: =Q77+INDEX(Data_Prices!Q:Q,MATCH($G87,Data_Prices!$A:$A,0))*Q$98 -> 9.2229237 | R87: =R77+INDEX(Data_Prices!R:R,MATCH($G87,Data_Prices!$A:$A,0))*R$98 -> 9.158565 | S87: =S77+INDEX(Data_Prices!S:S,MATCH($G87,Data_Prices!$A:$A,0))*S$98 -> 9.0895479 | T87: =T77+INDEX(Data_Prices!T:T,MATCH($G87,Data_Prices!$A:$A,0))*T$98 -> 9.0156817 | U87: =U77+INDEX(Data_Prices!U:U,MATCH($G87,Data_Prices!$A:$A,0))*U$98 -> 8.9443978 | V87: =V77+INDEX(Data_Prices!V:V,MATCH($G87,Data_Prices!$A:$A,0))*V$98 -> 8.9443978 | W87: =W77+INDEX(Data_Prices!W:W,MATCH($G87,Data_Prices!$A:$A,0))*W$98 -> 8.9443978 | X87: =X77+INDEX(Data_Prices!X:X,MATCH($G87,Data_Prices!$A:$A,0))*X$98 -> 8.9443978 | Y87: =Y77+INDEX(Data_Prices!Y:Y,MATCH($G87,Data_Prices!$A:$A,0))*Y$98 -> 8.9443978 | Z87: =Z77+INDEX(Data_Prices!Z:Z,MATCH($G87,Data_Prices!$A:$A,0))*Z$98 -> 8.9443978 | AA87: =AA77+INDEX(Data_Prices!AA:AA,MATCH($G87,Data_Prices!$A:$A,0))*AA$98 -> 8.9443978 | AB87: =AB77+INDEX(Data_Prices!AB:AB,MATCH($G87,Data_Prices!$A:$A,0))*AB$98 -> 8.9443978 | AC87: =AC77+INDEX(Data_Prices!AC:AC,MATCH($G87,Data_Prices!$A:$A,0))*AC$98 -> 8.9443978 | AD87: =AD77+INDEX(Data_Prices!AD:AD,MATCH($G87,Data_Prices!$A:$A,0))*AD$98 -> 8.9443978 | AE87: =AE77+INDEX(Data_Prices!AE:AE,MATCH($G87,Data_Prices!$A:$A,0))*AE$98 -> 8.9443978
B88: nga | C88: =$C$65 -> cem | D88: Natural gas | E88: $/GJ | F88: shp | G88: =Settings!$B$3&".mit.shp."&$B88&"."&Settings!$B$4&"."&$J$65 -> egy.mit.shp.nga.ind.1 | H88: =Settings!$B$3&".mit.shp."&$C$65&"."&$B88&".e."&$J$65 -> egy.mit.shp.cem.nga.e.1 | K88: =K78+INDEX(Data_Prices!K:K,MATCH($G88,Data_Prices!$A:$A,0))*K$98 -> 6.0634636 | L88: =L78+INDEX(Data_Prices!L:L,MATCH($G88,Data_Prices!$A:$A,0))*L$98 -> 5.4510151 | M88: =M78+INDEX(Data_Prices!M:M,MATCH($G88,Data_Prices!$A:$A,0))*M$98 -> 5.1193563 | N88: =N78+INDEX(Data_Prices!N:N,MATCH($G88,Data_Prices!$A:$A,0))*N$98 -> 5.0821846 | O88: =O78+INDEX(Data_Prices!O:O,MATCH($G88,Data_Prices!$A:$A,0))*O$98 -> 5.0821846 | P88: =P78+INDEX(Data_Prices!P:P,MATCH($G88,Data_Prices!$A:$A,0))*P$98 -> 5.0821846 | Q88: =Q78+INDEX(Data_Prices!Q:Q,MATCH($G88,Data_Prices!$A:$A,0))*Q$98 -> 5.0821846 | R88: =R78+INDEX(Data_Prices!R:R,MATCH($G88,Data_Prices!$A:$A,0))*R$98 -> 5.0821846 | S88: =S78+INDEX(Data_Prices!S:S,MATCH($G88,Data_Prices!$A:$A,0))*S$98 -> 5.0821846 | T88: =T78+INDEX(Data_Prices!T:T,MATCH($G88,Data_Prices!$A:$A,0))*T$98 -> 5.0821846 | U88: =U78+INDEX(Data_Prices!U:U,MATCH($G88,Data_Prices!$A:$A,0))*U$98 -> 5.0821846 | V88: =V78+INDEX(Data_Prices!V:V,MATCH($G88,Data_Prices!$A:$A,0))*V$98 -> 5.0821846 | W88: =W78+INDEX(Data_Prices!W:W,MATCH($G88,Data_Prices!$A:$A,0))*W$98 -> 5.0821846 | X88: =X78+INDEX(Data_Prices!X:X,MATCH($G88,Data_Prices!$A:$A,0))*X$98 -> 5.0821846 | Y88: =Y78+INDEX(Data_Prices!Y:Y,MATCH($G88,Data_Prices!$A:$A,0))*Y$98 -> 5.0821846 | Z88: =Z78+INDEX(Data_Prices!Z:Z,MATCH($G88,Data_Prices!$A:$A,0))*Z$98 -> 5.0821846 | AA88: =AA78+INDEX(Data_Prices!AA:AA,MATCH($G88,Data_Prices!$A:$A,0))*AA$98 -> 5.0821846 | AB88: =AB78+INDEX(Data_Prices!AB:AB,MATCH($G88,Data_Prices!$A:$A,0))*AB$98 -> 5.0821846 | AC88: =AC78+INDEX(Data_Prices!AC:AC,MATCH($G88,Data_Prices!$A:$A,0))*AC$98 -> 5.0821846 | AD88: =AD78+INDEX(Data_Prices!AD:AD,MATCH($G88,Data_Prices!$A:$A,0))*AD$98 -> 5.0821846 | AE88: =AE78+INDEX(Data_Prices!AE:AE,MATCH($G88,Data_Prices!$A:$A,0))*AE$98 -> 5.0821846
B89: gso | C89: =$C$65 -> cem | D89: Gasoline | E89: $/liter | F89: shp | G89: =Settings!$B$3&".mit.shp."&$B89&"."&Settings!$B$4&"."&$J$65 -> egy.mit.shp.gso.ind.1 | H89: =Settings!$B$3&".mit.shp."&$C$65&"."&$B89&".e."&$J$65 -> egy.mit.shp.cem.gso.e.1 | K89: =K79+INDEX(Data_Prices!K:K,MATCH($G89,Data_Prices!$A:$A,0))*K$98 -> 0.67114653 | L89: =L79+INDEX(Data_Prices!L:L,MATCH($G89,Data_Prices!$A:$A,0))*L$98 -> 0.61197798 | M89: =M79+INDEX(Data_Prices!M:M,MATCH($G89,Data_Prices!$A:$A,0))*M$98 -> 0.61180975 | N89: =N79+INDEX(Data_Prices!N:N,MATCH($G89,Data_Prices!$A:$A,0))*N$98 -> 0.6035831 | O89: =O79+INDEX(Data_Prices!O:O,MATCH($G89,Data_Prices!$A:$A,0))*O$98 -> 0.6035831 | P89: =P79+INDEX(Data_Prices!P:P,MATCH($G89,Data_Prices!$A:$A,0))*P$98 -> 0.6035831 | Q89: =Q79+INDEX(Data_Prices!Q:Q,MATCH($G89,Data_Prices!$A:$A,0))*Q$98 -> 0.6035831 | R89: =R79+INDEX(Data_Prices!R:R,MATCH($G89,Data_Prices!$A:$A,0))*R$98 -> 0.6035831 | S89: =S79+INDEX(Data_Prices!S:S,MATCH($G89,Data_Prices!$A:$A,0))*S$98 -> 0.6035831 | T89: =T79+INDEX(Data_Prices!T:T,MATCH($G89,Data_Prices!$A:$A,0))*T$98 -> 0.6035831 | U89: =U79+INDEX(Data_Prices!U:U,MATCH($G89,Data_Prices!$A:$A,0))*U$98 -> 0.6035831 | V89: =V79+INDEX(Data_Prices!V:V,MATCH($G89,Data_Prices!$A:$A,0))*V$98 -> 0.6035831 | W89: =W79+INDEX(Data_Prices!W:W,MATCH($G89,Data_Prices!$A:$A,0))*W$98 -> 0.6035831 | X89: =X79+INDEX(Data_Prices!X:X,MATCH($G89,Data_Prices!$A:$A,0))*X$98 -> 0.6035831 | Y89: =Y79+INDEX(Data_Prices!Y:Y,MATCH($G89,Data_Prices!$A:$A,0))*Y$98 -> 0.6035831 | Z89: =Z79+INDEX(Data_Prices!Z:Z,MATCH($G89,Data_Prices!$A:$A,0))*Z$98 -> 0.6035831 | AA89: =AA79+INDEX(Data_Prices!AA:AA,MATCH($G89,Data_Prices!$A:$A,0))*AA$98 -> 0.6035831 | AB89: =AB79+INDEX(Data_Prices!AB:AB,MATCH($G89,Data_Prices!$A:$A,0))*AB$98 -> 0.6035831 | AC89: =AC79+INDEX(Data_Prices!AC:AC,MATCH($G89,Data_Prices!$A:$A,0))*AC$98 -> 0.6035831 | AD89: =AD79+INDEX(Data_Prices!AD:AD,MATCH($G89,Data_Prices!$A:$A,0))*AD$98 -> 0.6035831 | AE89: =AE79+INDEX(Data_Prices!AE:AE,MATCH($G89,Data_Prices!$A:$A,0))*AE$98 -> 0.6035831
B90: die | C90: =$C$65 -> cem | D90: Diesel | E90: $/liter | F90: shp | G90: =Settings!$B$3&".mit.shp."&$B90&"."&Settings!$B$4&"."&$J$65 -> egy.mit.shp.die.ind.1 | H90: =Settings!$B$3&".mit.shp."&$C$65&"."&$B90&".e."&$J$65 -> egy.mit.shp.cem.die.e.1 | K90: =K80+INDEX(Data_Prices!K:K,MATCH($G90,Data_Prices!$A:$A,0))*K$98 -> 0.55971121 | L90: =L80+INDEX(Data_Prices!L:L,MATCH($G90,Data_Prices!$A:$A,0))*L$98 -> 0.49458873 | M90: =M80+INDEX(Data_Prices!M:M,MATCH($G90,Data_Prices!$A:$A,0))*M$98 -> 0.50778655 | N90: =N80+INDEX(Data_Prices!N:N,MATCH($G90,Data_Prices!$A:$A,0))*N$98 -> 0.47043643 | O90: =O80+INDEX(Data_Prices!O:O,MATCH($G90,Data_Prices!$A:$A,0))*O$98 -> 0.47043643 | P90: =P80+INDEX(Data_Prices!P:P,MATCH($G90,Data_Prices!$A:$A,0))*P$98 -> 0.47043643 | Q90: =Q80+INDEX(Data_Prices!Q:Q,MATCH($G90,Data_Prices!$A:$A,0))*Q$98 -> 0.47043643 | R90: =R80+INDEX(Data_Prices!R:R,MATCH($G90,Data_Prices!$A:$A,0))*R$98 -> 0.47043643 | S90: =S80+INDEX(Data_Prices!S:S,MATCH($G90,Data_Prices!$A:$A,0))*S$98 -> 0.47043643 | T90: =T80+INDEX(Data_Prices!T:T,MATCH($G90,Data_Prices!$A:$A,0))*T$98 -> 0.47043643 | U90: =U80+INDEX(Data_Prices!U:U,MATCH($G90,Data_Prices!$A:$A,0))*U$98 -> 0.47043643 | V90: =V80+INDEX(Data_Prices!V:V,MATCH($G90,Data_Prices!$A:$A,0))*V$98 -> 0.47043643 | W90: =W80+INDEX(Data_Prices!W:W,MATCH($G90,Data_Prices!$A:$A,0))*W$98 -> 0.47043643 | X90: =X80+INDEX(Data_Prices!X:X,MATCH($G90,Data_Prices!$A:$A,0))*X$98 -> 0.47043643 | Y90: =Y80+INDEX(Data_Prices!Y:Y,MATCH($G90,Data_Prices!$A:$A,0))*Y$98 -> 0.47043643 | Z90: =Z80+INDEX(Data_Prices!Z:Z,MATCH($G90,Data_Prices!$A:$A,0))*Z$98 -> 0.47043643 | AA90: =AA80+INDEX(Data_Prices!AA:AA,MATCH($G90,Data_Prices!$A:$A,0))*AA$98 -> 0.47043643 | AB90: =AB80+INDEX(Data_Prices!AB:AB,MATCH($G90,Data_Prices!$A:$A,0))*AB$98 -> 0.47043643 | AC90: =AC80+INDEX(Data_Prices!AC:AC,MATCH($G90,Data_Prices!$A:$A,0))*AC$98 -> 0.47043643 | AD90: =AD80+INDEX(Data_Prices!AD:AD,MATCH($G90,Data_Prices!$A:$A,0))*AD$98 -> 0.47043643 | AE90: =AE80+INDEX(Data_Prices!AE:AE,MATCH($G90,Data_Prices!$A:$A,0))*AE$98 -> 0.47043643
B91: lpg | C91: =$C$65 -> cem | D91: LPG | E91: $/liter | F91: shp | G91: =Settings!$B$3&".mit.shp."&$B91&"."&Settings!$B$4&"."&$J$65 -> egy.mit.shp.lpg.ind.1 | H91: =Settings!$B$3&".mit.shp."&$C$65&"."&$B91&".e."&$J$65 -> egy.mit.shp.cem.lpg.e.1 | K91: =K81+INDEX(Data_Prices!K:K,MATCH($G91,Data_Prices!$A:$A,0))*K$98 -> 0.20036669 | L91: =L81+INDEX(Data_Prices!L:L,MATCH($G91,Data_Prices!$A:$A,0))*L$98 -> 0.15734474 | M91: =M81+INDEX(Data_Prices!M:M,MATCH($G91,Data_Prices!$A:$A,0))*M$98 -> 0.16448404 | N91: =N81+INDEX(Data_Prices!N:N,MATCH($G91,Data_Prices!$A:$A,0))*N$98 -> 0.15070908 | O91: =O81+INDEX(Data_Prices!O:O,MATCH($G91,Data_Prices!$A:$A,0))*O$98 -> 0.15070908 | P91: =P81+INDEX(Data_Prices!P:P,MATCH($G91,Data_Prices!$A:$A,0))*P$98 -> 0.15070908 | Q91: =Q81+INDEX(Data_Prices!Q:Q,MATCH($G91,Data_Prices!$A:$A,0))*Q$98 -> 0.15070908 | R91: =R81+INDEX(Data_Prices!R:R,MATCH($G91,Data_Prices!$A:$A,0))*R$98 -> 0.15070908 | S91: =S81+INDEX(Data_Prices!S:S,MATCH($G91,Data_Prices!$A:$A,0))*S$98 -> 0.15070908 | T91: =T81+INDEX(Data_Prices!T:T,MATCH($G91,Data_Prices!$A:$A,0))*T$98 -> 0.15070908 | U91: =U81+INDEX(Data_Prices!U:U,MATCH($G91,Data_Prices!$A:$A,0))*U$98 -> 0.15070908 | V91: =V81+INDEX(Data_Prices!V:V,MATCH($G91,Data_Prices!$A:$A,0))*V$98 -> 0.15070908 | W91: =W81+INDEX(Data_Prices!W:W,MATCH($G91,Data_Prices!$A:$A,0))*W$98 -> 0.15070908 | X91: =X81+INDEX(Data_Prices!X:X,MATCH($G91,Data_Prices!$A:$A,0))*X$98 -> 0.15070908 | Y91: =Y81+INDEX(Data_Prices!Y:Y,MATCH($G91,Data_Prices!$A:$A,0))*Y$98 -> 0.15070908 | Z91: =Z81+INDEX(Data_Prices!Z:Z,MATCH($G91,Data_Prices!$A:$A,0))*Z$98 -> 0.15070908 | AA91: =AA81+INDEX(Data_Prices!AA:AA,MATCH($G91,Data_Prices!$A:$A,0))*AA$98 -> 0.15070908 | AB91: =AB81+INDEX(Data_Prices!AB:AB,MATCH($G91,Data_Prices!$A:$A,0))*AB$98 -> 0.15070908 | AC91: =AC81+INDEX(Data_Prices!AC:AC,MATCH($G91,Data_Prices!$A:$A,0))*AC$98 -> 0.15070908 | AD91: =AD81+INDEX(Data_Prices!AD:AD,MATCH($G91,Data_Prices!$A:$A,0))*AD$98 -> 0.15070908 | AE91: =AE81+INDEX(Data_Prices!AE:AE,MATCH($G91,Data_Prices!$A:$A,0))*AE$98 -> 0.15070908
B92: ker | C92: =$C$65 -> cem | D92: Kerosene | E92: $/liter | F92: shp | G92: =Settings!$B$3&".mit.shp."&$B92&"."&Settings!$B$4&"."&$J$65 -> egy.mit.shp.ker.ind.1 | H92: =Settings!$B$3&".mit.shp."&$C$65&"."&$B92&".e."&$J$65 -> egy.mit.shp.cem.ker.e.1 | K92: =K82+INDEX(Data_Prices!K:K,MATCH($G92,Data_Prices!$A:$A,0))*K$98 -> 0.48429424 | L92: =L82+INDEX(Data_Prices!L:L,MATCH($G92,Data_Prices!$A:$A,0))*L$98 -> 0.45642817 | M92: =M82+INDEX(Data_Prices!M:M,MATCH($G92,Data_Prices!$A:$A,0))*M$98 -> 0.4316892 | N92: =N82+INDEX(Data_Prices!N:N,MATCH($G92,Data_Prices!$A:$A,0))*N$98 -> 0.42507558 | O92: =O82+INDEX(Data_Prices!O:O,MATCH($G92,Data_Prices!$A:$A,0))*O$98 -> 0.42507558 | P92: =P82+INDEX(Data_Prices!P:P,MATCH($G92,Data_Prices!$A:$A,0))*P$98 -> 0.42507558 | Q92: =Q82+INDEX(Data_Prices!Q:Q,MATCH($G92,Data_Prices!$A:$A,0))*Q$98 -> 0.42507558 | R92: =R82+INDEX(Data_Prices!R:R,MATCH($G92,Data_Prices!$A:$A,0))*R$98 -> 0.42507558 | S92: =S82+INDEX(Data_Prices!S:S,MATCH($G92,Data_Prices!$A:$A,0))*S$98 -> 0.42507558 | T92: =T82+INDEX(Data_Prices!T:T,MATCH($G92,Data_Prices!$A:$A,0))*T$98 -> 0.42507558 | U92: =U82+INDEX(Data_Prices!U:U,MATCH($G92,Data_Prices!$A:$A,0))*U$98 -> 0.42507558 | V92: =V82+INDEX(Data_Prices!V:V,MATCH($G92,Data_Prices!$A:$A,0))*V$98 -> 0.42507558 | W92: =W82+INDEX(Data_Prices!W:W,MATCH($G92,Data_Prices!$A:$A,0))*W$98 -> 0.42507558 | X92: =X82+INDEX(Data_Prices!X:X,MATCH($G92,Data_Prices!$A:$A,0))*X$98 -> 0.42507558 | Y92: =Y82+INDEX(Data_Prices!Y:Y,MATCH($G92,Data_Prices!$A:$A,0))*Y$98 -> 0.42507558 | Z92: =Z82+INDEX(Data_Prices!Z:Z,MATCH($G92,Data_Prices!$A:$A,0))*Z$98 -> 0.42507558 | AA92: =AA82+INDEX(Data_Prices!AA:AA,MATCH($G92,Data_Prices!$A:$A,0))*AA$98 -> 0.42507558 | AB92: =AB82+INDEX(Data_Prices!AB:AB,MATCH($G92,Data_Prices!$A:$A,0))*AB$98 -> 0.42507558 | AC92: =AC82+INDEX(Data_Prices!AC:AC,MATCH($G92,Data_Prices!$A:$A,0))*AC$98 -> 0.42507558 | AD92: =AD82+INDEX(Data_Prices!AD:AD,MATCH($G92,Data_Prices!$A:$A,0))*AD$98 -> 0.42507558 | AE92: =AE82+INDEX(Data_Prices!AE:AE,MATCH($G92,Data_Prices!$A:$A,0))*AE$98 -> 0.42507558
B93: oop | C93: =$C$65 -> cem | D93: Other oil products | E93: $/bbl | F93: shp | G93: =Settings!$B$3&".mit.shp."&$B93&"."&Settings!$B$4&"."&$J$65 -> egy.mit.shp.oop.ind.1 | H93: =Settings!$B$3&".mit.shp."&$C$65&"."&$B93&".e."&$J$65 -> egy.mit.shp.cem.oop.e.1 | K93: =K83+INDEX(Data_Prices!K:K,MATCH($G93,Data_Prices!$A:$A,0))*K$98 -> 41.500338 | L93: =L83+INDEX(Data_Prices!L:L,MATCH($G93,Data_Prices!$A:$A,0))*L$98 -> 34.41537 | M93: =M83+INDEX(Data_Prices!M:M,MATCH($G93,Data_Prices!$A:$A,0))*M$98 -> 37.368961 | N93: =N83+INDEX(Data_Prices!N:N,MATCH($G93,Data_Prices!$A:$A,0))*N$98 -> 28.982761 | O93: =O83+INDEX(Data_Prices!O:O,MATCH($G93,Data_Prices!$A:$A,0))*O$98 -> 15 | P93: =P83+INDEX(Data_Prices!P:P,MATCH($G93,Data_Prices!$A:$A,0))*P$98 -> 24.25863 | Q93: =Q83+INDEX(Data_Prices!Q:Q,MATCH($G93,Data_Prices!$A:$A,0))*Q$98 -> 15 | R93: =R83+INDEX(Data_Prices!R:R,MATCH($G93,Data_Prices!$A:$A,0))*R$98 -> 15 | S93: =S83+INDEX(Data_Prices!S:S,MATCH($G93,Data_Prices!$A:$A,0))*S$98 -> 15 | T93: =T83+INDEX(Data_Prices!T:T,MATCH($G93,Data_Prices!$A:$A,0))*T$98 -> 15 | U93: =U83+INDEX(Data_Prices!U:U,MATCH($G93,Data_Prices!$A:$A,0))*U$98 -> 15 | V93: =V83+INDEX(Data_Prices!V:V,MATCH($G93,Data_Prices!$A:$A,0))*V$98 -> 15 | W93: =W83+INDEX(Data_Prices!W:W,MATCH($G93,Data_Prices!$A:$A,0))*W$98 -> 15 | X93: =X83+INDEX(Data_Prices!X:X,MATCH($G93,Data_Prices!$A:$A,0))*X$98 -> 15 | Y93: =Y83+INDEX(Data_Prices!Y:Y,MATCH($G93,Data_Prices!$A:$A,0))*Y$98 -> 15 | Z93: =Z83+INDEX(Data_Prices!Z:Z,MATCH($G93,Data_Prices!$A:$A,0))*Z$98 -> 15 | AA93: =AA83+INDEX(Data_Prices!AA:AA,MATCH($G93,Data_Prices!$A:$A,0))*AA$98 -> 15 | AB93: =AB83+INDEX(Data_Prices!AB:AB,MATCH($G93,Data_Prices!$A:$A,0))*AB$98 -> 15 | AC93: =AC83+INDEX(Data_Prices!AC:AC,MATCH($G93,Data_Prices!$A:$A,0))*AC$98 -> 15 | AD93: =AD83+INDEX(Data_Prices!AD:AD,MATCH($G93,Data_Prices!$A:$A,0))*AD$98 -> 15 | AE93: =AE83+INDEX(Data_Prices!AE:AE,MATCH($G93,Data_Prices!$A:$A,0))*AE$98 -> 15
B94: bio | C94: =$C$65 -> cem | D94: Biomass | E94: $/GJ | F94: shp | G94: =Settings!$B$3&".mit.shp."&$B94&"."&Settings!$B$4&"."&$J$65 -> egy.mit.shp.bio.ind.1 | H94: =Settings!$B$3&".mit.shp."&$C$65&"."&$B94&".e."&$J$65 -> egy.mit.shp.cem.bio.e.1 | K94: =K84+INDEX(Data_Prices!K:K,MATCH($G94,Data_Prices!$A:$A,0))*K$98 -> 15.334551 | L94: =L84+INDEX(Data_Prices!L:L,MATCH($G94,Data_Prices!$A:$A,0))*L$98 -> 14.199528 | M94: =M84+INDEX(Data_Prices!M:M,MATCH($G94,Data_Prices!$A:$A,0))*M$98 -> 13.840442 | N94: =N84+INDEX(Data_Prices!N:N,MATCH($G94,Data_Prices!$A:$A,0))*N$98 -> 13.567727 | O94: =O84+INDEX(Data_Prices!O:O,MATCH($G94,Data_Prices!$A:$A,0))*O$98 -> 13.567727 | P94: =P84+INDEX(Data_Prices!P:P,MATCH($G94,Data_Prices!$A:$A,0))*P$98 -> 13.567727 | Q94: =Q84+INDEX(Data_Prices!Q:Q,MATCH($G94,Data_Prices!$A:$A,0))*Q$98 -> 13.567727 | R94: =R84+INDEX(Data_Prices!R:R,MATCH($G94,Data_Prices!$A:$A,0))*R$98 -> 13.567727 | S94: =S84+INDEX(Data_Prices!S:S,MATCH($G94,Data_Prices!$A:$A,0))*S$98 -> 13.567727 | T94: =T84+INDEX(Data_Prices!T:T,MATCH($G94,Data_Prices!$A:$A,0))*T$98 -> 13.567727 | U94: =U84+INDEX(Data_Prices!U:U,MATCH($G94,Data_Prices!$A:$A,0))*U$98 -> 13.567727 | V94: =V84+INDEX(Data_Prices!V:V,MATCH($G94,Data_Prices!$A:$A,0))*V$98 -> 13.567727 | W94: =W84+INDEX(Data_Prices!W:W,MATCH($G94,Data_Prices!$A:$A,0))*W$98 -> 13.567727 | X94: =X84+INDEX(Data_Prices!X:X,MATCH($G94,Data_Prices!$A:$A,0))*X$98 -> 13.567727 | Y94: =Y84+INDEX(Data_Prices!Y:Y,MATCH($G94,Data_Prices!$A:$A,0))*Y$98 -> 13.567727 | Z94: =Z84+INDEX(Data_Prices!Z:Z,MATCH($G94,Data_Prices!$A:$A,0))*Z$98 -> 13.567727 | AA94: =AA84+INDEX(Data_Prices!AA:AA,MATCH($G94,Data_Prices!$A:$A,0))*AA$98 -> 13.567727 | AB94: =AB84+INDEX(Data_Prices!AB:AB,MATCH($G94,Data_Prices!$A:$A,0))*AB$98 -> 13.567727 | AC94: =AC84+INDEX(Data_Prices!AC:AC,MATCH($G94,Data_Prices!$A:$A,0))*AC$98 -> 13.567727 | AD94: =AD84+INDEX(Data_Prices!AD:AD,MATCH($G94,Data_Prices!$A:$A,0))*AD$98 -> 13.567727 | AE94: =AE84+INDEX(Data_Prices!AE:AE,MATCH($G94,Data_Prices!$A:$A,0))*AE$98 -> 13.567727
B95: ren | C95: =$C$65 -> cem | D95: Self-generated renewables | E95: $/kwh | F95: shp | G95: =Settings!$B$3&".mit.shp."&$B95&"."&Settings!$B$4&"."&$J$65 -> egy.mit.shp.ren.ind.1 | H95: =Settings!$B$3&".mit.shp."&$C$65&"."&$B95&".e."&$J$65 -> egy.mit.shp.cem.ren.e.1 | K95: =K85+INDEX(Data_Prices!K:K,MATCH($G95,Data_Prices!$A:$A,0))*K$98 -> 0 | L95: =L85+INDEX(Data_Prices!L:L,MATCH($G95,Data_Prices!$A:$A,0))*L$98 -> 0.14404499 | M95: =M85+INDEX(Data_Prices!M:M,MATCH($G95,Data_Prices!$A:$A,0))*M$98 -> 0.14102041 | N95: =N85+INDEX(Data_Prices!N:N,MATCH($G95,Data_Prices!$A:$A,0))*N$98 -> 0.13511636 | O95: =O85+INDEX(Data_Prices!O:O,MATCH($G95,Data_Prices!$A:$A,0))*O$98 -> 0.13098826 | P95: =P85+INDEX(Data_Prices!P:P,MATCH($G95,Data_Prices!$A:$A,0))*P$98 -> 0.12790842 | Q95: =Q85+INDEX(Data_Prices!Q:Q,MATCH($G95,Data_Prices!$A:$A,0))*Q$98 -> 0.12481431 | R95: =R85+INDEX(Data_Prices!R:R,MATCH($G95,Data_Prices!$A:$A,0))*R$98 -> 0.12146026 | S95: =S85+INDEX(Data_Prices!S:S,MATCH($G95,Data_Prices!$A:$A,0))*S$98 -> 0.11795074 | T95: =T85+INDEX(Data_Prices!T:T,MATCH($G95,Data_Prices!$A:$A,0))*T$98 -> 0.11419916 | U95: =U85+INDEX(Data_Prices!U:U,MATCH($G95,Data_Prices!$A:$A,0))*U$98 -> 0.1136651 | V95: =V85+INDEX(Data_Prices!V:V,MATCH($G95,Data_Prices!$A:$A,0))*V$98 -> 0.11301693 | W95: =W85+INDEX(Data_Prices!W:W,MATCH($G95,Data_Prices!$A:$A,0))*W$98 -> 0.11231407 | X95: =X85+INDEX(Data_Prices!X:X,MATCH($G95,Data_Prices!$A:$A,0))*X$98 -> 0.11142204 | Y95: =Y85+INDEX(Data_Prices!Y:Y,MATCH($G95,Data_Prices!$A:$A,0))*Y$98 -> 0.11043412 | Z95: =Z85+INDEX(Data_Prices!Z:Z,MATCH($G95,Data_Prices!$A:$A,0))*Z$98 -> 0.10948397 | AA95: =AA85+INDEX(Data_Prices!AA:AA,MATCH($G95,Data_Prices!$A:$A,0))*AA$98 -> 0.10839192 | AB95: =AB85+INDEX(Data_Prices!AB:AB,MATCH($G95,Data_Prices!$A:$A,0))*AB$98 -> 0.10735443 | AC95: =AC85+INDEX(Data_Prices!AC:AC,MATCH($G95,Data_Prices!$A:$A,0))*AC$98 -> 0.10516868 | AD95: =AD85+INDEX(Data_Prices!AD:AD,MATCH($G95,Data_Prices!$A:$A,0))*AD$98 -> 0.10305798 | AE95: =AE85+INDEX(Data_Prices!AE:AE,MATCH($G95,Data_Prices!$A:$A,0))*AE$98 -> 0.10093184
B96: Sector policy and macro drivers
B97: - | C97: =$C$65 -> cem | D97: Sector coverage factor of the new-policy wedge | E97: share | F97: tcf | G97: =Settings!$B$3&".mit.tcf."&$C$65&"."&$J$65 -> egy.mit.tcf.cem.1 | K97: =INDEX(Data_Prices!K:K,MATCH($G97,Data_Prices!$A:$A,0)) -> 0 | L97: =INDEX(Data_Prices!L:L,MATCH($G97,Data_Prices!$A:$A,0)) -> 0 | M97: =INDEX(Data_Prices!M:M,MATCH($G97,Data_Prices!$A:$A,0)) -> 0 | N97: =INDEX(Data_Prices!N:N,MATCH($G97,Data_Prices!$A:$A,0)) -> 0 | O97: =INDEX(Data_Prices!O:O,MATCH($G97,Data_Prices!$A:$A,0)) -> 0 | P97: =INDEX(Data_Prices!P:P,MATCH($G97,Data_Prices!$A:$A,0)) -> 0 | Q97: =INDEX(Data_Prices!Q:Q,MATCH($G97,Data_Prices!$A:$A,0)) -> 0 | R97: =INDEX(Data_Prices!R:R,MATCH($G97,Data_Prices!$A:$A,0)) -> 0 | S97: =INDEX(Data_Prices!S:S,MATCH($G97,Data_Prices!$A:$A,0)) -> 0 | T97: =INDEX(Data_Prices!T:T,MATCH($G97,Data_Prices!$A:$A,0)) -> 0 | U97: =INDEX(Data_Prices!U:U,MATCH($G97,Data_Prices!$A:$A,0)) -> 0 | V97: =INDEX(Data_Prices!V:V,MATCH($G97,Data_Prices!$A:$A,0)) -> 0 | W97: =INDEX(Data_Prices!W:W,MATCH($G97,Data_Prices!$A:$A,0)) -> 0 | X97: =INDEX(Data_Prices!X:X,MATCH($G97,Data_Prices!$A:$A,0)) -> 0 | Y97: =INDEX(Data_Prices!Y:Y,MATCH($G97,Data_Prices!$A:$A,0)) -> 0 | Z97: =INDEX(Data_Prices!Z:Z,MATCH($G97,Data_Prices!$A:$A,0)) -> 0 | AA97: =INDEX(Data_Prices!AA:AA,MATCH($G97,Data_Prices!$A:$A,0)) -> 0 | AB97: =INDEX(Data_Prices!AB:AB,MATCH($G97,Data_Prices!$A:$A,0)) -> 0 | AC97: =INDEX(Data_Prices!AC:AC,MATCH($G97,Data_Prices!$A:$A,0)) -> 0 | AD97: =INDEX(Data_Prices!AD:AD,MATCH($G97,Data_Prices!$A:$A,0)) -> 0 | AE97: =INDEX(Data_Prices!AE:AE,MATCH($G97,Data_Prices!$A:$A,0)) -> 0
B98: - | C98: =$C$65 -> cem | D98: Share of shadow price acting on efficiency | E98: share | F98: ssc | G98: =Settings!$B$3&".mit.ssc."&$C$65&"."&$J$65 -> egy.mit.ssc.cem.1 | K98: =INDEX(Data_Prices!K:K,MATCH($G98,Data_Prices!$A:$A,0)) -> 0 | L98: =INDEX(Data_Prices!L:L,MATCH($G98,Data_Prices!$A:$A,0)) -> 0 | M98: =INDEX(Data_Prices!M:M,MATCH($G98,Data_Prices!$A:$A,0)) -> 0 | N98: =INDEX(Data_Prices!N:N,MATCH($G98,Data_Prices!$A:$A,0)) -> 0 | O98: =INDEX(Data_Prices!O:O,MATCH($G98,Data_Prices!$A:$A,0)) -> 0 | P98: =INDEX(Data_Prices!P:P,MATCH($G98,Data_Prices!$A:$A,0)) -> 0 | Q98: =INDEX(Data_Prices!Q:Q,MATCH($G98,Data_Prices!$A:$A,0)) -> 0 | R98: =INDEX(Data_Prices!R:R,MATCH($G98,Data_Prices!$A:$A,0)) -> 0 | S98: =INDEX(Data_Prices!S:S,MATCH($G98,Data_Prices!$A:$A,0)) -> 0 | T98: =INDEX(Data_Prices!T:T,MATCH($G98,Data_Prices!$A:$A,0)) -> 0 | U98: =INDEX(Data_Prices!U:U,MATCH($G98,Data_Prices!$A:$A,0)) -> 0 | V98: =INDEX(Data_Prices!V:V,MATCH($G98,Data_Prices!$A:$A,0)) -> 0 | W98: =INDEX(Data_Prices!W:W,MATCH($G98,Data_Prices!$A:$A,0)) -> 0 | X98: =INDEX(Data_Prices!X:X,MATCH($G98,Data_Prices!$A:$A,0)) -> 0 | Y98: =INDEX(Data_Prices!Y:Y,MATCH($G98,Data_Prices!$A:$A,0)) -> 0 | Z98: =INDEX(Data_Prices!Z:Z,MATCH($G98,Data_Prices!$A:$A,0)) -> 0 | AA98: =INDEX(Data_Prices!AA:AA,MATCH($G98,Data_Prices!$A:$A,0)) -> 0 | AB98: =INDEX(Data_Prices!AB:AB,MATCH($G98,Data_Prices!$A:$A,0)) -> 0 | AC98: =INDEX(Data_Prices!AC:AC,MATCH($G98,Data_Prices!$A:$A,0)) -> 0 | AD98: =INDEX(Data_Prices!AD:AD,MATCH($G98,Data_Prices!$A:$A,0)) -> 0 | AE98: =INDEX(Data_Prices!AE:AE,MATCH($G98,Data_Prices!$A:$A,0)) -> 0
B99: - | C99: =$C$65 -> cem | D99: Post-policy real GDP growth | E99: % | F99: g | G99: =Settings!$B$3&".mit.gdp.pos.pct."&$J$65 -> egy.mit.gdp.pos.pct.1 | K99: =INDEX(Data_Macro!K:K,MATCH($G99,Data_Macro!$A:$A,0)) -> 0 | L99: =INDEX(Data_Macro!L:L,MATCH($G99,Data_Macro!$A:$A,0)) -> 0.06651345 | M99: =INDEX(Data_Macro!M:M,MATCH($G99,Data_Macro!$A:$A,0)) -> 0.03760281 | N99: =INDEX(Data_Macro!N:N,MATCH($G99,Data_Macro!$A:$A,0)) -> 0.02398801 | O99: =INDEX(Data_Macro!O:O,MATCH($G99,Data_Macro!$A:$A,0)) -> 0.04392387 | P99: =INDEX(Data_Macro!P:P,MATCH($G99,Data_Macro!$A:$A,0)) -> 0.04239706 | Q99: =INDEX(Data_Macro!Q:Q,MATCH($G99,Data_Macro!$A:$A,0)) -> 0.04829218 | R99: =INDEX(Data_Macro!R:R,MATCH($G99,Data_Macro!$A:$A,0)) -> 0.05535316 | S99: =INDEX(Data_Macro!S:S,MATCH($G99,Data_Macro!$A:$A,0)) -> 0.05226606 | T99: =INDEX(Data_Macro!T:T,MATCH($G99,Data_Macro!$A:$A,0)) -> 0.04841877 | U99: =INDEX(Data_Macro!U:U,MATCH($G99,Data_Macro!$A:$A,0)) -> 0.04788736 | V99: =INDEX(Data_Macro!V:V,MATCH($G99,Data_Macro!$A:$A,0)) -> 0.04735595 | W99: =INDEX(Data_Macro!W:W,MATCH($G99,Data_Macro!$A:$A,0)) -> 0.04682454 | X99: =INDEX(Data_Macro!X:X,MATCH($G99,Data_Macro!$A:$A,0)) -> 0.04629313 | Y99: =INDEX(Data_Macro!Y:Y,MATCH($G99,Data_Macro!$A:$A,0)) -> 0.04576172 | Z99: =INDEX(Data_Macro!Z:Z,MATCH($G99,Data_Macro!$A:$A,0)) -> 0.04523031 | AA99: =INDEX(Data_Macro!AA:AA,MATCH($G99,Data_Macro!$A:$A,0)) -> 0.0446989 | AB99: =INDEX(Data_Macro!AB:AB,MATCH($G99,Data_Macro!$A:$A,0)) -> 0.04416749 | AC99: =INDEX(Data_Macro!AC:AC,MATCH($G99,Data_Macro!$A:$A,0)) -> 0.04363608 | AD99: =INDEX(Data_Macro!AD:AD,MATCH($G99,Data_Macro!$A:$A,0)) -> 0.04310467 | AE99: =INDEX(Data_Macro!AE:AE,MATCH($G99,Data_Macro!$A:$A,0)) -> 0.04257326
B100: - | C100: =$C$65 -> cem | D100: Income-elasticity discount factor | E100: ratio | F100: delta | G100: =Settings!$B$3&".mit.inc.ela.adj."&$J$65 -> egy.mit.inc.ela.adj.1 | K100: =INDEX(Data_Macro!K:K,MATCH($G100,Data_Macro!$A:$A,0)) -> 0 | L100: =INDEX(Data_Macro!L:L,MATCH($G100,Data_Macro!$A:$A,0)) -> 1.0271517 | M100: =INDEX(Data_Macro!M:M,MATCH($G100,Data_Macro!$A:$A,0)) -> 1.0271517 | N100: =INDEX(Data_Macro!N:N,MATCH($G100,Data_Macro!$A:$A,0)) -> 1.0205698 | O100: =INDEX(Data_Macro!O:O,MATCH($G100,Data_Macro!$A:$A,0)) -> 1.0173344 | P100: =INDEX(Data_Macro!P:P,MATCH($G100,Data_Macro!$A:$A,0)) -> 1.0076683 | Q100: =INDEX(Data_Macro!Q:Q,MATCH($G100,Data_Macro!$A:$A,0)) -> 1.0007443 | R100: =INDEX(Data_Macro!R:R,MATCH($G100,Data_Macro!$A:$A,0)) -> 0.99188649 | S100: =INDEX(Data_Macro!S:S,MATCH($G100,Data_Macro!$A:$A,0)) -> 0.9806554 | T100: =INDEX(Data_Macro!T:T,MATCH($G100,Data_Macro!$A:$A,0)) -> 0.9702094 | U100: =INDEX(Data_Macro!U:U,MATCH($G100,Data_Macro!$A:$A,0)) -> 0.96419266 | V100: =INDEX(Data_Macro!V:V,MATCH($G100,Data_Macro!$A:$A,0)) -> 0.96161287 | W100: =INDEX(Data_Macro!W:W,MATCH($G100,Data_Macro!$A:$A,0)) -> 0.95919845 | X100: =INDEX(Data_Macro!X:X,MATCH($G100,Data_Macro!$A:$A,0)) -> 0.95695125 | Y100: =INDEX(Data_Macro!Y:Y,MATCH($G100,Data_Macro!$A:$A,0)) -> 0.95487298 | Z100: =INDEX(Data_Macro!Z:Z,MATCH($G100,Data_Macro!$A:$A,0)) -> 0.95296514 | AA100: =INDEX(Data_Macro!AA:AA,MATCH($G100,Data_Macro!$A:$A,0)) -> 0.9512291 | AB100: =INDEX(Data_Macro!AB:AB,MATCH($G100,Data_Macro!$A:$A,0)) -> 0.94966609 | AC100: =INDEX(Data_Macro!AC:AC,MATCH($G100,Data_Macro!$A:$A,0)) -> 0.94827716 | AD100: =INDEX(Data_Macro!AD:AD,MATCH($G100,Data_Macro!$A:$A,0)) -> 0.94706328 | AE100: =INDEX(Data_Macro!AE:AE,MATCH($G100,Data_Macro!$A:$A,0)) -> 0.94602527
B101: - | C101: =$C$65 -> cem | D101: Exogenous shock on energy consumption | E101: ratio | F101: psi | G101: =Settings!$B$3&".mit.shock."&$J$65 -> egy.mit.shock.1 | K101: =INDEX(Data_Macro!K:K,MATCH($G101,Data_Macro!$A:$A,0)) -> 0 | L101: =INDEX(Data_Macro!L:L,MATCH($G101,Data_Macro!$A:$A,0)) -> 0 | M101: =INDEX(Data_Macro!M:M,MATCH($G101,Data_Macro!$A:$A,0)) -> -0.20813308 | N101: =INDEX(Data_Macro!N:N,MATCH($G101,Data_Macro!$A:$A,0)) -> 0.092371429 | O101: =INDEX(Data_Macro!O:O,MATCH($G101,Data_Macro!$A:$A,0)) -> 0 | P101: =INDEX(Data_Macro!P:P,MATCH($G101,Data_Macro!$A:$A,0)) -> 0 | Q101: =INDEX(Data_Macro!Q:Q,MATCH($G101,Data_Macro!$A:$A,0)) -> 0 | R101: =INDEX(Data_Macro!R:R,MATCH($G101,Data_Macro!$A:$A,0)) -> 0 | S101: =INDEX(Data_Macro!S:S,MATCH($G101,Data_Macro!$A:$A,0)) -> 0 | T101: =INDEX(Data_Macro!T:T,MATCH($G101,Data_Macro!$A:$A,0)) -> 0 | U101: =INDEX(Data_Macro!U:U,MATCH($G101,Data_Macro!$A:$A,0)) -> 0 | V101: =INDEX(Data_Macro!V:V,MATCH($G101,Data_Macro!$A:$A,0)) -> 0 | W101: =INDEX(Data_Macro!W:W,MATCH($G101,Data_Macro!$A:$A,0)) -> 0 | X101: =INDEX(Data_Macro!X:X,MATCH($G101,Data_Macro!$A:$A,0)) -> 0 | Y101: =INDEX(Data_Macro!Y:Y,MATCH($G101,Data_Macro!$A:$A,0)) -> 0 | Z101: =INDEX(Data_Macro!Z:Z,MATCH($G101,Data_Macro!$A:$A,0)) -> 0 | AA101: =INDEX(Data_Macro!AA:AA,MATCH($G101,Data_Macro!$A:$A,0)) -> 0 | AB101: =INDEX(Data_Macro!AB:AB,MATCH($G101,Data_Macro!$A:$A,0)) -> 0 | AC101: =INDEX(Data_Macro!AC:AC,MATCH($G101,Data_Macro!$A:$A,0)) -> 0 | AD101: =INDEX(Data_Macro!AD:AD,MATCH($G101,Data_Macro!$A:$A,0)) -> 0 | AE101: =INDEX(Data_Macro!AE:AE,MATCH($G101,Data_Macro!$A:$A,0)) -> 0
B102: Kernel parameters (looked up from Data_Elast; column = Settings elasticity group)
...

Sheet MTInputs
B1: CPAT Inputs | E1: Links ----> | F1: Dashboard
B2: Explanation: this tabs is used for running MT as well as being a convenient place for all CPAT policy and parameter inputs to be viewed
B3: NB: Please do not change any cells. Make sure that "MT is active" switch is "False"
C5: =FALSE() -> FALSE | D5: <-- Should normally be "FALSE"!
D6: 6
B7: Parameters | C7: unit | D7: MT values | E7: "Dashboard" values | F7: Used for calculation | G7: Defaults | H7: NameOfParameter
B8: Country | F8: Egypt | G8: Egypt | H8: Countryname
B9: Scenario identification
B10: Scenario ID | C10: # | F10: N/A | G10: N/A | H10: MSTScenarioID
B11: Scenario status | C11: switch | F11: N/A | G11: N/A
B12: Scenario name | C12: name | F12: N/A | G12: N/A
B13: Chosen policy | C13: switch | F13: - Carbon tax | G13: - Carbon tax | H13: ScenarioSelected
B14: Scenario status for macro | C14: # | F14: N/A | G14: N/A
B15: Scenario parameters override? | C15: # | F15: N/A | G15: N/A
B16: CPAT-side parameters override? | C16: switch | F16: Manual* | G16: Manual* | H16: CPATDefaultsOrUserDefined
B17: Carbon pricing: main inputs
A18: X | B18: Carbon pricing start year | C18: year | F18: 2026 | G18: 2027 | H18: CPIntro
A19: X | B19: Starting carbon price | C19: nom. USD/tCO2 | F19: 0 | G19: 20 | H19: CPLevelStart
B20: Target level of carbon price | C20: nom. USD/tCO2 | F20: 50 | G20: 50 | H20: CPLevelTarget
A21: X | B21: Year to reach target level | C21: year | F21: 2030 | G21: 2035 | H21: CPOutro
B22: Carbon pricing: fuel coverage
B23: Apply tax to coal? | C23: switch | F23: =TRUE() -> TRUE | G23: =TRUE() -> TRUE | H23: MCovCoa
B24: Apply tax to natural gas? | C24: switch | F24: =TRUE() -> TRUE | G24: =TRUE() -> TRUE | H24: MCovNga
B25: Apply tax to gasoline? | C25: switch | F25: =TRUE() -> TRUE | G25: =TRUE() -> TRUE | H25: MCovGso
B26: Apply tax to diesel? | C26: switch | F26: =TRUE() -> TRUE | G26: =TRUE() -> TRUE | H26: MCovDie
B27: Apply tax to LPG? | C27: switch | F27: =TRUE() -> TRUE | G27: =TRUE() -> TRUE | H27: MCovLpg
B28: Apply tax to kerosene? | C28: switch | F28: =TRUE() -> TRUE | G28: =TRUE() -> TRUE | H28: MCovKer
B29: Apply tax to non-road oil products? | C29: switch | F29: =TRUE() -> TRUE | G29: =TRUE() -> TRUE | H29: MCovOop
B30: Carbon pricing: sector coverage
B31: Apply tax to power sector? | C31: switch | F31: =TRUE() -> TRUE | G31: =TRUE() -> TRUE | H31: MCovPow
B32: Apply tax to road transportation? | C32: switch | F32: =TRUE() -> TRUE | G32: =TRUE() -> TRUE | H32: MCovRod
B33: Apply tax to rail transportation? | C33: switch | F33: =TRUE() -> TRUE | G33: =TRUE() -> TRUE | H33: MCovRal
B34: Apply tax to domestic aviation? | C34: switch | F34: =TRUE() -> TRUE | G34: =TRUE() -> TRUE | H34: MCovAvi
B35: Apply tax to domestic shipping? | C35: switch | F35: =TRUE() -> TRUE | G35: =TRUE() -> TRUE | H35: MCovNav
B36: Apply tax to residential sector? | C36: switch | F36: =TRUE() -> TRUE | G36: =TRUE() -> TRUE | H36: MCovRes
B37: Apply tax to food & forestry? | C37: switch | F37: =TRUE() -> TRUE | G37: =TRUE() -> TRUE | H37: MCovFoo
B38: Apply tax to services (private / public)? | C38: switch | F38: =TRUE() -> TRUE | G38: =TRUE() -> TRUE | H38: MCovSrv
B39: Apply tax to mining & chemicals? | C39: switch | F39: =TRUE() -> TRUE | G39: =TRUE() -> TRUE | H39: MCovMch
B40: Apply tax to iron and steel? | C40: switch | F40: =TRUE() -> TRUE | G40: =TRUE() -> TRUE | H40: MCovIrn
B41: Apply tax to non-ferrous metals? | C41: switch | F41: =TRUE() -> TRUE | G41: =TRUE() -> TRUE | H41: MCovNfm
B42: Apply tax to machinery? | C42: switch | F42: =TRUE() -> TRUE | G42: =TRUE() -> TRUE | H42: MCovMac
... B47: Apply tax to other energy use? | C47: switch | F47: =TRUE() -> TRUE | G47: =TRUE() -> TRUE | H47: MCovOen
B48: Exemptions phaseout
B49: Apply exemption phaseout? | C49: switch | F49: =FALSE() -> FALSE | G49: =FALSE() -> FALSE | H49: ExemptPhaseout
B50: Year to start exemption phaseout (if applicable) | C50: year | F50: 2027 | G50: 2027 | H50: YearPha
B51: Period to reach full exemption phaseout (if applicable) | C51: year | F51: 5 | G51: 5 | H51: ExemptPhaseoutPeriod
B52: Feebates: Starting and End Date
B53: Start date | F53: 2027 | G53: 2027 | H53: D_FeebateIntro
B54: Target date | F54: 2035 | G54: 2035 | H54: D_FeebateOutro
B55: Feebates: Feebate starting rate
B56: Power sector | C56: USD/tCO2 | F56: 0 | G56: 0 | H56: D_Feb_Level_Start_Pow
B57: Transport | C57: USD/tCO2 | F57: 0 | G57: 0 | H57: D_Feb_Level_Start_Trans
B58: Residential | C58: USD/tCO2 | F58: 0 | G58: 0 | H58: D_Feb_Level_Start_Res
B59: Industry | C59: USD/tCO2 | F59: 0 | G59: 0 | H59: D_Feb_Level_Start_Ind
B60: Feebates: Feebate target rate
B61: Power sector | C61: USD/tCO2 | F61: 0 | G61: 0 | H61: D_Feb_Level_Target_Pow
B62: Transport | C62: USD/tCO2 | F62: 0 | G62: 0 | H62: D_Feb_Level_Target_Trans
B63: Residential | C63: USD/tCO2 | F63: 0 | G63: 0 | H63: D_Feb_Level_Target_Res
B64: Industry | C64: USD/tCO2 | F64: 0 | G64: 0 | H64: D_Feb_Level_Target_Ind
B65: Feebates sector coverage
B66: Apply tax to power sector? | C66: switch | F66: =FALSE() -> FALSE | G66: =TRUE() -> TRUE
B67: Apply tax to road transportation? | F67: =FALSE() -> FALSE | G67: =FALSE() -> FALSE
B68: Apply tax to rail transportation? | F68: =FALSE() -> FALSE | G68: =FALSE() -> FALSE
B69: Apply tax to domestic aviation? | F69: =FALSE() -> FALSE | G69: =FALSE() -> FALSE
B70: Apply tax to domestic shipping? | F70: =FALSE() -> FALSE | G70: =FALSE() -> FALSE
B71: Apply tax to residential sector? | C71: switch | F71: =FALSE() -> FALSE | G71: =TRUE() -> TRUE
B72: Apply tax to food & forestry? | F72: =FALSE() -> FALSE | G72: =TRUE() -> TRUE
B73: Apply tax to services (private / public)? | F73: =FALSE() -> FALSE | G73: =TRUE() -> TRUE
B74: Apply tax to mining & chemicals? | F74: =TRUE() -> TRUE | G74: =TRUE() -> TRUE
B75: Apply tax to iron and steel? | F75: =FALSE() -> FALSE | G75: =TRUE() -> TRUE
B76: Apply tax to non-ferrous metals? | F76: =TRUE() -> TRUE | G76: =TRUE() -> TRUE
B77: Apply tax to machinery? | F77: =TRUE() -> TRUE | G77: =TRUE() -> TRUE
B78: Apply tax to cement? | F78: =TRUE() -> TRUE | G78: =TRUE() -> TRUE
B79: Apply tax to other manucfacturing? | F79: =TRUE() -> TRUE | G79: =TRUE() -> TRUE
B80: Apply tax to construction? | F80: =TRUE() -> TRUE | G80: =TRUE() -> TRUE
B81: Apply tax to fuel transformation? | F81: =TRUE() -> TRUE | G81: =TRUE() -> TRUE
B82: Apply tax to other energy use? | F82: =TRUE() -> TRUE | G82: =TRUE() -> TRUE
B83: ETS Main Characteristics
B84: Apply new ETS? | F84: No | G84: No | H84: D_NewETS
B85: Change Relative to Baseline in Start Year | F85: 0 | G85: 0 | H85: D_ETSChangeRelStart
B86: Change Relative to Baseline in Target Year | F86: 0 | G86: 0 | H86: D_ETSChangeRelTarget
B87: Cap continuation after target year? | F87: Constant | G87: KeepRelativeCapConstant | H87: D_ETSCapCont
B88: ETS Start Year | F88: 2027 | G88: 2026 | H88: D_ETSIntro
B89: ETS Target Year | F89: 2035 | G89: 2035 | H89: D_ETSOutro
B90: Proportion Auctioned in Starting Year | F90: 0 | G90: 0 | H90: D_ETSAuctStart
B91: Proportion Auctioned in Target Year | F91: 0 | G91: 1 | H91: D_ETSAuctTarget
B92: Auction proportion continuation after target year? | F92: Constant | G92: Constant | H92: D_ETSAuctCont
B93: Override ETS price | F93: No | G93: No | H93: D_ETSPriceOverride
B94: ETS: modelling assumptions
B95: ETS Volatility | F95: Medium* | G95: Medium* | H95: D_ETSVolatility
B96: Impact of Volatility on Abatement Costs | F96: Medium* | G96: Medium* | H96: D_ETSVolImpact
B97: Carbon Tax Policy Risk | F97: 0.2 | G97: 0.2 | H97: D_ETSCTRisk
B98: ETS: sector coverage
B99: power sector | C99: switch | F99: =TRUE() -> TRUE | G99: =TRUE() -> TRUE
B100: road transportation | F100: =FALSE() -> FALSE | G100: =TRUE() -> TRUE
B101: rail transportation | F101: =FALSE() -> FALSE | G101: =TRUE() -> TRUE
B102: domestic aviation | F102: =FALSE() -> FALSE | G102: =TRUE() -> TRUE
B103: domestic shipping | F103: =FALSE() -> FALSE | G103: =TRUE() -> TRUE
