Workbook
Name POSTTAX: _xlfn.LAMBDA(_xlpm.pre_policy_p,_xlpm.new_policy,_xlpm.vat_rate,MAX(_xlpm.pre_policy_p+_xlpm.new_policy*(1+_xlpm.vat_rate),0.01))
Name SUPPLYCOST: _xlfn.LAMBDA(_xlpm.fix_sp,_xlpm.sp_prev,_xlpm.gp_now,_xlpm.gp_prev,_xlpm.fix_sp+(_xlpm.sp_prev-_xlpm.fix_sp)*_xlpm.gp_now/_xlpm.gp_prev)

Sheet Mitigation
A1: Variable | B1: Fuel | C1: Sector | D1: Param 1 | E1: Param 2 | F1: Param 3 | G1: Param 4 | H1: Description | I1: Unit | J1: Source | L1: Scenario 1: output code | AB1: Scenario 2: output code
A2: Mitigation module - price to fuel use (copy-pasteable, design 2, legacy CPAT sections)
A3: Scenario assumptions (one column group per scenario: code column + years; copy a whole group to add a scenario)
H4: Year | M4: =Settings!$C$7 -> 2022 | N4: =M4+1 -> 2023 | O4: =N4+1 -> 2024 | P4: =O4+1 -> 2025 | Q4: =P4+1 -> 2026 | R4: =Q4+1 -> 2027 | S4: =R4+1 -> 2028 | T4: =S4+1 -> 2029 | U4: =T4+1 -> 2030 | ... Z4: =Y4+1 -> 2035 | AC4: =Settings!$C$7 -> 2022 | AD4: =AC4+1 -> 2023 | AE4: =AD4+1 -> 2024 | AF4: =AE4+1 -> 2025 | AG4: =AF4+1 -> 2026 | AH4: =AG4+1 -> 2027 | AI4: =AH4+1 -> 2028 | AJ4: =AI4+1 -> 2029 | AK4: =AJ4+1 -> 2030 | ... AP4: =AO4+1 -> 2035
H5: Scenario number (MTInputs column) | L5: 1 | M5: =L5 -> 1 | N5: =M5 -> 1 | O5: =N5 -> 1 | P5: =O5 -> 1 | Q5: =P5 -> 1 | R5: =Q5 -> 1 | S5: =R5 -> 1 | T5: =S5 -> 1 | ... Z5: =Y5 -> 1 | AB5: =L5+1 -> 2 | AC5: =AB5 -> 2 | AD5: =AC5 -> 2 | AE5: =AD5 -> 2 | AF5: =AE5 -> 2 | AG5: =AF5 -> 2 | AH5: =AG5 -> 2 | AI5: =AH5 -> 2 | AJ5: =AI5 -> 2 | ... AP5: =AO5 -> 2
H6: Scenario name (from MTInputs) | M6: =INDEX(MTInputs!$J$6:$AZ$6,MATCH(M$5,MTInputs!$J$5:$AZ$5,0)) -> Baseline (no carbon price) | AC6: =INDEX(MTInputs!$J$6:$AZ$6,MATCH(AC$5,MTInputs!$J$5:$AZ$5,0)) -> Carbon price $20/tCO2 from 2027
A7: gdp.pos.pct | H7: =INDEX(Variables!$B$5:$B$65,MATCH($A7,Variables!$A$5:$A$65,0))&IF($C7="",""," | "&INDEX(Mapping!$B$5:$B$26,MATCH($C7,Mapping!$A$5:$A$26,0))&" | "&INDEX(Mapping!$B$30:$B$41,MATCH($B7,Mapping!$A$30:$A$41,0))) -> Real GDP growth | I7: =INDEX(Variables!$C$5:$C$65,MATCH($A7,Variables!$A$5:$A$65,0)) -> % | J7: =INDEX(Variables!$E$5:$E$65,MATCH($A7,Variables!$A$5:$A$65,0)) -> WEO (lookup by country) | L7: =LOWER(Settings!$C$4)&".mit."&$A7&IF($C7="","","."&$C7&"."&$B7)&IF(INDEX(Variables!$D$5:$D$65,MATCH($A7,Variables!$A$5:$A$65,0))="","","."&INDEX(Variables!$D$5:$D$65,MATCH($A7,Variables!$A$5:$A$65,0)))&"."&L$5 -> egy.mit.gdp.pos.pct.1 | M7: =INDEX(WEO!$F$4:$AZ$1000,MATCH(Settings!$C$4&"|gdp_growth",WEO!$A$4:$A$1000,0),MATCH(M$4,WEO!$F$3:$AZ$3,0)) -> 0.06651345 | N7: =INDEX(WEO!$F$4:$AZ$1000,MATCH(Settings!$C$4&"|gdp_growth",WEO!$A$4:$A$1000,0),MATCH(N$4,WEO!$F$3:$AZ$3,0)) -> 0.03760281 | O7: =INDEX(WEO!$F$4:$AZ$1000,MATCH(Settings!$C$4&"|gdp_growth",WEO!$A$4:$A$1000,0),MATCH(O$4,WEO!$F$3:$AZ$3,0)) -> 0.02398801 | P7: =INDEX(WEO!$F$4:$AZ$1000,MATCH(Settings!$C$4&"|gdp_growth",WEO!$A$4:$A$1000,0),MATCH(P$4,WEO!$F$3:$AZ$3,0)) -> 0.04392387 | Q7: =INDEX(WEO!$F$4:$AZ$1000,MATCH(Settings!$C$4&"|gdp_growth",WEO!$A$4:$A$1000,0),MATCH(Q$4,WEO!$F$3:$AZ$3,0)) -> 0.04239706 | R7: =INDEX(WEO!$F$4:$AZ$1000,MATCH(Settings!$C$4&"|gdp_growth",WEO!$A$4:$A$1000,0),MATCH(R$4,WEO!$F$3:$AZ$3,0)) -> 0.04829218 | S7: =INDEX(WEO!$F$4:$AZ$1000,MATCH(Settings!$C$4&"|gdp_growth",WEO!$A$4:$A$1000,0),MATCH(S$4,WEO!$F$3:$AZ$3,0)) -> 0.05535316 | T7: =INDEX(WEO!$F$4:$AZ$1000,MATCH(Settings!$C$4&"|gdp_growth",WEO!$A$4:$A$1000,0),MATCH(T$4,WEO!$F$3:$AZ$3,0)) -> 0.05226606 | ... Z7: =INDEX(WEO!$F$4:$AZ$1000,MATCH(Settings!$C$4&"|gdp_growth",WEO!$A$4:$A$1000,0),MATCH(Z$4,WEO!$F$3:$AZ$3,0)) -> 0.04576172 | AB7: =LOWER(Settings!$C$4)&".mit."&$A7&IF($C7="","","."&$C7&"."&$B7)&IF(INDEX(Variables!$D$5:$D$65,MATCH($A7,Variables!$A$5:$A$65,0))="","","."&INDEX(Variables!$D$5:$D$65,MATCH($A7,Variables!$A$5:$A$65,0)))&"."&AB$5 -> egy.mit.gdp.pos.pct.2 | AC7: =INDEX(WEO!$F$4:$AZ$1000,MATCH(Settings!$C$4&"|gdp_growth",WEO!$A$4:$A$1000,0),MATCH(AC$4,WEO!$F$3:$AZ$3,0)) -> 0.06651345 | AD7: =INDEX(WEO!$F$4:$AZ$1000,MATCH(Settings!$C$4&"|gdp_growth",WEO!$A$4:$A$1000,0),MATCH(AD$4,WEO!$F$3:$AZ$3,0)) -> 0.03760281 | AE7: =INDEX(WEO!$F$4:$AZ$1000,MATCH(Settings!$C$4&"|gdp_growth",WEO!$A$4:$A$1000,0),MATCH(AE$4,WEO!$F$3:$AZ$3,0)) -> 0.02398801 | AF7: =INDEX(WEO!$F$4:$AZ$1000,MATCH(Settings!$C$4&"|gdp_growth",WEO!$A$4:$A$1000,0),MATCH(AF$4,WEO!$F$3:$AZ$3,0)) -> 0.04392387 | AG7: =INDEX(WEO!$F$4:$AZ$1000,MATCH(Settings!$C$4&"|gdp_growth",WEO!$A$4:$A$1000,0),MATCH(AG$4,WEO!$F$3:$AZ$3,0)) -> 0.04239706 | AH7: =INDEX(WEO!$F$4:$AZ$1000,MATCH(Settings!$C$4&"|gdp_growth",WEO!$A$4:$A$1000,0),MATCH(AH$4,WEO!$F$3:$AZ$3,0)) -> 0.04829218 | AI7: =INDEX(WEO!$F$4:$AZ$1000,MATCH(Settings!$C$4&"|gdp_growth",WEO!$A$4:$A$1000,0),MATCH(AI$4,WEO!$F$3:$AZ$3,0)) -> 0.05535316 | AJ7: =INDEX(WEO!$F$4:$AZ$1000,MATCH(Settings!$C$4&"|gdp_growth",WEO!$A$4:$A$1000,0),MATCH(AJ$4,WEO!$F$3:$AZ$3,0)) -> 0.05226606 | ... AP7: =INDEX(WEO!$F$4:$AZ$1000,MATCH(Settings!$C$4&"|gdp_growth",WEO!$A$4:$A$1000,0),MATCH(AP$4,WEO!$F$3:$AZ$3,0)) -> 0.04576172
A8: infl | H8: =INDEX(Variables!$B$5:$B$65,MATCH($A8,Variables!$A$5:$A$65,0))&IF($C8="",""," | "&INDEX(Mapping!$B$5:$B$26,MATCH($C8,Mapping!$A$5:$A$26,0))&" | "&INDEX(Mapping!$B$30:$B$41,MATCH($B8,Mapping!$A$30:$A$41,0))) -> Inflation index: US CPI, ResultsYear = 1 (nominal -> real for domestic prices and nominal policy inputs) | I8: =INDEX(Variables!$C$5:$C$65,MATCH($A8,Variables!$A$5:$A$65,0)) -> index | J8: =INDEX(Variables!$E$5:$E$65,MATCH($A8,Variables!$A$5:$A$65,0)) -> WEO USA|pcpi: CPI(ResultsYear) / CPI(year) | L8: =LOWER(Settings!$C$4)&".mit."&$A8&IF($C8="","","."&$C8&"."&$B8)&IF(INDEX(Variables!$D$5:$D$65,MATCH($A8,Variables!$A$5:$A$65,0))="","","."&INDEX(Variables!$D$5:$D$65,MATCH($A8,Variables!$A$5:$A$65,0)))&"."&L$5 -> egy.mit.infl.1 | M8: =INDEX(WEO!$F$4:$AZ$1000,MATCH("USA|pcpi",WEO!$A$4:$A$1000,0),MATCH(Settings!$C$8,WEO!$F$3:$AZ$3,0))/INDEX(WEO!$F$4:$AZ$1000,MATCH("USA|pcpi",WEO!$A$4:$A$1000,0),MATCH(M$4,WEO!$F$3:$AZ$3,0)) -> 1.1368176 | N8: =INDEX(WEO!$F$4:$AZ$1000,MATCH("USA|pcpi",WEO!$A$4:$A$1000,0),MATCH(Settings!$C$8,WEO!$F$3:$AZ$3,0))/INDEX(WEO!$F$4:$AZ$1000,MATCH("USA|pcpi",WEO!$A$4:$A$1000,0),MATCH(N$4,WEO!$F$3:$AZ$3,0)) -> 1.091761 | O8: =INDEX(WEO!$F$4:$AZ$1000,MATCH("USA|pcpi",WEO!$A$4:$A$1000,0),MATCH(Settings!$C$8,WEO!$F$3:$AZ$3,0))/INDEX(WEO!$F$4:$AZ$1000,MATCH("USA|pcpi",WEO!$A$4:$A$1000,0),MATCH(O$4,WEO!$F$3:$AZ$3,0)) -> 1.0604552 | P8: =INDEX(WEO!$F$4:$AZ$1000,MATCH("USA|pcpi",WEO!$A$4:$A$1000,0),MATCH(Settings!$C$8,WEO!$F$3:$AZ$3,0))/INDEX(WEO!$F$4:$AZ$1000,MATCH("USA|pcpi",WEO!$A$4:$A$1000,0),MATCH(P$4,WEO!$F$3:$AZ$3,0)) -> 1.0322791 | Q8: =INDEX(WEO!$F$4:$AZ$1000,MATCH("USA|pcpi",WEO!$A$4:$A$1000,0),MATCH(Settings!$C$8,WEO!$F$3:$AZ$3,0))/INDEX(WEO!$F$4:$AZ$1000,MATCH("USA|pcpi",WEO!$A$4:$A$1000,0),MATCH(Q$4,WEO!$F$3:$AZ$3,0)) -> 1 | R8: =INDEX(WEO!$F$4:$AZ$1000,MATCH("USA|pcpi",WEO!$A$4:$A$1000,0),MATCH(Settings!$C$8,WEO!$F$3:$AZ$3,0))/INDEX(WEO!$F$4:$AZ$1000,MATCH("USA|pcpi",WEO!$A$4:$A$1000,0),MATCH(R$4,WEO!$F$3:$AZ$3,0)) -> 0.97903568 | S8: =INDEX(WEO!$F$4:$AZ$1000,MATCH("USA|pcpi",WEO!$A$4:$A$1000,0),MATCH(Settings!$C$8,WEO!$F$3:$AZ$3,0))/INDEX(WEO!$F$4:$AZ$1000,MATCH("USA|pcpi",WEO!$A$4:$A$1000,0),MATCH(S$4,WEO!$F$3:$AZ$3,0)) -> 0.95811375 | T8: =INDEX(WEO!$F$4:$AZ$1000,MATCH("USA|pcpi",WEO!$A$4:$A$1000,0),MATCH(Settings!$C$8,WEO!$F$3:$AZ$3,0))/INDEX(WEO!$F$4:$AZ$1000,MATCH("USA|pcpi",WEO!$A$4:$A$1000,0),MATCH(T$4,WEO!$F$3:$AZ$3,0)) -> 0.93759961 | ... Z8: =INDEX(WEO!$F$4:$AZ$1000,MATCH("USA|pcpi",WEO!$A$4:$A$1000,0),MATCH(Settings!$C$8,WEO!$F$3:$AZ$3,0))/INDEX(WEO!$F$4:$AZ$1000,MATCH("USA|pcpi",WEO!$A$4:$A$1000,0),MATCH(Z$4,WEO!$F$3:$AZ$3,0)) -> 0.89789601 | AB8: =LOWER(Settings!$C$4)&".mit."&$A8&IF($C8="","","."&$C8&"."&$B8)&IF(INDEX(Variables!$D$5:$D$65,MATCH($A8,Variables!$A$5:$A$65,0))="","","."&INDEX(Variables!$D$5:$D$65,MATCH($A8,Variables!$A$5:$A$65,0)))&"."&AB$5 -> egy.mit.infl.2 | AC8: =INDEX(WEO!$F$4:$AZ$1000,MATCH("USA|pcpi",WEO!$A$4:$A$1000,0),MATCH(Settings!$C$8,WEO!$F$3:$AZ$3,0))/INDEX(WEO!$F$4:$AZ$1000,MATCH("USA|pcpi",WEO!$A$4:$A$1000,0),MATCH(AC$4,WEO!$F$3:$AZ$3,0)) -> 1.1368176 | AD8: =INDEX(WEO!$F$4:$AZ$1000,MATCH("USA|pcpi",WEO!$A$4:$A$1000,0),MATCH(Settings!$C$8,WEO!$F$3:$AZ$3,0))/INDEX(WEO!$F$4:$AZ$1000,MATCH("USA|pcpi",WEO!$A$4:$A$1000,0),MATCH(AD$4,WEO!$F$3:$AZ$3,0)) -> 1.091761 | AE8: =INDEX(WEO!$F$4:$AZ$1000,MATCH("USA|pcpi",WEO!$A$4:$A$1000,0),MATCH(Settings!$C$8,WEO!$F$3:$AZ$3,0))/INDEX(WEO!$F$4:$AZ$1000,MATCH("USA|pcpi",WEO!$A$4:$A$1000,0),MATCH(AE$4,WEO!$F$3:$AZ$3,0)) -> 1.0604552 | AF8: =INDEX(WEO!$F$4:$AZ$1000,MATCH("USA|pcpi",WEO!$A$4:$A$1000,0),MATCH(Settings!$C$8,WEO!$F$3:$AZ$3,0))/INDEX(WEO!$F$4:$AZ$1000,MATCH("USA|pcpi",WEO!$A$4:$A$1000,0),MATCH(AF$4,WEO!$F$3:$AZ$3,0)) -> 1.0322791 | AG8: =INDEX(WEO!$F$4:$AZ$1000,MATCH("USA|pcpi",WEO!$A$4:$A$1000,0),MATCH(Settings!$C$8,WEO!$F$3:$AZ$3,0))/INDEX(WEO!$F$4:$AZ$1000,MATCH("USA|pcpi",WEO!$A$4:$A$1000,0),MATCH(AG$4,WEO!$F$3:$AZ$3,0)) -> 1 | AH8: =INDEX(WEO!$F$4:$AZ$1000,MATCH("USA|pcpi",WEO!$A$4:$A$1000,0),MATCH(Settings!$C$8,WEO!$F$3:$AZ$3,0))/INDEX(WEO!$F$4:$AZ$1000,MATCH("USA|pcpi",WEO!$A$4:$A$1000,0),MATCH(AH$4,WEO!$F$3:$AZ$3,0)) -> 0.97903568 | AI8: =INDEX(WEO!$F$4:$AZ$1000,MATCH("USA|pcpi",WEO!$A$4:$A$1000,0),MATCH(Settings!$C$8,WEO!$F$3:$AZ$3,0))/INDEX(WEO!$F$4:$AZ$1000,MATCH("USA|pcpi",WEO!$A$4:$A$1000,0),MATCH(AI$4,WEO!$F$3:$AZ$3,0)) -> 0.95811375 | AJ8: =INDEX(WEO!$F$4:$AZ$1000,MATCH("USA|pcpi",WEO!$A$4:$A$1000,0),MATCH(Settings!$C$8,WEO!$F$3:$AZ$3,0))/INDEX(WEO!$F$4:$AZ$1000,MATCH("USA|pcpi",WEO!$A$4:$A$1000,0),MATCH(AJ$4,WEO!$F$3:$AZ$3,0)) -> 0.93759961 | ... AP8: =INDEX(WEO!$F$4:$AZ$1000,MATCH("USA|pcpi",WEO!$A$4:$A$1000,0),MATCH(Settings!$C$8,WEO!$F$3:$AZ$3,0))/INDEX(WEO!$F$4:$AZ$1000,MATCH("USA|pcpi",WEO!$A$4:$A$1000,0),MATCH(AP$4,WEO!$F$3:$AZ$3,0)) -> 0.89789601
A9: defl | H9: =INDEX(Variables!$B$5:$B$65,MATCH($A9,Variables!$A$5:$A$65,0))&IF($C9="",""," | "&INDEX(Mapping!$B$5:$B$26,MATCH($C9,Mapping!$A$5:$A$26,0))&" | "&INDEX(Mapping!$B$30:$B$41,MATCH($B9,Mapping!$A$30:$A$41,0))) -> Deflator index: US GDP deflator, ResultsYear = 1 (nominal -> real for international prices) | I9: =INDEX(Variables!$C$5:$C$65,MATCH($A9,Variables!$A$5:$A$65,0)) -> index | J9: =INDEX(Variables!$E$5:$E$65,MATCH($A9,Variables!$A$5:$A$65,0)) -> WEO USA|ngdp_d: deflator(ResultsYear) / deflator(year) | L9: =LOWER(Settings!$C$4)&".mit."&$A9&IF($C9="","","."&$C9&"."&$B9)&IF(INDEX(Variables!$D$5:$D$65,MATCH($A9,Variables!$A$5:$A$65,0))="","","."&INDEX(Variables!$D$5:$D$65,MATCH($A9,Variables!$A$5:$A$65,0)))&"."&L$5 -> egy.mit.defl.1 | M9: =INDEX(WEO!$F$4:$AZ$1000,MATCH("USA|ngdp_d",WEO!$A$4:$A$1000,0),MATCH(Settings!$C$8,WEO!$F$3:$AZ$3,0))/INDEX(WEO!$F$4:$AZ$1000,MATCH("USA|ngdp_d",WEO!$A$4:$A$1000,0),MATCH(M$4,WEO!$F$3:$AZ$3,0)) -> 1.1242016 | N9: =INDEX(WEO!$F$4:$AZ$1000,MATCH("USA|ngdp_d",WEO!$A$4:$A$1000,0),MATCH(Settings!$C$8,WEO!$F$3:$AZ$3,0))/INDEX(WEO!$F$4:$AZ$1000,MATCH("USA|ngdp_d",WEO!$A$4:$A$1000,0),MATCH(N$4,WEO!$F$3:$AZ$3,0)) -> 1.0840899 | O9: =INDEX(WEO!$F$4:$AZ$1000,MATCH("USA|ngdp_d",WEO!$A$4:$A$1000,0),MATCH(Settings!$C$8,WEO!$F$3:$AZ$3,0))/INDEX(WEO!$F$4:$AZ$1000,MATCH("USA|ngdp_d",WEO!$A$4:$A$1000,0),MATCH(O$4,WEO!$F$3:$AZ$3,0)) -> 1.0578289 | P9: =INDEX(WEO!$F$4:$AZ$1000,MATCH("USA|ngdp_d",WEO!$A$4:$A$1000,0),MATCH(Settings!$C$8,WEO!$F$3:$AZ$3,0))/INDEX(WEO!$F$4:$AZ$1000,MATCH("USA|ngdp_d",WEO!$A$4:$A$1000,0),MATCH(P$4,WEO!$F$3:$AZ$3,0)) -> 1.0286485 | Q9: =INDEX(WEO!$F$4:$AZ$1000,MATCH("USA|ngdp_d",WEO!$A$4:$A$1000,0),MATCH(Settings!$C$8,WEO!$F$3:$AZ$3,0))/INDEX(WEO!$F$4:$AZ$1000,MATCH("USA|ngdp_d",WEO!$A$4:$A$1000,0),MATCH(Q$4,WEO!$F$3:$AZ$3,0)) -> 1 | R9: =INDEX(WEO!$F$4:$AZ$1000,MATCH("USA|ngdp_d",WEO!$A$4:$A$1000,0),MATCH(Settings!$C$8,WEO!$F$3:$AZ$3,0))/INDEX(WEO!$F$4:$AZ$1000,MATCH("USA|ngdp_d",WEO!$A$4:$A$1000,0),MATCH(R$4,WEO!$F$3:$AZ$3,0)) -> 0.97851281 | S9: =INDEX(WEO!$F$4:$AZ$1000,MATCH("USA|ngdp_d",WEO!$A$4:$A$1000,0),MATCH(Settings!$C$8,WEO!$F$3:$AZ$3,0))/INDEX(WEO!$F$4:$AZ$1000,MATCH("USA|ngdp_d",WEO!$A$4:$A$1000,0),MATCH(S$4,WEO!$F$3:$AZ$3,0)) -> 0.96271097 | T9: =INDEX(WEO!$F$4:$AZ$1000,MATCH("USA|ngdp_d",WEO!$A$4:$A$1000,0),MATCH(Settings!$C$8,WEO!$F$3:$AZ$3,0))/INDEX(WEO!$F$4:$AZ$1000,MATCH("USA|ngdp_d",WEO!$A$4:$A$1000,0),MATCH(T$4,WEO!$F$3:$AZ$3,0)) -> 0.94589198 | ... Z9: =INDEX(WEO!$F$4:$AZ$1000,MATCH("USA|ngdp_d",WEO!$A$4:$A$1000,0),MATCH(Settings!$C$8,WEO!$F$3:$AZ$3,0))/INDEX(WEO!$F$4:$AZ$1000,MATCH("USA|ngdp_d",WEO!$A$4:$A$1000,0),MATCH(Z$4,WEO!$F$3:$AZ$3,0)) -> 0.85192546 | AB9: =LOWER(Settings!$C$4)&".mit."&$A9&IF($C9="","","."&$C9&"."&$B9)&IF(INDEX(Variables!$D$5:$D$65,MATCH($A9,Variables!$A$5:$A$65,0))="","","."&INDEX(Variables!$D$5:$D$65,MATCH($A9,Variables!$A$5:$A$65,0)))&"."&AB$5 -> egy.mit.defl.2 | AC9: =INDEX(WEO!$F$4:$AZ$1000,MATCH("USA|ngdp_d",WEO!$A$4:$A$1000,0),MATCH(Settings!$C$8,WEO!$F$3:$AZ$3,0))/INDEX(WEO!$F$4:$AZ$1000,MATCH("USA|ngdp_d",WEO!$A$4:$A$1000,0),MATCH(AC$4,WEO!$F$3:$AZ$3,0)) -> 1.1242016 | AD9: =INDEX(WEO!$F$4:$AZ$1000,MATCH("USA|ngdp_d",WEO!$A$4:$A$1000,0),MATCH(Settings!$C$8,WEO!$F$3:$AZ$3,0))/INDEX(WEO!$F$4:$AZ$1000,MATCH("USA|ngdp_d",WEO!$A$4:$A$1000,0),MATCH(AD$4,WEO!$F$3:$AZ$3,0)) -> 1.0840899 | AE9: =INDEX(WEO!$F$4:$AZ$1000,MATCH("USA|ngdp_d",WEO!$A$4:$A$1000,0),MATCH(Settings!$C$8,WEO!$F$3:$AZ$3,0))/INDEX(WEO!$F$4:$AZ$1000,MATCH("USA|ngdp_d",WEO!$A$4:$A$1000,0),MATCH(AE$4,WEO!$F$3:$AZ$3,0)) -> 1.0578289 | AF9: =INDEX(WEO!$F$4:$AZ$1000,MATCH("USA|ngdp_d",WEO!$A$4:$A$1000,0),MATCH(Settings!$C$8,WEO!$F$3:$AZ$3,0))/INDEX(WEO!$F$4:$AZ$1000,MATCH("USA|ngdp_d",WEO!$A$4:$A$1000,0),MATCH(AF$4,WEO!$F$3:$AZ$3,0)) -> 1.0286485 | AG9: =INDEX(WEO!$F$4:$AZ$1000,MATCH("USA|ngdp_d",WEO!$A$4:$A$1000,0),MATCH(Settings!$C$8,WEO!$F$3:$AZ$3,0))/INDEX(WEO!$F$4:$AZ$1000,MATCH("USA|ngdp_d",WEO!$A$4:$A$1000,0),MATCH(AG$4,WEO!$F$3:$AZ$3,0)) -> 1 | AH9: =INDEX(WEO!$F$4:$AZ$1000,MATCH("USA|ngdp_d",WEO!$A$4:$A$1000,0),MATCH(Settings!$C$8,WEO!$F$3:$AZ$3,0))/INDEX(WEO!$F$4:$AZ$1000,MATCH("USA|ngdp_d",WEO!$A$4:$A$1000,0),MATCH(AH$4,WEO!$F$3:$AZ$3,0)) -> 0.97851281 | AI9: =INDEX(WEO!$F$4:$AZ$1000,MATCH("USA|ngdp_d",WEO!$A$4:$A$1000,0),MATCH(Settings!$C$8,WEO!$F$3:$AZ$3,0))/INDEX(WEO!$F$4:$AZ$1000,MATCH("USA|ngdp_d",WEO!$A$4:$A$1000,0),MATCH(AI$4,WEO!$F$3:$AZ$3,0)) -> 0.96271097 | AJ9: =INDEX(WEO!$F$4:$AZ$1000,MATCH("USA|ngdp_d",WEO!$A$4:$A$1000,0),MATCH(Settings!$C$8,WEO!$F$3:$AZ$3,0))/INDEX(WEO!$F$4:$AZ$1000,MATCH("USA|ngdp_d",WEO!$A$4:$A$1000,0),MATCH(AJ$4,WEO!$F$3:$AZ$3,0)) -> 0.94589198 | ... AP9: =INDEX(WEO!$F$4:$AZ$1000,MATCH("USA|ngdp_d",WEO!$A$4:$A$1000,0),MATCH(Settings!$C$8,WEO!$F$3:$AZ$3,0))/INDEX(WEO!$F$4:$AZ$1000,MATCH("USA|ngdp_d",WEO!$A$4:$A$1000,0),MATCH(AP$4,WEO!$F$3:$AZ$3,0)) -> 0.85192546
A11: 1. Policies (scenario inputs from MTInputs by row and scenario number; policy paths) | D11: MTInputs row
A12: cptraj | H12: =INDEX(Variables!$B$5:$B$65,MATCH($A12,Variables!$A$5:$A$65,0))&IF($C12="",""," | "&INDEX(Mapping!$B$5:$B$26,MATCH($C12,Mapping!$A$5:$A$26,0))&" | "&INDEX(Mapping!$B$30:$B$41,MATCH($B12,Mapping!$A$30:$A$41,0))) -> Carbon price trajectory used | I12: =INDEX(Variables!$C$5:$C$65,MATCH($A12,Variables!$A$5:$A$65,0)) -> $/tCO2 real | J12: =INDEX(Variables!$E$5:$E$65,MATCH($A12,Variables!$A$5:$A$65,0)) -> Calculation (legacy rows 2248, 2251); x infl if NomorReal = Nominal | L12: =LOWER(Settings!$C$4)&".mit."&$A12&IF($C12="","","."&$C12&"."&$B12)&IF(INDEX(Variables!$D$5:$D$65,MATCH($A12,Variables!$A$5:$A$65,0))="","","."&INDEX(Variables!$D$5:$D$65,MATCH($A12,Variables!$A$5:$A$65,0)))&"."&L$5 -> egy.mit.cptraj.1 | M12: =(IF(M$4<M$14,0,M$15+(M$16-M$15)/MAX(M$17-M$14,1)*IF(OR(M$4<=M$17,M$18="Linear*"),M$4-M$14,M$17-M$14)))*IF(LEFT(M$19,7)="Nominal",M$8,1) -> 0 | N12: =(IF(N$4<N$14,0,N$15+(N$16-N$15)/MAX(N$17-N$14,1)*IF(OR(N$4<=N$17,N$18="Linear*"),N$4-N$14,N$17-N$14)))*IF(LEFT(N$19,7)="Nominal",N$8,1) -> 0 | O12: =(IF(O$4<O$14,0,O$15+(O$16-O$15)/MAX(O$17-O$14,1)*IF(OR(O$4<=O$17,O$18="Linear*"),O$4-O$14,O$17-O$14)))*IF(LEFT(O$19,7)="Nominal",O$8,1) -> 0 | P12: =(IF(P$4<P$14,0,P$15+(P$16-P$15)/MAX(P$17-P$14,1)*IF(OR(P$4<=P$17,P$18="Linear*"),P$4-P$14,P$17-P$14)))*IF(LEFT(P$19,7)="Nominal",P$8,1) -> 0 | Q12: =(IF(Q$4<Q$14,0,Q$15+(Q$16-Q$15)/MAX(Q$17-Q$14,1)*IF(OR(Q$4<=Q$17,Q$18="Linear*"),Q$4-Q$14,Q$17-Q$14)))*IF(LEFT(Q$19,7)="Nominal",Q$8,1) -> 0 | R12: =(IF(R$4<R$14,0,R$15+(R$16-R$15)/MAX(R$17-R$14,1)*IF(OR(R$4<=R$17,R$18="Linear*"),R$4-R$14,R$17-R$14)))*IF(LEFT(R$19,7)="Nominal",R$8,1) -> 0 | S12: =(IF(S$4<S$14,0,S$15+(S$16-S$15)/MAX(S$17-S$14,1)*IF(OR(S$4<=S$17,S$18="Linear*"),S$4-S$14,S$17-S$14)))*IF(LEFT(S$19,7)="Nominal",S$8,1) -> 0 | T12: =(IF(T$4<T$14,0,T$15+(T$16-T$15)/MAX(T$17-T$14,1)*IF(OR(T$4<=T$17,T$18="Linear*"),T$4-T$14,T$17-T$14)))*IF(LEFT(T$19,7)="Nominal",T$8,1) -> 0 | ... Z12: =(IF(Z$4<Z$14,0,Z$15+(Z$16-Z$15)/MAX(Z$17-Z$14,1)*IF(OR(Z$4<=Z$17,Z$18="Linear*"),Z$4-Z$14,Z$17-Z$14)))*IF(LEFT(Z$19,7)="Nominal",Z$8,1) -> 0 | AB12: =LOWER(Settings!$C$4)&".mit."&$A12&IF($C12="","","."&$C12&"."&$B12)&IF(INDEX(Variables!$D$5:$D$65,MATCH($A12,Variables!$A$5:$A$65,0))="","","."&INDEX(Variables!$D$5:$D$65,MATCH($A12,Variables!$A$5:$A$65,0)))&"."&AB$5 -> egy.mit.cptraj.2 | AC12: =(IF(AC$4<AC$14,0,AC$15+(AC$16-AC$15)/MAX(AC$17-AC$14,1)*IF(OR(AC$4<=AC$17,AC$18="Linear*"),AC$4-AC$14,AC$17-AC$14)))*IF(LEFT(AC$19,7)="Nominal",AC$8,1) -> 0 | AD12: =(IF(AD$4<AD$14,0,AD$15+(AD$16-AD$15)/MAX(AD$17-AD$14,1)*IF(OR(AD$4<=AD$17,AD$18="Linear*"),AD$4-AD$14,AD$17-AD$14)))*IF(LEFT(AD$19,7)="Nominal",AD$8,1) -> 0 | AE12: =(IF(AE$4<AE$14,0,AE$15+(AE$16-AE$15)/MAX(AE$17-AE$14,1)*IF(OR(AE$4<=AE$17,AE$18="Linear*"),AE$4-AE$14,AE$17-AE$14)))*IF(LEFT(AE$19,7)="Nominal",AE$8,1) -> 0 | AF12: =(IF(AF$4<AF$14,0,AF$15+(AF$16-AF$15)/MAX(AF$17-AF$14,1)*IF(OR(AF$4<=AF$17,AF$18="Linear*"),AF$4-AF$14,AF$17-AF$14)))*IF(LEFT(AF$19,7)="Nominal",AF$8,1) -> 0 | AG12: =(IF(AG$4<AG$14,0,AG$15+(AG$16-AG$15)/MAX(AG$17-AG$14,1)*IF(OR(AG$4<=AG$17,AG$18="Linear*"),AG$4-AG$14,AG$17-AG$14)))*IF(LEFT(AG$19,7)="Nominal",AG$8,1) -> 0 | AH12: =(IF(AH$4<AH$14,0,AH$15+(AH$16-AH$15)/MAX(AH$17-AH$14,1)*IF(OR(AH$4<=AH$17,AH$18="Linear*"),AH$4-AH$14,AH$17-AH$14)))*IF(LEFT(AH$19,7)="Nominal",AH$8,1) -> 20 | AI12: =(IF(AI$4<AI$14,0,AI$15+(AI$16-AI$15)/MAX(AI$17-AI$14,1)*IF(OR(AI$4<=AI$17,AI$18="Linear*"),AI$4-AI$14,AI$17-AI$14)))*IF(LEFT(AI$19,7)="Nominal",AI$8,1) -> 20 | AJ12: =(IF(AJ$4<AJ$14,0,AJ$15+(AJ$16-AJ$15)/MAX(AJ$17-AJ$14,1)*IF(OR(AJ$4<=AJ$17,AJ$18="Linear*"),AJ$4-AJ$14,AJ$17-AJ$14)))*IF(LEFT(AJ$19,7)="Nominal",AJ$8,1) -> 20 | ... AP12: =(IF(AP$4<AP$14,0,AP$15+(AP$16-AP$15)/MAX(AP$17-AP$14,1)*IF(OR(AP$4<=AP$17,AP$18="Linear*"),AP$4-AP$14,AP$17-AP$14)))*IF(LEFT(AP$19,7)="Nominal",AP$8,1) -> 20
H13: Carbon tax (MTInputs rows 18-21, 265, 266)
A14: CPIntro | D14: 18 | H14: =INDEX(Variables!$B$5:$B$65,MATCH($A14,Variables!$A$5:$A$65,0))&IF($C14="",""," | "&INDEX(Mapping!$B$5:$B$26,MATCH($C14,Mapping!$A$5:$A$26,0))&" | "&INDEX(Mapping!$B$30:$B$41,MATCH($B14,Mapping!$A$30:$A$41,0))) -> Carbon pricing start year | I14: =INDEX(Variables!$C$5:$C$65,MATCH($A14,Variables!$A$5:$A$65,0)) -> year | J14: =INDEX(Variables!$E$5:$E$65,MATCH($A14,Variables!$A$5:$A$65,0)) -> MTInputs (scenario column) | L14: =LOWER(Settings!$C$4)&".mit."&$A14&IF($C14="","","."&$C14&"."&$B14)&IF(INDEX(Variables!$D$5:$D$65,MATCH($A14,Variables!$A$5:$A$65,0))="","","."&INDEX(Variables!$D$5:$D$65,MATCH($A14,Variables!$A$5:$A$65,0)))&"."&L$5 -> egy.mit.CPIntro.1 | M14: =INDEX(MTInputs!$J$1:$AZ$415,$D14,MATCH(M$5,MTInputs!$J$5:$AZ$5,0)) -> 2027 | N14: =INDEX(MTInputs!$J$1:$AZ$415,$D14,MATCH(N$5,MTInputs!$J$5:$AZ$5,0)) -> 2027 | O14: =INDEX(MTInputs!$J$1:$AZ$415,$D14,MATCH(O$5,MTInputs!$J$5:$AZ$5,0)) -> 2027 | P14: =INDEX(MTInputs!$J$1:$AZ$415,$D14,MATCH(P$5,MTInputs!$J$5:$AZ$5,0)) -> 2027 | Q14: =INDEX(MTInputs!$J$1:$AZ$415,$D14,MATCH(Q$5,MTInputs!$J$5:$AZ$5,0)) -> 2027 | R14: =INDEX(MTInputs!$J$1:$AZ$415,$D14,MATCH(R$5,MTInputs!$J$5:$AZ$5,0)) -> 2027 | S14: =INDEX(MTInputs!$J$1:$AZ$415,$D14,MATCH(S$5,MTInputs!$J$5:$AZ$5,0)) -> 2027 | T14: =INDEX(MTInputs!$J$1:$AZ$415,$D14,MATCH(T$5,MTInputs!$J$5:$AZ$5,0)) -> 2027 | ... Z14: =INDEX(MTInputs!$J$1:$AZ$415,$D14,MATCH(Z$5,MTInputs!$J$5:$AZ$5,0)) -> 2027 | AB14: =LOWER(Settings!$C$4)&".mit."&$A14&IF($C14="","","."&$C14&"."&$B14)&IF(INDEX(Variables!$D$5:$D$65,MATCH($A14,Variables!$A$5:$A$65,0))="","","."&INDEX(Variables!$D$5:$D$65,MATCH($A14,Variables!$A$5:$A$65,0)))&"."&AB$5 -> egy.mit.CPIntro.2 | AC14: =INDEX(MTInputs!$J$1:$AZ$415,$D14,MATCH(AC$5,MTInputs!$J$5:$AZ$5,0)) -> 2027 | AD14: =INDEX(MTInputs!$J$1:$AZ$415,$D14,MATCH(AD$5,MTInputs!$J$5:$AZ$5,0)) -> 2027 | AE14: =INDEX(MTInputs!$J$1:$AZ$415,$D14,MATCH(AE$5,MTInputs!$J$5:$AZ$5,0)) -> 2027 | AF14: =INDEX(MTInputs!$J$1:$AZ$415,$D14,MATCH(AF$5,MTInputs!$J$5:$AZ$5,0)) -> 2027 | AG14: =INDEX(MTInputs!$J$1:$AZ$415,$D14,MATCH(AG$5,MTInputs!$J$5:$AZ$5,0)) -> 2027 | AH14: =INDEX(MTInputs!$J$1:$AZ$415,$D14,MATCH(AH$5,MTInputs!$J$5:$AZ$5,0)) -> 2027 | AI14: =INDEX(MTInputs!$J$1:$AZ$415,$D14,MATCH(AI$5,MTInputs!$J$5:$AZ$5,0)) -> 2027 | AJ14: =INDEX(MTInputs!$J$1:$AZ$415,$D14,MATCH(AJ$5,MTInputs!$J$5:$AZ$5,0)) -> 2027 | ... AP14: =INDEX(MTInputs!$J$1:$AZ$415,$D14,MATCH(AP$5,MTInputs!$J$5:$AZ$5,0)) -> 2027
A15: CPLevelStart | D15: 19 | H15: =INDEX(Variables!$B$5:$B$65,MATCH($A15,Variables!$A$5:$A$65,0))&IF($C15="",""," | "&INDEX(Mapping!$B$5:$B$26,MATCH($C15,Mapping!$A$5:$A$26,0))&" | "&INDEX(Mapping!$B$30:$B$41,MATCH($B15,Mapping!$A$30:$A$41,0))) -> Starting carbon price | I15: =INDEX(Variables!$C$5:$C$65,MATCH($A15,Variables!$A$5:$A$65,0)) -> nom. USD/tCO2 | J15: =INDEX(Variables!$E$5:$E$65,MATCH($A15,Variables!$A$5:$A$65,0)) -> MTInputs (scenario column) | L15: =LOWER(Settings!$C$4)&".mit."&$A15&IF($C15="","","."&$C15&"."&$B15)&IF(INDEX(Variables!$D$5:$D$65,MATCH($A15,Variables!$A$5:$A$65,0))="","","."&INDEX(Variables!$D$5:$D$65,MATCH($A15,Variables!$A$5:$A$65,0)))&"."&L$5 -> egy.mit.CPLevelStart.1 | M15: =INDEX(MTInputs!$J$1:$AZ$415,$D15,MATCH(M$5,MTInputs!$J$5:$AZ$5,0)) -> 0 | N15: =INDEX(MTInputs!$J$1:$AZ$415,$D15,MATCH(N$5,MTInputs!$J$5:$AZ$5,0)) -> 0 | O15: =INDEX(MTInputs!$J$1:$AZ$415,$D15,MATCH(O$5,MTInputs!$J$5:$AZ$5,0)) -> 0 | P15: =INDEX(MTInputs!$J$1:$AZ$415,$D15,MATCH(P$5,MTInputs!$J$5:$AZ$5,0)) -> 0 | Q15: =INDEX(MTInputs!$J$1:$AZ$415,$D15,MATCH(Q$5,MTInputs!$J$5:$AZ$5,0)) -> 0 | R15: =INDEX(MTInputs!$J$1:$AZ$415,$D15,MATCH(R$5,MTInputs!$J$5:$AZ$5,0)) -> 0 | S15: =INDEX(MTInputs!$J$1:$AZ$415,$D15,MATCH(S$5,MTInputs!$J$5:$AZ$5,0)) -> 0 | T15: =INDEX(MTInputs!$J$1:$AZ$415,$D15,MATCH(T$5,MTInputs!$J$5:$AZ$5,0)) -> 0 | ... Z15: =INDEX(MTInputs!$J$1:$AZ$415,$D15,MATCH(Z$5,MTInputs!$J$5:$AZ$5,0)) -> 0 | AB15: =LOWER(Settings!$C$4)&".mit."&$A15&IF($C15="","","."&$C15&"."&$B15)&IF(INDEX(Variables!$D$5:$D$65,MATCH($A15,Variables!$A$5:$A$65,0))="","","."&INDEX(Variables!$D$5:$D$65,MATCH($A15,Variables!$A$5:$A$65,0)))&"."&AB$5 -> egy.mit.CPLevelStart.2 | AC15: =INDEX(MTInputs!$J$1:$AZ$415,$D15,MATCH(AC$5,MTInputs!$J$5:$AZ$5,0)) -> 20 | AD15: =INDEX(MTInputs!$J$1:$AZ$415,$D15,MATCH(AD$5,MTInputs!$J$5:$AZ$5,0)) -> 20 | AE15: =INDEX(MTInputs!$J$1:$AZ$415,$D15,MATCH(AE$5,MTInputs!$J$5:$AZ$5,0)) -> 20 | AF15: =INDEX(MTInputs!$J$1:$AZ$415,$D15,MATCH(AF$5,MTInputs!$J$5:$AZ$5,0)) -> 20 | AG15: =INDEX(MTInputs!$J$1:$AZ$415,$D15,MATCH(AG$5,MTInputs!$J$5:$AZ$5,0)) -> 20 | AH15: =INDEX(MTInputs!$J$1:$AZ$415,$D15,MATCH(AH$5,MTInputs!$J$5:$AZ$5,0)) -> 20 | AI15: =INDEX(MTInputs!$J$1:$AZ$415,$D15,MATCH(AI$5,MTInputs!$J$5:$AZ$5,0)) -> 20 | AJ15: =INDEX(MTInputs!$J$1:$AZ$415,$D15,MATCH(AJ$5,MTInputs!$J$5:$AZ$5,0)) -> 20 | ... AP15: =INDEX(MTInputs!$J$1:$AZ$415,$D15,MATCH(AP$5,MTInputs!$J$5:$AZ$5,0)) -> 20
A16: CPLevelTarget | D16: 20 | H16: =INDEX(Variables!$B$5:$B$65,MATCH($A16,Variables!$A$5:$A$65,0))&IF($C16="",""," | "&INDEX(Mapping!$B$5:$B$26,MATCH($C16,Mapping!$A$5:$A$26,0))&" | "&INDEX(Mapping!$B$30:$B$41,MATCH($B16,Mapping!$A$30:$A$41,0))) -> Target level of carbon price | I16: =INDEX(Variables!$C$5:$C$65,MATCH($A16,Variables!$A$5:$A$65,0)) -> nom. USD/tCO2 | J16: =INDEX(Variables!$E$5:$E$65,MATCH($A16,Variables!$A$5:$A$65,0)) -> MTInputs (scenario column) | L16: =LOWER(Settings!$C$4)&".mit."&$A16&IF($C16="","","."&$C16&"."&$B16)&IF(INDEX(Variables!$D$5:$D$65,MATCH($A16,Variables!$A$5:$A$65,0))="","","."&INDEX(Variables!$D$5:$D$65,MATCH($A16,Variables!$A$5:$A$65,0)))&"."&L$5 -> egy.mit.CPLevelTarget.1 | M16: =INDEX(MTInputs!$J$1:$AZ$415,$D16,MATCH(M$5,MTInputs!$J$5:$AZ$5,0)) -> 0 | N16: =INDEX(MTInputs!$J$1:$AZ$415,$D16,MATCH(N$5,MTInputs!$J$5:$AZ$5,0)) -> 0 | O16: =INDEX(MTInputs!$J$1:$AZ$415,$D16,MATCH(O$5,MTInputs!$J$5:$AZ$5,0)) -> 0 | P16: =INDEX(MTInputs!$J$1:$AZ$415,$D16,MATCH(P$5,MTInputs!$J$5:$AZ$5,0)) -> 0 | Q16: =INDEX(MTInputs!$J$1:$AZ$415,$D16,MATCH(Q$5,MTInputs!$J$5:$AZ$5,0)) -> 0 | R16: =INDEX(MTInputs!$J$1:$AZ$415,$D16,MATCH(R$5,MTInputs!$J$5:$AZ$5,0)) -> 0 | S16: =INDEX(MTInputs!$J$1:$AZ$415,$D16,MATCH(S$5,MTInputs!$J$5:$AZ$5,0)) -> 0 | T16: =INDEX(MTInputs!$J$1:$AZ$415,$D16,MATCH(T$5,MTInputs!$J$5:$AZ$5,0)) -> 0 | ... Z16: =INDEX(MTInputs!$J$1:$AZ$415,$D16,MATCH(Z$5,MTInputs!$J$5:$AZ$5,0)) -> 0 | AB16: =LOWER(Settings!$C$4)&".mit."&$A16&IF($C16="","","."&$C16&"."&$B16)&IF(INDEX(Variables!$D$5:$D$65,MATCH($A16,Variables!$A$5:$A$65,0))="","","."&INDEX(Variables!$D$5:$D$65,MATCH($A16,Variables!$A$5:$A$65,0)))&"."&AB$5 -> egy.mit.CPLevelTarget.2 | AC16: =INDEX(MTInputs!$J$1:$AZ$415,$D16,MATCH(AC$5,MTInputs!$J$5:$AZ$5,0)) -> 20 | AD16: =INDEX(MTInputs!$J$1:$AZ$415,$D16,MATCH(AD$5,MTInputs!$J$5:$AZ$5,0)) -> 20 | AE16: =INDEX(MTInputs!$J$1:$AZ$415,$D16,MATCH(AE$5,MTInputs!$J$5:$AZ$5,0)) -> 20 | AF16: =INDEX(MTInputs!$J$1:$AZ$415,$D16,MATCH(AF$5,MTInputs!$J$5:$AZ$5,0)) -> 20 | AG16: =INDEX(MTInputs!$J$1:$AZ$415,$D16,MATCH(AG$5,MTInputs!$J$5:$AZ$5,0)) -> 20 | AH16: =INDEX(MTInputs!$J$1:$AZ$415,$D16,MATCH(AH$5,MTInputs!$J$5:$AZ$5,0)) -> 20 | AI16: =INDEX(MTInputs!$J$1:$AZ$415,$D16,MATCH(AI$5,MTInputs!$J$5:$AZ$5,0)) -> 20 | AJ16: =INDEX(MTInputs!$J$1:$AZ$415,$D16,MATCH(AJ$5,MTInputs!$J$5:$AZ$5,0)) -> 20 | ... AP16: =INDEX(MTInputs!$J$1:$AZ$415,$D16,MATCH(AP$5,MTInputs!$J$5:$AZ$5,0)) -> 20
A17: CPOutro | D17: 21 | H17: =INDEX(Variables!$B$5:$B$65,MATCH($A17,Variables!$A$5:$A$65,0))&IF($C17="",""," | "&INDEX(Mapping!$B$5:$B$26,MATCH($C17,Mapping!$A$5:$A$26,0))&" | "&INDEX(Mapping!$B$30:$B$41,MATCH($B17,Mapping!$A$30:$A$41,0))) -> Year to reach target level | I17: =INDEX(Variables!$C$5:$C$65,MATCH($A17,Variables!$A$5:$A$65,0)) -> year | J17: =INDEX(Variables!$E$5:$E$65,MATCH($A17,Variables!$A$5:$A$65,0)) -> MTInputs (scenario column) | L17: =LOWER(Settings!$C$4)&".mit."&$A17&IF($C17="","","."&$C17&"."&$B17)&IF(INDEX(Variables!$D$5:$D$65,MATCH($A17,Variables!$A$5:$A$65,0))="","","."&INDEX(Variables!$D$5:$D$65,MATCH($A17,Variables!$A$5:$A$65,0)))&"."&L$5 -> egy.mit.CPOutro.1 | M17: =INDEX(MTInputs!$J$1:$AZ$415,$D17,MATCH(M$5,MTInputs!$J$5:$AZ$5,0)) -> 2030 | N17: =INDEX(MTInputs!$J$1:$AZ$415,$D17,MATCH(N$5,MTInputs!$J$5:$AZ$5,0)) -> 2030 | O17: =INDEX(MTInputs!$J$1:$AZ$415,$D17,MATCH(O$5,MTInputs!$J$5:$AZ$5,0)) -> 2030 | P17: =INDEX(MTInputs!$J$1:$AZ$415,$D17,MATCH(P$5,MTInputs!$J$5:$AZ$5,0)) -> 2030 | Q17: =INDEX(MTInputs!$J$1:$AZ$415,$D17,MATCH(Q$5,MTInputs!$J$5:$AZ$5,0)) -> 2030 | R17: =INDEX(MTInputs!$J$1:$AZ$415,$D17,MATCH(R$5,MTInputs!$J$5:$AZ$5,0)) -> 2030 | S17: =INDEX(MTInputs!$J$1:$AZ$415,$D17,MATCH(S$5,MTInputs!$J$5:$AZ$5,0)) -> 2030 | T17: =INDEX(MTInputs!$J$1:$AZ$415,$D17,MATCH(T$5,MTInputs!$J$5:$AZ$5,0)) -> 2030 | ... Z17: =INDEX(MTInputs!$J$1:$AZ$415,$D17,MATCH(Z$5,MTInputs!$J$5:$AZ$5,0)) -> 2030 | AB17: =LOWER(Settings!$C$4)&".mit."&$A17&IF($C17="","","."&$C17&"."&$B17)&IF(INDEX(Variables!$D$5:$D$65,MATCH($A17,Variables!$A$5:$A$65,0))="","","."&INDEX(Variables!$D$5:$D$65,MATCH($A17,Variables!$A$5:$A$65,0)))&"."&AB$5 -> egy.mit.CPOutro.2 | AC17: =INDEX(MTInputs!$J$1:$AZ$415,$D17,MATCH(AC$5,MTInputs!$J$5:$AZ$5,0)) -> 2030 | AD17: =INDEX(MTInputs!$J$1:$AZ$415,$D17,MATCH(AD$5,MTInputs!$J$5:$AZ$5,0)) -> 2030 | AE17: =INDEX(MTInputs!$J$1:$AZ$415,$D17,MATCH(AE$5,MTInputs!$J$5:$AZ$5,0)) -> 2030 | AF17: =INDEX(MTInputs!$J$1:$AZ$415,$D17,MATCH(AF$5,MTInputs!$J$5:$AZ$5,0)) -> 2030 | AG17: =INDEX(MTInputs!$J$1:$AZ$415,$D17,MATCH(AG$5,MTInputs!$J$5:$AZ$5,0)) -> 2030 | AH17: =INDEX(MTInputs!$J$1:$AZ$415,$D17,MATCH(AH$5,MTInputs!$J$5:$AZ$5,0)) -> 2030 | AI17: =INDEX(MTInputs!$J$1:$AZ$415,$D17,MATCH(AI$5,MTInputs!$J$5:$AZ$5,0)) -> 2030 | AJ17: =INDEX(MTInputs!$J$1:$AZ$415,$D17,MATCH(AJ$5,MTInputs!$J$5:$AZ$5,0)) -> 2030 | ... AP17: =INDEX(MTInputs!$J$1:$AZ$415,$D17,MATCH(AP$5,MTInputs!$J$5:$AZ$5,0)) -> 2030
A18: ExtendCarbonPriceBeyondOutro | D18: 265 | H18: =INDEX(Variables!$B$5:$B$65,MATCH($A18,Variables!$A$5:$A$65,0))&IF($C18="",""," | "&INDEX(Mapping!$B$5:$B$26,MATCH($C18,Mapping!$A$5:$A$26,0))&" | "&INDEX(Mapping!$B$30:$B$41,MATCH($B18,Mapping!$A$30:$A$41,0))) -> Price pathway continues to rise after target year? | I18: =INDEX(Variables!$C$5:$C$65,MATCH($A18,Variables!$A$5:$A$65,0)) -> switch | J18: =INDEX(Variables!$E$5:$E$65,MATCH($A18,Variables!$A$5:$A$65,0)) -> MTInputs (scenario column) | L18: =LOWER(Settings!$C$4)&".mit."&$A18&IF($C18="","","."&$C18&"."&$B18)&IF(INDEX(Variables!$D$5:$D$65,MATCH($A18,Variables!$A$5:$A$65,0))="","","."&INDEX(Variables!$D$5:$D$65,MATCH($A18,Variables!$A$5:$A$65,0)))&"."&L$5 -> egy.mit.ExtendCarbonPriceBeyondOutro.1 | M18: =INDEX(MTInputs!$J$1:$AZ$415,$D18,MATCH(M$5,MTInputs!$J$5:$AZ$5,0)) -> Linear* | N18: =INDEX(MTInputs!$J$1:$AZ$415,$D18,MATCH(N$5,MTInputs!$J$5:$AZ$5,0)) -> Linear* | O18: =INDEX(MTInputs!$J$1:$AZ$415,$D18,MATCH(O$5,MTInputs!$J$5:$AZ$5,0)) -> Linear* | P18: =INDEX(MTInputs!$J$1:$AZ$415,$D18,MATCH(P$5,MTInputs!$J$5:$AZ$5,0)) -> Linear* | Q18: =INDEX(MTInputs!$J$1:$AZ$415,$D18,MATCH(Q$5,MTInputs!$J$5:$AZ$5,0)) -> Linear* | R18: =INDEX(MTInputs!$J$1:$AZ$415,$D18,MATCH(R$5,MTInputs!$J$5:$AZ$5,0)) -> Linear* | S18: =INDEX(MTInputs!$J$1:$AZ$415,$D18,MATCH(S$5,MTInputs!$J$5:$AZ$5,0)) -> Linear* | T18: =INDEX(MTInputs!$J$1:$AZ$415,$D18,MATCH(T$5,MTInputs!$J$5:$AZ$5,0)) -> Linear* | ... Z18: =INDEX(MTInputs!$J$1:$AZ$415,$D18,MATCH(Z$5,MTInputs!$J$5:$AZ$5,0)) -> Linear* | AB18: =LOWER(Settings!$C$4)&".mit."&$A18&IF($C18="","","."&$C18&"."&$B18)&IF(INDEX(Variables!$D$5:$D$65,MATCH($A18,Variables!$A$5:$A$65,0))="","","."&INDEX(Variables!$D$5:$D$65,MATCH($A18,Variables!$A$5:$A$65,0)))&"."&AB$5 -> egy.mit.ExtendCarbonPriceBeyondOutro.2 | AC18: =INDEX(MTInputs!$J$1:$AZ$415,$D18,MATCH(AC$5,MTInputs!$J$5:$AZ$5,0)) -> Linear* | AD18: =INDEX(MTInputs!$J$1:$AZ$415,$D18,MATCH(AD$5,MTInputs!$J$5:$AZ$5,0)) -> Linear* | AE18: =INDEX(MTInputs!$J$1:$AZ$415,$D18,MATCH(AE$5,MTInputs!$J$5:$AZ$5,0)) -> Linear* | AF18: =INDEX(MTInputs!$J$1:$AZ$415,$D18,MATCH(AF$5,MTInputs!$J$5:$AZ$5,0)) -> Linear* | AG18: =INDEX(MTInputs!$J$1:$AZ$415,$D18,MATCH(AG$5,MTInputs!$J$5:$AZ$5,0)) -> Linear* | AH18: =INDEX(MTInputs!$J$1:$AZ$415,$D18,MATCH(AH$5,MTInputs!$J$5:$AZ$5,0)) -> Linear* | AI18: =INDEX(MTInputs!$J$1:$AZ$415,$D18,MATCH(AI$5,MTInputs!$J$5:$AZ$5,0)) -> Linear* | AJ18: =INDEX(MTInputs!$J$1:$AZ$415,$D18,MATCH(AJ$5,MTInputs!$J$5:$AZ$5,0)) -> Linear* | ... AP18: =INDEX(MTInputs!$J$1:$AZ$415,$D18,MATCH(AP$5,MTInputs!$J$5:$AZ$5,0)) -> Linear*
A19: NomorReal | D19: 266 | H19: =INDEX(Variables!$B$5:$B$65,MATCH($A19,Variables!$A$5:$A$65,0))&IF($C19="",""," | "&INDEX(Mapping!$B$5:$B$26,MATCH($C19,Mapping!$A$5:$A$26,0))&" | "&INDEX(Mapping!$B$30:$B$41,MATCH($B19,Mapping!$A$30:$A$41,0))) -> Tax pathway is in nominal or real terms? | I19: =INDEX(Variables!$C$5:$C$65,MATCH($A19,Variables!$A$5:$A$65,0)) -> switch | J19: =INDEX(Variables!$E$5:$E$65,MATCH($A19,Variables!$A$5:$A$65,0)) -> MTInputs (scenario column) | L19: =LOWER(Settings!$C$4)&".mit."&$A19&IF($C19="","","."&$C19&"."&$B19)&IF(INDEX(Variables!$D$5:$D$65,MATCH($A19,Variables!$A$5:$A$65,0))="","","."&INDEX(Variables!$D$5:$D$65,MATCH($A19,Variables!$A$5:$A$65,0)))&"."&L$5 -> egy.mit.NomorReal.1 | M19: =INDEX(MTInputs!$J$1:$AZ$415,$D19,MATCH(M$5,MTInputs!$J$5:$AZ$5,0)) -> Real* | N19: =INDEX(MTInputs!$J$1:$AZ$415,$D19,MATCH(N$5,MTInputs!$J$5:$AZ$5,0)) -> Real* | O19: =INDEX(MTInputs!$J$1:$AZ$415,$D19,MATCH(O$5,MTInputs!$J$5:$AZ$5,0)) -> Real* | P19: =INDEX(MTInputs!$J$1:$AZ$415,$D19,MATCH(P$5,MTInputs!$J$5:$AZ$5,0)) -> Real* | Q19: =INDEX(MTInputs!$J$1:$AZ$415,$D19,MATCH(Q$5,MTInputs!$J$5:$AZ$5,0)) -> Real* | R19: =INDEX(MTInputs!$J$1:$AZ$415,$D19,MATCH(R$5,MTInputs!$J$5:$AZ$5,0)) -> Real* | S19: =INDEX(MTInputs!$J$1:$AZ$415,$D19,MATCH(S$5,MTInputs!$J$5:$AZ$5,0)) -> Real* | T19: =INDEX(MTInputs!$J$1:$AZ$415,$D19,MATCH(T$5,MTInputs!$J$5:$AZ$5,0)) -> Real* | ... Z19: =INDEX(MTInputs!$J$1:$AZ$415,$D19,MATCH(Z$5,MTInputs!$J$5:$AZ$5,0)) -> Real* | AB19: =LOWER(Settings!$C$4)&".mit."&$A19&IF($C19="","","."&$C19&"."&$B19)&IF(INDEX(Variables!$D$5:$D$65,MATCH($A19,Variables!$A$5:$A$65,0))="","","."&INDEX(Variables!$D$5:$D$65,MATCH($A19,Variables!$A$5:$A$65,0)))&"."&AB$5 -> egy.mit.NomorReal.2 | AC19: =INDEX(MTInputs!$J$1:$AZ$415,$D19,MATCH(AC$5,MTInputs!$J$5:$AZ$5,0)) -> Real* | AD19: =INDEX(MTInputs!$J$1:$AZ$415,$D19,MATCH(AD$5,MTInputs!$J$5:$AZ$5,0)) -> Real* | AE19: =INDEX(MTInputs!$J$1:$AZ$415,$D19,MATCH(AE$5,MTInputs!$J$5:$AZ$5,0)) -> Real* | AF19: =INDEX(MTInputs!$J$1:$AZ$415,$D19,MATCH(AF$5,MTInputs!$J$5:$AZ$5,0)) -> Real* | AG19: =INDEX(MTInputs!$J$1:$AZ$415,$D19,MATCH(AG$5,MTInputs!$J$5:$AZ$5,0)) -> Real* | AH19: =INDEX(MTInputs!$J$1:$AZ$415,$D19,MATCH(AH$5,MTInputs!$J$5:$AZ$5,0)) -> Real* | AI19: =INDEX(MTInputs!$J$1:$AZ$415,$D19,MATCH(AI$5,MTInputs!$J$5:$AZ$5,0)) -> Real* | AJ19: =INDEX(MTInputs!$J$1:$AZ$415,$D19,MATCH(AJ$5,MTInputs!$J$5:$AZ$5,0)) -> Real* | ... AP19: =INDEX(MTInputs!$J$1:$AZ$415,$D19,MATCH(AP$5,MTInputs!$J$5:$AZ$5,0)) -> Real*
H20: Carbon tax coverage: fuels (MTInputs rows 23-29)
A21: ctcov | B21: coa | C21: all | D21: 23 | H21: =INDEX(Variables!$B$5:$B$65,MATCH($A21,Variables!$A$5:$A$65,0))&IF($C21="",""," | "&INDEX(Mapping!$B$5:$B$26,MATCH($C21,Mapping!$A$5:$A$26,0))&" | "&INDEX(Mapping!$B$30:$B$41,MATCH($B21,Mapping!$A$30:$A$41,0))) -> Carbon tax coverage (Apply tax?) | All subsectors | Coal | I21: =INDEX(Variables!$C$5:$C$65,MATCH($A21,Variables!$A$5:$A$65,0)) -> switch | J21: =INDEX(Variables!$E$5:$E$65,MATCH($A21,Variables!$A$5:$A$65,0)) -> MTInputs (scenario column) | L21: =LOWER(Settings!$C$4)&".mit."&$A21&IF($C21="","","."&$C21&"."&$B21)&IF(INDEX(Variables!$D$5:$D$65,MATCH($A21,Variables!$A$5:$A$65,0))="","","."&INDEX(Variables!$D$5:$D$65,MATCH($A21,Variables!$A$5:$A$65,0)))&"."&L$5 -> egy.mit.ctcov.all.coa.1 | M21: =INDEX(MTInputs!$J$1:$AZ$415,$D21,MATCH(M$5,MTInputs!$J$5:$AZ$5,0)) -> TRUE | N21: =INDEX(MTInputs!$J$1:$AZ$415,$D21,MATCH(N$5,MTInputs!$J$5:$AZ$5,0)) -> TRUE | O21: =INDEX(MTInputs!$J$1:$AZ$415,$D21,MATCH(O$5,MTInputs!$J$5:$AZ$5,0)) -> TRUE | P21: =INDEX(MTInputs!$J$1:$AZ$415,$D21,MATCH(P$5,MTInputs!$J$5:$AZ$5,0)) -> TRUE | Q21: =INDEX(MTInputs!$J$1:$AZ$415,$D21,MATCH(Q$5,MTInputs!$J$5:$AZ$5,0)) -> TRUE | R21: =INDEX(MTInputs!$J$1:$AZ$415,$D21,MATCH(R$5,MTInputs!$J$5:$AZ$5,0)) -> TRUE | S21: =INDEX(MTInputs!$J$1:$AZ$415,$D21,MATCH(S$5,MTInputs!$J$5:$AZ$5,0)) -> TRUE | T21: =INDEX(MTInputs!$J$1:$AZ$415,$D21,MATCH(T$5,MTInputs!$J$5:$AZ$5,0)) -> TRUE | ... Z21: =INDEX(MTInputs!$J$1:$AZ$415,$D21,MATCH(Z$5,MTInputs!$J$5:$AZ$5,0)) -> TRUE | AB21: =LOWER(Settings!$C$4)&".mit."&$A21&IF($C21="","","."&$C21&"."&$B21)&IF(INDEX(Variables!$D$5:$D$65,MATCH($A21,Variables!$A$5:$A$65,0))="","","."&INDEX(Variables!$D$5:$D$65,MATCH($A21,Variables!$A$5:$A$65,0)))&"."&AB$5 -> egy.mit.ctcov.all.coa.2 | AC21: =INDEX(MTInputs!$J$1:$AZ$415,$D21,MATCH(AC$5,MTInputs!$J$5:$AZ$5,0)) -> TRUE | AD21: =INDEX(MTInputs!$J$1:$AZ$415,$D21,MATCH(AD$5,MTInputs!$J$5:$AZ$5,0)) -> TRUE | AE21: =INDEX(MTInputs!$J$1:$AZ$415,$D21,MATCH(AE$5,MTInputs!$J$5:$AZ$5,0)) -> TRUE | AF21: =INDEX(MTInputs!$J$1:$AZ$415,$D21,MATCH(AF$5,MTInputs!$J$5:$AZ$5,0)) -> TRUE | AG21: =INDEX(MTInputs!$J$1:$AZ$415,$D21,MATCH(AG$5,MTInputs!$J$5:$AZ$5,0)) -> TRUE | AH21: =INDEX(MTInputs!$J$1:$AZ$415,$D21,MATCH(AH$5,MTInputs!$J$5:$AZ$5,0)) -> TRUE | AI21: =INDEX(MTInputs!$J$1:$AZ$415,$D21,MATCH(AI$5,MTInputs!$J$5:$AZ$5,0)) -> TRUE | AJ21: =INDEX(MTInputs!$J$1:$AZ$415,$D21,MATCH(AJ$5,MTInputs!$J$5:$AZ$5,0)) -> TRUE | ... AP21: =INDEX(MTInputs!$J$1:$AZ$415,$D21,MATCH(AP$5,MTInputs!$J$5:$AZ$5,0)) -> TRUE
A22: ctcov | B22: nga | C22: all | D22: 24 | H22: =INDEX(Variables!$B$5:$B$65,MATCH($A22,Variables!$A$5:$A$65,0))&IF($C22="",""," | "&INDEX(Mapping!$B$5:$B$26,MATCH($C22,Mapping!$A$5:$A$26,0))&" | "&INDEX(Mapping!$B$30:$B$41,MATCH($B22,Mapping!$A$30:$A$41,0))) -> Carbon tax coverage (Apply tax?) | All subsectors | Natural gas | I22: =INDEX(Variables!$C$5:$C$65,MATCH($A22,Variables!$A$5:$A$65,0)) -> switch | J22: =INDEX(Variables!$E$5:$E$65,MATCH($A22,Variables!$A$5:$A$65,0)) -> MTInputs (scenario column) | L22: =LOWER(Settings!$C$4)&".mit."&$A22&IF($C22="","","."&$C22&"."&$B22)&IF(INDEX(Variables!$D$5:$D$65,MATCH($A22,Variables!$A$5:$A$65,0))="","","."&INDEX(Variables!$D$5:$D$65,MATCH($A22,Variables!$A$5:$A$65,0)))&"."&L$5 -> egy.mit.ctcov.all.nga.1 | M22: =INDEX(MTInputs!$J$1:$AZ$415,$D22,MATCH(M$5,MTInputs!$J$5:$AZ$5,0)) -> TRUE | N22: =INDEX(MTInputs!$J$1:$AZ$415,$D22,MATCH(N$5,MTInputs!$J$5:$AZ$5,0)) -> TRUE | O22: =INDEX(MTInputs!$J$1:$AZ$415,$D22,MATCH(O$5,MTInputs!$J$5:$AZ$5,0)) -> TRUE | P22: =INDEX(MTInputs!$J$1:$AZ$415,$D22,MATCH(P$5,MTInputs!$J$5:$AZ$5,0)) -> TRUE | Q22: =INDEX(MTInputs!$J$1:$AZ$415,$D22,MATCH(Q$5,MTInputs!$J$5:$AZ$5,0)) -> TRUE | R22: =INDEX(MTInputs!$J$1:$AZ$415,$D22,MATCH(R$5,MTInputs!$J$5:$AZ$5,0)) -> TRUE | S22: =INDEX(MTInputs!$J$1:$AZ$415,$D22,MATCH(S$5,MTInputs!$J$5:$AZ$5,0)) -> TRUE | T22: =INDEX(MTInputs!$J$1:$AZ$415,$D22,MATCH(T$5,MTInputs!$J$5:$AZ$5,0)) -> TRUE | ... Z22: =INDEX(MTInputs!$J$1:$AZ$415,$D22,MATCH(Z$5,MTInputs!$J$5:$AZ$5,0)) -> TRUE | AB22: =LOWER(Settings!$C$4)&".mit."&$A22&IF($C22="","","."&$C22&"."&$B22)&IF(INDEX(Variables!$D$5:$D$65,MATCH($A22,Variables!$A$5:$A$65,0))="","","."&INDEX(Variables!$D$5:$D$65,MATCH($A22,Variables!$A$5:$A$65,0)))&"."&AB$5 -> egy.mit.ctcov.all.nga.2 | AC22: =INDEX(MTInputs!$J$1:$AZ$415,$D22,MATCH(AC$5,MTInputs!$J$5:$AZ$5,0)) -> TRUE | AD22: =INDEX(MTInputs!$J$1:$AZ$415,$D22,MATCH(AD$5,MTInputs!$J$5:$AZ$5,0)) -> TRUE | AE22: =INDEX(MTInputs!$J$1:$AZ$415,$D22,MATCH(AE$5,MTInputs!$J$5:$AZ$5,0)) -> TRUE | AF22: =INDEX(MTInputs!$J$1:$AZ$415,$D22,MATCH(AF$5,MTInputs!$J$5:$AZ$5,0)) -> TRUE | AG22: =INDEX(MTInputs!$J$1:$AZ$415,$D22,MATCH(AG$5,MTInputs!$J$5:$AZ$5,0)) -> TRUE | AH22: =INDEX(MTInputs!$J$1:$AZ$415,$D22,MATCH(AH$5,MTInputs!$J$5:$AZ$5,0)) -> TRUE | AI22: =INDEX(MTInputs!$J$1:$AZ$415,$D22,MATCH(AI$5,MTInputs!$J$5:$AZ$5,0)) -> TRUE | AJ22: =INDEX(MTInputs!$J$1:$AZ$415,$D22,MATCH(AJ$5,MTInputs!$J$5:$AZ$5,0)) -> TRUE | ... AP22: =INDEX(MTInputs!$J$1:$AZ$415,$D22,MATCH(AP$5,MTInputs!$J$5:$AZ$5,0)) -> TRUE
A23: ctcov | B23: gso | C23: all | D23: 25 | H23: =INDEX(Variables!$B$5:$B$65,MATCH($A23,Variables!$A$5:$A$65,0))&IF($C23="",""," | "&INDEX(Mapping!$B$5:$B$26,MATCH($C23,Mapping!$A$5:$A$26,0))&" | "&INDEX(Mapping!$B$30:$B$41,MATCH($B23,Mapping!$A$30:$A$41,0))) -> Carbon tax coverage (Apply tax?) | All subsectors | Gasoline | I23: =INDEX(Variables!$C$5:$C$65,MATCH($A23,Variables!$A$5:$A$65,0)) -> switch | J23: =INDEX(Variables!$E$5:$E$65,MATCH($A23,Variables!$A$5:$A$65,0)) -> MTInputs (scenario column) | L23: =LOWER(Settings!$C$4)&".mit."&$A23&IF($C23="","","."&$C23&"."&$B23)&IF(INDEX(Variables!$D$5:$D$65,MATCH($A23,Variables!$A$5:$A$65,0))="","","."&INDEX(Variables!$D$5:$D$65,MATCH($A23,Variables!$A$5:$A$65,0)))&"."&L$5 -> egy.mit.ctcov.all.gso.1 | M23: =INDEX(MTInputs!$J$1:$AZ$415,$D23,MATCH(M$5,MTInputs!$J$5:$AZ$5,0)) -> TRUE | N23: =INDEX(MTInputs!$J$1:$AZ$415,$D23,MATCH(N$5,MTInputs!$J$5:$AZ$5,0)) -> TRUE | O23: =INDEX(MTInputs!$J$1:$AZ$415,$D23,MATCH(O$5,MTInputs!$J$5:$AZ$5,0)) -> TRUE | P23: =INDEX(MTInputs!$J$1:$AZ$415,$D23,MATCH(P$5,MTInputs!$J$5:$AZ$5,0)) -> TRUE | Q23: =INDEX(MTInputs!$J$1:$AZ$415,$D23,MATCH(Q$5,MTInputs!$J$5:$AZ$5,0)) -> TRUE | R23: =INDEX(MTInputs!$J$1:$AZ$415,$D23,MATCH(R$5,MTInputs!$J$5:$AZ$5,0)) -> TRUE | S23: =INDEX(MTInputs!$J$1:$AZ$415,$D23,MATCH(S$5,MTInputs!$J$5:$AZ$5,0)) -> TRUE | T23: =INDEX(MTInputs!$J$1:$AZ$415,$D23,MATCH(T$5,MTInputs!$J$5:$AZ$5,0)) -> TRUE | ... Z23: =INDEX(MTInputs!$J$1:$AZ$415,$D23,MATCH(Z$5,MTInputs!$J$5:$AZ$5,0)) -> TRUE | AB23: =LOWER(Settings!$C$4)&".mit."&$A23&IF($C23="","","."&$C23&"."&$B23)&IF(INDEX(Variables!$D$5:$D$65,MATCH($A23,Variables!$A$5:$A$65,0))="","","."&INDEX(Variables!$D$5:$D$65,MATCH($A23,Variables!$A$5:$A$65,0)))&"."&AB$5 -> egy.mit.ctcov.all.gso.2 | AC23: =INDEX(MTInputs!$J$1:$AZ$415,$D23,MATCH(AC$5,MTInputs!$J$5:$AZ$5,0)) -> TRUE | AD23: =INDEX(MTInputs!$J$1:$AZ$415,$D23,MATCH(AD$5,MTInputs!$J$5:$AZ$5,0)) -> TRUE | AE23: =INDEX(MTInputs!$J$1:$AZ$415,$D23,MATCH(AE$5,MTInputs!$J$5:$AZ$5,0)) -> TRUE | AF23: =INDEX(MTInputs!$J$1:$AZ$415,$D23,MATCH(AF$5,MTInputs!$J$5:$AZ$5,0)) -> TRUE | AG23: =INDEX(MTInputs!$J$1:$AZ$415,$D23,MATCH(AG$5,MTInputs!$J$5:$AZ$5,0)) -> TRUE | AH23: =INDEX(MTInputs!$J$1:$AZ$415,$D23,MATCH(AH$5,MTInputs!$J$5:$AZ$5,0)) -> TRUE | AI23: =INDEX(MTInputs!$J$1:$AZ$415,$D23,MATCH(AI$5,MTInputs!$J$5:$AZ$5,0)) -> TRUE | AJ23: =INDEX(MTInputs!$J$1:$AZ$415,$D23,MATCH(AJ$5,MTInputs!$J$5:$AZ$5,0)) -> TRUE | ... AP23: =INDEX(MTInputs!$J$1:$AZ$415,$D23,MATCH(AP$5,MTInputs!$J$5:$AZ$5,0)) -> TRUE
A24: ctcov | B24: die | C24: all | D24: 26 | H24: =INDEX(Variables!$B$5:$B$65,MATCH($A24,Variables!$A$5:$A$65,0))&IF($C24="",""," | "&INDEX(Mapping!$B$5:$B$26,MATCH($C24,Mapping!$A$5:$A$26,0))&" | "&INDEX(Mapping!$B$30:$B$41,MATCH($B24,Mapping!$A$30:$A$41,0))) -> Carbon tax coverage (Apply tax?) | All subsectors | Diesel | I24: =INDEX(Variables!$C$5:$C$65,MATCH($A24,Variables!$A$5:$A$65,0)) -> switch | J24: =INDEX(Variables!$E$5:$E$65,MATCH($A24,Variables!$A$5:$A$65,0)) -> MTInputs (scenario column) | L24: =LOWER(Settings!$C$4)&".mit."&$A24&IF($C24="","","."&$C24&"."&$B24)&IF(INDEX(Variables!$D$5:$D$65,MATCH($A24,Variables!$A$5:$A$65,0))="","","."&INDEX(Variables!$D$5:$D$65,MATCH($A24,Variables!$A$5:$A$65,0)))&"."&L$5 -> egy.mit.ctcov.all.die.1 | M24: =INDEX(MTInputs!$J$1:$AZ$415,$D24,MATCH(M$5,MTInputs!$J$5:$AZ$5,0)) -> TRUE | N24: =INDEX(MTInputs!$J$1:$AZ$415,$D24,MATCH(N$5,MTInputs!$J$5:$AZ$5,0)) -> TRUE | O24: =INDEX(MTInputs!$J$1:$AZ$415,$D24,MATCH(O$5,MTInputs!$J$5:$AZ$5,0)) -> TRUE | P24: =INDEX(MTInputs!$J$1:$AZ$415,$D24,MATCH(P$5,MTInputs!$J$5:$AZ$5,0)) -> TRUE | Q24: =INDEX(MTInputs!$J$1:$AZ$415,$D24,MATCH(Q$5,MTInputs!$J$5:$AZ$5,0)) -> TRUE | R24: =INDEX(MTInputs!$J$1:$AZ$415,$D24,MATCH(R$5,MTInputs!$J$5:$AZ$5,0)) -> TRUE | S24: =INDEX(MTInputs!$J$1:$AZ$415,$D24,MATCH(S$5,MTInputs!$J$5:$AZ$5,0)) -> TRUE | T24: =INDEX(MTInputs!$J$1:$AZ$415,$D24,MATCH(T$5,MTInputs!$J$5:$AZ$5,0)) -> TRUE | ... Z24: =INDEX(MTInputs!$J$1:$AZ$415,$D24,MATCH(Z$5,MTInputs!$J$5:$AZ$5,0)) -> TRUE | AB24: =LOWER(Settings!$C$4)&".mit."&$A24&IF($C24="","","."&$C24&"."&$B24)&IF(INDEX(Variables!$D$5:$D$65,MATCH($A24,Variables!$A$5:$A$65,0))="","","."&INDEX(Variables!$D$5:$D$65,MATCH($A24,Variables!$A$5:$A$65,0)))&"."&AB$5 -> egy.mit.ctcov.all.die.2 | AC24: =INDEX(MTInputs!$J$1:$AZ$415,$D24,MATCH(AC$5,MTInputs!$J$5:$AZ$5,0)) -> TRUE | AD24: =INDEX(MTInputs!$J$1:$AZ$415,$D24,MATCH(AD$5,MTInputs!$J$5:$AZ$5,0)) -> TRUE | AE24: =INDEX(MTInputs!$J$1:$AZ$415,$D24,MATCH(AE$5,MTInputs!$J$5:$AZ$5,0)) -> TRUE | AF24: =INDEX(MTInputs!$J$1:$AZ$415,$D24,MATCH(AF$5,MTInputs!$J$5:$AZ$5,0)) -> TRUE | AG24: =INDEX(MTInputs!$J$1:$AZ$415,$D24,MATCH(AG$5,MTInputs!$J$5:$AZ$5,0)) -> TRUE | AH24: =INDEX(MTInputs!$J$1:$AZ$415,$D24,MATCH(AH$5,MTInputs!$J$5:$AZ$5,0)) -> TRUE | AI24: =INDEX(MTInputs!$J$1:$AZ$415,$D24,MATCH(AI$5,MTInputs!$J$5:$AZ$5,0)) -> TRUE | AJ24: =INDEX(MTInputs!$J$1:$AZ$415,$D24,MATCH(AJ$5,MTInputs!$J$5:$AZ$5,0)) -> TRUE | ... AP24: =INDEX(MTInputs!$J$1:$AZ$415,$D24,MATCH(AP$5,MTInputs!$J$5:$AZ$5,0)) -> TRUE
A25: ctcov | B25: lpg | C25: all | D25: 27 | H25: =INDEX(Variables!$B$5:$B$65,MATCH($A25,Variables!$A$5:$A$65,0))&IF($C25="",""," | "&INDEX(Mapping!$B$5:$B$26,MATCH($C25,Mapping!$A$5:$A$26,0))&" | "&INDEX(Mapping!$B$30:$B$41,MATCH($B25,Mapping!$A$30:$A$41,0))) -> Carbon tax coverage (Apply tax?) | All subsectors | LPG | I25: =INDEX(Variables!$C$5:$C$65,MATCH($A25,Variables!$A$5:$A$65,0)) -> switch | J25: =INDEX(Variables!$E$5:$E$65,MATCH($A25,Variables!$A$5:$A$65,0)) -> MTInputs (scenario column) | L25: =LOWER(Settings!$C$4)&".mit."&$A25&IF($C25="","","."&$C25&"."&$B25)&IF(INDEX(Variables!$D$5:$D$65,MATCH($A25,Variables!$A$5:$A$65,0))="","","."&INDEX(Variables!$D$5:$D$65,MATCH($A25,Variables!$A$5:$A$65,0)))&"."&L$5 -> egy.mit.ctcov.all.lpg.1 | M25: =INDEX(MTInputs!$J$1:$AZ$415,$D25,MATCH(M$5,MTInputs!$J$5:$AZ$5,0)) -> TRUE | N25: =INDEX(MTInputs!$J$1:$AZ$415,$D25,MATCH(N$5,MTInputs!$J$5:$AZ$5,0)) -> TRUE | O25: =INDEX(MTInputs!$J$1:$AZ$415,$D25,MATCH(O$5,MTInputs!$J$5:$AZ$5,0)) -> TRUE | P25: =INDEX(MTInputs!$J$1:$AZ$415,$D25,MATCH(P$5,MTInputs!$J$5:$AZ$5,0)) -> TRUE | Q25: =INDEX(MTInputs!$J$1:$AZ$415,$D25,MATCH(Q$5,MTInputs!$J$5:$AZ$5,0)) -> TRUE | R25: =INDEX(MTInputs!$J$1:$AZ$415,$D25,MATCH(R$5,MTInputs!$J$5:$AZ$5,0)) -> TRUE | S25: =INDEX(MTInputs!$J$1:$AZ$415,$D25,MATCH(S$5,MTInputs!$J$5:$AZ$5,0)) -> TRUE | T25: =INDEX(MTInputs!$J$1:$AZ$415,$D25,MATCH(T$5,MTInputs!$J$5:$AZ$5,0)) -> TRUE | ... Z25: =INDEX(MTInputs!$J$1:$AZ$415,$D25,MATCH(Z$5,MTInputs!$J$5:$AZ$5,0)) -> TRUE | AB25: =LOWER(Settings!$C$4)&".mit."&$A25&IF($C25="","","."&$C25&"."&$B25)&IF(INDEX(Variables!$D$5:$D$65,MATCH($A25,Variables!$A$5:$A$65,0))="","","."&INDEX(Variables!$D$5:$D$65,MATCH($A25,Variables!$A$5:$A$65,0)))&"."&AB$5 -> egy.mit.ctcov.all.lpg.2 | AC25: =INDEX(MTInputs!$J$1:$AZ$415,$D25,MATCH(AC$5,MTInputs!$J$5:$AZ$5,0)) -> TRUE | AD25: =INDEX(MTInputs!$J$1:$AZ$415,$D25,MATCH(AD$5,MTInputs!$J$5:$AZ$5,0)) -> TRUE | AE25: =INDEX(MTInputs!$J$1:$AZ$415,$D25,MATCH(AE$5,MTInputs!$J$5:$AZ$5,0)) -> TRUE | AF25: =INDEX(MTInputs!$J$1:$AZ$415,$D25,MATCH(AF$5,MTInputs!$J$5:$AZ$5,0)) -> TRUE | AG25: =INDEX(MTInputs!$J$1:$AZ$415,$D25,MATCH(AG$5,MTInputs!$J$5:$AZ$5,0)) -> TRUE | AH25: =INDEX(MTInputs!$J$1:$AZ$415,$D25,MATCH(AH$5,MTInputs!$J$5:$AZ$5,0)) -> TRUE | AI25: =INDEX(MTInputs!$J$1:$AZ$415,$D25,MATCH(AI$5,MTInputs!$J$5:$AZ$5,0)) -> TRUE | AJ25: =INDEX(MTInputs!$J$1:$AZ$415,$D25,MATCH(AJ$5,MTInputs!$J$5:$AZ$5,0)) -> TRUE | ... AP25: =INDEX(MTInputs!$J$1:$AZ$415,$D25,MATCH(AP$5,MTInputs!$J$5:$AZ$5,0)) -> TRUE
A26: ctcov | B26: ker | C26: all | D26: 28 | H26: =INDEX(Variables!$B$5:$B$65,MATCH($A26,Variables!$A$5:$A$65,0))&IF($C26="",""," | "&INDEX(Mapping!$B$5:$B$26,MATCH($C26,Mapping!$A$5:$A$26,0))&" | "&INDEX(Mapping!$B$30:$B$41,MATCH($B26,Mapping!$A$30:$A$41,0))) -> Carbon tax coverage (Apply tax?) | All subsectors | Kerosene | I26: =INDEX(Variables!$C$5:$C$65,MATCH($A26,Variables!$A$5:$A$65,0)) -> switch | J26: =INDEX(Variables!$E$5:$E$65,MATCH($A26,Variables!$A$5:$A$65,0)) -> MTInputs (scenario column) | L26: =LOWER(Settings!$C$4)&".mit."&$A26&IF($C26="","","."&$C26&"."&$B26)&IF(INDEX(Variables!$D$5:$D$65,MATCH($A26,Variables!$A$5:$A$65,0))="","","."&INDEX(Variables!$D$5:$D$65,MATCH($A26,Variables!$A$5:$A$65,0)))&"."&L$5 -> egy.mit.ctcov.all.ker.1 | M26: =INDEX(MTInputs!$J$1:$AZ$415,$D26,MATCH(M$5,MTInputs!$J$5:$AZ$5,0)) -> TRUE | N26: =INDEX(MTInputs!$J$1:$AZ$415,$D26,MATCH(N$5,MTInputs!$J$5:$AZ$5,0)) -> TRUE | O26: =INDEX(MTInputs!$J$1:$AZ$415,$D26,MATCH(O$5,MTInputs!$J$5:$AZ$5,0)) -> TRUE | P26: =INDEX(MTInputs!$J$1:$AZ$415,$D26,MATCH(P$5,MTInputs!$J$5:$AZ$5,0)) -> TRUE | Q26: =INDEX(MTInputs!$J$1:$AZ$415,$D26,MATCH(Q$5,MTInputs!$J$5:$AZ$5,0)) -> TRUE | R26: =INDEX(MTInputs!$J$1:$AZ$415,$D26,MATCH(R$5,MTInputs!$J$5:$AZ$5,0)) -> TRUE | S26: =INDEX(MTInputs!$J$1:$AZ$415,$D26,MATCH(S$5,MTInputs!$J$5:$AZ$5,0)) -> TRUE | T26: =INDEX(MTInputs!$J$1:$AZ$415,$D26,MATCH(T$5,MTInputs!$J$5:$AZ$5,0)) -> TRUE | ... Z26: =INDEX(MTInputs!$J$1:$AZ$415,$D26,MATCH(Z$5,MTInputs!$J$5:$AZ$5,0)) -> TRUE | AB26: =LOWER(Settings!$C$4)&".mit."&$A26&IF($C26="","","."&$C26&"."&$B26)&IF(INDEX(Variables!$D$5:$D$65,MATCH($A26,Variables!$A$5:$A$65,0))="","","."&INDEX(Variables!$D$5:$D$65,MATCH($A26,Variables!$A$5:$A$65,0)))&"."&AB$5 -> egy.mit.ctcov.all.ker.2 | AC26: =INDEX(MTInputs!$J$1:$AZ$415,$D26,MATCH(AC$5,MTInputs!$J$5:$AZ$5,0)) -> TRUE | AD26: =INDEX(MTInputs!$J$1:$AZ$415,$D26,MATCH(AD$5,MTInputs!$J$5:$AZ$5,0)) -> TRUE | AE26: =INDEX(MTInputs!$J$1:$AZ$415,$D26,MATCH(AE$5,MTInputs!$J$5:$AZ$5,0)) -> TRUE | AF26: =INDEX(MTInputs!$J$1:$AZ$415,$D26,MATCH(AF$5,MTInputs!$J$5:$AZ$5,0)) -> TRUE | AG26: =INDEX(MTInputs!$J$1:$AZ$415,$D26,MATCH(AG$5,MTInputs!$J$5:$AZ$5,0)) -> TRUE | AH26: =INDEX(MTInputs!$J$1:$AZ$415,$D26,MATCH(AH$5,MTInputs!$J$5:$AZ$5,0)) -> TRUE | AI26: =INDEX(MTInputs!$J$1:$AZ$415,$D26,MATCH(AI$5,MTInputs!$J$5:$AZ$5,0)) -> TRUE | AJ26: =INDEX(MTInputs!$J$1:$AZ$415,$D26,MATCH(AJ$5,MTInputs!$J$5:$AZ$5,0)) -> TRUE | ... AP26: =INDEX(MTInputs!$J$1:$AZ$415,$D26,MATCH(AP$5,MTInputs!$J$5:$AZ$5,0)) -> TRUE
A27: ctcov | B27: oop | C27: all | D27: 29 | H27: =INDEX(Variables!$B$5:$B$65,MATCH($A27,Variables!$A$5:$A$65,0))&IF($C27="",""," | "&INDEX(Mapping!$B$5:$B$26,MATCH($C27,Mapping!$A$5:$A$26,0))&" | "&INDEX(Mapping!$B$30:$B$41,MATCH($B27,Mapping!$A$30:$A$41,0))) -> Carbon tax coverage (Apply tax?) | All subsectors | Other oil products | I27: =INDEX(Variables!$C$5:$C$65,MATCH($A27,Variables!$A$5:$A$65,0)) -> switch | J27: =INDEX(Variables!$E$5:$E$65,MATCH($A27,Variables!$A$5:$A$65,0)) -> MTInputs (scenario column) | L27: =LOWER(Settings!$C$4)&".mit."&$A27&IF($C27="","","."&$C27&"."&$B27)&IF(INDEX(Variables!$D$5:$D$65,MATCH($A27,Variables!$A$5:$A$65,0))="","","."&INDEX(Variables!$D$5:$D$65,MATCH($A27,Variables!$A$5:$A$65,0)))&"."&L$5 -> egy.mit.ctcov.all.oop.1 | M27: =INDEX(MTInputs!$J$1:$AZ$415,$D27,MATCH(M$5,MTInputs!$J$5:$AZ$5,0)) -> TRUE | N27: =INDEX(MTInputs!$J$1:$AZ$415,$D27,MATCH(N$5,MTInputs!$J$5:$AZ$5,0)) -> TRUE | O27: =INDEX(MTInputs!$J$1:$AZ$415,$D27,MATCH(O$5,MTInputs!$J$5:$AZ$5,0)) -> TRUE | P27: =INDEX(MTInputs!$J$1:$AZ$415,$D27,MATCH(P$5,MTInputs!$J$5:$AZ$5,0)) -> TRUE | Q27: =INDEX(MTInputs!$J$1:$AZ$415,$D27,MATCH(Q$5,MTInputs!$J$5:$AZ$5,0)) -> TRUE | R27: =INDEX(MTInputs!$J$1:$AZ$415,$D27,MATCH(R$5,MTInputs!$J$5:$AZ$5,0)) -> TRUE | S27: =INDEX(MTInputs!$J$1:$AZ$415,$D27,MATCH(S$5,MTInputs!$J$5:$AZ$5,0)) -> TRUE | T27: =INDEX(MTInputs!$J$1:$AZ$415,$D27,MATCH(T$5,MTInputs!$J$5:$AZ$5,0)) -> TRUE | ... Z27: =INDEX(MTInputs!$J$1:$AZ$415,$D27,MATCH(Z$5,MTInputs!$J$5:$AZ$5,0)) -> TRUE | AB27: =LOWER(Settings!$C$4)&".mit."&$A27&IF($C27="","","."&$C27&"."&$B27)&IF(INDEX(Variables!$D$5:$D$65,MATCH($A27,Variables!$A$5:$A$65,0))="","","."&INDEX(Variables!$D$5:$D$65,MATCH($A27,Variables!$A$5:$A$65,0)))&"."&AB$5 -> egy.mit.ctcov.all.oop.2 | AC27: =INDEX(MTInputs!$J$1:$AZ$415,$D27,MATCH(AC$5,MTInputs!$J$5:$AZ$5,0)) -> TRUE | AD27: =INDEX(MTInputs!$J$1:$AZ$415,$D27,MATCH(AD$5,MTInputs!$J$5:$AZ$5,0)) -> TRUE | AE27: =INDEX(MTInputs!$J$1:$AZ$415,$D27,MATCH(AE$5,MTInputs!$J$5:$AZ$5,0)) -> TRUE | AF27: =INDEX(MTInputs!$J$1:$AZ$415,$D27,MATCH(AF$5,MTInputs!$J$5:$AZ$5,0)) -> TRUE | AG27: =INDEX(MTInputs!$J$1:$AZ$415,$D27,MATCH(AG$5,MTInputs!$J$5:$AZ$5,0)) -> TRUE | AH27: =INDEX(MTInputs!$J$1:$AZ$415,$D27,MATCH(AH$5,MTInputs!$J$5:$AZ$5,0)) -> TRUE | AI27: =INDEX(MTInputs!$J$1:$AZ$415,$D27,MATCH(AI$5,MTInputs!$J$5:$AZ$5,0)) -> TRUE | AJ27: =INDEX(MTInputs!$J$1:$AZ$415,$D27,MATCH(AJ$5,MTInputs!$J$5:$AZ$5,0)) -> TRUE | ... AP27: =INDEX(MTInputs!$J$1:$AZ$415,$D27,MATCH(AP$5,MTInputs!$J$5:$AZ$5,0)) -> TRUE
A28: ctcov | B28: bio | C28: all | H28: =INDEX(Variables!$B$5:$B$65,MATCH($A28,Variables!$A$5:$A$65,0))&IF($C28="",""," | "&INDEX(Mapping!$B$5:$B$26,MATCH($C28,Mapping!$A$5:$A$26,0))&" | "&INDEX(Mapping!$B$30:$B$41,MATCH($B28,Mapping!$A$30:$A$41,0))) -> Carbon tax coverage (Apply tax?) | All subsectors | Biomass | I28: =INDEX(Variables!$C$5:$C$65,MATCH($A28,Variables!$A$5:$A$65,0)) -> switch | J28: =INDEX(Variables!$E$5:$E$65,MATCH($A28,Variables!$A$5:$A$65,0)) -> MTInputs (scenario column) | L28: =LOWER(Settings!$C$4)&".mit."&$A28&IF($C28="","","."&$C28&"."&$B28)&IF(INDEX(Variables!$D$5:$D$65,MATCH($A28,Variables!$A$5:$A$65,0))="","","."&INDEX(Variables!$D$5:$D$65,MATCH($A28,Variables!$A$5:$A$65,0)))&"."&L$5 -> egy.mit.ctcov.all.bio.1 | M28: TRUE | N28: TRUE | O28: TRUE | P28: TRUE | Q28: TRUE | R28: TRUE | S28: TRUE | T28: TRUE | U28: TRUE | V28: TRUE | W28: TRUE | X28: TRUE | Y28: TRUE | Z28: TRUE | AB28: =LOWER(Settings!$C$4)&".mit."&$A28&IF($C28="","","."&$C28&"."&$B28)&IF(INDEX(Variables!$D$5:$D$65,MATCH($A28,Variables!$A$5:$A$65,0))="","","."&INDEX(Variables!$D$5:$D$65,MATCH($A28,Variables!$A$5:$A$65,0)))&"."&AB$5 -> egy.mit.ctcov.all.bio.2 | AC28: TRUE | AD28: TRUE | AE28: TRUE | AF28: TRUE | AG28: TRUE | AH28: TRUE | AI28: TRUE | AJ28: TRUE | AK28: TRUE | AL28: TRUE | AM28: TRUE | AN28: TRUE | AO28: TRUE | AP28: TRUE
H29: Carbon tax coverage: sectors (MTInputs rows 31-47)
A30: ctcov | B30: all | C30: pow | D30: 31 | H30: =INDEX(Variables!$B$5:$B$65,MATCH($A30,Variables!$A$5:$A$65,0))&IF($C30="",""," | "&INDEX(Mapping!$B$5:$B$26,MATCH($C30,Mapping!$A$5:$A$26,0))&" | "&INDEX(Mapping!$B$30:$B$41,MATCH($B30,Mapping!$A$30:$A$41,0))) -> Carbon tax coverage (Apply tax?) | Power | All fuels | I30: =INDEX(Variables!$C$5:$C$65,MATCH($A30,Variables!$A$5:$A$65,0)) -> switch | J30: =INDEX(Variables!$E$5:$E$65,MATCH($A30,Variables!$A$5:$A$65,0)) -> MTInputs (scenario column) | L30: =LOWER(Settings!$C$4)&".mit."&$A30&IF($C30="","","."&$C30&"."&$B30)&IF(INDEX(Variables!$D$5:$D$65,MATCH($A30,Variables!$A$5:$A$65,0))="","","."&INDEX(Variables!$D$5:$D$65,MATCH($A30,Variables!$A$5:$A$65,0)))&"."&L$5 -> egy.mit.ctcov.pow.all.1 | M30: =INDEX(MTInputs!$J$1:$AZ$415,$D30,MATCH(M$5,MTInputs!$J$5:$AZ$5,0)) -> TRUE | N30: =INDEX(MTInputs!$J$1:$AZ$415,$D30,MATCH(N$5,MTInputs!$J$5:$AZ$5,0)) -> TRUE | O30: =INDEX(MTInputs!$J$1:$AZ$415,$D30,MATCH(O$5,MTInputs!$J$5:$AZ$5,0)) -> TRUE | P30: =INDEX(MTInputs!$J$1:$AZ$415,$D30,MATCH(P$5,MTInputs!$J$5:$AZ$5,0)) -> TRUE | Q30: =INDEX(MTInputs!$J$1:$AZ$415,$D30,MATCH(Q$5,MTInputs!$J$5:$AZ$5,0)) -> TRUE | R30: =INDEX(MTInputs!$J$1:$AZ$415,$D30,MATCH(R$5,MTInputs!$J$5:$AZ$5,0)) -> TRUE | S30: =INDEX(MTInputs!$J$1:$AZ$415,$D30,MATCH(S$5,MTInputs!$J$5:$AZ$5,0)) -> TRUE | T30: =INDEX(MTInputs!$J$1:$AZ$415,$D30,MATCH(T$5,MTInputs!$J$5:$AZ$5,0)) -> TRUE | ... Z30: =INDEX(MTInputs!$J$1:$AZ$415,$D30,MATCH(Z$5,MTInputs!$J$5:$AZ$5,0)) -> TRUE | AB30: =LOWER(Settings!$C$4)&".mit."&$A30&IF($C30="","","."&$C30&"."&$B30)&IF(INDEX(Variables!$D$5:$D$65,MATCH($A30,Variables!$A$5:$A$65,0))="","","."&INDEX(Variables!$D$5:$D$65,MATCH($A30,Variables!$A$5:$A$65,0)))&"."&AB$5 -> egy.mit.ctcov.pow.all.2 | AC30: =INDEX(MTInputs!$J$1:$AZ$415,$D30,MATCH(AC$5,MTInputs!$J$5:$AZ$5,0)) -> TRUE | AD30: =INDEX(MTInputs!$J$1:$AZ$415,$D30,MATCH(AD$5,MTInputs!$J$5:$AZ$5,0)) -> TRUE | AE30: =INDEX(MTInputs!$J$1:$AZ$415,$D30,MATCH(AE$5,MTInputs!$J$5:$AZ$5,0)) -> TRUE | AF30: =INDEX(MTInputs!$J$1:$AZ$415,$D30,MATCH(AF$5,MTInputs!$J$5:$AZ$5,0)) -> TRUE | AG30: =INDEX(MTInputs!$J$1:$AZ$415,$D30,MATCH(AG$5,MTInputs!$J$5:$AZ$5,0)) -> TRUE | AH30: =INDEX(MTInputs!$J$1:$AZ$415,$D30,MATCH(AH$5,MTInputs!$J$5:$AZ$5,0)) -> TRUE | AI30: =INDEX(MTInputs!$J$1:$AZ$415,$D30,MATCH(AI$5,MTInputs!$J$5:$AZ$5,0)) -> TRUE | AJ30: =INDEX(MTInputs!$J$1:$AZ$415,$D30,MATCH(AJ$5,MTInputs!$J$5:$AZ$5,0)) -> TRUE | ... AP30: =INDEX(MTInputs!$J$1:$AZ$415,$D30,MATCH(AP$5,MTInputs!$J$5:$AZ$5,0)) -> TRUE
A31: ctcov | B31: all | C31: rod | D31: 32 | H31: =INDEX(Variables!$B$5:$B$65,MATCH($A31,Variables!$A$5:$A$65,0))&IF($C31="",""," | "&INDEX(Mapping!$B$5:$B$26,MATCH($C31,Mapping!$A$5:$A$26,0))&" | "&INDEX(Mapping!$B$30:$B$41,MATCH($B31,Mapping!$A$30:$A$41,0))) -> Carbon tax coverage (Apply tax?) | Road | All fuels | I31: =INDEX(Variables!$C$5:$C$65,MATCH($A31,Variables!$A$5:$A$65,0)) -> switch | J31: =INDEX(Variables!$E$5:$E$65,MATCH($A31,Variables!$A$5:$A$65,0)) -> MTInputs (scenario column) | L31: =LOWER(Settings!$C$4)&".mit."&$A31&IF($C31="","","."&$C31&"."&$B31)&IF(INDEX(Variables!$D$5:$D$65,MATCH($A31,Variables!$A$5:$A$65,0))="","","."&INDEX(Variables!$D$5:$D$65,MATCH($A31,Variables!$A$5:$A$65,0)))&"."&L$5 -> egy.mit.ctcov.rod.all.1 | M31: =INDEX(MTInputs!$J$1:$AZ$415,$D31,MATCH(M$5,MTInputs!$J$5:$AZ$5,0)) -> TRUE | N31: =INDEX(MTInputs!$J$1:$AZ$415,$D31,MATCH(N$5,MTInputs!$J$5:$AZ$5,0)) -> TRUE | O31: =INDEX(MTInputs!$J$1:$AZ$415,$D31,MATCH(O$5,MTInputs!$J$5:$AZ$5,0)) -> TRUE | P31: =INDEX(MTInputs!$J$1:$AZ$415,$D31,MATCH(P$5,MTInputs!$J$5:$AZ$5,0)) -> TRUE | Q31: =INDEX(MTInputs!$J$1:$AZ$415,$D31,MATCH(Q$5,MTInputs!$J$5:$AZ$5,0)) -> TRUE | R31: =INDEX(MTInputs!$J$1:$AZ$415,$D31,MATCH(R$5,MTInputs!$J$5:$AZ$5,0)) -> TRUE | S31: =INDEX(MTInputs!$J$1:$AZ$415,$D31,MATCH(S$5,MTInputs!$J$5:$AZ$5,0)) -> TRUE | T31: =INDEX(MTInputs!$J$1:$AZ$415,$D31,MATCH(T$5,MTInputs!$J$5:$AZ$5,0)) -> TRUE | ... Z31: =INDEX(MTInputs!$J$1:$AZ$415,$D31,MATCH(Z$5,MTInputs!$J$5:$AZ$5,0)) -> TRUE | AB31: =LOWER(Settings!$C$4)&".mit."&$A31&IF($C31="","","."&$C31&"."&$B31)&IF(INDEX(Variables!$D$5:$D$65,MATCH($A31,Variables!$A$5:$A$65,0))="","","."&INDEX(Variables!$D$5:$D$65,MATCH($A31,Variables!$A$5:$A$65,0)))&"."&AB$5 -> egy.mit.ctcov.rod.all.2 | AC31: =INDEX(MTInputs!$J$1:$AZ$415,$D31,MATCH(AC$5,MTInputs!$J$5:$AZ$5,0)) -> TRUE | AD31: =INDEX(MTInputs!$J$1:$AZ$415,$D31,MATCH(AD$5,MTInputs!$J$5:$AZ$5,0)) -> TRUE | AE31: =INDEX(MTInputs!$J$1:$AZ$415,$D31,MATCH(AE$5,MTInputs!$J$5:$AZ$5,0)) -> TRUE | AF31: =INDEX(MTInputs!$J$1:$AZ$415,$D31,MATCH(AF$5,MTInputs!$J$5:$AZ$5,0)) -> TRUE | AG31: =INDEX(MTInputs!$J$1:$AZ$415,$D31,MATCH(AG$5,MTInputs!$J$5:$AZ$5,0)) -> TRUE | AH31: =INDEX(MTInputs!$J$1:$AZ$415,$D31,MATCH(AH$5,MTInputs!$J$5:$AZ$5,0)) -> TRUE | AI31: =INDEX(MTInputs!$J$1:$AZ$415,$D31,MATCH(AI$5,MTInputs!$J$5:$AZ$5,0)) -> TRUE | AJ31: =INDEX(MTInputs!$J$1:$AZ$415,$D31,MATCH(AJ$5,MTInputs!$J$5:$AZ$5,0)) -> TRUE | ... AP31: =INDEX(MTInputs!$J$1:$AZ$415,$D31,MATCH(AP$5,MTInputs!$J$5:$AZ$5,0)) -> TRUE
A32: ctcov | B32: all | C32: ral | D32: 33 | H32: =INDEX(Variables!$B$5:$B$65,MATCH($A32,Variables!$A$5:$A$65,0))&IF($C32="",""," | "&INDEX(Mapping!$B$5:$B$26,MATCH($C32,Mapping!$A$5:$A$26,0))&" | "&INDEX(Mapping!$B$30:$B$41,MATCH($B32,Mapping!$A$30:$A$41,0))) -> Carbon tax coverage (Apply tax?) | Rail | All fuels | I32: =INDEX(Variables!$C$5:$C$65,MATCH($A32,Variables!$A$5:$A$65,0)) -> switch | J32: =INDEX(Variables!$E$5:$E$65,MATCH($A32,Variables!$A$5:$A$65,0)) -> MTInputs (scenario column) | L32: =LOWER(Settings!$C$4)&".mit."&$A32&IF($C32="","","."&$C32&"."&$B32)&IF(INDEX(Variables!$D$5:$D$65,MATCH($A32,Variables!$A$5:$A$65,0))="","","."&INDEX(Variables!$D$5:$D$65,MATCH($A32,Variables!$A$5:$A$65,0)))&"."&L$5 -> egy.mit.ctcov.ral.all.1 | M32: =INDEX(MTInputs!$J$1:$AZ$415,$D32,MATCH(M$5,MTInputs!$J$5:$AZ$5,0)) -> TRUE | N32: =INDEX(MTInputs!$J$1:$AZ$415,$D32,MATCH(N$5,MTInputs!$J$5:$AZ$5,0)) -> TRUE | O32: =INDEX(MTInputs!$J$1:$AZ$415,$D32,MATCH(O$5,MTInputs!$J$5:$AZ$5,0)) -> TRUE | P32: =INDEX(MTInputs!$J$1:$AZ$415,$D32,MATCH(P$5,MTInputs!$J$5:$AZ$5,0)) -> TRUE | Q32: =INDEX(MTInputs!$J$1:$AZ$415,$D32,MATCH(Q$5,MTInputs!$J$5:$AZ$5,0)) -> TRUE | R32: =INDEX(MTInputs!$J$1:$AZ$415,$D32,MATCH(R$5,MTInputs!$J$5:$AZ$5,0)) -> TRUE | S32: =INDEX(MTInputs!$J$1:$AZ$415,$D32,MATCH(S$5,MTInputs!$J$5:$AZ$5,0)) -> TRUE | T32: =INDEX(MTInputs!$J$1:$AZ$415,$D32,MATCH(T$5,MTInputs!$J$5:$AZ$5,0)) -> TRUE | ... Z32: =INDEX(MTInputs!$J$1:$AZ$415,$D32,MATCH(Z$5,MTInputs!$J$5:$AZ$5,0)) -> TRUE | AB32: =LOWER(Settings!$C$4)&".mit."&$A32&IF($C32="","","."&$C32&"."&$B32)&IF(INDEX(Variables!$D$5:$D$65,MATCH($A32,Variables!$A$5:$A$65,0))="","","."&INDEX(Variables!$D$5:$D$65,MATCH($A32,Variables!$A$5:$A$65,0)))&"."&AB$5 -> egy.mit.ctcov.ral.all.2 | AC32: =INDEX(MTInputs!$J$1:$AZ$415,$D32,MATCH(AC$5,MTInputs!$J$5:$AZ$5,0)) -> TRUE | AD32: =INDEX(MTInputs!$J$1:$AZ$415,$D32,MATCH(AD$5,MTInputs!$J$5:$AZ$5,0)) -> TRUE | AE32: =INDEX(MTInputs!$J$1:$AZ$415,$D32,MATCH(AE$5,MTInputs!$J$5:$AZ$5,0)) -> TRUE | AF32: =INDEX(MTInputs!$J$1:$AZ$415,$D32,MATCH(AF$5,MTInputs!$J$5:$AZ$5,0)) -> TRUE | AG32: =INDEX(MTInputs!$J$1:$AZ$415,$D32,MATCH(AG$5,MTInputs!$J$5:$AZ$5,0)) -> TRUE | AH32: =INDEX(MTInputs!$J$1:$AZ$415,$D32,MATCH(AH$5,MTInputs!$J$5:$AZ$5,0)) -> TRUE | AI32: =INDEX(MTInputs!$J$1:$AZ$415,$D32,MATCH(AI$5,MTInputs!$J$5:$AZ$5,0)) -> TRUE | AJ32: =INDEX(MTInputs!$J$1:$AZ$415,$D32,MATCH(AJ$5,MTInputs!$J$5:$AZ$5,0)) -> TRUE | ... AP32: =INDEX(MTInputs!$J$1:$AZ$415,$D32,MATCH(AP$5,MTInputs!$J$5:$AZ$5,0)) -> TRUE
A33: ctcov | B33: all | C33: avi | D33: 34 | H33: =INDEX(Variables!$B$5:$B$65,MATCH($A33,Variables!$A$5:$A$65,0))&IF($C33="",""," | "&INDEX(Mapping!$B$5:$B$26,MATCH($C33,Mapping!$A$5:$A$26,0))&" | "&INDEX(Mapping!$B$30:$B$41,MATCH($B33,Mapping!$A$30:$A$41,0))) -> Carbon tax coverage (Apply tax?) | Domestic aviation | All fuels | I33: =INDEX(Variables!$C$5:$C$65,MATCH($A33,Variables!$A$5:$A$65,0)) -> switch | J33: =INDEX(Variables!$E$5:$E$65,MATCH($A33,Variables!$A$5:$A$65,0)) -> MTInputs (scenario column) | L33: =LOWER(Settings!$C$4)&".mit."&$A33&IF($C33="","","."&$C33&"."&$B33)&IF(INDEX(Variables!$D$5:$D$65,MATCH($A33,Variables!$A$5:$A$65,0))="","","."&INDEX(Variables!$D$5:$D$65,MATCH($A33,Variables!$A$5:$A$65,0)))&"."&L$5 -> egy.mit.ctcov.avi.all.1 | M33: =INDEX(MTInputs!$J$1:$AZ$415,$D33,MATCH(M$5,MTInputs!$J$5:$AZ$5,0)) -> TRUE | N33: =INDEX(MTInputs!$J$1:$AZ$415,$D33,MATCH(N$5,MTInputs!$J$5:$AZ$5,0)) -> TRUE | O33: =INDEX(MTInputs!$J$1:$AZ$415,$D33,MATCH(O$5,MTInputs!$J$5:$AZ$5,0)) -> TRUE | P33: =INDEX(MTInputs!$J$1:$AZ$415,$D33,MATCH(P$5,MTInputs!$J$5:$AZ$5,0)) -> TRUE | Q33: =INDEX(MTInputs!$J$1:$AZ$415,$D33,MATCH(Q$5,MTInputs!$J$5:$AZ$5,0)) -> TRUE | R33: =INDEX(MTInputs!$J$1:$AZ$415,$D33,MATCH(R$5,MTInputs!$J$5:$AZ$5,0)) -> TRUE | S33: =INDEX(MTInputs!$J$1:$AZ$415,$D33,MATCH(S$5,MTInputs!$J$5:$AZ$5,0)) -> TRUE | T33: =INDEX(MTInputs!$J$1:$AZ$415,$D33,MATCH(T$5,MTInputs!$J$5:$AZ$5,0)) -> TRUE | ... Z33: =INDEX(MTInputs!$J$1:$AZ$415,$D33,MATCH(Z$5,MTInputs!$J$5:$AZ$5,0)) -> TRUE | AB33: =LOWER(Settings!$C$4)&".mit."&$A33&IF($C33="","","."&$C33&"."&$B33)&IF(INDEX(Variables!$D$5:$D$65,MATCH($A33,Variables!$A$5:$A$65,0))="","","."&INDEX(Variables!$D$5:$D$65,MATCH($A33,Variables!$A$5:$A$65,0)))&"."&AB$5 -> egy.mit.ctcov.avi.all.2 | AC33: =INDEX(MTInputs!$J$1:$AZ$415,$D33,MATCH(AC$5,MTInputs!$J$5:$AZ$5,0)) -> TRUE | AD33: =INDEX(MTInputs!$J$1:$AZ$415,$D33,MATCH(AD$5,MTInputs!$J$5:$AZ$5,0)) -> TRUE | AE33: =INDEX(MTInputs!$J$1:$AZ$415,$D33,MATCH(AE$5,MTInputs!$J$5:$AZ$5,0)) -> TRUE | AF33: =INDEX(MTInputs!$J$1:$AZ$415,$D33,MATCH(AF$5,MTInputs!$J$5:$AZ$5,0)) -> TRUE | AG33: =INDEX(MTInputs!$J$1:$AZ$415,$D33,MATCH(AG$5,MTInputs!$J$5:$AZ$5,0)) -> TRUE | AH33: =INDEX(MTInputs!$J$1:$AZ$415,$D33,MATCH(AH$5,MTInputs!$J$5:$AZ$5,0)) -> TRUE | AI33: =INDEX(MTInputs!$J$1:$AZ$415,$D33,MATCH(AI$5,MTInputs!$J$5:$AZ$5,0)) -> TRUE | AJ33: =INDEX(MTInputs!$J$1:$AZ$415,$D33,MATCH(AJ$5,MTInputs!$J$5:$AZ$5,0)) -> TRUE | ... AP33: =INDEX(MTInputs!$J$1:$AZ$415,$D33,MATCH(AP$5,MTInputs!$J$5:$AZ$5,0)) -> TRUE
A34: ctcov | B34: all | C34: nav | D34: 35 | H34: =INDEX(Variables!$B$5:$B$65,MATCH($A34,Variables!$A$5:$A$65,0))&IF($C34="",""," | "&INDEX(Mapping!$B$5:$B$26,MATCH($C34,Mapping!$A$5:$A$26,0))&" | "&INDEX(Mapping!$B$30:$B$41,MATCH($B34,Mapping!$A$30:$A$41,0))) -> Carbon tax coverage (Apply tax?) | Domestic navigation | All fuels | I34: =INDEX(Variables!$C$5:$C$65,MATCH($A34,Variables!$A$5:$A$65,0)) -> switch | J34: =INDEX(Variables!$E$5:$E$65,MATCH($A34,Variables!$A$5:$A$65,0)) -> MTInputs (scenario column) | L34: =LOWER(Settings!$C$4)&".mit."&$A34&IF($C34="","","."&$C34&"."&$B34)&IF(INDEX(Variables!$D$5:$D$65,MATCH($A34,Variables!$A$5:$A$65,0))="","","."&INDEX(Variables!$D$5:$D$65,MATCH($A34,Variables!$A$5:$A$65,0)))&"."&L$5 -> egy.mit.ctcov.nav.all.1 | M34: =INDEX(MTInputs!$J$1:$AZ$415,$D34,MATCH(M$5,MTInputs!$J$5:$AZ$5,0)) -> TRUE | N34: =INDEX(MTInputs!$J$1:$AZ$415,$D34,MATCH(N$5,MTInputs!$J$5:$AZ$5,0)) -> TRUE | O34: =INDEX(MTInputs!$J$1:$AZ$415,$D34,MATCH(O$5,MTInputs!$J$5:$AZ$5,0)) -> TRUE | P34: =INDEX(MTInputs!$J$1:$AZ$415,$D34,MATCH(P$5,MTInputs!$J$5:$AZ$5,0)) -> TRUE | Q34: =INDEX(MTInputs!$J$1:$AZ$415,$D34,MATCH(Q$5,MTInputs!$J$5:$AZ$5,0)) -> TRUE | R34: =INDEX(MTInputs!$J$1:$AZ$415,$D34,MATCH(R$5,MTInputs!$J$5:$AZ$5,0)) -> TRUE | S34: =INDEX(MTInputs!$J$1:$AZ$415,$D34,MATCH(S$5,MTInputs!$J$5:$AZ$5,0)) -> TRUE | T34: =INDEX(MTInputs!$J$1:$AZ$415,$D34,MATCH(T$5,MTInputs!$J$5:$AZ$5,0)) -> TRUE | ... Z34: =INDEX(MTInputs!$J$1:$AZ$415,$D34,MATCH(Z$5,MTInputs!$J$5:$AZ$5,0)) -> TRUE | AB34: =LOWER(Settings!$C$4)&".mit."&$A34&IF($C34="","","."&$C34&"."&$B34)&IF(INDEX(Variables!$D$5:$D$65,MATCH($A34,Variables!$A$5:$A$65,0))="","","."&INDEX(Variables!$D$5:$D$65,MATCH($A34,Variables!$A$5:$A$65,0)))&"."&AB$5 -> egy.mit.ctcov.nav.all.2 | AC34: =INDEX(MTInputs!$J$1:$AZ$415,$D34,MATCH(AC$5,MTInputs!$J$5:$AZ$5,0)) -> TRUE | AD34: =INDEX(MTInputs!$J$1:$AZ$415,$D34,MATCH(AD$5,MTInputs!$J$5:$AZ$5,0)) -> TRUE | AE34: =INDEX(MTInputs!$J$1:$AZ$415,$D34,MATCH(AE$5,MTInputs!$J$5:$AZ$5,0)) -> TRUE | AF34: =INDEX(MTInputs!$J$1:$AZ$415,$D34,MATCH(AF$5,MTInputs!$J$5:$AZ$5,0)) -> TRUE | AG34: =INDEX(MTInputs!$J$1:$AZ$415,$D34,MATCH(AG$5,MTInputs!$J$5:$AZ$5,0)) -> TRUE | AH34: =INDEX(MTInputs!$J$1:$AZ$415,$D34,MATCH(AH$5,MTInputs!$J$5:$AZ$5,0)) -> TRUE | AI34: =INDEX(MTInputs!$J$1:$AZ$415,$D34,MATCH(AI$5,MTInputs!$J$5:$AZ$5,0)) -> TRUE | AJ34: =INDEX(MTInputs!$J$1:$AZ$415,$D34,MATCH(AJ$5,MTInputs!$J$5:$AZ$5,0)) -> TRUE | ... AP34: =INDEX(MTInputs!$J$1:$AZ$415,$D34,MATCH(AP$5,MTInputs!$J$5:$AZ$5,0)) -> TRUE
A35: ctcov | B35: all | C35: res | D35: 36 | H35: =INDEX(Variables!$B$5:$B$65,MATCH($A35,Variables!$A$5:$A$65,0))&IF($C35="",""," | "&INDEX(Mapping!$B$5:$B$26,MATCH($C35,Mapping!$A$5:$A$26,0))&" | "&INDEX(Mapping!$B$30:$B$41,MATCH($B35,Mapping!$A$30:$A$41,0))) -> Carbon tax coverage (Apply tax?) | Residential | All fuels | I35: =INDEX(Variables!$C$5:$C$65,MATCH($A35,Variables!$A$5:$A$65,0)) -> switch | J35: =INDEX(Variables!$E$5:$E$65,MATCH($A35,Variables!$A$5:$A$65,0)) -> MTInputs (scenario column) | L35: =LOWER(Settings!$C$4)&".mit."&$A35&IF($C35="","","."&$C35&"."&$B35)&IF(INDEX(Variables!$D$5:$D$65,MATCH($A35,Variables!$A$5:$A$65,0))="","","."&INDEX(Variables!$D$5:$D$65,MATCH($A35,Variables!$A$5:$A$65,0)))&"."&L$5 -> egy.mit.ctcov.res.all.1 | M35: =INDEX(MTInputs!$J$1:$AZ$415,$D35,MATCH(M$5,MTInputs!$J$5:$AZ$5,0)) -> TRUE | N35: =INDEX(MTInputs!$J$1:$AZ$415,$D35,MATCH(N$5,MTInputs!$J$5:$AZ$5,0)) -> TRUE | O35: =INDEX(MTInputs!$J$1:$AZ$415,$D35,MATCH(O$5,MTInputs!$J$5:$AZ$5,0)) -> TRUE | P35: =INDEX(MTInputs!$J$1:$AZ$415,$D35,MATCH(P$5,MTInputs!$J$5:$AZ$5,0)) -> TRUE | Q35: =INDEX(MTInputs!$J$1:$AZ$415,$D35,MATCH(Q$5,MTInputs!$J$5:$AZ$5,0)) -> TRUE | R35: =INDEX(MTInputs!$J$1:$AZ$415,$D35,MATCH(R$5,MTInputs!$J$5:$AZ$5,0)) -> TRUE | S35: =INDEX(MTInputs!$J$1:$AZ$415,$D35,MATCH(S$5,MTInputs!$J$5:$AZ$5,0)) -> TRUE | T35: =INDEX(MTInputs!$J$1:$AZ$415,$D35,MATCH(T$5,MTInputs!$J$5:$AZ$5,0)) -> TRUE | ... Z35: =INDEX(MTInputs!$J$1:$AZ$415,$D35,MATCH(Z$5,MTInputs!$J$5:$AZ$5,0)) -> TRUE | AB35: =LOWER(Settings!$C$4)&".mit."&$A35&IF($C35="","","."&$C35&"."&$B35)&IF(INDEX(Variables!$D$5:$D$65,MATCH($A35,Variables!$A$5:$A$65,0))="","","."&INDEX(Variables!$D$5:$D$65,MATCH($A35,Variables!$A$5:$A$65,0)))&"."&AB$5 -> egy.mit.ctcov.res.all.2 | AC35: =INDEX(MTInputs!$J$1:$AZ$415,$D35,MATCH(AC$5,MTInputs!$J$5:$AZ$5,0)) -> TRUE | AD35: =INDEX(MTInputs!$J$1:$AZ$415,$D35,MATCH(AD$5,MTInputs!$J$5:$AZ$5,0)) -> TRUE | AE35: =INDEX(MTInputs!$J$1:$AZ$415,$D35,MATCH(AE$5,MTInputs!$J$5:$AZ$5,0)) -> TRUE | AF35: =INDEX(MTInputs!$J$1:$AZ$415,$D35,MATCH(AF$5,MTInputs!$J$5:$AZ$5,0)) -> TRUE | AG35: =INDEX(MTInputs!$J$1:$AZ$415,$D35,MATCH(AG$5,MTInputs!$J$5:$AZ$5,0)) -> TRUE | AH35: =INDEX(MTInputs!$J$1:$AZ$415,$D35,MATCH(AH$5,MTInputs!$J$5:$AZ$5,0)) -> TRUE | AI35: =INDEX(MTInputs!$J$1:$AZ$415,$D35,MATCH(AI$5,MTInputs!$J$5:$AZ$5,0)) -> TRUE | AJ35: =INDEX(MTInputs!$J$1:$AZ$415,$D35,MATCH(AJ$5,MTInputs!$J$5:$AZ$5,0)) -> TRUE | ... AP35: =INDEX(MTInputs!$J$1:$AZ$415,$D35,MATCH(AP$5,MTInputs!$J$5:$AZ$5,0)) -> TRUE
A36: ctcov | B36: all | C36: foo | D36: 37 | H36: =INDEX(Variables!$B$5:$B$65,MATCH($A36,Variables!$A$5:$A$65,0))&IF($C36="",""," | "&INDEX(Mapping!$B$5:$B$26,MATCH($C36,Mapping!$A$5:$A$26,0))&" | "&INDEX(Mapping!$B$30:$B$41,MATCH($B36,Mapping!$A$30:$A$41,0))) -> Carbon tax coverage (Apply tax?) | Food & forestry | All fuels | I36: =INDEX(Variables!$C$5:$C$65,MATCH($A36,Variables!$A$5:$A$65,0)) -> switch | J36: =INDEX(Variables!$E$5:$E$65,MATCH($A36,Variables!$A$5:$A$65,0)) -> MTInputs (scenario column) | L36: =LOWER(Settings!$C$4)&".mit."&$A36&IF($C36="","","."&$C36&"."&$B36)&IF(INDEX(Variables!$D$5:$D$65,MATCH($A36,Variables!$A$5:$A$65,0))="","","."&INDEX(Variables!$D$5:$D$65,MATCH($A36,Variables!$A$5:$A$65,0)))&"."&L$5 -> egy.mit.ctcov.foo.all.1 | M36: =INDEX(MTInputs!$J$1:$AZ$415,$D36,MATCH(M$5,MTInputs!$J$5:$AZ$5,0)) -> TRUE | N36: =INDEX(MTInputs!$J$1:$AZ$415,$D36,MATCH(N$5,MTInputs!$J$5:$AZ$5,0)) -> TRUE | O36: =INDEX(MTInputs!$J$1:$AZ$415,$D36,MATCH(O$5,MTInputs!$J$5:$AZ$5,0)) -> TRUE | P36: =INDEX(MTInputs!$J$1:$AZ$415,$D36,MATCH(P$5,MTInputs!$J$5:$AZ$5,0)) -> TRUE | Q36: =INDEX(MTInputs!$J$1:$AZ$415,$D36,MATCH(Q$5,MTInputs!$J$5:$AZ$5,0)) -> TRUE | R36: =INDEX(MTInputs!$J$1:$AZ$415,$D36,MATCH(R$5,MTInputs!$J$5:$AZ$5,0)) -> TRUE | S36: =INDEX(MTInputs!$J$1:$AZ$415,$D36,MATCH(S$5,MTInputs!$J$5:$AZ$5,0)) -> TRUE | T36: =INDEX(MTInputs!$J$1:$AZ$415,$D36,MATCH(T$5,MTInputs!$J$5:$AZ$5,0)) -> TRUE | ... Z36: =INDEX(MTInputs!$J$1:$AZ$415,$D36,MATCH(Z$5,MTInputs!$J$5:$AZ$5,0)) -> TRUE | AB36: =LOWER(Settings!$C$4)&".mit."&$A36&IF($C36="","","."&$C36&"."&$B36)&IF(INDEX(Variables!$D$5:$D$65,MATCH($A36,Variables!$A$5:$A$65,0))="","","."&INDEX(Variables!$D$5:$D$65,MATCH($A36,Variables!$A$5:$A$65,0)))&"."&AB$5 -> egy.mit.ctcov.foo.all.2 | AC36: =INDEX(MTInputs!$J$1:$AZ$415,$D36,MATCH(AC$5,MTInputs!$J$5:$AZ$5,0)) -> TRUE | AD36: =INDEX(MTInputs!$J$1:$AZ$415,$D36,MATCH(AD$5,MTInputs!$J$5:$AZ$5,0)) -> TRUE | AE36: =INDEX(MTInputs!$J$1:$AZ$415,$D36,MATCH(AE$5,MTInputs!$J$5:$AZ$5,0)) -> TRUE | AF36: =INDEX(MTInputs!$J$1:$AZ$415,$D36,MATCH(AF$5,MTInputs!$J$5:$AZ$5,0)) -> TRUE | AG36: =INDEX(MTInputs!$J$1:$AZ$415,$D36,MATCH(AG$5,MTInputs!$J$5:$AZ$5,0)) -> TRUE | AH36: =INDEX(MTInputs!$J$1:$AZ$415,$D36,MATCH(AH$5,MTInputs!$J$5:$AZ$5,0)) -> TRUE | AI36: =INDEX(MTInputs!$J$1:$AZ$415,$D36,MATCH(AI$5,MTInputs!$J$5:$AZ$5,0)) -> TRUE | AJ36: =INDEX(MTInputs!$J$1:$AZ$415,$D36,MATCH(AJ$5,MTInputs!$J$5:$AZ$5,0)) -> TRUE | ... AP36: =INDEX(MTInputs!$J$1:$AZ$415,$D36,MATCH(AP$5,MTInputs!$J$5:$AZ$5,0)) -> TRUE
A37: ctcov | B37: all | C37: srv | D37: 38 | H37: =INDEX(Variables!$B$5:$B$65,MATCH($A37,Variables!$A$5:$A$65,0))&IF($C37="",""," | "&INDEX(Mapping!$B$5:$B$26,MATCH($C37,Mapping!$A$5:$A$26,0))&" | "&INDEX(Mapping!$B$30:$B$41,MATCH($B37,Mapping!$A$30:$A$41,0))) -> Carbon tax coverage (Apply tax?) | Services (public & private) | All fuels | I37: =INDEX(Variables!$C$5:$C$65,MATCH($A37,Variables!$A$5:$A$65,0)) -> switch | J37: =INDEX(Variables!$E$5:$E$65,MATCH($A37,Variables!$A$5:$A$65,0)) -> MTInputs (scenario column) | L37: =LOWER(Settings!$C$4)&".mit."&$A37&IF($C37="","","."&$C37&"."&$B37)&IF(INDEX(Variables!$D$5:$D$65,MATCH($A37,Variables!$A$5:$A$65,0))="","","."&INDEX(Variables!$D$5:$D$65,MATCH($A37,Variables!$A$5:$A$65,0)))&"."&L$5 -> egy.mit.ctcov.srv.all.1 | M37: =INDEX(MTInputs!$J$1:$AZ$415,$D37,MATCH(M$5,MTInputs!$J$5:$AZ$5,0)) -> TRUE | N37: =INDEX(MTInputs!$J$1:$AZ$415,$D37,MATCH(N$5,MTInputs!$J$5:$AZ$5,0)) -> TRUE | O37: =INDEX(MTInputs!$J$1:$AZ$415,$D37,MATCH(O$5,MTInputs!$J$5:$AZ$5,0)) -> TRUE | P37: =INDEX(MTInputs!$J$1:$AZ$415,$D37,MATCH(P$5,MTInputs!$J$5:$AZ$5,0)) -> TRUE | Q37: =INDEX(MTInputs!$J$1:$AZ$415,$D37,MATCH(Q$5,MTInputs!$J$5:$AZ$5,0)) -> TRUE | R37: =INDEX(MTInputs!$J$1:$AZ$415,$D37,MATCH(R$5,MTInputs!$J$5:$AZ$5,0)) -> TRUE | S37: =INDEX(MTInputs!$J$1:$AZ$415,$D37,MATCH(S$5,MTInputs!$J$5:$AZ$5,0)) -> TRUE | T37: =INDEX(MTInputs!$J$1:$AZ$415,$D37,MATCH(T$5,MTInputs!$J$5:$AZ$5,0)) -> TRUE | ... Z37: =INDEX(MTInputs!$J$1:$AZ$415,$D37,MATCH(Z$5,MTInputs!$J$5:$AZ$5,0)) -> TRUE | AB37: =LOWER(Settings!$C$4)&".mit."&$A37&IF($C37="","","."&$C37&"."&$B37)&IF(INDEX(Variables!$D$5:$D$65,MATCH($A37,Variables!$A$5:$A$65,0))="","","."&INDEX(Variables!$D$5:$D$65,MATCH($A37,Variables!$A$5:$A$65,0)))&"."&AB$5 -> egy.mit.ctcov.srv.all.2 | AC37: =INDEX(MTInputs!$J$1:$AZ$415,$D37,MATCH(AC$5,MTInputs!$J$5:$AZ$5,0)) -> TRUE | AD37: =INDEX(MTInputs!$J$1:$AZ$415,$D37,MATCH(AD$5,MTInputs!$J$5:$AZ$5,0)) -> TRUE | AE37: =INDEX(MTInputs!$J$1:$AZ$415,$D37,MATCH(AE$5,MTInputs!$J$5:$AZ$5,0)) -> TRUE | AF37: =INDEX(MTInputs!$J$1:$AZ$415,$D37,MATCH(AF$5,MTInputs!$J$5:$AZ$5,0)) -> TRUE | AG37: =INDEX(MTInputs!$J$1:$AZ$415,$D37,MATCH(AG$5,MTInputs!$J$5:$AZ$5,0)) -> TRUE | AH37: =INDEX(MTInputs!$J$1:$AZ$415,$D37,MATCH(AH$5,MTInputs!$J$5:$AZ$5,0)) -> TRUE | AI37: =INDEX(MTInputs!$J$1:$AZ$415,$D37,MATCH(AI$5,MTInputs!$J$5:$AZ$5,0)) -> TRUE | AJ37: =INDEX(MTInputs!$J$1:$AZ$415,$D37,MATCH(AJ$5,MTInputs!$J$5:$AZ$5,0)) -> TRUE | ... AP37: =INDEX(MTInputs!$J$1:$AZ$415,$D37,MATCH(AP$5,MTInputs!$J$5:$AZ$5,0)) -> TRUE
A38: ctcov | B38: all | C38: mch | D38: 39 | H38: =INDEX(Variables!$B$5:$B$65,MATCH($A38,Variables!$A$5:$A$65,0))&IF($C38="",""," | "&INDEX(Mapping!$B$5:$B$26,MATCH($C38,Mapping!$A$5:$A$26,0))&" | "&INDEX(Mapping!$B$30:$B$41,MATCH($B38,Mapping!$A$30:$A$41,0))) -> Carbon tax coverage (Apply tax?) | Mining & chemicals | All fuels | I38: =INDEX(Variables!$C$5:$C$65,MATCH($A38,Variables!$A$5:$A$65,0)) -> switch | J38: =INDEX(Variables!$E$5:$E$65,MATCH($A38,Variables!$A$5:$A$65,0)) -> MTInputs (scenario column) | L38: =LOWER(Settings!$C$4)&".mit."&$A38&IF($C38="","","."&$C38&"."&$B38)&IF(INDEX(Variables!$D$5:$D$65,MATCH($A38,Variables!$A$5:$A$65,0))="","","."&INDEX(Variables!$D$5:$D$65,MATCH($A38,Variables!$A$5:$A$65,0)))&"."&L$5 -> egy.mit.ctcov.mch.all.1 | M38: =INDEX(MTInputs!$J$1:$AZ$415,$D38,MATCH(M$5,MTInputs!$J$5:$AZ$5,0)) -> TRUE | N38: =INDEX(MTInputs!$J$1:$AZ$415,$D38,MATCH(N$5,MTInputs!$J$5:$AZ$5,0)) -> TRUE | O38: =INDEX(MTInputs!$J$1:$AZ$415,$D38,MATCH(O$5,MTInputs!$J$5:$AZ$5,0)) -> TRUE | P38: =INDEX(MTInputs!$J$1:$AZ$415,$D38,MATCH(P$5,MTInputs!$J$5:$AZ$5,0)) -> TRUE | Q38: =INDEX(MTInputs!$J$1:$AZ$415,$D38,MATCH(Q$5,MTInputs!$J$5:$AZ$5,0)) -> TRUE | R38: =INDEX(MTInputs!$J$1:$AZ$415,$D38,MATCH(R$5,MTInputs!$J$5:$AZ$5,0)) -> TRUE | S38: =INDEX(MTInputs!$J$1:$AZ$415,$D38,MATCH(S$5,MTInputs!$J$5:$AZ$5,0)) -> TRUE | T38: =INDEX(MTInputs!$J$1:$AZ$415,$D38,MATCH(T$5,MTInputs!$J$5:$AZ$5,0)) -> TRUE | ... Z38: =INDEX(MTInputs!$J$1:$AZ$415,$D38,MATCH(Z$5,MTInputs!$J$5:$AZ$5,0)) -> TRUE | AB38: =LOWER(Settings!$C$4)&".mit."&$A38&IF($C38="","","."&$C38&"."&$B38)&IF(INDEX(Variables!$D$5:$D$65,MATCH($A38,Variables!$A$5:$A$65,0))="","","."&INDEX(Variables!$D$5:$D$65,MATCH($A38,Variables!$A$5:$A$65,0)))&"."&AB$5 -> egy.mit.ctcov.mch.all.2 | AC38: =INDEX(MTInputs!$J$1:$AZ$415,$D38,MATCH(AC$5,MTInputs!$J$5:$AZ$5,0)) -> TRUE | AD38: =INDEX(MTInputs!$J$1:$AZ$415,$D38,MATCH(AD$5,MTInputs!$J$5:$AZ$5,0)) -> TRUE | AE38: =INDEX(MTInputs!$J$1:$AZ$415,$D38,MATCH(AE$5,MTInputs!$J$5:$AZ$5,0)) -> TRUE | AF38: =INDEX(MTInputs!$J$1:$AZ$415,$D38,MATCH(AF$5,MTInputs!$J$5:$AZ$5,0)) -> TRUE | AG38: =INDEX(MTInputs!$J$1:$AZ$415,$D38,MATCH(AG$5,MTInputs!$J$5:$AZ$5,0)) -> TRUE | AH38: =INDEX(MTInputs!$J$1:$AZ$415,$D38,MATCH(AH$5,MTInputs!$J$5:$AZ$5,0)) -> TRUE | AI38: =INDEX(MTInputs!$J$1:$AZ$415,$D38,MATCH(AI$5,MTInputs!$J$5:$AZ$5,0)) -> TRUE | AJ38: =INDEX(MTInputs!$J$1:$AZ$415,$D38,MATCH(AJ$5,MTInputs!$J$5:$AZ$5,0)) -> TRUE | ... AP38: =INDEX(MTInputs!$J$1:$AZ$415,$D38,MATCH(AP$5,MTInputs!$J$5:$AZ$5,0)) -> TRUE
A39: ctcov | B39: all | C39: irn | D39: 40 | H39: =INDEX(Variables!$B$5:$B$65,MATCH($A39,Variables!$A$5:$A$65,0))&IF($C39="",""," | "&INDEX(Mapping!$B$5:$B$26,MATCH($C39,Mapping!$A$5:$A$26,0))&" | "&INDEX(Mapping!$B$30:$B$41,MATCH($B39,Mapping!$A$30:$A$41,0))) -> Carbon tax coverage (Apply tax?) | Iron & steel | All fuels | I39: =INDEX(Variables!$C$5:$C$65,MATCH($A39,Variables!$A$5:$A$65,0)) -> switch | J39: =INDEX(Variables!$E$5:$E$65,MATCH($A39,Variables!$A$5:$A$65,0)) -> MTInputs (scenario column) | L39: =LOWER(Settings!$C$4)&".mit."&$A39&IF($C39="","","."&$C39&"."&$B39)&IF(INDEX(Variables!$D$5:$D$65,MATCH($A39,Variables!$A$5:$A$65,0))="","","."&INDEX(Variables!$D$5:$D$65,MATCH($A39,Variables!$A$5:$A$65,0)))&"."&L$5 -> egy.mit.ctcov.irn.all.1 | M39: =INDEX(MTInputs!$J$1:$AZ$415,$D39,MATCH(M$5,MTInputs!$J$5:$AZ$5,0)) -> TRUE | N39: =INDEX(MTInputs!$J$1:$AZ$415,$D39,MATCH(N$5,MTInputs!$J$5:$AZ$5,0)) -> TRUE | O39: =INDEX(MTInputs!$J$1:$AZ$415,$D39,MATCH(O$5,MTInputs!$J$5:$AZ$5,0)) -> TRUE | P39: =INDEX(MTInputs!$J$1:$AZ$415,$D39,MATCH(P$5,MTInputs!$J$5:$AZ$5,0)) -> TRUE | Q39: =INDEX(MTInputs!$J$1:$AZ$415,$D39,MATCH(Q$5,MTInputs!$J$5:$AZ$5,0)) -> TRUE | R39: =INDEX(MTInputs!$J$1:$AZ$415,$D39,MATCH(R$5,MTInputs!$J$5:$AZ$5,0)) -> TRUE | S39: =INDEX(MTInputs!$J$1:$AZ$415,$D39,MATCH(S$5,MTInputs!$J$5:$AZ$5,0)) -> TRUE | T39: =INDEX(MTInputs!$J$1:$AZ$415,$D39,MATCH(T$5,MTInputs!$J$5:$AZ$5,0)) -> TRUE | ... Z39: =INDEX(MTInputs!$J$1:$AZ$415,$D39,MATCH(Z$5,MTInputs!$J$5:$AZ$5,0)) -> TRUE | AB39: =LOWER(Settings!$C$4)&".mit."&$A39&IF($C39="","","."&$C39&"."&$B39)&IF(INDEX(Variables!$D$5:$D$65,MATCH($A39,Variables!$A$5:$A$65,0))="","","."&INDEX(Variables!$D$5:$D$65,MATCH($A39,Variables!$A$5:$A$65,0)))&"."&AB$5 -> egy.mit.ctcov.irn.all.2 | AC39: =INDEX(MTInputs!$J$1:$AZ$415,$D39,MATCH(AC$5,MTInputs!$J$5:$AZ$5,0)) -> TRUE | AD39: =INDEX(MTInputs!$J$1:$AZ$415,$D39,MATCH(AD$5,MTInputs!$J$5:$AZ$5,0)) -> TRUE | AE39: =INDEX(MTInputs!$J$1:$AZ$415,$D39,MATCH(AE$5,MTInputs!$J$5:$AZ$5,0)) -> TRUE | AF39: =INDEX(MTInputs!$J$1:$AZ$415,$D39,MATCH(AF$5,MTInputs!$J$5:$AZ$5,0)) -> TRUE | AG39: =INDEX(MTInputs!$J$1:$AZ$415,$D39,MATCH(AG$5,MTInputs!$J$5:$AZ$5,0)) -> TRUE | AH39: =INDEX(MTInputs!$J$1:$AZ$415,$D39,MATCH(AH$5,MTInputs!$J$5:$AZ$5,0)) -> TRUE | AI39: =INDEX(MTInputs!$J$1:$AZ$415,$D39,MATCH(AI$5,MTInputs!$J$5:$AZ$5,0)) -> TRUE | AJ39: =INDEX(MTInputs!$J$1:$AZ$415,$D39,MATCH(AJ$5,MTInputs!$J$5:$AZ$5,0)) -> TRUE | ... AP39: =INDEX(MTInputs!$J$1:$AZ$415,$D39,MATCH(AP$5,MTInputs!$J$5:$AZ$5,0)) -> TRUE
A40: ctcov | B40: all | C40: nfm | D40: 41 | H40: =INDEX(Variables!$B$5:$B$65,MATCH($A40,Variables!$A$5:$A$65,0))&IF($C40="",""," | "&INDEX(Mapping!$B$5:$B$26,MATCH($C40,Mapping!$A$5:$A$26,0))&" | "&INDEX(Mapping!$B$30:$B$41,MATCH($B40,Mapping!$A$30:$A$41,0))) -> Carbon tax coverage (Apply tax?) | Other metals | All fuels | I40: =INDEX(Variables!$C$5:$C$65,MATCH($A40,Variables!$A$5:$A$65,0)) -> switch | J40: =INDEX(Variables!$E$5:$E$65,MATCH($A40,Variables!$A$5:$A$65,0)) -> MTInputs (scenario column) | L40: =LOWER(Settings!$C$4)&".mit."&$A40&IF($C40="","","."&$C40&"."&$B40)&IF(INDEX(Variables!$D$5:$D$65,MATCH($A40,Variables!$A$5:$A$65,0))="","","."&INDEX(Variables!$D$5:$D$65,MATCH($A40,Variables!$A$5:$A$65,0)))&"."&L$5 -> egy.mit.ctcov.nfm.all.1 | M40: =INDEX(MTInputs!$J$1:$AZ$415,$D40,MATCH(M$5,MTInputs!$J$5:$AZ$5,0)) -> TRUE | N40: =INDEX(MTInputs!$J$1:$AZ$415,$D40,MATCH(N$5,MTInputs!$J$5:$AZ$5,0)) -> TRUE | O40: =INDEX(MTInputs!$J$1:$AZ$415,$D40,MATCH(O$5,MTInputs!$J$5:$AZ$5,0)) -> TRUE | P40: =INDEX(MTInputs!$J$1:$AZ$415,$D40,MATCH(P$5,MTInputs!$J$5:$AZ$5,0)) -> TRUE | Q40: =INDEX(MTInputs!$J$1:$AZ$415,$D40,MATCH(Q$5,MTInputs!$J$5:$AZ$5,0)) -> TRUE | R40: =INDEX(MTInputs!$J$1:$AZ$415,$D40,MATCH(R$5,MTInputs!$J$5:$AZ$5,0)) -> TRUE | S40: =INDEX(MTInputs!$J$1:$AZ$415,$D40,MATCH(S$5,MTInputs!$J$5:$AZ$5,0)) -> TRUE | T40: =INDEX(MTInputs!$J$1:$AZ$415,$D40,MATCH(T$5,MTInputs!$J$5:$AZ$5,0)) -> TRUE | ... Z40: =INDEX(MTInputs!$J$1:$AZ$415,$D40,MATCH(Z$5,MTInputs!$J$5:$AZ$5,0)) -> TRUE | AB40: =LOWER(Settings!$C$4)&".mit."&$A40&IF($C40="","","."&$C40&"."&$B40)&IF(INDEX(Variables!$D$5:$D$65,MATCH($A40,Variables!$A$5:$A$65,0))="","","."&INDEX(Variables!$D$5:$D$65,MATCH($A40,Variables!$A$5:$A$65,0)))&"."&AB$5 -> egy.mit.ctcov.nfm.all.2 | AC40: =INDEX(MTInputs!$J$1:$AZ$415,$D40,MATCH(AC$5,MTInputs!$J$5:$AZ$5,0)) -> TRUE | AD40: =INDEX(MTInputs!$J$1:$AZ$415,$D40,MATCH(AD$5,MTInputs!$J$5:$AZ$5,0)) -> TRUE | AE40: =INDEX(MTInputs!$J$1:$AZ$415,$D40,MATCH(AE$5,MTInputs!$J$5:$AZ$5,0)) -> TRUE | AF40: =INDEX(MTInputs!$J$1:$AZ$415,$D40,MATCH(AF$5,MTInputs!$J$5:$AZ$5,0)) -> TRUE | AG40: =INDEX(MTInputs!$J$1:$AZ$415,$D40,MATCH(AG$5,MTInputs!$J$5:$AZ$5,0)) -> TRUE | AH40: =INDEX(MTInputs!$J$1:$AZ$415,$D40,MATCH(AH$5,MTInputs!$J$5:$AZ$5,0)) -> TRUE | AI40: =INDEX(MTInputs!$J$1:$AZ$415,$D40,MATCH(AI$5,MTInputs!$J$5:$AZ$5,0)) -> TRUE | AJ40: =INDEX(MTInputs!$J$1:$AZ$415,$D40,MATCH(AJ$5,MTInputs!$J$5:$AZ$5,0)) -> TRUE | ... AP40: =INDEX(MTInputs!$J$1:$AZ$415,$D40,MATCH(AP$5,MTInputs!$J$5:$AZ$5,0)) -> TRUE
A41: ctcov | B41: all | C41: mac | D41: 42 | H41: =INDEX(Variables!$B$5:$B$65,MATCH($A41,Variables!$A$5:$A$65,0))&IF($C41="",""," | "&INDEX(Mapping!$B$5:$B$26,MATCH($C41,Mapping!$A$5:$A$26,0))&" | "&INDEX(Mapping!$B$30:$B$41,MATCH($B41,Mapping!$A$30:$A$41,0))) -> Carbon tax coverage (Apply tax?) | Machinery | All fuels | I41: =INDEX(Variables!$C$5:$C$65,MATCH($A41,Variables!$A$5:$A$65,0)) -> switch | J41: =INDEX(Variables!$E$5:$E$65,MATCH($A41,Variables!$A$5:$A$65,0)) -> MTInputs (scenario column) | L41: =LOWER(Settings!$C$4)&".mit."&$A41&IF($C41="","","."&$C41&"."&$B41)&IF(INDEX(Variables!$D$5:$D$65,MATCH($A41,Variables!$A$5:$A$65,0))="","","."&INDEX(Variables!$D$5:$D$65,MATCH($A41,Variables!$A$5:$A$65,0)))&"."&L$5 -> egy.mit.ctcov.mac.all.1 | M41: =INDEX(MTInputs!$J$1:$AZ$415,$D41,MATCH(M$5,MTInputs!$J$5:$AZ$5,0)) -> TRUE | N41: =INDEX(MTInputs!$J$1:$AZ$415,$D41,MATCH(N$5,MTInputs!$J$5:$AZ$5,0)) -> TRUE | O41: =INDEX(MTInputs!$J$1:$AZ$415,$D41,MATCH(O$5,MTInputs!$J$5:$AZ$5,0)) -> TRUE | P41: =INDEX(MTInputs!$J$1:$AZ$415,$D41,MATCH(P$5,MTInputs!$J$5:$AZ$5,0)) -> TRUE | Q41: =INDEX(MTInputs!$J$1:$AZ$415,$D41,MATCH(Q$5,MTInputs!$J$5:$AZ$5,0)) -> TRUE | R41: =INDEX(MTInputs!$J$1:$AZ$415,$D41,MATCH(R$5,MTInputs!$J$5:$AZ$5,0)) -> TRUE | S41: =INDEX(MTInputs!$J$1:$AZ$415,$D41,MATCH(S$5,MTInputs!$J$5:$AZ$5,0)) -> TRUE | T41: =INDEX(MTInputs!$J$1:$AZ$415,$D41,MATCH(T$5,MTInputs!$J$5:$AZ$5,0)) -> TRUE | ... Z41: =INDEX(MTInputs!$J$1:$AZ$415,$D41,MATCH(Z$5,MTInputs!$J$5:$AZ$5,0)) -> TRUE | AB41: =LOWER(Settings!$C$4)&".mit."&$A41&IF($C41="","","."&$C41&"."&$B41)&IF(INDEX(Variables!$D$5:$D$65,MATCH($A41,Variables!$A$5:$A$65,0))="","","."&INDEX(Variables!$D$5:$D$65,MATCH($A41,Variables!$A$5:$A$65,0)))&"."&AB$5 -> egy.mit.ctcov.mac.all.2 | AC41: =INDEX(MTInputs!$J$1:$AZ$415,$D41,MATCH(AC$5,MTInputs!$J$5:$AZ$5,0)) -> TRUE | AD41: =INDEX(MTInputs!$J$1:$AZ$415,$D41,MATCH(AD$5,MTInputs!$J$5:$AZ$5,0)) -> TRUE | AE41: =INDEX(MTInputs!$J$1:$AZ$415,$D41,MATCH(AE$5,MTInputs!$J$5:$AZ$5,0)) -> TRUE | AF41: =INDEX(MTInputs!$J$1:$AZ$415,$D41,MATCH(AF$5,MTInputs!$J$5:$AZ$5,0)) -> TRUE | AG41: =INDEX(MTInputs!$J$1:$AZ$415,$D41,MATCH(AG$5,MTInputs!$J$5:$AZ$5,0)) -> TRUE | AH41: =INDEX(MTInputs!$J$1:$AZ$415,$D41,MATCH(AH$5,MTInputs!$J$5:$AZ$5,0)) -> TRUE | AI41: =INDEX(MTInputs!$J$1:$AZ$415,$D41,MATCH(AI$5,MTInputs!$J$5:$AZ$5,0)) -> TRUE | AJ41: =INDEX(MTInputs!$J$1:$AZ$415,$D41,MATCH(AJ$5,MTInputs!$J$5:$AZ$5,0)) -> TRUE | ... AP41: =INDEX(MTInputs!$J$1:$AZ$415,$D41,MATCH(AP$5,MTInputs!$J$5:$AZ$5,0)) -> TRUE
... A46: ctcov | B46: all | C46: oen | D46: 47 | H46: =INDEX(Variables!$B$5:$B$65,MATCH($A46,Variables!$A$5:$A$65,0))&IF($C46="",""," | "&INDEX(Mapping!$B$5:$B$26,MATCH($C46,Mapping!$A$5:$A$26,0))&" | "&INDEX(Mapping!$B$30:$B$41,MATCH($B46,Mapping!$A$30:$A$41,0))) -> Carbon tax coverage (Apply tax?) | Other energy use | All fuels | I46: =INDEX(Variables!$C$5:$C$65,MATCH($A46,Variables!$A$5:$A$65,0)) -> switch | J46: =INDEX(Variables!$E$5:$E$65,MATCH($A46,Variables!$A$5:$A$65,0)) -> MTInputs (scenario column) | L46: =LOWER(Settings!$C$4)&".mit."&$A46&IF($C46="","","."&$C46&"."&$B46)&IF(INDEX(Variables!$D$5:$D$65,MATCH($A46,Variables!$A$5:$A$65,0))="","","."&INDEX(Variables!$D$5:$D$65,MATCH($A46,Variables!$A$5:$A$65,0)))&"."&L$5 -> egy.mit.ctcov.oen.all.1 | M46: =INDEX(MTInputs!$J$1:$AZ$415,$D46,MATCH(M$5,MTInputs!$J$5:$AZ$5,0)) -> FALSE | N46: =INDEX(MTInputs!$J$1:$AZ$415,$D46,MATCH(N$5,MTInputs!$J$5:$AZ$5,0)) -> FALSE | O46: =INDEX(MTInputs!$J$1:$AZ$415,$D46,MATCH(O$5,MTInputs!$J$5:$AZ$5,0)) -> FALSE | P46: =INDEX(MTInputs!$J$1:$AZ$415,$D46,MATCH(P$5,MTInputs!$J$5:$AZ$5,0)) -> FALSE | Q46: =INDEX(MTInputs!$J$1:$AZ$415,$D46,MATCH(Q$5,MTInputs!$J$5:$AZ$5,0)) -> FALSE | R46: =INDEX(MTInputs!$J$1:$AZ$415,$D46,MATCH(R$5,MTInputs!$J$5:$AZ$5,0)) -> FALSE | S46: =INDEX(MTInputs!$J$1:$AZ$415,$D46,MATCH(S$5,MTInputs!$J$5:$AZ$5,0)) -> FALSE | T46: =INDEX(MTInputs!$J$1:$AZ$415,$D46,MATCH(T$5,MTInputs!$J$5:$AZ$5,0)) -> FALSE | ... Z46: =INDEX(MTInputs!$J$1:$AZ$415,$D46,MATCH(Z$5,MTInputs!$J$5:$AZ$5,0)) -> FALSE | AB46: =LOWER(Settings!$C$4)&".mit."&$A46&IF($C46="","","."&$C46&"."&$B46)&IF(INDEX(Variables!$D$5:$D$65,MATCH($A46,Variables!$A$5:$A$65,0))="","","."&INDEX(Variables!$D$5:$D$65,MATCH($A46,Variables!$A$5:$A$65,0)))&"."&AB$5 -> egy.mit.ctcov.oen.all.2 | AC46: =INDEX(MTInputs!$J$1:$AZ$415,$D46,MATCH(AC$5,MTInputs!$J$5:$AZ$5,0)) -> FALSE | AD46: =INDEX(MTInputs!$J$1:$AZ$415,$D46,MATCH(AD$5,MTInputs!$J$5:$AZ$5,0)) -> FALSE | AE46: =INDEX(MTInputs!$J$1:$AZ$415,$D46,MATCH(AE$5,MTInputs!$J$5:$AZ$5,0)) -> FALSE | AF46: =INDEX(MTInputs!$J$1:$AZ$415,$D46,MATCH(AF$5,MTInputs!$J$5:$AZ$5,0)) -> FALSE | AG46: =INDEX(MTInputs!$J$1:$AZ$415,$D46,MATCH(AG$5,MTInputs!$J$5:$AZ$5,0)) -> FALSE | AH46: =INDEX(MTInputs!$J$1:$AZ$415,$D46,MATCH(AH$5,MTInputs!$J$5:$AZ$5,0)) -> FALSE | AI46: =INDEX(MTInputs!$J$1:$AZ$415,$D46,MATCH(AI$5,MTInputs!$J$5:$AZ$5,0)) -> FALSE | AJ46: =INDEX(MTInputs!$J$1:$AZ$415,$D46,MATCH(AJ$5,MTInputs!$J$5:$AZ$5,0)) -> FALSE | ... AP46: =INDEX(MTInputs!$J$1:$AZ$415,$D46,MATCH(AP$5,MTInputs!$J$5:$AZ$5,0)) -> FALSE
H47: Fuel price reform (MTInputs rows 140-169; increases in price units)
A48: fpr.yr0 | D48: 140 | H48: =INDEX(Variables!$B$5:$B$65,MATCH($A48,Variables!$A$5:$A$65,0))&IF($C48="",""," | "&INDEX(Mapping!$B$5:$B$26,MATCH($C48,Mapping!$A$5:$A$26,0))&" | "&INDEX(Mapping!$B$30:$B$41,MATCH($B48,Mapping!$A$30:$A$41,0))) -> Fuel price reform: starting year | I48: =INDEX(Variables!$C$5:$C$65,MATCH($A48,Variables!$A$5:$A$65,0)) -> year | J48: =INDEX(Variables!$E$5:$E$65,MATCH($A48,Variables!$A$5:$A$65,0)) -> MTInputs (scenario column) | L48: =LOWER(Settings!$C$4)&".mit."&$A48&IF($C48="","","."&$C48&"."&$B48)&IF(INDEX(Variables!$D$5:$D$65,MATCH($A48,Variables!$A$5:$A$65,0))="","","."&INDEX(Variables!$D$5:$D$65,MATCH($A48,Variables!$A$5:$A$65,0)))&"."&L$5 -> egy.mit.fpr.yr0.1 | M48: =INDEX(MTInputs!$J$1:$AZ$415,$D48,MATCH(M$5,MTInputs!$J$5:$AZ$5,0)) -> 2027 | N48: =INDEX(MTInputs!$J$1:$AZ$415,$D48,MATCH(N$5,MTInputs!$J$5:$AZ$5,0)) -> 2027 | O48: =INDEX(MTInputs!$J$1:$AZ$415,$D48,MATCH(O$5,MTInputs!$J$5:$AZ$5,0)) -> 2027 | P48: =INDEX(MTInputs!$J$1:$AZ$415,$D48,MATCH(P$5,MTInputs!$J$5:$AZ$5,0)) -> 2027 | Q48: =INDEX(MTInputs!$J$1:$AZ$415,$D48,MATCH(Q$5,MTInputs!$J$5:$AZ$5,0)) -> 2027 | R48: =INDEX(MTInputs!$J$1:$AZ$415,$D48,MATCH(R$5,MTInputs!$J$5:$AZ$5,0)) -> 2027 | S48: =INDEX(MTInputs!$J$1:$AZ$415,$D48,MATCH(S$5,MTInputs!$J$5:$AZ$5,0)) -> 2027 | T48: =INDEX(MTInputs!$J$1:$AZ$415,$D48,MATCH(T$5,MTInputs!$J$5:$AZ$5,0)) -> 2027 | ... Z48: =INDEX(MTInputs!$J$1:$AZ$415,$D48,MATCH(Z$5,MTInputs!$J$5:$AZ$5,0)) -> 2027 | AB48: =LOWER(Settings!$C$4)&".mit."&$A48&IF($C48="","","."&$C48&"."&$B48)&IF(INDEX(Variables!$D$5:$D$65,MATCH($A48,Variables!$A$5:$A$65,0))="","","."&INDEX(Variables!$D$5:$D$65,MATCH($A48,Variables!$A$5:$A$65,0)))&"."&AB$5 -> egy.mit.fpr.yr0.2 | AC48: =INDEX(MTInputs!$J$1:$AZ$415,$D48,MATCH(AC$5,MTInputs!$J$5:$AZ$5,0)) -> 2027 | AD48: =INDEX(MTInputs!$J$1:$AZ$415,$D48,MATCH(AD$5,MTInputs!$J$5:$AZ$5,0)) -> 2027 | AE48: =INDEX(MTInputs!$J$1:$AZ$415,$D48,MATCH(AE$5,MTInputs!$J$5:$AZ$5,0)) -> 2027 | AF48: =INDEX(MTInputs!$J$1:$AZ$415,$D48,MATCH(AF$5,MTInputs!$J$5:$AZ$5,0)) -> 2027 | AG48: =INDEX(MTInputs!$J$1:$AZ$415,$D48,MATCH(AG$5,MTInputs!$J$5:$AZ$5,0)) -> 2027 | AH48: =INDEX(MTInputs!$J$1:$AZ$415,$D48,MATCH(AH$5,MTInputs!$J$5:$AZ$5,0)) -> 2027 | AI48: =INDEX(MTInputs!$J$1:$AZ$415,$D48,MATCH(AI$5,MTInputs!$J$5:$AZ$5,0)) -> 2027 | AJ48: =INDEX(MTInputs!$J$1:$AZ$415,$D48,MATCH(AJ$5,MTInputs!$J$5:$AZ$5,0)) -> 2027 | ... AP48: =INDEX(MTInputs!$J$1:$AZ$415,$D48,MATCH(AP$5,MTInputs!$J$5:$AZ$5,0)) -> 2027
A49: fpr.yr1 | D49: 141 | H49: =INDEX(Variables!$B$5:$B$65,MATCH($A49,Variables!$A$5:$A$65,0))&IF($C49="",""," | "&INDEX(Mapping!$B$5:$B$26,MATCH($C49,Mapping!$A$5:$A$26,0))&" | "&INDEX(Mapping!$B$30:$B$41,MATCH($B49,Mapping!$A$30:$A$41,0))) -> Fuel price reform: target year | I49: =INDEX(Variables!$C$5:$C$65,MATCH($A49,Variables!$A$5:$A$65,0)) -> year | J49: =INDEX(Variables!$E$5:$E$65,MATCH($A49,Variables!$A$5:$A$65,0)) -> MTInputs (scenario column) | L49: =LOWER(Settings!$C$4)&".mit."&$A49&IF($C49="","","."&$C49&"."&$B49)&IF(INDEX(Variables!$D$5:$D$65,MATCH($A49,Variables!$A$5:$A$65,0))="","","."&INDEX(Variables!$D$5:$D$65,MATCH($A49,Variables!$A$5:$A$65,0)))&"."&L$5 -> egy.mit.fpr.yr1.1 | M49: =INDEX(MTInputs!$J$1:$AZ$415,$D49,MATCH(M$5,MTInputs!$J$5:$AZ$5,0)) -> 2035 | N49: =INDEX(MTInputs!$J$1:$AZ$415,$D49,MATCH(N$5,MTInputs!$J$5:$AZ$5,0)) -> 2035 | O49: =INDEX(MTInputs!$J$1:$AZ$415,$D49,MATCH(O$5,MTInputs!$J$5:$AZ$5,0)) -> 2035 | P49: =INDEX(MTInputs!$J$1:$AZ$415,$D49,MATCH(P$5,MTInputs!$J$5:$AZ$5,0)) -> 2035 | Q49: =INDEX(MTInputs!$J$1:$AZ$415,$D49,MATCH(Q$5,MTInputs!$J$5:$AZ$5,0)) -> 2035 | R49: =INDEX(MTInputs!$J$1:$AZ$415,$D49,MATCH(R$5,MTInputs!$J$5:$AZ$5,0)) -> 2035 | S49: =INDEX(MTInputs!$J$1:$AZ$415,$D49,MATCH(S$5,MTInputs!$J$5:$AZ$5,0)) -> 2035 | T49: =INDEX(MTInputs!$J$1:$AZ$415,$D49,MATCH(T$5,MTInputs!$J$5:$AZ$5,0)) -> 2035 | ... Z49: =INDEX(MTInputs!$J$1:$AZ$415,$D49,MATCH(Z$5,MTInputs!$J$5:$AZ$5,0)) -> 2035 | AB49: =LOWER(Settings!$C$4)&".mit."&$A49&IF($C49="","","."&$C49&"."&$B49)&IF(INDEX(Variables!$D$5:$D$65,MATCH($A49,Variables!$A$5:$A$65,0))="","","."&INDEX(Variables!$D$5:$D$65,MATCH($A49,Variables!$A$5:$A$65,0)))&"."&AB$5 -> egy.mit.fpr.yr1.2 | AC49: =INDEX(MTInputs!$J$1:$AZ$415,$D49,MATCH(AC$5,MTInputs!$J$5:$AZ$5,0)) -> 2035 | AD49: =INDEX(MTInputs!$J$1:$AZ$415,$D49,MATCH(AD$5,MTInputs!$J$5:$AZ$5,0)) -> 2035 | AE49: =INDEX(MTInputs!$J$1:$AZ$415,$D49,MATCH(AE$5,MTInputs!$J$5:$AZ$5,0)) -> 2035 | AF49: =INDEX(MTInputs!$J$1:$AZ$415,$D49,MATCH(AF$5,MTInputs!$J$5:$AZ$5,0)) -> 2035 | AG49: =INDEX(MTInputs!$J$1:$AZ$415,$D49,MATCH(AG$5,MTInputs!$J$5:$AZ$5,0)) -> 2035 | AH49: =INDEX(MTInputs!$J$1:$AZ$415,$D49,MATCH(AH$5,MTInputs!$J$5:$AZ$5,0)) -> 2035 | AI49: =INDEX(MTInputs!$J$1:$AZ$415,$D49,MATCH(AI$5,MTInputs!$J$5:$AZ$5,0)) -> 2035 | AJ49: =INDEX(MTInputs!$J$1:$AZ$415,$D49,MATCH(AJ$5,MTInputs!$J$5:$AZ$5,0)) -> 2035 | ... AP49: =INDEX(MTInputs!$J$1:$AZ$415,$D49,MATCH(AP$5,MTInputs!$J$5:$AZ$5,0)) -> 2035
A50: fpr.s | B50: coa | C50: pow | D50: 142 | H50: =INDEX(Variables!$B$5:$B$65,MATCH($A50,Variables!$A$5:$A$65,0))&IF($C50="",""," | "&INDEX(Mapping!$B$5:$B$26,MATCH($C50,Mapping!$A$5:$A$26,0))&" | "&INDEX(Mapping!$B$30:$B$41,MATCH($B50,Mapping!$A$30:$A$41,0))) -> Fuel price reform: starting price increase | Power | Coal | I50: =INDEX(Variables!$C$5:$C$65,MATCH($A50,Variables!$A$5:$A$65,0)) -> price unit | J50: =INDEX(Variables!$E$5:$E$65,MATCH($A50,Variables!$A$5:$A$65,0)) -> MTInputs (scenario column) | L50: =LOWER(Settings!$C$4)&".mit."&$A50&IF($C50="","","."&$C50&"."&$B50)&IF(INDEX(Variables!$D$5:$D$65,MATCH($A50,Variables!$A$5:$A$65,0))="","","."&INDEX(Variables!$D$5:$D$65,MATCH($A50,Variables!$A$5:$A$65,0)))&"."&L$5 -> egy.mit.fpr.s.pow.coa.1 | M50: =INDEX(MTInputs!$J$1:$AZ$415,$D50,MATCH(M$5,MTInputs!$J$5:$AZ$5,0)) -> 0 | N50: =INDEX(MTInputs!$J$1:$AZ$415,$D50,MATCH(N$5,MTInputs!$J$5:$AZ$5,0)) -> 0 | O50: =INDEX(MTInputs!$J$1:$AZ$415,$D50,MATCH(O$5,MTInputs!$J$5:$AZ$5,0)) -> 0 | P50: =INDEX(MTInputs!$J$1:$AZ$415,$D50,MATCH(P$5,MTInputs!$J$5:$AZ$5,0)) -> 0 | Q50: =INDEX(MTInputs!$J$1:$AZ$415,$D50,MATCH(Q$5,MTInputs!$J$5:$AZ$5,0)) -> 0 | R50: =INDEX(MTInputs!$J$1:$AZ$415,$D50,MATCH(R$5,MTInputs!$J$5:$AZ$5,0)) -> 0 | S50: =INDEX(MTInputs!$J$1:$AZ$415,$D50,MATCH(S$5,MTInputs!$J$5:$AZ$5,0)) -> 0 | T50: =INDEX(MTInputs!$J$1:$AZ$415,$D50,MATCH(T$5,MTInputs!$J$5:$AZ$5,0)) -> 0 | ... Z50: =INDEX(MTInputs!$J$1:$AZ$415,$D50,MATCH(Z$5,MTInputs!$J$5:$AZ$5,0)) -> 0 | AB50: =LOWER(Settings!$C$4)&".mit."&$A50&IF($C50="","","."&$C50&"."&$B50)&IF(INDEX(Variables!$D$5:$D$65,MATCH($A50,Variables!$A$5:$A$65,0))="","","."&INDEX(Variables!$D$5:$D$65,MATCH($A50,Variables!$A$5:$A$65,0)))&"."&AB$5 -> egy.mit.fpr.s.pow.coa.2 | AC50: =INDEX(MTInputs!$J$1:$AZ$415,$D50,MATCH(AC$5,MTInputs!$J$5:$AZ$5,0)) -> 0 | AD50: =INDEX(MTInputs!$J$1:$AZ$415,$D50,MATCH(AD$5,MTInputs!$J$5:$AZ$5,0)) -> 0 | AE50: =INDEX(MTInputs!$J$1:$AZ$415,$D50,MATCH(AE$5,MTInputs!$J$5:$AZ$5,0)) -> 0 | AF50: =INDEX(MTInputs!$J$1:$AZ$415,$D50,MATCH(AF$5,MTInputs!$J$5:$AZ$5,0)) -> 0 | AG50: =INDEX(MTInputs!$J$1:$AZ$415,$D50,MATCH(AG$5,MTInputs!$J$5:$AZ$5,0)) -> 0 | AH50: =INDEX(MTInputs!$J$1:$AZ$415,$D50,MATCH(AH$5,MTInputs!$J$5:$AZ$5,0)) -> 0 | AI50: =INDEX(MTInputs!$J$1:$AZ$415,$D50,MATCH(AI$5,MTInputs!$J$5:$AZ$5,0)) -> 0 | AJ50: =INDEX(MTInputs!$J$1:$AZ$415,$D50,MATCH(AJ$5,MTInputs!$J$5:$AZ$5,0)) -> 0 | ... AP50: =INDEX(MTInputs!$J$1:$AZ$415,$D50,MATCH(AP$5,MTInputs!$J$5:$AZ$5,0)) -> 0
A51: fpr.s | B51: coa | C51: res | D51: 143 | H51: =INDEX(Variables!$B$5:$B$65,MATCH($A51,Variables!$A$5:$A$65,0))&IF($C51="",""," | "&INDEX(Mapping!$B$5:$B$26,MATCH($C51,Mapping!$A$5:$A$26,0))&" | "&INDEX(Mapping!$B$30:$B$41,MATCH($B51,Mapping!$A$30:$A$41,0))) -> Fuel price reform: starting price increase | Residential | Coal | I51: =INDEX(Variables!$C$5:$C$65,MATCH($A51,Variables!$A$5:$A$65,0)) -> price unit | J51: =INDEX(Variables!$E$5:$E$65,MATCH($A51,Variables!$A$5:$A$65,0)) -> MTInputs (scenario column) | L51: =LOWER(Settings!$C$4)&".mit."&$A51&IF($C51="","","."&$C51&"."&$B51)&IF(INDEX(Variables!$D$5:$D$65,MATCH($A51,Variables!$A$5:$A$65,0))="","","."&INDEX(Variables!$D$5:$D$65,MATCH($A51,Variables!$A$5:$A$65,0)))&"."&L$5 -> egy.mit.fpr.s.res.coa.1 | M51: =INDEX(MTInputs!$J$1:$AZ$415,$D51,MATCH(M$5,MTInputs!$J$5:$AZ$5,0)) -> 0 | N51: =INDEX(MTInputs!$J$1:$AZ$415,$D51,MATCH(N$5,MTInputs!$J$5:$AZ$5,0)) -> 0 | O51: =INDEX(MTInputs!$J$1:$AZ$415,$D51,MATCH(O$5,MTInputs!$J$5:$AZ$5,0)) -> 0 | P51: =INDEX(MTInputs!$J$1:$AZ$415,$D51,MATCH(P$5,MTInputs!$J$5:$AZ$5,0)) -> 0 | Q51: =INDEX(MTInputs!$J$1:$AZ$415,$D51,MATCH(Q$5,MTInputs!$J$5:$AZ$5,0)) -> 0 | R51: =INDEX(MTInputs!$J$1:$AZ$415,$D51,MATCH(R$5,MTInputs!$J$5:$AZ$5,0)) -> 0 | S51: =INDEX(MTInputs!$J$1:$AZ$415,$D51,MATCH(S$5,MTInputs!$J$5:$AZ$5,0)) -> 0 | T51: =INDEX(MTInputs!$J$1:$AZ$415,$D51,MATCH(T$5,MTInputs!$J$5:$AZ$5,0)) -> 0 | ... Z51: =INDEX(MTInputs!$J$1:$AZ$415,$D51,MATCH(Z$5,MTInputs!$J$5:$AZ$5,0)) -> 0 | AB51: =LOWER(Settings!$C$4)&".mit."&$A51&IF($C51="","","."&$C51&"."&$B51)&IF(INDEX(Variables!$D$5:$D$65,MATCH($A51,Variables!$A$5:$A$65,0))="","","."&INDEX(Variables!$D$5:$D$65,MATCH($A51,Variables!$A$5:$A$65,0)))&"."&AB$5 -> egy.mit.fpr.s.res.coa.2 | AC51: =INDEX(MTInputs!$J$1:$AZ$415,$D51,MATCH(AC$5,MTInputs!$J$5:$AZ$5,0)) -> 0 | AD51: =INDEX(MTInputs!$J$1:$AZ$415,$D51,MATCH(AD$5,MTInputs!$J$5:$AZ$5,0)) -> 0 | AE51: =INDEX(MTInputs!$J$1:$AZ$415,$D51,MATCH(AE$5,MTInputs!$J$5:$AZ$5,0)) -> 0 | AF51: =INDEX(MTInputs!$J$1:$AZ$415,$D51,MATCH(AF$5,MTInputs!$J$5:$AZ$5,0)) -> 0 | AG51: =INDEX(MTInputs!$J$1:$AZ$415,$D51,MATCH(AG$5,MTInputs!$J$5:$AZ$5,0)) -> 0 | AH51: =INDEX(MTInputs!$J$1:$AZ$415,$D51,MATCH(AH$5,MTInputs!$J$5:$AZ$5,0)) -> 0 | AI51: =INDEX(MTInputs!$J$1:$AZ$415,$D51,MATCH(AI$5,MTInputs!$J$5:$AZ$5,0)) -> 0 | AJ51: =INDEX(MTInputs!$J$1:$AZ$415,$D51,MATCH(AJ$5,MTInputs!$J$5:$AZ$5,0)) -> 0 | ... AP51: =INDEX(MTInputs!$J$1:$AZ$415,$D51,MATCH(AP$5,MTInputs!$J$5:$AZ$5,0)) -> 0
A52: fpr.s | B52: coa | C52: ind | D52: 144 | H52: =INDEX(Variables!$B$5:$B$65,MATCH($A52,Variables!$A$5:$A$65,0))&IF($C52="",""," | "&INDEX(Mapping!$B$5:$B$26,MATCH($C52,Mapping!$A$5:$A$26,0))&" | "&INDEX(Mapping!$B$30:$B$41,MATCH($B52,Mapping!$A$30:$A$41,0))) -> Fuel price reform: starting price increase | Industry | Coal | I52: =INDEX(Variables!$C$5:$C$65,MATCH($A52,Variables!$A$5:$A$65,0)) -> price unit | J52: =INDEX(Variables!$E$5:$E$65,MATCH($A52,Variables!$A$5:$A$65,0)) -> MTInputs (scenario column) | L52: =LOWER(Settings!$C$4)&".mit."&$A52&IF($C52="","","."&$C52&"."&$B52)&IF(INDEX(Variables!$D$5:$D$65,MATCH($A52,Variables!$A$5:$A$65,0))="","","."&INDEX(Variables!$D$5:$D$65,MATCH($A52,Variables!$A$5:$A$65,0)))&"."&L$5 -> egy.mit.fpr.s.ind.coa.1 | M52: =INDEX(MTInputs!$J$1:$AZ$415,$D52,MATCH(M$5,MTInputs!$J$5:$AZ$5,0)) -> 0 | N52: =INDEX(MTInputs!$J$1:$AZ$415,$D52,MATCH(N$5,MTInputs!$J$5:$AZ$5,0)) -> 0 | O52: =INDEX(MTInputs!$J$1:$AZ$415,$D52,MATCH(O$5,MTInputs!$J$5:$AZ$5,0)) -> 0 | P52: =INDEX(MTInputs!$J$1:$AZ$415,$D52,MATCH(P$5,MTInputs!$J$5:$AZ$5,0)) -> 0 | Q52: =INDEX(MTInputs!$J$1:$AZ$415,$D52,MATCH(Q$5,MTInputs!$J$5:$AZ$5,0)) -> 0 | R52: =INDEX(MTInputs!$J$1:$AZ$415,$D52,MATCH(R$5,MTInputs!$J$5:$AZ$5,0)) -> 0 | S52: =INDEX(MTInputs!$J$1:$AZ$415,$D52,MATCH(S$5,MTInputs!$J$5:$AZ$5,0)) -> 0 | T52: =INDEX(MTInputs!$J$1:$AZ$415,$D52,MATCH(T$5,MTInputs!$J$5:$AZ$5,0)) -> 0 | ... Z52: =INDEX(MTInputs!$J$1:$AZ$415,$D52,MATCH(Z$5,MTInputs!$J$5:$AZ$5,0)) -> 0 | AB52: =LOWER(Settings!$C$4)&".mit."&$A52&IF($C52="","","."&$C52&"."&$B52)&IF(INDEX(Variables!$D$5:$D$65,MATCH($A52,Variables!$A$5:$A$65,0))="","","."&INDEX(Variables!$D$5:$D$65,MATCH($A52,Variables!$A$5:$A$65,0)))&"."&AB$5 -> egy.mit.fpr.s.ind.coa.2 | AC52: =INDEX(MTInputs!$J$1:$AZ$415,$D52,MATCH(AC$5,MTInputs!$J$5:$AZ$5,0)) -> 0 | AD52: =INDEX(MTInputs!$J$1:$AZ$415,$D52,MATCH(AD$5,MTInputs!$J$5:$AZ$5,0)) -> 0 | AE52: =INDEX(MTInputs!$J$1:$AZ$415,$D52,MATCH(AE$5,MTInputs!$J$5:$AZ$5,0)) -> 0 | AF52: =INDEX(MTInputs!$J$1:$AZ$415,$D52,MATCH(AF$5,MTInputs!$J$5:$AZ$5,0)) -> 0 | AG52: =INDEX(MTInputs!$J$1:$AZ$415,$D52,MATCH(AG$5,MTInputs!$J$5:$AZ$5,0)) -> 0 | AH52: =INDEX(MTInputs!$J$1:$AZ$415,$D52,MATCH(AH$5,MTInputs!$J$5:$AZ$5,0)) -> 0 | AI52: =INDEX(MTInputs!$J$1:$AZ$415,$D52,MATCH(AI$5,MTInputs!$J$5:$AZ$5,0)) -> 0 | AJ52: =INDEX(MTInputs!$J$1:$AZ$415,$D52,MATCH(AJ$5,MTInputs!$J$5:$AZ$5,0)) -> 0 | ... AP52: =INDEX(MTInputs!$J$1:$AZ$415,$D52,MATCH(AP$5,MTInputs!$J$5:$AZ$5,0)) -> 0
A53: fpr.s | B53: nga | C53: pow | D53: 145 | H53: =INDEX(Variables!$B$5:$B$65,MATCH($A53,Variables!$A$5:$A$65,0))&IF($C53="",""," | "&INDEX(Mapping!$B$5:$B$26,MATCH($C53,Mapping!$A$5:$A$26,0))&" | "&INDEX(Mapping!$B$30:$B$41,MATCH($B53,Mapping!$A$30:$A$41,0))) -> Fuel price reform: starting price increase | Power | Natural gas | I53: =INDEX(Variables!$C$5:$C$65,MATCH($A53,Variables!$A$5:$A$65,0)) -> price unit | J53: =INDEX(Variables!$E$5:$E$65,MATCH($A53,Variables!$A$5:$A$65,0)) -> MTInputs (scenario column) | L53: =LOWER(Settings!$C$4)&".mit."&$A53&IF($C53="","","."&$C53&"."&$B53)&IF(INDEX(Variables!$D$5:$D$65,MATCH($A53,Variables!$A$5:$A$65,0))="","","."&INDEX(Variables!$D$5:$D$65,MATCH($A53,Variables!$A$5:$A$65,0)))&"."&L$5 -> egy.mit.fpr.s.pow.nga.1 | M53: =INDEX(MTInputs!$J$1:$AZ$415,$D53,MATCH(M$5,MTInputs!$J$5:$AZ$5,0)) -> 0 | N53: =INDEX(MTInputs!$J$1:$AZ$415,$D53,MATCH(N$5,MTInputs!$J$5:$AZ$5,0)) -> 0 | O53: =INDEX(MTInputs!$J$1:$AZ$415,$D53,MATCH(O$5,MTInputs!$J$5:$AZ$5,0)) -> 0 | P53: =INDEX(MTInputs!$J$1:$AZ$415,$D53,MATCH(P$5,MTInputs!$J$5:$AZ$5,0)) -> 0 | Q53: =INDEX(MTInputs!$J$1:$AZ$415,$D53,MATCH(Q$5,MTInputs!$J$5:$AZ$5,0)) -> 0 | R53: =INDEX(MTInputs!$J$1:$AZ$415,$D53,MATCH(R$5,MTInputs!$J$5:$AZ$5,0)) -> 0 | S53: =INDEX(MTInputs!$J$1:$AZ$415,$D53,MATCH(S$5,MTInputs!$J$5:$AZ$5,0)) -> 0 | T53: =INDEX(MTInputs!$J$1:$AZ$415,$D53,MATCH(T$5,MTInputs!$J$5:$AZ$5,0)) -> 0 | ... Z53: =INDEX(MTInputs!$J$1:$AZ$415,$D53,MATCH(Z$5,MTInputs!$J$5:$AZ$5,0)) -> 0 | AB53: =LOWER(Settings!$C$4)&".mit."&$A53&IF($C53="","","."&$C53&"."&$B53)&IF(INDEX(Variables!$D$5:$D$65,MATCH($A53,Variables!$A$5:$A$65,0))="","","."&INDEX(Variables!$D$5:$D$65,MATCH($A53,Variables!$A$5:$A$65,0)))&"."&AB$5 -> egy.mit.fpr.s.pow.nga.2 | AC53: =INDEX(MTInputs!$J$1:$AZ$415,$D53,MATCH(AC$5,MTInputs!$J$5:$AZ$5,0)) -> 0 | AD53: =INDEX(MTInputs!$J$1:$AZ$415,$D53,MATCH(AD$5,MTInputs!$J$5:$AZ$5,0)) -> 0 | AE53: =INDEX(MTInputs!$J$1:$AZ$415,$D53,MATCH(AE$5,MTInputs!$J$5:$AZ$5,0)) -> 0 | AF53: =INDEX(MTInputs!$J$1:$AZ$415,$D53,MATCH(AF$5,MTInputs!$J$5:$AZ$5,0)) -> 0 | AG53: =INDEX(MTInputs!$J$1:$AZ$415,$D53,MATCH(AG$5,MTInputs!$J$5:$AZ$5,0)) -> 0 | AH53: =INDEX(MTInputs!$J$1:$AZ$415,$D53,MATCH(AH$5,MTInputs!$J$5:$AZ$5,0)) -> 0 | AI53: =INDEX(MTInputs!$J$1:$AZ$415,$D53,MATCH(AI$5,MTInputs!$J$5:$AZ$5,0)) -> 0 | AJ53: =INDEX(MTInputs!$J$1:$AZ$415,$D53,MATCH(AJ$5,MTInputs!$J$5:$AZ$5,0)) -> 0 | ... AP53: =INDEX(MTInputs!$J$1:$AZ$415,$D53,MATCH(AP$5,MTInputs!$J$5:$AZ$5,0)) -> 0
A54: fpr.s | B54: nga | C54: res | D54: 146 | H54: =INDEX(Variables!$B$5:$B$65,MATCH($A54,Variables!$A$5:$A$65,0))&IF($C54="",""," | "&INDEX(Mapping!$B$5:$B$26,MATCH($C54,Mapping!$A$5:$A$26,0))&" | "&INDEX(Mapping!$B$30:$B$41,MATCH($B54,Mapping!$A$30:$A$41,0))) -> Fuel price reform: starting price increase | Residential | Natural gas | I54: =INDEX(Variables!$C$5:$C$65,MATCH($A54,Variables!$A$5:$A$65,0)) -> price unit | J54: =INDEX(Variables!$E$5:$E$65,MATCH($A54,Variables!$A$5:$A$65,0)) -> MTInputs (scenario column) | L54: =LOWER(Settings!$C$4)&".mit."&$A54&IF($C54="","","."&$C54&"."&$B54)&IF(INDEX(Variables!$D$5:$D$65,MATCH($A54,Variables!$A$5:$A$65,0))="","","."&INDEX(Variables!$D$5:$D$65,MATCH($A54,Variables!$A$5:$A$65,0)))&"."&L$5 -> egy.mit.fpr.s.res.nga.1 | M54: =INDEX(MTInputs!$J$1:$AZ$415,$D54,MATCH(M$5,MTInputs!$J$5:$AZ$5,0)) -> 0 | N54: =INDEX(MTInputs!$J$1:$AZ$415,$D54,MATCH(N$5,MTInputs!$J$5:$AZ$5,0)) -> 0 | O54: =INDEX(MTInputs!$J$1:$AZ$415,$D54,MATCH(O$5,MTInputs!$J$5:$AZ$5,0)) -> 0 | P54: =INDEX(MTInputs!$J$1:$AZ$415,$D54,MATCH(P$5,MTInputs!$J$5:$AZ$5,0)) -> 0 | Q54: =INDEX(MTInputs!$J$1:$AZ$415,$D54,MATCH(Q$5,MTInputs!$J$5:$AZ$5,0)) -> 0 | R54: =INDEX(MTInputs!$J$1:$AZ$415,$D54,MATCH(R$5,MTInputs!$J$5:$AZ$5,0)) -> 0 | S54: =INDEX(MTInputs!$J$1:$AZ$415,$D54,MATCH(S$5,MTInputs!$J$5:$AZ$5,0)) -> 0 | T54: =INDEX(MTInputs!$J$1:$AZ$415,$D54,MATCH(T$5,MTInputs!$J$5:$AZ$5,0)) -> 0 | ... Z54: =INDEX(MTInputs!$J$1:$AZ$415,$D54,MATCH(Z$5,MTInputs!$J$5:$AZ$5,0)) -> 0 | AB54: =LOWER(Settings!$C$4)&".mit."&$A54&IF($C54="","","."&$C54&"."&$B54)&IF(INDEX(Variables!$D$5:$D$65,MATCH($A54,Variables!$A$5:$A$65,0))="","","."&INDEX(Variables!$D$5:$D$65,MATCH($A54,Variables!$A$5:$A$65,0)))&"."&AB$5 -> egy.mit.fpr.s.res.nga.2 | AC54: =INDEX(MTInputs!$J$1:$AZ$415,$D54,MATCH(AC$5,MTInputs!$J$5:$AZ$5,0)) -> 0 | AD54: =INDEX(MTInputs!$J$1:$AZ$415,$D54,MATCH(AD$5,MTInputs!$J$5:$AZ$5,0)) -> 0 | AE54: =INDEX(MTInputs!$J$1:$AZ$415,$D54,MATCH(AE$5,MTInputs!$J$5:$AZ$5,0)) -> 0 | AF54: =INDEX(MTInputs!$J$1:$AZ$415,$D54,MATCH(AF$5,MTInputs!$J$5:$AZ$5,0)) -> 0 | AG54: =INDEX(MTInputs!$J$1:$AZ$415,$D54,MATCH(AG$5,MTInputs!$J$5:$AZ$5,0)) -> 0 | AH54: =INDEX(MTInputs!$J$1:$AZ$415,$D54,MATCH(AH$5,MTInputs!$J$5:$AZ$5,0)) -> 0 | AI54: =INDEX(MTInputs!$J$1:$AZ$415,$D54,MATCH(AI$5,MTInputs!$J$5:$AZ$5,0)) -> 0 | AJ54: =INDEX(MTInputs!$J$1:$AZ$415,$D54,MATCH(AJ$5,MTInputs!$J$5:$AZ$5,0)) -> 0 | ... AP54: =INDEX(MTInputs!$J$1:$AZ$415,$D54,MATCH(AP$5,MTInputs!$J$5:$AZ$5,0)) -> 0
A55: fpr.s | B55: nga | C55: ind | D55: 147 | H55: =INDEX(Variables!$B$5:$B$65,MATCH($A55,Variables!$A$5:$A$65,0))&IF($C55="",""," | "&INDEX(Mapping!$B$5:$B$26,MATCH($C55,Mapping!$A$5:$A$26,0))&" | "&INDEX(Mapping!$B$30:$B$41,MATCH($B55,Mapping!$A$30:$A$41,0))) -> Fuel price reform: starting price increase | Industry | Natural gas | I55: =INDEX(Variables!$C$5:$C$65,MATCH($A55,Variables!$A$5:$A$65,0)) -> price unit | J55: =INDEX(Variables!$E$5:$E$65,MATCH($A55,Variables!$A$5:$A$65,0)) -> MTInputs (scenario column) | L55: =LOWER(Settings!$C$4)&".mit."&$A55&IF($C55="","","."&$C55&"."&$B55)&IF(INDEX(Variables!$D$5:$D$65,MATCH($A55,Variables!$A$5:$A$65,0))="","","."&INDEX(Variables!$D$5:$D$65,MATCH($A55,Variables!$A$5:$A$65,0)))&"."&L$5 -> egy.mit.fpr.s.ind.nga.1 | M55: =INDEX(MTInputs!$J$1:$AZ$415,$D55,MATCH(M$5,MTInputs!$J$5:$AZ$5,0)) -> 0 | N55: =INDEX(MTInputs!$J$1:$AZ$415,$D55,MATCH(N$5,MTInputs!$J$5:$AZ$5,0)) -> 0 | O55: =INDEX(MTInputs!$J$1:$AZ$415,$D55,MATCH(O$5,MTInputs!$J$5:$AZ$5,0)) -> 0 | P55: =INDEX(MTInputs!$J$1:$AZ$415,$D55,MATCH(P$5,MTInputs!$J$5:$AZ$5,0)) -> 0 | Q55: =INDEX(MTInputs!$J$1:$AZ$415,$D55,MATCH(Q$5,MTInputs!$J$5:$AZ$5,0)) -> 0 | R55: =INDEX(MTInputs!$J$1:$AZ$415,$D55,MATCH(R$5,MTInputs!$J$5:$AZ$5,0)) -> 0 | S55: =INDEX(MTInputs!$J$1:$AZ$415,$D55,MATCH(S$5,MTInputs!$J$5:$AZ$5,0)) -> 0 | T55: =INDEX(MTInputs!$J$1:$AZ$415,$D55,MATCH(T$5,MTInputs!$J$5:$AZ$5,0)) -> 0 | ... Z55: =INDEX(MTInputs!$J$1:$AZ$415,$D55,MATCH(Z$5,MTInputs!$J$5:$AZ$5,0)) -> 0 | AB55: =LOWER(Settings!$C$4)&".mit."&$A55&IF($C55="","","."&$C55&"."&$B55)&IF(INDEX(Variables!$D$5:$D$65,MATCH($A55,Variables!$A$5:$A$65,0))="","","."&INDEX(Variables!$D$5:$D$65,MATCH($A55,Variables!$A$5:$A$65,0)))&"."&AB$5 -> egy.mit.fpr.s.ind.nga.2 | AC55: =INDEX(MTInputs!$J$1:$AZ$415,$D55,MATCH(AC$5,MTInputs!$J$5:$AZ$5,0)) -> 0 | AD55: =INDEX(MTInputs!$J$1:$AZ$415,$D55,MATCH(AD$5,MTInputs!$J$5:$AZ$5,0)) -> 0 | AE55: =INDEX(MTInputs!$J$1:$AZ$415,$D55,MATCH(AE$5,MTInputs!$J$5:$AZ$5,0)) -> 0 | AF55: =INDEX(MTInputs!$J$1:$AZ$415,$D55,MATCH(AF$5,MTInputs!$J$5:$AZ$5,0)) -> 0 | AG55: =INDEX(MTInputs!$J$1:$AZ$415,$D55,MATCH(AG$5,MTInputs!$J$5:$AZ$5,0)) -> 0 | AH55: =INDEX(MTInputs!$J$1:$AZ$415,$D55,MATCH(AH$5,MTInputs!$J$5:$AZ$5,0)) -> 0 | AI55: =INDEX(MTInputs!$J$1:$AZ$415,$D55,MATCH(AI$5,MTInputs!$J$5:$AZ$5,0)) -> 0 | AJ55: =INDEX(MTInputs!$J$1:$AZ$415,$D55,MATCH(AJ$5,MTInputs!$J$5:$AZ$5,0)) -> 0 | ... AP55: =INDEX(MTInputs!$J$1:$AZ$415,$D55,MATCH(AP$5,MTInputs!$J$5:$AZ$5,0)) -> 0
A56: fpr.s | B56: ecy | C56: res | D56: 148 | H56: =INDEX(Variables!$B$5:$B$65,MATCH($A56,Variables!$A$5:$A$65,0))&IF($C56="",""," | "&INDEX(Mapping!$B$5:$B$26,MATCH($C56,Mapping!$A$5:$A$26,0))&" | "&INDEX(Mapping!$B$30:$B$41,MATCH($B56,Mapping!$A$30:$A$41,0))) -> Fuel price reform: starting price increase | Residential | Electricity | I56: =INDEX(Variables!$C$5:$C$65,MATCH($A56,Variables!$A$5:$A$65,0)) -> price unit | J56: =INDEX(Variables!$E$5:$E$65,MATCH($A56,Variables!$A$5:$A$65,0)) -> MTInputs (scenario column) | L56: =LOWER(Settings!$C$4)&".mit."&$A56&IF($C56="","","."&$C56&"."&$B56)&IF(INDEX(Variables!$D$5:$D$65,MATCH($A56,Variables!$A$5:$A$65,0))="","","."&INDEX(Variables!$D$5:$D$65,MATCH($A56,Variables!$A$5:$A$65,0)))&"."&L$5 -> egy.mit.fpr.s.res.ecy.1 | M56: =INDEX(MTInputs!$J$1:$AZ$415,$D56,MATCH(M$5,MTInputs!$J$5:$AZ$5,0)) -> 0 | N56: =INDEX(MTInputs!$J$1:$AZ$415,$D56,MATCH(N$5,MTInputs!$J$5:$AZ$5,0)) -> 0 | O56: =INDEX(MTInputs!$J$1:$AZ$415,$D56,MATCH(O$5,MTInputs!$J$5:$AZ$5,0)) -> 0 | P56: =INDEX(MTInputs!$J$1:$AZ$415,$D56,MATCH(P$5,MTInputs!$J$5:$AZ$5,0)) -> 0 | Q56: =INDEX(MTInputs!$J$1:$AZ$415,$D56,MATCH(Q$5,MTInputs!$J$5:$AZ$5,0)) -> 0 | R56: =INDEX(MTInputs!$J$1:$AZ$415,$D56,MATCH(R$5,MTInputs!$J$5:$AZ$5,0)) -> 0 | S56: =INDEX(MTInputs!$J$1:$AZ$415,$D56,MATCH(S$5,MTInputs!$J$5:$AZ$5,0)) -> 0 | T56: =INDEX(MTInputs!$J$1:$AZ$415,$D56,MATCH(T$5,MTInputs!$J$5:$AZ$5,0)) -> 0 | ... Z56: =INDEX(MTInputs!$J$1:$AZ$415,$D56,MATCH(Z$5,MTInputs!$J$5:$AZ$5,0)) -> 0 | AB56: =LOWER(Settings!$C$4)&".mit."&$A56&IF($C56="","","."&$C56&"."&$B56)&IF(INDEX(Variables!$D$5:$D$65,MATCH($A56,Variables!$A$5:$A$65,0))="","","."&INDEX(Variables!$D$5:$D$65,MATCH($A56,Variables!$A$5:$A$65,0)))&"."&AB$5 -> egy.mit.fpr.s.res.ecy.2 | AC56: =INDEX(MTInputs!$J$1:$AZ$415,$D56,MATCH(AC$5,MTInputs!$J$5:$AZ$5,0)) -> 0 | AD56: =INDEX(MTInputs!$J$1:$AZ$415,$D56,MATCH(AD$5,MTInputs!$J$5:$AZ$5,0)) -> 0 | AE56: =INDEX(MTInputs!$J$1:$AZ$415,$D56,MATCH(AE$5,MTInputs!$J$5:$AZ$5,0)) -> 0 | AF56: =INDEX(MTInputs!$J$1:$AZ$415,$D56,MATCH(AF$5,MTInputs!$J$5:$AZ$5,0)) -> 0 | AG56: =INDEX(MTInputs!$J$1:$AZ$415,$D56,MATCH(AG$5,MTInputs!$J$5:$AZ$5,0)) -> 0 | AH56: =INDEX(MTInputs!$J$1:$AZ$415,$D56,MATCH(AH$5,MTInputs!$J$5:$AZ$5,0)) -> 0 | AI56: =INDEX(MTInputs!$J$1:$AZ$415,$D56,MATCH(AI$5,MTInputs!$J$5:$AZ$5,0)) -> 0 | AJ56: =INDEX(MTInputs!$J$1:$AZ$415,$D56,MATCH(AJ$5,MTInputs!$J$5:$AZ$5,0)) -> 0 | ... AP56: =INDEX(MTInputs!$J$1:$AZ$415,$D56,MATCH(AP$5,MTInputs!$J$5:$AZ$5,0)) -> 0
A57: fpr.s | B57: ecy | C57: ind | D57: 149 | H57: =INDEX(Variables!$B$5:$B$65,MATCH($A57,Variables!$A$5:$A$65,0))&IF($C57="",""," | "&INDEX(Mapping!$B$5:$B$26,MATCH($C57,Mapping!$A$5:$A$26,0))&" | "&INDEX(Mapping!$B$30:$B$41,MATCH($B57,Mapping!$A$30:$A$41,0))) -> Fuel price reform: starting price increase | Industry | Electricity | I57: =INDEX(Variables!$C$5:$C$65,MATCH($A57,Variables!$A$5:$A$65,0)) -> price unit | J57: =INDEX(Variables!$E$5:$E$65,MATCH($A57,Variables!$A$5:$A$65,0)) -> MTInputs (scenario column) | L57: =LOWER(Settings!$C$4)&".mit."&$A57&IF($C57="","","."&$C57&"."&$B57)&IF(INDEX(Variables!$D$5:$D$65,MATCH($A57,Variables!$A$5:$A$65,0))="","","."&INDEX(Variables!$D$5:$D$65,MATCH($A57,Variables!$A$5:$A$65,0)))&"."&L$5 -> egy.mit.fpr.s.ind.ecy.1 | M57: =INDEX(MTInputs!$J$1:$AZ$415,$D57,MATCH(M$5,MTInputs!$J$5:$AZ$5,0)) -> 0 | N57: =INDEX(MTInputs!$J$1:$AZ$415,$D57,MATCH(N$5,MTInputs!$J$5:$AZ$5,0)) -> 0 | O57: =INDEX(MTInputs!$J$1:$AZ$415,$D57,MATCH(O$5,MTInputs!$J$5:$AZ$5,0)) -> 0 | P57: =INDEX(MTInputs!$J$1:$AZ$415,$D57,MATCH(P$5,MTInputs!$J$5:$AZ$5,0)) -> 0 | Q57: =INDEX(MTInputs!$J$1:$AZ$415,$D57,MATCH(Q$5,MTInputs!$J$5:$AZ$5,0)) -> 0 | R57: =INDEX(MTInputs!$J$1:$AZ$415,$D57,MATCH(R$5,MTInputs!$J$5:$AZ$5,0)) -> 0 | S57: =INDEX(MTInputs!$J$1:$AZ$415,$D57,MATCH(S$5,MTInputs!$J$5:$AZ$5,0)) -> 0 | T57: =INDEX(MTInputs!$J$1:$AZ$415,$D57,MATCH(T$5,MTInputs!$J$5:$AZ$5,0)) -> 0 | ... Z57: =INDEX(MTInputs!$J$1:$AZ$415,$D57,MATCH(Z$5,MTInputs!$J$5:$AZ$5,0)) -> 0 | AB57: =LOWER(Settings!$C$4)&".mit."&$A57&IF($C57="","","."&$C57&"."&$B57)&IF(INDEX(Variables!$D$5:$D$65,MATCH($A57,Variables!$A$5:$A$65,0))="","","."&INDEX(Variables!$D$5:$D$65,MATCH($A57,Variables!$A$5:$A$65,0)))&"."&AB$5 -> egy.mit.fpr.s.ind.ecy.2 | AC57: =INDEX(MTInputs!$J$1:$AZ$415,$D57,MATCH(AC$5,MTInputs!$J$5:$AZ$5,0)) -> 0 | AD57: =INDEX(MTInputs!$J$1:$AZ$415,$D57,MATCH(AD$5,MTInputs!$J$5:$AZ$5,0)) -> 0 | AE57: =INDEX(MTInputs!$J$1:$AZ$415,$D57,MATCH(AE$5,MTInputs!$J$5:$AZ$5,0)) -> 0 | AF57: =INDEX(MTInputs!$J$1:$AZ$415,$D57,MATCH(AF$5,MTInputs!$J$5:$AZ$5,0)) -> 0 | AG57: =INDEX(MTInputs!$J$1:$AZ$415,$D57,MATCH(AG$5,MTInputs!$J$5:$AZ$5,0)) -> 0 | AH57: =INDEX(MTInputs!$J$1:$AZ$415,$D57,MATCH(AH$5,MTInputs!$J$5:$AZ$5,0)) -> 0 | AI57: =INDEX(MTInputs!$J$1:$AZ$415,$D57,MATCH(AI$5,MTInputs!$J$5:$AZ$5,0)) -> 0 | AJ57: =INDEX(MTInputs!$J$1:$AZ$415,$D57,MATCH(AJ$5,MTInputs!$J$5:$AZ$5,0)) -> 0 | ... AP57: =INDEX(MTInputs!$J$1:$AZ$415,$D57,MATCH(AP$5,MTInputs!$J$5:$AZ$5,0)) -> 0
A58: fpr.s | B58: gso | C58: all | D58: 150 | H58: =INDEX(Variables!$B$5:$B$65,MATCH($A58,Variables!$A$5:$A$65,0))&IF($C58="",""," | "&INDEX(Mapping!$B$5:$B$26,MATCH($C58,Mapping!$A$5:$A$26,0))&" | "&INDEX(Mapping!$B$30:$B$41,MATCH($B58,Mapping!$A$30:$A$41,0))) -> Fuel price reform: starting price increase | All subsectors | Gasoline | I58: =INDEX(Variables!$C$5:$C$65,MATCH($A58,Variables!$A$5:$A$65,0)) -> price unit | J58: =INDEX(Variables!$E$5:$E$65,MATCH($A58,Variables!$A$5:$A$65,0)) -> MTInputs (scenario column) | L58: =LOWER(Settings!$C$4)&".mit."&$A58&IF($C58="","","."&$C58&"."&$B58)&IF(INDEX(Variables!$D$5:$D$65,MATCH($A58,Variables!$A$5:$A$65,0))="","","."&INDEX(Variables!$D$5:$D$65,MATCH($A58,Variables!$A$5:$A$65,0)))&"."&L$5 -> egy.mit.fpr.s.all.gso.1 | M58: =INDEX(MTInputs!$J$1:$AZ$415,$D58,MATCH(M$5,MTInputs!$J$5:$AZ$5,0)) -> 0 | N58: =INDEX(MTInputs!$J$1:$AZ$415,$D58,MATCH(N$5,MTInputs!$J$5:$AZ$5,0)) -> 0 | O58: =INDEX(MTInputs!$J$1:$AZ$415,$D58,MATCH(O$5,MTInputs!$J$5:$AZ$5,0)) -> 0 | P58: =INDEX(MTInputs!$J$1:$AZ$415,$D58,MATCH(P$5,MTInputs!$J$5:$AZ$5,0)) -> 0 | Q58: =INDEX(MTInputs!$J$1:$AZ$415,$D58,MATCH(Q$5,MTInputs!$J$5:$AZ$5,0)) -> 0 | R58: =INDEX(MTInputs!$J$1:$AZ$415,$D58,MATCH(R$5,MTInputs!$J$5:$AZ$5,0)) -> 0 | S58: =INDEX(MTInputs!$J$1:$AZ$415,$D58,MATCH(S$5,MTInputs!$J$5:$AZ$5,0)) -> 0 | T58: =INDEX(MTInputs!$J$1:$AZ$415,$D58,MATCH(T$5,MTInputs!$J$5:$AZ$5,0)) -> 0 | ... Z58: =INDEX(MTInputs!$J$1:$AZ$415,$D58,MATCH(Z$5,MTInputs!$J$5:$AZ$5,0)) -> 0 | AB58: =LOWER(Settings!$C$4)&".mit."&$A58&IF($C58="","","."&$C58&"."&$B58)&IF(INDEX(Variables!$D$5:$D$65,MATCH($A58,Variables!$A$5:$A$65,0))="","","."&INDEX(Variables!$D$5:$D$65,MATCH($A58,Variables!$A$5:$A$65,0)))&"."&AB$5 -> egy.mit.fpr.s.all.gso.2 | AC58: =INDEX(MTInputs!$J$1:$AZ$415,$D58,MATCH(AC$5,MTInputs!$J$5:$AZ$5,0)) -> 0 | AD58: =INDEX(MTInputs!$J$1:$AZ$415,$D58,MATCH(AD$5,MTInputs!$J$5:$AZ$5,0)) -> 0 | AE58: =INDEX(MTInputs!$J$1:$AZ$415,$D58,MATCH(AE$5,MTInputs!$J$5:$AZ$5,0)) -> 0 | AF58: =INDEX(MTInputs!$J$1:$AZ$415,$D58,MATCH(AF$5,MTInputs!$J$5:$AZ$5,0)) -> 0 | AG58: =INDEX(MTInputs!$J$1:$AZ$415,$D58,MATCH(AG$5,MTInputs!$J$5:$AZ$5,0)) -> 0 | AH58: =INDEX(MTInputs!$J$1:$AZ$415,$D58,MATCH(AH$5,MTInputs!$J$5:$AZ$5,0)) -> 0 | AI58: =INDEX(MTInputs!$J$1:$AZ$415,$D58,MATCH(AI$5,MTInputs!$J$5:$AZ$5,0)) -> 0 | AJ58: =INDEX(MTInputs!$J$1:$AZ$415,$D58,MATCH(AJ$5,MTInputs!$J$5:$AZ$5,0)) -> 0 | ... AP58: =INDEX(MTInputs!$J$1:$AZ$415,$D58,MATCH(AP$5,MTInputs!$J$5:$AZ$5,0)) -> 0
A59: fpr.s | B59: die | C59: all | D59: 151 | H59: =INDEX(Variables!$B$5:$B$65,MATCH($A59,Variables!$A$5:$A$65,0))&IF($C59="",""," | "&INDEX(Mapping!$B$5:$B$26,MATCH($C59,Mapping!$A$5:$A$26,0))&" | "&INDEX(Mapping!$B$30:$B$41,MATCH($B59,Mapping!$A$30:$A$41,0))) -> Fuel price reform: starting price increase | All subsectors | Diesel | I59: =INDEX(Variables!$C$5:$C$65,MATCH($A59,Variables!$A$5:$A$65,0)) -> price unit | J59: =INDEX(Variables!$E$5:$E$65,MATCH($A59,Variables!$A$5:$A$65,0)) -> MTInputs (scenario column) | L59: =LOWER(Settings!$C$4)&".mit."&$A59&IF($C59="","","."&$C59&"."&$B59)&IF(INDEX(Variables!$D$5:$D$65,MATCH($A59,Variables!$A$5:$A$65,0))="","","."&INDEX(Variables!$D$5:$D$65,MATCH($A59,Variables!$A$5:$A$65,0)))&"."&L$5 -> egy.mit.fpr.s.all.die.1 | M59: =INDEX(MTInputs!$J$1:$AZ$415,$D59,MATCH(M$5,MTInputs!$J$5:$AZ$5,0)) -> 0 | N59: =INDEX(MTInputs!$J$1:$AZ$415,$D59,MATCH(N$5,MTInputs!$J$5:$AZ$5,0)) -> 0 | O59: =INDEX(MTInputs!$J$1:$AZ$415,$D59,MATCH(O$5,MTInputs!$J$5:$AZ$5,0)) -> 0 | P59: =INDEX(MTInputs!$J$1:$AZ$415,$D59,MATCH(P$5,MTInputs!$J$5:$AZ$5,0)) -> 0 | Q59: =INDEX(MTInputs!$J$1:$AZ$415,$D59,MATCH(Q$5,MTInputs!$J$5:$AZ$5,0)) -> 0 | R59: =INDEX(MTInputs!$J$1:$AZ$415,$D59,MATCH(R$5,MTInputs!$J$5:$AZ$5,0)) -> 0 | S59: =INDEX(MTInputs!$J$1:$AZ$415,$D59,MATCH(S$5,MTInputs!$J$5:$AZ$5,0)) -> 0 | T59: =INDEX(MTInputs!$J$1:$AZ$415,$D59,MATCH(T$5,MTInputs!$J$5:$AZ$5,0)) -> 0 | ... Z59: =INDEX(MTInputs!$J$1:$AZ$415,$D59,MATCH(Z$5,MTInputs!$J$5:$AZ$5,0)) -> 0 | AB59: =LOWER(Settings!$C$4)&".mit."&$A59&IF($C59="","","."&$C59&"."&$B59)&IF(INDEX(Variables!$D$5:$D$65,MATCH($A59,Variables!$A$5:$A$65,0))="","","."&INDEX(Variables!$D$5:$D$65,MATCH($A59,Variables!$A$5:$A$65,0)))&"."&AB$5 -> egy.mit.fpr.s.all.die.2 | AC59: =INDEX(MTInputs!$J$1:$AZ$415,$D59,MATCH(AC$5,MTInputs!$J$5:$AZ$5,0)) -> 0 | AD59: =INDEX(MTInputs!$J$1:$AZ$415,$D59,MATCH(AD$5,MTInputs!$J$5:$AZ$5,0)) -> 0 | AE59: =INDEX(MTInputs!$J$1:$AZ$415,$D59,MATCH(AE$5,MTInputs!$J$5:$AZ$5,0)) -> 0 | AF59: =INDEX(MTInputs!$J$1:$AZ$415,$D59,MATCH(AF$5,MTInputs!$J$5:$AZ$5,0)) -> 0 | AG59: =INDEX(MTInputs!$J$1:$AZ$415,$D59,MATCH(AG$5,MTInputs!$J$5:$AZ$5,0)) -> 0 | AH59: =INDEX(MTInputs!$J$1:$AZ$415,$D59,MATCH(AH$5,MTInputs!$J$5:$AZ$5,0)) -> 0 | AI59: =INDEX(MTInputs!$J$1:$AZ$415,$D59,MATCH(AI$5,MTInputs!$J$5:$AZ$5,0)) -> 0 | AJ59: =INDEX(MTInputs!$J$1:$AZ$415,$D59,MATCH(AJ$5,MTInputs!$J$5:$AZ$5,0)) -> 0 | ... AP59: =INDEX(MTInputs!$J$1:$AZ$415,$D59,MATCH(AP$5,MTInputs!$J$5:$AZ$5,0)) -> 0
A60: fpr.s | B60: lpg | C60: all | D60: 152 | H60: =INDEX(Variables!$B$5:$B$65,MATCH($A60,Variables!$A$5:$A$65,0))&IF($C60="",""," | "&INDEX(Mapping!$B$5:$B$26,MATCH($C60,Mapping!$A$5:$A$26,0))&" | "&INDEX(Mapping!$B$30:$B$41,MATCH($B60,Mapping!$A$30:$A$41,0))) -> Fuel price reform: starting price increase | All subsectors | LPG | I60: =INDEX(Variables!$C$5:$C$65,MATCH($A60,Variables!$A$5:$A$65,0)) -> price unit | J60: =INDEX(Variables!$E$5:$E$65,MATCH($A60,Variables!$A$5:$A$65,0)) -> MTInputs (scenario column) | L60: =LOWER(Settings!$C$4)&".mit."&$A60&IF($C60="","","."&$C60&"."&$B60)&IF(INDEX(Variables!$D$5:$D$65,MATCH($A60,Variables!$A$5:$A$65,0))="","","."&INDEX(Variables!$D$5:$D$65,MATCH($A60,Variables!$A$5:$A$65,0)))&"."&L$5 -> egy.mit.fpr.s.all.lpg.1 | M60: =INDEX(MTInputs!$J$1:$AZ$415,$D60,MATCH(M$5,MTInputs!$J$5:$AZ$5,0)) -> 0 | N60: =INDEX(MTInputs!$J$1:$AZ$415,$D60,MATCH(N$5,MTInputs!$J$5:$AZ$5,0)) -> 0 | O60: =INDEX(MTInputs!$J$1:$AZ$415,$D60,MATCH(O$5,MTInputs!$J$5:$AZ$5,0)) -> 0 | P60: =INDEX(MTInputs!$J$1:$AZ$415,$D60,MATCH(P$5,MTInputs!$J$5:$AZ$5,0)) -> 0 | Q60: =INDEX(MTInputs!$J$1:$AZ$415,$D60,MATCH(Q$5,MTInputs!$J$5:$AZ$5,0)) -> 0 | R60: =INDEX(MTInputs!$J$1:$AZ$415,$D60,MATCH(R$5,MTInputs!$J$5:$AZ$5,0)) -> 0 | S60: =INDEX(MTInputs!$J$1:$AZ$415,$D60,MATCH(S$5,MTInputs!$J$5:$AZ$5,0)) -> 0 | T60: =INDEX(MTInputs!$J$1:$AZ$415,$D60,MATCH(T$5,MTInputs!$J$5:$AZ$5,0)) -> 0 | ... Z60: =INDEX(MTInputs!$J$1:$AZ$415,$D60,MATCH(Z$5,MTInputs!$J$5:$AZ$5,0)) -> 0 | AB60: =LOWER(Settings!$C$4)&".mit."&$A60&IF($C60="","","."&$C60&"."&$B60)&IF(INDEX(Variables!$D$5:$D$65,MATCH($A60,Variables!$A$5:$A$65,0))="","","."&INDEX(Variables!$D$5:$D$65,MATCH($A60,Variables!$A$5:$A$65,0)))&"."&AB$5 -> egy.mit.fpr.s.all.lpg.2 | AC60: =INDEX(MTInputs!$J$1:$AZ$415,$D60,MATCH(AC$5,MTInputs!$J$5:$AZ$5,0)) -> 0 | AD60: =INDEX(MTInputs!$J$1:$AZ$415,$D60,MATCH(AD$5,MTInputs!$J$5:$AZ$5,0)) -> 0 | AE60: =INDEX(MTInputs!$J$1:$AZ$415,$D60,MATCH(AE$5,MTInputs!$J$5:$AZ$5,0)) -> 0 | AF60: =INDEX(MTInputs!$J$1:$AZ$415,$D60,MATCH(AF$5,MTInputs!$J$5:$AZ$5,0)) -> 0 | AG60: =INDEX(MTInputs!$J$1:$AZ$415,$D60,MATCH(AG$5,MTInputs!$J$5:$AZ$5,0)) -> 0 | AH60: =INDEX(MTInputs!$J$1:$AZ$415,$D60,MATCH(AH$5,MTInputs!$J$5:$AZ$5,0)) -> 0 | AI60: =INDEX(MTInputs!$J$1:$AZ$415,$D60,MATCH(AI$5,MTInputs!$J$5:$AZ$5,0)) -> 0 | AJ60: =INDEX(MTInputs!$J$1:$AZ$415,$D60,MATCH(AJ$5,MTInputs!$J$5:$AZ$5,0)) -> 0 | ... AP60: =INDEX(MTInputs!$J$1:$AZ$415,$D60,MATCH(AP$5,MTInputs!$J$5:$AZ$5,0)) -> 0
A61: fpr.s | B61: ker | C61: all | D61: 153 | H61: =INDEX(Variables!$B$5:$B$65,MATCH($A61,Variables!$A$5:$A$65,0))&IF($C61="",""," | "&INDEX(Mapping!$B$5:$B$26,MATCH($C61,Mapping!$A$5:$A$26,0))&" | "&INDEX(Mapping!$B$30:$B$41,MATCH($B61,Mapping!$A$30:$A$41,0))) -> Fuel price reform: starting price increase | All subsectors | Kerosene | I61: =INDEX(Variables!$C$5:$C$65,MATCH($A61,Variables!$A$5:$A$65,0)) -> price unit | J61: =INDEX(Variables!$E$5:$E$65,MATCH($A61,Variables!$A$5:$A$65,0)) -> MTInputs (scenario column) | L61: =LOWER(Settings!$C$4)&".mit."&$A61&IF($C61="","","."&$C61&"."&$B61)&IF(INDEX(Variables!$D$5:$D$65,MATCH($A61,Variables!$A$5:$A$65,0))="","","."&INDEX(Variables!$D$5:$D$65,MATCH($A61,Variables!$A$5:$A$65,0)))&"."&L$5 -> egy.mit.fpr.s.all.ker.1 | M61: =INDEX(MTInputs!$J$1:$AZ$415,$D61,MATCH(M$5,MTInputs!$J$5:$AZ$5,0)) -> 0 | N61: =INDEX(MTInputs!$J$1:$AZ$415,$D61,MATCH(N$5,MTInputs!$J$5:$AZ$5,0)) -> 0 | O61: =INDEX(MTInputs!$J$1:$AZ$415,$D61,MATCH(O$5,MTInputs!$J$5:$AZ$5,0)) -> 0 | P61: =INDEX(MTInputs!$J$1:$AZ$415,$D61,MATCH(P$5,MTInputs!$J$5:$AZ$5,0)) -> 0 | Q61: =INDEX(MTInputs!$J$1:$AZ$415,$D61,MATCH(Q$5,MTInputs!$J$5:$AZ$5,0)) -> 0 | R61: =INDEX(MTInputs!$J$1:$AZ$415,$D61,MATCH(R$5,MTInputs!$J$5:$AZ$5,0)) -> 0 | S61: =INDEX(MTInputs!$J$1:$AZ$415,$D61,MATCH(S$5,MTInputs!$J$5:$AZ$5,0)) -> 0 | T61: =INDEX(MTInputs!$J$1:$AZ$415,$D61,MATCH(T$5,MTInputs!$J$5:$AZ$5,0)) -> 0 | ... Z61: =INDEX(MTInputs!$J$1:$AZ$415,$D61,MATCH(Z$5,MTInputs!$J$5:$AZ$5,0)) -> 0 | AB61: =LOWER(Settings!$C$4)&".mit."&$A61&IF($C61="","","."&$C61&"."&$B61)&IF(INDEX(Variables!$D$5:$D$65,MATCH($A61,Variables!$A$5:$A$65,0))="","","."&INDEX(Variables!$D$5:$D$65,MATCH($A61,Variables!$A$5:$A$65,0)))&"."&AB$5 -> egy.mit.fpr.s.all.ker.2 | AC61: =INDEX(MTInputs!$J$1:$AZ$415,$D61,MATCH(AC$5,MTInputs!$J$5:$AZ$5,0)) -> 0 | AD61: =INDEX(MTInputs!$J$1:$AZ$415,$D61,MATCH(AD$5,MTInputs!$J$5:$AZ$5,0)) -> 0 | AE61: =INDEX(MTInputs!$J$1:$AZ$415,$D61,MATCH(AE$5,MTInputs!$J$5:$AZ$5,0)) -> 0 | AF61: =INDEX(MTInputs!$J$1:$AZ$415,$D61,MATCH(AF$5,MTInputs!$J$5:$AZ$5,0)) -> 0 | AG61: =INDEX(MTInputs!$J$1:$AZ$415,$D61,MATCH(AG$5,MTInputs!$J$5:$AZ$5,0)) -> 0 | AH61: =INDEX(MTInputs!$J$1:$AZ$415,$D61,MATCH(AH$5,MTInputs!$J$5:$AZ$5,0)) -> 0 | AI61: =INDEX(MTInputs!$J$1:$AZ$415,$D61,MATCH(AI$5,MTInputs!$J$5:$AZ$5,0)) -> 0 | AJ61: =INDEX(MTInputs!$J$1:$AZ$415,$D61,MATCH(AJ$5,MTInputs!$J$5:$AZ$5,0)) -> 0 | ... AP61: =INDEX(MTInputs!$J$1:$AZ$415,$D61,MATCH(AP$5,MTInputs!$J$5:$AZ$5,0)) -> 0
... A77: fpr.f | B77: bio | C77: all | D77: 169 | H77: =INDEX(Variables!$B$5:$B$65,MATCH($A77,Variables!$A$5:$A$65,0))&IF($C77="",""," | "&INDEX(Mapping!$B$5:$B$26,MATCH($C77,Mapping!$A$5:$A$26,0))&" | "&INDEX(Mapping!$B$30:$B$41,MATCH($B77,Mapping!$A$30:$A$41,0))) -> Fuel price reform: final price increase | All subsectors | Biomass | I77: =INDEX(Variables!$C$5:$C$65,MATCH($A77,Variables!$A$5:$A$65,0)) -> price unit | J77: =INDEX(Variables!$E$5:$E$65,MATCH($A77,Variables!$A$5:$A$65,0)) -> MTInputs (scenario column) | L77: =LOWER(Settings!$C$4)&".mit."&$A77&IF($C77="","","."&$C77&"."&$B77)&IF(INDEX(Variables!$D$5:$D$65,MATCH($A77,Variables!$A$5:$A$65,0))="","","."&INDEX(Variables!$D$5:$D$65,MATCH($A77,Variables!$A$5:$A$65,0)))&"."&L$5 -> egy.mit.fpr.f.all.bio.1 | M77: =INDEX(MTInputs!$J$1:$AZ$415,$D77,MATCH(M$5,MTInputs!$J$5:$AZ$5,0)) -> 0 | N77: =INDEX(MTInputs!$J$1:$AZ$415,$D77,MATCH(N$5,MTInputs!$J$5:$AZ$5,0)) -> 0 | O77: =INDEX(MTInputs!$J$1:$AZ$415,$D77,MATCH(O$5,MTInputs!$J$5:$AZ$5,0)) -> 0 | P77: =INDEX(MTInputs!$J$1:$AZ$415,$D77,MATCH(P$5,MTInputs!$J$5:$AZ$5,0)) -> 0 | Q77: =INDEX(MTInputs!$J$1:$AZ$415,$D77,MATCH(Q$5,MTInputs!$J$5:$AZ$5,0)) -> 0 | R77: =INDEX(MTInputs!$J$1:$AZ$415,$D77,MATCH(R$5,MTInputs!$J$5:$AZ$5,0)) -> 0 | S77: =INDEX(MTInputs!$J$1:$AZ$415,$D77,MATCH(S$5,MTInputs!$J$5:$AZ$5,0)) -> 0 | T77: =INDEX(MTInputs!$J$1:$AZ$415,$D77,MATCH(T$5,MTInputs!$J$5:$AZ$5,0)) -> 0 | ... Z77: =INDEX(MTInputs!$J$1:$AZ$415,$D77,MATCH(Z$5,MTInputs!$J$5:$AZ$5,0)) -> 0 | AB77: =LOWER(Settings!$C$4)&".mit."&$A77&IF($C77="","","."&$C77&"."&$B77)&IF(INDEX(Variables!$D$5:$D$65,MATCH($A77,Variables!$A$5:$A$65,0))="","","."&INDEX(Variables!$D$5:$D$65,MATCH($A77,Variables!$A$5:$A$65,0)))&"."&AB$5 -> egy.mit.fpr.f.all.bio.2 | AC77: =INDEX(MTInputs!$J$1:$AZ$415,$D77,MATCH(AC$5,MTInputs!$J$5:$AZ$5,0)) -> 0 | AD77: =INDEX(MTInputs!$J$1:$AZ$415,$D77,MATCH(AD$5,MTInputs!$J$5:$AZ$5,0)) -> 0 | AE77: =INDEX(MTInputs!$J$1:$AZ$415,$D77,MATCH(AE$5,MTInputs!$J$5:$AZ$5,0)) -> 0 | AF77: =INDEX(MTInputs!$J$1:$AZ$415,$D77,MATCH(AF$5,MTInputs!$J$5:$AZ$5,0)) -> 0 | AG77: =INDEX(MTInputs!$J$1:$AZ$415,$D77,MATCH(AG$5,MTInputs!$J$5:$AZ$5,0)) -> 0 | AH77: =INDEX(MTInputs!$J$1:$AZ$415,$D77,MATCH(AH$5,MTInputs!$J$5:$AZ$5,0)) -> 0 | AI77: =INDEX(MTInputs!$J$1:$AZ$415,$D77,MATCH(AI$5,MTInputs!$J$5:$AZ$5,0)) -> 0 | AJ77: =INDEX(MTInputs!$J$1:$AZ$415,$D77,MATCH(AJ$5,MTInputs!$J$5:$AZ$5,0)) -> 0 | ... AP77: =INDEX(MTInputs!$J$1:$AZ$415,$D77,MATCH(AP$5,MTInputs!$J$5:$AZ$5,0)) -> 0
A78: fpr | B78: coa | C78: pow | H78: =INDEX(Variables!$B$5:$B$65,MATCH($A78,Variables!$A$5:$A$65,0))&IF($C78="",""," | "&INDEX(Mapping!$B$5:$B$26,MATCH($C78,Mapping!$A$5:$A$26,0))&" | "&INDEX(Mapping!$B$30:$B$41,MATCH($B78,Mapping!$A$30:$A$41,0))) -> Fuel price reform: price increase path | Power | Coal | I78: =INDEX(Variables!$C$5:$C$65,MATCH($A78,Variables!$A$5:$A$65,0)) -> price unit | J78: =INDEX(Variables!$E$5:$E$65,MATCH($A78,Variables!$A$5:$A$65,0)) -> Calculation (assumed linear) | L78: =LOWER(Settings!$C$4)&".mit."&$A78&IF($C78="","","."&$C78&"."&$B78)&IF(INDEX(Variables!$D$5:$D$65,MATCH($A78,Variables!$A$5:$A$65,0))="","","."&INDEX(Variables!$D$5:$D$65,MATCH($A78,Variables!$A$5:$A$65,0)))&"."&L$5 -> egy.mit.fpr.pow.coa.1 | M78: =IF(M$4<M$48,0,M50+(M64-M50)/MAX(M$49-M$48,1)*(M$4-M$48)) -> 0 | N78: =IF(N$4<N$48,0,N50+(N64-N50)/MAX(N$49-N$48,1)*(N$4-N$48)) -> 0 | O78: =IF(O$4<O$48,0,O50+(O64-O50)/MAX(O$49-O$48,1)*(O$4-O$48)) -> 0 | P78: =IF(P$4<P$48,0,P50+(P64-P50)/MAX(P$49-P$48,1)*(P$4-P$48)) -> 0 | Q78: =IF(Q$4<Q$48,0,Q50+(Q64-Q50)/MAX(Q$49-Q$48,1)*(Q$4-Q$48)) -> 0 | R78: =IF(R$4<R$48,0,R50+(R64-R50)/MAX(R$49-R$48,1)*(R$4-R$48)) -> 0 | S78: =IF(S$4<S$48,0,S50+(S64-S50)/MAX(S$49-S$48,1)*(S$4-S$48)) -> 0 | T78: =IF(T$4<T$48,0,T50+(T64-T50)/MAX(T$49-T$48,1)*(T$4-T$48)) -> 0 | ... Z78: =IF(Z$4<Z$48,0,Z50+(Z64-Z50)/MAX(Z$49-Z$48,1)*(Z$4-Z$48)) -> 0 | AB78: =LOWER(Settings!$C$4)&".mit."&$A78&IF($C78="","","."&$C78&"."&$B78)&IF(INDEX(Variables!$D$5:$D$65,MATCH($A78,Variables!$A$5:$A$65,0))="","","."&INDEX(Variables!$D$5:$D$65,MATCH($A78,Variables!$A$5:$A$65,0)))&"."&AB$5 -> egy.mit.fpr.pow.coa.2 | AC78: =IF(AC$4<AC$48,0,AC50+(AC64-AC50)/MAX(AC$49-AC$48,1)*(AC$4-AC$48)) -> 0 | AD78: =IF(AD$4<AD$48,0,AD50+(AD64-AD50)/MAX(AD$49-AD$48,1)*(AD$4-AD$48)) -> 0 | AE78: =IF(AE$4<AE$48,0,AE50+(AE64-AE50)/MAX(AE$49-AE$48,1)*(AE$4-AE$48)) -> 0 | AF78: =IF(AF$4<AF$48,0,AF50+(AF64-AF50)/MAX(AF$49-AF$48,1)*(AF$4-AF$48)) -> 0 | AG78: =IF(AG$4<AG$48,0,AG50+(AG64-AG50)/MAX(AG$49-AG$48,1)*(AG$4-AG$48)) -> 0 | AH78: =IF(AH$4<AH$48,0,AH50+(AH64-AH50)/MAX(AH$49-AH$48,1)*(AH$4-AH$48)) -> 0 | AI78: =IF(AI$4<AI$48,0,AI50+(AI64-AI50)/MAX(AI$49-AI$48,1)*(AI$4-AI$48)) -> 0 | AJ78: =IF(AJ$4<AJ$48,0,AJ50+(AJ64-AJ50)/MAX(AJ$49-AJ$48,1)*(AJ$4-AJ$48)) -> 0 | ... AP78: =IF(AP$4<AP$48,0,AP50+(AP64-AP50)/MAX(AP$49-AP$48,1)*(AP$4-AP$48)) -> 0
A79: fpr | B79: coa | C79: res | H79: =INDEX(Variables!$B$5:$B$65,MATCH($A79,Variables!$A$5:$A$65,0))&IF($C79="",""," | "&INDEX(Mapping!$B$5:$B$26,MATCH($C79,Mapping!$A$5:$A$26,0))&" | "&INDEX(Mapping!$B$30:$B$41,MATCH($B79,Mapping!$A$30:$A$41,0))) -> Fuel price reform: price increase path | Residential | Coal | I79: =INDEX(Variables!$C$5:$C$65,MATCH($A79,Variables!$A$5:$A$65,0)) -> price unit | J79: =INDEX(Variables!$E$5:$E$65,MATCH($A79,Variables!$A$5:$A$65,0)) -> Calculation (assumed linear) | L79: =LOWER(Settings!$C$4)&".mit."&$A79&IF($C79="","","."&$C79&"."&$B79)&IF(INDEX(Variables!$D$5:$D$65,MATCH($A79,Variables!$A$5:$A$65,0))="","","."&INDEX(Variables!$D$5:$D$65,MATCH($A79,Variables!$A$5:$A$65,0)))&"."&L$5 -> egy.mit.fpr.res.coa.1 | M79: =IF(M$4<M$48,0,M51+(M65-M51)/MAX(M$49-M$48,1)*(M$4-M$48)) -> 0 | N79: =IF(N$4<N$48,0,N51+(N65-N51)/MAX(N$49-N$48,1)*(N$4-N$48)) -> 0 | O79: =IF(O$4<O$48,0,O51+(O65-O51)/MAX(O$49-O$48,1)*(O$4-O$48)) -> 0 | P79: =IF(P$4<P$48,0,P51+(P65-P51)/MAX(P$49-P$48,1)*(P$4-P$48)) -> 0 | Q79: =IF(Q$4<Q$48,0,Q51+(Q65-Q51)/MAX(Q$49-Q$48,1)*(Q$4-Q$48)) -> 0 | R79: =IF(R$4<R$48,0,R51+(R65-R51)/MAX(R$49-R$48,1)*(R$4-R$48)) -> 0 | S79: =IF(S$4<S$48,0,S51+(S65-S51)/MAX(S$49-S$48,1)*(S$4-S$48)) -> 0 | T79: =IF(T$4<T$48,0,T51+(T65-T51)/MAX(T$49-T$48,1)*(T$4-T$48)) -> 0 | ... Z79: =IF(Z$4<Z$48,0,Z51+(Z65-Z51)/MAX(Z$49-Z$48,1)*(Z$4-Z$48)) -> 0 | AB79: =LOWER(Settings!$C$4)&".mit."&$A79&IF($C79="","","."&$C79&"."&$B79)&IF(INDEX(Variables!$D$5:$D$65,MATCH($A79,Variables!$A$5:$A$65,0))="","","."&INDEX(Variables!$D$5:$D$65,MATCH($A79,Variables!$A$5:$A$65,0)))&"."&AB$5 -> egy.mit.fpr.res.coa.2 | AC79: =IF(AC$4<AC$48,0,AC51+(AC65-AC51)/MAX(AC$49-AC$48,1)*(AC$4-AC$48)) -> 0 | AD79: =IF(AD$4<AD$48,0,AD51+(AD65-AD51)/MAX(AD$49-AD$48,1)*(AD$4-AD$48)) -> 0 | AE79: =IF(AE$4<AE$48,0,AE51+(AE65-AE51)/MAX(AE$49-AE$48,1)*(AE$4-AE$48)) -> 0 | AF79: =IF(AF$4<AF$48,0,AF51+(AF65-AF51)/MAX(AF$49-AF$48,1)*(AF$4-AF$48)) -> 0 | AG79: =IF(AG$4<AG$48,0,AG51+(AG65-AG51)/MAX(AG$49-AG$48,1)*(AG$4-AG$48)) -> 0 | AH79: =IF(AH$4<AH$48,0,AH51+(AH65-AH51)/MAX(AH$49-AH$48,1)*(AH$4-AH$48)) -> 0 | AI79: =IF(AI$4<AI$48,0,AI51+(AI65-AI51)/MAX(AI$49-AI$48,1)*(AI$4-AI$48)) -> 0 | AJ79: =IF(AJ$4<AJ$48,0,AJ51+(AJ65-AJ51)/MAX(AJ$49-AJ$48,1)*(AJ$4-AJ$48)) -> 0 | ... AP79: =IF(AP$4<AP$48,0,AP51+(AP65-AP51)/MAX(AP$49-AP$48,1)*(AP$4-AP$48)) -> 0
A80: fpr | B80: coa | C80: ind | H80: =INDEX(Variables!$B$5:$B$65,MATCH($A80,Variables!$A$5:$A$65,0))&IF($C80="",""," | "&INDEX(Mapping!$B$5:$B$26,MATCH($C80,Mapping!$A$5:$A$26,0))&" | "&INDEX(Mapping!$B$30:$B$41,MATCH($B80,Mapping!$A$30:$A$41,0))) -> Fuel price reform: price increase path | Industry | Coal | I80: =INDEX(Variables!$C$5:$C$65,MATCH($A80,Variables!$A$5:$A$65,0)) -> price unit | J80: =INDEX(Variables!$E$5:$E$65,MATCH($A80,Variables!$A$5:$A$65,0)) -> Calculation (assumed linear) | L80: =LOWER(Settings!$C$4)&".mit."&$A80&IF($C80="","","."&$C80&"."&$B80)&IF(INDEX(Variables!$D$5:$D$65,MATCH($A80,Variables!$A$5:$A$65,0))="","","."&INDEX(Variables!$D$5:$D$65,MATCH($A80,Variables!$A$5:$A$65,0)))&"."&L$5 -> egy.mit.fpr.ind.coa.1 | M80: =IF(M$4<M$48,0,M52+(M66-M52)/MAX(M$49-M$48,1)*(M$4-M$48)) -> 0 | N80: =IF(N$4<N$48,0,N52+(N66-N52)/MAX(N$49-N$48,1)*(N$4-N$48)) -> 0 | O80: =IF(O$4<O$48,0,O52+(O66-O52)/MAX(O$49-O$48,1)*(O$4-O$48)) -> 0 | P80: =IF(P$4<P$48,0,P52+(P66-P52)/MAX(P$49-P$48,1)*(P$4-P$48)) -> 0 | Q80: =IF(Q$4<Q$48,0,Q52+(Q66-Q52)/MAX(Q$49-Q$48,1)*(Q$4-Q$48)) -> 0 | R80: =IF(R$4<R$48,0,R52+(R66-R52)/MAX(R$49-R$48,1)*(R$4-R$48)) -> 0 | S80: =IF(S$4<S$48,0,S52+(S66-S52)/MAX(S$49-S$48,1)*(S$4-S$48)) -> 0 | T80: =IF(T$4<T$48,0,T52+(T66-T52)/MAX(T$49-T$48,1)*(T$4-T$48)) -> 0 | ... Z80: =IF(Z$4<Z$48,0,Z52+(Z66-Z52)/MAX(Z$49-Z$48,1)*(Z$4-Z$48)) -> 0 | AB80: =LOWER(Settings!$C$4)&".mit."&$A80&IF($C80="","","."&$C80&"."&$B80)&IF(INDEX(Variables!$D$5:$D$65,MATCH($A80,Variables!$A$5:$A$65,0))="","","."&INDEX(Variables!$D$5:$D$65,MATCH($A80,Variables!$A$5:$A$65,0)))&"."&AB$5 -> egy.mit.fpr.ind.coa.2 | AC80: =IF(AC$4<AC$48,0,AC52+(AC66-AC52)/MAX(AC$49-AC$48,1)*(AC$4-AC$48)) -> 0 | AD80: =IF(AD$4<AD$48,0,AD52+(AD66-AD52)/MAX(AD$49-AD$48,1)*(AD$4-AD$48)) -> 0 | AE80: =IF(AE$4<AE$48,0,AE52+(AE66-AE52)/MAX(AE$49-AE$48,1)*(AE$4-AE$48)) -> 0 | AF80: =IF(AF$4<AF$48,0,AF52+(AF66-AF52)/MAX(AF$49-AF$48,1)*(AF$4-AF$48)) -> 0 | AG80: =IF(AG$4<AG$48,0,AG52+(AG66-AG52)/MAX(AG$49-AG$48,1)*(AG$4-AG$48)) -> 0 | AH80: =IF(AH$4<AH$48,0,AH52+(AH66-AH52)/MAX(AH$49-AH$48,1)*(AH$4-AH$48)) -> 0 | AI80: =IF(AI$4<AI$48,0,AI52+(AI66-AI52)/MAX(AI$49-AI$48,1)*(AI$4-AI$48)) -> 0 | AJ80: =IF(AJ$4<AJ$48,0,AJ52+(AJ66-AJ52)/MAX(AJ$49-AJ$48,1)*(AJ$4-AJ$48)) -> 0 | ... AP80: =IF(AP$4<AP$48,0,AP52+(AP66-AP52)/MAX(AP$49-AP$48,1)*(AP$4-AP$48)) -> 0
A81: fpr | B81: nga | C81: pow | H81: =INDEX(Variables!$B$5:$B$65,MATCH($A81,Variables!$A$5:$A$65,0))&IF($C81="",""," | "&INDEX(Mapping!$B$5:$B$26,MATCH($C81,Mapping!$A$5:$A$26,0))&" | "&INDEX(Mapping!$B$30:$B$41,MATCH($B81,Mapping!$A$30:$A$41,0))) -> Fuel price reform: price increase path | Power | Natural gas | I81: =INDEX(Variables!$C$5:$C$65,MATCH($A81,Variables!$A$5:$A$65,0)) -> price unit | J81: =INDEX(Variables!$E$5:$E$65,MATCH($A81,Variables!$A$5:$A$65,0)) -> Calculation (assumed linear) | L81: =LOWER(Settings!$C$4)&".mit."&$A81&IF($C81="","","."&$C81&"."&$B81)&IF(INDEX(Variables!$D$5:$D$65,MATCH($A81,Variables!$A$5:$A$65,0))="","","."&INDEX(Variables!$D$5:$D$65,MATCH($A81,Variables!$A$5:$A$65,0)))&"."&L$5 -> egy.mit.fpr.pow.nga.1 | M81: =IF(M$4<M$48,0,M53+(M67-M53)/MAX(M$49-M$48,1)*(M$4-M$48)) -> 0 | N81: =IF(N$4<N$48,0,N53+(N67-N53)/MAX(N$49-N$48,1)*(N$4-N$48)) -> 0 | O81: =IF(O$4<O$48,0,O53+(O67-O53)/MAX(O$49-O$48,1)*(O$4-O$48)) -> 0 | P81: =IF(P$4<P$48,0,P53+(P67-P53)/MAX(P$49-P$48,1)*(P$4-P$48)) -> 0 | Q81: =IF(Q$4<Q$48,0,Q53+(Q67-Q53)/MAX(Q$49-Q$48,1)*(Q$4-Q$48)) -> 0 | R81: =IF(R$4<R$48,0,R53+(R67-R53)/MAX(R$49-R$48,1)*(R$4-R$48)) -> 0 | S81: =IF(S$4<S$48,0,S53+(S67-S53)/MAX(S$49-S$48,1)*(S$4-S$48)) -> 0 | T81: =IF(T$4<T$48,0,T53+(T67-T53)/MAX(T$49-T$48,1)*(T$4-T$48)) -> 0 | ... Z81: =IF(Z$4<Z$48,0,Z53+(Z67-Z53)/MAX(Z$49-Z$48,1)*(Z$4-Z$48)) -> 0 | AB81: =LOWER(Settings!$C$4)&".mit."&$A81&IF($C81="","","."&$C81&"."&$B81)&IF(INDEX(Variables!$D$5:$D$65,MATCH($A81,Variables!$A$5:$A$65,0))="","","."&INDEX(Variables!$D$5:$D$65,MATCH($A81,Variables!$A$5:$A$65,0)))&"."&AB$5 -> egy.mit.fpr.pow.nga.2 | AC81: =IF(AC$4<AC$48,0,AC53+(AC67-AC53)/MAX(AC$49-AC$48,1)*(AC$4-AC$48)) -> 0 | AD81: =IF(AD$4<AD$48,0,AD53+(AD67-AD53)/MAX(AD$49-AD$48,1)*(AD$4-AD$48)) -> 0 | AE81: =IF(AE$4<AE$48,0,AE53+(AE67-AE53)/MAX(AE$49-AE$48,1)*(AE$4-AE$48)) -> 0 | AF81: =IF(AF$4<AF$48,0,AF53+(AF67-AF53)/MAX(AF$49-AF$48,1)*(AF$4-AF$48)) -> 0 | AG81: =IF(AG$4<AG$48,0,AG53+(AG67-AG53)/MAX(AG$49-AG$48,1)*(AG$4-AG$48)) -> 0 | AH81: =IF(AH$4<AH$48,0,AH53+(AH67-AH53)/MAX(AH$49-AH$48,1)*(AH$4-AH$48)) -> 0 | AI81: =IF(AI$4<AI$48,0,AI53+(AI67-AI53)/MAX(AI$49-AI$48,1)*(AI$4-AI$48)) -> 0 | AJ81: =IF(AJ$4<AJ$48,0,AJ53+(AJ67-AJ53)/MAX(AJ$49-AJ$48,1)*(AJ$4-AJ$48)) -> 0 | ... AP81: =IF(AP$4<AP$48,0,AP53+(AP67-AP53)/MAX(AP$49-AP$48,1)*(AP$4-AP$48)) -> 0
A82: fpr | B82: nga | C82: res | H82: =INDEX(Variables!$B$5:$B$65,MATCH($A82,Variables!$A$5:$A$65,0))&IF($C82="",""," | "&INDEX(Mapping!$B$5:$B$26,MATCH($C82,Mapping!$A$5:$A$26,0))&" | "&INDEX(Mapping!$B$30:$B$41,MATCH($B82,Mapping!$A$30:$A$41,0))) -> Fuel price reform: price increase path | Residential | Natural gas | I82: =INDEX(Variables!$C$5:$C$65,MATCH($A82,Variables!$A$5:$A$65,0)) -> price unit | J82: =INDEX(Variables!$E$5:$E$65,MATCH($A82,Variables!$A$5:$A$65,0)) -> Calculation (assumed linear) | L82: =LOWER(Settings!$C$4)&".mit."&$A82&IF($C82="","","."&$C82&"."&$B82)&IF(INDEX(Variables!$D$5:$D$65,MATCH($A82,Variables!$A$5:$A$65,0))="","","."&INDEX(Variables!$D$5:$D$65,MATCH($A82,Variables!$A$5:$A$65,0)))&"."&L$5 -> egy.mit.fpr.res.nga.1 | M82: =IF(M$4<M$48,0,M54+(M68-M54)/MAX(M$49-M$48,1)*(M$4-M$48)) -> 0 | N82: =IF(N$4<N$48,0,N54+(N68-N54)/MAX(N$49-N$48,1)*(N$4-N$48)) -> 0 | O82: =IF(O$4<O$48,0,O54+(O68-O54)/MAX(O$49-O$48,1)*(O$4-O$48)) -> 0 | P82: =IF(P$4<P$48,0,P54+(P68-P54)/MAX(P$49-P$48,1)*(P$4-P$48)) -> 0 | Q82: =IF(Q$4<Q$48,0,Q54+(Q68-Q54)/MAX(Q$49-Q$48,1)*(Q$4-Q$48)) -> 0 | R82: =IF(R$4<R$48,0,R54+(R68-R54)/MAX(R$49-R$48,1)*(R$4-R$48)) -> 0 | S82: =IF(S$4<S$48,0,S54+(S68-S54)/MAX(S$49-S$48,1)*(S$4-S$48)) -> 0 | T82: =IF(T$4<T$48,0,T54+(T68-T54)/MAX(T$49-T$48,1)*(T$4-T$48)) -> 0 | ... Z82: =IF(Z$4<Z$48,0,Z54+(Z68-Z54)/MAX(Z$49-Z$48,1)*(Z$4-Z$48)) -> 0 | AB82: =LOWER(Settings!$C$4)&".mit."&$A82&IF($C82="","","."&$C82&"."&$B82)&IF(INDEX(Variables!$D$5:$D$65,MATCH($A82,Variables!$A$5:$A$65,0))="","","."&INDEX(Variables!$D$5:$D$65,MATCH($A82,Variables!$A$5:$A$65,0)))&"."&AB$5 -> egy.mit.fpr.res.nga.2 | AC82: =IF(AC$4<AC$48,0,AC54+(AC68-AC54)/MAX(AC$49-AC$48,1)*(AC$4-AC$48)) -> 0 | AD82: =IF(AD$4<AD$48,0,AD54+(AD68-AD54)/MAX(AD$49-AD$48,1)*(AD$4-AD$48)) -> 0 | AE82: =IF(AE$4<AE$48,0,AE54+(AE68-AE54)/MAX(AE$49-AE$48,1)*(AE$4-AE$48)) -> 0 | AF82: =IF(AF$4<AF$48,0,AF54+(AF68-AF54)/MAX(AF$49-AF$48,1)*(AF$4-AF$48)) -> 0 | AG82: =IF(AG$4<AG$48,0,AG54+(AG68-AG54)/MAX(AG$49-AG$48,1)*(AG$4-AG$48)) -> 0 | AH82: =IF(AH$4<AH$48,0,AH54+(AH68-AH54)/MAX(AH$49-AH$48,1)*(AH$4-AH$48)) -> 0 | AI82: =IF(AI$4<AI$48,0,AI54+(AI68-AI54)/MAX(AI$49-AI$48,1)*(AI$4-AI$48)) -> 0 | AJ82: =IF(AJ$4<AJ$48,0,AJ54+(AJ68-AJ54)/MAX(AJ$49-AJ$48,1)*(AJ$4-AJ$48)) -> 0 | ... AP82: =IF(AP$4<AP$48,0,AP54+(AP68-AP54)/MAX(AP$49-AP$48,1)*(AP$4-AP$48)) -> 0
A83: fpr | B83: nga | C83: ind | H83: =INDEX(Variables!$B$5:$B$65,MATCH($A83,Variables!$A$5:$A$65,0))&IF($C83="",""," | "&INDEX(Mapping!$B$5:$B$26,MATCH($C83,Mapping!$A$5:$A$26,0))&" | "&INDEX(Mapping!$B$30:$B$41,MATCH($B83,Mapping!$A$30:$A$41,0))) -> Fuel price reform: price increase path | Industry | Natural gas | I83: =INDEX(Variables!$C$5:$C$65,MATCH($A83,Variables!$A$5:$A$65,0)) -> price unit | J83: =INDEX(Variables!$E$5:$E$65,MATCH($A83,Variables!$A$5:$A$65,0)) -> Calculation (assumed linear) | L83: =LOWER(Settings!$C$4)&".mit."&$A83&IF($C83="","","."&$C83&"."&$B83)&IF(INDEX(Variables!$D$5:$D$65,MATCH($A83,Variables!$A$5:$A$65,0))="","","."&INDEX(Variables!$D$5:$D$65,MATCH($A83,Variables!$A$5:$A$65,0)))&"."&L$5 -> egy.mit.fpr.ind.nga.1 | M83: =IF(M$4<M$48,0,M55+(M69-M55)/MAX(M$49-M$48,1)*(M$4-M$48)) -> 0 | N83: =IF(N$4<N$48,0,N55+(N69-N55)/MAX(N$49-N$48,1)*(N$4-N$48)) -> 0 | O83: =IF(O$4<O$48,0,O55+(O69-O55)/MAX(O$49-O$48,1)*(O$4-O$48)) -> 0 | P83: =IF(P$4<P$48,0,P55+(P69-P55)/MAX(P$49-P$48,1)*(P$4-P$48)) -> 0 | Q83: =IF(Q$4<Q$48,0,Q55+(Q69-Q55)/MAX(Q$49-Q$48,1)*(Q$4-Q$48)) -> 0 | R83: =IF(R$4<R$48,0,R55+(R69-R55)/MAX(R$49-R$48,1)*(R$4-R$48)) -> 0 | S83: =IF(S$4<S$48,0,S55+(S69-S55)/MAX(S$49-S$48,1)*(S$4-S$48)) -> 0 | T83: =IF(T$4<T$48,0,T55+(T69-T55)/MAX(T$49-T$48,1)*(T$4-T$48)) -> 0 | ... Z83: =IF(Z$4<Z$48,0,Z55+(Z69-Z55)/MAX(Z$49-Z$48,1)*(Z$4-Z$48)) -> 0 | AB83: =LOWER(Settings!$C$4)&".mit."&$A83&IF($C83="","","."&$C83&"."&$B83)&IF(INDEX(Variables!$D$5:$D$65,MATCH($A83,Variables!$A$5:$A$65,0))="","","."&INDEX(Variables!$D$5:$D$65,MATCH($A83,Variables!$A$5:$A$65,0)))&"."&AB$5 -> egy.mit.fpr.ind.nga.2 | AC83: =IF(AC$4<AC$48,0,AC55+(AC69-AC55)/MAX(AC$49-AC$48,1)*(AC$4-AC$48)) -> 0 | AD83: =IF(AD$4<AD$48,0,AD55+(AD69-AD55)/MAX(AD$49-AD$48,1)*(AD$4-AD$48)) -> 0 | AE83: =IF(AE$4<AE$48,0,AE55+(AE69-AE55)/MAX(AE$49-AE$48,1)*(AE$4-AE$48)) -> 0 | AF83: =IF(AF$4<AF$48,0,AF55+(AF69-AF55)/MAX(AF$49-AF$48,1)*(AF$4-AF$48)) -> 0 | AG83: =IF(AG$4<AG$48,0,AG55+(AG69-AG55)/MAX(AG$49-AG$48,1)*(AG$4-AG$48)) -> 0 | AH83: =IF(AH$4<AH$48,0,AH55+(AH69-AH55)/MAX(AH$49-AH$48,1)*(AH$4-AH$48)) -> 0 | AI83: =IF(AI$4<AI$48,0,AI55+(AI69-AI55)/MAX(AI$49-AI$48,1)*(AI$4-AI$48)) -> 0 | AJ83: =IF(AJ$4<AJ$48,0,AJ55+(AJ69-AJ55)/MAX(AJ$49-AJ$48,1)*(AJ$4-AJ$48)) -> 0 | ... AP83: =IF(AP$4<AP$48,0,AP55+(AP69-AP55)/MAX(AP$49-AP$48,1)*(AP$4-AP$48)) -> 0
A84: fpr | B84: ecy | C84: res | H84: =INDEX(Variables!$B$5:$B$65,MATCH($A84,Variables!$A$5:$A$65,0))&IF($C84="",""," | "&INDEX(Mapping!$B$5:$B$26,MATCH($C84,Mapping!$A$5:$A$26,0))&" | "&INDEX(Mapping!$B$30:$B$41,MATCH($B84,Mapping!$A$30:$A$41,0))) -> Fuel price reform: price increase path | Residential | Electricity | I84: =INDEX(Variables!$C$5:$C$65,MATCH($A84,Variables!$A$5:$A$65,0)) -> price unit | J84: =INDEX(Variables!$E$5:$E$65,MATCH($A84,Variables!$A$5:$A$65,0)) -> Calculation (assumed linear) | L84: =LOWER(Settings!$C$4)&".mit."&$A84&IF($C84="","","."&$C84&"."&$B84)&IF(INDEX(Variables!$D$5:$D$65,MATCH($A84,Variables!$A$5:$A$65,0))="","","."&INDEX(Variables!$D$5:$D$65,MATCH($A84,Variables!$A$5:$A$65,0)))&"."&L$5 -> egy.mit.fpr.res.ecy.1 | M84: =IF(M$4<M$48,0,M56+(M70-M56)/MAX(M$49-M$48,1)*(M$4-M$48)) -> 0 | N84: =IF(N$4<N$48,0,N56+(N70-N56)/MAX(N$49-N$48,1)*(N$4-N$48)) -> 0 | O84: =IF(O$4<O$48,0,O56+(O70-O56)/MAX(O$49-O$48,1)*(O$4-O$48)) -> 0 | P84: =IF(P$4<P$48,0,P56+(P70-P56)/MAX(P$49-P$48,1)*(P$4-P$48)) -> 0 | Q84: =IF(Q$4<Q$48,0,Q56+(Q70-Q56)/MAX(Q$49-Q$48,1)*(Q$4-Q$48)) -> 0 | R84: =IF(R$4<R$48,0,R56+(R70-R56)/MAX(R$49-R$48,1)*(R$4-R$48)) -> 0 | S84: =IF(S$4<S$48,0,S56+(S70-S56)/MAX(S$49-S$48,1)*(S$4-S$48)) -> 0 | T84: =IF(T$4<T$48,0,T56+(T70-T56)/MAX(T$49-T$48,1)*(T$4-T$48)) -> 0 | ... Z84: =IF(Z$4<Z$48,0,Z56+(Z70-Z56)/MAX(Z$49-Z$48,1)*(Z$4-Z$48)) -> 0 | AB84: =LOWER(Settings!$C$4)&".mit."&$A84&IF($C84="","","."&$C84&"."&$B84)&IF(INDEX(Variables!$D$5:$D$65,MATCH($A84,Variables!$A$5:$A$65,0))="","","."&INDEX(Variables!$D$5:$D$65,MATCH($A84,Variables!$A$5:$A$65,0)))&"."&AB$5 -> egy.mit.fpr.res.ecy.2 | AC84: =IF(AC$4<AC$48,0,AC56+(AC70-AC56)/MAX(AC$49-AC$48,1)*(AC$4-AC$48)) -> 0 | AD84: =IF(AD$4<AD$48,0,AD56+(AD70-AD56)/MAX(AD$49-AD$48,1)*(AD$4-AD$48)) -> 0 | AE84: =IF(AE$4<AE$48,0,AE56+(AE70-AE56)/MAX(AE$49-AE$48,1)*(AE$4-AE$48)) -> 0 | AF84: =IF(AF$4<AF$48,0,AF56+(AF70-AF56)/MAX(AF$49-AF$48,1)*(AF$4-AF$48)) -> 0 | AG84: =IF(AG$4<AG$48,0,AG56+(AG70-AG56)/MAX(AG$49-AG$48,1)*(AG$4-AG$48)) -> 0 | AH84: =IF(AH$4<AH$48,0,AH56+(AH70-AH56)/MAX(AH$49-AH$48,1)*(AH$4-AH$48)) -> 0 | AI84: =IF(AI$4<AI$48,0,AI56+(AI70-AI56)/MAX(AI$49-AI$48,1)*(AI$4-AI$48)) -> 0 | AJ84: =IF(AJ$4<AJ$48,0,AJ56+(AJ70-AJ56)/MAX(AJ$49-AJ$48,1)*(AJ$4-AJ$48)) -> 0 | ... AP84: =IF(AP$4<AP$48,0,AP56+(AP70-AP56)/MAX(AP$49-AP$48,1)*(AP$4-AP$48)) -> 0
A85: fpr | B85: ecy | C85: ind | H85: =INDEX(Variables!$B$5:$B$65,MATCH($A85,Variables!$A$5:$A$65,0))&IF($C85="",""," | "&INDEX(Mapping!$B$5:$B$26,MATCH($C85,Mapping!$A$5:$A$26,0))&" | "&INDEX(Mapping!$B$30:$B$41,MATCH($B85,Mapping!$A$30:$A$41,0))) -> Fuel price reform: price increase path | Industry | Electricity | I85: =INDEX(Variables!$C$5:$C$65,MATCH($A85,Variables!$A$5:$A$65,0)) -> price unit | J85: =INDEX(Variables!$E$5:$E$65,MATCH($A85,Variables!$A$5:$A$65,0)) -> Calculation (assumed linear) | L85: =LOWER(Settings!$C$4)&".mit."&$A85&IF($C85="","","."&$C85&"."&$B85)&IF(INDEX(Variables!$D$5:$D$65,MATCH($A85,Variables!$A$5:$A$65,0))="","","."&INDEX(Variables!$D$5:$D$65,MATCH($A85,Variables!$A$5:$A$65,0)))&"."&L$5 -> egy.mit.fpr.ind.ecy.1 | M85: =IF(M$4<M$48,0,M57+(M71-M57)/MAX(M$49-M$48,1)*(M$4-M$48)) -> 0 | N85: =IF(N$4<N$48,0,N57+(N71-N57)/MAX(N$49-N$48,1)*(N$4-N$48)) -> 0 | O85: =IF(O$4<O$48,0,O57+(O71-O57)/MAX(O$49-O$48,1)*(O$4-O$48)) -> 0 | P85: =IF(P$4<P$48,0,P57+(P71-P57)/MAX(P$49-P$48,1)*(P$4-P$48)) -> 0 | Q85: =IF(Q$4<Q$48,0,Q57+(Q71-Q57)/MAX(Q$49-Q$48,1)*(Q$4-Q$48)) -> 0 | R85: =IF(R$4<R$48,0,R57+(R71-R57)/MAX(R$49-R$48,1)*(R$4-R$48)) -> 0 | S85: =IF(S$4<S$48,0,S57+(S71-S57)/MAX(S$49-S$48,1)*(S$4-S$48)) -> 0 | T85: =IF(T$4<T$48,0,T57+(T71-T57)/MAX(T$49-T$48,1)*(T$4-T$48)) -> 0 | ... Z85: =IF(Z$4<Z$48,0,Z57+(Z71-Z57)/MAX(Z$49-Z$48,1)*(Z$4-Z$48)) -> 0 | AB85: =LOWER(Settings!$C$4)&".mit."&$A85&IF($C85="","","."&$C85&"."&$B85)&IF(INDEX(Variables!$D$5:$D$65,MATCH($A85,Variables!$A$5:$A$65,0))="","","."&INDEX(Variables!$D$5:$D$65,MATCH($A85,Variables!$A$5:$A$65,0)))&"."&AB$5 -> egy.mit.fpr.ind.ecy.2 | AC85: =IF(AC$4<AC$48,0,AC57+(AC71-AC57)/MAX(AC$49-AC$48,1)*(AC$4-AC$48)) -> 0 | AD85: =IF(AD$4<AD$48,0,AD57+(AD71-AD57)/MAX(AD$49-AD$48,1)*(AD$4-AD$48)) -> 0 | AE85: =IF(AE$4<AE$48,0,AE57+(AE71-AE57)/MAX(AE$49-AE$48,1)*(AE$4-AE$48)) -> 0 | AF85: =IF(AF$4<AF$48,0,AF57+(AF71-AF57)/MAX(AF$49-AF$48,1)*(AF$4-AF$48)) -> 0 | AG85: =IF(AG$4<AG$48,0,AG57+(AG71-AG57)/MAX(AG$49-AG$48,1)*(AG$4-AG$48)) -> 0 | AH85: =IF(AH$4<AH$48,0,AH57+(AH71-AH57)/MAX(AH$49-AH$48,1)*(AH$4-AH$48)) -> 0 | AI85: =IF(AI$4<AI$48,0,AI57+(AI71-AI57)/MAX(AI$49-AI$48,1)*(AI$4-AI$48)) -> 0 | AJ85: =IF(AJ$4<AJ$48,0,AJ57+(AJ71-AJ57)/MAX(AJ$49-AJ$48,1)*(AJ$4-AJ$48)) -> 0 | ... AP85: =IF(AP$4<AP$48,0,AP57+(AP71-AP57)/MAX(AP$49-AP$48,1)*(AP$4-AP$48)) -> 0
A86: fpr | B86: gso | C86: all | H86: =INDEX(Variables!$B$5:$B$65,MATCH($A86,Variables!$A$5:$A$65,0))&IF($C86="",""," | "&INDEX(Mapping!$B$5:$B$26,MATCH($C86,Mapping!$A$5:$A$26,0))&" | "&INDEX(Mapping!$B$30:$B$41,MATCH($B86,Mapping!$A$30:$A$41,0))) -> Fuel price reform: price increase path | All subsectors | Gasoline | I86: =INDEX(Variables!$C$5:$C$65,MATCH($A86,Variables!$A$5:$A$65,0)) -> price unit | J86: =INDEX(Variables!$E$5:$E$65,MATCH($A86,Variables!$A$5:$A$65,0)) -> Calculation (assumed linear) | L86: =LOWER(Settings!$C$4)&".mit."&$A86&IF($C86="","","."&$C86&"."&$B86)&IF(INDEX(Variables!$D$5:$D$65,MATCH($A86,Variables!$A$5:$A$65,0))="","","."&INDEX(Variables!$D$5:$D$65,MATCH($A86,Variables!$A$5:$A$65,0)))&"."&L$5 -> egy.mit.fpr.all.gso.1 | M86: =IF(M$4<M$48,0,M58+(M72-M58)/MAX(M$49-M$48,1)*(M$4-M$48)) -> 0 | N86: =IF(N$4<N$48,0,N58+(N72-N58)/MAX(N$49-N$48,1)*(N$4-N$48)) -> 0 | O86: =IF(O$4<O$48,0,O58+(O72-O58)/MAX(O$49-O$48,1)*(O$4-O$48)) -> 0 | P86: =IF(P$4<P$48,0,P58+(P72-P58)/MAX(P$49-P$48,1)*(P$4-P$48)) -> 0 | Q86: =IF(Q$4<Q$48,0,Q58+(Q72-Q58)/MAX(Q$49-Q$48,1)*(Q$4-Q$48)) -> 0 | R86: =IF(R$4<R$48,0,R58+(R72-R58)/MAX(R$49-R$48,1)*(R$4-R$48)) -> 0 | S86: =IF(S$4<S$48,0,S58+(S72-S58)/MAX(S$49-S$48,1)*(S$4-S$48)) -> 0 | T86: =IF(T$4<T$48,0,T58+(T72-T58)/MAX(T$49-T$48,1)*(T$4-T$48)) -> 0 | ... Z86: =IF(Z$4<Z$48,0,Z58+(Z72-Z58)/MAX(Z$49-Z$48,1)*(Z$4-Z$48)) -> 0 | AB86: =LOWER(Settings!$C$4)&".mit."&$A86&IF($C86="","","."&$C86&"."&$B86)&IF(INDEX(Variables!$D$5:$D$65,MATCH($A86,Variables!$A$5:$A$65,0))="","","."&INDEX(Variables!$D$5:$D$65,MATCH($A86,Variables!$A$5:$A$65,0)))&"."&AB$5 -> egy.mit.fpr.all.gso.2 | AC86: =IF(AC$4<AC$48,0,AC58+(AC72-AC58)/MAX(AC$49-AC$48,1)*(AC$4-AC$48)) -> 0 | AD86: =IF(AD$4<AD$48,0,AD58+(AD72-AD58)/MAX(AD$49-AD$48,1)*(AD$4-AD$48)) -> 0 | AE86: =IF(AE$4<AE$48,0,AE58+(AE72-AE58)/MAX(AE$49-AE$48,1)*(AE$4-AE$48)) -> 0 | AF86: =IF(AF$4<AF$48,0,AF58+(AF72-AF58)/MAX(AF$49-AF$48,1)*(AF$4-AF$48)) -> 0 | AG86: =IF(AG$4<AG$48,0,AG58+(AG72-AG58)/MAX(AG$49-AG$48,1)*(AG$4-AG$48)) -> 0 | AH86: =IF(AH$4<AH$48,0,AH58+(AH72-AH58)/MAX(AH$49-AH$48,1)*(AH$4-AH$48)) -> 0 | AI86: =IF(AI$4<AI$48,0,AI58+(AI72-AI58)/MAX(AI$49-AI$48,1)*(AI$4-AI$48)) -> 0 | AJ86: =IF(AJ$4<AJ$48,0,AJ58+(AJ72-AJ58)/MAX(AJ$49-AJ$48,1)*(AJ$4-AJ$48)) -> 0 | ... AP86: =IF(AP$4<AP$48,0,AP58+(AP72-AP58)/MAX(AP$49-AP$48,1)*(AP$4-AP$48)) -> 0
A87: fpr | B87: die | C87: all | H87: =INDEX(Variables!$B$5:$B$65,MATCH($A87,Variables!$A$5:$A$65,0))&IF($C87="",""," | "&INDEX(Mapping!$B$5:$B$26,MATCH($C87,Mapping!$A$5:$A$26,0))&" | "&INDEX(Mapping!$B$30:$B$41,MATCH($B87,Mapping!$A$30:$A$41,0))) -> Fuel price reform: price increase path | All subsectors | Diesel | I87: =INDEX(Variables!$C$5:$C$65,MATCH($A87,Variables!$A$5:$A$65,0)) -> price unit | J87: =INDEX(Variables!$E$5:$E$65,MATCH($A87,Variables!$A$5:$A$65,0)) -> Calculation (assumed linear) | L87: =LOWER(Settings!$C$4)&".mit."&$A87&IF($C87="","","."&$C87&"."&$B87)&IF(INDEX(Variables!$D$5:$D$65,MATCH($A87,Variables!$A$5:$A$65,0))="","","."&INDEX(Variables!$D$5:$D$65,MATCH($A87,Variables!$A$5:$A$65,0)))&"."&L$5 -> egy.mit.fpr.all.die.1 | M87: =IF(M$4<M$48,0,M59+(M73-M59)/MAX(M$49-M$48,1)*(M$4-M$48)) -> 0 | N87: =IF(N$4<N$48,0,N59+(N73-N59)/MAX(N$49-N$48,1)*(N$4-N$48)) -> 0 | O87: =IF(O$4<O$48,0,O59+(O73-O59)/MAX(O$49-O$48,1)*(O$4-O$48)) -> 0 | P87: =IF(P$4<P$48,0,P59+(P73-P59)/MAX(P$49-P$48,1)*(P$4-P$48)) -> 0 | Q87: =IF(Q$4<Q$48,0,Q59+(Q73-Q59)/MAX(Q$49-Q$48,1)*(Q$4-Q$48)) -> 0 | R87: =IF(R$4<R$48,0,R59+(R73-R59)/MAX(R$49-R$48,1)*(R$4-R$48)) -> 0 | S87: =IF(S$4<S$48,0,S59+(S73-S59)/MAX(S$49-S$48,1)*(S$4-S$48)) -> 0 | T87: =IF(T$4<T$48,0,T59+(T73-T59)/MAX(T$49-T$48,1)*(T$4-T$48)) -> 0 | ... Z87: =IF(Z$4<Z$48,0,Z59+(Z73-Z59)/MAX(Z$49-Z$48,1)*(Z$4-Z$48)) -> 0 | AB87: =LOWER(Settings!$C$4)&".mit."&$A87&IF($C87="","","."&$C87&"."&$B87)&IF(INDEX(Variables!$D$5:$D$65,MATCH($A87,Variables!$A$5:$A$65,0))="","","."&INDEX(Variables!$D$5:$D$65,MATCH($A87,Variables!$A$5:$A$65,0)))&"."&AB$5 -> egy.mit.fpr.all.die.2 | AC87: =IF(AC$4<AC$48,0,AC59+(AC73-AC59)/MAX(AC$49-AC$48,1)*(AC$4-AC$48)) -> 0 | AD87: =IF(AD$4<AD$48,0,AD59+(AD73-AD59)/MAX(AD$49-AD$48,1)*(AD$4-AD$48)) -> 0 | AE87: =IF(AE$4<AE$48,0,AE59+(AE73-AE59)/MAX(AE$49-AE$48,1)*(AE$4-AE$48)) -> 0 | AF87: =IF(AF$4<AF$48,0,AF59+(AF73-AF59)/MAX(AF$49-AF$48,1)*(AF$4-AF$48)) -> 0 | AG87: =IF(AG$4<AG$48,0,AG59+(AG73-AG59)/MAX(AG$49-AG$48,1)*(AG$4-AG$48)) -> 0 | AH87: =IF(AH$4<AH$48,0,AH59+(AH73-AH59)/MAX(AH$49-AH$48,1)*(AH$4-AH$48)) -> 0 | AI87: =IF(AI$4<AI$48,0,AI59+(AI73-AI59)/MAX(AI$49-AI$48,1)*(AI$4-AI$48)) -> 0 | AJ87: =IF(AJ$4<AJ$48,0,AJ59+(AJ73-AJ59)/MAX(AJ$49-AJ$48,1)*(AJ$4-AJ$48)) -> 0 | ... AP87: =IF(AP$4<AP$48,0,AP59+(AP73-AP59)/MAX(AP$49-AP$48,1)*(AP$4-AP$48)) -> 0
A88: fpr | B88: lpg | C88: all | H88: =INDEX(Variables!$B$5:$B$65,MATCH($A88,Variables!$A$5:$A$65,0))&IF($C88="",""," | "&INDEX(Mapping!$B$5:$B$26,MATCH($C88,Mapping!$A$5:$A$26,0))&" | "&INDEX(Mapping!$B$30:$B$41,MATCH($B88,Mapping!$A$30:$A$41,0))) -> Fuel price reform: price increase path | All subsectors | LPG | I88: =INDEX(Variables!$C$5:$C$65,MATCH($A88,Variables!$A$5:$A$65,0)) -> price unit | J88: =INDEX(Variables!$E$5:$E$65,MATCH($A88,Variables!$A$5:$A$65,0)) -> Calculation (assumed linear) | L88: =LOWER(Settings!$C$4)&".mit."&$A88&IF($C88="","","."&$C88&"."&$B88)&IF(INDEX(Variables!$D$5:$D$65,MATCH($A88,Variables!$A$5:$A$65,0))="","","."&INDEX(Variables!$D$5:$D$65,MATCH($A88,Variables!$A$5:$A$65,0)))&"."&L$5 -> egy.mit.fpr.all.lpg.1 | M88: =IF(M$4<M$48,0,M60+(M74-M60)/MAX(M$49-M$48,1)*(M$4-M$48)) -> 0 | N88: =IF(N$4<N$48,0,N60+(N74-N60)/MAX(N$49-N$48,1)*(N$4-N$48)) -> 0 | O88: =IF(O$4<O$48,0,O60+(O74-O60)/MAX(O$49-O$48,1)*(O$4-O$48)) -> 0 | P88: =IF(P$4<P$48,0,P60+(P74-P60)/MAX(P$49-P$48,1)*(P$4-P$48)) -> 0 | Q88: =IF(Q$4<Q$48,0,Q60+(Q74-Q60)/MAX(Q$49-Q$48,1)*(Q$4-Q$48)) -> 0 | R88: =IF(R$4<R$48,0,R60+(R74-R60)/MAX(R$49-R$48,1)*(R$4-R$48)) -> 0 | S88: =IF(S$4<S$48,0,S60+(S74-S60)/MAX(S$49-S$48,1)*(S$4-S$48)) -> 0 | T88: =IF(T$4<T$48,0,T60+(T74-T60)/MAX(T$49-T$48,1)*(T$4-T$48)) -> 0 | ... Z88: =IF(Z$4<Z$48,0,Z60+(Z74-Z60)/MAX(Z$49-Z$48,1)*(Z$4-Z$48)) -> 0 | AB88: =LOWER(Settings!$C$4)&".mit."&$A88&IF($C88="","","."&$C88&"."&$B88)&IF(INDEX(Variables!$D$5:$D$65,MATCH($A88,Variables!$A$5:$A$65,0))="","","."&INDEX(Variables!$D$5:$D$65,MATCH($A88,Variables!$A$5:$A$65,0)))&"."&AB$5 -> egy.mit.fpr.all.lpg.2 | AC88: =IF(AC$4<AC$48,0,AC60+(AC74-AC60)/MAX(AC$49-AC$48,1)*(AC$4-AC$48)) -> 0 | AD88: =IF(AD$4<AD$48,0,AD60+(AD74-AD60)/MAX(AD$49-AD$48,1)*(AD$4-AD$48)) -> 0 | AE88: =IF(AE$4<AE$48,0,AE60+(AE74-AE60)/MAX(AE$49-AE$48,1)*(AE$4-AE$48)) -> 0 | AF88: =IF(AF$4<AF$48,0,AF60+(AF74-AF60)/MAX(AF$49-AF$48,1)*(AF$4-AF$48)) -> 0 | AG88: =IF(AG$4<AG$48,0,AG60+(AG74-AG60)/MAX(AG$49-AG$48,1)*(AG$4-AG$48)) -> 0 | AH88: =IF(AH$4<AH$48,0,AH60+(AH74-AH60)/MAX(AH$49-AH$48,1)*(AH$4-AH$48)) -> 0 | AI88: =IF(AI$4<AI$48,0,AI60+(AI74-AI60)/MAX(AI$49-AI$48,1)*(AI$4-AI$48)) -> 0 | AJ88: =IF(AJ$4<AJ$48,0,AJ60+(AJ74-AJ60)/MAX(AJ$49-AJ$48,1)*(AJ$4-AJ$48)) -> 0 | ... AP88: =IF(AP$4<AP$48,0,AP60+(AP74-AP60)/MAX(AP$49-AP$48,1)*(AP$4-AP$48)) -> 0
A89: fpr | B89: ker | C89: all | H89: =INDEX(Variables!$B$5:$B$65,MATCH($A89,Variables!$A$5:$A$65,0))&IF($C89="",""," | "&INDEX(Mapping!$B$5:$B$26,MATCH($C89,Mapping!$A$5:$A$26,0))&" | "&INDEX(Mapping!$B$30:$B$41,MATCH($B89,Mapping!$A$30:$A$41,0))) -> Fuel price reform: price increase path | All subsectors | Kerosene | I89: =INDEX(Variables!$C$5:$C$65,MATCH($A89,Variables!$A$5:$A$65,0)) -> price unit | J89: =INDEX(Variables!$E$5:$E$65,MATCH($A89,Variables!$A$5:$A$65,0)) -> Calculation (assumed linear) | L89: =LOWER(Settings!$C$4)&".mit."&$A89&IF($C89="","","."&$C89&"."&$B89)&IF(INDEX(Variables!$D$5:$D$65,MATCH($A89,Variables!$A$5:$A$65,0))="","","."&INDEX(Variables!$D$5:$D$65,MATCH($A89,Variables!$A$5:$A$65,0)))&"."&L$5 -> egy.mit.fpr.all.ker.1 | M89: =IF(M$4<M$48,0,M61+(M75-M61)/MAX(M$49-M$48,1)*(M$4-M$48)) -> 0 | N89: =IF(N$4<N$48,0,N61+(N75-N61)/MAX(N$49-N$48,1)*(N$4-N$48)) -> 0 | O89: =IF(O$4<O$48,0,O61+(O75-O61)/MAX(O$49-O$48,1)*(O$4-O$48)) -> 0 | P89: =IF(P$4<P$48,0,P61+(P75-P61)/MAX(P$49-P$48,1)*(P$4-P$48)) -> 0 | Q89: =IF(Q$4<Q$48,0,Q61+(Q75-Q61)/MAX(Q$49-Q$48,1)*(Q$4-Q$48)) -> 0 | R89: =IF(R$4<R$48,0,R61+(R75-R61)/MAX(R$49-R$48,1)*(R$4-R$48)) -> 0 | S89: =IF(S$4<S$48,0,S61+(S75-S61)/MAX(S$49-S$48,1)*(S$4-S$48)) -> 0 | T89: =IF(T$4<T$48,0,T61+(T75-T61)/MAX(T$49-T$48,1)*(T$4-T$48)) -> 0 | ... Z89: =IF(Z$4<Z$48,0,Z61+(Z75-Z61)/MAX(Z$49-Z$48,1)*(Z$4-Z$48)) -> 0 | AB89: =LOWER(Settings!$C$4)&".mit."&$A89&IF($C89="","","."&$C89&"."&$B89)&IF(INDEX(Variables!$D$5:$D$65,MATCH($A89,Variables!$A$5:$A$65,0))="","","."&INDEX(Variables!$D$5:$D$65,MATCH($A89,Variables!$A$5:$A$65,0)))&"."&AB$5 -> egy.mit.fpr.all.ker.2 | AC89: =IF(AC$4<AC$48,0,AC61+(AC75-AC61)/MAX(AC$49-AC$48,1)*(AC$4-AC$48)) -> 0 | AD89: =IF(AD$4<AD$48,0,AD61+(AD75-AD61)/MAX(AD$49-AD$48,1)*(AD$4-AD$48)) -> 0 | AE89: =IF(AE$4<AE$48,0,AE61+(AE75-AE61)/MAX(AE$49-AE$48,1)*(AE$4-AE$48)) -> 0 | AF89: =IF(AF$4<AF$48,0,AF61+(AF75-AF61)/MAX(AF$49-AF$48,1)*(AF$4-AF$48)) -> 0 | AG89: =IF(AG$4<AG$48,0,AG61+(AG75-AG61)/MAX(AG$49-AG$48,1)*(AG$4-AG$48)) -> 0 | AH89: =IF(AH$4<AH$48,0,AH61+(AH75-AH61)/MAX(AH$49-AH$48,1)*(AH$4-AH$48)) -> 0 | AI89: =IF(AI$4<AI$48,0,AI61+(AI75-AI61)/MAX(AI$49-AI$48,1)*(AI$4-AI$48)) -> 0 | AJ89: =IF(AJ$4<AJ$48,0,AJ61+(AJ75-AJ61)/MAX(AJ$49-AJ$48,1)*(AJ$4-AJ$48)) -> 0 | ... AP89: =IF(AP$4<AP$48,0,AP61+(AP75-AP61)/MAX(AP$49-AP$48,1)*(AP$4-AP$48)) -> 0
... A91: fpr | B91: bio | C91: all | H91: =INDEX(Variables!$B$5:$B$65,MATCH($A91,Variables!$A$5:$A$65,0))&IF($C91="",""," | "&INDEX(Mapping!$B$5:$B$26,MATCH($C91,Mapping!$A$5:$A$26,0))&" | "&INDEX(Mapping!$B$30:$B$41,MATCH($B91,Mapping!$A$30:$A$41,0))) -> Fuel price reform: price increase path | All subsectors | Biomass | I91: =INDEX(Variables!$C$5:$C$65,MATCH($A91,Variables!$A$5:$A$65,0)) -> price unit | J91: =INDEX(Variables!$E$5:$E$65,MATCH($A91,Variables!$A$5:$A$65,0)) -> Calculation (assumed linear) | L91: =LOWER(Settings!$C$4)&".mit."&$A91&IF($C91="","","."&$C91&"."&$B91)&IF(INDEX(Variables!$D$5:$D$65,MATCH($A91,Variables!$A$5:$A$65,0))="","","."&INDEX(Variables!$D$5:$D$65,MATCH($A91,Variables!$A$5:$A$65,0)))&"."&L$5 -> egy.mit.fpr.all.bio.1 | M91: =IF(M$4<M$48,0,M63+(M77-M63)/MAX(M$49-M$48,1)*(M$4-M$48)) -> 0 | N91: =IF(N$4<N$48,0,N63+(N77-N63)/MAX(N$49-N$48,1)*(N$4-N$48)) -> 0 | O91: =IF(O$4<O$48,0,O63+(O77-O63)/MAX(O$49-O$48,1)*(O$4-O$48)) -> 0 | P91: =IF(P$4<P$48,0,P63+(P77-P63)/MAX(P$49-P$48,1)*(P$4-P$48)) -> 0 | Q91: =IF(Q$4<Q$48,0,Q63+(Q77-Q63)/MAX(Q$49-Q$48,1)*(Q$4-Q$48)) -> 0 | R91: =IF(R$4<R$48,0,R63+(R77-R63)/MAX(R$49-R$48,1)*(R$4-R$48)) -> 0 | S91: =IF(S$4<S$48,0,S63+(S77-S63)/MAX(S$49-S$48,1)*(S$4-S$48)) -> 0 | T91: =IF(T$4<T$48,0,T63+(T77-T63)/MAX(T$49-T$48,1)*(T$4-T$48)) -> 0 | ... Z91: =IF(Z$4<Z$48,0,Z63+(Z77-Z63)/MAX(Z$49-Z$48,1)*(Z$4-Z$48)) -> 0 | AB91: =LOWER(Settings!$C$4)&".mit."&$A91&IF($C91="","","."&$C91&"."&$B91)&IF(INDEX(Variables!$D$5:$D$65,MATCH($A91,Variables!$A$5:$A$65,0))="","","."&INDEX(Variables!$D$5:$D$65,MATCH($A91,Variables!$A$5:$A$65,0)))&"."&AB$5 -> egy.mit.fpr.all.bio.2 | AC91: =IF(AC$4<AC$48,0,AC63+(AC77-AC63)/MAX(AC$49-AC$48,1)*(AC$4-AC$48)) -> 0 | AD91: =IF(AD$4<AD$48,0,AD63+(AD77-AD63)/MAX(AD$49-AD$48,1)*(AD$4-AD$48)) -> 0 | AE91: =IF(AE$4<AE$48,0,AE63+(AE77-AE63)/MAX(AE$49-AE$48,1)*(AE$4-AE$48)) -> 0 | AF91: =IF(AF$4<AF$48,0,AF63+(AF77-AF63)/MAX(AF$49-AF$48,1)*(AF$4-AF$48)) -> 0 | AG91: =IF(AG$4<AG$48,0,AG63+(AG77-AG63)/MAX(AG$49-AG$48,1)*(AG$4-AG$48)) -> 0 | AH91: =IF(AH$4<AH$48,0,AH63+(AH77-AH63)/MAX(AH$49-AH$48,1)*(AH$4-AH$48)) -> 0 | AI91: =IF(AI$4<AI$48,0,AI63+(AI77-AI63)/MAX(AI$49-AI$48,1)*(AI$4-AI$48)) -> 0 | AJ91: =IF(AJ$4<AJ$48,0,AJ63+(AJ77-AJ63)/MAX(AJ$49-AJ$48,1)*(AJ$4-AJ$48)) -> 0 | ... AP91: =IF(AP$4<AP$48,0,AP63+(AP77-AP63)/MAX(AP$49-AP$48,1)*(AP$4-AP$48)) -> 0
H92: Feebates (MTInputs rows 53-64; rates in USD/tCO2)
A93: fb.yr0 | D93: 53 | H93: =INDEX(Variables!$B$5:$B$65,MATCH($A93,Variables!$A$5:$A$65,0))&IF($C93="",""," | "&INDEX(Mapping!$B$5:$B$26,MATCH($C93,Mapping!$A$5:$A$26,0))&" | "&INDEX(Mapping!$B$30:$B$41,MATCH($B93,Mapping!$A$30:$A$41,0))) -> Feebates: start date | I93: =INDEX(Variables!$C$5:$C$65,MATCH($A93,Variables!$A$5:$A$65,0)) -> year | J93: =INDEX(Variables!$E$5:$E$65,MATCH($A93,Variables!$A$5:$A$65,0)) -> MTInputs (scenario column) | L93: =LOWER(Settings!$C$4)&".mit."&$A93&IF($C93="","","."&$C93&"."&$B93)&IF(INDEX(Variables!$D$5:$D$65,MATCH($A93,Variables!$A$5:$A$65,0))="","","."&INDEX(Variables!$D$5:$D$65,MATCH($A93,Variables!$A$5:$A$65,0)))&"."&L$5 -> egy.mit.fb.yr0.1 | M93: =INDEX(MTInputs!$J$1:$AZ$415,$D93,MATCH(M$5,MTInputs!$J$5:$AZ$5,0)) -> 2027 | N93: =INDEX(MTInputs!$J$1:$AZ$415,$D93,MATCH(N$5,MTInputs!$J$5:$AZ$5,0)) -> 2027 | O93: =INDEX(MTInputs!$J$1:$AZ$415,$D93,MATCH(O$5,MTInputs!$J$5:$AZ$5,0)) -> 2027 | P93: =INDEX(MTInputs!$J$1:$AZ$415,$D93,MATCH(P$5,MTInputs!$J$5:$AZ$5,0)) -> 2027 | Q93: =INDEX(MTInputs!$J$1:$AZ$415,$D93,MATCH(Q$5,MTInputs!$J$5:$AZ$5,0)) -> 2027 | R93: =INDEX(MTInputs!$J$1:$AZ$415,$D93,MATCH(R$5,MTInputs!$J$5:$AZ$5,0)) -> 2027 | S93: =INDEX(MTInputs!$J$1:$AZ$415,$D93,MATCH(S$5,MTInputs!$J$5:$AZ$5,0)) -> 2027 | T93: =INDEX(MTInputs!$J$1:$AZ$415,$D93,MATCH(T$5,MTInputs!$J$5:$AZ$5,0)) -> 2027 | ... Z93: =INDEX(MTInputs!$J$1:$AZ$415,$D93,MATCH(Z$5,MTInputs!$J$5:$AZ$5,0)) -> 2027 | AB93: =LOWER(Settings!$C$4)&".mit."&$A93&IF($C93="","","."&$C93&"."&$B93)&IF(INDEX(Variables!$D$5:$D$65,MATCH($A93,Variables!$A$5:$A$65,0))="","","."&INDEX(Variables!$D$5:$D$65,MATCH($A93,Variables!$A$5:$A$65,0)))&"."&AB$5 -> egy.mit.fb.yr0.2 | AC93: =INDEX(MTInputs!$J$1:$AZ$415,$D93,MATCH(AC$5,MTInputs!$J$5:$AZ$5,0)) -> 2027 | AD93: =INDEX(MTInputs!$J$1:$AZ$415,$D93,MATCH(AD$5,MTInputs!$J$5:$AZ$5,0)) -> 2027 | AE93: =INDEX(MTInputs!$J$1:$AZ$415,$D93,MATCH(AE$5,MTInputs!$J$5:$AZ$5,0)) -> 2027 | AF93: =INDEX(MTInputs!$J$1:$AZ$415,$D93,MATCH(AF$5,MTInputs!$J$5:$AZ$5,0)) -> 2027 | AG93: =INDEX(MTInputs!$J$1:$AZ$415,$D93,MATCH(AG$5,MTInputs!$J$5:$AZ$5,0)) -> 2027 | AH93: =INDEX(MTInputs!$J$1:$AZ$415,$D93,MATCH(AH$5,MTInputs!$J$5:$AZ$5,0)) -> 2027 | AI93: =INDEX(MTInputs!$J$1:$AZ$415,$D93,MATCH(AI$5,MTInputs!$J$5:$AZ$5,0)) -> 2027 | AJ93: =INDEX(MTInputs!$J$1:$AZ$415,$D93,MATCH(AJ$5,MTInputs!$J$5:$AZ$5,0)) -> 2027 | ... AP93: =INDEX(MTInputs!$J$1:$AZ$415,$D93,MATCH(AP$5,MTInputs!$J$5:$AZ$5,0)) -> 2027
A94: fb.yr1 | D94: 54 | H94: =INDEX(Variables!$B$5:$B$65,MATCH($A94,Variables!$A$5:$A$65,0))&IF($C94="",""," | "&INDEX(Mapping!$B$5:$B$26,MATCH($C94,Mapping!$A$5:$A$26,0))&" | "&INDEX(Mapping!$B$30:$B$41,MATCH($B94,Mapping!$A$30:$A$41,0))) -> Feebates: target date | I94: =INDEX(Variables!$C$5:$C$65,MATCH($A94,Variables!$A$5:$A$65,0)) -> year | J94: =INDEX(Variables!$E$5:$E$65,MATCH($A94,Variables!$A$5:$A$65,0)) -> MTInputs (scenario column) | L94: =LOWER(Settings!$C$4)&".mit."&$A94&IF($C94="","","."&$C94&"."&$B94)&IF(INDEX(Variables!$D$5:$D$65,MATCH($A94,Variables!$A$5:$A$65,0))="","","."&INDEX(Variables!$D$5:$D$65,MATCH($A94,Variables!$A$5:$A$65,0)))&"."&L$5 -> egy.mit.fb.yr1.1 | M94: =INDEX(MTInputs!$J$1:$AZ$415,$D94,MATCH(M$5,MTInputs!$J$5:$AZ$5,0)) -> 2035 | N94: =INDEX(MTInputs!$J$1:$AZ$415,$D94,MATCH(N$5,MTInputs!$J$5:$AZ$5,0)) -> 2035 | O94: =INDEX(MTInputs!$J$1:$AZ$415,$D94,MATCH(O$5,MTInputs!$J$5:$AZ$5,0)) -> 2035 | P94: =INDEX(MTInputs!$J$1:$AZ$415,$D94,MATCH(P$5,MTInputs!$J$5:$AZ$5,0)) -> 2035 | Q94: =INDEX(MTInputs!$J$1:$AZ$415,$D94,MATCH(Q$5,MTInputs!$J$5:$AZ$5,0)) -> 2035 | R94: =INDEX(MTInputs!$J$1:$AZ$415,$D94,MATCH(R$5,MTInputs!$J$5:$AZ$5,0)) -> 2035 | S94: =INDEX(MTInputs!$J$1:$AZ$415,$D94,MATCH(S$5,MTInputs!$J$5:$AZ$5,0)) -> 2035 | T94: =INDEX(MTInputs!$J$1:$AZ$415,$D94,MATCH(T$5,MTInputs!$J$5:$AZ$5,0)) -> 2035 | ... Z94: =INDEX(MTInputs!$J$1:$AZ$415,$D94,MATCH(Z$5,MTInputs!$J$5:$AZ$5,0)) -> 2035 | AB94: =LOWER(Settings!$C$4)&".mit."&$A94&IF($C94="","","."&$C94&"."&$B94)&IF(INDEX(Variables!$D$5:$D$65,MATCH($A94,Variables!$A$5:$A$65,0))="","","."&INDEX(Variables!$D$5:$D$65,MATCH($A94,Variables!$A$5:$A$65,0)))&"."&AB$5 -> egy.mit.fb.yr1.2 | AC94: =INDEX(MTInputs!$J$1:$AZ$415,$D94,MATCH(AC$5,MTInputs!$J$5:$AZ$5,0)) -> 2035 | AD94: =INDEX(MTInputs!$J$1:$AZ$415,$D94,MATCH(AD$5,MTInputs!$J$5:$AZ$5,0)) -> 2035 | AE94: =INDEX(MTInputs!$J$1:$AZ$415,$D94,MATCH(AE$5,MTInputs!$J$5:$AZ$5,0)) -> 2035 | AF94: =INDEX(MTInputs!$J$1:$AZ$415,$D94,MATCH(AF$5,MTInputs!$J$5:$AZ$5,0)) -> 2035 | AG94: =INDEX(MTInputs!$J$1:$AZ$415,$D94,MATCH(AG$5,MTInputs!$J$5:$AZ$5,0)) -> 2035 | AH94: =INDEX(MTInputs!$J$1:$AZ$415,$D94,MATCH(AH$5,MTInputs!$J$5:$AZ$5,0)) -> 2035 | AI94: =INDEX(MTInputs!$J$1:$AZ$415,$D94,MATCH(AI$5,MTInputs!$J$5:$AZ$5,0)) -> 2035 | AJ94: =INDEX(MTInputs!$J$1:$AZ$415,$D94,MATCH(AJ$5,MTInputs!$J$5:$AZ$5,0)) -> 2035 | ... AP94: =INDEX(MTInputs!$J$1:$AZ$415,$D94,MATCH(AP$5,MTInputs!$J$5:$AZ$5,0)) -> 2035
A95: fb.s | B95: all | C95: pow | D95: 56 | H95: =INDEX(Variables!$B$5:$B$65,MATCH($A95,Variables!$A$5:$A$65,0))&IF($C95="",""," | "&INDEX(Mapping!$B$5:$B$26,MATCH($C95,Mapping!$A$5:$A$26,0))&" | "&INDEX(Mapping!$B$30:$B$41,MATCH($B95,Mapping!$A$30:$A$41,0))) -> Feebates: starting rate | Power | All fuels | I95: =INDEX(Variables!$C$5:$C$65,MATCH($A95,Variables!$A$5:$A$65,0)) -> USD/tCO2 | J95: =INDEX(Variables!$E$5:$E$65,MATCH($A95,Variables!$A$5:$A$65,0)) -> MTInputs (scenario column) | L95: =LOWER(Settings!$C$4)&".mit."&$A95&IF($C95="","","."&$C95&"."&$B95)&IF(INDEX(Variables!$D$5:$D$65,MATCH($A95,Variables!$A$5:$A$65,0))="","","."&INDEX(Variables!$D$5:$D$65,MATCH($A95,Variables!$A$5:$A$65,0)))&"."&L$5 -> egy.mit.fb.s.pow.all.1 | M95: =INDEX(MTInputs!$J$1:$AZ$415,$D95,MATCH(M$5,MTInputs!$J$5:$AZ$5,0)) -> 0 | N95: =INDEX(MTInputs!$J$1:$AZ$415,$D95,MATCH(N$5,MTInputs!$J$5:$AZ$5,0)) -> 0 | O95: =INDEX(MTInputs!$J$1:$AZ$415,$D95,MATCH(O$5,MTInputs!$J$5:$AZ$5,0)) -> 0 | P95: =INDEX(MTInputs!$J$1:$AZ$415,$D95,MATCH(P$5,MTInputs!$J$5:$AZ$5,0)) -> 0 | Q95: =INDEX(MTInputs!$J$1:$AZ$415,$D95,MATCH(Q$5,MTInputs!$J$5:$AZ$5,0)) -> 0 | R95: =INDEX(MTInputs!$J$1:$AZ$415,$D95,MATCH(R$5,MTInputs!$J$5:$AZ$5,0)) -> 0 | S95: =INDEX(MTInputs!$J$1:$AZ$415,$D95,MATCH(S$5,MTInputs!$J$5:$AZ$5,0)) -> 0 | T95: =INDEX(MTInputs!$J$1:$AZ$415,$D95,MATCH(T$5,MTInputs!$J$5:$AZ$5,0)) -> 0 | ... Z95: =INDEX(MTInputs!$J$1:$AZ$415,$D95,MATCH(Z$5,MTInputs!$J$5:$AZ$5,0)) -> 0 | AB95: =LOWER(Settings!$C$4)&".mit."&$A95&IF($C95="","","."&$C95&"."&$B95)&IF(INDEX(Variables!$D$5:$D$65,MATCH($A95,Variables!$A$5:$A$65,0))="","","."&INDEX(Variables!$D$5:$D$65,MATCH($A95,Variables!$A$5:$A$65,0)))&"."&AB$5 -> egy.mit.fb.s.pow.all.2 | AC95: =INDEX(MTInputs!$J$1:$AZ$415,$D95,MATCH(AC$5,MTInputs!$J$5:$AZ$5,0)) -> 0 | AD95: =INDEX(MTInputs!$J$1:$AZ$415,$D95,MATCH(AD$5,MTInputs!$J$5:$AZ$5,0)) -> 0 | AE95: =INDEX(MTInputs!$J$1:$AZ$415,$D95,MATCH(AE$5,MTInputs!$J$5:$AZ$5,0)) -> 0 | AF95: =INDEX(MTInputs!$J$1:$AZ$415,$D95,MATCH(AF$5,MTInputs!$J$5:$AZ$5,0)) -> 0 | AG95: =INDEX(MTInputs!$J$1:$AZ$415,$D95,MATCH(AG$5,MTInputs!$J$5:$AZ$5,0)) -> 0 | AH95: =INDEX(MTInputs!$J$1:$AZ$415,$D95,MATCH(AH$5,MTInputs!$J$5:$AZ$5,0)) -> 0 | AI95: =INDEX(MTInputs!$J$1:$AZ$415,$D95,MATCH(AI$5,MTInputs!$J$5:$AZ$5,0)) -> 0 | AJ95: =INDEX(MTInputs!$J$1:$AZ$415,$D95,MATCH(AJ$5,MTInputs!$J$5:$AZ$5,0)) -> 0 | ... AP95: =INDEX(MTInputs!$J$1:$AZ$415,$D95,MATCH(AP$5,MTInputs!$J$5:$AZ$5,0)) -> 0
A96: fb.s | B96: all | C96: tra | D96: 57 | H96: =INDEX(Variables!$B$5:$B$65,MATCH($A96,Variables!$A$5:$A$65,0))&IF($C96="",""," | "&INDEX(Mapping!$B$5:$B$26,MATCH($C96,Mapping!$A$5:$A$26,0))&" | "&INDEX(Mapping!$B$30:$B$41,MATCH($B96,Mapping!$A$30:$A$41,0))) -> Feebates: starting rate | Transport | All fuels | I96: =INDEX(Variables!$C$5:$C$65,MATCH($A96,Variables!$A$5:$A$65,0)) -> USD/tCO2 | J96: =INDEX(Variables!$E$5:$E$65,MATCH($A96,Variables!$A$5:$A$65,0)) -> MTInputs (scenario column) | L96: =LOWER(Settings!$C$4)&".mit."&$A96&IF($C96="","","."&$C96&"."&$B96)&IF(INDEX(Variables!$D$5:$D$65,MATCH($A96,Variables!$A$5:$A$65,0))="","","."&INDEX(Variables!$D$5:$D$65,MATCH($A96,Variables!$A$5:$A$65,0)))&"."&L$5 -> egy.mit.fb.s.tra.all.1 | M96: =INDEX(MTInputs!$J$1:$AZ$415,$D96,MATCH(M$5,MTInputs!$J$5:$AZ$5,0)) -> 0 | N96: =INDEX(MTInputs!$J$1:$AZ$415,$D96,MATCH(N$5,MTInputs!$J$5:$AZ$5,0)) -> 0 | O96: =INDEX(MTInputs!$J$1:$AZ$415,$D96,MATCH(O$5,MTInputs!$J$5:$AZ$5,0)) -> 0 | P96: =INDEX(MTInputs!$J$1:$AZ$415,$D96,MATCH(P$5,MTInputs!$J$5:$AZ$5,0)) -> 0 | Q96: =INDEX(MTInputs!$J$1:$AZ$415,$D96,MATCH(Q$5,MTInputs!$J$5:$AZ$5,0)) -> 0 | R96: =INDEX(MTInputs!$J$1:$AZ$415,$D96,MATCH(R$5,MTInputs!$J$5:$AZ$5,0)) -> 0 | S96: =INDEX(MTInputs!$J$1:$AZ$415,$D96,MATCH(S$5,MTInputs!$J$5:$AZ$5,0)) -> 0 | T96: =INDEX(MTInputs!$J$1:$AZ$415,$D96,MATCH(T$5,MTInputs!$J$5:$AZ$5,0)) -> 0 | ... Z96: =INDEX(MTInputs!$J$1:$AZ$415,$D96,MATCH(Z$5,MTInputs!$J$5:$AZ$5,0)) -> 0 | AB96: =LOWER(Settings!$C$4)&".mit."&$A96&IF($C96="","","."&$C96&"."&$B96)&IF(INDEX(Variables!$D$5:$D$65,MATCH($A96,Variables!$A$5:$A$65,0))="","","."&INDEX(Variables!$D$5:$D$65,MATCH($A96,Variables!$A$5:$A$65,0)))&"."&AB$5 -> egy.mit.fb.s.tra.all.2 | AC96: =INDEX(MTInputs!$J$1:$AZ$415,$D96,MATCH(AC$5,MTInputs!$J$5:$AZ$5,0)) -> 0 | AD96: =INDEX(MTInputs!$J$1:$AZ$415,$D96,MATCH(AD$5,MTInputs!$J$5:$AZ$5,0)) -> 0 | AE96: =INDEX(MTInputs!$J$1:$AZ$415,$D96,MATCH(AE$5,MTInputs!$J$5:$AZ$5,0)) -> 0 | AF96: =INDEX(MTInputs!$J$1:$AZ$415,$D96,MATCH(AF$5,MTInputs!$J$5:$AZ$5,0)) -> 0 | AG96: =INDEX(MTInputs!$J$1:$AZ$415,$D96,MATCH(AG$5,MTInputs!$J$5:$AZ$5,0)) -> 0 | AH96: =INDEX(MTInputs!$J$1:$AZ$415,$D96,MATCH(AH$5,MTInputs!$J$5:$AZ$5,0)) -> 0 | AI96: =INDEX(MTInputs!$J$1:$AZ$415,$D96,MATCH(AI$5,MTInputs!$J$5:$AZ$5,0)) -> 0 | AJ96: =INDEX(MTInputs!$J$1:$AZ$415,$D96,MATCH(AJ$5,MTInputs!$J$5:$AZ$5,0)) -> 0 | ... AP96: =INDEX(MTInputs!$J$1:$AZ$415,$D96,MATCH(AP$5,MTInputs!$J$5:$AZ$5,0)) -> 0
A97: fb.s | B97: all | C97: res | D97: 58 | H97: =INDEX(Variables!$B$5:$B$65,MATCH($A97,Variables!$A$5:$A$65,0))&IF($C97="",""," | "&INDEX(Mapping!$B$5:$B$26,MATCH($C97,Mapping!$A$5:$A$26,0))&" | "&INDEX(Mapping!$B$30:$B$41,MATCH($B97,Mapping!$A$30:$A$41,0))) -> Feebates: starting rate | Residential | All fuels | I97: =INDEX(Variables!$C$5:$C$65,MATCH($A97,Variables!$A$5:$A$65,0)) -> USD/tCO2 | J97: =INDEX(Variables!$E$5:$E$65,MATCH($A97,Variables!$A$5:$A$65,0)) -> MTInputs (scenario column) | L97: =LOWER(Settings!$C$4)&".mit."&$A97&IF($C97="","","."&$C97&"."&$B97)&IF(INDEX(Variables!$D$5:$D$65,MATCH($A97,Variables!$A$5:$A$65,0))="","","."&INDEX(Variables!$D$5:$D$65,MATCH($A97,Variables!$A$5:$A$65,0)))&"."&L$5 -> egy.mit.fb.s.res.all.1 | M97: =INDEX(MTInputs!$J$1:$AZ$415,$D97,MATCH(M$5,MTInputs!$J$5:$AZ$5,0)) -> 0 | N97: =INDEX(MTInputs!$J$1:$AZ$415,$D97,MATCH(N$5,MTInputs!$J$5:$AZ$5,0)) -> 0 | O97: =INDEX(MTInputs!$J$1:$AZ$415,$D97,MATCH(O$5,MTInputs!$J$5:$AZ$5,0)) -> 0 | P97: =INDEX(MTInputs!$J$1:$AZ$415,$D97,MATCH(P$5,MTInputs!$J$5:$AZ$5,0)) -> 0 | Q97: =INDEX(MTInputs!$J$1:$AZ$415,$D97,MATCH(Q$5,MTInputs!$J$5:$AZ$5,0)) -> 0 | R97: =INDEX(MTInputs!$J$1:$AZ$415,$D97,MATCH(R$5,MTInputs!$J$5:$AZ$5,0)) -> 0 | S97: =INDEX(MTInputs!$J$1:$AZ$415,$D97,MATCH(S$5,MTInputs!$J$5:$AZ$5,0)) -> 0 | T97: =INDEX(MTInputs!$J$1:$AZ$415,$D97,MATCH(T$5,MTInputs!$J$5:$AZ$5,0)) -> 0 | ... Z97: =INDEX(MTInputs!$J$1:$AZ$415,$D97,MATCH(Z$5,MTInputs!$J$5:$AZ$5,0)) -> 0 | AB97: =LOWER(Settings!$C$4)&".mit."&$A97&IF($C97="","","."&$C97&"."&$B97)&IF(INDEX(Variables!$D$5:$D$65,MATCH($A97,Variables!$A$5:$A$65,0))="","","."&INDEX(Variables!$D$5:$D$65,MATCH($A97,Variables!$A$5:$A$65,0)))&"."&AB$5 -> egy.mit.fb.s.res.all.2 | AC97: =INDEX(MTInputs!$J$1:$AZ$415,$D97,MATCH(AC$5,MTInputs!$J$5:$AZ$5,0)) -> 0 | AD97: =INDEX(MTInputs!$J$1:$AZ$415,$D97,MATCH(AD$5,MTInputs!$J$5:$AZ$5,0)) -> 0 | AE97: =INDEX(MTInputs!$J$1:$AZ$415,$D97,MATCH(AE$5,MTInputs!$J$5:$AZ$5,0)) -> 0 | AF97: =INDEX(MTInputs!$J$1:$AZ$415,$D97,MATCH(AF$5,MTInputs!$J$5:$AZ$5,0)) -> 0 | AG97: =INDEX(MTInputs!$J$1:$AZ$415,$D97,MATCH(AG$5,MTInputs!$J$5:$AZ$5,0)) -> 0 | AH97: =INDEX(MTInputs!$J$1:$AZ$415,$D97,MATCH(AH$5,MTInputs!$J$5:$AZ$5,0)) -> 0 | AI97: =INDEX(MTInputs!$J$1:$AZ$415,$D97,MATCH(AI$5,MTInputs!$J$5:$AZ$5,0)) -> 0 | AJ97: =INDEX(MTInputs!$J$1:$AZ$415,$D97,MATCH(AJ$5,MTInputs!$J$5:$AZ$5,0)) -> 0 | ... AP97: =INDEX(MTInputs!$J$1:$AZ$415,$D97,MATCH(AP$5,MTInputs!$J$5:$AZ$5,0)) -> 0
A98: fb.s | B98: all | C98: ind | D98: 59 | H98: =INDEX(Variables!$B$5:$B$65,MATCH($A98,Variables!$A$5:$A$65,0))&IF($C98="",""," | "&INDEX(Mapping!$B$5:$B$26,MATCH($C98,Mapping!$A$5:$A$26,0))&" | "&INDEX(Mapping!$B$30:$B$41,MATCH($B98,Mapping!$A$30:$A$41,0))) -> Feebates: starting rate | Industry | All fuels | I98: =INDEX(Variables!$C$5:$C$65,MATCH($A98,Variables!$A$5:$A$65,0)) -> USD/tCO2 | J98: =INDEX(Variables!$E$5:$E$65,MATCH($A98,Variables!$A$5:$A$65,0)) -> MTInputs (scenario column) | L98: =LOWER(Settings!$C$4)&".mit."&$A98&IF($C98="","","."&$C98&"."&$B98)&IF(INDEX(Variables!$D$5:$D$65,MATCH($A98,Variables!$A$5:$A$65,0))="","","."&INDEX(Variables!$D$5:$D$65,MATCH($A98,Variables!$A$5:$A$65,0)))&"."&L$5 -> egy.mit.fb.s.ind.all.1 | M98: =INDEX(MTInputs!$J$1:$AZ$415,$D98,MATCH(M$5,MTInputs!$J$5:$AZ$5,0)) -> 0 | N98: =INDEX(MTInputs!$J$1:$AZ$415,$D98,MATCH(N$5,MTInputs!$J$5:$AZ$5,0)) -> 0 | O98: =INDEX(MTInputs!$J$1:$AZ$415,$D98,MATCH(O$5,MTInputs!$J$5:$AZ$5,0)) -> 0 | P98: =INDEX(MTInputs!$J$1:$AZ$415,$D98,MATCH(P$5,MTInputs!$J$5:$AZ$5,0)) -> 0 | Q98: =INDEX(MTInputs!$J$1:$AZ$415,$D98,MATCH(Q$5,MTInputs!$J$5:$AZ$5,0)) -> 0 | R98: =INDEX(MTInputs!$J$1:$AZ$415,$D98,MATCH(R$5,MTInputs!$J$5:$AZ$5,0)) -> 0 | S98: =INDEX(MTInputs!$J$1:$AZ$415,$D98,MATCH(S$5,MTInputs!$J$5:$AZ$5,0)) -> 0 | T98: =INDEX(MTInputs!$J$1:$AZ$415,$D98,MATCH(T$5,MTInputs!$J$5:$AZ$5,0)) -> 0 | ... Z98: =INDEX(MTInputs!$J$1:$AZ$415,$D98,MATCH(Z$5,MTInputs!$J$5:$AZ$5,0)) -> 0 | AB98: =LOWER(Settings!$C$4)&".mit."&$A98&IF($C98="","","."&$C98&"."&$B98)&IF(INDEX(Variables!$D$5:$D$65,MATCH($A98,Variables!$A$5:$A$65,0))="","","."&INDEX(Variables!$D$5:$D$65,MATCH($A98,Variables!$A$5:$A$65,0)))&"."&AB$5 -> egy.mit.fb.s.ind.all.2 | AC98: =INDEX(MTInputs!$J$1:$AZ$415,$D98,MATCH(AC$5,MTInputs!$J$5:$AZ$5,0)) -> 0 | AD98: =INDEX(MTInputs!$J$1:$AZ$415,$D98,MATCH(AD$5,MTInputs!$J$5:$AZ$5,0)) -> 0 | AE98: =INDEX(MTInputs!$J$1:$AZ$415,$D98,MATCH(AE$5,MTInputs!$J$5:$AZ$5,0)) -> 0 | AF98: =INDEX(MTInputs!$J$1:$AZ$415,$D98,MATCH(AF$5,MTInputs!$J$5:$AZ$5,0)) -> 0 | AG98: =INDEX(MTInputs!$J$1:$AZ$415,$D98,MATCH(AG$5,MTInputs!$J$5:$AZ$5,0)) -> 0 | AH98: =INDEX(MTInputs!$J$1:$AZ$415,$D98,MATCH(AH$5,MTInputs!$J$5:$AZ$5,0)) -> 0 | AI98: =INDEX(MTInputs!$J$1:$AZ$415,$D98,MATCH(AI$5,MTInputs!$J$5:$AZ$5,0)) -> 0 | AJ98: =INDEX(MTInputs!$J$1:$AZ$415,$D98,MATCH(AJ$5,MTInputs!$J$5:$AZ$5,0)) -> 0 | ... AP98: =INDEX(MTInputs!$J$1:$AZ$415,$D98,MATCH(AP$5,MTInputs!$J$5:$AZ$5,0)) -> 0
A99: fb.t | B99: all | C99: pow | D99: 61 | H99: =INDEX(Variables!$B$5:$B$65,MATCH($A99,Variables!$A$5:$A$65,0))&IF($C99="",""," | "&INDEX(Mapping!$B$5:$B$26,MATCH($C99,Mapping!$A$5:$A$26,0))&" | "&INDEX(Mapping!$B$30:$B$41,MATCH($B99,Mapping!$A$30:$A$41,0))) -> Feebates: target rate | Power | All fuels | I99: =INDEX(Variables!$C$5:$C$65,MATCH($A99,Variables!$A$5:$A$65,0)) -> USD/tCO2 | J99: =INDEX(Variables!$E$5:$E$65,MATCH($A99,Variables!$A$5:$A$65,0)) -> MTInputs (scenario column) | L99: =LOWER(Settings!$C$4)&".mit."&$A99&IF($C99="","","."&$C99&"."&$B99)&IF(INDEX(Variables!$D$5:$D$65,MATCH($A99,Variables!$A$5:$A$65,0))="","","."&INDEX(Variables!$D$5:$D$65,MATCH($A99,Variables!$A$5:$A$65,0)))&"."&L$5 -> egy.mit.fb.t.pow.all.1 | M99: =INDEX(MTInputs!$J$1:$AZ$415,$D99,MATCH(M$5,MTInputs!$J$5:$AZ$5,0)) -> 0 | N99: =INDEX(MTInputs!$J$1:$AZ$415,$D99,MATCH(N$5,MTInputs!$J$5:$AZ$5,0)) -> 0 | O99: =INDEX(MTInputs!$J$1:$AZ$415,$D99,MATCH(O$5,MTInputs!$J$5:$AZ$5,0)) -> 0 | P99: =INDEX(MTInputs!$J$1:$AZ$415,$D99,MATCH(P$5,MTInputs!$J$5:$AZ$5,0)) -> 0 | Q99: =INDEX(MTInputs!$J$1:$AZ$415,$D99,MATCH(Q$5,MTInputs!$J$5:$AZ$5,0)) -> 0 | R99: =INDEX(MTInputs!$J$1:$AZ$415,$D99,MATCH(R$5,MTInputs!$J$5:$AZ$5,0)) -> 0 | S99: =INDEX(MTInputs!$J$1:$AZ$415,$D99,MATCH(S$5,MTInputs!$J$5:$AZ$5,0)) -> 0 | T99: =INDEX(MTInputs!$J$1:$AZ$415,$D99,MATCH(T$5,MTInputs!$J$5:$AZ$5,0)) -> 0 | ... Z99: =INDEX(MTInputs!$J$1:$AZ$415,$D99,MATCH(Z$5,MTInputs!$J$5:$AZ$5,0)) -> 0 | AB99: =LOWER(Settings!$C$4)&".mit."&$A99&IF($C99="","","."&$C99&"."&$B99)&IF(INDEX(Variables!$D$5:$D$65,MATCH($A99,Variables!$A$5:$A$65,0))="","","."&INDEX(Variables!$D$5:$D$65,MATCH($A99,Variables!$A$5:$A$65,0)))&"."&AB$5 -> egy.mit.fb.t.pow.all.2 | AC99: =INDEX(MTInputs!$J$1:$AZ$415,$D99,MATCH(AC$5,MTInputs!$J$5:$AZ$5,0)) -> 0 | AD99: =INDEX(MTInputs!$J$1:$AZ$415,$D99,MATCH(AD$5,MTInputs!$J$5:$AZ$5,0)) -> 0 | AE99: =INDEX(MTInputs!$J$1:$AZ$415,$D99,MATCH(AE$5,MTInputs!$J$5:$AZ$5,0)) -> 0 | AF99: =INDEX(MTInputs!$J$1:$AZ$415,$D99,MATCH(AF$5,MTInputs!$J$5:$AZ$5,0)) -> 0 | AG99: =INDEX(MTInputs!$J$1:$AZ$415,$D99,MATCH(AG$5,MTInputs!$J$5:$AZ$5,0)) -> 0 | AH99: =INDEX(MTInputs!$J$1:$AZ$415,$D99,MATCH(AH$5,MTInputs!$J$5:$AZ$5,0)) -> 0 | AI99: =INDEX(MTInputs!$J$1:$AZ$415,$D99,MATCH(AI$5,MTInputs!$J$5:$AZ$5,0)) -> 0 | AJ99: =INDEX(MTInputs!$J$1:$AZ$415,$D99,MATCH(AJ$5,MTInputs!$J$5:$AZ$5,0)) -> 0 | ... AP99: =INDEX(MTInputs!$J$1:$AZ$415,$D99,MATCH(AP$5,MTInputs!$J$5:$AZ$5,0)) -> 0
A100: fb.t | B100: all | C100: tra | D100: 62 | H100: =INDEX(Variables!$B$5:$B$65,MATCH($A100,Variables!$A$5:$A$65,0))&IF($C100="",""," | "&INDEX(Mapping!$B$5:$B$26,MATCH($C100,Mapping!$A$5:$A$26,0))&" | "&INDEX(Mapping!$B$30:$B$41,MATCH($B100,Mapping!$A$30:$A$41,0))) -> Feebates: target rate | Transport | All fuels | I100: =INDEX(Variables!$C$5:$C$65,MATCH($A100,Variables!$A$5:$A$65,0)) -> USD/tCO2 | J100: =INDEX(Variables!$E$5:$E$65,MATCH($A100,Variables!$A$5:$A$65,0)) -> MTInputs (scenario column) | L100: =LOWER(Settings!$C$4)&".mit."&$A100&IF($C100="","","."&$C100&"."&$B100)&IF(INDEX(Variables!$D$5:$D$65,MATCH($A100,Variables!$A$5:$A$65,0))="","","."&INDEX(Variables!$D$5:$D$65,MATCH($A100,Variables!$A$5:$A$65,0)))&"."&L$5 -> egy.mit.fb.t.tra.all.1 | M100: =INDEX(MTInputs!$J$1:$AZ$415,$D100,MATCH(M$5,MTInputs!$J$5:$AZ$5,0)) -> 0 | N100: =INDEX(MTInputs!$J$1:$AZ$415,$D100,MATCH(N$5,MTInputs!$J$5:$AZ$5,0)) -> 0 | O100: =INDEX(MTInputs!$J$1:$AZ$415,$D100,MATCH(O$5,MTInputs!$J$5:$AZ$5,0)) -> 0 | P100: =INDEX(MTInputs!$J$1:$AZ$415,$D100,MATCH(P$5,MTInputs!$J$5:$AZ$5,0)) -> 0 | Q100: =INDEX(MTInputs!$J$1:$AZ$415,$D100,MATCH(Q$5,MTInputs!$J$5:$AZ$5,0)) -> 0 | R100: =INDEX(MTInputs!$J$1:$AZ$415,$D100,MATCH(R$5,MTInputs!$J$5:$AZ$5,0)) -> 0 | S100: =INDEX(MTInputs!$J$1:$AZ$415,$D100,MATCH(S$5,MTInputs!$J$5:$AZ$5,0)) -> 0 | T100: =INDEX(MTInputs!$J$1:$AZ$415,$D100,MATCH(T$5,MTInputs!$J$5:$AZ$5,0)) -> 0 | ... Z100: =INDEX(MTInputs!$J$1:$AZ$415,$D100,MATCH(Z$5,MTInputs!$J$5:$AZ$5,0)) -> 0 | AB100: =LOWER(Settings!$C$4)&".mit."&$A100&IF($C100="","","."&$C100&"."&$B100)&IF(INDEX(Variables!$D$5:$D$65,MATCH($A100,Variables!$A$5:$A$65,0))="","","."&INDEX(Variables!$D$5:$D$65,MATCH($A100,Variables!$A$5:$A$65,0)))&"."&AB$5 -> egy.mit.fb.t.tra.all.2 | AC100: =INDEX(MTInputs!$J$1:$AZ$415,$D100,MATCH(AC$5,MTInputs!$J$5:$AZ$5,0)) -> 0 | AD100: =INDEX(MTInputs!$J$1:$AZ$415,$D100,MATCH(AD$5,MTInputs!$J$5:$AZ$5,0)) -> 0 | AE100: =INDEX(MTInputs!$J$1:$AZ$415,$D100,MATCH(AE$5,MTInputs!$J$5:$AZ$5,0)) -> 0 | AF100: =INDEX(MTInputs!$J$1:$AZ$415,$D100,MATCH(AF$5,MTInputs!$J$5:$AZ$5,0)) -> 0 | AG100: =INDEX(MTInputs!$J$1:$AZ$415,$D100,MATCH(AG$5,MTInputs!$J$5:$AZ$5,0)) -> 0 | AH100: =INDEX(MTInputs!$J$1:$AZ$415,$D100,MATCH(AH$5,MTInputs!$J$5:$AZ$5,0)) -> 0 | AI100: =INDEX(MTInputs!$J$1:$AZ$415,$D100,MATCH(AI$5,MTInputs!$J$5:$AZ$5,0)) -> 0 | AJ100: =INDEX(MTInputs!$J$1:$AZ$415,$D100,MATCH(AJ$5,MTInputs!$J$5:$AZ$5,0)) -> 0 | ... AP100: =INDEX(MTInputs!$J$1:$AZ$415,$D100,MATCH(AP$5,MTInputs!$J$5:$AZ$5,0)) -> 0
A101: fb.t | B101: all | C101: res | D101: 63 | H101: =INDEX(Variables!$B$5:$B$65,MATCH($A101,Variables!$A$5:$A$65,0))&IF($C101="",""," | "&INDEX(Mapping!$B$5:$B$26,MATCH($C101,Mapping!$A$5:$A$26,0))&" | "&INDEX(Mapping!$B$30:$B$41,MATCH($B101,Mapping!$A$30:$A$41,0))) -> Feebates: target rate | Residential | All fuels | I101: =INDEX(Variables!$C$5:$C$65,MATCH($A101,Variables!$A$5:$A$65,0)) -> USD/tCO2 | J101: =INDEX(Variables!$E$5:$E$65,MATCH($A101,Variables!$A$5:$A$65,0)) -> MTInputs (scenario column) | L101: =LOWER(Settings!$C$4)&".mit."&$A101&IF($C101="","","."&$C101&"."&$B101)&IF(INDEX(Variables!$D$5:$D$65,MATCH($A101,Variables!$A$5:$A$65,0))="","","."&INDEX(Variables!$D$5:$D$65,MATCH($A101,Variables!$A$5:$A$65,0)))&"."&L$5 -> egy.mit.fb.t.res.all.1 | M101: =INDEX(MTInputs!$J$1:$AZ$415,$D101,MATCH(M$5,MTInputs!$J$5:$AZ$5,0)) -> 0 | N101: =INDEX(MTInputs!$J$1:$AZ$415,$D101,MATCH(N$5,MTInputs!$J$5:$AZ$5,0)) -> 0 | O101: =INDEX(MTInputs!$J$1:$AZ$415,$D101,MATCH(O$5,MTInputs!$J$5:$AZ$5,0)) -> 0 | P101: =INDEX(MTInputs!$J$1:$AZ$415,$D101,MATCH(P$5,MTInputs!$J$5:$AZ$5,0)) -> 0 | Q101: =INDEX(MTInputs!$J$1:$AZ$415,$D101,MATCH(Q$5,MTInputs!$J$5:$AZ$5,0)) -> 0 | R101: =INDEX(MTInputs!$J$1:$AZ$415,$D101,MATCH(R$5,MTInputs!$J$5:$AZ$5,0)) -> 0 | S101: =INDEX(MTInputs!$J$1:$AZ$415,$D101,MATCH(S$5,MTInputs!$J$5:$AZ$5,0)) -> 0 | T101: =INDEX(MTInputs!$J$1:$AZ$415,$D101,MATCH(T$5,MTInputs!$J$5:$AZ$5,0)) -> 0 | ... Z101: =INDEX(MTInputs!$J$1:$AZ$415,$D101,MATCH(Z$5,MTInputs!$J$5:$AZ$5,0)) -> 0 | AB101: =LOWER(Settings!$C$4)&".mit."&$A101&IF($C101="","","."&$C101&"."&$B101)&IF(INDEX(Variables!$D$5:$D$65,MATCH($A101,Variables!$A$5:$A$65,0))="","","."&INDEX(Variables!$D$5:$D$65,MATCH($A101,Variables!$A$5:$A$65,0)))&"."&AB$5 -> egy.mit.fb.t.res.all.2 | AC101: =INDEX(MTInputs!$J$1:$AZ$415,$D101,MATCH(AC$5,MTInputs!$J$5:$AZ$5,0)) -> 0 | AD101: =INDEX(MTInputs!$J$1:$AZ$415,$D101,MATCH(AD$5,MTInputs!$J$5:$AZ$5,0)) -> 0 | AE101: =INDEX(MTInputs!$J$1:$AZ$415,$D101,MATCH(AE$5,MTInputs!$J$5:$AZ$5,0)) -> 0 | AF101: =INDEX(MTInputs!$J$1:$AZ$415,$D101,MATCH(AF$5,MTInputs!$J$5:$AZ$5,0)) -> 0 | AG101: =INDEX(MTInputs!$J$1:$AZ$415,$D101,MATCH(AG$5,MTInputs!$J$5:$AZ$5,0)) -> 0 | AH101: =INDEX(MTInputs!$J$1:$AZ$415,$D101,MATCH(AH$5,MTInputs!$J$5:$AZ$5,0)) -> 0 | AI101: =INDEX(MTInputs!$J$1:$AZ$415,$D101,MATCH(AI$5,MTInputs!$J$5:$AZ$5,0)) -> 0 | AJ101: =INDEX(MTInputs!$J$1:$AZ$415,$D101,MATCH(AJ$5,MTInputs!$J$5:$AZ$5,0)) -> 0 | ... AP101: =INDEX(MTInputs!$J$1:$AZ$415,$D101,MATCH(AP$5,MTInputs!$J$5:$AZ$5,0)) -> 0
A102: fb.t | B102: all | C102: ind | D102: 64 | H102: =INDEX(Variables!$B$5:$B$65,MATCH($A102,Variables!$A$5:$A$65,0))&IF($C102="",""," | "&INDEX(Mapping!$B$5:$B$26,MATCH($C102,Mapping!$A$5:$A$26,0))&" | "&INDEX(Mapping!$B$30:$B$41,MATCH($B102,Mapping!$A$30:$A$41,0))) -> Feebates: target rate | Industry | All fuels | I102: =INDEX(Variables!$C$5:$C$65,MATCH($A102,Variables!$A$5:$A$65,0)) -> USD/tCO2 | J102: =INDEX(Variables!$E$5:$E$65,MATCH($A102,Variables!$A$5:$A$65,0)) -> MTInputs (scenario column) | L102: =LOWER(Settings!$C$4)&".mit."&$A102&IF($C102="","","."&$C102&"."&$B102)&IF(INDEX(Variables!$D$5:$D$65,MATCH($A102,Variables!$A$5:$A$65,0))="","","."&INDEX(Variables!$D$5:$D$65,MATCH($A102,Variables!$A$5:$A$65,0)))&"."&L$5 -> egy.mit.fb.t.ind.all.1 | M102: =INDEX(MTInputs!$J$1:$AZ$415,$D102,MATCH(M$5,MTInputs!$J$5:$AZ$5,0)) -> 0 | N102: =INDEX(MTInputs!$J$1:$AZ$415,$D102,MATCH(N$5,MTInputs!$J$5:$AZ$5,0)) -> 0 | O102: =INDEX(MTInputs!$J$1:$AZ$415,$D102,MATCH(O$5,MTInputs!$J$5:$AZ$5,0)) -> 0 | P102: =INDEX(MTInputs!$J$1:$AZ$415,$D102,MATCH(P$5,MTInputs!$J$5:$AZ$5,0)) -> 0 | Q102: =INDEX(MTInputs!$J$1:$AZ$415,$D102,MATCH(Q$5,MTInputs!$J$5:$AZ$5,0)) -> 0 | R102: =INDEX(MTInputs!$J$1:$AZ$415,$D102,MATCH(R$5,MTInputs!$J$5:$AZ$5,0)) -> 0 | S102: =INDEX(MTInputs!$J$1:$AZ$415,$D102,MATCH(S$5,MTInputs!$J$5:$AZ$5,0)) -> 0 | T102: =INDEX(MTInputs!$J$1:$AZ$415,$D102,MATCH(T$5,MTInputs!$J$5:$AZ$5,0)) -> 0 | ... Z102: =INDEX(MTInputs!$J$1:$AZ$415,$D102,MATCH(Z$5,MTInputs!$J$5:$AZ$5,0)) -> 0 | AB102: =LOWER(Settings!$C$4)&".mit."&$A102&IF($C102="","","."&$C102&"."&$B102)&IF(INDEX(Variables!$D$5:$D$65,MATCH($A102,Variables!$A$5:$A$65,0))="","","."&INDEX(Variables!$D$5:$D$65,MATCH($A102,Variables!$A$5:$A$65,0)))&"."&AB$5 -> egy.mit.fb.t.ind.all.2 | AC102: =INDEX(MTInputs!$J$1:$AZ$415,$D102,MATCH(AC$5,MTInputs!$J$5:$AZ$5,0)) -> 0 | AD102: =INDEX(MTInputs!$J$1:$AZ$415,$D102,MATCH(AD$5,MTInputs!$J$5:$AZ$5,0)) -> 0 | AE102: =INDEX(MTInputs!$J$1:$AZ$415,$D102,MATCH(AE$5,MTInputs!$J$5:$AZ$5,0)) -> 0 | AF102: =INDEX(MTInputs!$J$1:$AZ$415,$D102,MATCH(AF$5,MTInputs!$J$5:$AZ$5,0)) -> 0 | AG102: =INDEX(MTInputs!$J$1:$AZ$415,$D102,MATCH(AG$5,MTInputs!$J$5:$AZ$5,0)) -> 0 | AH102: =INDEX(MTInputs!$J$1:$AZ$415,$D102,MATCH(AH$5,MTInputs!$J$5:$AZ$5,0)) -> 0 | AI102: =INDEX(MTInputs!$J$1:$AZ$415,$D102,MATCH(AI$5,MTInputs!$J$5:$AZ$5,0)) -> 0 | AJ102: =INDEX(MTInputs!$J$1:$AZ$415,$D102,MATCH(AJ$5,MTInputs!$J$5:$AZ$5,0)) -> 0 | ... AP102: =INDEX(MTInputs!$J$1:$AZ$415,$D102,MATCH(AP$5,MTInputs!$J$5:$AZ$5,0)) -> 0
A103: fb | B103: all | C103: pow | H103: =INDEX(Variables!$B$5:$B$65,MATCH($A103,Variables!$A$5:$A$65,0))&IF($C103="",""," | "&INDEX(Mapping!$B$5:$B$26,MATCH($C103,Mapping!$A$5:$A$26,0))&" | "&INDEX(Mapping!$B$30:$B$41,MATCH($B103,Mapping!$A$30:$A$41,0))) -> Feebates: rate path | Power | All fuels | I103: =INDEX(Variables!$C$5:$C$65,MATCH($A103,Variables!$A$5:$A$65,0)) -> USD/tCO2 | J103: =INDEX(Variables!$E$5:$E$65,MATCH($A103,Variables!$A$5:$A$65,0)) -> Calculation (assumed linear) | L103: =LOWER(Settings!$C$4)&".mit."&$A103&IF($C103="","","."&$C103&"."&$B103)&IF(INDEX(Variables!$D$5:$D$65,MATCH($A103,Variables!$A$5:$A$65,0))="","","."&INDEX(Variables!$D$5:$D$65,MATCH($A103,Variables!$A$5:$A$65,0)))&"."&L$5 -> egy.mit.fb.pow.all.1 | M103: =IF(M$4<M$93,0,M95+(M99-M95)/MAX(M$94-M$93,1)*(M$4-M$93)) -> 0 | N103: =IF(N$4<N$93,0,N95+(N99-N95)/MAX(N$94-N$93,1)*(N$4-N$93)) -> 0 | O103: =IF(O$4<O$93,0,O95+(O99-O95)/MAX(O$94-O$93,1)*(O$4-O$93)) -> 0 | P103: =IF(P$4<P$93,0,P95+(P99-P95)/MAX(P$94-P$93,1)*(P$4-P$93)) -> 0 | Q103: =IF(Q$4<Q$93,0,Q95+(Q99-Q95)/MAX(Q$94-Q$93,1)*(Q$4-Q$93)) -> 0 | R103: =IF(R$4<R$93,0,R95+(R99-R95)/MAX(R$94-R$93,1)*(R$4-R$93)) -> 0 | S103: =IF(S$4<S$93,0,S95+(S99-S95)/MAX(S$94-S$93,1)*(S$4-S$93)) -> 0 | T103: =IF(T$4<T$93,0,T95+(T99-T95)/MAX(T$94-T$93,1)*(T$4-T$93)) -> 0 | ... Z103: =IF(Z$4<Z$93,0,Z95+(Z99-Z95)/MAX(Z$94-Z$93,1)*(Z$4-Z$93)) -> 0 | AB103: =LOWER(Settings!$C$4)&".mit."&$A103&IF($C103="","","."&$C103&"."&$B103)&IF(INDEX(Variables!$D$5:$D$65,MATCH($A103,Variables!$A$5:$A$65,0))="","","."&INDEX(Variables!$D$5:$D$65,MATCH($A103,Variables!$A$5:$A$65,0)))&"."&AB$5 -> egy.mit.fb.pow.all.2 | AC103: =IF(AC$4<AC$93,0,AC95+(AC99-AC95)/MAX(AC$94-AC$93,1)*(AC$4-AC$93)) -> 0 | AD103: =IF(AD$4<AD$93,0,AD95+(AD99-AD95)/MAX(AD$94-AD$93,1)*(AD$4-AD$93)) -> 0 | AE103: =IF(AE$4<AE$93,0,AE95+(AE99-AE95)/MAX(AE$94-AE$93,1)*(AE$4-AE$93)) -> 0 | AF103: =IF(AF$4<AF$93,0,AF95+(AF99-AF95)/MAX(AF$94-AF$93,1)*(AF$4-AF$93)) -> 0 | AG103: =IF(AG$4<AG$93,0,AG95+(AG99-AG95)/MAX(AG$94-AG$93,1)*(AG$4-AG$93)) -> 0 | AH103: =IF(AH$4<AH$93,0,AH95+(AH99-AH95)/MAX(AH$94-AH$93,1)*(AH$4-AH$93)) -> 0 | AI103: =IF(AI$4<AI$93,0,AI95+(AI99-AI95)/MAX(AI$94-AI$93,1)*(AI$4-AI$93)) -> 0 | AJ103: =IF(AJ$4<AJ$93,0,AJ95+(AJ99-AJ95)/MAX(AJ$94-AJ$93,1)*(AJ$4-AJ$93)) -> 0 | ... AP103: =IF(AP$4<AP$93,0,AP95+(AP99-AP95)/MAX(AP$94-AP$93,1)*(AP$4-AP$93)) -> 0
A104: fb | B104: all | C104: tra | H104: =INDEX(Variables!$B$5:$B$65,MATCH($A104,Variables!$A$5:$A$65,0))&IF($C104="",""," | "&INDEX(Mapping!$B$5:$B$26,MATCH($C104,Mapping!$A$5:$A$26,0))&" | "&INDEX(Mapping!$B$30:$B$41,MATCH($B104,Mapping!$A$30:$A$41,0))) -> Feebates: rate path | Transport | All fuels | I104: =INDEX(Variables!$C$5:$C$65,MATCH($A104,Variables!$A$5:$A$65,0)) -> USD/tCO2 | J104: =INDEX(Variables!$E$5:$E$65,MATCH($A104,Variables!$A$5:$A$65,0)) -> Calculation (assumed linear) | L104: =LOWER(Settings!$C$4)&".mit."&$A104&IF($C104="","","."&$C104&"."&$B104)&IF(INDEX(Variables!$D$5:$D$65,MATCH($A104,Variables!$A$5:$A$65,0))="","","."&INDEX(Variables!$D$5:$D$65,MATCH($A104,Variables!$A$5:$A$65,0)))&"."&L$5 -> egy.mit.fb.tra.all.1 | M104: =IF(M$4<M$93,0,M96+(M100-M96)/MAX(M$94-M$93,1)*(M$4-M$93)) -> 0 | N104: =IF(N$4<N$93,0,N96+(N100-N96)/MAX(N$94-N$93,1)*(N$4-N$93)) -> 0 | O104: =IF(O$4<O$93,0,O96+(O100-O96)/MAX(O$94-O$93,1)*(O$4-O$93)) -> 0 | P104: =IF(P$4<P$93,0,P96+(P100-P96)/MAX(P$94-P$93,1)*(P$4-P$93)) -> 0 | Q104: =IF(Q$4<Q$93,0,Q96+(Q100-Q96)/MAX(Q$94-Q$93,1)*(Q$4-Q$93)) -> 0 | R104: =IF(R$4<R$93,0,R96+(R100-R96)/MAX(R$94-R$93,1)*(R$4-R$93)) -> 0 | S104: =IF(S$4<S$93,0,S96+(S100-S96)/MAX(S$94-S$93,1)*(S$4-S$93)) -> 0 | T104: =IF(T$4<T$93,0,T96+(T100-T96)/MAX(T$94-T$93,1)*(T$4-T$93)) -> 0 | ... Z104: =IF(Z$4<Z$93,0,Z96+(Z100-Z96)/MAX(Z$94-Z$93,1)*(Z$4-Z$93)) -> 0 | AB104: =LOWER(Settings!$C$4)&".mit."&$A104&IF($C104="","","."&$C104&"."&$B104)&IF(INDEX(Variables!$D$5:$D$65,MATCH($A104,Variables!$A$5:$A$65,0))="","","."&INDEX(Variables!$D$5:$D$65,MATCH($A104,Variables!$A$5:$A$65,0)))&"."&AB$5 -> egy.mit.fb.tra.all.2 | AC104: =IF(AC$4<AC$93,0,AC96+(AC100-AC96)/MAX(AC$94-AC$93,1)*(AC$4-AC$93)) -> 0 | AD104: =IF(AD$4<AD$93,0,AD96+(AD100-AD96)/MAX(AD$94-AD$93,1)*(AD$4-AD$93)) -> 0 | AE104: =IF(AE$4<AE$93,0,AE96+(AE100-AE96)/MAX(AE$94-AE$93,1)*(AE$4-AE$93)) -> 0 | AF104: =IF(AF$4<AF$93,0,AF96+(AF100-AF96)/MAX(AF$94-AF$93,1)*(AF$4-AF$93)) -> 0 | AG104: =IF(AG$4<AG$93,0,AG96+(AG100-AG96)/MAX(AG$94-AG$93,1)*(AG$4-AG$93)) -> 0 | AH104: =IF(AH$4<AH$93,0,AH96+(AH100-AH96)/MAX(AH$94-AH$93,1)*(AH$4-AH$93)) -> 0 | AI104: =IF(AI$4<AI$93,0,AI96+(AI100-AI96)/MAX(AI$94-AI$93,1)*(AI$4-AI$93)) -> 0 | AJ104: =IF(AJ$4<AJ$93,0,AJ96+(AJ100-AJ96)/MAX(AJ$94-AJ$93,1)*(AJ$4-AJ$93)) -> 0 | ... AP104: =IF(AP$4<AP$93,0,AP96+(AP100-AP96)/MAX(AP$94-AP$93,1)*(AP$4-AP$93)) -> 0
A105: fb | B105: all | C105: res | H105: =INDEX(Variables!$B$5:$B$65,MATCH($A105,Variables!$A$5:$A$65,0))&IF($C105="",""," | "&INDEX(Mapping!$B$5:$B$26,MATCH($C105,Mapping!$A$5:$A$26,0))&" | "&INDEX(Mapping!$B$30:$B$41,MATCH($B105,Mapping!$A$30:$A$41,0))) -> Feebates: rate path | Residential | All fuels | I105: =INDEX(Variables!$C$5:$C$65,MATCH($A105,Variables!$A$5:$A$65,0)) -> USD/tCO2 | J105: =INDEX(Variables!$E$5:$E$65,MATCH($A105,Variables!$A$5:$A$65,0)) -> Calculation (assumed linear) | L105: =LOWER(Settings!$C$4)&".mit."&$A105&IF($C105="","","."&$C105&"."&$B105)&IF(INDEX(Variables!$D$5:$D$65,MATCH($A105,Variables!$A$5:$A$65,0))="","","."&INDEX(Variables!$D$5:$D$65,MATCH($A105,Variables!$A$5:$A$65,0)))&"."&L$5 -> egy.mit.fb.res.all.1 | M105: =IF(M$4<M$93,0,M97+(M101-M97)/MAX(M$94-M$93,1)*(M$4-M$93)) -> 0 | N105: =IF(N$4<N$93,0,N97+(N101-N97)/MAX(N$94-N$93,1)*(N$4-N$93)) -> 0 | O105: =IF(O$4<O$93,0,O97+(O101-O97)/MAX(O$94-O$93,1)*(O$4-O$93)) -> 0 | P105: =IF(P$4<P$93,0,P97+(P101-P97)/MAX(P$94-P$93,1)*(P$4-P$93)) -> 0 | Q105: =IF(Q$4<Q$93,0,Q97+(Q101-Q97)/MAX(Q$94-Q$93,1)*(Q$4-Q$93)) -> 0 | R105: =IF(R$4<R$93,0,R97+(R101-R97)/MAX(R$94-R$93,1)*(R$4-R$93)) -> 0 | S105: =IF(S$4<S$93,0,S97+(S101-S97)/MAX(S$94-S$93,1)*(S$4-S$93)) -> 0 | T105: =IF(T$4<T$93,0,T97+(T101-T97)/MAX(T$94-T$93,1)*(T$4-T$93)) -> 0 | ... Z105: =IF(Z$4<Z$93,0,Z97+(Z101-Z97)/MAX(Z$94-Z$93,1)*(Z$4-Z$93)) -> 0 | AB105: =LOWER(Settings!$C$4)&".mit."&$A105&IF($C105="","","."&$C105&"."&$B105)&IF(INDEX(Variables!$D$5:$D$65,MATCH($A105,Variables!$A$5:$A$65,0))="","","."&INDEX(Variables!$D$5:$D$65,MATCH($A105,Variables!$A$5:$A$65,0)))&"."&AB$5 -> egy.mit.fb.res.all.2 | AC105: =IF(AC$4<AC$93,0,AC97+(AC101-AC97)/MAX(AC$94-AC$93,1)*(AC$4-AC$93)) -> 0 | AD105: =IF(AD$4<AD$93,0,AD97+(AD101-AD97)/MAX(AD$94-AD$93,1)*(AD$4-AD$93)) -> 0 | AE105: =IF(AE$4<AE$93,0,AE97+(AE101-AE97)/MAX(AE$94-AE$93,1)*(AE$4-AE$93)) -> 0 | AF105: =IF(AF$4<AF$93,0,AF97+(AF101-AF97)/MAX(AF$94-AF$93,1)*(AF$4-AF$93)) -> 0 | AG105: =IF(AG$4<AG$93,0,AG97+(AG101-AG97)/MAX(AG$94-AG$93,1)*(AG$4-AG$93)) -> 0 | AH105: =IF(AH$4<AH$93,0,AH97+(AH101-AH97)/MAX(AH$94-AH$93,1)*(AH$4-AH$93)) -> 0 | AI105: =IF(AI$4<AI$93,0,AI97+(AI101-AI97)/MAX(AI$94-AI$93,1)*(AI$4-AI$93)) -> 0 | AJ105: =IF(AJ$4<AJ$93,0,AJ97+(AJ101-AJ97)/MAX(AJ$94-AJ$93,1)*(AJ$4-AJ$93)) -> 0 | ... AP105: =IF(AP$4<AP$93,0,AP97+(AP101-AP97)/MAX(AP$94-AP$93,1)*(AP$4-AP$93)) -> 0
A106: fb | B106: all | C106: ind | H106: =INDEX(Variables!$B$5:$B$65,MATCH($A106,Variables!$A$5:$A$65,0))&IF($C106="",""," | "&INDEX(Mapping!$B$5:$B$26,MATCH($C106,Mapping!$A$5:$A$26,0))&" | "&INDEX(Mapping!$B$30:$B$41,MATCH($B106,Mapping!$A$30:$A$41,0))) -> Feebates: rate path | Industry | All fuels | I106: =INDEX(Variables!$C$5:$C$65,MATCH($A106,Variables!$A$5:$A$65,0)) -> USD/tCO2 | J106: =INDEX(Variables!$E$5:$E$65,MATCH($A106,Variables!$A$5:$A$65,0)) -> Calculation (assumed linear) | L106: =LOWER(Settings!$C$4)&".mit."&$A106&IF($C106="","","."&$C106&"."&$B106)&IF(INDEX(Variables!$D$5:$D$65,MATCH($A106,Variables!$A$5:$A$65,0))="","","."&INDEX(Variables!$D$5:$D$65,MATCH($A106,Variables!$A$5:$A$65,0)))&"."&L$5 -> egy.mit.fb.ind.all.1 | M106: =IF(M$4<M$93,0,M98+(M102-M98)/MAX(M$94-M$93,1)*(M$4-M$93)) -> 0 | N106: =IF(N$4<N$93,0,N98+(N102-N98)/MAX(N$94-N$93,1)*(N$4-N$93)) -> 0 | O106: =IF(O$4<O$93,0,O98+(O102-O98)/MAX(O$94-O$93,1)*(O$4-O$93)) -> 0 | P106: =IF(P$4<P$93,0,P98+(P102-P98)/MAX(P$94-P$93,1)*(P$4-P$93)) -> 0 | Q106: =IF(Q$4<Q$93,0,Q98+(Q102-Q98)/MAX(Q$94-Q$93,1)*(Q$4-Q$93)) -> 0 | R106: =IF(R$4<R$93,0,R98+(R102-R98)/MAX(R$94-R$93,1)*(R$4-R$93)) -> 0 | S106: =IF(S$4<S$93,0,S98+(S102-S98)/MAX(S$94-S$93,1)*(S$4-S$93)) -> 0 | T106: =IF(T$4<T$93,0,T98+(T102-T98)/MAX(T$94-T$93,1)*(T$4-T$93)) -> 0 | ... Z106: =IF(Z$4<Z$93,0,Z98+(Z102-Z98)/MAX(Z$94-Z$93,1)*(Z$4-Z$93)) -> 0 | AB106: =LOWER(Settings!$C$4)&".mit."&$A106&IF($C106="","","."&$C106&"."&$B106)&IF(INDEX(Variables!$D$5:$D$65,MATCH($A106,Variables!$A$5:$A$65,0))="","","."&INDEX(Variables!$D$5:$D$65,MATCH($A106,Variables!$A$5:$A$65,0)))&"."&AB$5 -> egy.mit.fb.ind.all.2 | AC106: =IF(AC$4<AC$93,0,AC98+(AC102-AC98)/MAX(AC$94-AC$93,1)*(AC$4-AC$93)) -> 0 | AD106: =IF(AD$4<AD$93,0,AD98+(AD102-AD98)/MAX(AD$94-AD$93,1)*(AD$4-AD$93)) -> 0 | AE106: =IF(AE$4<AE$93,0,AE98+(AE102-AE98)/MAX(AE$94-AE$93,1)*(AE$4-AE$93)) -> 0 | AF106: =IF(AF$4<AF$93,0,AF98+(AF102-AF98)/MAX(AF$94-AF$93,1)*(AF$4-AF$93)) -> 0 | AG106: =IF(AG$4<AG$93,0,AG98+(AG102-AG98)/MAX(AG$94-AG$93,1)*(AG$4-AG$93)) -> 0 | AH106: =IF(AH$4<AH$93,0,AH98+(AH102-AH98)/MAX(AH$94-AH$93,1)*(AH$4-AH$93)) -> 0 | AI106: =IF(AI$4<AI$93,0,AI98+(AI102-AI98)/MAX(AI$94-AI$93,1)*(AI$4-AI$93)) -> 0 | AJ106: =IF(AJ$4<AJ$93,0,AJ98+(AJ102-AJ98)/MAX(AJ$94-AJ$93,1)*(AJ$4-AJ$93)) -> 0 | ... AP106: =IF(AP$4<AP$93,0,AP98+(AP102-AP98)/MAX(AP$94-AP$93,1)*(AP$4-AP$93)) -> 0
H107: Feebates sector coverage (MTInputs rows 66-82)
A108: fbcov | B108: all | C108: pow | D108: 66 | H108: =INDEX(Variables!$B$5:$B$65,MATCH($A108,Variables!$A$5:$A$65,0))&IF($C108="",""," | "&INDEX(Mapping!$B$5:$B$26,MATCH($C108,Mapping!$A$5:$A$26,0))&" | "&INDEX(Mapping!$B$30:$B$41,MATCH($B108,Mapping!$A$30:$A$41,0))) -> Feebates sector coverage (Apply?) | Power | All fuels | I108: =INDEX(Variables!$C$5:$C$65,MATCH($A108,Variables!$A$5:$A$65,0)) -> switch | J108: =INDEX(Variables!$E$5:$E$65,MATCH($A108,Variables!$A$5:$A$65,0)) -> MTInputs (scenario column) | L108: =LOWER(Settings!$C$4)&".mit."&$A108&IF($C108="","","."&$C108&"."&$B108)&IF(INDEX(Variables!$D$5:$D$65,MATCH($A108,Variables!$A$5:$A$65,0))="","","."&INDEX(Variables!$D$5:$D$65,MATCH($A108,Variables!$A$5:$A$65,0)))&"."&L$5 -> egy.mit.fbcov.pow.all.1 | M108: =INDEX(MTInputs!$J$1:$AZ$415,$D108,MATCH(M$5,MTInputs!$J$5:$AZ$5,0)) -> FALSE | N108: =INDEX(MTInputs!$J$1:$AZ$415,$D108,MATCH(N$5,MTInputs!$J$5:$AZ$5,0)) -> FALSE | O108: =INDEX(MTInputs!$J$1:$AZ$415,$D108,MATCH(O$5,MTInputs!$J$5:$AZ$5,0)) -> FALSE | P108: =INDEX(MTInputs!$J$1:$AZ$415,$D108,MATCH(P$5,MTInputs!$J$5:$AZ$5,0)) -> FALSE | Q108: =INDEX(MTInputs!$J$1:$AZ$415,$D108,MATCH(Q$5,MTInputs!$J$5:$AZ$5,0)) -> FALSE | R108: =INDEX(MTInputs!$J$1:$AZ$415,$D108,MATCH(R$5,MTInputs!$J$5:$AZ$5,0)) -> FALSE | S108: =INDEX(MTInputs!$J$1:$AZ$415,$D108,MATCH(S$5,MTInputs!$J$5:$AZ$5,0)) -> FALSE | T108: =INDEX(MTInputs!$J$1:$AZ$415,$D108,MATCH(T$5,MTInputs!$J$5:$AZ$5,0)) -> FALSE | ... Z108: =INDEX(MTInputs!$J$1:$AZ$415,$D108,MATCH(Z$5,MTInputs!$J$5:$AZ$5,0)) -> FALSE | AB108: =LOWER(Settings!$C$4)&".mit."&$A108&IF($C108="","","."&$C108&"."&$B108)&IF(INDEX(Variables!$D$5:$D$65,MATCH($A108,Variables!$A$5:$A$65,0))="","","."&INDEX(Variables!$D$5:$D$65,MATCH($A108,Variables!$A$5:$A$65,0)))&"."&AB$5 -> egy.mit.fbcov.pow.all.2 | AC108: =INDEX(MTInputs!$J$1:$AZ$415,$D108,MATCH(AC$5,MTInputs!$J$5:$AZ$5,0)) -> FALSE | AD108: =INDEX(MTInputs!$J$1:$AZ$415,$D108,MATCH(AD$5,MTInputs!$J$5:$AZ$5,0)) -> FALSE | AE108: =INDEX(MTInputs!$J$1:$AZ$415,$D108,MATCH(AE$5,MTInputs!$J$5:$AZ$5,0)) -> FALSE | AF108: =INDEX(MTInputs!$J$1:$AZ$415,$D108,MATCH(AF$5,MTInputs!$J$5:$AZ$5,0)) -> FALSE | AG108: =INDEX(MTInputs!$J$1:$AZ$415,$D108,MATCH(AG$5,MTInputs!$J$5:$AZ$5,0)) -> FALSE | AH108: =INDEX(MTInputs!$J$1:$AZ$415,$D108,MATCH(AH$5,MTInputs!$J$5:$AZ$5,0)) -> FALSE | AI108: =INDEX(MTInputs!$J$1:$AZ$415,$D108,MATCH(AI$5,MTInputs!$J$5:$AZ$5,0)) -> FALSE | AJ108: =INDEX(MTInputs!$J$1:$AZ$415,$D108,MATCH(AJ$5,MTInputs!$J$5:$AZ$5,0)) -> FALSE | ... AP108: =INDEX(MTInputs!$J$1:$AZ$415,$D108,MATCH(AP$5,MTInputs!$J$5:$AZ$5,0)) -> FALSE
A109: fbcov | B109: all | C109: rod | D109: 67 | H109: =INDEX(Variables!$B$5:$B$65,MATCH($A109,Variables!$A$5:$A$65,0))&IF($C109="",""," | "&INDEX(Mapping!$B$5:$B$26,MATCH($C109,Mapping!$A$5:$A$26,0))&" | "&INDEX(Mapping!$B$30:$B$41,MATCH($B109,Mapping!$A$30:$A$41,0))) -> Feebates sector coverage (Apply?) | Road | All fuels | I109: =INDEX(Variables!$C$5:$C$65,MATCH($A109,Variables!$A$5:$A$65,0)) -> switch | J109: =INDEX(Variables!$E$5:$E$65,MATCH($A109,Variables!$A$5:$A$65,0)) -> MTInputs (scenario column) | L109: =LOWER(Settings!$C$4)&".mit."&$A109&IF($C109="","","."&$C109&"."&$B109)&IF(INDEX(Variables!$D$5:$D$65,MATCH($A109,Variables!$A$5:$A$65,0))="","","."&INDEX(Variables!$D$5:$D$65,MATCH($A109,Variables!$A$5:$A$65,0)))&"."&L$5 -> egy.mit.fbcov.rod.all.1 | M109: =INDEX(MTInputs!$J$1:$AZ$415,$D109,MATCH(M$5,MTInputs!$J$5:$AZ$5,0)) -> FALSE | N109: =INDEX(MTInputs!$J$1:$AZ$415,$D109,MATCH(N$5,MTInputs!$J$5:$AZ$5,0)) -> FALSE | O109: =INDEX(MTInputs!$J$1:$AZ$415,$D109,MATCH(O$5,MTInputs!$J$5:$AZ$5,0)) -> FALSE | P109: =INDEX(MTInputs!$J$1:$AZ$415,$D109,MATCH(P$5,MTInputs!$J$5:$AZ$5,0)) -> FALSE | Q109: =INDEX(MTInputs!$J$1:$AZ$415,$D109,MATCH(Q$5,MTInputs!$J$5:$AZ$5,0)) -> FALSE | R109: =INDEX(MTInputs!$J$1:$AZ$415,$D109,MATCH(R$5,MTInputs!$J$5:$AZ$5,0)) -> FALSE | S109: =INDEX(MTInputs!$J$1:$AZ$415,$D109,MATCH(S$5,MTInputs!$J$5:$AZ$5,0)) -> FALSE | T109: =INDEX(MTInputs!$J$1:$AZ$415,$D109,MATCH(T$5,MTInputs!$J$5:$AZ$5,0)) -> FALSE | ... Z109: =INDEX(MTInputs!$J$1:$AZ$415,$D109,MATCH(Z$5,MTInputs!$J$5:$AZ$5,0)) -> FALSE | AB109: =LOWER(Settings!$C$4)&".mit."&$A109&IF($C109="","","."&$C109&"."&$B109)&IF(INDEX(Variables!$D$5:$D$65,MATCH($A109,Variables!$A$5:$A$65,0))="","","."&INDEX(Variables!$D$5:$D$65,MATCH($A109,Variables!$A$5:$A$65,0)))&"."&AB$5 -> egy.mit.fbcov.rod.all.2 | AC109: =INDEX(MTInputs!$J$1:$AZ$415,$D109,MATCH(AC$5,MTInputs!$J$5:$AZ$5,0)) -> FALSE | AD109: =INDEX(MTInputs!$J$1:$AZ$415,$D109,MATCH(AD$5,MTInputs!$J$5:$AZ$5,0)) -> FALSE | AE109: =INDEX(MTInputs!$J$1:$AZ$415,$D109,MATCH(AE$5,MTInputs!$J$5:$AZ$5,0)) -> FALSE | AF109: =INDEX(MTInputs!$J$1:$AZ$415,$D109,MATCH(AF$5,MTInputs!$J$5:$AZ$5,0)) -> FALSE | AG109: =INDEX(MTInputs!$J$1:$AZ$415,$D109,MATCH(AG$5,MTInputs!$J$5:$AZ$5,0)) -> FALSE | AH109: =INDEX(MTInputs!$J$1:$AZ$415,$D109,MATCH(AH$5,MTInputs!$J$5:$AZ$5,0)) -> FALSE | AI109: =INDEX(MTInputs!$J$1:$AZ$415,$D109,MATCH(AI$5,MTInputs!$J$5:$AZ$5,0)) -> FALSE | AJ109: =INDEX(MTInputs!$J$1:$AZ$415,$D109,MATCH(AJ$5,MTInputs!$J$5:$AZ$5,0)) -> FALSE | ... AP109: =INDEX(MTInputs!$J$1:$AZ$415,$D109,MATCH(AP$5,MTInputs!$J$5:$AZ$5,0)) -> FALSE
A110: fbcov | B110: all | C110: ral | D110: 68 | H110: =INDEX(Variables!$B$5:$B$65,MATCH($A110,Variables!$A$5:$A$65,0))&IF($C110="",""," | "&INDEX(Mapping!$B$5:$B$26,MATCH($C110,Mapping!$A$5:$A$26,0))&" | "&INDEX(Mapping!$B$30:$B$41,MATCH($B110,Mapping!$A$30:$A$41,0))) -> Feebates sector coverage (Apply?) | Rail | All fuels | I110: =INDEX(Variables!$C$5:$C$65,MATCH($A110,Variables!$A$5:$A$65,0)) -> switch | J110: =INDEX(Variables!$E$5:$E$65,MATCH($A110,Variables!$A$5:$A$65,0)) -> MTInputs (scenario column) | L110: =LOWER(Settings!$C$4)&".mit."&$A110&IF($C110="","","."&$C110&"."&$B110)&IF(INDEX(Variables!$D$5:$D$65,MATCH($A110,Variables!$A$5:$A$65,0))="","","."&INDEX(Variables!$D$5:$D$65,MATCH($A110,Variables!$A$5:$A$65,0)))&"."&L$5 -> egy.mit.fbcov.ral.all.1 | M110: =INDEX(MTInputs!$J$1:$AZ$415,$D110,MATCH(M$5,MTInputs!$J$5:$AZ$5,0)) -> FALSE | N110: =INDEX(MTInputs!$J$1:$AZ$415,$D110,MATCH(N$5,MTInputs!$J$5:$AZ$5,0)) -> FALSE | O110: =INDEX(MTInputs!$J$1:$AZ$415,$D110,MATCH(O$5,MTInputs!$J$5:$AZ$5,0)) -> FALSE | P110: =INDEX(MTInputs!$J$1:$AZ$415,$D110,MATCH(P$5,MTInputs!$J$5:$AZ$5,0)) -> FALSE | Q110: =INDEX(MTInputs!$J$1:$AZ$415,$D110,MATCH(Q$5,MTInputs!$J$5:$AZ$5,0)) -> FALSE | R110: =INDEX(MTInputs!$J$1:$AZ$415,$D110,MATCH(R$5,MTInputs!$J$5:$AZ$5,0)) -> FALSE | S110: =INDEX(MTInputs!$J$1:$AZ$415,$D110,MATCH(S$5,MTInputs!$J$5:$AZ$5,0)) -> FALSE | T110: =INDEX(MTInputs!$J$1:$AZ$415,$D110,MATCH(T$5,MTInputs!$J$5:$AZ$5,0)) -> FALSE | ... Z110: =INDEX(MTInputs!$J$1:$AZ$415,$D110,MATCH(Z$5,MTInputs!$J$5:$AZ$5,0)) -> FALSE | AB110: =LOWER(Settings!$C$4)&".mit."&$A110&IF($C110="","","."&$C110&"."&$B110)&IF(INDEX(Variables!$D$5:$D$65,MATCH($A110,Variables!$A$5:$A$65,0))="","","."&INDEX(Variables!$D$5:$D$65,MATCH($A110,Variables!$A$5:$A$65,0)))&"."&AB$5 -> egy.mit.fbcov.ral.all.2 | AC110: =INDEX(MTInputs!$J$1:$AZ$415,$D110,MATCH(AC$5,MTInputs!$J$5:$AZ$5,0)) -> FALSE | AD110: =INDEX(MTInputs!$J$1:$AZ$415,$D110,MATCH(AD$5,MTInputs!$J$5:$AZ$5,0)) -> FALSE | AE110: =INDEX(MTInputs!$J$1:$AZ$415,$D110,MATCH(AE$5,MTInputs!$J$5:$AZ$5,0)) -> FALSE | AF110: =INDEX(MTInputs!$J$1:$AZ$415,$D110,MATCH(AF$5,MTInputs!$J$5:$AZ$5,0)) -> FALSE | AG110: =INDEX(MTInputs!$J$1:$AZ$415,$D110,MATCH(AG$5,MTInputs!$J$5:$AZ$5,0)) -> FALSE | AH110: =INDEX(MTInputs!$J$1:$AZ$415,$D110,MATCH(AH$5,MTInputs!$J$5:$AZ$5,0)) -> FALSE | AI110: =INDEX(MTInputs!$J$1:$AZ$415,$D110,MATCH(AI$5,MTInputs!$J$5:$AZ$5,0)) -> FALSE | AJ110: =INDEX(MTInputs!$J$1:$AZ$415,$D110,MATCH(AJ$5,MTInputs!$J$5:$AZ$5,0)) -> FALSE | ... AP110: =INDEX(MTInputs!$J$1:$AZ$415,$D110,MATCH(AP$5,MTInputs!$J$5:$AZ$5,0)) -> FALSE
A111: fbcov | B111: all | C111: avi | D111: 69 | H111: =INDEX(Variables!$B$5:$B$65,MATCH($A111,Variables!$A$5:$A$65,0))&IF($C111="",""," | "&INDEX(Mapping!$B$5:$B$26,MATCH($C111,Mapping!$A$5:$A$26,0))&" | "&INDEX(Mapping!$B$30:$B$41,MATCH($B111,Mapping!$A$30:$A$41,0))) -> Feebates sector coverage (Apply?) | Domestic aviation | All fuels | I111: =INDEX(Variables!$C$5:$C$65,MATCH($A111,Variables!$A$5:$A$65,0)) -> switch | J111: =INDEX(Variables!$E$5:$E$65,MATCH($A111,Variables!$A$5:$A$65,0)) -> MTInputs (scenario column) | L111: =LOWER(Settings!$C$4)&".mit."&$A111&IF($C111="","","."&$C111&"."&$B111)&IF(INDEX(Variables!$D$5:$D$65,MATCH($A111,Variables!$A$5:$A$65,0))="","","."&INDEX(Variables!$D$5:$D$65,MATCH($A111,Variables!$A$5:$A$65,0)))&"."&L$5 -> egy.mit.fbcov.avi.all.1 | M111: =INDEX(MTInputs!$J$1:$AZ$415,$D111,MATCH(M$5,MTInputs!$J$5:$AZ$5,0)) -> FALSE | N111: =INDEX(MTInputs!$J$1:$AZ$415,$D111,MATCH(N$5,MTInputs!$J$5:$AZ$5,0)) -> FALSE | O111: =INDEX(MTInputs!$J$1:$AZ$415,$D111,MATCH(O$5,MTInputs!$J$5:$AZ$5,0)) -> FALSE | P111: =INDEX(MTInputs!$J$1:$AZ$415,$D111,MATCH(P$5,MTInputs!$J$5:$AZ$5,0)) -> FALSE | Q111: =INDEX(MTInputs!$J$1:$AZ$415,$D111,MATCH(Q$5,MTInputs!$J$5:$AZ$5,0)) -> FALSE | R111: =INDEX(MTInputs!$J$1:$AZ$415,$D111,MATCH(R$5,MTInputs!$J$5:$AZ$5,0)) -> FALSE | S111: =INDEX(MTInputs!$J$1:$AZ$415,$D111,MATCH(S$5,MTInputs!$J$5:$AZ$5,0)) -> FALSE | T111: =INDEX(MTInputs!$J$1:$AZ$415,$D111,MATCH(T$5,MTInputs!$J$5:$AZ$5,0)) -> FALSE | ... Z111: =INDEX(MTInputs!$J$1:$AZ$415,$D111,MATCH(Z$5,MTInputs!$J$5:$AZ$5,0)) -> FALSE | AB111: =LOWER(Settings!$C$4)&".mit."&$A111&IF($C111="","","."&$C111&"."&$B111)&IF(INDEX(Variables!$D$5:$D$65,MATCH($A111,Variables!$A$5:$A$65,0))="","","."&INDEX(Variables!$D$5:$D$65,MATCH($A111,Variables!$A$5:$A$65,0)))&"."&AB$5 -> egy.mit.fbcov.avi.all.2 | AC111: =INDEX(MTInputs!$J$1:$AZ$415,$D111,MATCH(AC$5,MTInputs!$J$5:$AZ$5,0)) -> FALSE | AD111: =INDEX(MTInputs!$J$1:$AZ$415,$D111,MATCH(AD$5,MTInputs!$J$5:$AZ$5,0)) -> FALSE | AE111: =INDEX(MTInputs!$J$1:$AZ$415,$D111,MATCH(AE$5,MTInputs!$J$5:$AZ$5,0)) -> FALSE | AF111: =INDEX(MTInputs!$J$1:$AZ$415,$D111,MATCH(AF$5,MTInputs!$J$5:$AZ$5,0)) -> FALSE | AG111: =INDEX(MTInputs!$J$1:$AZ$415,$D111,MATCH(AG$5,MTInputs!$J$5:$AZ$5,0)) -> FALSE | AH111: =INDEX(MTInputs!$J$1:$AZ$415,$D111,MATCH(AH$5,MTInputs!$J$5:$AZ$5,0)) -> FALSE | AI111: =INDEX(MTInputs!$J$1:$AZ$415,$D111,MATCH(AI$5,MTInputs!$J$5:$AZ$5,0)) -> FALSE | AJ111: =INDEX(MTInputs!$J$1:$AZ$415,$D111,MATCH(AJ$5,MTInputs!$J$5:$AZ$5,0)) -> FALSE | ... AP111: =INDEX(MTInputs!$J$1:$AZ$415,$D111,MATCH(AP$5,MTInputs!$J$5:$AZ$5,0)) -> FALSE
