Workbook

Sheet README
B2: Integrated MF-C tool — macro-fiscal and climate
B3: Version 0.1. 217 countries, 91 indicators, built from the Global Fiscal Indicators dashboard (v1.2 panel) and the mitigation investment needs models (v1.1 workbook, NMIM v0.2).
B5: What this is | C5: The integrated macro-fiscal climate (MF-C) tool. It puts the Global Fiscal Indicators dashboard and the mitigation investment needs models on one country page: what a country's net zero programme needs and costs, beside whether it can pay for it, build it, and finance it. More modules will be added. The is_ccdr column flags the 98 economies with a published Country Climate and Development Report.
B7: How it is organised | C7: Thirteen blocks, in reading order. Four ASSESSMENT blocks carry the diagnosis: fiscal space, delivery, cost of capital, and financing. Three CONTEXT blocks explain it: fossil revenue in the budget, fossil trade and extraction, and power generation. Two INVESTMENT blocks give the need: Investment 1 (2030 snapshot, by sector and cost-of-capital lens) and Investment 2 (who pays, and the path to 2050). They read High / Medium / Low, like the Context blocks. Four APPENDIX blocks - fuel pricing, power market regulation, macro-model inputs and the integrated scenario - are reference detail in grey and carry no block verdict.
B9: How to use it | C9: Dashboard: pick a country in the yellow cell. Everything resolves - evaluation, score, value, observation year, coverage - grouped and coloured by block. Data_wide is the cross-section, Data_long names the source file for every value, Scores holds the 1-10 rescaling, Spec is the indicator list, Sources lists the datasets.
B11: Reading the rows | C11: Indented italic rows are components of the line above: subsidies split into explicit and implicit, net fuel trade into exports and imports, fossil rents into oil, gas and coal, and the headline WACC into its cross-check sources. They are scored individually but they are not independent of their parent.
B13: Evaluation and score | C13: Every indicator carries a plain-word Evaluation beside a 1-10 Score. Good / Medium / Bad where a direction exists. High / Medium / Low where the number is a magnitude rather than a verdict. High or Low Exporter / Importer for net fuel trade, read off the value. Thresholds: 7 and above, 4 to 7, below 4.
B15: Context blocks are magnitudes | C15: The three Context blocks use High / Medium / Low, not Good / Bad. A country reading High on Context 2 has a large extraction and export position - read as opportunity that is revenue it could expand, read as exposure it is revenue the transition puts at risk. The file does not pick one.
B17: Do not build an index | C17: Block averages are given, but do not average across blocks into a single country score. There are no defensible weights between them, and it would erase the triage: a country weak on Fiscal needs different instruments from one weak on PIMA.
B19: Non-negotiables | C19: Nothing is imputed; missing stays missing. Every value carries its observation year, because vintages span five years - fiscal core 2024, capex execution mostly 2022, rents and WACC 2021. Scores are relative to the 217-country sample and move if the sample changes.
B21: Appendix blocks | C21: Appendix A gives retail prices by fuel and sector, all from CPAT and all 2024. Appendix B describes how the power sector is organised. Note the vintages: the PSRT market-structure and regulator flags are 2013 and non-OECD only, so read them as structural context, not current state; RISE scores are 2023 and cover 140 countries.
B23: Appendix C and D | C23: Appendix C holds the WEO ratios the macro-fiscal models start from (revenue, primary balance, investment, current account, average growth). Appendix D is MODEL OUTPUT, not data: the integrated scenario from MacroFiscalModels (investment needs from NMIM, feasible power-sector carbon pricing from PriceFeasibility, a macro model, LIC-DSF-lite), with illustrative calibrations. Read it as a scenario, never as an observation; its year is the scenario year.
B25: A caveat on electricity prices | C25: The two electricity price rows come from the same CPAT series behind the cost-recovery indicators that were dropped from this tool on data-quality grounds. Retail prices are closer to observed than the modelled supply costs were, and they are the input CPAT uses to compute subsidies - but treat them as reference values rather than evidence.
B27: Not included | C27: IMF PIMA and C-PIMA scores. Publication is consent-based and the published subsample self-selects toward better performers, so a scored column would understate weakness. PEFA PI-11 is the substitute. Electricity cost recovery was also dropped: the CPAT retail-price basis is not reliable enough to carry a scored column.
... B33: Overlap with Appendix D | C33: Appendix D's budget need is the incremental budget need from NMIM, as passed through MacroFiscalModels; Investment 2's is the budget need of the whole net zero programme. Use Investment 2 for size and composition, Appendix D for what it does to the budget and debt.

Sheet Dashboard
B2: Country profile
B4: Country | C4: Kenya | D4: =INDEX(Data_wide!$A$2:$A$218,MATCH($C$4,Data_wide!$B$2:$B$218,0)) | F4: =INDEX(Data_wide!$C$2:$C$218,MATCH($C$4,Data_wide!$B$2:$B$218,0))
B6: ="CCDR economy: "&IF(INDEX(Data_wide!$E$2:$E$218,MATCH($C$4,Data_wide!$B$2:$B$218,0))=TRUE,"yes","no")&" | indicators with data: "&COUNT(F9:F115)&" of 91"
B7: Pick a country above. ● marks the headline indicator for each block.
C8: Indicator | D8: Evaluation | E8: Score | F8: Value | G8: Year | H8: Direction | I8: Area | J8: Data source | K8: Cov. | L8: Data?
C9: Fiscal — Can they pay for it? | D9: =IFERROR(IF(E9>=7,"Good",IF(E9>=4,"Medium","Bad")),"") | E9: =IFERROR(ROUND(AVERAGE(E10:E13),1),"") | H9: Fiscal space | I9: Debt service and revenue capacity | L9: =COUNT(F10:F13)&"/4"
B10: ● | C10: Interest-to-revenue, general govt (%) | D10: =IF(E10="","",IF(E10>=7,"Good",IF(E10>=4,"Medium","Bad"))) | E10: =IFERROR(INDEX(Scores!$C$6:$C$222,MATCH($C$4,Scores!$B$6:$B$222,0)),"") | F10: =IFERROR(IF(INDEX(Data_wide!$F$2:$F$218,MATCH($C$4,Data_wide!$B$2:$B$218,0))="","",INDEX(Data_wide!$F$2:$F$218,MATCH($C$4,Data_wide!$B$2:$B$218,0))),"") | G10: =IFERROR(IF(INDEX(Data_wide!$CS$2:$CS$218,MATCH($C$4,Data_wide!$B$2:$B$218,0))="","",INDEX(Data_wide!$CS$2:$CS$218,MATCH($C$4,Data_wide!$B$2:$B$218,0))),"") | H10: High = worse | I10: Debt service burden | J10: IMF WEO (derived) | K10: 184 | L10: =IF(F10="","-","Yes")
C11: Interest payments (net), general govt (% GDP) | D11: =IF(E11="","",IF(E11>=7,"Good",IF(E11>=4,"Medium","Bad"))) | E11: =IFERROR(INDEX(Scores!$D$6:$D$222,MATCH($C$4,Scores!$B$6:$B$222,0)),"") | F11: =IFERROR(IF(INDEX(Data_wide!$G$2:$G$218,MATCH($C$4,Data_wide!$B$2:$B$218,0))="","",INDEX(Data_wide!$G$2:$G$218,MATCH($C$4,Data_wide!$B$2:$B$218,0))),"") | G11: =IFERROR(IF(INDEX(Data_wide!$CT$2:$CT$218,MATCH($C$4,Data_wide!$B$2:$B$218,0))="","",INDEX(Data_wide!$CT$2:$CT$218,MATCH($C$4,Data_wide!$B$2:$B$218,0))),"") | H11: High = worse | I11: Debt service burden | J11: IMF WEO (derived) | K11: 189 | L11: =IF(F11="","-","Yes")
C12: Gross debt, general govt (% GDP) | D12: =IF(E12="","",IF(E12>=7,"Good",IF(E12>=4,"Medium","Bad"))) | E12: =IFERROR(INDEX(Scores!$E$6:$E$222,MATCH($C$4,Scores!$B$6:$B$222,0)),"") | F12: =IFERROR(IF(INDEX(Data_wide!$H$2:$H$218,MATCH($C$4,Data_wide!$B$2:$B$218,0))="","",INDEX(Data_wide!$H$2:$H$218,MATCH($C$4,Data_wide!$B$2:$B$218,0))),"") | G12: =IFERROR(IF(INDEX(Data_wide!$CU$2:$CU$218,MATCH($C$4,Data_wide!$B$2:$B$218,0))="","",INDEX(Data_wide!$CU$2:$CU$218,MATCH($C$4,Data_wide!$B$2:$B$218,0))),"") | H12: High = worse | I12: Fiscal space | J12: IMF WEO | K12: 191 | L12: =IF(F12="","-","Yes")
C13: Tax revenue (% GDP) | D13: =IF(E13="","",IF(E13>=7,"Good",IF(E13>=4,"Medium","Bad"))) | E13: =IFERROR(INDEX(Scores!$F$6:$F$222,MATCH($C$4,Scores!$B$6:$B$222,0)),"") | F13: =IFERROR(IF(INDEX(Data_wide!$I$2:$I$218,MATCH($C$4,Data_wide!$B$2:$B$218,0))="","",INDEX(Data_wide!$I$2:$I$218,MATCH($C$4,Data_wide!$B$2:$B$218,0))),"") | G13: =IFERROR(IF(INDEX(Data_wide!$CV$2:$CV$218,MATCH($C$4,Data_wide!$B$2:$B$218,0))="","",INDEX(Data_wide!$CV$2:$CV$218,MATCH($C$4,Data_wide!$B$2:$B$218,0))),"") | H13: High = better | I13: Revenue capacity | J13: IMF WoRLD 2026 | K13: 193 | L13: =IF(F13="","-","Yes")
C14: PIMA — Can they build it? | D14: =IFERROR(IF(E14>=7,"Good",IF(E14>=4,"Medium","Bad")),"") | E14: =IFERROR(ROUND(AVERAGE(E15:E18),1),"") | H14: Delivery | I14: Execution capacity and institutions | L14: =COUNT(F15:F18)&"/4"
B15: ● | C15: Capital budget execution rate (%) | D15: =IF(E15="","",IF(E15>=7,"Good",IF(E15>=4,"Medium","Bad"))) | E15: =IFERROR(INDEX(Scores!$G$6:$G$222,MATCH($C$4,Scores!$B$6:$B$222,0)),"") | F15: =IFERROR(IF(INDEX(Data_wide!$J$2:$J$218,MATCH($C$4,Data_wide!$B$2:$B$218,0))="","",INDEX(Data_wide!$J$2:$J$218,MATCH($C$4,Data_wide!$B$2:$B$218,0))),"") | G15: =IFERROR(IF(INDEX(Data_wide!$CW$2:$CW$218,MATCH($C$4,Data_wide!$B$2:$B$218,0))="","",INDEX(Data_wide!$CW$2:$CW$218,MATCH($C$4,Data_wide!$B$2:$B$218,0))),"") | H15: High = better (>100 worse) | I15: Delivery capacity | J15: World Bank BOOST | K15: 104 | L15: =IF(F15="","-","Yes")
C16: PEFA PI-11, public investment management (1-4) | D16: =IF(E16="","",IF(E16>=7,"Good",IF(E16>=4,"Medium","Bad"))) | E16: =IFERROR(INDEX(Scores!$H$6:$H$222,MATCH($C$4,Scores!$B$6:$B$222,0)),"") | F16: =IFERROR(IF(INDEX(Data_wide!$K$2:$K$218,MATCH($C$4,Data_wide!$B$2:$B$218,0))="","",INDEX(Data_wide!$K$2:$K$218,MATCH($C$4,Data_wide!$B$2:$B$218,0))),"") | G16: =IFERROR(IF(INDEX(Data_wide!$CX$2:$CX$218,MATCH($C$4,Data_wide!$B$2:$B$218,0))="","",INDEX(Data_wide!$CX$2:$CX$218,MATCH($C$4,Data_wide!$B$2:$B$218,0))),"") | H16: High = better | I16: PIM quality | J16: PEFA 2016 framework | K16: 82 | L16: =IF(F16="","-","Yes")
C17: PEFA PI-12.2, asset monitoring (1-4) | D17: =IF(E17="","",IF(E17>=7,"Good",IF(E17>=4,"Medium","Bad"))) | E17: =IFERROR(INDEX(Scores!$I$6:$I$222,MATCH($C$4,Scores!$B$6:$B$222,0)),"") | F17: =IFERROR(IF(INDEX(Data_wide!$L$2:$L$218,MATCH($C$4,Data_wide!$B$2:$B$218,0))="","",INDEX(Data_wide!$L$2:$L$218,MATCH($C$4,Data_wide!$B$2:$B$218,0))),"") | G17: =IFERROR(IF(INDEX(Data_wide!$CY$2:$CY$218,MATCH($C$4,Data_wide!$B$2:$B$218,0))="","",INDEX(Data_wide!$CY$2:$CY$218,MATCH($C$4,Data_wide!$B$2:$B$218,0))),"") | H17: High = better | I17: Asset management | J17: PEFA 2016 framework | K17: 83 | L17: =IF(F17="","-","Yes")
C18: Climate-PFM diagnostic on record (0/1) | D18: =IF(E18="","",IF(E18>=7,"Good",IF(E18>=4,"Medium","Bad"))) | E18: =IFERROR(INDEX(Scores!$J$6:$J$222,MATCH($C$4,Scores!$B$6:$B$222,0)),"") | F18: =IFERROR(IF(INDEX(Data_wide!$M$2:$M$218,MATCH($C$4,Data_wide!$B$2:$B$218,0))="","",INDEX(Data_wide!$M$2:$M$218,MATCH($C$4,Data_wide!$B$2:$B$218,0))),"") | G18: =IFERROR(IF(INDEX(Data_wide!$CZ$2:$CZ$218,MATCH($C$4,Data_wide!$B$2:$B$218,0))="","",INDEX(Data_wide!$CZ$2:$CZ$218,MATCH($C$4,Data_wide!$B$2:$B$218,0))),"") | H18: High = better | I18: Institutional history | J18: UNDP Global Climate PFR 2022 | K18: 217 | L18: =IF(F18="","-","Yes")
C19: Finance 1 — What does capital cost them? | D19: =IFERROR(IF(E19>=7,"Good",IF(E19>=4,"Medium","Bad")),"") | E19: =IFERROR(ROUND(AVERAGE(E20:E26),1),"") | H19: Cost of capital | I19: Project WACC and borrowing terms | L19: =COUNT(F20:F26)&"/7"
B20: ● | C20: WACC, solar PV, real after-tax (%) | D20: =IF(E20="","",IF(E20>=7,"Good",IF(E20>=4,"Medium","Bad"))) | E20: =IFERROR(INDEX(Scores!$K$6:$K$222,MATCH($C$4,Scores!$B$6:$B$222,0)),"") | F20: =IFERROR(IF(INDEX(Data_wide!$N$2:$N$218,MATCH($C$4,Data_wide!$B$2:$B$218,0))="","",INDEX(Data_wide!$N$2:$N$218,MATCH($C$4,Data_wide!$B$2:$B$218,0))),"") | G20: =IFERROR(IF(INDEX(Data_wide!$DA$2:$DA$218,MATCH($C$4,Data_wide!$B$2:$B$218,0))="","",INDEX(Data_wide!$DA$2:$DA$218,MATCH($C$4,Data_wide!$B$2:$B$218,0))),"") | H20: High = worse | I20: RE cost of capital | J20: IRENA (2022), ref. yr 2021 | K20: 43 | L20: =IF(F20="","-","Yes")
C21: cross-check: WACC nominal after-tax (%) | D21: =IF(E21="","",IF(E21>=7,"Good",IF(E21>=4,"Medium","Bad"))) | E21: =IFERROR(INDEX(Scores!$L$6:$L$222,MATCH($C$4,Scores!$B$6:$B$222,0)),"") | F21: =IFERROR(IF(INDEX(Data_wide!$O$2:$O$218,MATCH($C$4,Data_wide!$B$2:$B$218,0))="","",INDEX(Data_wide!$O$2:$O$218,MATCH($C$4,Data_wide!$B$2:$B$218,0))),"") | G21: =IFERROR(IF(INDEX(Data_wide!$DB$2:$DB$218,MATCH($C$4,Data_wide!$B$2:$B$218,0))="","",INDEX(Data_wide!$DB$2:$DB$218,MATCH($C$4,Data_wide!$B$2:$B$218,0))),"") | H21: High = worse | I21: RE cost of capital | J21: Steffen et al. (2025) | K21: 64 | L21: =IF(F21="","-","Yes")
C22: cross-check: WACC evidence strength (0-3) | E22: =IFERROR(INDEX(Scores!$M$6:$M$222,MATCH($C$4,Scores!$B$6:$B$222,0)),"") | F22: =IFERROR(IF(INDEX(Data_wide!$P$2:$P$218,MATCH($C$4,Data_wide!$B$2:$B$218,0))="","",INDEX(Data_wide!$P$2:$P$218,MATCH($C$4,Data_wide!$B$2:$B$218,0))),"") | G22: =IFERROR(IF(INDEX(Data_wide!$DC$2:$DC$218,MATCH($C$4,Data_wide!$B$2:$B$218,0))="","",INDEX(Data_wide!$DC$2:$DC$218,MATCH($C$4,Data_wide!$B$2:$B$218,0))),"") | H22: Not evaluated | I22: Data quality, not performance | J22: IRENA / Steffen / IEA | K22: 84 | L22: =IF(F22="","-","Yes")
C23: cross-check: IEA Observatory available (0/1) | E23: =IFERROR(INDEX(Scores!$N$6:$N$222,MATCH($C$4,Scores!$B$6:$B$222,0)),"") | F23: =IFERROR(IF(INDEX(Data_wide!$Q$2:$Q$218,MATCH($C$4,Data_wide!$B$2:$B$218,0))="","",INDEX(Data_wide!$Q$2:$Q$218,MATCH($C$4,Data_wide!$B$2:$B$218,0))),"") | G23: =IFERROR(IF(INDEX(Data_wide!$DD$2:$DD$218,MATCH($C$4,Data_wide!$B$2:$B$218,0))="","",INDEX(Data_wide!$DD$2:$DD$218,MATCH($C$4,Data_wide!$B$2:$B$218,0))),"") | H23: Not evaluated | I23: Data quality, not performance | J23: IEA CofC Observatory | K23: 9 | L23: =IF(F23="","-","Yes")
C24: Official-private rate spread (pp) | D24: =IF(E24="","",IF(E24>=7,"Good",IF(E24>=4,"Medium","Bad"))) | E24: =IFERROR(INDEX(Scores!$O$6:$O$222,MATCH($C$4,Scores!$B$6:$B$222,0)),"") | F24: =IFERROR(IF(INDEX(Data_wide!$R$2:$R$218,MATCH($C$4,Data_wide!$B$2:$B$218,0))="","",INDEX(Data_wide!$R$2:$R$218,MATCH($C$4,Data_wide!$B$2:$B$218,0))),"") | G24: =IFERROR(IF(INDEX(Data_wide!$DE$2:$DE$218,MATCH($C$4,Data_wide!$B$2:$B$218,0))="","",INDEX(Data_wide!$DE$2:$DE$218,MATCH($C$4,Data_wide!$B$2:$B$218,0))),"") | H24: High = worse | I24: Value of a guarantee | J24: IDS DT.INR.PRVT less OFFT | K24: 88 | L24: =IF(F24="","-","Yes")
C25: Private creditor interest rate (%) | D25: =IF(E25="","",IF(E25>=7,"Good",IF(E25>=4,"Medium","Bad"))) | E25: =IFERROR(INDEX(Scores!$P$6:$P$222,MATCH($C$4,Scores!$B$6:$B$222,0)),"") | F25: =IFERROR(IF(INDEX(Data_wide!$S$2:$S$218,MATCH($C$4,Data_wide!$B$2:$B$218,0))="","",INDEX(Data_wide!$S$2:$S$218,MATCH($C$4,Data_wide!$B$2:$B$218,0))),"") | G25: =IFERROR(IF(INDEX(Data_wide!$DF$2:$DF$218,MATCH($C$4,Data_wide!$B$2:$B$218,0))="","",INDEX(Data_wide!$DF$2:$DF$218,MATCH($C$4,Data_wide!$B$2:$B$218,0))),"") | H25: High = worse | I25: Market cost of borrowing | J25: IDS DT.INR.PRVT | K25: 88 | L25: =IF(F25="","-","Yes")
C26: Avg maturity, new commitments (yrs) | D26: =IF(E26="","",IF(E26>=7,"Good",IF(E26>=4,"Medium","Bad"))) | E26: =IFERROR(INDEX(Scores!$Q$6:$Q$222,MATCH($C$4,Scores!$B$6:$B$222,0)),"") | F26: =IFERROR(IF(INDEX(Data_wide!$T$2:$T$218,MATCH($C$4,Data_wide!$B$2:$B$218,0))="","",INDEX(Data_wide!$T$2:$T$218,MATCH($C$4,Data_wide!$B$2:$B$218,0))),"") | G26: =IFERROR(IF(INDEX(Data_wide!$DG$2:$DG$218,MATCH($C$4,Data_wide!$B$2:$B$218,0))="","",INDEX(Data_wide!$DG$2:$DG$218,MATCH($C$4,Data_wide!$B$2:$B$218,0))),"") | H26: High = better | I26: Borrowing terms | J26: IDS DT.MAT.DPPG | K26: 118 | L26: =IF(F26="","-","Yes")
C27: Finance 2 — Who finances it, and what risk does the budget carry? | D27: =IFERROR(IF(E27>=7,"Good",IF(E27>=4,"Medium","Bad")),"") | E27: =IFERROR(ROUND(AVERAGE(E28:E33),1),"") | H27: Financing and risk | I27: Creditors, exposure and mobilisation | L27: =COUNT(F28:F33)&"/6"
B28: ● | C28: Mitigation finance received (% GDP) | D28: =IF(E28="","",IF(E28>=7,"High",IF(E28>=4,"Medium","Low"))) | E28: =IFERROR(INDEX(Scores!$R$6:$R$222,MATCH($C$4,Scores!$B$6:$B$222,0)),"") | F28: =IFERROR(IF(INDEX(Data_wide!$U$2:$U$218,MATCH($C$4,Data_wide!$B$2:$B$218,0))="","",INDEX(Data_wide!$U$2:$U$218,MATCH($C$4,Data_wide!$B$2:$B$218,0))),"") | G28: =IFERROR(IF(INDEX(Data_wide!$DH$2:$DH$218,MATCH($C$4,Data_wide!$B$2:$B$218,0))="","",INDEX(Data_wide!$DH$2:$DH$218,MATCH($C$4,Data_wide!$B$2:$B$218,0))),"") | H28: High = more inflows | I28: Climate finance inflows | J28: OECD CRDF (recipient) + WEO | K28: 133 | L28: =IF(F28="","-","Yes")
C29: Multilateral share of PPG debt (%) | D29: =IF(E29="","",IF(E29>=7,"High",IF(E29>=4,"Medium","Low"))) | E29: =IFERROR(INDEX(Scores!$S$6:$S$222,MATCH($C$4,Scores!$B$6:$B$222,0)),"") | F29: =IFERROR(IF(INDEX(Data_wide!$V$2:$V$218,MATCH($C$4,Data_wide!$B$2:$B$218,0))="","",INDEX(Data_wide!$V$2:$V$218,MATCH($C$4,Data_wide!$B$2:$B$218,0))),"") | G29: =IFERROR(IF(INDEX(Data_wide!$DI$2:$DI$218,MATCH($C$4,Data_wide!$B$2:$B$218,0))="","",INDEX(Data_wide!$DI$2:$DI$218,MATCH($C$4,Data_wide!$B$2:$B$218,0))),"") | H29: High = more concessional | I29: Creditor mix - triage | J29: IDS DT.DOD.MLAT/DPPG | K29: 120 | L29: =IF(F29="","-","Yes")
C30: Private creditor share of PPG debt (%) | D30: =IF(E30="","",IF(E30>=7,"High",IF(E30>=4,"Medium","Low"))) | E30: =IFERROR(INDEX(Scores!$T$6:$T$222,MATCH($C$4,Scores!$B$6:$B$222,0)),"") | F30: =IFERROR(IF(INDEX(Data_wide!$W$2:$W$218,MATCH($C$4,Data_wide!$B$2:$B$218,0))="","",INDEX(Data_wide!$W$2:$W$218,MATCH($C$4,Data_wide!$B$2:$B$218,0))),"") | G30: =IFERROR(IF(INDEX(Data_wide!$DJ$2:$DJ$218,MATCH($C$4,Data_wide!$B$2:$B$218,0))="","",INDEX(Data_wide!$DJ$2:$DJ$218,MATCH($C$4,Data_wide!$B$2:$B$218,0))),"") | H30: High = more market-financed | I30: Creditor mix - triage | J30: IDS DT.DOD.PRVT/DPPG | K30: 107 | L30: =IF(F30="","-","Yes")
C31: USD share of PPG debt (%) | D31: =IF(E31="","",IF(E31>=7,"Good",IF(E31>=4,"Medium","Bad"))) | E31: =IFERROR(INDEX(Scores!$U$6:$U$222,MATCH($C$4,Scores!$B$6:$B$222,0)),"") | F31: =IFERROR(IF(INDEX(Data_wide!$X$2:$X$218,MATCH($C$4,Data_wide!$B$2:$B$218,0))="","",INDEX(Data_wide!$X$2:$X$218,MATCH($C$4,Data_wide!$B$2:$B$218,0))),"") | G31: =IFERROR(IF(INDEX(Data_wide!$DK$2:$DK$218,MATCH($C$4,Data_wide!$B$2:$B$218,0))="","",INDEX(Data_wide!$DK$2:$DK$218,MATCH($C$4,Data_wide!$B$2:$B$218,0))),"") | H31: High = worse | I31: FX exposure | J31: IDS DT.CUR.USDL.ZS | K31: 120 | L31: =IF(F31="","-","Yes")
C32: PEFA PI-10.3, contingent liabilities (1-4) | D32: =IF(E32="","",IF(E32>=7,"Good",IF(E32>=4,"Medium","Bad"))) | E32: =IFERROR(INDEX(Scores!$V$6:$V$222,MATCH($C$4,Scores!$B$6:$B$222,0)),"") | F32: =IFERROR(IF(INDEX(Data_wide!$Y$2:$Y$218,MATCH($C$4,Data_wide!$B$2:$B$218,0))="","",INDEX(Data_wide!$Y$2:$Y$218,MATCH($C$4,Data_wide!$B$2:$B$218,0))),"") | G32: =IFERROR(IF(INDEX(Data_wide!$DL$2:$DL$218,MATCH($C$4,Data_wide!$B$2:$B$218,0))="","",INDEX(Data_wide!$DL$2:$DL$218,MATCH($C$4,Data_wide!$B$2:$B$218,0))),"") | H32: High = better | I32: Fiscal risk disclosure | J32: PEFA 2016 framework | K32: 82 | L32: =IF(F32="","-","Yes")
C33: PPI investment commitments (% GDP) | D33: =IF(E33="","",IF(E33>=7,"Good",IF(E33>=4,"Medium","Bad"))) | E33: =IFERROR(INDEX(Scores!$W$6:$W$222,MATCH($C$4,Scores!$B$6:$B$222,0)),"") | F33: =IFERROR(IF(INDEX(Data_wide!$Z$2:$Z$218,MATCH($C$4,Data_wide!$B$2:$B$218,0))="","",INDEX(Data_wide!$Z$2:$Z$218,MATCH($C$4,Data_wide!$B$2:$B$218,0))),"") | G33: =IFERROR(IF(INDEX(Data_wide!$DM$2:$DM$218,MATCH($C$4,Data_wide!$B$2:$B$218,0))="","",INDEX(Data_wide!$DM$2:$DM$218,MATCH($C$4,Data_wide!$B$2:$B$218,0))),"") | H33: High = better | I33: Private mobilisation | J33: World Bank PPI + WEO | K33: 93 | L33: =IF(F33="","-","Yes")
C34: Context 1 — How much fossil and climate money runs through the budget? | D34: =IFERROR(IF(E34>=7,"High",IF(E34>=4,"Medium","Low")),"") | E34: =IFERROR(ROUND(AVERAGE(E35:E39),1),"") | H34: Fossil and climate fiscal | I34: Energy taxes levied, subsidies paid, environment spending | L34: =COUNT(F35:F39)&"/5"
B35: ● | C35: Excise revenue (% of total revenue) | D35: =IF(E35="","",IF(E35>=7,"High",IF(E35>=4,"Medium","Low"))) | E35: =IFERROR(INDEX(Scores!$X$6:$X$222,MATCH($C$4,Scores!$B$6:$B$222,0)),"") | F35: =IFERROR(IF(INDEX(Data_wide!$AA$2:$AA$218,MATCH($C$4,Data_wide!$B$2:$B$218,0))="","",INDEX(Data_wide!$AA$2:$AA$218,MATCH($C$4,Data_wide!$B$2:$B$218,0))),"") | G35: =IFERROR(IF(INDEX(Data_wide!$DN$2:$DN$218,MATCH($C$4,Data_wide!$B$2:$B$218,0))="","",INDEX(Data_wide!$DN$2:$DN$218,MATCH($C$4,Data_wide!$B$2:$B$218,0))),"") | H35: High = more already taxed | I35: Energy tax already levied | J35: IMF WoRLD 2026 | K35: 163 | L35: =IF(F35="","-","Yes")
C36: Fossil fuel subsidies, total (% GDP) | D36: =IF(E36="","",IF(E36>=7,"High",IF(E36>=4,"Medium","Low"))) | E36: =IFERROR(INDEX(Scores!$Y$6:$Y$222,MATCH($C$4,Scores!$B$6:$B$222,0)),"") | F36: =IFERROR(IF(INDEX(Data_wide!$AB$2:$AB$218,MATCH($C$4,Data_wide!$B$2:$B$218,0))="","",INDEX(Data_wide!$AB$2:$AB$218,MATCH($C$4,Data_wide!$B$2:$B$218,0))),"") | G36: =IFERROR(IF(INDEX(Data_wide!$DO$2:$DO$218,MATCH($C$4,Data_wide!$B$2:$B$218,0))="","",INDEX(Data_wide!$DO$2:$DO$218,MATCH($C$4,Data_wide!$B$2:$B$218,0))),"") | H36: High = more forgone | I36: Revenue forgone at home | J36: IMF FFS (CPAT) + WEO | K36: 185 | L36: =IF(F36="","-","Yes")
C37: of which: explicit (% GDP) | D37: =IF(E37="","",IF(E37>=7,"High",IF(E37>=4,"Medium","Low"))) | E37: =IFERROR(INDEX(Scores!$Z$6:$Z$222,MATCH($C$4,Scores!$B$6:$B$222,0)),"") | F37: =IFERROR(IF(INDEX(Data_wide!$AC$2:$AC$218,MATCH($C$4,Data_wide!$B$2:$B$218,0))="","",INDEX(Data_wide!$AC$2:$AC$218,MATCH($C$4,Data_wide!$B$2:$B$218,0))),"") | G37: =IFERROR(IF(INDEX(Data_wide!$DP$2:$DP$218,MATCH($C$4,Data_wide!$B$2:$B$218,0))="","",INDEX(Data_wide!$DP$2:$DP$218,MATCH($C$4,Data_wide!$B$2:$B$218,0))),"") | H37: High = more forgone | I37: Revenue forgone at home | J37: IMF FFS (CPAT) + WEO | K37: 185 | L37: =IF(F37="","-","Yes")
C38: of which: implicit (% GDP) | D38: =IF(E38="","",IF(E38>=7,"High",IF(E38>=4,"Medium","Low"))) | E38: =IFERROR(INDEX(Scores!$AA$6:$AA$222,MATCH($C$4,Scores!$B$6:$B$222,0)),"") | F38: =IFERROR(IF(INDEX(Data_wide!$AD$2:$AD$218,MATCH($C$4,Data_wide!$B$2:$B$218,0))="","",INDEX(Data_wide!$AD$2:$AD$218,MATCH($C$4,Data_wide!$B$2:$B$218,0))),"") | G38: =IFERROR(IF(INDEX(Data_wide!$DQ$2:$DQ$218,MATCH($C$4,Data_wide!$B$2:$B$218,0))="","",INDEX(Data_wide!$DQ$2:$DQ$218,MATCH($C$4,Data_wide!$B$2:$B$218,0))),"") | H38: High = more forgone | I38: Revenue forgone at home | J38: IMF FFS (CPAT) + WEO | K38: 185 | L38: =IF(F38="","-","Yes")
C39: Environment protection (% of expenditure) | D39: =IF(E39="","",IF(E39>=7,"High",IF(E39>=4,"Medium","Low"))) | E39: =IFERROR(INDEX(Scores!$AB$6:$AB$222,MATCH($C$4,Scores!$B$6:$B$222,0)),"") | F39: =IFERROR(IF(INDEX(Data_wide!$AE$2:$AE$218,MATCH($C$4,Data_wide!$B$2:$B$218,0))="","",INDEX(Data_wide!$AE$2:$AE$218,MATCH($C$4,Data_wide!$B$2:$B$218,0))),"") | G39: =IFERROR(IF(INDEX(Data_wide!$DR$2:$DR$218,MATCH($C$4,Data_wide!$B$2:$B$218,0))="","",INDEX(Data_wide!$DR$2:$DR$218,MATCH($C$4,Data_wide!$B$2:$B$218,0))),"") | H39: High = more climate spending | I39: Climate-relevant spending | J39: World Bank BOOST COFOG 705 | K39: 150 | L39: =IF(F39="","-","Yes")
C40: Context 2 — Does the country sell fossil fuels, or buy them? | D40: =IFERROR(IF(E40>=7,"High",IF(E40>=4,"Medium","Low")),"") | E40: =IFERROR(ROUND(AVERAGE(E41:E48),1),"") | H40: Fossil trade and extraction | I40: Rents, exports, imports and dependency | L40: =COUNT(F41:F48)&"/8"
B41: ● | C41: Net fuel trade (% merch. trade) | D41: =IF(F41="","",IF(F41>20,"High Exporter",IF(F41>0,"Low Exporter",IF(F41>=-20,"Low Importer","High Importer")))) | E41: =IFERROR(INDEX(Scores!$AC$6:$AC$222,MATCH($C$4,Scores!$B$6:$B$222,0)),"") | F41: =IFERROR(IF(INDEX(Data_wide!$AF$2:$AF$218,MATCH($C$4,Data_wide!$B$2:$B$218,0))="","",INDEX(Data_wide!$AF$2:$AF$218,MATCH($C$4,Data_wide!$B$2:$B$218,0))),"") | G41: =IFERROR(IF(INDEX(Data_wide!$DS$2:$DS$218,MATCH($C$4,Data_wide!$B$2:$B$218,0))="","",INDEX(Data_wide!$DS$2:$DS$218,MATCH($C$4,Data_wide!$B$2:$B$218,0))),"") | H41: + = exporter, - = importer | I41: Importer / exporter position | J41: WDI TX less TM.VAL.FUEL | K41: 197 | L41: =IF(F41="","-","Yes")
C42: of which: fuel exports (% merch. exports) | D42: =IF(E42="","",IF(E42>=7,"High",IF(E42>=4,"Medium","Low"))) | E42: =IFERROR(INDEX(Scores!$AD$6:$AD$222,MATCH($C$4,Scores!$B$6:$B$222,0)),"") | F42: =IFERROR(IF(INDEX(Data_wide!$AG$2:$AG$218,MATCH($C$4,Data_wide!$B$2:$B$218,0))="","",INDEX(Data_wide!$AG$2:$AG$218,MATCH($C$4,Data_wide!$B$2:$B$218,0))),"") | G42: =IFERROR(IF(INDEX(Data_wide!$DT$2:$DT$218,MATCH($C$4,Data_wide!$B$2:$B$218,0))="","",INDEX(Data_wide!$DT$2:$DT$218,MATCH($C$4,Data_wide!$B$2:$B$218,0))),"") | H42: High = more export-dependent | I42: Export dependence | J42: WDI TX.VAL.FUEL.ZS.UN | K42: 197 | L42: =IF(F42="","-","Yes")
C43: of which: fuel imports (% merch. imports) | D43: =IF(E43="","",IF(E43>=7,"High",IF(E43>=4,"Medium","Low"))) | E43: =IFERROR(INDEX(Scores!$AE$6:$AE$222,MATCH($C$4,Scores!$B$6:$B$222,0)),"") | F43: =IFERROR(IF(INDEX(Data_wide!$AH$2:$AH$218,MATCH($C$4,Data_wide!$B$2:$B$218,0))="","",INDEX(Data_wide!$AH$2:$AH$218,MATCH($C$4,Data_wide!$B$2:$B$218,0))),"") | G43: =IFERROR(IF(INDEX(Data_wide!$DU$2:$DU$218,MATCH($C$4,Data_wide!$B$2:$B$218,0))="","",INDEX(Data_wide!$DU$2:$DU$218,MATCH($C$4,Data_wide!$B$2:$B$218,0))),"") | H43: High = more relief available | I43: Import bill relief available | J43: WDI TM.VAL.FUEL.ZS.UN | K43: 198 | L43: =IF(F43="","-","Yes")
C44: Energy import dependency (% energy use) | D44: =IF(E44="","",IF(E44>=7,"High",IF(E44>=4,"Medium","Low"))) | E44: =IFERROR(INDEX(Scores!$AF$6:$AF$222,MATCH($C$4,Scores!$B$6:$B$222,0)),"") | F44: =IFERROR(IF(INDEX(Data_wide!$AI$2:$AI$218,MATCH($C$4,Data_wide!$B$2:$B$218,0))="","",INDEX(Data_wide!$AI$2:$AI$218,MATCH($C$4,Data_wide!$B$2:$B$218,0))),"") | G44: =IFERROR(IF(INDEX(Data_wide!$DV$2:$DV$218,MATCH($C$4,Data_wide!$B$2:$B$218,0))="","",INDEX(Data_wide!$DV$2:$DV$218,MATCH($C$4,Data_wide!$B$2:$B$218,0))),"") | H44: High = more relief available | I44: Import bill relief available | J44: WDI EG.IMP.CONS.ZS | K44: 145 | L44: =IF(F44="","-","Yes")
C45: Fossil fuel rents, total (% GDP) | D45: =IF(E45="","",IF(E45>=7,"High",IF(E45>=4,"Medium","Low"))) | E45: =IFERROR(INDEX(Scores!$AG$6:$AG$222,MATCH($C$4,Scores!$B$6:$B$222,0)),"") | F45: =IFERROR(IF(INDEX(Data_wide!$AJ$2:$AJ$218,MATCH($C$4,Data_wide!$B$2:$B$218,0))="","",INDEX(Data_wide!$AJ$2:$AJ$218,MATCH($C$4,Data_wide!$B$2:$B$218,0))),"") | G45: =IFERROR(IF(INDEX(Data_wide!$DW$2:$DW$218,MATCH($C$4,Data_wide!$B$2:$B$218,0))="","",INDEX(Data_wide!$DW$2:$DW$218,MATCH($C$4,Data_wide!$B$2:$B$218,0))),"") | H45: High = more extraction | I45: Extraction earnings | J45: WDI PETR+NGAS+COAL.RT.ZS | K45: 197 | L45: =IF(F45="","-","Yes")
C46: of which: oil rents (% GDP) | D46: =IF(E46="","",IF(E46>=7,"High",IF(E46>=4,"Medium","Low"))) | E46: =IFERROR(INDEX(Scores!$AH$6:$AH$222,MATCH($C$4,Scores!$B$6:$B$222,0)),"") | F46: =IFERROR(IF(INDEX(Data_wide!$AK$2:$AK$218,MATCH($C$4,Data_wide!$B$2:$B$218,0))="","",INDEX(Data_wide!$AK$2:$AK$218,MATCH($C$4,Data_wide!$B$2:$B$218,0))),"") | G46: =IFERROR(IF(INDEX(Data_wide!$DX$2:$DX$218,MATCH($C$4,Data_wide!$B$2:$B$218,0))="","",INDEX(Data_wide!$DX$2:$DX$218,MATCH($C$4,Data_wide!$B$2:$B$218,0))),"") | H46: High = more extraction | I46: Extraction earnings | J46: WDI NY.GDP.PETR.RT.ZS | K46: 200 | L46: =IF(F46="","-","Yes")
C47: of which: natural gas rents (% GDP) | D47: =IF(E47="","",IF(E47>=7,"High",IF(E47>=4,"Medium","Low"))) | E47: =IFERROR(INDEX(Scores!$AI$6:$AI$222,MATCH($C$4,Scores!$B$6:$B$222,0)),"") | F47: =IFERROR(IF(INDEX(Data_wide!$AL$2:$AL$218,MATCH($C$4,Data_wide!$B$2:$B$218,0))="","",INDEX(Data_wide!$AL$2:$AL$218,MATCH($C$4,Data_wide!$B$2:$B$218,0))),"") | G47: =IFERROR(IF(INDEX(Data_wide!$DY$2:$DY$218,MATCH($C$4,Data_wide!$B$2:$B$218,0))="","",INDEX(Data_wide!$DY$2:$DY$218,MATCH($C$4,Data_wide!$B$2:$B$218,0))),"") | H47: High = more extraction | I47: Extraction earnings | J47: WDI NY.GDP.NGAS.RT.ZS | K47: 201 | L47: =IF(F47="","-","Yes")
C48: of which: coal rents (% GDP) | D48: =IF(E48="","",IF(E48>=7,"High",IF(E48>=4,"Medium","Low"))) | E48: =IFERROR(INDEX(Scores!$AJ$6:$AJ$222,MATCH($C$4,Scores!$B$6:$B$222,0)),"") | F48: =IFERROR(IF(INDEX(Data_wide!$AM$2:$AM$218,MATCH($C$4,Data_wide!$B$2:$B$218,0))="","",INDEX(Data_wide!$AM$2:$AM$218,MATCH($C$4,Data_wide!$B$2:$B$218,0))),"") | G48: =IFERROR(IF(INDEX(Data_wide!$DZ$2:$DZ$218,MATCH($C$4,Data_wide!$B$2:$B$218,0))="","",INDEX(Data_wide!$DZ$2:$DZ$218,MATCH($C$4,Data_wide!$B$2:$B$218,0))),"") | H48: High = more extraction | I48: Extraction earnings | J48: WDI NY.GDP.COAL.RT.ZS | K48: 200 | L48: =IF(F48="","-","Yes")
C49: Context 3 — How is power generated today, and which way is it moving? | D49: =IFERROR(IF(E49>=7,"High",IF(E49>=4,"Medium","Low")),"") | E49: =IFERROR(ROUND(AVERAGE(E50:E53),1),"") | H49: Power generation | I49: Abatement opportunity and renewables momentum | L49: =COUNT(F50:F53)&"/4"
B50: ● | C50: Oil-fired share of generation (%) | D50: =IF(E50="","",IF(E50>=7,"High",IF(E50>=4,"Medium","Low"))) | E50: =IFERROR(INDEX(Scores!$AK$6:$AK$222,MATCH($C$4,Scores!$B$6:$B$222,0)),"") | F50: =IFERROR(IF(INDEX(Data_wide!$AN$2:$AN$218,MATCH($C$4,Data_wide!$B$2:$B$218,0))="","",INDEX(Data_wide!$AN$2:$AN$218,MATCH($C$4,Data_wide!$B$2:$B$218,0))),"") | G50: =IFERROR(IF(INDEX(Data_wide!$EA$2:$EA$218,MATCH($C$4,Data_wide!$B$2:$B$218,0))="","",INDEX(Data_wide!$EA$2:$EA$218,MATCH($C$4,Data_wide!$B$2:$B$218,0))),"") | H50: High = more opportunity | I50: Cheap abatement available | J50: Ember Yearly Electricity Data | K50: 200 | L50: =IF(F50="","-","Yes")
C51: Renewable share of electricity (%) | D51: =IF(E51="","",IF(E51>=7,"Good",IF(E51>=4,"Medium","Bad"))) | E51: =IFERROR(INDEX(Scores!$AL$6:$AL$222,MATCH($C$4,Scores!$B$6:$B$222,0)),"") | F51: =IFERROR(IF(INDEX(Data_wide!$AO$2:$AO$218,MATCH($C$4,Data_wide!$B$2:$B$218,0))="","",INDEX(Data_wide!$AO$2:$AO$218,MATCH($C$4,Data_wide!$B$2:$B$218,0))),"") | G51: =IFERROR(IF(INDEX(Data_wide!$EB$2:$EB$218,MATCH($C$4,Data_wide!$B$2:$B$218,0))="","",INDEX(Data_wide!$EB$2:$EB$218,MATCH($C$4,Data_wide!$B$2:$B$218,0))),"") | H51: High = better | I51: Transition starting point | J51: IMF FFS (CPAT) | K51: 186 | L51: =IF(F51="","-","Yes")
C52: Renewable share, YoY change (pp) | D52: =IF(E52="","",IF(E52>=7,"Good",IF(E52>=4,"Medium","Bad"))) | E52: =IFERROR(INDEX(Scores!$AM$6:$AM$222,MATCH($C$4,Scores!$B$6:$B$222,0)),"") | F52: =IFERROR(IF(INDEX(Data_wide!$AP$2:$AP$218,MATCH($C$4,Data_wide!$B$2:$B$218,0))="","",INDEX(Data_wide!$AP$2:$AP$218,MATCH($C$4,Data_wide!$B$2:$B$218,0))),"") | G52: =IFERROR(IF(INDEX(Data_wide!$EC$2:$EC$218,MATCH($C$4,Data_wide!$B$2:$B$218,0))="","",INDEX(Data_wide!$EC$2:$EC$218,MATCH($C$4,Data_wide!$B$2:$B$218,0))),"") | H52: High = moving faster | I52: Transition momentum | J52: Ember Yearly Electricity Data | K52: 198 | L52: =IF(F52="","-","Yes")
C53: Renewable capacity, YoY growth (%) | D53: =IF(E53="","",IF(E53>=7,"Good",IF(E53>=4,"Medium","Bad"))) | E53: =IFERROR(INDEX(Scores!$AN$6:$AN$222,MATCH($C$4,Scores!$B$6:$B$222,0)),"") | F53: =IFERROR(IF(INDEX(Data_wide!$AQ$2:$AQ$218,MATCH($C$4,Data_wide!$B$2:$B$218,0))="","",INDEX(Data_wide!$AQ$2:$AQ$218,MATCH($C$4,Data_wide!$B$2:$B$218,0))),"") | G53: =IFERROR(IF(INDEX(Data_wide!$ED$2:$ED$218,MATCH($C$4,Data_wide!$B$2:$B$218,0))="","",INDEX(Data_wide!$ED$2:$ED$218,MATCH($C$4,Data_wide!$B$2:$B$218,0))),"") | H53: High = moving faster | I53: Transition momentum | J53: Ember Yearly Electricity Data | K53: 183 | L53: =IF(F53="","-","Yes")
C54: Investment 1 — How large is the net zero investment need, and what does it cost? | D54: =IFERROR(IF(E54>=7,"High",IF(E54>=4,"Medium","Low")),"") | E54: =IFERROR(ROUND(AVERAGE(E55:E69),1),"") | H54: Investment needs, 2030 | I54: Model output, not data - Mitigation Investment Needs v1.1, 2030 snapshot | L54: =COUNT(F55:F69)&"/15"
B55: ● | C55: Total mitigation investment need, 2030 (% GDP) | D55: =IF(E55="","",IF(E55>=7,"High",IF(E55>=4,"Medium","Low"))) | E55: =IFERROR(INDEX(Scores!$AO$6:$AO$222,MATCH($C$4,Scores!$B$6:$B$222,0)),"") | F55: =IFERROR(IF(INDEX(Data_wide!$AR$2:$AR$218,MATCH($C$4,Data_wide!$B$2:$B$218,0))="","",INDEX(Data_wide!$AR$2:$AR$218,MATCH($C$4,Data_wide!$B$2:$B$218,0))),"") | G55: =IFERROR(IF(INDEX(Data_wide!$EE$2:$EE$218,MATCH($C$4,Data_wide!$B$2:$B$218,0))="","",INDEX(Data_wide!$EE$2:$EE$218,MATCH($C$4,Data_wide!$B$2:$B$218,0))),"") | H55: High = larger need | I55: Size of the need | J55: InvestmentNeeds v1.1 (model output) | K55: 194 | L55: =IF(F55="","-","Yes")
C56: Incremental investment need, 2030 (% GDP) | D56: =IF(E56="","",IF(E56>=7,"High",IF(E56>=4,"Medium","Low"))) | E56: =IFERROR(INDEX(Scores!$AP$6:$AP$222,MATCH($C$4,Scores!$B$6:$B$222,0)),"") | F56: =IFERROR(IF(INDEX(Data_wide!$AS$2:$AS$218,MATCH($C$4,Data_wide!$B$2:$B$218,0))="","",INDEX(Data_wide!$AS$2:$AS$218,MATCH($C$4,Data_wide!$B$2:$B$218,0))),"") | G56: =IFERROR(IF(INDEX(Data_wide!$EF$2:$EF$218,MATCH($C$4,Data_wide!$B$2:$B$218,0))="","",INDEX(Data_wide!$EF$2:$EF$218,MATCH($C$4,Data_wide!$B$2:$B$218,0))),"") | H56: High = larger need | I56: Above current trends | J56: InvestmentNeeds v1.1 (model output) | K56: 194 | L56: =IF(F56="","-","Yes")
C57: of which: power generation (% GDP) | D57: =IF(E57="","",IF(E57>=7,"High",IF(E57>=4,"Medium","Low"))) | E57: =IFERROR(INDEX(Scores!$AQ$6:$AQ$222,MATCH($C$4,Scores!$B$6:$B$222,0)),"") | F57: =IFERROR(IF(INDEX(Data_wide!$AT$2:$AT$218,MATCH($C$4,Data_wide!$B$2:$B$218,0))="","",INDEX(Data_wide!$AT$2:$AT$218,MATCH($C$4,Data_wide!$B$2:$B$218,0))),"") | G57: =IFERROR(IF(INDEX(Data_wide!$EG$2:$EG$218,MATCH($C$4,Data_wide!$B$2:$B$218,0))="","",INDEX(Data_wide!$EG$2:$EG$218,MATCH($C$4,Data_wide!$B$2:$B$218,0))),"") | H57: High = larger need | I57: Sector | J57: InvestmentNeeds v1.1 (model output) | K57: 194 | L57: =IF(F57="","-","Yes")
C58: of which: grids and storage (% GDP) | D58: =IF(E58="","",IF(E58>=7,"High",IF(E58>=4,"Medium","Low"))) | E58: =IFERROR(INDEX(Scores!$AR$6:$AR$222,MATCH($C$4,Scores!$B$6:$B$222,0)),"") | F58: =IFERROR(IF(INDEX(Data_wide!$AU$2:$AU$218,MATCH($C$4,Data_wide!$B$2:$B$218,0))="","",INDEX(Data_wide!$AU$2:$AU$218,MATCH($C$4,Data_wide!$B$2:$B$218,0))),"") | G58: =IFERROR(IF(INDEX(Data_wide!$EH$2:$EH$218,MATCH($C$4,Data_wide!$B$2:$B$218,0))="","",INDEX(Data_wide!$EH$2:$EH$218,MATCH($C$4,Data_wide!$B$2:$B$218,0))),"") | H58: High = larger need | I58: Sector | J58: InvestmentNeeds v1.1 (model output) | K58: 194 | L58: =IF(F58="","-","Yes")
C59: of which: transport (% GDP) | D59: =IF(E59="","",IF(E59>=7,"High",IF(E59>=4,"Medium","Low"))) | E59: =IFERROR(INDEX(Scores!$AS$6:$AS$222,MATCH($C$4,Scores!$B$6:$B$222,0)),"") | F59: =IFERROR(IF(INDEX(Data_wide!$AV$2:$AV$218,MATCH($C$4,Data_wide!$B$2:$B$218,0))="","",INDEX(Data_wide!$AV$2:$AV$218,MATCH($C$4,Data_wide!$B$2:$B$218,0))),"") | G59: =IFERROR(IF(INDEX(Data_wide!$EI$2:$EI$218,MATCH($C$4,Data_wide!$B$2:$B$218,0))="","",INDEX(Data_wide!$EI$2:$EI$218,MATCH($C$4,Data_wide!$B$2:$B$218,0))),"") | H59: High = larger need | I59: Sector | J59: InvestmentNeeds v1.1 (model output) | K59: 194 | L59: =IF(F59="","-","Yes")
C60: of which: buildings (% GDP) | D60: =IF(E60="","",IF(E60>=7,"High",IF(E60>=4,"Medium","Low"))) | E60: =IFERROR(INDEX(Scores!$AT$6:$AT$222,MATCH($C$4,Scores!$B$6:$B$222,0)),"") | F60: =IFERROR(IF(INDEX(Data_wide!$AW$2:$AW$218,MATCH($C$4,Data_wide!$B$2:$B$218,0))="","",INDEX(Data_wide!$AW$2:$AW$218,MATCH($C$4,Data_wide!$B$2:$B$218,0))),"") | G60: =IFERROR(IF(INDEX(Data_wide!$EJ$2:$EJ$218,MATCH($C$4,Data_wide!$B$2:$B$218,0))="","",INDEX(Data_wide!$EJ$2:$EJ$218,MATCH($C$4,Data_wide!$B$2:$B$218,0))),"") | H60: High = larger need | I60: Sector | J60: InvestmentNeeds v1.1 (model output) | K60: 194 | L60: =IF(F60="","-","Yes")
C61: of which: industry (% GDP) | D61: =IF(E61="","",IF(E61>=7,"High",IF(E61>=4,"Medium","Low"))) | E61: =IFERROR(INDEX(Scores!$AU$6:$AU$222,MATCH($C$4,Scores!$B$6:$B$222,0)),"") | F61: =IFERROR(IF(INDEX(Data_wide!$AX$2:$AX$218,MATCH($C$4,Data_wide!$B$2:$B$218,0))="","",INDEX(Data_wide!$AX$2:$AX$218,MATCH($C$4,Data_wide!$B$2:$B$218,0))),"") | G61: =IFERROR(IF(INDEX(Data_wide!$EK$2:$EK$218,MATCH($C$4,Data_wide!$B$2:$B$218,0))="","",INDEX(Data_wide!$EK$2:$EK$218,MATCH($C$4,Data_wide!$B$2:$B$218,0))),"") | H61: High = larger need | I61: Sector | J61: InvestmentNeeds v1.1 (model output) | K61: 194 | L61: =IF(F61="","-","Yes")
C62: of which: low-emission fuels and fuel supply (% GDP) | D62: =IF(E62="","",IF(E62>=7,"High",IF(E62>=4,"Medium","Low"))) | E62: =IFERROR(INDEX(Scores!$AV$6:$AV$222,MATCH($C$4,Scores!$B$6:$B$222,0)),"") | F62: =IFERROR(IF(INDEX(Data_wide!$AY$2:$AY$218,MATCH($C$4,Data_wide!$B$2:$B$218,0))="","",INDEX(Data_wide!$AY$2:$AY$218,MATCH($C$4,Data_wide!$B$2:$B$218,0))),"") | G62: =IFERROR(IF(INDEX(Data_wide!$EL$2:$EL$218,MATCH($C$4,Data_wide!$B$2:$B$218,0))="","",INDEX(Data_wide!$EL$2:$EL$218,MATCH($C$4,Data_wide!$B$2:$B$218,0))),"") | H62: High = larger need | I62: Sector | J62: InvestmentNeeds v1.1 (model output) | K62: 194 | L62: =IF(F62="","-","Yes")
C63: of which: AFOLU and nature (% GDP) | D63: =IF(E63="","",IF(E63>=7,"High",IF(E63>=4,"Medium","Low"))) | E63: =IFERROR(INDEX(Scores!$AW$6:$AW$222,MATCH($C$4,Scores!$B$6:$B$222,0)),"") | F63: =IFERROR(IF(INDEX(Data_wide!$AZ$2:$AZ$218,MATCH($C$4,Data_wide!$B$2:$B$218,0))="","",INDEX(Data_wide!$AZ$2:$AZ$218,MATCH($C$4,Data_wide!$B$2:$B$218,0))),"") | G63: =IFERROR(IF(INDEX(Data_wide!$EM$2:$EM$218,MATCH($C$4,Data_wide!$B$2:$B$218,0))="","",INDEX(Data_wide!$EM$2:$EM$218,MATCH($C$4,Data_wide!$B$2:$B$218,0))),"") | H63: High = larger need | I63: Sector | J63: InvestmentNeeds v1.1 (model output) | K63: 194 | L63: =IF(F63="","-","Yes")
C64: Incremental cost, market cost of capital (a), 2030 (% GDP) | D64: =IF(E64="","",IF(E64>=7,"High",IF(E64>=4,"Medium","Low"))) | E64: =IFERROR(INDEX(Scores!$AX$6:$AX$222,MATCH($C$4,Scores!$B$6:$B$222,0)),"") | F64: =IFERROR(IF(INDEX(Data_wide!$BA$2:$BA$218,MATCH($C$4,Data_wide!$B$2:$B$218,0))="","",INDEX(Data_wide!$BA$2:$BA$218,MATCH($C$4,Data_wide!$B$2:$B$218,0))),"") | G64: =IFERROR(IF(INDEX(Data_wide!$EN$2:$EN$218,MATCH($C$4,Data_wide!$B$2:$B$218,0))="","",INDEX(Data_wide!$EN$2:$EN$218,MATCH($C$4,Data_wide!$B$2:$B$218,0))),"") | H64: High = larger net cost | I64: Net cost after savings | J64: InvestmentNeeds v1.1 (model output) | K64: 194 | L64: =IF(F64="","-","Yes")
C65: Incremental cost, World Bank rate 6% (b), 2030 (% GDP) | D65: =IF(E65="","",IF(E65>=7,"High",IF(E65>=4,"Medium","Low"))) | E65: =IFERROR(INDEX(Scores!$AY$6:$AY$222,MATCH($C$4,Scores!$B$6:$B$222,0)),"") | F65: =IFERROR(IF(INDEX(Data_wide!$BB$2:$BB$218,MATCH($C$4,Data_wide!$B$2:$B$218,0))="","",INDEX(Data_wide!$BB$2:$BB$218,MATCH($C$4,Data_wide!$B$2:$B$218,0))),"") | G65: =IFERROR(IF(INDEX(Data_wide!$EO$2:$EO$218,MATCH($C$4,Data_wide!$B$2:$B$218,0))="","",INDEX(Data_wide!$EO$2:$EO$218,MATCH($C$4,Data_wide!$B$2:$B$218,0))),"") | H65: High = larger net cost | I65: Net cost after savings | J65: InvestmentNeeds v1.1 (model output) | K65: 194 | L65: =IF(F65="","-","Yes")
C66: Incremental cost, 6% + local co-benefits (c), 2030 (% GDP) | D66: =IF(E66="","",IF(E66>=7,"High",IF(E66>=4,"Medium","Low"))) | E66: =IFERROR(INDEX(Scores!$AZ$6:$AZ$222,MATCH($C$4,Scores!$B$6:$B$222,0)),"") | F66: =IFERROR(IF(INDEX(Data_wide!$BC$2:$BC$218,MATCH($C$4,Data_wide!$B$2:$B$218,0))="","",INDEX(Data_wide!$BC$2:$BC$218,MATCH($C$4,Data_wide!$B$2:$B$218,0))),"") | G66: =IFERROR(IF(INDEX(Data_wide!$EP$2:$EP$218,MATCH($C$4,Data_wide!$B$2:$B$218,0))="","",INDEX(Data_wide!$EP$2:$EP$218,MATCH($C$4,Data_wide!$B$2:$B$218,0))),"") | H66: High = larger net cost | I66: Net cost after co-benefits | J66: InvestmentNeeds v1.1 (model output) | K66: 194 | L66: =IF(F66="","-","Yes")
C67: Incremental cost per tonne abated, lens (b), 2030 (USD/tCO2e) | D67: =IF(E67="","",IF(E67>=7,"High",IF(E67>=4,"Medium","Low"))) | E67: =IFERROR(INDEX(Scores!$BA$6:$BA$222,MATCH($C$4,Scores!$B$6:$B$222,0)),"") | F67: =IFERROR(IF(INDEX(Data_wide!$BD$2:$BD$218,MATCH($C$4,Data_wide!$B$2:$B$218,0))="","",INDEX(Data_wide!$BD$2:$BD$218,MATCH($C$4,Data_wide!$B$2:$B$218,0))),"") | G67: =IFERROR(IF(INDEX(Data_wide!$EQ$2:$EQ$218,MATCH($C$4,Data_wide!$B$2:$B$218,0))="","",INDEX(Data_wide!$EQ$2:$EQ$218,MATCH($C$4,Data_wide!$B$2:$B$218,0))),"") | H67: High = costlier abatement | I67: Abatement cost | J67: InvestmentNeeds v1.1 (model output) | K67: 194 | L67: =IF(F67="","-","Yes")
C68: Cost-of-capital penalty on total investment, (a) less (b) (% GDP) | D68: =IF(E68="","",IF(E68>=7,"High",IF(E68>=4,"Medium","Low"))) | E68: =IFERROR(INDEX(Scores!$BB$6:$BB$222,MATCH($C$4,Scores!$B$6:$B$222,0)),"") | F68: =IFERROR(IF(INDEX(Data_wide!$BE$2:$BE$218,MATCH($C$4,Data_wide!$B$2:$B$218,0))="","",INDEX(Data_wide!$BE$2:$BE$218,MATCH($C$4,Data_wide!$B$2:$B$218,0))),"") | G68: =IFERROR(IF(INDEX(Data_wide!$ER$2:$ER$218,MATCH($C$4,Data_wide!$B$2:$B$218,0))="","",INDEX(Data_wide!$ER$2:$ER$218,MATCH($C$4,Data_wide!$B$2:$B$218,0))),"") | H68: High = capital costs more than 6% | I68: Cost of capital | J68: InvestmentNeeds v1.1 (model output) | K68: 194 | L68: =IF(F68="","-","Yes")
C69: PIMA-adjusted total investment, 2030 (% GDP) | D69: =IF(E69="","",IF(E69>=7,"High",IF(E69>=4,"Medium","Low"))) | E69: =IFERROR(INDEX(Scores!$BC$6:$BC$222,MATCH($C$4,Scores!$B$6:$B$222,0)),"") | F69: =IFERROR(IF(INDEX(Data_wide!$BF$2:$BF$218,MATCH($C$4,Data_wide!$B$2:$B$218,0))="","",INDEX(Data_wide!$BF$2:$BF$218,MATCH($C$4,Data_wide!$B$2:$B$218,0))),"") | G69: =IFERROR(IF(INDEX(Data_wide!$ES$2:$ES$218,MATCH($C$4,Data_wide!$B$2:$B$218,0))="","",INDEX(Data_wide!$ES$2:$ES$218,MATCH($C$4,Data_wide!$B$2:$B$218,0))),"") | H69: High = larger need | I69: Delivery (PIMA) | J69: InvestmentNeeds v1.1 (model output) | K69: 194 | L69: =IF(F69="","-","Yes")
C70: Investment 2 — Who pays for it, and how does the need evolve to 2050? | D70: =IFERROR(IF(E70>=7,"High",IF(E70>=4,"Medium","Low")),"") | E70: =IFERROR(ROUND(AVERAGE(E71:E81),1),"") | H70: Who pays, 2030-2050 | I70: Model output, not data - National Mitigation Investment Model (NMIM) v0.2 | L70: =COUNT(F71:F81)&"/11"
C71: Net zero investment, 2030 (% GDP) | D71: =IF(E71="","",IF(E71>=7,"High",IF(E71>=4,"Medium","Low"))) | E71: =IFERROR(INDEX(Scores!$BD$6:$BD$222,MATCH($C$4,Scores!$B$6:$B$222,0)),"") | F71: =IFERROR(IF(INDEX(Data_wide!$BG$2:$BG$218,MATCH($C$4,Data_wide!$B$2:$B$218,0))="","",INDEX(Data_wide!$BG$2:$BG$218,MATCH($C$4,Data_wide!$B$2:$B$218,0))),"") | G71: =IFERROR(IF(INDEX(Data_wide!$ET$2:$ET$218,MATCH($C$4,Data_wide!$B$2:$B$218,0))="","",INDEX(Data_wide!$ET$2:$ET$218,MATCH($C$4,Data_wide!$B$2:$B$218,0))),"") | H71: High = larger need | I71: Size of the need | J71: InvestmentNeeds NMIM v0.2 (model output) | K71: 186 | L71: =IF(F71="","-","Yes")
C72: of which: P1 pure public (% GDP) | D72: =IF(E72="","",IF(E72>=7,"High",IF(E72>=4,"Medium","Low"))) | E72: =IFERROR(INDEX(Scores!$BE$6:$BE$222,MATCH($C$4,Scores!$B$6:$B$222,0)),"") | F72: =IFERROR(IF(INDEX(Data_wide!$BH$2:$BH$218,MATCH($C$4,Data_wide!$B$2:$B$218,0))="","",INDEX(Data_wide!$BH$2:$BH$218,MATCH($C$4,Data_wide!$B$2:$B$218,0))),"") | G72: =IFERROR(IF(INDEX(Data_wide!$EU$2:$EU$218,MATCH($C$4,Data_wide!$B$2:$B$218,0))="","",INDEX(Data_wide!$EU$2:$EU$218,MATCH($C$4,Data_wide!$B$2:$B$218,0))),"") | H72: High = larger share | I72: Who pays | J72: InvestmentNeeds NMIM v0.2 (model output) | K72: 186 | L72: =IF(F72="","-","Yes")
C73: of which: P2 regulated utility (% GDP) | D73: =IF(E73="","",IF(E73>=7,"High",IF(E73>=4,"Medium","Low"))) | E73: =IFERROR(INDEX(Scores!$BF$6:$BF$222,MATCH($C$4,Scores!$B$6:$B$222,0)),"") | F73: =IFERROR(IF(INDEX(Data_wide!$BI$2:$BI$218,MATCH($C$4,Data_wide!$B$2:$B$218,0))="","",INDEX(Data_wide!$BI$2:$BI$218,MATCH($C$4,Data_wide!$B$2:$B$218,0))),"") | G73: =IFERROR(IF(INDEX(Data_wide!$EV$2:$EV$218,MATCH($C$4,Data_wide!$B$2:$B$218,0))="","",INDEX(Data_wide!$EV$2:$EV$218,MATCH($C$4,Data_wide!$B$2:$B$218,0))),"") | H73: High = larger share | I73: Who pays | J73: InvestmentNeeds NMIM v0.2 (model output) | K73: 186 | L73: =IF(F73="","-","Yes")
C74: of which: P3 contracted revenue (% GDP) | D74: =IF(E74="","",IF(E74>=7,"High",IF(E74>=4,"Medium","Low"))) | E74: =IFERROR(INDEX(Scores!$BG$6:$BG$222,MATCH($C$4,Scores!$B$6:$B$222,0)),"") | F74: =IFERROR(IF(INDEX(Data_wide!$BJ$2:$BJ$218,MATCH($C$4,Data_wide!$B$2:$B$218,0))="","",INDEX(Data_wide!$BJ$2:$BJ$218,MATCH($C$4,Data_wide!$B$2:$B$218,0))),"") | G74: =IFERROR(IF(INDEX(Data_wide!$EW$2:$EW$218,MATCH($C$4,Data_wide!$B$2:$B$218,0))="","",INDEX(Data_wide!$EW$2:$EW$218,MATCH($C$4,Data_wide!$B$2:$B$218,0))),"") | H74: High = larger share | I74: Who pays | J74: InvestmentNeeds NMIM v0.2 (model output) | K74: 186 | L74: =IF(F74="","-","Yes")
C75: of which: P4 viability gap (% GDP) | D75: =IF(E75="","",IF(E75>=7,"High",IF(E75>=4,"Medium","Low"))) | E75: =IFERROR(INDEX(Scores!$BH$6:$BH$222,MATCH($C$4,Scores!$B$6:$B$222,0)),"") | F75: =IFERROR(IF(INDEX(Data_wide!$BK$2:$BK$218,MATCH($C$4,Data_wide!$B$2:$B$218,0))="","",INDEX(Data_wide!$BK$2:$BK$218,MATCH($C$4,Data_wide!$B$2:$B$218,0))),"") | G75: =IFERROR(IF(INDEX(Data_wide!$EX$2:$EX$218,MATCH($C$4,Data_wide!$B$2:$B$218,0))="","",INDEX(Data_wide!$EX$2:$EX$218,MATCH($C$4,Data_wide!$B$2:$B$218,0))),"") | H75: High = larger share | I75: Who pays | J75: InvestmentNeeds NMIM v0.2 (model output) | K75: 186 | L75: =IF(F75="","-","Yes")
C76: of which: P5 pure private (% GDP) | D76: =IF(E76="","",IF(E76>=7,"High",IF(E76>=4,"Medium","Low"))) | E76: =IFERROR(INDEX(Scores!$BI$6:$BI$222,MATCH($C$4,Scores!$B$6:$B$222,0)),"") | F76: =IFERROR(IF(INDEX(Data_wide!$BL$2:$BL$218,MATCH($C$4,Data_wide!$B$2:$B$218,0))="","",INDEX(Data_wide!$BL$2:$BL$218,MATCH($C$4,Data_wide!$B$2:$B$218,0))),"") | G76: =IFERROR(IF(INDEX(Data_wide!$EY$2:$EY$218,MATCH($C$4,Data_wide!$B$2:$B$218,0))="","",INDEX(Data_wide!$EY$2:$EY$218,MATCH($C$4,Data_wide!$B$2:$B$218,0))),"") | H76: High = larger share | I76: Who pays | J76: InvestmentNeeds NMIM v0.2 (model output) | K76: 186 | L76: =IF(F76="","-","Yes")
B77: ● | C77: Direct budget need, net zero, 2030 (% GDP): P1 + public gap of P4 | D77: =IF(E77="","",IF(E77>=7,"High",IF(E77>=4,"Medium","Low"))) | E77: =IFERROR(INDEX(Scores!$BJ$6:$BJ$222,MATCH($C$4,Scores!$B$6:$B$222,0)),"") | F77: =IFERROR(IF(INDEX(Data_wide!$BM$2:$BM$218,MATCH($C$4,Data_wide!$B$2:$B$218,0))="","",INDEX(Data_wide!$BM$2:$BM$218,MATCH($C$4,Data_wide!$B$2:$B$218,0))),"") | G77: =IFERROR(IF(INDEX(Data_wide!$EZ$2:$EZ$218,MATCH($C$4,Data_wide!$B$2:$B$218,0))="","",INDEX(Data_wide!$EZ$2:$EZ$218,MATCH($C$4,Data_wide!$B$2:$B$218,0))),"") | H77: High = larger budget need | I77: Budget | J77: InvestmentNeeds NMIM v0.2 (model output) | K77: 186 | L77: =IF(F77="","-","Yes")
C78: Private capital, share of net zero investment, 2030 (%) | D78: =IF(E78="","",IF(E78>=7,"High",IF(E78>=4,"Medium","Low"))) | E78: =IFERROR(INDEX(Scores!$BK$6:$BK$222,MATCH($C$4,Scores!$B$6:$B$222,0)),"") | F78: =IFERROR(IF(INDEX(Data_wide!$BN$2:$BN$218,MATCH($C$4,Data_wide!$B$2:$B$218,0))="","",INDEX(Data_wide!$BN$2:$BN$218,MATCH($C$4,Data_wide!$B$2:$B$218,0))),"") | G78: =IFERROR(IF(INDEX(Data_wide!$FA$2:$FA$218,MATCH($C$4,Data_wide!$B$2:$B$218,0))="","",INDEX(Data_wide!$FA$2:$FA$218,MATCH($C$4,Data_wide!$B$2:$B$218,0))),"") | H78: High = more privately financed | I78: Private finance | J78: InvestmentNeeds NMIM v0.2 (model output) | K78: 186 | L78: =IF(F78="","-","Yes")
C79: Incremental investment, 2030 (% GDP) | D79: =IF(E79="","",IF(E79>=7,"High",IF(E79>=4,"Medium","Low"))) | E79: =IFERROR(INDEX(Scores!$BL$6:$BL$222,MATCH($C$4,Scores!$B$6:$B$222,0)),"") | F79: =IFERROR(IF(INDEX(Data_wide!$BO$2:$BO$218,MATCH($C$4,Data_wide!$B$2:$B$218,0))="","",INDEX(Data_wide!$BO$2:$BO$218,MATCH($C$4,Data_wide!$B$2:$B$218,0))),"") | G79: =IFERROR(IF(INDEX(Data_wide!$FB$2:$FB$218,MATCH($C$4,Data_wide!$B$2:$B$218,0))="","",INDEX(Data_wide!$FB$2:$FB$218,MATCH($C$4,Data_wide!$B$2:$B$218,0))),"") | H79: High = larger need | I79: Path | J79: InvestmentNeeds NMIM v0.2 (model output) | K79: 186 | L79: =IF(F79="","-","Yes")
C80: Incremental investment, 2050 (% GDP) | D80: =IF(E80="","",IF(E80>=7,"High",IF(E80>=4,"Medium","Low"))) | E80: =IFERROR(INDEX(Scores!$BM$6:$BM$222,MATCH($C$4,Scores!$B$6:$B$222,0)),"") | F80: =IFERROR(IF(INDEX(Data_wide!$BP$2:$BP$218,MATCH($C$4,Data_wide!$B$2:$B$218,0))="","",INDEX(Data_wide!$BP$2:$BP$218,MATCH($C$4,Data_wide!$B$2:$B$218,0))),"") | G80: =IFERROR(IF(INDEX(Data_wide!$FC$2:$FC$218,MATCH($C$4,Data_wide!$B$2:$B$218,0))="","",INDEX(Data_wide!$FC$2:$FC$218,MATCH($C$4,Data_wide!$B$2:$B$218,0))),"") | H80: High = larger need | I80: Path | J80: InvestmentNeeds NMIM v0.2 (model output) | K80: 186 | L80: =IF(F80="","-","Yes")
C81: Incremental cost, lens (b), present value 2025-2050 (% of 2030 GDP) | D81: =IF(E81="","",IF(E81>=7,"High",IF(E81>=4,"Medium","Low"))) | E81: =IFERROR(INDEX(Scores!$BN$6:$BN$222,MATCH($C$4,Scores!$B$6:$B$222,0)),"") | F81: =IFERROR(IF(INDEX(Data_wide!$BQ$2:$BQ$218,MATCH($C$4,Data_wide!$B$2:$B$218,0))="","",INDEX(Data_wide!$BQ$2:$BQ$218,MATCH($C$4,Data_wide!$B$2:$B$218,0))),"") | G81: =IFERROR(IF(INDEX(Data_wide!$FD$2:$FD$218,MATCH($C$4,Data_wide!$B$2:$B$218,0))="","",INDEX(Data_wide!$FD$2:$FD$218,MATCH($C$4,Data_wide!$B$2:$B$218,0))),"") | H81: High = larger net cost | I81: Net cost over the path | J81: InvestmentNeeds NMIM v0.2 (model output) | K81: 186 | L81: =IF(F81="","-","Yes")
C82: Appendix A — What do users actually pay for energy? | D82: reference | E82: =IFERROR(ROUND(AVERAGE(E83:E92),1),"") | H82: Fuel pricing | I82: Reference detail - retail prices by fuel and sector | L82: =COUNT(F83:F92)&"/10"
B83: ● | C83: Diesel, retail ($/litre) | D83: =IF(E83="","",IF(E83>=7,"High",IF(E83>=4,"Medium","Low"))) | E83: =IFERROR(INDEX(Scores!$BO$6:$BO$222,MATCH($C$4,Scores!$B$6:$B$222,0)),"") | F83: =IFERROR(IF(INDEX(Data_wide!$BR$2:$BR$218,MATCH($C$4,Data_wide!$B$2:$B$218,0))="","",INDEX(Data_wide!$BR$2:$BR$218,MATCH($C$4,Data_wide!$B$2:$B$218,0))),"") | G83: =IFERROR(IF(INDEX(Data_wide!$FE$2:$FE$218,MATCH($C$4,Data_wide!$B$2:$B$218,0))="","",INDEX(Data_wide!$FE$2:$FE$218,MATCH($C$4,Data_wide!$B$2:$B$218,0))),"") | H83: High = more expensive | I83: Transport fuel | J83: IMF FFS (CPAT) | K83: 183 | L83: =IF(F83="","-","Yes")
C84: Gasoline, retail ($/litre) | D84: =IF(E84="","",IF(E84>=7,"High",IF(E84>=4,"Medium","Low"))) | E84: =IFERROR(INDEX(Scores!$BP$6:$BP$222,MATCH($C$4,Scores!$B$6:$B$222,0)),"") | F84: =IFERROR(IF(INDEX(Data_wide!$BS$2:$BS$218,MATCH($C$4,Data_wide!$B$2:$B$218,0))="","",INDEX(Data_wide!$BS$2:$BS$218,MATCH($C$4,Data_wide!$B$2:$B$218,0))),"") | G84: =IFERROR(IF(INDEX(Data_wide!$FF$2:$FF$218,MATCH($C$4,Data_wide!$B$2:$B$218,0))="","",INDEX(Data_wide!$FF$2:$FF$218,MATCH($C$4,Data_wide!$B$2:$B$218,0))),"") | H84: High = more expensive | I84: Transport fuel | J84: IMF FFS (CPAT) | K84: 183 | L84: =IF(F84="","-","Yes")
C85: Electricity, residential ($/kWh) | D85: =IF(E85="","",IF(E85>=7,"High",IF(E85>=4,"Medium","Low"))) | E85: =IFERROR(INDEX(Scores!$BQ$6:$BQ$222,MATCH($C$4,Scores!$B$6:$B$222,0)),"") | F85: =IFERROR(IF(INDEX(Data_wide!$BT$2:$BT$218,MATCH($C$4,Data_wide!$B$2:$B$218,0))="","",INDEX(Data_wide!$BT$2:$BT$218,MATCH($C$4,Data_wide!$B$2:$B$218,0))),"") | G85: =IFERROR(IF(INDEX(Data_wide!$FG$2:$FG$218,MATCH($C$4,Data_wide!$B$2:$B$218,0))="","",INDEX(Data_wide!$FG$2:$FG$218,MATCH($C$4,Data_wide!$B$2:$B$218,0))),"") | H85: High = more expensive | I85: Electricity | J85: IMF FFS (CPAT) | K85: 186 | L85: =IF(F85="","-","Yes")
C86: Electricity, industry ($/kWh) | D86: =IF(E86="","",IF(E86>=7,"High",IF(E86>=4,"Medium","Low"))) | E86: =IFERROR(INDEX(Scores!$BR$6:$BR$222,MATCH($C$4,Scores!$B$6:$B$222,0)),"") | F86: =IFERROR(IF(INDEX(Data_wide!$BU$2:$BU$218,MATCH($C$4,Data_wide!$B$2:$B$218,0))="","",INDEX(Data_wide!$BU$2:$BU$218,MATCH($C$4,Data_wide!$B$2:$B$218,0))),"") | G86: =IFERROR(IF(INDEX(Data_wide!$FH$2:$FH$218,MATCH($C$4,Data_wide!$B$2:$B$218,0))="","",INDEX(Data_wide!$FH$2:$FH$218,MATCH($C$4,Data_wide!$B$2:$B$218,0))),"") | H86: High = more expensive | I86: Electricity | J86: IMF FFS (CPAT) | K86: 186 | L86: =IF(F86="","-","Yes")
C87: Natural gas, residential ($/GJ) | D87: =IF(E87="","",IF(E87>=7,"High",IF(E87>=4,"Medium","Low"))) | E87: =IFERROR(INDEX(Scores!$BS$6:$BS$222,MATCH($C$4,Scores!$B$6:$B$222,0)),"") | F87: =IFERROR(IF(INDEX(Data_wide!$BV$2:$BV$218,MATCH($C$4,Data_wide!$B$2:$B$218,0))="","",INDEX(Data_wide!$BV$2:$BV$218,MATCH($C$4,Data_wide!$B$2:$B$218,0))),"") | G87: =IFERROR(IF(INDEX(Data_wide!$FI$2:$FI$218,MATCH($C$4,Data_wide!$B$2:$B$218,0))="","",INDEX(Data_wide!$FI$2:$FI$218,MATCH($C$4,Data_wide!$B$2:$B$218,0))),"") | H87: High = more expensive | I87: Natural gas | J87: IMF FFS (CPAT) | K87: 179 | L87: =IF(F87="","-","Yes")
C88: Natural gas, industry ($/GJ) | D88: =IF(E88="","",IF(E88>=7,"High",IF(E88>=4,"Medium","Low"))) | E88: =IFERROR(INDEX(Scores!$BT$6:$BT$222,MATCH($C$4,Scores!$B$6:$B$222,0)),"") | F88: =IFERROR(IF(INDEX(Data_wide!$BW$2:$BW$218,MATCH($C$4,Data_wide!$B$2:$B$218,0))="","",INDEX(Data_wide!$BW$2:$BW$218,MATCH($C$4,Data_wide!$B$2:$B$218,0))),"") | G88: =IFERROR(IF(INDEX(Data_wide!$FJ$2:$FJ$218,MATCH($C$4,Data_wide!$B$2:$B$218,0))="","",INDEX(Data_wide!$FJ$2:$FJ$218,MATCH($C$4,Data_wide!$B$2:$B$218,0))),"") | H88: High = more expensive | I88: Natural gas | J88: IMF FFS (CPAT) | K88: 183 | L88: =IF(F88="","-","Yes")
C89: Natural gas, power sector ($/GJ) | D89: =IF(E89="","",IF(E89>=7,"High",IF(E89>=4,"Medium","Low"))) | E89: =IFERROR(INDEX(Scores!$BU$6:$BU$222,MATCH($C$4,Scores!$B$6:$B$222,0)),"") | F89: =IFERROR(IF(INDEX(Data_wide!$BX$2:$BX$218,MATCH($C$4,Data_wide!$B$2:$B$218,0))="","",INDEX(Data_wide!$BX$2:$BX$218,MATCH($C$4,Data_wide!$B$2:$B$218,0))),"") | G89: =IFERROR(IF(INDEX(Data_wide!$FK$2:$FK$218,MATCH($C$4,Data_wide!$B$2:$B$218,0))="","",INDEX(Data_wide!$FK$2:$FK$218,MATCH($C$4,Data_wide!$B$2:$B$218,0))),"") | H89: High = more expensive | I89: Natural gas | J89: IMF FFS (CPAT) | K89: 180 | L89: =IF(F89="","-","Yes")
C90: Coal, residential ($/GJ) | D90: =IF(E90="","",IF(E90>=7,"High",IF(E90>=4,"Medium","Low"))) | E90: =IFERROR(INDEX(Scores!$BV$6:$BV$222,MATCH($C$4,Scores!$B$6:$B$222,0)),"") | F90: =IFERROR(IF(INDEX(Data_wide!$BY$2:$BY$218,MATCH($C$4,Data_wide!$B$2:$B$218,0))="","",INDEX(Data_wide!$BY$2:$BY$218,MATCH($C$4,Data_wide!$B$2:$B$218,0))),"") | G90: =IFERROR(IF(INDEX(Data_wide!$FL$2:$FL$218,MATCH($C$4,Data_wide!$B$2:$B$218,0))="","",INDEX(Data_wide!$FL$2:$FL$218,MATCH($C$4,Data_wide!$B$2:$B$218,0))),"") | H90: High = more expensive | I90: Coal | J90: IMF FFS (CPAT) | K90: 186 | L90: =IF(F90="","-","Yes")
C91: Coal, industry ($/GJ) | D91: =IF(E91="","",IF(E91>=7,"High",IF(E91>=4,"Medium","Low"))) | E91: =IFERROR(INDEX(Scores!$BW$6:$BW$222,MATCH($C$4,Scores!$B$6:$B$222,0)),"") | F91: =IFERROR(IF(INDEX(Data_wide!$BZ$2:$BZ$218,MATCH($C$4,Data_wide!$B$2:$B$218,0))="","",INDEX(Data_wide!$BZ$2:$BZ$218,MATCH($C$4,Data_wide!$B$2:$B$218,0))),"") | G91: =IFERROR(IF(INDEX(Data_wide!$FM$2:$FM$218,MATCH($C$4,Data_wide!$B$2:$B$218,0))="","",INDEX(Data_wide!$FM$2:$FM$218,MATCH($C$4,Data_wide!$B$2:$B$218,0))),"") | H91: High = more expensive | I91: Coal | J91: IMF FFS (CPAT) | K91: 186 | L91: =IF(F91="","-","Yes")
C92: Coal, power sector ($/GJ) | D92: =IF(E92="","",IF(E92>=7,"High",IF(E92>=4,"Medium","Low"))) | E92: =IFERROR(INDEX(Scores!$BX$6:$BX$222,MATCH($C$4,Scores!$B$6:$B$222,0)),"") | F92: =IFERROR(IF(INDEX(Data_wide!$CA$2:$CA$218,MATCH($C$4,Data_wide!$B$2:$B$218,0))="","",INDEX(Data_wide!$CA$2:$CA$218,MATCH($C$4,Data_wide!$B$2:$B$218,0))),"") | G92: =IFERROR(IF(INDEX(Data_wide!$FN$2:$FN$218,MATCH($C$4,Data_wide!$B$2:$B$218,0))="","",INDEX(Data_wide!$FN$2:$FN$218,MATCH($C$4,Data_wide!$B$2:$B$218,0))),"") | H92: High = more expensive | I92: Coal | J92: IMF FFS (CPAT) | K92: 186 | L92: =IF(F92="","-","Yes")
C93: Appendix B — How is the power sector organised and regulated? | D93: reference | E93: =IFERROR(ROUND(AVERAGE(E94:E99),1),"") | H93: Power market regulation | I93: Reference detail - market structure and policy scores | L93: =COUNT(F94:F99)&"/6"
B94: ● | C94: Power market structure | D94: =IF(F94="","",IF(F94=3,"Wholesale market",IF(F94=2,"Single buyer","Vertically integrated"))) | E94: =IFERROR(INDEX(Scores!$BY$6:$BY$222,MATCH($C$4,Scores!$B$6:$B$222,0)),"") | F94: =IFERROR(IF(INDEX(Data_wide!$CB$2:$CB$218,MATCH($C$4,Data_wide!$B$2:$B$218,0))="","",INDEX(Data_wide!$CB$2:$CB$218,MATCH($C$4,Data_wide!$B$2:$B$218,0))),"") | G94: =IFERROR(IF(INDEX(Data_wide!$FO$2:$FO$218,MATCH($C$4,Data_wide!$B$2:$B$218,0))="","",INDEX(Data_wide!$FO$2:$FO$218,MATCH($C$4,Data_wide!$B$2:$B$218,0))),"") | H94: 1 integrated / 2 single buyer / 3 wholesale | I94: Market model | J94: PSRT (2013) | K94: 142 | L94: =IF(F94="","-","Yes")
C95: Independent regulator exists (0/1) | D95: =IF(F95="","",IF(F95=1,"Yes","No")) | E95: =IFERROR(INDEX(Scores!$BZ$6:$BZ$222,MATCH($C$4,Scores!$B$6:$B$222,0)),"") | F95: =IFERROR(IF(INDEX(Data_wide!$CC$2:$CC$218,MATCH($C$4,Data_wide!$B$2:$B$218,0))="","",INDEX(Data_wide!$CC$2:$CC$218,MATCH($C$4,Data_wide!$B$2:$B$218,0))),"") | G95: =IFERROR(IF(INDEX(Data_wide!$FP$2:$FP$218,MATCH($C$4,Data_wide!$B$2:$B$218,0))="","",INDEX(Data_wide!$FP$2:$FP$218,MATCH($C$4,Data_wide!$B$2:$B$218,0))),"") | H95: Yes / No | I95: Regulatory institutions | J95: PSRT (2013) | K95: 142 | L95: =IF(F95="","-","Yes")
C96: Generation unbundled (0/1) | D96: =IF(F96="","",IF(F96=1,"Yes","No")) | E96: =IFERROR(INDEX(Scores!$CA$6:$CA$222,MATCH($C$4,Scores!$B$6:$B$222,0)),"") | F96: =IFERROR(IF(INDEX(Data_wide!$CD$2:$CD$218,MATCH($C$4,Data_wide!$B$2:$B$218,0))="","",INDEX(Data_wide!$CD$2:$CD$218,MATCH($C$4,Data_wide!$B$2:$B$218,0))),"") | G96: =IFERROR(IF(INDEX(Data_wide!$FQ$2:$FQ$218,MATCH($C$4,Data_wide!$B$2:$B$218,0))="","",INDEX(Data_wide!$FQ$2:$FQ$218,MATCH($C$4,Data_wide!$B$2:$B$218,0))),"") | H96: Yes / No | I96: Market model | J96: PSRT (2013) | K96: 142 | L96: =IF(F96="","-","Yes")
C97: RISE renewable energy score (0-100) | D97: =IF(E97="","",IF(E97>=7,"High",IF(E97>=4,"Medium","Low"))) | E97: =IFERROR(INDEX(Scores!$CB$6:$CB$222,MATCH($C$4,Scores!$B$6:$B$222,0)),"") | F97: =IFERROR(IF(INDEX(Data_wide!$CE$2:$CE$218,MATCH($C$4,Data_wide!$B$2:$B$218,0))="","",INDEX(Data_wide!$CE$2:$CE$218,MATCH($C$4,Data_wide!$B$2:$B$218,0))),"") | G97: =IFERROR(IF(INDEX(Data_wide!$FR$2:$FR$218,MATCH($C$4,Data_wide!$B$2:$B$218,0))="","",INDEX(Data_wide!$FR$2:$FR$218,MATCH($C$4,Data_wide!$B$2:$B$218,0))),"") | H97: High = stronger framework | I97: RE policy environment | J97: World Bank RISE 2024 | K97: 140 | L97: =IF(F97="","-","Yes")
C98: RISE levelling the playing field (0-100) | D98: =IF(E98="","",IF(E98>=7,"High",IF(E98>=4,"Medium","Low"))) | E98: =IFERROR(INDEX(Scores!$CC$6:$CC$222,MATCH($C$4,Scores!$B$6:$B$222,0)),"") | F98: =IFERROR(IF(INDEX(Data_wide!$CF$2:$CF$218,MATCH($C$4,Data_wide!$B$2:$B$218,0))="","",INDEX(Data_wide!$CF$2:$CF$218,MATCH($C$4,Data_wide!$B$2:$B$218,0))),"") | G98: =IFERROR(IF(INDEX(Data_wide!$FS$2:$FS$218,MATCH($C$4,Data_wide!$B$2:$B$218,0))="","",INDEX(Data_wide!$FS$2:$FS$218,MATCH($C$4,Data_wide!$B$2:$B$218,0))),"") | H98: High = more level | I98: RE vs fossil parity | J98: World Bank RISE 2024 | K98: 140 | L98: =IF(F98="","-","Yes")
C99: RISE financing mechanisms, EE (0-100) | D99: =IF(E99="","",IF(E99>=7,"High",IF(E99>=4,"Medium","Low"))) | E99: =IFERROR(INDEX(Scores!$CD$6:$CD$222,MATCH($C$4,Scores!$B$6:$B$222,0)),"") | F99: =IFERROR(IF(INDEX(Data_wide!$CG$2:$CG$218,MATCH($C$4,Data_wide!$B$2:$B$218,0))="","",INDEX(Data_wide!$CG$2:$CG$218,MATCH($C$4,Data_wide!$B$2:$B$218,0))),"") | G99: =IFERROR(IF(INDEX(Data_wide!$FT$2:$FT$218,MATCH($C$4,Data_wide!$B$2:$B$218,0))="","",INDEX(Data_wide!$FT$2:$FT$218,MATCH($C$4,Data_wide!$B$2:$B$218,0))),"") | H99: High = more developed | I99: Energy-efficiency finance | J99: World Bank RISE 2024 | K99: 140 | L99: =IF(F99="","-","Yes")
C100: Appendix C — What do the macro-fiscal models start from? | D100: reference | E100: =IFERROR(ROUND(AVERAGE(E101:E105),1),"") | H100: Macro-model inputs | I100: Reference detail - WEO ratios read by MacroFiscalModels | L100: =COUNT(F101:F105)&"/5"
B101: ● | C101: Revenue, general govt (% GDP) | D101: =IF(E101="","",IF(E101>=7,"High",IF(E101>=4,"Medium","Low"))) | E101: =IFERROR(INDEX(Scores!$CE$6:$CE$222,MATCH($C$4,Scores!$B$6:$B$222,0)),"") | F101: =IFERROR(IF(INDEX(Data_wide!$CH$2:$CH$218,MATCH($C$4,Data_wide!$B$2:$B$218,0))="","",INDEX(Data_wide!$CH$2:$CH$218,MATCH($C$4,Data_wide!$B$2:$B$218,0))),"") | G101: =IFERROR(IF(INDEX(Data_wide!$FU$2:$FU$218,MATCH($C$4,Data_wide!$B$2:$B$218,0))="","",INDEX(Data_wide!$FU$2:$FU$218,MATCH($C$4,Data_wide!$B$2:$B$218,0))),"") | H101: High = more revenue | I101: Fiscal | J101: IMF WEO | K101: 195 | L101: =IF(F101="","-","Yes")
C102: Primary balance, general govt (% GDP) | D102: =IF(E102="","",IF(E102>=7,"High",IF(E102>=4,"Medium","Low"))) | E102: =IFERROR(INDEX(Scores!$CF$6:$CF$222,MATCH($C$4,Scores!$B$6:$B$222,0)),"") | F102: =IFERROR(IF(INDEX(Data_wide!$CI$2:$CI$218,MATCH($C$4,Data_wide!$B$2:$B$218,0))="","",INDEX(Data_wide!$CI$2:$CI$218,MATCH($C$4,Data_wide!$B$2:$B$218,0))),"") | G102: =IFERROR(IF(INDEX(Data_wide!$FV$2:$FV$218,MATCH($C$4,Data_wide!$B$2:$B$218,0))="","",INDEX(Data_wide!$FV$2:$FV$218,MATCH($C$4,Data_wide!$B$2:$B$218,0))),"") | H102: High = stronger balance | I102: Fiscal | J102: IMF WEO | K102: 189 | L102: =IF(F102="","-","Yes")
C103: Current account balance (% GDP) | D103: =IF(E103="","",IF(E103>=7,"High",IF(E103>=4,"Medium","Low"))) | E103: =IFERROR(INDEX(Scores!$CG$6:$CG$222,MATCH($C$4,Scores!$B$6:$B$222,0)),"") | F103: =IFERROR(IF(INDEX(Data_wide!$CJ$2:$CJ$218,MATCH($C$4,Data_wide!$B$2:$B$218,0))="","",INDEX(Data_wide!$CJ$2:$CJ$218,MATCH($C$4,Data_wide!$B$2:$B$218,0))),"") | G103: =IFERROR(IF(INDEX(Data_wide!$FW$2:$FW$218,MATCH($C$4,Data_wide!$B$2:$B$218,0))="","",INDEX(Data_wide!$FW$2:$FW$218,MATCH($C$4,Data_wide!$B$2:$B$218,0))),"") | H103: High = stronger balance | I103: External | J103: IMF WEO | K103: 194 | L103: =IF(F103="","-","Yes")
...

Sheet Data_wide
A1: iso3 | B1: country | C1: region | D1: income | E1: is_ccdr | F1: interest_to_revenue_pct | G1: interest_pct_gdp | H1: gross_debt_pct_gdp | I1: tax_revenue_pct_gdp | J1: capex_execution_rate_pct | K1: pefa_pi11_pim_score | L1: pefa_pi122_asset_monitoring | M1: climate_pfm_diagnostic_on_record | N1: wacc_solar_real_aftertax_pct | O1: wacc_steffen_nominal_aftertax_pct | P1: wacc_n_sources | Q1: wacc_iea_observatory_available | R1: ids_official_private_rate_spread_pp | S1: ids_private_creditor_rate_pct | T1: ids_avg_maturity_years | U1: mitigation_finance_received_pct_gdp | V1: ids_multilateral_share_pct | W1: ids_private_creditor_share_pct | X1: ids_usd_share_ppg_debt_pct | Y1: pefa_pi103_contingent_liabilities | Z1: ppi_commitments_pct_gdp | AA1: excise_revenue_pct_of_revenue | AB1: ff_subsidy_total_pct_gdp | AC1: ff_subsidy_explicit_pct_gdp | AD1: ff_subsidy_implicit_pct_gdp | AE1: env_protection_pct_of_expenditure | AF1: net_fuel_trade_pct_merch | AG1: fuel_exports_pct_merch | AH1: fuel_imports_pct_merch | AI1: energy_import_dep_pct | AJ1: fossil_rents_total_pct_gdp | AK1: oil_rents_pct_gdp | AL1: gas_rents_pct_gdp | AM1: coal_rents_pct_gdp | AN1: other_fossil_gen_share_pct | AO1: renewable_share_electricity_pct | AP1: re_share_change_pp | AQ1: re_capacity_growth_pct | AR1: inn_total_inv_2030_pct_gdp | AS1: inn_incr_inv_2030_pct_gdp | AT1: inn_incr_inv_gen_2030_pct_gdp | AU1: inn_incr_inv_grid_2030_pct_gdp | AV1: inn_incr_inv_trn_2030_pct_gdp | AW1: inn_incr_inv_bld_2030_pct_gdp | AX1: inn_incr_inv_ind_2030_pct_gdp | AY1: inn_incr_inv_fuel_2030_pct_gdp | AZ1: inn_incr_inv_afolu_2030_pct_gdp | BA1: inn_incr_cost_a_2030_pct_gdp | BB1: inn_incr_cost_b_2030_pct_gdp | BC1: inn_incr_cost_c_2030_pct_gdp | BD1: inn_cost_per_t_b_2030_usd | BE1: inn_coc_penalty_2030_pct_gdp | BF1: inn_pima_adj_inv_2030_pct_gdp | BG1: nmim_nz_inv_2030_pct_gdp | BH1: nmim_typ1_2030_pct_gdp | BI1: nmim_typ2_2030_pct_gdp | BJ1: nmim_typ3_2030_pct_gdp | BK1: nmim_typ4_2030_pct_gdp | BL1: nmim_typ5_2030_pct_gdp | BM1: nmim_budget_need_2030_pct_gdp | BN1: nmim_private_share_2030_pct | BO1: nmim_incr_inv_2030_pct_gdp | BP1: nmim_incr_inv_2050_pct_gdp | BQ1: nmim_pv_incr_cost_b_pct_gdp | BR1: price_diesel_usd_litre | BS1: price_gasoline_usd_litre | BT1: price_electricity_residential_usd_kwh | BU1: price_electricity_industry_usd_kwh | BV1: price_gas_residential_usd_gj | BW1: price_gas_industry_usd_gj | BX1: price_gas_power_usd_gj | BY1: price_coal_residential_usd_gj | BZ1: price_coal_industry_usd_gj | CA1: price_coal_power_usd_gj | CB1: power_market_structure | CC1: independent_regulator | CD1: generation_unbundled | CE1: rise_renewable_energy_score | CF1: rise_level_playing_field_score | CG1: rise_ee_financing_mechanisms_score | CH1: revenue_pct_gdp | CI1: primary_balance_pct_gdp | CJ1: current_account_pct_gdp | CK1: gross_capital_formation_pct_gdp | CL1: real_gdp_growth_5y_avg_pct | CM1: int_budget_need_2030_pct_gdp | CN1: int_pricing_revenue_2030_pct_gdp | CO1: int_financing_gap_2030_pct_gdp | CP1: int_gdp_dev_2050_pct | CQ1: int_debt_2050_pct_gdp | CR1: int_dsf_risk_code | CS1: interest_to_revenue_pct__year | CT1: interest_pct_gdp__year | CU1: gross_debt_pct_gdp__year | CV1: tax_revenue_pct_gdp__year | CW1: capex_execution_rate_pct__year | CX1: pefa_pi11_pim_score__year | CY1: pefa_pi122_asset_monitoring__year | CZ1: climate_pfm_diagnostic_on_record__year | DA1: wacc_solar_real_aftertax_pct__year | DB1: wacc_steffen_nominal_aftertax_pct__year | DC1: wacc_n_sources__year | DD1: wacc_iea_observatory_available__year | DE1: ids_official_private_rate_spread_pp__year | DF1: ids_private_creditor_rate_pct__year | DG1: ids_avg_maturity_years__year | DH1: mitigation_finance_received_pct_gdp__year | DI1: ids_multilateral_share_pct__year | DJ1: ids_private_creditor_share_pct__year | DK1: ids_usd_share_ppg_debt_pct__year | DL1: pefa_pi103_contingent_liabilities__year | DM1: ppi_commitments_pct_gdp__year | DN1: excise_revenue_pct_of_revenue__year | DO1: ff_subsidy_total_pct_gdp__year | DP1: ff_subsidy_explicit_pct_gdp__year | DQ1: ff_subsidy_implicit_pct_gdp__year | DR1: env_protection_pct_of_expenditure__year | DS1: net_fuel_trade_pct_merch__year | DT1: fuel_exports_pct_merch__year | DU1: fuel_imports_pct_merch__year | DV1: energy_import_dep_pct__year | DW1: fossil_rents_total_pct_gdp__year | DX1: oil_rents_pct_gdp__year | DY1: gas_rents_pct_gdp__year | DZ1: coal_rents_pct_gdp__year | EA1: other_fossil_gen_share_pct__year | EB1: renewable_share_electricity_pct__year | EC1: re_share_change_pp__year | ED1: re_capacity_growth_pct__year | EE1: inn_total_inv_2030_pct_gdp__year | EF1: inn_incr_inv_2030_pct_gdp__year | EG1: inn_incr_inv_gen_2030_pct_gdp__year | EH1: inn_incr_inv_grid_2030_pct_gdp__year | EI1: inn_incr_inv_trn_2030_pct_gdp__year | EJ1: inn_incr_inv_bld_2030_pct_gdp__year | EK1: inn_incr_inv_ind_2030_pct_gdp__year | EL1: inn_incr_inv_fuel_2030_pct_gdp__year | EM1: inn_incr_inv_afolu_2030_pct_gdp__year | EN1: inn_incr_cost_a_2030_pct_gdp__year | EO1: inn_incr_cost_b_2030_pct_gdp__year | EP1: inn_incr_cost_c_2030_pct_gdp__year | EQ1: inn_cost_per_t_b_2030_usd__year | ER1: inn_coc_penalty_2030_pct_gdp__year | ES1: inn_pima_adj_inv_2030_pct_gdp__year | ET1: nmim_nz_inv_2030_pct_gdp__year | EU1: nmim_typ1_2030_pct_gdp__year | EV1: nmim_typ2_2030_pct_gdp__year | EW1: nmim_typ3_2030_pct_gdp__year | EX1: nmim_typ4_2030_pct_gdp__year | EY1: nmim_typ5_2030_pct_gdp__year | EZ1: nmim_budget_need_2030_pct_gdp__year | FA1: nmim_private_share_2030_pct__year | FB1: nmim_incr_inv_2030_pct_gdp__year | FC1: nmim_incr_inv_2050_pct_gdp__year | FD1: nmim_pv_incr_cost_b_pct_gdp__year | FE1: price_diesel_usd_litre__year | FF1: price_gasoline_usd_litre__year | FG1: price_electricity_residential_usd_kwh__year | FH1: price_electricity_industry_usd_kwh__year | FI1: price_gas_residential_usd_gj__year | FJ1: price_gas_industry_usd_gj__year | FK1: price_gas_power_usd_gj__year | FL1: price_coal_residential_usd_gj__year | FM1: price_coal_industry_usd_gj__year | FN1: price_coal_power_usd_gj__year | FO1: power_market_structure__year | FP1: independent_regulator__year | FQ1: generation_unbundled__year | FR1: rise_renewable_energy_score__year | FS1: rise_level_playing_field_score__year | FT1: rise_ee_financing_mechanisms_score__year | FU1: revenue_pct_gdp__year | FV1: primary_balance_pct_gdp__year | FW1: current_account_pct_gdp__year | FX1: gross_capital_formation_pct_gdp__year | FY1: real_gdp_growth_5y_avg_pct__year | FZ1: int_budget_need_2030_pct_gdp__year | GA1: int_pricing_revenue_2030_pct_gdp__year | GB1: int_financing_gap_2030_pct_gdp__year | GC1: int_gdp_dev_2050_pct__year | GD1: int_debt_2050_pct_gdp__year | GE1: int_dsf_risk_code__year
A2: AFG | B2: Afghanistan | C2: Middle East & North Africa | D2: Low income | E2: FALSE | F2: 0.241 | G2: 0.046 | H2: 8.912 | I2: 10.867 | J2: 94.541 | K2: 1.5 | L2: 1 | M2: 0 | T2: 39.833 | U2: 0.056 | V2: 45.043 | X2: 72.025 | Y2: 1 | AA2: 0 | AB2: 9.3 | AC2: 1.383 | AD2: 7.917 | AE2: 0.436 | AF2: -14.644 | AG2: 8.051 | AH2: 22.695 | AJ2: 0.039 | AK2: 0.018 | AL2: 0.002 | AM2: 0.019 | AN2: 10.101 | AO2: 93.86 | AP2: 0.271 | AQ2: 1.923 | AR2: 8.8928901 | AS2: 2.1342936 | AT2: 0.4956232 | AU2: 0.33985591 | AV2: 0.31154014 | AW2: 0.23198169 | AX2: 0.096766924 | AY2: 0.12266699 | AZ2: 0.53585877 | BA2: 0.091178249 | BB2: 0.013370869 | BC2: -0.067820175 | BD2: 10.491672 | BE2: 0.32419742 | BF2: 10.850705 | BG2: 4.3584008 | BH2: 1.2832666 | BI2: 0.16395742 | BJ2: 0.28310723 | BK2: 2.0059837 | BL2: 0.62208593 | BM2: 1.8850616 | BN2: 52.986906 | BO2: 3.5820085 | BP2: 2.9387382 | BQ2: -13.376709 | BT2: 0.059 | BU2: 0.029 | BV2: 15.829 | BW2: 6.449 | BX2: 5.125 | BY2: 23.086 | BZ2: 7.124 | CA2: 4.833 | CB2: 3 | CC2: 0 | CD2: 0 | CE2: 12.116 | CF2: 0 | CG2: 33.333 | CH2: 19.121 | CI2: -0.502 | CJ2: -39.612 | CK2: 10.895 | CL2: -3.799 | CM2: 1.577 | CN2: 0.176 | CO2: 1.4 | CP2: 1.957 | CQ2: 27.67 | CR2: 1 | CS2: 2024 | CT2: 2024 | CU2: 2024 | CV2: 2024 | CW2: 2019 | CX2: 2018 | CY2: 2018 | CZ2: 2022 | DG2: 2019 | DH2: 2024 | DI2: 2024 | DK2: 2024 | DL2: 2018 | DN2: 2024 | DO2: 2024 | DP2: 2024 | DQ2: 2024 | DR2: 2020 | DS2: 2019 | DT2: 2019 | DU2: 2019 | DW2: 2021 | DX2: 2021 | DY2: 2021 | DZ2: 2021 | EA2: 2024 | EB2: 2024 | EC2: 2024 | ED2: 2024 | EE2: 2030 | EF2: 2030 | EG2: 2030 | EH2: 2030 | EI2: 2030 | EJ2: 2030 | EK2: 2030 | EL2: 2030 | EM2: 2030 | EN2: 2030 | EO2: 2030 | EP2: 2030 | EQ2: 2030 | ER2: 2030 | ES2: 2030 | ET2: 2030 | EU2: 2030 | EV2: 2030 | EW2: 2030 | EX2: 2030 | EY2: 2030 | EZ2: 2030 | FA2: 2030 | FB2: 2030 | FC2: 2050 | FD2: 2025-2050 | FG2: 2024 | FH2: 2024 | FI2: 2024 | FJ2: 2024 | FK2: 2024 | FL2: 2024 | FM2: 2024 | FN2: 2024 | FO2: 2013 | FP2: 2013 | FQ2: 2013 | FR2: 2023 | FS2: 2023 | FT2: 2023 | FU2: 2024 | FV2: 2024 | FW2: 2024 | FX2: 2024 | FY2: 2020-2024 avg | FZ2: 2030 | GA2: 2030 | GB2: 2030 | GC2: 2050 | GD2: 2050 | GE2: 2034
A3: ALB | B3: Albania | C3: Europe & Central Asia | D3: Upper middle income | E3: TRUE | F3: 7.667 | G3: 2.163 | H3: 54.505 | I3: 19.751 | J3: 100.792 | K3: 3 | L3: 2 | M3: 0 | R3: 1.982 | S3: 5.9 | T3: 18.669 | U3: 1.349 | V3: 46.852 | W3: 35.24 | X3: 34.055 | Y3: 2 | Z3: 0.23 | AA3: 9.063 | AB3: 1.686 | AC3: 0 | AD3: 1.686 | AE3: 1.095 | AF3: -5.325 | AG3: 3.258 | AH3: 8.583 | AI3: 22.702 | AJ3: 1.123 | AK3: 1.042 | AL3: 0.049 | AM3: 0.032 | AN3: 0 | AO3: 100 | AP3: -0.004 | AQ3: 20.147 | AR3: 4.7694382 | AS3: 1.1446652 | AT3: 0.37399992 | AU3: 0.25645709 | AV3: 0.13935624 | AW3: 0.11575342 | AX3: 0.051332012 | AY3: 0.056244476 | AZ3: 0.15152201 | BA3: 0.01498067 | BB3: -0.027000274 | BC3: -0.11103268 | BD3: -53.218321 | BE3: 0.1749206 | BF3: 5.3075286 | BG3: 1.6889921 | BH3: 0.14420362 | BI3: 0.24595084 | BJ3: 0.34637119 | BK3: 0.35033389 | BL3: 0.60213252 | BM3: 0.24930378 | BN3: 70.677504 | BO3: 0.97040461 | BP3: 0.91643395 | BQ3: -0.91440094 | BR3: 1.714 | BS3: 1.889 | BT3: 0.123 | BU3: 0.138 | BV3: 13.93 | BW3: 6.853 | BX3: 6.975 | BY3: 11.7 | BZ3: 5.333 | CA3: 4.713 | CB3: 3 | CC3: 1 | CD3: 1 | CE3: 51.011 | CF3: 40 | CG3: 16.667 | CH3: 28.212 | CI3: 1.438 | CJ3: -2.425 | CK3: 25.51 | CL3: 3.709 | CM3: 0.161 | CN3: 0 | CO3: 0.161 | CP3: 4.369 | CQ3: 54.43 | CS3: 2024 | CT3: 2024 | CU3: 2024 | CV3: 2024 | CW3: 2022 | CX3: 2025 | CY3: 2025 | CZ3: 2022 | DE3: 2024 | DF3: 2023 | DG3: 2024 | DH3: 2024 | DI3: 2024 | DJ3: 2024 | DK3: 2024 | DL3: 2025 | DM3: 2020-2024 avg | DN3: 2024 | DO3: 2024 | DP3: 2024 | DQ3: 2024 | DR3: 2022 | DS3: 2024 | DT3: 2024 | DU3: 2024 | DV3: 2023 | DW3: 2021 | DX3: 2021 | DY3: 2021 | DZ3: 2021 | EA3: 2025 | EB3: 2024 | EC3: 2025 | ED3: 2024 | EE3: 2030 | EF3: 2030 | EG3: 2030 | EH3: 2030 | EI3: 2030 | EJ3: 2030 | EK3: 2030 | EL3: 2030 | EM3: 2030 | EN3: 2030 | EO3: 2030 | EP3: 2030 | EQ3: 2030 | ER3: 2030 | ES3: 2030 | ET3: 2030 | EU3: 2030 | EV3: 2030 | EW3: 2030 | EX3: 2030 | EY3: 2030 | EZ3: 2030 | FA3: 2030 | FB3: 2030 | FC3: 2050 | FD3: 2025-2050 | FE3: 2024 | FF3: 2024 | FG3: 2024 | FH3: 2024 | FI3: 2024 | FJ3: 2024 | FK3: 2024 | FL3: 2024 | FM3: 2024 | FN3: 2024 | FO3: 2013 | FP3: 2013 | FQ3: 2013 | FR3: 2023 | FS3: 2023 | FT3: 2023 | FU3: 2024 | FV3: 2024 | FW3: 2024 | FX3: 2024 | FY3: 2020-2024 avg | FZ3: 2030 | GA3: 2030 | GB3: 2030 | GC3: 2050 | GD3: 2050
A4: DZA | B4: Algeria | C4: Middle East & North Africa | D4: Upper middle income | E4: FALSE | F4: 4.884 | G4: 1.123 | H4: 48.069 | I4: 9.35 | M4: 0 | N4: 11 | P4: 1 | T4: 19.583 | U4: 0.014 | V4: 84.213 | W4: 0 | X4: 0 | Z4: 0.005 | AA4: 1.195 | AB4: 19.195 | AC4: 9.347 | AD4: 9.848 | AF4: 91.904 | AG4: 96.112 | AH4: 4.208 | AI4: -129.337 | AJ4: 22.458 | AK4: 14.462 | AL4: 7.996 | AM4: 0 | AN4: 0.342 | AO4: 2.422 | AP4: 0.12 | AQ4: 0 | AR4: 5.7794066 | AS4: 1.3870576 | AT4: 0.34751635 | AU4: 0.23829692 | AV4: 0.19273818 | AW4: 0.19837275 | AX4: 0.066861937 | AY4: 0.10448006 | AZ4: 0.23879139 | BA4: 0.11251862 | BB4: 0.028888981 | BC4: -0.027798306 | BD4: 31.259575 | BE4: 0.34845683 | BF4: 6.6344421 | BG4: 4.0442591 | BH4: 0.9160609 | BI4: 0.39948238 | BJ4: 0.40722623 | BK4: 1.6451074 | BL4: 0.67638209 | BM4: 1.4095931 | BN4: 55.26806 | BO4: 2.9572435 | BP4: 2.8240353 | BQ4: 1.7147137 | BR4: 0.182 | BS4: 0.288 | BT4: 0.036 | BU4: 0.013 | BV4: 0.796 | BW4: 0.99 | BX4: 1.262 | BY4: 14.762 | BZ4: 7.281 | CA4: 5.787 | CB4: 2 | CC4: 1 | CD4: 1 | CE4: 19.339 | CF4: 0 | CG4: 50 | CH4: 22.995 | CI4: -12.668 | CJ4: -1.073 | CK4: 41.124 | CL4: 2.04 | CM4: 1.026 | CN4: 0.134 | CO4: 0.892 | CP4: -14.69 | CQ4: 85.27 | CS4: 2024 | CT4: 2024 | CU4: 2024 | CV4: 2024 | CZ4: 2022 | DA4: 2021 | DC4: 2021-2024 | DG4: 2016 | DH4: 2024 | DI4: 2024 | DJ4: 2023 | DK4: 2024 | DM4: 2020-2024 avg | DN4: 2024 | DO4: 2024 | DP4: 2024 | DQ4: 2024 | DS4: 2017 | DT4: 2017 | DU4: 2017 | DV4: 2023 | DW4: 2021 | DX4: 2021 | DY4: 2021 | DZ4: 2021 | EA4: 2024 | EB4: 2024 | EC4: 2024 | ED4: 2024 | EE4: 2030 | EF4: 2030 | EG4: 2030 | EH4: 2030 | EI4: 2030 | EJ4: 2030 | EK4: 2030 | EL4: 2030 | EM4: 2030 | EN4: 2030 | EO4: 2030 | EP4: 2030 | EQ4: 2030 | ER4: 2030 | ES4: 2030 | ET4: 2030 | EU4: 2030 | EV4: 2030 | EW4: 2030 | EX4: 2030 | EY4: 2030 | EZ4: 2030 | FA4: 2030 | FB4: 2030 | FC4: 2050 | FD4: 2025-2050 | FE4: 2024 | FF4: 2024 | FG4: 2024 | FH4: 2024 | FI4: 2024 | FJ4: 2024 | FK4: 2024 | FL4: 2024 | FM4: 2024 | FN4: 2024 | FO4: 2013 | FP4: 2013 | FQ4: 2013 | FR4: 2023 | FS4: 2023 | FT4: 2023 | FU4: 2024 | FV4: 2024 | FW4: 2024 | FX4: 2024 | FY4: 2020-2024 avg | FZ4: 2030 | GA4: 2030 | GB4: 2030 | GC4: 2050 | GD4: 2050
A5: ASM | B5: American Samoa | C5: East Asia & Pacific | D5: High income | E5: FALSE | M5: 0 | AJ5: 0 | AK5: 0 | AL5: 0 | AM5: 0 | AN5: 94.444 | AP5: 5.556 | AQ5: 0 | CZ5: 2022 | DW5: 2021 | DX5: 2021 | DY5: 2021 | DZ5: 2021 | EA5: 2024 | EC5: 2024 | ED5: 2024
A6: AND | B6: Andorra | C6: Europe & Central Asia | D6: High income | E6: FALSE | F6: 1.325 | G6: 0.529 | H6: 32.889 | I6: 15.812 | M6: 0 | AF6: -8.638 | AG6: 0.01 | AH6: 8.648 | AR6: 3.5281571 | AS6: 1.3406997 | AT6: 0.46338539 | AU6: 0.31774998 | AV6: 0.19469002 | AW6: 0.15186413 | AX6: 0.087731103 | AY6: 0.10526126 | AZ6: 0.020017811 | BA6: -0.014405898 | BB6: -0.0094267006 | BC6: -0.12780851 | BD6: -21.668497 | BE6: -0.013103152 | BF6: 3.6863159 | CB6: 1 | CC6: 0 | CD6: 0 | CH6: 39.91 | CI6: 3.312 | CJ6: 15.941 | CL6: 2.62 | CS6: 2024 | CT6: 2024 | CU6: 2024 | CV6: 2024 | CZ6: 2022 | DS6: 2023 | DT6: 2023 | DU6: 2023 | EE6: 2030 | EF6: 2030 | EG6: 2030 | EH6: 2030 | EI6: 2030 | EJ6: 2030 | EK6: 2030 | EL6: 2030 | EM6: 2030 | EN6: 2030 | EO6: 2030 | EP6: 2030 | EQ6: 2030 | ER6: 2030 | ES6: 2030 | FO6: 2013 | FP6: 2013 | FQ6: 2013 | FU6: 2024 | FV6: 2024 | FW6: 2024 | FY6: 2020-2024 avg
A7: AGO | B7: Angola | C7: Sub-Saharan Africa | D7: Lower middle income | E7: TRUE | F7: 25.816 | G7: 4.593 | H7: 57.107 | I7: 5.608 | J7: 113.01 | M7: 0 | R7: -1.088 | S7: 4.681 | T7: 11.087 | U7: 0.333 | V7: 13.443 | W7: 77.629 | X7: 86.499 | Z7: 0.438 | AB7: 5.948 | AC7: 3.212 | AD7: 2.737 | AE7: 0.077 | AF7: 73.589 | AG7: 94.135 | AH7: 20.546 | AI7: -353.972 | AJ7: 29.286 | AK7: 28.274 | AL7: 1.012 | AM7: 0 | AN7: 17.319 | AO7: 72.85 | AP7: -0.331 | AQ7: 1.222 | AR7: 5.3038794 | AS7: 1.272931 | AT7: 0.30159661 | AU7: 0.2068091 | AV7: 0.1507162 | AW7: 0.13412771 | AX7: 0.048323464 | AY7: 0.067789568 | AZ7: 0.36356838 | BA7: 0.072825439 | BB7: 0.026139022 | BC7: -0.028290735 | BD7: 31.081943 | BE7: 0.19452674 | BF7: 6.0885629 | BG7: 3.4866256 | BH7: 1.6148338 | BI7: 0.13878981 | BJ7: 0.17937386 | BK7: 1.228093 | BL7: 0.32553508 | BM7: 1.9832617 | BN7: 39.137385 | BO7: 2.8726504 | BP7: 2.0180929 | BQ7: 14.62693 | BR7: 0.185 | BS7: 0.303 | BT7: 0.012 | BU7: 0.01 | BV7: 12.161 | BW7: 6.696 | BX7: 6.034 | BY7: 13.997 | BZ7: 7.187 | CA7: 5.66 | CB7: 1 | CC7: 1 | CD7: 0 | CE7: 28.259 | CF7: 0 | CG7: 0 | CH7: 17.791 | CI7: 3.401 | CJ7: 5.277 | CK7: 10.638 | CL7: 1.711 | CM7: 1.751 | CN7: 0.006 | CO7: 1.745 | CP7: -20.53 | CQ7: 82.13 | CR7: 3 | CS7: 2024 | CT7: 2024 | CU7: 2024 | CV7: 2024 | CW7: 2022 | CZ7: 2022 | DE7: 2024 | DF7: 2024 | DG7: 2024 | DH7: 2024 | DI7: 2024 | DJ7: 2024 | DK7: 2024 | DM7: 2020-2024 avg | DO7: 2024 | DP7: 2024 | DQ7: 2024 | DR7: 2022 | DS7: 2024 | DT7: 2024 | DU7: 2024 | DV7: 2022 | DW7: 2021 | DX7: 2021 | DY7: 2021 | DZ7: 2021 | EA7: 2024 | EB7: 2024 | EC7: 2024 | ED7: 2024 | EE7: 2030 | EF7: 2030 | EG7: 2030 | EH7: 2030 | EI7: 2030 | EJ7: 2030 | EK7: 2030 | EL7: 2030 | EM7: 2030 | EN7: 2030 | EO7: 2030 | EP7: 2030 | EQ7: 2030 | ER7: 2030 | ES7: 2030 | ET7: 2030 | EU7: 2030 | EV7: 2030 | EW7: 2030 | EX7: 2030 | EY7: 2030 | EZ7: 2030 | FA7: 2030 | FB7: 2030 | FC7: 2050 | FD7: 2025-2050 | FE7: 2024 | FF7: 2024 | FG7: 2024 | FH7: 2024 | FI7: 2024 | FJ7: 2024 | FK7: 2024 | FL7: 2024 | FM7: 2024 | FN7: 2024 | FO7: 2013 | FP7: 2013 | FQ7: 2013 | FR7: 2023 | FS7: 2023 | FT7: 2023 | FU7: 2024 | FV7: 2024 | FW7: 2024 | FX7: 2024 | FY7: 2020-2024 avg | FZ7: 2030 | GA7: 2030 | GB7: 2030 | GC7: 2050 | GD7: 2050 | GE7: 2034
A8: ATG | B8: Antigua and Barbuda | C8: Latin America & Caribbean | D8: High income | E8: FALSE | F8: 10.827 | G8: 2.368 | H8: 71.773 | I8: 15.581 | M8: 0 | AB8: 2.169 | AC8: 0.35 | AD8: 1.818 | AF8: -0.678 | AG8: 0 | AH8: 0.678 | AJ8: 0 | AK8: 0 | AL8: 0 | AM8: 0 | AN8: 91.892 | AO8: 21.024 | AP8: 2.552 | AQ8: 0 | AR8: 4.6231267 | AS8: 1.1095504 | AT8: 0.29273368 | AU8: 0.20073167 | AV8: 0.22294024 | AW8: 0.072253597 | AX8: 0.11787678 | AY8: 0.094842268 | AZ8: 0.10817217 | BA8: -0.041850375 | BB8: -0.081747733 | BC8: -0.10183365 | BD8: -97.494993 | BE8: 0.16623899 | BF8: 5.3070961 | BG8: 4.1327783 | BH8: 0.099574618 | BI8: 1.0787503 | BJ8: 0.7289363 | BK8: 0.93707767 | BL8: 1.2884395 | BM8: 0.38069792 | BN8: 64.686028 | BO8: 3.289848 | BP8: 3.3102898 | BQ8: 0.17714738 | BR8: 1.206 | BS8: 1.56 | BT8: 0.449 | BU8: 0.822 | BV8: 24.233 | BW8: 12.771 | BX8: 11.447 | BY8: 14.266 | BZ8: 7.124 | CA8: 5.575 | CB8: 2 | CC8: 0 | CD8: 0 | CH8: 21.872 | CI8: 4.014 | CJ8: -7.457 | CK8: 33.398 | CL8: 0.842 | CM8: 0.299 | CN8: 1.837 | CO8: -1.538 | CP8: 18.43 | CQ8: 54.07 | CS8: 2024 | CT8: 2024 | CU8: 2024 | CV8: 2024 | CZ8: 2022 | DO8: 2024 | DP8: 2024 | DQ8: 2024 | DS8: 2024 | DT8: 2024 | DU8: 2024 | DW8: 2021 | DX8: 2021 | DY8: 2021 | DZ8: 2021 | EA8: 2024 | EB8: 2024 | EC8: 2024 | ED8: 2024 | EE8: 2030 | EF8: 2030 | EG8: 2030 | EH8: 2030 | EI8: 2030 | EJ8: 2030 | EK8: 2030 | EL8: 2030 | EM8: 2030 | EN8: 2030 | EO8: 2030 | EP8: 2030 | EQ8: 2030 | ER8: 2030 | ES8: 2030 | ET8: 2030 | EU8: 2030 | EV8: 2030 | EW8: 2030 | EX8: 2030 | EY8: 2030 | EZ8: 2030 | FA8: 2030 | FB8: 2030 | FC8: 2050 | FD8: 2025-2050 | FE8: 2024 | FF8: 2024 | FG8: 2024 | FH8: 2024 | FI8: 2024 | FJ8: 2024 | FK8: 2024 | FL8: 2024 | FM8: 2024 | FN8: 2024 | FO8: 2013 | FP8: 2013 | FQ8: 2013 | FU8: 2024 | FV8: 2024 | FW8: 2024 | FX8: 2024 | FY8: 2020-2024 avg | FZ8: 2030 | GA8: 2030 | GB8: 2030 | GC8: 2050 | GD8: 2050
A9: ARG | B9: Argentina | C9: Latin America & Caribbean | D9: Upper middle income | E9: TRUE | F9: 5.445 | G9: 1.714 | H9: 84.653 | I9: 22.823 | J9: 97.306 | K9: 1.5 | L9: 2 | M9: 0 | N9: 13.8 | O9: 9.3 | P9: 2 | R9: -2.971 | S9: 3.721 | T9: 12.617 | U9: 0.336 | V9: 31.558 | W9: 62.387 | X9: 92.809 | Y9: 3 | Z9: 0.076 | AA9: 3.4 | AB9: 6.221 | AC9: 2.164 | AD9: 4.058 | AE9: 0.274 | AF9: 2.551 | AG9: 8.77 | AH9: 6.219 | AI9: 0.416 | AJ9: 1.933 | AK9: 1.544 | AL9: 0.389 | AM9: 0 | AN9: 3.866 | AO9: 37.229 | AP9: 0.2 | AQ9: 6.841 | AR9: 4.7471991 | AS9: 1.1393278 | AT9: 0.31180059 | AU9: 0.21380612 | AV9: 0.1367259 | AW9: 0.12584165 | AX9: 0.055652711 | AY9: 0.069348591 | AZ9: 0.22615223 | BA9: 0.078604395 | BB9: 0.014930971 | BC9: -0.037927559 | BD9: 21.442011 | BE9: 0.26530593 | BF9: 5.7923189 | BG9: 2.6957288 | BH9: 0.42720891 | BI9: 0.28082479 | BJ9: 0.37133381 | BK9: 1.0490511 | BL9: 0.56731018 | BM9: 0.74192425 | BN9: 62.060388 | BO9: 1.9132613 | BP9: 1.7162013 | BQ9: 6.6670093 | BR9: 0.961 | BS9: 1.071 | BT9: 0.081 | BU9: 0.114 | BV9: 9.735 | BW9: 7.576 | BY9: 14.944 | BZ9: 7.328 | CA9: 5.767 | CB9: 3 | CC9: 1 | CD9: 1 | CE9: 49.622 | CF9: 40 | CG9: 66.667 | CH9: 31.477 | CI9: 2.172 | CJ9: 0.894 | CK9: 15.829 | CL9: 0.673 | CM9: 0.595 | CN9: 0.117 | CO9: 0.478 | CP9: 6.661 | CQ9: 86.56 | CS9: 2024 | CT9: 2024 | CU9: 2024 | CV9: 2024 | CW9: 2022 | CX9: 2019 | CY9: 2019 | CZ9: 2022 | DA9: 2021 | DB9: 2020 | DC9: 2021-2024 | DE9: 2024 | DF9: 2024 | DG9: 2024 | DH9: 2024 | DI9: 2024 | DJ9: 2024 | DK9: 2024 | DL9: 2019 | DM9: 2020-2024 avg | DN9: 2024 | DO9: 2024 | DP9: 2024 | DQ9: 2024 | DR9: 2022 | DS9: 2024 | DT9: 2024 | DU9: 2024 | DV9: 2023 | DW9: 2021 | DX9: 2021 | DY9: 2021 | DZ9: 2021 | EA9: 2025 | EB9: 2024 | EC9: 2025 | ED9: 2025 | EE9: 2030 | EF9: 2030 | EG9: 2030 | EH9: 2030 | EI9: 2030 | EJ9: 2030 | EK9: 2030 | EL9: 2030 | EM9: 2030 | EN9: 2030 | EO9: 2030 | EP9: 2030 | EQ9: 2030 | ER9: 2030 | ES9: 2030 | ET9: 2030 | EU9: 2030 | EV9: 2030 | EW9: 2030 | EX9: 2030 | EY9: 2030 | EZ9: 2030 | FA9: 2030 | FB9: 2030 | FC9: 2050 | FD9: 2025-2050 | FE9: 2024 | FF9: 2024 | FG9: 2024 | FH9: 2024 | FI9: 2024 | FJ9: 2024 | FL9: 2024 | FM9: 2024 | FN9: 2024 | FO9: 2013 | FP9: 2013 | FQ9: 2013 | FR9: 2023 | FS9: 2023 | FT9: 2023 | FU9: 2024 | FV9: 2024 | FW9: 2024 | FX9: 2024 | FY9: 2020-2024 avg | FZ9: 2030 | GA9: 2030 | GB9: 2030 | GC9: 2050 | GD9: 2050
A10: ARM | B10: Armenia | C10: Europe & Central Asia | D10: Upper middle income | E10: TRUE | F10: 12.158 | G10: 3.076 | H10: 49.961 | I10: 22.441 | J10: 107.426 | K10: 1 | L10: 2 | M10: 1 | R10: -0.421 | S10: 3.6 | T10: 21.977 | U10: 1.203 | V10: 56.811 | W10: 25.356 | X10: 72.468 | Y10: 3 | Z10: 0.089 | AA10: 6.304 | AB10: 4.261 | AC10: 0 | AD10: 4.261 | AE10: 1.407 | AF10: -5.718 | AG10: 0.679 | AH10: 6.397 | AI10: 76.872 | AJ10: 0 | AK10: 0 | AL10: 0 | AM10: 0 | AN10: 0 | AO10: 34.939 | AP10: -1.384 | AQ10: 11.413 | AR10: 4.2378666 | AS10: 1.017088 | AT10: 0.30666802 | AU10: 0.21028664 | AV10: 0.10258892 | AW10: 0.14261642 | AX10: 0.050758188 | AY10: 0.06550504 | AZ10: 0.13866477 | BA10: 0.070461711 | BB10: 0.03314974 | BC10: -0.018825165 | BD10: 68.202919 | BE10: 0.15546654 | BF10: 5.3679644 | BG10: 3.2463078 | BH10: 0.25631292 | BI10: 0.77198062 | BJ10: 0.79046401 | BK10: 0.46417243 | BL10: 0.96337784 | BM10: 0.39556465 | BN10: 64.034672 | BO10: 1.9322344 | BP10: 1.5564725 | BQ10: 7.5612426 | BT10: 0.111 | BU10: 0.123 | BY10: 13.161 | BZ10: 7.123 | CA10: 4.35 | CB10: 3 | CC10: 1 | CD10: 1 | CE10: 36.267 | CF10: 0 | CG10: 83.333 | CH10: 25.301 | CI10: -0.597 | CJ10: -4.602 | CK10: 23.833 | CL10: 5.088 | CM10: 0.3 | CN10: 0.227 | CO10: 0.073 | CP10: 4.999 | CQ10: 49.76 | CS10: 2024 | CT10: 2024 | CU10: 2024 | CV10: 2024 | CW10: 2022 | CX10: 2024 | CY10: 2024 | CZ10: 2022 | DE10: 2024 | DF10: 2021 | DG10: 2024 | DH10: 2024 | DI10: 2024 | DJ10: 2024 | DK10: 2024 | DL10: 2024 | DM10: 2020-2024 avg | DN10: 2024 | DO10: 2024 | DP10: 2024 | DQ10: 2024 | DR10: 2022 | DS10: 2024 | DT10: 2024 | DU10: 2024 | DV10: 2022 | DW10: 2021 | DX10: 2021 | DY10: 2021 | DZ10: 2021 | EA10: 2025 | EB10: 2024 | EC10: 2025 | ED10: 2025 | EE10: 2030 | EF10: 2030 | EG10: 2030 | EH10: 2030 | EI10: 2030 | EJ10: 2030 | EK10: 2030 | EL10: 2030 | EM10: 2030 | EN10: 2030 | EO10: 2030 | EP10: 2030 | EQ10: 2030 | ER10: 2030 | ES10: 2030 | ET10: 2030 | EU10: 2030 | EV10: 2030 | EW10: 2030 | EX10: 2030 | EY10: 2030 | EZ10: 2030 | FA10: 2030 | FB10: 2030 | FC10: 2050 | FD10: 2025-2050 | FG10: 2024 | FH10: 2024 | FL10: 2024 | FM10: 2024 | FN10: 2024 | FO10: 2013 | FP10: 2013 | FQ10: 2013 | FR10: 2023 | FS10: 2023 | FT10: 2023 | FU10: 2024 | FV10: 2024 | FW10: 2024 | FX10: 2024 | FY10: 2020-2024 avg | FZ10: 2030 | GA10: 2030 | GB10: 2030 | GC10: 2050 | GD10: 2050
A11: ABW | B11: Aruba | C11: Latin America & Caribbean | D11: High income | E11: FALSE | F11: 16.586 | G11: 4.056 | H11: 68.646 | I11: 20.958 | M11: 0 | AA11: 8.393 | AB11: 0 | AC11: 0 | AD11: 0 | AF11: -5.855 | AG11: 0.06 | AH11: 5.915 | AJ11: 0 | AK11: 0 | AL11: 0 | AM11: 0 | AN11: 83 | AO11: 29.227 | AP11: 0 | AQ11: 0 | AR11: 4.3704137 | AS11: 1.0488993 | AT11: 0.33710484 | AU11: 0.23115761 | AV11: 0.14169749 | AW11: 0.083945238 | AX11: 0.093086034 | AY11: 0.071079887 | AZ11: 0.090828192 | BA11: -0.056703435 | BB11: -0.094966609 | BC11: -0.1123927 | BD11: -118.24358 | BE11: 0.15942989 | BF11: 5.0169955 | BG11: 3.3255038 | BH11: 0.087498006 | BI11: 1.4676455 | BJ11: 0.2985025 | BK11: 0.57843004 | BL11: 0.8934278 | BM11: 0.26102702 | BN11: 48.017726 | BO11: 2.3451367 | BP11: 2.2152324 | BQ11: -6.1045555 | BR11: 1.328 | BS11: 1.462 | BT11: 0.275 | BU11: 0.318 | BV11: 10.375 | BW11: 2.458 | BX11: 2.458 | BY11: 12.376 | BZ11: 7.124 | CA11: 5.575 | CB11: 1 | CC11: 0 | CD11: 0 | CH11: 24.454 | CI11: 7.743 | CJ11: 9.639 | CL11: 3.593 | CM11: 0.187 | CN11: 0.82 | CO11: -0.632 | CP11: 14.33 | CQ11: 57.95 | CS11: 2024 | CT11: 2024 | CU11: 2024 | CV11: 2024 | CZ11: 2022 | DN11: 2024 | DO11: 2024 | DP11: 2024 | DQ11: 2024 | DS11: 2023 | DT11: 2023 | DU11: 2023 | DW11: 2021 | DX11: 2021 | DY11: 2021 | DZ11: 2021 | EA11: 2024 | EB11: 2024 | EC11: 2024 | ED11: 2024 | EE11: 2030 | EF11: 2030 | EG11: 2030 | EH11: 2030 | EI11: 2030 | EJ11: 2030 | EK11: 2030 | EL11: 2030 | EM11: 2030 | EN11: 2030 | EO11: 2030 | EP11: 2030 | EQ11: 2030 | ER11: 2030 | ES11: 2030 | ET11: 2030 | EU11: 2030 | EV11: 2030 | EW11: 2030 | EX11: 2030 | EY11: 2030 | EZ11: 2030 | FA11: 2030 | FB11: 2030 | FC11: 2050 | FD11: 2025-2050 | FE11: 2024 | FF11: 2024 | FG11: 2024 | FH11: 2024 | FI11: 2024 | FJ11: 2024 | FK11: 2024 | FL11: 2024 | FM11: 2024 | FN11: 2024 | FO11: 2013 | FP11: 2013 | FQ11: 2013 | FU11: 2024 | FV11: 2024 | FW11: 2024 | FY11: 2020-2024 avg | FZ11: 2030 | GA11: 2030 | GB11: 2030 | GC11: 2050 | GD11: 2050
A12: AUS | B12: Australia | C12: East Asia & Pacific | D12: High income | E12: FALSE | F12: 2.416 | G12: 0.881 | H12: 50.611 | I12: 29.408 | M12: 0 | O12: 5.02 | P12: 1 | AA12: 3.229 | AB12: 2.2 | AC12: 0.115 | AD12: 2.086 | AE12: 2.124 | AF12: 15.237 | AG12: 26.894 | AH12: 11.657 | AI12: -214.472 | AJ12: 2.768 | AK12: 0.264 | AL12: 1.718 | AM12: 0.786 | AN12: 2.219 | AO12: 39.611 | AP12: 3.628 | AQ12: 9.616 | AR12: 3.3797869 | AS12: 1.284319 | AT12: 0.42454479 | AU12: 0.29111643 | AV12: 0.22134023 | AW12: 0.1120502 | AX12: 0.096674217 | AY12: 0.11249355 | AZ12: 0.026099604 | BA12: 0.02246574 | BB12: 0.031677882 | BC12: 0.014829091 | BD12: 42.359262 | BE12: -0.024242477 | BF12: 3.5312946 | BG12: 4.0276262 | BH12: 0.2007776 | BI12: 1.0142759 | BJ12: 0.96285218 | BK12: 0.23884172 | BL12: 1.6108788 | BM12: 0.27243012 | BN12: 68.052994 | BO12: 2.3753812 | BP12: 1.2610067 | BQ12: 7.8045855 | BR12: 1.121 | BS12: 1.189 | BT12: 0.257 | BU12: 0.235 | BV12: 19.703 | BW12: 11.238 | BX12: 9.914 | BY12: 6.096 | BZ12: 5.777 | CA12: 4.461 | CE12: 67.981 | CF12: 60 | CG12: 50 | CH12: 36.463 | CI12: -1.37 | CJ12: -2.245 | CK12: 24.506 | CL12: 2.132 | CM12: 0.135 | CN12: 0.194 | CO12: -0.059 | CP12: 4.851 | CQ12: 49.32 | CS12: 2024 | CT12: 2024 | CU12: 2024 | CV12: 2024 | CZ12: 2022 | DB12: 2020 | DC12: 2021-2024 | DN12: 2024 | DO12: 2024 | DP12: 2024 | DQ12: 2024 | DR12: 2022 | DS12: 2025 | DT12: 2025 | DU12: 2025 | DV12: 2023 | DW12: 2021 | DX12: 2021 | DY12: 2021 | DZ12: 2021 | EA12: 2025 | EB12: 2024 | EC12: 2025 | ED12: 2025 | EE12: 2030 | EF12: 2030 | EG12: 2030 | EH12: 2030 | EI12: 2030 | EJ12: 2030 | EK12: 2030 | EL12: 2030 | EM12: 2030 | EN12: 2030 | EO12: 2030 | EP12: 2030 | EQ12: 2030 | ER12: 2030 | ES12: 2030 | ET12: 2030 | EU12: 2030 | EV12: 2030 | EW12: 2030 | EX12: 2030 | EY12: 2030 | EZ12: 2030 | FA12: 2030 | FB12: 2030 | FC12: 2050 | FD12: 2025-2050 | FE12: 2024 | FF12: 2024 | FG12: 2024 | FH12: 2024 | FI12: 2024 | FJ12: 2024 | FK12: 2024 | FL12: 2024 | FM12: 2024 | FN12: 2024 | FR12: 2023 | FS12: 2023 | FT12: 2023 | FU12: 2024 | FV12: 2024 | FW12: 2024 | FX12: 2024 | FY12: 2020-2024 avg | FZ12: 2030 | GA12: 2030 | GB12: 2030 | GC12: 2050 | GD12: 2050
A13: AUT | B13: Austria | C13: Europe & Central Asia | D13: High income | E13: FALSE | F13: 1.964 | G13: 0.992 | H13: 79.176 | I13: 28.33 | M13: 0 | O13: 6.11 | P13: 1 | AA13: 3.409 | AB13: 0.21 | AC13: 0.041 | AD13: 0.17 | AE13: 0.939 | AF13: -4.681 | AG13: 2.771 | AH13: 7.452 | AI13: 63.966 | AJ13: 0.062 | AK13: 0.038 | AL13: 0.024 | AM13: 0 | AN13: 4.464 | AO13: 88.811 | AP13: -2.7 | AQ13: 7.467 | AR13: 3.0715332 | AS13: 1.1671826 | AT13: 0.40753227 | AU13: 0.2794507 | AV13: 0.18386029 | AW13: 0.12037145 | AX13: 0.075662649 | AY13: 0.08489596 | AZ13: 0.015409305 | BA13: 0.034339155 | BB13: 0.033374552 | BC13: 0.021722757 | BD13: 99.36919 | BE13: 0.0025384294 | BF13: 3.2092226 | BG13: 2.5737515 | BH13: 0.25062596 | BI13: 0.44641495 | BJ13: 0.59399297 | BK13: 0.17998711 | BL13: 1.1027305 | BM13: 0.30462209 | BN13: 70.819365 | BO13: 1.0957333 | BP13: 0.85497882 | BQ13: 1.2170908 | BR13: 1.639 | BS13: 1.696 | BT13: 0.28 | BU13: 0.167 | BV13: 39.334 | BW13: 20.896 | BX13: 20.896 | BY13: 21.913 | BZ13: 26.879 | CA13: 18.327 | CE13: 82.426 | CF13: 40 | CG13: 50 | CH13: 50.51 | CI13: -3.685 | CJ13: 1.527 | CK13: 23.577 | CL13: 0.498 | CM13: 0.131 | CN13: 0.084 | CO13: 0.047 | CP13: 3.947 | CQ13: 77.71 | CS13: 2024 | CT13: 2024 | CU13: 2024 | CV13: 2024 | CZ13: 2022 | DB13: 2020 | DC13: 2021-2024 | DN13: 2023 | DO13: 2024 | DP13: 2024 | DQ13: 2024 | DR13: 2022 | DS13: 2024 | DT13: 2024 | DU13: 2024 | DV13: 2023 | DW13: 2021 | DX13: 2021 | DY13: 2021 | DZ13: 2021 | EA13: 2025 | EB13: 2024 | EC13: 2025 | ED13: 2025 | EE13: 2030 | EF13: 2030 | EG13: 2030 | EH13: 2030 | EI13: 2030 | EJ13: 2030 | EK13: 2030 | EL13: 2030 | EM13: 2030 | EN13: 2030 | EO13: 2030 | EP13: 2030 | EQ13: 2030 | ER13: 2030 | ES13: 2030 | ET13: 2030 | EU13: 2030 | EV13: 2030 | EW13: 2030 | EX13: 2030 | EY13: 2030 | EZ13: 2030 | FA13: 2030 | FB13: 2030 | FC13: 2050 | FD13: 2025-2050 | FE13: 2024 | FF13: 2024 | FG13: 2024 | FH13: 2024 | FI13: 2024 | FJ13: 2024 | FK13: 2024 | FL13: 2024 | FM13: 2024 | FN13: 2024 | FR13: 2023 | FS13: 2023 | FT13: 2023 | FU13: 2024 | FV13: 2024 | FW13: 2024 | FX13: 2024 | FY13: 2020-2024 avg | FZ13: 2030 | GA13: 2030 | GB13: 2030 | GC13: 2050 | GD13: 2050
A14: AZE | B14: Azerbaijan | C14: Europe & Central Asia | D14: Upper middle income | E14: TRUE | F14: 1.134 | G14: 0.43 | H14: 21.64 | I14: 17.785 | J14: 99.354 | M14: 1 | N14: 7 | P14: 1 | R14: 2.041 | S14: 7.23 | T14: 21.499 | U14: 0.611 | V14: 50.922 | W14: 40.628 | X14: 78.594 | Z14: 0.49 | AA14: 3.536 | AB14: 13.299 | AC14: 5.538 | AD14: 7.76 | AE14: 0.863 | AF14: 80.472 | AG14: 85.924 | AH14: 5.452 | AI14: -255.959 | AJ14: 29.57 | AK14: 20.983 | AL14: 8.587 | AM14: 0 | AN14: 0.366 | AO14: 7.837 | AP14: -2.236 | AQ14: 1.111 | AR14: 6.4972007 | AS14: 1.5593282 | AT14: 0.41607704 | AU14: 0.28530997 | AV14: 0.18074683 | AW14: 0.22811903 | AX14: 0.066928693 | AY14: 0.10762843 | AZ14: 0.27451818 | BA14: 0.070603439 | BB14: 0.031589222 | BC14: -0.039095356 | BD14: 30.939819 | BE14: 0.16255924 | BF14: 7.4584304 | BG14: 4.4050998 | BH14: 1.2030709 | BI14: 0.57929177 | BJ14: 0.54470819 | BK14: 1.187545 | BL14: 0.89048392 | BM14: 1.5593344 | BN14: 51.451131 | BO14: 3.2916333 | BP14: 3.0872531 | BQ14: 12.841008 | BR14: 0.447 | BS14: 0.537 | BT14: 0.046 | BU14: 0.063 | BV14: 3.758 | BW14: 3.758 | BX14: 3.758 | BY14: 12.967 | BZ14: 7.151 | CA14: 4.371 | CB14: 1 | CC14: 0 | CD14: 0 | CE14: 11.283 | CF14: 0 | CG14: 0 | CH14: 37.913 | CI14: 4.484 | CJ14: 6.276 | CK14: 16.772 | CL14: 2.328 | CM14: 1.175 | CN14: 0.152 | CO14: 1.023 | CP14: -19.79 | CQ14: 52.15 | CS14: 2024 | CT14: 2024 | CU14: 2024 | CV14: 2024 | CW14: 2022 | CZ14: 2022 | DA14: 2021 | DC14: 2021-2024 | DE14: 2024 | DF14: 2022 | DG14: 2024 | DH14: 2024 | DI14: 2024 | DJ14: 2024 | DK14: 2024 | DM14: 2020-2024 avg | DN14: 2024 | DO14: 2024 | DP14: 2024 | DQ14: 2024 | DR14: 2022 | DS14: 2025 | DT14: 2025 | DU14: 2025 | DV14: 2023 | DW14: 2021 | DX14: 2021 | DY14: 2021 | DZ14: 2021 | EA14: 2025 | EB14: 2024 | EC14: 2025 | ED14: 2025 | EE14: 2030 | EF14: 2030 | EG14: 2030 | EH14: 2030 | EI14: 2030 | EJ14: 2030 | EK14: 2030 | EL14: 2030 | EM14: 2030 | EN14: 2030 | EO14: 2030 | EP14: 2030 | EQ14: 2030 | ER14: 2030 | ES14: 2030 | ET14: 2030 | EU14: 2030 | EV14: 2030 | EW14: 2030 | EX14: 2030 | EY14: 2030 | EZ14: 2030 | FA14: 2030 | FB14: 2030 | FC14: 2050 | FD14: 2025-2050 | FE14: 2024 | FF14: 2024 | FG14: 2024 | FH14: 2024 | FI14: 2024 | FJ14: 2024 | FK14: 2024 | FL14: 2024 | FM14: 2024 | FN14: 2024 | FO14: 2013 | FP14: 2013 | FQ14: 2013 | FR14: 2023 | FS14: 2023 | FT14: 2023 | FU14: 2024 | FV14: 2024 | FW14: 2024 | FX14: 2024 | FY14: 2020-2024 avg | FZ14: 2030 | GA14: 2030 | GB14: 2030 | GC14: 2050 | GD14: 2050
A15: BHS | B15: Bahamas, The | C15: Latin America & Caribbean | D15: High income | E15: FALSE | F15: 19.934 | G15: 3.941 | H15: 73.813 | I15: 17.325 | J15: 89.195 | M15: 0 | AA15: 0.615 | AB15: 2.413 | AC15: 0 | AD15: 2.413 | AE15: 1.765 | AF15: -16.28 | AG15: 0 | AH15: 16.28 | AJ15: 0 | AK15: 0 | AL15: 0 | AM15: 0 | AN15: 99.111 | AO15: 13.528 | AP15: -0.016 | AQ15: 0 | AR15: 3.5759159 | AS15: 0.85821981 | AT15: 0.244231 | AU15: 0.16747268 | AV15: 0.17027287 | AW15: 0.06854367 | AX15: 0.05439834 | AY15: 0.057465867 | AZ15: 0.095835372 | BA15: -0.033604002 | BB15: -0.064578137 | BC15: -0.093430491 | BD15: -92.013765 | BE15: 0.1290589 | BF15: 4.1049555 | BG15: 2.5034627 | BH15: 0.10470978 | BI15: 0.78134981 | BJ15: 0.55693279 | BK15: 0.3817509 | BL15: 0.67871937 | BM15: 0.21923505 | BN15: 60.031964 | BO15: 1.4531638 | BP15: 1.3156346 | BQ15: -5.2545467 | BR15: 1.276 | BS15: 1.624 | BT15: 0.331 | BU15: 0.357 | BV15: 22.783 | BW15: 12.77 | BX15: 11.446 | BY15: 13.412 | BZ15: 7.124 | CA15: 5.575 | CB15: 2 | CC15: 1 | CD15: 0 | CH15: 19.77 | CI15: 2.741 | CJ15: -7.617 | CK15: 26.465 | CL15: 2.96 | CM15: 0.142 | CN15: 0.894 | CO15: -0.751 | CP15: 9.678 | CQ15: 64.06 | CS15: 2024 | CT15: 2024 | CU15: 2024 | CV15: 2024 | CW15: 2022 | CZ15: 2022 | DN15: 2024 | DO15: 2024 | DP15: 2024 | DQ15: 2024 | DR15: 2022 | DS15: 2024 | DT15: 2024 | DU15: 2024 | DW15: 2021 | DX15: 2021 | DY15: 2021 | DZ15: 2021 | EA15: 2024 | EB15: 2024 | EC15: 2024 | ED15: 2024 | EE15: 2030 | EF15: 2030 | EG15: 2030 | EH15: 2030 | EI15: 2030 | EJ15: 2030 | EK15: 2030 | EL15: 2030 | EM15: 2030 | EN15: 2030 | EO15: 2030 | EP15: 2030 | EQ15: 2030 | ER15: 2030 | ES15: 2030 | ET15: 2030 | EU15: 2030 | EV15: 2030 | EW15: 2030 | EX15: 2030 | EY15: 2030 | EZ15: 2030 | FA15: 2030 | FB15: 2030 | FC15: 2050 | FD15: 2025-2050 | FE15: 2024 | FF15: 2024 | FG15: 2024 | FH15: 2024 | FI15: 2024 | FJ15: 2024 | FK15: 2024 | FL15: 2024 | FM15: 2024 | FN15: 2024 | FO15: 2013 | FP15: 2013 | FQ15: 2013 | FU15: 2024 | FV15: 2024 | FW15: 2024 | FX15: 2024 | FY15: 2020-2024 avg | FZ15: 2030 | GA15: 2030 | GB15: 2030 | GC15: 2050 | GD15: 2050
A16: BHR | B16: Bahrain | C16: Middle East & North Africa | D16: High income | E16: FALSE | F16: 36.382 | G16: 6.508 | H16: 133.672 | I16: 4.403 | M16: 0 | AA16: 2.516 | AB16: 13.367 | AC16: 6.783 | AD16: 6.584 | AF16: -2.594 | AG16: 0 | AH16: 2.594 | AI16: -45.475 | AJ16: 16.64 | AK16: 10.938 | AL16: 5.702 | AM16: 0 | AN16: 0 | AO16: 14.725 | AP16: 0.024 | AQ16: 16.667 | AR16: 11.051361 | AS16: 2.6523267 | AT16: 0.95034341 | AU16: 0.65166405 | AV16: 0.17485276 | AW16: 0.14292591 | AX16: 0.13313699 | AY16: 0.17231905 | AZ16: 0.42708458 | BA16: 0.22419098 | BB16: 0.12586536 | BC16: 0.059888606 | BD16: 68.450337 | BE16: 0.40969009 | BF16: 12.686357 | BG16: 4.8348104 | BH16: 1.0646775 | BI16: 0.60899898 | BJ16: 0.5665128 | BK16: 1.8238554 | BL16: 0.77076567 | BM16: 1.6118341 | BN16: 54.065766 | BO16: 3.6128799 | BP16: 3.9105218 | BQ16: 16.372731 | BR16: 0.478 | BS16: 0.42 | BT16: 0.021 | BU16: 0.037 | BV16: 3.694 | BW16: 4.22 | BX16: 4.22 | BY16: 13.646 | BZ16: 7.281 | CA16: 5.787 | CB16: 2 | CC16: 1 | CD16: 0 | CE16: 16.019 | CF16: 0 | CG16: 0 | CH16: 17.888 | CI16: -4.499 | CJ16: 4.834 | CK16: 28.435 | CL16: 2.279 | CM16: 1.191 | CN16: 0.144 | CO16: 1.048 | CP16: 14.54 | CQ16: 135.9 | CS16: 2024 | CT16: 2024 | CU16: 2024 | CV16: 2024 | CZ16: 2022 | DN16: 2024 | DO16: 2024 | DP16: 2024 | DQ16: 2024 | DS16: 2024 | DT16: 2024 | DU16: 2024 | DV16: 2022 | DW16: 2021 | DX16: 2021 | DY16: 2021 | DZ16: 2021 | EA16: 2024 | EB16: 2024 | EC16: 2024 | ED16: 2024 | EE16: 2030 | EF16: 2030 | EG16: 2030 | EH16: 2030 | EI16: 2030 | EJ16: 2030 | EK16: 2030 | EL16: 2030 | EM16: 2030 | EN16: 2030 | EO16: 2030 | EP16: 2030 | EQ16: 2030 | ER16: 2030 | ES16: 2030 | ET16: 2030 | EU16: 2030 | EV16: 2030 | EW16: 2030 | EX16: 2030 | EY16: 2030 | EZ16: 2030 | FA16: 2030 | FB16: 2030 | FC16: 2050 | FD16: 2025-2050 | FE16: 2024 | FF16: 2024 | FG16: 2024 | FH16: 2024 | FI16: 2024 | FJ16: 2024 | FK16: 2024 | FL16: 2024 | FM16: 2024 | FN16: 2024 | FO16: 2013 | FP16: 2013 | FQ16: 2013 | FR16: 2023 | FS16: 2023 | FT16: 2023 | FU16: 2024 | FV16: 2024 | FW16: 2024 | FX16: 2024 | FY16: 2020-2024 avg | FZ16: 2030 | GA16: 2030 | GB16: 2030 | GC16: 2050 | GD16: 2050
A17: BGD | B17: Bangladesh | C17: South Asia | D17: Lower middle income | E17: TRUE | F17: 27.513 | G17: 2.294 | H17: 40.972 | I17: 7.391 | J17: 78.21 | K17: 2.5 | L17: 1 | M17: 1 | N17: 6.8 | P17: 1 | T17: 25.241 | U17: 0.399 | V17: 53.135 | W17: 8.171 | X17: 72.255 | Y17: 2 | Z17: 0.215 | AA17: 12.98 | AB17: 8.949 | AC17: 2.547 | AD17: 6.402 | AE17: 0.163 | AF17: -9.025 | AG17: 1.097 | AH17: 10.122 | AI17: 44.307 | AJ17: 0.535 | AK17: 0.032 | AL17: 0.49 | AM17: 0.013 | AN17: 12.068 | AO17: 19.248 | AP17: 0.184 | AQ17: 25.21 | AR17: 5.2910001 | AS17: 1.26984 | AT17: 0.39615875 | AU17: 0.27165172 | AV17: 0.11695458 | AW17: 0.11612172 | AX17: 0.058740436 | AY17: 0.074678286 | AZ17: 0.23553454 | BA17: 0.05685669 | BB17: 0.027007586 | BC17: -0.074900924 | BD17: 26.566927 | BE17: 0.12437127 | BF17: 6.0540559 | BG17: 2.6431427 | BH17: 0.75706008 | BI17: 0.37702143 | BJ17: 0.36843063 | BK17: 0.77216732 | BL17: 0.36846327 | BM17: 0.98871027 | BN17: 48.329249 | BO17: 1.6864842 | BP17: 1.3932749 | BQ17: 2.3697454 | BR17: 0.89 | BS17: 1.374 | BT17: 0.038 | BU17: 0.067 | BV17: 4.031 | BW17: 6.719 | BX17: 3.472 | BY17: 12.345 | BZ17: 6.822 | CA17: 4.506 | CB17: 2 | CC17: 1 | CD17: 1 | CE17: 26.786 | CF17: 0 | CG17: 50 | CH17: 8.338 | CI17: -1.401 | CJ17: -1.446 | CK17: 30.7 | CL17: 5.497 | CM17: 0.663 | CN17: 0.133 | CO17: 0.531 | CP17: 1.163 | CQ17: 49.04 | CR17: 3 | CS17: 2024 | CT17: 2024 | CU17: 2024 | CV17: 2024 | CW17: 2020 | CX17: 2023 | CY17: 2023 | CZ17: 2022 | DA17: 2021 | DC17: 2021-2024 | DG17: 2024 | DH17: 2024 | DI17: 2024 | DJ17: 2024 | DK17: 2024 | DL17: 2023 | DM17: 2020-2024 avg | DN17: 2024 | DO17: 2024 | DP17: 2024 | DQ17: 2024 | DR17: 2020 | DS17: 2018 | DT17: 2018 | DU17: 2018 | DV17: 2022 | DW17: 2021 | DX17: 2021 | DY17: 2021 | DZ17: 2021 | EA17: 2025 | EB17: 2024 | EC17: 2025 | ED17: 2025 | EE17: 2030 | EF17: 2030 | EG17: 2030 | EH17: 2030 | EI17: 2030 | EJ17: 2030 | EK17: 2030 | EL17: 2030 | EM17: 2030 | EN17: 2030 | EO17: 2030 | EP17: 2030 | EQ17: 2030 | ER17: 2030 | ES17: 2030 | ET17: 2030 | EU17: 2030 | EV17: 2030 | EW17: 2030 | EX17: 2030 | EY17: 2030 | EZ17: 2030 | FA17: 2030 | FB17: 2030 | FC17: 2050 | FD17: 2025-2050 | FE17: 2024 | FF17: 2024 | FG17: 2024 | FH17: 2024 | FI17: 2024 | FJ17: 2024 | FK17: 2024 | FL17: 2024 | FM17: 2024 | FN17: 2024 | FO17: 2013 | FP17: 2013 | FQ17: 2013 | FR17: 2023 | FS17: 2023 | FT17: 2023 | FU17: 2024 | FV17: 2024 | FW17: 2024 | FX17: 2024 | FY17: 2020-2024 avg | FZ17: 2030 | GA17: 2030 | GB17: 2030 | GC17: 2050 | GD17: 2050 | GE17: 2034
A18: BRB | B18: Barbados | C18: Latin America & Caribbean | D18: High income | E18: FALSE | F18: 17.856 | G18: 4.865 | H18: 98.903 | I18: 27.746 | M18: 0 | AA18: 5.898 | AB18: 0.331 | AC18: 0.282 | AD18: 0.049 | AF18: -14.651 | AG18: 8.01 | AH18: 22.661 | AJ18: 0.316 | AK18: 0.309 | AL18: 0.007 | AM18: 0 | AN18: 88.288 | AO18: 21.68 | AP18: 0.827 | AQ18: 0 | AR18: 3.67648 | AS18: 0.88235521 | AT18: 0.28173838 | AU18: 0.19319203 | AV18: 0.13035467 | AW18: 0.073802864 | AX18: 0.058188376 | AY18: 0.053592768 | AZ18: 0.091486127 | BA18: -0.0185007 | BB18: -0.05066312 | BC18: -0.068982242 | BD18: -70.695455 | BE18: 0.13401008 | BF18: 4.2203976 | BG18: 2.2450916 | BH18: 0.17228913 | BI18: 0.89270143 | BJ18: 0.20342302 | BK18: 0.38981862 | BL18: 0.58685938 | BM18: 0.28923472 | BN18: 47.354658 | BO18: 1.3764459 | BP18: 1.2860268 | BQ18: -3.9014054 | BR18: 1.518 | BS18: 2.07 | BT18: 0.344 | BU18: 0.336 | BV18: 25.409 | BW18: 33.116 | BX18: 33.116 | BY18: 14.327 | BZ18: 7.124 | CA18: 5.575 | CH18: 27.245 | CI18: 4.029 | CJ18: -3.902 | CK18: 18.17 | CL18: 2.348 | CM18: 0.175 | CN18: 0.574 | CO18: -0.4 | CP18: 8.365 | CQ18: 90.65 | CS18: 2024 | CT18: 2024 | CU18: 2024 | CV18: 2024 | CZ18: 2022 | DN18: 2024 | DO18: 2024 | DP18: 2024 | DQ18: 2024 | DS18: 2024 | DT18: 2024 | DU18: 2024 | DW18: 2021 | DX18: 2021 | DY18: 2021 | DZ18: 2021 | EA18: 2024 | EB18: 2024 | EC18: 2024 | ED18: 2024 | EE18: 2030 | EF18: 2030 | EG18: 2030 | EH18: 2030 | EI18: 2030 | EJ18: 2030 | EK18: 2030 | EL18: 2030 | EM18: 2030 | EN18: 2030 | EO18: 2030 | EP18: 2030 | EQ18: 2030 | ER18: 2030 | ES18: 2030 | ET18: 2030 | EU18: 2030 | EV18: 2030 | EW18: 2030 | EX18: 2030 | EY18: 2030 | EZ18: 2030 | FA18: 2030 | FB18: 2030 | FC18: 2050 | FD18: 2025-2050 | FE18: 2024 | FF18: 2024 | FG18: 2024 | FH18: 2024 | FI18: 2024 | FJ18: 2024 | FK18: 2024 | FL18: 2024 | FM18: 2024 | FN18: 2024 | FU18: 2024 | FV18: 2024 | FW18: 2024 | FX18: 2024 | FY18: 2020-2024 avg | FZ18: 2030 | GA18: 2030 | GB18: 2030 | GC18: 2050 | GD18: 2050
A19: BLR | B19: Belarus | C19: Europe & Central Asia | D19: Upper middle income | E19: FALSE | F19: 3.101 | G19: 1.282 | H19: 38.699 | I19: 27.239 | M19: 0 | R19: 3.653 | S19: 6.177 | T19: 4.521 | U19: 0.006 | V19: 19.746 | W19: 16.436 | X19: 86.631 | AA19: 6.144 | AB19: 19.914 | AC19: 5.205 | AD19: 14.709 | AE19: 0.258 | AF19: -7.787 | AG19: 12.613 | AH19: 20.4 | AI19: 77.08 | AJ19: 0.853 | AK19: 0.814 | AL19: 0.039 | AM19: 0 | AN19: 4.149 | AO19: 6.677 | AP19: 0.526 | AQ19: 3.509 | AR19: 7.3248957 | AS19: 1.757975 | AT19: 0.50439447 | AU19: 0.3458705 | AV19: 0.22921726 | AW19: 0.17056389 | AX19: 0.10354169 | AY19: 0.1328871 | AZ19: 0.27150005 | BA19: 0.1048571 | BB19: 0.040690123 | BC19: -0.072319139 | BD19: 40.507734 | BE19: 0.26736241 | BF19: 8.4085789 | BG19: 4.6179275 | BH19: 0.967008 | BI19: 1.2390202 | BJ19: 0.30116211 | BK19: 1.3223345 | BL19: 0.78840267 | BM19: 1.3637084 | BN19: 43.638601 | BO19: 3.4544393 | BP19: 3.7431327 | BQ19: 11.371085 | BR19: 0.673 | BS19: 0.738 | BT19: 0.072 | BU19: 0.096 | BV19: 1.797 | BW19: 5.755 | BX19: 5.755 | BY19: 4.167 | BZ19: 7.124 | CA19: 4.351 | CB19: 1 | CC19: 0 | CD19: 0 | CE19: 22.474 | CF19: 0 | CG19: 0 | CH19: 41.345 | CI19: 1.821 | CJ19: -3.079 | CK19: 25.841 | CL19: 1.115 | CM19: 1.012 | CN19: 0.311 | CO19: 0.701 | CP19: 15.47 | CQ19: 47.71 | CS19: 2024 | CT19: 2024 | CU19: 2024 | CV19: 2024 | CZ19: 2022 | DE19: 2021 | DF19: 2020 | DG19: 2021 | DH19: 2024 | DI19: 2024 | DJ19: 2024 | DK19: 2024 | DN19: 2024 | DO19: 2024 | DP19: 2024 | DQ19: 2024 | DR19: 2022 | DS19: 2020 | DT19: 2020 | DU19: 2020 | DV19: 2022 | DW19: 2021 | DX19: 2021 | DY19: 2021 | DZ19: 2021 | EA19: 2025 | EB19: 2024 | EC19: 2025 | ED19: 2025 | EE19: 2030 | EF19: 2030 | EG19: 2030 | EH19: 2030 | EI19: 2030 | EJ19: 2030 | EK19: 2030 | EL19: 2030 | EM19: 2030 | EN19: 2030 | EO19: 2030 | EP19: 2030 | EQ19: 2030 | ER19: 2030 | ES19: 2030 | ET19: 2030 | EU19: 2030 | EV19: 2030 | EW19: 2030 | EX19: 2030 | EY19: 2030 | EZ19: 2030 | FA19: 2030 | FB19: 2030 | FC19: 2050 | FD19: 2025-2050 | FE19: 2024 | FF19: 2024 | FG19: 2024 | FH19: 2024 | FI19: 2024 | FJ19: 2024 | FK19: 2024 | FL19: 2024 | FM19: 2024 | FN19: 2024 | FO19: 2013 | FP19: 2013 | FQ19: 2013 | FR19: 2023 | FS19: 2023 | FT19: 2023 | FU19: 2024 | FV19: 2024 | FW19: 2024 | FX19: 2024 | FY19: 2020-2024 avg | FZ19: 2030 | GA19: 2030 | GB19: 2030 | GC19: 2050 | GD19: 2050
A20: BEL | B20: Belgium | C20: Europe & Central Asia | D20: High income | E20: FALSE | F20: 3.258 | G20: 1.619 | H20: 103.89 | I20: 29.571 | M20: 0 | O20: 3.8 | P20: 1 | AA20: 4.187 | AB20: 0.401 | AC20: 0 | AD20: 0.401 | AE20: 2.423 | AF20: -4.412 | AG20: 11.601 | AH20: 16.013 | AI20: 89.175 | AJ20: 0.031 | AK20: 0.031 | AL20: 0 | AM20: 0 | AN20: 0.492 | AO20: 26.329 | AP20: 5.476 | AQ20: 6.946 | AR20: 3.116506 | AS20: 1.1842723 | AT20: 0.39434999 | AU20: 0.27041142 | AV20: 0.17738168 | AW20: 0.1522423 | AX20: 0.080562239 | AY20: 0.093575636 | AZ20: 0.015749022 | BA20: -0.0063190644 | BB20: 0.012279183 | BC20: 0.0014096878 | BD20: 32.949521 | BE20: -0.048942755 | BF20: 3.2562115 | BG20: 2.8703148 | BH20: 0.25362806 | BI20: 0.55836024 | BJ20: 0.64332444 | BK20: 0.14866674 | BL20: 1.2663353 | BM20: 0.29822809 | BN20: 70.15699 | BO20: 1.6711625 | BP20: 0.97068593 | BQ20: 2.7624765 | BR20: 1.776 | BS20: 1.763 | BT20: 0.361 | BU20: 0.141 | BV20: 25.619 | BW20: 18.394 | BX20: 18.394 | BY20: 18.668 | BZ20: 21.366 | CA20: 21.366 | CE20: 80.593 | CF20: 60 | CG20: 100 | CH20: 49.693 | CI20: -2.743 | CJ20: -0.378 | CK20: 24.496 | CL20: 1.64 | CM20: 0.167 | CN20: 0.124 | CO20: 0.043 | CP20: 4.991 | CQ20: 100.5 | CS20: 2024 | CT20: 2024 | CU20: 2024 | CV20: 2024 | CZ20: 2022 | DB20: 2019 | DC20: 2021-2024 | DN20: 2023 | DO20: 2024 | DP20: 2024 | DQ20: 2024 | DR20: 2021 | DS20: 2024 | DT20: 2024 | DU20: 2024 | DV20: 2023 | DW20: 2021 | DX20: 2021 | DY20: 2021 | DZ20: 2021 | EA20: 2025 | EB20: 2024 | EC20: 2025 | ED20: 2025 | EE20: 2030 | EF20: 2030 | EG20: 2030 | EH20: 2030 | EI20: 2030 | EJ20: 2030 | EK20: 2030 | EL20: 2030 | EM20: 2030 | EN20: 2030 | EO20: 2030 | EP20: 2030 | EQ20: 2030 | ER20: 2030 | ES20: 2030 | ET20: 2030 | EU20: 2030 | EV20: 2030 | EW20: 2030 | EX20: 2030 | EY20: 2030 | EZ20: 2030 | FA20: 2030 | FB20: 2030 | FC20: 2050 | FD20: 2025-2050 | FE20: 2024 | FF20: 2024 | FG20: 2024 | FH20: 2024 | FI20: 2024 | FJ20: 2024 | FK20: 2024 | FL20: 2024 | FM20: 2024 | FN20: 2024 | FR20: 2023 | FS20: 2023 | FT20: 2023 | FU20: 2024 | FV20: 2024 | FW20: 2024 | FX20: 2024 | FY20: 2020-2024 avg | FZ20: 2030 | GA20: 2030 | GB20: 2030 | GC20: 2050 | GD20: 2050
A21: BLZ | B21: Belize | C21: Latin America & Caribbean | D21: Upper middle income | E21: FALSE | F21: 10.001 | G21: 2.524 | H21: 65.436 | I21: 23.227 | J21: 84.932 | M21: 0 | R21: -2.554 | S21: 2 | T21: 23.598 | U21: 1.034 | V21: 38.626 | W21: 28.076 | X21: 98.364 | AA21: 14.424 | AB21: 2.935 | AC21: 0.757 | AD21: 2.178 | AE21: 3.002 | AF21: -13.775 | AG21: 0.01 | AH21: 13.785 | AJ21: 0.282 | AK21: 0.28 | AL21: 0.002 | AM21: 0 | AN21: 12.766 | AO21: 77.617 | AP21: -1.655 | AQ21: 0 | AR21: 8.2497211 | AS21: 1.9799331 | AT21: 0.37976149 | AU21: 0.26040788 | AV21: 0.24232454 | AW21: 0.14241281 | AX21: 0.056269982 | AY21: 0.074925296 | AZ21: 0.82383108 | BA21: 0.10821602 | BB21: 0.03541256 | BC21: -0.07674035 | BD21: 23.022257 | BE21: 0.30334775 | BF21: 9.4702278 | BG21: 9.7476186 | BH21: 4.8493618 | BI21: 0.25390538 | BJ21: 0.28473681 | BK21: 3.5630839 | BL21: 0.79653069 | BM21: 5.918287 | BN21: 36.679997 | BO21: 8.9958315 | BP21: 5.7592709 | BQ21: 69.597609 | BR21: 1.153 | BS21: 1.379 | BT21: 0.219 | BU21: 0.175 | BV21: 14.744 | BW21: 5.164 | BX21: 3.841 | BY21: 13.717 | BZ21: 7.124 | CA21: 5.575 | CB21: 2 | CC21: 1 | CD21: 0 | CH21: 25.238 | CI21: 1.009 | CJ21: -1.918 | CK21: 18.298 | CL21: 3.545 | CM21: 5.707 | CN21: 0.14 | CO21: 5.567 | CP21: 9.092 | CQ21: 116.4 | CS21: 2024 | CT21: 2024 | CU21: 2024 | CV21: 2024 | CW21: 2022 | CZ21: 2022 | DE21: 2024 | DF21: 2023 | DG21: 2024 | DH21: 2024 | DI21: 2024 | DJ21: 2024 | DK21: 2024 | DN21: 2024 | DO21: 2024 | DP21: 2024 | DQ21: 2024 | DR21: 2022 | DS21: 2025 | DT21: 2025 | DU21: 2025 | DW21: 2021 | DX21: 2021 | DY21: 2021 | DZ21: 2021 | EA21: 2024 | EB21: 2024 | EC21: 2024 | ED21: 2024 | EE21: 2030 | EF21: 2030 | EG21: 2030 | EH21: 2030 | EI21: 2030 | EJ21: 2030 | EK21: 2030 | EL21: 2030 | EM21: 2030 | EN21: 2030 | EO21: 2030 | EP21: 2030 | EQ21: 2030 | ER21: 2030 | ES21: 2030 | ET21: 2030 | EU21: 2030 | EV21: 2030 | EW21: 2030 | EX21: 2030 | EY21: 2030 | EZ21: 2030 | FA21: 2030 | FB21: 2030 | FC21: 2050 | FD21: 2025-2050 | FE21: 2024 | FF21: 2023 | FG21: 2024 | FH21: 2024 | FI21: 2024 | FJ21: 2024 | FK21: 2024 | FL21: 2024 | FM21: 2024 | FN21: 2024 | FO21: 2013 | FP21: 2013 | FQ21: 2013 | FU21: 2024 | FV21: 2024 | FW21: 2024 | FX21: 2024 | FY21: 2020-2024 avg | FZ21: 2030 | GA21: 2030 | GB21: 2030 | GC21: 2050 | GD21: 2050
A22: BEN | B22: Benin | C22: Sub-Saharan Africa | D22: Lower middle income | E22: TRUE | F22: 12.832 | G22: 1.944 | H22: 60.527 | I22: 13.217 | J22: 63.759 | M22: 1 | R22: 5.998 | S22: 7.518 | T22: 17.058 | U22: 0.559 | V22: 45.43 | W22: 43.264 | X22: 28.794 | Z22: 0.043 | AA22: 1.299 | AB22: 2.821 | AC22: 0 | AD22: 2.821 | AE22: 1.185 | AF22: -13.654 | AG22: 0 | AH22: 13.654 | AI22: 40.903 | AJ22: 0 | AK22: 0 | AL22: 0 | AM22: 0 | AN22: 23.762 | AO22: 17.379 | AP22: 0.96 | AQ22: 0 | AR22: 4.3345147 | AS22: 1.0402835 | AT22: 0.2064311 | AU22: 0.14155275 | AV22: 0.2006801 | AW22: 0.063950425 | AX22: 0.036910863 | AY22: 0.059364246 | AZ22: 0.33139405 | BA22: 0.04829286 | BB22: 0.010602923 | BC22: -0.0356587 | BD22: 12.359037 | BE22: 0.1570414 | BF22: 4.9757854 | BG22: 3.8716011 | BH22: 1.6625372 | BI22: 0.28529631 | BJ22: 0.31847024 | BK22: 1.1769739 | BL22: 0.42832348 | BM22: 2.0156294 | BN22: 40.569144 | BO22: 3.1232626 | BP22: 1.8730867 | BQ22: 6.1505855 | BR22: 1.05 | BS22: 1.117 | BT22: 0.203 | BU22: 0.202 | BV22: 18.748 | BW22: 7.947 | BX22: 6.623 | BY22: 14.388 | BZ22: 7.124 | CA22: 5.575 | CB22: 2 | CC22: 0 | CD22: 0 | CE22: 15.317 | CF22: 0 | CG22: 0 | CH22: 15.15 | CI22: -1.12 | CJ22: -6.042 | CK22: 35.062 | CL22: 6.201 | CM22: 1.861 | CN22: 0.247 | CO22: 1.614 | CP22: 8.539 | CQ22: 71.08 | CR22: 3 | CS22: 2024 | CT22: 2024 | CU22: 2024 | CV22: 2024 | CW22: 2022 | CZ22: 2022 | DE22: 2024 | DF22: 2024 | DG22: 2024 | DH22: 2024 | DI22: 2024 | DJ22: 2024 | DK22: 2024 | DM22: 2020-2024 avg | DN22: 2017 | DO22: 2024 | DP22: 2024 | DQ22: 2024 | DR22: 2022 | DS22: 2024 | DT22: 2024 | DU22: 2024 | DV22: 2022 | DW22: 2021 | DX22: 2021 | DY22: 2021 | DZ22: 2021 | EA22: 2024 | EB22: 2024 | EC22: 2024 | ED22: 2024 | EE22: 2030 | EF22: 2030 | EG22: 2030 | EH22: 2030 | EI22: 2030 | EJ22: 2030 | EK22: 2030 | EL22: 2030 | EM22: 2030 | EN22: 2030 | EO22: 2030 | EP22: 2030 | EQ22: 2030 | ER22: 2030 | ES22: 2030 | ET22: 2030 | EU22: 2030 | EV22: 2030 | EW22: 2030 | EX22: 2030 | EY22: 2030 | EZ22: 2030 | FA22: 2030 | FB22: 2030 | FC22: 2050 | FD22: 2025-2050 | FE22: 2024 | FF22: 2024 | FG22: 2024 | FH22: 2024 | FI22: 2024 | FJ22: 2024 | FK22: 2024 | FL22: 2024 | FM22: 2024 | FN22: 2024 | FO22: 2013 | FP22: 2013 | FQ22: 2013 | FR22: 2023 | FS22: 2023 | FT22: 2023 | FU22: 2024 | FV22: 2024 | FW22: 2024 | FX22: 2024 | FY22: 2020-2024 avg | FZ22: 2030 | GA22: 2030 | GB22: 2030 | GC22: 2050 | GD22: 2050 | GE22: 2034
A23: BMU | B23: Bermuda | C23: North America | D23: High income | E23: FALSE | M23: 0 | AF23: -11.504 | AG23: 0 | AH23: 11.504 | AJ23: 0 | AK23: 0 | AL23: 0 | AM23: 0 | CZ23: 2022 | DS23: 2024 | DT23: 2024 | DU23: 2024 | DW23: 2021 | DX23: 2021 | DY23: 2021 | DZ23: 2021
A24: BTN | B24: Bhutan | C24: South Asia | D24: Lower middle income | E24: TRUE | F24: 7.297 | G24: 1.937 | H24: 108.717 | I24: 10.845 | J24: 66.852 | K24: 1.5 | L24: 2 | M24: 0 | T24: 31.819 | U24: 0.675 | V24: 29.965 | W24: 0.061 | X24: 30.909 | Y24: 4 | AA24: 1.247 | AB24: 4.38 | AC24: 0.038 | AD24: 4.343 | AE24: 0.088 | AF24: -14.027 | AG24: 0 | AH24: 14.027 | AJ24: 0 | AK24: 0 | AL24: 0 | AM24: 0 | AN24: 0 | AO24: 99.647 | AP24: 0 | AQ24: 5.15 | AR24: 6.9909471 | AS24: 1.6778273 | AT24: 0.62181493 | AU24: 0.42638738 | AV24: 0.14888069 | AW24: 0.10290173 | AX24: 0.095217386 | AY24: 0.068212704 | AZ24: 0.21441248 | BA24: 0.10984154 | BB24: 0.047792606 | BC24: -0.011762163 | BD24: 67.304736 | BE24: 0.25853722 | BF24: 8.5300393 | BG24: 2.2127771 | BH24: 0.29639973 | BI24: 0.066832015 | BJ24: 0.035096525 | BK24: 1.1388949 | BL24: 0.67555399 | BM24: 0.63806819 | BN24: 68.144094 | BO24: 1.8152333 | BP24: 2.6285161 | BQ24: 2.652516 | BR24: 1.133 | BS24: 1.49 | BT24: 0.015 | BU24: 0.019 | BV24: 23.519 | BW24: 13.439 | BX24: 12.116 | BY24: 12.596 | BZ24: 7.124 | CA24: 4.833 | CB24: 1 | CC24: 1 | CD24: 0 | CH24: 26.545 | CI24: 0.148 | CJ24: -20.411 | CK24: 41.186 | CL24: 2.018 | CM24: 0.472 | CN24: 0 | CO24: 0.472 | CP24: 7.654 | CQ24: 111.4 | CR24: 3 | CS24: 2024 | CT24: 2024 | CU24: 2024 | CV24: 2024 | CW24: 2021 | CX24: 2023 | CY24: 2023 | CZ24: 2022 | DG24: 2024 | DH24: 2024 | DI24: 2024 | DJ24: 2024 | DK24: 2024 | DL24: 2023 | DN24: 2024 | DO24: 2024 | DP24: 2024 | DQ24: 2024 | DR24: 2021 | DS24: 2025 | DT24: 2025 | DU24: 2025 | DW24: 2021 | DX24: 2021 | DY24: 2021 | DZ24: 2021 | EA24: 2024 | EB24: 2024 | EC24: 2024 | ED24: 2024 | EE24: 2030 | EF24: 2030 | EG24: 2030 | EH24: 2030 | EI24: 2030 | EJ24: 2030 | EK24: 2030 | EL24: 2030 | EM24: 2030 | EN24: 2030 | EO24: 2030 | EP24: 2030 | EQ24: 2030 | ER24: 2030 | ES24: 2030 | ET24: 2030 | EU24: 2030 | EV24: 2030 | EW24: 2030 | EX24: 2030 | EY24: 2030 | EZ24: 2030 | FA24: 2030 | FB24: 2030 | FC24: 2050 | FD24: 2025-2050 | FE24: 2024 | FF24: 2024 | FG24: 2024 | FH24: 2024 | FI24: 2024 | FJ24: 2024 | FK24: 2024 | FL24: 2024 | FM24: 2024 | FN24: 2024 | FO24: 2013 | FP24: 2013 | FQ24: 2013 | FU24: 2024 | FV24: 2024 | FW24: 2024 | FX24: 2024 | FY24: 2020-2024 avg | FZ24: 2030 | GA24: 2030 | GB24: 2030 | GC24: 2050 | GD24: 2050 | GE24: 2034
A25: BOL | B25: Bolivia | C25: Latin America & Caribbean | D25: Lower middle income | E25: FALSE | F25: 10.651 | G25: 2.644 | H25: 83.219 | I25: 17.786 | K25: 1.5 | L25: 1 | M25: 0 | R25: 0.561 | S25: 7.5 | T25: 21.072 | U25: 0.223 | V25: 69.636 | W25: 14.267 | X25: 91.899 | Y25: 2 | AA25: 6.089 | AB25: 11.758 | AC25: 4.201 | AD25: 7.557 | AF25: -10.248 | AG25: 18.943 | AH25: 29.191 | AI25: -67.334 | AJ25: 3.117 | AK25: 1.263 | AL25: 1.854 | AM25: 0 | AN25: 1.467 | AO25: 39.476 | AP25: 2.098 | AQ25: 0 | AR25: 10.366294 | AS25: 2.4879105 | AT25: 0.45865852 | AU25: 0.3145087 | AV25: 0.33863277 | AW25: 0.17689121 | AX25: 0.096240557 | AY25: 0.12929955 | AZ25: 0.97367924 | BA25: 0.14645983 | BB25: 0.055376378 | BC25: -0.082347257 | BD25: 27.101583 | BE25: 0.37951439 | BF25: 12.648486 | BG25: 10.498604 | BH25: 5.3910841 | BI25: 0.33736039 | BJ25: 0.48356894 | BK25: 3.5374822 | BL25: 0.74910799 | BM25: 6.4523288 | BN25: 35.327693 | BO25: 9.8761369 | BP25: 7.6190326 | BQ25: 77.588208 | BR25: 0.488 | BS25: 0.488 | BT25: 0.113 | BU25: 0.084 | BV25: 8.362 | BW25: 5.694 | BX25: 2.454 | BY25: 14.259 | BZ25: 7.281 | CA25: 5.787 | CB25: 3 | CC25: 1 | CD25: 1 | CE25: 22.426 | CF25: 0 | CG25: 50 | CH25: 24.823 | CI25: -6.057 | CJ25: -2.361 | CK25: 17.947 | CL25: 0.49 | CM25: 6.321 | CN25: 0.149 | CO25: 6.172 | CP25: 0.791 | CQ25: 121.8 | CR25: 3 | CS25: 2024 | CT25: 2024 | CU25: 2024 | CV25: 2024 | CX25: 2025 | CY25: 2025 | CZ25: 2022 | DE25: 2024 | DF25: 2022 | DG25: 2024 | DH25: 2024 | DI25: 2024 | DJ25: 2024 | DK25: 2024 | DL25: 2025 | DN25: 2024 | DO25: 2024 | DP25: 2024 | DQ25: 2024 | DS25: 2024 | DT25: 2024 | DU25: 2024 | DV25: 2022 | DW25: 2021 | DX25: 2021 | DY25: 2021 | DZ25: 2021 | EA25: 2025 | EB25: 2024 | EC25: 2025 | ED25: 2025 | EE25: 2030 | EF25: 2030 | EG25: 2030 | EH25: 2030 | EI25: 2030 | EJ25: 2030 | EK25: 2030 | EL25: 2030 | EM25: 2030 | EN25: 2030 | EO25: 2030 | EP25: 2030 | EQ25: 2030 | ER25: 2030 | ES25: 2030 | ET25: 2030 | EU25: 2030 | EV25: 2030 | EW25: 2030 | EX25: 2030 | EY25: 2030 | EZ25: 2030 | FA25: 2030 | FB25: 2030 | FC25: 2050 | FD25: 2025-2050 | FE25: 2024 | FF25: 2024 | FG25: 2024 | FH25: 2024 | FI25: 2024 | FJ25: 2024 | FK25: 2024 | FL25: 2024 | FM25: 2024 | FN25: 2024 | FO25: 2013 | FP25: 2013 | FQ25: 2013 | FR25: 2023 | FS25: 2023 | FT25: 2023 | FU25: 2024 | FV25: 2024 | FW25: 2024 | FX25: 2024 | FY25: 2020-2024 avg | FZ25: 2030 | GA25: 2030 | GB25: 2030 | GC25: 2050 | GD25: 2050 | GE25: 2034
A26: BIH | B26: Bosnia and Herzegovina | C26: Europe & Central Asia | D26: Upper middle income | E26: TRUE | F26: 2.381 | G26: 0.983 | H26: 29.403 | I26: 22.644 | K26: 1.5 | L26: 2 | M26: 0 | N26: 10.4 | P26: 1 | R26: 0.421 | S26: 4.75 | T26: 21.233 | U26: 0.674 | V26: 72.691 | W26: 12.956 | X26: 26.339 | Y26: 1 | Z26: 0.386 | AA26: 11.929 | AB26: 9.396 | AC26: 0.218 | AD26: 9.178 | AF26: -5.044 | AG26: 6.51 | AH26: 11.554 | AI26: 24.932 | AJ26: 0.302 | AK26: 0 | AL26: 0 | AM26: 0.302 | AN26: 1.033 | AO26: 50.223 | AP26: 3.114 | AQ26: 2.941 | AR26: 7.0477686 | AS26: 1.6914645 | AT26: 0.54032611 | AU26: 0.37050933 | AV26: 0.23723097 | AW26: 0.14846195 | AX26: 0.071783565 | AY26: 0.11373447 | AZ26: 0.20941806 | BA26: 0.15901321 | BB26: 0.065985164 | BC26: 0.0025698015 | BD26: 54.825983 | BE26: 0.38761687 | BF26: 8.5993703 | BG26: 4.0381174 | BH26: 0.19751041 | BI26: 0.90584669 | BJ26: 0.99177688 | BK26: 0.98555576 | BL26: 0.95742767 | BM26: 0.49317714 | BN26: 65.354553 | BO26: 2.3274111 | BP26: 2.1554291 | BQ26: 6.947649 | BR26: 1.298 | BS26: 1.41 | BT26: 0.095 | BU26: 0.096 | BV26: 15.796 | BW26: 15.846 | BX26: 15.846 | BY26: 7.706 | BZ26: 2.61 | CA26: 2.696 | CB26: 3 | CC26: 1 | CD26: 1 | CE26: 35.833 | CF26: 0 | CG26: 50 | CH26: 41.291 | CI26: -0.981 | CJ26: -3.461 | CK26: 26.7 | CL26: 2.765 | CM26: 0.367 | CN26: 0.442 | CO26: -0.074 | CP26: 8.443 | CQ26: 30.33 | CS26: 2024 | CT26: 2024 | CU26: 2024 | CV26: 2024 | CX26: 2023 | CY26: 2023 | CZ26: 2022 | DA26: 2021 | DC26: 2021-2024 | DE26: 2024 | DF26: 2021 | DG26: 2024 | DH26: 2024 | DI26: 2024 | DJ26: 2024 | DK26: 2024 | DL26: 2023 | DM26: 2020-2024 avg | DN26: 2024 | DO26: 2024 | DP26: 2024 | DQ26: 2024 | DS26: 2025 | DT26: 2025 | DU26: 2025 | DV26: 2023 | DW26: 2021 | DX26: 2021 | DY26: 2021 | DZ26: 2021 | EA26: 2025 | EB26: 2024 | EC26: 2025 | ED26: 2025 | EE26: 2030 | EF26: 2030 | EG26: 2030 | EH26: 2030 | EI26: 2030 | EJ26: 2030 | EK26: 2030 | EL26: 2030 | EM26: 2030 | EN26: 2030 | EO26: 2030 | EP26: 2030 | EQ26: 2030 | ER26: 2030 | ES26: 2030 | ET26: 2030 | EU26: 2030 | EV26: 2030 | EW26: 2030 | EX26: 2030 | EY26: 2030 | EZ26: 2030 | FA26: 2030 | FB26: 2030 | FC26: 2050 | FD26: 2025-2050 | FE26: 2024 | FF26: 2024 | FG26: 2024 | FH26: 2024 | FI26: 2024 | FJ26: 2024 | FK26: 2024 | FL26: 2024 | FM26: 2024 | FN26: 2024 | FO26: 2013 | FP26: 2013 | FQ26: 2013 | FR26: 2023 | FS26: 2023 | FT26: 2023 | FU26: 2024 | FV26: 2024 | FW26: 2024 | FX26: 2024 | FY26: 2020-2024 avg | FZ26: 2030 | GA26: 2030 | GB26: 2030 | GC26: 2050 | GD26: 2050
A27: BWA | B27: Botswana | C27: Sub-Saharan Africa | D27: Upper middle income | E27: TRUE | F27: 4.724 | G27: 1.25 | H27: 33.182 | I27: 22.356 | J27: 100.531 | K27: 2 | L27: 1 | M27: 0 | T27: 17.583 | U27: 0.396 | V27: 93.535 | W27: 0 | X27: 44.695 | Y27: 4 | Z27: 0.229 | AB27: 4.774 | AC27: 0.319 | AD27: 4.455 | AE27: 0.687 | AF27: -19.818 | AG27: 0.668 | AH27: 20.486 | AI27: 23.682 | AJ27: 0.5 | AK27: 0 | AL27: 0 | AM27: 0.5 | AN27: 1.458 | AO27: 12.373 | AP27: -0.018 | AQ27: 600 | AR27: 7.3623928 | AS27: 1.7669743 | AT27: 0.33939887 | AU27: 0.23273065 | AV27: 0.21066559 | AW27: 0.08638336 | AX27: 0.045190698 | AY27: 0.078060082 | AZ27: 0.77454501 | BA27: 0.14754317 | BB27: 0.082495622 | BC27: -0.03975209 | BD27: 41.665111 | BE27: 0.27103145 | BF27: 8.6854894 | BG27: 10.405896 | BH27: 5.1118297 | BI27: 0.59306534 | BJ27: 0.45823718 | BK27: 3.6732779 | BL27: 0.56948614 | BM27: 6.2138131 | BN27: 34.586332 | BO27: 9.555895 | BP27: 5.416871 | BQ27: 83.16207 | BR27: 1.098 | BS27: 1.156 | BT27: 0.094 | BU27: 0.108 | BV27: 22.825 | BW27: 12.08 | BX27: 10.757 | BY27: 6.108 | BZ27: 3.373 | CA27: 2.049 | CB27: 2 | CC27: 0 | CD27: 0 | CH27: 26.46 | CI27: -6.008 | CJ27: -4.242 | CK27: 36.276 | CL27: 1.778 | CM27: 6.098 | CN27: 0.342 | CO27: 5.756 | CP27: 4.978 | CQ27: 88.17 | CS27: 2024 | CT27: 2024 | CU27: 2024 | CV27: 2024 | CW27: 2022 | CX27: 2020 | CY27: 2020 | CZ27: 2022 | DG27: 2024 | DH27: 2024 | DI27: 2024 | DJ27: 2019 | DK27: 2024 | DL27: 2020 | DM27: 2020-2024 avg | DO27: 2024 | DP27: 2024 | DQ27: 2024 | DR27: 2022 | DS27: 2023 | DT27: 2023 | DU27: 2023 | DV27: 2022 | DW27: 2021 | DX27: 2021 | DY27: 2021 | DZ27: 2021 | EA27: 2024 | EB27: 2024 | EC27: 2024 | ED27: 2024 | EE27: 2030 | EF27: 2030 | EG27: 2030 | EH27: 2030 | EI27: 2030 | EJ27: 2030 | EK27: 2030 | EL27: 2030 | EM27: 2030 | EN27: 2030 | EO27: 2030 | EP27: 2030 | EQ27: 2030 | ER27: 2030 | ES27: 2030 | ET27: 2030 | EU27: 2030 | EV27: 2030 | EW27: 2030 | EX27: 2030 | EY27: 2030 | EZ27: 2030 | FA27: 2030 | FB27: 2030 | FC27: 2050 | FD27: 2025-2050 | FE27: 2024 | FF27: 2024 | FG27: 2024 | FH27: 2024 | FI27: 2024 | FJ27: 2024 | FK27: 2024 | FL27: 2024 | FM27: 2024 | FN27: 2024 | FO27: 2013 | FP27: 2013 | FQ27: 2013 | FU27: 2024 | FV27: 2024 | FW27: 2024 | FX27: 2024 | FY27: 2020-2024 avg | FZ27: 2030 | GA27: 2030 | GB27: 2030 | GC27: 2050 | GD27: 2050
A28: BRA | B28: Brazil | C28: Latin America & Caribbean | D28: Upper middle income | E28: TRUE | F28: 15.121 | G28: 5.953 | H28: 87.028 | I28: 25.562 | J28: 87.319 | M28: 0 | N28: 6.3 | O28: 11.125 | P28: 3 | Q28: 1 | R28: 1.341 | S28: 7.018 | T28: 14.23 | U28: 0.132 | V28: 18.795 | W28: 77.406 | X28: 96.534 | Z28: 0.529 | AA28: 0.073 | AB28: 2.961 | AC28: 0.146 | AD28: 2.815 | AE28: 0.386 | AF28: 5.029 | AG28: 16.117 | AH28: 11.088 | AI28: -13.681 | AJ28: 2.688 | AK28: 2.604 | AL28: 0.07 | AM28: 0.014 | AN28: 1.682 | AO28: 82.939 | AP28: -0.702 | AQ28: 6.731 | AR28: 5.672902 | AS28: 1.3614965 | AT28: 0.38115066 | AU28: 0.26136045 | AV28: 0.1685896 | AW28: 0.097755935 | AX28: 0.061954123 | AY28: 0.066731797 | AZ28: 0.3239539 | BA28: 0.093957818 | BB28: 0.052450201 | BC28: -0.0055876009 | BD28: 72.191974 | BE28: 0.17294841 | BF28: 6.5121806 | BG28: 3.3782731 | BH28: 0.70497044 | BI28: 0.43754295 | BJ28: 0.48245256 | BK28: 0.94697644 | BL28: 0.80633067 | BM28: 0.98906337 | BN28: 57.771136 | BO28: 2.4906316 | BP28: 2.2423118 | BQ28: 11.557853 | BR28: 0.999 | BS28: 1.103 | BT28: 0.16 | BU28: 0.133 | BW28: 20.98 | BX28: 17.367 | BY28: 12.954 | BZ28: 6.222 | CA28: 6.222 | CB28: 3 | CC28: 1 | CD28: 1 | CE28: 65.093 | CF28: 20 | CG28: 100 | CH28: 39.37 | CI28: -0.219 | CJ28: -3.027 | CK28: 16.981 | CL28: 2.233 | CM28: 0.9 | CN28: 0.349 | CO28: 0.552 | CP28: 6.482 | CQ28: 90.28 | CS28: 2024 | CT28: 2024 | CU28: 2024 | CV28: 2024 | CW28: 2022 | CZ28: 2022 | DA28: 2021 | DB28: 2022 | DC28: 2021-2024 | DD28: 2024 | DE28: 2024 | DF28: 2024 | DG28: 2024 | DH28: 2024 | DI28: 2024 | DJ28: 2024 | DK28: 2024 | DM28: 2020-2024 avg | DN28: 2024 | DO28: 2024 | DP28: 2024 | DQ28: 2024 | DR28: 2022 | DS28: 2025 | DT28: 2025 | DU28: 2025 | DV28: 2023 | DW28: 2021 | DX28: 2021 | DY28: 2021 | DZ28: 2021 | EA28: 2025 | EB28: 2024 | EC28: 2025 | ED28: 2025 | EE28: 2030 | EF28: 2030 | EG28: 2030 | EH28: 2030 | EI28: 2030 | EJ28: 2030 | EK28: 2030 | EL28: 2030 | EM28: 2030 | EN28: 2030 | EO28: 2030 | EP28: 2030 | EQ28: 2030 | ER28: 2030 | ES28: 2030 | ET28: 2030 | EU28: 2030 | EV28: 2030 | EW28: 2030 | EX28: 2030 | EY28: 2030 | EZ28: 2030 | FA28: 2030 | FB28: 2030 | FC28: 2050 | FD28: 2025-2050 | FE28: 2024 | FF28: 2024 | FG28: 2024 | FH28: 2024 | FJ28: 2023 | FK28: 2024 | FL28: 2024 | FM28: 2024 | FN28: 2024 | FO28: 2013 | FP28: 2013 | FQ28: 2013 | FR28: 2023 | FS28: 2023 | FT28: 2023 | FU28: 2024 | FV28: 2024 | FW28: 2024 | FX28: 2024 | FY28: 2020-2024 avg | FZ28: 2030 | GA28: 2030 | GB28: 2030 | GC28: 2050 | GD28: 2050
A29: VGB | B29: British Virgin Islands | C29: Latin America & Caribbean | D29: High income | E29: FALSE | M29: 0 | AN29: 100 | AP29: 0 | CZ29: 2022 | EA29: 2023 | EC29: 2023
A30: BRN | B30: Brunei Darussalam | C30: East Asia & Pacific | D30: High income | E30: FALSE | F30: 0 | G30: 0 | H30: 1.568 | I30: 6.065 | M30: 0 | AB30: 8.623 | AC30: 2.549 | AD30: 6.074 | AF30: 9.554 | AG30: 75.472 | AH30: 65.918 | AI30: -172.553 | AJ30: 24.231 | AK30: 10.373 | AL30: 13.858 | AM30: 0 | AN30: 0.899 | AO30: 14.095 | AP30: 0.18 | AQ30: 0 | AR30: 6.3366962 | AS30: 1.5208071 | AT30: 0.44476142 | AU30: 0.30497926 | AV30: 0.18014672 | AW30: 0.10019454 | AX30: 0.11080171 | AY30: 0.11945078 | AZ30: 0.26047266 | BA30: 0.1034512 | BB30: 0.047789086 | BC30: 0.0062517514 | BD30: 41.881617 | BE30: 0.23192546 | BF30: 7.2741801 | BG30: 3.8815246 | BH30: 0.62559434 | BI30: 0.97305086 | BJ30: 0.23496826 | BK30: 1.2748373 | BL30: 0.7730738 | BM30: 1.0080455 | BN30: 48.960869 | BO30: 2.9392541 | BP30: 3.049532 | BQ30: 7.7464949 | BR30: 0.277 | BS30: 0.322 | BT30: 0.088 | BU30: 0.053 | BV30: 4.924 | BW30: 4.924 | BX30: 4.924 | BY30: 11.451 | BZ30: 7.124 | CA30: 4.833 | CB30: 1 | CC30: 0 | CD30: 0 | CH30: 17.428 | CI30: -12.889 | CJ30: 14.54 | CK30: 27.899 | CL30: 0.619 | CM30: 0.765 | CN30: 0.332 | CO30: 0.433 | CP30: 13.01 | CQ30: 18.86 | CS30: 2024 | CT30: 2024 | CU30: 2024 | CV30: 2024 | CZ30: 2022 | DO30: 2024 | DP30: 2024 | DQ30: 2024 | DS30: 2024 | DT30: 2024 | DU30: 2024 | DV30: 2022 | DW30: 2021 | DX30: 2021 | DY30: 2021 | DZ30: 2021 | EA30: 2024 | EB30: 2024 | EC30: 2024 | ED30: 2024 | EE30: 2030 | EF30: 2030 | EG30: 2030 | EH30: 2030 | EI30: 2030 | EJ30: 2030 | EK30: 2030 | EL30: 2030 | EM30: 2030 | EN30: 2030 | EO30: 2030 | EP30: 2030 | EQ30: 2030 | ER30: 2030 | ES30: 2030 | ET30: 2030 | EU30: 2030 | EV30: 2030 | EW30: 2030 | EX30: 2030 | EY30: 2030 | EZ30: 2030 | FA30: 2030 | FB30: 2030 | FC30: 2050 | FD30: 2025-2050 | FE30: 2024 | FF30: 2024 | FG30: 2024 | FH30: 2024 | FI30: 2024 | FJ30: 2024 | FK30: 2024 | FL30: 2024 | FM30: 2024 | FN30: 2024 | FO30: 2013 | FP30: 2013 | FQ30: 2013 | FU30: 2024 | FV30: 2024 | FW30: 2024 | FX30: 2024 | FY30: 2020-2024 avg | FZ30: 2030 | GA30: 2030 | GB30: 2030 | GC30: 2050 | GD30: 2050
A31: BGR | B31: Bulgaria | C31: Europe & Central Asia | D31: High income | E31: FALSE | F31: 0.739 | G31: 0.246 | H31: 23.84 | I31: 38.831 | J31: 59.428 | M31: 0 | O31: 9.11 | P31: 1 | Z31: 0.383 | AA31: 9.96 | AB31: 6.152 | AC31: 0.292 | AD31: 5.861 | AE31: 2.35 | AF31: -4.49 | AG31: 7.764 | AH31: 12.254 | AI31: 40.931 | AJ31: 0.151 | AK31: 0.019 | AL31: 0.006 | AM31: 0.126 | AN31: 0.685 | AO31: 35.194 | AP31: 2.911 | AQ31: 17.067 | AR31: 5.4493744 | AS31: 1.3078499 | AT31: 0.42990141 | AU31: 0.29478954 | AV31: 0.16107471 | AW31: 0.12317102 | AX31: 0.066134613 | AY31: 0.084369344 | AZ31: 0.14840922 | BA31: 0.071910458 | BB31: 0.039466205 | BC31: -0.023046618 | BD31: 60.068149 | BE31: 0.13518439 | BF31: 6.2555833 | BG31: 3.0979834 | BH31: 0.14688544 | BI31: 0.73585184 | BJ31: 0.73110316 | BK31: 0.55792425 | BL31: 0.92621866 | BM31: 0.31426272 | BN31: 66.103286 | BO31: 1.6365682 | BP31: 1.8690446 | BQ31: 3.4474546 | BR31: 1.272 | BS31: 1.418 | BT31: 0.13 | BU31: 0.126 | BV31: 19.063 | BW31: 16.43 | BX31: 16.43 | BY31: 7.123 | BZ31: 12.911 | CA31: 12.622 | CB31: 3 | CC31: 1 | CD31: 1 | CE31: 65.074 | CF31: 0 | CG31: 33.333 | CH31: 33.277 | CI31: -2.762 | CJ31: -1.352 | CK31: 20.43 | CL31: 2.77 | CM31: 0.222 | CN31: 0.346 | CO31: -0.124 | CP31: 6.447 | CQ31: 24.66 | CS31: 2024 | CT31: 2024 | CU31: 2024 | CV31: 2024 | CW31: 2022 | CZ31: 2022 | DB31: 2020 | DC31: 2021-2024 | DM31: 2020-2024 avg | DN31: 2024 | DO31: 2024 | DP31: 2024 | DQ31: 2024 | DR31: 2022 | DS31: 2024 | DT31: 2024 | DU31: 2024 | DV31: 2023 | DW31: 2021 | DX31: 2021 | DY31: 2021 | DZ31: 2021 | EA31: 2025 | EB31: 2024 | EC31: 2025 | ED31: 2025 | EE31: 2030 | EF31: 2030 | EG31: 2030 | EH31: 2030 | EI31: 2030 | EJ31: 2030 | EK31: 2030 | EL31: 2030 | EM31: 2030 | EN31: 2030 | EO31: 2030 | EP31: 2030 | EQ31: 2030 | ER31: 2030 | ES31: 2030 | ET31: 2030 | EU31: 2030 | EV31: 2030 | EW31: 2030 | EX31: 2030 | EY31: 2030 | EZ31: 2030 | FA31: 2030 | FB31: 2030 | FC31: 2050 | FD31: 2025-2050 | FE31: 2024 | FF31: 2024 | FG31: 2024 | FH31: 2024 | FI31: 2024 | FJ31: 2024 | FK31: 2024 | FL31: 2024 | FM31: 2024 | FN31: 2024 | FO31: 2013 | FP31: 2013 | FQ31: 2013 | FR31: 2023 | FS31: 2023 | FT31: 2023 | FU31: 2024 | FV31: 2024 | FW31: 2024 | FX31: 2024 | FY31: 2020-2024 avg | FZ31: 2030 | GA31: 2030 | GB31: 2030 | GC31: 2050 | GD31: 2050
A32: BFA | B32: Burkina Faso | C32: Sub-Saharan Africa | D32: Low income | E32: TRUE | F32: 10.068 | G32: 2.214 | H32: 57.247 | I32: 18.804 | J32: 83.3 | K32: 1.5 | L32: 1 | M32: 0 | N32: 5.8 | P32: 1 | R32: 5.942 | S32: 6.75 | T32: 38.569 | U32: 0.601 | V32: 89.774 | W32: 1.916 | X32: 59.568 | Y32: 1 | Z32: 0.225 | AA32: 13.856 | AB32: 2.111 | AC32: 0.955 | AD32: 1.156 | AE32: 0.44 | AF32: -41.128 | AG32: 0.021 | AH32: 41.149 | AJ32: 0 | AK32: 0 | AL32: 0 | AM32: 0 | AN32: 82.84 | AO32: 29.879 | AP32: 1.184 | AQ32: 14.286 | AR32: 6.5142244 | AS32: 1.5634138 | AT32: 0.26631022 | AU32: 0.18261272 | AV32: 0.1944061 | AW32: 0.083263163 | AX32: 0.048656103 | AY32: 0.064188533 | AZ32: 0.72397701 | BA32: 0.051128836 | BB32: 0.027602169 | BC32: -0.072658307 | BD32: 17.255115 | BE32: 0.098027781 | BF32: 7.9483637 | BG32: 7.2350947 | BH32: 3.8076842 | BI32: 0.35851417 | BJ32: 0.36951458 | BK32: 2.0279919 | BL32: 0.67138991 | BM32: 4.4160817 | BN32: 34.007831 | BO32: 6.4713893 | BP32: 3.9066423 | BQ32: 42.162309 | BR32: 1.137 | BS32: 1.415 | BT32: 0.186 | BU32: 0.304 | BV32: 17.629 | BW32: 6.998 | BX32: 5.675 | BY32: 10.843 | BZ32: 7.124 | CA32: 5.575 | CB32: 2 | CC32: 0 | CD32: 0 | CE32: 25.759 | CF32: 0 | CG32: 0 | CH32: 21.99 | CI32: -3.622 | CJ32: -3.484 | CK32: 21.934 | CL32: 3.676 | CM32: 4.214 | CN32: 0.41 | CO32: 3.804 | CP32: 1.073 | CQ32: 97.99 | CR32: 3 | CS32: 2024 | CT32: 2024 | CU32: 2024 | CV32: 2024 | CW32: 2020 | CX32: 2017 | CY32: 2017 | CZ32: 2022 | DA32: 2021 | DC32: 2021-2024 | DE32: 2024 | DF32: 2024 | DG32: 2024 | DH32: 2024 | DI32: 2024 | DJ32: 2024 | DK32: 2024 | DL32: 2017 | DM32: 2020-2024 avg | DN32: 2024 | DO32: 2024 | DP32: 2024 | DQ32: 2024 | DR32: 2020 | DS32: 2024 | DT32: 2024 | DU32: 2024 | DW32: 2021 | DX32: 2021 | DY32: 2021 | DZ32: 2021 | EA32: 2024 | EB32: 2024 | EC32: 2024 | ED32: 2024 | EE32: 2030 | EF32: 2030 | EG32: 2030 | EH32: 2030 | EI32: 2030 | EJ32: 2030 | EK32: 2030 | EL32: 2030 | EM32: 2030 | EN32: 2030 | EO32: 2030 | EP32: 2030 | EQ32: 2030 | ER32: 2030 | ES32: 2030 | ET32: 2030 | EU32: 2030 | EV32: 2030 | EW32: 2030 | EX32: 2030 | EY32: 2030 | EZ32: 2030 | FA32: 2030 | FB32: 2030 | FC32: 2050 | FD32: 2025-2050 | FE32: 2024 | FF32: 2024 | FG32: 2024 | FH32: 2024 | FI32: 2024 | FJ32: 2024 | FK32: 2024 | FL32: 2024 | FM32: 2024 | FN32: 2024 | FO32: 2013 | FP32: 2013 | FQ32: 2013 | FR32: 2023 | FS32: 2023 | FT32: 2023 | FU32: 2024 | FV32: 2024 | FW32: 2024 | FX32: 2024 | FY32: 2020-2024 avg | FZ32: 2030 | GA32: 2030 | GB32: 2030 | GC32: 2050 | GD32: 2050 | GE32: 2034
A33: BDI | B33: Burundi | C33: Sub-Saharan Africa | D33: Low income | E33: FALSE | F33: 9.091 | G33: 1.588 | H33: 53.057 | I33: 12.122 | J33: 80.264 | K33: 1 | L33: 1 | M33: 0 | T33: 5.25 | U33: 5.86 | V33: 66.37 | X33: 48.894 | Y33: 1 | Z33: 0.122 | AB33: 0.472 | AC33: 0.238 | AD33: 0.233 | AE33: 0.019 | AF33: -20.26 | AG33: 1.887 | AH33: 22.147 | AJ33: 0 | AK33: 0 | AL33: 0 | AM33: 0 | AN33: 24.49 | AO33: 64.288 | AP33: -0.49 | AQ33: 0 | AR33: 6.0190619 | AS33: 1.4445749 | AT33: 0.23935015 | AU33: 0.16412581 | AV33: 0.18302965 | AW33: 0.072861613 | AX33: 0.043271703 | AY33: 0.059822697 | AZ33: 0.68211324 | BA33: 0.11245298 | BB33: 0.059352069 | BC33: -0.032429036 | BD33: 46.680321 | BE33: 0.22125378 | BF33: 7.6241451 | BG33: 5.3258592 | BH33: 2.709919 | BI33: 0.15365681 | BJ33: 0.21860462 | BK33: 1.7432546 | BL33: 0.50042415 | BM33: 3.2328954 | BN33: 36.413035 | BO33: 4.6387994 | BP33: 2.9337264 | BQ33: 38.348071 | BR33: 1.615 | BS33: 1.599 | BT33: 0.119 | BU33: 0.164 | BV33: 24.468 | BW33: 12.794 | BX33: 11.471 | BY33: 14.388 | BZ33: 7.124 | CA33: 5.575 | CB33: 1 | CC33: 0 | CD33: 0 | CE33: 10.489 | CF33: 0 | CG33: 0 | CH33: 17.467 | CI33: -3.239 | CJ33: -8.569 | CK33: 19.571 | CL33: 2.418 | CM33: 2.994 | CN33: 0.033 | CO33: 2.961 | CP33: 0.626 | CQ33: 87.39 | CR33: 3 | CS33: 2024 | CT33: 2024 | CU33: 2024 | CV33: 2024 | CW33: 2022 | CX33: 2023 | CY33: 2023 | CZ33: 2022 | DG33: 2024 | DH33: 2024 | DI33: 2024 | DK33: 2024 | DL33: 2023 | DM33: 2020-2024 avg | DO33: 2024 | DP33: 2024 | DQ33: 2024 | DR33: 2022 | DS33: 2023 | DT33: 2023 | DU33: 2023 | DW33: 2021 | DX33: 2021 | DY33: 2021 | DZ33: 2021 | EA33: 2024 | EB33: 2024 | EC33: 2024 | ED33: 2024 | EE33: 2030 | EF33: 2030 | EG33: 2030 | EH33: 2030 | EI33: 2030 | EJ33: 2030 | EK33: 2030 | EL33: 2030 | EM33: 2030 | EN33: 2030 | EO33: 2030 | EP33: 2030 | EQ33: 2030 | ER33: 2030 | ES33: 2030 | ET33: 2030 | EU33: 2030 | EV33: 2030 | EW33: 2030 | EX33: 2030 | EY33: 2030 | EZ33: 2030 | FA33: 2030 | FB33: 2030 | FC33: 2050 | FD33: 2025-2050 | FE33: 2024 | FF33: 2024 | FG33: 2024 | FH33: 2024 | FI33: 2024 | FJ33: 2024 | FK33: 2024 | FL33: 2024 | FM33: 2024 | FN33: 2024 | FO33: 2013 | FP33: 2013 | FQ33: 2013 | FR33: 2023 | FS33: 2023 | FT33: 2023 | FU33: 2024 | FV33: 2024 | FW33: 2024 | FX33: 2024 | FY33: 2020-2024 avg | FZ33: 2030 | GA33: 2030 | GB33: 2030 | GC33: 2050 | GD33: 2050 | GE33: 2034
A34: CPV | B34: Cabo Verde | C34: Sub-Saharan Africa | D34: Upper middle income | E34: TRUE | F34: 9.365 | G34: 2.344 | H34: 112.847 | I34: 19.436 | J34: 43.59 | M34: 0 | R34: -1.628 | S34: 1.3 | T34: 18.705 | U34: 0.921 | V34: 60.234 | W34: 22.544 | X34: 37.991 | Z34: 1.129 | AA34: 5.328 | AB34: 2.359 | AC34: 0.35 | AD34: 2.009 | AE34: 1.772 | AF34: -14.359 | AG34: 0 | AH34: 14.359 | AJ34: 17.18 | AK34: 0 | AL34: 0 | AM34: 17.18 | AN34: 69.231 | AO34: 30.744 | AP34: 2.769 | AQ34: 0 | AR34: 3.9342525 | AS34: 0.94422059 | AT34: 0.26823709 | AU34: 0.18393401 | AV34: 0.15669838 | AW34: 0.084747788 | AX34: 0.058438333 | AY34: 0.061099726 | AZ34: 0.13106526 | BA34: 0.029138965 | BB34: -0.0051409926 | BC34: -0.027424028 | BD34: -7.5928437 | BE34: 0.14283316 | BF34: 4.5163063 | BG34: 2.8478858 | BH34: 0.29444982 | BI34: 0.77881932 | BJ34: 0.54681495 | BK34: 0.65901663 | BL34: 0.56878509 | BM34: 0.49215481 | BN34: 55.37131 | BO34: 1.7718112 | BP34: 1.6478742 | BQ34: -2.2691484 | BR34: 1.108 | BS34: 1.36 | BT34: 0.352 | BU34: 0.199 | BV34: 20.454 | BW34: 9.844 | BX34: 8.521 | BY34: 14.022 | BZ34: 7.124 | CA34: 5.575 | CH34: 25.029 | CI34: 1.278 | CJ34: 3.935 | CK34: 23.314 | CL34: 2.822 | CM34: 0.323 | CN34: 1.139 | CO34: -0.816 | CP34: 8.472 | CQ34: 102.2 | CS34: 2024 | CT34: 2024 | CU34: 2024 | CV34: 2024 | CW34: 2022 | CZ34: 2022 | DE34: 2024 | DF34: 2022 | DG34: 2024 | DH34: 2024 | DI34: 2024 | DJ34: 2024 | DK34: 2024 | DM34: 2020-2024 avg | DN34: 2024 | DO34: 2024 | DP34: 2024 | DQ34: 2024 | DR34: 2022 | DS34: 2023 | DT34: 2023 | DU34: 2024 | DW34: 2021 | DX34: 2021 | DY34: 2021 | DZ34: 2021 | EA34: 2024 | EB34: 2024 | EC34: 2024 | ED34: 2024 | EE34: 2030 | EF34: 2030 | EG34: 2030 | EH34: 2030 | EI34: 2030 | EJ34: 2030 | EK34: 2030 | EL34: 2030 | EM34: 2030 | EN34: 2030 | EO34: 2030 | EP34: 2030 | EQ34: 2030 | ER34: 2030 | ES34: 2030 | ET34: 2030 | EU34: 2030 | EV34: 2030 | EW34: 2030 | EX34: 2030 | EY34: 2030 | EZ34: 2030 | FA34: 2030 | FB34: 2030 | FC34: 2050 | FD34: 2025-2050 | FE34: 2024 | FF34: 2024 | FG34: 2024 | FH34: 2024 | FI34: 2024 | FJ34: 2024 | FK34: 2024 | FL34: 2024 | FM34: 2024 | FN34: 2024 | FU34: 2024 | FV34: 2024 | FW34: 2024 | FX34: 2024 | FY34: 2020-2024 avg | FZ34: 2030 | GA34: 2030 | GB34: 2030 | GC34: 2050 | GD34: 2050
A35: KHM | B35: Cambodia | C35: East Asia & Pacific | D35: Lower middle income | E35: TRUE | F35: 1.8 | G35: 0.272 | H35: 26.138 | I35: 12.531 | K35: 1.5 | L35: 2 | M35: 1 | O35: 10 | P35: 1 | T35: 25.816 | U35: 1.014 | V35: 38.421 | X35: 64.757 | Y35: 1 | Z35: 0.268 | AA35: 14.177 | AB35: 5.498 | AC35: 0.182 | AD35: 5.316 | AF35: -13.342 | AG35: 0.001 | AH35: 13.343 | AI35: 58.931 | AJ35: 0.046 | AK35: 0.041 | AL35: 0 | AM35: 0.005 | AN35: 2.534 | AO35: 67.328 | AP35: 5.219 | AQ35: 17.958 | AR35: 6.7322046 | AS35: 1.6157291 | AT35: 0.39130892 | AU35: 0.26832612 | AV35: 0.21537191 | AW35: 0.11073013 | AX35: 0.055725627 | AY35: 0.074792492 | AZ35: 0.4994739 | BA35: 0.10944115 | BB35: 0.057138187 | BC35: -0.023989925 | BD35: 40.813095 | BE35: 0.21792903 | BF35: 8.2143334 | BG35: 5.9958513 | BH35: 2.2982276 | BI35: 0.79509133 | BJ35: 0.57906076 | BK35: 1.624179 | BL35: 0.69929254 | BM35: 2.7854814 | BN35: 40.282497 | BO35: 4.9255285 | BP35: 3.1502852 | BQ35: 27.467721 | BR35: 0.913 | BS35: 1.014 | BT35: 0.118 | BU35: 0.155 | BV35: 23.633 | BW35: 13.543 | BX35: 12.219 | BY35: 12.581 | BZ35: 7.115 | CA35: 4.826 | CB35: 2 | CC35: 1 | CD35: 0 | CE35: 16.508 | CF35: 0 | CG35: 33.333 | CH35: 15.112 | CI35: -1.174 | CJ35: 0.495 | CK35: 32.186 | CL35: 3.295 | CM35: 2.654 | CN35: 0.369 | CO35: 2.286 | CP35: 8.395 | CQ35: 47.36 | CR35: 2 | CS35: 2024 | CT35: 2024 | CU35: 2024 | CV35: 2024 | CX35: 2022 | CY35: 2022 | CZ35: 2022 | DB35: 2016 | DC35: 2021-2024 | DG35: 2024 | DH35: 2024 | DI35: 2024 | DK35: 2024 | DL35: 2022 | DM35: 2020-2024 avg | DN35: 2014 | DO35: 2024 | DP35: 2024 | DQ35: 2024 | DS35: 2024 | DT35: 2024 | DU35: 2024 | DV35: 2021 | DW35: 2021 | DX35: 2021 | DY35: 2021 | DZ35: 2021 | EA35: 2025 | EB35: 2024 | EC35: 2025 | ED35: 2025 | EE35: 2030 | EF35: 2030 | EG35: 2030 | EH35: 2030 | EI35: 2030 | EJ35: 2030 | EK35: 2030 | EL35: 2030 | EM35: 2030 | EN35: 2030 | EO35: 2030 | EP35: 2030 | EQ35: 2030 | ER35: 2030 | ES35: 2030 | ET35: 2030 | EU35: 2030 | EV35: 2030 | EW35: 2030 | EX35: 2030 | EY35: 2030 | EZ35: 2030 | FA35: 2030 | FB35: 2030 | FC35: 2050 | FD35: 2025-2050 | FE35: 2024 | FF35: 2024 | FG35: 2024 | FH35: 2024 | FI35: 2024 | FJ35: 2024 | FK35: 2024 | FL35: 2024 | FM35: 2024 | FN35: 2024 | FO35: 2013 | FP35: 2013 | FQ35: 2013 | FR35: 2023 | FS35: 2023 | FT35: 2023 | FU35: 2024 | FV35: 2024 | FW35: 2024 | FX35: 2024 | FY35: 2020-2024 avg | FZ35: 2030 | GA35: 2030 | GB35: 2030 | GC35: 2050 | GD35: 2050 | GE35: 2034
A36: CMR | B36: Cameroon | C36: Sub-Saharan Africa | D36: Lower middle income | E36: TRUE | F36: 7.909 | G36: 1.23 | H36: 43.413 | I36: 12.672 | J36: 83.775 | K36: 1.5 | L36: 1 | M36: 0 | R36: 4.227 | S36: 8.467 | T36: 16.43 | U36: 0.611 | V36: 48.489 | W36: 14.372 | X36: 56.06 | Y36: 3 | Z36: 0.05 | AB36: 0.817 | AC36: 0.105 | AD36: 0.712 | AE36: 0.142 | AF36: 29.893 | AG36: 54.071 | AH36: 24.178 | AI36: -28.713 | AJ36: 2.947 | AK36: 2.362 | AL36: 0.585 | AM36: 0 | AN36: 4.821 | AO36: 78.733 | AP36: -0.129 | AQ36: 42.857 | AR36: 5.3494793 | AS36: 1.283875 | AT36: 0.27953323 | AU36: 0.19167993 | AV36: 0.1308178 | AW36: 0.084549173 | AX36: 0.043848548 | AY36: 0.05726586 | AZ36: 0.49618047 | BA36: 0.101314 | BB36: 0.053952687 | BC36: -0.014943485 | BD36: 56.136283 | BE36: 0.19733879 | BF36: 6.5271941 | BG36: 4.6461372 | BH36: 2.2022935 | BI36: 0.32541341 | BJ36: 0.28243568 | BK36: 1.4498658 | BL36: 0.38612885 | BM36: 2.6372532 | BN36: 36.233768 | BO36: 3.904541 | BP36: 2.470764 | BQ36: 37.85034 | BR36: 1.208 | BS36: 1.367 | BT36: 0.108 | BU36: 0.154 | BV36: 15.374 | BW36: 8.922 | BX36: 8.26 | BY36: 14.54 | BZ36: 7.124 | CA36: 5.575 | CB36: 1 | CC36: 1 | CD36: 0 | CE36: 13.854 | CF36: 0 | CG36: 50 | CH36: 15.552 | CI36: -0.279 | CJ36: -3.268 | CK36: 18.905 | CL36: 2.842 | CM36: 2.527 | CN36: 0.034 | CO36: 2.492 | CP36: 1.723 | CQ36: 68.29 | CR36: 3 | CS36: 2024 | CT36: 2024 | CU36: 2024 | CV36: 2024 | CW36: 2021 | CX36: 2023 | CY36: 2023 | CZ36: 2022 | DE36: 2024 | DF36: 2024 | DG36: 2024 | DH36: 2024 | DI36: 2024 | DJ36: 2024 | DK36: 2024 | DL36: 2023 | DM36: 2020-2024 avg | DO36: 2024 | DP36: 2024 | DQ36: 2024 | DR36: 2021 | DS36: 2023 | DT36: 2023 | DU36: 2023 | DV36: 2022 | DW36: 2021 | DX36: 2021 | DY36: 2021 | DZ36: 2021 | EA36: 2024 | EB36: 2024 | EC36: 2024 | ED36: 2024 | EE36: 2030 | EF36: 2030 | EG36: 2030 | EH36: 2030 | EI36: 2030 | EJ36: 2030 | EK36: 2030 | EL36: 2030 | EM36: 2030 | EN36: 2030 | EO36: 2030 | EP36: 2030 | EQ36: 2030 | ER36: 2030 | ES36: 2030 | ET36: 2030 | EU36: 2030 | EV36: 2030 | EW36: 2030 | EX36: 2030 | EY36: 2030 | EZ36: 2030 | FA36: 2030 | FB36: 2030 | FC36: 2050 | FD36: 2025-2050 | FE36: 2024 | FF36: 2024 | FG36: 2024 | FH36: 2024 | FI36: 2024 | FJ36: 2024 | FK36: 2024 | FL36: 2024 | FM36: 2024 | FN36: 2024 | FO36: 2013 | FP36: 2013 | FQ36: 2013 | FR36: 2023 | FS36: 2023 | FT36: 2023 | FU36: 2024 | FV36: 2024 | FW36: 2024 | FX36: 2024 | FY36: 2020-2024 avg | FZ36: 2030 | GA36: 2030 | GB36: 2030 | GC36: 2050 | GD36: 2050 | GE36: 2034
A37: CAN | B37: Canada | C37: North America | D37: High income | E37: FALSE | F37: 0.014 | G37: 0.006 | H37: 110.019 | I37: 29.456 | M37: 0 | AA37: 1.93 | AB37: 1.176 | AC37: 0.082 | AD37: 1.094 | AE37: 1.621 | AF37: 21.188 | AG37: 27.697 | AH37: 6.509 | AI37: -89.626 | AJ37: 3.697 | AK37: 2.83 | AL37: 0.794 | AM37: 0.073 | AN37: 1.166 | AO37: 74.209 | AP37: -0.382 | AQ37: 0.987 | AR37: 4.3721809 | AS37: 1.6614287 | AT37: 0.56643442 | AU37: 0.38841217 | AV37: 0.22886685 | AW37: 0.18874782 | AX37: 0.13712554 | AY37: 0.12817534 | AZ37: 0.023666603 | BA37: 0.043711842 | BB37: 0.049885233 | BC37: 0.03420259 | BD37: 94.708353 | BE37: -0.016245767 | BF37: 4.5681752 | BG37: 4.2033166 | BH37: 0.30302552 | BI37: 1.1376292 | BJ37: 0.80451029 | BK37: 0.30586051 | BL37: 1.6522911 | BM37: 0.39478367 | BN37: 63.542768 | BO37: 2.815631 | BP37: 1.8012267 | BQ37: 12.618718 | BR37: 1.172 | BS37: 1.299 | BT37: 0.122 | BU37: 0.106 | BV37: 9.94 | BW37: 8.749 | BX37: 8.749 | BY37: 10.635 | BZ37: 11.811 | CA37: 10.078 | CE37: 66.87 | CF37: 60 | CG37: 100 | CH37: 42.221 | CI37: -2.116 | CJ37: -0.482 | CK37: 23.168 | CL37: 1.921 | CM37: 0.257 | CN37: 0.126 | CO37: 0.131 | CP37: 6.113 | CQ37: 106.1 | CS37: 2024 | CT37: 2024 | CU37: 2024 | CV37: 2024 | CZ37: 2022 | DN37: 2024 | DO37: 2024 | DP37: 2024 | DQ37: 2024 | DR37: 2022 | DS37: 2024 | DT37: 2024 | DU37: 2024 | DV37: 2023 | DW37: 2021 | DX37: 2021 | DY37: 2021 | DZ37: 2021 | EA37: 2025 | EB37: 2024 | EC37: 2025 | ED37: 2025 | EE37: 2030 | EF37: 2030 | EG37: 2030 | EH37: 2030 | EI37: 2030 | EJ37: 2030 | EK37: 2030 | EL37: 2030 | EM37: 2030 | EN37: 2030 | EO37: 2030 | EP37: 2030 | EQ37: 2030 | ER37: 2030 | ES37: 2030 | ET37: 2030 | EU37: 2030 | EV37: 2030 | EW37: 2030 | EX37: 2030 | EY37: 2030 | EZ37: 2030 | FA37: 2030 | FB37: 2030 | FC37: 2050 | FD37: 2025-2050 | FE37: 2024 | FF37: 2024 | FG37: 2024 | FH37: 2024 | FI37: 2024 | FJ37: 2024 | FK37: 2024 | FL37: 2024 | FM37: 2024 | FN37: 2024 | FR37: 2023 | FS37: 2023 | FT37: 2023 | FU37: 2024 | FV37: 2024 | FW37: 2024 | FX37: 2024 | FY37: 2020-2024 avg | FZ37: 2030 | GA37: 2030 | GB37: 2030 | GC37: 2050 | GD37: 2050
A38: CYM | B38: Cayman Islands | C38: Latin America & Caribbean | D38: High income | E38: FALSE | M38: 0 | AF38: 38.704 | AG38: 52.311 | AH38: 13.607 | AJ38: 0 | AK38: 0 | AL38: 0 | AM38: 0 | AN38: 95.775 | AP38: 1.368 | AQ38: 0 | CZ38: 2022 | DS38: 2024 | DT38: 2024 | DU38: 2024 | DW38: 2021 | DX38: 2021 | DY38: 2021 | DZ38: 2021 | EA38: 2024 | EC38: 2024 | ED38: 2024
A39: CAF | B39: Central African Republic | C39: Sub-Saharan Africa | D39: Low income | E39: TRUE | F39: 5.955 | G39: 0.853 | H39: 59.883 | I39: 7.795 | J39: 10.003 | M39: 0 | T39: 36 | U39: 0.975 | V39: 38.85 | W39: 0.36 | X39: 62.097 | AA39: 6.874 | AB39: 0.026 | AC39: 0.001 | AD39: 0.025 | AE39: 0.58 | AF39: -26.452 | AG39: 0.032 | AH39: 26.484 | AJ39: 0 | AK39: 0 | AL39: 0 | AM39: 0 | AN39: 0 | AO39: 100 | AP39: 0 | AQ39: 200 | AR39: 23.146489 | AS39: 5.5551574 | AT39: 0.21416396 | AU39: 0.14685529 | AV39: 0.17130526 | AW39: 0.080195277 | AX39: 0.03825966 | AY39: 0.057963731 | AZ39: 4.8464143 | BA39: 0.46176981 | BB39: 0.25288276 | BC39: -0.38855623 | BD39: 34.790916 | BE39: 0.87036272 | BF39: 29.318886 | BG39: 50.774797 | BH39: 37.164342 | BI39: 0.13126202 | BJ39: 0.17779519 | BK39: 12.134243 | BL39: 1.1671543 | BM39: 40.804615 | BN39: 19.377565 | BO39: 50.276558 | BP39: 24.862295 | BQ39: 549.99599 | BR39: 1.997 | BS39: 1.814 | BT39: 0.143 | BU39: 0.077 | BV39: 19.18 | BW39: 8.176 | BX39: 6.853 | BY39: 14.509 | BZ39: 7.124 | CA39: 5.575 | CB39: 2 | CC39: 0 | CD39: 0 | CE39: 8.333 | CF39: 0 | CG39: 0 | CH39: 14.323 | CI39: -4.178 | CJ39: -9.099 | CK39: 16.357 | CL39: 0.996 | CM39: 40.64 | CN39: 0 | CO39: 40.64 | CP39: -0.169 | CQ39: 236.3 | CR39: 3 | CS39: 2024 | CT39: 2024 | CU39: 2024 | CV39: 2024 | CW39: 2021 | CZ39: 2022 | DG39: 2022 | DH39: 2024 | DI39: 2024 | DJ39: 2024 | DK39: 2024 | DN39: 2024 | DO39: 2024 | DP39: 2024 | DQ39: 2024 | DR39: 2021 | DS39: 2024 | DT39: 2024 | DU39: 2024 | DW39: 2021 | DX39: 2021 | DY39: 2021 | DZ39: 2021 | EA39: 2023 | EB39: 2024 | EC39: 2023 | ED39: 2023 | EE39: 2030 | EF39: 2030 | EG39: 2030 | EH39: 2030 | EI39: 2030 | EJ39: 2030 | EK39: 2030 | EL39: 2030 | EM39: 2030 | EN39: 2030 | EO39: 2030 | EP39: 2030 | EQ39: 2030 | ER39: 2030 | ES39: 2030 | ET39: 2030 | EU39: 2030 | EV39: 2030 | EW39: 2030 | EX39: 2030 | EY39: 2030 | EZ39: 2030 | FA39: 2030 | FB39: 2030 | FC39: 2050 | FD39: 2025-2050 | FE39: 2024 | FF39: 2024 | FG39: 2024 | FH39: 2024 | FI39: 2024 | FJ39: 2024 | FK39: 2024 | FL39: 2024 | FM39: 2024 | FN39: 2024 | FO39: 2013 | FP39: 2013 | FQ39: 2013 | FR39: 2023 | FS39: 2023 | FT39: 2023 | FU39: 2024 | FV39: 2024 | FW39: 2024 | FX39: 2024 | FY39: 2020-2024 avg | FZ39: 2030 | GA39: 2030 | GB39: 2030 | GC39: 2050 | GD39: 2050 | GE39: 2034
A40: TCD | B40: Chad | C40: Sub-Saharan Africa | D40: Low income | E40: TRUE | F40: 7.362 | G40: 1.181 | H40: 31.427 | I40: 7.372 | K40: 1.5 | L40: 2 | M40: 0 | T40: 18.06 | U40: 0.826 | V40: 31.116 | W40: 7.912 | X40: 62.778 | Y40: 1 | Z40: 0.263 | AB40: 0.703 | AC40: 0.477 | AD40: 0.226 | AF40: -9.992 | AG40: 7.943 | AH40: 17.935 | AI40: -177.763 | AJ40: 16.765 | AK40: 16.752 | AL40: 0.013 | AM40: 0 | AN40: 94.595 | AO40: 16.893 | AP40: -0.151 | AR40: 8.8656355 | AS40: 2.1277525 | AT40: 0.18376689 | AU40: 0.12601158 | AV40: 0.10660765 | AW40: 0.067417325 | AX40: 0.039844794 | AY40: 0.048498007 | AZ40: 1.5556063 | BA40: 0.1722096 | BB40: 0.092663811 | BC40: -0.11148983 | BD40: 34.604542 | BE40: 0.33144079 | BF40: 10.81745 | BG40: 10.212908 | BH40: 5.1091709 | BI40: 0.10436029 | BJ40: 0.16405576 | BK40: 3.9134115 | BL40: 0.92190923 | BM40: 6.2831943 | BN40: 37.456062 | BO40: 9.7375565 | BP40: 6.2696006 | BQ40: 114.9628 | BR40: 1.32 | BS40: 1.155 | BT40: 0.14 | BU40: 0.206 | BV40: 24.493 | BW40: 12.815 | BX40: 11.492 | BY40: 14.388 | BZ40: 7.124 | CA40: 5.575 | CB40: 1 | CC40: 0 | CD40: 0 | CE40: 32.093 | CF40: 0 | CG40: 0 | CH40: 16.042 | CI40: -0.847 | CJ40: 1.357 | CK40: 32.045 | CL40: 3.333 | CM40: 6.099 | CN40: 0.036 | CO40: 6.063 | CP40: -11.27 | CQ40: 87.05 | CR40: 3 | CS40: 2024 | CT40: 2024 | CU40: 2024 | CV40: 2024 | CX40: 2018 | CY40: 2018 | CZ40: 2022 | DG40: 2024 | DH40: 2024 | DI40: 2024 | DJ40: 2024 | DK40: 2024 | DL40: 2018 | DM40: 2020-2024 avg | DO40: 2024 | DP40: 2024 | DQ40: 2024 | DS40: 1975 | DT40: 1975 | DU40: 1995 | DV40: 2022 | DW40: 2021 | DX40: 2021 | DY40: 2021 | DZ40: 2021 | EA40: 2024 | EB40: 2024 | EC40: 2024 | EE40: 2030 | EF40: 2030 | EG40: 2030 | EH40: 2030 | EI40: 2030 | EJ40: 2030 | EK40: 2030 | EL40: 2030 | EM40: 2030 | EN40: 2030 | EO40: 2030 | EP40: 2030 | EQ40: 2030 | ER40: 2030 | ES40: 2030 | ET40: 2030 | EU40: 2030 | EV40: 2030 | EW40: 2030 | EX40: 2030 | EY40: 2030 | EZ40: 2030 | FA40: 2030 | FB40: 2030 | FC40: 2050 | FD40: 2025-2050 | FE40: 2024 | FF40: 2024 | FG40: 2024 | FH40: 2024 | FI40: 2024 | FJ40: 2024 | FK40: 2024 | FL40: 2024 | FM40: 2024 | FN40: 2024 | FO40: 2013 | FP40: 2013 | FQ40: 2013 | FR40: 2023 | FS40: 2023 | FT40: 2023 | FU40: 2024 | FV40: 2024 | FW40: 2024 | FX40: 2024 | FY40: 2020-2024 avg | FZ40: 2030 | GA40: 2030 | GB40: 2030 | GC40: 2050 | GD40: 2050 | GE40: 2034
A41: CHI | B41: Channel Islands | C41: Europe & Central Asia | D41: High income | E41: FALSE | M41: 0 | CZ41: 2022
A42: CHL | B42: Chile | C42: Latin America & Caribbean | D42: High income | E42: FALSE | F42: 3.195 | G42: 0.764 | H42: 41.65 | I42: 19.632 | J42: 106.026 | M42: 0 | O42: 6.03 | P42: 1 | AA42: 5.251 | AB42: 4.633 | AC42: 0.083 | AD42: 4.55 | AE42: 0.272 | AF42: -14.631 | AG42: 0.891 | AH42: 15.522 | AI42: 62.276 | AJ42: 0.034 | AK42: 0.013 | AL42: 0.021 | AM42: 0 | AN42: 0.565 | AO42: 64.207 | AP42: -3.668 | AQ42: 11.425 | AR42: 5.0672521 | AS42: 1.2161405 | AT42: 0.37656157 | AU42: 0.25821365 | AV42: 0.19295081 | AW42: 0.10017204 | AX42: 0.056498178 | AY42: 0.070660124 | AZ42: 0.16108414 | BA42: 0.036229483 | BB42: 0.035955105 | BC42: -0.0099047186 | BD42: 56.70536 | BE42: 0.0011432416 | BF42: 5.8169278 | BG42: 2.4886321 | BH42: 0.16328769 | BI42: 0.52777984 | BJ42: 0.53030399 | BK42: 0.25978358 | BL42: 1.007477 | BM42: 0.24122277 | BN42: 69.099386 | BO42: 1.3443476 | BP42: 1.4454729 | BQ42: -1.0688955 | BR42: 0.924 | BS42: 1.355 | BT42: 0.182 | BU42: 0.164 | BV42: 36.308 | BW42: 14.738 | BX42: 14.738 | BY42: 15.314 | BZ42: 9.436 | CA42: 4.546 | CE42: 67.056 | CF42: 40 | CG42: 83.333 | CH42: 23.912 | CI42: -2.051 | CJ42: -1.469 | CK42: 23.24 | CL42: 2.098 | CM42: 0.168 | CN42: 0.391 | CO42: -0.223 | CP42: 6.964 | CQ42: 39.9 | CS42: 2024 | CT42: 2024 | CU42: 2024 | CV42: 2024 | CW42: 2022 | CZ42: 2022 | DB42: 2020 | DC42: 2021-2024 | DN42: 2023 | DO42: 2024 | DP42: 2024 | DQ42: 2024 | DR42: 2022 | DS42: 2025 | DT42: 2025 | DU42: 2025 | DV42: 2023 | DW42: 2021 | DX42: 2021 | DY42: 2021 | DZ42: 2021 | EA42: 2025 | EB42: 2024 | EC42: 2025 | ED42: 2025 | EE42: 2030 | EF42: 2030 | EG42: 2030 | EH42: 2030 | EI42: 2030 | EJ42: 2030 | EK42: 2030 | EL42: 2030 | EM42: 2030 | EN42: 2030 | EO42: 2030 | EP42: 2030 | EQ42: 2030 | ER42: 2030 | ES42: 2030 | ET42: 2030 | EU42: 2030 | EV42: 2030 | EW42: 2030 | EX42: 2030 | EY42: 2030 | EZ42: 2030 | FA42: 2030 | FB42: 2030 | FC42: 2050 | FD42: 2025-2050 | FE42: 2024 | FF42: 2024 | FG42: 2024 | FH42: 2024 | FI42: 2024 | FJ42: 2024 | FK42: 2024 | FL42: 2024 | FM42: 2024 | FN42: 2024 | FR42: 2023 | FS42: 2023 | FT42: 2023 | FU42: 2024 | FV42: 2024 | FW42: 2024 | FX42: 2024 | FY42: 2020-2024 avg | FZ42: 2030 | GA42: 2030 | GB42: 2030 | GC42: 2050 | GD42: 2050
A43: CHN | B43: China | C43: East Asia & Pacific | D43: Upper middle income | E43: TRUE | F43: 3.693 | G43: 0.954 | H43: 90.421 | I43: 12.968 | M43: 1 | N43: 2.5 | O43: 3.23 | P43: 2 | R43: 0.656 | S43: 5.003 | T43: 12.477 | U43: 0.01 | V43: 6.488 | W43: 91.269 | X43: 80.027 | Z43: 0.137 | AA43: 4.786 | AB43: 14.978 | AC43: 0.243 | AD43: 14.735 | AE43: 2.159 | AF43: -18.924 | AG43: 1.498 | AH43: 20.422 | AI43: 23.962 | AJ43: 1.128 | AK43: 0.309 | AL43: 0.211 | AM43: 0.608 | AN43: 0.839 | AO43: 47.897 | AP43: 3.288 | AQ43: 24.355 | AR43: 3.4972681 | AS43: 1.3289619 | AT43: 0.45812167 | AU43: 0.31414057 | AV43: 0.19437448 | AW43: 0.15118015 | AX43: 0.086388658 | AY43: 0.10471352 | AZ43: 0.020042823 | BA43: 0.017700445 | BB43: 0.037788489 | BC43: -0.1099576 | BD43: 46.323712 | BE43: -0.052863274 | BF43: 4.1440232 | BG43: 6.2452276 | BH43: 0.28520682 | BI43: 2.5353543 | BJ43: 1.4146199 | BK43: 0.68217076 | BL43: 1.3278759 | BM43: 0.48985805 | BN43: 51.559615 | BO43: 3.3618124 | BP43: 2.2869423 | BQ43: 22.165443 | BR43: 0.946 | BS43: 1.079 | BT43: 0.072 | BU43: 0.088 | BV43: 10.244 | BW43: 13.944 | BX43: 13.944 | BY43: 2.255 | BZ43: 8.96 | CA43: 5.389 | CB43: 2 | CC43: 1 | CD43: 1 | CE43: 58.41 | CF43: 60 | CG43: 33.333 | CH43: 25.831 | CI43: -6.154 | CJ43: 2.238 | CK43: 40.607 | CL43: 4.877 | CM43: 0.335 | CN43: 0.358 | CO43: -0.023 | CP43: 5.513 | CQ43: 89.14 | CS43: 2024 | CT43: 2024 | CU43: 2024 | CV43: 2024 | CZ43: 2022 | DA43: 2021 | DB43: 2020 | DC43: 2021-2024 | DE43: 2024 | DF43: 2024 | DG43: 2024 | DH43: 2024 | DI43: 2024 | DJ43: 2024 | DK43: 2024 | DM43: 2020-2024 avg | DN43: 2024 | DO43: 2024 | DP43: 2024 | DQ43: 2024 | DR43: 2020 | DS43: 2024 | DT43: 2024 | DU43: 2024 | DV43: 2023 | DW43: 2021 | DX43: 2021 | DY43: 2021 | DZ43: 2021 | EA43: 2025 | EB43: 2024 | EC43: 2025 | ED43: 2025 | EE43: 2030 | EF43: 2030 | EG43: 2030 | EH43: 2030 | EI43: 2030 | EJ43: 2030 | EK43: 2030 | EL43: 2030 | EM43: 2030 | EN43: 2030 | EO43: 2030 | EP43: 2030 | EQ43: 2030 | ER43: 2030 | ES43: 2030 | ET43: 2030 | EU43: 2030 | EV43: 2030 | EW43: 2030 | EX43: 2030 | EY43: 2030 | EZ43: 2030 | FA43: 2030 | FB43: 2030 | FC43: 2050 | FD43: 2025-2050 | FE43: 2024 | FF43: 2024 | FG43: 2024 | FH43: 2024 | FI43: 2024 | FJ43: 2024 | FK43: 2024 | FL43: 2024 | FM43: 2024 | FN43: 2024 | FO43: 2013 | FP43: 2013 | FQ43: 2013 | FR43: 2023 | FS43: 2023 | FT43: 2023 | FU43: 2024 | FV43: 2024 | FW43: 2024 | FX43: 2024 | FY43: 2020-2024 avg | FZ43: 2030 | GA43: 2030 | GB43: 2030 | GC43: 2050 | GD43: 2050
A44: COL | B44: Colombia | C44: Latin America & Caribbean | D44: Upper middle income | E44: TRUE | F44: 13.549 | G44: 3.838 | H44: 61.008 | I44: 23.02 | J44: 83.432 | K44: 3 | L44: 2 | M44: 1 | N44: 5.6 | O44: 5.96 | P44: 2 | R44: 1.297 | S44: 8.145 | T44: 15.241 | U44: 0.298 | V44: 30.423 | W44: 64.853 | X44: 94.587 | Y44: 4 | Z44: 0.439 | AA44: 3.045 | AB44: 5.808 | AC44: 0.438 | AD44: 5.37 | AE44: 0.21 | AF44: 35.657 | AG44: 45.304 | AH44: 9.647 | AI44: -141.972 | AJ44: 4.326 | AK44: 3.424 | AL44: 0.176 | AM44: 0.726 | AN44: 3.1 | AO44: 79.858 | AP44: 15.673 | AQ44: 2.258 | AR44: 5.0448515 | AS44: 1.2107644 | AT44: 0.32128854 | AU44: 0.22031214 | AV44: 0.15624353 | AW44: 0.11146891 | AX44: 0.051967636 | AY44: 0.066629955 | AZ44: 0.28285365 | BA44: 0.053684878 | BB44: 0.045917428 | BC44: -0.043189159 | BD44: 65.413031 | BE44: 0.032364375 | BF44: 5.6140142 | BG44: 2.5466311 | BH44: 0.70340218 | BI44: 0.16625202 | BJ44: 0.26705109 | BK44: 0.6823251 | BL44: 0.72760067 | BM44: 0.90809971 | BN44: 57.812824 | BO44: 1.9582078 | BP44: 1.6078277 | BQ44: 9.799895 | BR44: 0.556 | BS44: 1.155 | BT44: 0.221 | BU44: 0.179 | BV44: 15.428 | BW44: 14.245 | BX44: 14.245 | BY44: 6.323 | BZ44: 2.537 | CA44: 2.325 | CB44: 3 | CC44: 1 | CD44: 1 | CE44: 48.923 | CF44: 20 | CG44: 50 | CH44: 28.327 | CI44: -2.199 | CJ44: -1.668 | CK44: 16.473 | CL44: 2.656 | CM44: 0.825 | CN44: 0.202 | CO44: 0.623 | CP44: 4.641 | CQ44: 66.53 | CS44: 2024 | CT44: 2024 | CU44: 2024 | CV44: 2024 | CW44: 2022 | CX44: 2024 | CY44: 2024 | CZ44: 2022 | DA44: 2021 | DB44: 2020 | DC44: 2021-2024 | DE44: 2024 | DF44: 2024 | DG44: 2024 | DH44: 2024 | DI44: 2024 | DJ44: 2024 | DK44: 2024 | DL44: 2024 | DM44: 2020-2024 avg | DN44: 2023 | DO44: 2024 | DP44: 2024 | DQ44: 2024 | DR44: 2022 | DS44: 2024 | DT44: 2024 | DU44: 2024 | DV44: 2023 | DW44: 2021 | DX44: 2021 | DY44: 2021 | DZ44: 2021 | EA44: 2025 | EB44: 2024 | EC44: 2025 | ED44: 2025 | EE44: 2030 | EF44: 2030 | EG44: 2030 | EH44: 2030 | EI44: 2030 | EJ44: 2030 | EK44: 2030 | EL44: 2030 | EM44: 2030 | EN44: 2030 | EO44: 2030 | EP44: 2030 | EQ44: 2030 | ER44: 2030 | ES44: 2030 | ET44: 2030 | EU44: 2030 | EV44: 2030 | EW44: 2030 | EX44: 2030 | EY44: 2030 | EZ44: 2030 | FA44: 2030 | FB44: 2030 | FC44: 2050 | FD44: 2025-2050 | FE44: 2024 | FF44: 2024 | FG44: 2024 | FH44: 2024 | FI44: 2024 | FJ44: 2024 | FK44: 2024 | FL44: 2024 | FM44: 2024 | FN44: 2024 | FO44: 2013 | FP44: 2013 | FQ44: 2013 | FR44: 2023 | FS44: 2023 | FT44: 2023 | FU44: 2024 | FV44: 2024 | FW44: 2024 | FX44: 2024 | FY44: 2020-2024 avg | FZ44: 2030 | GA44: 2030 | GB44: 2030 | GC44: 2050 | GD44: 2050
A45: COM | B45: Comoros | C45: Sub-Saharan Africa | D45: Lower middle income | E45: TRUE | F45: 1.901 | G45: 0.313 | H45: 29.996 | I45: 8.858 | J45: 100 | M45: 0 | R45: 2.486 | S45: 3 | T45: 13.77 | U45: 3.72 | V45: 43.679 | W45: 0 | X45: 35.225 | AA45: 19.801 | AB45: 0.744 | AC45: 0 | AD45: 0.744 | AE45: 0.119 | AF45: -10.223 | AG45: 0.005 | AH45: 10.228 | AJ45: 0 | AK45: 0 | AL45: 0 | AM45: 0 | AN45: 100 | AO45: 14.618 | AP45: 0 | AR45: 4.6286883 | AS45: 1.1108852 | AT45: 0.22552901 | AU45: 0.15464846 | AV45: 0.24814295 | AW45: 0.10058035 | AX45: 0.058425904 | AY45: 0.07811802 | AZ45: 0.24544051 | BA45: 0.016380481 | BB45: -0.02349997 | BC45: -0.060611225 | BD45: -25.388848 | BE45: 0.16616855 | BF45: 5.3134806 | BG45: 3.2717428 | BH45: 0.60755878 | BI45: 0.81484188 | BJ45: 0.25130938 | BK45: 0.99494418 | BL45: 0.60308855 | BM45: 0.90604203 | BN45: 47.401613 | BO45: 2.5267958 | BP45: 2.3407494 | BQ45: -10.367374 | BR45: 1.189 | BS45: 1.712 | BT45: 0.455 | BU45: 0.389 | BV45: 19.641 | BW45: 9.914 | BX45: 8.591 | BY45: 13.412 | BZ45: 7.124 | CA45: 5.575 | CH45: 16.463 | CI45: -2.362 | CJ45: -2.285 | CK45: 7.087 | CL45: 2.148 | CM45: 0.751 | CN45: 0 | CO45: 0.751 | CP45: 15.19 | CQ45: 34.99 | CR45: 2 | CS45: 2024 | CT45: 2024 | CU45: 2024 | CV45: 2024 | CW45: 2020 | CZ45: 2022 | DE45: 2023 | DF45: 2020 | DG45: 2023 | DH45: 2024 | DI45: 2024 | DJ45: 2024 | DK45: 2024 | DN45: 2024 | DO45: 2024 | DP45: 2024 | DQ45: 2024 | DR45: 2020 | DS45: 2023 | DT45: 2023 | DU45: 2023 | DW45: 2021 | DX45: 2021 | DY45: 2021 | DZ45: 2021 | EA45: 2023 | EB45: 2024 | EC45: 2023 | EE45: 2030 | EF45: 2030 | EG45: 2030 | EH45: 2030 | EI45: 2030 | EJ45: 2030 | EK45: 2030 | EL45: 2030 | EM45: 2030 | EN45: 2030 | EO45: 2030 | EP45: 2030 | EQ45: 2030 | ER45: 2030 | ES45: 2030 | ET45: 2030 | EU45: 2030 | EV45: 2030 | EW45: 2030 | EX45: 2030 | EY45: 2030 | EZ45: 2030 | FA45: 2030 | FB45: 2030 | FC45: 2050 | FD45: 2025-2050 | FE45: 2024 | FF45: 2024 | FG45: 2024 | FH45: 2024 | FI45: 2024 | FJ45: 2024 | FK45: 2024 | FL45: 2024 | FM45: 2024 | FN45: 2024 | FU45: 2024 | FV45: 2024 | FW45: 2024 | FX45: 2024 | FY45: 2020-2024 avg | FZ45: 2030 | GA45: 2030 | GB45: 2030 | GC45: 2050 | GD45: 2050 | GE45: 2034
A46: COD | B46: Congo, Dem. Rep. | C46: Sub-Saharan Africa | D46: Low income | E46: TRUE | F46: 1.716 | G46: 0.254 | H46: 15.841 | I46: 9.752 | J46: 25.041 | K46: 1 | L46: 1 | M46: 0 | R46: 4.505 | S46: 4.853 | T46: 34.309 | U46: 0.691 | V46: 51.574 | W46: 0.89 | X46: 88.255 | Y46: 1 | Z46: 0.585 | AA46: 4.549 | AB46: 0.333 | AC46: 0 | AD46: 0.333 | AE46: 0.309 | AF46: -36.486 | AG46: 0 | AH46: 36.486 | AI46: 1.596 | AJ46: 0.65 | AK46: 0.65 | AL46: 0 | AM46: 0 | AN46: 0 | AO46: 99.988 | AP46: 0 | AQ46: 2.181 | AR46: 12.777718 | AS46: 3.0666523 | AT46: 0.27196304 | AU46: 0.18648894 | AV46: 0.1006795 | AW46: 0.060581734 | AX46: 0.037457503 | AY46: 0.041864926 | AZ46: 2.3676167 | BA46: 0.23450213 | BB46: 0.1193007 | BC46: -0.20130134 | BD46: 32.762912 | BE46: 0.48000594 | BF46: 16.185109 | BG46: 29.99248 | BH46: 23.11172 | BI46: 0.10622916 | BJ46: 0.17046829 | BK46: 6.3230704 | BL46: 0.28099199 | BM46: 25.008641 | BN46: 16.262775 | BO46: 29.174789 | BP46: 11.977081 | BQ46: 313.59079 | BR46: 1.183 | BS46: 1.286 | BT46: 0.063 | BU46: 0.049 | BV46: 12.555 | BW46: 6.853 | BX46: 6.191 | BY46: 14.144 | BZ46: 7.124 | CA46: 5.575 | CB46: 1 | CC46: 0 | CD46: 0 | CE46: 16.394 | CF46: 0 | CG46: 0 | CH46: 14.804 | CI46: -1.407 | CJ46: -4.153 | CK46: 13.809 | CL46: 6.223 | CM46: 24.66 | CN46: 0 | CO46: 24.66 | CP46: -0.18 | CQ46: 130.9 | CR46: 3 | CS46: 2024 | CT46: 2024 | CU46: 2024 | CV46: 2024 | CW46: 2021 | CX46: 2020 | CY46: 2020 | CZ46: 2022 | DE46: 2024 | DF46: 2023 | DG46: 2024 | DH46: 2024 | DI46: 2024 | DJ46: 2024 | DK46: 2024 | DL46: 2020 | DM46: 2020-2024 avg | DN46: 2024 | DO46: 2024 | DP46: 2024 | DQ46: 2024 | DR46: 2021 | DS46: 2023 | DT46: 2023 | DU46: 2023 | DV46: 2022 | DW46: 2021 | DX46: 2021 | DY46: 2021 | DZ46: 2021 | EA46: 2024 | EB46: 2024 | EC46: 2024 | ED46: 2024 | EE46: 2030 | EF46: 2030 | EG46: 2030 | EH46: 2030 | EI46: 2030 | EJ46: 2030 | EK46: 2030 | EL46: 2030 | EM46: 2030 | EN46: 2030 | EO46: 2030 | EP46: 2030 | EQ46: 2030 | ER46: 2030 | ES46: 2030 | ET46: 2030 | EU46: 2030 | EV46: 2030 | EW46: 2030 | EX46: 2030 | EY46: 2030 | EZ46: 2030 | FA46: 2030 | FB46: 2030 | FC46: 2050 | FD46: 2025-2050 | FE46: 2024 | FF46: 2024 | FG46: 2024 | FH46: 2024 | FI46: 2024 | FJ46: 2024 | FK46: 2024 | FL46: 2024 | FM46: 2024 | FN46: 2024 | FO46: 2013 | FP46: 2013 | FQ46: 2013 | FR46: 2023 | FS46: 2023 | FT46: 2023 | FU46: 2024 | FV46: 2024 | FW46: 2024 | FX46: 2024 | FY46: 2020-2024 avg | FZ46: 2030 | GA46: 2030 | GB46: 2030 | GC46: 2050 | GD46: 2050 | GE46: 2034
A47: COG | B47: Congo, Rep. | C47: Sub-Saharan Africa | D47: Lower middle income | E47: TRUE | F47: 18.447 | G47: 4.661 | H47: 98.028 | I47: 10.585 | M47: 0 | R47: 2.645 | S47: 5.5 | T47: 17.747 | U47: 0.702 | V47: 25.083 | W47: 32.233 | X47: 77.15 | AA47: 0.914 | AB47: 3.343 | AC47: 0.932 | AD47: 2.412 | AF47: 80.661 | AG47: 85.863 | AH47: 5.202 | AI47: -347.42 | AJ47: 34.74 | AK47: 34.383 | AL47: 0.357 | AM47: 0 | AN47: 5.311 | AO47: 39.43 | AP47: -2.628 | AQ47: 0 | AR47: 6.6164759 | AS47: 1.5879542 | AT47: 0.29369452 | AU47: 0.20139053 | AV47: 0.15665913 | AW47: 0.086875906 | AX47: 0.044120944 | AY47: 0.07842578 | AZ47: 0.72678739 | BA47: 0.1231371 | BB47: 0.064510731 | BC47: -0.034391123 | BD47: 44.097303 | BE47: 0.24427655 | BF47: 7.5953517 | BG47: 5.9917303 | BH47: 2.6615437 | BI47: 0.25239302 | BJ47: 0.097542393 | BK47: 2.4689112 | BL47: 0.51133992 | BM47: 3.4022171 | BN47: 39.005764 | BO47: 5.4171068 | BP47: 4.3522364 | BQ47: 52.486366 | BR47: 0.941 | BS47: 1.258 | BT47: 0.128 | BU47: 0.045 | BV47: 14.167 | BW47: 8.036 | BX47: 7.374 | BY47: 14.388 | BZ47: 7.124 | CA47: 5.575 | CB47: 1 | CC47: 0 | CD47: 0 | CE47: 3.056 | CF47: 0 | CG47: 0 | CH47: 25.267 | CI47: 8.276 | CJ47: -3.012 | CK47: 27.146 | CL47: 0.135 | CM47: 3.176 | CN47: 0.19 | CO47: 2.986 | CP47: -24.76 | CQ47: 131 | CR47: 3 | CS47: 2024 | CT47: 2024 | CU47: 2024 | CV47: 2024 | CZ47: 2022 | DE47: 2024 | DF47: 2024 | DG47: 2024 | DH47: 2024 | DI47: 2024 | DJ47: 2024 | DK47: 2024 | DN47: 2024 | DO47: 2024 | DP47: 2024 | DQ47: 2024 | DS47: 2023 | DT47: 2023 | DU47: 2023 | DV47: 2022 | DW47: 2021 | DX47: 2021 | DY47: 2021 | DZ47: 2021 | EA47: 2024 | EB47: 2024 | EC47: 2024 | ED47: 2024 | EE47: 2030 | EF47: 2030 | EG47: 2030 | EH47: 2030 | EI47: 2030 | EJ47: 2030 | EK47: 2030 | EL47: 2030 | EM47: 2030 | EN47: 2030 | EO47: 2030 | EP47: 2030 | EQ47: 2030 | ER47: 2030 | ES47: 2030 | ET47: 2030 | EU47: 2030 | EV47: 2030 | EW47: 2030 | EX47: 2030 | EY47: 2030 | EZ47: 2030 | FA47: 2030 | FB47: 2030 | FC47: 2050 | FD47: 2025-2050 | FE47: 2024 | FF47: 2024 | FG47: 2024 | FH47: 2024 | FI47: 2024 | FJ47: 2024 | FK47: 2024 | FL47: 2024 | FM47: 2024 | FN47: 2024 | FO47: 2012 | FP47: 2012 | FQ47: 2012 | FR47: 2023 | FS47: 2023 | FT47: 2023 | FU47: 2024 | FV47: 2024 | FW47: 2024 | FX47: 2024 | FY47: 2020-2024 avg | FZ47: 2030 | GA47: 2030 | GB47: 2030 | GC47: 2050 | GD47: 2050 | GE47: 2034
A48: CRI | B48: Costa Rica | C48: Latin America & Caribbean | D48: High income | E48: FALSE | F48: 32.096 | G48: 4.774 | H48: 58.91 | I48: 13.192 | J48: 100 | K48: 2.5 | L48: 2 | M48: 0 | O48: 6.79 | P48: 1 | U48: 0.265 | Y48: 2 | AA48: 14.682 | AB48: 1.667 | AC48: 0.183 | AD48: 1.484 | AE48: 0.123 | AF48: -10.245 | AG48: 0.018 | AH48: 10.263 | AI48: 60.421 | AJ48: 0.009 | AK48: 0.009 | AL48: 0 | AM48: 0 | AN48: -9.863 | AO48: 100 | AP48: 9.954 | AQ48: 1.379 | AR48: 3.3503795 | AS48: 0.80409107 | AT48: 0.24293519 | AU48: 0.16658413 | AV48: 0.1222821 | AW48: 0.070066363 | AX48: 0.034522395 | AY48: 0.043680024 | AZ48: 0.12402087 | BA48: -0.030999504 | BB48: -0.03585394 | BC48: -0.094569814 | BD48: -93.683383 | BE48: 0.020226817 | BF48: 3.8335634 | BG48: 1.1421926 | BH48: 0.10462775 | BI48: 0.17084689 | BJ48: 0.2638678 | BK48: 0.107021 | BL48: 0.49582912 | BM48: 0.13673405 | BN48: 73.071008 | BO48: 0.503716 | BP48: 0.46375684 | BQ48: -1.4533957 | BR48: 1.229 | BS48: 1.319 | BT48: 0.191 | BU48: 0.232 | BV48: 14.81 | BW48: 5.164 | BX48: 3.841 | BY48: 13.778 | BZ48: 7.124 | CA48: 5.575 | CB48: 3 | CC48: 1 | CD48: 0 | CE48: 52.241 | CF48: 20 | CG48: 50 | CH48: 14.874 | CI48: 1.045 | CJ48: -0.933 | CK48: 16.194 | CL48: 3.682 | CM48: 0.064 | CN48: 0 | CO48: 0.064 | CP48: 2.494 | CQ48: 58.38 | CS48: 2024 | CT48: 2024 | CU48: 2024 | CV48: 2024 | CW48: 2022 | CX48: 2022 | CY48: 2022 | CZ48: 2022 | DB48: 2020 | DC48: 2021-2024 | DH48: 2024 | DL48: 2022 | DN48: 2024 | DO48: 2024 | DP48: 2024 | DQ48: 2024 | DR48: 2022 | DS48: 2024 | DT48: 2024 | DU48: 2024 | DV48: 2023 | DW48: 2021 | DX48: 2021 | DY48: 2021 | DZ48: 2021 | EA48: 2025 | EB48: 2024 | EC48: 2025 | ED48: 2025 | EE48: 2030 | EF48: 2030 | EG48: 2030 | EH48: 2030 | EI48: 2030 | EJ48: 2030 | EK48: 2030 | EL48: 2030 | EM48: 2030 | EN48: 2030 | EO48: 2030 | EP48: 2030 | EQ48: 2030 | ER48: 2030 | ES48: 2030 | ET48: 2030 | EU48: 2030 | EV48: 2030 | EW48: 2030 | EX48: 2030 | EY48: 2030 | EZ48: 2030 | FA48: 2030 | FB48: 2030 | FC48: 2050 | FD48: 2025-2050 | FE48: 2024 | FF48: 2024 | FG48: 2024 | FH48: 2024 | FI48: 2024 | FJ48: 2024 | FK48: 2024 | FL48: 2024 | FM48: 2024 | FN48: 2024 | FO48: 2013 | FP48: 2013 | FQ48: 2013 | FR48: 2023 | FS48: 2023 | FT48: 2023 | FU48: 2024 | FV48: 2024 | FW48: 2024 | FX48: 2024 | FY48: 2020-2024 avg | FZ48: 2030 | GA48: 2030 | GB48: 2030 | GC48: 2050 | GD48: 2050
A49: HRV | B49: Croatia | C49: Europe & Central Asia | D49: High income | E49: TRUE | F49: 2.286 | G49: 1.053 | H49: 57.369 | I49: 27.216 | J49: 99.991 | M49: 1 | N49: 5.3 | O49: 5.87 | P49: 2 | AA49: 8.022 | AB49: 2.659 | AC49: 0.779 | AD49: 1.88 | AE49: 3.648 | AF49: -2.451 | AG49: 13.092 | AH49: 15.543 | AI49: 57.291 | AJ49: 0.463 | AK49: 0.28 | AL49: 0.183 | AM49: 0 | AN49: -0.136 | AO49: 81.801 | AP49: 2.915 | AQ49: 10.989 | AR49: 3.6906854 | AS49: 1.4024605 | AT49: 0.48944988 | AU49: 0.33562277 | AV49: 0.20669261 | AW49: 0.16243049 | AX49: 0.083569671 | AY49: 0.099686854 | AZ49: 0.025008187 | BA49: 0.017318447 | BB49: 0.010516883 | BC49: -0.0094910316 | BD49: 23.556439 | BE49: 0.017898851 | BF49: 3.85613 | BG49: 3.1259947 | BH49: 0.25059654 | BI49: 0.61283977 | BJ49: 0.72210545 | BK49: 0.29225509 | BL49: 1.2481979 | BM49: 0.33827306 | BN49: 69.574074 | BO49: 1.4166511 | BP49: 0.94769063 | BQ49: -0.91408059 | BR49: 1.512 | BS49: 1.663 | BT49: 0.16 | BU49: 0.218 | BV49: 13.575 | BW49: 19.497 | BX49: 19.497 | BY49: 11.633 | BZ49: 16.877 | CA49: 12.775 | CB49: 3 | CC49: 1 | CD49: 1 | CE49: 59.222 | CF49: 20 | CG49: 16.667 | CH49: 46.056 | CI49: -0.894 | CJ49: -2.189 | CK49: 24.401 | CL49: 3.841 | CM49: 0.187 | CN49: 0.157 | CO49: 0.03 | CP49: 5.525 | CQ49: 56.1 | CS49: 2024 | CT49: 2024 | CU49: 2024 | CV49: 2024 | CW49: 2022 | CZ49: 2022 | DA49: 2021 | DB49: 2020 | DC49: 2021-2024 | DN49: 2023 | DO49: 2024 | DP49: 2024 | DQ49: 2024 | DR49: 2022 | DS49: 2024 | DT49: 2024 | DU49: 2024 | DV49: 2023 | DW49: 2021 | DX49: 2021 | DY49: 2021 | DZ49: 2021 | EA49: 2025 | EB49: 2024 | EC49: 2025 | ED49: 2025 | EE49: 2030 | EF49: 2030 | EG49: 2030 | EH49: 2030 | EI49: 2030 | EJ49: 2030 | EK49: 2030 | EL49: 2030 | EM49: 2030 | EN49: 2030 | EO49: 2030 | EP49: 2030 | EQ49: 2030 | ER49: 2030 | ES49: 2030 | ET49: 2030 | EU49: 2030 | EV49: 2030 | EW49: 2030 | EX49: 2030 | EY49: 2030 | EZ49: 2030 | FA49: 2030 | FB49: 2030 | FC49: 2050 | FD49: 2025-2050 | FE49: 2024 | FF49: 2024 | FG49: 2024 | FH49: 2024 | FI49: 2024 | FJ49: 2024 | FK49: 2024 | FL49: 2024 | FM49: 2024 | FN49: 2024 | FO49: 2013 | FP49: 2013 | FQ49: 2013 | FR49: 2023 | FS49: 2023 | FT49: 2023 | FU49: 2024 | FV49: 2024 | FW49: 2024 | FX49: 2024 | FY49: 2020-2024 avg | FZ49: 2030 | GA49: 2030 | GB49: 2030 | GC49: 2050 | GD49: 2050
A50: CUB | B50: Cuba | C50: Latin America & Caribbean | D50: Upper middle income | E50: FALSE | M50: 0 | AF50: -25.161 | AG50: 5.736 | AH50: 30.897 | AI50: 62.813 | AJ50: 0.246 | AK50: 0.222 | AL50: 0.024 | AM50: 0 | AN50: 82.347 | AP50: 0.367 | AQ50: 13.58 | CB50: 2 | CC50: 0 | CD50: 0 | CZ50: 2022 | DS50: 2021 | DT50: 2021 | DU50: 2021 | DV50: 2022 | DW50: 2020 | DX50: 2020 | DY50: 2020 | DZ50: 2020 | EA50: 2024 | EC50: 2024 | ED50: 2024 | FO50: 2013 | FP50: 2013 | FQ50: 2013
A51: CUW | B51: Curaçao | C51: Latin America & Caribbean | D51: High income | E51: FALSE | M51: 0 | AI51: 236.119 | AM51: 0 | CZ51: 2022 | DV51: 2018 | DZ51: 2021
A52: CYP | B52: Cyprus | C52: Europe & Central Asia | D52: High income | E52: FALSE | F52: 2.848 | G52: 1.208 | H52: 62.836 | I52: 25.292 | M52: 0 | O52: 5.1 | P52: 1 | AA52: 3.845 | AB52: 0.351 | AC52: 0 | AD52: 0.351 | AE52: 0.868 | AF52: 26.669 | AG52: 49.069 | AH52: 22.4 | AI52: 117.038 | AJ52: 0 | AK52: 0 | AL52: 0 | AM52: 0 | AN52: 72.25 | AO52: 42.898 | AP52: 3.743 | AQ52: 13.043 | AR52: 2.8490672 | AS52: 1.0826455 | AT52: 0.36025638 | AU52: 0.24703294 | AV52: 0.1808472 | AW52: 0.098828246 | AX52: 0.091071137 | AY52: 0.08629901 | AZ52: 0.01831062 | BA52: -0.042830023 | BB52: -0.035679021 | BC52: -0.051029267 | BD52: -51.395209 | BE52: -0.018818427 | BF52: 2.976784 | BG52: 3.965383 | BH52: 0.16510991 | BI52: 2.2042065 | BJ52: 0.41569474 | BK52: 0.1733139 | BL52: 1.0070579 | BM52: 0.21710408 | BN52: 38.938796 | BO52: 2.3072561 | BP52: 1.3257949 | BQ52: 1.2303149 | BR52: 1.461 | BS52: 1.558 | BT52: 0.351 | BU52: 0.262 | BV52: 24.701 | BW52: 16.484 | BX52: 15.159 | BY52: 10.469 | BZ52: 11.496 | CA52: 10.312 | CB52: 1 | CC52: 1 | CD52: 0 | CH52: 42.422 | CI52: 5.347 | CJ52: -8.204 | CK52: 20.522 | CL52: 4.802 | CM52: 0.083 | CN52: 0.438 | CO52: -0.354 | CP52: 5.94 | CQ52: 58.99 | CS52: 2024 | CT52: 2024 | CU52: 2024 | CV52: 2024 | CZ52: 2022 | DB52: 2019 | DC52: 2021-2024 | DN52: 2023 | DO52: 2024 | DP52: 2024 | DQ52: 2024 | DR52: 2021 | DS52: 2024 | DT52: 2024 | DU52: 2024 | DV52: 2022 | DW52: 2021 | DX52: 2021 | DY52: 2021 | DZ52: 2021 | EA52: 2025 | EB52: 2024 | EC52: 2025 | ED52: 2025 | EE52: 2030 | EF52: 2030 | EG52: 2030 | EH52: 2030 | EI52: 2030 | EJ52: 2030 | EK52: 2030 | EL52: 2030 | EM52: 2030 | EN52: 2030 | EO52: 2030 | EP52: 2030 | EQ52: 2030 | ER52: 2030 | ES52: 2030 | ET52: 2030 | EU52: 2030 | EV52: 2030 | EW52: 2030 | EX52: 2030 | EY52: 2030 | EZ52: 2030 | FA52: 2030 | FB52: 2030 | FC52: 2050 | FD52: 2025-2050 | FE52: 2024 | FF52: 2024 | FG52: 2024 | FH52: 2024 | FI52: 2024 | FJ52: 2024 | FK52: 2024 | FL52: 2024 | FM52: 2024 | FN52: 2024 | FO52: 2013 | FP52: 2013 | FQ52: 2013 | FU52: 2024 | FV52: 2024 | FW52: 2024 | FX52: 2024 | FY52: 2020-2024 avg | FZ52: 2030 | GA52: 2030 | GB52: 2030 | GC52: 2050 | GD52: 2050
A53: CZE | B53: Czechia | C53: Europe & Central Asia | D53: High income | E53: FALSE | F53: 1.643 | G53: 0.671 | H53: 43.291 | I53: 18.865 | M53: 0 | O53: 5.75 | P53: 1 | AA53: 5.157 | AB53: 2.688 | AC53: 0 | AD53: 2.688 | AE53: 2.005 | AF53: -3.803 | AG53: 1.65 | AH53: 5.453 | AI53: 41.975 | AJ53: 0.116 | AK53: 0.01 | AL53: 0.012 | AM53: 0.094 | AN53: 0.212 | AO53: 44.556 | AP53: -0.156 | AQ53: 9.019 | AR53: 3.562866 | AS53: 1.3538891 | AT53: 0.45427858 | AU53: 0.31150531 | AV53: 0.19506375 | AW53: 0.16254821 | AX53: 0.093816654 | AY53: 0.10965583 | AZ53: 0.027020744 | BA53: 0.035033725 | BB53: 0.037559247 | BC53: -0.00067472821 | BD53: 56.448026 | BE53: -0.0066461081 | BF53: 3.7225807 | BG53: 4.1946065 | BH53: 0.32612289 | BI53: 0.95800296 | BJ53: 1.0419445 | BK53: 0.23638689 | BL53: 1.6321493 | BM53: 0.39703895 | BN53: 67.695613 | BO53: 2.4888041 | BP53: 1.3772104 | BQ53: 4.2229637 | BR53: 1.452 | BS53: 1.611 | BT53: 0.362 | BU53: 0.188 | BV53: 31.773 | BW53: 22.918 | BX53: 22.918 | BY53: 11.853 | BZ53: 10.146 | CA53: 10.146 | CE53: 77.704 | CF53: 40 | CG53: 50 | CH53: 40.829 | CI53: -1.358 | CJ53: 1.744 | CK53: 26.322 | CL53: 0.574 | CM53: 0.263 | CN53: 0.334 | CO53: -0.071 | CP53: 6.557 | CQ53: 42.59 | CS53: 2024 | CT53: 2024 | CU53: 2024 | CV53: 2024 | CZ53: 2022 | DB53: 2019 | DC53: 2021-2024 | DN53: 2024 | DO53: 2024 | DP53: 2024 | DQ53: 2024 | DR53: 2021 | DS53: 2024 | DT53: 2024 | DU53: 2024 | DV53: 2023 | DW53: 2021 | DX53: 2021 | DY53: 2021 | DZ53: 2021 | EA53: 2025 | EB53: 2024 | EC53: 2025 | ED53: 2025 | EE53: 2030 | EF53: 2030 | EG53: 2030 | EH53: 2030 | EI53: 2030 | EJ53: 2030 | EK53: 2030 | EL53: 2030 | EM53: 2030 | EN53: 2030 | EO53: 2030 | EP53: 2030 | EQ53: 2030 | ER53: 2030 | ES53: 2030 | ET53: 2030 | EU53: 2030 | EV53: 2030 | EW53: 2030 | EX53: 2030 | EY53: 2030 | EZ53: 2030 | FA53: 2030 | FB53: 2030 | FC53: 2050 | FD53: 2025-2050 | FE53: 2024 | FF53: 2024 | FG53: 2024 | FH53: 2024 | FI53: 2024 | FJ53: 2024 | FK53: 2024 | FL53: 2024 | FM53: 2024 | FN53: 2024 | FR53: 2023 | FS53: 2023 | FT53: 2023 | FU53: 2024 | FV53: 2024 | FW53: 2024 | FX53: 2024 | FY53: 2020-2024 avg | FZ53: 2030 | GA53: 2030 | GB53: 2030 | GC53: 2050 | GD53: 2050
A54: CIV | B54: Côte d'Ivoire | C54: Sub-Saharan Africa | D54: Lower middle income | E54: TRUE | F54: 16.23 | G54: 2.662 | H54: 59.459 | I54: 13.576 | K54: 2 | L54: 2 | M54: 0 | R54: 2.822 | S54: 6.284 | T54: 14.149 | U54: 1.945 | V54: 26.321 | W54: 55.023 | X54: 40.066 | Y54: 3 | Z54: 0.507 | AA54: 6.823 | AB54: 1.993 | AC54: 0.338 | AD54: 1.655 | AF54: -11.741 | AG54: 15.122 | AH54: 26.863 | AI54: 14.379 | AJ54: 1.009 | AK54: 0.7 | AL54: 0.309 | AM54: 0 | AN54: 0.185 | AO54: 32.97 | AP54: -1.23 | AQ54: 11.957 | AR54: 3.6387478 | AS54: 0.87329948 | AT54: 0.2368503 | AU54: 0.16241164 | AV54: 0.12892337 | AW54: 0.086065621 | AX54: 0.03653268 | AY54: 0.054413431 | AZ54: 0.16810243 | BA54: 0.047190424 | BB54: 0.015354192 | BC54: -0.011285613 | BD54: 28.126744 | BE54: 0.13265097 | BF54: 4.2926677 | BG54: 1.5534233 | BH54: 0.27180632 | BI54: 0.27941655 | BJ54: 0.26117933 | BK54: 0.39146042 | BL54: 0.34956067 | BM54: 0.38924444 | BN54: 56.955648 | BO54: 0.87496525 | BP54: 0.71459026 | BQ54: -3.6361758 | BR54: 1.118 | BS54: 1.443 | BT54: 0.131 | BU54: 0.14 | BV54: 15.318 | BW54: 9.011 | BX54: 6.224 | BY54: 14.388 | BZ54: 7.124 | CA54: 5.575 | CB54: 2 | CC54: 1 | CD54: 0 | CE54: 28.407 | CF54: 0 | CG54: 50 | CH54: 16.402 | CI54: -1.302 | CJ54: -4.467 | CK54: 20.87 | CL54: 5.357 | CM54: 0.251 | CN54: 0.162 | CO54: 0.089 | CP54: 4.406 | CQ54: 59.28 | CR54: 3 | CS54: 2024 | CT54: 2024 | CU54: 2024 | CV54: 2024 | CX54: 2026 | CY54: 2026 | CZ54: 2022 | DE54: 2024 | DF54: 2024 | DG54: 2024 | DH54: 2024 | DI54: 2024 | DJ54: 2024 | DK54: 2024 | DL54: 2026 | DM54: 2020-2024 avg | DN54: 2024 | DO54: 2024 | DP54: 2024 | DQ54: 2024 | DS54: 2024 | DT54: 2024 | DU54: 2024 | DV54: 2022 | DW54: 2021 | DX54: 2021 | DY54: 2021 | DZ54: 2021 | EA54: 2024 | EB54: 2024 | EC54: 2024 | ED54: 2024 | EE54: 2030 | EF54: 2030 | EG54: 2030 | EH54: 2030 | EI54: 2030 | EJ54: 2030 | EK54: 2030 | EL54: 2030 | EM54: 2030 | EN54: 2030 | EO54: 2030 | EP54: 2030 | EQ54: 2030 | ER54: 2030 | ES54: 2030 | ET54: 2030 | EU54: 2030 | EV54: 2030 | EW54: 2030 | EX54: 2030 | EY54: 2030 | EZ54: 2030 | FA54: 2030 | FB54: 2030 | FC54: 2050 | FD54: 2025-2050 | FE54: 2024 | FF54: 2024 | FG54: 2024 | FH54: 2024 | FI54: 2024 | FJ54: 2024 | FK54: 2024 | FL54: 2024 | FM54: 2024 | FN54: 2024 | FO54: 2013 | FP54: 2013 | FQ54: 2013 | FR54: 2023 | FS54: 2023 | FT54: 2023 | FU54: 2024 | FV54: 2024 | FW54: 2024 | FX54: 2024 | FY54: 2020-2024 avg | FZ54: 2030 | GA54: 2030 | GB54: 2030 | GC54: 2050 | GD54: 2050 | GE54: 2034
A55: DNK | B55: Denmark | C55: Europe & Central Asia | D55: High income | E55: FALSE | G55: -0.751 | H55: 30.544 | I55: 45.339 | M55: 0 | O55: 3.75 | P55: 1 | AA55: 3.964 | AB55: 0.279 | AC55: 0.102 | AD55: 0.177 | AE55: 0.727 | AF55: -2.109 | AG55: 3.951 | AH55: 6.06 | AI55: 43.787 | AJ55: 0.325 | AK55: 0.27 | AL55: 0.055 | AM55: 0 | AN55: 4.952 | AO55: 89.565 | AP55: 4.989 | AQ55: 8.488 | AR55: 2.4210749 | AS55: 0.92000845 | AT55: 0.3188045 | AU55: 0.2186088 | AV55: 0.1440332 | AW55: 0.097174866 | AX55: 0.056833392 | AY55: 0.066532807 | AZ55: 0.018020869 | BA55: 0.011790557 | BB55: 0.026563457 | BC55: 0.018236647 | BD55: 108.40803 | BE55: -0.038876053 | BF55: 2.5296058 | BG55: 2.0703077 | BH55: 0.19029477 | BI55: 0.39851942 | BJ55: 0.48640994 | BK55: 0.10610125 | BL55: 0.8889823 | BM55: 0.22212515 | BN55: 70.021626 | BO55: 0.76422438 | BP55: 0.53162822 | BQ55: 2.0630998 | BR55: 1.674 | BS55: 2.155 | BT55: 0.404 | BU55: 0.122 | BV55: 38.13 | BW55: 21.029 | BX55: 21.029 | BY55: 19.275 | BZ55: 19.848 | CA55: 13.763 | CE55: 89.519 | CF55: 80 | CG55: 100 | CH55: 51.788 | CI55: 3.708 | CJ55: 12.193 | CK55: 23.207 | CL55: 1.85 | CM55: 0.09 | CN55: 0 | CO55: 0.09 | CP55: 2.12 | CQ55: 31.07 | CT55: 2024 | CU55: 2024 | CV55: 2024 | CZ55: 2022 | DB55: 2020 | DC55: 2021-2024 | DN55: 2024 | DO55: 2024 | DP55: 2024 | DQ55: 2024 | DR55: 2021 | DS55: 2025 | DT55: 2025 | DU55: 2025 | DV55: 2023 | DW55: 2021 | DX55: 2021 | DY55: 2021 | DZ55: 2021 | EA55: 2025 | EB55: 2024 | EC55: 2025 | ED55: 2025 | EE55: 2030 | EF55: 2030 | EG55: 2030 | EH55: 2030 | EI55: 2030 | EJ55: 2030 | EK55: 2030 | EL55: 2030 | EM55: 2030 | EN55: 2030 | EO55: 2030 | EP55: 2030 | EQ55: 2030 | ER55: 2030 | ES55: 2030 | ET55: 2030 | EU55: 2030 | EV55: 2030 | EW55: 2030 | EX55: 2030 | EY55: 2030 | EZ55: 2030 | FA55: 2030 | FB55: 2030 | FC55: 2050 | FD55: 2025-2050 | FE55: 2024 | FF55: 2024 | FG55: 2024 | FH55: 2024 | FI55: 2024 | FJ55: 2024 | FK55: 2024 | FL55: 2024 | FM55: 2024 | FN55: 2024 | FR55: 2023 | FS55: 2023 | FT55: 2023 | FU55: 2024 | FV55: 2024 | FW55: 2024 | FX55: 2024 | FY55: 2020-2024 avg | FZ55: 2030 | GA55: 2030 | GB55: 2030 | GC55: 2050 | GD55: 2050
A56: DJI | B56: Djibouti | C56: Middle East & North Africa | D56: Lower middle income | E56: TRUE | F56: 1.353 | G56: 0.252 | H56: 33.957 | I56: 11.033 | K56: 2.5 | L56: 2 | M56: 0 | T56: 23.191 | U56: 0.178 | V56: 32.829 | W56: 0 | X56: 71.18 | Y56: 1 | Z56: 0.737 | AA56: 4.645 | AB56: 0.756 | AC56: 0 | AD56: 0.756 | AF56: -6.911 | AG56: 0.995 | AH56: 7.906 | AJ56: 0 | AK56: 0 | AL56: 0 | AM56: 0 | AN56: 65 | AO56: 46.499 | AP56: 0 | AQ56: 0 | AR56: 3.6863864 | AS56: 0.88473273 | AT56: 0.25238679 | AU56: 0.17306523 | AV56: 0.096489068 | AW56: 0.085565651 | AX56: 0.038592625 | AY56: 0.043849737 | AZ56: 0.19478364 | BA56: 0.030761881 | BB56: -0.0017644113 | BC56: -0.01331361 | BD56: -2.537078 | BE56: 0.13552622 | BF56: 4.2180285 | BG56: 2.0938761 | BH56: 0.25415102 | BI56: 0.57550297 | BJ56: 0.42573031 | BK56: 0.44766738 | BL56: 0.39082445 | BM56: 0.38845124 | BN56: 53.963169 | BO56: 1.0267657 | BP56: 0.89815359 | BQ56: -5.789321 | BR56: 1.222 | BS56: 2.179 | BT56: 0.267 | BU56: 0.218 | BV56: 16.5 | BW56: 7.059 | BX56: 5.735 | BY56: 13.412 | BZ56: 7.124 | CA56: 5.575 | CB56: 1 | CC56: 0 | CD56: 0 | CH56: 18.627 | CI56: -2.434 | CJ56: 14.552 | CK56: 0.252 | CL56: 4.913 | CM56: 0.266 | CN56: 0.324 | CO56: -0.057 | CP56: 5.551 | CQ56: 33.91 | CR56: 2 | CS56: 2024 | CT56: 2024 | CU56: 2024 | CV56: 2024 | CX56: 2023 | CY56: 2023 | CZ56: 2022 | DG56: 2024 | DH56: 2024 | DI56: 2024 | DJ56: 2017 | DK56: 2024 | DL56: 2023 | DM56: 2020-2024 avg | DN56: 2024 | DO56: 2024 | DP56: 2024 | DQ56: 2024 | DS56: 2023 | DT56: 2023 | DU56: 2023 | DW56: 2021 | DX56: 2021 | DY56: 2021 | DZ56: 2021 | EA56: 2024 | EB56: 2024 | EC56: 2024 | ED56: 2024 | EE56: 2030 | EF56: 2030 | EG56: 2030 | EH56: 2030 | EI56: 2030 | EJ56: 2030 | EK56: 2030 | EL56: 2030 | EM56: 2030 | EN56: 2030 | EO56: 2030 | EP56: 2030 | EQ56: 2030 | ER56: 2030 | ES56: 2030 | ET56: 2030 | EU56: 2030 | EV56: 2030 | EW56: 2030 | EX56: 2030 | EY56: 2030 | EZ56: 2030 | FA56: 2030 | FB56: 2030 | FC56: 2050 | FD56: 2025-2050 | FE56: 2024 | FF56: 2024 | FG56: 2024 | FH56: 2024 | FI56: 2024 | FJ56: 2024 | FK56: 2024 | FL56: 2024 | FM56: 2024 | FN56: 2024 | FO56: 2013 | FP56: 2013 | FQ56: 2013 | FU56: 2024 | FV56: 2024 | FW56: 2024 | FX56: 2024 | FY56: 2020-2024 avg | FZ56: 2030 | GA56: 2030 | GB56: 2030 | GC56: 2050 | GD56: 2050 | GE56: 2034
A57: DMA | B57: Dominica | C57: Latin America & Caribbean | D57: Upper middle income | E57: TRUE | F57: 3.87 | G57: 2.347 | H57: 108.234 | I57: 22.278 | J57: 142.064 | M57: 0 | R57: 2.431 | S57: 3.744 | T57: 34.204 | U57: 4.433 | V57: 81.175 | W57: 9.418 | X57: 86.243 | AA57: 4.882 | AB57: 1.927 | AC57: 0.225 | AD57: 1.701 | AE57: 9.427 | AF57: -18.576 | AG57: 0.008 | AH57: 18.584 | AJ57: 0 | AK57: 0 | AL57: 0 | AM57: 0 | AN57: 86.667 | AO57: 28.243 | AP57: 0 | AQ57: 0 | AR57: 4.5805864 | AS57: 1.0993407 | AT57: 0.34097104 | AU57: 0.23380871 | AV57: 0.15478635 | AW57: 0.088606369 | AX57: 0.073181924 | AY57: 0.0660142 | AZ57: 0.14197215 | BA57: -0.046200866 | BB57: -0.08633014 | BC57: -0.10986222 | BD57: -96.263703 | BE57: 0.16720531 | BF57: 5.2582622 | BG57: 2.49879 | BH57: 0.13702673 | BI57: 0.94037181 | BJ57: 0.21627066 | BK57: 0.49987918 | BL57: 0.70524161 | BM57: 0.28699048 | BN57: 50.881735 | BO57: 1.7133659 | BP57: 1.7433115 | BQ57: -15.613159 | BR57: 1.113 | BS57: 1.4 | BT57: 0.254 | BU57: 0.267 | BV57: 18.535 | BW57: 8.176 | BX57: 6.853 | BY57: 14.022 | BZ57: 7.124 | CA57: 5.575 | CB57: 3 | CC57: 1 | CD57: 0 | CH57: 60.648 | CI57: -4.407 | CJ57: -37.804 | CK57: 40.197 | CL57: 0.824 | CM57: 0.204 | CN57: 0 | CO57: 0.204 | CP57: 13.17 | CQ57: 98.23 | CS57: 2024 | CT57: 2024 | CU57: 2024 | CV57: 2024 | CW57: 2022 | CZ57: 2022 | DE57: 2024 | DF57: 2024 | DG57: 2024 | DH57: 2024 | DI57: 2024 | DJ57: 2024 | DK57: 2024 | DN57: 2024 | DO57: 2024 | DP57: 2024 | DQ57: 2024 | DR57: 2022 | DS57: 2023 | DT57: 2023 | DU57: 2023 | DW57: 2021 | DX57: 2021 | DY57: 2021 | DZ57: 2021 | EA57: 2023 | EB57: 2024 | EC57: 2023 | ED57: 2023 | EE57: 2030 | EF57: 2030 | EG57: 2030 | EH57: 2030 | EI57: 2030 | EJ57: 2030 | EK57: 2030 | EL57: 2030 | EM57: 2030 | EN57: 2030 | EO57: 2030 | EP57: 2030 | EQ57: 2030 | ER57: 2030 | ES57: 2030 | ET57: 2030 | EU57: 2030 | EV57: 2030 | EW57: 2030 | EX57: 2030 | EY57: 2030 | EZ57: 2030 | FA57: 2030 | FB57: 2030 | FC57: 2050 | FD57: 2025-2050 | FE57: 2024 | FF57: 2024 | FG57: 2024 | FH57: 2024 | FI57: 2024 | FJ57: 2024 | FK57: 2024 | FL57: 2024 | FM57: 2024 | FN57: 2024 | FO57: 2013 | FP57: 2013 | FQ57: 2013 | FU57: 2024 | FV57: 2024 | FW57: 2024 | FX57: 2024 | FY57: 2020-2024 avg | FZ57: 2030 | GA57: 2030 | GB57: 2030 | GC57: 2050 | GD57: 2050
A58: DOM | B58: Dominican Republic | C58: Latin America & Caribbean | D58: Upper middle income | E58: TRUE | F58: 20.656 | G58: 3.383 | H58: 58.792 | I58: 14.512 | J58: 72.615 | K58: 2.5 | L58: 1 | M58: 0 | N58: 5.6 | P58: 1 | R58: 1.72 | S58: 8.624 | T58: 17.484 | U58: 0.555 | V58: 18.727 | W58: 77.064 | X58: 87.602 | Y58: 4 | Z58: 0.417 | AA58: 11.756 | AB58: 6.807 | AC58: 1.089 | AD58: 5.718 | AE58: 0.942 | AF58: -16.208 | AG58: 0.435 | AH58: 16.643 | AI58: 94.421 | AJ58: 0 | AK58: 0 | AL58: 0 | AM58: 0 | AN58: 20.361 | AO58: 36.065 | AP58: 4.992 | AQ58: 27.734 | AR58: 4.3940153 | AS58: 1.0545637 | AT58: 0.31261142 | AU58: 0.21436212 | AV58: 0.13738641 | AW58: 0.10471354 | AX58: 0.056414449 | AY58: 0.06693118 | AZ58: 0.16214456 | BA58: 0.011684444 | BB58: -0.0023687336 | BC58: -0.086671098 | BD58: -3.0357699 | BE58: 0.058554905 | BF58: 5.02771 | BG58: 2.1807836 | BH58: 0.35139967 | BI58: 0.2260329 | BJ58: 0.35262016 | BK58: 0.4812616 | BL58: 0.76946924 | BM58: 0.49577815 | BN58: 66.901298 | BO58: 1.2878119 | BP58: 1.2404437 | BQ58: -3.1731068 | BR58: 0.911 | BS58: 1.198 | BT58: 0.091 | BU58: 0.143 | BV58: 23.723 | BW58: 23.723 | BX58: 23.723 | BY58: 14.388 | BZ58: 7.124 | CA58: 5.575 | CB58: 3 | CC58: 1 | CD58: 1 | CE58: 31.249 | CF58: 0 | CG58: 33.333 | CH58: 16.378 | CI58: 0.296 | CJ58: -3.344 | CK58: 26.998 | CL58: 3.693 | CM58: 0.291 | CN58: 0.153 | CO58: 0.139 | CP58: 7.365 | CQ58: 58.67 | CS58: 2024 | CT58: 2024 | CU58: 2024 | CV58: 2024 | CW58: 2022 | CX58: 2022 | CY58: 2022 | CZ58: 2022 | DA58: 2021 | DC58: 2021-2024 | DE58: 2024 | DF58: 2024 | DG58: 2024 | DH58: 2024 | DI58: 2024 | DJ58: 2024 | DK58: 2024 | DL58: 2022 | DM58: 2020-2024 avg | DN58: 2024 | DO58: 2024 | DP58: 2024 | DQ58: 2024 | DR58: 2022 | DS58: 2024 | DT58: 2024 | DU58: 2024 | DV58: 2022 | DW58: 2021 | DX58: 2021 | DY58: 2021 | DZ58: 2021 | EA58: 2025 | EB58: 2024 | EC58: 2025 | ED58: 2025 | EE58: 2030 | EF58: 2030 | EG58: 2030 | EH58: 2030 | EI58: 2030 | EJ58: 2030 | EK58: 2030 | EL58: 2030 | EM58: 2030 | EN58: 2030 | EO58: 2030 | EP58: 2030 | EQ58: 2030 | ER58: 2030 | ES58: 2030 | ET58: 2030 | EU58: 2030 | EV58: 2030 | EW58: 2030 | EX58: 2030 | EY58: 2030 | EZ58: 2030 | FA58: 2030 | FB58: 2030 | FC58: 2050 | FD58: 2025-2050 | FE58: 2024 | FF58: 2024 | FG58: 2024 | FH58: 2024 | FI58: 2024 | FJ58: 2024 | FK58: 2024 | FL58: 2024 | FM58: 2024 | FN58: 2024 | FO58: 2013 | FP58: 2013 | FQ58: 2013 | FR58: 2023 | FS58: 2023 | FT58: 2023 | FU58: 2024 | FV58: 2024 | FW58: 2024 | FX58: 2024 | FY58: 2020-2024 avg | FZ58: 2030 | GA58: 2030 | GB58: 2030 | GC58: 2050 | GD58: 2050
A59: ECU | B59: Ecuador | C59: Latin America & Caribbean | D59: Upper middle income | E59: TRUE | F59: 2.993 | G59: 1.109 | H59: 54.134 | I59: 13.631 | J59: 67.671 | M59: 1 | N59: 12.2 | P59: 1 | R59: -0.36 | S59: 6.101 | T59: 15.097 | U59: 0.908 | V59: 48.973 | W59: 40.533 | X59: 97.883 | Z59: 0.181 | AA59: 1.637 | AB59: 11.495 | AC59: 4.171 | AD59: 7.324 | AE59: 0.234 | AF59: 2.472 | AG59: 27.481 | AH59: 25.009 | AI59: -69.401 | AJ59: 6.417 | AK59: 6.403 | AL59: 0.014 | AM59: 0 | AN59: 17.923 | AO59: 81.952 | AP59: 6.956 | AQ59: 0.348 | AR59: 5.8763422 | AS59: 1.4103221 | AT59: 0.37518939 | AU59: 0.25727273 | AV59: 0.25639608 | AW59: 0.11794172 | AX59: 0.058799332 | AY59: 0.077890554 | AZ59: 0.26683233 | BA59: 0.12323723 | BB59: 0.022916975 | BC59: -0.03883923 | BD59: 29.841167 | BE59: 0.41800105 | BF59: 6.7457189 | BG59: 4.0582566 | BH59: 0.77602379 | BI59: 0.53940247 | BJ59: 0.66512569 | BK59: 1.4495773 | BL59: 0.62812733 | BM59: 1.210897 | BN59: 56.870656 | BO59: 3.0022454 | BP59: 2.7545829 | BQ59: 3.7455288 | BR59: 0.413 | BS59: 0.59 | BT59: 0.103 | BU59: 0.071 | BV59: 15.553 | BW59: 11.17 | BX59: 10.508 | BY59: 13.656 | BZ59: 7.281 | CA59: 5.575 | CB59: 3 | CC59: 1 | CD59: 1 | CE59: 40.87 | CF59: 0 | CG59: 100 | CH59: 37.056 | CI59: -0.176 | CJ59: 5.69 | CK59: 19.506 | CL59: 1.187 | CM59: 1.051 | CN59: 0.207 | CO59: 0.844 | CP59: 12.03 | CQ59: 58.98 | CS59: 2024 | CT59: 2024 | CU59: 2024 | CV59: 2024 | CW59: 2022 | CZ59: 2022 | DA59: 2021 | DC59: 2021-2024 | DE59: 2024 | DF59: 2024 | DG59: 2024 | DH59: 2024 | DI59: 2024 | DJ59: 2024 | DK59: 2024 | DM59: 2020-2024 avg | DN59: 2024 | DO59: 2024 | DP59: 2024 | DQ59: 2024 | DR59: 2022 | DS59: 2024 | DT59: 2024 | DU59: 2024 | DV59: 2022 | DW59: 2021 | DX59: 2021 | DY59: 2021 | DZ59: 2021 | EA59: 2025 | EB59: 2024 | EC59: 2025 | ED59: 2025 | EE59: 2030 | EF59: 2030 | EG59: 2030 | EH59: 2030 | EI59: 2030 | EJ59: 2030 | EK59: 2030 | EL59: 2030 | EM59: 2030 | EN59: 2030 | EO59: 2030 | EP59: 2030 | EQ59: 2030 | ER59: 2030 | ES59: 2030 | ET59: 2030 | EU59: 2030 | EV59: 2030 | EW59: 2030 | EX59: 2030 | EY59: 2030 | EZ59: 2030 | FA59: 2030 | FB59: 2030 | FC59: 2050 | FD59: 2025-2050 | FE59: 2024 | FF59: 2024 | FG59: 2024 | FH59: 2024 | FI59: 2024 | FJ59: 2024 | FK59: 2024 | FL59: 2024 | FM59: 2024 | FN59: 2024 | FO59: 2013 | FP59: 2013 | FQ59: 2013 | FR59: 2023 | FS59: 2023 | FT59: 2023 | FU59: 2024 | FV59: 2024 | FW59: 2024 | FX59: 2024 | FY59: 2020-2024 avg | FZ59: 2030 | GA59: 2030 | GB59: 2030 | GC59: 2050 | GD59: 2050
A60: EGY | B60: Egypt, Arab Rep. | C60: Middle East & North Africa | D60: Lower middle income | E60: TRUE | F60: 55.785 | G60: 8.823 | H60: 90.926 | I60: 11.726 | M60: 0 | N60: 8.8 | O60: 9.71 | P60: 2 | R60: 1.841 | S60: 8.372 | T60: 8.034 | U60: 0.749 | V60: 28.761 | W60: 43.589 | X60: 67.815 | Z60: 0.448 | AA60: 7.227 | AB60: 29.096 | AC60: 12.535 | AD60: 16.561 | AF60: -5.492 | AG60: 12.454 | AH60: 17.946 | AI60: 20.256 | AJ60: 5.032 | AK60: 2.986 | AL60: 2.046 | AM60: 0 | AN60: 7.358 | AO60: 28.214 | AP60: 1.818 | AQ60: 20.104 | AR60: 7.1817778 | AS60: 1.7236267 | AT60: 0.536818 | AU60: 0.36810377 | AV60: 0.22425173 | AW60: 0.16894257 | AX60: 0.086240384 | AY60: 0.1114419 | AZ60: 0.22782833 | BA60: 0.056260215 | BB60: -0.0044250079 | BC60: -0.14070631 | BD60: -4.108499 | BE60: 0.25285509 | BF60: 8.2442874 | BG60: 3.2340555 | BH60: 0.77745606 | BI60: 0.313961 | BJ60: 0.36607764 | BK60: 1.254909 | BL60: 0.52165174 | BM60: 1.1539288 | BN60: 54.611484 | BO60: 2.0107366 | BP60: 1.9103521 | BQ60: -41.212581 | BR60: 0.206 | BS60: 0.277 | BT60: 0.043 | BU60: 0.049 | BV60: 2.198 | BW60: 4.797 | BX60: 2.503 | BY60: 13.9 | BZ60: 7.281 | CA60: 5.575 | CB60: 3 | CC60: 1 | CD60: 1 | CE60: 44.188 | CF60: 0 | CG60: 0 | CH60: 15.816 | CI60: 1.705 | CJ60: -5.431 | CK60: 12.997 | CL60: 3.928 | CM60: 0.683 | CN60: 0.153 | CO60: 0.53 | CP60: 23.19 | CQ60: 82.57 | CR60: 3 | CS60: 2024 | CT60: 2024 | CU60: 2024 | CV60: 2024 | CZ60: 2022 | DA60: 2021 | DB60: 2020 | DC60: 2021-2024 | DE60: 2024 | DF60: 2024 | DG60: 2024 | DH60: 2024 | DI60: 2024 | DJ60: 2024 | DK60: 2024 | DM60: 2020-2024 avg | DN60: 2024 | DO60: 2024 | DP60: 2024 | DQ60: 2024 | DS60: 2024 | DT60: 2024 | DU60: 2024 | DV60: 2023 | DW60: 2021 | DX60: 2021 | DY60: 2021 | DZ60: 2021 | EA60: 2025 | EB60: 2024 | EC60: 2025 | ED60: 2025 | EE60: 2030 | EF60: 2030 | EG60: 2030 | EH60: 2030 | EI60: 2030 | EJ60: 2030 | EK60: 2030 | EL60: 2030 | EM60: 2030 | EN60: 2030 | EO60: 2030 | EP60: 2030 | EQ60: 2030 | ER60: 2030 | ES60: 2030 | ET60: 2030 | EU60: 2030 | EV60: 2030 | EW60: 2030 | EX60: 2030 | EY60: 2030 | EZ60: 2030 | FA60: 2030 | FB60: 2030 | FC60: 2050 | FD60: 2025-2050 | FE60: 2024 | FF60: 2024 | FG60: 2024 | FH60: 2024 | FI60: 2024 | FJ60: 2024 | FK60: 2024 | FL60: 2024 | FM60: 2024 | FN60: 2024 | FO60: 2013 | FP60: 2013 | FQ60: 2013 | FR60: 2023 | FS60: 2023 | FT60: 2023 | FU60: 2024 | FV60: 2024 | FW60: 2024 | FX60: 2024 | FY60: 2020-2024 avg | FZ60: 2030 | GA60: 2030 | GB60: 2030 | GC60: 2050 | GD60: 2050 | GE60: 2034
A61: SLV | B61: El Salvador | C61: Latin America & Caribbean | D61: Upper middle income | E61: FALSE | F61: 17.093 | G61: 4.583 | H61: 87.369 | I61: 21.626 | J61: 52.336 | K61: 2.5 | L61: 1 | M61: 0 | O61: 4.8 | P61: 1 | R61: 2.449 | S61: 8.851 | T61: 18.867 | U61: 1.295 | V61: 46.512 | W61: 51.264 | X61: 98.162 | Y61: 1 | Z61: 0.019 | AA61: 4.117 | AB61: 5.882 | AC61: 0.721 | AD61: 5.161 | AE61: 0.12 | AF61: -9.828 | AG61: 5.001 | AH61: 14.829 | AI61: 59.505 | AJ61: 0 | AK61: 0 | AL61: 0 | AM61: 0 | AN61: 8.97 | AO61: 73.939 | AP61: 0.199 | AQ61: 5.488 | AR61: 5.2814965 | AS61: 1.2675592 | AT61: 0.38590398 | AU61: 0.26461987 | AV61: 0.20903429 | AW61: 0.11250649 | AX61: 0.057108645 | AY61: 0.068425466 | AZ61: 0.16996043 | BA61: 0.031143544 | BB61: 0.04228009 | BC61: 0.0035374821 | BD61: 79.183654 | BE61: -0.046402275 | BF61: 6.0431817 | BG61: 2.4225112 | BH61: 0.33167303 | BI61: 0.34266311 | BJ61: 0.45182697 | BK61: 0.41957736 | BL61: 0.87677073 | BM61: 0.45754624 | BN61: 66.967775 | BO61: 1.5701448 | BP61: 1.4348021 | BQ61: -9.1889869 | BR61: 0.886 | BS61: 1.016 | BT61: 0.205 | BU61: 0.194 | BV61: 23.405 | BW61: 12.771 | BX61: 11.447 | BY61: 14.018 | BZ61: 7.124 | CA61: 5.787 | CB61: 3 | CC61: 1 | CD61: 1 | CE61: 27.392 | CF61: 20 | CG61: 33.333 | CH61: 26.812 | CI61: 0.033 | CJ61: -1.789 | CK61: 20.344 | CL61: 2.622 | CM61: 0.346 | CN61: 0.298 | CO61: 0.048 | CP61: 9.158 | CQ61: 82.51 | CS61: 2024 | CT61: 2024 | CU61: 2024 | CV61: 2024 | CW61: 2022 | CX61: 2019 | CY61: 2019 | CZ61: 2022 | DB61: 2014 | DC61: 2021-2024 | DE61: 2024 | DF61: 2024 | DG61: 2024 | DH61: 2024 | DI61: 2024 | DJ61: 2024 | DK61: 2024 | DL61: 2019 | DM61: 2020-2024 avg | DN61: 2024 | DO61: 2024 | DP61: 2024 | DQ61: 2024 | DR61: 2022 | DS61: 2024 | DT61: 2024 | DU61: 2024 | DV61: 2022 | DW61: 2021 | DX61: 2021 | DY61: 2021 | DZ61: 2021 | EA61: 2025 | EB61: 2024 | EC61: 2025 | ED61: 2024 | EE61: 2030 | EF61: 2030 | EG61: 2030 | EH61: 2030 | EI61: 2030 | EJ61: 2030 | EK61: 2030 | EL61: 2030 | EM61: 2030 | EN61: 2030 | EO61: 2030 | EP61: 2030 | EQ61: 2030 | ER61: 2030 | ES61: 2030 | ET61: 2030 | EU61: 2030 | EV61: 2030 | EW61: 2030 | EX61: 2030 | EY61: 2030 | EZ61: 2030 | FA61: 2030 | FB61: 2030 | FC61: 2050 | FD61: 2025-2050 | FE61: 2024 | FF61: 2024 | FG61: 2024 | FH61: 2024 | FI61: 2024 | FJ61: 2024 | FK61: 2024 | FL61: 2024 | FM61: 2024 | FN61: 2024 | FO61: 2013 | FP61: 2013 | FQ61: 2013 | FR61: 2023 | FS61: 2023 | FT61: 2023 | FU61: 2024 | FV61: 2024 | FW61: 2024 | FX61: 2024 | FY61: 2020-2024 avg | FZ61: 2030 | GA61: 2030 | GB61: 2030 | GC61: 2050 | GD61: 2050
A62: GNQ | B62: Equatorial Guinea | C62: Sub-Saharan Africa | D62: Upper middle income | E62: FALSE | F62: 6.118 | G62: 1.096 | H62: 36.436 | I62: 5.536 | J62: 152.021 | M62: 0 | T62: 5 | U62: 0.014 | V62: 7.409 | X62: 68.919 | Z62: 0.447 | AA62: 1.072 | AB62: 2.929 | AC62: 0.161 | AD62: 2.768 | AF62: -1.039 | AG62: 1.709 | AH62: 2.748 | AI62: -422.769 | AJ62: 21.57 | AK62: 14.94 | AL62: 6.63 | AM62: 0 | AN62: 0.671 | AO62: 37.117 | AP62: 2.37 | AQ62: 0 | AR62: 7.0078752 | AS62: 1.68189 | AT62: 0.36461894 | AU62: 0.25002442 | AV62: 0.16581614 | AW62: 0.11782575 | AX62: 0.10889129 | AY62: 0.10458785 | AZ62: 0.57012565 | BA62: 0.13947183 | BB62: 0.077594249 | BC62: -0.0040665084 | BD62: 58.782585 | BE62: 0.25782326 | BF62: 8.0446567 | BG62: 4.8218253 | BH62: 1.3337993 | BI62: 0.6298237 | BJ62: 0.14683135 | BK62: 1.9499261 | BL62: 0.76144492 | BM62: 1.9187771 | BN62: 47.144481 | BO62: 4.420966 | BP62: 5.341173 | BQ62: 48.521316 | BR62: 0.719 | BS62: 0.811 | BT62: 0.126 | BU62: 0.095 | BV62: 10.773 | BW62: 5.397 | BX62: 4.735 | BY62: 14.022 | BZ62: 7.124 | CA62: 5.575 | CB62: 1 | CC62: 1 | CD62: 0 | CH62: 17.914 | CI62: 0.542 | CJ62: -0.643 | CK62: 28.897 | CL62: -0.983 | CM62: 1.832 | CN62: 0.124 | CO62: 1.709 | CP62: -15.06 | CQ62: 80.89 | CS62: 2024 | CT62: 2024 | CU62: 2024 | CV62: 2024 | CW62: 2022 | CZ62: 2022 | DG62: 2022 | DH62: 2024 | DI62: 2024 | DK62: 2024 | DM62: 2020-2024 avg | DN62: 2023 | DO62: 2024 | DP62: 2024 | DQ62: 2024 | DS62: 1983 | DT62: 1983 | DU62: 1983 | DV62: 2022 | DW62: 2021 | DX62: 2021 | DY62: 2021 | DZ62: 2021 | EA62: 2024 | EB62: 2024 | EC62: 2024 | ED62: 2024 | EE62: 2030 | EF62: 2030 | EG62: 2030 | EH62: 2030 | EI62: 2030 | EJ62: 2030 | EK62: 2030 | EL62: 2030 | EM62: 2030 | EN62: 2030 | EO62: 2030 | EP62: 2030 | EQ62: 2030 | ER62: 2030 | ES62: 2030 | ET62: 2030 | EU62: 2030 | EV62: 2030 | EW62: 2030 | EX62: 2030 | EY62: 2030 | EZ62: 2030 | FA62: 2030 | FB62: 2030 | FC62: 2050 | FD62: 2025-2050 | FE62: 2024 | FF62: 2024 | FG62: 2024 | FH62: 2024 | FI62: 2024 | FJ62: 2024 | FK62: 2024 | FL62: 2024 | FM62: 2024 | FN62: 2024 | FO62: 2013 | FP62: 2013 | FQ62: 2013 | FU62: 2024 | FV62: 2024 | FW62: 2024 | FX62: 2024 | FY62: 2020-2024 avg | FZ62: 2030 | GA62: 2030 | GB62: 2030 | GC62: 2050 | GD62: 2050
A63: ERI | B63: Eritrea | C63: Sub-Saharan Africa | D63: Low income | E63: FALSE | F63: 5.186 | G63: 1.762 | H63: 260.393 | I63: 15.258 | M63: 0 | T63: 39.917 | U63: 0.193 | V63: 88.922 | X63: 76.019 | AF63: -0.865 | AG63: 0 | AH63: 0.865 | AI63: 34.79 | AJ63: 0 | AK63: 0 | AL63: 0 | AM63: 0 | AN63: 88.889 | AP63: 0.907 | AQ63: 0 | CB63: 1 | CC63: 0 | CD63: 0 | CE63: 7.426 | CF63: 0 | CG63: 0 | CH63: 33.973 | CI63: 4.479 | CJ63: 12.988 | CK63: 5.006 | CS63: 2019 | CT63: 2019 | CU63: 2019 | CV63: 2019 | CZ63: 2022 | DG63: 2015 | DH63: 2024 | DI63: 2024 | DK63: 2024 | DS63: 2002 | DT63: 2002 | DU63: 2003 | DV63: 2004 | DW63: 2011 | DX63: 2011 | DY63: 2011 | DZ63: 2011 | EA63: 2024 | EC63: 2024 | ED63: 2024 | FO63: 2013 | FP63: 2013 | FQ63: 2013 | FR63: 2023 | FS63: 2023 | FT63: 2023 | FU63: 2019 | FV63: 2019 | FW63: 2019 | FX63: 2019
A64: EST | B64: Estonia | C64: Europe & Central Asia | D64: High income | E64: FALSE | F64: 0.656 | G64: 0.276 | H64: 23.472 | I64: 22.862 | M64: 0 | O64: 7.635 | P64: 1 | AA64: 7.341 | AB64: 0.696 | AC64: 0.045 | AD64: 0.651 | AE64: 1.337 | AF64: -1.174 | AG64: 7.771 | AH64: 8.945 | AI64: 3.771 | AJ64: 0.962 | AK64: 0.962 | AL64: 0 | AM64: 0 | AN64: 38.449 | AO64: 49.357 | AP64: 4.507 | AQ64: 4.669 | AR64: 3.3589502 | AS64: 1.2764011 | AT64: 0.44327067 | AU64: 0.30395703 | AV64: 0.19578864 | AW64: 0.12378145 | AX64: 0.076617765 | AY64: 0.09917032 | AZ64: 0.033815206 | BA64: 0.02334692 | BB64: 0.0072088219 | BC64: -0.02241168 | BD64: 11.998091 | BE64: 0.042468678 | BF64: 3.5095238 | BG64: 3.1586283 | BH64: 0.33246821 | BI64: 0.63345994 | BJ64: 0.69948592 | BK64: 0.44544682 | BL64: 1.0477674 | BM64: 0.46610225 | BN64: 65.188617 | BO64: 1.5704712 | BP64: 1.1949785 | BQ64: 5.061079 | BR64: 1.502 | BS64: 1.81 | BT64: 0.244 | BU64: 0.151 | BV64: 22.225 | BW64: 20.556 | BX64: 20.556 | BY64: 7.409 | BZ64: 10.173 | CA64: 9.254 | CH64: 42.076 | CI64: -1.264 | CJ64: -1.246 | CK64: 24.554 | CL64: 0.262 | CM64: 0.315 | CN64: 0.221 | CO64: 0.094 | CP64: 3.691 | CQ64: 26.31 | CS64: 2024 | CT64: 2024 | CU64: 2024 | CV64: 2024 | CZ64: 2022 | DB64: 2019 | DC64: 2021-2024 | DN64: 2023 | DO64: 2024 | DP64: 2024 | DQ64: 2024 | DR64: 2021 | DS64: 2024 | DT64: 2024 | DU64: 2024 | DV64: 2023 | DW64: 2021 | DX64: 2021 | DY64: 2021 | DZ64: 2021 | EA64: 2025 | EB64: 2024 | EC64: 2025 | ED64: 2025 | EE64: 2030 | EF64: 2030 | EG64: 2030 | EH64: 2030 | EI64: 2030 | EJ64: 2030 | EK64: 2030 | EL64: 2030 | EM64: 2030 | EN64: 2030 | EO64: 2030 | EP64: 2030 | EQ64: 2030 | ER64: 2030 | ES64: 2030 | ET64: 2030 | EU64: 2030 | EV64: 2030 | EW64: 2030 | EX64: 2030 | EY64: 2030 | EZ64: 2030 | FA64: 2030 | FB64: 2030 | FC64: 2050 | FD64: 2025-2050 | FE64: 2024 | FF64: 2024 | FG64: 2024 | FH64: 2024 | FI64: 2024 | FJ64: 2024 | FK64: 2024 | FL64: 2024 | FM64: 2024 | FN64: 2024 | FU64: 2024 | FV64: 2024 | FW64: 2024 | FX64: 2024 | FY64: 2020-2024 avg | FZ64: 2030 | GA64: 2030 | GB64: 2030 | GC64: 2050 | GD64: 2050
